[
  {
    "numero_procedimento": "N/A",
    "entidade": "AnÃºncio de procedimento  n.Âº 20661/2025  -  DiÃ¡rio da RepÃºblica n.Âº 147/2025, SÃ©rie II de 2025-08-01",
    "link": "https://diariodarepublica.pt/dr/detalhe/contrato-publico/20661-927415986"
  },
  {
    "numero_procedimento": "N/A",
    "entidade": "AnÃºncio de procedimento  n.Âº 20662/2025  -  DiÃ¡rio da RepÃºblica n.Âº 147/2025, SÃ©rie II de 2025-08-01",
    "link": "https://diariodarepublica.pt/dr/detalhe/contrato-publico/20662-927415987"
  },
  {
    "numero_procedimento": "N/A",
    "entidade": "AnÃºncio de procedimento  n.Âº 20664/2025  -  DiÃ¡rio da RepÃºblica n.Âº 147/2025, SÃ©rie II de 2025-08-01",
    "link": "https://diariodarepublica.pt/dr/detalhe/contrato-publico/20664-927415988"
  },
  {
    "numero_procedimento": "N/A",
    "entidade": "AnÃºncio de procedimento  n.Âº 20675/2025  -  DiÃ¡rio da RepÃºblica n.Âº 147/2025, SÃ©rie II de 2025-08-01",
    "link": "https://diariodarepublica.pt/dr/detalhe/contrato-publico/20675-927415990"
  },
  {
    "numero_procedimento": "N/A",
    "entidade": "AnÃºncio de procedimento  n.Âº 20681/2025  -  DiÃ¡rio da RepÃºblica n.Âº 147/2025, SÃ©rie II de 2025-08-01",
    "link": "https://diariodarepublica.pt/dr/detalhe/contrato-publico/20681-927416007"
  },
  {
    "numero_procedimento": "N/A",
    "entidade": "AnÃºncio de procedimento  n.Âº 20685/2025  -  DiÃ¡rio da RepÃºblica n.Âº 147/2025, SÃ©rie II de 2025-08-01",
    "link": "https://diariodarepublica.pt/dr/detalhe/contrato-publico/20685-927416008"
  },
  {
    "numero_procedimento": "N/A",
    "entidade": "AnÃºncio de procedimento  n.Âº 20687/2025  -  DiÃ¡rio da RepÃºblica n.Âº 147/2025, SÃ©rie II de 2025-08-01",
    "link": "https://diariodarepublica.pt/dr/detalhe/contrato-publico/20687-927416009"
  },
  {
    "numero_procedimento": "N/A",
    "entidade": "EPF-Ensino Profissional de Felgueiras, E.M., Unipessoal, Lda",
    "link": "https://diariodarepublica.pt/dr/detalhe/contrato-publico/20688-927416010",
    "detalhes_completos": "1 - IDENTIFICAÇÃO E CONTACTOS DA ENTIDADE ADJUDICANTE\nDesignação da entidade adjudicante: EPF-Ensino Profissional de Felgueiras, E.M., Unipessoal, Lda\nNIPC: 504575848\nServiço/Órgão/Pessoa de contacto: Gerência\nEndereço: Rua dos Bombeiros Voluntários de Felgueiras, 104\nCódigo postal: 4610-165\nLocalidade: Felgueiras\nPaís: Portugal\nNUT III: PT11C\nDistrito: Porto\nConcelho: Felgueiras\nFreguesia: União das Freguesias de Margaride (Santa Eulália), Várzea, Lagares, Varziela e Moure\nTelefone: 255312482\nFax: 211512419\nEndereço da Entidade (URL): www.epfelgueiras.pt\nEndereço Eletrónico: epf@epfelgueiras.pt\neDelivery Gateway (URL): https://www.acingov.pt\nFunção da Organização: Adquirente\nNorma jurídica da Entidade Adjudicante: Organismo de direito público\nÁrea de atividade da Autoridade Adjudicante: Serviços públicos das administrações públicas\n\n2 - JORNAL OFICIAL DA UNIÃO EUROPEIA\nO procedimento a que este anúncio diz respeito também é publicitado no Jornal Oficial da União Europeia? Não\n\n3 - AVISO\nModelo de Anúncio: Concurso público\nData de Envio do Anúncio: 31-07-2025\n\n5 - PROCESSO\nTipo de Procedimento: Concurso público\nPreço base do procedimento: Sim\nValor do preço base do procedimento: 57.458,83 EUR\nProcedimento com lotes? Sim\nNº Máx. de Lotes Autorizado: 3\nNúmero máximo de lotes que podem ser adjudicados a um concorrente: 3\n\n6 - OBJETO DO CONTRATO\nNúmero de referência interna: CoP001/2025\nDesignação do contrato: Aquisição de serviços de alojamento para formandos/as deslocados, em regime de exclusividade, dos cursos profissionais de Escola Profissional de Felgueiras para o ano letivo de 2025/2026\nDescrição: Aquisição de serviços de alojamento para formandos/as deslocados, em regime de exclusividade, dos cursos profissionais de Escola Profissional de Felgueiras para o ano letivo de 2025/2026\nTipo de Contrato Principal: Aquisição de Serviços\nTipo de Contrato: Aquisição de Serviços\nClassificação CPV (Vocabulário Comum para os Contratos Públicos)\nObjeto principal\nVocabulário Principal: 98341000\nPreço base s/IVA: 57.458,83 EUR\nLotes: \nNº: LOT-0001\nDescrição do Lote: Alojamento para 8 estudantes\nPreço base s/IVA: 16.910,96 EUR\nClassificação CPV (Vocabulário Comum para os Contratos Públicos)\nObjeto principal\nVocabulário Principal: 98341000\nNº: LOT-0002\nDescrição do Lote: Alojamento para 9 estudantes\nPreço base s/IVA: 20.177,85 EUR\nClassificação CPV (Vocabulário Comum para os Contratos Públicos)\nObjeto principal\nVocabulário Principal: 98341000\nNº: LOT-0003\nDescrição do Lote: Alojamento para 9 estudantes\nPreço base s/IVA: 20.370,02 EUR\nClassificação CPV (Vocabulário Comum para os Contratos Públicos)\nObjeto principal\nVocabulário Principal: 98341000\n\n7 - INDICAÇÕES ADICIONAIS\nO contrato envolve aquisição conjunta (satisfação de várias entidades)? Não\nO contrato é adjudicado por uma central de compras? Não\n\n8 - TÉCNICAS\nO concurso destina-se à celebração de um acordo-quadro? Inexistência de acordo-quadro\nÉ utilizado um leilão eletrónico? Não\nÉ adotada uma fase de negociação? Não\nSistema de Aquisição Dinâmico: Inexistência de sistema de aquisição dinâmico\n\n9 - LOCAL DA EXECUÇÃO DO CONTRATO\nLOCAL DA EXECUÇÃO DO CONTRATO (PROCEDIMENTO)\nPaís: Portugal\nNUT III: PT11C\nLocalidade: União das Freguesias de Margaride (Santa Eulália), Várzea, Lagares, Varziela e Moure\nDistrito: Porto\nConcelho: Felgueiras\nFreguesia: União das Freguesias de Margaride (Santa Eulália), Várzea, Lagares, Varziela e Moure\nLOCAL DA EXECUÇÃO DO CONTRATO (LOTE)\nIdentificador do Lote: LOT-0001; LOT-0002; LOT-0003\nPaís: Portugal\nNUT III: PT11C\nLocalidade: União das Freguesias de Margaride (Santa Eulália), Várzea, Lagares, Varziela e Moure\nDistrito: Porto\nConcelho: Felgueiras\nFreguesia: União das Freguesias de Margaride (Santa Eulália), Várzea, Lagares, Varziela e Moure\n\n10 - PRAZO DE EXECUÇÃO DO CONTRATO\nIdentificador do Lote: LOT-0001; LOT-0002; LOT-0003\nPrazo de execução do contrato: 321 DIAS\nPrevisão de renovações: Não\n\n11 - FUNDOS EU\nIdentificador do Lote: LOT-0001; LOT-0002; LOT-0003\nTêm fundos EU? Sim\n\n12 - DOCUMENTOS DE HABILITAÇÃO\nHabilitação para o exercício da atividade profissional: Não\n\n13 - CONDIÇÕES DE APRESENTAÇÃO\nPlataforma eletrónica utilizada pela entidade adjudicante: ACIN\nURL para Apresentação: https://www.acingov.pt\nAdmissibilidade da apresentação de propostas variantes: Não autorizado\nPrazo para apresentação das propostas: 06-08-2025 23:59\nPrazo durante o qual os concorrentes são obrigados a manter as respetivas propostas: 66 dias a contar do termo do prazo para a apresentação das propostas\nIndicação de Subcontratação na Proposta: Inexistência de indicação de subcontratação\n\n14 - PRESTAÇÃO DE CAUÇÃO\nPrestação de caução: Não\n\n15 - FORNECIMENTO DAS PEÇAS DO CONCURSO, APRESENTAÇÃO DE PEDIDOS DE PARTICIPAÇÃO E APRESENTAÇÃO DAS PROPOSTAS\nLink para acesso às peças do concurso (URL): https://www.acingov.pt/acingovprod/2/zonaPublica/zona_publica_c/donwloadProcedurePiece/OTMwMjQ4\n\n20 - OUTROS REQUISITOS\nIdentificador do Lote: LOT-0001; LOT-0002; LOT-0003\nInformação sobre contratos reservados. Aplica-se a contratos reservados (54º-A)? Não\n\n21 - CRITÉRIO DE ADJUDICAÇÃO\nO Critério de adjudicação é diferenciado por lote? Não\nMultifator: Sim\nFator: \nNome: Outros\nOutro Nome: Avaliação do Preço da Proposta\nPonderação: 60%\nSubfatores: Não\nFator: \nNome: Outros\nOutro Nome: Avaliação de proximidade\nPonderação: 40%\nSubfatores: Não\n\n24 - CONDIÇÕES DO CONTRATO\nIdentificador do Lote: LOT-0001; LOT-0002; LOT-0003\nFaturação Eletrónica: Necessário\nObrigação de Subcontratação:\nCódigo da Obrigação de Subcontratação: Não é aplicável nenhuma obrigação de subcontratação.\n\n25 - COMPRA PÚBLICA ESTRATÉGICA\nCompra Pública Estratégica: Inexistência de contratação pública estratégica\n\n26 - INFORMAÇÕES ADICIONAIS\nIdentificador do Lote: LOT-0001; LOT-0002; LOT-0003\nContrato adequado para PME: Não\nCobertura ACP (Acordo dos Contratos Públicos da Organização Mundial do Comércio): Não\n\n27 - IDENTIFICAÇÃO E CONTACTOS DO ÓRGÃO DE RECURSOS ADMINISTRATIVOS\nDesignação: Gerência\nEndereço: Rua dos Bombeiros Voluntários de Felgueiras, 104\nCódigo postal: 4610-165\nLocalidade: Felgueiras\nTelefone: 255312482\nFax: 255312419\nEndereço eletrónico: epf@epfelgueiras.pt\nPrazo de interposição do recurso: 5 dias\n\n28 - IDENTIFICAÇÃO DO(S) AUTOR(ES) DE ANÚNCIO\nNome: Vera Lúcia Ribeiro Sampaio\nCargo: Gerente\n419385207",
    "nipc": "504575848",
    "distrito": "Porto",
    "concelho": "Felgueiras",
    "freguesia": "União das Freguesias de Margaride (Santa Eulália), Várzea, Lagares, Varziela e Moure",
    "site": "www.epfelgueiras.pt",
    "email": "epf@epfelgueiras.pt",
    "designacao_contrato": "Aquisição de serviços de alojamento para formandos/as deslocados, em regime de exclusividade, dos cursos profissionais de Escola Profissional de Felgueiras para o ano letivo de 2025/2026",
    "descricao": "Aquisição de serviços de alojamento para formandos/as deslocados, em regime de exclusividade, dos cursos profissionais de Escola Profissional de Felgueiras para o ano letivo de 2025/2026",
    "preco_base": "57.458,83 EUR",
    "prazo_execucao": "321 DIAS",
    "fundos_eu": "Sim",
    "plataforma_eletronica": "ACIN",
    "url_procedimento": "https://www.acingov.pt",
    "autor_nome": "Vera Lúcia Ribeiro Sampaio",
    "autor_cargo": "Gerente"
  },
  {
    "numero_procedimento": "N/A",
    "entidade": "AnÃºncio de procedimento  n.Âº 20690/2025  -  DiÃ¡rio da RepÃºblica n.Âº 147/2025, SÃ©rie II de 2025-08-01",
    "link": "https://diariodarepublica.pt/dr/detalhe/contrato-publico/20690-927416011"
  },
  {
    "numero_procedimento": "N/A",
    "entidade": "AnÃºncio de procedimento  n.Âº 20692/2025  -  DiÃ¡rio da RepÃºblica n.Âº 147/2025, SÃ©rie II de 2025-08-01",
    "link": "https://diariodarepublica.pt/dr/detalhe/contrato-publico/20692-927416012"
  },
  {
    "numero_procedimento": "N/A",
    "entidade": "AnÃºncio de procedimento  n.Âº 20694/2025  -  DiÃ¡rio da RepÃºblica n.Âº 147/2025, SÃ©rie II de 2025-08-01",
    "link": "https://diariodarepublica.pt/dr/detalhe/contrato-publico/20694-927416013"
  },
  {
    "numero_procedimento": "N/A",
    "entidade": "AnÃºncio de procedimento  n.Âº 20695/2025  -  DiÃ¡rio da RepÃºblica n.Âº 147/2025, SÃ©rie II de 2025-08-01",
    "link": "https://diariodarepublica.pt/dr/detalhe/contrato-publico/20695-927416014"
  },
  {
    "numero_procedimento": "N/A",
    "entidade": "AnÃºncio de procedimento  n.Âº 20696/2025  -  DiÃ¡rio da RepÃºblica n.Âº 147/2025, SÃ©rie II de 2025-08-01",
    "link": "https://diariodarepublica.pt/dr/detalhe/contrato-publico/20696-927416015"
  },
  {
    "numero_procedimento": "N/A",
    "entidade": "AnÃºncio de procedimento  n.Âº 20697/2025  -  DiÃ¡rio da RepÃºblica n.Âº 147/2025, SÃ©rie II de 2025-08-01",
    "link": "https://diariodarepublica.pt/dr/detalhe/contrato-publico/20697-927416016"
  },
  {
    "numero_procedimento": "N/A",
    "entidade": "AnÃºncio de procedimento  n.Âº 20698/2025  -  DiÃ¡rio da RepÃºblica n.Âº 147/2025, SÃ©rie II de 2025-08-01",
    "link": "https://diariodarepublica.pt/dr/detalhe/contrato-publico/20698-927416017"
  },
  {
    "numero_procedimento": "N/A",
    "entidade": "AnÃºncio de procedimento  n.Âº 20700/2025  -  DiÃ¡rio da RepÃºblica n.Âº 147/2025, SÃ©rie II de 2025-08-01",
    "link": "https://diariodarepublica.pt/dr/detalhe/contrato-publico/20700-927416018"
  },
  {
    "numero_procedimento": "N/A",
    "entidade": "AnÃºncio de procedimento  n.Âº 20702/2025  -  DiÃ¡rio da RepÃºblica n.Âº 147/2025, SÃ©rie II de 2025-08-01",
    "link": "https://diariodarepublica.pt/dr/detalhe/contrato-publico/20702-927416019"
  },
  {
    "numero_procedimento": "N/A",
    "entidade": "AnÃºncio de procedimento  n.Âº 20663/2025  -  DiÃ¡rio da RepÃºblica n.Âº 147/2025, SÃ©rie II de 2025-08-01",
    "link": "https://diariodarepublica.pt/dr/detalhe/contrato-publico/20663-927474289"
  },
  {
    "numero_procedimento": "N/A",
    "entidade": "AnÃºncio de procedimento  n.Âº 20665/2025  -  DiÃ¡rio da RepÃºblica n.Âº 147/2025, SÃ©rie II de 2025-08-01",
    "link": "https://diariodarepublica.pt/dr/detalhe/contrato-publico/20665-927474290"
  },
  {
    "numero_procedimento": "N/A",
    "entidade": "AnÃºncio de procedimento  n.Âº 20666/2025  -  DiÃ¡rio da RepÃºblica n.Âº 147/2025, SÃ©rie II de 2025-08-01",
    "link": "https://diariodarepublica.pt/dr/detalhe/contrato-publico/20666-927474291"
  },
  {
    "numero_procedimento": "N/A",
    "entidade": "AnÃºncio de procedimento  n.Âº 20667/2025  -  DiÃ¡rio da RepÃºblica n.Âº 147/2025, SÃ©rie II de 2025-08-01",
    "link": "https://diariodarepublica.pt/dr/detalhe/contrato-publico/20667-927474292"
  },
  {
    "numero_procedimento": "N/A",
    "entidade": "AnÃºncio de procedimento  n.Âº 20668/2025  -  DiÃ¡rio da RepÃºblica n.Âº 147/2025, SÃ©rie II de 2025-08-01",
    "link": "https://diariodarepublica.pt/dr/detalhe/contrato-publico/20668-927474293"
  },
  {
    "numero_procedimento": "N/A",
    "entidade": "AnÃºncio de procedimento  n.Âº 20669/2025  -  DiÃ¡rio da RepÃºblica n.Âº 147/2025, SÃ©rie II de 2025-08-01",
    "link": "https://diariodarepublica.pt/dr/detalhe/contrato-publico/20669-927474294"
  },
  {
    "numero_procedimento": "N/A",
    "entidade": "IPO Porto FG, EPE",
    "link": "https://diariodarepublica.pt/dr/detalhe/contrato-publico/20670-927474295",
    "detalhes_completos": "1 - IDENTIFICAÇÃO E CONTACTOS DA ENTIDADE ADJUDICANTE\nDesignação da entidade adjudicante: IPO Porto FG, EPE\nNIPC: 506362299\nEndereço: Rua Drº António Bernardino De Almeida S/N, Porto\nCódigo postal: 4200-072\nLocalidade: Área Metropolitana do Porto\nPaís: Portugal\nNUT III: PT11A\nDistrito: Porto\nConcelho: Porto\nFreguesia: Todas\nTelefone: 225084000\nFax: 225084001\nEndereço da Entidade (URL): http://www.ipoporto.pt/\nEndereço Eletrónico: compras@ipoporto.min-saude.pt\neDelivery Gateway (URL): https://community.vortal.biz/public/\nFunção da Organização: Adquirente\nNorma jurídica da Entidade Adjudicante: Organismo de direito público\nÁrea de atividade da Autoridade Adjudicante: Saúde\n\n2 - JORNAL OFICIAL DA UNIÃO EUROPEIA\nO procedimento a que este anúncio diz respeito também é publicitado no Jornal Oficial da União Europeia? Não\n\n3 - AVISO\nModelo de Anúncio: Concurso público\nData de Envio do Anúncio: 31-07-2025\n\n5 - PROCESSO\nTipo de Procedimento: Concurso público\nPreço base do procedimento: Sim\nValor do preço base do procedimento: 53.437,27 EUR\nProcedimento com lotes? Sim\nNº Máx. de Lotes Autorizado: 12\nNúmero máximo de lotes que podem ser adjudicados a um concorrente: 12\n\n6 - OBJETO DO CONTRATO\nNúmero de referência interna: CP 1660/25\nDesignação do contrato: CP 1660/25 - Aquisição de detergentes e desinfetantes para o Serviço Central de Esterilização para 2025\nDescrição: CP 1660/25 - Aquisição de detergentes e desinfetantes para o Serviço Central de Esterilização para 2025\nTipo de Contrato Principal: Aquisição de Bens Móveis\nTipo de Contrato: Aquisição de Bens Móveis\nClassificação CPV (Vocabulário Comum para os Contratos Públicos)\nObjeto principal\nVocabulário Principal: 24455000\nPreço base s/IVA: 53.437,27 EUR\nLotes: \nNº: LOT-0001\nDescrição do Lote: Lote 1\nPreço base s/IVA: 7.134,00 EUR\nClassificação CPV (Vocabulário Comum para os Contratos Públicos)\nObjeto principal\nVocabulário Principal: 24455000\nNº: LOT-0002\nDescrição do Lote: Lote 2\nPreço base s/IVA: 6.264,00 EUR\nClassificação CPV (Vocabulário Comum para os Contratos Públicos)\nObjeto principal\nVocabulário Principal: 24455000\nNº: LOT-0003\nDescrição do Lote: Lote 3\nPreço base s/IVA: 2.723,40 EUR\nClassificação CPV (Vocabulário Comum para os Contratos Públicos)\nObjeto principal\nVocabulário Principal: 24455000\nNº: LOT-0004\nDescrição do Lote: Lote 4\nPreço base s/IVA: 4.270,80 EUR\nClassificação CPV (Vocabulário Comum para os Contratos Públicos)\nObjeto principal\nVocabulário Principal: 24455000\nNº: LOT-0005\nDescrição do Lote: Lote 5\nPreço base s/IVA: 1.162,44 EUR\nClassificação CPV (Vocabulário Comum para os Contratos Públicos)\nObjeto principal\nVocabulário Principal: 24455000\nNº: LOT-0006\nDescrição do Lote: Lote 6\nPreço base s/IVA: 2.274,00 EUR\nClassificação CPV (Vocabulário Comum para os Contratos Públicos)\nObjeto principal\nVocabulário Principal: 24455000\nNº: LOT-0007\nDescrição do Lote: Lote 7\nPreço base s/IVA: 2.500,30 EUR\nClassificação CPV (Vocabulário Comum para os Contratos Públicos)\nObjeto principal\nVocabulário Principal: 24455000\nNº: LOT-0008\nDescrição do Lote: Lote 8\nPreço base s/IVA: 5.402,16 EUR\nClassificação CPV (Vocabulário Comum para os Contratos Públicos)\nObjeto principal\nVocabulário Principal: 24455000\nNº: LOT-0009\nDescrição do Lote: Lote 9\nPreço base s/IVA: 1.853,28 EUR\nClassificação CPV (Vocabulário Comum para os Contratos Públicos)\nObjeto principal\nVocabulário Principal: 24455000\nNº: LOT-0010\nDescrição do Lote: Lote 10\nPreço base s/IVA: 333,00 EUR\nClassificação CPV (Vocabulário Comum para os Contratos Públicos)\nObjeto principal\nVocabulário Principal: 24455000\nNº: LOT-0011\nDescrição do Lote: Lote 11\nPreço base s/IVA: 19.450,00 EUR\nClassificação CPV (Vocabulário Comum para os Contratos Públicos)\nObjeto principal\nVocabulário Principal: 24455000\nNº: LOT-0012\nDescrição do Lote: Lote 12\nPreço base s/IVA: 69,89 EUR\nClassificação CPV (Vocabulário Comum para os Contratos Públicos)\nObjeto principal\nVocabulário Principal: 24455000\n\n7 - INDICAÇÕES ADICIONAIS\nO contrato envolve aquisição conjunta (satisfação de várias entidades)? Não\nO contrato é adjudicado por uma central de compras? Não\n\n8 - TÉCNICAS\nO concurso destina-se à celebração de um acordo-quadro? Inexistência de acordo-quadro\nÉ utilizado um leilão eletrónico? Não\nÉ adotada uma fase de negociação? Não\nSistema de Aquisição Dinâmico: Inexistência de sistema de aquisição dinâmico\n\n9 - LOCAL DA EXECUÇÃO DO CONTRATO\nLOCAL DA EXECUÇÃO DO CONTRATO (PROCEDIMENTO)\nPaís: Portugal\nNUT III: PT11A\nLocalidade: Área Metropolitana do Porto\nDistrito: Porto\nConcelho: Porto\nFreguesia: Freguesia de Paranhos - Porto\nLOCAL DA EXECUÇÃO DO CONTRATO (LOTE)\nIdentificador do Lote: LOT-0001; LOT-0002; LOT-0003; LOT-0004; LOT-0005; LOT-0006; LOT-0007; LOT-0008; LOT-0009; LOT-0010; LOT-0011; LOT-0012\nPaís: Portugal\nNUT III: PT11A\nLocalidade: Área Metropolitana do Porto\nDistrito: Porto\nConcelho: Porto\nFreguesia: Freguesia de Paranhos - Porto\n\n10 - PRAZO DE EXECUÇÃO DO CONTRATO\nIdentificador do Lote: LOT-0001; LOT-0002; LOT-0003; LOT-0004; LOT-0005; LOT-0006; LOT-0007; LOT-0008; LOT-0009; LOT-0010; LOT-0011; LOT-0012\nPrazo de execução do contrato: 120 DIAS\nPrevisão de renovações: Não\n\n11 - FUNDOS EU\nIdentificador do Lote: LOT-0001; LOT-0002; LOT-0003; LOT-0004; LOT-0005; LOT-0006; LOT-0007; LOT-0008; LOT-0009; LOT-0010; LOT-0011; LOT-0012\nTêm fundos EU? Não\n\n12 - DOCUMENTOS DE HABILITAÇÃO\nHabilitação para o exercício da atividade profissional: Não\n\n13 - CONDIÇÕES DE APRESENTAÇÃO\nPlataforma eletrónica utilizada pela entidade adjudicante: VORTAL\nURL para Apresentação: https://community.vortal.biz/public/\nAdmissibilidade da apresentação de propostas variantes: Não autorizado\nPrazo para apresentação das propostas: 15-08-2025 17:00\nPrazo durante o qual os concorrentes são obrigados a manter as respetivas propostas: 155 dias a contar do termo do prazo para a apresentação das propostas\nIndicação de Subcontratação na Proposta: Inexistência de indicação de subcontratação\n\n14 - PRESTAÇÃO DE CAUÇÃO\nPrestação de caução: Não\n\n15 - FORNECIMENTO DAS PEÇAS DO CONCURSO, APRESENTAÇÃO DE PEDIDOS DE PARTICIPAÇÃO E APRESENTAÇÃO DAS PROPOSTAS\nLink para acesso às peças do concurso (URL): https://community.vortal.biz/Public/public-tender-documents/eFdiaGxCMGFmQWhGNFkyTWljMFBYUWlTQURiWUFFQ0hXZE80V1BrdTc4cGUwTks1OWdOeWx6LzNEcXJ1ZVBIbXk0YkhWbWpIcW1pQk4vQnJuNkFqelE9PTRpJDBo\n\n20 - OUTROS REQUISITOS\nIdentificador do Lote: LOT-0001; LOT-0002; LOT-0003; LOT-0004; LOT-0005; LOT-0006; LOT-0007; LOT-0008; LOT-0009; LOT-0010; LOT-0011; LOT-0012\nInformação sobre contratos reservados. Aplica-se a contratos reservados (54º-A)? Não\n\n21 - CRITÉRIO DE ADJUDICAÇÃO\nO Critério de adjudicação é diferenciado por lote? Não\nMultifator: Sim\nFator: \nNome: Qualidade\nPonderação: 40%\nSubfatores: Não\nFator: \nNome: Qualidade\nPonderação: 60%\nSubfatores: Não\n\n24 - CONDIÇÕES DO CONTRATO\nIdentificador do Lote: LOT-0001; LOT-0002; LOT-0003; LOT-0004; LOT-0005; LOT-0006; LOT-0007; LOT-0008; LOT-0009; LOT-0010; LOT-0011; LOT-0012\nFaturação Eletrónica: Permitido\nObrigação de Subcontratação:\nCódigo da Obrigação de Subcontratação: Não é aplicável nenhuma obrigação de subcontratação.\n\n25 - COMPRA PÚBLICA ESTRATÉGICA\nCompra Pública Estratégica: Inexistência de contratação pública estratégica\n\n26 - INFORMAÇÕES ADICIONAIS\nIdentificador do Lote: LOT-0001; LOT-0002; LOT-0003; LOT-0004; LOT-0005; LOT-0006; LOT-0007; LOT-0008; LOT-0009; LOT-0010; LOT-0011; LOT-0012\nContrato adequado para PME: Sim\nCobertura ACP (Acordo dos Contratos Públicos da Organização Mundial do Comércio): Não\n\n27 - IDENTIFICAÇÃO E CONTACTOS DO ÓRGÃO DE RECURSOS ADMINISTRATIVOS\nDesignação: Conselho de Administração\nEndereço: Rua Dr António Bernardino de Almeida\nCódigo postal: 4200-072\nLocalidade: Porto\nTelefone: +351 225084000\nFax: +351 225084001\nEndereço eletrónico: compras@ipoporto.min-saude.pt\n\n28 - IDENTIFICAÇÃO DO(S) AUTOR(ES) DE ANÚNCIO\nNome: Sandra Luís\nCargo: Diretora do serviço de Aprovisionamento e Logística\n419378647",
    "nipc": "506362299",
    "distrito": "Porto",
    "concelho": "Porto",
    "freguesia": "Todas",
    "site": "http://www.ipoporto.pt/",
    "email": "compras@ipoporto.min-saude.pt",
    "designacao_contrato": "CP 1660/25 - Aquisição de detergentes e desinfetantes para o Serviço Central de Esterilização para 2025",
    "descricao": "CP 1660/25 - Aquisição de detergentes e desinfetantes para o Serviço Central de Esterilização para 2025",
    "preco_base": "53.437,27 EUR",
    "prazo_execucao": "120 DIAS",
    "fundos_eu": "Não",
    "plataforma_eletronica": "VORTAL",
    "url_procedimento": "https://community.vortal.biz/public/",
    "autor_nome": "Sandra Luís",
    "autor_cargo": "Diretora do serviço de Aprovisionamento e Logística"
  },
  {
    "numero_procedimento": "N/A",
    "entidade": "AnÃºncio de procedimento  n.Âº 20671/2025  -  DiÃ¡rio da RepÃºblica n.Âº 147/2025, SÃ©rie II de 2025-08-01",
    "link": "https://diariodarepublica.pt/dr/detalhe/contrato-publico/20671-927474296"
  },
  {
    "numero_procedimento": "N/A",
    "entidade": "AnÃºncio de procedimento  n.Âº 20672/2025  -  DiÃ¡rio da RepÃºblica n.Âº 147/2025, SÃ©rie II de 2025-08-01",
    "link": "https://diariodarepublica.pt/dr/detalhe/contrato-publico/20672-927474297"
  },
  {
    "numero_procedimento": "N/A",
    "entidade": "AnÃºncio de procedimento  n.Âº 20673/2025  -  DiÃ¡rio da RepÃºblica n.Âº 147/2025, SÃ©rie II de 2025-08-01",
    "link": "https://diariodarepublica.pt/dr/detalhe/contrato-publico/20673-927474298"
  },
  {
    "numero_procedimento": "N/A",
    "entidade": "AnÃºncio de procedimento  n.Âº 20674/2025  -  DiÃ¡rio da RepÃºblica n.Âº 147/2025, SÃ©rie II de 2025-08-01",
    "link": "https://diariodarepublica.pt/dr/detalhe/contrato-publico/20674-927474299"
  },
  {
    "numero_procedimento": "N/A",
    "entidade": "AnÃºncio de procedimento  n.Âº 20676/2025  -  DiÃ¡rio da RepÃºblica n.Âº 147/2025, SÃ©rie II de 2025-08-01",
    "link": "https://diariodarepublica.pt/dr/detalhe/contrato-publico/20676-927474300"
  },
  {
    "numero_procedimento": "N/A",
    "entidade": "AnÃºncio de procedimento  n.Âº 20677/2025  -  DiÃ¡rio da RepÃºblica n.Âº 147/2025, SÃ©rie II de 2025-08-01",
    "link": "https://diariodarepublica.pt/dr/detalhe/contrato-publico/20677-927474301"
  },
  {
    "numero_procedimento": "N/A",
    "entidade": "AnÃºncio de procedimento  n.Âº 20678/2025  -  DiÃ¡rio da RepÃºblica n.Âº 147/2025, SÃ©rie II de 2025-08-01",
    "link": "https://diariodarepublica.pt/dr/detalhe/contrato-publico/20678-927474314"
  },
  {
    "numero_procedimento": "N/A",
    "entidade": "AnÃºncio de procedimento  n.Âº 20679/2025  -  DiÃ¡rio da RepÃºblica n.Âº 147/2025, SÃ©rie II de 2025-08-01",
    "link": "https://diariodarepublica.pt/dr/detalhe/contrato-publico/20679-927474315"
  },
  {
    "numero_procedimento": "N/A",
    "entidade": "AnÃºncio de procedimento  n.Âº 20680/2025  -  DiÃ¡rio da RepÃºblica n.Âº 147/2025, SÃ©rie II de 2025-08-01",
    "link": "https://diariodarepublica.pt/dr/detalhe/contrato-publico/20680-927474316"
  },
  {
    "numero_procedimento": "N/A",
    "entidade": "AnÃºncio de procedimento  n.Âº 20682/2025  -  DiÃ¡rio da RepÃºblica n.Âº 147/2025, SÃ©rie II de 2025-08-01",
    "link": "https://diariodarepublica.pt/dr/detalhe/contrato-publico/20682-927474324"
  },
  {
    "numero_procedimento": "N/A",
    "entidade": "AnÃºncio de procedimento  n.Âº 20683/2025  -  DiÃ¡rio da RepÃºblica n.Âº 147/2025, SÃ©rie II de 2025-08-01",
    "link": "https://diariodarepublica.pt/dr/detalhe/contrato-publico/20683-927474325"
  },
  {
    "numero_procedimento": "N/A",
    "entidade": "AnÃºncio de procedimento  n.Âº 20684/2025  -  DiÃ¡rio da RepÃºblica n.Âº 147/2025, SÃ©rie II de 2025-08-01",
    "link": "https://diariodarepublica.pt/dr/detalhe/contrato-publico/20684-927474326"
  },
  {
    "numero_procedimento": "N/A",
    "entidade": "AnÃºncio de procedimento  n.Âº 20686/2025  -  DiÃ¡rio da RepÃºblica n.Âº 147/2025, SÃ©rie II de 2025-08-01",
    "link": "https://diariodarepublica.pt/dr/detalhe/contrato-publico/20686-927474327"
  },
  {
    "numero_procedimento": "N/A",
    "entidade": "AnÃºncio de procedimento  n.Âº 20689/2025  -  DiÃ¡rio da RepÃºblica n.Âº 147/2025, SÃ©rie II de 2025-08-01",
    "link": "https://diariodarepublica.pt/dr/detalhe/contrato-publico/20689-927474328"
  },
  {
    "numero_procedimento": "N/A",
    "entidade": "AnÃºncio de procedimento  n.Âº 20691/2025  -  DiÃ¡rio da RepÃºblica n.Âº 147/2025, SÃ©rie II de 2025-08-01",
    "link": "https://diariodarepublica.pt/dr/detalhe/contrato-publico/20691-927474329"
  },
  {
    "numero_procedimento": "N/A",
    "entidade": "AnÃºncio de procedimento  n.Âº 20693/2025  -  DiÃ¡rio da RepÃºblica n.Âº 147/2025, SÃ©rie II de 2025-08-01",
    "link": "https://diariodarepublica.pt/dr/detalhe/contrato-publico/20693-927474330"
  },
  {
    "numero_procedimento": "N/A",
    "entidade": "AnÃºncio de procedimento  n.Âº 20699/2025  -  DiÃ¡rio da RepÃºblica n.Âº 147/2025, SÃ©rie II de 2025-08-01",
    "link": "https://diariodarepublica.pt/dr/detalhe/contrato-publico/20699-927474334"
  },
  {
    "numero_procedimento": "N/A",
    "entidade": "AnÃºncio de procedimento  n.Âº 20701/2025  -  DiÃ¡rio da RepÃºblica n.Âº 147/2025, SÃ©rie II de 2025-08-01",
    "link": "https://diariodarepublica.pt/dr/detalhe/contrato-publico/20701-927474335"
  }
]