[
  {
    "numero_procedimento": "N/A",
    "entidade": "Lisboa SRU",
    "link": "https://diariodarepublica.pt/dr/detalhe/contrato-publico/20661-927415986",
    "detalhes_completos": "1 - IDENTIFICAÇÃO E CONTACTOS DA ENTIDADE ADJUDICANTE\nDesignação da entidade adjudicante: Lisboa SRU\nNIPC: 507023129\nEndereço: Praça do Município, 31 ¿ 2.º/4.º Piso\nCódigo postal: 1100-365\nLocalidade: Lisboa\nPaís: Portugal\nNUT III: PT170\nDistrito: Lisboa\nConcelho: Lisboa\nFreguesia: Freguesia de Santa Maria Maior - Lisboa\nTelefone: 218847030\nFax: 2188470030\nEndereço da Entidade (URL): https://www.lisboaocidentalsru.pt\nEndereço Eletrónico: compras.publicas@lisboaocidentalsru.pt\nFunção da Organização: Adquirente\nNorma jurídica da Entidade Adjudicante: Organismo de direito público, controlado por uma autoridade da administração central\nÁrea de atividade da Autoridade Adjudicante: Serviços públicos das administrações públicas\n\n2 - JORNAL OFICIAL DA UNIÃO EUROPEIA\nO procedimento a que este anúncio diz respeito também é publicitado no Jornal Oficial da União Europeia? Sim\n\n3 - AVISO\nModelo de Anúncio: Concurso de conceção\nData de Envio do Anúncio: 29-07-2025\n\n5 - PROCESSO\nTipo de Procedimento: Concurso público\nPreço base do procedimento: Sim\nValor do preço base do procedimento: 810.000,00 EUR\nProcedimento com lotes? Não\n\n6 - OBJETO DO CONTRATO\nNúmero de referência interna: SRU20250000394\nDesignação do contrato: Escola Secundária D. Luísa de Gusmão\nDescrição: Escola Secundária D. Luísa de Gusmão\nOpções: Não\nTipo de Contrato Principal: Aquisição de Serviços\nTipo de Contrato: Aquisição de Serviços\nClassificação CPV (Vocabulário Comum para os Contratos Públicos)\nObjeto principal\nVocabulário Principal: 71300000\nPreço base s/IVA: 810.000,00 EUR\n\n7 - INDICAÇÕES ADICIONAIS\nEstá prevista a possibilidade de o(s) vencedor(es) do concurso de conceção realizar(em) o desenvolvimento de parte(s) do projeto vencedor, mediante procedimento por ajuste direto? Sim\nO contrato envolve aquisição conjunta (satisfação de várias entidades)? Não\n\n8 - TÉCNICAS\nSistema de Aquisição Dinâmico: Inexistência de sistema de aquisição dinâmico\n\n9 - LOCAL DA EXECUÇÃO DO CONTRATO\nLOCAL DA EXECUÇÃO DO CONTRATO (PROCEDIMENTO)\nPaís: Portugal\nNUT III: PT170\nLocalidade: Lisboa\nDistrito: Lisboa\nConcelho: Lisboa\nFreguesia: Freguesia de Arroios - Lisboa\n\n11 - FUNDOS EU\nTêm fundos EU? Não\n\n12 - DOCUMENTOS DE HABILITAÇÃO\nHabilitação para o exercício da atividade profissional: Não\n\n13 - CONDIÇÕES DE APRESENTAÇÃO\nPlataforma eletrónica utilizada pela entidade adjudicante: ANOGOV\nURL para Apresentação: https://www.anogov.com/lisboaocidental-sru/faces/\nModo de apresentação dos trabalhos de conceção: De acordo com os Termos de Referência\n\n15 - FORNECIMENTO DAS PEÇAS DO CONCURSO, APRESENTAÇÃO DE PEDIDOS DE PARTICIPAÇÃO E APRESENTAÇÃO DAS PROPOSTAS\nLink para acesso às peças do concurso (URL): https://www.anogov.com/lisboaocidental-sru/faces/app/acessoDocs.jsp?codigoAcesso=Tg2iFkczXZ0sG4VRZlgKEPZKbZzuCpIFiZFVKlCNKbXdck6pjk\n\n16 - MODALIDADE DO CONCURSO DE CONCEÇÃO/IDEIAS\nÉ um concurso de conceção simplificado? Não\nModalidade do concurso: Concurso Público\nPrazo para apresentação dos trabalhos de conceção/ideias: 62 DIAS\nRequisitos mínimos de capacidade técnica: N.A\n\n20 - OUTROS REQUISITOS\nInformação sobre contratos reservados. Aplica-se a contratos reservados (54º-A)? Não\n\n22 - NÚMERO DE TRABALHOS DE CONCEÇÃO / IDEIAS A SELECIONAR\nNúmero de trabalhos de VII/ideias a selecionar: 4\n\n23 - PRÉMIOS\nPrémios: Sim\nMontante global dos prémios de participação: 26000\nPrémio:\nDescrição: Prémio\nClassificação: 3\nValor: 5000\nPrémio:\nDescrição: Prémio\nClassificação: 1\nValor: 10000\nPrémio:\nDescrição: Prémio\nClassificação: 4\nValor: 3000\nPrémio:\nDescrição: Prémio\nClassificação: 2\nValor: 8000\n\n24 - CONDIÇÕES DO CONTRATO\nFaturação Eletrónica: Permitido\nObrigação de Subcontratação:\nCódigo da Obrigação de Subcontratação: Não é aplicável nenhuma obrigação de subcontratação.\n\n25 - COMPRA PÚBLICA ESTRATÉGICA\nCompra Pública Estratégica: Inexistência de contratação pública estratégica\n\n26 - INFORMAÇÕES ADICIONAIS\n\n27 - IDENTIFICAÇÃO E CONTACTOS DO ÓRGÃO DE RECURSOS ADMINISTRATIVOS\nDesignação: Lisboa Ocidental SRU EM S.A\nEndereço: Praça do Município 31 2º\nCódigo postal: 1100-365\nLocalidade: Lisboa\nEndereço eletrónico: geral@lisboasru.pt\n\n28 - IDENTIFICAÇÃO DO(S) AUTOR(ES) DE ANÚNCIO\nNome: Luis Santos\nCargo: Assistente Técnico\n419370919",
    "nipc": "507023129",
    "distrito": "Lisboa",
    "concelho": "Lisboa",
    "freguesia": "Freguesia de Santa Maria Maior - Lisboa",
    "site": "https://www.lisboaocidentalsru.pt",
    "email": "compras.publicas@lisboaocidentalsru.pt",
    "designacao_contrato": "Escola Secundária D. Luísa de Gusmão",
    "descricao": "Escola Secundária D. Luísa de Gusmão",
    "preco_base": "810.000,00 EUR",
    "prazo_execucao": null,
    "prazo_apresentacao_propostas": null,
    "fundos_eu": "Não",
    "plataforma_eletronica": "ANOGOV",
    "url_procedimento": "https://www.anogov.com/lisboaocidental-sru/faces/",
    "autor_nome": "Luis Santos",
    "autor_cargo": "Assistente Técnico"
  },
  {
    "numero_procedimento": "N/A",
    "entidade": "Associação Turismo de Lisboa",
    "link": "https://diariodarepublica.pt/dr/detalhe/contrato-publico/20662-927415987",
    "detalhes_completos": "1 - IDENTIFICAÇÃO E CONTACTOS DA ENTIDADE ADJUDICANTE\nDesignação da entidade adjudicante: Associação Turismo de Lisboa\nNIPC: 501880160\nServiço/Órgão/Pessoa de contacto: André Duque\nEndereço: R do Arsenal, 15\nCódigo postal: 1100-038\nLocalidade: Lisboa\nPaís: Portugal\nNUT III: PT170\nDistrito: Lisboa\nConcelho: Lisboa\nFreguesia: Todas\nTelefone: 210312700\nFax: 210312899\nEndereço da Entidade (URL): https://www.visitlisboa.com/pt-pt\nEndereço Eletrónico: atl@visitlisboa.com\neDelivery Gateway (URL): https://community.vortal.biz/public/\nFunção da Organização: Adquirente\nNorma jurídica da Entidade Adjudicante: Organização que adjudica um contrato subvencionado por uma autoridade da administração central\nÁrea de atividade da Autoridade Adjudicante: Atividades recreativas, culturais e religiosas\n\n2 - JORNAL OFICIAL DA UNIÃO EUROPEIA\nO procedimento a que este anúncio diz respeito também é publicitado no Jornal Oficial da União Europeia? Não\n\n3 - AVISO\nModelo de Anúncio: Concurso público\nData de Envio do Anúncio: 31-07-2025\n\n5 - PROCESSO\nTipo de Procedimento: Concurso público\nPreço base do procedimento: Sim\nValor do preço base do procedimento: 2.950.000,00 EUR\nProcedimento com lotes? Não\n\n6 - OBJETO DO CONTRATO\nNúmero de referência interna: 12.i_Empreitada_CP_03_2025\nDesignação do contrato: Concurso Publico n.º 12.i_Empreitada_CP_03_2025\nDescrição: Empreitada de obra pública de recuperação da envolvente exterior do Museu Nacional de Arte Antiga\nTipo de Contrato Principal: Empreitada de Obras Públicas\nTipo de Contrato: Empreitada de Obras Públicas\nClassificação CPV (Vocabulário Comum para os Contratos Públicos)\nObjeto principal\nVocabulário Principal: 45200000\nPreço base s/IVA: 2.950.000,00 EUR\n\n7 - INDICAÇÕES ADICIONAIS\nO contrato envolve aquisição conjunta (satisfação de várias entidades)? Não\nO contrato é adjudicado por uma central de compras? Não\n\n8 - TÉCNICAS\nO concurso destina-se à celebração de um acordo-quadro? Inexistência de acordo-quadro\nÉ utilizado um leilão eletrónico? Não\nÉ adotada uma fase de negociação? Não\nSistema de Aquisição Dinâmico: Inexistência de sistema de aquisição dinâmico\n\n9 - LOCAL DA EXECUÇÃO DO CONTRATO\nLOCAL DA EXECUÇÃO DO CONTRATO (PROCEDIMENTO)\nPaís: Portugal\nNUT III: PT170\nLocalidade: Lisboa\nDistrito: Lisboa\nConcelho: Lisboa\nFreguesia: Freguesia da Estrela\n\n10 - PRAZO DE EXECUÇÃO DO CONTRATO\nPrazo de execução do contrato: 10 MESES\nPrevisão de renovações: Não\n\n11 - FUNDOS EU\nTêm fundos EU? Não\n\n12 - DOCUMENTOS DE HABILITAÇÃO\nHabilitação para o exercício da atividade profissional: Sim\nTipo: Alvará\nDescrição: i. 1.ª categoria, 2.ª subcategoria, classe 2;\nii. 1.ª categoria, 4.ª subcategoria, classe 1;\niii. 1.ª categoria, 5.ª subcategoria, classe 1;\niv. 1.ª categoria, 6.ª subcategoria, classe 1;\nv. 1.ª categoria, 8.ª subcategoria, classe 1;\nvi. 1.ª categoria, 10.ª subcategoria, classe 5;\nvii. 5.ª categoria, 1.ª subcategoria, classe 1;\nnos termos constantes do Anexo I da Lei n.º 41/2015, de 3 de junho, e no artigo 1.º da\nPortaria n.º 212/2022, de 23 de agosto;\n\n13 - CONDIÇÕES DE APRESENTAÇÃO\nPlataforma eletrónica utilizada pela entidade adjudicante: VORTAL\nURL para Apresentação: https://community.vortal.biz/public/\nAdmissibilidade da apresentação de propostas variantes: Não autorizado\nPrazo para apresentação das propostas: 15-08-2025 18:00\nPrazo durante o qual os concorrentes são obrigados a manter as respetivas propostas: 66 dias a contar do termo do prazo para a apresentação das propostas\nIndicação de Subcontratação na Proposta: Inexistência de indicação de subcontratação\n\n14 - PRESTAÇÃO DE CAUÇÃO\nPrestação de caução: Sim\nPercentagem: 5%\nDescrição da Garantia Exigida: cfr. programa de procedimento\n\n15 - FORNECIMENTO DAS PEÇAS DO CONCURSO, APRESENTAÇÃO DE PEDIDOS DE PARTICIPAÇÃO E APRESENTAÇÃO DAS PROPOSTAS\nLink para acesso às peças do concurso (URL): https://community.vortal.biz/Public/public-tender-documents/bjlmdUJkclFPWStSbHNNZllmdkhFOTBCWnllSFd6VWQ1RW9sSUU0eVNMaVZVYkZtUVhKQmVVdFlOWW16cnpJTTh0NUQrK3pqbnpKbzM4N0E4V3VSTnc9PUhkYmZB\n\n20 - OUTROS REQUISITOS\nInformação sobre contratos reservados. Aplica-se a contratos reservados (54º-A)? Não\n\n21 - CRITÉRIO DE ADJUDICAÇÃO\nMultifator: Não\nMonofator:\nNome: Preço\n\n24 - CONDIÇÕES DO CONTRATO\nFaturação Eletrónica: Permitido\nObrigação de Subcontratação:\nCódigo da Obrigação de Subcontratação: Não é aplicável nenhuma obrigação de subcontratação.\n\n25 - COMPRA PÚBLICA ESTRATÉGICA\nCompra Pública Estratégica: Inexistência de contratação pública estratégica\n\n26 - INFORMAÇÕES ADICIONAIS\nContrato adequado para PME: Sim\nCobertura ACP (Acordo dos Contratos Públicos da Organização Mundial do Comércio): Não\n\n27 - IDENTIFICAÇÃO E CONTACTOS DO ÓRGÃO DE RECURSOS ADMINISTRATIVOS\nDesignação: Comissão Executiva\nEndereço: Rua do Arsenal n.º 23\nCódigo postal: 1100-038\nLocalidade: Lisboa\nTelefone: +351 210312700\nFax: +351 210312899\nEndereço eletrónico: atl@visitlisboa.com\nPrazo de interposição do recurso: 5 dias\n\n28 - IDENTIFICAÇÃO DO(S) AUTOR(ES) DE ANÚNCIO\nNome: David Mendes Coelho\nCargo: Assessoria ao Gabinete Jurídico\n419382186",
    "nipc": "501880160",
    "distrito": "Lisboa",
    "concelho": "Lisboa",
    "freguesia": "Todas",
    "site": "https://www.visitlisboa.com/pt-pt",
    "email": "atl@visitlisboa.com",
    "designacao_contrato": "Concurso Publico n.º 12.i_Empreitada_CP_03_2025",
    "descricao": "Empreitada de obra pública de recuperação da envolvente exterior do Museu Nacional de Arte Antiga",
    "preco_base": "2.950.000,00 EUR",
    "prazo_execucao": "10 MESES",
    "prazo_apresentacao_propostas": "15-08-2025 18:00",
    "fundos_eu": "Não",
    "plataforma_eletronica": "VORTAL",
    "url_procedimento": "https://community.vortal.biz/public/",
    "autor_nome": "David Mendes Coelho",
    "autor_cargo": "Assessoria ao Gabinete Jurídico"
  },
  {
    "numero_procedimento": "N/A",
    "entidade": "Património Cultural, IP",
    "link": "https://diariodarepublica.pt/dr/detalhe/contrato-publico/20664-927415988",
    "detalhes_completos": "1 - IDENTIFICAÇÃO E CONTACTOS DA ENTIDADE ADJUDICANTE\nDesignação da entidade adjudicante: Património Cultural, IP\nNIPC: 517842920\nServiço/Órgão/Pessoa de contacto: Departamento de Projetos e Obras\nEndereço: Palacete Vilar de Allen, Rua António Cardoso, 175\nCódigo postal: 4150-081\nLocalidade: Porto\nPaís: Portugal\nNUT III: PT11A\nDistrito: Porto\nConcelho: Porto\nFreguesia: Todas\nTelefone: 213614200\nFax: 213614200\nEndereço da Entidade (URL): www.patrimoniocultural.gov.pt\nEndereço Eletrónico: dpo@patrimoniocultural.gov.pt\neDelivery Gateway (URL): https://www.acingov.pt\nFunção da Organização: Adquirente\nSubfunção da Organização: Organização que recebe as propostas\nNorma jurídica da Entidade Adjudicante: Organismo de direito público\nÁrea de atividade da Autoridade Adjudicante: Serviços públicos das administrações públicas\n\n2 - JORNAL OFICIAL DA UNIÃO EUROPEIA\nO procedimento a que este anúncio diz respeito também é publicitado no Jornal Oficial da União Europeia? Não\n\n3 - AVISO\nModelo de Anúncio: Concurso público\nData de Envio do Anúncio: 31-07-2025\n\n5 - PROCESSO\nTipo de Procedimento: Concurso público\nPreço base do procedimento: Sim\nValor do preço base do procedimento: 1.049.500,00 EUR\nProcedimento com lotes? Não\n\n6 - OBJETO DO CONTRATO\nNúmero de referência interna: CP/29/2025\nDesignação do contrato: ID 6925 PRR - Forte de Sacavém -Recuperação geral das instalações técnicas\nDescrição: ID 6925 PRR - Forte de Sacavém -Recuperação geral das instalações técnicas\n\nTipo de Contrato Principal: Empreitada de Obras Públicas\nTipo de Contrato: Empreitada de Obras Públicas\nClassificação CPV (Vocabulário Comum para os Contratos Públicos)\nObjeto principal\nVocabulário Principal: 45331000\nPreço base s/IVA: 1.049.500,00 EUR\n\n7 - INDICAÇÕES ADICIONAIS\nO contrato envolve aquisição conjunta (satisfação de várias entidades)? Não\nO contrato é adjudicado por uma central de compras? Não\n\n8 - TÉCNICAS\nO concurso destina-se à celebração de um acordo-quadro? Inexistência de acordo-quadro\nÉ utilizado um leilão eletrónico? Não\nÉ adotada uma fase de negociação? Não\nSistema de Aquisição Dinâmico: Inexistência de sistema de aquisição dinâmico\n\n9 - LOCAL DA EXECUÇÃO DO CONTRATO\nLOCAL DA EXECUÇÃO DO CONTRATO (PROCEDIMENTO)\nPaís: Portugal\nNUT III: PT170\nLocalidade: União das Freguesias de Sacavém e Prior Velho\nDistrito: Lisboa\nConcelho: Loures\nFreguesia: União das Freguesias de Sacavém e Prior Velho\n\n10 - PRAZO DE EXECUÇÃO DO CONTRATO\nPrazo de execução do contrato: 270 DIAS\nPrevisão de renovações: Não\n\n11 - FUNDOS EU\nTêm fundos EU? Sim\n\n12 - DOCUMENTOS DE HABILITAÇÃO\nHabilitação para o exercício da atividade profissional: Sim\nTipo: Alvará\nDescrição: - 1.ª Subcategoria (Instalações elétricas de utilização de baixa tensão com potência até 50 kVA) da 4ª categoria (instalações elétricas e mecânicas), em classe correspondente ao valor da parte dos trabalhos a que respeita (instalações elétricas);\n- 9.ª subcategoria (Infraestruturas de telecomunicações) da 4ª categoria (instalações elétricas e mecânicas), em classe correspondente ao valor da parte dos trabalhos a que respeita (instalações de telecomunicações);\n- 12.ª subcategoria (Aquecimento, ventilação, ar condicionado e refrigeração) da 4ª categoria (instalações elétricas e mecânicas), em classe correspondente ao valor da parte dos trabalhos a que respeita (instalações de ar condicionado).\n\n13 - CONDIÇÕES DE APRESENTAÇÃO\nPlataforma eletrónica utilizada pela entidade adjudicante: ACIN\nURL para Apresentação: https://www.acingov.pt\nAdmissibilidade da apresentação de propostas variantes: Não autorizado\nPrazo para apresentação das propostas: 14-08-2025 23:59\nPrazo durante o qual os concorrentes são obrigados a manter as respetivas propostas: 180 dias a contar do termo do prazo para a apresentação das propostas\nIndicação de Subcontratação na Proposta: Inexistência de indicação de subcontratação\n\n14 - PRESTAÇÃO DE CAUÇÃO\nPrestação de caução: Sim\nPercentagem: 5%\nDescrição da Garantia Exigida: O valor da caução é de 5.00% do preço contratual.\n\n15 - FORNECIMENTO DAS PEÇAS DO CONCURSO, APRESENTAÇÃO DE PEDIDOS DE PARTICIPAÇÃO E APRESENTAÇÃO DAS PROPOSTAS\nLink para acesso às peças do concurso (URL): https://www.acingov.pt/acingovprod/2/zonaPublica/zona_publica_c/donwloadProcedurePiece/OTMwNTM4\n\n20 - OUTROS REQUISITOS\nInformação sobre contratos reservados. Aplica-se a contratos reservados (54º-A)? Não\n\n21 - CRITÉRIO DE ADJUDICAÇÃO\nMultifator: Não\nMonofator:\nNome: Preço\n\n24 - CONDIÇÕES DO CONTRATO\nFaturação Eletrónica: Permitido\nObrigação de Subcontratação:\nCódigo da Obrigação de Subcontratação: Não é aplicável nenhuma obrigação de subcontratação.\n\n25 - COMPRA PÚBLICA ESTRATÉGICA\nCompra Pública Estratégica: Inexistência de contratação pública estratégica\n\n26 - INFORMAÇÕES ADICIONAIS\nContrato adequado para PME: Sim\nCobertura ACP (Acordo dos Contratos Públicos da Organização Mundial do Comércio): Não\n\n27 - IDENTIFICAÇÃO E CONTACTOS DO ÓRGÃO DE RECURSOS ADMINISTRATIVOS\nDesignação: Presidente do Concelho Diretivo\nEndereço: Palácio Nacional da Ajuda, Ala Norte\nCódigo postal: 1349-021\nLocalidade: Lisboa\nTelefone: 213614200\nFax: \nEndereço eletrónico: joao.soalheiro@patrimoniocultural.gov.pt\n\n28 - IDENTIFICAÇÃO DO(S) AUTOR(ES) DE ANÚNCIO\nNome: Raquel Barroso\nCargo: Assistente Técnico\n419384308",
    "nipc": "517842920",
    "distrito": "Porto",
    "concelho": "Porto",
    "freguesia": "Todas",
    "site": "www.patrimoniocultural.gov.pt",
    "email": "dpo@patrimoniocultural.gov.pt",
    "designacao_contrato": "ID 6925 PRR - Forte de Sacavém -Recuperação geral das instalações técnicas",
    "descricao": "ID 6925 PRR - Forte de Sacavém -Recuperação geral das instalações técnicas",
    "preco_base": "1.049.500,00 EUR",
    "prazo_execucao": "270 DIAS",
    "prazo_apresentacao_propostas": "14-08-2025 23:59",
    "fundos_eu": "Sim",
    "plataforma_eletronica": "ACIN",
    "url_procedimento": "https://www.acingov.pt",
    "autor_nome": "Raquel Barroso",
    "autor_cargo": "Assistente Técnico"
  },
  {
    "numero_procedimento": "N/A",
    "entidade": "AC, Águas de Coimbra, EM",
    "link": "https://diariodarepublica.pt/dr/detalhe/contrato-publico/20675-927415990",
    "detalhes_completos": "1 - IDENTIFICAÇÃO E CONTACTOS DA ENTIDADE ADJUDICANTE\nDesignação da entidade adjudicante: AC, Águas de Coimbra, EM\nNIPC: 506566307\nEndereço: Rua da Alegria nº 111\nCódigo postal: 3000-018\nLocalidade: Coimbra\nPaís: Portugal\nNUT III: PT16E\nDistrito: Coimbra\nConcelho: Coimbra\nFreguesia: União das Freguesias de Coimbra (Sé Nova, Santa Cruz, Almedina e São Bartolomeu)\nTelefone: 239096000\nFax: 239096082\nEndereço da Entidade (URL): www.aguasdecoimbra.pt\nEndereço Eletrónico: geral@aguasdecoimbra.pt\nFunção da Organização: Adquirente\nNorma jurídica da Entidade Adjudicante: Organismo de direito público, controlado por uma autoridade local\nÁrea de atividade da Entidade Adjudicante: Atividades relacionadas com a água\n\n2 - JORNAL OFICIAL DA UNIÃO EUROPEIA\nO procedimento a que este anúncio diz respeito também é publicitado no Jornal Oficial da União Europeia? Não\n\n3 - AVISO\nModelo de Anúncio: Concurso público\nData de Envio do Anúncio: 31-07-2025\n\n5 - PROCESSO\nTipo de Procedimento: Concurso público\nPreço base do procedimento: Sim\nValor do preço base do procedimento: 940.000,00 EUR\nProcedimento com lotes? Não\n\n6 - OBJETO DO CONTRATO\nNúmero de referência interna: CP-18-2025\nDesignação do contrato: CP-18-2025-EXECUÇÃO DE PEQUENOS PROLONGAMENTOS DE REDE E RAMAIS DOMICILIÁRIOS - FASE 18\nDescrição: Execução de pequenos prolongamentos de rede e ramais domiciliários - Fase 18\nTipo de Contrato Principal: Empreitada de Obras Públicas\nTipo de Contrato: Empreitada de Obras Públicas\nClassificação CPV (Vocabulário Comum para os Contratos Públicos)\nObjeto principal\nVocabulário Principal: 45232440\nPreço base s/IVA: 940.000,00 EUR\n\n7 - INDICAÇÕES ADICIONAIS\nO contrato envolve aquisição conjunta (satisfação de várias entidades)? Não\nO contrato é adjudicado por uma central de compras? Não\n\n8 - TÉCNICAS\nO concurso destina-se à celebração de um acordo-quadro? Inexistência de acordo-quadro\nÉ utilizado um leilão eletrónico? Não\nÉ adotada uma fase de negociação? Não\nSistema de Aquisição Dinâmico: Inexistência de sistema de aquisição dinâmico\n\n9 - LOCAL DA EXECUÇÃO DO CONTRATO\nLOCAL DA EXECUÇÃO DO CONTRATO (PROCEDIMENTO)\nPaís: Portugal\nNUT III: PT16E\nLocalidade: Coimbra\nDistrito: Coimbra\nConcelho: Coimbra\nFreguesia: Todas\n\n10 - PRAZO DE EXECUÇÃO DO CONTRATO\nPrazo de execução do contrato: 540 DIAS\nPrevisão de renovações: Não\n\n11 - FUNDOS EU\nTêm fundos EU? Não\n\n12 - DOCUMENTOS DE HABILITAÇÃO\nHabilitação para o exercício da atividade profissional: Sim\nTipo: Alvará\nDescrição: 6ª subcategoria da 2ª categoria e da classe correspondente ao valor global da proposta. \n\n13 - CONDIÇÕES DE APRESENTAÇÃO\nPlataforma eletrónica utilizada pela entidade adjudicante: ANOGOV\nURL para Apresentação: https://www.anogov.com/em-aguasdecoimbra/faces/\nAdmissibilidade da apresentação de propostas variantes: Não autorizado\nPrazo para apresentação das propostas: 18-08-2025 23:59\nPrazo durante o qual os concorrentes são obrigados a manter as respetivas propostas: 90 dias a contar do termo do prazo para a apresentação das propostas\nApresentação de Catálogo Eletrónico: Permitido\nIndicação de Subcontratação na Proposta: O(s) subcontratante(s) proposto(s) necessário(s) para cumprir a obrigação de subcontratar uma percentagem mínima do contrato\n\n14 - PRESTAÇÃO DE CAUÇÃO\nPrestação de caução: Sim\nPercentagem: 5%\nDescrição da Garantia Exigida: Depósito em dinheiro ou em títulos emitidos ou garantidos pelo Estado ou mediante garantia bancária, ou seguro caução.\n\n15 - FORNECIMENTO DAS PEÇAS DO CONCURSO, APRESENTAÇÃO DE PEDIDOS DE PARTICIPAÇÃO E APRESENTAÇÃO DAS PROPOSTAS\nLink para acesso às peças do concurso (URL): https://www.anogov.com/em-aguasdecoimbra/faces/app/acessoDocs.jsp?codigoAcesso=oonukOsiIUxjEcu7ekBxvLq9q0Zaaq2XMzeQBulBrBZRVFYrNS\n\n20 - OUTROS REQUISITOS\nInformação sobre contratos reservados. Aplica-se a contratos reservados (54º-A)? Não\n\n21 - CRITÉRIO DE ADJUDICAÇÃO\nMultifator: Sim\nFator: \nNome: Preço\nPonderação: 70%\nSubfatores: Não\nFator: \nNome: Outros\nOutro Nome: Valia técnica da proposta\nPonderação: 30%\nSubfatores: Não\n\n24 - CONDIÇÕES DO CONTRATO\nFaturação Eletrónica: Permitido\nObrigação de Subcontratação:\nCódigo da Obrigação de Subcontratação: Não é aplicável nenhuma obrigação de subcontratação.\n\n25 - COMPRA PÚBLICA ESTRATÉGICA\nCompra Pública Estratégica: Inexistência de contratação pública estratégica\n\n26 - INFORMAÇÕES ADICIONAIS\nContrato adequado para PME: Não\nCobertura ACP (Acordo dos Contratos Públicos da Organização Mundial do Comércio): Não\n\n27 - IDENTIFICAÇÃO E CONTACTOS DO ÓRGÃO DE RECURSOS ADMINISTRATIVOS\nDesignação: Conselho de Administração da AC, Águas de Coimbra, EM\nEndereço: Rua da Alegria, n.º 111\nCódigo postal: 3000-018\nLocalidade: Coimbra\nEndereço eletrónico: geral@aguasdecoimbra.pt\nPrazo de interposição do recurso: 5 dias\n\n28 - IDENTIFICAÇÃO DO(S) AUTOR(ES) DE ANÚNCIO\nNome: José Alfeu Almeida de Sá Marques\nCargo: Presidente do Conselho de Administração \n419373098",
    "nipc": "506566307",
    "distrito": "Coimbra",
    "concelho": "Coimbra",
    "freguesia": "União das Freguesias de Coimbra (Sé Nova, Santa Cruz, Almedina e São Bartolomeu)",
    "site": "www.aguasdecoimbra.pt",
    "email": "geral@aguasdecoimbra.pt",
    "designacao_contrato": "CP-18-2025-EXECUÇÃO DE PEQUENOS PROLONGAMENTOS DE REDE E RAMAIS DOMICILIÁRIOS - FASE 18",
    "descricao": "Execução de pequenos prolongamentos de rede e ramais domiciliários - Fase 18",
    "preco_base": "940.000,00 EUR",
    "prazo_execucao": "540 DIAS",
    "prazo_apresentacao_propostas": "18-08-2025 23:59",
    "fundos_eu": "Não",
    "plataforma_eletronica": "ANOGOV",
    "url_procedimento": "https://www.anogov.com/em-aguasdecoimbra/faces/",
    "autor_nome": "José Alfeu Almeida de Sá Marques",
    "autor_cargo": "Presidente do Conselho de Administração"
  },
  {
    "numero_procedimento": "N/A",
    "entidade": "Município da Maia",
    "link": "https://diariodarepublica.pt/dr/detalhe/contrato-publico/20681-927416007",
    "detalhes_completos": "1 - IDENTIFICAÇÃO E CONTACTOS DA ENTIDADE ADJUDICANTE\nDesignação da entidade adjudicante: Município da Maia\nNIPC: 505387131\nServiço/Órgão/Pessoa de contacto: Presidente da Câmara\nEndereço: Praça Dr. José Vieira de Carvalho\nCódigo postal: 4470-202\nLocalidade: Maia\nPaís: Portugal\nNUT III: PT11A\nDistrito: Porto\nConcelho: Maia\nFreguesia: Todas\nTelefone: 229408600\nFax: 229418411\nEndereço da Entidade (URL): www.cm-maia.pt\nEndereço Eletrónico: geral@cm-maia.pt\neDelivery Gateway (URL): https://www.acingov.pt\nFunção da Organização: Adquirente\nSubfunção da Organização: Organização que recebe as propostas\nNorma jurídica da Entidade Adjudicante: Autoridade local\nÁrea de atividade da Autoridade Adjudicante: Serviços públicos das administrações públicas\n\n2 - JORNAL OFICIAL DA UNIÃO EUROPEIA\nO procedimento a que este anúncio diz respeito também é publicitado no Jornal Oficial da União Europeia? Não\n\n3 - AVISO\nModelo de Anúncio: Concurso público\nData de Envio do Anúncio: 31-07-2025\n\n5 - PROCESSO\nTipo de Procedimento: Concurso público\nPreço base do procedimento: Sim\nValor do preço base do procedimento: 224.650,00 EUR\nProcedimento com lotes? Não\n\n6 - OBJETO DO CONTRATO\nNúmero de referência interna: 874.CPN.E.25\nDesignação do contrato: REQUALIFICAÇÃO URBANÍSTICA DA RUA ARMANDO NOGUEIRA DA SILVA, FREGUESIA DO CASTÊLO DA MAIA\nDescrição: REQUALIFICAÇÃO URBANÍSTICA DA RUA ARMANDO NOGUEIRA DA SILVA, FREGUESIA DO CASTÊLO DA MAIA\nTipo de Contrato Principal: Empreitada de Obras Públicas\nTipo de Contrato: Empreitada de Obras Públicas\nClassificação CPV (Vocabulário Comum para os Contratos Públicos)\nObjeto principal\nVocabulário Principal: 45112700\nPreço base s/IVA: 224.650,00 EUR\n\n7 - INDICAÇÕES ADICIONAIS\nO contrato envolve aquisição conjunta (satisfação de várias entidades)? Não\nO contrato é adjudicado por uma central de compras? Não\n\n8 - TÉCNICAS\nO concurso destina-se à celebração de um acordo-quadro? Inexistência de acordo-quadro\nÉ utilizado um leilão eletrónico? Não\nÉ adotada uma fase de negociação? Não\nSistema de Aquisição Dinâmico: Inexistência de sistema de aquisição dinâmico\n\n9 - LOCAL DA EXECUÇÃO DO CONTRATO\nLOCAL DA EXECUÇÃO DO CONTRATO (PROCEDIMENTO)\nPaís: Portugal\nNUT III: PT11A\nLocalidade: Freguesia de Cidade da Maia\nDistrito: Porto\nConcelho: Maia\nFreguesia: Freguesia de Cidade da Maia\n\n10 - PRAZO DE EXECUÇÃO DO CONTRATO\nPrazo de execução do contrato: 210 DIAS\nPrevisão de renovações: Não\n\n11 - FUNDOS EU\nTêm fundos EU? Não\n\n12 - DOCUMENTOS DE HABILITAÇÃO\nHabilitação para o exercício da atividade profissional: Sim\nTipo: Alvará\nDescrição: 1.ª Subcategoria da 2.ª Categoria, da classe correspondente ao valor global da proposta e as 1.ª Subcategorias da 4.ª Categoria e 9.ª Subcategorias da 2.ª Categoria, a qual tem de ser da classe que cubra o valor dos respetivos trabalhos\n\n13 - CONDIÇÕES DE APRESENTAÇÃO\nPlataforma eletrónica utilizada pela entidade adjudicante: ACIN\nURL para Apresentação: https://www.acingov.pt\nAdmissibilidade da apresentação de propostas variantes: Não autorizado\nPrazo para apresentação das propostas: 10-09-2025 23:59\nPrazo durante o qual os concorrentes são obrigados a manter as respetivas propostas: 66 dias a contar do termo do prazo para a apresentação das propostas\nIndicação de Subcontratação na Proposta: Inexistência de indicação de subcontratação\n\n14 - PRESTAÇÃO DE CAUÇÃO\nPrestação de caução: Sim\nPercentagem: 5%\nDescrição da Garantia Exigida: O valor da caução é de 5.00% do preço contratual.\n\n15 - FORNECIMENTO DAS PEÇAS DO CONCURSO, APRESENTAÇÃO DE PEDIDOS DE PARTICIPAÇÃO E APRESENTAÇÃO DAS PROPOSTAS\nLink para acesso às peças do concurso (URL): https://www.acingov.pt/acingovprod/2/zonaPublica/zona_publica_c/donwloadProcedurePiece/OTMwNDg3\n\n20 - OUTROS REQUISITOS\nInformação sobre contratos reservados. Aplica-se a contratos reservados (54º-A)? Não\n\n21 - CRITÉRIO DE ADJUDICAÇÃO\nMultifator: Não\nMonofator:\nNome: Preço\n\n24 - CONDIÇÕES DO CONTRATO\nFaturação Eletrónica: Permitido\nObrigação de Subcontratação:\nCódigo da Obrigação de Subcontratação: Não é aplicável nenhuma obrigação de subcontratação.\n\n25 - COMPRA PÚBLICA ESTRATÉGICA\nCompra Pública Estratégica: Inexistência de contratação pública estratégica\n\n26 - INFORMAÇÕES ADICIONAIS\nContrato adequado para PME: Não\nCobertura ACP (Acordo dos Contratos Públicos da Organização Mundial do Comércio): Não\n\n27 - IDENTIFICAÇÃO E CONTACTOS DO ÓRGÃO DE RECURSOS ADMINISTRATIVOS\nDesignação: Presidente da câmara municipal da maia\nEndereço: PRAÇA DOUTOR JOSÉ VEIRA DE CARVALHO\nCódigo postal: 4470-202\nLocalidade: MAIA\nTelefone: 229408600\nFax: 229480901\nEndereço eletrónico: geral@cm-maia.pt\nPrazo de interposição do recurso: 5 dias\n\n28 - IDENTIFICAÇÃO DO(S) AUTOR(ES) DE ANÚNCIO\nNome: António Domingos da Silva Tiago\nCargo: Presidente da Câmara Municipal da Maia\n419383571",
    "nipc": "505387131",
    "distrito": "Porto",
    "concelho": "Maia",
    "freguesia": "Todas",
    "site": "www.cm-maia.pt",
    "email": "geral@cm-maia.pt",
    "designacao_contrato": "REQUALIFICAÇÃO URBANÍSTICA DA RUA ARMANDO NOGUEIRA DA SILVA, FREGUESIA DO CASTÊLO DA MAIA",
    "descricao": "REQUALIFICAÇÃO URBANÍSTICA DA RUA ARMANDO NOGUEIRA DA SILVA, FREGUESIA DO CASTÊLO DA MAIA",
    "preco_base": "224.650,00 EUR",
    "prazo_execucao": "210 DIAS",
    "prazo_apresentacao_propostas": "10-09-2025 23:59",
    "fundos_eu": "Não",
    "plataforma_eletronica": "ACIN",
    "url_procedimento": "https://www.acingov.pt",
    "autor_nome": "António Domingos da Silva Tiago",
    "autor_cargo": "Presidente da Câmara Municipal da Maia"
  },
  {
    "numero_procedimento": "N/A",
    "entidade": "Câmara Municipal de Matosinhos",
    "link": "https://diariodarepublica.pt/dr/detalhe/contrato-publico/20685-927416008",
    "detalhes_completos": "1 - IDENTIFICAÇÃO E CONTACTOS DA ENTIDADE ADJUDICANTE\nDesignação da entidade adjudicante: Câmara Municipal de Matosinhos\nNIPC: 501305912\nServiço/Órgão/Pessoa de contacto: Divisão Contratação Pública\nEndereço: Av. D. Afonso Henriques\nCódigo postal: 4454-510\nLocalidade: Matosinhos\nPaís: Portugal\nNUT III: PT11A\nDistrito: Porto\nConcelho: Matosinhos\nFreguesia: Todas\nTelefone: 229390900\nFax: 229351645\nEndereço da Entidade (URL): http://www.cm-matosinhos.pt\nEndereço Eletrónico: contratacaopublica@cm-matosinhos.pt\neDelivery Gateway (URL): https://www.acingov.pt\nFunção da Organização: Adquirente\nSubfunção da Organização: Organização que recebe as propostas\nNorma jurídica da Entidade Adjudicante: Organismo de direito público\nÁrea de atividade da Autoridade Adjudicante: Serviços públicos das administrações públicas\n\n2 - JORNAL OFICIAL DA UNIÃO EUROPEIA\nO procedimento a que este anúncio diz respeito também é publicitado no Jornal Oficial da União Europeia? Não\n\n3 - AVISO\nModelo de Anúncio: Concurso público\nData de Envio do Anúncio: 31-07-2025\n\n5 - PROCESSO\nTipo de Procedimento: Concurso público\nPreço base do procedimento: Sim\nValor do preço base do procedimento: 48.500,00 EUR\nProcedimento com lotes? Não\n\n6 - OBJETO DO CONTRATO\nNúmero de referência interna: CP/2025/19888\nDesignação do contrato: PROJETO DE PAVILHÕES GIMNODESPORTIVOS - Custóias - ESPECIALIDADES\nDescrição: PROJETO DE PAVILHÕES GIMNODESPORTIVOS - Custóias - ESPECIALIDADES\nTipo de Contrato Principal: Aquisição de Serviços\nTipo de Contrato: Aquisição de Serviços\nClassificação CPV (Vocabulário Comum para os Contratos Públicos)\nObjeto principal\nVocabulário Principal: 71330000\nPreço base s/IVA: 48.500,00 EUR\n\n7 - INDICAÇÕES ADICIONAIS\nO contrato envolve aquisição conjunta (satisfação de várias entidades)? Não\nO contrato é adjudicado por uma central de compras? Não\n\n8 - TÉCNICAS\nO concurso destina-se à celebração de um acordo-quadro? Inexistência de acordo-quadro\nÉ utilizado um leilão eletrónico? Não\nÉ adotada uma fase de negociação? Não\nSistema de Aquisição Dinâmico: Inexistência de sistema de aquisição dinâmico\n\n9 - LOCAL DA EXECUÇÃO DO CONTRATO\nLOCAL DA EXECUÇÃO DO CONTRATO (PROCEDIMENTO)\nPaís: Portugal\nNUT III: PT11A\nLocalidade: Matosunhos\nDistrito: Porto\nConcelho: Matosinhos\nFreguesia: Todas\n\n10 - PRAZO DE EXECUÇÃO DO CONTRATO\nPrazo de execução do contrato: 4 MESES\nPrevisão de renovações: Não\n\n11 - FUNDOS EU\nTêm fundos EU? Não\n\n12 - DOCUMENTOS DE HABILITAÇÃO\nHabilitação para o exercício da atividade profissional: Não\n\n13 - CONDIÇÕES DE APRESENTAÇÃO\nPlataforma eletrónica utilizada pela entidade adjudicante: ACIN\nURL para Apresentação: https://www.acingov.pt\nAdmissibilidade da apresentação de propostas variantes: Não autorizado\nPrazo para apresentação das propostas: 11-08-2025 23:59\nPrazo durante o qual os concorrentes são obrigados a manter as respetivas propostas: 66 dias a contar do termo do prazo para a apresentação das propostas\nIndicação de Subcontratação na Proposta: Inexistência de indicação de subcontratação\n\n14 - PRESTAÇÃO DE CAUÇÃO\nPrestação de caução: Não\n\n15 - FORNECIMENTO DAS PEÇAS DO CONCURSO, APRESENTAÇÃO DE PEDIDOS DE PARTICIPAÇÃO E APRESENTAÇÃO DAS PROPOSTAS\nLink para acesso às peças do concurso (URL): https://www.acingov.pt/acingovprod/2/zonaPublica/zona_publica_c/donwloadProcedurePiece/OTMwMTIz\n\n20 - OUTROS REQUISITOS\nInformação sobre contratos reservados. Aplica-se a contratos reservados (54º-A)? Não\n\n21 - CRITÉRIO DE ADJUDICAÇÃO\nMultifator: Sim\nFator: \nNome: Preço\nPonderação: 40%\nSubfatores: Não\nFator: \nNome: Qualidade\nPonderação: 60%\nSubfatores: Não\n\n24 - CONDIÇÕES DO CONTRATO\nFaturação Eletrónica: Permitido\nObrigação de Subcontratação:\nCódigo da Obrigação de Subcontratação: Não é aplicável nenhuma obrigação de subcontratação.\n\n25 - COMPRA PÚBLICA ESTRATÉGICA\nCompra Pública Estratégica: Redução dos impactos ambientais\nDescrição do Processo de Adjudicação Estratégico: O processo de adjudicação em apreço assenta na desmaterialização dos documentos, assim como na comunicação não presencial com as entidades concorrentes. Em suma, o procedimento pugna pela redução dos impactos ambientais ao evitar a elaboração física de documentos e a deslocação dos membros das equipas. Acresce a valoração do projeto com medidas de eficiência energética, nomeadamente no que se refere à iluminação e consumos energéticos.\nCritérios de contratos Públicos Ecológicos: Outros critérios de contratação pública ecológica\nCategorias da estratégia nacional: Outros\nOutra categoria (Descrição): Este serviço não está listado na ENCPE 2020.\nContratos Públicos Ecológicos: Outros\nDiretiva Veículos Não Poluentes: Não\nCritério de Acessibilidade: Os critérios de acessibilidade para as pessoas com deficiência estão incluídos\n\n26 - INFORMAÇÕES ADICIONAIS\nContrato adequado para PME: Sim\nCobertura ACP (Acordo dos Contratos Públicos da Organização Mundial do Comércio): Não\n\n27 - IDENTIFICAÇÃO E CONTACTOS DO ÓRGÃO DE RECURSOS ADMINISTRATIVOS\nDesignação: Câmara Municipal\nEndereço: Av. D. Afonso Henriques\nCódigo postal: 4454-510\nLocalidade: Matosinhos\nTelefone: 229390900\nFax: \nEndereço eletrónico: contratacaopublica@cm-matosinhos.pt\nPrazo de interposição do recurso: 5 dias\n\n28 - IDENTIFICAÇÃO DO(S) AUTOR(ES) DE ANÚNCIO\nNome: Dra. Luísa Salgueiro\nCargo: Presidente da Câmara\n419376679",
    "nipc": "501305912",
    "distrito": "Porto",
    "concelho": "Matosinhos",
    "freguesia": "Todas",
    "site": "http://www.cm-matosinhos.pt",
    "email": "contratacaopublica@cm-matosinhos.pt",
    "designacao_contrato": "PROJETO DE PAVILHÕES GIMNODESPORTIVOS - Custóias - ESPECIALIDADES",
    "descricao": "PROJETO DE PAVILHÕES GIMNODESPORTIVOS - Custóias - ESPECIALIDADES",
    "preco_base": "48.500,00 EUR",
    "prazo_execucao": "4 MESES",
    "prazo_apresentacao_propostas": "11-08-2025 23:59",
    "fundos_eu": "Não",
    "plataforma_eletronica": "ACIN",
    "url_procedimento": "https://www.acingov.pt",
    "autor_nome": "Dra. Luísa Salgueiro",
    "autor_cargo": "Presidente da Câmara"
  },
  {
    "numero_procedimento": "N/A",
    "entidade": "EPF-Ensino Profissional de Felgueiras, E.M., Unipessoal, Lda",
    "link": "https://diariodarepublica.pt/dr/detalhe/contrato-publico/20687-927416009",
    "detalhes_completos": "1 - IDENTIFICAÇÃO E CONTACTOS DA ENTIDADE ADJUDICANTE\nDesignação da entidade adjudicante: EPF-Ensino Profissional de Felgueiras, E.M., Unipessoal, Lda\nNIPC: 504575848\nServiço/Órgão/Pessoa de contacto: Gerência\nEndereço: Rua dos Bombeiros Voluntários de Felgueiras, 104\nCódigo postal: 4610-165\nLocalidade: Felgueiras\nPaís: Portugal\nNUT III: PT11C\nDistrito: Porto\nConcelho: Felgueiras\nFreguesia: União das Freguesias de Margaride (Santa Eulália), Várzea, Lagares, Varziela e Moure\nTelefone: 255312482\nFax: 255312419\nEndereço da Entidade (URL): www.epfelgueiras.pt\nEndereço Eletrónico: epf@epfelgueiras.pt\neDelivery Gateway (URL): https://www.acingov.pt\nFunção da Organização: Adquirente\nNorma jurídica da Entidade Adjudicante: Organismo de direito público\nÁrea de atividade da Autoridade Adjudicante: Serviços públicos das administrações públicas\n\n2 - JORNAL OFICIAL DA UNIÃO EUROPEIA\nO procedimento a que este anúncio diz respeito também é publicitado no Jornal Oficial da União Europeia? Não\n\n3 - AVISO\nModelo de Anúncio: Concurso público\nData de Envio do Anúncio: 31-07-2025\n\n5 - PROCESSO\nTipo de Procedimento: Concurso público\nPreço base do procedimento: Sim\nValor do preço base do procedimento: 103.545,00 EUR\nProcedimento com lotes? Não\n\n6 - OBJETO DO CONTRATO\nNúmero de referência interna: CoP002/2025\nDesignação do contrato: Serviço de refeições para o ano letivo 2025-2026\nDescrição: Serviço de refeições para o ano letivo 2025-2026\nTipo de Contrato Principal: Aquisição de Serviços\nTipo de Contrato: Aquisição de Serviços\nClassificação CPV (Vocabulário Comum para os Contratos Públicos)\nObjeto principal\nVocabulário Principal: 55524000\nPreço base s/IVA: 103.545,00 EUR\n\n7 - INDICAÇÕES ADICIONAIS\nO contrato envolve aquisição conjunta (satisfação de várias entidades)? Não\nO contrato é adjudicado por uma central de compras? Não\n\n8 - TÉCNICAS\nO concurso destina-se à celebração de um acordo-quadro? Inexistência de acordo-quadro\nÉ utilizado um leilão eletrónico? Não\nÉ adotada uma fase de negociação? Não\nSistema de Aquisição Dinâmico: Inexistência de sistema de aquisição dinâmico\n\n9 - LOCAL DA EXECUÇÃO DO CONTRATO\nLOCAL DA EXECUÇÃO DO CONTRATO (PROCEDIMENTO)\nPaís: Portugal\nNUT III: PT11C\nLocalidade: União das Freguesias de Margaride (Santa Eulália), Várzea, Lagares, Varziela e Moure\nDistrito: Porto\nConcelho: Felgueiras\nFreguesia: União das Freguesias de Margaride (Santa Eulália), Várzea, Lagares, Varziela e Moure\n\n10 - PRAZO DE EXECUÇÃO DO CONTRATO\nPrazo de execução do contrato: 321 DIAS\nPrevisão de renovações: Não\n\n11 - FUNDOS EU\nTêm fundos EU? Sim\n\n12 - DOCUMENTOS DE HABILITAÇÃO\nHabilitação para o exercício da atividade profissional: Não\n\n13 - CONDIÇÕES DE APRESENTAÇÃO\nPlataforma eletrónica utilizada pela entidade adjudicante: ACIN\nURL para Apresentação: https://www.acingov.pt\nAdmissibilidade da apresentação de propostas variantes: Não autorizado\nPrazo para apresentação das propostas: 06-08-2025 23:59\nPrazo durante o qual os concorrentes são obrigados a manter as respetivas propostas: 66 dias a contar do termo do prazo para a apresentação das propostas\nIndicação de Subcontratação na Proposta: Inexistência de indicação de subcontratação\n\n14 - PRESTAÇÃO DE CAUÇÃO\nPrestação de caução: Não\n\n15 - FORNECIMENTO DAS PEÇAS DO CONCURSO, APRESENTAÇÃO DE PEDIDOS DE PARTICIPAÇÃO E APRESENTAÇÃO DAS PROPOSTAS\nLink para acesso às peças do concurso (URL): https://www.acingov.pt/acingovprod/2/zonaPublica/zona_publica_c/donwloadProcedurePiece/OTMwMzAz\n\n20 - OUTROS REQUISITOS\nInformação sobre contratos reservados. Aplica-se a contratos reservados (54º-A)? Não\n\n21 - CRITÉRIO DE ADJUDICAÇÃO\nMultifator: Sim\nFator: \nNome: Outros\nOutro Nome: Avaliação do preço da proposta\nPonderação: 55%\nSubfatores: Não\nFator: \nNome: Outros\nOutro Nome: Avaliação de proximidade\nPonderação: 45%\nSubfatores: Não\n\n24 - CONDIÇÕES DO CONTRATO\nFaturação Eletrónica: Necessário\nObrigação de Subcontratação:\nCódigo da Obrigação de Subcontratação: Não é aplicável nenhuma obrigação de subcontratação.\n\n25 - COMPRA PÚBLICA ESTRATÉGICA\nCompra Pública Estratégica: Inexistência de contratação pública estratégica\n\n26 - INFORMAÇÕES ADICIONAIS\nContrato adequado para PME: Sim\nCobertura ACP (Acordo dos Contratos Públicos da Organização Mundial do Comércio): Não\n\n27 - IDENTIFICAÇÃO E CONTACTOS DO ÓRGÃO DE RECURSOS ADMINISTRATIVOS\nDesignação: Gerência\nEndereço: Rua dos Bombeiros Voluntários de Felgueiras, 104\nCódigo postal: 4610-165\nLocalidade: MARGARIDE\nTelefone: 255132482\nFax: 255312419\nEndereço eletrónico: epf@epfelgueiras.pt\nPrazo de interposição do recurso: 5 dias\n\n28 - IDENTIFICAÇÃO DO(S) AUTOR(ES) DE ANÚNCIO\nNome: Vera Lúcia Ribeiro Sampaio\nCargo: Gerente\n419384868",
    "nipc": "504575848",
    "distrito": "Porto",
    "concelho": "Felgueiras",
    "freguesia": "União das Freguesias de Margaride (Santa Eulália), Várzea, Lagares, Varziela e Moure",
    "site": "www.epfelgueiras.pt",
    "email": "epf@epfelgueiras.pt",
    "designacao_contrato": "Serviço de refeições para o ano letivo 2025-2026",
    "descricao": "Serviço de refeições para o ano letivo 2025-2026",
    "preco_base": "103.545,00 EUR",
    "prazo_execucao": "321 DIAS",
    "prazo_apresentacao_propostas": "06-08-2025 23:59",
    "fundos_eu": "Sim",
    "plataforma_eletronica": "ACIN",
    "url_procedimento": "https://www.acingov.pt",
    "autor_nome": "Vera Lúcia Ribeiro Sampaio",
    "autor_cargo": "Gerente"
  },
  {
    "numero_procedimento": "N/A",
    "entidade": "EPF-Ensino Profissional de Felgueiras, E.M., Unipessoal, Lda",
    "link": "https://diariodarepublica.pt/dr/detalhe/contrato-publico/20688-927416010",
    "detalhes_completos": "1 - IDENTIFICAÇÃO E CONTACTOS DA ENTIDADE ADJUDICANTE\nDesignação da entidade adjudicante: EPF-Ensino Profissional de Felgueiras, E.M., Unipessoal, Lda\nNIPC: 504575848\nServiço/Órgão/Pessoa de contacto: Gerência\nEndereço: Rua dos Bombeiros Voluntários de Felgueiras, 104\nCódigo postal: 4610-165\nLocalidade: Felgueiras\nPaís: Portugal\nNUT III: PT11C\nDistrito: Porto\nConcelho: Felgueiras\nFreguesia: União das Freguesias de Margaride (Santa Eulália), Várzea, Lagares, Varziela e Moure\nTelefone: 255312482\nFax: 211512419\nEndereço da Entidade (URL): www.epfelgueiras.pt\nEndereço Eletrónico: epf@epfelgueiras.pt\neDelivery Gateway (URL): https://www.acingov.pt\nFunção da Organização: Adquirente\nNorma jurídica da Entidade Adjudicante: Organismo de direito público\nÁrea de atividade da Autoridade Adjudicante: Serviços públicos das administrações públicas\n\n2 - JORNAL OFICIAL DA UNIÃO EUROPEIA\nO procedimento a que este anúncio diz respeito também é publicitado no Jornal Oficial da União Europeia? Não\n\n3 - AVISO\nModelo de Anúncio: Concurso público\nData de Envio do Anúncio: 31-07-2025\n\n5 - PROCESSO\nTipo de Procedimento: Concurso público\nPreço base do procedimento: Sim\nValor do preço base do procedimento: 57.458,83 EUR\nProcedimento com lotes? Sim\nNº Máx. de Lotes Autorizado: 3\nNúmero máximo de lotes que podem ser adjudicados a um concorrente: 3\n\n6 - OBJETO DO CONTRATO\nNúmero de referência interna: CoP001/2025\nDesignação do contrato: Aquisição de serviços de alojamento para formandos/as deslocados, em regime de exclusividade, dos cursos profissionais de Escola Profissional de Felgueiras para o ano letivo de 2025/2026\nDescrição: Aquisição de serviços de alojamento para formandos/as deslocados, em regime de exclusividade, dos cursos profissionais de Escola Profissional de Felgueiras para o ano letivo de 2025/2026\nTipo de Contrato Principal: Aquisição de Serviços\nTipo de Contrato: Aquisição de Serviços\nClassificação CPV (Vocabulário Comum para os Contratos Públicos)\nObjeto principal\nVocabulário Principal: 98341000\nPreço base s/IVA: 57.458,83 EUR\nLotes: \nNº: LOT-0001\nDescrição do Lote: Alojamento para 8 estudantes\nPreço base s/IVA: 16.910,96 EUR\nClassificação CPV (Vocabulário Comum para os Contratos Públicos)\nObjeto principal\nVocabulário Principal: 98341000\nNº: LOT-0002\nDescrição do Lote: Alojamento para 9 estudantes\nPreço base s/IVA: 20.177,85 EUR\nClassificação CPV (Vocabulário Comum para os Contratos Públicos)\nObjeto principal\nVocabulário Principal: 98341000\nNº: LOT-0003\nDescrição do Lote: Alojamento para 9 estudantes\nPreço base s/IVA: 20.370,02 EUR\nClassificação CPV (Vocabulário Comum para os Contratos Públicos)\nObjeto principal\nVocabulário Principal: 98341000\n\n7 - INDICAÇÕES ADICIONAIS\nO contrato envolve aquisição conjunta (satisfação de várias entidades)? Não\nO contrato é adjudicado por uma central de compras? Não\n\n8 - TÉCNICAS\nO concurso destina-se à celebração de um acordo-quadro? Inexistência de acordo-quadro\nÉ utilizado um leilão eletrónico? Não\nÉ adotada uma fase de negociação? Não\nSistema de Aquisição Dinâmico: Inexistência de sistema de aquisição dinâmico\n\n9 - LOCAL DA EXECUÇÃO DO CONTRATO\nLOCAL DA EXECUÇÃO DO CONTRATO (PROCEDIMENTO)\nPaís: Portugal\nNUT III: PT11C\nLocalidade: União das Freguesias de Margaride (Santa Eulália), Várzea, Lagares, Varziela e Moure\nDistrito: Porto\nConcelho: Felgueiras\nFreguesia: União das Freguesias de Margaride (Santa Eulália), Várzea, Lagares, Varziela e Moure\nLOCAL DA EXECUÇÃO DO CONTRATO (LOTE)\nIdentificador do Lote: LOT-0001; LOT-0002; LOT-0003\nPaís: Portugal\nNUT III: PT11C\nLocalidade: União das Freguesias de Margaride (Santa Eulália), Várzea, Lagares, Varziela e Moure\nDistrito: Porto\nConcelho: Felgueiras\nFreguesia: União das Freguesias de Margaride (Santa Eulália), Várzea, Lagares, Varziela e Moure\n\n10 - PRAZO DE EXECUÇÃO DO CONTRATO\nIdentificador do Lote: LOT-0001; LOT-0002; LOT-0003\nPrazo de execução do contrato: 321 DIAS\nPrevisão de renovações: Não\n\n11 - FUNDOS EU\nIdentificador do Lote: LOT-0001; LOT-0002; LOT-0003\nTêm fundos EU? Sim\n\n12 - DOCUMENTOS DE HABILITAÇÃO\nHabilitação para o exercício da atividade profissional: Não\n\n13 - CONDIÇÕES DE APRESENTAÇÃO\nPlataforma eletrónica utilizada pela entidade adjudicante: ACIN\nURL para Apresentação: https://www.acingov.pt\nAdmissibilidade da apresentação de propostas variantes: Não autorizado\nPrazo para apresentação das propostas: 06-08-2025 23:59\nPrazo durante o qual os concorrentes são obrigados a manter as respetivas propostas: 66 dias a contar do termo do prazo para a apresentação das propostas\nIndicação de Subcontratação na Proposta: Inexistência de indicação de subcontratação\n\n14 - PRESTAÇÃO DE CAUÇÃO\nPrestação de caução: Não\n\n15 - FORNECIMENTO DAS PEÇAS DO CONCURSO, APRESENTAÇÃO DE PEDIDOS DE PARTICIPAÇÃO E APRESENTAÇÃO DAS PROPOSTAS\nLink para acesso às peças do concurso (URL): https://www.acingov.pt/acingovprod/2/zonaPublica/zona_publica_c/donwloadProcedurePiece/OTMwMjQ4\n\n20 - OUTROS REQUISITOS\nIdentificador do Lote: LOT-0001; LOT-0002; LOT-0003\nInformação sobre contratos reservados. Aplica-se a contratos reservados (54º-A)? Não\n\n21 - CRITÉRIO DE ADJUDICAÇÃO\nO Critério de adjudicação é diferenciado por lote? Não\nMultifator: Sim\nFator: \nNome: Outros\nOutro Nome: Avaliação do Preço da Proposta\nPonderação: 60%\nSubfatores: Não\nFator: \nNome: Outros\nOutro Nome: Avaliação de proximidade\nPonderação: 40%\nSubfatores: Não\n\n24 - CONDIÇÕES DO CONTRATO\nIdentificador do Lote: LOT-0001; LOT-0002; LOT-0003\nFaturação Eletrónica: Necessário\nObrigação de Subcontratação:\nCódigo da Obrigação de Subcontratação: Não é aplicável nenhuma obrigação de subcontratação.\n\n25 - COMPRA PÚBLICA ESTRATÉGICA\nCompra Pública Estratégica: Inexistência de contratação pública estratégica\n\n26 - INFORMAÇÕES ADICIONAIS\nIdentificador do Lote: LOT-0001; LOT-0002; LOT-0003\nContrato adequado para PME: Não\nCobertura ACP (Acordo dos Contratos Públicos da Organização Mundial do Comércio): Não\n\n27 - IDENTIFICAÇÃO E CONTACTOS DO ÓRGÃO DE RECURSOS ADMINISTRATIVOS\nDesignação: Gerência\nEndereço: Rua dos Bombeiros Voluntários de Felgueiras, 104\nCódigo postal: 4610-165\nLocalidade: Felgueiras\nTelefone: 255312482\nFax: 255312419\nEndereço eletrónico: epf@epfelgueiras.pt\nPrazo de interposição do recurso: 5 dias\n\n28 - IDENTIFICAÇÃO DO(S) AUTOR(ES) DE ANÚNCIO\nNome: Vera Lúcia Ribeiro Sampaio\nCargo: Gerente\n419385207",
    "nipc": "504575848",
    "distrito": "Porto",
    "concelho": "Felgueiras",
    "freguesia": "União das Freguesias de Margaride (Santa Eulália), Várzea, Lagares, Varziela e Moure",
    "site": "www.epfelgueiras.pt",
    "email": "epf@epfelgueiras.pt",
    "designacao_contrato": "Aquisição de serviços de alojamento para formandos/as deslocados, em regime de exclusividade, dos cursos profissionais de Escola Profissional de Felgueiras para o ano letivo de 2025/2026",
    "descricao": "Aquisição de serviços de alojamento para formandos/as deslocados, em regime de exclusividade, dos cursos profissionais de Escola Profissional de Felgueiras para o ano letivo de 2025/2026",
    "preco_base": "57.458,83 EUR",
    "prazo_execucao": "321 DIAS",
    "prazo_apresentacao_propostas": "06-08-2025 23:59",
    "fundos_eu": "Sim",
    "plataforma_eletronica": "ACIN",
    "url_procedimento": "https://www.acingov.pt",
    "autor_nome": "Vera Lúcia Ribeiro Sampaio",
    "autor_cargo": "Gerente"
  },
  {
    "numero_procedimento": "N/A",
    "entidade": "CENTRO SOCIAL DE LEÇA DO BALIO",
    "link": "https://diariodarepublica.pt/dr/detalhe/contrato-publico/20690-927416011",
    "detalhes_completos": "1 - IDENTIFICAÇÃO E CONTACTOS DA ENTIDADE ADJUDICANTE\nDesignação da entidade adjudicante: CENTRO SOCIAL DE LEÇA DO BALIO\nNIPC: 501904662\nServiço/Órgão/Pessoa de contacto: Direção do CSLB\nEndereço: PRACETA PROFESSOR FRANCO Nº 63\nCódigo postal: 4465-637\nLocalidade: LEÇA DO BALIO\nPaís: Portugal\nNUT III: PT11A\nDistrito: Porto\nConcelho: Matosinhos\nFreguesia: União das Freguesias de Custóias, Leça do Balio e Guifões\nTelefone: 229517233\nFax: 229517233\nEndereço da Entidade (URL): www.centrosocialdelecadobalio.pt\nEndereço Eletrónico: inf-gondivai-sede@centrosocialdelecadobalio.pt\neDelivery Gateway (URL): https://www.acingov.pt\nFunção da Organização: Adquirente\nSubfunção da Organização: Organização que recebe as propostas\nNorma jurídica da Entidade Adjudicante: Organismo de direito público\nÁrea de atividade da Autoridade Adjudicante: Serviços públicos das administrações públicas\n\n2 - JORNAL OFICIAL DA UNIÃO EUROPEIA\nO procedimento a que este anúncio diz respeito também é publicitado no Jornal Oficial da União Europeia? Não\n\n3 - AVISO\nModelo de Anúncio: Concurso público\nData de Envio do Anúncio: 31-07-2025\n\n5 - PROCESSO\nTipo de Procedimento: Concurso público\nPreço base do procedimento: Sim\nValor do preço base do procedimento: 359.741,29 EUR\nProcedimento com lotes? Não\n\n6 - OBJETO DO CONTRATO\nNúmero de referência interna: CP/1/2025\nDesignação do contrato: Construção da Creche de Recarei\nDescrição: Construção da Creche de Recarei\nTipo de Contrato Principal: Empreitada de Obras Públicas\nTipo de Contrato: Empreitada de Obras Públicas\nClassificação CPV (Vocabulário Comum para os Contratos Públicos)\nObjeto principal\nVocabulário Principal: 45000000\nPreço base s/IVA: 359.741,29 EUR\n\n7 - INDICAÇÕES ADICIONAIS\nO contrato envolve aquisição conjunta (satisfação de várias entidades)? Não\nO contrato é adjudicado por uma central de compras? Não\n\n8 - TÉCNICAS\nO concurso destina-se à celebração de um acordo-quadro? Inexistência de acordo-quadro\nÉ utilizado um leilão eletrónico? Não\nÉ adotada uma fase de negociação? Não\nSistema de Aquisição Dinâmico: Inexistência de sistema de aquisição dinâmico\n\n9 - LOCAL DA EXECUÇÃO DO CONTRATO\nLOCAL DA EXECUÇÃO DO CONTRATO (PROCEDIMENTO)\nPaís: Portugal\nNUT III: PT11A\nLocalidade: União das Freguesias de Custóias, Leça do Balio e Guifões\nDistrito: Porto\nConcelho: Matosinhos\nFreguesia: União das Freguesias de Custóias, Leça do Balio e Guifões\n\n10 - PRAZO DE EXECUÇÃO DO CONTRATO\nPrazo de execução do contrato: 5 MESES\nPrevisão de renovações: Não\n\n11 - FUNDOS EU\nTêm fundos EU? Sim\n\n12 - DOCUMENTOS DE HABILITAÇÃO\nHabilitação para o exercício da atividade profissional: Sim\nTipo: Alvará\nDescrição: Classe 3 para as Subcategorias - 4ª; 5ª; 6ª; 7ª; 8ª; 9ª da 1ª Categoria;\nClasse necessária para a execução da empreitada nas subcategorias 9ª; 10ª; 12ª; 14ª da 4ª Categoria e nas subcategorias 1ª; 11ª; 12ª da 5ª Categoria.\n\n13 - CONDIÇÕES DE APRESENTAÇÃO\nPlataforma eletrónica utilizada pela entidade adjudicante: ACIN\nURL para Apresentação: https://www.acingov.pt\nAdmissibilidade da apresentação de propostas variantes: Não autorizado\nPrazo para apresentação das propostas: 21-08-2025 16:30\nPrazo durante o qual os concorrentes são obrigados a manter as respetivas propostas: 66 dias a contar do termo do prazo para a apresentação das propostas\nIndicação de Subcontratação na Proposta: Inexistência de indicação de subcontratação\n\n14 - PRESTAÇÃO DE CAUÇÃO\nPrestação de caução: Não\n\n15 - FORNECIMENTO DAS PEÇAS DO CONCURSO, APRESENTAÇÃO DE PEDIDOS DE PARTICIPAÇÃO E APRESENTAÇÃO DAS PROPOSTAS\nLink para acesso às peças do concurso (URL): https://www.acingov.pt/acingovprod/2/zonaPublica/zona_publica_c/donwloadProcedurePiece/OTMwNTI5\n\n20 - OUTROS REQUISITOS\nInformação sobre contratos reservados. Aplica-se a contratos reservados (54º-A)? Não\n\n21 - CRITÉRIO DE ADJUDICAÇÃO\nMultifator: Não\nMonofator:\nNome: Preço\n\n24 - CONDIÇÕES DO CONTRATO\nFaturação Eletrónica: Não autorizado\nObrigação de Subcontratação:\nCódigo da Obrigação de Subcontratação: Não é aplicável nenhuma obrigação de subcontratação.\n\n25 - COMPRA PÚBLICA ESTRATÉGICA\nCompra Pública Estratégica: Inexistência de contratação pública estratégica\n\n26 - INFORMAÇÕES ADICIONAIS\nContrato adequado para PME: Não\nCobertura ACP (Acordo dos Contratos Públicos da Organização Mundial do Comércio): Não\n\n27 - IDENTIFICAÇÃO E CONTACTOS DO ÓRGÃO DE RECURSOS ADMINISTRATIVOS\nDesignação: Direção\nEndereço: PRACETA PROFESSOR FRANCO Nº 63\nCódigo postal: 4465-637\nLocalidade: LEÇA DO BALIO\nTelefone: 229517233\nFax: \nEndereço eletrónico: inf-gondivai-sede@centrosocialdelecadobalio.pt\n\n28 - IDENTIFICAÇÃO DO(S) AUTOR(ES) DE ANÚNCIO\nNome: Paulo Carvalho\nCargo: Presidente\n419382842",
    "nipc": "501904662",
    "distrito": "Porto",
    "concelho": "Matosinhos",
    "freguesia": "União das Freguesias de Custóias, Leça do Balio e Guifões",
    "site": "www.centrosocialdelecadobalio.pt",
    "email": "inf-gondivai-sede@centrosocialdelecadobalio.pt",
    "designacao_contrato": "Construção da Creche de Recarei",
    "descricao": "Construção da Creche de Recarei",
    "preco_base": "359.741,29 EUR",
    "prazo_execucao": "5 MESES",
    "prazo_apresentacao_propostas": "21-08-2025 16:30",
    "fundos_eu": "Sim",
    "plataforma_eletronica": "ACIN",
    "url_procedimento": "https://www.acingov.pt",
    "autor_nome": "Paulo Carvalho",
    "autor_cargo": "Presidente"
  },
  {
    "numero_procedimento": "N/A",
    "entidade": "Serviços de Ação Social da Universidade de Coimbra",
    "link": "https://diariodarepublica.pt/dr/detalhe/contrato-publico/20692-927416012",
    "detalhes_completos": "1 - IDENTIFICAÇÃO E CONTACTOS DA ENTIDADE ADJUDICANTE\nDesignação da entidade adjudicante: Serviços de Ação Social da Universidade de Coimbra\nNIPC: 600038106\nServiço/Órgão/Pessoa de contacto: Administrador dos SASUC\nEndereço: Rua Guilherme Moreira, nº 12\nCódigo postal: 3000-210\nLocalidade: Coimbra\nPaís: Portugal\nNUT III: PT16E\nDistrito: Coimbra\nConcelho: Coimbra\nFreguesia: Freguesia de Santo António dos Olivais\nTelefone: 239855240\nEndereço da Entidade (URL): https://www.uc.pt/sasuc/\nEndereço Eletrónico: gabadmin@sas.uc.pt\neDelivery Gateway (URL): https://www.acingov.pt\nFunção da Organização: Adquirente\nNorma jurídica da Entidade Adjudicante: Organismo de direito público\nÁrea de atividade da Autoridade Adjudicante: Educação\n\n2 - JORNAL OFICIAL DA UNIÃO EUROPEIA\nO procedimento a que este anúncio diz respeito também é publicitado no Jornal Oficial da União Europeia? Sim\n\n3 - AVISO\nModelo de Anúncio: Concurso público\nData de Envio do Anúncio: 29-07-2025\n\n5 - PROCESSO\nTipo de Procedimento: Concurso público\nPreço base do procedimento: Sim\nValor do preço base do procedimento: 185.878,85 EUR\nProcedimento com lotes? Sim\nNº Máx. de Lotes Autorizado: 30\nNúmero máximo de lotes que podem ser adjudicados a um concorrente: 30\n\n6 - OBJETO DO CONTRATO\nNúmero de referência interna: CPI04/25\nDesignação do contrato: Aquisição por lotes, de produtos alimentares diversos c/ transformação para o período previsível de novembro a 31 de janeiro de 2026\nDescrição: Aquisição por lotes de produtos alimentares c/transformação\nOpções: Não\nTipo de Contrato Principal: Aquisição de Bens Móveis\nTipo de Contrato: Aquisição de Bens Móveis\nClassificação CPV (Vocabulário Comum para os Contratos Públicos)\nObjeto principal\nVocabulário Principal: 15000000\nPreço base s/IVA: 185.878,85 EUR\nLotes: \nNº: LOT-0001\nDescrição do Lote: Peixe Seco\nPreço base s/IVA: 15.290,00 EUR\nClassificação CPV (Vocabulário Comum para os Contratos Públicos)\nObjeto principal\nVocabulário Principal: 15000000\nNº: LOT-0002\nDescrição do Lote: Conservas de Peixe\nPreço base s/IVA: 6.770,00 EUR\nClassificação CPV (Vocabulário Comum para os Contratos Públicos)\nObjeto principal\nVocabulário Principal: 15000000\nNº: LOT-0003\nDescrição do Lote: Farinhas, Féculas e Amidos\nPreço base s/IVA: 7.147,50 EUR\nClassificação CPV (Vocabulário Comum para os Contratos Públicos)\nObjeto principal\nVocabulário Principal: 15000000\nNº: LOT-0004\nDescrição do Lote: Produtos da Transformação de Cereais\nPreço base s/IVA: 1.033,00 EUR\nClassificação CPV (Vocabulário Comum para os Contratos Públicos)\nObjeto principal\nVocabulário Principal: 15000000\nNº: LOT-0005\nDescrição do Lote: Bolachas\nPreço base s/IVA: 332,00 EUR\nClassificação CPV (Vocabulário Comum para os Contratos Públicos)\nObjeto principal\nVocabulário Principal: 15000000\nNº: LOT-0006\nDescrição do Lote: Arroz\nPreço base s/IVA: 13.600,00 EUR\nClassificação CPV (Vocabulário Comum para os Contratos Públicos)\nObjeto principal\nVocabulário Principal: 15000000\nNº: LOT-0007\nDescrição do Lote: Massas Alimentícias\nPreço base s/IVA: 4.933,75 EUR\nClassificação CPV (Vocabulário Comum para os Contratos Públicos)\nObjeto principal\nVocabulário Principal: 15000000\nNº: LOT-0008\nDescrição do Lote: Batata Frita\nPreço base s/IVA: 245,00 EUR\nClassificação CPV (Vocabulário Comum para os Contratos Públicos)\nObjeto principal\nVocabulário Principal: 15000000\nNº: LOT-0009\nDescrição do Lote: Produtos Enlatados\nPreço base s/IVA: 10.342,50 EUR\nClassificação CPV (Vocabulário Comum para os Contratos Públicos)\nObjeto principal\nVocabulário Principal: 15000000\nNº: LOT-0010\nDescrição do Lote: zeite Extra Virgem\nPreço base s/IVA: 26.800,00 EUR\nClassificação CPV (Vocabulário Comum para os Contratos Públicos)\nObjeto principal\nVocabulário Principal: 15000000\nNº: LOT-0011\nDescrição do Lote: Óleo Alimentar\nPreço base s/IVA: 9.375,00 EUR\nClassificação CPV (Vocabulário Comum para os Contratos Públicos)\nObjeto principal\nVocabulário Principal: 15000000\nNº: LOT-0012\nDescrição do Lote: Creme Vegetal\nPreço base s/IVA: 1.600,00 EUR\nClassificação CPV (Vocabulário Comum para os Contratos Públicos)\nObjeto principal\nVocabulário Principal: 15000000\nNº: LOT-0013\nDescrição do Lote: Produtos de Pastelaria Diversos\nPreço base s/IVA: 10.122,50 EUR\nClassificação CPV (Vocabulário Comum para os Contratos Públicos)\nObjeto principal\nVocabulário Principal: 15000000\nNº: LOT-0014\nDescrição do Lote: Produtos de Panificação Diversos\nPreço base s/IVA: 3.794,00 EUR\nClassificação CPV (Vocabulário Comum para os Contratos Públicos)\nObjeto principal\nVocabulário Principal: 15000000\nNº: LOT-0015\nDescrição do Lote: Fermento\nPreço base s/IVA: 1.581,00 EUR\nClassificação CPV (Vocabulário Comum para os Contratos Públicos)\nObjeto principal\nVocabulário Principal: 15000000\nNº: LOT-0016\nDescrição do Lote: Frutos Secos\nPreço base s/IVA: 200,00 EUR\nClassificação CPV (Vocabulário Comum para os Contratos Públicos)\nObjeto principal\nVocabulário Principal: 15000000\nNº: LOT-0017\nDescrição do Lote: Fruta Cristalizada\nPreço base s/IVA: 295,00 EUR\nClassificação CPV (Vocabulário Comum para os Contratos Públicos)\nObjeto principal\nVocabulário Principal: 15000000\nNº: LOT-0018\nDescrição do Lote: Lacticínios\nPreço base s/IVA: 16.687,50 EUR\nClassificação CPV (Vocabulário Comum para os Contratos Públicos)\nObjeto principal\nVocabulário Principal: 15000000\nNº: LOT-0019\nDescrição do Lote: Queijos\nPreço base s/IVA: 21.255,40 EUR\nClassificação CPV (Vocabulário Comum para os Contratos Públicos)\nObjeto principal\nVocabulário Principal: 15000000\nNº: LOT-0020\nDescrição do Lote: Café, Chá e Produtos Afins\nPreço base s/IVA: 2.803,30 EUR\nClassificação CPV (Vocabulário Comum para os Contratos Públicos)\nObjeto principal\nVocabulário Principal: 15000000\nNº: LOT-0021\nDescrição do Lote: Condimentos e Temperos\nPreço base s/IVA: 12.160,40 EUR\nClassificação CPV (Vocabulário Comum para os Contratos Públicos)\nObjeto principal\nVocabulário Principal: 15000000\nNº: LOT-0022\nDescrição do Lote: Preparados para Sobremesas\nPreço base s/IVA: 1.450,00 EUR\nClassificação CPV (Vocabulário Comum para os Contratos Públicos)\nObjeto principal\nVocabulário Principal: 15000000\nNº: LOT-0023\nDescrição do Lote: Recheios para Sanduíches\nPreço base s/IVA: 180,00 EUR\nClassificação CPV (Vocabulário Comum para os Contratos Públicos)\nObjeto principal\nVocabulário Principal: 15000000\nNº: LOT-0024\nDescrição do Lote: Chocolates e Pastilhas\nPreço base s/IVA: 3.175,00 EUR\nClassificação CPV (Vocabulário Comum para os Contratos Públicos)\nObjeto principal\nVocabulário Principal: 15000000\nNº: LOT-0025\nDescrição do Lote: Produtos Nutricionais Especiais I\nPreço base s/IVA: 11.200,00 EUR\nClassificação CPV (Vocabulário Comum para os Contratos Públicos)\nObjeto principal\nVocabulário Principal: 15000000\nNº: LOT-0026\nDescrição do Lote: Produtos Nutricionais Especiais II\nPreço base s/IVA: 2.437,00 EUR\nClassificação CPV (Vocabulário Comum para os Contratos Públicos)\nObjeto principal\nVocabulário Principal: 15000000\nNº: LOT-0027\nDescrição do Lote: Produtos Nutricionais Especiais III\nPreço base s/IVA: 257,50 EUR\nClassificação CPV (Vocabulário Comum para os Contratos Públicos)\nObjeto principal\nVocabulário Principal: 15000000\nNº: LOT-0028\nDescrição do Lote: Produtos Nutricionais s/ glúten I\nPreço base s/IVA: 124,00 EUR\nClassificação CPV (Vocabulário Comum para os Contratos Públicos)\nObjeto principal\nVocabulário Principal: 15000000\nNº: LOT-0029\nDescrição do Lote: Produtos Nutricionais s/ glúten II\nPreço base s/IVA: 375,00 EUR\nClassificação CPV (Vocabulário Comum para os Contratos Públicos)\nObjeto principal\nVocabulário Principal: 15000000\nNº: LOT-0030\nDescrição do Lote: Madalenas\nPreço base s/IVA: 312,50 EUR\nClassificação CPV (Vocabulário Comum para os Contratos Públicos)\nObjeto principal\nVocabulário Principal: 15000000\n\n7 - INDICAÇÕES ADICIONAIS\nO contrato envolve aquisição conjunta (satisfação de várias entidades)? Não\nO contrato é adjudicado por uma central de compras? Não\n\n8 - TÉCNICAS\nO concurso destina-se à celebração de um acordo-quadro? Inexistência de acordo-quadro\nÉ utilizado um leilão eletrónico? Não\nÉ adotada uma fase de negociação? Não\nSistema de Aquisição Dinâmico: Inexistência de sistema de aquisição dinâmico\n\n9 - LOCAL DA EXECUÇÃO DO CONTRATO\nLOCAL DA EXECUÇÃO DO CONTRATO (PROCEDIMENTO)\nPaís: Portugal\nNUT III: PT16E\nLocalidade: Coimbra\nDistrito: Coimbra\nConcelho: Coimbra\nFreguesia: Todas\nLOCAL DA EXECUÇÃO DO CONTRATO (LOTE)\nIdentificador do Lote: LOT-0001; LOT-0002; LOT-0003; LOT-0004; LOT-0005; LOT-0006; LOT-0007; LOT-0008; LOT-0009; LOT-0010; LOT-0011; LOT-0012; LOT-0013; LOT-0014; LOT-0015; LOT-0016; LOT-0017; LOT-0018; LOT-0019; LOT-0020; LOT-0021; LOT-0022; LOT-0023; LOT-0024; LOT-0025; LOT-0026; LOT-0027; LOT-0028; LOT-0029; LOT-0030\nPaís: Portugal\nNUT III: PT16E\nLocalidade: Coimbra\nDistrito: Coimbra\nConcelho: Coimbra\nFreguesia: Todas\n\n10 - PRAZO DE EXECUÇÃO DO CONTRATO\nIdentificador do Lote: LOT-0001; LOT-0002; LOT-0003; LOT-0004; LOT-0005; LOT-0006; LOT-0007; LOT-0008; LOT-0009; LOT-0010; LOT-0011; LOT-0012; LOT-0013; LOT-0014; LOT-0015; LOT-0016; LOT-0017; LOT-0018; LOT-0019; LOT-0020; LOT-0021; LOT-0022; LOT-0023; LOT-0024; LOT-0025; LOT-0026; LOT-0027; LOT-0028; LOT-0029; LOT-0030\nPrazo de execução do contrato: 3 MESES\nPrevisão de renovações: Não\n\n11 - FUNDOS EU\nIdentificador do Lote: LOT-0001; LOT-0002; LOT-0003; LOT-0004; LOT-0005; LOT-0006; LOT-0007; LOT-0008; LOT-0009; LOT-0010; LOT-0011; LOT-0012; LOT-0013; LOT-0014; LOT-0015; LOT-0016; LOT-0017; LOT-0018; LOT-0019; LOT-0020; LOT-0021; LOT-0022; LOT-0023; LOT-0024; LOT-0025; LOT-0026; LOT-0027; LOT-0028; LOT-0029; LOT-0030\nTêm fundos EU? Não\n\n12 - DOCUMENTOS DE HABILITAÇÃO\nHabilitação para o exercício da atividade profissional: Sim\nTipo: Outros\nDescrição - Outros: Documento Operador / Receptor\nDescrição: i. Quando se trata de fornecimento de produtos de origem animal, o fornecedor deverá apresentar a Licença de exploração Industrial ou documento comprovativo de atribuição do nº de controlo veterinário;\nii. Quando se trata de fornecimento de produtos de origem vegetal e armazenistas em geral, o fornecedor deverá apresentar documento comprovativo de licenciamento de atividade para o estabelecimento;\niii. Em qualquer dos casos previstos em i. e ii., o fornecedor deve ainda apresentar o documento de registo de operador quer o transporte dos bens seja efetuado pelo próprio quer o mesmo seja subcontratado a terceiros.\n\n13 - CONDIÇÕES DE APRESENTAÇÃO\nPlataforma eletrónica utilizada pela entidade adjudicante: ACIN\nURL para Apresentação: https://www.acingov.pt\nAdmissibilidade da apresentação de propostas variantes: Não autorizado\nPrazo para apresentação das propostas: 31-08-2025 23:59\nPrazo durante o qual os concorrentes são obrigados a manter as respetivas propostas: 66 dias a contar do termo do prazo para a apresentação das propostas\nApresentação de Catálogo Eletrónico: Permitido\nIndicação de Subcontratação na Proposta: Inexistência de indicação de subcontratação\n\n14 - PRESTAÇÃO DE CAUÇÃO\nPrestação de caução: Não\n\n15 - FORNECIMENTO DAS PEÇAS DO CONCURSO, APRESENTAÇÃO DE PEDIDOS DE PARTICIPAÇÃO E APRESENTAÇÃO DAS PROPOSTAS\nLink para acesso às peças do concurso (URL): https://www.acingov.pt/acingovprod/2/zonaPublica/zona_publica_c/donwloadProcedurePiece/OTE3MzU5\n\n20 - OUTROS REQUISITOS\nIdentificador do Lote: LOT-0001; LOT-0002; LOT-0003; LOT-0004; LOT-0005; LOT-0006; LOT-0007; LOT-0008; LOT-0009; LOT-0010; LOT-0011; LOT-0012; LOT-0013; LOT-0014; LOT-0015; LOT-0016; LOT-0017; LOT-0018; LOT-0019; LOT-0020; LOT-0021; LOT-0022; LOT-0023; LOT-0024; LOT-0025; LOT-0026; LOT-0027; LOT-0028; LOT-0029; LOT-0030\nInformação sobre contratos reservados. Aplica-se a contratos reservados (54º-A)? Não\n\n21 - CRITÉRIO DE ADJUDICAÇÃO\nO Critério de adjudicação é diferenciado por lote? Não\nMultifator: Sim\nFator: \nNome: Outros\nOutro Nome: Outros\nPonderação: 100%\nSubfatores: Não\n\n24 - CONDIÇÕES DO CONTRATO\nIdentificador do Lote: LOT-0001; LOT-0002; LOT-0003; LOT-0004; LOT-0005; LOT-0006; LOT-0007; LOT-0008; LOT-0009; LOT-0010; LOT-0011; LOT-0012; LOT-0013; LOT-0014; LOT-0015; LOT-0016; LOT-0017; LOT-0018; LOT-0019; LOT-0020; LOT-0021; LOT-0022; LOT-0023; LOT-0024; LOT-0025; LOT-0026; LOT-0027; LOT-0028; LOT-0029; LOT-0030\nFaturação Eletrónica: Permitido\nObrigação de Subcontratação:\nCódigo da Obrigação de Subcontratação: Não é aplicável nenhuma obrigação de subcontratação.\n\n25 - COMPRA PÚBLICA ESTRATÉGICA\nCompra Pública Estratégica: Redução dos impactos ambientais\nDescrição do Processo de Adjudicação Estratégico: De acordo c/ as peças do procedimento\nCritérios de contratos Públicos Ecológicos: Outros critérios de contratação pública ecológica\nCategorias da estratégia nacional: Produtos alimentares, serviços de assistência de restauração (catering) e máquinas de distribuição automática\nDiretiva Veículos Não Poluentes: Não\nCritério de Acessibilidade: Os critérios de acessibilidade para as pessoas com deficiência não estão incluídos porque o contrato não se destina a pessoas singulares\n\n26 - INFORMAÇÕES ADICIONAIS\nIdentificador do Lote: LOT-0001; LOT-0002; LOT-0003; LOT-0004; LOT-0005; LOT-0006; LOT-0007; LOT-0008; LOT-0009; LOT-0010; LOT-0011; LOT-0012; LOT-0013; LOT-0014; LOT-0015; LOT-0016; LOT-0017; LOT-0018; LOT-0019; LOT-0020; LOT-0021; LOT-0022; LOT-0023; LOT-0024; LOT-0025; LOT-0026; LOT-0027; LOT-0028; LOT-0029; LOT-0030\nContrato adequado para PME: Não\nCobertura ACP (Acordo dos Contratos Públicos da Organização Mundial do Comércio): Não\n\n27 - IDENTIFICAÇÃO E CONTACTOS DO ÓRGÃO DE RECURSOS ADMINISTRATIVOS\nDesignação: Reitor da Universidade de Coimbra\nEndereço: Paço das Escolas\nCódigo postal: 3004-531\nLocalidade: Coimbra\nTelefone: 239859900\nFax: \nEndereço eletrónico: greitor@uc.pt\n\n28 - IDENTIFICAÇÃO DO(S) AUTOR(ES) DE ANÚNCIO\nNome: Amílcar Falcão\nCargo: Reitor da UC\n419372571",
    "nipc": "600038106",
    "distrito": "Coimbra",
    "concelho": "Coimbra",
    "freguesia": "Freguesia de Santo António dos Olivais",
    "site": "https://www.uc.pt/sasuc/",
    "email": "gabadmin@sas.uc.pt",
    "designacao_contrato": "Aquisição por lotes, de produtos alimentares diversos c/ transformação para o período previsível de novembro a 31 de janeiro de 2026",
    "descricao": "Aquisição por lotes de produtos alimentares c/transformação",
    "preco_base": "185.878,85 EUR",
    "prazo_execucao": "3 MESES",
    "prazo_apresentacao_propostas": "31-08-2025 23:59",
    "fundos_eu": "Não",
    "plataforma_eletronica": "ACIN",
    "url_procedimento": "https://www.acingov.pt",
    "autor_nome": "Amílcar Falcão",
    "autor_cargo": "Reitor da UC"
  },
  {
    "numero_procedimento": "N/A",
    "entidade": "CASA PIA DE LISBOA, I.P.",
    "link": "https://diariodarepublica.pt/dr/detalhe/contrato-publico/20694-927416013",
    "detalhes_completos": "1 - IDENTIFICAÇÃO E CONTACTOS DA ENTIDADE ADJUDICANTE\nDesignação da entidade adjudicante: CASA PIA DE LISBOA, I.P.\nNIPC: 501390642\nEndereço: Avenida do Restelo n.º 1\nCódigo postal: 1449-008\nLocalidade: Lisboa\nPaís: Portugal\nNUT III: PT170\nDistrito: Lisboa\nConcelho: Lisboa\nFreguesia: Freguesia de Belém\nTelefone: 213614000\nFax: 213614030\nEndereço da Entidade (URL): www.casapia.pt\nEndereço Eletrónico: contratacao.publica@casapia.pt\neDelivery Gateway (URL): https://www.acingov.pt\nFunção da Organização: Adquirente\nNorma jurídica da Entidade Adjudicante: Organismo de direito público\nÁrea de atividade da Autoridade Adjudicante: Proteção social\n\n2 - JORNAL OFICIAL DA UNIÃO EUROPEIA\nO procedimento a que este anúncio diz respeito também é publicitado no Jornal Oficial da União Europeia? Não\n\n3 - AVISO\nModelo de Anúncio: Concurso público\nData de Envio do Anúncio: 31-07-2025\n\n5 - PROCESSO\nTipo de Procedimento: Concurso público\nPreço base do procedimento: Sim\nValor do preço base do procedimento: 87.000,00 EUR\nProcedimento com lotes? Não\n\n6 - OBJETO DO CONTRATO\nNúmero de referência interna: NPD 2525000460\nDesignação do contrato: 2525000460 Correção da Anomalias na CA Areia Branca\nDescrição: Correção da Anomalias na CA Areia Branca\nTipo de Contrato Principal: Empreitada de Obras Públicas\nTipo de Contrato: Empreitada de Obras Públicas\nClassificação CPV (Vocabulário Comum para os Contratos Públicos)\nObjeto principal\nVocabulário Principal: 45113000\nPreço base s/IVA: 87.000,00 EUR\n\n7 - INDICAÇÕES ADICIONAIS\nO contrato envolve aquisição conjunta (satisfação de várias entidades)? Não\nO contrato é adjudicado por uma central de compras? Não\n\n8 - TÉCNICAS\nO concurso destina-se à celebração de um acordo-quadro? Inexistência de acordo-quadro\nÉ utilizado um leilão eletrónico? Não\nÉ adotada uma fase de negociação? Não\nSistema de Aquisição Dinâmico: Inexistência de sistema de aquisição dinâmico\n\n9 - LOCAL DA EXECUÇÃO DO CONTRATO\nLOCAL DA EXECUÇÃO DO CONTRATO (PROCEDIMENTO)\nPaís: Portugal\nNUT III: PT170\nLocalidade: União das Freguesias de Lourinhã e Atalaia\nDistrito: Lisboa\nConcelho: Lourinhã\nFreguesia: União das Freguesias de Lourinhã e Atalaia\n\n10 - PRAZO DE EXECUÇÃO DO CONTRATO\nPrazo de execução do contrato: 105 DIAS\nPrevisão de renovações: Não\n\n11 - FUNDOS EU\nTêm fundos EU? Não\n\n12 - DOCUMENTOS DE HABILITAÇÃO\nHabilitação para o exercício da atividade profissional: Sim\nTipo: Alvará\nDescrição: 5.ª Subcategoria da 1.ª Categoria na classe correspondente ao valor total da sua proposta\n\n13 - CONDIÇÕES DE APRESENTAÇÃO\nPlataforma eletrónica utilizada pela entidade adjudicante: ACIN\nURL para Apresentação: https://www.acingov.pt\nAdmissibilidade da apresentação de propostas variantes: Não autorizado\nPrazo para apresentação das propostas: 13-08-2025 23:59\nPrazo durante o qual os concorrentes são obrigados a manter as respetivas propostas: 66 dias a contar do termo do prazo para a apresentação das propostas\nIndicação de Subcontratação na Proposta: Inexistência de indicação de subcontratação\n\n14 - PRESTAÇÃO DE CAUÇÃO\nPrestação de caução: Sim\nPercentagem: 5%\nDescrição da Garantia Exigida: O valor da caução é de 5.00% do preço contratual.\n\n15 - FORNECIMENTO DAS PEÇAS DO CONCURSO, APRESENTAÇÃO DE PEDIDOS DE PARTICIPAÇÃO E APRESENTAÇÃO DAS PROPOSTAS\nLink para acesso às peças do concurso (URL): https://www.acingov.pt/acingovprod/2/zonaPublica/zona_publica_c/donwloadProcedurePiece/OTMwMTYx\n\n20 - OUTROS REQUISITOS\nInformação sobre contratos reservados. Aplica-se a contratos reservados (54º-A)? Não\n\n21 - CRITÉRIO DE ADJUDICAÇÃO\nMultifator: Sim\nFator: \nNome: Preço\nPonderação: 70%\nSubfatores: Não\nFator: \nNome: Outros\nOutro Nome: Valia Técnica da Proposta\nPonderação: 30%\nSubfatores: Não\n\n24 - CONDIÇÕES DO CONTRATO\nFaturação Eletrónica: Necessário\nObrigação de Subcontratação:\nCódigo da Obrigação de Subcontratação: Não é aplicável nenhuma obrigação de subcontratação.\n\n25 - COMPRA PÚBLICA ESTRATÉGICA\nCompra Pública Estratégica: Redução dos impactos ambientais\nDescrição do Processo de Adjudicação Estratégico: Ver peças do procedimento\nCritérios de contratos Públicos Ecológicos: Critérios de contratação pública ecológica nacional\nCategorias da estratégia nacional: Outros\nOutra categoria (Descrição): Outra prioridade\nContratos Públicos Ecológicos: Outros\nDiretiva Veículos Não Poluentes: Não\nCritério de Acessibilidade: Os critérios de acessibilidade para as pessoas com deficiência não estão incluídos porque o contrato não se destina a pessoas singulares\n\n26 - INFORMAÇÕES ADICIONAIS\nContrato adequado para PME: Não\nCobertura ACP (Acordo dos Contratos Públicos da Organização Mundial do Comércio): Não\n\n27 - IDENTIFICAÇÃO E CONTACTOS DO ÓRGÃO DE RECURSOS ADMINISTRATIVOS\nDesignação: Conselho Diretivo\nEndereço: Avenida do Restelo, 01\nCódigo postal: 1449-008\nLocalidade: LISBOA\nTelefone: 213614000\nFax: \nEndereço eletrónico: contratacao.publica@casapia.pt\n\n28 - IDENTIFICAÇÃO DO(S) AUTOR(ES) DE ANÚNCIO\nNome: João Paulo Barra Ludovino Mota Croa Felicio\nCargo: Técnico Superior\n419378103",
    "nipc": "501390642",
    "distrito": "Lisboa",
    "concelho": "Lisboa",
    "freguesia": "Freguesia de Belém",
    "site": "www.casapia.pt",
    "email": "contratacao.publica@casapia.pt",
    "designacao_contrato": "2525000460 Correção da Anomalias na CA Areia Branca",
    "descricao": "Correção da Anomalias na CA Areia Branca",
    "preco_base": "87.000,00 EUR",
    "prazo_execucao": "105 DIAS",
    "prazo_apresentacao_propostas": "13-08-2025 23:59",
    "fundos_eu": "Não",
    "plataforma_eletronica": "ACIN",
    "url_procedimento": "https://www.acingov.pt",
    "autor_nome": "João Paulo Barra Ludovino Mota Croa Felicio",
    "autor_cargo": "Técnico Superior"
  },
  {
    "numero_procedimento": "N/A",
    "entidade": "Junta de Freguesia da Misericórdia",
    "link": "https://diariodarepublica.pt/dr/detalhe/contrato-publico/20695-927416014",
    "detalhes_completos": "1 - IDENTIFICAÇÃO E CONTACTOS DA ENTIDADE ADJUDICANTE\nDesignação da entidade adjudicante: Junta de Freguesia da Misericórdia\nNIPC: 510833349\nServiço/Órgão/Pessoa de contacto: carla almeida \nEndereço: Largo Dr. António de Sousa Macedo 7D\nCódigo postal: 1200-153\nLocalidade: Lisboa\nPaís: Portugal\nNUT III: PT170\nDistrito: Lisboa\nConcelho: Lisboa\nFreguesia: Freguesia de Misericórdia\nTelefone: 213929800\nFax: 213929809\nEndereço da Entidade (URL): www.jf-misericordia.pt\nEndereço Eletrónico: geral@jf-misericordia.pt\nFunção da Organização: Adquirente\nNorma jurídica da Entidade Adjudicante: Autoridade local\nÁrea de atividade da Autoridade Adjudicante: Serviços públicos das administrações públicas\n\n2 - JORNAL OFICIAL DA UNIÃO EUROPEIA\nO procedimento a que este anúncio diz respeito também é publicitado no Jornal Oficial da União Europeia? Não\n\n3 - AVISO\nModelo de Anúncio: Concurso público\nData de Envio do Anúncio: 31-07-2025\n\n5 - PROCESSO\nTipo de Procedimento: Concurso público\nPreço base do procedimento: Sim\nValor do preço base do procedimento: 90.000,00 EUR\nProcedimento com lotes? Não\n\n6 - OBJETO DO CONTRATO\nNúmero de referência interna: CPNº06/JFM/2025\nDesignação do contrato: AQUISIÇÃO DE SERVIÇOS DE LAVAGEM COM PRESSÃO E APLICAÇÃO DE PRODUTO DE DESINFEÇÃO NO ESPAÇO PÚBLICO DA FREGUESIA DA MISERICÓRDIA\nDescrição: AQUISIÇÃO DE SERVIÇOS DE LAVAGEM COM PRESSÃO E APLICAÇÃO DE PRODUTO DE DESINFEÇÃO NO ESPAÇO PÚBLICO DA FREGUESIA DA MISERICÓRDIA\nTipo de Contrato Principal: Aquisição de Serviços\nTipo de Contrato: Aquisição de Serviços\nClassificação CPV (Vocabulário Comum para os Contratos Públicos)\nObjeto principal\nVocabulário Principal: 90600000\nPreço base s/IVA: 90.000,00 EUR\n\n7 - INDICAÇÕES ADICIONAIS\nO contrato envolve aquisição conjunta (satisfação de várias entidades)? Não\nO contrato é adjudicado por uma central de compras? Não\n\n8 - TÉCNICAS\nO concurso destina-se à celebração de um acordo-quadro? Inexistência de acordo-quadro\nÉ utilizado um leilão eletrónico? Não\nÉ adotada uma fase de negociação? Não\nSistema de Aquisição Dinâmico: Inexistência de sistema de aquisição dinâmico\n\n9 - LOCAL DA EXECUÇÃO DO CONTRATO\nLOCAL DA EXECUÇÃO DO CONTRATO (PROCEDIMENTO)\nPaís: Portugal\nNUT III: PT170\nLocalidade: LISBOA\nDistrito: Lisboa\nConcelho: Lisboa\nFreguesia: Freguesia de Misericórdia\n\n10 - PRAZO DE EXECUÇÃO DO CONTRATO\nPrazo de execução do contrato: 3 MESES\nPrevisão de renovações: Não\n\n11 - FUNDOS EU\nTêm fundos EU? Não\n\n12 - DOCUMENTOS DE HABILITAÇÃO\nHabilitação para o exercício da atividade profissional: Não\n\n13 - CONDIÇÕES DE APRESENTAÇÃO\nPlataforma eletrónica utilizada pela entidade adjudicante: ANOGOV\nURL para Apresentação: https://www.anogov.com/jf-misericordia/faces/\nAdmissibilidade da apresentação de propostas variantes: Não autorizado\nPrazo para apresentação das propostas: 05-08-2025 23:59\nPrazo durante o qual os concorrentes são obrigados a manter as respetivas propostas: 66 dias a contar do termo do prazo para a apresentação das propostas\nApresentação de Catálogo Eletrónico: Necessário\nIndicação de Subcontratação na Proposta: Inexistência de indicação de subcontratação\n\n14 - PRESTAÇÃO DE CAUÇÃO\nPrestação de caução: Não\n\n15 - FORNECIMENTO DAS PEÇAS DO CONCURSO, APRESENTAÇÃO DE PEDIDOS DE PARTICIPAÇÃO E APRESENTAÇÃO DAS PROPOSTAS\nLink para acesso às peças do concurso (URL): https://www.anogov.com/jf-misericordia/faces/app/acessoDocs.jsp?codigoAcesso=FYRYkn15yYLuqFZuA2fEI5r6QEFMnplK09tkCWJTzqAyWXtrsO\n\n20 - OUTROS REQUISITOS\nInformação sobre contratos reservados. Aplica-se a contratos reservados (54º-A)? Não\n\n21 - CRITÉRIO DE ADJUDICAÇÃO\nMultifator: Não\nMonofator:\nNome: Preço\n\n24 - CONDIÇÕES DO CONTRATO\nFaturação Eletrónica: Permitido\nObrigação de Subcontratação:\nCódigo da Obrigação de Subcontratação: Não é aplicável nenhuma obrigação de subcontratação.\n\n25 - COMPRA PÚBLICA ESTRATÉGICA\nCompra Pública Estratégica: Inexistência de contratação pública estratégica\n\n26 - INFORMAÇÕES ADICIONAIS\nContrato adequado para PME: Não\nCobertura ACP (Acordo dos Contratos Públicos da Organização Mundial do Comércio): Não\n\n27 - IDENTIFICAÇÃO E CONTACTOS DO ÓRGÃO DE RECURSOS ADMINISTRATIVOS\nDesignação: JUNTA DE FREGUESIA DA MISERICORDIA\nEndereço: LARGO DR. ANTONIO DE SOUSA DE MACEDO 7D\nCódigo postal: 1200-153\nLocalidade: LISBOA\nTelefone: 213929800\nFax: \nEndereço eletrónico: GERAL@JF-MISERICORDIA.PT\nPrazo de interposição do recurso: 5 dias\n\n28 - IDENTIFICAÇÃO DO(S) AUTOR(ES) DE ANÚNCIO\nNome: CARLA ALMEIDA\nCargo: VOGAL\n419385564",
    "nipc": "510833349",
    "distrito": "Lisboa",
    "concelho": "Lisboa",
    "freguesia": "Freguesia de Misericórdia",
    "site": "www.jf-misericordia.pt",
    "email": "geral@jf-misericordia.pt",
    "designacao_contrato": "AQUISIÇÃO DE SERVIÇOS DE LAVAGEM COM PRESSÃO E APLICAÇÃO DE PRODUTO DE DESINFEÇÃO NO ESPAÇO PÚBLICO DA FREGUESIA DA MISERICÓRDIA",
    "descricao": "AQUISIÇÃO DE SERVIÇOS DE LAVAGEM COM PRESSÃO E APLICAÇÃO DE PRODUTO DE DESINFEÇÃO NO ESPAÇO PÚBLICO DA FREGUESIA DA MISERICÓRDIA",
    "preco_base": "90.000,00 EUR",
    "prazo_execucao": "3 MESES",
    "prazo_apresentacao_propostas": "05-08-2025 23:59",
    "fundos_eu": "Não",
    "plataforma_eletronica": "ANOGOV",
    "url_procedimento": "https://www.anogov.com/jf-misericordia/faces/",
    "autor_nome": "CARLA ALMEIDA",
    "autor_cargo": "VOGAL"
  },
  {
    "numero_procedimento": "N/A",
    "entidade": "CENTRO SOCIAL DE LEÇA DO BALIO",
    "link": "https://diariodarepublica.pt/dr/detalhe/contrato-publico/20696-927416015",
    "detalhes_completos": "1 - IDENTIFICAÇÃO E CONTACTOS DA ENTIDADE ADJUDICANTE\nDesignação da entidade adjudicante: CENTRO SOCIAL DE LEÇA DO BALIO\nNIPC: 501904662\nServiço/Órgão/Pessoa de contacto: Direção\nEndereço: PRACETA PROFESSOR FRANCO Nº 63\nCódigo postal: 4465-637\nLocalidade: LEÇA DO BALIO\nPaís: Portugal\nNUT III: PT11A\nDistrito: Porto\nConcelho: Matosinhos\nFreguesia: União das Freguesias de Custóias, Leça do Balio e Guifões\nTelefone: 229517233\nFax: 229517233\nEndereço da Entidade (URL): www.centrosocialdelecadobalio.pt\nEndereço Eletrónico: inf-gondivai-sede@centrosocialdelecadobalio.pt\neDelivery Gateway (URL): https://www.acingov.pt\nFunção da Organização: Adquirente\nSubfunção da Organização: Organização que recebe as propostas\nNorma jurídica da Entidade Adjudicante: Organismo de direito público\nÁrea de atividade da Autoridade Adjudicante: Serviços públicos das administrações públicas\n\n2 - JORNAL OFICIAL DA UNIÃO EUROPEIA\nO procedimento a que este anúncio diz respeito também é publicitado no Jornal Oficial da União Europeia? Não\n\n3 - AVISO\nModelo de Anúncio: Concurso público\nData de Envio do Anúncio: 31-07-2025\n\n5 - PROCESSO\nTipo de Procedimento: Concurso público\nPreço base do procedimento: Sim\nValor do preço base do procedimento: 98.832,72 EUR\nProcedimento com lotes? Sim\nNº Máx. de Lotes Autorizado: 2\nNúmero máximo de lotes que podem ser adjudicados a um concorrente: 2\n\n6 - OBJETO DO CONTRATO\nNúmero de referência interna: CP/2/2025\nDesignação do contrato: Aquisição de viaturas elétricas\nDescrição: Aquisição de viaturas elétricas\nTipo de Contrato Principal: Aquisição de Bens Móveis\nTipo de Contrato: Aquisição de Bens Móveis\nClassificação CPV (Vocabulário Comum para os Contratos Públicos)\nObjeto principal\nVocabulário Principal: 34114300\nPreço base s/IVA: 98.832,72 EUR\nLotes: \nNº: LOT-0001\nDescrição do Lote: Aquisição de aquisição de viatura elétrica ligeira de passageiros transformada com as características de 7 lugares, com pega e degrau.\nPreço base s/IVA: 29.234,02 EUR\nClassificação CPV (Vocabulário Comum para os Contratos Públicos)\nObjeto principal\nVocabulário Principal: 34114300\nNº: LOT-0002\nDescrição do Lote: Aquisição de aquisição de viatura elétrica ligeira de passageiros transformada com as características tipo Maxus eDeliver  L3H2 72 kWh, de 9 lugares, com peso bruto de 3.500Kg, com altura máxima de 2.525 mm, com transformação para 2 cadeiras de rodas\nPreço base s/IVA: 69.598,70 EUR\nClassificação CPV (Vocabulário Comum para os Contratos Públicos)\nObjeto principal\nVocabulário Principal: 34114300\n\n7 - INDICAÇÕES ADICIONAIS\nO contrato envolve aquisição conjunta (satisfação de várias entidades)? Não\nO contrato é adjudicado por uma central de compras? Não\n\n8 - TÉCNICAS\nO concurso destina-se à celebração de um acordo-quadro? Inexistência de acordo-quadro\nÉ utilizado um leilão eletrónico? Não\nÉ adotada uma fase de negociação? Não\nSistema de Aquisição Dinâmico: Inexistência de sistema de aquisição dinâmico\n\n9 - LOCAL DA EXECUÇÃO DO CONTRATO\nLOCAL DA EXECUÇÃO DO CONTRATO (PROCEDIMENTO)\nPaís: Portugal\nNUT III: PT11A\nLocalidade: União das Freguesias de Custóias, Leça do Balio e Guifões\nDistrito: Porto\nConcelho: Matosinhos\nFreguesia: União das Freguesias de Custóias, Leça do Balio e Guifões\nLOCAL DA EXECUÇÃO DO CONTRATO (LOTE)\nIdentificador do Lote: LOT-0001; LOT-0002\nPaís: Portugal\nNUT III: PT11A\nLocalidade: União das Freguesias de Custóias, Leça do Balio e Guifões\nDistrito: Porto\nConcelho: Matosinhos\nFreguesia: União das Freguesias de Custóias, Leça do Balio e Guifões\n\n10 - PRAZO DE EXECUÇÃO DO CONTRATO\nIdentificador do Lote: LOT-0001; LOT-0002\nPrazo de execução do contrato: 6 MESES\nPrevisão de renovações: Não\n\n11 - FUNDOS EU\nIdentificador do Lote: LOT-0001; LOT-0002\nTêm fundos EU? Não\n\n12 - DOCUMENTOS DE HABILITAÇÃO\nHabilitação para o exercício da atividade profissional: Não\n\n13 - CONDIÇÕES DE APRESENTAÇÃO\nPlataforma eletrónica utilizada pela entidade adjudicante: ACIN\nURL para Apresentação: https://www.acingov.pt\nAdmissibilidade da apresentação de propostas variantes: Não autorizado\nPrazo para apresentação das propostas: 04-08-2025 23:59\nPrazo durante o qual os concorrentes são obrigados a manter as respetivas propostas: 66 dias a contar do termo do prazo para a apresentação das propostas\nIndicação de Subcontratação na Proposta: Inexistência de indicação de subcontratação\n\n14 - PRESTAÇÃO DE CAUÇÃO\nPrestação de caução: Não\n\n15 - FORNECIMENTO DAS PEÇAS DO CONCURSO, APRESENTAÇÃO DE PEDIDOS DE PARTICIPAÇÃO E APRESENTAÇÃO DAS PROPOSTAS\nLink para acesso às peças do concurso (URL): https://www.acingov.pt/acingovprod/2/zonaPublica/zona_publica_c/donwloadProcedurePiece/OTMwNjU0\n\n20 - OUTROS REQUISITOS\nIdentificador do Lote: LOT-0001; LOT-0002\nInformação sobre contratos reservados. Aplica-se a contratos reservados (54º-A)? Não\n\n21 - CRITÉRIO DE ADJUDICAÇÃO\nO Critério de adjudicação é diferenciado por lote? Não\nMultifator: Não\nMonofator:\nNome: Preço\n\n24 - CONDIÇÕES DO CONTRATO\nIdentificador do Lote: LOT-0001; LOT-0002\nFaturação Eletrónica: Não autorizado\nObrigação de Subcontratação:\nCódigo da Obrigação de Subcontratação: Não é aplicável nenhuma obrigação de subcontratação.\n\n25 - COMPRA PÚBLICA ESTRATÉGICA\nCompra Pública Estratégica: Inexistência de contratação pública estratégica\n\n26 - INFORMAÇÕES ADICIONAIS\nIdentificador do Lote: LOT-0001; LOT-0002\nContrato adequado para PME: Não\nCobertura ACP (Acordo dos Contratos Públicos da Organização Mundial do Comércio): Não\n\n27 - IDENTIFICAÇÃO E CONTACTOS DO ÓRGÃO DE RECURSOS ADMINISTRATIVOS\nDesignação: Direção\nEndereço: PRACETA PROFESSOR FRANCO Nº 63\nCódigo postal: 4465-637\nLocalidade: LEÇA DO BALIO\nTelefone: 229517233\nFax: \nEndereço eletrónico: inf-gondivai-sede@centrosocialdelecadobalio.pt\n\n28 - IDENTIFICAÇÃO DO(S) AUTOR(ES) DE ANÚNCIO\nNome: Paulo Carvalho\nCargo: Presidente\n419385718",
    "nipc": "501904662",
    "distrito": "Porto",
    "concelho": "Matosinhos",
    "freguesia": "União das Freguesias de Custóias, Leça do Balio e Guifões",
    "site": "www.centrosocialdelecadobalio.pt",
    "email": "inf-gondivai-sede@centrosocialdelecadobalio.pt",
    "designacao_contrato": "Aquisição de viaturas elétricas",
    "descricao": "Aquisição de viaturas elétricas",
    "preco_base": "98.832,72 EUR",
    "prazo_execucao": "6 MESES",
    "prazo_apresentacao_propostas": "04-08-2025 23:59",
    "fundos_eu": "Não",
    "plataforma_eletronica": "ACIN",
    "url_procedimento": "https://www.acingov.pt",
    "autor_nome": "Paulo Carvalho",
    "autor_cargo": "Presidente"
  },
  {
    "numero_procedimento": "N/A",
    "entidade": "SIMARSUL - Saneamento da Península de Setúbal, S.A.",
    "link": "https://diariodarepublica.pt/dr/detalhe/contrato-publico/20697-927416016",
    "detalhes_completos": "1 - IDENTIFICAÇÃO E CONTACTOS DA ENTIDADE ADJUDICANTE\nDesignação da entidade adjudicante: SIMARSUL - Saneamento da Península de Setúbal, S.A.\nNIPC: 514385901\nServiço/Órgão/Pessoa de contacto: Direção de Operação\nEndereço: ETAR da Quinta do Conde, Estrada Nacional 10, Quinta do Conde III\nCódigo postal: 2975-403\nLocalidade: Quinta do Conde - Sesimbra\nPaís: Portugal\nNUT III: PT170\nDistrito: Setúbal\nConcelho: Sesimbra\nFreguesia: Freguesia de Quinta do Conde\nTelefone: 265544000\nFax: 265544000\nEndereço da Entidade (URL): www.simarsul.adp.pt\nEndereço Eletrónico: geral.simarsul@adp.pt\neDelivery Gateway (URL): https://www.acingov.pt\nFunção da Organização: Adquirente\nNorma jurídica da Entidade Adjudicante: Organismo de direito público\nÁrea de atividade da Autoridade Adjudicante: Proteção ambiental\n\n2 - JORNAL OFICIAL DA UNIÃO EUROPEIA\nO procedimento a que este anúncio diz respeito também é publicitado no Jornal Oficial da União Europeia? Sim\n\n3 - AVISO\nModelo de Anúncio: Concurso público\nData de Envio do Anúncio: 29-07-2025\n\n5 - PROCESSO\nTipo de Procedimento: Concurso público\nPreço base do procedimento: Sim\nValor do preço base do procedimento: 4.990.200,00 EUR\nProcedimento com lotes? Sim\nNº Máx. de Lotes Autorizado: 3\nNúmero máximo de lotes que podem ser adjudicados a um concorrente: 3\n\n6 - OBJETO DO CONTRATO\nNúmero de referência interna: 049/CPI/2025\nDesignação do contrato: Prestação de serviços de recolha, transporte e encaminhamento a destino final de lamas da SIMARSUL\nDescrição: Prestação de serviços de recolha, transporte e encaminhamento a destino final de lamas da SIMARSUL\nOpções: Não\nTipo de Contrato Principal: Aquisição de Serviços\nTipo de Contrato: Aquisição de Serviços\nClassificação CPV (Vocabulário Comum para os Contratos Públicos)\nObjeto principal\nVocabulário Principal: 90513800\nPreço base s/IVA: 4.990.200,00 EUR\nLotes: \nNº: LOT-0001\nDescrição do Lote: Prestação de serviços de recolha, transporte e encaminhamento a destino final adequado de lamas - Lote 1 - ETAR dos Centros Operacionais de Redes, Seixal, Quinta do Conde e Sesimbra\nPreço base s/IVA: 1.500.000,00 EUR\nClassificação CPV (Vocabulário Comum para os Contratos Públicos)\nObjeto principal\nVocabulário Principal: 90513800\nNº: LOT-0002\nDescrição do Lote: Prestação de serviços de recolha, transporte e encaminhamento a destino final adequado de lamas - Lote 2 - ETAR dos Centros Operacionais de Barreiro/Moita, Afonsoeiro, Seixalinho e Pegões\nPreço base s/IVA: 1.990.200,00 EUR\nClassificação CPV (Vocabulário Comum para os Contratos Públicos)\nObjeto principal\nVocabulário Principal: 90513800\nNº: LOT-0003\nDescrição do Lote: Prestação de serviços de recolha, transporte e encaminhamento a destino final adequado de lamas - Lote 3 - ETAR do Centro Operacional de Setúbal\nPreço base s/IVA: 1.500.000,00 EUR\nClassificação CPV (Vocabulário Comum para os Contratos Públicos)\nObjeto principal\nVocabulário Principal: 90513800\n\n7 - INDICAÇÕES ADICIONAIS\nO contrato envolve aquisição conjunta (satisfação de várias entidades)? Não\nO contrato é adjudicado por uma central de compras? Não\n\n8 - TÉCNICAS\nO concurso destina-se à celebração de um acordo-quadro? Inexistência de acordo-quadro\nÉ utilizado um leilão eletrónico? Não\nÉ adotada uma fase de negociação? Não\nSistema de Aquisição Dinâmico: Inexistência de sistema de aquisição dinâmico\n\n9 - LOCAL DA EXECUÇÃO DO CONTRATO\nLOCAL DA EXECUÇÃO DO CONTRATO (PROCEDIMENTO)\nPaís: Portugal\nNUT III: PT170\nLocalidade: Freguesia de Quinta do Conde\nDistrito: Setúbal\nConcelho: Sesimbra\nFreguesia: Freguesia de Quinta do Conde\nLOCAL DA EXECUÇÃO DO CONTRATO (LOTE)\nIdentificador do Lote: LOT-0001; LOT-0002; LOT-0003\nPaís: Portugal\nNUT III: PT170\nLocalidade: Freguesia de Quinta do Conde\nDistrito: Setúbal\nConcelho: Sesimbra\nFreguesia: Freguesia de Quinta do Conde\n\n10 - PRAZO DE EXECUÇÃO DO CONTRATO\nIdentificador do Lote: LOT-0001; LOT-0002; LOT-0003\nPrazo de execução do contrato: 12 MESES\nPrevisão de renovações: Sim\nIndicar número máximo de renovações: 1\nPrazo de renovações diferente do prazo inicial: Não\n\n11 - FUNDOS EU\nIdentificador do Lote: LOT-0001; LOT-0002; LOT-0003\nTêm fundos EU? Não\n\n12 - DOCUMENTOS DE HABILITAÇÃO\nHabilitação para o exercício da atividade profissional: Sim\nTipo: Alvará\nDescrição: Alvarás/Licenças exigidos nas peças do procedimento\n\n13 - CONDIÇÕES DE APRESENTAÇÃO\nPlataforma eletrónica utilizada pela entidade adjudicante: ACIN\nURL para Apresentação: https://www.acingov.pt\nAdmissibilidade da apresentação de propostas variantes: Não autorizado\nPrazo para apresentação das propostas: 28-08-2025 18:00\nPrazo durante o qual os concorrentes são obrigados a manter as respetivas propostas: 180 dias a contar do termo do prazo para a apresentação das propostas\nApresentação de Catálogo Eletrónico: Não autorizado\nIndicação de Subcontratação na Proposta: Inexistência de indicação de subcontratação\n\n14 - PRESTAÇÃO DE CAUÇÃO\nPrestação de caução: Sim\nPercentagem: 5%\nDescrição da Garantia Exigida: O valor da caução é de 5.00% do preço contratual.\n\n15 - FORNECIMENTO DAS PEÇAS DO CONCURSO, APRESENTAÇÃO DE PEDIDOS DE PARTICIPAÇÃO E APRESENTAÇÃO DAS PROPOSTAS\nLink para acesso às peças do concurso (URL): https://www.acingov.pt/acingovprod/2/zonaPublica/zona_publica_c/donwloadProcedurePiece/OTI5NDU2\n\n20 - OUTROS REQUISITOS\nIdentificador do Lote: LOT-0001; LOT-0002; LOT-0003\nInformação sobre contratos reservados. Aplica-se a contratos reservados (54º-A)? Não\n\n21 - CRITÉRIO DE ADJUDICAÇÃO\nO Critério de adjudicação é diferenciado por lote? Não\nMultifator: Não\nMonofator:\nNome: Preço\n\n24 - CONDIÇÕES DO CONTRATO\nIdentificador do Lote: LOT-0001; LOT-0002; LOT-0003\nFaturação Eletrónica: Necessário\nObrigação de Subcontratação:\nCódigo da Obrigação de Subcontratação: Não é aplicável nenhuma obrigação de subcontratação.\n\n25 - COMPRA PÚBLICA ESTRATÉGICA\nCompra Pública Estratégica: Inexistência de contratação pública estratégica\n\n26 - INFORMAÇÕES ADICIONAIS\nIdentificador do Lote: LOT-0001; LOT-0002; LOT-0003\nContrato adequado para PME: Sim\nCobertura ACP (Acordo dos Contratos Públicos da Organização Mundial do Comércio): Não\n\n27 - IDENTIFICAÇÃO E CONTACTOS DO ÓRGÃO DE RECURSOS ADMINISTRATIVOS\nDesignação: Conselho de Administração da SIMARSUL, S.A.\nEndereço: ETAR da Quinta do Conde, EN 10, Quinta do Conde III\nCódigo postal: 2975-403\nLocalidade: Quinta do Conde\nTelefone: 265544000\nFax: \nEndereço eletrónico: geral.simarsul@adp.pt\n\n28 - IDENTIFICAÇÃO DO(S) AUTOR(ES) DE ANÚNCIO\nNome: José Fialho\nCargo: Presidente do Conselho de Administração\n419370879",
    "nipc": "514385901",
    "distrito": "Setúbal",
    "concelho": "Sesimbra",
    "freguesia": "Freguesia de Quinta do Conde",
    "site": "www.simarsul.adp.pt",
    "email": "geral.simarsul@adp.pt",
    "designacao_contrato": "Prestação de serviços de recolha, transporte e encaminhamento a destino final de lamas da SIMARSUL",
    "descricao": "Prestação de serviços de recolha, transporte e encaminhamento a destino final de lamas da SIMARSUL",
    "preco_base": "4.990.200,00 EUR",
    "prazo_execucao": "12 MESES",
    "prazo_apresentacao_propostas": "28-08-2025 18:00",
    "fundos_eu": "Não",
    "plataforma_eletronica": "ACIN",
    "url_procedimento": "https://www.acingov.pt",
    "autor_nome": "José Fialho",
    "autor_cargo": "Presidente do Conselho de Administração"
  },
  {
    "numero_procedimento": "N/A",
    "entidade": "Instituto Politécnico do Porto",
    "link": "https://diariodarepublica.pt/dr/detalhe/contrato-publico/20698-927416017",
    "detalhes_completos": "1 - IDENTIFICAÇÃO E CONTACTOS DA ENTIDADE ADJUDICANTE\nDesignação da entidade adjudicante: Instituto Politécnico do Porto\nNIPC: 503606251\nServiço/Órgão/Pessoa de contacto: Gabinete de Aprovisionamento e Compras\nEndereço: RUA DR. ROBERTO FRIAS, 712\nCódigo postal: 4200-465\nLocalidade: PORTO\nPaís: Portugal\nNUT III: PT11A\nDistrito: Porto\nConcelho: Porto\nFreguesia: Freguesia de Paranhos - Porto\nTelefone: 225571000\nFax: 225020772\nEndereço da Entidade (URL): www.ipp.pt\nEndereço Eletrónico: centralcompras@sc.ipp.pt\neDelivery Gateway (URL): https://www.acingov.pt\nFunção da Organização: Adquirente\nNorma jurídica da Entidade Adjudicante: Organismo de direito público\nÁrea de atividade da Autoridade Adjudicante: Educação\n\n2 - JORNAL OFICIAL DA UNIÃO EUROPEIA\nO procedimento a que este anúncio diz respeito também é publicitado no Jornal Oficial da União Europeia? Sim\n\n3 - AVISO\nModelo de Anúncio: Concurso público\nData de Envio do Anúncio: 29-07-2025\n\n5 - PROCESSO\nTipo de Procedimento: Concurso público\nPreço base do procedimento: Sim\nValor do preço base do procedimento: 546.256,05 EUR\nProcedimento com lotes? Sim\nNº Máx. de Lotes Autorizado: 31\nNúmero máximo de lotes que podem ser adjudicados a um concorrente: 31\n\n6 - OBJETO DO CONTRATO\nNúmero de referência interna: 27/000/A/789_2025\nDesignação do contrato: Aquisição de Equipamento Informático para o Instituto Politécnico do Porto\nDescrição: Aquisição de Equipamento Informático para o Instituto Politécnico do Porto \nOpções: Não\nTipo de Contrato Principal: Aquisição de Bens Móveis\nTipo de Contrato: Aquisição de Bens Móveis\nClassificação CPV (Vocabulário Comum para os Contratos Públicos)\nObjeto principal\nVocabulário Principal: 30213300\nPreço base s/IVA: 133.680,00 EUR\nObjeto Complementar\nVocabulário Principal: 30213100\nPreço base s/IVA: 31.200,00 EUR\nObjeto Complementar\nVocabulário Principal: 30213000\nPreço base s/IVA: 51.779,28 EUR\nObjeto Complementar\nVocabulário Principal: 30210000\nPreço base s/IVA: 24.287,31 EUR\nObjeto Complementar\nVocabulário Principal: 32322000\nPreço base s/IVA: 26.600,49 EUR\nObjeto Complementar\nVocabulário Principal: 48822000\nPreço base s/IVA: 19.772,36 EUR\nObjeto Complementar\nVocabulário Principal: 42991200\nPreço base s/IVA: 16.151,01 EUR\nObjeto Complementar\nVocabulário Principal: 32323300\nPreço base s/IVA: 52.169,32 EUR\nObjeto Complementar\nVocabulário Principal: 32321200\nPreço base s/IVA: 14.445,56 EUR\nObjeto Complementar\nVocabulário Principal: 32427000\nPreço base s/IVA: 16.824,32 EUR\nObjeto Complementar\nVocabulário Principal: 32580000\nPreço base s/IVA: 18.500,00 EUR\nObjeto Complementar\nVocabulário Principal: 35121000\nPreço base s/IVA: 1.462,00 EUR\nObjeto Complementar\nVocabulário Principal: 32581000\nPreço base s/IVA: 2.280,00 EUR\nObjeto Complementar\nVocabulário Principal: 30237000\nPreço base s/IVA: 3.314,89 EUR\nObjeto Complementar\nVocabulário Principal: 30233000\nPreço base s/IVA: 4.814,92 EUR\nObjeto Complementar\nVocabulário Principal: 32424000\nPreço base s/IVA: 4.734,16 EUR\nObjeto Complementar\nVocabulário Principal: 32420000\nPreço base s/IVA: 2.207,06 EUR\nObjeto Complementar\nVocabulário Principal: 33196200\nPreço base s/IVA: 17.183,76 EUR\nObjeto Complementar\nVocabulário Principal: 30237400\nPreço base s/IVA: 4.922,77 EUR\nObjeto Complementar\nVocabulário Principal: 30211400\nPreço base s/IVA: 10.820,00 EUR\nObjeto Complementar\nVocabulário Principal: 30231000\nPreço base s/IVA: 24.529,50 EUR\nObjeto Complementar\nVocabulário Principal: 30214000\nPreço base s/IVA: 8.005,70 EUR\nObjeto Complementar\nVocabulário Principal: 30215000\nPreço base s/IVA: 4.593,48 EUR\nObjeto Complementar\nVocabulário Principal: 30211300\nPreço base s/IVA: 7.781,02 EUR\nObjeto Complementar\nVocabulário Principal: 30232110\nPreço base s/IVA: 3.810,96 EUR\nObjeto Complementar\nVocabulário Principal: 30231300\nPreço base s/IVA: 5.411,16 EUR\nObjeto Complementar\nVocabulário Principal: 32232000\nPreço base s/IVA: 4.194,30 EUR\nObjeto Complementar\nVocabulário Principal: 32342400\nPreço base s/IVA: 3.075,83 EUR\nObjeto Complementar\nVocabulário Principal: 30231310\nPreço base s/IVA: 4.500,68 EUR\nObjeto Complementar\nVocabulário Principal: 32342410\nPreço base s/IVA: 9.512,53 EUR\nObjeto Complementar\nVocabulário Principal: 31527260\nPreço base s/IVA: 13.691,68 EUR\nLotes: \nNº: LOT-0001\nDescrição do Lote: Postos de Trabalho Profissionais Standard\nPreço base s/IVA: 133.680,00 EUR\nClassificação CPV (Vocabulário Comum para os Contratos Públicos)\nObjeto principal\nVocabulário Principal: 30213300\nNº: LOT-0002\nDescrição do Lote: Posto de Trabalho Móvel Institucional\nPreço base s/IVA: 31.200,00 EUR\nClassificação CPV (Vocabulário Comum para os Contratos Públicos)\nObjeto principal\nVocabulário Principal: 30213100\nNº: LOT-0003\nDescrição do Lote: Computadores com Sistema Operativo macOS e Tablets iPadOS\nPreço base s/IVA: 51.779,28 EUR\nClassificação CPV (Vocabulário Comum para os Contratos Públicos)\nObjeto principal\nVocabulário Principal: 30213000\nNº: LOT-0004\nDescrição do Lote: Portáteis de Produtividade e Multimédia\nPreço base s/IVA: 24.287,31 EUR\nClassificação CPV (Vocabulário Comum para os Contratos Públicos)\nObjeto principal\nVocabulário Principal: 30210000\nNº: LOT-0005\nDescrição do Lote: Equipamentos de Multimédia\nPreço base s/IVA: 26.600,49 EUR\nClassificação CPV (Vocabulário Comum para os Contratos Públicos)\nObjeto principal\nVocabulário Principal: 32322000\nNº: LOT-0006\nDescrição do Lote: Equipamentos Servidores\nPreço base s/IVA: 19.772,36 EUR\nClassificação CPV (Vocabulário Comum para os Contratos Públicos)\nObjeto principal\nVocabulário Principal: 48822000\nNº: LOT-0007\nDescrição do Lote: Equipamentos e Materiais para Prototipagem Digital - FabLab\nPreço base s/IVA: 16.151,01 EUR\nClassificação CPV (Vocabulário Comum para os Contratos Públicos)\nObjeto principal\nVocabulário Principal: 42991200\nNº: LOT-0008\nDescrição do Lote: Equipamento Audiovisual de Estúdio - Vídeo\nPreço base s/IVA: 52.169,32 EUR\nClassificação CPV (Vocabulário Comum para os Contratos Públicos)\nObjeto principal\nVocabulário Principal: 32323300\nNº: LOT-0009\nDescrição do Lote: Equipamento Audiovisual de Uso Geral\nPreço base s/IVA: 14.445,56 EUR\nClassificação CPV (Vocabulário Comum para os Contratos Públicos)\nObjeto principal\nVocabulário Principal: 32321200\nNº: LOT-0010\nDescrição do Lote: Firewall de próxima geração com alta disponibilidade\nPreço base s/IVA: 16.824,32 EUR\nClassificação CPV (Vocabulário Comum para os Contratos Públicos)\nObjeto principal\nVocabulário Principal: 32427000\nNº: LOT-0011\nDescrição do Lote: Kit Educacional de Análise Forense Móvel\nPreço base s/IVA: 18.500,00 EUR\nClassificação CPV (Vocabulário Comum para os Contratos Públicos)\nObjeto principal\nVocabulário Principal: 32580000\nNº: LOT-0012\nDescrição do Lote: Terminal de controlo de acesso e tranca com software de gestão centralizada\nPreço base s/IVA: 1.462,00 EUR\nClassificação CPV (Vocabulário Comum para os Contratos Públicos)\nObjeto principal\nVocabulário Principal: 35121000\nNº: LOT-0013\nDescrição do Lote: Bridges Forenses para Aquisição de Dados Digitais\nPreço base s/IVA: 2.280,00 EUR\nClassificação CPV (Vocabulário Comum para os Contratos Públicos)\nObjeto principal\nVocabulário Principal: 32581000\nNº: LOT-0014\nDescrição do Lote: Acessórios de Informática\nPreço base s/IVA: 3.314,89 EUR\nClassificação CPV (Vocabulário Comum para os Contratos Públicos)\nObjeto principal\nVocabulário Principal: 30237000\nNº: LOT-0015\nDescrição do Lote: Acessórios de Armazenamento\nPreço base s/IVA: 4.814,92 EUR\nClassificação CPV (Vocabulário Comum para os Contratos Públicos)\nObjeto principal\nVocabulário Principal: 30233000\nNº: LOT-0016\nDescrição do Lote: Equipamento passivo de rede - Biblioteca Pólo II\nPreço base s/IVA: 4.734,16 EUR\nClassificação CPV (Vocabulário Comum para os Contratos Públicos)\nObjeto principal\nVocabulário Principal: 32424000\nNº: LOT-0017\nDescrição do Lote: Equipamentos de Comunicações e de Redes de Dados\nPreço base s/IVA: 2.207,06 EUR\nClassificação CPV (Vocabulário Comum para os Contratos Públicos)\nObjeto principal\nVocabulário Principal: 32420000\nNº: LOT-0018\nDescrição do Lote: Tecnologias de Apoio - Visual\nPreço base s/IVA: 17.183,76 EUR\nClassificação CPV (Vocabulário Comum para os Contratos Públicos)\nObjeto principal\nVocabulário Principal: 33196200\nNº: LOT-0019\nDescrição do Lote: Tecnologias de Apoio - Motor\nPreço base s/IVA: 4.922,77 EUR\nClassificação CPV (Vocabulário Comum para os Contratos Públicos)\nObjeto principal\nVocabulário Principal: 30237400\nNº: LOT-0020\nDescrição do Lote: Postos de Trabalho Avançados para Formação Digital\nPreço base s/IVA: 10.820,00 EUR\nClassificação CPV (Vocabulário Comum para os Contratos Públicos)\nObjeto principal\nVocabulário Principal: 30211400\nNº: LOT-0021\nDescrição do Lote: Postos de Trabalho All-in-One de 24 Polegadas\nPreço base s/IVA: 24.529,50 EUR\nClassificação CPV (Vocabulário Comum para os Contratos Públicos)\nObjeto principal\nVocabulário Principal: 30231000\nNº: LOT-0022\nDescrição do Lote: Estações de Trabalho Profissionais\nPreço base s/IVA: 8.005,70 EUR\nClassificação CPV (Vocabulário Comum para os Contratos Públicos)\nObjeto principal\nVocabulário Principal: 30214000\nNº: LOT-0023\nDescrição do Lote: Desktops de Performance e Formato Compacto\nPreço base s/IVA: 4.593,48 EUR\nClassificação CPV (Vocabulário Comum para os Contratos Públicos)\nObjeto principal\nVocabulário Principal: 30215000\nNº: LOT-0024\nDescrição do Lote: Estações de Trabalho Móveis (Workstations)\nPreço base s/IVA: 7.781,02 EUR\nClassificação CPV (Vocabulário Comum para os Contratos Públicos)\nObjeto principal\nVocabulário Principal: 30211300\nNº: LOT-0025\nDescrição do Lote: Equipamento e Consumíveis de Impressão\nPreço base s/IVA: 3.810,96 EUR\nClassificação CPV (Vocabulário Comum para os Contratos Públicos)\nObjeto principal\nVocabulário Principal: 30232110\nNº: LOT-0026\nDescrição do Lote: Monitores\nPreço base s/IVA: 5.411,16 EUR\nClassificação CPV (Vocabulário Comum para os Contratos Públicos)\nObjeto principal\nVocabulário Principal: 30231300\nNº: LOT-0027\nDescrição do Lote: Equipamento para Videoconferência e Colaboração\nPreço base s/IVA: 4.194,30 EUR\nClassificação CPV (Vocabulário Comum para os Contratos Públicos)\nObjeto principal\nVocabulário Principal: 32232000\nNº: LOT-0028\nDescrição do Lote: Equipamento de Áudio para Eventos\nPreço base s/IVA: 3.075,83 EUR\nClassificação CPV (Vocabulário Comum para os Contratos Públicos)\nObjeto principal\nVocabulário Principal: 32342400\nNº: LOT-0029\nDescrição do Lote: Quadro Interativo\nPreço base s/IVA: 4.500,68 EUR\nClassificação CPV (Vocabulário Comum para os Contratos Públicos)\nObjeto principal\nVocabulário Principal: 30231310\nNº: LOT-0030\nDescrição do Lote: Equipamento Audiovisual de Estúdio - Áudio\nPreço base s/IVA: 9.512,53 EUR\nClassificação CPV (Vocabulário Comum para os Contratos Públicos)\nObjeto principal\nVocabulário Principal: 32342410\nNº: LOT-0031\nDescrição do Lote: Equipamento Audiovisual de Estúdio - Iluminação\nPreço base s/IVA: 13.691,68 EUR\nClassificação CPV (Vocabulário Comum para os Contratos Públicos)\nObjeto principal\nVocabulário Principal: 31527260\n\n7 - INDICAÇÕES ADICIONAIS\nO contrato envolve aquisição conjunta (satisfação de várias entidades)? Não\nO contrato é adjudicado por uma central de compras? Não\n\n8 - TÉCNICAS\nO concurso destina-se à celebração de um acordo-quadro? Inexistência de acordo-quadro\nÉ utilizado um leilão eletrónico? Não\nÉ adotada uma fase de negociação? Não\nSistema de Aquisição Dinâmico: Inexistência de sistema de aquisição dinâmico\n\n9 - LOCAL DA EXECUÇÃO DO CONTRATO\nLOCAL DA EXECUÇÃO DO CONTRATO (PROCEDIMENTO)\nPaís: Portugal\nNUT III: PT11A\nLocalidade: Freguesia de Paranhos - Porto\nDistrito: Porto\nConcelho: Porto\nFreguesia: Freguesia de Paranhos - Porto\nPaís: Portugal\nNUT III: PT11A\nLocalidade: Freguesia de Vila do Conde\nDistrito: Porto\nConcelho: Vila do Conde\nFreguesia: Freguesia de Vila do Conde\nPaís: Portugal\nNUT III: PT11A\nLocalidade: União das Freguesias de Margaride (Santa Eulália), Várzea, Lagares, Varziela e Moure\nDistrito: Porto\nConcelho: Felgueiras\nFreguesia: União das Freguesias de Margaride (Santa Eulália), Várzea, Lagares, Varziela e Moure\nLOCAL DA EXECUÇÃO DO CONTRATO (LOTE)\nIdentificador do Lote: LOT-0001; LOT-0002; LOT-0003; LOT-0004; LOT-0005; LOT-0006; LOT-0007; LOT-0008; LOT-0009; LOT-0010; LOT-0011; LOT-0012; LOT-0013; LOT-0014; LOT-0015; LOT-0016; LOT-0017; LOT-0018; LOT-0019; LOT-0020; LOT-0021; LOT-0022; LOT-0023; LOT-0024; LOT-0025; LOT-0026; LOT-0027; LOT-0028; LOT-0029; LOT-0030; LOT-0031\nPaís: Portugal\nNUT III: PT11A\nLocalidade: União das Freguesias de Margaride (Santa Eulália), Várzea, Lagares, Varziela e Moure\nDistrito: Porto\nConcelho: Felgueiras\nFreguesia: União das Freguesias de Margaride (Santa Eulália), Várzea, Lagares, Varziela e Moure\nIdentificador do Lote: LOT-0001; LOT-0002; LOT-0003; LOT-0004; LOT-0005; LOT-0006; LOT-0007; LOT-0008; LOT-0009; LOT-0010; LOT-0011; LOT-0012; LOT-0013; LOT-0014; LOT-0015; LOT-0016; LOT-0017; LOT-0018; LOT-0019; LOT-0020; LOT-0021; LOT-0022; LOT-0023; LOT-0024; LOT-0025; LOT-0026; LOT-0027; LOT-0028; LOT-0029; LOT-0030; LOT-0031\nPaís: Portugal\nNUT III: PT11A\nLocalidade: Freguesia de Vila do Conde\nDistrito: Porto\nConcelho: Vila do Conde\nFreguesia: Freguesia de Vila do Conde\nIdentificador do Lote: LOT-0001; LOT-0002; LOT-0003; LOT-0004; LOT-0005; LOT-0006; LOT-0007; LOT-0008; LOT-0009; LOT-0010; LOT-0011; LOT-0012; LOT-0013; LOT-0014; LOT-0015; LOT-0016; LOT-0017; LOT-0018; LOT-0019; LOT-0020; LOT-0021; LOT-0022; LOT-0023; LOT-0024; LOT-0025; LOT-0026; LOT-0027; LOT-0028; LOT-0029; LOT-0030; LOT-0031\nPaís: Portugal\nNUT III: PT11A\nLocalidade: Freguesia de Paranhos - Porto\nDistrito: Porto\nConcelho: Porto\nFreguesia: Freguesia de Paranhos - Porto\n\n10 - PRAZO DE EXECUÇÃO DO CONTRATO\nIdentificador do Lote: LOT-0001; LOT-0002; LOT-0003; LOT-0004; LOT-0005; LOT-0006; LOT-0007; LOT-0008; LOT-0009; LOT-0010; LOT-0011; LOT-0012; LOT-0013; LOT-0014; LOT-0015; LOT-0016; LOT-0017; LOT-0018; LOT-0019; LOT-0020; LOT-0021; LOT-0022; LOT-0023; LOT-0024; LOT-0025; LOT-0026; LOT-0027; LOT-0028; LOT-0029; LOT-0030; LOT-0031\nPrazo de execução do contrato: 30 DIAS\nPrevisão de renovações: Não\n\n11 - FUNDOS EU\nIdentificador do Lote: LOT-0001; LOT-0002; LOT-0003; LOT-0004; LOT-0005; LOT-0006; LOT-0007; LOT-0008; LOT-0009; LOT-0010; LOT-0011; LOT-0012; LOT-0013; LOT-0014; LOT-0015; LOT-0016; LOT-0017; LOT-0018; LOT-0019; LOT-0020; LOT-0021; LOT-0022; LOT-0023; LOT-0024; LOT-0025; LOT-0026; LOT-0027; LOT-0028; LOT-0029; LOT-0030; LOT-0031\nTêm fundos EU? Sim\n\n12 - DOCUMENTOS DE HABILITAÇÃO\nHabilitação para o exercício da atividade profissional: Não\n\n13 - CONDIÇÕES DE APRESENTAÇÃO\nPlataforma eletrónica utilizada pela entidade adjudicante: ACIN\nURL para Apresentação: https://www.acingov.pt\nAdmissibilidade da apresentação de propostas variantes: Não autorizado\nPrazo para apresentação das propostas: 28-08-2025 23:59\nPrazo durante o qual os concorrentes são obrigados a manter as respetivas propostas: 120 dias a contar do termo do prazo para a apresentação das propostas\nApresentação de Catálogo Eletrónico: Permitido\nIndicação de Subcontratação na Proposta: Inexistência de indicação de subcontratação\n\n14 - PRESTAÇÃO DE CAUÇÃO\nPrestação de caução: Sim\nPercentagem: 5%\nDescrição da Garantia Exigida: O valor da caução é de 5.00% do preço contratual.\n\n15 - FORNECIMENTO DAS PEÇAS DO CONCURSO, APRESENTAÇÃO DE PEDIDOS DE PARTICIPAÇÃO E APRESENTAÇÃO DAS PROPOSTAS\nLink para acesso às peças do concurso (URL): https://www.acingov.pt/acingovprod/2/zonaPublica/zona_publica_c/donwloadProcedurePiece/OTE5MzQ3\n\n20 - OUTROS REQUISITOS\nIdentificador do Lote: LOT-0001; LOT-0002; LOT-0003; LOT-0004; LOT-0005; LOT-0006; LOT-0007; LOT-0008; LOT-0009; LOT-0010; LOT-0011; LOT-0012; LOT-0013; LOT-0014; LOT-0015; LOT-0016; LOT-0017; LOT-0018; LOT-0019; LOT-0020; LOT-0021; LOT-0022; LOT-0023; LOT-0024; LOT-0025; LOT-0026; LOT-0027; LOT-0028; LOT-0029; LOT-0030; LOT-0031\nInformação sobre contratos reservados. Aplica-se a contratos reservados (54º-A)? Não\n\n21 - CRITÉRIO DE ADJUDICAÇÃO\nO Critério de adjudicação é diferenciado por lote? Não\nMultifator: Sim\nFator: \nNome: Preço\nPonderação: 80%\nSubfatores: Não\nFator: \nNome: Outros\nOutro Nome: Prazo de entrega\nPonderação: 20%\nSubfatores: Não\n\n24 - CONDIÇÕES DO CONTRATO\nIdentificador do Lote: LOT-0001; LOT-0002; LOT-0003; LOT-0004; LOT-0005; LOT-0006; LOT-0007; LOT-0008; LOT-0009; LOT-0010; LOT-0011; LOT-0012; LOT-0013; LOT-0014; LOT-0015; LOT-0016; LOT-0017; LOT-0018; LOT-0019; LOT-0020; LOT-0021; LOT-0022; LOT-0023; LOT-0024; LOT-0025; LOT-0026; LOT-0027; LOT-0028; LOT-0029; LOT-0030; LOT-0031\nFaturação Eletrónica: Necessário\nObrigação de Subcontratação:\nCódigo da Obrigação de Subcontratação: Não é aplicável nenhuma obrigação de subcontratação.\n\n25 - COMPRA PÚBLICA ESTRATÉGICA\nCompra Pública Estratégica: Redução dos impactos ambientais\nDescrição do Processo de Adjudicação Estratégico: Conforme peças do procedimento\nCritérios de contratos Públicos Ecológicos: Critérios de contratação pública ecológica nacional\nCategorias da estratégia nacional: Computadores, monitores, tabletes e telemóveis inteligentes\nDiretiva Veículos Não Poluentes: Não\nCritério de Acessibilidade: Os critérios de acessibilidade para as pessoas com deficiência não estão incluídos porque o contrato não se destina a pessoas singulares\n\n26 - INFORMAÇÕES ADICIONAIS\nIdentificador do Lote: LOT-0001; LOT-0002; LOT-0003; LOT-0004; LOT-0005; LOT-0006; LOT-0007; LOT-0008; LOT-0009; LOT-0010; LOT-0011; LOT-0012; LOT-0013; LOT-0014; LOT-0015; LOT-0016; LOT-0017; LOT-0018; LOT-0019; LOT-0020; LOT-0021; LOT-0022; LOT-0023; LOT-0024; LOT-0025; LOT-0026; LOT-0027; LOT-0028; LOT-0029; LOT-0030; LOT-0031\nContrato adequado para PME: Sim\nCobertura ACP (Acordo dos Contratos Públicos da Organização Mundial do Comércio): Não\n\n27 - IDENTIFICAÇÃO E CONTACTOS DO ÓRGÃO DE RECURSOS ADMINISTRATIVOS\nDesignação: Presidente do Instituto Politécnico do Porto\nEndereço: RUA DR. ROBERTO FRIAS, 712\nCódigo postal: 4200-465\nLocalidade: PORTO\nTelefone: 225571000\nFax: 225020772\nEndereço eletrónico: centralcompras@sc.ipp.pt\nPrazo de interposição do recurso: 10 dias\n\n28 - IDENTIFICAÇÃO DO(S) AUTOR(ES) DE ANÚNCIO\nNome: Paulo Alberto da Silva Pereira\nCargo: Presidente do Instituto Politécnico do Porto\n419373162",
    "nipc": "503606251",
    "distrito": "Porto",
    "concelho": "Porto",
    "freguesia": "Freguesia de Paranhos - Porto",
    "site": "www.ipp.pt",
    "email": "centralcompras@sc.ipp.pt",
    "designacao_contrato": "Aquisição de Equipamento Informático para o Instituto Politécnico do Porto",
    "descricao": "Aquisição de Equipamento Informático para o Instituto Politécnico do Porto",
    "preco_base": "133.680,00 EUR",
    "prazo_execucao": "30 DIAS",
    "prazo_apresentacao_propostas": "28-08-2025 23:59",
    "fundos_eu": "Sim",
    "plataforma_eletronica": "ACIN",
    "url_procedimento": "https://www.acingov.pt",
    "autor_nome": "Paulo Alberto da Silva Pereira",
    "autor_cargo": "Presidente do Instituto Politécnico do Porto"
  },
  {
    "numero_procedimento": "N/A",
    "entidade": "AdRA - Águas da Região de Aveiro, S.A.",
    "link": "https://diariodarepublica.pt/dr/detalhe/contrato-publico/20700-927416018",
    "detalhes_completos": "1 - IDENTIFICAÇÃO E CONTACTOS DA ENTIDADE ADJUDICANTE\nDesignação da entidade adjudicante: AdRA - Águas da Região de Aveiro, S.A.\nNIPC: 509107630\nServiço/Órgão/Pessoa de contacto: Compras e Logística\nEndereço: Travessa da rua da Paz, nº 4\nCódigo postal: 3800-587\nLocalidade: Cacia - Aveiro\nPaís: Portugal\nNUT III: PT16D\nDistrito: Aveiro\nConcelho: Aveiro\nFreguesia: Freguesia de Cacia\nTelefone: 234910200\nFax: 234910299\nEndereço da Entidade (URL): www.adra.pt\nEndereço Eletrónico: adra@adp.pt\neDelivery Gateway (URL): https://www.acingov.pt\nFunção da Organização: Adquirente\nSubfunção da Organização: Organização cujo orçamento é utilizado para pagar o contrato; Organização que executa o pagamento; Organização responsável pelo tratamento das propostas; Organização que recebe as propostas; Organização que trata os pedidos de participação; Organização que recebe pedidos de participação; Organização que assina o contrato\nNorma jurídica da Entidade Adjudicante: Organismo de direito público\nÁrea de atividade da Autoridade Adjudicante: Proteção ambiental\n\n2 - JORNAL OFICIAL DA UNIÃO EUROPEIA\nO procedimento a que este anúncio diz respeito também é publicitado no Jornal Oficial da União Europeia? Sim\n\n3 - AVISO\nModelo de Anúncio: Concurso público\nData de Envio do Anúncio: 30-07-2025\n\n5 - PROCESSO\nTipo de Procedimento: Concurso público\nPreço base do procedimento: Sim\nValor do preço base do procedimento: 876.975,00 EUR\nProcedimento com lotes? Não\n\n6 - OBJETO DO CONTRATO\nNúmero de referência interna: CP/2025/34_DC\nDesignação do contrato: CP/2025/34_DC - aquisição de serviços de apreciação de projetos, vistorias e verificações, inspeções de redes prediais e assessoria técnica\nDescrição: CP/2025/34_DC - aquisição de serviços de apreciação de projetos, vistorias e verificações, inspeções de redes prediais e assessoria técnica\nOpções: Não\nTipo de Contrato Principal: Aquisição de Serviços\nTipo de Contrato: Aquisição de Serviços\nClassificação CPV (Vocabulário Comum para os Contratos Públicos)\nObjeto principal\nVocabulário Principal: 71621000\nPreço base s/IVA: 876.975,00 EUR\n\n7 - INDICAÇÕES ADICIONAIS\nO contrato envolve aquisição conjunta (satisfação de várias entidades)? Não\nO contrato é adjudicado por uma central de compras? Não\n\n8 - TÉCNICAS\nO concurso destina-se à celebração de um acordo-quadro? Inexistência de acordo-quadro\nÉ utilizado um leilão eletrónico? Não\nÉ adotada uma fase de negociação? Não\nSistema de Aquisição Dinâmico: Inexistência de sistema de aquisição dinâmico\n\n9 - LOCAL DA EXECUÇÃO DO CONTRATO\nLOCAL DA EXECUÇÃO DO CONTRATO (PROCEDIMENTO)\nPaís: Portugal\nNUT III: PT16D\nLocalidade: Freguesia de Cacia\nDistrito: Aveiro\nConcelho: Aveiro\nFreguesia: Freguesia de Cacia\n\n10 - PRAZO DE EXECUÇÃO DO CONTRATO\nPrazo de execução do contrato: 3 ANOS\nPrevisão de renovações: Não\n\n11 - FUNDOS EU\nTêm fundos EU? Não\n\n12 - DOCUMENTOS DE HABILITAÇÃO\nHabilitação para o exercício da atividade profissional: Não\n\n13 - CONDIÇÕES DE APRESENTAÇÃO\nPlataforma eletrónica utilizada pela entidade adjudicante: ACIN\nURL para Apresentação: https://www.acingov.pt\nAdmissibilidade da apresentação de propostas variantes: Não autorizado\nPrazo para apresentação das propostas: 02-09-2025 18:00\nPrazo durante o qual os concorrentes são obrigados a manter as respetivas propostas: 90 dias a contar do termo do prazo para a apresentação das propostas\nApresentação de Catálogo Eletrónico: Não autorizado\nIndicação de Subcontratação na Proposta: Inexistência de indicação de subcontratação\n\n14 - PRESTAÇÃO DE CAUÇÃO\nPrestação de caução: Sim\nPercentagem: 3%\nDescrição da Garantia Exigida: O valor da caução é de 3.00% do preço contratual.\n\n15 - FORNECIMENTO DAS PEÇAS DO CONCURSO, APRESENTAÇÃO DE PEDIDOS DE PARTICIPAÇÃO E APRESENTAÇÃO DAS PROPOSTAS\nLink para acesso às peças do concurso (URL): https://www.acingov.pt/acingovprod/2/zonaPublica/zona_publica_c/donwloadProcedurePiece/OTI5NDUy\n\n20 - OUTROS REQUISITOS\nInformação sobre contratos reservados. Aplica-se a contratos reservados (54º-A)? Não\n\n21 - CRITÉRIO DE ADJUDICAÇÃO\nMultifator: Sim\nFator: \nNome: Preço\nPonderação: 60%\nSubfatores: Não\nFator: \nNome: Qualidade\nPonderação: 40%\nSubfatores: Não\n\n24 - CONDIÇÕES DO CONTRATO\nFaturação Eletrónica: Necessário\nObrigação de Subcontratação:\nCódigo da Obrigação de Subcontratação: Não é aplicável nenhuma obrigação de subcontratação.\n\n25 - COMPRA PÚBLICA ESTRATÉGICA\nCompra Pública Estratégica: Inexistência de contratação pública estratégica\n\n26 - INFORMAÇÕES ADICIONAIS\nContrato adequado para PME: Sim\nCobertura ACP (Acordo dos Contratos Públicos da Organização Mundial do Comércio): Não\n\n27 - IDENTIFICAÇÃO E CONTACTOS DO ÓRGÃO DE RECURSOS ADMINISTRATIVOS\nDesignação: Conselho de Administração\nEndereço: Travessa do rua da Paz, nº 4\nCódigo postal: 3800-587\nLocalidade: Cacia - Aveiro\nTelefone: 234910200\nFax: \nEndereço eletrónico: adra@adp.pt\nPrazo de interposição do recurso: 30 dias\n\n28 - IDENTIFICAÇÃO DO(S) AUTOR(ES) DE ANÚNCIO\nNome: Anabela Carvalhinhos\nCargo: Gestora do Procedimento\n419372977",
    "nipc": "509107630",
    "distrito": "Aveiro",
    "concelho": "Aveiro",
    "freguesia": "Freguesia de Cacia",
    "site": "www.adra.pt",
    "email": "adra@adp.pt",
    "designacao_contrato": "CP/2025/34_DC - aquisição de serviços de apreciação de projetos, vistorias e verificações, inspeções de redes prediais e assessoria técnica",
    "descricao": "CP/2025/34_DC - aquisição de serviços de apreciação de projetos, vistorias e verificações, inspeções de redes prediais e assessoria técnica",
    "preco_base": "876.975,00 EUR",
    "prazo_execucao": "3 ANOS",
    "prazo_apresentacao_propostas": "02-09-2025 18:00",
    "fundos_eu": "Não",
    "plataforma_eletronica": "ACIN",
    "url_procedimento": "https://www.acingov.pt",
    "autor_nome": "Anabela Carvalhinhos",
    "autor_cargo": "Gestora do Procedimento"
  },
  {
    "numero_procedimento": "N/A",
    "entidade": "Serviços Municipalizados de Água e Saneamento de Viseu",
    "link": "https://diariodarepublica.pt/dr/detalhe/contrato-publico/20702-927416019",
    "detalhes_completos": "1 - IDENTIFICAÇÃO E CONTACTOS DA ENTIDADE ADJUDICANTE\nDesignação da entidade adjudicante: Serviços Municipalizados de Água e Saneamento de Viseu\nNIPC: 680020063\nEndereço: Rua Conselheiro Afonso de Melo\nCódigo postal: 3510-024\nLocalidade: Viseu\nPaís: Portugal\nNUT III: PT16G\nDistrito: Viseu\nConcelho: Viseu\nFreguesia: Freguesia de Viseu\nTelefone: 232470670\nFax: 232424080\nEndereço da Entidade (URL): www.smasviseu.pt\nEndereço Eletrónico: geral@smasviseu.pt\neDelivery Gateway (URL): https://www.acingov.pt\nFunção da Organização: Adquirente\nNorma jurídica da Entidade Adjudicante: Autoridade local\nÁrea de atividade da Autoridade Adjudicante: Serviços públicos das administrações públicas\n\n2 - JORNAL OFICIAL DA UNIÃO EUROPEIA\nO procedimento a que este anúncio diz respeito também é publicitado no Jornal Oficial da União Europeia? Não\n\n3 - AVISO\nModelo de Anúncio: Concurso público\nData de Envio do Anúncio: 01-08-2025\n\n5 - PROCESSO\nTipo de Procedimento: Concurso público\nPreço base do procedimento: Sim\nValor do preço base do procedimento: 128.556,61 EUR\nProcedimento com lotes? Não\n\n6 - OBJETO DO CONTRATO\nNúmero de referência interna: E1200\nDesignação do contrato: Saneamento Básico na Rua da Quinta da Magarenha\nDescrição: Saneamento Básico na Rua da Quinta da Magarenha\nTipo de Contrato Principal: Empreitada de Obras Públicas\nTipo de Contrato: Empreitada de Obras Públicas\nClassificação CPV (Vocabulário Comum para os Contratos Públicos)\nObjeto principal\nVocabulário Principal: 45232460\nPreço base s/IVA: 128.556,61 EUR\n\n7 - INDICAÇÕES ADICIONAIS\nO contrato envolve aquisição conjunta (satisfação de várias entidades)? Não\nO contrato é adjudicado por uma central de compras? Não\n\n8 - TÉCNICAS\nO concurso destina-se à celebração de um acordo-quadro? Inexistência de acordo-quadro\nÉ utilizado um leilão eletrónico? Não\nÉ adotada uma fase de negociação? Não\nSistema de Aquisição Dinâmico: Inexistência de sistema de aquisição dinâmico\n\n9 - LOCAL DA EXECUÇÃO DO CONTRATO\nLOCAL DA EXECUÇÃO DO CONTRATO (PROCEDIMENTO)\nPaís: Portugal\nNUT III: PT16G\nLocalidade: Freguesia de Fragosela\nDistrito: Viseu\nConcelho: Viseu\nFreguesia: Freguesia de Fragosela\n\n10 - PRAZO DE EXECUÇÃO DO CONTRATO\nPrazo de execução do contrato: 120 DIAS\nPrevisão de renovações: Não\n\n11 - FUNDOS EU\nTêm fundos EU? Não\n\n12 - DOCUMENTOS DE HABILITAÇÃO\nHabilitação para o exercício da atividade profissional: Sim\nTipo: Alvará\nDescrição: O certificado do alvará de construção previsto deve conter:\nA 6ª subcategoria da 2ª categoria, sendo que a classe da 6ª subcategoria da 2ª categoria tem de ser de classe que cubra o valor global da proposta e integrar-se na categoria em que o tipo da obra se enquadra.\n\n13 - CONDIÇÕES DE APRESENTAÇÃO\nPlataforma eletrónica utilizada pela entidade adjudicante: ACIN\nURL para Apresentação: https://www.acingov.pt\nAdmissibilidade da apresentação de propostas variantes: Não autorizado\nPrazo para apresentação das propostas: 22-08-2025 23:59\nPrazo durante o qual os concorrentes são obrigados a manter as respetivas propostas: 120 dias a contar do termo do prazo para a apresentação das propostas\nIndicação de Subcontratação na Proposta: Inexistência de indicação de subcontratação\n\n14 - PRESTAÇÃO DE CAUÇÃO\nPrestação de caução: Não\n\n15 - FORNECIMENTO DAS PEÇAS DO CONCURSO, APRESENTAÇÃO DE PEDIDOS DE PARTICIPAÇÃO E APRESENTAÇÃO DAS PROPOSTAS\nLink para acesso às peças do concurso (URL): https://www.acingov.pt/acingovprod/2/zonaPublica/zona_publica_c/donwloadProcedurePiece/OTI5Mjk2\n\n20 - OUTROS REQUISITOS\nInformação sobre contratos reservados. Aplica-se a contratos reservados (54º-A)? Não\n\n21 - CRITÉRIO DE ADJUDICAÇÃO\nMultifator: Não\nMonofator:\nNome: Preço\n\n24 - CONDIÇÕES DO CONTRATO\nFaturação Eletrónica: Permitido\nObrigação de Subcontratação:\nCódigo da Obrigação de Subcontratação: Não é aplicável nenhuma obrigação de subcontratação.\n\n25 - COMPRA PÚBLICA ESTRATÉGICA\nCompra Pública Estratégica: Inexistência de contratação pública estratégica\n\n26 - INFORMAÇÕES ADICIONAIS\nContrato adequado para PME: Sim\nCobertura ACP (Acordo dos Contratos Públicos da Organização Mundial do Comércio): Não\n\n27 - IDENTIFICAÇÃO E CONTACTOS DO ÓRGÃO DE RECURSOS ADMINISTRATIVOS\nDesignação: Município de Viseu\nEndereço: Praça da República S/N\nCódigo postal: 3514-501\nLocalidade: Viseu\nTelefone: 00351232427427\nFax: 00351232423112\nEndereço eletrónico: geral@cmviseu.pt\nPrazo de interposição do recurso: 5 dias\n\n28 - IDENTIFICAÇÃO DO(S) AUTOR(ES) DE ANÚNCIO\nNome: João Paulo Lopes Gouveia\nCargo: Vogal do Conselho de Administração\n419369226",
    "nipc": "680020063",
    "distrito": "Viseu",
    "concelho": "Viseu",
    "freguesia": "Freguesia de Viseu",
    "site": "www.smasviseu.pt",
    "email": "geral@smasviseu.pt",
    "designacao_contrato": "Saneamento Básico na Rua da Quinta da Magarenha",
    "descricao": "Saneamento Básico na Rua da Quinta da Magarenha",
    "preco_base": "128.556,61 EUR",
    "prazo_execucao": "120 DIAS",
    "prazo_apresentacao_propostas": "22-08-2025 23:59",
    "fundos_eu": "Não",
    "plataforma_eletronica": "ACIN",
    "url_procedimento": "https://www.acingov.pt",
    "autor_nome": "João Paulo Lopes Gouveia",
    "autor_cargo": "Vogal do Conselho de Administração"
  },
  {
    "numero_procedimento": "N/A",
    "entidade": "Lisboa SRU",
    "link": "https://diariodarepublica.pt/dr/detalhe/contrato-publico/20663-927474289",
    "detalhes_completos": "1 - IDENTIFICAÇÃO E CONTACTOS DA ENTIDADE ADJUDICANTE\nDesignação da entidade adjudicante: Lisboa SRU\nNIPC: 507023129\nEndereço: Praça do Município, 31 ¿ 2.º/4.º Piso\nCódigo postal: 1100-365\nLocalidade: Lisboa\nPaís: Portugal\nNUT III: PT170\nDistrito: Lisboa\nConcelho: Lisboa\nFreguesia: Freguesia de Santa Maria Maior - Lisboa\nTelefone: 218847030\nFax: 2188470030\nEndereço da Entidade (URL): https://www.lisboaocidentalsru.pt\nEndereço Eletrónico: compras.publicas@lisboaocidentalsru.pt\nFunção da Organização: Adquirente\nNorma jurídica da Entidade Adjudicante: Organismo de direito público, controlado por uma autoridade da administração central\nÁrea de atividade da Autoridade Adjudicante: Serviços públicos das administrações públicas\n\n2 - JORNAL OFICIAL DA UNIÃO EUROPEIA\nO procedimento a que este anúncio diz respeito também é publicitado no Jornal Oficial da União Europeia? Sim\n\n3 - AVISO\nModelo de Anúncio: Concurso público\nData de Envio do Anúncio: 29-07-2025\n\n5 - PROCESSO\nTipo de Procedimento: Concurso público\nPreço base do procedimento: Sim\nValor do preço base do procedimento: 1.260.000,00 EUR\nProcedimento com lotes? Não\n\n6 - OBJETO DO CONTRATO\nNúmero de referência interna: SRU20250000384\nDesignação do contrato:  AQUISIÇÃO DE SERVIÇOS DE ELABORAÇÃO DE PROJETO DE CONSTRUÇÃO, REQUALIFICAÇÃO E AMPLIAÇÃO DA ESCOLA SECUNDÁRIA DO RESTELO, FREGUESIA DE BELÉM\nDescrição: Aquisição de Serviços \nOpções: Não\nTipo de Contrato Principal: Aquisição de Serviços\nTipo de Contrato: Aquisição de Serviços\nClassificação CPV (Vocabulário Comum para os Contratos Públicos)\nObjeto principal\nVocabulário Principal: 71000000\nPreço base s/IVA: 1.260.000,00 EUR\n\n7 - INDICAÇÕES ADICIONAIS\nO contrato envolve aquisição conjunta (satisfação de várias entidades)? Não\nO contrato é adjudicado por uma central de compras? Não\n\n8 - TÉCNICAS\nO concurso destina-se à celebração de um acordo-quadro? Inexistência de acordo-quadro\nÉ utilizado um leilão eletrónico? Não\nÉ adotada uma fase de negociação? Não\nSistema de Aquisição Dinâmico: Inexistência de sistema de aquisição dinâmico\n\n9 - LOCAL DA EXECUÇÃO DO CONTRATO\nLOCAL DA EXECUÇÃO DO CONTRATO (PROCEDIMENTO)\nPaís: Portugal\nNUT III: PT170\nLocalidade: Lisboa\nDistrito: Lisboa\nConcelho: Lisboa\nFreguesia: Freguesia de Belém\n\n10 - PRAZO DE EXECUÇÃO DO CONTRATO\nPrazo de execução do contrato: 1815 DIAS\nPrevisão de renovações: Não\n\n11 - FUNDOS EU\nTêm fundos EU? Não\n\n12 - DOCUMENTOS DE HABILITAÇÃO\nHabilitação para o exercício da atividade profissional: Não\n\n13 - CONDIÇÕES DE APRESENTAÇÃO\nPlataforma eletrónica utilizada pela entidade adjudicante: ANOGOV\nURL para Apresentação: https://www.anogov.com/lisboaocidental-sru/faces/\nAdmissibilidade da apresentação de propostas variantes: Não autorizado\nPrazo para apresentação das propostas: 28-08-2025 17:00\nPrazo durante o qual os concorrentes são obrigados a manter as respetivas propostas: 120 dias a contar do termo do prazo para a apresentação das propostas\nApresentação de Catálogo Eletrónico: Não autorizado\nIndicação de Subcontratação na Proposta: Inexistência de indicação de subcontratação\n\n14 - PRESTAÇÃO DE CAUÇÃO\nPrestação de caução: Sim\nPercentagem: 5%\nDescrição da Garantia Exigida: De acordo com as peças do procedimento\n\n15 - FORNECIMENTO DAS PEÇAS DO CONCURSO, APRESENTAÇÃO DE PEDIDOS DE PARTICIPAÇÃO E APRESENTAÇÃO DAS PROPOSTAS\nLink para acesso às peças do concurso (URL): https://www.anogov.com/lisboaocidental-sru/faces/app/acessoDocs.jsp?codigoAcesso=sm3UTu0vKRzNr8nKEZXP5fQ3b3dLnbox2qB7aO9eaqmY1SHied\n\n20 - OUTROS REQUISITOS\nInformação sobre contratos reservados. Aplica-se a contratos reservados (54º-A)? Não\n\n21 - CRITÉRIO DE ADJUDICAÇÃO\nMultifator: Sim\nFator: \nNome: Outros\nOutro Nome:  Experiência da equipa técnica \nPonderação: 60%\nSubfatores: Não\nFator: \nNome: Preço\nPonderação: 20%\nSubfatores: Não\nFator: \nNome: Outros\nOutro Nome: Aspetos relevantes da estratégia de manutenção do edifício escolar a considerar no futuro projeto\nPonderação: 20%\nSubfatores: Não\n\n24 - CONDIÇÕES DO CONTRATO\nFaturação Eletrónica: Permitido\nObrigação de Subcontratação:\nCódigo da Obrigação de Subcontratação: Não é aplicável nenhuma obrigação de subcontratação.\n\n25 - COMPRA PÚBLICA ESTRATÉGICA\nCompra Pública Estratégica: Inexistência de contratação pública estratégica\n\n26 - INFORMAÇÕES ADICIONAIS\nContrato adequado para PME: Sim\nCobertura ACP (Acordo dos Contratos Públicos da Organização Mundial do Comércio): Não\n\n27 - IDENTIFICAÇÃO E CONTACTOS DO ÓRGÃO DE RECURSOS ADMINISTRATIVOS\nDesignação: Lisboa Ocidental SRU EM S.A\nEndereço: Praça do Município, n.º 31\nCódigo postal: 1100-365\nLocalidade: Lisboa\nEndereço eletrónico: geral@lisboasru.pt\n\n28 - IDENTIFICAÇÃO DO(S) AUTOR(ES) DE ANÚNCIO\nNome: Luis Santos\nCargo: Assistente Técnico\n419371186",
    "nipc": "507023129",
    "distrito": "Lisboa",
    "concelho": "Lisboa",
    "freguesia": "Freguesia de Santa Maria Maior - Lisboa",
    "site": "https://www.lisboaocidentalsru.pt",
    "email": "compras.publicas@lisboaocidentalsru.pt",
    "designacao_contrato": "AQUISIÇÃO DE SERVIÇOS DE ELABORAÇÃO DE PROJETO DE CONSTRUÇÃO, REQUALIFICAÇÃO E AMPLIAÇÃO DA ESCOLA SECUNDÁRIA DO RESTELO, FREGUESIA DE BELÉM",
    "descricao": "Aquisição de Serviços",
    "preco_base": "1.260.000,00 EUR",
    "prazo_execucao": "1815 DIAS",
    "prazo_apresentacao_propostas": "28-08-2025 17:00",
    "fundos_eu": "Não",
    "plataforma_eletronica": "ANOGOV",
    "url_procedimento": "https://www.anogov.com/lisboaocidental-sru/faces/",
    "autor_nome": "Luis Santos",
    "autor_cargo": "Assistente Técnico"
  },
  {
    "numero_procedimento": "N/A",
    "entidade": "Câmara Municipal de Palmela",
    "link": "https://diariodarepublica.pt/dr/detalhe/contrato-publico/20665-927474290",
    "detalhes_completos": "1 - IDENTIFICAÇÃO E CONTACTOS DA ENTIDADE ADJUDICANTE\nDesignação da entidade adjudicante: Câmara Municipal de Palmela\nNIPC: 506187543\nServiço/Órgão/Pessoa de contacto: Câmara Municipal de Palmela/Departamento de Ambiente e Serviços Urbanos/Divisão de Infraestruturas Viárias e Espaço Público\nEndereço: Largo Município , Palmela\nCódigo postal: 2954-001\nLocalidade: Setúbal\nPaís: Portugal\nNUT III: PT170\nDistrito: Setúbal\nConcelho: Palmela\nFreguesia: Freguesia de Palmela\nTelefone: 212 336 600\nFax: 212 336 619\nEndereço da Entidade (URL): www.cm-palmela.pt\nEndereço Eletrónico: geral@cm-palmela.pt\neDelivery Gateway (URL): https://community.vortal.biz/public/\nFunção da Organização: Adquirente\nNorma jurídica da Entidade Adjudicante: Organismo de direito público\nÁrea de atividade da Autoridade Adjudicante: Serviços públicos das administrações públicas\n\n2 - JORNAL OFICIAL DA UNIÃO EUROPEIA\nO procedimento a que este anúncio diz respeito também é publicitado no Jornal Oficial da União Europeia? Não\n\n3 - AVISO\nModelo de Anúncio: Concurso público\nData de Envio do Anúncio: 31-07-2025\n\n5 - PROCESSO\nTipo de Procedimento: Concurso público\nPreço base do procedimento: Sim\nValor do preço base do procedimento: 36.792,31 EUR\nProcedimento com lotes? Não\n\n6 - OBJETO DO CONTRATO\nNúmero de referência interna: 35/25\nDesignação do contrato: Sinalização Horizontal em Arruamentos Municipais - Ano 2025\nDescrição: Os trabalhos a realizar visam a execução de marcas rodoviárias em arruamentos, estradas e caminhos municipais.\nTipo de Contrato Principal: Empreitada de Obras Públicas\nTipo de Contrato: Empreitada de Obras Públicas\nClassificação CPV (Vocabulário Comum para os Contratos Públicos)\nObjeto principal\nVocabulário Principal: 45233221\nPreço base s/IVA: 36.792,31 EUR\n\n7 - INDICAÇÕES ADICIONAIS\nO contrato envolve aquisição conjunta (satisfação de várias entidades)? Não\nO contrato é adjudicado por uma central de compras? Não\n\n8 - TÉCNICAS\nO concurso destina-se à celebração de um acordo-quadro? Inexistência de acordo-quadro\nÉ utilizado um leilão eletrónico? Não\nÉ adotada uma fase de negociação? Não\nSistema de Aquisição Dinâmico: Inexistência de sistema de aquisição dinâmico\n\n9 - LOCAL DA EXECUÇÃO DO CONTRATO\nLOCAL DA EXECUÇÃO DO CONTRATO (PROCEDIMENTO)\nPaís: Portugal\nNUT III: PT170\nLocalidade: Setúbal\nDistrito: Setúbal\nConcelho: Palmela\nFreguesia: Todas\n\n10 - PRAZO DE EXECUÇÃO DO CONTRATO\nPrazo de execução do contrato: 90 DIAS\nPrevisão de renovações: Não\n\n11 - FUNDOS EU\nTêm fundos EU? Não\n\n12 - DOCUMENTOS DE HABILITAÇÃO\nHabilitação para o exercício da atividade profissional: Não\n\n13 - CONDIÇÕES DE APRESENTAÇÃO\nPlataforma eletrónica utilizada pela entidade adjudicante: VORTAL\nURL para Apresentação: https://community.vortal.biz/public/\nAdmissibilidade da apresentação de propostas variantes: Não autorizado\nPrazo para apresentação das propostas: 15-08-2025 23:59\nPrazo durante o qual os concorrentes são obrigados a manter as respetivas propostas: 66 dias a contar do termo do prazo para a apresentação das propostas\nIndicação de Subcontratação na Proposta: Inexistência de indicação de subcontratação\n\n14 - PRESTAÇÃO DE CAUÇÃO\nPrestação de caução: Não\n\n15 - FORNECIMENTO DAS PEÇAS DO CONCURSO, APRESENTAÇÃO DE PEDIDOS DE PARTICIPAÇÃO E APRESENTAÇÃO DAS PROPOSTAS\nLink para acesso às peças do concurso (URL): https://community.vortal.biz/Public/public-tender-documents/TTJSZ09uWGdSaVVPc2plUTJkZDBMVDB0MVdVUjdnVlNzMHdrM0JDdGt3c3RoejNobWN4V3l6am44UUZCa0I4R0xGSmEzc3NaWlZUTU5wV2o4UHgxdkE9PVhGaDBl\n\n20 - OUTROS REQUISITOS\nInformação sobre contratos reservados. Aplica-se a contratos reservados (54º-A)? Não\n\n21 - CRITÉRIO DE ADJUDICAÇÃO\nMultifator: Não\nMonofator:\nNome: Preço\n\n24 - CONDIÇÕES DO CONTRATO\nFaturação Eletrónica: Permitido\nObrigação de Subcontratação:\nCódigo da Obrigação de Subcontratação: Não é aplicável nenhuma obrigação de subcontratação.\n\n25 - COMPRA PÚBLICA ESTRATÉGICA\nCompra Pública Estratégica: Inexistência de contratação pública estratégica\n\n26 - INFORMAÇÕES ADICIONAIS\nContrato adequado para PME: Sim\nCobertura ACP (Acordo dos Contratos Públicos da Organização Mundial do Comércio): Não\n\n27 - IDENTIFICAÇÃO E CONTACTOS DO ÓRGÃO DE RECURSOS ADMINISTRATIVOS\nDesignação: Câmara Municipal de Palmela\nEndereço: Largo do Município\nCódigo postal: 2954-001\nLocalidade: Palmela\nTelefone: +351 212336675\nFax: +351 212336676\nEndereço eletrónico: geral@cm-palmela.pt\n\n28 - IDENTIFICAÇÃO DO(S) AUTOR(ES) DE ANÚNCIO\nNome: Álvaro Manuel Balseiro Amaro\nCargo: Presidente da Câmara Municipal de Palmela\n419371826",
    "nipc": "506187543",
    "distrito": "Setúbal",
    "concelho": "Palmela",
    "freguesia": "Freguesia de Palmela",
    "site": "www.cm-palmela.pt",
    "email": "geral@cm-palmela.pt",
    "designacao_contrato": "Sinalização Horizontal em Arruamentos Municipais - Ano 2025",
    "descricao": "Os trabalhos a realizar visam a execução de marcas rodoviárias em arruamentos, estradas e caminhos municipais.",
    "preco_base": "36.792,31 EUR",
    "prazo_execucao": "90 DIAS",
    "prazo_apresentacao_propostas": "15-08-2025 23:59",
    "fundos_eu": "Não",
    "plataforma_eletronica": "VORTAL",
    "url_procedimento": "https://community.vortal.biz/public/",
    "autor_nome": "Álvaro Manuel Balseiro Amaro",
    "autor_cargo": "Presidente da Câmara Municipal de Palmela"
  },
  {
    "numero_procedimento": "N/A",
    "entidade": "Centro Social de Paramos",
    "link": "https://diariodarepublica.pt/dr/detalhe/contrato-publico/20666-927474291",
    "detalhes_completos": "1 - IDENTIFICAÇÃO E CONTACTOS DA ENTIDADE ADJUDICANTE\nDesignação da entidade adjudicante: Centro Social de Paramos\nNIPC: 501086803\nServiço/Órgão/Pessoa de contacto: Direção \nEndereço: Travessa da Junta, nº 44\nCódigo postal: 4500-541\nLocalidade: Aveiro\nPaís: Portugal\nNUT III: PT11A\nDistrito: Aveiro\nConcelho: Espinho\nFreguesia: Freguesia de Paramos\nTelefone: 227330870\nFax: 227330870\nEndereço Eletrónico: geral@centrosocialparamos.org\neDelivery Gateway (URL): https://community.vortal.biz/public/\nFunção da Organização: Adquirente\nNorma jurídica da Entidade Adjudicante: Organismo de direito público\nÁrea de atividade da Autoridade Adjudicante: Proteção social\n\n2 - JORNAL OFICIAL DA UNIÃO EUROPEIA\nO procedimento a que este anúncio diz respeito também é publicitado no Jornal Oficial da União Europeia? Não\n\n3 - AVISO\nModelo de Anúncio: Concurso público\nData de Envio do Anúncio: 31-07-2025\n\n5 - PROCESSO\nTipo de Procedimento: Concurso público\nPreço base do procedimento: Sim\nValor do preço base do procedimento: 39.700,00 EUR\nProcedimento com lotes? Não\n\n6 - OBJETO DO CONTRATO\nNúmero de referência interna: RENOVACAO AP.  HABITACAO PARTILHADA - CPU01/2025\nDesignação do contrato: RENOVACAO DEAPARTAMENTO PARA  HABITACAO PARTILHADA \nDescrição: RENOVAÇÃO DE APARTAMENTO PARA PROJETO DE HABITAÇÃO PARTILHADA\nTipo de Contrato Principal: Empreitada de Obras Públicas\nTipo de Contrato: Empreitada de Obras Públicas\nClassificação CPV (Vocabulário Comum para os Contratos Públicos)\nObjeto principal\nVocabulário Principal: 45453100\nPreço base s/IVA: 39.700,00 EUR\n\n7 - INDICAÇÕES ADICIONAIS\nO contrato envolve aquisição conjunta (satisfação de várias entidades)? Não\nO contrato é adjudicado por uma central de compras? Não\n\n8 - TÉCNICAS\nO concurso destina-se à celebração de um acordo-quadro? Inexistência de acordo-quadro\nÉ utilizado um leilão eletrónico? Não\nÉ adotada uma fase de negociação? Não\nSistema de Aquisição Dinâmico: Inexistência de sistema de aquisição dinâmico\n\n9 - LOCAL DA EXECUÇÃO DO CONTRATO\nLOCAL DA EXECUÇÃO DO CONTRATO (PROCEDIMENTO)\nPaís: Portugal\nNUT III: PT11A\nLocalidade: Aveiro\nDistrito: Aveiro\nConcelho: Espinho\nFreguesia: Freguesia de Paramos\n\n10 - PRAZO DE EXECUÇÃO DO CONTRATO\nPrazo de execução do contrato: 90 DIAS\nPrevisão de renovações: Não\n\n11 - FUNDOS EU\nTêm fundos EU? Não\n\n12 - DOCUMENTOS DE HABILITAÇÃO\nHabilitação para o exercício da atividade profissional: Não\n\n13 - CONDIÇÕES DE APRESENTAÇÃO\nPlataforma eletrónica utilizada pela entidade adjudicante: VORTAL\nURL para Apresentação: https://community.vortal.biz/public/\nAdmissibilidade da apresentação de propostas variantes: Não autorizado\nPrazo para apresentação das propostas: 20-08-2025 17:00\nPrazo durante o qual os concorrentes são obrigados a manter as respetivas propostas: 66 dias a contar do termo do prazo para a apresentação das propostas\nIndicação de Subcontratação na Proposta: Inexistência de indicação de subcontratação\n\n14 - PRESTAÇÃO DE CAUÇÃO\nPrestação de caução: Não\n\n15 - FORNECIMENTO DAS PEÇAS DO CONCURSO, APRESENTAÇÃO DE PEDIDOS DE PARTICIPAÇÃO E APRESENTAÇÃO DAS PROPOSTAS\nLink para acesso às peças do concurso (URL): https://community.vortal.biz/Public/public-tender-documents/RHFxVm5iaE1tazR2SmlmOThreG84ai9lbHJXVGpkUThMZGJWYTFFOTlQOW5nODlJTlF2SW9KTStaOWtUSzhocW1yUTZ4WFo3K3J6eGVZekNKOHhuK1E9PVIyNzhz\n\n20 - OUTROS REQUISITOS\nInformação sobre contratos reservados. Aplica-se a contratos reservados (54º-A)? Não\n\n21 - CRITÉRIO DE ADJUDICAÇÃO\nMultifator: Não\nMonofator:\nNome: Preço\n\n24 - CONDIÇÕES DO CONTRATO\nFaturação Eletrónica: Não autorizado\nObrigação de Subcontratação:\nCódigo da Obrigação de Subcontratação: Não é aplicável nenhuma obrigação de subcontratação.\n\n25 - COMPRA PÚBLICA ESTRATÉGICA\nCompra Pública Estratégica: Inexistência de contratação pública estratégica\n\n26 - INFORMAÇÕES ADICIONAIS\nContrato adequado para PME: Sim\nCobertura ACP (Acordo dos Contratos Públicos da Organização Mundial do Comércio): Não\n\n27 - IDENTIFICAÇÃO E CONTACTOS DO ÓRGÃO DE RECURSOS ADMINISTRATIVOS\nDesignação: Rui Filipe da Silva Brandão\nEndereço: Travessa da Junta,44\nCódigo postal: 4500-541\nLocalidade: Espinho\nTelefone: +351 917974099\nFax: +351 227330870\nEndereço eletrónico: ruibrandao@centrosocialparamos.org\n\n28 - IDENTIFICAÇÃO DO(S) AUTOR(ES) DE ANÚNCIO\nNome: Américo de Castro Pinto dos Santos\nCargo: Presidente da Direção\n419382745",
    "nipc": "501086803",
    "distrito": "Aveiro",
    "concelho": "Espinho",
    "freguesia": "Freguesia de Paramos",
    "site": null,
    "email": "geral@centrosocialparamos.org",
    "designacao_contrato": "RENOVACAO DEAPARTAMENTO PARA HABITACAO PARTILHADA",
    "descricao": "RENOVAÇÃO DE APARTAMENTO PARA PROJETO DE HABITAÇÃO PARTILHADA",
    "preco_base": "39.700,00 EUR",
    "prazo_execucao": "90 DIAS",
    "prazo_apresentacao_propostas": "20-08-2025 17:00",
    "fundos_eu": "Não",
    "plataforma_eletronica": "VORTAL",
    "url_procedimento": "https://community.vortal.biz/public/",
    "autor_nome": "Américo de Castro Pinto dos Santos",
    "autor_cargo": "Presidente da Direção"
  },
  {
    "numero_procedimento": "N/A",
    "entidade": "Município da Batalha",
    "link": "https://diariodarepublica.pt/dr/detalhe/contrato-publico/20667-927474292",
    "detalhes_completos": "1 - IDENTIFICAÇÃO E CONTACTOS DA ENTIDADE ADJUDICANTE\nDesignação da entidade adjudicante: Município da Batalha\nNIPC: 501290206\nEndereço: Rua Infante D. Fernando\nCódigo postal: 2440-118\nLocalidade: Leiria\nPaís: Portugal\nNUT III: PT16F\nDistrito: Leiria\nConcelho: Batalha\nFreguesia: Freguesia de Batalha\nTelefone: 244769110\nFax: 244769110\nEndereço da Entidade (URL): https://www.cm-batalha.pt\nEndereço Eletrónico: geral@cm-batalha.pt\neDelivery Gateway (URL): https://community.vortal.biz/public/\nFunção da Organização: Adquirente\nNorma jurídica da Entidade Adjudicante: Autoridade local\nÁrea de atividade da Autoridade Adjudicante: Serviços públicos das administrações públicas\n\n2 - JORNAL OFICIAL DA UNIÃO EUROPEIA\nO procedimento a que este anúncio diz respeito também é publicitado no Jornal Oficial da União Europeia? Não\n\n3 - AVISO\nModelo de Anúncio: Concurso limitado por prévia qualificação\nData de Envio do Anúncio: 31-07-2025\n\n5 - PROCESSO\nTipo de Procedimento: Concurso limitado por prévia qualificação\nPreço base do procedimento: Sim\nValor do preço base do procedimento: 81.022,00 EUR\nProcedimento com lotes? Não\n\n6 - OBJETO DO CONTRATO\nNúmero de referência interna: 61/2025\nDesignação do contrato: Prestação de Serviços Jurídicos e de Patrocínio Judiciário.\nDescrição: Prestação de Serviços Jurídicos e de Patrocínio Judiciário.\nTipo de Contrato Principal: Aquisição de Serviços\nTipo de Contrato: Aquisição de Serviços\nClassificação CPV (Vocabulário Comum para os Contratos Públicos)\nObjeto principal\nVocabulário Principal: 79111000\nPreço base s/IVA: 81.022,00 EUR\n\n7 - INDICAÇÕES ADICIONAIS\nO contrato envolve aquisição conjunta (satisfação de várias entidades)? Não\nO contrato é adjudicado por uma central de compras? Não\n\n8 - TÉCNICAS\nO concurso destina-se à celebração de um acordo-quadro? Inexistência de acordo-quadro\nÉ utilizado um leilão eletrónico? Não\nSistema de Aquisição Dinâmico: Inexistência de sistema de aquisição dinâmico\n\n9 - LOCAL DA EXECUÇÃO DO CONTRATO\nLOCAL DA EXECUÇÃO DO CONTRATO (PROCEDIMENTO)\nPaís: Portugal\nNUT III: PT16F\nLocalidade: Leiria\nDistrito: Leiria\nConcelho: Batalha\nFreguesia: Freguesia de Batalha\n\n10 - PRAZO DE EXECUÇÃO DO CONTRATO\nPrazo de execução do contrato: 24 MESES\nPrevisão de renovações: Não\n\n11 - FUNDOS EU\nTêm fundos EU? Não\n\n12 - DOCUMENTOS DE HABILITAÇÃO\nHabilitação para o exercício da atividade profissional: Sim\nTipo: Ordem Profissional\nDescrição: Advogados com Cédula ativa da ordem das avogados, nos termos  clausula 11º do Programa do procedimento\n\n13 - CONDIÇÕES DE APRESENTAÇÃO\nPlataforma eletrónica utilizada pela entidade adjudicante: VORTAL\nURL para Apresentação: https://community.vortal.biz/public/\nAdmissibilidade da apresentação de propostas variantes: Não autorizado\nPrazo para apresentação das candidaturas: 08-08-2025 23:59\nRequisitos mínimos \nRequisitos mínimos de capacidade técnica: Determinado no Programa do procedimento, clausula 11º \nRequisitos mínimos de capacidade financeira: Conforme as peças do procedimento\nPrazo durante o qual os concorrentes são obrigados a manter as respetivas propostas: 60 dias a contar do termo do prazo para a apresentação das propostas\nIndicação de Subcontratação na Proposta: Inexistência de indicação de subcontratação\n\n14 - PRESTAÇÃO DE CAUÇÃO\nPrestação de caução: Não\n\n15 - FORNECIMENTO DAS PEÇAS DO CONCURSO, APRESENTAÇÃO DE PEDIDOS DE PARTICIPAÇÃO E APRESENTAÇÃO DAS PROPOSTAS\nLink para acesso às peças do concurso (URL): https://community.vortal.biz/Public/public-tender-documents/cmhWYk43MWN1V3dYNU1mVkNWNi9vQS8yNUFHVkY3VXFsS2RoRlF2KzhlVHVEbUNmaVVoTXZaYzJEcTVkSnFJR0pZQnVoS2RYNjFQQ2IrNHZ3MzlicFE9PUJocl9q\n\n20 - OUTROS REQUISITOS\nInformação sobre contratos reservados. Aplica-se a contratos reservados (54º-A)? Não\n\n21 - CRITÉRIO DE ADJUDICAÇÃO\nMultifator: Não\nMonofator:\nNome: Outros\nOutro nome: Preço\n\n24 - CONDIÇÕES DO CONTRATO\nFaturação Eletrónica: Permitido\nObrigação de Subcontratação:\nCódigo da Obrigação de Subcontratação: Não é aplicável nenhuma obrigação de subcontratação.\n\n25 - COMPRA PÚBLICA ESTRATÉGICA\nCompra Pública Estratégica: Inexistência de contratação pública estratégica\n\n26 - INFORMAÇÕES ADICIONAIS\nContrato adequado para PME: Sim\nCobertura ACP (Acordo dos Contratos Públicos da Organização Mundial do Comércio): Não\n\n27 - IDENTIFICAÇÃO E CONTACTOS DO ÓRGÃO DE RECURSOS ADMINISTRATIVOS\nDesignação: Tribunal Administrativo e Fiscal de Leiria\nEndereço: Rua João Paulo II, R/C\nCódigo postal: 2410-241\nLocalidade: Leiria\nTelefone: +351 244870600\nFax: +351 213506006\nEndereço eletrónico: leiria.taf@tribunais.org.pt\n\n28 - IDENTIFICAÇÃO DO(S) AUTOR(ES) DE ANÚNCIO\nNome: Raul Miguel de Castro\nCargo: Presidente da Câmara Municipal da Batalha\n419383206",
    "nipc": "501290206",
    "distrito": "Leiria",
    "concelho": "Batalha",
    "freguesia": "Freguesia de Batalha",
    "site": "https://www.cm-batalha.pt",
    "email": "geral@cm-batalha.pt",
    "designacao_contrato": "Prestação de Serviços Jurídicos e de Patrocínio Judiciário.",
    "descricao": "Prestação de Serviços Jurídicos e de Patrocínio Judiciário.",
    "preco_base": "81.022,00 EUR",
    "prazo_execucao": "24 MESES",
    "prazo_apresentacao_propostas": null,
    "fundos_eu": "Não",
    "plataforma_eletronica": "VORTAL",
    "url_procedimento": "https://community.vortal.biz/public/",
    "autor_nome": "Raul Miguel de Castro",
    "autor_cargo": "Presidente da Câmara Municipal da Batalha"
  },
  {
    "numero_procedimento": "N/A",
    "entidade": "Câmara Municipal de Palmela",
    "link": "https://diariodarepublica.pt/dr/detalhe/contrato-publico/20668-927474293",
    "detalhes_completos": "1 - IDENTIFICAÇÃO E CONTACTOS DA ENTIDADE ADJUDICANTE\nDesignação da entidade adjudicante: Câmara Municipal de Palmela\nNIPC: 506187543\nEndereço: Largo Município , Palmela\nCódigo postal: 2954-001\nLocalidade: Setúbal\nPaís: Portugal\nNUT III: PT170\nDistrito: Setúbal\nConcelho: Palmela\nFreguesia: Freguesia de Palmela\nTelefone: 212 336 600\nFax: 212 336 619\nEndereço da Entidade (URL): www.cm-palmela.pt\nEndereço Eletrónico: geral@cm-palmela.pt\neDelivery Gateway (URL): https://community.vortal.biz/public/\nFunção da Organização: Adquirente\nNorma jurídica da Entidade Adjudicante: Organismo de direito público\nÁrea de atividade da Autoridade Adjudicante: Serviços públicos das administrações públicas\n\n2 - JORNAL OFICIAL DA UNIÃO EUROPEIA\nO procedimento a que este anúncio diz respeito também é publicitado no Jornal Oficial da União Europeia? Não\n\n3 - AVISO\nModelo de Anúncio: Concurso público\nData de Envio do Anúncio: 31-07-2025\n\n5 - PROCESSO\nTipo de Procedimento: Concurso público\nPreço base do procedimento: Sim\nValor do preço base do procedimento: 81.500,00 EUR\nProcedimento com lotes? Não\n\n6 - OBJETO DO CONTRATO\nNúmero de referência interna: 5034/2025\nDesignação do contrato: Empreitada de Requalificação da UCSP de Poceirão\nDescrição: Empreitada de Requalificação da UCSP de Poceirão - Os trabalhos a realizar englobam essencialmente trabalhos de beneficiação e reforço do isolamento térmico das fachadas com sistema ETICS, tratamento e pintura de paredes e tetos interiores, substituição de estores, reforço do isolamento da laje de esteira da cobertura com lã de rocha, revisão das coberturas, limpeza de caleiras e substituição dos órgãos de apoio à drenagem de águas pluviais\nTipo de Contrato Principal: Empreitada de Obras Públicas\nTipo de Contrato: Empreitada de Obras Públicas\nClassificação CPV (Vocabulário Comum para os Contratos Públicos)\nObjeto principal\nVocabulário Principal: 45200000\nPreço base s/IVA: 81.500,00 EUR\n\n7 - INDICAÇÕES ADICIONAIS\nO contrato envolve aquisição conjunta (satisfação de várias entidades)? Não\nO contrato é adjudicado por uma central de compras? Não\n\n8 - TÉCNICAS\nO concurso destina-se à celebração de um acordo-quadro? Inexistência de acordo-quadro\nÉ utilizado um leilão eletrónico? Não\nÉ adotada uma fase de negociação? Não\nSistema de Aquisição Dinâmico: Inexistência de sistema de aquisição dinâmico\n\n9 - LOCAL DA EXECUÇÃO DO CONTRATO\nLOCAL DA EXECUÇÃO DO CONTRATO (PROCEDIMENTO)\nPaís: Portugal\nNUT III: PT170\nLocalidade: Poceirão\nDistrito: Setúbal\nConcelho: Palmela\nFreguesia: União das Freguesias de Poceirão e Marateca\n\n10 - PRAZO DE EXECUÇÃO DO CONTRATO\nPrazo de execução do contrato: 60 DIAS\nPrevisão de renovações: Não\n\n11 - FUNDOS EU\nTêm fundos EU? Sim\n\n12 - DOCUMENTOS DE HABILITAÇÃO\nHabilitação para o exercício da atividade profissional: Sim\nTipo: Alvará\nDescrição: Alvarás nos termos das peças do procedimento\n\n13 - CONDIÇÕES DE APRESENTAÇÃO\nPlataforma eletrónica utilizada pela entidade adjudicante: VORTAL\nURL para Apresentação: https://community.vortal.biz/public/\nAdmissibilidade da apresentação de propostas variantes: Não autorizado\nPrazo para apresentação das propostas: 15-08-2025 23:59\nPrazo durante o qual os concorrentes são obrigados a manter as respetivas propostas: 120 dias a contar do termo do prazo para a apresentação das propostas\nIndicação de Subcontratação na Proposta: Inexistência de indicação de subcontratação\n\n14 - PRESTAÇÃO DE CAUÇÃO\nPrestação de caução: Não\n\n15 - FORNECIMENTO DAS PEÇAS DO CONCURSO, APRESENTAÇÃO DE PEDIDOS DE PARTICIPAÇÃO E APRESENTAÇÃO DAS PROPOSTAS\nLink para acesso às peças do concurso (URL): https://community.vortal.biz/Public/public-tender-documents/MTdsYzdXaXV1MXZXQ0VGSXdQNitPclpaelZYWmJveGh1TWxsWm05Ri85eGhhSjh4Y3djaWkzK0Y5SUt2bERrRTNFWldyeEcySUlDOG5lNHpZZUUzR1E9PShqdyQl\n\n20 - OUTROS REQUISITOS\nInformação sobre contratos reservados. Aplica-se a contratos reservados (54º-A)? Não\n\n21 - CRITÉRIO DE ADJUDICAÇÃO\nMultifator: Não\nMonofator:\nNome: Outros\nOutro nome: Preço\n\n24 - CONDIÇÕES DO CONTRATO\nFaturação Eletrónica: Permitido\nObrigação de Subcontratação:\nCódigo da Obrigação de Subcontratação: Não é aplicável nenhuma obrigação de subcontratação.\n\n25 - COMPRA PÚBLICA ESTRATÉGICA\nCompra Pública Estratégica: Inexistência de contratação pública estratégica\n\n26 - INFORMAÇÕES ADICIONAIS\nContrato adequado para PME: Sim\nCobertura ACP (Acordo dos Contratos Públicos da Organização Mundial do Comércio): Não\n\n27 - IDENTIFICAÇÃO E CONTACTOS DO ÓRGÃO DE RECURSOS ADMINISTRATIVOS\nDesignação: Município de Palmela\nEndereço: Largo do Municipio\nCódigo postal: 2954-001\nLocalidade: Palmela\nTelefone: +351 0351212336670\nFax: +351 0351212336671\nEndereço eletrónico: depop@cm-palmela.pt\n\n28 - IDENTIFICAÇÃO DO(S) AUTOR(ES) DE ANÚNCIO\nNome: Álvaro Amaro\nCargo: Presidente da Câmara Municipal de Palmela\n419362876",
    "nipc": "506187543",
    "distrito": "Setúbal",
    "concelho": "Palmela",
    "freguesia": "Freguesia de Palmela",
    "site": "www.cm-palmela.pt",
    "email": "geral@cm-palmela.pt",
    "designacao_contrato": "Empreitada de Requalificação da UCSP de Poceirão",
    "descricao": "Empreitada de Requalificação da UCSP de Poceirão - Os trabalhos a realizar englobam essencialmente trabalhos de beneficiação e reforço do isolamento térmico das fachadas com sistema ETICS, tratamento e pintura de paredes e tetos interiores, substituição de estores, reforço do isolamento da laje de esteira da cobertura com lã de rocha, revisão das coberturas, limpeza de caleiras e substituição dos órgãos de apoio à drenagem de águas pluviais",
    "preco_base": "81.500,00 EUR",
    "prazo_execucao": "60 DIAS",
    "prazo_apresentacao_propostas": "15-08-2025 23:59",
    "fundos_eu": "Sim",
    "plataforma_eletronica": "VORTAL",
    "url_procedimento": "https://community.vortal.biz/public/",
    "autor_nome": "Álvaro Amaro",
    "autor_cargo": "Presidente da Câmara Municipal de Palmela"
  },
  {
    "numero_procedimento": "N/A",
    "entidade": "Câmara Municipal de Palmela",
    "link": "https://diariodarepublica.pt/dr/detalhe/contrato-publico/20669-927474294",
    "detalhes_completos": "1 - IDENTIFICAÇÃO E CONTACTOS DA ENTIDADE ADJUDICANTE\nDesignação da entidade adjudicante: Câmara Municipal de Palmela\nNIPC: 506187543\nEndereço: Largo Município , Palmela\nCódigo postal: 2954-001\nLocalidade: Setúbal\nPaís: Portugal\nNUT III: PT170\nDistrito: Setúbal\nConcelho: Palmela\nFreguesia: Freguesia de Palmela\nTelefone: 212 336 600\nFax: 212 336 619\nEndereço da Entidade (URL): www.cm-palmela.pt\nEndereço Eletrónico: geral@cm-palmela.pt\neDelivery Gateway (URL): https://community.vortal.biz/public/\nFunção da Organização: Adquirente\nNorma jurídica da Entidade Adjudicante: Organismo de direito público\nÁrea de atividade da Autoridade Adjudicante: Serviços públicos das administrações públicas\n\n2 - JORNAL OFICIAL DA UNIÃO EUROPEIA\nO procedimento a que este anúncio diz respeito também é publicitado no Jornal Oficial da União Europeia? Não\n\n3 - AVISO\nModelo de Anúncio: Concurso público\nData de Envio do Anúncio: 31-07-2025\n\n5 - PROCESSO\nTipo de Procedimento: Concurso público\nPreço base do procedimento: Sim\nValor do preço base do procedimento: 135.500,00 EUR\nProcedimento com lotes? Não\n\n6 - OBJETO DO CONTRATO\nNúmero de referência interna: 5033/2025\nDesignação do contrato: Empreitada de Requalificação da UCSP de Águas de Moura\nDescrição: Empreitada de Requalificação da UCSP de Águas de Moura - Os trabalhos a realizar englobam essencialmente trabalhos de beneficiação e reforço do isolamento térmico das fachadas com sistema ETICS, pintura integral de paredes e tetos interiores, reforço do isolamento da laje de esteira da cobertura com lã de rocha, revisão das coberturas, limpeza de caleiras e substituição dos órgãos de apoio à drenagem de águas pluviais.\nTipo de Contrato Principal: Empreitada de Obras Públicas\nTipo de Contrato: Empreitada de Obras Públicas\nClassificação CPV (Vocabulário Comum para os Contratos Públicos)\nObjeto principal\nVocabulário Principal: 45200000\nPreço base s/IVA: 135.500,00 EUR\n\n7 - INDICAÇÕES ADICIONAIS\nO contrato envolve aquisição conjunta (satisfação de várias entidades)? Não\nO contrato é adjudicado por uma central de compras? Não\n\n8 - TÉCNICAS\nO concurso destina-se à celebração de um acordo-quadro? Inexistência de acordo-quadro\nÉ utilizado um leilão eletrónico? Não\nÉ adotada uma fase de negociação? Não\nSistema de Aquisição Dinâmico: Inexistência de sistema de aquisição dinâmico\n\n9 - LOCAL DA EXECUÇÃO DO CONTRATO\nLOCAL DA EXECUÇÃO DO CONTRATO (PROCEDIMENTO)\nPaís: Portugal\nNUT III: PT170\nLocalidade: Setúbal\nDistrito: Setúbal\nConcelho: Palmela\nFreguesia: União das Freguesias de Poceirão e Marateca\n\n10 - PRAZO DE EXECUÇÃO DO CONTRATO\nPrazo de execução do contrato: 60 DIAS\nPrevisão de renovações: Não\n\n11 - FUNDOS EU\nTêm fundos EU? Sim\n\n12 - DOCUMENTOS DE HABILITAÇÃO\nHabilitação para o exercício da atividade profissional: Sim\nTipo: Alvará\nDescrição: Alvarás nos termos das peças do procedimento\n\n13 - CONDIÇÕES DE APRESENTAÇÃO\nPlataforma eletrónica utilizada pela entidade adjudicante: VORTAL\nURL para Apresentação: https://community.vortal.biz/public/\nAdmissibilidade da apresentação de propostas variantes: Não autorizado\nPrazo para apresentação das propostas: 15-08-2025 23:59\nPrazo durante o qual os concorrentes são obrigados a manter as respetivas propostas: 120 dias a contar do termo do prazo para a apresentação das propostas\nIndicação de Subcontratação na Proposta: Inexistência de indicação de subcontratação\n\n14 - PRESTAÇÃO DE CAUÇÃO\nPrestação de caução: Não\n\n15 - FORNECIMENTO DAS PEÇAS DO CONCURSO, APRESENTAÇÃO DE PEDIDOS DE PARTICIPAÇÃO E APRESENTAÇÃO DAS PROPOSTAS\nLink para acesso às peças do concurso (URL): https://community.vortal.biz/Public/public-tender-documents/Y1FkUXJvZGJoK1loUk1JU09zL2U5dy9Jc0JWQm9QbzMwSCtyK2FpNGVibEdSZ2ZqamFBMjhqRmVCWWNEb2twVHF3M0Zsbzh1WFliNHBabmZHUml1TXc9PWpHdypr\n\n20 - OUTROS REQUISITOS\nInformação sobre contratos reservados. Aplica-se a contratos reservados (54º-A)? Não\n\n21 - CRITÉRIO DE ADJUDICAÇÃO\nMultifator: Não\nMonofator:\nNome: Outros\nOutro nome: Preço\n\n24 - CONDIÇÕES DO CONTRATO\nFaturação Eletrónica: Permitido\nObrigação de Subcontratação:\nCódigo da Obrigação de Subcontratação: Não é aplicável nenhuma obrigação de subcontratação.\n\n25 - COMPRA PÚBLICA ESTRATÉGICA\nCompra Pública Estratégica: Inexistência de contratação pública estratégica\n\n26 - INFORMAÇÕES ADICIONAIS\nContrato adequado para PME: Sim\nCobertura ACP (Acordo dos Contratos Públicos da Organização Mundial do Comércio): Não\n\n27 - IDENTIFICAÇÃO E CONTACTOS DO ÓRGÃO DE RECURSOS ADMINISTRATIVOS\nDesignação: Município de Palmela\nEndereço: Largo do Município\nCódigo postal: 2954-001\nLocalidade: Palmela\nTelefone: +351 0351212336670\nFax: +351 0351212336671\nEndereço eletrónico: depop@cm-palmela.pt\n\n28 - IDENTIFICAÇÃO DO(S) AUTOR(ES) DE ANÚNCIO\nNome: Álvaro Amaro\nCargo: Presidente da Câmara Municipal de Palmela\n419362162",
    "nipc": "506187543",
    "distrito": "Setúbal",
    "concelho": "Palmela",
    "freguesia": "Freguesia de Palmela",
    "site": "www.cm-palmela.pt",
    "email": "geral@cm-palmela.pt",
    "designacao_contrato": "Empreitada de Requalificação da UCSP de Águas de Moura",
    "descricao": "Empreitada de Requalificação da UCSP de Águas de Moura - Os trabalhos a realizar englobam essencialmente trabalhos de beneficiação e reforço do isolamento térmico das fachadas com sistema ETICS, pintura integral de paredes e tetos interiores, reforço do isolamento da laje de esteira da cobertura com lã de rocha, revisão das coberturas, limpeza de caleiras e substituição dos órgãos de apoio à drenagem de águas pluviais.",
    "preco_base": "135.500,00 EUR",
    "prazo_execucao": "60 DIAS",
    "prazo_apresentacao_propostas": "15-08-2025 23:59",
    "fundos_eu": "Sim",
    "plataforma_eletronica": "VORTAL",
    "url_procedimento": "https://community.vortal.biz/public/",
    "autor_nome": "Álvaro Amaro",
    "autor_cargo": "Presidente da Câmara Municipal de Palmela"
  },
  {
    "numero_procedimento": "N/A",
    "entidade": "IPO Porto FG, EPE",
    "link": "https://diariodarepublica.pt/dr/detalhe/contrato-publico/20670-927474295",
    "detalhes_completos": "1 - IDENTIFICAÇÃO E CONTACTOS DA ENTIDADE ADJUDICANTE\nDesignação da entidade adjudicante: IPO Porto FG, EPE\nNIPC: 506362299\nEndereço: Rua Drº António Bernardino De Almeida S/N, Porto\nCódigo postal: 4200-072\nLocalidade: Área Metropolitana do Porto\nPaís: Portugal\nNUT III: PT11A\nDistrito: Porto\nConcelho: Porto\nFreguesia: Todas\nTelefone: 225084000\nFax: 225084001\nEndereço da Entidade (URL): http://www.ipoporto.pt/\nEndereço Eletrónico: compras@ipoporto.min-saude.pt\neDelivery Gateway (URL): https://community.vortal.biz/public/\nFunção da Organização: Adquirente\nNorma jurídica da Entidade Adjudicante: Organismo de direito público\nÁrea de atividade da Autoridade Adjudicante: Saúde\n\n2 - JORNAL OFICIAL DA UNIÃO EUROPEIA\nO procedimento a que este anúncio diz respeito também é publicitado no Jornal Oficial da União Europeia? Não\n\n3 - AVISO\nModelo de Anúncio: Concurso público\nData de Envio do Anúncio: 31-07-2025\n\n5 - PROCESSO\nTipo de Procedimento: Concurso público\nPreço base do procedimento: Sim\nValor do preço base do procedimento: 53.437,27 EUR\nProcedimento com lotes? Sim\nNº Máx. de Lotes Autorizado: 12\nNúmero máximo de lotes que podem ser adjudicados a um concorrente: 12\n\n6 - OBJETO DO CONTRATO\nNúmero de referência interna: CP 1660/25\nDesignação do contrato: CP 1660/25 - Aquisição de detergentes e desinfetantes para o Serviço Central de Esterilização para 2025\nDescrição: CP 1660/25 - Aquisição de detergentes e desinfetantes para o Serviço Central de Esterilização para 2025\nTipo de Contrato Principal: Aquisição de Bens Móveis\nTipo de Contrato: Aquisição de Bens Móveis\nClassificação CPV (Vocabulário Comum para os Contratos Públicos)\nObjeto principal\nVocabulário Principal: 24455000\nPreço base s/IVA: 53.437,27 EUR\nLotes: \nNº: LOT-0001\nDescrição do Lote: Lote 1\nPreço base s/IVA: 7.134,00 EUR\nClassificação CPV (Vocabulário Comum para os Contratos Públicos)\nObjeto principal\nVocabulário Principal: 24455000\nNº: LOT-0002\nDescrição do Lote: Lote 2\nPreço base s/IVA: 6.264,00 EUR\nClassificação CPV (Vocabulário Comum para os Contratos Públicos)\nObjeto principal\nVocabulário Principal: 24455000\nNº: LOT-0003\nDescrição do Lote: Lote 3\nPreço base s/IVA: 2.723,40 EUR\nClassificação CPV (Vocabulário Comum para os Contratos Públicos)\nObjeto principal\nVocabulário Principal: 24455000\nNº: LOT-0004\nDescrição do Lote: Lote 4\nPreço base s/IVA: 4.270,80 EUR\nClassificação CPV (Vocabulário Comum para os Contratos Públicos)\nObjeto principal\nVocabulário Principal: 24455000\nNº: LOT-0005\nDescrição do Lote: Lote 5\nPreço base s/IVA: 1.162,44 EUR\nClassificação CPV (Vocabulário Comum para os Contratos Públicos)\nObjeto principal\nVocabulário Principal: 24455000\nNº: LOT-0006\nDescrição do Lote: Lote 6\nPreço base s/IVA: 2.274,00 EUR\nClassificação CPV (Vocabulário Comum para os Contratos Públicos)\nObjeto principal\nVocabulário Principal: 24455000\nNº: LOT-0007\nDescrição do Lote: Lote 7\nPreço base s/IVA: 2.500,30 EUR\nClassificação CPV (Vocabulário Comum para os Contratos Públicos)\nObjeto principal\nVocabulário Principal: 24455000\nNº: LOT-0008\nDescrição do Lote: Lote 8\nPreço base s/IVA: 5.402,16 EUR\nClassificação CPV (Vocabulário Comum para os Contratos Públicos)\nObjeto principal\nVocabulário Principal: 24455000\nNº: LOT-0009\nDescrição do Lote: Lote 9\nPreço base s/IVA: 1.853,28 EUR\nClassificação CPV (Vocabulário Comum para os Contratos Públicos)\nObjeto principal\nVocabulário Principal: 24455000\nNº: LOT-0010\nDescrição do Lote: Lote 10\nPreço base s/IVA: 333,00 EUR\nClassificação CPV (Vocabulário Comum para os Contratos Públicos)\nObjeto principal\nVocabulário Principal: 24455000\nNº: LOT-0011\nDescrição do Lote: Lote 11\nPreço base s/IVA: 19.450,00 EUR\nClassificação CPV (Vocabulário Comum para os Contratos Públicos)\nObjeto principal\nVocabulário Principal: 24455000\nNº: LOT-0012\nDescrição do Lote: Lote 12\nPreço base s/IVA: 69,89 EUR\nClassificação CPV (Vocabulário Comum para os Contratos Públicos)\nObjeto principal\nVocabulário Principal: 24455000\n\n7 - INDICAÇÕES ADICIONAIS\nO contrato envolve aquisição conjunta (satisfação de várias entidades)? Não\nO contrato é adjudicado por uma central de compras? Não\n\n8 - TÉCNICAS\nO concurso destina-se à celebração de um acordo-quadro? Inexistência de acordo-quadro\nÉ utilizado um leilão eletrónico? Não\nÉ adotada uma fase de negociação? Não\nSistema de Aquisição Dinâmico: Inexistência de sistema de aquisição dinâmico\n\n9 - LOCAL DA EXECUÇÃO DO CONTRATO\nLOCAL DA EXECUÇÃO DO CONTRATO (PROCEDIMENTO)\nPaís: Portugal\nNUT III: PT11A\nLocalidade: Área Metropolitana do Porto\nDistrito: Porto\nConcelho: Porto\nFreguesia: Freguesia de Paranhos - Porto\nLOCAL DA EXECUÇÃO DO CONTRATO (LOTE)\nIdentificador do Lote: LOT-0001; LOT-0002; LOT-0003; LOT-0004; LOT-0005; LOT-0006; LOT-0007; LOT-0008; LOT-0009; LOT-0010; LOT-0011; LOT-0012\nPaís: Portugal\nNUT III: PT11A\nLocalidade: Área Metropolitana do Porto\nDistrito: Porto\nConcelho: Porto\nFreguesia: Freguesia de Paranhos - Porto\n\n10 - PRAZO DE EXECUÇÃO DO CONTRATO\nIdentificador do Lote: LOT-0001; LOT-0002; LOT-0003; LOT-0004; LOT-0005; LOT-0006; LOT-0007; LOT-0008; LOT-0009; LOT-0010; LOT-0011; LOT-0012\nPrazo de execução do contrato: 120 DIAS\nPrevisão de renovações: Não\n\n11 - FUNDOS EU\nIdentificador do Lote: LOT-0001; LOT-0002; LOT-0003; LOT-0004; LOT-0005; LOT-0006; LOT-0007; LOT-0008; LOT-0009; LOT-0010; LOT-0011; LOT-0012\nTêm fundos EU? Não\n\n12 - DOCUMENTOS DE HABILITAÇÃO\nHabilitação para o exercício da atividade profissional: Não\n\n13 - CONDIÇÕES DE APRESENTAÇÃO\nPlataforma eletrónica utilizada pela entidade adjudicante: VORTAL\nURL para Apresentação: https://community.vortal.biz/public/\nAdmissibilidade da apresentação de propostas variantes: Não autorizado\nPrazo para apresentação das propostas: 15-08-2025 17:00\nPrazo durante o qual os concorrentes são obrigados a manter as respetivas propostas: 155 dias a contar do termo do prazo para a apresentação das propostas\nIndicação de Subcontratação na Proposta: Inexistência de indicação de subcontratação\n\n14 - PRESTAÇÃO DE CAUÇÃO\nPrestação de caução: Não\n\n15 - FORNECIMENTO DAS PEÇAS DO CONCURSO, APRESENTAÇÃO DE PEDIDOS DE PARTICIPAÇÃO E APRESENTAÇÃO DAS PROPOSTAS\nLink para acesso às peças do concurso (URL): https://community.vortal.biz/Public/public-tender-documents/eFdiaGxCMGFmQWhGNFkyTWljMFBYUWlTQURiWUFFQ0hXZE80V1BrdTc4cGUwTks1OWdOeWx6LzNEcXJ1ZVBIbXk0YkhWbWpIcW1pQk4vQnJuNkFqelE9PTRpJDBo\n\n20 - OUTROS REQUISITOS\nIdentificador do Lote: LOT-0001; LOT-0002; LOT-0003; LOT-0004; LOT-0005; LOT-0006; LOT-0007; LOT-0008; LOT-0009; LOT-0010; LOT-0011; LOT-0012\nInformação sobre contratos reservados. Aplica-se a contratos reservados (54º-A)? Não\n\n21 - CRITÉRIO DE ADJUDICAÇÃO\nO Critério de adjudicação é diferenciado por lote? Não\nMultifator: Sim\nFator: \nNome: Qualidade\nPonderação: 40%\nSubfatores: Não\nFator: \nNome: Qualidade\nPonderação: 60%\nSubfatores: Não\n\n24 - CONDIÇÕES DO CONTRATO\nIdentificador do Lote: LOT-0001; LOT-0002; LOT-0003; LOT-0004; LOT-0005; LOT-0006; LOT-0007; LOT-0008; LOT-0009; LOT-0010; LOT-0011; LOT-0012\nFaturação Eletrónica: Permitido\nObrigação de Subcontratação:\nCódigo da Obrigação de Subcontratação: Não é aplicável nenhuma obrigação de subcontratação.\n\n25 - COMPRA PÚBLICA ESTRATÉGICA\nCompra Pública Estratégica: Inexistência de contratação pública estratégica\n\n26 - INFORMAÇÕES ADICIONAIS\nIdentificador do Lote: LOT-0001; LOT-0002; LOT-0003; LOT-0004; LOT-0005; LOT-0006; LOT-0007; LOT-0008; LOT-0009; LOT-0010; LOT-0011; LOT-0012\nContrato adequado para PME: Sim\nCobertura ACP (Acordo dos Contratos Públicos da Organização Mundial do Comércio): Não\n\n27 - IDENTIFICAÇÃO E CONTACTOS DO ÓRGÃO DE RECURSOS ADMINISTRATIVOS\nDesignação: Conselho de Administração\nEndereço: Rua Dr António Bernardino de Almeida\nCódigo postal: 4200-072\nLocalidade: Porto\nTelefone: +351 225084000\nFax: +351 225084001\nEndereço eletrónico: compras@ipoporto.min-saude.pt\n\n28 - IDENTIFICAÇÃO DO(S) AUTOR(ES) DE ANÚNCIO\nNome: Sandra Luís\nCargo: Diretora do serviço de Aprovisionamento e Logística\n419378647",
    "nipc": "506362299",
    "distrito": "Porto",
    "concelho": "Porto",
    "freguesia": "Todas",
    "site": "http://www.ipoporto.pt/",
    "email": "compras@ipoporto.min-saude.pt",
    "designacao_contrato": "CP 1660/25 - Aquisição de detergentes e desinfetantes para o Serviço Central de Esterilização para 2025",
    "descricao": "CP 1660/25 - Aquisição de detergentes e desinfetantes para o Serviço Central de Esterilização para 2025",
    "preco_base": "53.437,27 EUR",
    "prazo_execucao": "120 DIAS",
    "prazo_apresentacao_propostas": "15-08-2025 17:00",
    "fundos_eu": "Não",
    "plataforma_eletronica": "VORTAL",
    "url_procedimento": "https://community.vortal.biz/public/",
    "autor_nome": "Sandra Luís",
    "autor_cargo": "Diretora do serviço de Aprovisionamento e Logística"
  },
  {
    "numero_procedimento": "N/A",
    "entidade": "Instituto Hidrográfico",
    "link": "https://diariodarepublica.pt/dr/detalhe/contrato-publico/20671-927474296",
    "detalhes_completos": "1 - IDENTIFICAÇÃO E CONTACTOS DA ENTIDADE ADJUDICANTE\nDesignação da entidade adjudicante: Instituto Hidrográfico\nNIPC: 501494170\nServiço/Órgão/Pessoa de contacto: CFR AN Paulo Martins Gonçalves\nEndereço: Rua das Trinas, n.º 49\nCódigo postal: 1249-093\nLocalidade: Lisboa\nPaís: Portugal\nNUT III: PT170\nDistrito: Lisboa\nConcelho: Lisboa\nFreguesia: Freguesia da Estrela\nTelefone: 210943270\nFax: 210943277\nEndereço da Entidade (URL): www.hidrografico.pt\nEndereço Eletrónico: administrativo@hidrografico.pt\neDelivery Gateway (URL): https://www.acingov.pt\nFunção da Organização: Adquirente\nNorma jurídica da Entidade Adjudicante: Organismo de direito público\nÁrea de atividade da Autoridade Adjudicante: Serviços públicos das administrações públicas\n\n2 - JORNAL OFICIAL DA UNIÃO EUROPEIA\nO procedimento a que este anúncio diz respeito também é publicitado no Jornal Oficial da União Europeia? Não\n\n3 - AVISO\nModelo de Anúncio: Concurso público\nData de Envio do Anúncio: 31-07-2025\n\n5 - PROCESSO\nTipo de Procedimento: Concurso público\nPreço base do procedimento: Sim\nValor do preço base do procedimento: 30.000,00 EUR\nProcedimento com lotes? Não\n\n6 - OBJETO DO CONTRATO\nNúmero de referência interna: 403/IT/2025\nDesignação do contrato: Aquisição de Quadro Geral de Baixa Potência para a Base Hidrográfica da Azinheira\nDescrição: Aquisição de Quadro Geral de Baixa Potência para a Base Hidrográfica da Azinheira\nTipo de Contrato Principal: Aquisição de Bens Móveis\nTipo de Contrato: Aquisição de Bens Móveis\nClassificação CPV (Vocabulário Comum para os Contratos Públicos)\nObjeto principal\nVocabulário Principal: 31214500\nPreço base s/IVA: 30.000,00 EUR\n\n7 - INDICAÇÕES ADICIONAIS\nO contrato envolve aquisição conjunta (satisfação de várias entidades)? Não\nO contrato é adjudicado por uma central de compras? Não\n\n8 - TÉCNICAS\nO concurso destina-se à celebração de um acordo-quadro? Inexistência de acordo-quadro\nÉ utilizado um leilão eletrónico? Não\nÉ adotada uma fase de negociação? Não\nSistema de Aquisição Dinâmico: Inexistência de sistema de aquisição dinâmico\n\n9 - LOCAL DA EXECUÇÃO DO CONTRATO\nLOCAL DA EXECUÇÃO DO CONTRATO (PROCEDIMENTO)\nPaís: Portugal\nNUT III: PT170\nLocalidade: Freguesia da Estrela\nDistrito: Lisboa\nConcelho: Lisboa\nFreguesia: Freguesia da Estrela\n\n10 - PRAZO DE EXECUÇÃO DO CONTRATO\nPrazo de execução do contrato: 120 DIAS\nPrevisão de renovações: Não\n\n11 - FUNDOS EU\nTêm fundos EU? Não\n\n12 - DOCUMENTOS DE HABILITAÇÃO\nHabilitação para o exercício da atividade profissional: Não\n\n13 - CONDIÇÕES DE APRESENTAÇÃO\nPlataforma eletrónica utilizada pela entidade adjudicante: ACIN\nURL para Apresentação: https://www.acingov.pt\nAdmissibilidade da apresentação de propostas variantes: Não autorizado\nPrazo para apresentação das propostas: 10-08-2025 23:59\nPrazo durante o qual os concorrentes são obrigados a manter as respetivas propostas: 66 dias a contar do termo do prazo para a apresentação das propostas\nIndicação de Subcontratação na Proposta: Inexistência de indicação de subcontratação\n\n14 - PRESTAÇÃO DE CAUÇÃO\nPrestação de caução: Não\n\n15 - FORNECIMENTO DAS PEÇAS DO CONCURSO, APRESENTAÇÃO DE PEDIDOS DE PARTICIPAÇÃO E APRESENTAÇÃO DAS PROPOSTAS\nLink para acesso às peças do concurso (URL): https://www.acingov.pt/acingovprod/2/zonaPublica/zona_publica_c/donwloadProcedurePiece/OTE3MDk5\n\n20 - OUTROS REQUISITOS\nInformação sobre contratos reservados. Aplica-se a contratos reservados (54º-A)? Não\n\n21 - CRITÉRIO DE ADJUDICAÇÃO\nMultifator: Não\nMonofator:\nNome: Preço\n\n24 - CONDIÇÕES DO CONTRATO\nFaturação Eletrónica: Permitido\nObrigação de Subcontratação:\nCódigo da Obrigação de Subcontratação: Não é aplicável nenhuma obrigação de subcontratação.\n\n25 - COMPRA PÚBLICA ESTRATÉGICA\nCompra Pública Estratégica: Inexistência de contratação pública estratégica\n\n26 - INFORMAÇÕES ADICIONAIS\nContrato adequado para PME: Não\nCobertura ACP (Acordo dos Contratos Públicos da Organização Mundial do Comércio): Não\n\n27 - IDENTIFICAÇÃO E CONTACTOS DO ÓRGÃO DE RECURSOS ADMINISTRATIVOS\nDesignação: Contra-Almirante João Paulo Ramalho Marreiros\nEndereço: Rua das Trinas, n.º 49\nCódigo postal: 1249-093\nLocalidade: Lisboa\nTelefone: 210943278\nFax: \nEndereço eletrónico: administrativo@hidrografico.pt\n\n28 - IDENTIFICAÇÃO DO(S) AUTOR(ES) DE ANÚNCIO\nNome: Paulo Martins Gonçalves\nCargo: Diretor Financeiro do Instituto Hidrográfico\n419384243",
    "nipc": "501494170",
    "distrito": "Lisboa",
    "concelho": "Lisboa",
    "freguesia": "Freguesia da Estrela",
    "site": "www.hidrografico.pt",
    "email": "administrativo@hidrografico.pt",
    "designacao_contrato": "Aquisição de Quadro Geral de Baixa Potência para a Base Hidrográfica da Azinheira",
    "descricao": "Aquisição de Quadro Geral de Baixa Potência para a Base Hidrográfica da Azinheira",
    "preco_base": "30.000,00 EUR",
    "prazo_execucao": "120 DIAS",
    "prazo_apresentacao_propostas": "10-08-2025 23:59",
    "fundos_eu": "Não",
    "plataforma_eletronica": "ACIN",
    "url_procedimento": "https://www.acingov.pt",
    "autor_nome": "Paulo Martins Gonçalves",
    "autor_cargo": "Diretor Financeiro do Instituto Hidrográfico"
  },
  {
    "numero_procedimento": "N/A",
    "entidade": "AC, Águas de Coimbra, EM",
    "link": "https://diariodarepublica.pt/dr/detalhe/contrato-publico/20672-927474297",
    "detalhes_completos": "1 - IDENTIFICAÇÃO E CONTACTOS DA ENTIDADE ADJUDICANTE\nDesignação da entidade adjudicante: AC, Águas de Coimbra, EM\nNIPC: 506566307\nEndereço: Rua da Alegria nº 111\nCódigo postal: 3000-018\nLocalidade: Coimbra\nPaís: Portugal\nNUT III: PT16E\nDistrito: Coimbra\nConcelho: Coimbra\nFreguesia: União das Freguesias de Coimbra (Sé Nova, Santa Cruz, Almedina e São Bartolomeu)\nTelefone: 239096000\nFax: 239096082\nEndereço da Entidade (URL): www.aguasdecoimbra.pt\nEndereço Eletrónico: geral@aguasdecoimbra.pt\nFunção da Organização: Adquirente\nNorma jurídica da Entidade Adjudicante: Organismo de direito público, controlado por uma autoridade local\nÁrea de atividade da Entidade Adjudicante: Atividades relacionadas com a água\n\n2 - JORNAL OFICIAL DA UNIÃO EUROPEIA\nO procedimento a que este anúncio diz respeito também é publicitado no Jornal Oficial da União Europeia? Não\n\n3 - AVISO\nModelo de Anúncio: Concurso público\nData de Envio do Anúncio: 31-07-2025\n\n5 - PROCESSO\nTipo de Procedimento: Concurso público\nPreço base do procedimento: Sim\nValor do preço base do procedimento: 275.000,00 EUR\nProcedimento com lotes? Não\n\n6 - OBJETO DO CONTRATO\nNúmero de referência interna: CP-14B-2025\nDesignação do contrato: CP-14B-2025-CONSTRUÇÃO DAS REDES DE DRENAGEM DE ÁGUAS RESIDUAIS E REMODELAÇÃO DA REDE DE ABASTECIMENTO DE ÁGUA NO BECO DO OLHEIRO - ADÉMIA\nDescrição: Construção das redes de drenagem de águas residuais e remodelação da rede de abastecimento de água no beco do Olheiro - Adémia\nTipo de Contrato Principal: Empreitada de Obras Públicas\nTipo de Contrato: Empreitada de Obras Públicas\nClassificação CPV (Vocabulário Comum para os Contratos Públicos)\nObjeto principal\nVocabulário Principal: 45232130\nPreço base s/IVA: 275.000,00 EUR\n\n7 - INDICAÇÕES ADICIONAIS\nO contrato envolve aquisição conjunta (satisfação de várias entidades)? Não\nO contrato é adjudicado por uma central de compras? Não\n\n8 - TÉCNICAS\nO concurso destina-se à celebração de um acordo-quadro? Inexistência de acordo-quadro\nÉ utilizado um leilão eletrónico? Não\nÉ adotada uma fase de negociação? Não\nSistema de Aquisição Dinâmico: Inexistência de sistema de aquisição dinâmico\n\n9 - LOCAL DA EXECUÇÃO DO CONTRATO\nLOCAL DA EXECUÇÃO DO CONTRATO (PROCEDIMENTO)\nPaís: Portugal\nNUT III: PT16E\nLocalidade: Beco do Olheiro - Adémia\nDistrito: Coimbra\nConcelho: Coimbra\nFreguesia: União das Freguesias de Trouxemil e Torre de Vilela\n\n10 - PRAZO DE EXECUÇÃO DO CONTRATO\nPrazo de execução do contrato: 160 DIAS\nPrevisão de renovações: Não\n\n11 - FUNDOS EU\nTêm fundos EU? Não\n\n12 - DOCUMENTOS DE HABILITAÇÃO\nHabilitação para o exercício da atividade profissional: Sim\nTipo: Alvará\nDescrição: 6ª subcategoria da 2ª categoria e da classe correspondente ao valor global da proposta.\n\n13 - CONDIÇÕES DE APRESENTAÇÃO\nPlataforma eletrónica utilizada pela entidade adjudicante: ANOGOV\nURL para Apresentação: https://www.anogov.com/em-aguasdecoimbra/faces/\nAdmissibilidade da apresentação de propostas variantes: Não autorizado\nPrazo para apresentação das propostas: 18-08-2025 23:59\nPrazo durante o qual os concorrentes são obrigados a manter as respetivas propostas: 90 dias a contar do termo do prazo para a apresentação das propostas\nApresentação de Catálogo Eletrónico: Permitido\nIndicação de Subcontratação na Proposta: O(s) subcontratante(s) proposto(s) necessário(s) para cumprir a obrigação de subcontratar uma percentagem mínima do contrato\n\n14 - PRESTAÇÃO DE CAUÇÃO\nPrestação de caução: Sim\nPercentagem: 5%\nDescrição da Garantia Exigida: Depósito em dinheiro ou em títulos emitidos ou garantidos pelo Estado ou mediante garantia bancária, ou seguro caução\n\n15 - FORNECIMENTO DAS PEÇAS DO CONCURSO, APRESENTAÇÃO DE PEDIDOS DE PARTICIPAÇÃO E APRESENTAÇÃO DAS PROPOSTAS\nLink para acesso às peças do concurso (URL): https://www.anogov.com/em-aguasdecoimbra/faces/app/acessoDocs.jsp?codigoAcesso=2UXLp4eIoO6jbImkQKdadOQZS8vLr1Q5Vw2fExGlL6YZq68TXX\n\n20 - OUTROS REQUISITOS\nInformação sobre contratos reservados. Aplica-se a contratos reservados (54º-A)? Não\n\n21 - CRITÉRIO DE ADJUDICAÇÃO\nMultifator: Sim\nFator: \nNome: Outros\nOutro Nome: Valia técnica da proposta\nPonderação: 40%\nSubfatores: Não\nFator: \nNome: Preço\nPonderação: 60%\nSubfatores: Não\n\n24 - CONDIÇÕES DO CONTRATO\nFaturação Eletrónica: Permitido\nObrigação de Subcontratação:\nCódigo da Obrigação de Subcontratação: Não é aplicável nenhuma obrigação de subcontratação.\n\n25 - COMPRA PÚBLICA ESTRATÉGICA\nCompra Pública Estratégica: Inexistência de contratação pública estratégica\n\n26 - INFORMAÇÕES ADICIONAIS\nContrato adequado para PME: Não\nCobertura ACP (Acordo dos Contratos Públicos da Organização Mundial do Comércio): Não\n\n27 - IDENTIFICAÇÃO E CONTACTOS DO ÓRGÃO DE RECURSOS ADMINISTRATIVOS\nDesignação: Conselho de Administração da AC, Águas de Coimbra, EM\nEndereço: Rua da Alegria, n.º 111\nCódigo postal: 3000-018\nLocalidade: Coimbra\nEndereço eletrónico: geral@aguasdecoimbra.pt\nPrazo de interposição do recurso: 5 dias\n\n28 - IDENTIFICAÇÃO DO(S) AUTOR(ES) DE ANÚNCIO\nNome: José Alfeu Almeida de Sá Marques\nCargo: Presidente do Conselho de Administração\n419372344",
    "nipc": "506566307",
    "distrito": "Coimbra",
    "concelho": "Coimbra",
    "freguesia": "União das Freguesias de Coimbra (Sé Nova, Santa Cruz, Almedina e São Bartolomeu)",
    "site": "www.aguasdecoimbra.pt",
    "email": "geral@aguasdecoimbra.pt",
    "designacao_contrato": "CP-14B-2025-CONSTRUÇÃO DAS REDES DE DRENAGEM DE ÁGUAS RESIDUAIS E REMODELAÇÃO DA REDE DE ABASTECIMENTO DE ÁGUA NO BECO DO OLHEIRO - ADÉMIA",
    "descricao": "Construção das redes de drenagem de águas residuais e remodelação da rede de abastecimento de água no beco do Olheiro - Adémia",
    "preco_base": "275.000,00 EUR",
    "prazo_execucao": "160 DIAS",
    "prazo_apresentacao_propostas": "18-08-2025 23:59",
    "fundos_eu": "Não",
    "plataforma_eletronica": "ANOGOV",
    "url_procedimento": "https://www.anogov.com/em-aguasdecoimbra/faces/",
    "autor_nome": "José Alfeu Almeida de Sá Marques",
    "autor_cargo": "Presidente do Conselho de Administração"
  },
  {
    "numero_procedimento": "N/A",
    "entidade": "AC, Águas de Coimbra, EM",
    "link": "https://diariodarepublica.pt/dr/detalhe/contrato-publico/20673-927474298",
    "detalhes_completos": "1 - IDENTIFICAÇÃO E CONTACTOS DA ENTIDADE ADJUDICANTE\nDesignação da entidade adjudicante: AC, Águas de Coimbra, EM\nNIPC: 506566307\nEndereço: Rua da Alegria nº 111\nCódigo postal: 3000-018\nLocalidade: Coimbra\nPaís: Portugal\nNUT III: PT16E\nDistrito: Coimbra\nConcelho: Coimbra\nFreguesia: União das Freguesias de Coimbra (Sé Nova, Santa Cruz, Almedina e São Bartolomeu)\nTelefone: 239096000\nFax: 239096082\nEndereço da Entidade (URL): www.aguasdecoimbra.pt\nEndereço Eletrónico: geral@aguasdecoimbra.pt\nFunção da Organização: Adquirente\nNorma jurídica da Entidade Adjudicante: Organismo de direito público, controlado por uma autoridade local\nÁrea de atividade da Entidade Adjudicante: Atividades relacionadas com a água\n\n2 - JORNAL OFICIAL DA UNIÃO EUROPEIA\nO procedimento a que este anúncio diz respeito também é publicitado no Jornal Oficial da União Europeia? Não\n\n3 - AVISO\nModelo de Anúncio: Concurso público\nData de Envio do Anúncio: 31-07-2025\n\n5 - PROCESSO\nTipo de Procedimento: Concurso público\nPreço base do procedimento: Sim\nValor do preço base do procedimento: 32.000,00 EUR\nProcedimento com lotes? Não\n\n6 - OBJETO DO CONTRATO\nNúmero de referência interna: CP-17-2025\nDesignação do contrato: CP-17-2025-AQUISIÇÃO DE SERVIÇO DE APLICAÇÃO DE ESCADAS EM CÉLULAS DE ÁGUA POTÁVEL\nDescrição: Aquisição de serviço de aplicação de escadas em células de água potável\nTipo de Contrato Principal: Aquisição de Serviços\nTipo de Contrato: Aquisição de Serviços\nClassificação CPV (Vocabulário Comum para os Contratos Públicos)\nObjeto principal\nVocabulário Principal: 51511000\nPreço base s/IVA: 32.000,00 EUR\n\n7 - INDICAÇÕES ADICIONAIS\nO contrato envolve aquisição conjunta (satisfação de várias entidades)? Não\nO contrato é adjudicado por uma central de compras? Não\n\n8 - TÉCNICAS\nO concurso destina-se à celebração de um acordo-quadro? Inexistência de acordo-quadro\nÉ utilizado um leilão eletrónico? Não\nÉ adotada uma fase de negociação? Não\nSistema de Aquisição Dinâmico: Inexistência de sistema de aquisição dinâmico\n\n9 - LOCAL DA EXECUÇÃO DO CONTRATO\nLOCAL DA EXECUÇÃO DO CONTRATO (PROCEDIMENTO)\nPaís: Portugal\nNUT III: PT16E\nLocalidade: Coimbra\nDistrito: Coimbra\nConcelho: Coimbra\nFreguesia: União das Freguesias de Coimbra (Sé Nova, Santa Cruz, Almedina e São Bartolomeu)\n\n10 - PRAZO DE EXECUÇÃO DO CONTRATO\nPrazo de execução do contrato: 90 DIAS\nPrevisão de renovações: Não\n\n11 - FUNDOS EU\nTêm fundos EU? Não\n\n12 - DOCUMENTOS DE HABILITAÇÃO\nHabilitação para o exercício da atividade profissional: Não\n\n13 - CONDIÇÕES DE APRESENTAÇÃO\nPlataforma eletrónica utilizada pela entidade adjudicante: ANOGOV\nURL para Apresentação: https://www.anogov.com/em-aguasdecoimbra/faces/\nAdmissibilidade da apresentação de propostas variantes: Não autorizado\nPrazo para apresentação das propostas: 13-08-2025 23:59\nPrazo durante o qual os concorrentes são obrigados a manter as respetivas propostas: 66 dias a contar do termo do prazo para a apresentação das propostas\nApresentação de Catálogo Eletrónico: Permitido\nIndicação de Subcontratação na Proposta: O(s) subcontratante(s) proposto(s) necessário(s) para cumprir a obrigação de subcontratar uma percentagem mínima do contrato\n\n14 - PRESTAÇÃO DE CAUÇÃO\nPrestação de caução: Não\n\n15 - FORNECIMENTO DAS PEÇAS DO CONCURSO, APRESENTAÇÃO DE PEDIDOS DE PARTICIPAÇÃO E APRESENTAÇÃO DAS PROPOSTAS\nLink para acesso às peças do concurso (URL): https://www.anogov.com/em-aguasdecoimbra/faces/app/acessoDocs.jsp?codigoAcesso=3jTqACRyMfsOF5KHYmdTfZe7DETDkTSdhq3deu0tubBpwFnVx5\n\n20 - OUTROS REQUISITOS\nInformação sobre contratos reservados. Aplica-se a contratos reservados (54º-A)? Não\n\n21 - CRITÉRIO DE ADJUDICAÇÃO\nMultifator: Não\nMonofator:\nNome: Preço\n\n24 - CONDIÇÕES DO CONTRATO\nFaturação Eletrónica: Permitido\nObrigação de Subcontratação:\nCódigo da Obrigação de Subcontratação: Não é aplicável nenhuma obrigação de subcontratação.\n\n25 - COMPRA PÚBLICA ESTRATÉGICA\nCompra Pública Estratégica: Inexistência de contratação pública estratégica\n\n26 - INFORMAÇÕES ADICIONAIS\nContrato adequado para PME: Não\nCobertura ACP (Acordo dos Contratos Públicos da Organização Mundial do Comércio): Não\n\n27 - IDENTIFICAÇÃO E CONTACTOS DO ÓRGÃO DE RECURSOS ADMINISTRATIVOS\nDesignação: Conselho de Administração da AC, Águas de Coimbra, EM\nEndereço: Rua da Alegria, n.º 111\nCódigo postal: 3000-018\nLocalidade: Coimbra\nEndereço eletrónico: geral@aguasdecoimbra.pt\nPrazo de interposição do recurso: 5 dias\n\n28 - IDENTIFICAÇÃO DO(S) AUTOR(ES) DE ANÚNCIO\nNome: José Alfeu Almeida de Sá Marques\nCargo: Presidente do Conselho de Administração\n419377375",
    "nipc": "506566307",
    "distrito": "Coimbra",
    "concelho": "Coimbra",
    "freguesia": "União das Freguesias de Coimbra (Sé Nova, Santa Cruz, Almedina e São Bartolomeu)",
    "site": "www.aguasdecoimbra.pt",
    "email": "geral@aguasdecoimbra.pt",
    "designacao_contrato": "CP-17-2025-AQUISIÇÃO DE SERVIÇO DE APLICAÇÃO DE ESCADAS EM CÉLULAS DE ÁGUA POTÁVEL",
    "descricao": "Aquisição de serviço de aplicação de escadas em células de água potável",
    "preco_base": "32.000,00 EUR",
    "prazo_execucao": "90 DIAS",
    "prazo_apresentacao_propostas": "13-08-2025 23:59",
    "fundos_eu": "Não",
    "plataforma_eletronica": "ANOGOV",
    "url_procedimento": "https://www.anogov.com/em-aguasdecoimbra/faces/",
    "autor_nome": "José Alfeu Almeida de Sá Marques",
    "autor_cargo": "Presidente do Conselho de Administração"
  },
  {
    "numero_procedimento": "N/A",
    "entidade": "Instituto da Conservação da Natureza e das Florestas, I. P.",
    "link": "https://diariodarepublica.pt/dr/detalhe/contrato-publico/20674-927474299",
    "detalhes_completos": "1 - IDENTIFICAÇÃO E CONTACTOS DA ENTIDADE ADJUDICANTE\nDesignação da entidade adjudicante: Instituto da Conservação da Natureza e das Florestas, I. P.\nNIPC: 510342647\nServiço/Órgão/Pessoa de contacto: Instituto da Conservação da Natureza e das Florestas, I. P.\nEndereço: Estrada Exterior da Circunvalação, 11846\nCódigo postal: 4460-281\nLocalidade: Senhora da Hora\nPaís: Portugal\nNUT III: Todas\nDistrito: Todos\nConcelho: Todos\nFreguesia: Todas\nTelefone: 213507900\nEndereço da Entidade (URL): https://icnf.pt/\nEndereço Eletrónico: geral@icnf.pt\nFunção da Organização: Adquirente\nNorma jurídica da Entidade Adjudicante: Autoridade da administração central\nÁrea de atividade da Entidade Adjudicante: Prospeção e extração de carvão ou de outros combustíveis sólidos\n\n2 - AVISO\nData de Envio do Anúncio: 31-07-2025\n\n3 - PROCESSO\nModelo de Anúncio: Hasta pública de alienação de bens móveis\nPreço de licitação base do procedimento: Sim\nValor da licitação base do procedimento: 346.650,00 EUR\nContratação por Lotes? Não\n\n4 - OBJETO DO CONTRATO\nNúmero de referência interna: HASTA PÚBLICA N.º 02/DRCNFN/2025\nDesignação do procedimento de alienação de bens móveis: Alienação de 35 lotes de material lenhoso através de Hasta pública em leilão eletrônico\nTipo de bens: Material Lenhoso\nLegislação aplicável: CCP\nAvaliação do bem: 346.650,00 EUR\nClassificação CPV (Vocabulário Comum para os Contratos Públicos)\nObjeto: Objeto principal\nVocabulário Principal: Madeira\n\n5 - DESTINATÁRIOS\nDestinatários:  Todos os operadores com registo RIO\n\n6 - INDICAÇÕES ADICIONAIS\nReferência do Portal dos Contratos Públicos:Não aplicável\nA entidade adjudicante atua como compradora no procedimento? Sim\nÉ utilizado um leilão eletrónico?  Sim\nÉ adotada uma fase de negociação?  Não\n\n7 - CONSULTA DAS PEÇAS E OBTENÇÃO DE CÓPIAS\nLink para acesso às peças do concurso (URL):https://www.vortal.biz\n\n8 -  PEDIDOS DE ESCLARECIMENTO SOBRE AS PEÇAS DO PROCEDIMENTO\nPedidos de esclarecimento sobre as peças do procedimento: Artigo 6.º do Programa do Procedimento\n\n9 -  DOCUMENTOS DE HABILITAÇÃO\nDocumentos de habilitação: Artigo 13.º Programa do procedimento\n\n10 -  CONDIÇÕES DE PARTICIPAÇÃO\nCondições de participação: Artigo 10.º do Programa do procedimento\n\n11 - DATA, LOCAL E REGRAS ATO PÚBLICO\nData, Local e Regras do Ato Publico: Artigo 10.º do Programa do procedimento\n\n12- CONDIÇÕES DE APRESENTAÇÃO\nModo de apresentação das propostas: Plataforma\nLocal de apresentação das propostas:  Vortal\nPrazo para apresentação das propostas: 18-08-2025\nPrazo durante o qual os concorrentes são obrigados a manter as respetivas propostas: 90 dias a contar do termo do prazo para a apresentação das propostas\n\n13- CRITÉRIO DE SELEÇÃO\nApenas o valor licitado? Sim\nFator de avaliação: \nPonderação: 0\n\n14 - PRESTAÇÃO DE CAUÇÃO\nPrestação de caução: Sim\nPercentagem: 2%\n\n15 - IDENTIFICAÇÃO DO(S) AUTOR(ES) DE ANÚNCIO\nNome: Emídio Alberto Rodrigues Miranda\nCargo: Técnico Superior\n419328264",
    "nipc": "510342647",
    "distrito": "Todos",
    "concelho": "Todos",
    "freguesia": "Todas",
    "site": "https://icnf.pt/",
    "email": "geral@icnf.pt",
    "designacao_contrato": null,
    "descricao": null,
    "preco_base": null,
    "prazo_execucao": null,
    "prazo_apresentacao_propostas": "18-08-2025",
    "fundos_eu": null,
    "plataforma_eletronica": null,
    "url_procedimento": null,
    "autor_nome": null,
    "autor_cargo": "Técnico Superior"
  },
  {
    "numero_procedimento": "N/A",
    "entidade": "Grupo Desportivo de Deficientes do Centro de Medicina de Reabilitação de Alcoitão",
    "link": "https://diariodarepublica.pt/dr/detalhe/contrato-publico/20676-927474300",
    "detalhes_completos": "1 - IDENTIFICAÇÃO E CONTACTOS DA ENTIDADE ADJUDICANTE\nDesignação da entidade adjudicante: Grupo Desportivo de Deficientes do Centro de Medicina de Reabilitação de Alcoitão\nNIPC: 502588144\nServiço/Órgão/Pessoa de contacto: Direção\nEndereço: Rua Rio da Costa, 100, R/C E\nCódigo postal: 2645-221\nLocalidade: Alcabideche\nPaís: Portugal\nNUT III: PT170\nDistrito: Lisboa\nConcelho: Cascais\nFreguesia: Freguesia de Alcabideche\nTelefone: 924381696\nEndereço da Entidade (URL): https://www.facebook.com/gddalcoitao\nEndereço Eletrónico: gddalcoitao@gmail.com\neDelivery Gateway (URL): https://www.acingov.pt\nFunção da Organização: Adquirente\nSubfunção da Organização: Organização cujo orçamento é utilizado para pagar o contrato; Organização que executa o pagamento; Organização que fornece informações adicionais sobre o processo de adjudicação; Organização que fornece mais informações sobre os prazos dos procedimentos de recurso; Organização responsável pelo tratamento das propostas; Organização que recebe as propostas; Organização que trata os pedidos de participação; Organização que recebe pedidos de participação; Organização que fornece mais informações sobre os procedimentos de recurso; Organização que assina o contrato\nNorma jurídica da Entidade Adjudicante: Organismo de direito público\nÁrea de atividade da Autoridade Adjudicante: Serviços públicos das administrações públicas\n\n2 - JORNAL OFICIAL DA UNIÃO EUROPEIA\nO procedimento a que este anúncio diz respeito também é publicitado no Jornal Oficial da União Europeia? Não\n\n3 - AVISO\nModelo de Anúncio: Concurso público\nData de Envio do Anúncio: 31-07-2025\n\n5 - PROCESSO\nTipo de Procedimento: Concurso público\nPreço base do procedimento: Sim\nValor do preço base do procedimento: 123.735,64 EUR\nProcedimento com lotes? Sim\nNº Máx. de Lotes Autorizado: 2\nNúmero máximo de lotes que podem ser adjudicados a um concorrente: 2\n\n6 - OBJETO DO CONTRATO\nNúmero de referência interna: 202501\nDesignação do contrato: FORNECIMENTO DE 2 (DUAS) VIATURAS LIGEIRAS.\nDescrição: FORNECIMENTO DE 2 (DUAS) VIATURAS LIGEIRAS.\nTipo de Contrato Principal: Aquisição de Bens Móveis\nTipo de Contrato: Aquisição de Bens Móveis\nClassificação CPV (Vocabulário Comum para os Contratos Públicos)\nObjeto principal\nVocabulário Principal: 34114300\nPreço base s/IVA: 123.735,64 EUR\nLotes: \nNº: LOT-0001\nDescrição do Lote: 1 (uma) viatura ligeira de passageiros (9 lugares).\nPreço base s/IVA: 68.132,56 EUR\nClassificação CPV (Vocabulário Comum para os Contratos Públicos)\nObjeto principal\nVocabulário Principal: 34114300\nNº: LOT-0002\nDescrição do Lote: 1 (uma) viatura ligeira tipo furgão.\nPreço base s/IVA: 55.603,08 EUR\nClassificação CPV (Vocabulário Comum para os Contratos Públicos)\nObjeto principal\nVocabulário Principal: 34114300\n\n7 - INDICAÇÕES ADICIONAIS\nO contrato envolve aquisição conjunta (satisfação de várias entidades)? Não\nO contrato é adjudicado por uma central de compras? Não\n\n8 - TÉCNICAS\nO concurso destina-se à celebração de um acordo-quadro? Inexistência de acordo-quadro\nÉ utilizado um leilão eletrónico? Não\nÉ adotada uma fase de negociação? Não\nSistema de Aquisição Dinâmico: Inexistência de sistema de aquisição dinâmico\n\n9 - LOCAL DA EXECUÇÃO DO CONTRATO\nLOCAL DA EXECUÇÃO DO CONTRATO (PROCEDIMENTO)\nPaís: Portugal\nNUT III: PT111\nLocalidade: Freguesia de Alcabideche\nDistrito: Lisboa\nConcelho: Cascais\nFreguesia: Freguesia de Alcabideche\nLOCAL DA EXECUÇÃO DO CONTRATO (LOTE)\nIdentificador do Lote: LOT-0001; LOT-0002\nPaís: Portugal\nNUT III: PT111\nLocalidade: Freguesia de Alcabideche\nDistrito: Lisboa\nConcelho: Cascais\nFreguesia: Freguesia de Alcabideche\n\n10 - PRAZO DE EXECUÇÃO DO CONTRATO\nIdentificador do Lote: LOT-0001; LOT-0002\nPrazo de execução do contrato: 60 DIAS\nPrevisão de renovações: Não\n\n11 - FUNDOS EU\nIdentificador do Lote: LOT-0001; LOT-0002\nTêm fundos EU? Não\n\n12 - DOCUMENTOS DE HABILITAÇÃO\nHabilitação para o exercício da atividade profissional: Não\n\n13 - CONDIÇÕES DE APRESENTAÇÃO\nPlataforma eletrónica utilizada pela entidade adjudicante: ACIN\nURL para Apresentação: https://www.acingov.pt\nAdmissibilidade da apresentação de propostas variantes: Não autorizado\nPrazo para apresentação das propostas: 15-08-2025 23:59\nPrazo durante o qual os concorrentes são obrigados a manter as respetivas propostas: 66 dias a contar do termo do prazo para a apresentação das propostas\nIndicação de Subcontratação na Proposta: Inexistência de indicação de subcontratação\n\n14 - PRESTAÇÃO DE CAUÇÃO\nPrestação de caução: Não\n\n15 - FORNECIMENTO DAS PEÇAS DO CONCURSO, APRESENTAÇÃO DE PEDIDOS DE PARTICIPAÇÃO E APRESENTAÇÃO DAS PROPOSTAS\nLink para acesso às peças do concurso (URL): https://www.acingov.pt/acingovprod/2/zonaPublica/zona_publica_c/donwloadProcedurePiece/OTI5MjY2\n\n20 - OUTROS REQUISITOS\nIdentificador do Lote: LOT-0001; LOT-0002\nInformação sobre contratos reservados. Aplica-se a contratos reservados (54º-A)? Não\n\n21 - CRITÉRIO DE ADJUDICAÇÃO\nO Critério de adjudicação é diferenciado por lote? Não\nMultifator: Não\nMonofator:\nNome: Preço\n\n24 - CONDIÇÕES DO CONTRATO\nIdentificador do Lote: LOT-0001; LOT-0002\nFaturação Eletrónica: Permitido\nObrigação de Subcontratação:\nCódigo da Obrigação de Subcontratação: Não é aplicável nenhuma obrigação de subcontratação.\n\n25 - COMPRA PÚBLICA ESTRATÉGICA\nCompra Pública Estratégica: Inexistência de contratação pública estratégica\n\n26 - INFORMAÇÕES ADICIONAIS\nIdentificador do Lote: LOT-0001; LOT-0002\nContrato adequado para PME: Não\nCobertura ACP (Acordo dos Contratos Públicos da Organização Mundial do Comércio): Não\n\n27 - IDENTIFICAÇÃO E CONTACTOS DO ÓRGÃO DE RECURSOS ADMINISTRATIVOS\nDesignação: Direção\nEndereço: Rua Rio da Costa, 100, C/V Esq.\nCódigo postal: 2645-221\nLocalidade: Alcabideche\nTelefone: 924381696\nFax: \nEndereço eletrónico: gddalcoitao@gmail.com\nPrazo de interposição do recurso: 30 dias\n\n28 - IDENTIFICAÇÃO DO(S) AUTOR(ES) DE ANÚNCIO\nNome: Hugo Maia\nCargo: Direção\n419384405",
    "nipc": "502588144",
    "distrito": "Lisboa",
    "concelho": "Cascais",
    "freguesia": "Freguesia de Alcabideche",
    "site": "https://www.facebook.com/gddalcoitao",
    "email": "gddalcoitao@gmail.com",
    "designacao_contrato": "FORNECIMENTO DE 2 (DUAS) VIATURAS LIGEIRAS.",
    "descricao": "FORNECIMENTO DE 2 (DUAS) VIATURAS LIGEIRAS.",
    "preco_base": "123.735,64 EUR",
    "prazo_execucao": "60 DIAS",
    "prazo_apresentacao_propostas": "15-08-2025 23:59",
    "fundos_eu": "Não",
    "plataforma_eletronica": "ACIN",
    "url_procedimento": "https://www.acingov.pt",
    "autor_nome": "Hugo Maia",
    "autor_cargo": "Direção"
  },
  {
    "numero_procedimento": "N/A",
    "entidade": "EMECB - Emp. Mun.de Educação e Cultura de Barcelos",
    "link": "https://diariodarepublica.pt/dr/detalhe/contrato-publico/20677-927474301",
    "detalhes_completos": "1 - IDENTIFICAÇÃO E CONTACTOS DA ENTIDADE ADJUDICANTE\nDesignação da entidade adjudicante: EMECB - Emp. Mun.de Educação e Cultura de Barcelos\nNIPC: 504635417\nEndereço: Lug. do Barreiro - Urbanização do Sardoal-Ap. 5002\nCódigo postal: 4750-001\nLocalidade: Barcelos\nPaís: Portugal\nNUT III: PT112\nDistrito: Braga\nConcelho: Barcelos\nFreguesia: Todas\nTelefone: 253808290\nFax: 253808299\nEndereço da Entidade (URL): www.etgbarcelos.com\nEndereço Eletrónico: info@emecb.com\neDelivery Gateway (URL): https://community.vortal.biz/public/\nFunção da Organização: Adquirente\nNorma jurídica da Entidade Adjudicante: Organismo de direito público, controlado por uma autoridade local\nÁrea de atividade da Autoridade Adjudicante: Educação\n\n2 - JORNAL OFICIAL DA UNIÃO EUROPEIA\nO procedimento a que este anúncio diz respeito também é publicitado no Jornal Oficial da União Europeia? Não\n\n3 - AVISO\nModelo de Anúncio: Concurso público\nData de Envio do Anúncio: 31-07-2025\n\n5 - PROCESSO\nTipo de Procedimento: Concurso público\nPreço base do procedimento: Sim\nValor do preço base do procedimento: 138.495,42 EUR\nProcedimento com lotes? Não\n\n6 - OBJETO DO CONTRATO\nNúmero de referência interna: CPN 03/2025\nDesignação do contrato: Confeção e Fornecimento de Refeições para os alunos da ETG – Ano letivo 2025/2026\nDescrição: Confeção e Fornecimento de Refeições para os alunos da ETG – Ano letivo 2025/2026\nTipo de Contrato Principal: Aquisição de Serviços\nTipo de Contrato: Aquisição de Serviços\nClassificação CPV (Vocabulário Comum para os Contratos Públicos)\nObjeto principal\nVocabulário Principal: 55524000\nPreço base s/IVA: 138.495,42 EUR\n\n7 - INDICAÇÕES ADICIONAIS\nO contrato envolve aquisição conjunta (satisfação de várias entidades)? Não\nO contrato é adjudicado por uma central de compras? Não\n\n8 - TÉCNICAS\nO concurso destina-se à celebração de um acordo-quadro? Inexistência de acordo-quadro\nÉ utilizado um leilão eletrónico? Não\nÉ adotada uma fase de negociação? Não\nSistema de Aquisição Dinâmico: Inexistência de sistema de aquisição dinâmico\n\n9 - LOCAL DA EXECUÇÃO DO CONTRATO\nLOCAL DA EXECUÇÃO DO CONTRATO (PROCEDIMENTO)\nPaís: Portugal\nNUT III: PT112\nLocalidade: Braga\nDistrito: Braga\nConcelho: Barcelos\nFreguesia: Todas\n\n10 - PRAZO DE EXECUÇÃO DO CONTRATO\nPrazo de execução do contrato: 10 MESES\nPrevisão de renovações: Não\n\n11 - FUNDOS EU\nTêm fundos EU? Não\n\n12 - DOCUMENTOS DE HABILITAÇÃO\nHabilitação para o exercício da atividade profissional: Sim\nTipo: Outros\nDescrição - Outros: HACCP\nDescrição: HACCP\n\n13 - CONDIÇÕES DE APRESENTAÇÃO\nPlataforma eletrónica utilizada pela entidade adjudicante: VORTAL\nURL para Apresentação: https://community.vortal.biz/public/\nAdmissibilidade da apresentação de propostas variantes: Não autorizado\nPrazo para apresentação das propostas: 06-08-2025 17:00\nPrazo durante o qual os concorrentes são obrigados a manter as respetivas propostas: 66 dias a contar do termo do prazo para a apresentação das propostas\nIndicação de Subcontratação na Proposta: Inexistência de indicação de subcontratação\n\n14 - PRESTAÇÃO DE CAUÇÃO\nPrestação de caução: Não\n\n15 - FORNECIMENTO DAS PEÇAS DO CONCURSO, APRESENTAÇÃO DE PEDIDOS DE PARTICIPAÇÃO E APRESENTAÇÃO DAS PROPOSTAS\nLink para acesso às peças do concurso (URL): https://community.vortal.biz/Public/public-tender-documents/VzRCS2VxQUJxT0Fqd2NrTmhLR1p4OEFQTG9WelpCdURINVhIS3NRNWFGbXFMUTJsVnNWRU4yeUhsd2NTbEFLL0VyWGs2b0JpbGhncXVlcEVuVkFLL3c9PV5hejlC\n\n20 - OUTROS REQUISITOS\nInformação sobre contratos reservados. Aplica-se a contratos reservados (54º-A)? Não\n\n21 - CRITÉRIO DE ADJUDICAÇÃO\nMultifator: Sim\nFator: \nNome: Qualidade\nPonderação: 60%\nSubfatores: Sim\nSubfatores: \nNome: Memória Descritiva \nPonderação : 40%; \nNome: Plano Alimentar \nPonderação : 30%; \nNome: Plano Nutricional \nPonderação : 30%; \nFator: \nNome: Preço\nPonderação: 20%\nSubfatores: Não\nFator: \nNome: Qualidade\nPonderação: 20%\nSubfatores: Não\n\n24 - CONDIÇÕES DO CONTRATO\nFaturação Eletrónica: Permitido\nObrigação de Subcontratação:\nCódigo da Obrigação de Subcontratação: Não é aplicável nenhuma obrigação de subcontratação.\n\n25 - COMPRA PÚBLICA ESTRATÉGICA\nCompra Pública Estratégica: Redução dos impactos ambientais\nDescrição do Processo de Adjudicação Estratégico: Conforme as peças do procedimento\nCritérios de contratos Públicos Ecológicos: Critérios de contratação pública ecológica nacional\nCategorias da estratégia nacional: Produtos alimentares, serviços de assistência de restauração (catering) e máquinas de distribuição automática\nDiretiva Veículos Não Poluentes: Não\nCritério de Acessibilidade: Os critérios de acessibilidade para as pessoas com deficiência estão incluídos\n\n26 - INFORMAÇÕES ADICIONAIS\nContrato adequado para PME: Sim\nCobertura ACP (Acordo dos Contratos Públicos da Organização Mundial do Comércio): Não\n\n27 - IDENTIFICAÇÃO E CONTACTOS DO ÓRGÃO DE RECURSOS ADMINISTRATIVOS\nDesignação: Empresa Municipal de Educação e Cultura de Barcelos\nEndereço: Rua da Feiteira nº 10\nCódigo postal: 4750-001\nLocalidade: Barcelos\nTelefone: +351 253808290\nFax: +351 253808290\nEndereço eletrónico: geral@emec.pt\n\n28 - IDENTIFICAÇÃO DO(S) AUTOR(ES) DE ANÚNCIO\nNome: Jorge Manuel Oliveira da Cruz\nCargo: Presidente do Conselho de Administração\n419384543",
    "nipc": "504635417",
    "distrito": "Braga",
    "concelho": "Barcelos",
    "freguesia": "Todas",
    "site": "www.etgbarcelos.com",
    "email": "info@emecb.com",
    "designacao_contrato": "Confeção e Fornecimento de Refeições para os alunos da ETG – Ano letivo 2025/2026",
    "descricao": "Confeção e Fornecimento de Refeições para os alunos da ETG – Ano letivo 2025/2026",
    "preco_base": "138.495,42 EUR",
    "prazo_execucao": "10 MESES",
    "prazo_apresentacao_propostas": "06-08-2025 17:00",
    "fundos_eu": "Não",
    "plataforma_eletronica": "VORTAL",
    "url_procedimento": "https://community.vortal.biz/public/",
    "autor_nome": "Jorge Manuel Oliveira da Cruz",
    "autor_cargo": "Presidente do Conselho de Administração"
  },
  {
    "numero_procedimento": "N/A",
    "entidade": "MUNICÍPIO DE LOULÉ",
    "link": "https://diariodarepublica.pt/dr/detalhe/contrato-publico/20678-927474314",
    "detalhes_completos": "1 - IDENTIFICAÇÃO E CONTACTOS DA ENTIDADE ADJUDICANTE\nDesignação da entidade adjudicante: MUNICÍPIO DE LOULÉ\nNIPC: 502098139\nEndereço: Praça da República\nCódigo postal: 8104-001\nLocalidade: Faro\nPaís: Portugal\nNUT III: PT150\nDistrito: Faro\nConcelho: Loulé\nFreguesia: Todas\nTelefone: 289400834\nFax: 289415557\nEndereço da Entidade (URL): www.cm-loule.pt\nEndereço Eletrónico: aprovisionamento@cm-loule.pt\neDelivery Gateway (URL): https://community.vortal.biz/public/\nFunção da Organização: Adquirente\nNorma jurídica da Entidade Adjudicante: Organismo de direito público\nÁrea de atividade da Autoridade Adjudicante: Serviços públicos das administrações públicas\n\n2 - JORNAL OFICIAL DA UNIÃO EUROPEIA\nO procedimento a que este anúncio diz respeito também é publicitado no Jornal Oficial da União Europeia? Sim\n\n3 - AVISO\nModelo de Anúncio: Concurso público\nData de Envio do Anúncio: 29-07-2025\n\n5 - PROCESSO\nTipo de Procedimento: Concurso público\nPreço base do procedimento: Sim\nValor do preço base do procedimento: 68.632,00 EUR\nProcedimento com lotes? Sim\nNº Máx. de Lotes Autorizado: 5\nNúmero máximo de lotes que podem ser adjudicados a um concorrente: 5\n\n6 - OBJETO DO CONTRATO\nNúmero de referência interna: FM-2025-317 DACP\nDesignação do contrato: CONTRATAÇÃO DO FORNECIMENTO CONTÍNUO DE FARDAMENTO, EQUIPAMENTOS DE PROTEÇÃO INDIVIDUAL (EPIS) E MATERIAL PARA INCÊNDIOS RURAIS PARA A DIVISÃO DE AMBIENTE (DA) E EQUIPAMENTOS DE PROTEÇÃO INDIVIDUAL (E\nDescrição: CONTRATAÇÃO DO FORNECIMENTO CONTÍNUO DE FARDAMENTO, EQUIPAMENTOS DE PROTEÇÃO INDIVIDUAL (EPIS) E MATERIAL PARA INCÊNDIOS RURAIS PARA A DIVISÃO DE AMBIENTE (DA) E EQUIPAMENTOS DE PROTEÇÃO INDIVIDUAL (EPIS) PARA A UNIDADE OPERACIONAL DE ESPAÇOS VERDES E JARDINS (UOEVJ)\nOpções: Não\nTipo de Contrato Principal: Aquisição de Bens Móveis\nTipo de Contrato: Aquisição de Bens Móveis\nClassificação CPV (Vocabulário Comum para os Contratos Públicos)\nObjeto principal\nVocabulário Principal: 35110000\nPreço base s/IVA: 68.632,00 EUR\nLotes: \nNº: LOT-0001\nDescrição do Lote: LOTE 1 \nPreço base s/IVA: 15.480,00 EUR\nClassificação CPV (Vocabulário Comum para os Contratos Públicos)\nObjeto principal\nVocabulário Principal: 35110000\nNº: LOT-0002\nDescrição do Lote: LOTE 2 \nPreço base s/IVA: 17.652,00 EUR\nClassificação CPV (Vocabulário Comum para os Contratos Públicos)\nObjeto principal\nVocabulário Principal: 35110000\nNº: LOT-0003\nDescrição do Lote: LOTE 3\nPreço base s/IVA: 13.440,00 EUR\nClassificação CPV (Vocabulário Comum para os Contratos Públicos)\nObjeto principal\nVocabulário Principal: 35110000\nNº: LOT-0004\nDescrição do Lote: LOTE 4\nPreço base s/IVA: 10.370,00 EUR\nClassificação CPV (Vocabulário Comum para os Contratos Públicos)\nObjeto principal\nVocabulário Principal: 35110000\nNº: LOT-0005\nDescrição do Lote: LOTE 5\nPreço base s/IVA: 11.690,00 EUR\nClassificação CPV (Vocabulário Comum para os Contratos Públicos)\nObjeto principal\nVocabulário Principal: 35110000\n\n7 - INDICAÇÕES ADICIONAIS\nO contrato envolve aquisição conjunta (satisfação de várias entidades)? Não\nO contrato é adjudicado por uma central de compras? Não\n\n8 - TÉCNICAS\nO concurso destina-se à celebração de um acordo-quadro? Inexistência de acordo-quadro\nÉ utilizado um leilão eletrónico? Não\nÉ adotada uma fase de negociação? Não\nSistema de Aquisição Dinâmico: Inexistência de sistema de aquisição dinâmico\n\n9 - LOCAL DA EXECUÇÃO DO CONTRATO\nLOCAL DA EXECUÇÃO DO CONTRATO (PROCEDIMENTO)\nPaís: Portugal\nNUT III: PT150\nLocalidade: Faro\nDistrito: Faro\nConcelho: Loulé\nFreguesia: Todas\nLOCAL DA EXECUÇÃO DO CONTRATO (LOTE)\nIdentificador do Lote: LOT-0001; LOT-0002; LOT-0003; LOT-0004; LOT-0005\nPaís: Portugal\nNUT III: PT150\nLocalidade: Faro\nDistrito: Faro\nConcelho: Loulé\nFreguesia: Todas\n\n10 - PRAZO DE EXECUÇÃO DO CONTRATO\nIdentificador do Lote: LOT-0001; LOT-0002; LOT-0003; LOT-0004; LOT-0005\nPrazo de execução do contrato: 16 MESES\nPrevisão de renovações: Não\n\n11 - FUNDOS EU\nIdentificador do Lote: LOT-0001; LOT-0002; LOT-0003; LOT-0004; LOT-0005\nTêm fundos EU? Não\n\n12 - DOCUMENTOS DE HABILITAÇÃO\nHabilitação para o exercício da atividade profissional: Não\n\n13 - CONDIÇÕES DE APRESENTAÇÃO\nPlataforma eletrónica utilizada pela entidade adjudicante: VORTAL\nURL para Apresentação: https://community.vortal.biz/public/\nAdmissibilidade da apresentação de propostas variantes: Não autorizado\nPrazo para apresentação das propostas: 03-09-2025 18:00\nPrazo durante o qual os concorrentes são obrigados a manter as respetivas propostas: 90 dias a contar do termo do prazo para a apresentação das propostas\nApresentação de Catálogo Eletrónico: Não autorizado\nIndicação de Subcontratação na Proposta: Inexistência de indicação de subcontratação\n\n14 - PRESTAÇÃO DE CAUÇÃO\nPrestação de caução: Não\n\n15 - FORNECIMENTO DAS PEÇAS DO CONCURSO, APRESENTAÇÃO DE PEDIDOS DE PARTICIPAÇÃO E APRESENTAÇÃO DAS PROPOSTAS\nLink para acesso às peças do concurso (URL): https://community.vortal.biz/Public/public-tender-documents/SVRBM0lIMDNZMzk4dnRxakZTdm44eGg1b0pGYUN2Rng5SU5LQ3A2eHZTTFM0QVFOeG5lT1Y2QnNkSEQyVHNibDVLd1B1d1paRno0R0hGdXB5T1d6V1E9PU9OI0lO\n\n20 - OUTROS REQUISITOS\nIdentificador do Lote: LOT-0001; LOT-0002; LOT-0003; LOT-0004; LOT-0005\nInformação sobre contratos reservados. Aplica-se a contratos reservados (54º-A)? Não\n\n21 - CRITÉRIO DE ADJUDICAÇÃO\nO Critério de adjudicação é diferenciado por lote? Não\nMultifator: Não\nMonofator:\nNome: Preço\n\n24 - CONDIÇÕES DO CONTRATO\nIdentificador do Lote: LOT-0001; LOT-0002; LOT-0003; LOT-0004; LOT-0005\nFaturação Eletrónica: Permitido\nObrigação de Subcontratação:\nCódigo da Obrigação de Subcontratação: Não é aplicável nenhuma obrigação de subcontratação.\n\n25 - COMPRA PÚBLICA ESTRATÉGICA\nCompra Pública Estratégica: Inexistência de contratação pública estratégica\n\n26 - INFORMAÇÕES ADICIONAIS\nIdentificador do Lote: LOT-0001; LOT-0002; LOT-0003; LOT-0004; LOT-0005\nContrato adequado para PME: Sim\nCobertura ACP (Acordo dos Contratos Públicos da Organização Mundial do Comércio): Não\n\n27 - IDENTIFICAÇÃO E CONTACTOS DO ÓRGÃO DE RECURSOS ADMINISTRATIVOS\nDesignação: Câmara Municipal de Loulé\nEndereço: Praça da República\nCódigo postal: 8104-001\nLocalidade: Loulé\nTelefone: +351 289400600\nFax: +351 289415557\nEndereço eletrónico: geral@cm-loule.pt\n\n28 - IDENTIFICAÇÃO DO(S) AUTOR(ES) DE ANÚNCIO\nNome: Vítor Manuel Gonçalves Aleixo\nCargo: Presidente da Câmara Municipal\n419365232",
    "nipc": "502098139",
    "distrito": "Faro",
    "concelho": "Loulé",
    "freguesia": "Todas",
    "site": "www.cm-loule.pt",
    "email": "aprovisionamento@cm-loule.pt",
    "designacao_contrato": "CONTRATAÇÃO DO FORNECIMENTO CONTÍNUO DE FARDAMENTO, EQUIPAMENTOS DE PROTEÇÃO INDIVIDUAL (EPIS) E MATERIAL PARA INCÊNDIOS RURAIS PARA A DIVISÃO DE AMBIENTE (DA) E EQUIPAMENTOS DE PROTEÇÃO INDIVIDUAL (E",
    "descricao": "CONTRATAÇÃO DO FORNECIMENTO CONTÍNUO DE FARDAMENTO, EQUIPAMENTOS DE PROTEÇÃO INDIVIDUAL (EPIS) E MATERIAL PARA INCÊNDIOS RURAIS PARA A DIVISÃO DE AMBIENTE (DA) E EQUIPAMENTOS DE PROTEÇÃO INDIVIDUAL (EPIS) PARA A UNIDADE OPERACIONAL DE ESPAÇOS VERDES E JARDINS (UOEVJ)",
    "preco_base": "68.632,00 EUR",
    "prazo_execucao": "16 MESES",
    "prazo_apresentacao_propostas": "03-09-2025 18:00",
    "fundos_eu": "Não",
    "plataforma_eletronica": "VORTAL",
    "url_procedimento": "https://community.vortal.biz/public/",
    "autor_nome": "Vítor Manuel Gonçalves Aleixo",
    "autor_cargo": "Presidente da Câmara Municipal"
  },
  {
    "numero_procedimento": "N/A",
    "entidade": "MUNICÍPIO DE LOULÉ",
    "link": "https://diariodarepublica.pt/dr/detalhe/contrato-publico/20679-927474315",
    "detalhes_completos": "1 - IDENTIFICAÇÃO E CONTACTOS DA ENTIDADE ADJUDICANTE\nDesignação da entidade adjudicante: MUNICÍPIO DE LOULÉ\nNIPC: 502098139\nEndereço: Praça da República\nCódigo postal: 8104-001\nLocalidade: Faro\nPaís: Portugal\nNUT III: PT150\nDistrito: Faro\nConcelho: Loulé\nFreguesia: Todas\nTelefone: 289400834\nFax: 289415557\nEndereço da Entidade (URL): www.cm-loule.pt\nEndereço Eletrónico: aprovisionamento@cm-loule.pt\neDelivery Gateway (URL): https://community.vortal.biz/public/\nFunção da Organização: Adquirente\nNorma jurídica da Entidade Adjudicante: Organismo de direito público\nÁrea de atividade da Autoridade Adjudicante: Serviços públicos das administrações públicas\n\n2 - JORNAL OFICIAL DA UNIÃO EUROPEIA\nO procedimento a que este anúncio diz respeito também é publicitado no Jornal Oficial da União Europeia? Não\n\n3 - AVISO\nModelo de Anúncio: Concurso público\nData de Envio do Anúncio: 31-07-2025\n\n5 - PROCESSO\nTipo de Procedimento: Concurso público\nPreço base do procedimento: Sim\nValor do preço base do procedimento: 171.600,00 EUR\nProcedimento com lotes? Não\n\n6 - OBJETO DO CONTRATO\nNúmero de referência interna: OM-057-2025-DCME \nDesignação do contrato: Recuperação e Manutenção de Edifícios e Equipamentos Desportivos Municipais: Requalificação dos Campos de Ténis de Loulé\nDescrição: Reparação de fissuras, aplicação de revestimento em acrílico, aplicação de camadas de desgaste, marcação dos campos de jogos, retirada e colocação de guardas metálicas, levantamento e colocação de pavimento cerâmico e pinturas.\nTipo de Contrato Principal: Empreitada de Obras Públicas\nTipo de Contrato: Empreitada de Obras Públicas\nClassificação CPV (Vocabulário Comum para os Contratos Públicos)\nObjeto principal\nVocabulário Principal: 45453100\nPreço base s/IVA: 171.600,00 EUR\n\n7 - INDICAÇÕES ADICIONAIS\nO contrato envolve aquisição conjunta (satisfação de várias entidades)? Não\nO contrato é adjudicado por uma central de compras? Não\n\n8 - TÉCNICAS\nO concurso destina-se à celebração de um acordo-quadro? Inexistência de acordo-quadro\nÉ utilizado um leilão eletrónico? Não\nÉ adotada uma fase de negociação? Não\nSistema de Aquisição Dinâmico: Inexistência de sistema de aquisição dinâmico\n\n9 - LOCAL DA EXECUÇÃO DO CONTRATO\nLOCAL DA EXECUÇÃO DO CONTRATO (PROCEDIMENTO)\nPaís: Portugal\nNUT III: PT150\nLocalidade: Faro\nDistrito: Faro\nConcelho: Loulé\nFreguesia: Todas\n\n10 - PRAZO DE EXECUÇÃO DO CONTRATO\nPrazo de execução do contrato: 60 DIAS\nPrevisão de renovações: Não\n\n11 - FUNDOS EU\nTêm fundos EU? Não\n\n12 - DOCUMENTOS DE HABILITAÇÃO\nHabilitação para o exercício da atividade profissional: Sim\nTipo: Alvará\nDescrição: 1ª subcategoria (estruturas e elementos de betão) e 5ªsubcategoria da 1ªcategoria (estuques, pinturas e outros revestimentos)\n\n13 - CONDIÇÕES DE APRESENTAÇÃO\nPlataforma eletrónica utilizada pela entidade adjudicante: VORTAL\nURL para Apresentação: https://community.vortal.biz/public/\nAdmissibilidade da apresentação de propostas variantes: Não autorizado\nPrazo para apresentação das propostas: 13-08-2025 17:00\nPrazo durante o qual os concorrentes são obrigados a manter as respetivas propostas: 180 dias a contar do termo do prazo para a apresentação das propostas\nIndicação de Subcontratação na Proposta: Inexistência de indicação de subcontratação\n\n14 - PRESTAÇÃO DE CAUÇÃO\nPrestação de caução: Não\n\n15 - FORNECIMENTO DAS PEÇAS DO CONCURSO, APRESENTAÇÃO DE PEDIDOS DE PARTICIPAÇÃO E APRESENTAÇÃO DAS PROPOSTAS\nLink para acesso às peças do concurso (URL): https://community.vortal.biz/Public/public-tender-documents/dnRFTGZtNHZHeWNJdHcyRlNmTnJJK1Q0bFhQV1l4ZC9Eek9mQnA5OElOazVYQmdkZWVPdmNSVk1pZEE5UHdNbHFpZEZWQnlFU0VPaVdsMks4MUJGcEE9PTdZI2RQ\n\n20 - OUTROS REQUISITOS\nInformação sobre contratos reservados. Aplica-se a contratos reservados (54º-A)? Não\n\n21 - CRITÉRIO DE ADJUDICAÇÃO\nMultifator: Não\nMonofator:\nNome: Outros\nOutro nome: Preço\n\n24 - CONDIÇÕES DO CONTRATO\nFaturação Eletrónica: Permitido\nObrigação de Subcontratação:\nCódigo da Obrigação de Subcontratação: Não é aplicável nenhuma obrigação de subcontratação.\n\n25 - COMPRA PÚBLICA ESTRATÉGICA\nCompra Pública Estratégica: Inexistência de contratação pública estratégica\n\n26 - INFORMAÇÕES ADICIONAIS\nContrato adequado para PME: Sim\nCobertura ACP (Acordo dos Contratos Públicos da Organização Mundial do Comércio): Não\n\n27 - IDENTIFICAÇÃO E CONTACTOS DO ÓRGÃO DE RECURSOS ADMINISTRATIVOS\nDesignação: Câmara Municipal de Loulé\nEndereço: Praça da Republica\nCódigo postal: 8104-001\nLocalidade: Loulé\nTelefone: +351 289400600\nFax: +351 289415557\nEndereço eletrónico: geral@cm-loule.pt\n\n28 - IDENTIFICAÇÃO DO(S) AUTOR(ES) DE ANÚNCIO\nNome: Vitor Aleixo\nCargo: Presidente da Câmara\n419380314",
    "nipc": "502098139",
    "distrito": "Faro",
    "concelho": "Loulé",
    "freguesia": "Todas",
    "site": "www.cm-loule.pt",
    "email": "aprovisionamento@cm-loule.pt",
    "designacao_contrato": "Recuperação e Manutenção de Edifícios e Equipamentos Desportivos Municipais: Requalificação dos Campos de Ténis de Loulé",
    "descricao": "Reparação de fissuras, aplicação de revestimento em acrílico, aplicação de camadas de desgaste, marcação dos campos de jogos, retirada e colocação de guardas metálicas, levantamento e colocação de pavimento cerâmico e pinturas.",
    "preco_base": "171.600,00 EUR",
    "prazo_execucao": "60 DIAS",
    "prazo_apresentacao_propostas": "13-08-2025 17:00",
    "fundos_eu": "Não",
    "plataforma_eletronica": "VORTAL",
    "url_procedimento": "https://community.vortal.biz/public/",
    "autor_nome": "Vitor Aleixo",
    "autor_cargo": "Presidente da Câmara"
  },
  {
    "numero_procedimento": "N/A",
    "entidade": "MUNICÍPIO DE LOULÉ",
    "link": "https://diariodarepublica.pt/dr/detalhe/contrato-publico/20680-927474316",
    "detalhes_completos": "1 - IDENTIFICAÇÃO E CONTACTOS DA ENTIDADE ADJUDICANTE\nDesignação da entidade adjudicante: MUNICÍPIO DE LOULÉ\nNIPC: 502098139\nEndereço: Praça da República\nCódigo postal: 8104-001\nLocalidade: Faro\nPaís: Portugal\nNUT III: PT150\nDistrito: Faro\nConcelho: Loulé\nFreguesia: Todas\nTelefone: 289400834\nFax: 289415557\nEndereço da Entidade (URL): www.cm-loule.pt\nEndereço Eletrónico: aprovisionamento@cm-loule.pt\neDelivery Gateway (URL): https://community.vortal.biz/public/\nFunção da Organização: Adquirente\nNorma jurídica da Entidade Adjudicante: Organismo de direito público\nÁrea de atividade da Autoridade Adjudicante: Serviços públicos das administrações públicas\n\n2 - JORNAL OFICIAL DA UNIÃO EUROPEIA\nO procedimento a que este anúncio diz respeito também é publicitado no Jornal Oficial da União Europeia? Não\n\n3 - AVISO\nModelo de Anúncio: Concurso público\nData de Envio do Anúncio: 31-07-2025\n\n5 - PROCESSO\nTipo de Procedimento: Concurso público\nPreço base do procedimento: Sim\nValor do preço base do procedimento: 105.875,00 EUR\nProcedimento com lotes? Sim\nNº Máx. de Lotes Autorizado: 3\nNúmero máximo de lotes que podem ser adjudicados a um concorrente: 3\n\n6 - OBJETO DO CONTRATO\nNúmero de referência interna: FM-2025-351 DACP\nDesignação do contrato: CONTRATAÇÃO DE FORNECIMENTO CONTINUO DE INERTES\nDescrição: CONTRATAÇÃO DE FORNECIMENTO CONTINUO DE INERTES\nTipo de Contrato Principal: Aquisição de Bens Móveis\nTipo de Contrato: Aquisição de Bens Móveis\nClassificação CPV (Vocabulário Comum para os Contratos Públicos)\nObjeto principal\nVocabulário Principal: 44110000\nPreço base s/IVA: 105.875,00 EUR\nLotes: \nNº: LOT-0001\nDescrição do Lote: LOTE 1 \nPreço base s/IVA: 44.375,00 EUR\nClassificação CPV (Vocabulário Comum para os Contratos Públicos)\nObjeto principal\nVocabulário Principal: 44110000\nNº: LOT-0002\nDescrição do Lote: LOTE 2 \nPreço base s/IVA: 36.000,00 EUR\nClassificação CPV (Vocabulário Comum para os Contratos Públicos)\nObjeto principal\nVocabulário Principal: 44110000\nNº: LOT-0003\nDescrição do Lote: LOTE 3\nPreço base s/IVA: 25.500,00 EUR\nClassificação CPV (Vocabulário Comum para os Contratos Públicos)\nObjeto principal\nVocabulário Principal: 44110000\n\n7 - INDICAÇÕES ADICIONAIS\nO contrato envolve aquisição conjunta (satisfação de várias entidades)? Não\nO contrato é adjudicado por uma central de compras? Não\n\n8 - TÉCNICAS\nO concurso destina-se à celebração de um acordo-quadro? Inexistência de acordo-quadro\nÉ utilizado um leilão eletrónico? Não\nÉ adotada uma fase de negociação? Não\nSistema de Aquisição Dinâmico: Inexistência de sistema de aquisição dinâmico\n\n9 - LOCAL DA EXECUÇÃO DO CONTRATO\nLOCAL DA EXECUÇÃO DO CONTRATO (PROCEDIMENTO)\nPaís: Portugal\nNUT III: PT150\nLocalidade: Faro\nDistrito: Faro\nConcelho: Loulé\nFreguesia: Todas\nLOCAL DA EXECUÇÃO DO CONTRATO (LOTE)\nIdentificador do Lote: LOT-0001; LOT-0002; LOT-0003\nPaís: Portugal\nNUT III: PT150\nLocalidade: Faro\nDistrito: Faro\nConcelho: Loulé\nFreguesia: Todas\n\n10 - PRAZO DE EXECUÇÃO DO CONTRATO\nIdentificador do Lote: LOT-0001; LOT-0002; LOT-0003\nPrazo de execução do contrato: 12 MESES\nPrevisão de renovações: Não\n\n11 - FUNDOS EU\nIdentificador do Lote: LOT-0001; LOT-0002; LOT-0003\nTêm fundos EU? Não\n\n12 - DOCUMENTOS DE HABILITAÇÃO\nHabilitação para o exercício da atividade profissional: Não\n\n13 - CONDIÇÕES DE APRESENTAÇÃO\nPlataforma eletrónica utilizada pela entidade adjudicante: VORTAL\nURL para Apresentação: https://community.vortal.biz/public/\nAdmissibilidade da apresentação de propostas variantes: Não autorizado\nPrazo para apresentação das propostas: 25-08-2025 18:00\nPrazo durante o qual os concorrentes são obrigados a manter as respetivas propostas: 90 dias a contar do termo do prazo para a apresentação das propostas\nIndicação de Subcontratação na Proposta: Inexistência de indicação de subcontratação\n\n14 - PRESTAÇÃO DE CAUÇÃO\nPrestação de caução: Não\n\n15 - FORNECIMENTO DAS PEÇAS DO CONCURSO, APRESENTAÇÃO DE PEDIDOS DE PARTICIPAÇÃO E APRESENTAÇÃO DAS PROPOSTAS\nLink para acesso às peças do concurso (URL): https://community.vortal.biz/Public/public-tender-documents/YkR3ODlaWUtLaW4yOWxjZkprS2o5Skd4WTMzZ3lUOVlFTjRROEhXWnBYUFhqTElYb01aOVUxVTFCOEpZcUJlRDduYzJISFhteFl0NXd1UDVEb1JJR1E9PWI1KV9v\n\n20 - OUTROS REQUISITOS\nIdentificador do Lote: LOT-0001; LOT-0002; LOT-0003\nInformação sobre contratos reservados. Aplica-se a contratos reservados (54º-A)? Não\n\n21 - CRITÉRIO DE ADJUDICAÇÃO\nO Critério de adjudicação é diferenciado por lote? Não\nMultifator: Não\nMonofator:\nNome: Preço\n\n24 - CONDIÇÕES DO CONTRATO\nIdentificador do Lote: LOT-0001; LOT-0002; LOT-0003\nFaturação Eletrónica: Permitido\nObrigação de Subcontratação:\nCódigo da Obrigação de Subcontratação: Não é aplicável nenhuma obrigação de subcontratação.\n\n25 - COMPRA PÚBLICA ESTRATÉGICA\nCompra Pública Estratégica: Inexistência de contratação pública estratégica\n\n26 - INFORMAÇÕES ADICIONAIS\nIdentificador do Lote: LOT-0001; LOT-0002; LOT-0003\nContrato adequado para PME: Sim\nCobertura ACP (Acordo dos Contratos Públicos da Organização Mundial do Comércio): Não\n\n27 - IDENTIFICAÇÃO E CONTACTOS DO ÓRGÃO DE RECURSOS ADMINISTRATIVOS\nDesignação: Câmara Municipal de Loulé\nEndereço: Praça da República\nCódigo postal: 8104-001\nLocalidade: Loulé\nTelefone: +351 289400600\nFax: +351 289415557\nEndereço eletrónico: geral@cm-loule.pt\n\n28 - IDENTIFICAÇÃO DO(S) AUTOR(ES) DE ANÚNCIO\nNome: Vítor Manuel Gonçalves Aleixo\nCargo: Presidente da Câmara Municipal\n419381157",
    "nipc": "502098139",
    "distrito": "Faro",
    "concelho": "Loulé",
    "freguesia": "Todas",
    "site": "www.cm-loule.pt",
    "email": "aprovisionamento@cm-loule.pt",
    "designacao_contrato": "CONTRATAÇÃO DE FORNECIMENTO CONTINUO DE INERTES",
    "descricao": "CONTRATAÇÃO DE FORNECIMENTO CONTINUO DE INERTES",
    "preco_base": "105.875,00 EUR",
    "prazo_execucao": "12 MESES",
    "prazo_apresentacao_propostas": "25-08-2025 18:00",
    "fundos_eu": "Não",
    "plataforma_eletronica": "VORTAL",
    "url_procedimento": "https://community.vortal.biz/public/",
    "autor_nome": "Vítor Manuel Gonçalves Aleixo",
    "autor_cargo": "Presidente da Câmara Municipal"
  },
  {
    "numero_procedimento": "N/A",
    "entidade": "Unidade Local de Saúde de Almada-Seixal, E.P.E.",
    "link": "https://diariodarepublica.pt/dr/detalhe/contrato-publico/20682-927474324",
    "detalhes_completos": "1 - IDENTIFICAÇÃO E CONTACTOS DA ENTIDADE ADJUDICANTE\nDesignação da entidade adjudicante: Unidade Local de Saúde de Almada-Seixal, E.P.E.\nNIPC: 506361470\nEndereço: Av. Torrado da Silva\nCódigo postal: 2805-267\nLocalidade: Setúbal\nPaís: Portugal\nNUT III: PT170\nDistrito: Setúbal\nConcelho: Almada\nFreguesia: União das Freguesias de Almada, Cova da Piedade, Pragal e Cacilhas\nTelefone: 212727205\nFax: 212727211\nEndereço da Entidade (URL): http://www.hgo.pt\nEndereço Eletrónico: aprovisionamento@hgo.min-saude.pt\neDelivery Gateway (URL): https://community.vortal.biz/public/\nFunção da Organização: Adquirente\nNorma jurídica da Entidade Adjudicante: Organismo de direito público\nÁrea de atividade da Autoridade Adjudicante: Saúde\n\n2 - JORNAL OFICIAL DA UNIÃO EUROPEIA\nO procedimento a que este anúncio diz respeito também é publicitado no Jornal Oficial da União Europeia? Não\n\n3 - AVISO\nModelo de Anúncio: Concurso público\nData de Envio do Anúncio: 31-07-2025\n\n5 - PROCESSO\nTipo de Procedimento: Concurso público\nPreço base do procedimento: Sim\nValor do preço base do procedimento: 38.139,00 EUR\nProcedimento com lotes? Sim\nNº Máx. de Lotes Autorizado: 10\nNúmero máximo de lotes que podem ser adjudicados a um concorrente: 10\n\n6 - OBJETO DO CONTRATO\nNúmero de referência interna: 21126325\nDesignação do contrato: FARDAS DESCARTÁVEIS - ANOS 2025, 2026 E 2027\nDescrição: FARDAS DESCARTÁVEIS\nTipo de Contrato Principal: Aquisição de Bens Móveis\nTipo de Contrato: Aquisição de Bens Móveis\nClassificação CPV (Vocabulário Comum para os Contratos Públicos)\nObjeto principal\nVocabulário Principal: 33140000\nPreço base s/IVA: 38.139,00 EUR\nLotes: \nNº: LOT-0001\nDescrição do Lote: Lote 1\nPreço base s/IVA: 740,00 EUR\nClassificação CPV (Vocabulário Comum para os Contratos Públicos)\nObjeto principal\nVocabulário Principal: 33140000\nNº: LOT-0002\nDescrição do Lote: Lote 2\nPreço base s/IVA: 1.702,00 EUR\nClassificação CPV (Vocabulário Comum para os Contratos Públicos)\nObjeto principal\nVocabulário Principal: 33140000\nNº: LOT-0003\nDescrição do Lote: Lote 3\nPreço base s/IVA: 3.276,00 EUR\nClassificação CPV (Vocabulário Comum para os Contratos Públicos)\nObjeto principal\nVocabulário Principal: 33140000\nNº: LOT-0004\nDescrição do Lote: Lote 4\nPreço base s/IVA: 3.432,00 EUR\nClassificação CPV (Vocabulário Comum para os Contratos Públicos)\nObjeto principal\nVocabulário Principal: 33140000\nNº: LOT-0005\nDescrição do Lote: Lote 5\nPreço base s/IVA: 1.640,00 EUR\nClassificação CPV (Vocabulário Comum para os Contratos Públicos)\nObjeto principal\nVocabulário Principal: 33140000\nNº: LOT-0006\nDescrição do Lote: Lote 6\nPreço base s/IVA: 172,00 EUR\nClassificação CPV (Vocabulário Comum para os Contratos Públicos)\nObjeto principal\nVocabulário Principal: 33140000\nNº: LOT-0007\nDescrição do Lote: Lote 7\nPreço base s/IVA: 92,00 EUR\nClassificação CPV (Vocabulário Comum para os Contratos Públicos)\nObjeto principal\nVocabulário Principal: 33140000\nNº: LOT-0008\nDescrição do Lote: Lote 8\nPreço base s/IVA: 8.786,25 EUR\nClassificação CPV (Vocabulário Comum para os Contratos Públicos)\nObjeto principal\nVocabulário Principal: 33140000\nNº: LOT-0009\nDescrição do Lote: Lote 9\nPreço base s/IVA: 12.753,75 EUR\nClassificação CPV (Vocabulário Comum para os Contratos Públicos)\nObjeto principal\nVocabulário Principal: 33140000\nNº: LOT-0010\nDescrição do Lote: Lote 10\nPreço base s/IVA: 5.545,00 EUR\nClassificação CPV (Vocabulário Comum para os Contratos Públicos)\nObjeto principal\nVocabulário Principal: 33140000\n\n7 - INDICAÇÕES ADICIONAIS\nO contrato envolve aquisição conjunta (satisfação de várias entidades)? Não\nO contrato é adjudicado por uma central de compras? Não\n\n8 - TÉCNICAS\nO concurso destina-se à celebração de um acordo-quadro? Inexistência de acordo-quadro\nÉ utilizado um leilão eletrónico? Não\nÉ adotada uma fase de negociação? Não\nSistema de Aquisição Dinâmico: Inexistência de sistema de aquisição dinâmico\n\n9 - LOCAL DA EXECUÇÃO DO CONTRATO\nLOCAL DA EXECUÇÃO DO CONTRATO (PROCEDIMENTO)\nPaís: Portugal\nNUT III: PT170\nLocalidade: Setúbal\nDistrito: Setúbal\nConcelho: Almada\nFreguesia: União das Freguesias de Almada, Cova da Piedade, Pragal e Cacilhas\nLOCAL DA EXECUÇÃO DO CONTRATO (LOTE)\nIdentificador do Lote: LOT-0001; LOT-0002; LOT-0003; LOT-0004; LOT-0005; LOT-0006; LOT-0007; LOT-0008; LOT-0009; LOT-0010\nPaís: Portugal\nNUT III: PT170\nLocalidade: Setúbal\nDistrito: Setúbal\nConcelho: Almada\nFreguesia: União das Freguesias de Almada, Cova da Piedade, Pragal e Cacilhas\n\n10 - PRAZO DE EXECUÇÃO DO CONTRATO\nIdentificador do Lote: LOT-0001; LOT-0002; LOT-0003; LOT-0004; LOT-0005; LOT-0006; LOT-0007; LOT-0008; LOT-0009; LOT-0010\nPrazo de execução do contrato: 29 MESES\nPrevisão de renovações: Não\n\n11 - FUNDOS EU\nIdentificador do Lote: LOT-0001; LOT-0002; LOT-0003; LOT-0004; LOT-0005; LOT-0006; LOT-0007; LOT-0008; LOT-0009; LOT-0010\nTêm fundos EU? Não\n\n12 - DOCUMENTOS DE HABILITAÇÃO\nHabilitação para o exercício da atividade profissional: Não\n\n13 - CONDIÇÕES DE APRESENTAÇÃO\nPlataforma eletrónica utilizada pela entidade adjudicante: VORTAL\nURL para Apresentação: https://community.vortal.biz/public/\nAdmissibilidade da apresentação de propostas variantes: Não autorizado\nPrazo para apresentação das propostas: 18-08-2025 17:00\nPrazo durante o qual os concorrentes são obrigados a manter as respetivas propostas: 180 dias a contar do termo do prazo para a apresentação das propostas\nIndicação de Subcontratação na Proposta: Inexistência de indicação de subcontratação\n\n14 - PRESTAÇÃO DE CAUÇÃO\nPrestação de caução: Não\n\n15 - FORNECIMENTO DAS PEÇAS DO CONCURSO, APRESENTAÇÃO DE PEDIDOS DE PARTICIPAÇÃO E APRESENTAÇÃO DAS PROPOSTAS\nLink para acesso às peças do concurso (URL): https://community.vortal.biz/Public/public-tender-documents/UWtDaTdObEpvRUxkU1RHRmNzVlVIZFpZaG40bFdTMXVvQ3VIcWVlMEFDdTZkdndHbWt2QzVqd0tqZEV3ZlpDMTRyRTJ1ZHdyVjdCS2dVTHM1REVaVFE9PUVkX3Em\n\n20 - OUTROS REQUISITOS\nIdentificador do Lote: LOT-0001; LOT-0002; LOT-0003; LOT-0004; LOT-0005; LOT-0006; LOT-0007; LOT-0008; LOT-0009; LOT-0010\nInformação sobre contratos reservados. Aplica-se a contratos reservados (54º-A)? Não\n\n21 - CRITÉRIO DE ADJUDICAÇÃO\nO Critério de adjudicação é diferenciado por lote? Não\nMultifator: Sim\nFator: \nNome: Preço\nPonderação: 45%\nSubfatores: Não\nFator: \nNome: Qualidade\nPonderação: 55%\nSubfatores: Não\n\n24 - CONDIÇÕES DO CONTRATO\nIdentificador do Lote: LOT-0001; LOT-0002; LOT-0003; LOT-0004; LOT-0005; LOT-0006; LOT-0007; LOT-0008; LOT-0009; LOT-0010\nFaturação Eletrónica: Permitido\nObrigação de Subcontratação:\nCódigo da Obrigação de Subcontratação: Não é aplicável nenhuma obrigação de subcontratação.\n\n25 - COMPRA PÚBLICA ESTRATÉGICA\nCompra Pública Estratégica: Inexistência de contratação pública estratégica\n\n26 - INFORMAÇÕES ADICIONAIS\nIdentificador do Lote: LOT-0001; LOT-0002; LOT-0003; LOT-0004; LOT-0005; LOT-0006; LOT-0007; LOT-0008; LOT-0009; LOT-0010\nContrato adequado para PME: Sim\nCobertura ACP (Acordo dos Contratos Públicos da Organização Mundial do Comércio): Não\n\n27 - IDENTIFICAÇÃO E CONTACTOS DO ÓRGÃO DE RECURSOS ADMINISTRATIVOS\nDesignação: Serviço de Gestão de Compras da Unidade Local de Saúde de Almada-Seixal, E.P.E.\nEndereço: Avenida Torrado da Silva\nCódigo postal: 2805-267\nLocalidade: Almada\nTelefone: +351 212727205\nFax: +351 212727211\nEndereço eletrónico: Bensconsumo@ulsas.min-saude.pt\n\n28 - IDENTIFICAÇÃO DO(S) AUTOR(ES) DE ANÚNCIO\nNome: Verónica Ferreira\nCargo: Assistente Técnica\n419372563",
    "nipc": "506361470",
    "distrito": "Setúbal",
    "concelho": "Almada",
    "freguesia": "União das Freguesias de Almada, Cova da Piedade, Pragal e Cacilhas",
    "site": "http://www.hgo.pt",
    "email": "aprovisionamento@hgo.min-saude.pt",
    "designacao_contrato": "FARDAS DESCARTÁVEIS - ANOS 2025, 2026 E 2027",
    "descricao": "FARDAS DESCARTÁVEIS",
    "preco_base": "38.139,00 EUR",
    "prazo_execucao": "29 MESES",
    "prazo_apresentacao_propostas": "18-08-2025 17:00",
    "fundos_eu": "Não",
    "plataforma_eletronica": "VORTAL",
    "url_procedimento": "https://community.vortal.biz/public/",
    "autor_nome": "Verónica Ferreira",
    "autor_cargo": "Assistente Técnica"
  },
  {
    "numero_procedimento": "N/A",
    "entidade": "Secretaria-Geral do MAI",
    "link": "https://diariodarepublica.pt/dr/detalhe/contrato-publico/20683-927474325",
    "detalhes_completos": "Alteração do Anúncio de procedimento n.º 19969/2025, de 2025-07-25, com o ID 419355578\n\n1 - IDENTIFICAÇÃO E CONTACTOS DA ENTIDADE ADJUDICANTE\nDesignação da entidade adjudicante: Secretaria-Geral do MAI\nNIPC: 600014665\nEndereço: Rua São Mamede, 23\nCódigo postal: 1100-523\nLocalidade: Lisboa\nPaís: Portugal\nNUT III: PT170\nDistrito: Lisboa\nConcelho: Lisboa\nFreguesia: Freguesia de Santa Maria Maior - Lisboa\nTelefone: 213409000\nFax: 213409010\nEndereço da Entidade (URL): www.sg.mai.gov.pt/\nEndereço Eletrónico: gab.sec.geral@sg.mai.gov.pt\neDelivery Gateway (URL): https://community.vortal.biz/public/\nFunção da Organização: Adquirente\nNorma jurídica da Entidade Adjudicante: Autoridade da administração central\nÁrea de atividade da Autoridade Adjudicante: Serviços públicos das administrações públicas\n\n2 - JORNAL OFICIAL DA UNIÃO EUROPEIA\nO procedimento a que este anúncio diz respeito também é publicitado no Jornal Oficial da União Europeia? Não\n\n3 - AVISO\nModelo de Anúncio: Concurso público\nData de Envio do Anúncio: 31-07-2025\n\n5 - PROCESSO\nTipo de Procedimento: Concurso público\nPreço base do procedimento: Sim\nValor do preço base do procedimento: 66.000,00 EUR\nProcedimento com lotes? Não\n\n6 - OBJETO DO CONTRATO\nNúmero de referência interna: Proc. 36/DPIE/2025 Cópia\nDesignação do contrato: Aquisição de Carabina para formação de caçadores, para a PSP, no âmbito do DLPIEFSS.\nDescrição: Aquisição de Carabina para formação de caçadores, para a PSP, no âmbito do DLPIEFSS.\nTipo de Contrato Principal: Aquisição de Bens Móveis\nTipo de Contrato: Aquisição de Bens Móveis\nClassificação CPV (Vocabulário Comum para os Contratos Públicos)\nObjeto principal\nVocabulário Principal: 35320000\nPreço base s/IVA: 66.000,00 EUR\n\n7 - INDICAÇÕES ADICIONAIS\nO contrato envolve aquisição conjunta (satisfação de várias entidades)? Não\nO contrato é adjudicado por uma central de compras? Não\n\n8 - TÉCNICAS\nO concurso destina-se à celebração de um acordo-quadro? Inexistência de acordo-quadro\nÉ utilizado um leilão eletrónico? Não\nÉ adotada uma fase de negociação? Não\nSistema de Aquisição Dinâmico: Inexistência de sistema de aquisição dinâmico\n\n9 - LOCAL DA EXECUÇÃO DO CONTRATO\nLOCAL DA EXECUÇÃO DO CONTRATO (PROCEDIMENTO)\nPaís: Portugal\nNUT III: PT170\nLocalidade: Lisboa\nDistrito: Lisboa\nConcelho: Oeiras\nFreguesia: União das Freguesias de Carnaxide e Queijas\n\n10 - PRAZO DE EXECUÇÃO DO CONTRATO\nPrazo de execução do contrato: 120 DIAS\nPrevisão de renovações: Não\n\n11 - FUNDOS EU\nTêm fundos EU? Não\n\n12 - DOCUMENTOS DE HABILITAÇÃO\nHabilitação para o exercício da atividade profissional: Não\n\n13 - CONDIÇÕES DE APRESENTAÇÃO\nPlataforma eletrónica utilizada pela entidade adjudicante: VORTAL\nURL para Apresentação: https://community.vortal.biz/public/\nAdmissibilidade da apresentação de propostas variantes: Não autorizado\nPrazo para apresentação das propostas: 12-08-2025 23:59\nPrazo durante o qual os concorrentes são obrigados a manter as respetivas propostas: 66 dias a contar do termo do prazo para a apresentação das propostas\nApresentação de Catálogo Eletrónico: Permitido\nIndicação de Subcontratação na Proposta: Inexistência de indicação de subcontratação\n\n14 - PRESTAÇÃO DE CAUÇÃO\nPrestação de caução: Não\n\n15 - FORNECIMENTO DAS PEÇAS DO CONCURSO, APRESENTAÇÃO DE PEDIDOS DE PARTICIPAÇÃO E APRESENTAÇÃO DAS PROPOSTAS\nLink para acesso às peças do concurso (URL): https://community.vortal.biz/Public/public-tender-documents/RjdFQ25HeG5nMk90SDMzY0QvcnNSK0NoZjlDTmNxcUFEbE1aS0VvRi84OFJGVDU4WjE0VXlueE16aEpVMkVUb0JTdHdHZFk5OEpsY3JOYmhBcTVETUE9PSE4d0dO\n\n20 - OUTROS REQUISITOS\nInformação sobre contratos reservados. Aplica-se a contratos reservados (54º-A)? Não\n\n21 - CRITÉRIO DE ADJUDICAÇÃO\nMultifator: Não\nMonofator:\nNome: Preço\n\n24 - CONDIÇÕES DO CONTRATO\nFaturação Eletrónica: Permitido\nObrigação de Subcontratação:\nCódigo da Obrigação de Subcontratação: Não é aplicável nenhuma obrigação de subcontratação.\n\n25 - COMPRA PÚBLICA ESTRATÉGICA\nCompra Pública Estratégica: Inexistência de contratação pública estratégica\n\n26 - INFORMAÇÕES ADICIONAIS\nContrato adequado para PME: Sim\nCobertura ACP (Acordo dos Contratos Públicos da Organização Mundial do Comércio): Não\n\n27 - IDENTIFICAÇÃO E CONTACTOS DO ÓRGÃO DE RECURSOS ADMINISTRATIVOS\nDesignação: Ministério da Administração Interna\nEndereço: Praça do Comércio - Ala Oriental\nCódigo postal: 1149-015\nLocalidade: Lisboa\nTelefone: +351 213409000\nFax: +351 213409000\nEndereço eletrónico: dpie@sg.mai.gov.pt\n\n28 - IDENTIFICAÇÃO DO(S) AUTOR(ES) DE ANÚNCIO\nNome: Ricardo Alberto Gasiba Carrilho\nCargo: Secretário Geral do Ministério da Administração Interna\n\n29 - ALTERAÇÃO\nIdentificador da Versão do Anúncio a Alterar: 86a29067-ef64-4451-ab1f-a55c8e392b87-01\nIdentificador das Secções Alteradas do Anúncio Anterior: Alteração\nAlteração dos Documentos do Concurso: Sim\nData de alteração dos documentos do concurso: 31-07-2025\n419383328",
    "nipc": "600014665",
    "distrito": "Lisboa",
    "concelho": "Lisboa",
    "freguesia": "Freguesia de Santa Maria Maior - Lisboa",
    "site": "www.sg.mai.gov.pt/",
    "email": "gab.sec.geral@sg.mai.gov.pt",
    "designacao_contrato": "Aquisição de Carabina para formação de caçadores, para a PSP, no âmbito do DLPIEFSS.",
    "descricao": "Aquisição de Carabina para formação de caçadores, para a PSP, no âmbito do DLPIEFSS.",
    "preco_base": "66.000,00 EUR",
    "prazo_execucao": "120 DIAS",
    "prazo_apresentacao_propostas": "12-08-2025 23:59",
    "fundos_eu": "Não",
    "plataforma_eletronica": "VORTAL",
    "url_procedimento": "https://community.vortal.biz/public/",
    "autor_nome": "Ricardo Alberto Gasiba Carrilho",
    "autor_cargo": "Secretário Geral do Ministério da Administração Interna"
  },
  {
    "numero_procedimento": "N/A",
    "entidade": "Câmara Municipal de Matosinhos",
    "link": "https://diariodarepublica.pt/dr/detalhe/contrato-publico/20684-927474326",
    "detalhes_completos": "1 - IDENTIFICAÇÃO E CONTACTOS DA ENTIDADE ADJUDICANTE\nDesignação da entidade adjudicante: Câmara Municipal de Matosinhos\nNIPC: 501305912\nServiço/Órgão/Pessoa de contacto: Divisão Contratação Pública\nEndereço: Av. D. Afonso Henriques\nCódigo postal: 4454-510\nLocalidade: Matosinhos\nPaís: Portugal\nNUT III: PT11A\nDistrito: Porto\nConcelho: Matosinhos\nFreguesia: Todas\nTelefone: 229390900\nFax: 229351645\nEndereço da Entidade (URL): http://www.cm-matosinhos.pt\nEndereço Eletrónico: contratacaopublica@cm-matosinhos.pt\neDelivery Gateway (URL): https://www.acingov.pt\nFunção da Organização: Adquirente\nSubfunção da Organização: Organização que recebe as propostas\nNorma jurídica da Entidade Adjudicante: Organismo de direito público\nÁrea de atividade da Autoridade Adjudicante: Serviços públicos das administrações públicas\n\n2 - JORNAL OFICIAL DA UNIÃO EUROPEIA\nO procedimento a que este anúncio diz respeito também é publicitado no Jornal Oficial da União Europeia? Não\n\n3 - AVISO\nModelo de Anúncio: Concurso público\nData de Envio do Anúncio: 31-07-2025\n\n5 - PROCESSO\nTipo de Procedimento: Concurso público\nPreço base do procedimento: Sim\nValor do preço base do procedimento: 330.000,00 EUR\nProcedimento com lotes? Não\n\n6 - OBJETO DO CONTRATO\nNúmero de referência interna: CP/2025/27714_REV 1.0\nDesignação do contrato: Trabalhos de Reabilitação na EB de Matosinhos\nDescrição: Trabalhos de Reabilitação na EB de Matosinhos\nTipo de Contrato Principal: Empreitada de Obras Públicas\nTipo de Contrato: Empreitada de Obras Públicas\nClassificação CPV (Vocabulário Comum para os Contratos Públicos)\nObjeto principal\nVocabulário Principal: 45453100\nPreço base s/IVA: 330.000,00 EUR\n\n7 - INDICAÇÕES ADICIONAIS\nO contrato envolve aquisição conjunta (satisfação de várias entidades)? Não\nO contrato é adjudicado por uma central de compras? Não\n\n8 - TÉCNICAS\nO concurso destina-se à celebração de um acordo-quadro? Inexistência de acordo-quadro\nÉ utilizado um leilão eletrónico? Não\nÉ adotada uma fase de negociação? Não\nSistema de Aquisição Dinâmico: Inexistência de sistema de aquisição dinâmico\n\n9 - LOCAL DA EXECUÇÃO DO CONTRATO\nLOCAL DA EXECUÇÃO DO CONTRATO (PROCEDIMENTO)\nPaís: Portugal\nNUT III: PT11A\nLocalidade: Matosinhos\nDistrito: Porto\nConcelho: Matosinhos\nFreguesia: Todas\n\n10 - PRAZO DE EXECUÇÃO DO CONTRATO\nPrazo de execução do contrato: 120 DIAS\nPrevisão de renovações: Não\n\n11 - FUNDOS EU\nTêm fundos EU? Não\n\n12 - DOCUMENTOS DE HABILITAÇÃO\nHabilitação para o exercício da atividade profissional: Sim\nTipo: Alvará\nDescrição: Categoria: 1ª Edifícios e património construído;\nSubcategoria: 5ª Estuques, pinturas e outros revestimentos.\n\n13 - CONDIÇÕES DE APRESENTAÇÃO\nPlataforma eletrónica utilizada pela entidade adjudicante: ACIN\nURL para Apresentação: https://www.acingov.pt\nAdmissibilidade da apresentação de propostas variantes: Não autorizado\nPrazo para apresentação das propostas: 18-08-2025 23:59\nPrazo durante o qual os concorrentes são obrigados a manter as respetivas propostas: 66 dias a contar do termo do prazo para a apresentação das propostas\nIndicação de Subcontratação na Proposta: Inexistência de indicação de subcontratação\n\n14 - PRESTAÇÃO DE CAUÇÃO\nPrestação de caução: Não\n\n15 - FORNECIMENTO DAS PEÇAS DO CONCURSO, APRESENTAÇÃO DE PEDIDOS DE PARTICIPAÇÃO E APRESENTAÇÃO DAS PROPOSTAS\nLink para acesso às peças do concurso (URL): https://www.acingov.pt/acingovprod/2/zonaPublica/zona_publica_c/donwloadProcedurePiece/OTMwMTY3\n\n20 - OUTROS REQUISITOS\nInformação sobre contratos reservados. Aplica-se a contratos reservados (54º-A)? Não\n\n21 - CRITÉRIO DE ADJUDICAÇÃO\nMultifator: Sim\nFator: \nNome: Preço\nPonderação: 60%\nSubfatores: Não\nFator: \nNome: Qualidade\nPonderação: 40%\nSubfatores: Não\n\n24 - CONDIÇÕES DO CONTRATO\nFaturação Eletrónica: Permitido\nObrigação de Subcontratação:\nCódigo da Obrigação de Subcontratação: Não é aplicável nenhuma obrigação de subcontratação.\n\n25 - COMPRA PÚBLICA ESTRATÉGICA\nCompra Pública Estratégica: Inexistência de contratação pública estratégica\n\n26 - INFORMAÇÕES ADICIONAIS\nContrato adequado para PME: Sim\nCobertura ACP (Acordo dos Contratos Públicos da Organização Mundial do Comércio): Não\n\n27 - IDENTIFICAÇÃO E CONTACTOS DO ÓRGÃO DE RECURSOS ADMINISTRATIVOS\nDesignação: Câmara Municipal\nEndereço: Av. D. Afonso Henriques\nCódigo postal: 4454-510\nLocalidade: Matosinhos\nTelefone: 229390900\nFax: \nEndereço eletrónico: contratacaopublica@cm-matosinhos.pt\nPrazo de interposição do recurso: 5 dias\n\n28 - IDENTIFICAÇÃO DO(S) AUTOR(ES) DE ANÚNCIO\nNome: Dra. Luísa Salgueiro\nCargo: Presidente da Câmara\n419377334",
    "nipc": "501305912",
    "distrito": "Porto",
    "concelho": "Matosinhos",
    "freguesia": "Todas",
    "site": "http://www.cm-matosinhos.pt",
    "email": "contratacaopublica@cm-matosinhos.pt",
    "designacao_contrato": "Trabalhos de Reabilitação na EB de Matosinhos",
    "descricao": "Trabalhos de Reabilitação na EB de Matosinhos",
    "preco_base": "330.000,00 EUR",
    "prazo_execucao": "120 DIAS",
    "prazo_apresentacao_propostas": "18-08-2025 23:59",
    "fundos_eu": "Não",
    "plataforma_eletronica": "ACIN",
    "url_procedimento": "https://www.acingov.pt",
    "autor_nome": "Dra. Luísa Salgueiro",
    "autor_cargo": "Presidente da Câmara"
  },
  {
    "numero_procedimento": "N/A",
    "entidade": "Câmara Municipal do Seixal",
    "link": "https://diariodarepublica.pt/dr/detalhe/contrato-publico/20686-927474327",
    "detalhes_completos": "1 - IDENTIFICAÇÃO E CONTACTOS DA ENTIDADE ADJUDICANTE\nDesignação da entidade adjudicante: Câmara Municipal do Seixal\nNIPC: 506173968\nServiço/Órgão/Pessoa de contacto: Divisão de Compras e Aprovisionamento\nEndereço: Rua Lino de Carvalho n.º 1\nCódigo postal: 2840-748\nLocalidade: Aldeia de Paio Pires\nPaís: Portugal\nNUT III: PT170\nDistrito: Setúbal\nConcelho: Seixal\nFreguesia: União das Freguesias do Seixal, Arrentela e Aldeia de Paio Pires\nTelefone: 212276700\nFax: 00\nEndereço da Entidade (URL): www.cm-seixal.pt\nEndereço Eletrónico: gestao.concursos@cm-seixal.pt\neDelivery Gateway (URL): https://www.acingov.pt\nFunção da Organização: Adquirente\nNorma jurídica da Entidade Adjudicante: Organismo de direito público\nÁrea de atividade da Autoridade Adjudicante: Serviços públicos das administrações públicas\n\n2 - JORNAL OFICIAL DA UNIÃO EUROPEIA\nO procedimento a que este anúncio diz respeito também é publicitado no Jornal Oficial da União Europeia? Não\n\n3 - AVISO\nModelo de Anúncio: Concurso público\nData de Envio do Anúncio: 31-07-2025\n\n5 - PROCESSO\nTipo de Procedimento: Concurso público\nPreço base do procedimento: Sim\nValor do preço base do procedimento: 170.000,00 EUR\nProcedimento com lotes? Não\n\n6 - OBJETO DO CONTRATO\nNúmero de referência interna: CP 1186/DCA/2025\nDesignação do contrato: Aquisição de serviços de lavagem e higienização de contentores de resíduos urbanos pelo período de 12 meses\nDescrição: Aquisição de serviços de lavagem e higienização de contentores de resíduos urbanos pelo período de 12 meses\nTipo de Contrato Principal: Aquisição de Serviços\nTipo de Contrato: Aquisição de Serviços\nClassificação CPV (Vocabulário Comum para os Contratos Públicos)\nObjeto principal\nVocabulário Principal: 90918000\nPreço base s/IVA: 170.000,00 EUR\n\n7 - INDICAÇÕES ADICIONAIS\nO contrato envolve aquisição conjunta (satisfação de várias entidades)? Não\nO contrato é adjudicado por uma central de compras? Não\n\n8 - TÉCNICAS\nO concurso destina-se à celebração de um acordo-quadro? Inexistência de acordo-quadro\nÉ utilizado um leilão eletrónico? Não\nÉ adotada uma fase de negociação? Não\nSistema de Aquisição Dinâmico: Inexistência de sistema de aquisição dinâmico\n\n9 - LOCAL DA EXECUÇÃO DO CONTRATO\nLOCAL DA EXECUÇÃO DO CONTRATO (PROCEDIMENTO)\nPaís: Portugal\nNUT III: PT170\nLocalidade: União das Freguesias do Seixal, Arrentela e Aldeia de Paio Pires\nDistrito: Setúbal\nConcelho: Seixal\nFreguesia: União das Freguesias do Seixal, Arrentela e Aldeia de Paio Pires\n\n10 - PRAZO DE EXECUÇÃO DO CONTRATO\nPrazo de execução do contrato: 12 MESES\nPrevisão de renovações: Não\n\n11 - FUNDOS EU\nTêm fundos EU? Não\n\n12 - DOCUMENTOS DE HABILITAÇÃO\nHabilitação para o exercício da atividade profissional: Não\n\n13 - CONDIÇÕES DE APRESENTAÇÃO\nPlataforma eletrónica utilizada pela entidade adjudicante: ACIN\nURL para Apresentação: https://www.acingov.pt\nAdmissibilidade da apresentação de propostas variantes: Não autorizado\nPrazo para apresentação das propostas: 10-08-2025 23:59\nPrazo durante o qual os concorrentes são obrigados a manter as respetivas propostas: 66 dias a contar do termo do prazo para a apresentação das propostas\nIndicação de Subcontratação na Proposta: Inexistência de indicação de subcontratação\n\n14 - PRESTAÇÃO DE CAUÇÃO\nPrestação de caução: Não\n\n15 - FORNECIMENTO DAS PEÇAS DO CONCURSO, APRESENTAÇÃO DE PEDIDOS DE PARTICIPAÇÃO E APRESENTAÇÃO DAS PROPOSTAS\nLink para acesso às peças do concurso (URL): https://www.acingov.pt/acingovprod/2/zonaPublica/zona_publica_c/donwloadProcedurePiece/OTMwNDkz\n\n20 - OUTROS REQUISITOS\nInformação sobre contratos reservados. Aplica-se a contratos reservados (54º-A)? Não\n\n21 - CRITÉRIO DE ADJUDICAÇÃO\nMultifator: Não\nMonofator:\nNome: Preço\n\n24 - CONDIÇÕES DO CONTRATO\nFaturação Eletrónica: Permitido\nObrigação de Subcontratação:\nCódigo da Obrigação de Subcontratação: Não é aplicável nenhuma obrigação de subcontratação.\n\n25 - COMPRA PÚBLICA ESTRATÉGICA\nCompra Pública Estratégica: Inexistência de contratação pública estratégica\n\n26 - INFORMAÇÕES ADICIONAIS\nContrato adequado para PME: Sim\nCobertura ACP (Acordo dos Contratos Públicos da Organização Mundial do Comércio): Não\n\n27 - IDENTIFICAÇÃO E CONTACTOS DO ÓRGÃO DE RECURSOS ADMINISTRATIVOS\nDesignação: Câmara Municipal do Seixal\nEndereço: Alameda dos Bombeiros Voluntários, 45\nCódigo postal: 2844-001\nLocalidade: Seixal\nTelefone: 212276700\nFax: \nEndereço eletrónico: gestao.concursos@cm-seixal.pt\n\n28 - IDENTIFICAÇÃO DO(S) AUTOR(ES) DE ANÚNCIO\nNome: Paulo Alexandre da Conceição Silva\nCargo: Presidente da Câmara Municipal do Seixal\n419384219",
    "nipc": "506173968",
    "distrito": "Setúbal",
    "concelho": "Seixal",
    "freguesia": "União das Freguesias do Seixal, Arrentela e Aldeia de Paio Pires",
    "site": "www.cm-seixal.pt",
    "email": "gestao.concursos@cm-seixal.pt",
    "designacao_contrato": "Aquisição de serviços de lavagem e higienização de contentores de resíduos urbanos pelo período de 12 meses",
    "descricao": "Aquisição de serviços de lavagem e higienização de contentores de resíduos urbanos pelo período de 12 meses",
    "preco_base": "170.000,00 EUR",
    "prazo_execucao": "12 MESES",
    "prazo_apresentacao_propostas": "10-08-2025 23:59",
    "fundos_eu": "Não",
    "plataforma_eletronica": "ACIN",
    "url_procedimento": "https://www.acingov.pt",
    "autor_nome": "Paulo Alexandre da Conceição Silva",
    "autor_cargo": "Presidente da Câmara Municipal do Seixal"
  },
  {
    "numero_procedimento": "N/A",
    "entidade": "Municipio de Oliveira de Azeméis",
    "link": "https://diariodarepublica.pt/dr/detalhe/contrato-publico/20689-927474328",
    "detalhes_completos": "1 - IDENTIFICAÇÃO E CONTACTOS DA ENTIDADE ADJUDICANTE\nDesignação da entidade adjudicante: Municipio de Oliveira de Azeméis\nNIPC: 506302970\nEndereço: Largo da Républica\nCódigo postal: 3720-240\nLocalidade: Oliveira de Azeméis\nPaís: Portugal\nNUT III: PT11A\nDistrito: Aveiro\nConcelho: Oliveira de Azemeis\nFreguesia: União das Freguesias de Oliveira de Azeméis, Santiago de Riba-Ul, Ul, Macinhata da Seixa e Madail\nTelefone: 256600600\nFax: 256600626\nEndereço da Entidade (URL): www.cm-oaz.pt\nEndereço Eletrónico: geral@cm-oaz.pt\neDelivery Gateway (URL): https://www.acingov.pt\nFunção da Organização: Adquirente\nNorma jurídica da Entidade Adjudicante: Organismo de direito público\nÁrea de atividade da Autoridade Adjudicante: Serviços públicos das administrações públicas\n\n2 - JORNAL OFICIAL DA UNIÃO EUROPEIA\nO procedimento a que este anúncio diz respeito também é publicitado no Jornal Oficial da União Europeia? Não\n\n3 - AVISO\nModelo de Anúncio: Concurso público\nData de Envio do Anúncio: 31-07-2025\n\n5 - PROCESSO\nTipo de Procedimento: Concurso público\nPreço base do procedimento: Sim\nValor do preço base do procedimento: 272.756,80 EUR\nProcedimento com lotes? Não\n\n6 - OBJETO DO CONTRATO\nNúmero de referência interna: CP/21/2025 (N.º 014/2025/DOMTE)\nDesignação do contrato: Reabilitação com Refuncionalização da Escola de Santo António - Ossela\nDescrição: Reabilitação com Refuncionalização da Escola de Santo António - Ossela \nTipo de Contrato Principal: Empreitada de Obras Públicas\nTipo de Contrato: Empreitada de Obras Públicas\nClassificação CPV (Vocabulário Comum para os Contratos Públicos)\nObjeto principal\nVocabulário Principal: 45212000\nPreço base s/IVA: 272.756,80 EUR\n\n7 - INDICAÇÕES ADICIONAIS\nO contrato envolve aquisição conjunta (satisfação de várias entidades)? Não\nO contrato é adjudicado por uma central de compras? Não\n\n8 - TÉCNICAS\nO concurso destina-se à celebração de um acordo-quadro? Inexistência de acordo-quadro\nÉ utilizado um leilão eletrónico? Não\nÉ adotada uma fase de negociação? Não\nSistema de Aquisição Dinâmico: Inexistência de sistema de aquisição dinâmico\n\n9 - LOCAL DA EXECUÇÃO DO CONTRATO\nLOCAL DA EXECUÇÃO DO CONTRATO (PROCEDIMENTO)\nPaís: Portugal\nNUT III: PT11A\nLocalidade: Freguesia de Ossela\nDistrito: Aveiro\nConcelho: Oliveira de Azemeis\nFreguesia: Freguesia de Ossela\n\n10 - PRAZO DE EXECUÇÃO DO CONTRATO\nPrazo de execução do contrato: 180 DIAS\nPrevisão de renovações: Não\n\n11 - FUNDOS EU\nTêm fundos EU? Não\n\n12 - DOCUMENTOS DE HABILITAÇÃO\nHabilitação para o exercício da atividade profissional: Sim\nTipo: Alvará\nDescrição: 1.ª subcategoria - Estruturas e elementos de betão da 1.ª categoria  Edifícios e património construído, a qual tem de ser de classe que cubra o valor global da proposta  e as 4.ª, 5.ª, 6.ª e 7.ª subcategorias da 1.ª categoria - Edifícios e património construído, as 1.ª e 12.ª subcategorias da 4.ª categoria  Instalações elétricas e mecânicas, e as 1.ª e 8.ª subcategorias da 5.ª categoria  Outros trabalhos e da classe correspondente ao valor dos trabalhos especializados que lhes correspondam.\n\n13 - CONDIÇÕES DE APRESENTAÇÃO\nPlataforma eletrónica utilizada pela entidade adjudicante: ACIN\nURL para Apresentação: https://www.acingov.pt\nAdmissibilidade da apresentação de propostas variantes: Não autorizado\nPrazo para apresentação das propostas: 15-08-2025 23:59\nPrazo durante o qual os concorrentes são obrigados a manter as respetivas propostas: 110 dias a contar do termo do prazo para a apresentação das propostas\nIndicação de Subcontratação na Proposta: Inexistência de indicação de subcontratação\n\n14 - PRESTAÇÃO DE CAUÇÃO\nPrestação de caução: Não\n\n15 - FORNECIMENTO DAS PEÇAS DO CONCURSO, APRESENTAÇÃO DE PEDIDOS DE PARTICIPAÇÃO E APRESENTAÇÃO DAS PROPOSTAS\nLink para acesso às peças do concurso (URL): https://www.acingov.pt/acingovprod/2/zonaPublica/zona_publica_c/donwloadProcedurePiece/OTMwNTM2\n\n20 - OUTROS REQUISITOS\nInformação sobre contratos reservados. Aplica-se a contratos reservados (54º-A)? Não\n\n21 - CRITÉRIO DE ADJUDICAÇÃO\nMultifator: Não\nMonofator:\nNome: Preço\n\n24 - CONDIÇÕES DO CONTRATO\nFaturação Eletrónica: Permitido\nObrigação de Subcontratação:\nCódigo da Obrigação de Subcontratação: Não é aplicável nenhuma obrigação de subcontratação.\n\n25 - COMPRA PÚBLICA ESTRATÉGICA\nCompra Pública Estratégica: Inexistência de contratação pública estratégica\n\n26 - INFORMAÇÕES ADICIONAIS\nContrato adequado para PME: Sim\nCobertura ACP (Acordo dos Contratos Públicos da Organização Mundial do Comércio): Não\n\n27 - IDENTIFICAÇÃO E CONTACTOS DO ÓRGÃO DE RECURSOS ADMINISTRATIVOS\nDesignação: Presidente da Câmara Municipal\nEndereço: Largo da República\nCódigo postal: 3720-240\nLocalidade: Oliveira de Azeméis\nTelefone: 256600600\nFax: 256674694\nEndereço eletrónico: presidencia@cm-oaz.pt\n\n28 - IDENTIFICAÇÃO DO(S) AUTOR(ES) DE ANÚNCIO\nNome: Joaquim Jorge Ferreira\nCargo: Presidente da Câmara Municipal\n419383311",
    "nipc": "506302970",
    "distrito": "Aveiro",
    "concelho": "Oliveira de Azemeis",
    "freguesia": "União das Freguesias de Oliveira de Azeméis, Santiago de Riba-Ul, Ul, Macinhata da Seixa e Madail",
    "site": "www.cm-oaz.pt",
    "email": "geral@cm-oaz.pt",
    "designacao_contrato": "Reabilitação com Refuncionalização da Escola de Santo António - Ossela",
    "descricao": "Reabilitação com Refuncionalização da Escola de Santo António - Ossela",
    "preco_base": "272.756,80 EUR",
    "prazo_execucao": "180 DIAS",
    "prazo_apresentacao_propostas": "15-08-2025 23:59",
    "fundos_eu": "Não",
    "plataforma_eletronica": "ACIN",
    "url_procedimento": "https://www.acingov.pt",
    "autor_nome": "Joaquim Jorge Ferreira",
    "autor_cargo": "Presidente da Câmara Municipal"
  },
  {
    "numero_procedimento": "N/A",
    "entidade": "Serviços de Ação Social da Universidade de Coimbra",
    "link": "https://diariodarepublica.pt/dr/detalhe/contrato-publico/20691-927474329",
    "detalhes_completos": "1 - IDENTIFICAÇÃO E CONTACTOS DA ENTIDADE ADJUDICANTE\nDesignação da entidade adjudicante: Serviços de Ação Social da Universidade de Coimbra\nNIPC: 600038106\nServiço/Órgão/Pessoa de contacto: SASUC-DCL\nEndereço: Rua Guilherme Moreira n.º12\nCódigo postal: 3000-210\nLocalidade: Coimbra\nPaís: Portugal\nNUT III: PT16E\nDistrito: Coimbra\nConcelho: Coimbra\nFreguesia: Todas\nTelefone: 239855950\nEndereço da Entidade (URL): https://www.uc.pt/sasuc/\nEndereço Eletrónico: dcl@sas.uc.pt\neDelivery Gateway (URL): https://www.acingov.pt\nFunção da Organização: Adquirente\nNorma jurídica da Entidade Adjudicante: Organismo de direito público\nÁrea de atividade da Autoridade Adjudicante: Educação\n\n2 - JORNAL OFICIAL DA UNIÃO EUROPEIA\nO procedimento a que este anúncio diz respeito também é publicitado no Jornal Oficial da União Europeia? Sim\n\n3 - AVISO\nModelo de Anúncio: Concurso público\nData de Envio do Anúncio: 29-07-2025\n\n5 - PROCESSO\nTipo de Procedimento: Concurso público\nPreço base do procedimento: Sim\nValor do preço base do procedimento: 421.023,40 EUR\nProcedimento com lotes? Sim\nNº Máx. de Lotes Autorizado: 14\nNúmero máximo de lotes que podem ser adjudicados a um concorrente: 14\n\n6 - OBJETO DO CONTRATO\nNúmero de referência interna: CPI05/25\nDesignação do contrato: CPI05/25\nDescrição: Aquisição, por lotes, de carne de suíno e produtos da agricultura.\nOpções: Não\nTipo de Contrato Principal: Aquisição de Bens Móveis\nTipo de Contrato: Aquisição de Bens Móveis\nClassificação CPV (Vocabulário Comum para os Contratos Públicos)\nObjeto principal\nVocabulário Principal: 15100000\nPreço base s/IVA: 227.317,85 EUR\nObjeto Complementar\nVocabulário Principal: 03000000\nPreço base s/IVA: 193.705,55 EUR\nLotes: \nNº: LOT-0001\nDescrição do Lote: Carne de suíno fresca\nPreço base s/IVA: 8.927,25 EUR\nClassificação CPV (Vocabulário Comum para os Contratos Públicos)\nObjeto principal\nVocabulário Principal: 15100000\nNº: LOT-0002\nDescrição do Lote: Carne de suíno fresca - Peças preparadas\nPreço base s/IVA: 91.554,00 EUR\nClassificação CPV (Vocabulário Comum para os Contratos Públicos)\nObjeto principal\nVocabulário Principal: 15100000\nNº: LOT-0003\nDescrição do Lote: Carne de suíno fresca, desossada/fatiada\nPreço base s/IVA: 33.425,00 EUR\nClassificação CPV (Vocabulário Comum para os Contratos Públicos)\nObjeto principal\nVocabulário Principal: 15100000\nNº: LOT-0004\nDescrição do Lote: Salsicharia, fiambre, hambúrgueres e fumados\nPreço base s/IVA: 18.591,10 EUR\nClassificação CPV (Vocabulário Comum para os Contratos Públicos)\nObjeto principal\nVocabulário Principal: 15100000\nNº: LOT-0005\nDescrição do Lote: Borrego / Cabrito\nPreço base s/IVA: 1.998,75 EUR\nClassificação CPV (Vocabulário Comum para os Contratos Públicos)\nObjeto principal\nVocabulário Principal: 15100000\nNº: LOT-0006\nDescrição do Lote: Carne de aves fresca\nPreço base s/IVA: 56.999,00 EUR\nClassificação CPV (Vocabulário Comum para os Contratos Públicos)\nObjeto principal\nVocabulário Principal: 15100000\nNº: LOT-0007\nDescrição do Lote: Charcutaria Diversa\nPreço base s/IVA: 15.822,75 EUR\nClassificação CPV (Vocabulário Comum para os Contratos Públicos)\nObjeto principal\nVocabulário Principal: 15100000\nNº: LOT-0008\nDescrição do Lote: Peixes\nPreço base s/IVA: 10.381,75 EUR\nClassificação CPV (Vocabulário Comum para os Contratos Públicos)\nObjeto principal\nVocabulário Principal: 03000000\nNº: LOT-0009\nDescrição do Lote: Produtos hortícolas frescos\nPreço base s/IVA: 52.465,60 EUR\nClassificação CPV (Vocabulário Comum para os Contratos Públicos)\nObjeto principal\nVocabulário Principal: 03000000\nNº: LOT-0010\nDescrição do Lote: Batatas e produtos hortícolas\nPreço base s/IVA: 16.488,00 EUR\nClassificação CPV (Vocabulário Comum para os Contratos Públicos)\nObjeto principal\nVocabulário Principal: 03000000\nNº: LOT-0011\nDescrição do Lote: Produtos IV Gama Transformados\nPreço base s/IVA: 51.750,00 EUR\nClassificação CPV (Vocabulário Comum para os Contratos Públicos)\nObjeto principal\nVocabulário Principal: 03000000\nNº: LOT-0012\nDescrição do Lote: Leguminosas secas\nPreço base s/IVA: 7.420,00 EUR\nClassificação CPV (Vocabulário Comum para os Contratos Públicos)\nObjeto principal\nVocabulário Principal: 03000000\nNº: LOT-0013\nDescrição do Lote: Frutas\nPreço base s/IVA: 35.400,20 EUR\nClassificação CPV (Vocabulário Comum para os Contratos Públicos)\nObjeto principal\nVocabulário Principal: 03000000\nNº: LOT-0014\nDescrição do Lote: Ovos\nPreço base s/IVA: 19.800,00 EUR\nClassificação CPV (Vocabulário Comum para os Contratos Públicos)\nObjeto principal\nVocabulário Principal: 03000000\n\n7 - INDICAÇÕES ADICIONAIS\nO contrato envolve aquisição conjunta (satisfação de várias entidades)? Não\nO contrato é adjudicado por uma central de compras? Não\n\n8 - TÉCNICAS\nO concurso destina-se à celebração de um acordo-quadro? Inexistência de acordo-quadro\nÉ utilizado um leilão eletrónico? Não\nÉ adotada uma fase de negociação? Não\nSistema de Aquisição Dinâmico: Inexistência de sistema de aquisição dinâmico\n\n9 - LOCAL DA EXECUÇÃO DO CONTRATO\nLOCAL DA EXECUÇÃO DO CONTRATO (PROCEDIMENTO)\nPaís: Portugal\nNUT III: PT16E\nLocalidade: Coimbra\nDistrito: Coimbra\nConcelho: Coimbra\nFreguesia: Todas\nLOCAL DA EXECUÇÃO DO CONTRATO (LOTE)\nIdentificador do Lote: LOT-0001; LOT-0002; LOT-0003; LOT-0004; LOT-0005; LOT-0006; LOT-0007; LOT-0008; LOT-0009; LOT-0010; LOT-0011; LOT-0012; LOT-0013; LOT-0014\nPaís: Portugal\nNUT III: PT16E\nLocalidade: Coimbra\nDistrito: Coimbra\nConcelho: Coimbra\nFreguesia: Todas\n\n10 - PRAZO DE EXECUÇÃO DO CONTRATO\nIdentificador do Lote: LOT-0001; LOT-0002; LOT-0003; LOT-0004; LOT-0005; LOT-0006; LOT-0007; LOT-0008; LOT-0009; LOT-0010; LOT-0011; LOT-0012; LOT-0013; LOT-0014\nPrazo de execução do contrato: 4 MESES\nPrevisão de renovações: Não\n\n11 - FUNDOS EU\nIdentificador do Lote: LOT-0001; LOT-0002; LOT-0003; LOT-0004; LOT-0005; LOT-0006; LOT-0007; LOT-0008; LOT-0009; LOT-0010; LOT-0011; LOT-0012; LOT-0013; LOT-0014\nTêm fundos EU? Não\n\n12 - DOCUMENTOS DE HABILITAÇÃO\nHabilitação para o exercício da atividade profissional: Não\n\n13 - CONDIÇÕES DE APRESENTAÇÃO\nPlataforma eletrónica utilizada pela entidade adjudicante: ACIN\nURL para Apresentação: https://www.acingov.pt\nAdmissibilidade da apresentação de propostas variantes: Não autorizado\nPrazo para apresentação das propostas: 31-08-2025 23:59\nPrazo durante o qual os concorrentes são obrigados a manter as respetivas propostas: 66 dias a contar do termo do prazo para a apresentação das propostas\nApresentação de Catálogo Eletrónico: Permitido\nIndicação de Subcontratação na Proposta: Inexistência de indicação de subcontratação\n\n14 - PRESTAÇÃO DE CAUÇÃO\nPrestação de caução: Não\n\n15 - FORNECIMENTO DAS PEÇAS DO CONCURSO, APRESENTAÇÃO DE PEDIDOS DE PARTICIPAÇÃO E APRESENTAÇÃO DAS PROPOSTAS\nLink para acesso às peças do concurso (URL): https://www.acingov.pt/acingovprod/2/zonaPublica/zona_publica_c/donwloadProcedurePiece/OTE5MDY5\n\n20 - OUTROS REQUISITOS\nIdentificador do Lote: LOT-0001; LOT-0002; LOT-0003; LOT-0004; LOT-0005; LOT-0006; LOT-0007; LOT-0008; LOT-0009; LOT-0010; LOT-0011; LOT-0012; LOT-0013; LOT-0014\nInformação sobre contratos reservados. Aplica-se a contratos reservados (54º-A)? Não\n\n21 - CRITÉRIO DE ADJUDICAÇÃO\nO Critério de adjudicação é diferenciado por lote? Não\nMultifator: Sim\nFator: \nNome: Outros\nOutro Nome: Outros\nPonderação: 100%\nSubfatores: Não\n\n24 - CONDIÇÕES DO CONTRATO\nIdentificador do Lote: LOT-0001; LOT-0002; LOT-0003; LOT-0004; LOT-0005; LOT-0006; LOT-0007; LOT-0008; LOT-0009; LOT-0010; LOT-0011; LOT-0012; LOT-0013; LOT-0014\nFaturação Eletrónica: Permitido\nObrigação de Subcontratação:\nCódigo da Obrigação de Subcontratação: Não é aplicável nenhuma obrigação de subcontratação.\n\n25 - COMPRA PÚBLICA ESTRATÉGICA\nCompra Pública Estratégica: Redução dos impactos ambientais\nDescrição do Processo de Adjudicação Estratégico: De acordo com peças procedimento.\nCritérios de contratos Públicos Ecológicos: Critérios de contratação pública ecológica nacional\nCategorias da estratégia nacional: Produtos alimentares, serviços de assistência de restauração (catering) e máquinas de distribuição automática\nDiretiva Veículos Não Poluentes: Não\nCritério de Acessibilidade: Os critérios de acessibilidade para as pessoas com deficiência não estão incluídos porque o contrato não se destina a pessoas singulares\n\n26 - INFORMAÇÕES ADICIONAIS\nIdentificador do Lote: LOT-0001; LOT-0002; LOT-0003; LOT-0004; LOT-0005; LOT-0006; LOT-0007; LOT-0008; LOT-0009; LOT-0010; LOT-0011; LOT-0012; LOT-0013; LOT-0014\nContrato adequado para PME: Sim\nCobertura ACP (Acordo dos Contratos Públicos da Organização Mundial do Comércio): Não\n\n27 - IDENTIFICAÇÃO E CONTACTOS DO ÓRGÃO DE RECURSOS ADMINISTRATIVOS\nDesignação: Reitor da UC\nEndereço: Paços das Escolas\nCódigo postal: 3000-210\nLocalidade: Coimbra\nTelefone: 239240855\nFax: \nEndereço eletrónico: dcl@sas.uc.pt\n\n28 - IDENTIFICAÇÃO DO(S) AUTOR(ES) DE ANÚNCIO\nNome: Amilcar Falcão\nCargo: Reitor\n419372814",
    "nipc": "600038106",
    "distrito": "Coimbra",
    "concelho": "Coimbra",
    "freguesia": "Todas",
    "site": "https://www.uc.pt/sasuc/",
    "email": "dcl@sas.uc.pt",
    "designacao_contrato": "CPI05/25",
    "descricao": "Aquisição, por lotes, de carne de suíno e produtos da agricultura.",
    "preco_base": "227.317,85 EUR",
    "prazo_execucao": "4 MESES",
    "prazo_apresentacao_propostas": "31-08-2025 23:59",
    "fundos_eu": "Não",
    "plataforma_eletronica": "ACIN",
    "url_procedimento": "https://www.acingov.pt",
    "autor_nome": "Amilcar Falcão",
    "autor_cargo": "Reitor"
  },
  {
    "numero_procedimento": "N/A",
    "entidade": "CASA PIA DE LISBOA, I.P.",
    "link": "https://diariodarepublica.pt/dr/detalhe/contrato-publico/20693-927474330",
    "detalhes_completos": "1 - IDENTIFICAÇÃO E CONTACTOS DA ENTIDADE ADJUDICANTE\nDesignação da entidade adjudicante: CASA PIA DE LISBOA, I.P.\nNIPC: 501390642\nServiço/Órgão/Pessoa de contacto: Casa Pia de Lisboa, I. P. Unidade de Contratação Pública João Paulo Felício\nEndereço: Avenida do Restelo n.º 1\nCódigo postal: 1449-008\nLocalidade: Lisboa\nPaís: Portugal\nNUT III: PT170\nDistrito: Lisboa\nConcelho: Lisboa\nFreguesia: Freguesia de Belém\nTelefone: 213614000\nFax: 213614030\nEndereço da Entidade (URL): www.casapia.pt\nEndereço Eletrónico: contratacao.publica@casapia.pt\neDelivery Gateway (URL): https://www.acingov.pt\nFunção da Organização: Adquirente\nNorma jurídica da Entidade Adjudicante: Organismo de direito público\nÁrea de atividade da Autoridade Adjudicante: Proteção social\n\n2 - JORNAL OFICIAL DA UNIÃO EUROPEIA\nO procedimento a que este anúncio diz respeito também é publicitado no Jornal Oficial da União Europeia? Não\n\n3 - AVISO\nModelo de Anúncio: Concurso público\nData de Envio do Anúncio: 31-07-2025\n\n5 - PROCESSO\nTipo de Procedimento: Concurso público\nPreço base do procedimento: Sim\nValor do preço base do procedimento: 58.115,00 EUR\nProcedimento com lotes? Sim\nNº Máx. de Lotes Autorizado: 10\nNúmero máximo de lotes que podem ser adjudicados a um concorrente: 10\n\n6 - OBJETO DO CONTRATO\nNúmero de referência interna: 2525000372\nDesignação do contrato: Aquisição de Instrumentos e Materiais para Instrumentos Musicais\nDescrição: Aquisição de Instrumentos e Materiais para Instrumentos Musicais\nTipo de Contrato Principal: Aquisição de Bens Móveis\nTipo de Contrato: Aquisição de Bens Móveis\nClassificação CPV (Vocabulário Comum para os Contratos Públicos)\nObjeto principal\nVocabulário Principal: 37300000\nPreço base s/IVA: 58.115,00 EUR\nLotes: \nNº: LOT-0001\nDescrição do Lote: Instrumentos musicais de cordas\nPreço base s/IVA: 20.970,00 EUR\nClassificação CPV (Vocabulário Comum para os Contratos Públicos)\nObjeto principal\nVocabulário Principal: 37313000\nNº: LOT-0002\nDescrição do Lote: Acessórios para instrumentos de cordas\nPreço base s/IVA: 19.340,00 EUR\nClassificação CPV (Vocabulário Comum para os Contratos Públicos)\nObjeto principal\nVocabulário Principal: 37321300\nNº: LOT-0003\nDescrição do Lote: Equipamento de som\nPreço base s/IVA: 6.400,00 EUR\nClassificação CPV (Vocabulário Comum para os Contratos Públicos)\nObjeto principal\nVocabulário Principal: 32342410\nNº: LOT-0004\nDescrição do Lote: Pianos\nPreço base s/IVA: 2.250,00 EUR\nClassificação CPV (Vocabulário Comum para os Contratos Públicos)\nObjeto principal\nVocabulário Principal: 37311100\nNº: LOT-0005\nDescrição do Lote: Equipamento e produtos auxiliares de transporte\nPreço base s/IVA: 960,00 EUR\nClassificação CPV (Vocabulário Comum para os Contratos Públicos)\nObjeto principal\nVocabulário Principal: 34000000\nNº: LOT-0006\nDescrição do Lote: Instrumentos musicais de sopro\nPreço base s/IVA: 1.800,00 EUR\nClassificação CPV (Vocabulário Comum para os Contratos Públicos)\nObjeto principal\nVocabulário Principal: 37314000\nNº: LOT-0007\nDescrição do Lote: Peças e acessórios para instrumentos musicais\nPreço base s/IVA: 925,00 EUR\nClassificação CPV (Vocabulário Comum para os Contratos Públicos)\nObjeto principal\nVocabulário Principal: 37320000\nNº: LOT-0008\nDescrição do Lote: Instrumentos musicais de percussão\nPreço base s/IVA: 450,00 EUR\nClassificação CPV (Vocabulário Comum para os Contratos Públicos)\nObjeto principal\nVocabulário Principal: 37316000\nNº: LOT-0009\nDescrição do Lote: Peças e acessórios para instrumentos musicais\nPreço base s/IVA: 4.450,00 EUR\nClassificação CPV (Vocabulário Comum para os Contratos Públicos)\nObjeto principal\nVocabulário Principal: 37320000\nNº: LOT-0010\nDescrição do Lote: Peças e acessórios para instrumentos musicais\nPreço base s/IVA: 570,00 EUR\nClassificação CPV (Vocabulário Comum para os Contratos Públicos)\nObjeto principal\nVocabulário Principal: 37320000\n\n7 - INDICAÇÕES ADICIONAIS\nO contrato envolve aquisição conjunta (satisfação de várias entidades)? Não\nO contrato é adjudicado por uma central de compras? Não\n\n8 - TÉCNICAS\nO concurso destina-se à celebração de um acordo-quadro? Inexistência de acordo-quadro\nÉ utilizado um leilão eletrónico? Não\nÉ adotada uma fase de negociação? Não\nSistema de Aquisição Dinâmico: Inexistência de sistema de aquisição dinâmico\n\n9 - LOCAL DA EXECUÇÃO DO CONTRATO\nLOCAL DA EXECUÇÃO DO CONTRATO (PROCEDIMENTO)\nPaís: Portugal\nNUT III: PT170\nLocalidade: Lisboa\nDistrito: Lisboa\nConcelho: Lisboa\nFreguesia: Freguesia de Belém\nLOCAL DA EXECUÇÃO DO CONTRATO (LOTE)\nIdentificador do Lote: LOT-0001; LOT-0002; LOT-0003; LOT-0004; LOT-0005; LOT-0006; LOT-0007; LOT-0008; LOT-0009; LOT-0010\nPaís: Portugal\nNUT III: PT170\nLocalidade: Lisboa\nDistrito: Lisboa\nConcelho: Lisboa\nFreguesia: Freguesia de Belém\n\n10 - PRAZO DE EXECUÇÃO DO CONTRATO\nIdentificador do Lote: LOT-0001; LOT-0002; LOT-0003; LOT-0004; LOT-0005; LOT-0006; LOT-0007; LOT-0008; LOT-0009; LOT-0010\nPrazo de execução do contrato: 30 DIAS\nPrevisão de renovações: Não\n\n11 - FUNDOS EU\nIdentificador do Lote: LOT-0001; LOT-0002; LOT-0003; LOT-0004; LOT-0005; LOT-0006; LOT-0007; LOT-0008; LOT-0009; LOT-0010\nTêm fundos EU? Não\n\n12 - DOCUMENTOS DE HABILITAÇÃO\nHabilitação para o exercício da atividade profissional: Não\n\n13 - CONDIÇÕES DE APRESENTAÇÃO\nPlataforma eletrónica utilizada pela entidade adjudicante: ACIN\nURL para Apresentação: https://www.acingov.pt\nAdmissibilidade da apresentação de propostas variantes: Não autorizado\nPrazo para apresentação das propostas: 09-08-2025 23:59\nPrazo durante o qual os concorrentes são obrigados a manter as respetivas propostas: 66 dias a contar do termo do prazo para a apresentação das propostas\nIndicação de Subcontratação na Proposta: Inexistência de indicação de subcontratação\n\n14 - PRESTAÇÃO DE CAUÇÃO\nPrestação de caução: Não\n\n15 - FORNECIMENTO DAS PEÇAS DO CONCURSO, APRESENTAÇÃO DE PEDIDOS DE PARTICIPAÇÃO E APRESENTAÇÃO DAS PROPOSTAS\nLink para acesso às peças do concurso (URL): https://www.acingov.pt/acingovprod/2/zonaPublica/zona_publica_c/donwloadProcedurePiece/OTMwMzYz\n\n20 - OUTROS REQUISITOS\nIdentificador do Lote: LOT-0001; LOT-0002; LOT-0003; LOT-0004; LOT-0005; LOT-0006; LOT-0007; LOT-0008; LOT-0009; LOT-0010\nInformação sobre contratos reservados. Aplica-se a contratos reservados (54º-A)? Não\n\n21 - CRITÉRIO DE ADJUDICAÇÃO\nO Critério de adjudicação é diferenciado por lote? Não\nMultifator: Não\nMonofator:\nNome: Preço\n\n24 - CONDIÇÕES DO CONTRATO\nIdentificador do Lote: LOT-0001; LOT-0002; LOT-0003; LOT-0004; LOT-0005; LOT-0006; LOT-0007; LOT-0008; LOT-0009; LOT-0010\nFaturação Eletrónica: Necessário\nObrigação de Subcontratação:\nCódigo da Obrigação de Subcontratação: Não é aplicável nenhuma obrigação de subcontratação.\n\n25 - COMPRA PÚBLICA ESTRATÉGICA\nCompra Pública Estratégica: Inexistência de contratação pública estratégica\n\n26 - INFORMAÇÕES ADICIONAIS\nIdentificador do Lote: LOT-0001; LOT-0002; LOT-0003; LOT-0004; LOT-0005; LOT-0006; LOT-0007; LOT-0008; LOT-0009; LOT-0010\nContrato adequado para PME: Não\nCobertura ACP (Acordo dos Contratos Públicos da Organização Mundial do Comércio): Não\n\n27 - IDENTIFICAÇÃO E CONTACTOS DO ÓRGÃO DE RECURSOS ADMINISTRATIVOS\nDesignação: Conselho Diretivo\nEndereço: Av. do Restelo, 1\nCódigo postal: 1449-008\nLocalidade: LISBOA\nTelefone: 213614000\nFax: \nEndereço eletrónico: contratacao.publica@casapia.pt\n\n28 - IDENTIFICAÇÃO DO(S) AUTOR(ES) DE ANÚNCIO\nNome: João Paulo Barra Ludovino Mota Croa Felicio\nCargo: Técnico Superior\n419379765",
    "nipc": "501390642",
    "distrito": "Lisboa",
    "concelho": "Lisboa",
    "freguesia": "Freguesia de Belém",
    "site": "www.casapia.pt",
    "email": "contratacao.publica@casapia.pt",
    "designacao_contrato": "Aquisição de Instrumentos e Materiais para Instrumentos Musicais",
    "descricao": "Aquisição de Instrumentos e Materiais para Instrumentos Musicais",
    "preco_base": "58.115,00 EUR",
    "prazo_execucao": "30 DIAS",
    "prazo_apresentacao_propostas": "09-08-2025 23:59",
    "fundos_eu": "Não",
    "plataforma_eletronica": "ACIN",
    "url_procedimento": "https://www.acingov.pt",
    "autor_nome": "João Paulo Barra Ludovino Mota Croa Felicio",
    "autor_cargo": "Técnico Superior"
  },
  {
    "numero_procedimento": "N/A",
    "entidade": "Foco Saúde, S.A.",
    "link": "https://diariodarepublica.pt/dr/detalhe/contrato-publico/20699-927474334",
    "detalhes_completos": "Alteração do Anúncio de procedimento n.º 18287/2025, de 2025-07-10, com o ID 419275136\n\n1 - IDENTIFICAÇÃO E CONTACTOS DA ENTIDADE ADJUDICANTE\nDesignação da entidade adjudicante: Foco Saúde, S.A.\nNIPC: 515189928\nServiço/Órgão/Pessoa de contacto: Direção da FOCO SAÚDE, S.A.\nEndereço: Rua Comendador Inácio Souza, Nº 776\nCódigo postal: 4430-362\nLocalidade: Vila Nova de Gaia\nPaís: Portugal\nNUT III: PT11A\nDistrito: Porto\nConcelho: Vila Nova de Gaia\nFreguesia: Freguesia de Canidelo - Vila Nova de Gaia\nTelefone: 220404440\nFax: 220404440\nEndereço da Entidade (URL): www.focosaude.pt\nEndereço Eletrónico: info@focosaude.pt\neDelivery Gateway (URL): https://www.acingov.pt\nFunção da Organização: Adquirente\nSubfunção da Organização: Organização que recebe as propostas\nNorma jurídica da Entidade Adjudicante: Organismo de direito público\nÁrea de atividade da Autoridade Adjudicante: Serviços públicos das administrações públicas\n\n2 - JORNAL OFICIAL DA UNIÃO EUROPEIA\nO procedimento a que este anúncio diz respeito também é publicitado no Jornal Oficial da União Europeia? Sim\n\n3 - AVISO\nModelo de Anúncio: Concurso público\nData de Envio do Anúncio: 29-07-2025\n\n5 - PROCESSO\nTipo de Procedimento: Concurso público\nPreço base do procedimento: Sim\nValor do preço base do procedimento: 13.780.000,00 EUR\nProcedimento com lotes? Não\n\n6 - OBJETO DO CONTRATO\nNúmero de referência interna: CPI 01/2025\nDesignação do contrato: Construção de Unidade de Cuidados Continuados Rua Quinta da Bela Vista  Vila Nova de Gaia\nDescrição: Construção de Unidade de Cuidados Continuados Rua Quinta da Bela Vista  Vila Nova de Gaia \nOpções: Não\nTipo de Contrato Principal: Empreitada de Obras Públicas\nTipo de Contrato: Empreitada de Obras Públicas\nClassificação CPV (Vocabulário Comum para os Contratos Públicos)\nObjeto principal\nVocabulário Principal: 45215100\nPreço base s/IVA: 13.780.000,00 EUR\n\n7 - INDICAÇÕES ADICIONAIS\nO contrato envolve aquisição conjunta (satisfação de várias entidades)? Não\nO contrato é adjudicado por uma central de compras? Não\n\n8 - TÉCNICAS\nO concurso destina-se à celebração de um acordo-quadro? Inexistência de acordo-quadro\nÉ utilizado um leilão eletrónico? Não\nÉ adotada uma fase de negociação? Não\nSistema de Aquisição Dinâmico: Inexistência de sistema de aquisição dinâmico\n\n9 - LOCAL DA EXECUÇÃO DO CONTRATO\nLOCAL DA EXECUÇÃO DO CONTRATO (PROCEDIMENTO)\nPaís: Portugal\nNUT III: PT111\nLocalidade: Porto\nDistrito: Porto\nConcelho: Vila Nova de Gaia\nFreguesia: Todas\n\n10 - PRAZO DE EXECUÇÃO DO CONTRATO\nPrazo de execução do contrato: 16 MESES\nPrevisão de renovações: Não\n\n11 - FUNDOS EU\nTêm fundos EU? Não\n\n12 - DOCUMENTOS DE HABILITAÇÃO\nHabilitação para o exercício da atividade profissional: Sim\nTipo: Alvará\nDescrição: Habilitações de acordo com o que consta na alínea e) do n.º 1 do artigo 16.º do Programa de Procedimento\n\n13 - CONDIÇÕES DE APRESENTAÇÃO\nPlataforma eletrónica utilizada pela entidade adjudicante: ACIN\nURL para Apresentação: https://www.acingov.pt\nAdmissibilidade da apresentação de propostas variantes: Não autorizado\nPrazo para apresentação das propostas: 08-08-2025 17:00\nPrazo durante o qual os concorrentes são obrigados a manter as respetivas propostas: 90 dias a contar do termo do prazo para a apresentação das propostas\nApresentação de Catálogo Eletrónico: Não autorizado\nIndicação de Subcontratação na Proposta: Inexistência de indicação de subcontratação\n\n14 - PRESTAÇÃO DE CAUÇÃO\nPrestação de caução: Sim\nPercentagem: 5%\nDescrição da Garantia Exigida: O valor da caução é de 5.00% do preço contratual.\n\n15 - FORNECIMENTO DAS PEÇAS DO CONCURSO, APRESENTAÇÃO DE PEDIDOS DE PARTICIPAÇÃO E APRESENTAÇÃO DAS PROPOSTAS\nLink para acesso às peças do concurso (URL): https://www.acingov.pt/acingovprod/2/zonaPublica/zona_publica_c/donwloadProcedurePiece/OTE3MjM4\n\n20 - OUTROS REQUISITOS\nInformação sobre contratos reservados. Aplica-se a contratos reservados (54º-A)? Não\n\n21 - CRITÉRIO DE ADJUDICAÇÃO\nMultifator: Não\nMonofator:\nNome: Preço\n\n24 - CONDIÇÕES DO CONTRATO\nFaturação Eletrónica: Permitido\nObrigação de Subcontratação:\nCódigo da Obrigação de Subcontratação: Não é aplicável nenhuma obrigação de subcontratação.\n\n25 - COMPRA PÚBLICA ESTRATÉGICA\nCompra Pública Estratégica: Inexistência de contratação pública estratégica\n\n26 - INFORMAÇÕES ADICIONAIS\nContrato adequado para PME: Sim\nCobertura ACP (Acordo dos Contratos Públicos da Organização Mundial do Comércio): Não\n\n27 - IDENTIFICAÇÃO E CONTACTOS DO ÓRGÃO DE RECURSOS ADMINISTRATIVOS\nDesignação: Administração da Foco Saúde, S.A.\nEndereço: Rua Comendador Inácio Souza, Nº 776\nCódigo postal: 4430-362\nLocalidade: Vila Nova de Gaia\nTelefone: 220404440\nFax: 220404440\nEndereço eletrónico: info@focosaude.pt\nPrazo de interposição do recurso: 10 dias\n\n28 - IDENTIFICAÇÃO DO(S) AUTOR(ES) DE ANÚNCIO\nNome: Manuel Carlos Miranda Borges\nCargo: Administrador\n\n29 - ALTERAÇÃO\nMotivo da Alteração: Correção pelo adquirente\nIdentificador da Versão do Anúncio a Alterar: bc277cd1-6a0d-43e3-a443-8731e5603f29-01\nIdentificador das Secções Alteradas do Anúncio Anterior: Processo; Condições de Apresentação\nDescrição das Alterações: Modificação do prazo para a apresentação de propostas\nAlteração dos Documentos do Concurso: Sim\nData de alteração dos documentos do concurso: 29-07-2025\n419373502",
    "nipc": "515189928",
    "distrito": "Porto",
    "concelho": "Vila Nova de Gaia",
    "freguesia": "Freguesia de Canidelo - Vila Nova de Gaia",
    "site": "www.focosaude.pt",
    "email": "info@focosaude.pt",
    "designacao_contrato": "Construção de Unidade de Cuidados Continuados Rua Quinta da Bela Vista  Vila Nova de Gaia",
    "descricao": "Construção de Unidade de Cuidados Continuados Rua Quinta da Bela Vista  Vila Nova de Gaia",
    "preco_base": "13.780.000,00 EUR",
    "prazo_execucao": "16 MESES",
    "prazo_apresentacao_propostas": "08-08-2025 17:00",
    "fundos_eu": "Não",
    "plataforma_eletronica": "ACIN",
    "url_procedimento": "https://www.acingov.pt",
    "autor_nome": "Manuel Carlos Miranda Borges",
    "autor_cargo": "Administrador"
  },
  {
    "numero_procedimento": "N/A",
    "entidade": "AdRA - Águas da Região de Aveiro, S.A.",
    "link": "https://diariodarepublica.pt/dr/detalhe/contrato-publico/20701-927474335",
    "detalhes_completos": "1 - IDENTIFICAÇÃO E CONTACTOS DA ENTIDADE ADJUDICANTE\nDesignação da entidade adjudicante: AdRA - Águas da Região de Aveiro, S.A.\nNIPC: 509107630\nServiço/Órgão/Pessoa de contacto: Compras e Logística\nEndereço: Travessa do rua da Paz, nº 4\nCódigo postal: 3800-587\nLocalidade: Cacia - Aveiro\nPaís: Portugal\nNUT III: PT16D\nDistrito: Aveiro\nConcelho: Aveiro\nFreguesia: Freguesia de Cacia\nTelefone: 234910200\nFax: 234910299\nEndereço da Entidade (URL): www.adra.pt\nEndereço Eletrónico: adra@adp.pt\neDelivery Gateway (URL): https://www.acingov.pt\nFunção da Organização: Adquirente\nSubfunção da Organização: Organização cujo orçamento é utilizado para pagar o contrato; Organização que executa o pagamento; Organização responsável pelo tratamento das propostas; Organização que recebe as propostas; Organização que trata os pedidos de participação; Organização que recebe pedidos de participação; Organização que assina o contrato\nNorma jurídica da Entidade Adjudicante: Organismo de direito público\nÁrea de atividade da Autoridade Adjudicante: Proteção ambiental\n\n2 - JORNAL OFICIAL DA UNIÃO EUROPEIA\nO procedimento a que este anúncio diz respeito também é publicitado no Jornal Oficial da União Europeia? Sim\n\n3 - AVISO\nModelo de Anúncio: Concurso limitado por prévia qualificação\nData de Envio do Anúncio: 30-07-2025\n\n5 - PROCESSO\nTipo de Procedimento: Concurso limitado por prévia qualificação\nPreço base do procedimento: Sim\nValor do preço base do procedimento: 1.427.260,00 EUR\nProcedimento com lotes? Não\n\n6 - OBJETO DO CONTRATO\nNúmero de referência interna: CLPQ/2025/03_SE\nDesignação do contrato: CLPQ/2025/03_SE - Aquisição de serviços de vigilância humana e ligações a central de receção de alarmes dos sistemas de segurança eletrónica da AdRA\nDescrição: CLPQ/2025/03_SE - Aquisição de serviços de vigilância humana e ligações a central de receção de alarmes dos sistemas de segurança eletrónica da AdRA\nOpções: Não\nTipo de Contrato Principal: Aquisição de Serviços\nTipo de Contrato: Aquisição de Serviços\nClassificação CPV (Vocabulário Comum para os Contratos Públicos)\nObjeto principal\nVocabulário Principal: 79714000\nPreço base s/IVA: 1.427.260,00 EUR\n\n7 - INDICAÇÕES ADICIONAIS\nO contrato envolve aquisição conjunta (satisfação de várias entidades)? Não\nO contrato é adjudicado por uma central de compras? Não\n\n8 - TÉCNICAS\nO concurso destina-se à celebração de um acordo-quadro? Inexistência de acordo-quadro\nÉ utilizado um leilão eletrónico? Não\nSistema de Aquisição Dinâmico: Inexistência de sistema de aquisição dinâmico\n\n9 - LOCAL DA EXECUÇÃO DO CONTRATO\nLOCAL DA EXECUÇÃO DO CONTRATO (PROCEDIMENTO)\nPaís: Portugal\nNUT III: PT16D\nLocalidade: Freguesia de Cacia\nDistrito: Aveiro\nConcelho: Aveiro\nFreguesia: Freguesia de Cacia\n\n10 - PRAZO DE EXECUÇÃO DO CONTRATO\nPrazo de execução do contrato: 12 MESES\nPrevisão de renovações: Sim\nIndicar número máximo de renovações: 2\nPrazo de renovações diferente do prazo inicial: Não\n\n11 - FUNDOS EU\nTêm fundos EU? Não\n\n12 - DOCUMENTOS DE HABILITAÇÃO\nHabilitação para o exercício da atividade profissional: Não\n\n13 - CONDIÇÕES DE APRESENTAÇÃO\nPlataforma eletrónica utilizada pela entidade adjudicante: ACIN\nURL para Apresentação: https://www.acingov.pt\nAdmissibilidade da apresentação de propostas variantes: Não autorizado\nPrazo para apresentação das candidaturas: 02-09-2025 18:00\nPrazo para a decisão de qualificação: 44 dias a contar do termo do prazo para a apresentação das candidaturas\nRequisitos mínimos \nRequisitos mínimos de capacidade técnica: Experiência curricular, recursos humanos, tecnológicos, de equipamentos e outros; Sistema de controlo de qualidade \nRequisitos mínimos de capacidade financeira: V ≤ R\nem que:\nV = preço contratual (1.427.260,00)\nR = valor médio do EBITDA relativo aos últimos 3 (três) exercícios encerrados contabilisticamente\n\nPrazo durante o qual os concorrentes são obrigados a manter as respetivas propostas: 90 dias a contar do termo do prazo para a apresentação das propostas\nApresentação de Catálogo Eletrónico: Não autorizado\nIndicação de Subcontratação na Proposta: Inexistência de indicação de subcontratação\n\n14 - PRESTAÇÃO DE CAUÇÃO\nPrestação de caução: Sim\nPercentagem: 3%\nDescrição da Garantia Exigida: O valor da caução é de 3.00% do preço contratual.\n\n15 - FORNECIMENTO DAS PEÇAS DO CONCURSO, APRESENTAÇÃO DE PEDIDOS DE PARTICIPAÇÃO E APRESENTAÇÃO DAS PROPOSTAS\nLink para acesso às peças do concurso (URL): https://www.acingov.pt/acingovprod/2/zonaPublica/zona_publica_c/donwloadProcedurePiece/OTI5NDY1\n\n20 - OUTROS REQUISITOS\nInformação sobre contratos reservados. Aplica-se a contratos reservados (54º-A)? Não\n\n21 - CRITÉRIO DE ADJUDICAÇÃO\nMultifator: Não\nMonofator:\nNome: Preço\n\n24 - CONDIÇÕES DO CONTRATO\nFaturação Eletrónica: Necessário\nObrigação de Subcontratação:\nCódigo da Obrigação de Subcontratação: Não é aplicável nenhuma obrigação de subcontratação.\n\n25 - COMPRA PÚBLICA ESTRATÉGICA\nCompra Pública Estratégica: Inexistência de contratação pública estratégica\n\n26 - INFORMAÇÕES ADICIONAIS\nContrato adequado para PME: Sim\nCobertura ACP (Acordo dos Contratos Públicos da Organização Mundial do Comércio): Não\n\n27 - IDENTIFICAÇÃO E CONTACTOS DO ÓRGÃO DE RECURSOS ADMINISTRATIVOS\nDesignação: Conselho de Administração\nEndereço: Travessa do rua da Paz, nº 4\nCódigo postal: 3800-587\nLocalidade: Cacia - Aveiro\nTelefone: 234910200\nFax: \nEndereço eletrónico: adra@adp.pt\nPrazo de interposição do recurso: 30 dias\n\n28 - IDENTIFICAÇÃO DO(S) AUTOR(ES) DE ANÚNCIO\nNome: Anabela Carvalhinhos\nCargo: Gestora do Procedimento\n419372685",
    "nipc": "509107630",
    "distrito": "Aveiro",
    "concelho": "Aveiro",
    "freguesia": "Freguesia de Cacia",
    "site": "www.adra.pt",
    "email": "adra@adp.pt",
    "designacao_contrato": "CLPQ/2025/03_SE - Aquisição de serviços de vigilância humana e ligações a central de receção de alarmes dos sistemas de segurança eletrónica da AdRA",
    "descricao": "CLPQ/2025/03_SE - Aquisição de serviços de vigilância humana e ligações a central de receção de alarmes dos sistemas de segurança eletrónica da AdRA",
    "preco_base": "1.427.260,00 EUR",
    "prazo_execucao": "12 MESES",
    "prazo_apresentacao_propostas": null,
    "fundos_eu": "Não",
    "plataforma_eletronica": "ACIN",
    "url_procedimento": "https://www.acingov.pt",
    "autor_nome": "Anabela Carvalhinhos",
    "autor_cargo": "Gestora do Procedimento"
  }
]