[
  {
    "numero_procedimento": "N/A",
    "entidade": "AnÃºncio de procedimento  n.Âº 23102/2025  -  DiÃ¡rio da RepÃºblica n.Âº 167/2025, SÃ©rie II de 2025-09-01",
    "link": "https://diariodarepublica.pt/dr/detalhe/contrato-publico/23102-933628155"
  },
  {
    "numero_procedimento": "N/A",
    "entidade": "AnÃºncio de procedimento  n.Âº 23103/2025  -  DiÃ¡rio da RepÃºblica n.Âº 167/2025, SÃ©rie II de 2025-09-01",
    "link": "https://diariodarepublica.pt/dr/detalhe/contrato-publico/23103-933628156"
  },
  {
    "numero_procedimento": "N/A",
    "entidade": "AnÃºncio de procedimento  n.Âº 23104/2025  -  DiÃ¡rio da RepÃºblica n.Âº 167/2025, SÃ©rie II de 2025-09-01",
    "link": "https://diariodarepublica.pt/dr/detalhe/contrato-publico/23104-933628157"
  },
  {
    "numero_procedimento": "N/A",
    "entidade": "AnÃºncio de procedimento  n.Âº 23105/2025  -  DiÃ¡rio da RepÃºblica n.Âº 167/2025, SÃ©rie II de 2025-09-01",
    "link": "https://diariodarepublica.pt/dr/detalhe/contrato-publico/23105-933628158"
  },
  {
    "numero_procedimento": "N/A",
    "entidade": "Serviços Municipalizados de Castelo Branco",
    "link": "https://diariodarepublica.pt/dr/detalhe/contrato-publico/23109-933628159",
    "detalhes_completos": "1 - IDENTIFICAÇÃO E CONTACTOS DA ENTIDADE ADJUDICANTE\nDesignação da entidade adjudicante: Serviços Municipalizados de Castelo Branco\nNIPC: 680017640\nServiço/Órgão/Pessoa de contacto: Conselho de Administração\nEndereço: Av. Nuno Álvares Nº 32 r/c\nCódigo postal: 6000-083\nLocalidade: Castelo Branco\nPaís: Portugal\nNUT III: PT16H\nDistrito: Castelo Branco\nConcelho: Castelo Branco\nFreguesia: Todas\nTelefone: 272340500\nFax: 272340501\nEndereço da Entidade (URL): www.sm-castelobranco.pt\nEndereço Eletrónico: geral@sm-castelobranco.pt\neDelivery Gateway (URL): https://www.acingov.pt\nFunção da Organização: Adquirente\nNorma jurídica da Entidade Adjudicante: Organismo de direito público\nÁrea de atividade da Autoridade Adjudicante: Serviços públicos das administrações públicas\n\n2 - JORNAL OFICIAL DA UNIÃO EUROPEIA\nO procedimento a que este anúncio diz respeito também é publicitado no Jornal Oficial da União Europeia? Não\n\n3 - AVISO\nModelo de Anúncio: Concurso público\nData de Envio do Anúncio: 29-08-2025\n\n5 - PROCESSO\nTipo de Procedimento: Concurso público\nPreço base do procedimento: Sim\nValor do preço base do procedimento: 119.124,28 EUR\nProcedimento com lotes? Não\n\n6 - OBJETO DO CONTRATO\nNúmero de referência interna: 8/2025\nDesignação do contrato: Renovação das infraestruturas de água e drenagem de águas residuais, construção de rede de pluviais na Rua Capitão Rodrigo Saldanha em Alcains\nDescrição: Renovação das infraestruturas de água e drenagem de águas residuais, construção de rede de pluviais na Rua Capitão Rodrigo Saldanha em Alcains\nTipo de Contrato Principal: Empreitada de Obras Públicas\nTipo de Contrato: Empreitada de Obras Públicas\nClassificação CPV (Vocabulário Comum para os Contratos Públicos)\nObjeto principal\nVocabulário Principal: 45231300\nPreço base s/IVA: 119.124,28 EUR\n\n7 - INDICAÇÕES ADICIONAIS\nO contrato envolve aquisição conjunta (satisfação de várias entidades)? Não\nO contrato é adjudicado por uma central de compras? Não\n\n8 - TÉCNICAS\nO concurso destina-se à celebração de um acordo-quadro? Inexistência de acordo-quadro\nÉ utilizado um leilão eletrónico? Não\nÉ adotada uma fase de negociação? Não\nSistema de Aquisição Dinâmico: Inexistência de sistema de aquisição dinâmico\n\n9 - LOCAL DA EXECUÇÃO DO CONTRATO\nLOCAL DA EXECUÇÃO DO CONTRATO (PROCEDIMENTO)\nPaís: Portugal\nNUT III: PT16H\nLocalidade: Freguesia de Alcains\nDistrito: Castelo Branco\nConcelho: Castelo Branco\nFreguesia: Freguesia de Alcains\n\n10 - PRAZO DE EXECUÇÃO DO CONTRATO\nPrazo de execução do contrato: 90 DIAS\nPrevisão de renovações: Não\n\n11 - FUNDOS EU\nTêm fundos EU? Não\n\n12 - DOCUMENTOS DE HABILITAÇÃO\nHabilitação para o exercício da atividade profissional: Não\n\n13 - CONDIÇÕES DE APRESENTAÇÃO\nPlataforma eletrónica utilizada pela entidade adjudicante: ACIN\nURL para Apresentação: https://www.acingov.pt\nAdmissibilidade da apresentação de propostas variantes: Não autorizado\nPrazo para apresentação das propostas: 12-09-2025 23:59\nPrazo durante o qual os concorrentes são obrigados a manter as respetivas propostas: 90 dias a contar do termo do prazo para a apresentação das propostas\nIndicação de Subcontratação na Proposta: Inexistência de indicação de subcontratação\n\n14 - PRESTAÇÃO DE CAUÇÃO\nPrestação de caução: Sim\nPercentagem: 5%\nDescrição da Garantia Exigida: O valor da caução é de 5.00% do preço contratual.\n\n15 - FORNECIMENTO DAS PEÇAS DO CONCURSO, APRESENTAÇÃO DE PEDIDOS DE PARTICIPAÇÃO E APRESENTAÇÃO DAS PROPOSTAS\nLink para acesso às peças do concurso (URL): https://www.acingov.pt/acingovprod/2/zonaPublica/zona_publica_c/donwloadProcedurePiece/OTczNDY5\n\n20 - OUTROS REQUISITOS\nInformação sobre contratos reservados. Aplica-se a contratos reservados (54º-A)? Não\n\n21 - CRITÉRIO DE ADJUDICAÇÃO\nMultifator: Sim\nFator: \nNome: Preço\nPonderação: 70%\nSubfatores: Não\nFator: \nNome: Outros\nOutro Nome: Valia Técnica da Proposta\nPonderação: 30%\nSubfatores: Não\n\n24 - CONDIÇÕES DO CONTRATO\nFaturação Eletrónica: Permitido\nObrigação de Subcontratação:\nCódigo da Obrigação de Subcontratação: Não é aplicável nenhuma obrigação de subcontratação.\n\n25 - COMPRA PÚBLICA ESTRATÉGICA\nCompra Pública Estratégica: Inexistência de contratação pública estratégica\n\n26 - INFORMAÇÕES ADICIONAIS\nContrato adequado para PME: Não\nCobertura ACP (Acordo dos Contratos Públicos da Organização Mundial do Comércio): Não\n\n27 - IDENTIFICAÇÃO E CONTACTOS DO ÓRGÃO DE RECURSOS ADMINISTRATIVOS\nDesignação: Conselho de Administração\nEndereço: Av. Nuno Álvares Nº 32 r/c\nCódigo postal: 6000-083\nLocalidade: Castelo Branco\nTelefone: 272340500\nFax: 272340501\nEndereço eletrónico: geral@sm-castelobranco.pt\nPrazo de interposição do recurso: 5 dias\n\n28 - IDENTIFICAÇÃO DO(S) AUTOR(ES) DE ANÚNCIO\nNome: Engª. Sónia Cristina Cristóvão Mexia\nCargo: Administradora\n419484181",
    "nipc": "680017640",
    "distrito": "Castelo Branco",
    "concelho": "Castelo Branco",
    "freguesia": "Todas",
    "site": "www.sm-castelobranco.pt",
    "email": "geral@sm-castelobranco.pt",
    "designacao_contrato": "Renovação das infraestruturas de água e drenagem de águas residuais, construção de rede de pluviais na Rua Capitão Rodrigo Saldanha em Alcains",
    "descricao": "Renovação das infraestruturas de água e drenagem de águas residuais, construção de rede de pluviais na Rua Capitão Rodrigo Saldanha em Alcains",
    "preco_base": "119.124,28 EUR",
    "prazo_execucao": "90 DIAS",
    "prazo_apresentacao_propostas": "12-09-2025 23:59",
    "fundos_eu": "Não",
    "plataforma_eletronica": "ACIN",
    "url_procedimento": "https://www.acingov.pt",
    "autor_nome": "Engª. Sónia Cristina Cristóvão Mexia",
    "autor_cargo": "Administradora"
  },
  {
    "numero_procedimento": "N/A",
    "entidade": "AnÃºncio de procedimento  n.Âº 23111/2025  -  DiÃ¡rio da RepÃºblica n.Âº 167/2025, SÃ©rie II de 2025-09-01",
    "link": "https://diariodarepublica.pt/dr/detalhe/contrato-publico/23111-933628160"
  },
  {
    "numero_procedimento": "N/A",
    "entidade": "AnÃºncio de procedimento  n.Âº 23112/2025  -  DiÃ¡rio da RepÃºblica n.Âº 167/2025, SÃ©rie II de 2025-09-01",
    "link": "https://diariodarepublica.pt/dr/detalhe/contrato-publico/23112-933628169"
  },
  {
    "numero_procedimento": "N/A",
    "entidade": "AnÃºncio de procedimento  n.Âº 23114/2025  -  DiÃ¡rio da RepÃºblica n.Âº 167/2025, SÃ©rie II de 2025-09-01",
    "link": "https://diariodarepublica.pt/dr/detalhe/contrato-publico/23114-933628170"
  },
  {
    "numero_procedimento": "N/A",
    "entidade": "AnÃºncio de procedimento  n.Âº 23116/2025  -  DiÃ¡rio da RepÃºblica n.Âº 167/2025, SÃ©rie II de 2025-09-01",
    "link": "https://diariodarepublica.pt/dr/detalhe/contrato-publico/23116-933628171"
  },
  {
    "numero_procedimento": "N/A",
    "entidade": "AnÃºncio de procedimento  n.Âº 23119/2025  -  DiÃ¡rio da RepÃºblica n.Âº 167/2025, SÃ©rie II de 2025-09-01",
    "link": "https://diariodarepublica.pt/dr/detalhe/contrato-publico/23119-933628172"
  },
  {
    "numero_procedimento": "N/A",
    "entidade": "AnÃºncio de procedimento  n.Âº 23120/2025  -  DiÃ¡rio da RepÃºblica n.Âº 167/2025, SÃ©rie II de 2025-09-01",
    "link": "https://diariodarepublica.pt/dr/detalhe/contrato-publico/23120-933628173"
  },
  {
    "numero_procedimento": "N/A",
    "entidade": "AnÃºncio de procedimento  n.Âº 23122/2025  -  DiÃ¡rio da RepÃºblica n.Âº 167/2025, SÃ©rie II de 2025-09-01",
    "link": "https://diariodarepublica.pt/dr/detalhe/contrato-publico/23122-933628174"
  },
  {
    "numero_procedimento": "N/A",
    "entidade": "AnÃºncio de procedimento  n.Âº 23106/2025  -  DiÃ¡rio da RepÃºblica n.Âº 167/2025, SÃ©rie II de 2025-09-01",
    "link": "https://diariodarepublica.pt/dr/detalhe/contrato-publico/23106-933746508"
  },
  {
    "numero_procedimento": "N/A",
    "entidade": "AnÃºncio de procedimento  n.Âº 23107/2025  -  DiÃ¡rio da RepÃºblica n.Âº 167/2025, SÃ©rie II de 2025-09-01",
    "link": "https://diariodarepublica.pt/dr/detalhe/contrato-publico/23107-933746512"
  },
  {
    "numero_procedimento": "N/A",
    "entidade": "AnÃºncio de procedimento  n.Âº 23108/2025  -  DiÃ¡rio da RepÃºblica n.Âº 167/2025, SÃ©rie II de 2025-09-01",
    "link": "https://diariodarepublica.pt/dr/detalhe/contrato-publico/23108-933746513"
  },
  {
    "numero_procedimento": "N/A",
    "entidade": "AnÃºncio de procedimento  n.Âº 23110/2025  -  DiÃ¡rio da RepÃºblica n.Âº 167/2025, SÃ©rie II de 2025-09-01",
    "link": "https://diariodarepublica.pt/dr/detalhe/contrato-publico/23110-933746514"
  },
  {
    "numero_procedimento": "N/A",
    "entidade": "AnÃºncio de procedimento  n.Âº 23113/2025  -  DiÃ¡rio da RepÃºblica n.Âº 167/2025, SÃ©rie II de 2025-09-01",
    "link": "https://diariodarepublica.pt/dr/detalhe/contrato-publico/23113-933766721"
  },
  {
    "numero_procedimento": "N/A",
    "entidade": "AnÃºncio de procedimento  n.Âº 23115/2025  -  DiÃ¡rio da RepÃºblica n.Âº 167/2025, SÃ©rie II de 2025-09-01",
    "link": "https://diariodarepublica.pt/dr/detalhe/contrato-publico/23115-933766725"
  },
  {
    "numero_procedimento": "N/A",
    "entidade": "AnÃºncio de procedimento  n.Âº 23117/2025  -  DiÃ¡rio da RepÃºblica n.Âº 167/2025, SÃ©rie II de 2025-09-01",
    "link": "https://diariodarepublica.pt/dr/detalhe/contrato-publico/23117-933766726"
  },
  {
    "numero_procedimento": "N/A",
    "entidade": "AnÃºncio de procedimento  n.Âº 23118/2025  -  DiÃ¡rio da RepÃºblica n.Âº 167/2025, SÃ©rie II de 2025-09-01",
    "link": "https://diariodarepublica.pt/dr/detalhe/contrato-publico/23118-933766727"
  },
  {
    "numero_procedimento": "N/A",
    "entidade": "AnÃºncio de procedimento  n.Âº 23121/2025  -  DiÃ¡rio da RepÃºblica n.Âº 167/2025, SÃ©rie II de 2025-09-01",
    "link": "https://diariodarepublica.pt/dr/detalhe/contrato-publico/23121-933766728"
  },
  {
    "numero_procedimento": "N/A",
    "entidade": "AnÃºncio de procedimento  n.Âº 23123/2025  -  DiÃ¡rio da RepÃºblica n.Âº 167/2025, SÃ©rie II de 2025-09-01",
    "link": "https://diariodarepublica.pt/dr/detalhe/contrato-publico/23123-933766729"
  },
  {
    "numero_procedimento": "N/A",
    "entidade": "AnÃºncio de procedimento  n.Âº 23125/2025  -  DiÃ¡rio da RepÃºblica n.Âº 167/2025, SÃ©rie II de 2025-09-01",
    "link": "https://diariodarepublica.pt/dr/detalhe/contrato-publico/23125-933766730"
  },
  {
    "numero_procedimento": "N/A",
    "entidade": "AnÃºncio de procedimento  n.Âº 23126/2025  -  DiÃ¡rio da RepÃºblica n.Âº 167/2025, SÃ©rie II de 2025-09-01",
    "link": "https://diariodarepublica.pt/dr/detalhe/contrato-publico/23126-933766731"
  },
  {
    "numero_procedimento": "N/A",
    "entidade": "AnÃºncio de procedimento  n.Âº 23127/2025  -  DiÃ¡rio da RepÃºblica n.Âº 167/2025, SÃ©rie II de 2025-09-01",
    "link": "https://diariodarepublica.pt/dr/detalhe/contrato-publico/23127-933766732"
  },
  {
    "numero_procedimento": "N/A",
    "entidade": "AnÃºncio de procedimento  n.Âº 23128/2025  -  DiÃ¡rio da RepÃºblica n.Âº 167/2025, SÃ©rie II de 2025-09-01",
    "link": "https://diariodarepublica.pt/dr/detalhe/contrato-publico/23128-933766733"
  },
  {
    "numero_procedimento": "N/A",
    "entidade": "AnÃºncio de procedimento  n.Âº 23130/2025  -  DiÃ¡rio da RepÃºblica n.Âº 167/2025, SÃ©rie II de 2025-09-01",
    "link": "https://diariodarepublica.pt/dr/detalhe/contrato-publico/23130-933766734"
  },
  {
    "numero_procedimento": "N/A",
    "entidade": "AnÃºncio de procedimento  n.Âº 23133/2025  -  DiÃ¡rio da RepÃºblica n.Âº 167/2025, SÃ©rie II de 2025-09-01",
    "link": "https://diariodarepublica.pt/dr/detalhe/contrato-publico/23133-933766735"
  },
  {
    "numero_procedimento": "N/A",
    "entidade": "AnÃºncio de procedimento  n.Âº 23136/2025  -  DiÃ¡rio da RepÃºblica n.Âº 167/2025, SÃ©rie II de 2025-09-01",
    "link": "https://diariodarepublica.pt/dr/detalhe/contrato-publico/23136-933766736"
  },
  {
    "numero_procedimento": "N/A",
    "entidade": "AnÃºncio de procedimento  n.Âº 23137/2025  -  DiÃ¡rio da RepÃºblica n.Âº 167/2025, SÃ©rie II de 2025-09-01",
    "link": "https://diariodarepublica.pt/dr/detalhe/contrato-publico/23137-933766737"
  },
  {
    "numero_procedimento": "N/A",
    "entidade": "AnÃºncio de procedimento  n.Âº 23140/2025  -  DiÃ¡rio da RepÃºblica n.Âº 167/2025, SÃ©rie II de 2025-09-01",
    "link": "https://diariodarepublica.pt/dr/detalhe/contrato-publico/23140-933766738"
  },
  {
    "numero_procedimento": "N/A",
    "entidade": "AnÃºncio de procedimento  n.Âº 23141/2025  -  DiÃ¡rio da RepÃºblica n.Âº 167/2025, SÃ©rie II de 2025-09-01",
    "link": "https://diariodarepublica.pt/dr/detalhe/contrato-publico/23141-933766739"
  },
  {
    "numero_procedimento": "N/A",
    "entidade": "AnÃºncio de procedimento  n.Âº 23144/2025  -  DiÃ¡rio da RepÃºblica n.Âº 167/2025, SÃ©rie II de 2025-09-01",
    "link": "https://diariodarepublica.pt/dr/detalhe/contrato-publico/23144-933766740"
  },
  {
    "numero_procedimento": "N/A",
    "entidade": "AnÃºncio de procedimento  n.Âº 23145/2025  -  DiÃ¡rio da RepÃºblica n.Âº 167/2025, SÃ©rie II de 2025-09-01",
    "link": "https://diariodarepublica.pt/dr/detalhe/contrato-publico/23145-933766741"
  },
  {
    "numero_procedimento": "N/A",
    "entidade": "AnÃºncio de procedimento  n.Âº 23147/2025  -  DiÃ¡rio da RepÃºblica n.Âº 167/2025, SÃ©rie II de 2025-09-01",
    "link": "https://diariodarepublica.pt/dr/detalhe/contrato-publico/23147-933766742"
  },
  {
    "numero_procedimento": "N/A",
    "entidade": "AnÃºncio de procedimento  n.Âº 23150/2025  -  DiÃ¡rio da RepÃºblica n.Âº 167/2025, SÃ©rie II de 2025-09-01",
    "link": "https://diariodarepublica.pt/dr/detalhe/contrato-publico/23150-933766743"
  },
  {
    "numero_procedimento": "N/A",
    "entidade": "AnÃºncio de procedimento  n.Âº 23152/2025  -  DiÃ¡rio da RepÃºblica n.Âº 167/2025, SÃ©rie II de 2025-09-01",
    "link": "https://diariodarepublica.pt/dr/detalhe/contrato-publico/23152-933766744"
  },
  {
    "numero_procedimento": "N/A",
    "entidade": "AnÃºncio de procedimento  n.Âº 23153/2025  -  DiÃ¡rio da RepÃºblica n.Âº 167/2025, SÃ©rie II de 2025-09-01",
    "link": "https://diariodarepublica.pt/dr/detalhe/contrato-publico/23153-933766745"
  },
  {
    "numero_procedimento": "N/A",
    "entidade": "AnÃºncio de procedimento  n.Âº 23154/2025  -  DiÃ¡rio da RepÃºblica n.Âº 167/2025, SÃ©rie II de 2025-09-01",
    "link": "https://diariodarepublica.pt/dr/detalhe/contrato-publico/23154-933766746"
  },
  {
    "numero_procedimento": "N/A",
    "entidade": "AnÃºncio de procedimento  n.Âº 23156/2025  -  DiÃ¡rio da RepÃºblica n.Âº 167/2025, SÃ©rie II de 2025-09-01",
    "link": "https://diariodarepublica.pt/dr/detalhe/contrato-publico/23156-933766747"
  },
  {
    "numero_procedimento": "N/A",
    "entidade": "AnÃºncio de procedimento  n.Âº 23159/2025  -  DiÃ¡rio da RepÃºblica n.Âº 167/2025, SÃ©rie II de 2025-09-01",
    "link": "https://diariodarepublica.pt/dr/detalhe/contrato-publico/23159-933766748"
  },
  {
    "numero_procedimento": "N/A",
    "entidade": "AnÃºncio de procedimento  n.Âº 23124/2025  -  DiÃ¡rio da RepÃºblica n.Âº 167/2025, SÃ©rie II de 2025-09-01",
    "link": "https://diariodarepublica.pt/dr/detalhe/contrato-publico/23124-933788275"
  },
  {
    "numero_procedimento": "N/A",
    "entidade": "AnÃºncio de procedimento  n.Âº 23129/2025  -  DiÃ¡rio da RepÃºblica n.Âº 167/2025, SÃ©rie II de 2025-09-01",
    "link": "https://diariodarepublica.pt/dr/detalhe/contrato-publico/23129-933788276"
  },
  {
    "numero_procedimento": "N/A",
    "entidade": "AnÃºncio de procedimento  n.Âº 23131/2025  -  DiÃ¡rio da RepÃºblica n.Âº 167/2025, SÃ©rie II de 2025-09-01",
    "link": "https://diariodarepublica.pt/dr/detalhe/contrato-publico/23131-933788277"
  },
  {
    "numero_procedimento": "N/A",
    "entidade": "AnÃºncio de procedimento  n.Âº 23132/2025  -  DiÃ¡rio da RepÃºblica n.Âº 167/2025, SÃ©rie II de 2025-09-01",
    "link": "https://diariodarepublica.pt/dr/detalhe/contrato-publico/23132-933788278"
  },
  {
    "numero_procedimento": "N/A",
    "entidade": "AnÃºncio de procedimento  n.Âº 23134/2025  -  DiÃ¡rio da RepÃºblica n.Âº 167/2025, SÃ©rie II de 2025-09-01",
    "link": "https://diariodarepublica.pt/dr/detalhe/contrato-publico/23134-933788279"
  },
  {
    "numero_procedimento": "N/A",
    "entidade": "AnÃºncio de procedimento  n.Âº 23135/2025  -  DiÃ¡rio da RepÃºblica n.Âº 167/2025, SÃ©rie II de 2025-09-01",
    "link": "https://diariodarepublica.pt/dr/detalhe/contrato-publico/23135-933788280"
  },
  {
    "numero_procedimento": "N/A",
    "entidade": "AnÃºncio de procedimento  n.Âº 23138/2025  -  DiÃ¡rio da RepÃºblica n.Âº 167/2025, SÃ©rie II de 2025-09-01",
    "link": "https://diariodarepublica.pt/dr/detalhe/contrato-publico/23138-933788281"
  },
  {
    "numero_procedimento": "N/A",
    "entidade": "AnÃºncio de procedimento  n.Âº 23139/2025  -  DiÃ¡rio da RepÃºblica n.Âº 167/2025, SÃ©rie II de 2025-09-01",
    "link": "https://diariodarepublica.pt/dr/detalhe/contrato-publico/23139-933788282"
  },
  {
    "numero_procedimento": "N/A",
    "entidade": "AnÃºncio de procedimento  n.Âº 23142/2025  -  DiÃ¡rio da RepÃºblica n.Âº 167/2025, SÃ©rie II de 2025-09-01",
    "link": "https://diariodarepublica.pt/dr/detalhe/contrato-publico/23142-933788283"
  },
  {
    "numero_procedimento": "N/A",
    "entidade": "AnÃºncio de procedimento  n.Âº 23143/2025  -  DiÃ¡rio da RepÃºblica n.Âº 167/2025, SÃ©rie II de 2025-09-01",
    "link": "https://diariodarepublica.pt/dr/detalhe/contrato-publico/23143-933788284"
  },
  {
    "numero_procedimento": "N/A",
    "entidade": "AnÃºncio de procedimento  n.Âº 23146/2025  -  DiÃ¡rio da RepÃºblica n.Âº 167/2025, SÃ©rie II de 2025-09-01",
    "link": "https://diariodarepublica.pt/dr/detalhe/contrato-publico/23146-933788285"
  },
  {
    "numero_procedimento": "N/A",
    "entidade": "AnÃºncio de procedimento  n.Âº 23148/2025  -  DiÃ¡rio da RepÃºblica n.Âº 167/2025, SÃ©rie II de 2025-09-01",
    "link": "https://diariodarepublica.pt/dr/detalhe/contrato-publico/23148-933788286"
  },
  {
    "numero_procedimento": "N/A",
    "entidade": "AnÃºncio de procedimento  n.Âº 23149/2025  -  DiÃ¡rio da RepÃºblica n.Âº 167/2025, SÃ©rie II de 2025-09-01",
    "link": "https://diariodarepublica.pt/dr/detalhe/contrato-publico/23149-933788287"
  },
  {
    "numero_procedimento": "N/A",
    "entidade": "AnÃºncio de procedimento  n.Âº 23151/2025  -  DiÃ¡rio da RepÃºblica n.Âº 167/2025, SÃ©rie II de 2025-09-01",
    "link": "https://diariodarepublica.pt/dr/detalhe/contrato-publico/23151-933788288"
  },
  {
    "numero_procedimento": "N/A",
    "entidade": "AnÃºncio de procedimento  n.Âº 23155/2025  -  DiÃ¡rio da RepÃºblica n.Âº 167/2025, SÃ©rie II de 2025-09-01",
    "link": "https://diariodarepublica.pt/dr/detalhe/contrato-publico/23155-933788289"
  },
  {
    "numero_procedimento": "N/A",
    "entidade": "AnÃºncio de procedimento  n.Âº 23157/2025  -  DiÃ¡rio da RepÃºblica n.Âº 167/2025, SÃ©rie II de 2025-09-01",
    "link": "https://diariodarepublica.pt/dr/detalhe/contrato-publico/23157-933788290"
  },
  {
    "numero_procedimento": "N/A",
    "entidade": "AnÃºncio de procedimento  n.Âº 23158/2025  -  DiÃ¡rio da RepÃºblica n.Âº 167/2025, SÃ©rie II de 2025-09-01",
    "link": "https://diariodarepublica.pt/dr/detalhe/contrato-publico/23158-933788291"
  },
  {
    "numero_procedimento": "N/A",
    "entidade": "AnÃºncio de procedimento  n.Âº 23160/2025  -  DiÃ¡rio da RepÃºblica n.Âº 167/2025, SÃ©rie II de 2025-09-01",
    "link": "https://diariodarepublica.pt/dr/detalhe/contrato-publico/23160-933788292"
  }
]