[
  {
    "numero_procedimento": "N/A",
    "entidade": "AnÃºncio de procedimento  n.Âº 25745/2025  -  DiÃ¡rio da RepÃºblica n.Âº 189/2025, SÃ©rie II de 2025-10-01",
    "link": "https://diariodarepublica.pt/dr/detalhe/contrato-publico/25745-937425319"
  },
  {
    "numero_procedimento": "N/A",
    "entidade": "AnÃºncio de procedimento  n.Âº 25752/2025  -  DiÃ¡rio da RepÃºblica n.Âº 189/2025, SÃ©rie II de 2025-10-01",
    "link": "https://diariodarepublica.pt/dr/detalhe/contrato-publico/25752-937425321"
  },
  {
    "numero_procedimento": "N/A",
    "entidade": "Águas e Energia do Porto E.M",
    "link": "https://diariodarepublica.pt/dr/detalhe/contrato-publico/25753-937425322",
    "detalhes_completos": "1 - IDENTIFICAÇÃO E CONTACTOS DA ENTIDADE ADJUDICANTE\nDesignação da entidade adjudicante: Águas e Energia do Porto E.M\nNIPC: 507718666\nServiço/Órgão/Pessoa de contacto: Administrador\nEndereço: Rua Barão de Nova Sintra, Nº 285\nCódigo postal: 4300-367\nLocalidade: Porto\nPaís: Portugal\nNUT III: PTZZZ\nDistrito: Todos\nConcelho: Todos\nFreguesia: Todas\nTelefone: 225190854\nFax: 225190807\nEndereço da Entidade (URL): www.aguasdoporto.pt\nEndereço Eletrónico: contratos@aguasdoporto.pt\neDelivery Gateway (URL): https://www.acingov.pt\nFunção da Organização: Adquirente\nNorma jurídica da Entidade Adjudicante: Organismo de direito público\nÁrea de atividade da Autoridade Adjudicante: Serviços públicos das administrações públicas\n\n2 - JORNAL OFICIAL DA UNIÃO EUROPEIA\nO procedimento a que este anúncio diz respeito também é publicitado no Jornal Oficial da União Europeia? Não\n\n3 - AVISO\nModelo de Anúncio: Concurso público\nData de Envio do Anúncio: 30-09-2025\n\n5 - PROCESSO\nTipo de Procedimento: Concurso público\nPreço base do procedimento: Sim\nValor do preço base do procedimento: 20.000,00 EUR\nProcedimento com lotes? Não\n\n6 - OBJETO DO CONTRATO\nNúmero de referência interna: 2196CP25\nDesignação do contrato: 2196CP25 Aquisição de bebedouros\nDescrição: 2196CP25 Aquisição de bebedouros\nTipo de Contrato Principal: Aquisição de Bens Móveis\nTipo de Contrato: Aquisição de Bens Móveis\nClassificação CPV (Vocabulário Comum para os Contratos Públicos)\nObjeto principal\nVocabulário Principal: 39370000\nPreço base s/IVA: 20.000,00 EUR\n\n7 - INDICAÇÕES ADICIONAIS\nO contrato envolve aquisição conjunta (satisfação de várias entidades)? Não\nO contrato é adjudicado por uma central de compras? Não\n\n8 - TÉCNICAS\nO concurso destina-se à celebração de um acordo-quadro? Inexistência de acordo-quadro\nÉ utilizado um leilão eletrónico? Não\nÉ adotada uma fase de negociação? Não\nSistema de Aquisição Dinâmico: Inexistência de sistema de aquisição dinâmico\n\n9 - LOCAL DA EXECUÇÃO DO CONTRATO\nLOCAL DA EXECUÇÃO DO CONTRATO (PROCEDIMENTO)\nPaís: Portugal\nNUT III: PT11A\nLocalidade: Porto\nDistrito: Porto\nConcelho: Porto\nFreguesia: Todas\n\n10 - PRAZO DE EXECUÇÃO DO CONTRATO\nPrazo de execução do contrato: 42 DIAS\nPrevisão de renovações: Não\n\n11 - FUNDOS EU\nTêm fundos EU? Não\n\n12 - DOCUMENTOS DE HABILITAÇÃO\nHabilitação para o exercício da atividade profissional: Não\n\n13 - CONDIÇÕES DE APRESENTAÇÃO\nPlataforma eletrónica utilizada pela entidade adjudicante: ACIN\nURL para Apresentação: https://www.acingov.pt\nAdmissibilidade da apresentação de propostas variantes: Não autorizado\nPrazo para apresentação das propostas: 07-10-2025 17:00\nPrazo durante o qual os concorrentes são obrigados a manter as respetivas propostas: 66 dias a contar do termo do prazo para a apresentação das propostas\nIndicação de Subcontratação na Proposta: Inexistência de indicação de subcontratação\n\n14 - PRESTAÇÃO DE CAUÇÃO\nPrestação de caução: Não\n\n15 - FORNECIMENTO DAS PEÇAS DO CONCURSO, APRESENTAÇÃO DE PEDIDOS DE PARTICIPAÇÃO E APRESENTAÇÃO DAS PROPOSTAS\nLink para acesso às peças do concurso (URL): https://www.acingov.pt/acingovprod/2/zonaPublica/zona_publica_c/donwloadProcedurePiece/OTgxNzAx\n\n20 - OUTROS REQUISITOS\nInformação sobre contratos reservados. Aplica-se a contratos reservados (54º-A)? Não\n\n21 - CRITÉRIO DE ADJUDICAÇÃO\nMultifator: Não\nMonofator:\nNome: Outros\nOutro nome: Fator Preço\n\n24 - CONDIÇÕES DO CONTRATO\nFaturação Eletrónica: Permitido\nObrigação de Subcontratação:\nCódigo da Obrigação de Subcontratação: Não é aplicável nenhuma obrigação de subcontratação.\n\n25 - COMPRA PÚBLICA ESTRATÉGICA\nCompra Pública Estratégica: Inexistência de contratação pública estratégica\n\n26 - INFORMAÇÕES ADICIONAIS\nContrato adequado para PME: Sim\nCobertura ACP (Acordo dos Contratos Públicos da Organização Mundial do Comércio): Não\n\n27 - IDENTIFICAÇÃO E CONTACTOS DO ÓRGÃO DE RECURSOS ADMINISTRATIVOS\nDesignação: Conselho de Administração da CMPEAE - EMPRESA DE ÁGUAS E ENERGIA DO MUNICIPIO DO PORTO, E.M.\nEndereço: R. do Barão de Nova Sintra 285\nCódigo postal: 4300-367\nLocalidade: Porto\nTelefone: 220100220\nFax: \nEndereço eletrónico: contratos@aguasdoporto.pt\n\n28 - IDENTIFICAÇÃO DO(S) AUTOR(ES) DE ANÚNCIO\nNome: Eng. Ruben Fernandes\nCargo: Administrador Executivo\n419597014",
    "nipc": "507718666",
    "distrito": "Todos",
    "concelho": "Todos",
    "freguesia": "Todas",
    "site": "www.aguasdoporto.pt",
    "email": "contratos@aguasdoporto.pt",
    "designacao_contrato": "2196CP25 Aquisição de bebedouros",
    "descricao": "2196CP25 Aquisição de bebedouros",
    "preco_base": "20.000,00 EUR",
    "prazo_execucao": "42 DIAS",
    "prazo_apresentacao_propostas": "07-10-2025 17:00",
    "fundos_eu": "Não",
    "plataforma_eletronica": "ACIN",
    "url_procedimento": "https://www.acingov.pt",
    "autor_nome": "Eng. Ruben Fernandes",
    "autor_cargo": "Administrador Executivo"
  },
  {
    "numero_procedimento": "N/A",
    "entidade": "AnÃºncio de procedimento  n.Âº 25755/2025  -  DiÃ¡rio da RepÃºblica n.Âº 189/2025, SÃ©rie II de 2025-10-01",
    "link": "https://diariodarepublica.pt/dr/detalhe/contrato-publico/25755-937425324"
  },
  {
    "numero_procedimento": "N/A",
    "entidade": "AnÃºncio de procedimento  n.Âº 25756/2025  -  DiÃ¡rio da RepÃºblica n.Âº 189/2025, SÃ©rie II de 2025-10-01",
    "link": "https://diariodarepublica.pt/dr/detalhe/contrato-publico/25756-937425325"
  },
  {
    "numero_procedimento": "N/A",
    "entidade": "Agência para a Integração Migrações e Asilo",
    "link": "https://diariodarepublica.pt/dr/detalhe/contrato-publico/25744-937446097",
    "detalhes_completos": "1 - IDENTIFICAÇÃO E CONTACTOS DA ENTIDADE ADJUDICANTE\nDesignação da entidade adjudicante: Agência para a Integração Migrações e Asilo\nNIPC: 517686260\nEndereço: Avenida António Augusto de Aguiar, n.º 20\nCódigo postal: 1069-119\nLocalidade:  Lisboa \nPaís: Portugal\nNUT III: PT170\nDistrito: Lisboa\nConcelho: Lisboa\nFreguesia: Freguesia de Avenidas Novas\nTelefone: 213585500\nEndereço da Entidade (URL): https://aima.gov.pt/pt\nEndereço Eletrónico: geral@aima.gov.pt\neDelivery Gateway (URL): https://community.vortal.biz/public/\nFunção da Organização: Adquirente\nNorma jurídica da Entidade Adjudicante: Autoridade da administração central\nÁrea de atividade da Autoridade Adjudicante: Serviços públicos das administrações públicas\n\n2 - JORNAL OFICIAL DA UNIÃO EUROPEIA\nO procedimento a que este anúncio diz respeito também é publicitado no Jornal Oficial da União Europeia? Não\n\n3 - AVISO\nModelo de Anúncio: Concurso público\nData de Envio do Anúncio: 30-09-2025\n\n5 - PROCESSO\nTipo de Procedimento: Concurso público\nPreço base do procedimento: Sim\nValor do preço base do procedimento: 199.915,00 EUR\nProcedimento com lotes? Não\n\n6 - OBJETO DO CONTRATO\nNúmero de referência interna: CP14/25\nDesignação do contrato: Aquisição de serviços cloud Oracle\nDescrição: Aquisição de serviços cloud Oracle\nTipo de Contrato Principal: Aquisição de Serviços\nTipo de Contrato: Aquisição de Serviços\nClassificação CPV (Vocabulário Comum para os Contratos Públicos)\nObjeto principal\nVocabulário Principal: 72415000\nPreço base s/IVA: 199.915,00 EUR\n\n7 - INDICAÇÕES ADICIONAIS\nO contrato envolve aquisição conjunta (satisfação de várias entidades)? Não\nO contrato é adjudicado por uma central de compras? Não\n\n8 - TÉCNICAS\nO concurso destina-se à celebração de um acordo-quadro? Inexistência de acordo-quadro\nÉ utilizado um leilão eletrónico? Não\nÉ adotada uma fase de negociação? Não\nSistema de Aquisição Dinâmico: Inexistência de sistema de aquisição dinâmico\n\n9 - LOCAL DA EXECUÇÃO DO CONTRATO\nLOCAL DA EXECUÇÃO DO CONTRATO (PROCEDIMENTO)\nPaís: Portugal\nNUT III: PT170\nLocalidade: Lisboa\nDistrito: Lisboa\nConcelho: Lisboa\nFreguesia: Freguesia de Avenidas Novas\n\n10 - PRAZO DE EXECUÇÃO DO CONTRATO\nPrazo de execução do contrato: 12 MESES\nPrevisão de renovações: Não\n\n11 - FUNDOS EU\nTêm fundos EU? Não\n\n12 - DOCUMENTOS DE HABILITAÇÃO\nHabilitação para o exercício da atividade profissional: Não\n\n13 - CONDIÇÕES DE APRESENTAÇÃO\nPlataforma eletrónica utilizada pela entidade adjudicante: VORTAL\nURL para Apresentação: https://community.vortal.biz/public/\nAdmissibilidade da apresentação de propostas variantes: Não autorizado\nPrazo para apresentação das propostas: 09-10-2025 23:59\nPrazo durante o qual os concorrentes são obrigados a manter as respetivas propostas: 66 dias a contar do termo do prazo para a apresentação das propostas\nIndicação de Subcontratação na Proposta: Inexistência de indicação de subcontratação\n\n14 - PRESTAÇÃO DE CAUÇÃO\nPrestação de caução: Não\n\n15 - FORNECIMENTO DAS PEÇAS DO CONCURSO, APRESENTAÇÃO DE PEDIDOS DE PARTICIPAÇÃO E APRESENTAÇÃO DAS PROPOSTAS\nLink para acesso às peças do concurso (URL): https://community.vortal.biz/Public/public-tender-documents/cUFzaFNyNnRaSC9BRmdXem1iSlVnVTQzOTRBcTc0QUxpTnJVOWZFdi9ab21keU80Z3RMczB3ZmZkeGtpRHF2c1FrbmJTa1l4YTBjeGNpY1hnU3A4SEE9PUFQNm0j\n\n20 - OUTROS REQUISITOS\nInformação sobre contratos reservados. Aplica-se a contratos reservados (54º-A)? Não\n\n21 - CRITÉRIO DE ADJUDICAÇÃO\nMultifator: Sim\nFator: \nNome: Preço\nPonderação: 50%\nSubfatores: Não\nFator: \nNome: Qualidade\nPonderação: 50%\nSubfatores: Não\n\n24 - CONDIÇÕES DO CONTRATO\nFaturação Eletrónica: Permitido\nObrigação de Subcontratação:\nCódigo da Obrigação de Subcontratação: Não é aplicável nenhuma obrigação de subcontratação.\n\n25 - COMPRA PÚBLICA ESTRATÉGICA\nCompra Pública Estratégica: Inexistência de contratação pública estratégica\n\n26 - INFORMAÇÕES ADICIONAIS\nContrato adequado para PME: Sim\nCobertura ACP (Acordo dos Contratos Públicos da Organização Mundial do Comércio): Não\n\n27 - IDENTIFICAÇÃO E CONTACTOS DO ÓRGÃO DE RECURSOS ADMINISTRATIVOS\nDesignação: Conselho Diretivo da AIMA, I.P.\nEndereço: Av. António Augusto Aguiar, nº 20\nCódigo postal: 1069-119\nLocalidade: Lisboa\nTelefone: +351 213585500\nFax: +351 214236640\nEndereço eletrónico: aquisicoes@aima.gov.pt\n\n28 - IDENTIFICAÇÃO DO(S) AUTOR(ES) DE ANÚNCIO\nNome: Bruno Sousa\nCargo: Assistente Técnico\n419594009",
    "nipc": "517686260",
    "distrito": "Lisboa",
    "concelho": "Lisboa",
    "freguesia": "Freguesia de Avenidas Novas",
    "site": "https://aima.gov.pt/pt",
    "email": "geral@aima.gov.pt",
    "designacao_contrato": "Aquisição de serviços cloud Oracle",
    "descricao": "Aquisição de serviços cloud Oracle",
    "preco_base": "199.915,00 EUR",
    "prazo_execucao": "12 MESES",
    "prazo_apresentacao_propostas": "09-10-2025 23:59",
    "fundos_eu": "Não",
    "plataforma_eletronica": "VORTAL",
    "url_procedimento": "https://community.vortal.biz/public/",
    "autor_nome": "Bruno Sousa",
    "autor_cargo": "Assistente Técnico"
  },
  {
    "numero_procedimento": "N/A",
    "entidade": "AnÃºncio de procedimento  n.Âº 25746/2025  -  DiÃ¡rio da RepÃºblica n.Âº 189/2025, SÃ©rie II de 2025-10-01",
    "link": "https://diariodarepublica.pt/dr/detalhe/contrato-publico/25746-937446134"
  },
  {
    "numero_procedimento": "N/A",
    "entidade": "FEIRA VIVA - CULTURA E DESPORTO, E.M.",
    "link": "https://diariodarepublica.pt/dr/detalhe/contrato-publico/25747-937446135",
    "detalhes_completos": "1 - IDENTIFICAÇÃO E CONTACTOS DA ENTIDADE ADJUDICANTE\nDesignação da entidade adjudicante: FEIRA VIVA - CULTURA E DESPORTO, E.M.\nNIPC: 505120151\nEndereço: Rua Interior do Europarque\nCódigo postal: 4520-153\nLocalidade: Aveiro\nPaís: Portugal\nNUT III: PT11A\nDistrito: Aveiro\nConcelho: Santa Maria da Feira\nFreguesia: União das Freguesias de Santa Maria da Feira, Travanca, Sanfins e Espargo\nTelefone: 256330900\nFax: 256330909\nEndereço Eletrónico: procedimentos@feiraviva.com\neDelivery Gateway (URL): https://community.vortal.biz/public/\nFunção da Organização: Adquirente\nNorma jurídica da Entidade Adjudicante: Autoridade da administração central\nÁrea de atividade da Autoridade Adjudicante: Serviços públicos das administrações públicas\n\n2 - JORNAL OFICIAL DA UNIÃO EUROPEIA\nO procedimento a que este anúncio diz respeito também é publicitado no Jornal Oficial da União Europeia? Não\n\n3 - AVISO\nModelo de Anúncio: Concurso público\nData de Envio do Anúncio: 30-09-2025\n\n5 - PROCESSO\nTipo de Procedimento: Concurso público\nPreço base do procedimento: Sim\nValor do preço base do procedimento: 28.275,00 EUR\nProcedimento com lotes? Não\n\n6 - OBJETO DO CONTRATO\nNúmero de referência interna: 306_2025_CP_BS\nDesignação do contrato: 306_2025_CP_BS - Prestação de Serviços de Limpeza para o HMC\nDescrição: 306_2025_CP_BS - Prestação de Serviços de Limpeza para o HMC\nTipo de Contrato Principal: Aquisição de Serviços\nTipo de Contrato: Aquisição de Serviços\nClassificação CPV (Vocabulário Comum para os Contratos Públicos)\nObjeto principal\nVocabulário Principal: 90910000\nPreço base s/IVA: 28.275,00 EUR\n\n7 - INDICAÇÕES ADICIONAIS\nO contrato envolve aquisição conjunta (satisfação de várias entidades)? Não\nO contrato é adjudicado por uma central de compras? Não\n\n8 - TÉCNICAS\nO concurso destina-se à celebração de um acordo-quadro? Inexistência de acordo-quadro\nÉ utilizado um leilão eletrónico? Não\nÉ adotada uma fase de negociação? Não\nSistema de Aquisição Dinâmico: Inexistência de sistema de aquisição dinâmico\n\n9 - LOCAL DA EXECUÇÃO DO CONTRATO\nLOCAL DA EXECUÇÃO DO CONTRATO (PROCEDIMENTO)\nPaís: Portugal\nNUT III: PT11A\nLocalidade: Aveiro\nDistrito: Aveiro\nConcelho: Santa Maria da Feira\nFreguesia: Todas\n\n10 - PRAZO DE EXECUÇÃO DO CONTRATO\nPrazo de execução do contrato: 365 DIAS\nPrevisão de renovações: Não\n\n11 - FUNDOS EU\nTêm fundos EU? Não\n\n12 - DOCUMENTOS DE HABILITAÇÃO\nHabilitação para o exercício da atividade profissional: Sim\nTipo: Outros\nDescrição - Outros: Outros\nDescrição: na\n\n13 - CONDIÇÕES DE APRESENTAÇÃO\nPlataforma eletrónica utilizada pela entidade adjudicante: VORTAL\nURL para Apresentação: https://community.vortal.biz/public/\nAdmissibilidade da apresentação de propostas variantes: Não autorizado\nPrazo para apresentação das propostas: 09-10-2025 23:59\nPrazo durante o qual os concorrentes são obrigados a manter as respetivas propostas: 120 dias a contar do termo do prazo para a apresentação das propostas\nIndicação de Subcontratação na Proposta: Inexistência de indicação de subcontratação\n\n14 - PRESTAÇÃO DE CAUÇÃO\nPrestação de caução: Não\n\n15 - FORNECIMENTO DAS PEÇAS DO CONCURSO, APRESENTAÇÃO DE PEDIDOS DE PARTICIPAÇÃO E APRESENTAÇÃO DAS PROPOSTAS\nLink para acesso às peças do concurso (URL): https://community.vortal.biz/Public/public-tender-documents/WW1od1BrbWQrYXdBcmxsNWFtVHlRSUF1bUxDQ3dmbDVJZVlYK2VBU1NZUWREYU1zMFl0RmtwbkNpUmxtOVZEUHFIOXFWbFptY3dqc0xwWHhtTHZUcEE9PSojWWFV\n\n20 - OUTROS REQUISITOS\nInformação sobre contratos reservados. Aplica-se a contratos reservados (54º-A)? Não\n\n21 - CRITÉRIO DE ADJUDICAÇÃO\nMultifator: Não\nMonofator:\nNome: Preço\n\n24 - CONDIÇÕES DO CONTRATO\nFaturação Eletrónica: Permitido\nObrigação de Subcontratação:\nCódigo da Obrigação de Subcontratação: Não é aplicável nenhuma obrigação de subcontratação.\n\n25 - COMPRA PÚBLICA ESTRATÉGICA\nCompra Pública Estratégica: Inexistência de contratação pública estratégica\n\n26 - INFORMAÇÕES ADICIONAIS\nContrato adequado para PME: Sim\nCobertura ACP (Acordo dos Contratos Públicos da Organização Mundial do Comércio): Não\n\n27 - IDENTIFICAÇÃO E CONTACTOS DO ÓRGÃO DE RECURSOS ADMINISTRATIVOS\nDesignação: Conselho de Administração da Feira Viva Cultura e Desporto, E.M\nEndereço: Rua Interior ao Europarque\nCódigo postal: 4520-153\nLocalidade: Santa Maria da Feira\nTelefone: +351 256370200\nFax: +351 256370200\nEndereço eletrónico: procedimentos@feiraviva.com\n\n28 - IDENTIFICAÇÃO DO(S) AUTOR(ES) DE ANÚNCIO\nNome: Paulo Sérgio Pais\nCargo: Diretor Geral\n419596107",
    "nipc": "505120151",
    "distrito": "Aveiro",
    "concelho": "Santa Maria da Feira",
    "freguesia": "União das Freguesias de Santa Maria da Feira, Travanca, Sanfins e Espargo",
    "site": null,
    "email": "procedimentos@feiraviva.com",
    "designacao_contrato": "306_2025_CP_BS - Prestação de Serviços de Limpeza para o HMC",
    "descricao": "306_2025_CP_BS - Prestação de Serviços de Limpeza para o HMC",
    "preco_base": "28.275,00 EUR",
    "prazo_execucao": "365 DIAS",
    "prazo_apresentacao_propostas": "09-10-2025 23:59",
    "fundos_eu": "Não",
    "plataforma_eletronica": "VORTAL",
    "url_procedimento": "https://community.vortal.biz/public/",
    "autor_nome": "Paulo Sérgio Pais",
    "autor_cargo": "Diretor Geral"
  },
  {
    "numero_procedimento": "N/A",
    "entidade": "Câmara Municipal da Madalena",
    "link": "https://diariodarepublica.pt/dr/detalhe/contrato-publico/25748-937446142",
    "detalhes_completos": "1 - IDENTIFICAÇÃO E CONTACTOS DA ENTIDADE ADJUDICANTE\nDesignação da entidade adjudicante: Câmara Municipal da Madalena\nNIPC: 512070946\nServiço/Órgão/Pessoa de contacto: Presidente da Câmara Municipal\nEndereço: Largo Cardeal Costa Nunes\nCódigo postal: 9950-324\nLocalidade: Madalena\nPaís: Portugal\nNUT III: PT200\nDistrito: Região Autónoma dos Açores\nConcelho: Madalena\nFreguesia: Freguesia de Candelária - Madalena\nTelefone: 292628700\nFax: 292628746\nEndereço da Entidade (URL): www.cm-madalena.pt\nEndereço Eletrónico: geral@cm-madalena.pt\neDelivery Gateway (URL): https://www.acingov.pt\nFunção da Organização: Adquirente\nSubfunção da Organização: Organização que recebe as propostas\nNorma jurídica da Entidade Adjudicante: Organismo de direito público\nÁrea de atividade da Autoridade Adjudicante: Serviços públicos das administrações públicas\n\n2 - JORNAL OFICIAL DA UNIÃO EUROPEIA\nO procedimento a que este anúncio diz respeito também é publicitado no Jornal Oficial da União Europeia? Não\n\n3 - AVISO\nModelo de Anúncio: Concurso público\nData de Envio do Anúncio: 30-09-2025\n\n5 - PROCESSO\nTipo de Procedimento: Concurso público\nPreço base do procedimento: Sim\nValor do preço base do procedimento: 395.187,04 EUR\nProcedimento com lotes? Não\n\n6 - OBJETO DO CONTRATO\nNúmero de referência interna: CP/10/2025\nDesignação do contrato: EMPREITADA DE REQUALIFICAÇÃO DA ÁREA ADJACENTE À IGREJA E ESCOLA DA CANDELÁRIA\nDescrição: EMPREITADA DE REQUALIFICAÇÃO DA ÁREA ADJACENTE À IGREJA E ESCOLA DA CANDELÁRIA\nTipo de Contrato Principal: Empreitada de Obras Públicas\nTipo de Contrato: Empreitada de Obras Públicas\nClassificação CPV (Vocabulário Comum para os Contratos Públicos)\nObjeto principal\nVocabulário Principal: 45200000\nPreço base s/IVA: 395.187,04 EUR\n\n7 - INDICAÇÕES ADICIONAIS\nO contrato envolve aquisição conjunta (satisfação de várias entidades)? Não\nO contrato é adjudicado por uma central de compras? Não\n\n8 - TÉCNICAS\nO concurso destina-se à celebração de um acordo-quadro? Inexistência de acordo-quadro\nÉ utilizado um leilão eletrónico? Não\nÉ adotada uma fase de negociação? Não\nSistema de Aquisição Dinâmico: Inexistência de sistema de aquisição dinâmico\n\n9 - LOCAL DA EXECUÇÃO DO CONTRATO\nLOCAL DA EXECUÇÃO DO CONTRATO (PROCEDIMENTO)\nPaís: Portugal\nNUT III: PT200\nLocalidade: Freguesia de Candelária - Madalena\nDistrito: Região Autónoma dos Açores\nConcelho: Madalena\nFreguesia: Freguesia de Candelária - Madalena\n\n10 - PRAZO DE EXECUÇÃO DO CONTRATO\nPrazo de execução do contrato: 180 DIAS\nPrevisão de renovações: Não\n\n11 - FUNDOS EU\nTêm fundos EU? Não\n\n12 - DOCUMENTOS DE HABILITAÇÃO\nHabilitação para o exercício da atividade profissional: Sim\nTipo: Alvará\nDescrição: - 1.ª Subcategoria da 1.ª Categoria, de classe que cubra o valor total da obra;\n- 4.ª Subcategoria da 1.ª Categoria, de classe que cubra o valor total da obra;\n- 5.ª Subcategoria da 1.ª Categoria, de classe que cubra o valor total da obra;\n- 10.ª Subcategoria da 1.ª Categoria, de classe que cubra os respetivos trabalhos;\n- 1.ª Subcategoria da 2.ª Categoria, de classe que cubra os respetivos trabalhos;\n- 8.ª Subcategoria da 2.ª Categoria, de classe que cubra o valor total da obra;\n- 9.ª Subcategoria da 2.ª Categoria, de classe que cubra os respetivos trabalhos;\n- 11.ª Subcategoria da 2.ª Categoria, de classe que cubra os respetivos trabalhos;\n- 1.ª Subcategoria da 4.ª Categoria, de classe que cubra os respetivos trabalhos.\n- 2.ª Subcategoria da 5.ª Categoria, de classe que cubra o valor total da obra.\n\n13 - CONDIÇÕES DE APRESENTAÇÃO\nPlataforma eletrónica utilizada pela entidade adjudicante: ACIN\nURL para Apresentação: https://www.acingov.pt\nAdmissibilidade da apresentação de propostas variantes: Não autorizado\nPrazo para apresentação das propostas: 13-10-2025 23:59\nPrazo durante o qual os concorrentes são obrigados a manter as respetivas propostas: 66 dias a contar do termo do prazo para a apresentação das propostas\nIndicação de Subcontratação na Proposta: Inexistência de indicação de subcontratação\n\n14 - PRESTAÇÃO DE CAUÇÃO\nPrestação de caução: Não\n\n15 - FORNECIMENTO DAS PEÇAS DO CONCURSO, APRESENTAÇÃO DE PEDIDOS DE PARTICIPAÇÃO E APRESENTAÇÃO DAS PROPOSTAS\nLink para acesso às peças do concurso (URL): https://www.acingov.pt/acingovprod/2/zonaPublica/zona_publica_c/donwloadProcedurePiece/OTgwMjU5\n\n20 - OUTROS REQUISITOS\nInformação sobre contratos reservados. Aplica-se a contratos reservados (54º-A)? Não\n\n21 - CRITÉRIO DE ADJUDICAÇÃO\nMultifator: Não\nMonofator:\nNome: Preço\n\n24 - CONDIÇÕES DO CONTRATO\nFaturação Eletrónica: Permitido\nObrigação de Subcontratação:\nCódigo da Obrigação de Subcontratação: Não é aplicável nenhuma obrigação de subcontratação.\n\n25 - COMPRA PÚBLICA ESTRATÉGICA\nCompra Pública Estratégica: Inexistência de contratação pública estratégica\n\n26 - INFORMAÇÕES ADICIONAIS\nContrato adequado para PME: Sim\nCobertura ACP (Acordo dos Contratos Públicos da Organização Mundial do Comércio): Não\n\n27 - IDENTIFICAÇÃO E CONTACTOS DO ÓRGÃO DE RECURSOS ADMINISTRATIVOS\nDesignação: Presidente da Câmara Municipal\nEndereço: Largo Cardeal Costa Nunes\nCódigo postal: 9950-324\nLocalidade: Madalena\nTelefone: 292628700\nFax: 292628746\nEndereço eletrónico: geral@cm-madalena.pt\nPrazo de interposição do recurso: 5 dias\n\n28 - IDENTIFICAÇÃO DO(S) AUTOR(ES) DE ANÚNCIO\nNome: Catarina Isabel Gaspar Manito\nCargo: Presidente da Câmara\n419591482",
    "nipc": "512070946",
    "distrito": "Região Autónoma dos Açores",
    "concelho": "Madalena",
    "freguesia": "Freguesia de Candelária - Madalena",
    "site": "www.cm-madalena.pt",
    "email": "geral@cm-madalena.pt",
    "designacao_contrato": "EMPREITADA DE REQUALIFICAÇÃO DA ÁREA ADJACENTE À IGREJA E ESCOLA DA CANDELÁRIA",
    "descricao": "EMPREITADA DE REQUALIFICAÇÃO DA ÁREA ADJACENTE À IGREJA E ESCOLA DA CANDELÁRIA",
    "preco_base": "395.187,04 EUR",
    "prazo_execucao": "180 DIAS",
    "prazo_apresentacao_propostas": "13-10-2025 23:59",
    "fundos_eu": "Não",
    "plataforma_eletronica": "ACIN",
    "url_procedimento": "https://www.acingov.pt",
    "autor_nome": "Catarina Isabel Gaspar Manito",
    "autor_cargo": "Presidente da Câmara"
  },
  {
    "numero_procedimento": "N/A",
    "entidade": "AnÃºncio de procedimento  n.Âº 25749/2025  -  DiÃ¡rio da RepÃºblica n.Âº 189/2025, SÃ©rie II de 2025-10-01",
    "link": "https://diariodarepublica.pt/dr/detalhe/contrato-publico/25749-937446143"
  },
  {
    "numero_procedimento": "N/A",
    "entidade": "AnÃºncio de procedimento  n.Âº 25750/2025  -  DiÃ¡rio da RepÃºblica n.Âº 189/2025, SÃ©rie II de 2025-10-01",
    "link": "https://diariodarepublica.pt/dr/detalhe/contrato-publico/25750-937446166"
  },
  {
    "numero_procedimento": "N/A",
    "entidade": "AnÃºncio de procedimento  n.Âº 25751/2025  -  DiÃ¡rio da RepÃºblica n.Âº 189/2025, SÃ©rie II de 2025-10-01",
    "link": "https://diariodarepublica.pt/dr/detalhe/contrato-publico/25751-937446167"
  },
  {
    "numero_procedimento": "N/A",
    "entidade": "AnÃºncio de procedimento  n.Âº 25754/2025  -  DiÃ¡rio da RepÃºblica n.Âº 189/2025, SÃ©rie II de 2025-10-01",
    "link": "https://diariodarepublica.pt/dr/detalhe/contrato-publico/25754-937471333"
  },
  {
    "numero_procedimento": "N/A",
    "entidade": "AnÃºncio de procedimento  n.Âº 25757/2025  -  DiÃ¡rio da RepÃºblica n.Âº 189/2025, SÃ©rie II de 2025-10-01",
    "link": "https://diariodarepublica.pt/dr/detalhe/contrato-publico/25757-937471334"
  },
  {
    "numero_procedimento": "N/A",
    "entidade": "AnÃºncio de procedimento  n.Âº 25758/2025  -  DiÃ¡rio da RepÃºblica n.Âº 189/2025, SÃ©rie II de 2025-10-01",
    "link": "https://diariodarepublica.pt/dr/detalhe/contrato-publico/25758-937471335"
  },
  {
    "numero_procedimento": "N/A",
    "entidade": "AnÃºncio de procedimento  n.Âº 25759/2025  -  DiÃ¡rio da RepÃºblica n.Âº 189/2025, SÃ©rie II de 2025-10-01",
    "link": "https://diariodarepublica.pt/dr/detalhe/contrato-publico/25759-937471336"
  },
  {
    "numero_procedimento": "N/A",
    "entidade": "AnÃºncio de procedimento  n.Âº 25760/2025  -  DiÃ¡rio da RepÃºblica n.Âº 189/2025, SÃ©rie II de 2025-10-01",
    "link": "https://diariodarepublica.pt/dr/detalhe/contrato-publico/25760-937471337"
  },
  {
    "numero_procedimento": "N/A",
    "entidade": "AnÃºncio de procedimento  n.Âº 25761/2025  -  DiÃ¡rio da RepÃºblica n.Âº 189/2025, SÃ©rie II de 2025-10-01",
    "link": "https://diariodarepublica.pt/dr/detalhe/contrato-publico/25761-937471338"
  },
  {
    "numero_procedimento": "N/A",
    "entidade": "AnÃºncio de procedimento  n.Âº 25762/2025  -  DiÃ¡rio da RepÃºblica n.Âº 189/2025, SÃ©rie II de 2025-10-01",
    "link": "https://diariodarepublica.pt/dr/detalhe/contrato-publico/25762-937471339"
  },
  {
    "numero_procedimento": "N/A",
    "entidade": "Instituto Português de Oncologia de Lisboa FG, E.P.E.",
    "link": "https://diariodarepublica.pt/dr/detalhe/contrato-publico/25764-937471340",
    "detalhes_completos": "Alteração do Anúncio de procedimento n.º 24987/2025, de 2025-09-22, com o ID 419561641\n\n1 - IDENTIFICAÇÃO E CONTACTOS DA ENTIDADE ADJUDICANTE\nDesignação da entidade adjudicante: Instituto Português de Oncologia de Lisboa FG, E.P.E.\nNIPC: 506361616\nEndereço: Rua Profº Lima Basto\nCódigo postal: 1099-023\nLocalidade: Lisboa\nPaís: Portugal\nNUT III: PT170\nDistrito: Lisboa\nConcelho: Lisboa\nFreguesia: Todas\nTelefone: 217229800\nFax: 217229880\nEndereço da Entidade (URL): www.ipolisboa.min-saude.pt/\nEndereço Eletrónico: ipofg@ipolisboa.min-saude.pt\neDelivery Gateway (URL): https://community.vortal.biz/public/\nFunção da Organização: Adquirente\nNorma jurídica da Entidade Adjudicante: Organismo de direito público\nÁrea de atividade da Autoridade Adjudicante: Saúde\n\n2 - JORNAL OFICIAL DA UNIÃO EUROPEIA\nO procedimento a que este anúncio diz respeito também é publicitado no Jornal Oficial da União Europeia? Não\n\n3 - AVISO\nModelo de Anúncio: Concurso público\nData de Envio do Anúncio: 01-10-2025\n\n5 - PROCESSO\nTipo de Procedimento: Concurso público\nPreço base do procedimento: Sim\nValor do preço base do procedimento: 216.000,00 EUR\nProcedimento com lotes? Não\n\n6 - OBJETO DO CONTRATO\nNúmero de referência interna: PN/2395/2025\nDesignação do contrato: Aquisição de Sistema de Imagem guiada por superfície Corporal Independente do Acelerador Linear\nDescrição: Aquisição de Sistema de Imagem guiada por superfície Corporal Independente do Acelerador Linear\nTipo de Contrato Principal: Aquisição de Bens Móveis\nTipo de Contrato: Aquisição de Bens Móveis\nClassificação CPV (Vocabulário Comum para os Contratos Públicos)\nObjeto principal\nVocabulário Principal: 33100000\nPreço base s/IVA: 216.000,00 EUR\n\n7 - INDICAÇÕES ADICIONAIS\nO contrato envolve aquisição conjunta (satisfação de várias entidades)? Não\nO contrato é adjudicado por uma central de compras? Não\n\n8 - TÉCNICAS\nO concurso destina-se à celebração de um acordo-quadro? Inexistência de acordo-quadro\nÉ utilizado um leilão eletrónico? Não\nÉ adotada uma fase de negociação? Não\nSistema de Aquisição Dinâmico: Inexistência de sistema de aquisição dinâmico\n\n9 - LOCAL DA EXECUÇÃO DO CONTRATO\nLOCAL DA EXECUÇÃO DO CONTRATO (PROCEDIMENTO)\nPaís: Portugal\nNUT III: PT170\nLocalidade: Lisboa\nDistrito: Lisboa\nConcelho: Lisboa\nFreguesia: Freguesia de São Domingos de Benfica\n\n10 - PRAZO DE EXECUÇÃO DO CONTRATO\nPrazo de execução do contrato: 30 DIAS\nPrevisão de renovações: Não\n\n11 - FUNDOS EU\nTêm fundos EU? Sim\n\n12 - DOCUMENTOS DE HABILITAÇÃO\nHabilitação para o exercício da atividade profissional: Não\n\n13 - CONDIÇÕES DE APRESENTAÇÃO\nPlataforma eletrónica utilizada pela entidade adjudicante: VORTAL\nURL para Apresentação: https://community.vortal.biz/public/\nAdmissibilidade da apresentação de propostas variantes: Não autorizado\nPrazo para apresentação das propostas: 06-10-2025 17:59\nPrazo durante o qual os concorrentes são obrigados a manter as respetivas propostas: 90 dias a contar do termo do prazo para a apresentação das propostas\nIndicação de Subcontratação na Proposta: Inexistência de indicação de subcontratação\n\n14 - PRESTAÇÃO DE CAUÇÃO\nPrestação de caução: Não\n\n15 - FORNECIMENTO DAS PEÇAS DO CONCURSO, APRESENTAÇÃO DE PEDIDOS DE PARTICIPAÇÃO E APRESENTAÇÃO DAS PROPOSTAS\nLink para acesso às peças do concurso (URL): https://community.vortal.biz/Public/public-tender-documents/R3o4dGJUUHBKM0VqdnZ4R1B1Tk8wYm9jSFpwYmc5cWdpZmZxR0JwaXpMVXdzZ0dFUWpkRnVrZW1lTUdZemViVHZ5OTByZ0psZnMzVmM3d2VTNDUxVkE9PUV2R2RV\n\n20 - OUTROS REQUISITOS\nInformação sobre contratos reservados. Aplica-se a contratos reservados (54º-A)? Não\n\n21 - CRITÉRIO DE ADJUDICAÇÃO\nMultifator: Sim\nFator: \nNome: Preço\nPonderação: 60%\nSubfatores: Não\nFator: \nNome: Qualidade\nPonderação: 40%\nSubfatores: Não\n\n24 - CONDIÇÕES DO CONTRATO\nFaturação Eletrónica: Permitido\nObrigação de Subcontratação:\nCódigo da Obrigação de Subcontratação: Não é aplicável nenhuma obrigação de subcontratação.\n\n25 - COMPRA PÚBLICA ESTRATÉGICA\nCompra Pública Estratégica: Inexistência de contratação pública estratégica\n\n26 - INFORMAÇÕES ADICIONAIS\nContrato adequado para PME: Sim\nCobertura ACP (Acordo dos Contratos Públicos da Organização Mundial do Comércio): Não\n\n27 - IDENTIFICAÇÃO E CONTACTOS DO ÓRGÃO DE RECURSOS ADMINISTRATIVOS\nDesignação: Conselho de Administração\nEndereço: Rua Profesor Lima Basto\nCódigo postal: 1099-023\nLocalidade: Lisboa\nTelefone: +351 217229800\nFax: +351 217229880\nEndereço eletrónico: ipofg@ipolisboa.min-saude.pt\n\n28 - IDENTIFICAÇÃO DO(S) AUTOR(ES) DE ANÚNCIO\nNome: Ricardo Costa\nCargo: Técnico Superior\n\n29 - ALTERAÇÃO\nMotivo da Alteração: Correção pelo adquirente\nIdentificador da Versão do Anúncio a Alterar: ec145451-1090-4d8c-b805-2a8a020105c9-01\nIdentificador das Secções Alteradas do Anúncio Anterior: Alteração\nDescrição das Alterações: Prazo de apresentação e programa de concurso\nAlteração dos Documentos do Concurso: Sim\nData de alteração dos documentos do concurso: 01-10-2025\n419597411",
    "nipc": "506361616",
    "distrito": "Lisboa",
    "concelho": "Lisboa",
    "freguesia": "Todas",
    "site": "www.ipolisboa.min-saude.pt/",
    "email": "ipofg@ipolisboa.min-saude.pt",
    "designacao_contrato": "Aquisição de Sistema de Imagem guiada por superfície Corporal Independente do Acelerador Linear",
    "descricao": "Aquisição de Sistema de Imagem guiada por superfície Corporal Independente do Acelerador Linear",
    "preco_base": "216.000,00 EUR",
    "prazo_execucao": "30 DIAS",
    "prazo_apresentacao_propostas": "06-10-2025 17:59",
    "fundos_eu": "Sim",
    "plataforma_eletronica": "VORTAL",
    "url_procedimento": "https://community.vortal.biz/public/",
    "autor_nome": "Ricardo Costa",
    "autor_cargo": "Técnico Superior"
  },
  {
    "numero_procedimento": "N/A",
    "entidade": "Grupo Desportivo do Zambujeiro",
    "link": "https://diariodarepublica.pt/dr/detalhe/contrato-publico/25763-937474590",
    "detalhes_completos": "1 - IDENTIFICAÇÃO E CONTACTOS DA ENTIDADE ADJUDICANTE\nDesignação da entidade adjudicante: Grupo Desportivo do Zambujeiro\nNIPC: 501610901\nServiço/Órgão/Pessoa de contacto: Direção\nEndereço: Rua Principal, 873, Zambujeiro\nCódigo postal: 2755-307\nLocalidade: Alcabideche\nPaís: Portugal\nNUT III: PT170\nDistrito: Lisboa\nConcelho: Cascais\nFreguesia: Freguesia de Alcabideche\nTelefone: 910000000\nEndereço da Entidade (URL): www.gd-zambujeiro.com\nEndereço Eletrónico: secretaria@gd-zambujeiro.com\neDelivery Gateway (URL): https://www.acingov.pt\nFunção da Organização: Adquirente\nSubfunção da Organização: Organização cujo orçamento é utilizado para pagar o contrato; Organização que executa o pagamento; Organização que fornece informações adicionais sobre o processo de adjudicação; Organização que fornece mais informações sobre os prazos dos procedimentos de recurso; Organização responsável pelo tratamento das propostas; Organização que recebe as propostas; Organização que trata os pedidos de participação; Organização que recebe pedidos de participação; Organização que fornece mais informações sobre os procedimentos de recurso; Organização que assina o contrato\nNorma jurídica da Entidade Adjudicante: Organismo de direito público\nÁrea de atividade da Autoridade Adjudicante: Serviços públicos das administrações públicas\n\n2 - JORNAL OFICIAL DA UNIÃO EUROPEIA\nO procedimento a que este anúncio diz respeito também é publicitado no Jornal Oficial da União Europeia? Não\n\n3 - AVISO\nModelo de Anúncio: Concurso público\nData de Envio do Anúncio: 01-10-2025\n\n5 - PROCESSO\nTipo de Procedimento: Concurso público\nPreço base do procedimento: Sim\nValor do preço base do procedimento: 430.000,00 EUR\nProcedimento com lotes? Não\n\n6 - OBJETO DO CONTRATO\nNúmero de referência interna: 202501\nDesignação do contrato: Empreitada de remodelação e ampliação do Grupo Desportivo do Zambujeiro.\nDescrição: Empreitada de remodelação e ampliação do Grupo Desportivo do Zambujeiro.\nTipo de Contrato Principal: Empreitada de Obras Públicas\nTipo de Contrato: Empreitada de Obras Públicas\nClassificação CPV (Vocabulário Comum para os Contratos Públicos)\nObjeto principal\nVocabulário Principal: 45262700\nPreço base s/IVA: 430.000,00 EUR\n\n7 - INDICAÇÕES ADICIONAIS\nO contrato envolve aquisição conjunta (satisfação de várias entidades)? Não\nO contrato é adjudicado por uma central de compras? Não\n\n8 - TÉCNICAS\nO concurso destina-se à celebração de um acordo-quadro? Inexistência de acordo-quadro\nÉ utilizado um leilão eletrónico? Não\nÉ adotada uma fase de negociação? Não\nSistema de Aquisição Dinâmico: Inexistência de sistema de aquisição dinâmico\n\n9 - LOCAL DA EXECUÇÃO DO CONTRATO\nLOCAL DA EXECUÇÃO DO CONTRATO (PROCEDIMENTO)\nPaís: Portugal\nNUT III: PT170\nLocalidade: Freguesia de Alcabideche\nDistrito: Lisboa\nConcelho: Cascais\nFreguesia: Freguesia de Alcabideche\n\n10 - PRAZO DE EXECUÇÃO DO CONTRATO\nPrazo de execução do contrato: 12 MESES\nPrevisão de renovações: Não\n\n11 - FUNDOS EU\nTêm fundos EU? Não\n\n12 - DOCUMENTOS DE HABILITAÇÃO\nHabilitação para o exercício da atividade profissional: Sim\nTipo: Alvará\nDescrição: A Subcategoria e categoria a qual tem de ser classe que cubra o valor global da\nproposta e integrar-se na categoria em que o tipo da obra se enquadra:\n1.º Subcategoria 1.º Categoria\nE, as subcategorias e categorias correspondentes, cada uma, ao valor dos trabalhos\nespecializados que lhe respeitam, consoante a parte que a cada um desses\ntrabalhos cabe na proposta:\n1.º Subcategoria 1.º Categoria\n4.º Subcategoria 1.º Categoria\n5.º Subcategoria 1.º Categoria\n7.º Subcategoria 1.º Categoria\n8.º Subcategoria 1.º Categoria\n1.º Subcategoria 4.º Categoria\n11.º Subcategoria 4.º Categoria\n9.º Subcategoria 4.º Categoria\n10.º Subcategoria 4.º Categoria\n12.º Subcategoria 4.º Categoria\n\n13 - CONDIÇÕES DE APRESENTAÇÃO\nPlataforma eletrónica utilizada pela entidade adjudicante: ACIN\nURL para Apresentação: https://www.acingov.pt\nAdmissibilidade da apresentação de propostas variantes: Não autorizado\nPrazo para apresentação das propostas: 29-11-2025 23:59\nPrazo durante o qual os concorrentes são obrigados a manter as respetivas propostas: 120 dias a contar do termo do prazo para a apresentação das propostas\nIndicação de Subcontratação na Proposta: Inexistência de indicação de subcontratação\n\n14 - PRESTAÇÃO DE CAUÇÃO\nPrestação de caução: Não\n\n15 - FORNECIMENTO DAS PEÇAS DO CONCURSO, APRESENTAÇÃO DE PEDIDOS DE PARTICIPAÇÃO E APRESENTAÇÃO DAS PROPOSTAS\nLink para acesso às peças do concurso (URL): https://www.acingov.pt/acingovprod/2/zonaPublica/zona_publica_c/donwloadProcedurePiece/OTc5NjE0\n\n20 - OUTROS REQUISITOS\nInformação sobre contratos reservados. Aplica-se a contratos reservados (54º-A)? Não\n\n21 - CRITÉRIO DE ADJUDICAÇÃO\nMultifator: Sim\nFator: \nNome: Outros\nOutro Nome: Multifator\nPonderação: 100%\nSubfatores: Não\n\n24 - CONDIÇÕES DO CONTRATO\nFaturação Eletrónica: Permitido\nObrigação de Subcontratação:\nCódigo da Obrigação de Subcontratação: Não é aplicável nenhuma obrigação de subcontratação.\n\n25 - COMPRA PÚBLICA ESTRATÉGICA\nCompra Pública Estratégica: Inexistência de contratação pública estratégica\n\n26 - INFORMAÇÕES ADICIONAIS\nContrato adequado para PME: Não\nCobertura ACP (Acordo dos Contratos Públicos da Organização Mundial do Comércio): Não\n\n27 - IDENTIFICAÇÃO E CONTACTOS DO ÓRGÃO DE RECURSOS ADMINISTRATIVOS\nDesignação: Direção\nEndereço: Rua Principal, 873, Zambujeiro\nCódigo postal: 2755-307\nLocalidade: Alcabideche\nTelefone: 910000000\nFax: \nEndereço eletrónico: secretaria@gd-zambujeiro.com\nPrazo de interposição do recurso: 30 dias\n\n28 - IDENTIFICAÇÃO DO(S) AUTOR(ES) DE ANÚNCIO\nNome: Jorge Santos\nCargo: Vogal\n419592779",
    "nipc": "501610901",
    "distrito": "Lisboa",
    "concelho": "Cascais",
    "freguesia": "Freguesia de Alcabideche",
    "site": "www.gd-zambujeiro.com",
    "email": "secretaria@gd-zambujeiro.com",
    "designacao_contrato": "Empreitada de remodelação e ampliação do Grupo Desportivo do Zambujeiro.",
    "descricao": "Empreitada de remodelação e ampliação do Grupo Desportivo do Zambujeiro.",
    "preco_base": "430.000,00 EUR",
    "prazo_execucao": "12 MESES",
    "prazo_apresentacao_propostas": "29-11-2025 23:59",
    "fundos_eu": "Não",
    "plataforma_eletronica": "ACIN",
    "url_procedimento": "https://www.acingov.pt",
    "autor_nome": "Jorge Santos",
    "autor_cargo": "Vogal"
  }
]