[
  {
    "numero_procedimento": "N/A",
    "entidade": "AnÃºncio de procedimento  n.Âº 20661/2025  -  DiÃ¡rio da RepÃºblica n.Âº 147/2025, SÃ©rie II de 2025-08-01",
    "link": "https://diariodarepublica.pt/dr/detalhe/contrato-publico/20661-927415986"
  },
  {
    "numero_procedimento": "N/A",
    "entidade": "AnÃºncio de procedimento  n.Âº 20662/2025  -  DiÃ¡rio da RepÃºblica n.Âº 147/2025, SÃ©rie II de 2025-08-01",
    "link": "https://diariodarepublica.pt/dr/detalhe/contrato-publico/20662-927415987"
  },
  {
    "numero_procedimento": "N/A",
    "entidade": "AnÃºncio de procedimento  n.Âº 20664/2025  -  DiÃ¡rio da RepÃºblica n.Âº 147/2025, SÃ©rie II de 2025-08-01",
    "link": "https://diariodarepublica.pt/dr/detalhe/contrato-publico/20664-927415988"
  },
  {
    "numero_procedimento": "N/A",
    "entidade": "AnÃºncio de procedimento  n.Âº 20675/2025  -  DiÃ¡rio da RepÃºblica n.Âº 147/2025, SÃ©rie II de 2025-08-01",
    "link": "https://diariodarepublica.pt/dr/detalhe/contrato-publico/20675-927415990"
  },
  {
    "numero_procedimento": "N/A",
    "entidade": "AnÃºncio de procedimento  n.Âº 20681/2025  -  DiÃ¡rio da RepÃºblica n.Âº 147/2025, SÃ©rie II de 2025-08-01",
    "link": "https://diariodarepublica.pt/dr/detalhe/contrato-publico/20681-927416007"
  },
  {
    "numero_procedimento": "N/A",
    "entidade": "AnÃºncio de procedimento  n.Âº 20685/2025  -  DiÃ¡rio da RepÃºblica n.Âº 147/2025, SÃ©rie II de 2025-08-01",
    "link": "https://diariodarepublica.pt/dr/detalhe/contrato-publico/20685-927416008"
  },
  {
    "numero_procedimento": "N/A",
    "entidade": "AnÃºncio de procedimento  n.Âº 20687/2025  -  DiÃ¡rio da RepÃºblica n.Âº 147/2025, SÃ©rie II de 2025-08-01",
    "link": "https://diariodarepublica.pt/dr/detalhe/contrato-publico/20687-927416009"
  },
  {
    "numero_procedimento": "N/A",
    "entidade": "AnÃºncio de procedimento  n.Âº 20688/2025  -  DiÃ¡rio da RepÃºblica n.Âº 147/2025, SÃ©rie II de 2025-08-01",
    "link": "https://diariodarepublica.pt/dr/detalhe/contrato-publico/20688-927416010"
  },
  {
    "numero_procedimento": "N/A",
    "entidade": "AnÃºncio de procedimento  n.Âº 20690/2025  -  DiÃ¡rio da RepÃºblica n.Âº 147/2025, SÃ©rie II de 2025-08-01",
    "link": "https://diariodarepublica.pt/dr/detalhe/contrato-publico/20690-927416011"
  },
  {
    "numero_procedimento": "N/A",
    "entidade": "AnÃºncio de procedimento  n.Âº 20692/2025  -  DiÃ¡rio da RepÃºblica n.Âº 147/2025, SÃ©rie II de 2025-08-01",
    "link": "https://diariodarepublica.pt/dr/detalhe/contrato-publico/20692-927416012"
  },
  {
    "numero_procedimento": "N/A",
    "entidade": "AnÃºncio de procedimento  n.Âº 20694/2025  -  DiÃ¡rio da RepÃºblica n.Âº 147/2025, SÃ©rie II de 2025-08-01",
    "link": "https://diariodarepublica.pt/dr/detalhe/contrato-publico/20694-927416013"
  },
  {
    "numero_procedimento": "N/A",
    "entidade": "AnÃºncio de procedimento  n.Âº 20695/2025  -  DiÃ¡rio da RepÃºblica n.Âº 147/2025, SÃ©rie II de 2025-08-01",
    "link": "https://diariodarepublica.pt/dr/detalhe/contrato-publico/20695-927416014"
  },
  {
    "numero_procedimento": "N/A",
    "entidade": "AnÃºncio de procedimento  n.Âº 20696/2025  -  DiÃ¡rio da RepÃºblica n.Âº 147/2025, SÃ©rie II de 2025-08-01",
    "link": "https://diariodarepublica.pt/dr/detalhe/contrato-publico/20696-927416015"
  },
  {
    "numero_procedimento": "N/A",
    "entidade": "AnÃºncio de procedimento  n.Âº 20697/2025  -  DiÃ¡rio da RepÃºblica n.Âº 147/2025, SÃ©rie II de 2025-08-01",
    "link": "https://diariodarepublica.pt/dr/detalhe/contrato-publico/20697-927416016"
  },
  {
    "numero_procedimento": "N/A",
    "entidade": "AnÃºncio de procedimento  n.Âº 20698/2025  -  DiÃ¡rio da RepÃºblica n.Âº 147/2025, SÃ©rie II de 2025-08-01",
    "link": "https://diariodarepublica.pt/dr/detalhe/contrato-publico/20698-927416017"
  },
  {
    "numero_procedimento": "N/A",
    "entidade": "AnÃºncio de procedimento  n.Âº 20700/2025  -  DiÃ¡rio da RepÃºblica n.Âº 147/2025, SÃ©rie II de 2025-08-01",
    "link": "https://diariodarepublica.pt/dr/detalhe/contrato-publico/20700-927416018"
  },
  {
    "numero_procedimento": "N/A",
    "entidade": "AnÃºncio de procedimento  n.Âº 20702/2025  -  DiÃ¡rio da RepÃºblica n.Âº 147/2025, SÃ©rie II de 2025-08-01",
    "link": "https://diariodarepublica.pt/dr/detalhe/contrato-publico/20702-927416019"
  },
  {
    "numero_procedimento": "N/A",
    "entidade": "AnÃºncio de procedimento  n.Âº 20707/2025  -  DiÃ¡rio da RepÃºblica n.Âº 147/2025, SÃ©rie II de 2025-08-01",
    "link": "https://diariodarepublica.pt/dr/detalhe/contrato-publico/20707-927416020"
  },
  {
    "numero_procedimento": "N/A",
    "entidade": "AnÃºncio de procedimento  n.Âº 20708/2025  -  DiÃ¡rio da RepÃºblica n.Âº 147/2025, SÃ©rie II de 2025-08-01",
    "link": "https://diariodarepublica.pt/dr/detalhe/contrato-publico/20708-927416021"
  },
  {
    "numero_procedimento": "N/A",
    "entidade": "AnÃºncio de procedimento  n.Âº 20710/2025  -  DiÃ¡rio da RepÃºblica n.Âº 147/2025, SÃ©rie II de 2025-08-01",
    "link": "https://diariodarepublica.pt/dr/detalhe/contrato-publico/20710-927416022"
  },
  {
    "numero_procedimento": "N/A",
    "entidade": "AnÃºncio de procedimento  n.Âº 20711/2025  -  DiÃ¡rio da RepÃºblica n.Âº 147/2025, SÃ©rie II de 2025-08-01",
    "link": "https://diariodarepublica.pt/dr/detalhe/contrato-publico/20711-927416023"
  },
  {
    "numero_procedimento": "N/A",
    "entidade": "AnÃºncio de procedimento  n.Âº 20712/2025  -  DiÃ¡rio da RepÃºblica n.Âº 147/2025, SÃ©rie II de 2025-08-01",
    "link": "https://diariodarepublica.pt/dr/detalhe/contrato-publico/20712-927416024"
  },
  {
    "numero_procedimento": "N/A",
    "entidade": "AnÃºncio de procedimento  n.Âº 20663/2025  -  DiÃ¡rio da RepÃºblica n.Âº 147/2025, SÃ©rie II de 2025-08-01",
    "link": "https://diariodarepublica.pt/dr/detalhe/contrato-publico/20663-927474289"
  },
  {
    "numero_procedimento": "N/A",
    "entidade": "AnÃºncio de procedimento  n.Âº 20665/2025  -  DiÃ¡rio da RepÃºblica n.Âº 147/2025, SÃ©rie II de 2025-08-01",
    "link": "https://diariodarepublica.pt/dr/detalhe/contrato-publico/20665-927474290"
  },
  {
    "numero_procedimento": "N/A",
    "entidade": "AnÃºncio de procedimento  n.Âº 20666/2025  -  DiÃ¡rio da RepÃºblica n.Âº 147/2025, SÃ©rie II de 2025-08-01",
    "link": "https://diariodarepublica.pt/dr/detalhe/contrato-publico/20666-927474291"
  },
  {
    "numero_procedimento": "N/A",
    "entidade": "AnÃºncio de procedimento  n.Âº 20667/2025  -  DiÃ¡rio da RepÃºblica n.Âº 147/2025, SÃ©rie II de 2025-08-01",
    "link": "https://diariodarepublica.pt/dr/detalhe/contrato-publico/20667-927474292"
  },
  {
    "numero_procedimento": "N/A",
    "entidade": "Câmara Municipal de Palmela",
    "link": "https://diariodarepublica.pt/dr/detalhe/contrato-publico/20668-927474293",
    "detalhes_completos": "1 - IDENTIFICAÇÃO E CONTACTOS DA ENTIDADE ADJUDICANTE\nDesignação da entidade adjudicante: Câmara Municipal de Palmela\nNIPC: 506187543\nEndereço: Largo Município , Palmela\nCódigo postal: 2954-001\nLocalidade: Setúbal\nPaís: Portugal\nNUT III: PT170\nDistrito: Setúbal\nConcelho: Palmela\nFreguesia: Freguesia de Palmela\nTelefone: 212 336 600\nFax: 212 336 619\nEndereço da Entidade (URL): www.cm-palmela.pt\nEndereço Eletrónico: geral@cm-palmela.pt\neDelivery Gateway (URL): https://community.vortal.biz/public/\nFunção da Organização: Adquirente\nNorma jurídica da Entidade Adjudicante: Organismo de direito público\nÁrea de atividade da Autoridade Adjudicante: Serviços públicos das administrações públicas\n\n2 - JORNAL OFICIAL DA UNIÃO EUROPEIA\nO procedimento a que este anúncio diz respeito também é publicitado no Jornal Oficial da União Europeia? Não\n\n3 - AVISO\nModelo de Anúncio: Concurso público\nData de Envio do Anúncio: 31-07-2025\n\n5 - PROCESSO\nTipo de Procedimento: Concurso público\nPreço base do procedimento: Sim\nValor do preço base do procedimento: 81.500,00 EUR\nProcedimento com lotes? Não\n\n6 - OBJETO DO CONTRATO\nNúmero de referência interna: 5034/2025\nDesignação do contrato: Empreitada de Requalificação da UCSP de Poceirão\nDescrição: Empreitada de Requalificação da UCSP de Poceirão - Os trabalhos a realizar englobam essencialmente trabalhos de beneficiação e reforço do isolamento térmico das fachadas com sistema ETICS, tratamento e pintura de paredes e tetos interiores, substituição de estores, reforço do isolamento da laje de esteira da cobertura com lã de rocha, revisão das coberturas, limpeza de caleiras e substituição dos órgãos de apoio à drenagem de águas pluviais\nTipo de Contrato Principal: Empreitada de Obras Públicas\nTipo de Contrato: Empreitada de Obras Públicas\nClassificação CPV (Vocabulário Comum para os Contratos Públicos)\nObjeto principal\nVocabulário Principal: 45200000\nPreço base s/IVA: 81.500,00 EUR\n\n7 - INDICAÇÕES ADICIONAIS\nO contrato envolve aquisição conjunta (satisfação de várias entidades)? Não\nO contrato é adjudicado por uma central de compras? Não\n\n8 - TÉCNICAS\nO concurso destina-se à celebração de um acordo-quadro? Inexistência de acordo-quadro\nÉ utilizado um leilão eletrónico? Não\nÉ adotada uma fase de negociação? Não\nSistema de Aquisição Dinâmico: Inexistência de sistema de aquisição dinâmico\n\n9 - LOCAL DA EXECUÇÃO DO CONTRATO\nLOCAL DA EXECUÇÃO DO CONTRATO (PROCEDIMENTO)\nPaís: Portugal\nNUT III: PT170\nLocalidade: Poceirão\nDistrito: Setúbal\nConcelho: Palmela\nFreguesia: União das Freguesias de Poceirão e Marateca\n\n10 - PRAZO DE EXECUÇÃO DO CONTRATO\nPrazo de execução do contrato: 60 DIAS\nPrevisão de renovações: Não\n\n11 - FUNDOS EU\nTêm fundos EU? Sim\n\n12 - DOCUMENTOS DE HABILITAÇÃO\nHabilitação para o exercício da atividade profissional: Sim\nTipo: Alvará\nDescrição: Alvarás nos termos das peças do procedimento\n\n13 - CONDIÇÕES DE APRESENTAÇÃO\nPlataforma eletrónica utilizada pela entidade adjudicante: VORTAL\nURL para Apresentação: https://community.vortal.biz/public/\nAdmissibilidade da apresentação de propostas variantes: Não autorizado\nPrazo para apresentação das propostas: 15-08-2025 23:59\nPrazo durante o qual os concorrentes são obrigados a manter as respetivas propostas: 120 dias a contar do termo do prazo para a apresentação das propostas\nIndicação de Subcontratação na Proposta: Inexistência de indicação de subcontratação\n\n14 - PRESTAÇÃO DE CAUÇÃO\nPrestação de caução: Não\n\n15 - FORNECIMENTO DAS PEÇAS DO CONCURSO, APRESENTAÇÃO DE PEDIDOS DE PARTICIPAÇÃO E APRESENTAÇÃO DAS PROPOSTAS\nLink para acesso às peças do concurso (URL): https://community.vortal.biz/Public/public-tender-documents/MTdsYzdXaXV1MXZXQ0VGSXdQNitPclpaelZYWmJveGh1TWxsWm05Ri85eGhhSjh4Y3djaWkzK0Y5SUt2bERrRTNFWldyeEcySUlDOG5lNHpZZUUzR1E9PShqdyQl\n\n20 - OUTROS REQUISITOS\nInformação sobre contratos reservados. Aplica-se a contratos reservados (54º-A)? Não\n\n21 - CRITÉRIO DE ADJUDICAÇÃO\nMultifator: Não\nMonofator:\nNome: Outros\nOutro nome: Preço\n\n24 - CONDIÇÕES DO CONTRATO\nFaturação Eletrónica: Permitido\nObrigação de Subcontratação:\nCódigo da Obrigação de Subcontratação: Não é aplicável nenhuma obrigação de subcontratação.\n\n25 - COMPRA PÚBLICA ESTRATÉGICA\nCompra Pública Estratégica: Inexistência de contratação pública estratégica\n\n26 - INFORMAÇÕES ADICIONAIS\nContrato adequado para PME: Sim\nCobertura ACP (Acordo dos Contratos Públicos da Organização Mundial do Comércio): Não\n\n27 - IDENTIFICAÇÃO E CONTACTOS DO ÓRGÃO DE RECURSOS ADMINISTRATIVOS\nDesignação: Município de Palmela\nEndereço: Largo do Municipio\nCódigo postal: 2954-001\nLocalidade: Palmela\nTelefone: +351 0351212336670\nFax: +351 0351212336671\nEndereço eletrónico: depop@cm-palmela.pt\n\n28 - IDENTIFICAÇÃO DO(S) AUTOR(ES) DE ANÚNCIO\nNome: Álvaro Amaro\nCargo: Presidente da Câmara Municipal de Palmela\n419362876",
    "nipc": "506187543",
    "distrito": "Setúbal",
    "concelho": "Palmela",
    "freguesia": "Freguesia de Palmela",
    "site": "www.cm-palmela.pt",
    "email": "geral@cm-palmela.pt",
    "designacao_contrato": "Empreitada de Requalificação da UCSP de Poceirão",
    "descricao": "Empreitada de Requalificação da UCSP de Poceirão - Os trabalhos a realizar englobam essencialmente trabalhos de beneficiação e reforço do isolamento térmico das fachadas com sistema ETICS, tratamento e pintura de paredes e tetos interiores, substituição de estores, reforço do isolamento da laje de esteira da cobertura com lã de rocha, revisão das coberturas, limpeza de caleiras e substituição dos órgãos de apoio à drenagem de águas pluviais",
    "preco_base": "81.500,00 EUR",
    "prazo_execucao": "60 DIAS",
    "prazo_apresentacao_propostas": "15-08-2025 23:59",
    "fundos_eu": "Sim",
    "plataforma_eletronica": "VORTAL",
    "url_procedimento": "https://community.vortal.biz/public/",
    "autor_nome": "Álvaro Amaro",
    "autor_cargo": "Presidente da Câmara Municipal de Palmela"
  },
  {
    "numero_procedimento": "N/A",
    "entidade": "AnÃºncio de procedimento  n.Âº 20669/2025  -  DiÃ¡rio da RepÃºblica n.Âº 147/2025, SÃ©rie II de 2025-08-01",
    "link": "https://diariodarepublica.pt/dr/detalhe/contrato-publico/20669-927474294"
  },
  {
    "numero_procedimento": "N/A",
    "entidade": "AnÃºncio de procedimento  n.Âº 20670/2025  -  DiÃ¡rio da RepÃºblica n.Âº 147/2025, SÃ©rie II de 2025-08-01",
    "link": "https://diariodarepublica.pt/dr/detalhe/contrato-publico/20670-927474295"
  },
  {
    "numero_procedimento": "N/A",
    "entidade": "AnÃºncio de procedimento  n.Âº 20671/2025  -  DiÃ¡rio da RepÃºblica n.Âº 147/2025, SÃ©rie II de 2025-08-01",
    "link": "https://diariodarepublica.pt/dr/detalhe/contrato-publico/20671-927474296"
  },
  {
    "numero_procedimento": "N/A",
    "entidade": "AnÃºncio de procedimento  n.Âº 20672/2025  -  DiÃ¡rio da RepÃºblica n.Âº 147/2025, SÃ©rie II de 2025-08-01",
    "link": "https://diariodarepublica.pt/dr/detalhe/contrato-publico/20672-927474297"
  },
  {
    "numero_procedimento": "N/A",
    "entidade": "AnÃºncio de procedimento  n.Âº 20673/2025  -  DiÃ¡rio da RepÃºblica n.Âº 147/2025, SÃ©rie II de 2025-08-01",
    "link": "https://diariodarepublica.pt/dr/detalhe/contrato-publico/20673-927474298"
  },
  {
    "numero_procedimento": "N/A",
    "entidade": "AnÃºncio de procedimento  n.Âº 20674/2025  -  DiÃ¡rio da RepÃºblica n.Âº 147/2025, SÃ©rie II de 2025-08-01",
    "link": "https://diariodarepublica.pt/dr/detalhe/contrato-publico/20674-927474299"
  },
  {
    "numero_procedimento": "N/A",
    "entidade": "AnÃºncio de procedimento  n.Âº 20676/2025  -  DiÃ¡rio da RepÃºblica n.Âº 147/2025, SÃ©rie II de 2025-08-01",
    "link": "https://diariodarepublica.pt/dr/detalhe/contrato-publico/20676-927474300"
  },
  {
    "numero_procedimento": "N/A",
    "entidade": "AnÃºncio de procedimento  n.Âº 20677/2025  -  DiÃ¡rio da RepÃºblica n.Âº 147/2025, SÃ©rie II de 2025-08-01",
    "link": "https://diariodarepublica.pt/dr/detalhe/contrato-publico/20677-927474301"
  },
  {
    "numero_procedimento": "N/A",
    "entidade": "AnÃºncio de procedimento  n.Âº 20678/2025  -  DiÃ¡rio da RepÃºblica n.Âº 147/2025, SÃ©rie II de 2025-08-01",
    "link": "https://diariodarepublica.pt/dr/detalhe/contrato-publico/20678-927474314"
  },
  {
    "numero_procedimento": "N/A",
    "entidade": "AnÃºncio de procedimento  n.Âº 20679/2025  -  DiÃ¡rio da RepÃºblica n.Âº 147/2025, SÃ©rie II de 2025-08-01",
    "link": "https://diariodarepublica.pt/dr/detalhe/contrato-publico/20679-927474315"
  },
  {
    "numero_procedimento": "N/A",
    "entidade": "AnÃºncio de procedimento  n.Âº 20680/2025  -  DiÃ¡rio da RepÃºblica n.Âº 147/2025, SÃ©rie II de 2025-08-01",
    "link": "https://diariodarepublica.pt/dr/detalhe/contrato-publico/20680-927474316"
  },
  {
    "numero_procedimento": "N/A",
    "entidade": "AnÃºncio de procedimento  n.Âº 20682/2025  -  DiÃ¡rio da RepÃºblica n.Âº 147/2025, SÃ©rie II de 2025-08-01",
    "link": "https://diariodarepublica.pt/dr/detalhe/contrato-publico/20682-927474324"
  },
  {
    "numero_procedimento": "N/A",
    "entidade": "AnÃºncio de procedimento  n.Âº 20683/2025  -  DiÃ¡rio da RepÃºblica n.Âº 147/2025, SÃ©rie II de 2025-08-01",
    "link": "https://diariodarepublica.pt/dr/detalhe/contrato-publico/20683-927474325"
  },
  {
    "numero_procedimento": "N/A",
    "entidade": "AnÃºncio de procedimento  n.Âº 20684/2025  -  DiÃ¡rio da RepÃºblica n.Âº 147/2025, SÃ©rie II de 2025-08-01",
    "link": "https://diariodarepublica.pt/dr/detalhe/contrato-publico/20684-927474326"
  },
  {
    "numero_procedimento": "N/A",
    "entidade": "AnÃºncio de procedimento  n.Âº 20686/2025  -  DiÃ¡rio da RepÃºblica n.Âº 147/2025, SÃ©rie II de 2025-08-01",
    "link": "https://diariodarepublica.pt/dr/detalhe/contrato-publico/20686-927474327"
  },
  {
    "numero_procedimento": "N/A",
    "entidade": "AnÃºncio de procedimento  n.Âº 20689/2025  -  DiÃ¡rio da RepÃºblica n.Âº 147/2025, SÃ©rie II de 2025-08-01",
    "link": "https://diariodarepublica.pt/dr/detalhe/contrato-publico/20689-927474328"
  },
  {
    "numero_procedimento": "N/A",
    "entidade": "AnÃºncio de procedimento  n.Âº 20691/2025  -  DiÃ¡rio da RepÃºblica n.Âº 147/2025, SÃ©rie II de 2025-08-01",
    "link": "https://diariodarepublica.pt/dr/detalhe/contrato-publico/20691-927474329"
  },
  {
    "numero_procedimento": "N/A",
    "entidade": "AnÃºncio de procedimento  n.Âº 20693/2025  -  DiÃ¡rio da RepÃºblica n.Âº 147/2025, SÃ©rie II de 2025-08-01",
    "link": "https://diariodarepublica.pt/dr/detalhe/contrato-publico/20693-927474330"
  },
  {
    "numero_procedimento": "N/A",
    "entidade": "AnÃºncio de procedimento  n.Âº 20699/2025  -  DiÃ¡rio da RepÃºblica n.Âº 147/2025, SÃ©rie II de 2025-08-01",
    "link": "https://diariodarepublica.pt/dr/detalhe/contrato-publico/20699-927474334"
  },
  {
    "numero_procedimento": "N/A",
    "entidade": "AdRA - Águas da Região de Aveiro, S.A.",
    "link": "https://diariodarepublica.pt/dr/detalhe/contrato-publico/20701-927474335",
    "detalhes_completos": "1 - IDENTIFICAÇÃO E CONTACTOS DA ENTIDADE ADJUDICANTE\nDesignação da entidade adjudicante: AdRA - Águas da Região de Aveiro, S.A.\nNIPC: 509107630\nServiço/Órgão/Pessoa de contacto: Compras e Logística\nEndereço: Travessa do rua da Paz, nº 4\nCódigo postal: 3800-587\nLocalidade: Cacia - Aveiro\nPaís: Portugal\nNUT III: PT16D\nDistrito: Aveiro\nConcelho: Aveiro\nFreguesia: Freguesia de Cacia\nTelefone: 234910200\nFax: 234910299\nEndereço da Entidade (URL): www.adra.pt\nEndereço Eletrónico: adra@adp.pt\neDelivery Gateway (URL): https://www.acingov.pt\nFunção da Organização: Adquirente\nSubfunção da Organização: Organização cujo orçamento é utilizado para pagar o contrato; Organização que executa o pagamento; Organização responsável pelo tratamento das propostas; Organização que recebe as propostas; Organização que trata os pedidos de participação; Organização que recebe pedidos de participação; Organização que assina o contrato\nNorma jurídica da Entidade Adjudicante: Organismo de direito público\nÁrea de atividade da Autoridade Adjudicante: Proteção ambiental\n\n2 - JORNAL OFICIAL DA UNIÃO EUROPEIA\nO procedimento a que este anúncio diz respeito também é publicitado no Jornal Oficial da União Europeia? Sim\n\n3 - AVISO\nModelo de Anúncio: Concurso limitado por prévia qualificação\nData de Envio do Anúncio: 30-07-2025\n\n5 - PROCESSO\nTipo de Procedimento: Concurso limitado por prévia qualificação\nPreço base do procedimento: Sim\nValor do preço base do procedimento: 1.427.260,00 EUR\nProcedimento com lotes? Não\n\n6 - OBJETO DO CONTRATO\nNúmero de referência interna: CLPQ/2025/03_SE\nDesignação do contrato: CLPQ/2025/03_SE - Aquisição de serviços de vigilância humana e ligações a central de receção de alarmes dos sistemas de segurança eletrónica da AdRA\nDescrição: CLPQ/2025/03_SE - Aquisição de serviços de vigilância humana e ligações a central de receção de alarmes dos sistemas de segurança eletrónica da AdRA\nOpções: Não\nTipo de Contrato Principal: Aquisição de Serviços\nTipo de Contrato: Aquisição de Serviços\nClassificação CPV (Vocabulário Comum para os Contratos Públicos)\nObjeto principal\nVocabulário Principal: 79714000\nPreço base s/IVA: 1.427.260,00 EUR\n\n7 - INDICAÇÕES ADICIONAIS\nO contrato envolve aquisição conjunta (satisfação de várias entidades)? Não\nO contrato é adjudicado por uma central de compras? Não\n\n8 - TÉCNICAS\nO concurso destina-se à celebração de um acordo-quadro? Inexistência de acordo-quadro\nÉ utilizado um leilão eletrónico? Não\nSistema de Aquisição Dinâmico: Inexistência de sistema de aquisição dinâmico\n\n9 - LOCAL DA EXECUÇÃO DO CONTRATO\nLOCAL DA EXECUÇÃO DO CONTRATO (PROCEDIMENTO)\nPaís: Portugal\nNUT III: PT16D\nLocalidade: Freguesia de Cacia\nDistrito: Aveiro\nConcelho: Aveiro\nFreguesia: Freguesia de Cacia\n\n10 - PRAZO DE EXECUÇÃO DO CONTRATO\nPrazo de execução do contrato: 12 MESES\nPrevisão de renovações: Sim\nIndicar número máximo de renovações: 2\nPrazo de renovações diferente do prazo inicial: Não\n\n11 - FUNDOS EU\nTêm fundos EU? Não\n\n12 - DOCUMENTOS DE HABILITAÇÃO\nHabilitação para o exercício da atividade profissional: Não\n\n13 - CONDIÇÕES DE APRESENTAÇÃO\nPlataforma eletrónica utilizada pela entidade adjudicante: ACIN\nURL para Apresentação: https://www.acingov.pt\nAdmissibilidade da apresentação de propostas variantes: Não autorizado\nPrazo para apresentação das candidaturas: 02-09-2025 18:00\nPrazo para a decisão de qualificação: 44 dias a contar do termo do prazo para a apresentação das candidaturas\nRequisitos mínimos \nRequisitos mínimos de capacidade técnica: Experiência curricular, recursos humanos, tecnológicos, de equipamentos e outros; Sistema de controlo de qualidade \nRequisitos mínimos de capacidade financeira: V ≤ R\nem que:\nV = preço contratual (1.427.260,00)\nR = valor médio do EBITDA relativo aos últimos 3 (três) exercícios encerrados contabilisticamente\n\nPrazo durante o qual os concorrentes são obrigados a manter as respetivas propostas: 90 dias a contar do termo do prazo para a apresentação das propostas\nApresentação de Catálogo Eletrónico: Não autorizado\nIndicação de Subcontratação na Proposta: Inexistência de indicação de subcontratação\n\n14 - PRESTAÇÃO DE CAUÇÃO\nPrestação de caução: Sim\nPercentagem: 3%\nDescrição da Garantia Exigida: O valor da caução é de 3.00% do preço contratual.\n\n15 - FORNECIMENTO DAS PEÇAS DO CONCURSO, APRESENTAÇÃO DE PEDIDOS DE PARTICIPAÇÃO E APRESENTAÇÃO DAS PROPOSTAS\nLink para acesso às peças do concurso (URL): https://www.acingov.pt/acingovprod/2/zonaPublica/zona_publica_c/donwloadProcedurePiece/OTI5NDY1\n\n20 - OUTROS REQUISITOS\nInformação sobre contratos reservados. Aplica-se a contratos reservados (54º-A)? Não\n\n21 - CRITÉRIO DE ADJUDICAÇÃO\nMultifator: Não\nMonofator:\nNome: Preço\n\n24 - CONDIÇÕES DO CONTRATO\nFaturação Eletrónica: Necessário\nObrigação de Subcontratação:\nCódigo da Obrigação de Subcontratação: Não é aplicável nenhuma obrigação de subcontratação.\n\n25 - COMPRA PÚBLICA ESTRATÉGICA\nCompra Pública Estratégica: Inexistência de contratação pública estratégica\n\n26 - INFORMAÇÕES ADICIONAIS\nContrato adequado para PME: Sim\nCobertura ACP (Acordo dos Contratos Públicos da Organização Mundial do Comércio): Não\n\n27 - IDENTIFICAÇÃO E CONTACTOS DO ÓRGÃO DE RECURSOS ADMINISTRATIVOS\nDesignação: Conselho de Administração\nEndereço: Travessa do rua da Paz, nº 4\nCódigo postal: 3800-587\nLocalidade: Cacia - Aveiro\nTelefone: 234910200\nFax: \nEndereço eletrónico: adra@adp.pt\nPrazo de interposição do recurso: 30 dias\n\n28 - IDENTIFICAÇÃO DO(S) AUTOR(ES) DE ANÚNCIO\nNome: Anabela Carvalhinhos\nCargo: Gestora do Procedimento\n419372685",
    "nipc": "509107630",
    "distrito": "Aveiro",
    "concelho": "Aveiro",
    "freguesia": "Freguesia de Cacia",
    "site": "www.adra.pt",
    "email": "adra@adp.pt",
    "designacao_contrato": "CLPQ/2025/03_SE - Aquisição de serviços de vigilância humana e ligações a central de receção de alarmes dos sistemas de segurança eletrónica da AdRA",
    "descricao": "CLPQ/2025/03_SE - Aquisição de serviços de vigilância humana e ligações a central de receção de alarmes dos sistemas de segurança eletrónica da AdRA",
    "preco_base": "1.427.260,00 EUR",
    "prazo_execucao": "12 MESES",
    "prazo_apresentacao_propostas": null,
    "fundos_eu": "Não",
    "plataforma_eletronica": "ACIN",
    "url_procedimento": "https://www.acingov.pt",
    "autor_nome": "Anabela Carvalhinhos",
    "autor_cargo": "Gestora do Procedimento"
  },
  {
    "numero_procedimento": "N/A",
    "entidade": "AnÃºncio de procedimento  n.Âº 20705/2025  -  DiÃ¡rio da RepÃºblica n.Âº 147/2025, SÃ©rie II de 2025-08-01",
    "link": "https://diariodarepublica.pt/dr/detalhe/contrato-publico/20705-927474336"
  },
  {
    "numero_procedimento": "N/A",
    "entidade": "AnÃºncio de procedimento  n.Âº 20706/2025  -  DiÃ¡rio da RepÃºblica n.Âº 147/2025, SÃ©rie II de 2025-08-01",
    "link": "https://diariodarepublica.pt/dr/detalhe/contrato-publico/20706-927474337"
  },
  {
    "numero_procedimento": "N/A",
    "entidade": "AnÃºncio de procedimento  n.Âº 20709/2025  -  DiÃ¡rio da RepÃºblica n.Âº 147/2025, SÃ©rie II de 2025-08-01",
    "link": "https://diariodarepublica.pt/dr/detalhe/contrato-publico/20709-927474338"
  },
  {
    "numero_procedimento": "N/A",
    "entidade": "AnÃºncio de procedimento  n.Âº 20713/2025  -  DiÃ¡rio da RepÃºblica n.Âº 147/2025, SÃ©rie II de 2025-08-01",
    "link": "https://diariodarepublica.pt/dr/detalhe/contrato-publico/20713-927474339"
  },
  {
    "numero_procedimento": "N/A",
    "entidade": "AnÃºncio de procedimento  n.Âº 20714/2025  -  DiÃ¡rio da RepÃºblica n.Âº 147/2025, SÃ©rie II de 2025-08-01",
    "link": "https://diariodarepublica.pt/dr/detalhe/contrato-publico/20714-927635194"
  },
  {
    "numero_procedimento": "N/A",
    "entidade": "AnÃºncio de procedimento  n.Âº 20715/2025  -  DiÃ¡rio da RepÃºblica n.Âº 147/2025, SÃ©rie II de 2025-08-01",
    "link": "https://diariodarepublica.pt/dr/detalhe/contrato-publico/20715-927635195"
  },
  {
    "numero_procedimento": "N/A",
    "entidade": "AnÃºncio de procedimento  n.Âº 20716/2025  -  DiÃ¡rio da RepÃºblica n.Âº 147/2025, SÃ©rie II de 2025-08-01",
    "link": "https://diariodarepublica.pt/dr/detalhe/contrato-publico/20716-927635196"
  },
  {
    "numero_procedimento": "N/A",
    "entidade": "AnÃºncio de procedimento  n.Âº 20717/2025  -  DiÃ¡rio da RepÃºblica n.Âº 147/2025, SÃ©rie II de 2025-08-01",
    "link": "https://diariodarepublica.pt/dr/detalhe/contrato-publico/20717-927635197"
  },
  {
    "numero_procedimento": "N/A",
    "entidade": "AnÃºncio de procedimento  n.Âº 20718/2025  -  DiÃ¡rio da RepÃºblica n.Âº 147/2025, SÃ©rie II de 2025-08-01",
    "link": "https://diariodarepublica.pt/dr/detalhe/contrato-publico/20718-927635198"
  },
  {
    "numero_procedimento": "N/A",
    "entidade": "AnÃºncio de procedimento  n.Âº 20719/2025  -  DiÃ¡rio da RepÃºblica n.Âº 147/2025, SÃ©rie II de 2025-08-01",
    "link": "https://diariodarepublica.pt/dr/detalhe/contrato-publico/20719-927635199"
  },
  {
    "numero_procedimento": "N/A",
    "entidade": "AnÃºncio de procedimento  n.Âº 20720/2025  -  DiÃ¡rio da RepÃºblica n.Âº 147/2025, SÃ©rie II de 2025-08-01",
    "link": "https://diariodarepublica.pt/dr/detalhe/contrato-publico/20720-927635200"
  },
  {
    "numero_procedimento": "N/A",
    "entidade": "AnÃºncio de procedimento  n.Âº 20721/2025  -  DiÃ¡rio da RepÃºblica n.Âº 147/2025, SÃ©rie II de 2025-08-01",
    "link": "https://diariodarepublica.pt/dr/detalhe/contrato-publico/20721-927635201"
  },
  {
    "numero_procedimento": "N/A",
    "entidade": "AnÃºncio de procedimento  n.Âº 20722/2025  -  DiÃ¡rio da RepÃºblica n.Âº 147/2025, SÃ©rie II de 2025-08-01",
    "link": "https://diariodarepublica.pt/dr/detalhe/contrato-publico/20722-927635202"
  },
  {
    "numero_procedimento": "N/A",
    "entidade": "AnÃºncio de procedimento  n.Âº 20723/2025  -  DiÃ¡rio da RepÃºblica n.Âº 147/2025, SÃ©rie II de 2025-08-01",
    "link": "https://diariodarepublica.pt/dr/detalhe/contrato-publico/20723-927635203"
  },
  {
    "numero_procedimento": "N/A",
    "entidade": "AnÃºncio de procedimento  n.Âº 20724/2025  -  DiÃ¡rio da RepÃºblica n.Âº 147/2025, SÃ©rie II de 2025-08-01",
    "link": "https://diariodarepublica.pt/dr/detalhe/contrato-publico/20724-927635204"
  },
  {
    "numero_procedimento": "N/A",
    "entidade": "AnÃºncio de procedimento  n.Âº 20725/2025  -  DiÃ¡rio da RepÃºblica n.Âº 147/2025, SÃ©rie II de 2025-08-01",
    "link": "https://diariodarepublica.pt/dr/detalhe/contrato-publico/20725-927635205"
  },
  {
    "numero_procedimento": "N/A",
    "entidade": "AnÃºncio de procedimento  n.Âº 20703/2025  -  DiÃ¡rio da RepÃºblica n.Âº 147/2025, SÃ©rie II de 2025-08-01",
    "link": "https://diariodarepublica.pt/dr/detalhe/contrato-publico/20703-927635206"
  },
  {
    "numero_procedimento": "N/A",
    "entidade": "AnÃºncio de procedimento  n.Âº 20726/2025  -  DiÃ¡rio da RepÃºblica n.Âº 147/2025, SÃ©rie II de 2025-08-01",
    "link": "https://diariodarepublica.pt/dr/detalhe/contrato-publico/20726-927635207"
  },
  {
    "numero_procedimento": "N/A",
    "entidade": "AnÃºncio de procedimento  n.Âº 20727/2025  -  DiÃ¡rio da RepÃºblica n.Âº 147/2025, SÃ©rie II de 2025-08-01",
    "link": "https://diariodarepublica.pt/dr/detalhe/contrato-publico/20727-927635208"
  },
  {
    "numero_procedimento": "N/A",
    "entidade": "AnÃºncio de procedimento  n.Âº 20728/2025  -  DiÃ¡rio da RepÃºblica n.Âº 147/2025, SÃ©rie II de 2025-08-01",
    "link": "https://diariodarepublica.pt/dr/detalhe/contrato-publico/20728-927635209"
  },
  {
    "numero_procedimento": "N/A",
    "entidade": "AnÃºncio de procedimento  n.Âº 20729/2025  -  DiÃ¡rio da RepÃºblica n.Âº 147/2025, SÃ©rie II de 2025-08-01",
    "link": "https://diariodarepublica.pt/dr/detalhe/contrato-publico/20729-927635210"
  },
  {
    "numero_procedimento": "N/A",
    "entidade": "AnÃºncio de procedimento  n.Âº 20732/2025  -  DiÃ¡rio da RepÃºblica n.Âº 147/2025, SÃ©rie II de 2025-08-01",
    "link": "https://diariodarepublica.pt/dr/detalhe/contrato-publico/20732-927635239"
  },
  {
    "numero_procedimento": "N/A",
    "entidade": "AnÃºncio de procedimento  n.Âº 20733/2025  -  DiÃ¡rio da RepÃºblica n.Âº 147/2025, SÃ©rie II de 2025-08-01",
    "link": "https://diariodarepublica.pt/dr/detalhe/contrato-publico/20733-927635240"
  },
  {
    "numero_procedimento": "N/A",
    "entidade": "AnÃºncio de procedimento  n.Âº 20704/2025  -  DiÃ¡rio da RepÃºblica n.Âº 147/2025, SÃ©rie II de 2025-08-01",
    "link": "https://diariodarepublica.pt/dr/detalhe/contrato-publico/20704-927635244"
  },
  {
    "numero_procedimento": "N/A",
    "entidade": "AnÃºncio de procedimento  n.Âº 20740/2025  -  DiÃ¡rio da RepÃºblica n.Âº 147/2025, SÃ©rie II de 2025-08-01",
    "link": "https://diariodarepublica.pt/dr/detalhe/contrato-publico/20740-927635246"
  },
  {
    "numero_procedimento": "N/A",
    "entidade": "AnÃºncio de procedimento  n.Âº 20741/2025  -  DiÃ¡rio da RepÃºblica n.Âº 147/2025, SÃ©rie II de 2025-08-01",
    "link": "https://diariodarepublica.pt/dr/detalhe/contrato-publico/20741-927635247"
  },
  {
    "numero_procedimento": "N/A",
    "entidade": "AnÃºncio de procedimento  n.Âº 20744/2025  -  DiÃ¡rio da RepÃºblica n.Âº 147/2025, SÃ©rie II de 2025-08-01",
    "link": "https://diariodarepublica.pt/dr/detalhe/contrato-publico/20744-927635248"
  },
  {
    "numero_procedimento": "N/A",
    "entidade": "AnÃºncio de procedimento  n.Âº 20745/2025  -  DiÃ¡rio da RepÃºblica n.Âº 147/2025, SÃ©rie II de 2025-08-01",
    "link": "https://diariodarepublica.pt/dr/detalhe/contrato-publico/20745-927635249"
  },
  {
    "numero_procedimento": "N/A",
    "entidade": "AnÃºncio de procedimento  n.Âº 20746/2025  -  DiÃ¡rio da RepÃºblica n.Âº 147/2025, SÃ©rie II de 2025-08-01",
    "link": "https://diariodarepublica.pt/dr/detalhe/contrato-publico/20746-927635250"
  },
  {
    "numero_procedimento": "N/A",
    "entidade": "AnÃºncio de procedimento  n.Âº 20747/2025  -  DiÃ¡rio da RepÃºblica n.Âº 147/2025, SÃ©rie II de 2025-08-01",
    "link": "https://diariodarepublica.pt/dr/detalhe/contrato-publico/20747-927635251"
  },
  {
    "numero_procedimento": "N/A",
    "entidade": "AnÃºncio de procedimento  n.Âº 20748/2025  -  DiÃ¡rio da RepÃºblica n.Âº 147/2025, SÃ©rie II de 2025-08-01",
    "link": "https://diariodarepublica.pt/dr/detalhe/contrato-publico/20748-927635252"
  },
  {
    "numero_procedimento": "N/A",
    "entidade": "AnÃºncio de procedimento  n.Âº 20749/2025  -  DiÃ¡rio da RepÃºblica n.Âº 147/2025, SÃ©rie II de 2025-08-01",
    "link": "https://diariodarepublica.pt/dr/detalhe/contrato-publico/20749-927635253"
  },
  {
    "numero_procedimento": "N/A",
    "entidade": "AnÃºncio de procedimento  n.Âº 20751/2025  -  DiÃ¡rio da RepÃºblica n.Âº 147/2025, SÃ©rie II de 2025-08-01",
    "link": "https://diariodarepublica.pt/dr/detalhe/contrato-publico/20751-927635254"
  },
  {
    "numero_procedimento": "N/A",
    "entidade": "AnÃºncio de procedimento  n.Âº 20754/2025  -  DiÃ¡rio da RepÃºblica n.Âº 147/2025, SÃ©rie II de 2025-08-01",
    "link": "https://diariodarepublica.pt/dr/detalhe/contrato-publico/20754-927635255"
  },
  {
    "numero_procedimento": "N/A",
    "entidade": "AnÃºncio de procedimento  n.Âº 20756/2025  -  DiÃ¡rio da RepÃºblica n.Âº 147/2025, SÃ©rie II de 2025-08-01",
    "link": "https://diariodarepublica.pt/dr/detalhe/contrato-publico/20756-927635256"
  },
  {
    "numero_procedimento": "N/A",
    "entidade": "AnÃºncio de procedimento  n.Âº 20757/2025  -  DiÃ¡rio da RepÃºblica n.Âº 147/2025, SÃ©rie II de 2025-08-01",
    "link": "https://diariodarepublica.pt/dr/detalhe/contrato-publico/20757-927635257"
  },
  {
    "numero_procedimento": "N/A",
    "entidade": "AnÃºncio de procedimento  n.Âº 20760/2025  -  DiÃ¡rio da RepÃºblica n.Âº 147/2025, SÃ©rie II de 2025-08-01",
    "link": "https://diariodarepublica.pt/dr/detalhe/contrato-publico/20760-927635258"
  },
  {
    "numero_procedimento": "N/A",
    "entidade": "AnÃºncio de procedimento  n.Âº 20761/2025  -  DiÃ¡rio da RepÃºblica n.Âº 147/2025, SÃ©rie II de 2025-08-01",
    "link": "https://diariodarepublica.pt/dr/detalhe/contrato-publico/20761-927635259"
  },
  {
    "numero_procedimento": "N/A",
    "entidade": "AnÃºncio de procedimento  n.Âº 20768/2025  -  DiÃ¡rio da RepÃºblica n.Âº 147/2025, SÃ©rie II de 2025-08-01",
    "link": "https://diariodarepublica.pt/dr/detalhe/contrato-publico/20768-927635261"
  },
  {
    "numero_procedimento": "N/A",
    "entidade": "AnÃºncio de procedimento  n.Âº 20769/2025  -  DiÃ¡rio da RepÃºblica n.Âº 147/2025, SÃ©rie II de 2025-08-01",
    "link": "https://diariodarepublica.pt/dr/detalhe/contrato-publico/20769-927635262"
  },
  {
    "numero_procedimento": "N/A",
    "entidade": "AnÃºncio de procedimento  n.Âº 20772/2025  -  DiÃ¡rio da RepÃºblica n.Âº 147/2025, SÃ©rie II de 2025-08-01",
    "link": "https://diariodarepublica.pt/dr/detalhe/contrato-publico/20772-927635263"
  },
  {
    "numero_procedimento": "N/A",
    "entidade": "AnÃºncio de procedimento  n.Âº 20773/2025  -  DiÃ¡rio da RepÃºblica n.Âº 147/2025, SÃ©rie II de 2025-08-01",
    "link": "https://diariodarepublica.pt/dr/detalhe/contrato-publico/20773-927635264"
  },
  {
    "numero_procedimento": "N/A",
    "entidade": "AnÃºncio de procedimento  n.Âº 20774/2025  -  DiÃ¡rio da RepÃºblica n.Âº 147/2025, SÃ©rie II de 2025-08-01",
    "link": "https://diariodarepublica.pt/dr/detalhe/contrato-publico/20774-927635265"
  },
  {
    "numero_procedimento": "N/A",
    "entidade": "AnÃºncio de procedimento  n.Âº 20775/2025  -  DiÃ¡rio da RepÃºblica n.Âº 147/2025, SÃ©rie II de 2025-08-01",
    "link": "https://diariodarepublica.pt/dr/detalhe/contrato-publico/20775-927635266"
  },
  {
    "numero_procedimento": "N/A",
    "entidade": "AnÃºncio de procedimento  n.Âº 20778/2025  -  DiÃ¡rio da RepÃºblica n.Âº 147/2025, SÃ©rie II de 2025-08-01",
    "link": "https://diariodarepublica.pt/dr/detalhe/contrato-publico/20778-927635267"
  },
  {
    "numero_procedimento": "N/A",
    "entidade": "AnÃºncio de procedimento  n.Âº 20779/2025  -  DiÃ¡rio da RepÃºblica n.Âº 147/2025, SÃ©rie II de 2025-08-01",
    "link": "https://diariodarepublica.pt/dr/detalhe/contrato-publico/20779-927635268"
  },
  {
    "numero_procedimento": "N/A",
    "entidade": "AnÃºncio de procedimento  n.Âº 20730/2025  -  DiÃ¡rio da RepÃºblica n.Âº 147/2025, SÃ©rie II de 2025-08-01",
    "link": "https://diariodarepublica.pt/dr/detalhe/contrato-publico/20730-927638126"
  },
  {
    "numero_procedimento": "N/A",
    "entidade": "AnÃºncio de procedimento  n.Âº 20731/2025  -  DiÃ¡rio da RepÃºblica n.Âº 147/2025, SÃ©rie II de 2025-08-01",
    "link": "https://diariodarepublica.pt/dr/detalhe/contrato-publico/20731-927638127"
  },
  {
    "numero_procedimento": "N/A",
    "entidade": "AnÃºncio de procedimento  n.Âº 20734/2025  -  DiÃ¡rio da RepÃºblica n.Âº 147/2025, SÃ©rie II de 2025-08-01",
    "link": "https://diariodarepublica.pt/dr/detalhe/contrato-publico/20734-927638128"
  },
  {
    "numero_procedimento": "N/A",
    "entidade": "AnÃºncio de procedimento  n.Âº 20735/2025  -  DiÃ¡rio da RepÃºblica n.Âº 147/2025, SÃ©rie II de 2025-08-01",
    "link": "https://diariodarepublica.pt/dr/detalhe/contrato-publico/20735-927638129"
  },
  {
    "numero_procedimento": "N/A",
    "entidade": "AnÃºncio de procedimento  n.Âº 20736/2025  -  DiÃ¡rio da RepÃºblica n.Âº 147/2025, SÃ©rie II de 2025-08-01",
    "link": "https://diariodarepublica.pt/dr/detalhe/contrato-publico/20736-927638132"
  },
  {
    "numero_procedimento": "N/A",
    "entidade": "AnÃºncio de procedimento  n.Âº 20737/2025  -  DiÃ¡rio da RepÃºblica n.Âº 147/2025, SÃ©rie II de 2025-08-01",
    "link": "https://diariodarepublica.pt/dr/detalhe/contrato-publico/20737-927638141"
  },
  {
    "numero_procedimento": "N/A",
    "entidade": "AnÃºncio de procedimento  n.Âº 20738/2025  -  DiÃ¡rio da RepÃºblica n.Âº 147/2025, SÃ©rie II de 2025-08-01",
    "link": "https://diariodarepublica.pt/dr/detalhe/contrato-publico/20738-927638142"
  },
  {
    "numero_procedimento": "N/A",
    "entidade": "AnÃºncio de procedimento  n.Âº 20739/2025  -  DiÃ¡rio da RepÃºblica n.Âº 147/2025, SÃ©rie II de 2025-08-01",
    "link": "https://diariodarepublica.pt/dr/detalhe/contrato-publico/20739-927638143"
  },
  {
    "numero_procedimento": "N/A",
    "entidade": "AnÃºncio de procedimento  n.Âº 20742/2025  -  DiÃ¡rio da RepÃºblica n.Âº 147/2025, SÃ©rie II de 2025-08-01",
    "link": "https://diariodarepublica.pt/dr/detalhe/contrato-publico/20742-927638145"
  },
  {
    "numero_procedimento": "N/A",
    "entidade": "AnÃºncio de procedimento  n.Âº 20743/2025  -  DiÃ¡rio da RepÃºblica n.Âº 147/2025, SÃ©rie II de 2025-08-01",
    "link": "https://diariodarepublica.pt/dr/detalhe/contrato-publico/20743-927638146"
  },
  {
    "numero_procedimento": "N/A",
    "entidade": "AnÃºncio de procedimento  n.Âº 20750/2025  -  DiÃ¡rio da RepÃºblica n.Âº 147/2025, SÃ©rie II de 2025-08-01",
    "link": "https://diariodarepublica.pt/dr/detalhe/contrato-publico/20750-927638147"
  },
  {
    "numero_procedimento": "N/A",
    "entidade": "AnÃºncio de procedimento  n.Âº 20752/2025  -  DiÃ¡rio da RepÃºblica n.Âº 147/2025, SÃ©rie II de 2025-08-01",
    "link": "https://diariodarepublica.pt/dr/detalhe/contrato-publico/20752-927638148"
  },
  {
    "numero_procedimento": "N/A",
    "entidade": "AnÃºncio de procedimento  n.Âº 20753/2025  -  DiÃ¡rio da RepÃºblica n.Âº 147/2025, SÃ©rie II de 2025-08-01",
    "link": "https://diariodarepublica.pt/dr/detalhe/contrato-publico/20753-927638149"
  },
  {
    "numero_procedimento": "N/A",
    "entidade": "AnÃºncio de procedimento  n.Âº 20755/2025  -  DiÃ¡rio da RepÃºblica n.Âº 147/2025, SÃ©rie II de 2025-08-01",
    "link": "https://diariodarepublica.pt/dr/detalhe/contrato-publico/20755-927638150"
  },
  {
    "numero_procedimento": "N/A",
    "entidade": "AnÃºncio de procedimento  n.Âº 20758/2025  -  DiÃ¡rio da RepÃºblica n.Âº 147/2025, SÃ©rie II de 2025-08-01",
    "link": "https://diariodarepublica.pt/dr/detalhe/contrato-publico/20758-927638151"
  },
  {
    "numero_procedimento": "N/A",
    "entidade": "AnÃºncio de procedimento  n.Âº 20759/2025  -  DiÃ¡rio da RepÃºblica n.Âº 147/2025, SÃ©rie II de 2025-08-01",
    "link": "https://diariodarepublica.pt/dr/detalhe/contrato-publico/20759-927638152"
  },
  {
    "numero_procedimento": "N/A",
    "entidade": "Município de Lisboa",
    "link": "https://diariodarepublica.pt/dr/detalhe/contrato-publico/20762-927638153",
    "detalhes_completos": "1 - IDENTIFICAÇÃO E CONTACTOS DA ENTIDADE ADJUDICANTE\nDesignação da entidade adjudicante: Município de Lisboa\nNIPC: 500051070\nServiço/Órgão/Pessoa de contacto: Departamento de Edifícios Municipais\nEndereço: Campo Grande N.º 25 - 9.º A\nCódigo postal: 1749-099\nLocalidade: Lisboa\nPaís: Portugal\nNUT III: PT170\nDistrito: Lisboa\nConcelho: Lisboa\nFreguesia: Freguesia de Alvalade - Lisboa\nTelefone: 217988000\nFax: 217988000\nEndereço da Entidade (URL): http://www.lisboa.pt\nEndereço Eletrónico: dmf.da.dcp@cm-lisboa.pt\neDelivery Gateway (URL): https://www.acingov.pt\nFunção da Organização: Adquirente\nSubfunção da Organização: Organização que recebe as propostas\nNorma jurídica da Entidade Adjudicante: Autoridade local\nÁrea de atividade da Autoridade Adjudicante: Serviços públicos das administrações públicas\n\n2 - JORNAL OFICIAL DA UNIÃO EUROPEIA\nO procedimento a que este anúncio diz respeito também é publicitado no Jornal Oficial da União Europeia? Não\n\n3 - AVISO\nModelo de Anúncio: Concurso público\nData de Envio do Anúncio: 01-08-2025\n\n5 - PROCESSO\nTipo de Procedimento: Concurso público\nPreço base do procedimento: Sim\nValor do preço base do procedimento: 10.651,58 EUR\nProcedimento com lotes? Não\n\n6 - OBJETO DO CONTRATO\nNúmero de referência interna: 25/CP/DGES/ND/2025\nDesignação do contrato: Empreitada n.º 9/DMMC/DEM/DPCE/25 - Beneficiação do Recreio da EB/JI Luisa Ducla Soares, Santo António - Processo n.º 0025/CP/DGES/ND/2025\nDescrição: Empreitada n.º 9/DMMC/DEM/DPCE/25 - Beneficiação do Recreio da EB/JI Luisa Ducla Soares, Santo António - Processo n.º 0025/CP/DGES/ND/2025\nTipo de Contrato Principal: Empreitada de Obras Públicas\nTipo de Contrato: Empreitada de Obras Públicas\nClassificação CPV (Vocabulário Comum para os Contratos Públicos)\nObjeto principal\nVocabulário Principal: 45112720\nPreço base s/IVA: 10.651,58 EUR\n\n7 - INDICAÇÕES ADICIONAIS\nO contrato envolve aquisição conjunta (satisfação de várias entidades)? Não\nO contrato é adjudicado por uma central de compras? Não\n\n8 - TÉCNICAS\nO concurso destina-se à celebração de um acordo-quadro? Inexistência de acordo-quadro\nÉ utilizado um leilão eletrónico? Não\nÉ adotada uma fase de negociação? Não\nSistema de Aquisição Dinâmico: Inexistência de sistema de aquisição dinâmico\n\n9 - LOCAL DA EXECUÇÃO DO CONTRATO\nLOCAL DA EXECUÇÃO DO CONTRATO (PROCEDIMENTO)\nPaís: Portugal\nNUT III: PT170\nLocalidade: Freguesia de Santo António - Lisboa\nDistrito: Lisboa\nConcelho: Lisboa\nFreguesia: Freguesia de Santo António - Lisboa\n\n10 - PRAZO DE EXECUÇÃO DO CONTRATO\nPrazo de execução do contrato: 90 DIAS\nPrevisão de renovações: Não\n\n11 - FUNDOS EU\nTêm fundos EU? Não\n\n12 - DOCUMENTOS DE HABILITAÇÃO\nHabilitação para o exercício da atividade profissional: Não\n\n13 - CONDIÇÕES DE APRESENTAÇÃO\nPlataforma eletrónica utilizada pela entidade adjudicante: ACIN\nURL para Apresentação: https://www.acingov.pt\nAdmissibilidade da apresentação de propostas variantes: Não autorizado\nPrazo para apresentação das propostas: 22-08-2025 23:59\nPrazo durante o qual os concorrentes são obrigados a manter as respetivas propostas: 180 dias a contar do termo do prazo para a apresentação das propostas\nIndicação de Subcontratação na Proposta: Inexistência de indicação de subcontratação\n\n14 - PRESTAÇÃO DE CAUÇÃO\nPrestação de caução: Não\n\n15 - FORNECIMENTO DAS PEÇAS DO CONCURSO, APRESENTAÇÃO DE PEDIDOS DE PARTICIPAÇÃO E APRESENTAÇÃO DAS PROPOSTAS\nLink para acesso às peças do concurso (URL): https://www.acingov.pt/acingovprod/2/zonaPublica/zona_publica_c/donwloadProcedurePiece/OTMwNTA5\n\n20 - OUTROS REQUISITOS\nInformação sobre contratos reservados. Aplica-se a contratos reservados (54º-A)? Não\n\n21 - CRITÉRIO DE ADJUDICAÇÃO\nMultifator: Não\nMonofator:\nNome: Preço\n\n24 - CONDIÇÕES DO CONTRATO\nFaturação Eletrónica: Permitido\nObrigação de Subcontratação:\nCódigo da Obrigação de Subcontratação: Não é aplicável nenhuma obrigação de subcontratação.\n\n25 - COMPRA PÚBLICA ESTRATÉGICA\nCompra Pública Estratégica: Redução dos impactos ambientais; Realização dos objetivos sociais\nDescrição do Processo de Adjudicação Estratégico: Implementação da ISO 20400 no Município de Lisboa\nCritérios de contratos Públicos Ecológicos: Critérios de contratação pública ecológica nacional; Outros critérios de contratação pública ecológica\nCategorias da estratégia nacional: Manutenção de espaços públicos\nContratos Públicos Ecológicos: A transição para uma economia circular\nDiretiva Veículos Não Poluentes: Não\nContratos Públicos Sociais: Condições de trabalho justas; Igualdade de género; Igualdade étnica\nCritério de Acessibilidade: Os critérios de acessibilidade para as pessoas com deficiência estão incluídos\n\n26 - INFORMAÇÕES ADICIONAIS\nContrato adequado para PME: Não\nCobertura ACP (Acordo dos Contratos Públicos da Organização Mundial do Comércio): Não\n\n27 - IDENTIFICAÇÃO E CONTACTOS DO ÓRGÃO DE RECURSOS ADMINISTRATIVOS\nDesignação: Município de Lisboa\nEndereço: Campo Grande N.º 13, 2º e 6ºandar\nCódigo postal: 1700-087\nLocalidade: Lisboa\nTelefone: 217806196\nFax: \nEndereço eletrónico: dmmc.dges.dle@cm-lisboa.pt\n\n28 - IDENTIFICAÇÃO DO(S) AUTOR(ES) DE ANÚNCIO\nNome: Fátima Proença\nCargo: Diretora Departamento\n419385986",
    "nipc": "500051070",
    "distrito": "Lisboa",
    "concelho": "Lisboa",
    "freguesia": "Freguesia de Alvalade - Lisboa",
    "site": "http://www.lisboa.pt",
    "email": "dmf.da.dcp@cm-lisboa.pt",
    "designacao_contrato": "Empreitada n.º 9/DMMC/DEM/DPCE/25 - Beneficiação do Recreio da EB/JI Luisa Ducla Soares, Santo António - Processo n.º 0025/CP/DGES/ND/2025",
    "descricao": "Empreitada n.º 9/DMMC/DEM/DPCE/25 - Beneficiação do Recreio da EB/JI Luisa Ducla Soares, Santo António - Processo n.º 0025/CP/DGES/ND/2025",
    "preco_base": "10.651,58 EUR",
    "prazo_execucao": "90 DIAS",
    "prazo_apresentacao_propostas": "22-08-2025 23:59",
    "fundos_eu": "Não",
    "plataforma_eletronica": "ACIN",
    "url_procedimento": "https://www.acingov.pt",
    "autor_nome": "Fátima Proença",
    "autor_cargo": "Diretora Departamento"
  },
  {
    "numero_procedimento": "N/A",
    "entidade": "AnÃºncio de procedimento  n.Âº 20763/2025  -  DiÃ¡rio da RepÃºblica n.Âº 147/2025, SÃ©rie II de 2025-08-01",
    "link": "https://diariodarepublica.pt/dr/detalhe/contrato-publico/20763-927638154"
  },
  {
    "numero_procedimento": "N/A",
    "entidade": "AnÃºncio de procedimento  n.Âº 20764/2025  -  DiÃ¡rio da RepÃºblica n.Âº 147/2025, SÃ©rie II de 2025-08-01",
    "link": "https://diariodarepublica.pt/dr/detalhe/contrato-publico/20764-927638155"
  },
  {
    "numero_procedimento": "N/A",
    "entidade": "AnÃºncio de procedimento  n.Âº 20765/2025  -  DiÃ¡rio da RepÃºblica n.Âº 147/2025, SÃ©rie II de 2025-08-01",
    "link": "https://diariodarepublica.pt/dr/detalhe/contrato-publico/20765-927638156"
  },
  {
    "numero_procedimento": "N/A",
    "entidade": "AnÃºncio de procedimento  n.Âº 20766/2025  -  DiÃ¡rio da RepÃºblica n.Âº 147/2025, SÃ©rie II de 2025-08-01",
    "link": "https://diariodarepublica.pt/dr/detalhe/contrato-publico/20766-927638157"
  },
  {
    "numero_procedimento": "N/A",
    "entidade": "AnÃºncio de procedimento  n.Âº 20767/2025  -  DiÃ¡rio da RepÃºblica n.Âº 147/2025, SÃ©rie II de 2025-08-01",
    "link": "https://diariodarepublica.pt/dr/detalhe/contrato-publico/20767-927638158"
  },
  {
    "numero_procedimento": "N/A",
    "entidade": "AnÃºncio de procedimento  n.Âº 20770/2025  -  DiÃ¡rio da RepÃºblica n.Âº 147/2025, SÃ©rie II de 2025-08-01",
    "link": "https://diariodarepublica.pt/dr/detalhe/contrato-publico/20770-927638160"
  },
  {
    "numero_procedimento": "N/A",
    "entidade": "AnÃºncio de procedimento  n.Âº 20771/2025  -  DiÃ¡rio da RepÃºblica n.Âº 147/2025, SÃ©rie II de 2025-08-01",
    "link": "https://diariodarepublica.pt/dr/detalhe/contrato-publico/20771-927638161"
  },
  {
    "numero_procedimento": "N/A",
    "entidade": "AnÃºncio de procedimento  n.Âº 20776/2025  -  DiÃ¡rio da RepÃºblica n.Âº 147/2025, SÃ©rie II de 2025-08-01",
    "link": "https://diariodarepublica.pt/dr/detalhe/contrato-publico/20776-927638162"
  },
  {
    "numero_procedimento": "N/A",
    "entidade": "Município de Armamar",
    "link": "https://diariodarepublica.pt/dr/detalhe/contrato-publico/20777-927638163",
    "detalhes_completos": "1 - IDENTIFICAÇÃO E CONTACTOS DA ENTIDADE ADJUDICANTE\nDesignação da entidade adjudicante: Município de Armamar\nNIPC: 506843190\nServiço/Órgão/Pessoa de contacto: Divisão Municipal de Administração e Desenvolvimento Social\nEndereço: Praça da República\nCódigo postal: 5110-127\nLocalidade: Armamar\nPaís: Portugal\nNUT III: PT11D\nDistrito: Viseu\nConcelho: Armamar\nFreguesia: Todas\nTelefone: 254850800\nEndereço da Entidade (URL): https://www.cm-armamar.pt/\nEndereço Eletrónico: geral@cm-armamar.pt\neDelivery Gateway (URL): https://www.acingov.pt\nFunção da Organização: Adquirente\nNorma jurídica da Entidade Adjudicante: Organismo de direito público\nÁrea de atividade da Autoridade Adjudicante: Serviços públicos das administrações públicas\n\n2 - JORNAL OFICIAL DA UNIÃO EUROPEIA\nO procedimento a que este anúncio diz respeito também é publicitado no Jornal Oficial da União Europeia? Não\n\n3 - AVISO\nModelo de Anúncio: Concurso público\nData de Envio do Anúncio: 01-08-2025\n\n5 - PROCESSO\nTipo de Procedimento: Concurso público\nPreço base do procedimento: Sim\nValor do preço base do procedimento: 95.000,00 EUR\nProcedimento com lotes? Sim\nNº Máx. de Lotes Autorizado: 3\nNúmero máximo de lotes que podem ser adjudicados a um concorrente: 3\n\n6 - OBJETO DO CONTRATO\nNúmero de referência interna: 65MUNAMM25\nDesignação do contrato: Produção da XVIII Feria da Maçã\nDescrição: Produção da XVIII Feria da Maçã\nTipo de Contrato Principal: Aquisição de Serviços\nTipo de Contrato: Aquisição de Serviços\nClassificação CPV (Vocabulário Comum para os Contratos Públicos)\nObjeto principal\nVocabulário Principal: 79952000\nPreço base s/IVA: 95.000,00 EUR\nLotes: \nNº: LOT-0001\nDescrição do Lote: Locação de equipamentos e estruturas\nPreço base s/IVA: 45.000,00 EUR\nClassificação CPV (Vocabulário Comum para os Contratos Públicos)\nObjeto principal\nVocabulário Principal: 79952000\nNº: LOT-0002\nDescrição do Lote: Contratação de artistas, produção musical e animação\nPreço base s/IVA: 40.000,00 EUR\nClassificação CPV (Vocabulário Comum para os Contratos Públicos)\nObjeto principal\nVocabulário Principal: 79952000\nNº: LOT-0003\nDescrição do Lote: Comunicação/publicidade\nPreço base s/IVA: 10.000,00 EUR\nClassificação CPV (Vocabulário Comum para os Contratos Públicos)\nObjeto principal\nVocabulário Principal: 79952000\n\n7 - INDICAÇÕES ADICIONAIS\nO contrato envolve aquisição conjunta (satisfação de várias entidades)? Não\nO contrato é adjudicado por uma central de compras? Não\n\n8 - TÉCNICAS\nO concurso destina-se à celebração de um acordo-quadro? Inexistência de acordo-quadro\nÉ utilizado um leilão eletrónico? Não\nÉ adotada uma fase de negociação? Não\nSistema de Aquisição Dinâmico: Inexistência de sistema de aquisição dinâmico\n\n9 - LOCAL DA EXECUÇÃO DO CONTRATO\nLOCAL DA EXECUÇÃO DO CONTRATO (PROCEDIMENTO)\nPaís: Portugal\nNUT III: PT11D\nLocalidade: Freguesia de Armamar\nDistrito: Viseu\nConcelho: Armamar\nFreguesia: Freguesia de Armamar\nLOCAL DA EXECUÇÃO DO CONTRATO (LOTE)\nIdentificador do Lote: LOT-0001; LOT-0002; LOT-0003\nPaís: Portugal\nNUT III: PT11D\nLocalidade: Freguesia de Armamar\nDistrito: Viseu\nConcelho: Armamar\nFreguesia: Freguesia de Armamar\n\n10 - PRAZO DE EXECUÇÃO DO CONTRATO\nIdentificador do Lote: LOT-0001; LOT-0002; LOT-0003\nData de Início: 10-10-2025\nData de Fim: 24-10-2025\nPrevisão de renovações: Não\n\n11 - FUNDOS EU\nIdentificador do Lote: LOT-0001; LOT-0002; LOT-0003\nTêm fundos EU? Não\n\n12 - DOCUMENTOS DE HABILITAÇÃO\nHabilitação para o exercício da atividade profissional: Não\n\n13 - CONDIÇÕES DE APRESENTAÇÃO\nPlataforma eletrónica utilizada pela entidade adjudicante: ACIN\nURL para Apresentação: https://www.acingov.pt\nAdmissibilidade da apresentação de propostas variantes: Não autorizado\nPrazo para apresentação das propostas: 19-08-2025 23:59\nPrazo durante o qual os concorrentes são obrigados a manter as respetivas propostas: 66 dias a contar do termo do prazo para a apresentação das propostas\nIndicação de Subcontratação na Proposta: Inexistência de indicação de subcontratação\n\n14 - PRESTAÇÃO DE CAUÇÃO\nPrestação de caução: Não\n\n15 - FORNECIMENTO DAS PEÇAS DO CONCURSO, APRESENTAÇÃO DE PEDIDOS DE PARTICIPAÇÃO E APRESENTAÇÃO DAS PROPOSTAS\nLink para acesso às peças do concurso (URL): https://www.acingov.pt/acingovprod/2/zonaPublica/zona_publica_c/donwloadProcedurePiece/OTMwNTEx\n\n20 - OUTROS REQUISITOS\nIdentificador do Lote: LOT-0001; LOT-0002; LOT-0003\nInformação sobre contratos reservados. Aplica-se a contratos reservados (54º-A)? Não\n\n21 - CRITÉRIO DE ADJUDICAÇÃO\nO Critério de adjudicação é diferenciado por lote? Não\nMultifator: Não\nMonofator:\nNome: Preço\n\n24 - CONDIÇÕES DO CONTRATO\nIdentificador do Lote: LOT-0001; LOT-0002; LOT-0003\nFaturação Eletrónica: Permitido\nObrigação de Subcontratação:\nCódigo da Obrigação de Subcontratação: Não é aplicável nenhuma obrigação de subcontratação.\n\n25 - COMPRA PÚBLICA ESTRATÉGICA\nCompra Pública Estratégica: Inexistência de contratação pública estratégica\n\n26 - INFORMAÇÕES ADICIONAIS\nIdentificador do Lote: LOT-0001; LOT-0002; LOT-0003\nContrato adequado para PME: Não\nCobertura ACP (Acordo dos Contratos Públicos da Organização Mundial do Comércio): Não\n\n27 - IDENTIFICAÇÃO E CONTACTOS DO ÓRGÃO DE RECURSOS ADMINISTRATIVOS\nDesignação: Câmara Municipal de Armamar\nEndereço: Praça da República\nCódigo postal: 5110-127\nLocalidade: Armamar\nTelefone: 254850800\nFax: 000000000\nEndereço eletrónico: geral@cm-armamar.pt\nPrazo de interposição do recurso: 5 dias\n\n28 - IDENTIFICAÇÃO DO(S) AUTOR(ES) DE ANÚNCIO\nNome: António José da Silva Fernandes\nCargo: Chefe de Divisão\n419386058",
    "nipc": "506843190",
    "distrito": "Viseu",
    "concelho": "Armamar",
    "freguesia": "Todas",
    "site": "https://www.cm-armamar.pt/",
    "email": "geral@cm-armamar.pt",
    "designacao_contrato": "Produção da XVIII Feria da Maçã",
    "descricao": "Produção da XVIII Feria da Maçã",
    "preco_base": "95.000,00 EUR",
    "prazo_execucao": null,
    "prazo_apresentacao_propostas": "19-08-2025 23:59",
    "fundos_eu": "Não",
    "plataforma_eletronica": "ACIN",
    "url_procedimento": "https://www.acingov.pt",
    "autor_nome": "António José da Silva Fernandes",
    "autor_cargo": "Chefe de Divisão"
  },
  {
    "numero_procedimento": "N/A",
    "entidade": "AnÃºncio de procedimento  n.Âº 20780/2025  -  DiÃ¡rio da RepÃºblica n.Âº 147/2025, SÃ©rie II de 2025-08-01",
    "link": "https://diariodarepublica.pt/dr/detalhe/contrato-publico/20780-927638164"
  },
  {
    "numero_procedimento": "N/A",
    "entidade": "AnÃºncio de procedimento  n.Âº 20781/2025  -  DiÃ¡rio da RepÃºblica n.Âº 147/2025, SÃ©rie II de 2025-08-01",
    "link": "https://diariodarepublica.pt/dr/detalhe/contrato-publico/20781-927638165"
  },
  {
    "numero_procedimento": "N/A",
    "entidade": "AnÃºncio de procedimento  n.Âº 20786/2025  -  DiÃ¡rio da RepÃºblica n.Âº 147/2025, SÃ©rie II de 2025-08-01",
    "link": "https://diariodarepublica.pt/dr/detalhe/contrato-publico/20786-927638166"
  },
  {
    "numero_procedimento": "N/A",
    "entidade": "AnÃºncio de procedimento  n.Âº 20793/2025  -  DiÃ¡rio da RepÃºblica n.Âº 147/2025, SÃ©rie II de 2025-08-01",
    "link": "https://diariodarepublica.pt/dr/detalhe/contrato-publico/20793-927638167"
  },
  {
    "numero_procedimento": "N/A",
    "entidade": "AnÃºncio de procedimento  n.Âº 20794/2025  -  DiÃ¡rio da RepÃºblica n.Âº 147/2025, SÃ©rie II de 2025-08-01",
    "link": "https://diariodarepublica.pt/dr/detalhe/contrato-publico/20794-927638168"
  },
  {
    "numero_procedimento": "N/A",
    "entidade": "AnÃºncio de procedimento  n.Âº 20797/2025  -  DiÃ¡rio da RepÃºblica n.Âº 147/2025, SÃ©rie II de 2025-08-01",
    "link": "https://diariodarepublica.pt/dr/detalhe/contrato-publico/20797-927638169"
  },
  {
    "numero_procedimento": "N/A",
    "entidade": "AnÃºncio de procedimento  n.Âº 20798/2025  -  DiÃ¡rio da RepÃºblica n.Âº 147/2025, SÃ©rie II de 2025-08-01",
    "link": "https://diariodarepublica.pt/dr/detalhe/contrato-publico/20798-927638170"
  },
  {
    "numero_procedimento": "N/A",
    "entidade": "AnÃºncio de procedimento  n.Âº 20800/2025  -  DiÃ¡rio da RepÃºblica n.Âº 147/2025, SÃ©rie II de 2025-08-01",
    "link": "https://diariodarepublica.pt/dr/detalhe/contrato-publico/20800-927638171"
  },
  {
    "numero_procedimento": "N/A",
    "entidade": "AnÃºncio de procedimento  n.Âº 20782/2025  -  DiÃ¡rio da RepÃºblica n.Âº 147/2025, SÃ©rie II de 2025-08-01",
    "link": "https://diariodarepublica.pt/dr/detalhe/contrato-publico/20782-927679778"
  },
  {
    "numero_procedimento": "N/A",
    "entidade": "AnÃºncio de procedimento  n.Âº 20783/2025  -  DiÃ¡rio da RepÃºblica n.Âº 147/2025, SÃ©rie II de 2025-08-01",
    "link": "https://diariodarepublica.pt/dr/detalhe/contrato-publico/20783-927679779"
  },
  {
    "numero_procedimento": "N/A",
    "entidade": "AnÃºncio de procedimento  n.Âº 20784/2025  -  DiÃ¡rio da RepÃºblica n.Âº 147/2025, SÃ©rie II de 2025-08-01",
    "link": "https://diariodarepublica.pt/dr/detalhe/contrato-publico/20784-927679780"
  },
  {
    "numero_procedimento": "N/A",
    "entidade": "AnÃºncio de procedimento  n.Âº 20785/2025  -  DiÃ¡rio da RepÃºblica n.Âº 147/2025, SÃ©rie II de 2025-08-01",
    "link": "https://diariodarepublica.pt/dr/detalhe/contrato-publico/20785-927679781"
  },
  {
    "numero_procedimento": "N/A",
    "entidade": "AnÃºncio de procedimento  n.Âº 20787/2025  -  DiÃ¡rio da RepÃºblica n.Âº 147/2025, SÃ©rie II de 2025-08-01",
    "link": "https://diariodarepublica.pt/dr/detalhe/contrato-publico/20787-927679782"
  },
  {
    "numero_procedimento": "N/A",
    "entidade": "AnÃºncio de procedimento  n.Âº 20788/2025  -  DiÃ¡rio da RepÃºblica n.Âº 147/2025, SÃ©rie II de 2025-08-01",
    "link": "https://diariodarepublica.pt/dr/detalhe/contrato-publico/20788-927679783"
  },
  {
    "numero_procedimento": "N/A",
    "entidade": "Município de Odivelas",
    "link": "https://diariodarepublica.pt/dr/detalhe/contrato-publico/20789-927679784",
    "detalhes_completos": "1 - IDENTIFICAÇÃO E CONTACTOS DA ENTIDADE ADJUDICANTE\nDesignação da entidade adjudicante: Município de Odivelas\nNIPC: 504293125\nServiço/Órgão/Pessoa de contacto: DOMH/DPOE\nEndereço: R. Guilherme Gomes Fernandes, Paços do Concelho\nCódigo postal: 2675-372\nLocalidade: Lisboa\nPaís: Portugal\nNUT III: PT170\nDistrito: Lisboa\nConcelho: Odivelas\nFreguesia: Freguesia de Odivelas - Odivelas\nTelefone: 219320000\nFax: 219 320 000\nEndereço da Entidade (URL): https://www.cm-odivelas.pt/\nEndereço Eletrónico: geral@cm-odivelas.pt\neDelivery Gateway (URL): https://community.vortal.biz/public/\nFunção da Organização: Adquirente\nNorma jurídica da Entidade Adjudicante: Organismo de direito público\nÁrea de atividade da Autoridade Adjudicante: Serviços públicos das administrações públicas\n\n2 - JORNAL OFICIAL DA UNIÃO EUROPEIA\nO procedimento a que este anúncio diz respeito também é publicitado no Jornal Oficial da União Europeia? Não\n\n3 - AVISO\nModelo de Anúncio: Concurso público\nData de Envio do Anúncio: 01-08-2025\n\n5 - PROCESSO\nTipo de Procedimento: Concurso público\nPreço base do procedimento: Sim\nValor do preço base do procedimento: 349.679,00 EUR\nProcedimento com lotes? Não\n\n6 - OBJETO DO CONTRATO\nNúmero de referência interna: 3803/PO/FA-DOMH\nDesignação do contrato: Requalificação do Espaço Público no Bairro da Urmeira, na Pontinha\nDescrição: Requalificação do Espaço Público no Bairro da Urmeira, na Pontinha\nTipo de Contrato Principal: Empreitada de Obras Públicas\nTipo de Contrato: Empreitada de Obras Públicas\nClassificação CPV (Vocabulário Comum para os Contratos Públicos)\nObjeto principal\nVocabulário Principal: 45233160\nPreço base s/IVA: 349.679,00 EUR\n\n7 - INDICAÇÕES ADICIONAIS\nO contrato envolve aquisição conjunta (satisfação de várias entidades)? Não\nO contrato é adjudicado por uma central de compras? Não\n\n8 - TÉCNICAS\nO concurso destina-se à celebração de um acordo-quadro? Inexistência de acordo-quadro\nÉ utilizado um leilão eletrónico? Não\nÉ adotada uma fase de negociação? Não\nSistema de Aquisição Dinâmico: Inexistência de sistema de aquisição dinâmico\n\n9 - LOCAL DA EXECUÇÃO DO CONTRATO\nLOCAL DA EXECUÇÃO DO CONTRATO (PROCEDIMENTO)\nPaís: Portugal\nNUT III: PT170\nLocalidade: Lisboa\nDistrito: Lisboa\nConcelho: Odivelas\nFreguesia: União das Freguesias de Pontinha e Famões\n\n10 - PRAZO DE EXECUÇÃO DO CONTRATO\nPrazo de execução do contrato: 60 DIAS\nPrevisão de renovações: Não\n\n11 - FUNDOS EU\nTêm fundos EU? Não\n\n12 - DOCUMENTOS DE HABILITAÇÃO\nHabilitação para o exercício da atividade profissional: Sim\nTipo: Alvará\nDescrição: A 1ª e 8ª subcategoria da 2ª categoria para o valor global da proposta, a qual tem de ser de classe que cubra o valor global da proposta e integrar-se na categoria em que o tipo da obra se enquadra.\n\n13 - CONDIÇÕES DE APRESENTAÇÃO\nPlataforma eletrónica utilizada pela entidade adjudicante: VORTAL\nURL para Apresentação: https://community.vortal.biz/public/\nAdmissibilidade da apresentação de propostas variantes: Não autorizado\nPrazo para apresentação das propostas: 22-08-2025 23:59\nPrazo durante o qual os concorrentes são obrigados a manter as respetivas propostas: 120 dias a contar do termo do prazo para a apresentação das propostas\nIndicação de Subcontratação na Proposta: Inexistência de indicação de subcontratação\n\n14 - PRESTAÇÃO DE CAUÇÃO\nPrestação de caução: Sim\nPercentagem: 5%\nDescrição da Garantia Exigida: De acordo com o ponto 18 do Programa de Procedimento\n\n15 - FORNECIMENTO DAS PEÇAS DO CONCURSO, APRESENTAÇÃO DE PEDIDOS DE PARTICIPAÇÃO E APRESENTAÇÃO DAS PROPOSTAS\nLink para acesso às peças do concurso (URL): https://community.vortal.biz/Public/public-tender-documents/MjhJN2pvUXhvRUQ4R0VtQ0tZNlozU3RMQjFnSVc4b0ZIeFIwczI2MzZLOUtTVzZubGpyc3RrZFlaSXYxNllFU3FoZjA5YVR0SmtBcFBkMFQ1QzVyTlE9PVNsTFgw\n\n20 - OUTROS REQUISITOS\nInformação sobre contratos reservados. Aplica-se a contratos reservados (54º-A)? Não\n\n21 - CRITÉRIO DE ADJUDICAÇÃO\nMultifator: Não\nMonofator:\nNome: Preço\n\n24 - CONDIÇÕES DO CONTRATO\nFaturação Eletrónica: Permitido\nObrigação de Subcontratação:\nCódigo da Obrigação de Subcontratação: Não é aplicável nenhuma obrigação de subcontratação.\n\n25 - COMPRA PÚBLICA ESTRATÉGICA\nCompra Pública Estratégica: Inexistência de contratação pública estratégica\n\n26 - INFORMAÇÕES ADICIONAIS\nContrato adequado para PME: Sim\nCobertura ACP (Acordo dos Contratos Públicos da Organização Mundial do Comércio): Não\n\n27 - IDENTIFICAÇÃO E CONTACTOS DO ÓRGÃO DE RECURSOS ADMINISTRATIVOS\nDesignação: Câmara Municipal de Odivelas\nEndereço: Rua Guilherme Gomes Fernandes, Paços do Concelho\nCódigo postal: 2675-372\nLocalidade: Odivelas\nTelefone: +351 219320000\nFax: +351 219320000\nEndereço eletrónico: geral@cm-odivelas.pt\n\n28 - IDENTIFICAÇÃO DO(S) AUTOR(ES) DE ANÚNCIO\nNome: Dr. Hugo Martins\nCargo: Presidente da Câmara\n419372214",
    "nipc": "504293125",
    "distrito": "Lisboa",
    "concelho": "Odivelas",
    "freguesia": "Freguesia de Odivelas - Odivelas",
    "site": "https://www.cm-odivelas.pt/",
    "email": "geral@cm-odivelas.pt",
    "designacao_contrato": "Requalificação do Espaço Público no Bairro da Urmeira, na Pontinha",
    "descricao": "Requalificação do Espaço Público no Bairro da Urmeira, na Pontinha",
    "preco_base": "349.679,00 EUR",
    "prazo_execucao": "60 DIAS",
    "prazo_apresentacao_propostas": "22-08-2025 23:59",
    "fundos_eu": "Não",
    "plataforma_eletronica": "VORTAL",
    "url_procedimento": "https://community.vortal.biz/public/",
    "autor_nome": "Dr. Hugo Martins",
    "autor_cargo": "Presidente da Câmara"
  },
  {
    "numero_procedimento": "N/A",
    "entidade": "AnÃºncio de procedimento  n.Âº 20790/2025  -  DiÃ¡rio da RepÃºblica n.Âº 147/2025, SÃ©rie II de 2025-08-01",
    "link": "https://diariodarepublica.pt/dr/detalhe/contrato-publico/20790-927679785"
  },
  {
    "numero_procedimento": "N/A",
    "entidade": "AnÃºncio de procedimento  n.Âº 20791/2025  -  DiÃ¡rio da RepÃºblica n.Âº 147/2025, SÃ©rie II de 2025-08-01",
    "link": "https://diariodarepublica.pt/dr/detalhe/contrato-publico/20791-927679786"
  },
  {
    "numero_procedimento": "N/A",
    "entidade": "AnÃºncio de procedimento  n.Âº 20792/2025  -  DiÃ¡rio da RepÃºblica n.Âº 147/2025, SÃ©rie II de 2025-08-01",
    "link": "https://diariodarepublica.pt/dr/detalhe/contrato-publico/20792-927679787"
  },
  {
    "numero_procedimento": "N/A",
    "entidade": "AnÃºncio de procedimento  n.Âº 20795/2025  -  DiÃ¡rio da RepÃºblica n.Âº 147/2025, SÃ©rie II de 2025-08-01",
    "link": "https://diariodarepublica.pt/dr/detalhe/contrato-publico/20795-927679788"
  },
  {
    "numero_procedimento": "N/A",
    "entidade": "AnÃºncio de procedimento  n.Âº 20796/2025  -  DiÃ¡rio da RepÃºblica n.Âº 147/2025, SÃ©rie II de 2025-08-01",
    "link": "https://diariodarepublica.pt/dr/detalhe/contrato-publico/20796-927679789"
  },
  {
    "numero_procedimento": "N/A",
    "entidade": "AnÃºncio de procedimento  n.Âº 20799/2025  -  DiÃ¡rio da RepÃºblica n.Âº 147/2025, SÃ©rie II de 2025-08-01",
    "link": "https://diariodarepublica.pt/dr/detalhe/contrato-publico/20799-927679791"
  },
  {
    "numero_procedimento": "N/A",
    "entidade": "AnÃºncio de procedimento  n.Âº 20801/2025  -  DiÃ¡rio da RepÃºblica n.Âº 147/2025, SÃ©rie II de 2025-08-01",
    "link": "https://diariodarepublica.pt/dr/detalhe/contrato-publico/20801-927679796"
  },
  {
    "numero_procedimento": "N/A",
    "entidade": "AnÃºncio de procedimento  n.Âº 20802/2025  -  DiÃ¡rio da RepÃºblica n.Âº 147/2025, SÃ©rie II de 2025-08-01",
    "link": "https://diariodarepublica.pt/dr/detalhe/contrato-publico/20802-927679824"
  },
  {
    "numero_procedimento": "N/A",
    "entidade": "AnÃºncio de procedimento  n.Âº 20803/2025  -  DiÃ¡rio da RepÃºblica n.Âº 147/2025, SÃ©rie II de 2025-08-01",
    "link": "https://diariodarepublica.pt/dr/detalhe/contrato-publico/20803-927679825"
  },
  {
    "numero_procedimento": "N/A",
    "entidade": "AnÃºncio de procedimento  n.Âº 20805/2025  -  DiÃ¡rio da RepÃºblica n.Âº 147/2025, SÃ©rie II de 2025-08-01",
    "link": "https://diariodarepublica.pt/dr/detalhe/contrato-publico/20805-927679826"
  },
  {
    "numero_procedimento": "N/A",
    "entidade": "AnÃºncio de procedimento  n.Âº 20806/2025  -  DiÃ¡rio da RepÃºblica n.Âº 147/2025, SÃ©rie II de 2025-08-01",
    "link": "https://diariodarepublica.pt/dr/detalhe/contrato-publico/20806-927679827"
  },
  {
    "numero_procedimento": "N/A",
    "entidade": "AnÃºncio de procedimento  n.Âº 20807/2025  -  DiÃ¡rio da RepÃºblica n.Âº 147/2025, SÃ©rie II de 2025-08-01",
    "link": "https://diariodarepublica.pt/dr/detalhe/contrato-publico/20807-927679828"
  },
  {
    "numero_procedimento": "N/A",
    "entidade": "AnÃºncio de procedimento  n.Âº 20808/2025  -  DiÃ¡rio da RepÃºblica n.Âº 147/2025, SÃ©rie II de 2025-08-01",
    "link": "https://diariodarepublica.pt/dr/detalhe/contrato-publico/20808-927679829"
  },
  {
    "numero_procedimento": "N/A",
    "entidade": "AnÃºncio de procedimento  n.Âº 20809/2025  -  DiÃ¡rio da RepÃºblica n.Âº 147/2025, SÃ©rie II de 2025-08-01",
    "link": "https://diariodarepublica.pt/dr/detalhe/contrato-publico/20809-927679830"
  },
  {
    "numero_procedimento": "N/A",
    "entidade": "AnÃºncio de procedimento  n.Âº 20811/2025  -  DiÃ¡rio da RepÃºblica n.Âº 147/2025, SÃ©rie II de 2025-08-01",
    "link": "https://diariodarepublica.pt/dr/detalhe/contrato-publico/20811-927679831"
  },
  {
    "numero_procedimento": "N/A",
    "entidade": "AnÃºncio de procedimento  n.Âº 20804/2025  -  DiÃ¡rio da RepÃºblica n.Âº 147/2025, SÃ©rie II de 2025-08-01",
    "link": "https://diariodarepublica.pt/dr/detalhe/contrato-publico/20804-927680183"
  },
  {
    "numero_procedimento": "N/A",
    "entidade": "AnÃºncio de procedimento  n.Âº 20810/2025  -  DiÃ¡rio da RepÃºblica n.Âº 147/2025, SÃ©rie II de 2025-08-01",
    "link": "https://diariodarepublica.pt/dr/detalhe/contrato-publico/20810-927680184"
  },
  {
    "numero_procedimento": "N/A",
    "entidade": "AnÃºncio de procedimento  n.Âº 20812/2025  -  DiÃ¡rio da RepÃºblica n.Âº 147/2025, SÃ©rie II de 2025-08-01",
    "link": "https://diariodarepublica.pt/dr/detalhe/contrato-publico/20812-927680185"
  },
  {
    "numero_procedimento": "N/A",
    "entidade": "AnÃºncio de procedimento  n.Âº 20813/2025  -  DiÃ¡rio da RepÃºblica n.Âº 147/2025, SÃ©rie II de 2025-08-01",
    "link": "https://diariodarepublica.pt/dr/detalhe/contrato-publico/20813-927680186"
  },
  {
    "numero_procedimento": "N/A",
    "entidade": "AnÃºncio de procedimento  n.Âº 20814/2025  -  DiÃ¡rio da RepÃºblica n.Âº 147/2025, SÃ©rie II de 2025-08-01",
    "link": "https://diariodarepublica.pt/dr/detalhe/contrato-publico/20814-927680187"
  },
  {
    "numero_procedimento": "N/A",
    "entidade": "AnÃºncio de procedimento  n.Âº 20818/2025  -  DiÃ¡rio da RepÃºblica n.Âº 147/2025, SÃ©rie II de 2025-08-01",
    "link": "https://diariodarepublica.pt/dr/detalhe/contrato-publico/20818-927680192"
  },
  {
    "numero_procedimento": "N/A",
    "entidade": "AnÃºncio de procedimento  n.Âº 20820/2025  -  DiÃ¡rio da RepÃºblica n.Âº 147/2025, SÃ©rie II de 2025-08-01",
    "link": "https://diariodarepublica.pt/dr/detalhe/contrato-publico/20820-927680193"
  },
  {
    "numero_procedimento": "N/A",
    "entidade": "AnÃºncio de procedimento  n.Âº 20815/2025  -  DiÃ¡rio da RepÃºblica n.Âº 147/2025, SÃ©rie II de 2025-08-01",
    "link": "https://diariodarepublica.pt/dr/detalhe/contrato-publico/20815-927681115"
  },
  {
    "numero_procedimento": "N/A",
    "entidade": "AnÃºncio de procedimento  n.Âº 20816/2025  -  DiÃ¡rio da RepÃºblica n.Âº 147/2025, SÃ©rie II de 2025-08-01",
    "link": "https://diariodarepublica.pt/dr/detalhe/contrato-publico/20816-927681116"
  },
  {
    "numero_procedimento": "N/A",
    "entidade": "AnÃºncio de procedimento  n.Âº 20817/2025  -  DiÃ¡rio da RepÃºblica n.Âº 147/2025, SÃ©rie II de 2025-08-01",
    "link": "https://diariodarepublica.pt/dr/detalhe/contrato-publico/20817-927681117"
  },
  {
    "numero_procedimento": "N/A",
    "entidade": "AnÃºncio de procedimento  n.Âº 20819/2025  -  DiÃ¡rio da RepÃºblica n.Âº 147/2025, SÃ©rie II de 2025-08-01",
    "link": "https://diariodarepublica.pt/dr/detalhe/contrato-publico/20819-927681118"
  }
]