[
  {
    "numero_procedimento": "N/A",
    "entidade": "Unidade Local de Saúde de Lisboa Ocidental, E. P. E.",
    "link": "https://diariodarepublica.pt/dr/detalhe/contrato-publico/23250-933788344",
    "detalhes_completos": "Alteração do Anúncio de procedimento n.º 22254/2025, de 2025-08-20, com o ID 419442611\n\n1 - IDENTIFICAÇÃO E CONTACTOS DA ENTIDADE ADJUDICANTE\nDesignação da entidade adjudicante: Unidade Local de Saúde de Lisboa Ocidental, E. P. E.\nNIPC: 507618319\nEndereço: Santa Maria de Belém  Estrada do Forte do Alto do Duque\nCódigo postal: 1449-005\nLocalidade: Lisboa\nPaís: Portugal\nNUT III: PT170\nDistrito: Lisboa\nConcelho: Lisboa\nFreguesia: Todas\nTelefone: 210431000\nFax: 210431642\nEndereço da Entidade (URL): www.chlo.min-saude.pt/\nEndereço Eletrónico: comprasgeral@ulslo.min-saude.pt\neDelivery Gateway (URL): https://community.vortal.biz/public/\nFunção da Organização: Adquirente\nNorma jurídica da Entidade Adjudicante: Organismo de direito público\nÁrea de atividade da Autoridade Adjudicante: Saúde\n\n2 - JORNAL OFICIAL DA UNIÃO EUROPEIA\nO procedimento a que este anúncio diz respeito também é publicitado no Jornal Oficial da União Europeia? Não\n\n3 - AVISO\nModelo de Anúncio: Concurso público\nData de Envio do Anúncio: 01-09-2025\n\n5 - PROCESSO\nTipo de Procedimento: Concurso público\nPreço base do procedimento: Sim\nValor do preço base do procedimento: 82.835,92 EUR\nProcedimento com lotes? Não\n\n6 - OBJETO DO CONTRATO\nNúmero de referência interna: 148003425\nDesignação do contrato: 148003425_Aquisição, Instalação e Colocação  em Serviço de Cadeiras de Dentistas, Kits de Material e Kits de Turbinas no novo Edifício do Centro de Saúde de Cascais\nDescrição: 148003425 para Aquisição, Instalação e Colocação  em Serviço de Cadeiras de Dentistas, Kits de Material e Kits de Turbinas no novo Edifício do Centro de Saúde de Cascais, da Unidade Local de Saúde de Lisboa Ocidental, EPE, no âmbito do Plano de Recuperação e Resiliência, da Reforma RE-R01: Reforma dos Cuidados de Saúde Primários, do Investimento RE-C01-I01: Cuidado de Saúde Primários e no cumprimento da Meta I1.09 Modernizar Equipamentos\nTipo de Contrato Principal: Aquisição de Bens Móveis\nTipo de Contrato: Aquisição de Bens Móveis\nClassificação CPV (Vocabulário Comum para os Contratos Públicos)\nObjeto principal\nVocabulário Principal: 33100000\nPreço base s/IVA: 82.835,92 EUR\n\n7 - INDICAÇÕES ADICIONAIS\nO contrato envolve aquisição conjunta (satisfação de várias entidades)? Não\nO contrato é adjudicado por uma central de compras? Não\n\n8 - TÉCNICAS\nO concurso destina-se à celebração de um acordo-quadro? Inexistência de acordo-quadro\nÉ utilizado um leilão eletrónico? Não\nÉ adotada uma fase de negociação? Não\nSistema de Aquisição Dinâmico: Inexistência de sistema de aquisição dinâmico\n\n9 - LOCAL DA EXECUÇÃO DO CONTRATO\nLOCAL DA EXECUÇÃO DO CONTRATO (PROCEDIMENTO)\nPaís: Portugal\nNUT III: PT170\nLocalidade: Lisboa\nDistrito: Lisboa\nConcelho: Lisboa\nFreguesia: Todas\n\n10 - PRAZO DE EXECUÇÃO DO CONTRATO\nPrazo de execução do contrato: 30 DIAS\nPrevisão de renovações: Não\n\n11 - FUNDOS EU\nTêm fundos EU? Não\n\n12 - DOCUMENTOS DE HABILITAÇÃO\nHabilitação para o exercício da atividade profissional: Não\n\n13 - CONDIÇÕES DE APRESENTAÇÃO\nPlataforma eletrónica utilizada pela entidade adjudicante: VORTAL\nURL para Apresentação: https://community.vortal.biz/public/\nAdmissibilidade da apresentação de propostas variantes: Não autorizado\nPrazo para apresentação das propostas: 01-09-2025 17:00\nPrazo durante o qual os concorrentes são obrigados a manter as respetivas propostas: 66 dias a contar do termo do prazo para a apresentação das propostas\nApresentação de Catálogo Eletrónico: Permitido\nIndicação de Subcontratação na Proposta: Inexistência de indicação de subcontratação\n\n14 - PRESTAÇÃO DE CAUÇÃO\nPrestação de caução: Não\n\n15 - FORNECIMENTO DAS PEÇAS DO CONCURSO, APRESENTAÇÃO DE PEDIDOS DE PARTICIPAÇÃO E APRESENTAÇÃO DAS PROPOSTAS\nLink para acesso às peças do concurso (URL): https://community.vortal.biz/Public/public-tender-documents/Z0hiWUZrZjVGM3lOZ1crOWZFRld5d0ZyOTJTSSswdWZtbU5kdzJDeXEyRVN3Z3N4NEF5ZDRXc1o3OWFGMXRsUmhtRlFaekQrbWNxUFAwVVZqWnl1eFE9PUF0a19f\n\n20 - OUTROS REQUISITOS\nInformação sobre contratos reservados. Aplica-se a contratos reservados (54º-A)? Não\n\n21 - CRITÉRIO DE ADJUDICAÇÃO\nMultifator: Não\nMonofator:\nNome: Preço\n\n24 - CONDIÇÕES DO CONTRATO\nFaturação Eletrónica: Permitido\nObrigação de Subcontratação:\nCódigo da Obrigação de Subcontratação: Não é aplicável nenhuma obrigação de subcontratação.\n\n25 - COMPRA PÚBLICA ESTRATÉGICA\nCompra Pública Estratégica: Inexistência de contratação pública estratégica\n\n26 - INFORMAÇÕES ADICIONAIS\nContrato adequado para PME: Sim\nCobertura ACP (Acordo dos Contratos Públicos da Organização Mundial do Comércio): Não\n\n27 - IDENTIFICAÇÃO E CONTACTOS DO ÓRGÃO DE RECURSOS ADMINISTRATIVOS\nDesignação: Conselho de Administração\nEndereço: Estrada do Forte do Alto do Duque\nCódigo postal: 1449-005\nLocalidade: Lisboa\nTelefone: +351 210431000\nFax: +351 210431639\nEndereço eletrónico: compras.adm.hot.ps.inv@ulslo.min-saude.pt\n\n28 - IDENTIFICAÇÃO DO(S) AUTOR(ES) DE ANÚNCIO\nNome: Ana Santos\nCargo: Assistente Técnica\n\n29 - ALTERAÇÃO\nMotivo da Alteração: Informações atualizadas\nIdentificador da Versão do Anúncio a Alterar: 6e4ba875-e55a-4618-9b53-3901f0249ece-01\nIdentificador das Secções Alteradas do Anúncio Anterior: Alteração\nDescrição das Alterações: Retificações às peças\nAlteração dos Documentos do Concurso: Sim\nData de alteração dos documentos do concurso: 01-09-2025\n419484595",
    "nipc": "507618319",
    "distrito": "Lisboa",
    "concelho": "Lisboa",
    "freguesia": "Todas",
    "site": "www.chlo.min-saude.pt/",
    "email": "comprasgeral@ulslo.min-saude.pt",
    "designacao_contrato": "148003425_Aquisição, Instalação e Colocação em Serviço de Cadeiras de Dentistas, Kits de Material e Kits de Turbinas no novo Edifício do Centro de Saúde de Cascais",
    "descricao": "148003425 para Aquisição, Instalação e Colocação em Serviço de Cadeiras de Dentistas, Kits de Material e Kits de Turbinas no novo Edifício do Centro de Saúde de Cascais, da Unidade Local de Saúde de Lisboa Ocidental, EPE, no âmbito do Plano de Recuperação e Resiliência, da Reforma RE-R01: Reforma dos Cuidados de Saúde Primários, do Investimento RE-C01-I01: Cuidado de Saúde Primários e no cumprimento da Meta I1.09 Modernizar Equipamentos",
    "preco_base": "82.835,92 EUR",
    "prazo_execucao": "30 DIAS",
    "prazo_apresentacao_propostas": "01-09-2025 17:00",
    "fundos_eu": "Não",
    "plataforma_eletronica": "VORTAL",
    "url_procedimento": "https://community.vortal.biz/public/",
    "autor_nome": "Ana Santos",
    "autor_cargo": "Assistente Técnica"
  },
  {
    "numero_procedimento": "N/A",
    "entidade": "Município de Proença-a-Nova",
    "link": "https://diariodarepublica.pt/dr/detalhe/contrato-publico/23252-933788345",
    "detalhes_completos": "1 - IDENTIFICAÇÃO E CONTACTOS DA ENTIDADE ADJUDICANTE\nDesignação da entidade adjudicante: Município de Proença-a-Nova\nNIPC: 505377802\nServiço/Órgão/Pessoa de contacto: Município de Proença-a-Nova\nEndereço: Avenida do Colégio, S/N\nCódigo postal: 6150-401\nLocalidade: Proença-a-Nova\nPaís: Portugal\nNUT III: PT16H\nDistrito: Castelo Branco\nConcelho: Proença-a-Nova\nFreguesia: União das Freguesias de Proença-a-Nova e Peral\nTelefone: 274670000\nFax: 274672697\nEndereço da Entidade (URL): www.cm-proencanova.pt\nEndereço Eletrónico: geral@cm-proencanova.pt\neDelivery Gateway (URL): https://www.acingov.pt\nFunção da Organização: Adquirente\nNorma jurídica da Entidade Adjudicante: Organismo de direito público\nÁrea de atividade da Autoridade Adjudicante: Serviços públicos das administrações públicas\n\n2 - JORNAL OFICIAL DA UNIÃO EUROPEIA\nO procedimento a que este anúncio diz respeito também é publicitado no Jornal Oficial da União Europeia? Não\n\n3 - AVISO\nModelo de Anúncio: Concurso público\nData de Envio do Anúncio: 01-09-2025\n\n5 - PROCESSO\nTipo de Procedimento: Concurso público\nPreço base do procedimento: Sim\nValor do preço base do procedimento: 31.501,46 EUR\nProcedimento com lotes? Não\n\n6 - OBJETO DO CONTRATO\nNúmero de referência interna: 67/PS/2025 - 2025/300.10.005/2087\nDesignação do contrato: Requalificação da Via Ferrata e Setores de Escalada, danificados pelo incêndio de agosto de 2023\nDescrição: Requalificação da Via Ferrata e Setores de Escalada, danificados pelo incêndio de agosto de 2023\nTipo de Contrato Principal: Aquisição de Serviços\nTipo de Contrato: Aquisição de Serviços\nClassificação CPV (Vocabulário Comum para os Contratos Públicos)\nObjeto principal\nVocabulário Principal: 92620000\nPreço base s/IVA: 31.501,46 EUR\n\n7 - INDICAÇÕES ADICIONAIS\nO contrato envolve aquisição conjunta (satisfação de várias entidades)? Não\nO contrato é adjudicado por uma central de compras? Não\n\n8 - TÉCNICAS\nO concurso destina-se à celebração de um acordo-quadro? Inexistência de acordo-quadro\nÉ utilizado um leilão eletrónico? Não\nÉ adotada uma fase de negociação? Não\nSistema de Aquisição Dinâmico: Inexistência de sistema de aquisição dinâmico\n\n9 - LOCAL DA EXECUÇÃO DO CONTRATO\nLOCAL DA EXECUÇÃO DO CONTRATO (PROCEDIMENTO)\nPaís: Portugal\nNUT III: PT16H\nLocalidade: Serra das Talhadas\nDistrito: Castelo Branco\nConcelho: Proença-a-Nova\nFreguesia: Freguesia de Montes da Senhora\n\n10 - PRAZO DE EXECUÇÃO DO CONTRATO\nPrazo de execução do contrato: 90 DIAS\nPrevisão de renovações: Não\n\n11 - FUNDOS EU\nTêm fundos EU? Sim\n\n12 - DOCUMENTOS DE HABILITAÇÃO\nHabilitação para o exercício da atividade profissional: Sim\nTipo: Certificado\nDescrição: Atendendo ao objeto do contrato o Prestador de Serviços deverá dispor de pessoal  técnico com formação (Nivel 3) em instalação/certificação de ancoragens, emitido pela IRATA - Industrial Rope Access Trade Association ou equivalente\n\n13 - CONDIÇÕES DE APRESENTAÇÃO\nPlataforma eletrónica utilizada pela entidade adjudicante: ACIN\nURL para Apresentação: https://www.acingov.pt\nAdmissibilidade da apresentação de propostas variantes: Não autorizado\nPrazo para apresentação das propostas: 10-09-2025 23:59\nPrazo durante o qual os concorrentes são obrigados a manter as respetivas propostas: 66 dias a contar do termo do prazo para a apresentação das propostas\nIndicação de Subcontratação na Proposta: Inexistência de indicação de subcontratação\n\n14 - PRESTAÇÃO DE CAUÇÃO\nPrestação de caução: Não\n\n15 - FORNECIMENTO DAS PEÇAS DO CONCURSO, APRESENTAÇÃO DE PEDIDOS DE PARTICIPAÇÃO E APRESENTAÇÃO DAS PROPOSTAS\nLink para acesso às peças do concurso (URL): https://www.acingov.pt/acingovprod/2/zonaPublica/zona_publica_c/donwloadProcedurePiece/OTcyMzc4\n\n20 - OUTROS REQUISITOS\nInformação sobre contratos reservados. Aplica-se a contratos reservados (54º-A)? Não\n\n21 - CRITÉRIO DE ADJUDICAÇÃO\nMultifator: Não\nMonofator:\nNome: Preço\n\n24 - CONDIÇÕES DO CONTRATO\nFaturação Eletrónica: Necessário\nObrigação de Subcontratação:\nCódigo da Obrigação de Subcontratação: Não é aplicável nenhuma obrigação de subcontratação.\n\n25 - COMPRA PÚBLICA ESTRATÉGICA\nCompra Pública Estratégica: Inexistência de contratação pública estratégica\n\n26 - INFORMAÇÕES ADICIONAIS\nContrato adequado para PME: Sim\nCobertura ACP (Acordo dos Contratos Públicos da Organização Mundial do Comércio): Não\n\n27 - IDENTIFICAÇÃO E CONTACTOS DO ÓRGÃO DE RECURSOS ADMINISTRATIVOS\nDesignação: Câmara Municipal de Proença-a-Nova\nEndereço: Avenida do Colégio, S/\nCódigo postal: 6150-401\nLocalidade: Proença-a-Nova\nTelefone: 274670000\nFax: \nEndereço eletrónico: geral@cm-proencanova.pt\nPrazo de interposição do recurso: 5 dias\n\n28 - IDENTIFICAÇÃO DO(S) AUTOR(ES) DE ANÚNCIO\nNome: João Manuel Ventura Grilo de MeloLobo\nCargo: Presidente da Câmara\n419484684",
    "nipc": "505377802",
    "distrito": "Castelo Branco",
    "concelho": "Proença-a-Nova",
    "freguesia": "União das Freguesias de Proença-a-Nova e Peral",
    "site": "www.cm-proencanova.pt",
    "email": "geral@cm-proencanova.pt",
    "designacao_contrato": "Requalificação da Via Ferrata e Setores de Escalada, danificados pelo incêndio de agosto de 2023",
    "descricao": "Requalificação da Via Ferrata e Setores de Escalada, danificados pelo incêndio de agosto de 2023",
    "preco_base": "31.501,46 EUR",
    "prazo_execucao": "90 DIAS",
    "prazo_apresentacao_propostas": "10-09-2025 23:59",
    "fundos_eu": "Sim",
    "plataforma_eletronica": "ACIN",
    "url_procedimento": "https://www.acingov.pt",
    "autor_nome": "João Manuel Ventura Grilo de MeloLobo",
    "autor_cargo": "Presidente da Câmara"
  },
  {
    "numero_procedimento": "N/A",
    "entidade": "Unidade Local de Saúde de Gaia/Espinho, E. P. E.",
    "link": "https://diariodarepublica.pt/dr/detalhe/contrato-publico/23254-933788346",
    "detalhes_completos": "1 - IDENTIFICAÇÃO E CONTACTOS DA ENTIDADE ADJUDICANTE\nDesignação da entidade adjudicante: Unidade Local de Saúde de Gaia/Espinho, E. P. E.\nNIPC: 508142156\nEndereço: R Conceição Fernandes , Vila Nova Gaia\nCódigo postal: 4434-502\nLocalidade: Área Metropolitana do Porto\nPaís: Portugal\nNUT III: PT11A\nDistrito: Porto\nConcelho: Vila Nova de Gaia\nFreguesia: Freguesia de Vilar de Andorinho\nTelefone: 227865100\nFax: 227830209\nEndereço da Entidade (URL): www.chvng.min-saude.pt\nEndereço Eletrónico: info@chvng.min-saude.pt\neDelivery Gateway (URL): https://community.vortal.biz/public/\nFunção da Organização: Adquirente\nNorma jurídica da Entidade Adjudicante: Organismo de direito público\nÁrea de atividade da Autoridade Adjudicante: Saúde\n\n2 - JORNAL OFICIAL DA UNIÃO EUROPEIA\nO procedimento a que este anúncio diz respeito também é publicitado no Jornal Oficial da União Europeia? Não\n\n3 - AVISO\nModelo de Anúncio: Concurso público\nData de Envio do Anúncio: 01-09-2025\n\n5 - PROCESSO\nTipo de Procedimento: Concurso público\nPreço base do procedimento: Sim\nValor do preço base do procedimento: 210.000,00 EUR\nProcedimento com lotes? Não\n\n6 - OBJETO DO CONTRATO\nNúmero de referência interna: 8656725\nDesignação do contrato: Aquisição de Serviços para a Construção de um Modelo Dinâmico de Distribuição da Capacidade Instalada no Bloco Operatório e Consulta Externa\nDescrição: Aquisição de Serviços para a Construção de um Modelo Dinâmico de Distribuição da Capacidade Instalada no Bloco Operatório e Consulta Externa\nTipo de Contrato Principal: Aquisição de Serviços\nTipo de Contrato: Aquisição de Serviços\nClassificação CPV (Vocabulário Comum para os Contratos Públicos)\nObjeto principal\nVocabulário Principal: 79420000\nPreço base s/IVA: 210.000,00 EUR\n\n7 - INDICAÇÕES ADICIONAIS\nO contrato envolve aquisição conjunta (satisfação de várias entidades)? Não\nO contrato é adjudicado por uma central de compras? Não\n\n8 - TÉCNICAS\nO concurso destina-se à celebração de um acordo-quadro? Inexistência de acordo-quadro\nÉ utilizado um leilão eletrónico? Não\nÉ adotada uma fase de negociação? Não\nSistema de Aquisição Dinâmico: Inexistência de sistema de aquisição dinâmico\n\n9 - LOCAL DA EXECUÇÃO DO CONTRATO\nLOCAL DA EXECUÇÃO DO CONTRATO (PROCEDIMENTO)\nPaís: Portugal\nNUT III: PT11A\nLocalidade: Área Metropolitana do Porto\nDistrito: Porto\nConcelho: Vila Nova de Gaia\nFreguesia: Freguesia de Vilar de Andorinho\n\n10 - PRAZO DE EXECUÇÃO DO CONTRATO\nPrazo de execução do contrato: 90 DIAS\nPrevisão de renovações: Não\n\n11 - FUNDOS EU\nTêm fundos EU? Não\n\n12 - DOCUMENTOS DE HABILITAÇÃO\nHabilitação para o exercício da atividade profissional: Não\n\n13 - CONDIÇÕES DE APRESENTAÇÃO\nPlataforma eletrónica utilizada pela entidade adjudicante: VORTAL\nURL para Apresentação: https://community.vortal.biz/public/\nAdmissibilidade da apresentação de propostas variantes: Não autorizado\nPrazo para apresentação das propostas: 15-09-2025 18:00\nPrazo durante o qual os concorrentes são obrigados a manter as respetivas propostas: 66 dias a contar do termo do prazo para a apresentação das propostas\nIndicação de Subcontratação na Proposta: Inexistência de indicação de subcontratação\n\n14 - PRESTAÇÃO DE CAUÇÃO\nPrestação de caução: Não\n\n15 - FORNECIMENTO DAS PEÇAS DO CONCURSO, APRESENTAÇÃO DE PEDIDOS DE PARTICIPAÇÃO E APRESENTAÇÃO DAS PROPOSTAS\nLink para acesso às peças do concurso (URL): https://community.vortal.biz/Public/public-tender-documents/Y1B4WituM2ZFMTkwc2RDUnhiNms0K0VOKzlvb2dNcFdLVmV3aXlobnZPdE82cGRiTU1YcnM1T2ViUHpoY1FkY3dRdExpci84MUtraCt6MGtjV2Ewb2c9PXV0OXcp\n\n20 - OUTROS REQUISITOS\nInformação sobre contratos reservados. Aplica-se a contratos reservados (54º-A)? Não\n\n21 - CRITÉRIO DE ADJUDICAÇÃO\nMultifator: Sim\nFator: \nNome: Preço\nPonderação: 35%\nSubfatores: Não\nFator: \nNome: Qualidade\nPonderação: 32.5%\nSubfatores: Não\nFator: \nNome: Qualidade\nPonderação: 32.5%\nSubfatores: Não\n\n24 - CONDIÇÕES DO CONTRATO\nFaturação Eletrónica: Permitido\nObrigação de Subcontratação:\nCódigo da Obrigação de Subcontratação: Não é aplicável nenhuma obrigação de subcontratação.\n\n25 - COMPRA PÚBLICA ESTRATÉGICA\nCompra Pública Estratégica: Inexistência de contratação pública estratégica\n\n26 - INFORMAÇÕES ADICIONAIS\nContrato adequado para PME: Sim\nCobertura ACP (Acordo dos Contratos Públicos da Organização Mundial do Comércio): Não\n\n27 - IDENTIFICAÇÃO E CONTACTOS DO ÓRGÃO DE RECURSOS ADMINISTRATIVOS\nDesignação: Conselho de Administração da ULSG/E, EPE\nEndereço: Rua Conceição Fernandes S/N\nCódigo postal: 4434-502\nLocalidade: Vila Nova de Gaia\nTelefone: +351 227865100\nFax: +351 227830209\nEndereço eletrónico: ca@ulsge.min-saude.pt\n\n28 - IDENTIFICAÇÃO DO(S) AUTOR(ES) DE ANÚNCIO\nNome: Diogo Sousa\nCargo: Técnico Superior\n419480269",
    "nipc": "508142156",
    "distrito": "Porto",
    "concelho": "Vila Nova de Gaia",
    "freguesia": "Freguesia de Vilar de Andorinho",
    "site": "www.chvng.min-saude.pt",
    "email": "info@chvng.min-saude.pt",
    "designacao_contrato": "Aquisição de Serviços para a Construção de um Modelo Dinâmico de Distribuição da Capacidade Instalada no Bloco Operatório e Consulta Externa",
    "descricao": "Aquisição de Serviços para a Construção de um Modelo Dinâmico de Distribuição da Capacidade Instalada no Bloco Operatório e Consulta Externa",
    "preco_base": "210.000,00 EUR",
    "prazo_execucao": "90 DIAS",
    "prazo_apresentacao_propostas": "15-09-2025 18:00",
    "fundos_eu": "Não",
    "plataforma_eletronica": "VORTAL",
    "url_procedimento": "https://community.vortal.biz/public/",
    "autor_nome": "Diogo Sousa",
    "autor_cargo": "Técnico Superior"
  },
  {
    "numero_procedimento": "N/A",
    "entidade": "Município de Aveiro",
    "link": "https://diariodarepublica.pt/dr/detalhe/contrato-publico/23255-933788347",
    "detalhes_completos": "1 - IDENTIFICAÇÃO E CONTACTOS DA ENTIDADE ADJUDICANTE\nDesignação da entidade adjudicante: Município de Aveiro\nNIPC: 505931192\nServiço/Órgão/Pessoa de contacto: obrasmunicipais@cm-aveiro.pt\nEndereço: Praça da República\nCódigo postal: 3810-156\nLocalidade: Aveiro\nPaís: Portugal\nNUT III: PT16D\nDistrito: Aveiro\nConcelho: Aveiro\nFreguesia: União das Freguesias de Glória e Vera Cruz\nTelefone: 234406300\nFax: 234406301\nEndereço da Entidade (URL): www.cm-aveiro.pt\nEndereço Eletrónico: geral@cm-aveiro.pt\neDelivery Gateway (URL): https://www.acingov.pt\nFunção da Organização: Adquirente\nNorma jurídica da Entidade Adjudicante: Organismo de direito público\nÁrea de atividade da Autoridade Adjudicante: Serviços públicos das administrações públicas\n\n2 - JORNAL OFICIAL DA UNIÃO EUROPEIA\nO procedimento a que este anúncio diz respeito também é publicitado no Jornal Oficial da União Europeia? Não\n\n3 - AVISO\nModelo de Anúncio: Concurso público\nData de Envio do Anúncio: 01-09-2025\n\n5 - PROCESSO\nTipo de Procedimento: Concurso público\nPreço base do procedimento: Sim\nValor do preço base do procedimento: 105.000,00 EUR\nProcedimento com lotes? Não\n\n6 - OBJETO DO CONTRATO\nNúmero de referência interna: PS/CP/01/25\nDesignação do contrato: Locação de Contentores para refeitório da Escola das Cardadeiras - Esgueira\nDescrição: Locação de Contentores para refeitório da Escola das Cardadeiras - Esgueira\nTipo de Contrato Principal: Locação de Bens Móveis\nTipo de Contrato: Locação de Bens Móveis\nClassificação CPV (Vocabulário Comum para os Contratos Públicos)\nObjeto principal\nVocabulário Principal: 44211100\nPreço base s/IVA: 105.000,00 EUR\n\n7 - INDICAÇÕES ADICIONAIS\nO contrato envolve aquisição conjunta (satisfação de várias entidades)? Não\nO contrato é adjudicado por uma central de compras? Não\n\n8 - TÉCNICAS\nO concurso destina-se à celebração de um acordo-quadro? Inexistência de acordo-quadro\nÉ utilizado um leilão eletrónico? Não\nÉ adotada uma fase de negociação? Não\nSistema de Aquisição Dinâmico: Inexistência de sistema de aquisição dinâmico\n\n9 - LOCAL DA EXECUÇÃO DO CONTRATO\nLOCAL DA EXECUÇÃO DO CONTRATO (PROCEDIMENTO)\nPaís: Portugal\nNUT III: PT16D\nLocalidade: Freguesia de Esgueira\nDistrito: Aveiro\nConcelho: Aveiro\nFreguesia: Freguesia de Esgueira\n\n10 - PRAZO DE EXECUÇÃO DO CONTRATO\nPrazo de execução do contrato: 24 MESES\nPrevisão de renovações: Não\n\n11 - FUNDOS EU\nTêm fundos EU? Não\n\n12 - DOCUMENTOS DE HABILITAÇÃO\nHabilitação para o exercício da atividade profissional: Não\n\n13 - CONDIÇÕES DE APRESENTAÇÃO\nPlataforma eletrónica utilizada pela entidade adjudicante: ACIN\nURL para Apresentação: https://www.acingov.pt\nAdmissibilidade da apresentação de propostas variantes: Não autorizado\nPrazo para apresentação das propostas: 22-09-2025 17:00\nPrazo durante o qual os concorrentes são obrigados a manter as respetivas propostas: 120 dias a contar do termo do prazo para a apresentação das propostas\nIndicação de Subcontratação na Proposta: Inexistência de indicação de subcontratação\n\n14 - PRESTAÇÃO DE CAUÇÃO\nPrestação de caução: Não\n\n15 - FORNECIMENTO DAS PEÇAS DO CONCURSO, APRESENTAÇÃO DE PEDIDOS DE PARTICIPAÇÃO E APRESENTAÇÃO DAS PROPOSTAS\nLink para acesso às peças do concurso (URL): https://www.acingov.pt/acingovprod/2/zonaPublica/zona_publica_c/donwloadProcedurePiece/OTcyODY3\n\n20 - OUTROS REQUISITOS\nInformação sobre contratos reservados. Aplica-se a contratos reservados (54º-A)? Não\n\n21 - CRITÉRIO DE ADJUDICAÇÃO\nMultifator: Não\nMonofator:\nNome: Preço\n\n24 - CONDIÇÕES DO CONTRATO\nFaturação Eletrónica: Permitido\nObrigação de Subcontratação:\nCódigo da Obrigação de Subcontratação: Não é aplicável nenhuma obrigação de subcontratação.\n\n25 - COMPRA PÚBLICA ESTRATÉGICA\nCompra Pública Estratégica: Inexistência de contratação pública estratégica\n\n26 - INFORMAÇÕES ADICIONAIS\nContrato adequado para PME: Sim\nCobertura ACP (Acordo dos Contratos Públicos da Organização Mundial do Comércio): Não\n\n27 - IDENTIFICAÇÃO E CONTACTOS DO ÓRGÃO DE RECURSOS ADMINISTRATIVOS\nDesignação: Câmara Municipal de Aveiro\nEndereço: Praça da República\nCódigo postal: 3810-156\nLocalidade: Aveiro\nTelefone: 351234460300\nFax: 351234460300\nEndereço eletrónico: geral@cm-aveiro.pt\nPrazo de interposição do recurso: 5 dias\n\n28 - IDENTIFICAÇÃO DO(S) AUTOR(ES) DE ANÚNCIO\nNome: José Agostinho Ribau Esteves\nCargo: Presidente\n419475799",
    "nipc": "505931192",
    "distrito": "Aveiro",
    "concelho": "Aveiro",
    "freguesia": "União das Freguesias de Glória e Vera Cruz",
    "site": "www.cm-aveiro.pt",
    "email": "geral@cm-aveiro.pt",
    "designacao_contrato": "Locação de Contentores para refeitório da Escola das Cardadeiras - Esgueira",
    "descricao": "Locação de Contentores para refeitório da Escola das Cardadeiras - Esgueira",
    "preco_base": "105.000,00 EUR",
    "prazo_execucao": "24 MESES",
    "prazo_apresentacao_propostas": "22-09-2025 17:00",
    "fundos_eu": "Não",
    "plataforma_eletronica": "ACIN",
    "url_procedimento": "https://www.acingov.pt",
    "autor_nome": "José Agostinho Ribau Esteves",
    "autor_cargo": "Presidente"
  },
  {
    "numero_procedimento": "N/A",
    "entidade": "SPMS- Serviços Partilhados do M. da Saúde, E.P.E.",
    "link": "https://diariodarepublica.pt/dr/detalhe/contrato-publico/23256-933788348",
    "detalhes_completos": "1 - IDENTIFICAÇÃO E CONTACTOS DA ENTIDADE ADJUDICANTE\nDesignação da entidade adjudicante: SPMS- Serviços Partilhados do M. da Saúde, E.P.E.\nNIPC: 509540716\nEndereço: Avenida da República 61\nCódigo postal: 1050-189\nLocalidade: Lisboa\nPaís: Portugal\nNUT III: PT170\nDistrito: Lisboa\nConcelho: Lisboa\nFreguesia: Todas\nTelefone: 211545600\nFax: 211545649\nEndereço da Entidade (URL): www.spms.min-saude.pt/\nEndereço Eletrónico: contratacao@spms.min-saude.pt\neDelivery Gateway (URL): https://community.vortal.biz/public/\nFunção da Organização: Adquirente\nNorma jurídica da Entidade Adjudicante: Empresa pública\nÁrea de atividade da Autoridade Adjudicante: Saúde\n\n2 - JORNAL OFICIAL DA UNIÃO EUROPEIA\nO procedimento a que este anúncio diz respeito também é publicitado no Jornal Oficial da União Europeia? Não\n\n3 - AVISO\nModelo de Anúncio: Concurso público\nData de Envio do Anúncio: 01-09-2025\n\n5 - PROCESSO\nTipo de Procedimento: Concurso público\nPreço base do procedimento: Sim\nValor do preço base do procedimento: 193.050,00 EUR\nProcedimento com lotes? Não\n\n6 - OBJETO DO CONTRATO\nNúmero de referência interna: 20250436\nDesignação do contrato: (DAG) AQUISIÇÃO DE RENOVAÇÃO DA SUBSCRIÇÃO DO LICENCIAMENTO ATLASSIAN PARA 2025 (20250436)\nDescrição: (DAG) AQUISIÇÃO DE RENOVAÇÃO DA SUBSCRIÇÃO DO LICENCIAMENTO ATLASSIAN PARA 2025 (20250436)\nTipo de Contrato Principal: Aquisição de Serviços\nTipo de Contrato: Aquisição de Serviços\nClassificação CPV (Vocabulário Comum para os Contratos Públicos)\nObjeto principal\nVocabulário Principal: 72500000\nPreço base s/IVA: 193.050,00 EUR\n\n7 - INDICAÇÕES ADICIONAIS\nO contrato envolve aquisição conjunta (satisfação de várias entidades)? Não\nO contrato é adjudicado por uma central de compras? Não\n\n8 - TÉCNICAS\nO concurso destina-se à celebração de um acordo-quadro? Inexistência de acordo-quadro\nÉ utilizado um leilão eletrónico? Não\nÉ adotada uma fase de negociação? Não\nSistema de Aquisição Dinâmico: Inexistência de sistema de aquisição dinâmico\n\n9 - LOCAL DA EXECUÇÃO DO CONTRATO\nLOCAL DA EXECUÇÃO DO CONTRATO (PROCEDIMENTO)\nPaís: Portugal\nNUT III: PT170\nLocalidade: Lisboa\nDistrito: Lisboa\nConcelho: Lisboa\nFreguesia: Todas\n\n10 - PRAZO DE EXECUÇÃO DO CONTRATO\nPrazo de execução do contrato: 3 MESES\nPrevisão de renovações: Não\n\n11 - FUNDOS EU\nTêm fundos EU? Não\n\n12 - DOCUMENTOS DE HABILITAÇÃO\nHabilitação para o exercício da atividade profissional: Não\n\n13 - CONDIÇÕES DE APRESENTAÇÃO\nPlataforma eletrónica utilizada pela entidade adjudicante: VORTAL\nURL para Apresentação: https://community.vortal.biz/public/\nAdmissibilidade da apresentação de propostas variantes: Não autorizado\nPrazo para apresentação das propostas: 08-09-2025 18:00\nPrazo durante o qual os concorrentes são obrigados a manter as respetivas propostas: 180 dias a contar do termo do prazo para a apresentação das propostas\nIndicação de Subcontratação na Proposta: Inexistência de indicação de subcontratação\n\n14 - PRESTAÇÃO DE CAUÇÃO\nPrestação de caução: Sim\nPercentagem: 2%\nDescrição da Garantia Exigida: Ver artigo 29.º do Programa de Concurso\n\n15 - FORNECIMENTO DAS PEÇAS DO CONCURSO, APRESENTAÇÃO DE PEDIDOS DE PARTICIPAÇÃO E APRESENTAÇÃO DAS PROPOSTAS\nLink para acesso às peças do concurso (URL): https://community.vortal.biz/Public/public-tender-documents/UlN1WU04U1NGbnBxSkI4RlRWYkZ4a3IvK3BIYys4OGlZdDNudjlZaUk2ZEppNzJyeFEvQWhQOVNyOUo0MFZUVWlYQWZQdnRCRzFBbEJsVUc3MG1oMFE9PUxDTXUw\n\n20 - OUTROS REQUISITOS\nInformação sobre contratos reservados. Aplica-se a contratos reservados (54º-A)? Não\n\n21 - CRITÉRIO DE ADJUDICAÇÃO\nMultifator: Não\nMonofator:\nNome: Preço\n\n24 - CONDIÇÕES DO CONTRATO\nFaturação Eletrónica: Permitido\nObrigação de Subcontratação:\nCódigo da Obrigação de Subcontratação: Não é aplicável nenhuma obrigação de subcontratação.\n\n25 - COMPRA PÚBLICA ESTRATÉGICA\nCompra Pública Estratégica: Inexistência de contratação pública estratégica\n\n26 - INFORMAÇÕES ADICIONAIS\nContrato adequado para PME: Sim\nCobertura ACP (Acordo dos Contratos Públicos da Organização Mundial do Comércio): Não\n\n27 - IDENTIFICAÇÃO E CONTACTOS DO ÓRGÃO DE RECURSOS ADMINISTRATIVOS\nDesignação: Serviços Partilhados do Ministério da Saúde, EPE\nEndereço: Avenida da República, nº 61\nCódigo postal: 1050-189\nLocalidade: Lisboa\nTelefone: +351 211545600\nFax: +351 211545649\nEndereço eletrónico: contratacao@spms.min-saude.pt\n\n28 - IDENTIFICAÇÃO DO(S) AUTOR(ES) DE ANÚNCIO\nNome: Ana Gonçalves\nCargo: Coordenadora da Unidade de Aprovisionamento\n419489552",
    "nipc": "509540716",
    "distrito": "Lisboa",
    "concelho": "Lisboa",
    "freguesia": "Todas",
    "site": "www.spms.min-saude.pt/",
    "email": "contratacao@spms.min-saude.pt",
    "designacao_contrato": "(DAG) AQUISIÇÃO DE RENOVAÇÃO DA SUBSCRIÇÃO DO LICENCIAMENTO ATLASSIAN PARA 2025 (20250436)",
    "descricao": "(DAG) AQUISIÇÃO DE RENOVAÇÃO DA SUBSCRIÇÃO DO LICENCIAMENTO ATLASSIAN PARA 2025 (20250436)",
    "preco_base": "193.050,00 EUR",
    "prazo_execucao": "3 MESES",
    "prazo_apresentacao_propostas": "08-09-2025 18:00",
    "fundos_eu": "Não",
    "plataforma_eletronica": "VORTAL",
    "url_procedimento": "https://community.vortal.biz/public/",
    "autor_nome": "Ana Gonçalves",
    "autor_cargo": "Coordenadora da Unidade de Aprovisionamento"
  },
  {
    "numero_procedimento": "N/A",
    "entidade": "Unidade Local de Saúde do Alto Alentejo E.P.E",
    "link": "https://diariodarepublica.pt/dr/detalhe/contrato-publico/23263-933788349",
    "detalhes_completos": "1 - IDENTIFICAÇÃO E CONTACTOS DA ENTIDADE ADJUDICANTE\nDesignação da entidade adjudicante: Unidade Local de Saúde do Alto Alentejo E.P.E\nNIPC: 508094461\nEndereço: Av. De Santo António\nCódigo postal: 7300-853\nLocalidade: Portalegre\nPaís: Portugal\nNUT III: PT186\nDistrito: Portalegre\nConcelho: Portalegre\nFreguesia: União das Freguesias da Sé e São Lourenço\nTelefone: 245301000\nFax: 245301002\nEndereço da Entidade (URL): www.hportalegre.min-saude.pt\nEndereço Eletrónico: aprov.portalegre.elvas@ulsna.min-saude.pt\neDelivery Gateway (URL): https://community.vortal.biz/public/\nFunção da Organização: Adquirente\nNorma jurídica da Entidade Adjudicante: Empresa pública\nÁrea de atividade da Entidade Adjudicante: Atividades aeroportuárias\n\n2 - JORNAL OFICIAL DA UNIÃO EUROPEIA\nO procedimento a que este anúncio diz respeito também é publicitado no Jornal Oficial da União Europeia? Não\n\n3 - AVISO\nModelo de Anúncio: Concurso público\nData de Envio do Anúncio: 01-09-2025\n\n5 - PROCESSO\nTipo de Procedimento: Concurso público\nPreço base do procedimento: Sim\nValor do preço base do procedimento: 242.715,00 EUR\nProcedimento com lotes? Não\n\n6 - OBJETO DO CONTRATO\nNúmero de referência interna: 17103525\nDesignação do contrato: Projeto N.º 11332- Submedida i1.08 – Requalificar ou adaptar edifícios para aumentar a eficiência energética, cumprir planos de contingências e/ou assegurar a acessibilidade, a segurança e o conforto \nDescrição: Projeto N.º 11332- Submedida i1.08 – Requalificar ou adaptar edifícios para aumentar a eficiência energética, cumprir planos de contingências e/ou assegurar a acessibilidade, a segurança e o conforto de utentes e profissionais, prevista no Plano de Recuperação e Resiliência Empreitada para Requalificação do Centro de Saúde de Portalegre da Unidade Local de Saúde do Alto Alentejo, EPE \nTipo de Contrato Principal: Empreitada de Obras Públicas\nTipo de Contrato: Empreitada de Obras Públicas\nClassificação CPV (Vocabulário Comum para os Contratos Públicos)\nObjeto principal\nVocabulário Principal: 45454000\nPreço base s/IVA: 242.715,00 EUR\n\n7 - INDICAÇÕES ADICIONAIS\nO contrato envolve aquisição conjunta (satisfação de várias entidades)? Não\nO contrato é adjudicado por uma central de compras? Não\n\n8 - TÉCNICAS\nO concurso destina-se à celebração de um acordo-quadro? Inexistência de acordo-quadro\nÉ utilizado um leilão eletrónico? Não\nÉ adotada uma fase de negociação? Não\nSistema de Aquisição Dinâmico: Inexistência de sistema de aquisição dinâmico\n\n9 - LOCAL DA EXECUÇÃO DO CONTRATO\nLOCAL DA EXECUÇÃO DO CONTRATO (PROCEDIMENTO)\nPaís: Portugal\nNUT III: PT186\nLocalidade: Portalegre\nDistrito: Portalegre\nConcelho: Portalegre\nFreguesia: União das Freguesias da Sé e São Lourenço\n\n10 - PRAZO DE EXECUÇÃO DO CONTRATO\nPrazo de execução do contrato: 180 DIAS\nPrevisão de renovações: Não\n\n11 - FUNDOS EU\nTêm fundos EU? Sim\n\n12 - DOCUMENTOS DE HABILITAÇÃO\nHabilitação para o exercício da atividade profissional: Não\n\n13 - CONDIÇÕES DE APRESENTAÇÃO\nPlataforma eletrónica utilizada pela entidade adjudicante: VORTAL\nURL para Apresentação: https://community.vortal.biz/public/\nAdmissibilidade da apresentação de propostas variantes: Não autorizado\nPrazo para apresentação das propostas: 16-09-2025 18:00\nPrazo durante o qual os concorrentes são obrigados a manter as respetivas propostas: 180 dias a contar do termo do prazo para a apresentação das propostas\nIndicação de Subcontratação na Proposta: Inexistência de indicação de subcontratação\n\n14 - PRESTAÇÃO DE CAUÇÃO\nPrestação de caução: Não\n\n15 - FORNECIMENTO DAS PEÇAS DO CONCURSO, APRESENTAÇÃO DE PEDIDOS DE PARTICIPAÇÃO E APRESENTAÇÃO DAS PROPOSTAS\nLink para acesso às peças do concurso (URL): https://community.vortal.biz/Public/public-tender-documents/M1BjMzZMWnZ5NHVLVVg4bkt1aSsvUUM5WU5UOXhFeGsxalBRekgrREFrcWs4QTdYbFkzeHdhRTlKV0dxTy9vYU0vNzVxL3BSbm0yNEQxZlRweWFnQmc9PTBWMUM2\n\n20 - OUTROS REQUISITOS\nInformação sobre contratos reservados. Aplica-se a contratos reservados (54º-A)? Não\n\n21 - CRITÉRIO DE ADJUDICAÇÃO\nMultifator: Sim\nFator: \nNome: Preço\nPonderação: 70%\nSubfatores: Não\nFator: \nNome: Qualidade\nPonderação: 30%\nSubfatores: Não\n\n24 - CONDIÇÕES DO CONTRATO\nFaturação Eletrónica: Permitido\nObrigação de Subcontratação:\nCódigo da Obrigação de Subcontratação: Não é aplicável nenhuma obrigação de subcontratação.\n\n25 - COMPRA PÚBLICA ESTRATÉGICA\nCompra Pública Estratégica: Redução dos impactos ambientais\nDescrição do Processo de Adjudicação Estratégico: Conforme as peças do procedimento\nCritérios de contratos Públicos Ecológicos: Critérios de contratação pública ecológica nacional\nCategorias da estratégia nacional: Conceção, construção e gestão de edifícios de escritórios\nDiretiva Veículos Não Poluentes: Não\nCritério de Acessibilidade: Os critérios de acessibilidade para as pessoas com deficiência não estão incluídos porque o contrato não se destina a pessoas singulares\n\n26 - INFORMAÇÕES ADICIONAIS\nContrato adequado para PME: Sim\nCobertura ACP (Acordo dos Contratos Públicos da Organização Mundial do Comércio): Não\n\n27 - IDENTIFICAÇÃO E CONTACTOS DO ÓRGÃO DE RECURSOS ADMINISTRATIVOS\nDesignação: Conselho de Administração\nEndereço: AVENIDA DE SANTO ANTÓNIO\nCódigo postal: 7300-853\nLocalidade: Portalegre\nTelefone: +351 245301000\nFax: +351 245330359\nEndereço eletrónico: admin@ulsaale.min-saude.pt\n\n28 - IDENTIFICAÇÃO DO(S) AUTOR(ES) DE ANÚNCIO\nNome: José Lopes\nCargo: Presidente do Conselho de Administração\n419490353",
    "nipc": "508094461",
    "distrito": "Portalegre",
    "concelho": "Portalegre",
    "freguesia": "União das Freguesias da Sé e São Lourenço",
    "site": "www.hportalegre.min-saude.pt",
    "email": "aprov.portalegre.elvas@ulsna.min-saude.pt",
    "designacao_contrato": "Projeto N.º 11332- Submedida i1.08 – Requalificar ou adaptar edifícios para aumentar a eficiência energética, cumprir planos de contingências e/ou assegurar a acessibilidade, a segurança e o conforto",
    "descricao": "Projeto N.º 11332- Submedida i1.08 – Requalificar ou adaptar edifícios para aumentar a eficiência energética, cumprir planos de contingências e/ou assegurar a acessibilidade, a segurança e o conforto de utentes e profissionais, prevista no Plano de Recuperação e Resiliência Empreitada para Requalificação do Centro de Saúde de Portalegre da Unidade Local de Saúde do Alto Alentejo, EPE",
    "preco_base": "242.715,00 EUR",
    "prazo_execucao": "180 DIAS",
    "prazo_apresentacao_propostas": "16-09-2025 18:00",
    "fundos_eu": "Sim",
    "plataforma_eletronica": "VORTAL",
    "url_procedimento": "https://community.vortal.biz/public/",
    "autor_nome": "José Lopes",
    "autor_cargo": "Presidente do Conselho de Administração"
  },
  {
    "numero_procedimento": "N/A",
    "entidade": "Infraestruturas de Portugal",
    "link": "https://diariodarepublica.pt/dr/detalhe/contrato-publico/23265-933788350",
    "detalhes_completos": "1 - IDENTIFICAÇÃO E CONTACTOS DA ENTIDADE ADJUDICANTE\nDesignação da entidade adjudicante: Infraestruturas de Portugal\nNIPC: 503933813\nServiço/Órgão/Pessoa de contacto: Direção de Compras e Logística - Departamento de Compras - Edifício 2\nEndereço: Praça da Portagem\nCódigo postal: 2809-013\nLocalidade: Almada\nPaís: Portugal\nNUT III: PT170\nDistrito: Setúbal\nConcelho: Almada\nFreguesia: União das Freguesias de Almada, Cova da Piedade, Pragal e Cacilhas\nTelefone:  212 879 300 \nFax: 21 287 90 00\nEndereço da Entidade (URL): www.infraestruturasdeportugal.pt\nEndereço Eletrónico: dcl@infraestruturasdeportugal.pt\nFunção da Organização: Adquirente\nNorma jurídica da Entidade Adjudicante: Organismo de direito público\nÁrea de atividade da Entidade Adjudicante: Serviços ferroviários\n\n2 - JORNAL OFICIAL DA UNIÃO EUROPEIA\nO procedimento a que este anúncio diz respeito também é publicitado no Jornal Oficial da União Europeia? Não\n\n3 - AVISO\nModelo de Anúncio: Concurso público\nData de Envio do Anúncio: 01-09-2025\n\n5 - PROCESSO\nTipo de Procedimento: Concurso público\nPreço base do procedimento: Sim\nValor do preço base do procedimento: 950.000,00 EUR\nProcedimento com lotes? Não\n\n6 - OBJETO DO CONTRATO\nNúmero de referência interna: 10021140\nDesignação do contrato: Empreitada - EN263 - KM11+500 A KM23+564 - CONSERVAÇÃO CORRETIVA DO PAVIMENTO\nDescrição: EN263 - KM11+500 A KM23+564 - CONSERVAÇÃO CORRETIVA DO PAVIMENTO\nTipo de Contrato Principal: Empreitada de Obras Públicas\nTipo de Contrato: Empreitada de Obras Públicas\nClassificação CPV (Vocabulário Comum para os Contratos Públicos)\nObjeto principal\nVocabulário Principal: 45233141\nPreço base s/IVA: 950.000,00 EUR\n\n7 - INDICAÇÕES ADICIONAIS\nO contrato envolve aquisição conjunta (satisfação de várias entidades)? Não\nO contrato é adjudicado por uma central de compras? Não\n\n8 - TÉCNICAS\nO concurso destina-se à celebração de um acordo-quadro? Inexistência de acordo-quadro\nÉ utilizado um leilão eletrónico? Não\nÉ adotada uma fase de negociação? Não\nSistema de Aquisição Dinâmico: Inexistência de sistema de aquisição dinâmico\n\n9 - LOCAL DA EXECUÇÃO DO CONTRATO\nLOCAL DA EXECUÇÃO DO CONTRATO (PROCEDIMENTO)\nPaís: Portugal\nNUT III: PT184\nLocalidade: Relíquias\nDistrito: Beja\nConcelho: Odemira\nFreguesia: Freguesia de Relíquias\nPaís: Portugal\nNUT III: PT184\nLocalidade: UF Garvão e Santa Luzia\nDistrito: Beja\nConcelho: Ourique\nFreguesia: União das Freguesias de Garvão e Santa Luzia\n\n10 - PRAZO DE EXECUÇÃO DO CONTRATO\nPrazo de execução do contrato: 90 DIAS\nPrevisão de renovações: Não\n\n11 - FUNDOS EU\nTêm fundos EU? Não\n\n12 - DOCUMENTOS DE HABILITAÇÃO\nHabilitação para o exercício da atividade profissional: Sim\nTipo: Alvará\nDescrição: 1.ª Subcategoria da 2.ª Categoria e da classe que cubra o valor global da proposta\n\n13 - CONDIÇÕES DE APRESENTAÇÃO\nPlataforma eletrónica utilizada pela entidade adjudicante: ANOGOV\nURL para Apresentação: https://www.anogov.com/infraestruturasdeportugal-ip/faces/\nAdmissibilidade da apresentação de propostas variantes: Não autorizado\nPrazo para apresentação das propostas: 22-09-2025 17:00\nPrazo durante o qual os concorrentes são obrigados a manter as respetivas propostas: 120 dias a contar do termo do prazo para a apresentação das propostas\nApresentação de Catálogo Eletrónico: Não autorizado\nIndicação de Subcontratação na Proposta: Inexistência de indicação de subcontratação\n\n14 - PRESTAÇÃO DE CAUÇÃO\nPrestação de caução: Sim\nPercentagem: 5%\nDescrição da Garantia Exigida: 5% do preço contratual\n\n15 - FORNECIMENTO DAS PEÇAS DO CONCURSO, APRESENTAÇÃO DE PEDIDOS DE PARTICIPAÇÃO E APRESENTAÇÃO DAS PROPOSTAS\nLink para acesso às peças do concurso (URL): https://www.anogov.com/infraestruturasdeportugal-ip/faces/app/acessoDocs.jsp?codigoAcesso=fCrlQT3jiWTYghvA4v5EWKF25KEEAGXwSeorDnYGd8t6vM1kSF\n\n20 - OUTROS REQUISITOS\nInformação sobre contratos reservados. Aplica-se a contratos reservados (54º-A)? Não\n\n21 - CRITÉRIO DE ADJUDICAÇÃO\nMultifator: Não\nMonofator:\nNome: Preço\n\n24 - CONDIÇÕES DO CONTRATO\nFaturação Eletrónica: Permitido\nObrigação de Subcontratação:\nCódigo da Obrigação de Subcontratação: Não é aplicável nenhuma obrigação de subcontratação.\n\n25 - COMPRA PÚBLICA ESTRATÉGICA\nCompra Pública Estratégica: Redução dos impactos ambientais\nDescrição do Processo de Adjudicação Estratégico: Definiçõesdassoluçõesgeraisquefundamentamautilizaçãodemateriaisrecicladosouqueincorporemmateriaisreciclados,descrevendoapercentagemmínimarelativamenteàquantidadetotal de matérias-primas a usar em obra\nCritérios de contratos Públicos Ecológicos: Critérios de contratação pública ecológica nacional\nCategorias da estratégia nacional: Conceção, construção, reabilitação e conservação de estradas\nDiretiva Veículos Não Poluentes: Não\nCritério de Acessibilidade: Os critérios de acessibilidade para as pessoas com deficiência não estão incluídos porque o contrato não se destina a pessoas singulares\n\n26 - INFORMAÇÕES ADICIONAIS\nContrato adequado para PME: Sim\nCobertura ACP (Acordo dos Contratos Públicos da Organização Mundial do Comércio): Não\n\n27 - IDENTIFICAÇÃO E CONTACTOS DO ÓRGÃO DE RECURSOS ADMINISTRATIVOS\nDesignação: Conselho de Administração da Infraestruturas de Portugal, S.A.\nEndereço: Praça da Portagem\nCódigo postal: 2809-013\nLocalidade: Almada\nEndereço eletrónico: contratos@infraestruturasdeportugal.pt\n\n28 - IDENTIFICAÇÃO DO(S) AUTOR(ES) DE ANÚNCIO\nNome: Clara Lourenço\nCargo: Diretora de Compras e Logística\n419484327",
    "nipc": "503933813",
    "distrito": "Setúbal",
    "concelho": "Almada",
    "freguesia": "União das Freguesias de Almada, Cova da Piedade, Pragal e Cacilhas",
    "site": "www.infraestruturasdeportugal.pt",
    "email": "dcl@infraestruturasdeportugal.pt",
    "designacao_contrato": "Empreitada - EN263 - KM11+500 A KM23+564 - CONSERVAÇÃO CORRETIVA DO PAVIMENTO",
    "descricao": "EN263 - KM11+500 A KM23+564 - CONSERVAÇÃO CORRETIVA DO PAVIMENTO",
    "preco_base": "950.000,00 EUR",
    "prazo_execucao": "90 DIAS",
    "prazo_apresentacao_propostas": "22-09-2025 17:00",
    "fundos_eu": "Não",
    "plataforma_eletronica": "ANOGOV",
    "url_procedimento": "https://www.anogov.com/infraestruturasdeportugal-ip/faces/",
    "autor_nome": "Clara Lourenço",
    "autor_cargo": "Diretora de Compras e Logística"
  },
  {
    "numero_procedimento": "N/A",
    "entidade": "Instituto Português de Oncologia de Lisboa FG, E.P.E.",
    "link": "https://diariodarepublica.pt/dr/detalhe/contrato-publico/23266-933788363",
    "detalhes_completos": "1 - IDENTIFICAÇÃO E CONTACTOS DA ENTIDADE ADJUDICANTE\nDesignação da entidade adjudicante: Instituto Português de Oncologia de Lisboa FG, E.P.E.\nNIPC: 506361616\nEndereço: Rua Profº Lima Basto\nCódigo postal: 1099-023\nLocalidade: Lisboa\nPaís: Portugal\nNUT III: PT170\nDistrito: Lisboa\nConcelho: Lisboa\nFreguesia: Todas\nTelefone: 217229800\nFax: 217229880\nEndereço da Entidade (URL): www.ipolisboa.min-saude.pt/\nEndereço Eletrónico: ipofg@ipolisboa.min-saude.pt\neDelivery Gateway (URL): https://community.vortal.biz/public/\nFunção da Organização: Adquirente\nNorma jurídica da Entidade Adjudicante: Organismo de direito público\nÁrea de atividade da Autoridade Adjudicante: Saúde\n\n2 - JORNAL OFICIAL DA UNIÃO EUROPEIA\nO procedimento a que este anúncio diz respeito também é publicitado no Jornal Oficial da União Europeia? Não\n\n3 - AVISO\nModelo de Anúncio: Concurso público\nData de Envio do Anúncio: 02-09-2025\n\n5 - PROCESSO\nTipo de Procedimento: Concurso público\nPreço base do procedimento: Sim\nValor do preço base do procedimento: 60.000,00 EUR\nProcedimento com lotes? Sim\nNº Máx. de Lotes Autorizado: 2\nNúmero máximo de lotes que podem ser adjudicados a um concorrente: 2\n\n6 - OBJETO DO CONTRATO\nNúmero de referência interna: PN/2177/2025\nDesignação do contrato: Aquisição de Ecógrafos (Portátil e Transportável) \nDescrição: Aquisição de Ecógrafos (Portátil e Transportável) \nTipo de Contrato Principal: Aquisição de Bens Móveis\nTipo de Contrato: Aquisição de Bens Móveis\nClassificação CPV (Vocabulário Comum para os Contratos Públicos)\nObjeto principal\nVocabulário Principal: 33100000\nPreço base s/IVA: 60.000,00 EUR\nLotes: \nNº: LOT-0001\nDescrição do Lote: Lote 1\nPreço base s/IVA: 30.000,00 EUR\nClassificação CPV (Vocabulário Comum para os Contratos Públicos)\nObjeto principal\nVocabulário Principal: 33100000\nNº: LOT-0002\nDescrição do Lote: Lote 2\nPreço base s/IVA: 30.000,00 EUR\nClassificação CPV (Vocabulário Comum para os Contratos Públicos)\nObjeto principal\nVocabulário Principal: 33100000\n\n7 - INDICAÇÕES ADICIONAIS\nO contrato envolve aquisição conjunta (satisfação de várias entidades)? Não\nO contrato é adjudicado por uma central de compras? Não\n\n8 - TÉCNICAS\nO concurso destina-se à celebração de um acordo-quadro? Inexistência de acordo-quadro\nÉ utilizado um leilão eletrónico? Não\nÉ adotada uma fase de negociação? Não\nSistema de Aquisição Dinâmico: Inexistência de sistema de aquisição dinâmico\n\n9 - LOCAL DA EXECUÇÃO DO CONTRATO\nLOCAL DA EXECUÇÃO DO CONTRATO (PROCEDIMENTO)\nPaís: Portugal\nNUT III: PT170\nLocalidade: Lisboa\nDistrito: Lisboa\nConcelho: Lisboa\nFreguesia: Freguesia de São Domingos de Benfica\nLOCAL DA EXECUÇÃO DO CONTRATO (LOTE)\nIdentificador do Lote: LOT-0001; LOT-0002\nPaís: Portugal\nNUT III: PT170\nLocalidade: Lisboa\nDistrito: Lisboa\nConcelho: Lisboa\nFreguesia: Freguesia de São Domingos de Benfica\n\n10 - PRAZO DE EXECUÇÃO DO CONTRATO\nIdentificador do Lote: LOT-0001; LOT-0002\nPrazo de execução do contrato: 30 DIAS\nPrevisão de renovações: Não\n\n11 - FUNDOS EU\nIdentificador do Lote: LOT-0001; LOT-0002\nTêm fundos EU? Sim\n\n12 - DOCUMENTOS DE HABILITAÇÃO\nHabilitação para o exercício da atividade profissional: Não\n\n13 - CONDIÇÕES DE APRESENTAÇÃO\nPlataforma eletrónica utilizada pela entidade adjudicante: VORTAL\nURL para Apresentação: https://community.vortal.biz/public/\nAdmissibilidade da apresentação de propostas variantes: Não autorizado\nPrazo para apresentação das propostas: 11-09-2025 17:59\nPrazo durante o qual os concorrentes são obrigados a manter as respetivas propostas: 90 dias a contar do termo do prazo para a apresentação das propostas\nIndicação de Subcontratação na Proposta: Inexistência de indicação de subcontratação\n\n14 - PRESTAÇÃO DE CAUÇÃO\nPrestação de caução: Não\n\n15 - FORNECIMENTO DAS PEÇAS DO CONCURSO, APRESENTAÇÃO DE PEDIDOS DE PARTICIPAÇÃO E APRESENTAÇÃO DAS PROPOSTAS\nLink para acesso às peças do concurso (URL): https://community.vortal.biz/Public/public-tender-documents/ZG9FQnpBWVVWM3lJSGJnODVMa0lUQ25DRHAzYzd4c3IxbmUySm9BZTZJTk5ZQUsreTA3ZzZmNUVmYTRQMC95R01YTm0vR3hzRG1xbE02TngxdXEySGc9PXUlaGJa\n\n20 - OUTROS REQUISITOS\nIdentificador do Lote: LOT-0001; LOT-0002\nInformação sobre contratos reservados. Aplica-se a contratos reservados (54º-A)? Não\n\n21 - CRITÉRIO DE ADJUDICAÇÃO\nO Critério de adjudicação é diferenciado por lote? Não\nMultifator: Sim\nFator: \nNome: Preço\nPonderação: 25%\nSubfatores: Não\nFator: \nNome: Qualidade\nPonderação: 65%\nSubfatores: Não\nFator: \nNome: Qualidade\nPonderação: 10%\nSubfatores: Não\n\n24 - CONDIÇÕES DO CONTRATO\nIdentificador do Lote: LOT-0001; LOT-0002\nFaturação Eletrónica: Permitido\nObrigação de Subcontratação:\nCódigo da Obrigação de Subcontratação: Não é aplicável nenhuma obrigação de subcontratação.\n\n25 - COMPRA PÚBLICA ESTRATÉGICA\nCompra Pública Estratégica: Inexistência de contratação pública estratégica\n\n26 - INFORMAÇÕES ADICIONAIS\nIdentificador do Lote: LOT-0001; LOT-0002\nContrato adequado para PME: Sim\nCobertura ACP (Acordo dos Contratos Públicos da Organização Mundial do Comércio): Não\n\n27 - IDENTIFICAÇÃO E CONTACTOS DO ÓRGÃO DE RECURSOS ADMINISTRATIVOS\nDesignação: Conselho de Administração\nEndereço: Rua Professor Lima Basto\nCódigo postal: 1099-023\nLocalidade: Lisboa\nTelefone: +351 217229800\nFax: +351 217229880\nEndereço eletrónico: ipofg@ipolisboa.min-saude.pt\n\n28 - IDENTIFICAÇÃO DO(S) AUTOR(ES) DE ANÚNCIO\nNome: Ricardo Costa\nCargo: Técnico Superior\n419490231",
    "nipc": "506361616",
    "distrito": "Lisboa",
    "concelho": "Lisboa",
    "freguesia": "Todas",
    "site": "www.ipolisboa.min-saude.pt/",
    "email": "ipofg@ipolisboa.min-saude.pt",
    "designacao_contrato": "Aquisição de Ecógrafos (Portátil e Transportável)",
    "descricao": "Aquisição de Ecógrafos (Portátil e Transportável)",
    "preco_base": "60.000,00 EUR",
    "prazo_execucao": "30 DIAS",
    "prazo_apresentacao_propostas": "11-09-2025 17:59",
    "fundos_eu": "Sim",
    "plataforma_eletronica": "VORTAL",
    "url_procedimento": "https://community.vortal.biz/public/",
    "autor_nome": "Ricardo Costa",
    "autor_cargo": "Técnico Superior"
  },
  {
    "numero_procedimento": "N/A",
    "entidade": "ESTAMO - Participações Imobiliárias, SA",
    "link": "https://diariodarepublica.pt/dr/detalhe/contrato-publico/23251-933891652",
    "detalhes_completos": "1 - IDENTIFICAÇÃO E CONTACTOS DA ENTIDADE ADJUDICANTE\nDesignação da entidade adjudicante: ESTAMO - Participações Imobiliárias, SA\nNIPC: 503152544\nEndereço: Ruia de Santa Marta, 55, 6º Andar\nCódigo postal: 1150-294\nLocalidade: Lisboa\nPaís: Portugal\nNUT III: PT187\nDistrito: Lisboa\nConcelho: Lisboa\nFreguesia: Freguesia de Santo António - Lisboa\nTelefone: 217802090\nFax: 217802090\nEndereço da Entidade (URL): www.estamo.pt\nEndereço Eletrónico: geral@estamo.pt\nFunção da Organização: Adquirente\nNorma jurídica da Entidade Adjudicante: Empresa pública, controlada por uma autoridade da administração central\nÁrea de atividade da Entidade Adjudicante: Serviços postais\n\n2 - JORNAL OFICIAL DA UNIÃO EUROPEIA\nO procedimento a que este anúncio diz respeito também é publicitado no Jornal Oficial da União Europeia? Não\n\n3 - AVISO\nModelo de Anúncio: Concurso público\nData de Envio do Anúncio: 01-09-2025\n\n5 - PROCESSO\nTipo de Procedimento: Concurso público\nPreço base do procedimento: Sim\nValor do preço base do procedimento: 2.500.000,00 EUR\nProcedimento com lotes? Não\n\n6 - OBJETO DO CONTRATO\nNúmero de referência interna: E1/2025\nDesignação do contrato: Reabilitação e Restauro da Capela de santo Amaro em Lisboa\nDescrição: Reabilitação e Restauro da Capela de santo Amaro em Lisboa\nTipo de Contrato Principal: Empreitada de Obras Públicas\nTipo de Contrato: Empreitada de Obras Públicas\nClassificação CPV (Vocabulário Comum para os Contratos Públicos)\nObjeto principal\nVocabulário Principal: 45212300\nPreço base s/IVA: 2.500.000,00 EUR\n\n7 - INDICAÇÕES ADICIONAIS\nO contrato envolve aquisição conjunta (satisfação de várias entidades)? Não\nO contrato é adjudicado por uma central de compras? Não\n\n8 - TÉCNICAS\nO concurso destina-se à celebração de um acordo-quadro? Inexistência de acordo-quadro\nÉ utilizado um leilão eletrónico? Não\nÉ adotada uma fase de negociação? Não\nSistema de Aquisição Dinâmico: Inexistência de sistema de aquisição dinâmico\n\n9 - LOCAL DA EXECUÇÃO DO CONTRATO\nLOCAL DA EXECUÇÃO DO CONTRATO (PROCEDIMENTO)\nPaís: Portugal\nNUT III: PT170\nLocalidade: Lisboa\nDistrito: Lisboa\nConcelho: Lisboa\nFreguesia: Freguesia de Alcântara\n\n10 - PRAZO DE EXECUÇÃO DO CONTRATO\nPrazo de execução do contrato: 365 DIAS\nPrevisão de renovações: Não\n\n11 - FUNDOS EU\nTêm fundos EU? Não\n\n12 - DOCUMENTOS DE HABILITAÇÃO\nHabilitação para o exercício da atividade profissional: Não\n\n13 - CONDIÇÕES DE APRESENTAÇÃO\nPlataforma eletrónica utilizada pela entidade adjudicante: ANOGOV\nURL para Apresentação: https://www.anogov.com/op-estamo/faces/\nAdmissibilidade da apresentação de propostas variantes: Não autorizado\nPrazo para apresentação das propostas: 22-09-2025 23:59\nPrazo durante o qual os concorrentes são obrigados a manter as respetivas propostas: 66 dias a contar do termo do prazo para a apresentação das propostas\nApresentação de Catálogo Eletrónico: Necessário\nIndicação de Subcontratação na Proposta: O(s) subcontratante(s) proposto(s) necessário(s) para cumprir a obrigação de subcontratar uma percentagem mínima do contrato\n\n14 - PRESTAÇÃO DE CAUÇÃO\nPrestação de caução: Não\n\n15 - FORNECIMENTO DAS PEÇAS DO CONCURSO, APRESENTAÇÃO DE PEDIDOS DE PARTICIPAÇÃO E APRESENTAÇÃO DAS PROPOSTAS\nLink para acesso às peças do concurso (URL): https://www.anogov.com/op-estamo/faces/app/acessoDocs.jsp?codigoAcesso=b2ACedjDaKAZwD80gL3qJ5H1z20WWIrxopb5L5yYD6lAXkBv8G\n\n20 - OUTROS REQUISITOS\nInformação sobre contratos reservados. Aplica-se a contratos reservados (54º-A)? Não\n\n21 - CRITÉRIO DE ADJUDICAÇÃO\nMultifator: Sim\nFator: \nNome: Outros\nOutro Nome: Prazo\nPonderação: 10%\nSubfatores: Não\nFator: \nNome: Preço\nPonderação: 90%\nSubfatores: Não\n\n24 - CONDIÇÕES DO CONTRATO\nFaturação Eletrónica: Permitido\nObrigação de Subcontratação:\nCódigo da Obrigação de Subcontratação: Não é aplicável nenhuma obrigação de subcontratação.\n\n25 - COMPRA PÚBLICA ESTRATÉGICA\nCompra Pública Estratégica: Inexistência de contratação pública estratégica\n\n26 - INFORMAÇÕES ADICIONAIS\nContrato adequado para PME: Sim\nCobertura ACP (Acordo dos Contratos Públicos da Organização Mundial do Comércio): Não\n\n27 - IDENTIFICAÇÃO E CONTACTOS DO ÓRGÃO DE RECURSOS ADMINISTRATIVOS\nDesignação: Conselho de Administração da ESTAMO - Participações Imobiliárias S.A.\nEndereço: Rua de Santa Marta, 55, 6º\nCódigo postal: 1150-294\nLocalidade: Lisboa\nTelefone: 217802090\nFax: \nEndereço eletrónico: geral@estamo.pt\nPrazo de interposição do recurso: 30 dias\n\n28 - IDENTIFICAÇÃO DO(S) AUTOR(ES) DE ANÚNCIO\nNome: Andreia Ribeiro\nCargo: Técnica \n419487616",
    "nipc": "503152544",
    "distrito": "Lisboa",
    "concelho": "Lisboa",
    "freguesia": "Freguesia de Santo António - Lisboa",
    "site": "www.estamo.pt",
    "email": "geral@estamo.pt",
    "designacao_contrato": "Reabilitação e Restauro da Capela de santo Amaro em Lisboa",
    "descricao": "Reabilitação e Restauro da Capela de santo Amaro em Lisboa",
    "preco_base": "2.500.000,00 EUR",
    "prazo_execucao": "365 DIAS",
    "prazo_apresentacao_propostas": "22-09-2025 23:59",
    "fundos_eu": "Não",
    "plataforma_eletronica": "ANOGOV",
    "url_procedimento": "https://www.anogov.com/op-estamo/faces/",
    "autor_nome": "Andreia Ribeiro",
    "autor_cargo": "Técnica"
  },
  {
    "numero_procedimento": "N/A",
    "entidade": "Unidade Local de Saúde de Lisboa Ocidental, E. P. E.",
    "link": "https://diariodarepublica.pt/dr/detalhe/contrato-publico/23253-933891653",
    "detalhes_completos": "1 - IDENTIFICAÇÃO E CONTACTOS DA ENTIDADE ADJUDICANTE\nDesignação da entidade adjudicante: Unidade Local de Saúde de Lisboa Ocidental, E. P. E.\nNIPC: 507618319\nEndereço: Santa Maria de Belém  Estrada do Forte do Alto do Duque\nCódigo postal: 1449-005\nLocalidade: Lisboa\nPaís: Portugal\nNUT III: PT170\nDistrito: Lisboa\nConcelho: Lisboa\nFreguesia: Todas\nTelefone: 210431000\nFax: 210431642\nEndereço da Entidade (URL): www.chlo.min-saude.pt/\nEndereço Eletrónico: comprasgeral@ulslo.min-saude.pt\neDelivery Gateway (URL): https://community.vortal.biz/public/\nFunção da Organização: Adquirente\nNorma jurídica da Entidade Adjudicante: Organismo de direito público\nÁrea de atividade da Autoridade Adjudicante: Saúde\n\n2 - JORNAL OFICIAL DA UNIÃO EUROPEIA\nO procedimento a que este anúncio diz respeito também é publicitado no Jornal Oficial da União Europeia? Não\n\n3 - AVISO\nModelo de Anúncio: Concurso público\nData de Envio do Anúncio: 01-09-2025\n\n5 - PROCESSO\nTipo de Procedimento: Concurso público\nPreço base do procedimento: Sim\nValor do preço base do procedimento: 67.465,00 EUR\nProcedimento com lotes? Não\n\n6 - OBJETO DO CONTRATO\nNúmero de referência interna: LG-142006425 Lentes Especiais\nDesignação do contrato: 142006425  Aquisição de Lentes Especiais 2025\nDescrição: 142006425 Aquisição de Lentes Especiais 2025\nTipo de Contrato Principal: Aquisição de Bens Móveis\nTipo de Contrato: Aquisição de Bens Móveis\nClassificação CPV (Vocabulário Comum para os Contratos Públicos)\nObjeto principal\nVocabulário Principal: 33140000\nPreço base s/IVA: 67.465,00 EUR\n\n7 - INDICAÇÕES ADICIONAIS\nO contrato envolve aquisição conjunta (satisfação de várias entidades)? Não\nO contrato é adjudicado por uma central de compras? Não\n\n8 - TÉCNICAS\nO concurso destina-se à celebração de um acordo-quadro? Inexistência de acordo-quadro\nÉ utilizado um leilão eletrónico? Não\nÉ adotada uma fase de negociação? Não\nSistema de Aquisição Dinâmico: Inexistência de sistema de aquisição dinâmico\n\n9 - LOCAL DA EXECUÇÃO DO CONTRATO\nLOCAL DA EXECUÇÃO DO CONTRATO (PROCEDIMENTO)\nPaís: Portugal\nNUT III: PT170\nLocalidade: Lisboa\nDistrito: Lisboa\nConcelho: Lisboa\nFreguesia: Todas\n\n10 - PRAZO DE EXECUÇÃO DO CONTRATO\nPrazo de execução do contrato: 151 DIAS\nPrevisão de renovações: Não\n\n11 - FUNDOS EU\nTêm fundos EU? Não\n\n12 - DOCUMENTOS DE HABILITAÇÃO\nHabilitação para o exercício da atividade profissional: Não\n\n13 - CONDIÇÕES DE APRESENTAÇÃO\nPlataforma eletrónica utilizada pela entidade adjudicante: VORTAL\nURL para Apresentação: https://community.vortal.biz/public/\nAdmissibilidade da apresentação de propostas variantes: Não autorizado\nPrazo para apresentação das propostas: 18-09-2025 23:59\nPrazo durante o qual os concorrentes são obrigados a manter as respetivas propostas: 66 dias a contar do termo do prazo para a apresentação das propostas\nIndicação de Subcontratação na Proposta: Inexistência de indicação de subcontratação\n\n14 - PRESTAÇÃO DE CAUÇÃO\nPrestação de caução: Não\n\n15 - FORNECIMENTO DAS PEÇAS DO CONCURSO, APRESENTAÇÃO DE PEDIDOS DE PARTICIPAÇÃO E APRESENTAÇÃO DAS PROPOSTAS\nLink para acesso às peças do concurso (URL): https://community.vortal.biz/Public/public-tender-documents/UXdFdEwxaXhhcjJJb0NXZE9lNy9PLzJDeXBGTTJoUE9nS1VvSjczTkZYTGk4ZGlhQnp5am1MblA1aE1WUGNCQVh0bkE1eXFhNFp3VlFKOW5mWGhBK1E9PTVPdUJM\n\n20 - OUTROS REQUISITOS\nInformação sobre contratos reservados. Aplica-se a contratos reservados (54º-A)? Não\n\n21 - CRITÉRIO DE ADJUDICAÇÃO\nMultifator: Não\nMonofator:\nNome: Preço\n\n24 - CONDIÇÕES DO CONTRATO\nFaturação Eletrónica: Permitido\nObrigação de Subcontratação:\nCódigo da Obrigação de Subcontratação: Não é aplicável nenhuma obrigação de subcontratação.\n\n25 - COMPRA PÚBLICA ESTRATÉGICA\nCompra Pública Estratégica: Inexistência de contratação pública estratégica\n\n26 - INFORMAÇÕES ADICIONAIS\nContrato adequado para PME: Sim\nCobertura ACP (Acordo dos Contratos Públicos da Organização Mundial do Comércio): Não\n\n27 - IDENTIFICAÇÃO E CONTACTOS DO ÓRGÃO DE RECURSOS ADMINISTRATIVOS\nDesignação: SGC\nEndereço: Estrada do Forte do Alto do Duque\nCódigo postal: 1449-005\nLocalidade: Lisboa\nTelefone: +351 210431000\nFax: +351 210431642\nEndereço eletrónico: comprascclinico@ulslo.min-saude.pt\n\n28 - IDENTIFICAÇÃO DO(S) AUTOR(ES) DE ANÚNCIO\nNome: Andrea Malta\nCargo: Diretora Serviço Gestão Compras\n419487608",
    "nipc": "507618319",
    "distrito": "Lisboa",
    "concelho": "Lisboa",
    "freguesia": "Todas",
    "site": "www.chlo.min-saude.pt/",
    "email": "comprasgeral@ulslo.min-saude.pt",
    "designacao_contrato": "142006425 Aquisição de Lentes Especiais 2025",
    "descricao": "142006425 Aquisição de Lentes Especiais 2025",
    "preco_base": "67.465,00 EUR",
    "prazo_execucao": "151 DIAS",
    "prazo_apresentacao_propostas": "18-09-2025 23:59",
    "fundos_eu": "Não",
    "plataforma_eletronica": "VORTAL",
    "url_procedimento": "https://community.vortal.biz/public/",
    "autor_nome": "Andrea Malta",
    "autor_cargo": "Diretora Serviço Gestão Compras"
  },
  {
    "numero_procedimento": "N/A",
    "entidade": "Unidade Local de Saúde de Coimbra, E. P. E.",
    "link": "https://diariodarepublica.pt/dr/detalhe/contrato-publico/23257-933891654",
    "detalhes_completos": "1 - IDENTIFICAÇÃO E CONTACTOS DA ENTIDADE ADJUDICANTE\nDesignação da entidade adjudicante: Unidade Local de Saúde de Coimbra, E. P. E.\nNIPC: 510103448\nEndereço: Praceta Prof. Mota Pinto\nCódigo postal: 3004-561\nLocalidade: Coimbra\nPaís: Portugal\nNUT III: PT16E\nDistrito: Coimbra\nConcelho: Coimbra\nFreguesia: Todas\nTelefone: 239400605\nFax: 239400605\nEndereço da Entidade (URL): https://www.chuc.min-saude.pt\nEndereço Eletrónico: ana.rosete@ulscoimbra.min-saude.pt\neDelivery Gateway (URL): https://community.vortal.biz/public/\nFunção da Organização: Adquirente\nNorma jurídica da Entidade Adjudicante: Organismo de direito público\nÁrea de atividade da Autoridade Adjudicante: Saúde\n\n2 - JORNAL OFICIAL DA UNIÃO EUROPEIA\nO procedimento a que este anúncio diz respeito também é publicitado no Jornal Oficial da União Europeia? Não\n\n3 - AVISO\nModelo de Anúncio: Concurso público\nData de Envio do Anúncio: 01-09-2025\n\n5 - PROCESSO\nTipo de Procedimento: Concurso público\nPreço base do procedimento: Sim\nValor do preço base do procedimento: 192.000,00 EUR\nProcedimento com lotes? Não\n\n6 - OBJETO DO CONTRATO\nNúmero de referência interna: 010900502025\nDesignação do contrato: Aquisição de um sistema de câmara de retinografia e módulo de angiografia para o Bloco Operatório do Serviço de Oftalmologia do polo HP da Unidade Local de Saúde de Coimbra, E.P.E.\nDescrição: Aquisição de um sistema de câmara de retinografia e módulo de angiografia para o Bloco Operatório do Serviço de Oftalmologia do polo HP da Unidade Local de Saúde de Coimbra, E.P.E.\nTipo de Contrato Principal: Aquisição de Bens Móveis\nTipo de Contrato: Aquisição de Bens Móveis\nClassificação CPV (Vocabulário Comum para os Contratos Públicos)\nObjeto principal\nVocabulário Principal: 33122000\nPreço base s/IVA: 192.000,00 EUR\n\n7 - INDICAÇÕES ADICIONAIS\nO contrato envolve aquisição conjunta (satisfação de várias entidades)? Não\nO contrato é adjudicado por uma central de compras? Não\n\n8 - TÉCNICAS\nO concurso destina-se à celebração de um acordo-quadro? Inexistência de acordo-quadro\nÉ utilizado um leilão eletrónico? Não\nÉ adotada uma fase de negociação? Não\nSistema de Aquisição Dinâmico: Inexistência de sistema de aquisição dinâmico\n\n9 - LOCAL DA EXECUÇÃO DO CONTRATO\nLOCAL DA EXECUÇÃO DO CONTRATO (PROCEDIMENTO)\nPaís: Portugal\nNUT III: PT16E\nLocalidade: Coimbra\nDistrito: Coimbra\nConcelho: Coimbra\nFreguesia: Freguesia de Santo António dos Olivais\n\n10 - PRAZO DE EXECUÇÃO DO CONTRATO\nPrazo de execução do contrato: 30 DIAS\nPrevisão de renovações: Não\n\n11 - FUNDOS EU\nTêm fundos EU? Não\n\n12 - DOCUMENTOS DE HABILITAÇÃO\nHabilitação para o exercício da atividade profissional: Não\n\n13 - CONDIÇÕES DE APRESENTAÇÃO\nPlataforma eletrónica utilizada pela entidade adjudicante: VORTAL\nURL para Apresentação: https://community.vortal.biz/public/\nAdmissibilidade da apresentação de propostas variantes: Não autorizado\nPrazo para apresentação das propostas: 16-09-2025 23:59\nPrazo durante o qual os concorrentes são obrigados a manter as respetivas propostas: 90 dias a contar do termo do prazo para a apresentação das propostas\nIndicação de Subcontratação na Proposta: Inexistência de indicação de subcontratação\n\n14 - PRESTAÇÃO DE CAUÇÃO\nPrestação de caução: Não\n\n15 - FORNECIMENTO DAS PEÇAS DO CONCURSO, APRESENTAÇÃO DE PEDIDOS DE PARTICIPAÇÃO E APRESENTAÇÃO DAS PROPOSTAS\nLink para acesso às peças do concurso (URL): https://community.vortal.biz/Public/public-tender-documents/aWdLWDJmeU5GR0FnamRmTzRoemlGekVQcTFsbFRqb2tUWXF5UG1rczRmUkZvaDZjbUloM0lVaFZmWTZERXEvZ1RQeGt0TU9Ec3V1RmEzL21DaktSbFE9PUNHWVQx\n\n20 - OUTROS REQUISITOS\nInformação sobre contratos reservados. Aplica-se a contratos reservados (54º-A)? Não\n\n21 - CRITÉRIO DE ADJUDICAÇÃO\nMultifator: Sim\nFator: \nNome: Preço\nPonderação: 60%\nSubfatores: Não\nFator: \nNome: Qualidade\nPonderação: 40%\nSubfatores: Não\n\n24 - CONDIÇÕES DO CONTRATO\nFaturação Eletrónica: Permitido\nObrigação de Subcontratação:\nCódigo da Obrigação de Subcontratação: Não é aplicável nenhuma obrigação de subcontratação.\n\n25 - COMPRA PÚBLICA ESTRATÉGICA\nCompra Pública Estratégica: Inexistência de contratação pública estratégica\n\n26 - INFORMAÇÕES ADICIONAIS\nContrato adequado para PME: Sim\nCobertura ACP (Acordo dos Contratos Públicos da Organização Mundial do Comércio): Não\n\n27 - IDENTIFICAÇÃO E CONTACTOS DO ÓRGÃO DE RECURSOS ADMINISTRATIVOS\nDesignação: Conselho de Administração da Unidade Local de Saúde de Coimbra, E.P.E.\nEndereço: Praceta Prof. Mota Pinto\nCódigo postal: 3004-561\nLocalidade: Coimbra\nTelefone: +351 239400400\nFax: +351 239400400\nEndereço eletrónico: casec@ulscoimbra.min-saude.pt\n\n28 - IDENTIFICAÇÃO DO(S) AUTOR(ES) DE ANÚNCIO\nNome: Esperança Mariano\nCargo: Assistente Técnica\n419486709",
    "nipc": "510103448",
    "distrito": "Coimbra",
    "concelho": "Coimbra",
    "freguesia": "Todas",
    "site": "https://www.chuc.min-saude.pt",
    "email": "ana.rosete@ulscoimbra.min-saude.pt",
    "designacao_contrato": "Aquisição de um sistema de câmara de retinografia e módulo de angiografia para o Bloco Operatório do Serviço de Oftalmologia do polo HP da Unidade Local de Saúde de Coimbra, E.P.E.",
    "descricao": "Aquisição de um sistema de câmara de retinografia e módulo de angiografia para o Bloco Operatório do Serviço de Oftalmologia do polo HP da Unidade Local de Saúde de Coimbra, E.P.E.",
    "preco_base": "192.000,00 EUR",
    "prazo_execucao": "30 DIAS",
    "prazo_apresentacao_propostas": "16-09-2025 23:59",
    "fundos_eu": "Não",
    "plataforma_eletronica": "VORTAL",
    "url_procedimento": "https://community.vortal.biz/public/",
    "autor_nome": "Esperança Mariano",
    "autor_cargo": "Assistente Técnica"
  },
  {
    "numero_procedimento": "N/A",
    "entidade": "Unidade Local de Saúde de Entre O Douro e Vouga, E.P.E",
    "link": "https://diariodarepublica.pt/dr/detalhe/contrato-publico/23258-933891655",
    "detalhes_completos": "1 - IDENTIFICAÇÃO E CONTACTOS DA ENTIDADE ADJUDICANTE\nDesignação da entidade adjudicante: Unidade Local de Saúde de Entre O Douro e Vouga, E.P.E\nNIPC: 508878462\nEndereço: RUA DOUTOR CÂNDIDO DE PINHO\nCódigo postal: 4520-211\nLocalidade: Aveiro\nPaís: Portugal\nNUT III: PT11A\nDistrito: Aveiro\nConcelho: Santa Maria da Feira\nFreguesia: União das Freguesias de Santa Maria da Feira, Travanca, Sanfins e Espargo\nTelefone: 256379735\nEndereço da Entidade (URL): www.ulsedv.min-saude.pt\nEndereço Eletrónico: concursos@ulsedv.min-saude.pt\neDelivery Gateway (URL): https://community.vortal.biz/public/\nFunção da Organização: Adquirente\nNorma jurídica da Entidade Adjudicante: Organismo de direito público\nÁrea de atividade da Autoridade Adjudicante: Saúde\n\n2 - JORNAL OFICIAL DA UNIÃO EUROPEIA\nO procedimento a que este anúncio diz respeito também é publicitado no Jornal Oficial da União Europeia? Não\n\n3 - AVISO\nModelo de Anúncio: Concurso público\nData de Envio do Anúncio: 01-09-2025\n\n5 - PROCESSO\nTipo de Procedimento: Concurso público\nPreço base do procedimento: Sim\nValor do preço base do procedimento: 499.521,13 EUR\nProcedimento com lotes? Não\n\n6 - OBJETO DO CONTRATO\nNúmero de referência interna: 0200027.422025\nDesignação do contrato: EMPREITADA DE REFORMULAÇÃO DO BLOCO OPERATÓRIO CENTRAL NO PISO 3 NA UNIDADE DE SANTA MARIA DA FEIRA\nDescrição: EMPREITADA DE REFORMULAÇÃO DO BLOCO OPERATÓRIO CENTRAL NO PISO 3 NA UNIDADE DE SANTA MARIA DA FEIRA\nTipo de Contrato Principal: Empreitada de Obras Públicas\nTipo de Contrato: Empreitada de Obras Públicas\nClassificação CPV (Vocabulário Comum para os Contratos Públicos)\nObjeto principal\nVocabulário Principal: 45215140\nPreço base s/IVA: 499.521,13 EUR\n\n7 - INDICAÇÕES ADICIONAIS\nO contrato envolve aquisição conjunta (satisfação de várias entidades)? Não\nO contrato é adjudicado por uma central de compras? Não\n\n8 - TÉCNICAS\nO concurso destina-se à celebração de um acordo-quadro? Inexistência de acordo-quadro\nÉ utilizado um leilão eletrónico? Não\nÉ adotada uma fase de negociação? Não\nSistema de Aquisição Dinâmico: Inexistência de sistema de aquisição dinâmico\n\n9 - LOCAL DA EXECUÇÃO DO CONTRATO\nLOCAL DA EXECUÇÃO DO CONTRATO (PROCEDIMENTO)\nPaís: Portugal\nNUT III: PT11A\nLocalidade: Aveiro\nDistrito: Aveiro\nConcelho: Santa Maria da Feira\nFreguesia: União das Freguesias de Santa Maria da Feira, Travanca, Sanfins e Espargo\n\n10 - PRAZO DE EXECUÇÃO DO CONTRATO\nPrazo de execução do contrato: 45 DIAS\nPrevisão de renovações: Não\n\n11 - FUNDOS EU\nTêm fundos EU? Não\n\n12 - DOCUMENTOS DE HABILITAÇÃO\nHabilitação para o exercício da atividade profissional: Não\n\n13 - CONDIÇÕES DE APRESENTAÇÃO\nPlataforma eletrónica utilizada pela entidade adjudicante: VORTAL\nURL para Apresentação: https://community.vortal.biz/public/\nAdmissibilidade da apresentação de propostas variantes: Não autorizado\nPrazo para apresentação das propostas: 26-09-2025 17:00\nPrazo durante o qual os concorrentes são obrigados a manter as respetivas propostas: 180 dias a contar do termo do prazo para a apresentação das propostas\nIndicação de Subcontratação na Proposta: Inexistência de indicação de subcontratação\n\n14 - PRESTAÇÃO DE CAUÇÃO\nPrestação de caução: Sim\nPercentagem: 5%\nDescrição da Garantia Exigida: Garantia bancaria\n\n15 - FORNECIMENTO DAS PEÇAS DO CONCURSO, APRESENTAÇÃO DE PEDIDOS DE PARTICIPAÇÃO E APRESENTAÇÃO DAS PROPOSTAS\nLink para acesso às peças do concurso (URL): https://community.vortal.biz/Public/public-tender-documents/MmlnOEdSbjNRS0lESTFRcGc1TkpxUVNyT1ZSWm9qVHFQeHRkNFFzMWxPUmM5Qm1GWHlZc0h2NVQ2cUV1eXVhMGUrenpMRkMvZGlnRVJ4YkpEOW00U0E9PWMrT01a\n\n20 - OUTROS REQUISITOS\nInformação sobre contratos reservados. Aplica-se a contratos reservados (54º-A)? Não\n\n21 - CRITÉRIO DE ADJUDICAÇÃO\nMultifator: Sim\nFator: \nNome: Preço\nPonderação: 50%\nSubfatores: Não\nFator: \nNome: Qualidade\nPonderação: 40%\nSubfatores: Não\nFator: \nNome: Qualidade\nPonderação: 10%\nSubfatores: Não\n\n24 - CONDIÇÕES DO CONTRATO\nFaturação Eletrónica: Permitido\nObrigação de Subcontratação:\nCódigo da Obrigação de Subcontratação: Não é aplicável nenhuma obrigação de subcontratação.\n\n25 - COMPRA PÚBLICA ESTRATÉGICA\nCompra Pública Estratégica: Inexistência de contratação pública estratégica\n\n26 - INFORMAÇÕES ADICIONAIS\nContrato adequado para PME: Sim\nCobertura ACP (Acordo dos Contratos Públicos da Organização Mundial do Comércio): Não\n\n27 - IDENTIFICAÇÃO E CONTACTOS DO ÓRGÃO DE RECURSOS ADMINISTRATIVOS\nDesignação: Conselho de Administração\nEndereço: Rua Dr. Cândido de Pinho\nCódigo postal: 4520-211\nLocalidade: Santa Maria da Feira\nTelefone: +351 256379735\nFax: +351 256379778\nEndereço eletrónico: concursos@ulsedv.min-saude.pt\n\n28 - IDENTIFICAÇÃO DO(S) AUTOR(ES) DE ANÚNCIO\nNome: Armenia Costa\nCargo: Técnica Superior Serviço de Compras\n419489869",
    "nipc": "508878462",
    "distrito": "Aveiro",
    "concelho": "Santa Maria da Feira",
    "freguesia": "União das Freguesias de Santa Maria da Feira, Travanca, Sanfins e Espargo",
    "site": "www.ulsedv.min-saude.pt",
    "email": "concursos@ulsedv.min-saude.pt",
    "designacao_contrato": "EMPREITADA DE REFORMULAÇÃO DO BLOCO OPERATÓRIO CENTRAL NO PISO 3 NA UNIDADE DE SANTA MARIA DA FEIRA",
    "descricao": "EMPREITADA DE REFORMULAÇÃO DO BLOCO OPERATÓRIO CENTRAL NO PISO 3 NA UNIDADE DE SANTA MARIA DA FEIRA",
    "preco_base": "499.521,13 EUR",
    "prazo_execucao": "45 DIAS",
    "prazo_apresentacao_propostas": "26-09-2025 17:00",
    "fundos_eu": "Não",
    "plataforma_eletronica": "VORTAL",
    "url_procedimento": "https://community.vortal.biz/public/",
    "autor_nome": "Armenia Costa",
    "autor_cargo": "Técnica Superior Serviço de Compras"
  },
  {
    "numero_procedimento": "N/A",
    "entidade": "Município de Braga",
    "link": "https://diariodarepublica.pt/dr/detalhe/contrato-publico/23259-933891656",
    "detalhes_completos": "1 - IDENTIFICAÇÃO E CONTACTOS DA ENTIDADE ADJUDICANTE\nDesignação da entidade adjudicante: Município de Braga\nNIPC: 506901173\nEndereço: Praça do Municípal\nCódigo postal: 4700-435\nLocalidade: Braga\nPaís: Portugal\nNUT III: PT112\nDistrito: Braga\nConcelho: Braga\nFreguesia: União das Freguesias de Braga (Maximinos, Sé e Cividade)\nTelefone: 253616060\nFax: 253203151\nEndereço da Entidade (URL): www.cm-braga.pt\nEndereço Eletrónico: contratacao.publica@cm-braga.pt\neDelivery Gateway (URL): https://community.vortal.biz/public/\nFunção da Organização: Adquirente\nNorma jurídica da Entidade Adjudicante: Autoridade local\nÁrea de atividade da Autoridade Adjudicante: Serviços públicos das administrações públicas\n\n2 - JORNAL OFICIAL DA UNIÃO EUROPEIA\nO procedimento a que este anúncio diz respeito também é publicitado no Jornal Oficial da União Europeia? Não\n\n3 - AVISO\nModelo de Anúncio: Concurso público\nData de Envio do Anúncio: 01-09-2025\n\n5 - PROCESSO\nTipo de Procedimento: Concurso público\nPreço base do procedimento: Sim\nValor do preço base do procedimento: 618.991,93 EUR\nProcedimento com lotes? Não\n\n6 - OBJETO DO CONTRATO\nNúmero de referência interna: CPE.27.25.DMOSM\nDesignação do contrato: REPAVIMENTAÇÃO DA AVENIDA DE REQUEIXO\nDescrição: REPAVIMENTAÇÃO DA AVENIDA DE REQUEIXO\nTipo de Contrato Principal: Empreitada de Obras Públicas\nTipo de Contrato: Empreitada de Obras Públicas\nClassificação CPV (Vocabulário Comum para os Contratos Públicos)\nObjeto principal\nVocabulário Principal: 45233200\nPreço base s/IVA: 618.991,93 EUR\n\n7 - INDICAÇÕES ADICIONAIS\nO contrato envolve aquisição conjunta (satisfação de várias entidades)? Não\nO contrato é adjudicado por uma central de compras? Não\n\n8 - TÉCNICAS\nO concurso destina-se à celebração de um acordo-quadro? Inexistência de acordo-quadro\nÉ utilizado um leilão eletrónico? Não\nÉ adotada uma fase de negociação? Não\nSistema de Aquisição Dinâmico: Inexistência de sistema de aquisição dinâmico\n\n9 - LOCAL DA EXECUÇÃO DO CONTRATO\nLOCAL DA EXECUÇÃO DO CONTRATO (PROCEDIMENTO)\nPaís: Portugal\nNUT III: PT112\nLocalidade: Braga\nDistrito: Braga\nConcelho: Braga\nFreguesia: Freguesia de Sobreposta\n\n10 - PRAZO DE EXECUÇÃO DO CONTRATO\nPrazo de execução do contrato: 120 DIAS\nPrevisão de renovações: Não\n\n11 - FUNDOS EU\nTêm fundos EU? Não\n\n12 - DOCUMENTOS DE HABILITAÇÃO\nHabilitação para o exercício da atividade profissional: Sim\nTipo: Alvará\nDescrição: De acordo com o artigo 22.º do Programa do Concurso.\n\n13 - CONDIÇÕES DE APRESENTAÇÃO\nPlataforma eletrónica utilizada pela entidade adjudicante: VORTAL\nURL para Apresentação: https://community.vortal.biz/public/\nAdmissibilidade da apresentação de propostas variantes: Não autorizado\nPrazo para apresentação das propostas: 01-10-2025 18:00\nPrazo durante o qual os concorrentes são obrigados a manter as respetivas propostas: 120 dias a contar do termo do prazo para a apresentação das propostas\nIndicação de Subcontratação na Proposta: Inexistência de indicação de subcontratação\n\n14 - PRESTAÇÃO DE CAUÇÃO\nPrestação de caução: Sim\nPercentagem: 5%\nDescrição da Garantia Exigida: De acordo com o artigo 24.º do Programa do Concurso.\n\n15 - FORNECIMENTO DAS PEÇAS DO CONCURSO, APRESENTAÇÃO DE PEDIDOS DE PARTICIPAÇÃO E APRESENTAÇÃO DAS PROPOSTAS\nLink para acesso às peças do concurso (URL): https://community.vortal.biz/Public/public-tender-documents/UEdkNzBYYlN2eTEyUXpKcGZQLzQwSVNRc3BwUFBqVGtzSHQ1bXJXblJkVlRRRC9adHhobVJiQzMrVFpDMXc1UFQrUW1zRU9yU3lUV0E4b3c4WjZDdHc9PSR4SkFV\n\n20 - OUTROS REQUISITOS\nInformação sobre contratos reservados. Aplica-se a contratos reservados (54º-A)? Não\n\n21 - CRITÉRIO DE ADJUDICAÇÃO\nMultifator: Não\nMonofator:\nNome: Preço\n\n24 - CONDIÇÕES DO CONTRATO\nFaturação Eletrónica: Permitido\nObrigação de Subcontratação:\nCódigo da Obrigação de Subcontratação: Não é aplicável nenhuma obrigação de subcontratação.\n\n25 - COMPRA PÚBLICA ESTRATÉGICA\nCompra Pública Estratégica: Inexistência de contratação pública estratégica\n\n26 - INFORMAÇÕES ADICIONAIS\nContrato adequado para PME: Sim\nCobertura ACP (Acordo dos Contratos Públicos da Organização Mundial do Comércio): Não\n\n27 - IDENTIFICAÇÃO E CONTACTOS DO ÓRGÃO DE RECURSOS ADMINISTRATIVOS\nDesignação: Câmara Municipal de Braga\nEndereço: Praça do Município\nCódigo postal: 4700-435\nLocalidade: Braga\nTelefone: +351 253616060\nFax: +351 253203151\nEndereço eletrónico: info@cm-braga.pt\n\n28 - IDENTIFICAÇÃO DO(S) AUTOR(ES) DE ANÚNCIO\nNome: Rita Gonçalves\nCargo: Técnica Superior\n419489536",
    "nipc": "506901173",
    "distrito": "Braga",
    "concelho": "Braga",
    "freguesia": "União das Freguesias de Braga (Maximinos, Sé e Cividade)",
    "site": "www.cm-braga.pt",
    "email": "contratacao.publica@cm-braga.pt",
    "designacao_contrato": "REPAVIMENTAÇÃO DA AVENIDA DE REQUEIXO",
    "descricao": "REPAVIMENTAÇÃO DA AVENIDA DE REQUEIXO",
    "preco_base": "618.991,93 EUR",
    "prazo_execucao": "120 DIAS",
    "prazo_apresentacao_propostas": "01-10-2025 18:00",
    "fundos_eu": "Não",
    "plataforma_eletronica": "VORTAL",
    "url_procedimento": "https://community.vortal.biz/public/",
    "autor_nome": "Rita Gonçalves",
    "autor_cargo": "Técnica Superior"
  },
  {
    "numero_procedimento": "N/A",
    "entidade": "Câmara Municipal de Matosinhos",
    "link": "https://diariodarepublica.pt/dr/detalhe/contrato-publico/23260-933891657",
    "detalhes_completos": "1 - IDENTIFICAÇÃO E CONTACTOS DA ENTIDADE ADJUDICANTE\nDesignação da entidade adjudicante: Câmara Municipal de Matosinhos\nNIPC: 501305912\nServiço/Órgão/Pessoa de contacto: Div. Contratação Pública\nEndereço: Av. D. Afonso Henriques\nCódigo postal: 4454-510\nLocalidade: Matosinhos\nPaís: Portugal\nNUT III: PT11A\nDistrito: Porto\nConcelho: Matosinhos\nFreguesia: Todas\nTelefone: 229390900\nFax: 229351645\nEndereço da Entidade (URL): http://www.cm-matosinhos.pt\nEndereço Eletrónico: contratacaopublica@cm-matosinhos.pt\neDelivery Gateway (URL): https://www.acingov.pt\nFunção da Organização: Adquirente\nSubfunção da Organização: Organização que recebe as propostas\nNorma jurídica da Entidade Adjudicante: Organismo de direito público\nÁrea de atividade da Autoridade Adjudicante: Serviços públicos das administrações públicas\n\n2 - JORNAL OFICIAL DA UNIÃO EUROPEIA\nO procedimento a que este anúncio diz respeito também é publicitado no Jornal Oficial da União Europeia? Não\n\n3 - AVISO\nModelo de Anúncio: Concurso público\nData de Envio do Anúncio: 01-09-2025\n\n5 - PROCESSO\nTipo de Procedimento: Concurso público\nPreço base do procedimento: Sim\nValor do preço base do procedimento: 43.419,20 EUR\nProcedimento com lotes? Não\n\n6 - OBJETO DO CONTRATO\nNúmero de referência interna: CP/68/2025 (EDOC/2025/27672)\nDesignação do contrato: AQUISIÇÃO DE SINALÉTICA INFORMATIVA PARA INSTALAÇÃO EM PARQUES DO CONCELHO\nDescrição: AQUISIÇÃO DE SINALÉTICA INFORMATIVA PARA INSTALAÇÃO EM PARQUES DO CONCELHO\nTipo de Contrato Principal: Aquisição de Bens Móveis\nTipo de Contrato: Aquisição de Bens Móveis\nClassificação CPV (Vocabulário Comum para os Contratos Públicos)\nObjeto principal\nVocabulário Principal: 34928000\nPreço base s/IVA: 43.419,20 EUR\n\n7 - INDICAÇÕES ADICIONAIS\nO contrato envolve aquisição conjunta (satisfação de várias entidades)? Não\nO contrato é adjudicado por uma central de compras? Não\n\n8 - TÉCNICAS\nO concurso destina-se à celebração de um acordo-quadro? Inexistência de acordo-quadro\nÉ utilizado um leilão eletrónico? Não\nÉ adotada uma fase de negociação? Não\nSistema de Aquisição Dinâmico: Inexistência de sistema de aquisição dinâmico\n\n9 - LOCAL DA EXECUÇÃO DO CONTRATO\nLOCAL DA EXECUÇÃO DO CONTRATO (PROCEDIMENTO)\nPaís: Portugal\nNUT III: PT11A\nLocalidade: Matosinhos\nDistrito: Porto\nConcelho: Matosinhos\nFreguesia: Todas\n\n10 - PRAZO DE EXECUÇÃO DO CONTRATO\nPrazo de execução do contrato: 60 DIAS\nPrevisão de renovações: Não\n\n11 - FUNDOS EU\nTêm fundos EU? Não\n\n12 - DOCUMENTOS DE HABILITAÇÃO\nHabilitação para o exercício da atividade profissional: Não\n\n13 - CONDIÇÕES DE APRESENTAÇÃO\nPlataforma eletrónica utilizada pela entidade adjudicante: ACIN\nURL para Apresentação: https://www.acingov.pt\nAdmissibilidade da apresentação de propostas variantes: Não autorizado\nPrazo para apresentação das propostas: 07-09-2025 23:59\nPrazo durante o qual os concorrentes são obrigados a manter as respetivas propostas: 66 dias a contar do termo do prazo para a apresentação das propostas\nIndicação de Subcontratação na Proposta: Inexistência de indicação de subcontratação\n\n14 - PRESTAÇÃO DE CAUÇÃO\nPrestação de caução: Não\n\n15 - FORNECIMENTO DAS PEÇAS DO CONCURSO, APRESENTAÇÃO DE PEDIDOS DE PARTICIPAÇÃO E APRESENTAÇÃO DAS PROPOSTAS\nLink para acesso às peças do concurso (URL): https://www.acingov.pt/acingovprod/2/zonaPublica/zona_publica_c/donwloadProcedurePiece/OTczMjI2\n\n20 - OUTROS REQUISITOS\nInformação sobre contratos reservados. Aplica-se a contratos reservados (54º-A)? Não\n\n21 - CRITÉRIO DE ADJUDICAÇÃO\nMultifator: Não\nMonofator:\nNome: Preço\n\n24 - CONDIÇÕES DO CONTRATO\nFaturação Eletrónica: Não autorizado\nObrigação de Subcontratação:\nCódigo da Obrigação de Subcontratação: Não é aplicável nenhuma obrigação de subcontratação.\n\n25 - COMPRA PÚBLICA ESTRATÉGICA\nCompra Pública Estratégica: Inexistência de contratação pública estratégica\n\n26 - INFORMAÇÕES ADICIONAIS\nContrato adequado para PME: Não\nCobertura ACP (Acordo dos Contratos Públicos da Organização Mundial do Comércio): Não\n\n27 - IDENTIFICAÇÃO E CONTACTOS DO ÓRGÃO DE RECURSOS ADMINISTRATIVOS\nDesignação: Câmara Municipal\nEndereço: Av. D Aonso Henriques\nCódigo postal: 4454-510\nLocalidade: Matosinhos\nTelefone: 229390900\nFax: \nEndereço eletrónico: contratacaopublica@cm-matosinhos.pt\nPrazo de interposição do recurso: 5 dias\n\n28 - IDENTIFICAÇÃO DO(S) AUTOR(ES) DE ANÚNCIO\nNome: Luísa Maria Neves Salgueiro \nCargo: Presidente da Câmara\n419480099",
    "nipc": "501305912",
    "distrito": "Porto",
    "concelho": "Matosinhos",
    "freguesia": "Todas",
    "site": "http://www.cm-matosinhos.pt",
    "email": "contratacaopublica@cm-matosinhos.pt",
    "designacao_contrato": "AQUISIÇÃO DE SINALÉTICA INFORMATIVA PARA INSTALAÇÃO EM PARQUES DO CONCELHO",
    "descricao": "AQUISIÇÃO DE SINALÉTICA INFORMATIVA PARA INSTALAÇÃO EM PARQUES DO CONCELHO",
    "preco_base": "43.419,20 EUR",
    "prazo_execucao": "60 DIAS",
    "prazo_apresentacao_propostas": "07-09-2025 23:59",
    "fundos_eu": "Não",
    "plataforma_eletronica": "ACIN",
    "url_procedimento": "https://www.acingov.pt",
    "autor_nome": "Luísa Maria Neves Salgueiro",
    "autor_cargo": "Presidente da Câmara"
  },
  {
    "numero_procedimento": "N/A",
    "entidade": "Unidade Local de Saúde do Alto Alentejo E.P.E",
    "link": "https://diariodarepublica.pt/dr/detalhe/contrato-publico/23261-933891658",
    "detalhes_completos": "Alteração do Anúncio de procedimento n.º 21205/2025, de 2025-08-06, com o ID 419407571\n\n1 - IDENTIFICAÇÃO E CONTACTOS DA ENTIDADE ADJUDICANTE\nDesignação da entidade adjudicante: Unidade Local de Saúde do Alto Alentejo E.P.E\nNIPC: 508094461\nEndereço: Av. De Santo António\nCódigo postal: 7300-853\nLocalidade: Portalegre\nPaís: Portugal\nNUT III: PT186\nDistrito: Portalegre\nConcelho: Portalegre\nFreguesia: União das Freguesias da Sé e São Lourenço\nTelefone: 245301000\nFax: 245301002\nEndereço da Entidade (URL): www.hportalegre.min-saude.pt\nEndereço Eletrónico: aprov.portalegre.elvas@ulsna.min-saude.pt\neDelivery Gateway (URL): https://community.vortal.biz/public/\nFunção da Organização: Adquirente\nNorma jurídica da Entidade Adjudicante: Empresa pública\nÁrea de atividade da Entidade Adjudicante: Atividades aeroportuárias\n\n2 - JORNAL OFICIAL DA UNIÃO EUROPEIA\nO procedimento a que este anúncio diz respeito também é publicitado no Jornal Oficial da União Europeia? Não\n\n3 - AVISO\nModelo de Anúncio: Concurso público\nData de Envio do Anúncio: 01-09-2025\n\n5 - PROCESSO\nTipo de Procedimento: Concurso público\nPreço base do procedimento: Sim\nValor do preço base do procedimento: 340.564,00 EUR\nProcedimento com lotes? Não\n\n6 - OBJETO DO CONTRATO\nNúmero de referência interna: 17102425\nDesignação do contrato: Requalificação do Centro de Saúde de Alter do Chão\nDescrição: Projeto N.º 11301 - Submedida i1.08 – Requalificar ou adaptar edifícios para aumentar a eficiência energética, cumprir planos de contingências e/ou assegurar a acessibilidade, a segurança e o conforto de utentes e profissionais, prevista no Plano de Recuperação e Resiliência Empreitada para Requalificação do Centro de Saúde de Alter do Chão da Unidade Local de Saúde do alto Alentejo, EPE \nTipo de Contrato Principal: Empreitada de Obras Públicas\nTipo de Contrato: Empreitada de Obras Públicas\nClassificação CPV (Vocabulário Comum para os Contratos Públicos)\nObjeto principal\nVocabulário Principal: 45454000\nPreço base s/IVA: 340.564,00 EUR\n\n7 - INDICAÇÕES ADICIONAIS\nO contrato envolve aquisição conjunta (satisfação de várias entidades)? Não\nO contrato é adjudicado por uma central de compras? Não\n\n8 - TÉCNICAS\nO concurso destina-se à celebração de um acordo-quadro? Inexistência de acordo-quadro\nÉ utilizado um leilão eletrónico? Não\nÉ adotada uma fase de negociação? Não\nSistema de Aquisição Dinâmico: Inexistência de sistema de aquisição dinâmico\n\n9 - LOCAL DA EXECUÇÃO DO CONTRATO\nLOCAL DA EXECUÇÃO DO CONTRATO (PROCEDIMENTO)\nPaís: Portugal\nNUT III: PT186\nLocalidade: Portalegre\nDistrito: Portalegre\nConcelho: Portalegre\nFreguesia: União das Freguesias da Sé e São Lourenço\n\n10 - PRAZO DE EXECUÇÃO DO CONTRATO\nPrazo de execução do contrato: 180 DIAS\nPrevisão de renovações: Não\n\n11 - FUNDOS EU\nTêm fundos EU? Sim\n\n12 - DOCUMENTOS DE HABILITAÇÃO\nHabilitação para o exercício da atividade profissional: Não\n\n13 - CONDIÇÕES DE APRESENTAÇÃO\nPlataforma eletrónica utilizada pela entidade adjudicante: VORTAL\nURL para Apresentação: https://community.vortal.biz/public/\nAdmissibilidade da apresentação de propostas variantes: Não autorizado\nPrazo para apresentação das propostas: 15-09-2025 23:59\nPrazo durante o qual os concorrentes são obrigados a manter as respetivas propostas: 180 dias a contar do termo do prazo para a apresentação das propostas\nApresentação de Catálogo Eletrónico: Permitido\nIndicação de Subcontratação na Proposta: Inexistência de indicação de subcontratação\n\n14 - PRESTAÇÃO DE CAUÇÃO\nPrestação de caução: Sim\nPercentagem: 5%\nDescrição da Garantia Exigida: Conforme definido nas peças do concurso\n\n15 - FORNECIMENTO DAS PEÇAS DO CONCURSO, APRESENTAÇÃO DE PEDIDOS DE PARTICIPAÇÃO E APRESENTAÇÃO DAS PROPOSTAS\nLink para acesso às peças do concurso (URL): https://community.vortal.biz/Public/public-tender-documents/RXFPYW96M3JjdUhaeE1vdDFLTEI0ZVlLdkJtRXJ4aDRoZ2N1aVdIdko1bG5ON0ltOC8rTlV1TVdra2NVUXFWcHRiWW82WXhnMGhadHlTNmpkbWg3dkE9PTIzZldZ\n\n20 - OUTROS REQUISITOS\nInformação sobre contratos reservados. Aplica-se a contratos reservados (54º-A)? Não\n\n21 - CRITÉRIO DE ADJUDICAÇÃO\nMultifator: Sim\nFator: \nNome: Preço\nPonderação: 70%\nSubfatores: Não\nFator: \nNome: Outros\nOutro Nome: Prazo Execução\nPonderação: 30%\nSubfatores: Não\n\n24 - CONDIÇÕES DO CONTRATO\nFaturação Eletrónica: Permitido\nObrigação de Subcontratação:\nCódigo da Obrigação de Subcontratação: Não é aplicável nenhuma obrigação de subcontratação.\n\n25 - COMPRA PÚBLICA ESTRATÉGICA\nCompra Pública Estratégica: Redução dos impactos ambientais\nDescrição do Processo de Adjudicação Estratégico: Conforme as peças do procedimento\nCritérios de contratos Públicos Ecológicos: Outros critérios de contratação pública ecológica\nCategorias da estratégia nacional: Conceção, construção e gestão de edifícios de escritórios\nDiretiva Veículos Não Poluentes: Não\nCritério de Acessibilidade: Os critérios de acessibilidade para as pessoas com deficiência não estão incluídos porque o contrato não se destina a pessoas singulares\n\n26 - INFORMAÇÕES ADICIONAIS\nContrato adequado para PME: Sim\nCobertura ACP (Acordo dos Contratos Públicos da Organização Mundial do Comércio): Não\n\n27 - IDENTIFICAÇÃO E CONTACTOS DO ÓRGÃO DE RECURSOS ADMINISTRATIVOS\nDesignação: Conselho de Administração\nEndereço: AVENIDA DE SANTO ANTÓNIO\nCódigo postal: 7300-853\nLocalidade: Portalegre\nTelefone: +351 245301000\nFax: +351 245303359\nEndereço eletrónico: admin@ulsaale.min-saude.pt\n\n28 - IDENTIFICAÇÃO DO(S) AUTOR(ES) DE ANÚNCIO\nNome: José Miguel da Costa Lopes\nCargo: Presidente do Conselho de Administração\n\n29 - ALTERAÇÃO\nMotivo da Alteração: Correção pelo adquirente\nIdentificador da Versão do Anúncio a Alterar: 8add43df-7662-4d66-8dcc-25b3f2ce5975-01\nIdentificador das Secções Alteradas do Anúncio Anterior: Condições de Apresentação\nDescrição das Alterações: Prorrogação do Prazo para Apresentação de Proposta\nAlteração dos Documentos do Concurso: Sim\nData de alteração dos documentos do concurso: 01-09-2025\n419487268",
    "nipc": "508094461",
    "distrito": "Portalegre",
    "concelho": "Portalegre",
    "freguesia": "União das Freguesias da Sé e São Lourenço",
    "site": "www.hportalegre.min-saude.pt",
    "email": "aprov.portalegre.elvas@ulsna.min-saude.pt",
    "designacao_contrato": "Requalificação do Centro de Saúde de Alter do Chão",
    "descricao": "Projeto N.º 11301 - Submedida i1.08 – Requalificar ou adaptar edifícios para aumentar a eficiência energética, cumprir planos de contingências e/ou assegurar a acessibilidade, a segurança e o conforto de utentes e profissionais, prevista no Plano de Recuperação e Resiliência Empreitada para Requalificação do Centro de Saúde de Alter do Chão da Unidade Local de Saúde do alto Alentejo, EPE",
    "preco_base": "340.564,00 EUR",
    "prazo_execucao": "180 DIAS",
    "prazo_apresentacao_propostas": "15-09-2025 23:59",
    "fundos_eu": "Sim",
    "plataforma_eletronica": "VORTAL",
    "url_procedimento": "https://community.vortal.biz/public/",
    "autor_nome": "José Miguel da Costa Lopes",
    "autor_cargo": "Presidente do Conselho de Administração"
  },
  {
    "numero_procedimento": "N/A",
    "entidade": "Unidade Local de Saúde do Alto Alentejo E.P.E",
    "link": "https://diariodarepublica.pt/dr/detalhe/contrato-publico/23262-933891659",
    "detalhes_completos": "1 - IDENTIFICAÇÃO E CONTACTOS DA ENTIDADE ADJUDICANTE\nDesignação da entidade adjudicante: Unidade Local de Saúde do Alto Alentejo E.P.E\nNIPC: 508094461\nEndereço: Av. De Santo António\nCódigo postal: 7300-853\nLocalidade: Portalegre\nPaís: Portugal\nNUT III: PT186\nDistrito: Portalegre\nConcelho: Portalegre\nFreguesia: União das Freguesias da Sé e São Lourenço\nTelefone: 245301000\nFax: 245301002\nEndereço da Entidade (URL): www.hportalegre.min-saude.pt\nEndereço Eletrónico: aprov.portalegre.elvas@ulsna.min-saude.pt\neDelivery Gateway (URL): https://community.vortal.biz/public/\nFunção da Organização: Adquirente\nNorma jurídica da Entidade Adjudicante: Empresa pública\nÁrea de atividade da Entidade Adjudicante: Atividades aeroportuárias\n\n2 - JORNAL OFICIAL DA UNIÃO EUROPEIA\nO procedimento a que este anúncio diz respeito também é publicitado no Jornal Oficial da União Europeia? Não\n\n3 - AVISO\nModelo de Anúncio: Concurso público\nData de Envio do Anúncio: 01-09-2025\n\n5 - PROCESSO\nTipo de Procedimento: Concurso público\nPreço base do procedimento: Sim\nValor do preço base do procedimento: 424.335,00 EUR\nProcedimento com lotes? Não\n\n6 - OBJETO DO CONTRATO\nNúmero de referência interna: 17103325\nDesignação do contrato: Projeto N.º 11314- Submedida i1.08 –Empreitada para Requalificação do Centro de Saúde de Sousel da Unidade Local de Saúde do Alto Alentejo, EPE.”\nDescrição: Projeto N.º 11314- Submedida i1.08 –Empreitada para Requalificação do Centro de Saúde de Sousel da Unidade Local de Saúde do Alto Alentejo, EPE.”\nTipo de Contrato Principal: Empreitada de Obras Públicas\nTipo de Contrato: Empreitada de Obras Públicas\nClassificação CPV (Vocabulário Comum para os Contratos Públicos)\nObjeto principal\nVocabulário Principal: 45454000\nPreço base s/IVA: 424.335,00 EUR\n\n7 - INDICAÇÕES ADICIONAIS\nO contrato envolve aquisição conjunta (satisfação de várias entidades)? Não\nO contrato é adjudicado por uma central de compras? Não\n\n8 - TÉCNICAS\nO concurso destina-se à celebração de um acordo-quadro? Inexistência de acordo-quadro\nÉ utilizado um leilão eletrónico? Não\nÉ adotada uma fase de negociação? Não\nSistema de Aquisição Dinâmico: Inexistência de sistema de aquisição dinâmico\n\n9 - LOCAL DA EXECUÇÃO DO CONTRATO\nLOCAL DA EXECUÇÃO DO CONTRATO (PROCEDIMENTO)\nPaís: Portugal\nNUT III: PT186\nLocalidade: Portalegre\nDistrito: Portalegre\nConcelho: Portalegre\nFreguesia: União das Freguesias da Sé e São Lourenço\n\n10 - PRAZO DE EXECUÇÃO DO CONTRATO\nPrazo de execução do contrato: 180 DIAS\nPrevisão de renovações: Não\n\n11 - FUNDOS EU\nTêm fundos EU? Sim\n\n12 - DOCUMENTOS DE HABILITAÇÃO\nHabilitação para o exercício da atividade profissional: Não\n\n13 - CONDIÇÕES DE APRESENTAÇÃO\nPlataforma eletrónica utilizada pela entidade adjudicante: VORTAL\nURL para Apresentação: https://community.vortal.biz/public/\nAdmissibilidade da apresentação de propostas variantes: Não autorizado\nPrazo para apresentação das propostas: 16-09-2025 18:00\nPrazo durante o qual os concorrentes são obrigados a manter as respetivas propostas: 180 dias a contar do termo do prazo para a apresentação das propostas\nIndicação de Subcontratação na Proposta: Inexistência de indicação de subcontratação\n\n14 - PRESTAÇÃO DE CAUÇÃO\nPrestação de caução: Sim\nPercentagem: 5%\nDescrição da Garantia Exigida: De acordo com o artigo 15.º do Programa de Concurso\n\n15 - FORNECIMENTO DAS PEÇAS DO CONCURSO, APRESENTAÇÃO DE PEDIDOS DE PARTICIPAÇÃO E APRESENTAÇÃO DAS PROPOSTAS\nLink para acesso às peças do concurso (URL): https://community.vortal.biz/Public/public-tender-documents/MGs2ZENZRU9DSDNOaFdWTlR6TnA4aDJmWHVKQ3VKVVNUU05LYk1WOHM4S25QN2Q3ODY0QVR4UUtuczF4Z2dUdlZkeGNNZXIraTNlRVJPbm5qc1pTWGc9PVZ5MyE3\n\n20 - OUTROS REQUISITOS\nInformação sobre contratos reservados. Aplica-se a contratos reservados (54º-A)? Não\n\n21 - CRITÉRIO DE ADJUDICAÇÃO\nMultifator: Sim\nFator: \nNome: Preço\nPonderação: 70%\nSubfatores: Não\nFator: \nNome: Qualidade\nPonderação: 30%\nSubfatores: Não\n\n24 - CONDIÇÕES DO CONTRATO\nFaturação Eletrónica: Permitido\nObrigação de Subcontratação:\nCódigo da Obrigação de Subcontratação: Não é aplicável nenhuma obrigação de subcontratação.\n\n25 - COMPRA PÚBLICA ESTRATÉGICA\nCompra Pública Estratégica: Redução dos impactos ambientais\nDescrição do Processo de Adjudicação Estratégico: Conforme as peças do procedimento\nCritérios de contratos Públicos Ecológicos: Critérios de contratação pública ecológica nacional\nCategorias da estratégia nacional: Conceção, construção e gestão de edifícios de escritórios\nDiretiva Veículos Não Poluentes: Não\nCritério de Acessibilidade: Os critérios de acessibilidade para as pessoas com deficiência não estão incluídos porque o contrato não se destina a pessoas singulares\n\n26 - INFORMAÇÕES ADICIONAIS\nContrato adequado para PME: Sim\nCobertura ACP (Acordo dos Contratos Públicos da Organização Mundial do Comércio): Não\n\n27 - IDENTIFICAÇÃO E CONTACTOS DO ÓRGÃO DE RECURSOS ADMINISTRATIVOS\nDesignação: Conselho de Administração\nEndereço: AVENIDA DE SANTO ANTONIO\nCódigo postal: 7300-853\nLocalidade: Portalegre\nTelefone: +351 245301000\nFax: +351 245330359\nEndereço eletrónico: admin@ulsaale.min-saude.pt\n\n28 - IDENTIFICAÇÃO DO(S) AUTOR(ES) DE ANÚNCIO\nNome: José Lopes\nCargo: Presidente do Conselho de Administração\n419490686",
    "nipc": "508094461",
    "distrito": "Portalegre",
    "concelho": "Portalegre",
    "freguesia": "União das Freguesias da Sé e São Lourenço",
    "site": "www.hportalegre.min-saude.pt",
    "email": "aprov.portalegre.elvas@ulsna.min-saude.pt",
    "designacao_contrato": "Projeto N.º 11314- Submedida i1.08 –Empreitada para Requalificação do Centro de Saúde de Sousel da Unidade Local de Saúde do Alto Alentejo, EPE.”",
    "descricao": "Projeto N.º 11314- Submedida i1.08 –Empreitada para Requalificação do Centro de Saúde de Sousel da Unidade Local de Saúde do Alto Alentejo, EPE.”",
    "preco_base": "424.335,00 EUR",
    "prazo_execucao": "180 DIAS",
    "prazo_apresentacao_propostas": "16-09-2025 18:00",
    "fundos_eu": "Sim",
    "plataforma_eletronica": "VORTAL",
    "url_procedimento": "https://community.vortal.biz/public/",
    "autor_nome": "José Lopes",
    "autor_cargo": "Presidente do Conselho de Administração"
  },
  {
    "numero_procedimento": "N/A",
    "entidade": "AnÃºncio de procedimento  n.Âº 23264/2025  -  DiÃ¡rio da RepÃºblica n.Âº 168/2025, SÃ©rie II de 2025-09-02",
    "link": "https://diariodarepublica.pt/dr/detalhe/contrato-publico/23264-933891660"
  }
]