[
  {
    "numero_procedimento": "N/A",
    "entidade": "Inframoura, E.M.",
    "link": "https://diariodarepublica.pt/dr/detalhe/contrato-publico/25857-937591436",
    "detalhes_completos": "1 - IDENTIFICAÇÃO E CONTACTOS DA ENTIDADE ADJUDICANTE\nDesignação da entidade adjudicante: Inframoura, E.M.\nNIPC: 504915266\nServiço/Órgão/Pessoa de contacto: Conselho de Adminsitração da Inframoura, E.M.\nEndereço: Rua das Amoreiras, Vilamoura\nCódigo postal: 8125-497\nLocalidade: Faro\nPaís: Portugal\nNUT III: PT150\nDistrito: Faro\nConcelho: Loulé\nFreguesia: Freguesia de Quarteira\nTelefone: 289310650\nEndereço da Entidade (URL): www.inframoura.pt\nEndereço Eletrónico: info@inframoura.pt\neDelivery Gateway (URL): https://community.vortal.biz/public/\nFunção da Organização: Adquirente\nNorma jurídica da Entidade Adjudicante: Autoridade local\nÁrea de atividade da Autoridade Adjudicante: Serviços públicos das administrações públicas\n\n2 - JORNAL OFICIAL DA UNIÃO EUROPEIA\nO procedimento a que este anúncio diz respeito também é publicitado no Jornal Oficial da União Europeia? Não\n\n3 - AVISO\nModelo de Anúncio: Concurso público\nData de Envio do Anúncio: 01-10-2025\n\n5 - PROCESSO\nTipo de Procedimento: Concurso público\nPreço base do procedimento: Sim\nValor do preço base do procedimento: 71.000,00 EUR\nProcedimento com lotes? Não\n\n6 - OBJETO DO CONTRATO\nNúmero de referência interna: PPC17/2025_BS/DR \nDesignação do contrato: PPC17/2025_BS/DR - Aquisição de contentores de recolha de resíduos\nDescrição: PPC17/2025_BS/DR - Aquisição de contentores de recolha de resíduos\nTipo de Contrato Principal: Aquisição de Bens Móveis\nTipo de Contrato: Aquisição de Bens Móveis\nClassificação CPV (Vocabulário Comum para os Contratos Públicos)\nObjeto principal\nVocabulário Principal: 44613300\nPreço base s/IVA: 71.000,00 EUR\n\n7 - INDICAÇÕES ADICIONAIS\nO contrato envolve aquisição conjunta (satisfação de várias entidades)? Não\nO contrato é adjudicado por uma central de compras? Não\n\n8 - TÉCNICAS\nO concurso destina-se à celebração de um acordo-quadro? Inexistência de acordo-quadro\nÉ utilizado um leilão eletrónico? Não\nÉ adotada uma fase de negociação? Não\nSistema de Aquisição Dinâmico: Inexistência de sistema de aquisição dinâmico\n\n9 - LOCAL DA EXECUÇÃO DO CONTRATO\nLOCAL DA EXECUÇÃO DO CONTRATO (PROCEDIMENTO)\nPaís: Portugal\nNUT III: PT150\nLocalidade: Faro\nDistrito: Faro\nConcelho: Loulé\nFreguesia: Freguesia de Quarteira\n\n10 - PRAZO DE EXECUÇÃO DO CONTRATO\nPrazo de execução do contrato: 30 DIAS\nPrevisão de renovações: Não\n\n11 - FUNDOS EU\nTêm fundos EU? Não\n\n12 - DOCUMENTOS DE HABILITAÇÃO\nHabilitação para o exercício da atividade profissional: Sim\nTipo: Outros\nDescrição - Outros: .\nDescrição: Não aplicável\n\n13 - CONDIÇÕES DE APRESENTAÇÃO\nPlataforma eletrónica utilizada pela entidade adjudicante: VORTAL\nURL para Apresentação: https://community.vortal.biz/public/\nAdmissibilidade da apresentação de propostas variantes: Não autorizado\nPrazo para apresentação das propostas: 10-10-2025 17:00\nPrazo durante o qual os concorrentes são obrigados a manter as respetivas propostas: 66 dias a contar do termo do prazo para a apresentação das propostas\nIndicação de Subcontratação na Proposta: Inexistência de indicação de subcontratação\n\n14 - PRESTAÇÃO DE CAUÇÃO\nPrestação de caução: Não\n\n15 - FORNECIMENTO DAS PEÇAS DO CONCURSO, APRESENTAÇÃO DE PEDIDOS DE PARTICIPAÇÃO E APRESENTAÇÃO DAS PROPOSTAS\nLink para acesso às peças do concurso (URL): https://community.vortal.biz/Public/public-tender-documents/ZCtCUWFWbHNucmF2QzNMK2JKdms5UXBwWWFROHkxcEhzaE1CcnJ6TVNoZEhwSmsxVkdNRXI4aHZYN25iL3hVV1VFS3N3SmR6anh5bm8raWo5MTZKcnc9PUFVZWZM\n\n20 - OUTROS REQUISITOS\nInformação sobre contratos reservados. Aplica-se a contratos reservados (54º-A)? Não\n\n21 - CRITÉRIO DE ADJUDICAÇÃO\nMultifator: Não\nMonofator:\nNome: Outros\nOutro nome: Preço\n\n24 - CONDIÇÕES DO CONTRATO\nFaturação Eletrónica: Permitido\nObrigação de Subcontratação:\nCódigo da Obrigação de Subcontratação: Não é aplicável nenhuma obrigação de subcontratação.\n\n25 - COMPRA PÚBLICA ESTRATÉGICA\nCompra Pública Estratégica: Inexistência de contratação pública estratégica\n\n26 - INFORMAÇÕES ADICIONAIS\nContrato adequado para PME: Sim\nCobertura ACP (Acordo dos Contratos Públicos da Organização Mundial do Comércio): Não\n\n27 - IDENTIFICAÇÃO E CONTACTOS DO ÓRGÃO DE RECURSOS ADMINISTRATIVOS\nDesignação: Conselho de Administração da Inframoura- Empresa de Infraestruturas de Vilamoura, E.M.\nEndereço: Rua das Amoreiras\nCódigo postal: 8125-497\nLocalidade: Loulé\nTelefone: +351 289310650\nFax: +351 289310650\nEndereço eletrónico: info@inframoura.pt\n\n28 - IDENTIFICAÇÃO DO(S) AUTOR(ES) DE ANÚNCIO\nNome: Jorge Aleixo Ramos\nCargo: Presidente do Conselho de Administração da Inframoura E.M.\n419599064",
    "nipc": "504915266",
    "distrito": "Faro",
    "concelho": "Loulé",
    "freguesia": "Freguesia de Quarteira",
    "site": "www.inframoura.pt",
    "email": "info@inframoura.pt",
    "designacao_contrato": "PPC17/2025_BS/DR - Aquisição de contentores de recolha de resíduos",
    "descricao": "PPC17/2025_BS/DR - Aquisição de contentores de recolha de resíduos",
    "preco_base": "71.000,00 EUR",
    "prazo_execucao": "30 DIAS",
    "prazo_apresentacao_propostas": "10-10-2025 17:00",
    "fundos_eu": "Não",
    "plataforma_eletronica": "VORTAL",
    "url_procedimento": "https://community.vortal.biz/public/",
    "autor_nome": "Jorge Aleixo Ramos",
    "autor_cargo": "Presidente do Conselho de Administração da Inframoura E.M."
  },
  {
    "numero_procedimento": "N/A",
    "entidade": "Secretaria-Geral do MAI",
    "link": "https://diariodarepublica.pt/dr/detalhe/contrato-publico/25859-937591437",
    "detalhes_completos": "1 - IDENTIFICAÇÃO E CONTACTOS DA ENTIDADE ADJUDICANTE\nDesignação da entidade adjudicante: Secretaria-Geral do MAI\nNIPC: 600014665\nEndereço: Rua São Mamede, 23\nCódigo postal: 1100-523\nLocalidade: Lisboa\nPaís: Portugal\nNUT III: PT170\nDistrito: Lisboa\nConcelho: Lisboa\nFreguesia: Freguesia de Santa Maria Maior - Lisboa\nTelefone: 213409000\nFax: 213409010\nEndereço da Entidade (URL): www.sg.mai.gov.pt/\nEndereço Eletrónico: gab.sec.geral@sg.mai.gov.pt\neDelivery Gateway (URL): https://community.vortal.biz/public/\nFunção da Organização: Adquirente\nNorma jurídica da Entidade Adjudicante: Autoridade da administração central\nÁrea de atividade da Autoridade Adjudicante: Serviços públicos das administrações públicas\n\n2 - JORNAL OFICIAL DA UNIÃO EUROPEIA\nO procedimento a que este anúncio diz respeito também é publicitado no Jornal Oficial da União Europeia? Sim\n\n3 - AVISO\nModelo de Anúncio: Concurso público\nData de Envio do Anúncio: 29-09-2025\n\n5 - PROCESSO\nTipo de Procedimento: Concurso público\nPreço base do procedimento: Não\nProcedimento com lotes? Sim\nNº Máx. de Lotes Autorizado: 6\nNúmero máximo de lotes que podem ser adjudicados a um concorrente: 6\n\n6 - OBJETO DO CONTRATO\nNúmero de referência interna: Proc. 24/DPIE/2025 Cópia\nDesignação do contrato: Proc. 24_DPIE_2025 - Aquisição de Cinemómetros para GNR e PSP, para os anos 2025 e 2026, no âmbito do DLPIEFSS.\nDescrição: Proc. 24_DPIE_2025 - Aquisição de Cinemómetros para GNR e PSP, para os anos 2025 e 2026, no âmbito do DLPIEFSS.\nOpções: Não\nTipo de Contrato Principal: Aquisição de Bens Móveis\nTipo de Contrato: Aquisição de Bens Móveis\nClassificação CPV (Vocabulário Comum para os Contratos Públicos)\nObjeto principal\nVocabulário Principal: 35100000\nLotes: \nNº: LOT-0001\nDescrição do Lote: Lote 1 - Cinemómetro RADAR para GNR\nClassificação CPV (Vocabulário Comum para os Contratos Públicos)\nObjeto principal\nVocabulário Principal: 35100000\nNº: LOT-0002\nDescrição do Lote: Lote 2 - Cinemómetro laser (Lidar) para GNR\nClassificação CPV (Vocabulário Comum para os Contratos Públicos)\nObjeto principal\nVocabulário Principal: 35100000\nNº: LOT-0003\nDescrição do Lote: Lote 3 - Cinemómetro laser portátil para GNR\nClassificação CPV (Vocabulário Comum para os Contratos Públicos)\nObjeto principal\nVocabulário Principal: 35100000\nNº: LOT-0004\nDescrição do Lote: Lote 4 -Cinemómetro de perseguição para GNR \nClassificação CPV (Vocabulário Comum para os Contratos Públicos)\nObjeto principal\nVocabulário Principal: 35100000\nNº: LOT-0005\nDescrição do Lote: Lote 5 -Radares de controlo de velocidade para PSP\nClassificação CPV (Vocabulário Comum para os Contratos Públicos)\nObjeto principal\nVocabulário Principal: 35100000\nNº: LOT-0006\nDescrição do Lote: Lote 6 - Radares de perseguição para PSP\nClassificação CPV (Vocabulário Comum para os Contratos Públicos)\nObjeto principal\nVocabulário Principal: 35100000\n\n7 - INDICAÇÕES ADICIONAIS\nO contrato envolve aquisição conjunta (satisfação de várias entidades)? Não\nO contrato é adjudicado por uma central de compras? Não\n\n8 - TÉCNICAS\nO concurso destina-se à celebração de um acordo-quadro? Inexistência de acordo-quadro\nÉ utilizado um leilão eletrónico? Não\nÉ adotada uma fase de negociação? Não\nSistema de Aquisição Dinâmico: Inexistência de sistema de aquisição dinâmico\n\n9 - LOCAL DA EXECUÇÃO DO CONTRATO\nLOCAL DA EXECUÇÃO DO CONTRATO (PROCEDIMENTO)\nPaís: Portugal\nNUT III: PT170\nLocalidade: Lisboa\nDistrito: Lisboa\nConcelho: Lisboa\nFreguesia: Todas\nLOCAL DA EXECUÇÃO DO CONTRATO (LOTE)\nIdentificador do Lote: LOT-0001; LOT-0002; LOT-0003; LOT-0004; LOT-0005; LOT-0006\nPaís: Portugal\nNUT III: PT170\nLocalidade: Lisboa\nDistrito: Lisboa\nConcelho: Lisboa\nFreguesia: Todas\n\n10 - PRAZO DE EXECUÇÃO DO CONTRATO\nIdentificador do Lote: LOT-0001; LOT-0002; LOT-0003; LOT-0004; LOT-0005; LOT-0006\nPrazo de execução do contrato: 60 DIAS\nPrevisão de renovações: Não\n\n11 - FUNDOS EU\nIdentificador do Lote: LOT-0001; LOT-0002; LOT-0003; LOT-0004; LOT-0005; LOT-0006\nTêm fundos EU? Não\n\n12 - DOCUMENTOS DE HABILITAÇÃO\nHabilitação para o exercício da atividade profissional: Não\n\n13 - CONDIÇÕES DE APRESENTAÇÃO\nPlataforma eletrónica utilizada pela entidade adjudicante: VORTAL\nURL para Apresentação: https://community.vortal.biz/public/\nAdmissibilidade da apresentação de propostas variantes: Não autorizado\nPrazo para apresentação das propostas: 03-11-2025 23:59\nPrazo durante o qual os concorrentes são obrigados a manter as respetivas propostas: 99 dias a contar do termo do prazo para a apresentação das propostas\nApresentação de Catálogo Eletrónico: Permitido\nIndicação de Subcontratação na Proposta: Inexistência de indicação de subcontratação\n\n14 - PRESTAÇÃO DE CAUÇÃO\nPrestação de caução: Sim\nPercentagem: 5%\nDescrição da Garantia Exigida: De acordo com o artigo 19º do programa do procedimento\n\n15 - FORNECIMENTO DAS PEÇAS DO CONCURSO, APRESENTAÇÃO DE PEDIDOS DE PARTICIPAÇÃO E APRESENTAÇÃO DAS PROPOSTAS\nLink para acesso às peças do concurso (URL): https://community.vortal.biz/Public/public-tender-documents/VGIrMzZ3ZS9CcDV4SFhpQUg0N3BKL2l2MDE5eFVjOTltNHZ0NTlSLzNTT0c4WDRkUjh0ZDJMQkZjOExsRk4wbU5GNEtXQUFkUnUwNjFyK1h0djRTMWc9PWZMK1pp\n\n20 - OUTROS REQUISITOS\nIdentificador do Lote: LOT-0001; LOT-0002; LOT-0003; LOT-0004; LOT-0005; LOT-0006\nInformação sobre contratos reservados. Aplica-se a contratos reservados (54º-A)? Não\n\n21 - CRITÉRIO DE ADJUDICAÇÃO\nO Critério de adjudicação é diferenciado por lote? Não\nMultifator: Sim\nFator: \nNome: Preço\nPonderação: 80%\nSubfatores: Não\nFator: \nNome: Qualidade\nPonderação: 20%\nSubfatores: Não\n\n24 - CONDIÇÕES DO CONTRATO\nIdentificador do Lote: LOT-0001; LOT-0002; LOT-0003; LOT-0004; LOT-0005; LOT-0006\nFaturação Eletrónica: Permitido\nObrigação de Subcontratação:\nCódigo da Obrigação de Subcontratação: Não é aplicável nenhuma obrigação de subcontratação.\n\n25 - COMPRA PÚBLICA ESTRATÉGICA\nCompra Pública Estratégica: Inexistência de contratação pública estratégica\n\n26 - INFORMAÇÕES ADICIONAIS\nIdentificador do Lote: LOT-0001; LOT-0002; LOT-0003; LOT-0004; LOT-0005; LOT-0006\nContrato adequado para PME: Sim\nCobertura ACP (Acordo dos Contratos Públicos da Organização Mundial do Comércio): Não\n\n27 - IDENTIFICAÇÃO E CONTACTOS DO ÓRGÃO DE RECURSOS ADMINISTRATIVOS\nDesignação: Ministério da Administração Interna\nEndereço: Praça do Comércio - Ala Oriental\nCódigo postal: 1149-015\nLocalidade: Lisboa\nTelefone: +351 213409081\nFax: +351 213409081\nEndereço eletrónico: dpie@sg.mai.gov.pt\n\n28 - IDENTIFICAÇÃO DO(S) AUTOR(ES) DE ANÚNCIO\nNome: Ricardo Carrilho\nCargo: Secretário Geral do Ministério da Administração Interna\n419589011",
    "nipc": "600014665",
    "distrito": "Lisboa",
    "concelho": "Lisboa",
    "freguesia": "Freguesia de Santa Maria Maior - Lisboa",
    "site": "www.sg.mai.gov.pt/",
    "email": "gab.sec.geral@sg.mai.gov.pt",
    "designacao_contrato": "Proc. 24_DPIE_2025 - Aquisição de Cinemómetros para GNR e PSP, para os anos 2025 e 2026, no âmbito do DLPIEFSS.",
    "descricao": "Proc. 24_DPIE_2025 - Aquisição de Cinemómetros para GNR e PSP, para os anos 2025 e 2026, no âmbito do DLPIEFSS.",
    "preco_base": null,
    "prazo_execucao": "60 DIAS",
    "prazo_apresentacao_propostas": "03-11-2025 23:59",
    "fundos_eu": "Não",
    "plataforma_eletronica": "VORTAL",
    "url_procedimento": "https://community.vortal.biz/public/",
    "autor_nome": "Ricardo Carrilho",
    "autor_cargo": "Secretário Geral do Ministério da Administração Interna"
  },
  {
    "numero_procedimento": "N/A",
    "entidade": "Unidade Local de Saúde do Alentejo Central, E.P.E",
    "link": "https://diariodarepublica.pt/dr/detalhe/contrato-publico/25861-937591438",
    "detalhes_completos": "1 - IDENTIFICAÇÃO E CONTACTOS DA ENTIDADE ADJUDICANTE\nDesignação da entidade adjudicante: Unidade Local de Saúde do Alentejo Central, E.P.E\nNIPC: 508085888\nEndereço: Largo Sr. da Pobreza\nCódigo postal: 7000-811\nLocalidade: Évora\nPaís: Portugal\nNUT III: PT187\nDistrito: Évora\nConcelho: Évora\nFreguesia: Todas\nTelefone: 266740111\nFax: 266744212\nEndereço da Entidade (URL): www.hevora.min-saude.pt\nEndereço Eletrónico: concursos.aprov@ulsac.min-saude.pt\neDelivery Gateway (URL): https://community.vortal.biz/public/\nFunção da Organização: Adquirente\nNorma jurídica da Entidade Adjudicante: Organismo de direito público\nÁrea de atividade da Autoridade Adjudicante: Saúde\n\n2 - JORNAL OFICIAL DA UNIÃO EUROPEIA\nO procedimento a que este anúncio diz respeito também é publicitado no Jornal Oficial da União Europeia? Sim\n\n3 - AVISO\nModelo de Anúncio: Concurso público\nData de Envio do Anúncio: 29-09-2025\n\n5 - PROCESSO\nTipo de Procedimento: Concurso público\nPreço base do procedimento: Sim\nValor do preço base do procedimento: 623.135,40 EUR\nProcedimento com lotes? Sim\nNº Máx. de Lotes Autorizado: 2\nNúmero máximo de lotes que podem ser adjudicados a um concorrente: 2\n\n6 - OBJETO DO CONTRATO\nNúmero de referência interna: 120028/26\nDesignação do contrato: Aquisição de Próteses Totais da Anca \nDescrição: Aquisição de Próteses Totais da Anca (não cimentadas, não cimentadas “standard”, cimentadas, cimentadas “standard”, dupla mobilidade cimentada, dupla mobilidade não cimentada, biarticular cimentada e biarticular não cimentada)\nOpções: Não\nTipo de Contrato Principal: Aquisição de Bens Móveis\nTipo de Contrato: Aquisição de Bens Móveis\nClassificação CPV (Vocabulário Comum para os Contratos Públicos)\nObjeto principal\nVocabulário Principal: 33183200\nPreço base s/IVA: 623.135,40 EUR\nLotes: \nNº: LOT-0001\nDescrição do Lote: Lote 1\nPreço base s/IVA: 566.135,40 EUR\nClassificação CPV (Vocabulário Comum para os Contratos Públicos)\nObjeto principal\nVocabulário Principal: 33183200\nNº: LOT-0002\nDescrição do Lote: Lote 2\nPreço base s/IVA: 57.000,00 EUR\nClassificação CPV (Vocabulário Comum para os Contratos Públicos)\nObjeto principal\nVocabulário Principal: 33183200\n\n7 - INDICAÇÕES ADICIONAIS\nO contrato envolve aquisição conjunta (satisfação de várias entidades)? Não\nO contrato é adjudicado por uma central de compras? Não\n\n8 - TÉCNICAS\nO concurso destina-se à celebração de um acordo-quadro? Inexistência de acordo-quadro\nÉ utilizado um leilão eletrónico? Não\nÉ adotada uma fase de negociação? Não\nSistema de Aquisição Dinâmico: Inexistência de sistema de aquisição dinâmico\n\n9 - LOCAL DA EXECUÇÃO DO CONTRATO\nLOCAL DA EXECUÇÃO DO CONTRATO (PROCEDIMENTO)\nPaís: Portugal\nNUT III: PT187\nLocalidade: Évora\nDistrito: Évora\nConcelho: Évora\nFreguesia: União das Freguesias de Évora (São Mamede, Sé, São Pedro e Santo Antão)\nLOCAL DA EXECUÇÃO DO CONTRATO (LOTE)\nIdentificador do Lote: LOT-0001; LOT-0002\nPaís: Portugal\nNUT III: PT187\nLocalidade: Évora\nDistrito: Évora\nConcelho: Évora\nFreguesia: União das Freguesias de Évora (São Mamede, Sé, São Pedro e Santo Antão)\n\n10 - PRAZO DE EXECUÇÃO DO CONTRATO\nIdentificador do Lote: LOT-0001; LOT-0002\nPrazo de execução do contrato: 36 MESES\nPrevisão de renovações: Sim\nIndicar número máximo de renovações: 2\nPrazo de renovações diferente do prazo inicial: Não\n\n11 - FUNDOS EU\nIdentificador do Lote: LOT-0001; LOT-0002\nTêm fundos EU? Não\n\n12 - DOCUMENTOS DE HABILITAÇÃO\nHabilitação para o exercício da atividade profissional: Não\n\n13 - CONDIÇÕES DE APRESENTAÇÃO\nPlataforma eletrónica utilizada pela entidade adjudicante: VORTAL\nURL para Apresentação: https://community.vortal.biz/public/\nAdmissibilidade da apresentação de propostas variantes: Não autorizado\nPrazo para apresentação das propostas: 29-10-2025 18:00\nPrazo durante o qual os concorrentes são obrigados a manter as respetivas propostas: 120 dias a contar do termo do prazo para a apresentação das propostas\nApresentação de Catálogo Eletrónico: Permitido\nIndicação de Subcontratação na Proposta: Inexistência de indicação de subcontratação\n\n14 - PRESTAÇÃO DE CAUÇÃO\nPrestação de caução: Sim\nPercentagem: 5%\nDescrição da Garantia Exigida: Garantia Bancária\n\n15 - FORNECIMENTO DAS PEÇAS DO CONCURSO, APRESENTAÇÃO DE PEDIDOS DE PARTICIPAÇÃO E APRESENTAÇÃO DAS PROPOSTAS\nLink para acesso às peças do concurso (URL): https://community.vortal.biz/Public/public-tender-documents/ZVdmbXpFbVJrQXdEVzNnOEp2cEVhdGYvenRGOURxeXZxWnVrMU9vTzRGKzROOUxGaGJDaUFIZzZxdUMzei9sRFIyTU56VXdvb3JuU24wUzdJb0hFM2c9PUc3TjRZ\n\n20 - OUTROS REQUISITOS\nIdentificador do Lote: LOT-0001; LOT-0002\nInformação sobre contratos reservados. Aplica-se a contratos reservados (54º-A)? Não\n\n21 - CRITÉRIO DE ADJUDICAÇÃO\nO Critério de adjudicação é diferenciado por lote? Sim\nIdentificador do lote: LOT-0001\nMultifator: Sim\nFator: \nNome: Preço\nPonderação: 50%\nSubfatores: Não\nFator: \nNome: Qualidade\nPonderação: 50%\nSubfatores: Não\nO Critério de adjudicação é diferenciado por lote? Sim\nIdentificador do lote: LOT-0002\nMultifator: Sim\nFator: \nNome: Qualidade\nPonderação: 80%\nSubfatores: Não\nFator: \nNome: Qualidade\nPonderação: 20%\nSubfatores: Não\n\n24 - CONDIÇÕES DO CONTRATO\nIdentificador do Lote: LOT-0001; LOT-0002\nFaturação Eletrónica: Permitido\nObrigação de Subcontratação:\nCódigo da Obrigação de Subcontratação: Não é aplicável nenhuma obrigação de subcontratação.\n\n25 - COMPRA PÚBLICA ESTRATÉGICA\nCompra Pública Estratégica: Inexistência de contratação pública estratégica\n\n26 - INFORMAÇÕES ADICIONAIS\nIdentificador do Lote: LOT-0001; LOT-0002\nContrato adequado para PME: Sim\nCobertura ACP (Acordo dos Contratos Públicos da Organização Mundial do Comércio): Não\n\n27 - IDENTIFICAÇÃO E CONTACTOS DO ÓRGÃO DE RECURSOS ADMINISTRATIVOS\nDesignação: Unidade Local de Saúde do Alentejo Central, E.P.E.\nEndereço: Largo Sr. de Pobreza\nCódigo postal: 7000-811\nLocalidade: Évora\nTelefone: +351 266740111\nFax: +351 266744212\nEndereço eletrónico: concursos.aprov@ulsac.min-saude.pt\n\n28 - IDENTIFICAÇÃO DO(S) AUTOR(ES) DE ANÚNCIO\nNome: Vitor Rui Gomes Fialho\nCargo: Presidente do Conselho de Administração\n419587773",
    "nipc": "508085888",
    "distrito": "Évora",
    "concelho": "Évora",
    "freguesia": "Todas",
    "site": "www.hevora.min-saude.pt",
    "email": "concursos.aprov@ulsac.min-saude.pt",
    "designacao_contrato": "Aquisição de Próteses Totais da Anca",
    "descricao": "Aquisição de Próteses Totais da Anca (não cimentadas, não cimentadas “standard”, cimentadas, cimentadas “standard”, dupla mobilidade cimentada, dupla mobilidade não cimentada, biarticular cimentada e biarticular não cimentada)",
    "preco_base": "623.135,40 EUR",
    "prazo_execucao": "36 MESES",
    "prazo_apresentacao_propostas": "29-10-2025 18:00",
    "fundos_eu": "Não",
    "plataforma_eletronica": "VORTAL",
    "url_procedimento": "https://community.vortal.biz/public/",
    "autor_nome": "Vitor Rui Gomes Fialho",
    "autor_cargo": "Presidente do Conselho de Administração"
  },
  {
    "numero_procedimento": "N/A",
    "entidade": "Infraestruturas de Portugal",
    "link": "https://diariodarepublica.pt/dr/detalhe/contrato-publico/25862-937591439",
    "detalhes_completos": "1 - IDENTIFICAÇÃO E CONTACTOS DA ENTIDADE ADJUDICANTE\nDesignação da entidade adjudicante: Infraestruturas de Portugal\nNIPC: 503933813\nServiço/Órgão/Pessoa de contacto: Direção de Compras e Logística - Departamento de Compras - Edifício 2\nEndereço: Praça da Portagem\nCódigo postal: 2809-013\nLocalidade: Almada\nPaís: Portugal\nNUT III: PT170\nDistrito: Setúbal\nConcelho: Almada\nFreguesia: União das Freguesias de Almada, Cova da Piedade, Pragal e Cacilhas\nTelefone:  212 879 300 \nFax: 21 287 90 00\nEndereço da Entidade (URL): www.infraestruturasdeportugal.pt\nEndereço Eletrónico: dcl@infraestruturasdeportugal.pt\nFunção da Organização: Adquirente\nNorma jurídica da Entidade Adjudicante: Organismo de direito público\nÁrea de atividade da Entidade Adjudicante: Serviços ferroviários\n\n2 - JORNAL OFICIAL DA UNIÃO EUROPEIA\nO procedimento a que este anúncio diz respeito também é publicitado no Jornal Oficial da União Europeia? Não\n\n3 - AVISO\nModelo de Anúncio: Concurso público\nData de Envio do Anúncio: 01-10-2025\n\n5 - PROCESSO\nTipo de Procedimento: Concurso público\nPreço base do procedimento: Sim\nValor do preço base do procedimento: 37.700,00 EUR\nProcedimento com lotes? Não\n\n6 - OBJETO DO CONTRATO\nNúmero de referência interna: 10021233\nDesignação do contrato: Aquisição de aferrolhamento completo para VCC Tg 0,0728\nDescrição: Aquisição de aferrolhamento completo para VCC Tg 0,0728\nTipo de Contrato Principal: Aquisição de Bens Móveis\nTipo de Contrato: Aquisição de Bens Móveis\nClassificação CPV (Vocabulário Comum para os Contratos Públicos)\nObjeto principal\nVocabulário Principal: 34946120\nPreço base s/IVA: 37.700,00 EUR\n\n7 - INDICAÇÕES ADICIONAIS\nO contrato envolve aquisição conjunta (satisfação de várias entidades)? Não\nO contrato é adjudicado por uma central de compras? Não\n\n8 - TÉCNICAS\nO concurso destina-se à celebração de um acordo-quadro? Inexistência de acordo-quadro\nÉ utilizado um leilão eletrónico? Não\nÉ adotada uma fase de negociação? Não\nSistema de Aquisição Dinâmico: Inexistência de sistema de aquisição dinâmico\n\n9 - LOCAL DA EXECUÇÃO DO CONTRATO\nLOCAL DA EXECUÇÃO DO CONTRATO (PROCEDIMENTO)\nPaís: Portugal\nNUT III: PT16I\nLocalidade: Entroncamento\nDistrito: Santarém\nConcelho: Entroncamento\nFreguesia: Freguesia de Nossa Senhora de Fátima - Entroncamento\n\n10 - PRAZO DE EXECUÇÃO DO CONTRATO\nPrazo de execução do contrato: 180 DIAS\nPrevisão de renovações: Não\n\n11 - FUNDOS EU\nTêm fundos EU? Não\n\n12 - DOCUMENTOS DE HABILITAÇÃO\nHabilitação para o exercício da atividade profissional: Não\n\n13 - CONDIÇÕES DE APRESENTAÇÃO\nPlataforma eletrónica utilizada pela entidade adjudicante: ANOGOV\nURL para Apresentação: https://www.anogov.com/infraestruturasdeportugal-ip/faces/\nAdmissibilidade da apresentação de propostas variantes: Não autorizado\nPrazo para apresentação das propostas: 31-10-2025 17:00\nPrazo durante o qual os concorrentes são obrigados a manter as respetivas propostas: 120 dias a contar do termo do prazo para a apresentação das propostas\nApresentação de Catálogo Eletrónico: Necessário\nIndicação de Subcontratação na Proposta: A parte do contrato que o proponente tenciona subcontratar\n\n14 - PRESTAÇÃO DE CAUÇÃO\nPrestação de caução: Não\n\n15 - FORNECIMENTO DAS PEÇAS DO CONCURSO, APRESENTAÇÃO DE PEDIDOS DE PARTICIPAÇÃO E APRESENTAÇÃO DAS PROPOSTAS\nLink para acesso às peças do concurso (URL): https://www.anogov.com/infraestruturasdeportugal-ip/faces/app/acessoDocs.jsp?codigoAcesso=0cTPC7E0VcsPRTvwyq0IwNLVofJQ7i0CmUI0WMe7PCt9y7Henx\n\n20 - OUTROS REQUISITOS\nInformação sobre contratos reservados. Aplica-se a contratos reservados (54º-A)? Não\n\n21 - CRITÉRIO DE ADJUDICAÇÃO\nMultifator: Não\nMonofator:\nNome: Preço\n\n24 - CONDIÇÕES DO CONTRATO\nFaturação Eletrónica: Necessário\nObrigação de Subcontratação:\nCódigo da Obrigação de Subcontratação: Não é aplicável nenhuma obrigação de subcontratação.\n\n25 - COMPRA PÚBLICA ESTRATÉGICA\nCompra Pública Estratégica: Inexistência de contratação pública estratégica\n\n26 - INFORMAÇÕES ADICIONAIS\nContrato adequado para PME: Não\nCobertura ACP (Acordo dos Contratos Públicos da Organização Mundial do Comércio): Não\n\n27 - IDENTIFICAÇÃO E CONTACTOS DO ÓRGÃO DE RECURSOS ADMINISTRATIVOS\nDesignação: Conselho de Administração Executivo da Infraestruturas de Portugal, S.A.\nEndereço: Praça da Portagem\nCódigo postal: 2809-013\nLocalidade: Almada\nEndereço eletrónico: dcl@infraestruturasdeportugal.pt\n\n28 - IDENTIFICAÇÃO DO(S) AUTOR(ES) DE ANÚNCIO\nNome: Margarida Veloso\nCargo: Diretora de Compras\n419599518",
    "nipc": "503933813",
    "distrito": "Setúbal",
    "concelho": "Almada",
    "freguesia": "União das Freguesias de Almada, Cova da Piedade, Pragal e Cacilhas",
    "site": "www.infraestruturasdeportugal.pt",
    "email": "dcl@infraestruturasdeportugal.pt",
    "designacao_contrato": "Aquisição de aferrolhamento completo para VCC Tg 0,0728",
    "descricao": "Aquisição de aferrolhamento completo para VCC Tg 0,0728",
    "preco_base": "37.700,00 EUR",
    "prazo_execucao": "180 DIAS",
    "prazo_apresentacao_propostas": "31-10-2025 17:00",
    "fundos_eu": "Não",
    "plataforma_eletronica": "ANOGOV",
    "url_procedimento": "https://www.anogov.com/infraestruturasdeportugal-ip/faces/",
    "autor_nome": "Margarida Veloso",
    "autor_cargo": "Diretora de Compras"
  },
  {
    "numero_procedimento": "N/A",
    "entidade": "WEMOB - E.M., S.A.",
    "link": "https://diariodarepublica.pt/dr/detalhe/contrato-publico/25866-937591440",
    "detalhes_completos": "1 - IDENTIFICAÇÃO E CONTACTOS DA ENTIDADE ADJUDICANTE\nDesignação da entidade adjudicante: WEMOB - E.M., S.A.\nNIPC: 507001206\nEndereço: Rua Sociedade Filarmónica Incrível Almadense, 5 e 7, RC\nCódigo postal: 2800-208\nLocalidade: Setúbal\nPaís: Portugal\nNUT III: PT170\nDistrito: Setúbal\nConcelho: Almada\nFreguesia: Todas\nTelefone: 212743918\nFax: 212743919\nEndereço Eletrónico: concursospublicos@wemob.pt\neDelivery Gateway (URL): https://community.vortal.biz/public/\nFunção da Organização: Adquirente\nNorma jurídica da Entidade Adjudicante: Autoridade da administração central\nÁrea de atividade da Autoridade Adjudicante: Serviços públicos das administrações públicas\n\n2 - JORNAL OFICIAL DA UNIÃO EUROPEIA\nO procedimento a que este anúncio diz respeito também é publicitado no Jornal Oficial da União Europeia? Não\n\n3 - AVISO\nModelo de Anúncio: Concurso público\nData de Envio do Anúncio: 01-10-2025\n\n5 - PROCESSO\nTipo de Procedimento: Concurso público\nPreço base do procedimento: Sim\nValor do preço base do procedimento: 33.588,00 EUR\nProcedimento com lotes? Não\n\n6 - OBJETO DO CONTRATO\nNúmero de referência interna: CP34/2025\nDesignação do contrato: FORNECIMENTO E GESTÃO DE LICENÇAS MICROSOFT\nDescrição: FORNECIMENTO E GESTÃO DE LICENÇAS MICROSOFT\nTipo de Contrato Principal: Aquisição de Bens Móveis\nTipo de Contrato: Aquisição de Bens Móveis\nClassificação CPV (Vocabulário Comum para os Contratos Públicos)\nObjeto principal\nVocabulário Principal: 48620000\nPreço base s/IVA: 33.588,00 EUR\n\n7 - INDICAÇÕES ADICIONAIS\nO contrato envolve aquisição conjunta (satisfação de várias entidades)? Não\nO contrato é adjudicado por uma central de compras? Não\n\n8 - TÉCNICAS\nO concurso destina-se à celebração de um acordo-quadro? Inexistência de acordo-quadro\nÉ utilizado um leilão eletrónico? Não\nÉ adotada uma fase de negociação? Não\nSistema de Aquisição Dinâmico: Inexistência de sistema de aquisição dinâmico\n\n9 - LOCAL DA EXECUÇÃO DO CONTRATO\nLOCAL DA EXECUÇÃO DO CONTRATO (PROCEDIMENTO)\nPaís: Portugal\nNUT III: PT170\nLocalidade: Setúbal\nDistrito: Setúbal\nConcelho: Almada\nFreguesia: Todas\n\n10 - PRAZO DE EXECUÇÃO DO CONTRATO\nPrazo de execução do contrato: 24 MESES\nPrevisão de renovações: Não\n\n11 - FUNDOS EU\nTêm fundos EU? Não\n\n12 - DOCUMENTOS DE HABILITAÇÃO\nHabilitação para o exercício da atividade profissional: Não\n\n13 - CONDIÇÕES DE APRESENTAÇÃO\nPlataforma eletrónica utilizada pela entidade adjudicante: VORTAL\nURL para Apresentação: https://community.vortal.biz/public/\nAdmissibilidade da apresentação de propostas variantes: Não autorizado\nPrazo para apresentação das propostas: 07-10-2025 23:59\nPrazo durante o qual os concorrentes são obrigados a manter as respetivas propostas: 90 dias a contar do termo do prazo para a apresentação das propostas\nIndicação de Subcontratação na Proposta: Inexistência de indicação de subcontratação\n\n14 - PRESTAÇÃO DE CAUÇÃO\nPrestação de caução: Não\n\n15 - FORNECIMENTO DAS PEÇAS DO CONCURSO, APRESENTAÇÃO DE PEDIDOS DE PARTICIPAÇÃO E APRESENTAÇÃO DAS PROPOSTAS\nLink para acesso às peças do concurso (URL): https://community.vortal.biz/Public/public-tender-documents/V3VqSEx6Z2hYRGlickllcnZXVlhzNXRZQzJMdWhnRmNBWmxITVdXcDVTK0NTNHRYRWo0bVoxOWNOU2dYVGFBZ0haWDZKOTZtQ2J0K3hmZ2ZlY2RCNEE9PWUhYlkm\n\n20 - OUTROS REQUISITOS\nInformação sobre contratos reservados. Aplica-se a contratos reservados (54º-A)? Não\n\n21 - CRITÉRIO DE ADJUDICAÇÃO\nMultifator: Não\nMonofator:\nNome: Preço\n\n24 - CONDIÇÕES DO CONTRATO\nFaturação Eletrónica: Permitido\nObrigação de Subcontratação:\nCódigo da Obrigação de Subcontratação: Não é aplicável nenhuma obrigação de subcontratação.\n\n25 - COMPRA PÚBLICA ESTRATÉGICA\nCompra Pública Estratégica: Inexistência de contratação pública estratégica\n\n26 - INFORMAÇÕES ADICIONAIS\nContrato adequado para PME: Sim\nCobertura ACP (Acordo dos Contratos Públicos da Organização Mundial do Comércio): Não\n\n27 - IDENTIFICAÇÃO E CONTACTOS DO ÓRGÃO DE RECURSOS ADMINISTRATIVOS\nDesignação: Conselho de Administração\nEndereço: Rua Sociedade Filarmónica Incrível Almadense, 5 e 7, RC\nCódigo postal: 2800-208\nLocalidade: Almada\nTelefone: +351 212743918\nFax: +351 212743219\nEndereço eletrónico: concursospubliccos@wemob.pt\n\n28 - IDENTIFICAÇÃO DO(S) AUTOR(ES) DE ANÚNCIO\nNome: Luisa Ferreira\nCargo: Presidente do Conselho de Administração\n419598384",
    "nipc": "507001206",
    "distrito": "Setúbal",
    "concelho": "Almada",
    "freguesia": "Todas",
    "site": null,
    "email": "concursospublicos@wemob.pt",
    "designacao_contrato": "FORNECIMENTO E GESTÃO DE LICENÇAS MICROSOFT",
    "descricao": "FORNECIMENTO E GESTÃO DE LICENÇAS MICROSOFT",
    "preco_base": "33.588,00 EUR",
    "prazo_execucao": "24 MESES",
    "prazo_apresentacao_propostas": "07-10-2025 23:59",
    "fundos_eu": "Não",
    "plataforma_eletronica": "VORTAL",
    "url_procedimento": "https://community.vortal.biz/public/",
    "autor_nome": "Luisa Ferreira",
    "autor_cargo": "Presidente do Conselho de Administração"
  },
  {
    "numero_procedimento": "N/A",
    "entidade": "Município de Gouveia",
    "link": "https://diariodarepublica.pt/dr/detalhe/contrato-publico/25868-937591441",
    "detalhes_completos": "1 - IDENTIFICAÇÃO E CONTACTOS DA ENTIDADE ADJUDICANTE\nDesignação da entidade adjudicante: Município de Gouveia\nNIPC: 506510476\nEndereço: Av. 25 De Abril\nCódigo postal: 6290-554\nLocalidade: Guarda\nPaís: Portugal\nNUT III: PT16J\nDistrito: Guarda\nConcelho: Gouveia\nFreguesia: Freguesia de Gouveia - Gouveia\nTelefone: 238490210\nFax: 238494686\nEndereço da Entidade (URL): www.cm-gouveia.pt\nEndereço Eletrónico: aprovisionamento@cm-gouveia.pt\neDelivery Gateway (URL): https://community.vortal.biz/public/\nFunção da Organização: Adquirente\nNorma jurídica da Entidade Adjudicante: Autoridade local\nÁrea de atividade da Autoridade Adjudicante: Serviços públicos das administrações públicas\n\n2 - JORNAL OFICIAL DA UNIÃO EUROPEIA\nO procedimento a que este anúncio diz respeito também é publicitado no Jornal Oficial da União Europeia? Não\n\n3 - AVISO\nModelo de Anúncio: Concurso público\nData de Envio do Anúncio: 01-10-2025\n\n5 - PROCESSO\nTipo de Procedimento: Concurso público\nPreço base do procedimento: Sim\nValor do preço base do procedimento: 948.533,61 EUR\nProcedimento com lotes? Não\n\n6 - OBJETO DO CONTRATO\nNúmero de referência interna: 37GVA/2025\nDesignação do contrato: CASA DO TERRITÓRIO - CENTRO INTERPRETATIVO DA IDENTIDADE E MEMÓRIA\nDescrição: CASA DO TERRITÓRIO - CENTRO INTERPRETATIVO DA IDENTIDADE E MEMÓRIA\nTipo de Contrato Principal: Empreitada de Obras Públicas\nTipo de Contrato: Empreitada de Obras Públicas\nClassificação CPV (Vocabulário Comum para os Contratos Públicos)\nObjeto principal\nVocabulário Principal: 45262690\nPreço base s/IVA: 948.533,61 EUR\n\n7 - INDICAÇÕES ADICIONAIS\nO contrato envolve aquisição conjunta (satisfação de várias entidades)? Não\nO contrato é adjudicado por uma central de compras? Não\n\n8 - TÉCNICAS\nO concurso destina-se à celebração de um acordo-quadro? Inexistência de acordo-quadro\nÉ utilizado um leilão eletrónico? Não\nÉ adotada uma fase de negociação? Não\nSistema de Aquisição Dinâmico: Inexistência de sistema de aquisição dinâmico\n\n9 - LOCAL DA EXECUÇÃO DO CONTRATO\nLOCAL DA EXECUÇÃO DO CONTRATO (PROCEDIMENTO)\nPaís: Portugal\nNUT III: PT16J\nLocalidade: Guarda\nDistrito: Guarda\nConcelho: Gouveia\nFreguesia: Todas\n\n10 - PRAZO DE EXECUÇÃO DO CONTRATO\nPrazo de execução do contrato: 480 DIAS\nPrevisão de renovações: Não\n\n11 - FUNDOS EU\nTêm fundos EU? Não\n\n12 - DOCUMENTOS DE HABILITAÇÃO\nHabilitação para o exercício da atividade profissional: Não\n\n13 - CONDIÇÕES DE APRESENTAÇÃO\nPlataforma eletrónica utilizada pela entidade adjudicante: VORTAL\nURL para Apresentação: https://community.vortal.biz/public/\nAdmissibilidade da apresentação de propostas variantes: Não autorizado\nPrazo para apresentação das propostas: 20-10-2025 17:30\nPrazo durante o qual os concorrentes são obrigados a manter as respetivas propostas: 150 dias a contar do termo do prazo para a apresentação das propostas\nIndicação de Subcontratação na Proposta: Inexistência de indicação de subcontratação\n\n14 - PRESTAÇÃO DE CAUÇÃO\nPrestação de caução: Não\n\n15 - FORNECIMENTO DAS PEÇAS DO CONCURSO, APRESENTAÇÃO DE PEDIDOS DE PARTICIPAÇÃO E APRESENTAÇÃO DAS PROPOSTAS\nLink para acesso às peças do concurso (URL): https://community.vortal.biz/Public/public-tender-documents/bGVjQ2JPR25SRkRVUDFsM3V1N3UzeHgyaGc5VVBnMzE3VEwzQjNNbzNQUzZxOWd1N3NLK3AxdGMwMCtoN3A0bXp2VXAzOW5TWTMvcGJzdTU3WndXQ1E9PSRKISRP\n\n20 - OUTROS REQUISITOS\nInformação sobre contratos reservados. Aplica-se a contratos reservados (54º-A)? Não\n\n21 - CRITÉRIO DE ADJUDICAÇÃO\nMultifator: Sim\nFator: \nNome: Preço\nPonderação: 80%\nSubfatores: Não\nFator: \nNome: Qualidade\nPonderação: 20%\nSubfatores: Não\n\n24 - CONDIÇÕES DO CONTRATO\nFaturação Eletrónica: Permitido\nObrigação de Subcontratação:\nCódigo da Obrigação de Subcontratação: Não é aplicável nenhuma obrigação de subcontratação.\n\n25 - COMPRA PÚBLICA ESTRATÉGICA\nCompra Pública Estratégica: Inexistência de contratação pública estratégica\n\n26 - INFORMAÇÕES ADICIONAIS\nContrato adequado para PME: Sim\nCobertura ACP (Acordo dos Contratos Públicos da Organização Mundial do Comércio): Não\n\n27 - IDENTIFICAÇÃO E CONTACTOS DO ÓRGÃO DE RECURSOS ADMINISTRATIVOS\nDesignação: Câmara Municipal de Gouveia\nEndereço: Av. 25 de Abril\nCódigo postal: 6290-554\nLocalidade: Gouveia\nTelefone: +351 238490210\nFax: +351 000000000\nEndereço eletrónico: geral@cm-gouveia.pt\n\n28 - IDENTIFICAÇÃO DO(S) AUTOR(ES) DE ANÚNCIO\nNome: Dr. Luis Manuel Tadeu Marques\nCargo: Presidente da Câmara Municipal \n419592502",
    "nipc": "506510476",
    "distrito": "Guarda",
    "concelho": "Gouveia",
    "freguesia": "Freguesia de Gouveia - Gouveia",
    "site": "www.cm-gouveia.pt",
    "email": "aprovisionamento@cm-gouveia.pt",
    "designacao_contrato": "CASA DO TERRITÓRIO - CENTRO INTERPRETATIVO DA IDENTIDADE E MEMÓRIA",
    "descricao": "CASA DO TERRITÓRIO - CENTRO INTERPRETATIVO DA IDENTIDADE E MEMÓRIA",
    "preco_base": "948.533,61 EUR",
    "prazo_execucao": "480 DIAS",
    "prazo_apresentacao_propostas": "20-10-2025 17:30",
    "fundos_eu": "Não",
    "plataforma_eletronica": "VORTAL",
    "url_procedimento": "https://community.vortal.biz/public/",
    "autor_nome": "Dr. Luis Manuel Tadeu Marques",
    "autor_cargo": "Presidente da Câmara Municipal"
  },
  {
    "numero_procedimento": "N/A",
    "entidade": "Serviços Municipalizados de Água e Saneamento Câmara Municipal Leiria",
    "link": "https://diariodarepublica.pt/dr/detalhe/contrato-publico/25869-937591442",
    "detalhes_completos": "1 - IDENTIFICAÇÃO E CONTACTOS DA ENTIDADE ADJUDICANTE\nDesignação da entidade adjudicante: Serviços Municipalizados de Água e Saneamento Câmara Municipal Leiria\nNIPC: 680017550\nEndereço: Rua da Cooperativa, 65 C  São Romão\nCódigo postal: 2410-256\nLocalidade: Leiria\nPaís: Portugal\nNUT III: PT16F\nDistrito: Leiria\nConcelho: Leiria\nFreguesia: União das Freguesias de Leiria, Pousos, Barreira e Cortes\nTelefone: 244817300\nEndereço da Entidade (URL): https://www.smas-leiria.pt/\nEndereço Eletrónico: geral@smas-leiria.pt\neDelivery Gateway (URL): https://community.vortal.biz/public/\nFunção da Organização: Adquirente\nNorma jurídica da Entidade Adjudicante: Organismo de direito público\nÁrea de atividade da Autoridade Adjudicante: Serviços públicos das administrações públicas\n\n2 - JORNAL OFICIAL DA UNIÃO EUROPEIA\nO procedimento a que este anúncio diz respeito também é publicitado no Jornal Oficial da União Europeia? Não\n\n3 - AVISO\nModelo de Anúncio: Concurso público\nData de Envio do Anúncio: 01-10-2025\n\n5 - PROCESSO\nTipo de Procedimento: Concurso público\nPreço base do procedimento: Sim\nValor do preço base do procedimento: 9.000,00 EUR\nProcedimento com lotes? Não\n\n6 - OBJETO DO CONTRATO\nNúmero de referência interna: 271/CPN/B/25\nDesignação do contrato: Aquisição de Material de Informática (Periféricos), em regime de Fornecimento Contínuo\nDescrição: Aquisição de Material de Informática (Periféricos), em regime de Fornecimento Contínuo\nTipo de Contrato Principal: Aquisição de Bens Móveis\nTipo de Contrato: Aquisição de Bens Móveis\nClassificação CPV (Vocabulário Comum para os Contratos Públicos)\nObjeto principal\nVocabulário Principal: 30200000\nPreço base s/IVA: 9.000,00 EUR\n\n7 - INDICAÇÕES ADICIONAIS\nO contrato envolve aquisição conjunta (satisfação de várias entidades)? Não\nO contrato é adjudicado por uma central de compras? Não\n\n8 - TÉCNICAS\nO concurso destina-se à celebração de um acordo-quadro? Inexistência de acordo-quadro\nÉ utilizado um leilão eletrónico? Não\nÉ adotada uma fase de negociação? Não\nSistema de Aquisição Dinâmico: Inexistência de sistema de aquisição dinâmico\n\n9 - LOCAL DA EXECUÇÃO DO CONTRATO\nLOCAL DA EXECUÇÃO DO CONTRATO (PROCEDIMENTO)\nPaís: Portugal\nNUT III: PT16F\nLocalidade: Leiria\nDistrito: Leiria\nConcelho: Leiria\nFreguesia: União das Freguesias de Leiria, Pousos, Barreira e Cortes\n\n10 - PRAZO DE EXECUÇÃO DO CONTRATO\nPrazo de execução do contrato: 12 MESES\nPrevisão de renovações: Não\n\n11 - FUNDOS EU\nTêm fundos EU? Não\n\n12 - DOCUMENTOS DE HABILITAÇÃO\nHabilitação para o exercício da atividade profissional: Não\n\n13 - CONDIÇÕES DE APRESENTAÇÃO\nPlataforma eletrónica utilizada pela entidade adjudicante: VORTAL\nURL para Apresentação: https://community.vortal.biz/public/\nAdmissibilidade da apresentação de propostas variantes: Não autorizado\nPrazo para apresentação das propostas: 13-10-2025 15:00\nPrazo durante o qual os concorrentes são obrigados a manter as respetivas propostas: 90 dias a contar do termo do prazo para a apresentação das propostas\nIndicação de Subcontratação na Proposta: Inexistência de indicação de subcontratação\n\n14 - PRESTAÇÃO DE CAUÇÃO\nPrestação de caução: Não\n\n15 - FORNECIMENTO DAS PEÇAS DO CONCURSO, APRESENTAÇÃO DE PEDIDOS DE PARTICIPAÇÃO E APRESENTAÇÃO DAS PROPOSTAS\nLink para acesso às peças do concurso (URL): https://community.vortal.biz/Public/public-tender-documents/ZXlqaTNOeHJtcVJ1M1dUNTZOUFdmS3F1U0RnbUNrcFliaXJXQXh5K20yN0ZBSkp0T3AzNDNPS0pzTDdoRTNvVy96MmIwZFBZL2R1ZnlYSTlLcXU5d2c9PXlpSHEz\n\n20 - OUTROS REQUISITOS\nInformação sobre contratos reservados. Aplica-se a contratos reservados (54º-A)? Não\n\n21 - CRITÉRIO DE ADJUDICAÇÃO\nMultifator: Não\nMonofator:\nNome: Outros\nOutro nome: Preço\n\n24 - CONDIÇÕES DO CONTRATO\nFaturação Eletrónica: Permitido\nObrigação de Subcontratação:\nCódigo da Obrigação de Subcontratação: Não é aplicável nenhuma obrigação de subcontratação.\n\n25 - COMPRA PÚBLICA ESTRATÉGICA\nCompra Pública Estratégica: Inexistência de contratação pública estratégica\n\n26 - INFORMAÇÕES ADICIONAIS\nContrato adequado para PME: Sim\nCobertura ACP (Acordo dos Contratos Públicos da Organização Mundial do Comércio): Não\n\n27 - IDENTIFICAÇÃO E CONTACTOS DO ÓRGÃO DE RECURSOS ADMINISTRATIVOS\nDesignação: Tribunal Administrativo e Fiscal de Leiria\nEndereço: R. João Paulo II 258, Leiria\nCódigo postal: 2440-112\nLocalidade: Leiria\nTelefone: +351 244870600\nFax: +351 213506006\nEndereço eletrónico: leiria.taf@tribunais.org.pt\n\n28 - IDENTIFICAÇÃO DO(S) AUTOR(ES) DE ANÚNCIO\nNome: Leandro Miguel Gomes de Sousa\nCargo: Diretor Delegado dos SMAS de Leiria\n419599907",
    "nipc": "680017550",
    "distrito": "Leiria",
    "concelho": "Leiria",
    "freguesia": "União das Freguesias de Leiria, Pousos, Barreira e Cortes",
    "site": "https://www.smas-leiria.pt/",
    "email": "geral@smas-leiria.pt",
    "designacao_contrato": "Aquisição de Material de Informática (Periféricos), em regime de Fornecimento Contínuo",
    "descricao": "Aquisição de Material de Informática (Periféricos), em regime de Fornecimento Contínuo",
    "preco_base": "9.000,00 EUR",
    "prazo_execucao": "12 MESES",
    "prazo_apresentacao_propostas": "13-10-2025 15:00",
    "fundos_eu": "Não",
    "plataforma_eletronica": "VORTAL",
    "url_procedimento": "https://community.vortal.biz/public/",
    "autor_nome": "Leandro Miguel Gomes de Sousa",
    "autor_cargo": "Diretor Delegado dos SMAS de Leiria"
  },
  {
    "numero_procedimento": "N/A",
    "entidade": "ORDEM DOS ADVOGADOS",
    "link": "https://diariodarepublica.pt/dr/detalhe/contrato-publico/25858-937614429",
    "detalhes_completos": "Alteração do Anúncio de procedimento n.º 23738/2025, de 2025-09-08, com o ID 419506886\n\n1 - IDENTIFICAÇÃO E CONTACTOS DA ENTIDADE ADJUDICANTE\nDesignação da entidade adjudicante: ORDEM DOS ADVOGADOS\nNIPC: 500965099\nEndereço: Lg.  S.Domingos Nr. 14 1º\nCódigo postal: 1050-000\nLocalidade: Lisboa\nPaís: Portugal\nNUT III: PT170\nDistrito: Lisboa\nConcelho: Lisboa\nFreguesia: Todas\nTelefone: 218823550\nFax: 218862403\nEndereço da Entidade (URL): https://portal.oa.pt/\nEndereço Eletrónico: cons.geral@cg.oa.pt\neDelivery Gateway (URL): https://community.vortal.biz/public/\nFunção da Organização: Adquirente\nNorma jurídica da Entidade Adjudicante: Autoridade da administração central\nÁrea de atividade da Autoridade Adjudicante: Serviços públicos das administrações públicas\n\n2 - JORNAL OFICIAL DA UNIÃO EUROPEIA\nO procedimento a que este anúncio diz respeito também é publicitado no Jornal Oficial da União Europeia? Sim\n\n3 - AVISO\nModelo de Anúncio: Concurso público\nData de Envio do Anúncio: 29-09-2025\n\n5 - PROCESSO\nTipo de Procedimento: Concurso público\nPreço base do procedimento: Sim\nValor do preço base do procedimento: 462.420,00 EUR\nProcedimento com lotes? Não\n\n6 - OBJETO DO CONTRATO\nNúmero de referência interna: CNI489/OA/2025_Fornecimento de Serviços de Email \nDesignação do contrato: CNI489/OA/2025_ Fornecimento de Serviços de Email para os Advogados\nDescrição: CNI489/OA/2025_ Fornecimento de Serviços de Email para os Advogados\n\nOpções: Não\nTipo de Contrato Principal: Aquisição de Serviços\nTipo de Contrato: Aquisição de Serviços\nClassificação CPV (Vocabulário Comum para os Contratos Públicos)\nObjeto principal\nVocabulário Principal: 72412000\nPreço base s/IVA: 462.420,00 EUR\n\n7 - INDICAÇÕES ADICIONAIS\nO contrato envolve aquisição conjunta (satisfação de várias entidades)? Não\nO contrato é adjudicado por uma central de compras? Não\n\n8 - TÉCNICAS\nO concurso destina-se à celebração de um acordo-quadro? Inexistência de acordo-quadro\nÉ utilizado um leilão eletrónico? Não\nÉ adotada uma fase de negociação? Não\nSistema de Aquisição Dinâmico: Inexistência de sistema de aquisição dinâmico\n\n9 - LOCAL DA EXECUÇÃO DO CONTRATO\nLOCAL DA EXECUÇÃO DO CONTRATO (PROCEDIMENTO)\nPaís: Portugal\nNUT III: PT170\nLocalidade: Lisboa\nDistrito: Lisboa\nConcelho: Lisboa\nFreguesia: Todas\n\n10 - PRAZO DE EXECUÇÃO DO CONTRATO\nPrazo de execução do contrato: 38 MESES\nPrevisão de renovações: Não\n\n11 - FUNDOS EU\nTêm fundos EU? Não\n\n12 - DOCUMENTOS DE HABILITAÇÃO\nHabilitação para o exercício da atividade profissional: Não\n\n13 - CONDIÇÕES DE APRESENTAÇÃO\nPlataforma eletrónica utilizada pela entidade adjudicante: VORTAL\nURL para Apresentação: https://community.vortal.biz/public/\nAdmissibilidade da apresentação de propostas variantes: Não autorizado\nPrazo para apresentação das propostas: 13-10-2025 23:59\nPrazo durante o qual os concorrentes são obrigados a manter as respetivas propostas: 66 dias a contar do termo do prazo para a apresentação das propostas\nApresentação de Catálogo Eletrónico: Não autorizado\nIndicação de Subcontratação na Proposta: Inexistência de indicação de subcontratação\n\n14 - PRESTAÇÃO DE CAUÇÃO\nPrestação de caução: Não\n\n15 - FORNECIMENTO DAS PEÇAS DO CONCURSO, APRESENTAÇÃO DE PEDIDOS DE PARTICIPAÇÃO E APRESENTAÇÃO DAS PROPOSTAS\nLink para acesso às peças do concurso (URL): https://community.vortal.biz/Public/public-tender-documents/WHJoVGRwNUJJajlXeVZTMHVkR21yamVJNmR3RUp4NVJzQlZvUlY2ZWl3eUpyWGFxV0JwQkVmWGpnU3daWDBZSHRaWDJ3OUcvajVJbk1ZK0djaS83WVE9PTkhR0A0\n\n20 - OUTROS REQUISITOS\nInformação sobre contratos reservados. Aplica-se a contratos reservados (54º-A)? Não\n\n21 - CRITÉRIO DE ADJUDICAÇÃO\nMultifator: Não\nMonofator:\nNome: Outros\nOutro nome: Critério de avaliação multifator\n\n24 - CONDIÇÕES DO CONTRATO\nFaturação Eletrónica: Permitido\nObrigação de Subcontratação:\nCódigo da Obrigação de Subcontratação: Não é aplicável nenhuma obrigação de subcontratação.\n\n25 - COMPRA PÚBLICA ESTRATÉGICA\nCompra Pública Estratégica: Inexistência de contratação pública estratégica\n\n26 - INFORMAÇÕES ADICIONAIS\nContrato adequado para PME: Sim\nCobertura ACP (Acordo dos Contratos Públicos da Organização Mundial do Comércio): Não\n\n27 - IDENTIFICAÇÃO E CONTACTOS DO ÓRGÃO DE RECURSOS ADMINISTRATIVOS\nDesignação: Presidente do Conselho Geral da Ordem dos Advogados\nEndereço: Largo de S. Domingos\nCódigo postal: 1169-060\nLocalidade: Lisboa\nTelefone: +351 218823550\nFax: +351 218862403\nEndereço eletrónico: gab.bastonaria@cg.oa.pt\n\n28 - IDENTIFICAÇÃO DO(S) AUTOR(ES) DE ANÚNCIO\nNome: Ana Rola\nCargo: Serviço de compras Conselho Geral da Ordem dos Advogados\n\n29 - ALTERAÇÃO\nMotivo da Alteração: Correção pelo adquirente\nIdentificador da Versão do Anúncio a Alterar: 5f8b9e5c-7aaa-468e-90db-9bcab844f9f3-01\nIdentificador das Secções Alteradas do Anúncio Anterior: Alteração\nAlteração dos Documentos do Concurso: Não\n419586874",
    "nipc": "500965099",
    "distrito": "Lisboa",
    "concelho": "Lisboa",
    "freguesia": "Todas",
    "site": "https://portal.oa.pt/",
    "email": "cons.geral@cg.oa.pt",
    "designacao_contrato": "CNI489/OA/2025_ Fornecimento de Serviços de Email para os Advogados",
    "descricao": "CNI489/OA/2025_ Fornecimento de Serviços de Email para os Advogados",
    "preco_base": "462.420,00 EUR",
    "prazo_execucao": "38 MESES",
    "prazo_apresentacao_propostas": "13-10-2025 23:59",
    "fundos_eu": "Não",
    "plataforma_eletronica": "VORTAL",
    "url_procedimento": "https://community.vortal.biz/public/",
    "autor_nome": "Ana Rola",
    "autor_cargo": "Serviço de compras Conselho Geral da Ordem dos Advogados"
  },
  {
    "numero_procedimento": "N/A",
    "entidade": "Município de Odemira",
    "link": "https://diariodarepublica.pt/dr/detalhe/contrato-publico/25860-937614430",
    "detalhes_completos": "1 - IDENTIFICAÇÃO E CONTACTOS DA ENTIDADE ADJUDICANTE\nDesignação da entidade adjudicante: Município de Odemira\nNIPC: 505311313\nServiço/Órgão/Pessoa de contacto: Divisão Financeira e de Contratação Pública \nEndereço: Praça da República\nCódigo postal: 7630-139\nLocalidade: Beja\nPaís: Portugal\nNUT III: PT181\nDistrito: Beja\nConcelho: Odemira\nFreguesia: Freguesia de São Salvador e Santa Maria\nTelefone: 283320900\nFax: 283327323\nEndereço da Entidade (URL): www.cm-odemira.pt\nEndereço Eletrónico: geral@cm-odemira.pt\neDelivery Gateway (URL): https://community.vortal.biz/public/\nFunção da Organização: Adquirente\nNorma jurídica da Entidade Adjudicante: Organismo de direito público, controlado por uma autoridade local\nÁrea de atividade da Autoridade Adjudicante: Serviços públicos das administrações públicas\n\n2 - JORNAL OFICIAL DA UNIÃO EUROPEIA\nO procedimento a que este anúncio diz respeito também é publicitado no Jornal Oficial da União Europeia? Não\n\n3 - AVISO\nModelo de Anúncio: Concurso público\nData de Envio do Anúncio: 01-10-2025\n\n5 - PROCESSO\nTipo de Procedimento: Concurso público\nPreço base do procedimento: Sim\nValor do preço base do procedimento: 147.971,00 EUR\nProcedimento com lotes? Sim\nNº Máx. de Lotes Autorizado: 2\nNúmero máximo de lotes que podem ser adjudicados a um concorrente: 2\n\n6 - OBJETO DO CONTRATO\nNúmero de referência interna: CMO/1545/CPN/B/25\nDesignação do contrato: AQUISIÇÃO DE EQUIPAMENTO TECNOLÓGICO PARA O BAIRRO COMERCIAL DIGITAL E CRIATIVO DE ODEMIRA \nDescrição: AQUISIÇÃO DE EQUIPAMENTO TECNOLÓGICO PARA O BAIRRO COMERCIAL DIGITAL E CRIATIVO DE ODEMIRA \nTipo de Contrato Principal: Aquisição de Bens Móveis\nTipo de Contrato: Aquisição de Bens Móveis\nClassificação CPV (Vocabulário Comum para os Contratos Públicos)\nObjeto principal\nVocabulário Principal: 30231320\nPreço base s/IVA: 147.971,00 EUR\nLotes: \nNº: LOT-0001\nDescrição do Lote: Lote 1 - Mobiliário Urbano \nPreço base s/IVA: 75.971,00 EUR\nClassificação CPV (Vocabulário Comum para os Contratos Públicos)\nObjeto principal\nVocabulário Principal: 30231320\nNº: LOT-0002\nDescrição do Lote: Lote 2 - Mobilidade\nPreço base s/IVA: 72.000,00 EUR\nClassificação CPV (Vocabulário Comum para os Contratos Públicos)\nObjeto principal\nVocabulário Principal: 30231320\n\n7 - INDICAÇÕES ADICIONAIS\nO contrato envolve aquisição conjunta (satisfação de várias entidades)? Não\nO contrato é adjudicado por uma central de compras? Não\n\n8 - TÉCNICAS\nO concurso destina-se à celebração de um acordo-quadro? Inexistência de acordo-quadro\nÉ utilizado um leilão eletrónico? Não\nÉ adotada uma fase de negociação? Não\nSistema de Aquisição Dinâmico: Inexistência de sistema de aquisição dinâmico\n\n9 - LOCAL DA EXECUÇÃO DO CONTRATO\nLOCAL DA EXECUÇÃO DO CONTRATO (PROCEDIMENTO)\nPaís: Portugal\nNUT III: PTZZZ\nLocalidade: Odemira\nDistrito: Beja\nConcelho: Odemira\nFreguesia: Freguesia de São Salvador e Santa Maria\nLOCAL DA EXECUÇÃO DO CONTRATO (LOTE)\nIdentificador do Lote: LOT-0001; LOT-0002\nPaís: Portugal\nNUT III: PT181\nLocalidade: Odemira\nDistrito: Beja\nConcelho: Odemira\nFreguesia: Freguesia de São Salvador e Santa Maria\n\n10 - PRAZO DE EXECUÇÃO DO CONTRATO\nIdentificador do Lote: LOT-0001; LOT-0002\nPrazo de execução do contrato: 30 DIAS\nPrevisão de renovações: Não\n\n11 - FUNDOS EU\nIdentificador do Lote: LOT-0001; LOT-0002\nTêm fundos EU? Não\n\n12 - DOCUMENTOS DE HABILITAÇÃO\nHabilitação para o exercício da atividade profissional: Não\n\n13 - CONDIÇÕES DE APRESENTAÇÃO\nPlataforma eletrónica utilizada pela entidade adjudicante: VORTAL\nURL para Apresentação: https://community.vortal.biz/public/\nAdmissibilidade da apresentação de propostas variantes: Não autorizado\nPrazo para apresentação das propostas: 16-10-2025 17:00\nPrazo durante o qual os concorrentes são obrigados a manter as respetivas propostas: 90 dias a contar do termo do prazo para a apresentação das propostas\nIndicação de Subcontratação na Proposta: Inexistência de indicação de subcontratação\n\n14 - PRESTAÇÃO DE CAUÇÃO\nPrestação de caução: Não\n\n15 - FORNECIMENTO DAS PEÇAS DO CONCURSO, APRESENTAÇÃO DE PEDIDOS DE PARTICIPAÇÃO E APRESENTAÇÃO DAS PROPOSTAS\nLink para acesso às peças do concurso (URL): https://community.vortal.biz/Public/public-tender-documents/MDMyQTE2NXV5Yno4eWxoNzFsN3k0dEZLR1RYL1hyL1pmWC9VaUhGL1d1VVFNRXU1ZFpJbit2bGMvTjRJZThWQVYwWEVoam1Tb3RQM3dvRlBweWdHTXc9PWhwcDdv\n\n20 - OUTROS REQUISITOS\nIdentificador do Lote: LOT-0001; LOT-0002\nInformação sobre contratos reservados. Aplica-se a contratos reservados (54º-A)? Não\n\n21 - CRITÉRIO DE ADJUDICAÇÃO\nO Critério de adjudicação é diferenciado por lote? Não\nMultifator: Não\nMonofator:\nNome: Outros\nOutro nome: Preço\n\n24 - CONDIÇÕES DO CONTRATO\nIdentificador do Lote: LOT-0001; LOT-0002\nFaturação Eletrónica: Permitido\nObrigação de Subcontratação:\nCódigo da Obrigação de Subcontratação: Não é aplicável nenhuma obrigação de subcontratação.\n\n25 - COMPRA PÚBLICA ESTRATÉGICA\nCompra Pública Estratégica: Inexistência de contratação pública estratégica\n\n26 - INFORMAÇÕES ADICIONAIS\nIdentificador do Lote: LOT-0001; LOT-0002\nContrato adequado para PME: Sim\nCobertura ACP (Acordo dos Contratos Públicos da Organização Mundial do Comércio): Não\n\n27 - IDENTIFICAÇÃO E CONTACTOS DO ÓRGÃO DE RECURSOS ADMINISTRATIVOS\nDesignação: Tribunal Administrativo e Fiscal de Beja\nEndereço: RUA DE ANGOLA\nCódigo postal: 7800-054\nLocalidade: Beja\nTelefone: +351 284311550\nFax: +351 213506009\nEndereço eletrónico: beja.taf@tribunais.org.pt\nPrazo de interposição do recurso: 10 dias\n\n28 - IDENTIFICAÇÃO DO(S) AUTOR(ES) DE ANÚNCIO\nNome: Hélder António Guerreiro \nCargo: Presidente \n419586785",
    "nipc": "505311313",
    "distrito": "Beja",
    "concelho": "Odemira",
    "freguesia": "Freguesia de São Salvador e Santa Maria",
    "site": "www.cm-odemira.pt",
    "email": "geral@cm-odemira.pt",
    "designacao_contrato": "AQUISIÇÃO DE EQUIPAMENTO TECNOLÓGICO PARA O BAIRRO COMERCIAL DIGITAL E CRIATIVO DE ODEMIRA",
    "descricao": "AQUISIÇÃO DE EQUIPAMENTO TECNOLÓGICO PARA O BAIRRO COMERCIAL DIGITAL E CRIATIVO DE ODEMIRA",
    "preco_base": "147.971,00 EUR",
    "prazo_execucao": "30 DIAS",
    "prazo_apresentacao_propostas": "16-10-2025 17:00",
    "fundos_eu": "Não",
    "plataforma_eletronica": "VORTAL",
    "url_procedimento": "https://community.vortal.biz/public/",
    "autor_nome": "Hélder António Guerreiro",
    "autor_cargo": "Presidente"
  },
  {
    "numero_procedimento": "N/A",
    "entidade": "Unidade Local de Saúde de São João E.P.E.",
    "link": "https://diariodarepublica.pt/dr/detalhe/contrato-publico/25863-937614431",
    "detalhes_completos": "1 - IDENTIFICAÇÃO E CONTACTOS DA ENTIDADE ADJUDICANTE\nDesignação da entidade adjudicante: Unidade Local de Saúde de São João E.P.E.\nNIPC: 509821197\nServiço/Órgão/Pessoa de contacto: Serviço de Aprovisionamento\nEndereço: Alameda Prof. Hernâni Monteiro\nCódigo postal: 4200-319\nLocalidade: Área Metropolitana do Porto\nPaís: Portugal\nNUT III: PT11A\nDistrito: Porto\nConcelho: Porto\nFreguesia: Freguesia de Paranhos - Porto\nTelefone: 225512100\nFax: 225504463\nEndereço da Entidade (URL): https://portal-chsj.min-saude.pt/\nEndereço Eletrónico: geral@ulssjoao.min-saude.pt\neDelivery Gateway (URL): https://community.vortal.biz/public/\nFunção da Organização: Adquirente\nNorma jurídica da Entidade Adjudicante: Organismo de direito público\nÁrea de atividade da Autoridade Adjudicante: Saúde\n\n2 - JORNAL OFICIAL DA UNIÃO EUROPEIA\nO procedimento a que este anúncio diz respeito também é publicitado no Jornal Oficial da União Europeia? Sim\n\n3 - AVISO\nModelo de Anúncio: Concurso público\nData de Envio do Anúncio: 29-09-2025\n\n5 - PROCESSO\nTipo de Procedimento: Concurso público\nPreço base do procedimento: Sim\nValor do preço base do procedimento: 370.500,00 EUR\nProcedimento com lotes? Não\n\n6 - OBJETO DO CONTRATO\nNúmero de referência interna: 61001525\nDesignação do contrato: Aquisição de Papel Higiénico para a Unidade Local de Saúde São João, EPE\nDescrição: Aquisição de Papel Higiénico para a Unidade Local de Saúde São João, EPE\nOpções: Não\nTipo de Contrato Principal: Aquisição de Bens Móveis\nTipo de Contrato: Aquisição de Bens Móveis\nClassificação CPV (Vocabulário Comum para os Contratos Públicos)\nObjeto principal\nVocabulário Principal: 33760000\nPreço base s/IVA: 370.500,00 EUR\n\n7 - INDICAÇÕES ADICIONAIS\nO contrato envolve aquisição conjunta (satisfação de várias entidades)? Não\nO contrato é adjudicado por uma central de compras? Não\n\n8 - TÉCNICAS\nO concurso destina-se à celebração de um acordo-quadro? Inexistência de acordo-quadro\nÉ utilizado um leilão eletrónico? Não\nÉ adotada uma fase de negociação? Não\nSistema de Aquisição Dinâmico: Inexistência de sistema de aquisição dinâmico\n\n9 - LOCAL DA EXECUÇÃO DO CONTRATO\nLOCAL DA EXECUÇÃO DO CONTRATO (PROCEDIMENTO)\nPaís: Portugal\nNUT III: PT11A\nLocalidade: Área Metropolitana do Porto\nDistrito: Porto\nConcelho: Porto\nFreguesia: Freguesia de Paranhos - Porto\n\n10 - PRAZO DE EXECUÇÃO DO CONTRATO\nPrazo de execução do contrato: 36 MESES\nPrevisão de renovações: Não\n\n11 - FUNDOS EU\nTêm fundos EU? Não\n\n12 - DOCUMENTOS DE HABILITAÇÃO\nHabilitação para o exercício da atividade profissional: Não\n\n13 - CONDIÇÕES DE APRESENTAÇÃO\nPlataforma eletrónica utilizada pela entidade adjudicante: VORTAL\nURL para Apresentação: https://community.vortal.biz/public/\nAdmissibilidade da apresentação de propostas variantes: Não autorizado\nPrazo para apresentação das propostas: 31-10-2025 17:00\nPrazo durante o qual os concorrentes são obrigados a manter as respetivas propostas: 90 dias a contar do termo do prazo para a apresentação das propostas\nApresentação de Catálogo Eletrónico: Permitido\nIndicação de Subcontratação na Proposta: Inexistência de indicação de subcontratação\n\n14 - PRESTAÇÃO DE CAUÇÃO\nPrestação de caução: Não\n\n15 - FORNECIMENTO DAS PEÇAS DO CONCURSO, APRESENTAÇÃO DE PEDIDOS DE PARTICIPAÇÃO E APRESENTAÇÃO DAS PROPOSTAS\nLink para acesso às peças do concurso (URL): https://community.vortal.biz/Public/public-tender-documents/K3ZBQjcxcFVZY0VQTGJuM2E4dHFvRUJlUHhLcmhCZGpBVmtGNmRMUHNqM1R4bW12NmZQaHJySnJCcXZEdy9taXhQcFhKd3hOUldNQnd1RVBaTi81VFE9PUlXSmg1\n\n20 - OUTROS REQUISITOS\nInformação sobre contratos reservados. Aplica-se a contratos reservados (54º-A)? Não\n\n21 - CRITÉRIO DE ADJUDICAÇÃO\nMultifator: Não\nMonofator:\nNome: Preço\n\n24 - CONDIÇÕES DO CONTRATO\nFaturação Eletrónica: Permitido\nObrigação de Subcontratação:\nCódigo da Obrigação de Subcontratação: Não é aplicável nenhuma obrigação de subcontratação.\n\n25 - COMPRA PÚBLICA ESTRATÉGICA\nCompra Pública Estratégica: Inexistência de contratação pública estratégica\n\n26 - INFORMAÇÕES ADICIONAIS\nContrato adequado para PME: Sim\nCobertura ACP (Acordo dos Contratos Públicos da Organização Mundial do Comércio): Não\n\n27 - IDENTIFICAÇÃO E CONTACTOS DO ÓRGÃO DE RECURSOS ADMINISTRATIVOS\nDesignação: Conselho Administração\nEndereço: ULS São João - Alameda Prof. Hernani Monteiro\nCódigo postal: 4200-319\nLocalidade: Porto\nTelefone: +351 225512100\nFax: +351 225025766\nEndereço eletrónico: ca@ulssjoao.min-saude.pt\n\n28 - IDENTIFICAÇÃO DO(S) AUTOR(ES) DE ANÚNCIO\nNome: Tiago Ferreira\nCargo: Diretor do Serviço de Aprovisionamento\n419586493",
    "nipc": "509821197",
    "distrito": "Porto",
    "concelho": "Porto",
    "freguesia": "Freguesia de Paranhos - Porto",
    "site": "https://portal-chsj.min-saude.pt/",
    "email": "geral@ulssjoao.min-saude.pt",
    "designacao_contrato": "Aquisição de Papel Higiénico para a Unidade Local de Saúde São João, EPE",
    "descricao": "Aquisição de Papel Higiénico para a Unidade Local de Saúde São João, EPE",
    "preco_base": "370.500,00 EUR",
    "prazo_execucao": "36 MESES",
    "prazo_apresentacao_propostas": "31-10-2025 17:00",
    "fundos_eu": "Não",
    "plataforma_eletronica": "VORTAL",
    "url_procedimento": "https://community.vortal.biz/public/",
    "autor_nome": "Tiago Ferreira",
    "autor_cargo": "Diretor do Serviço de Aprovisionamento"
  },
  {
    "numero_procedimento": "N/A",
    "entidade": "Unidade Local de Saúde de São João E.P.E.",
    "link": "https://diariodarepublica.pt/dr/detalhe/contrato-publico/25864-937614432",
    "detalhes_completos": "1 - IDENTIFICAÇÃO E CONTACTOS DA ENTIDADE ADJUDICANTE\nDesignação da entidade adjudicante: Unidade Local de Saúde de São João E.P.E.\nNIPC: 509821197\nServiço/Órgão/Pessoa de contacto: Serviço de Aprovisionamento\nEndereço: Alameda Prof. Hernâni Monteiro\nCódigo postal: 4200-319\nLocalidade: Área Metropolitana do Porto\nPaís: Portugal\nNUT III: PT11A\nDistrito: Porto\nConcelho: Porto\nFreguesia: Freguesia de Paranhos - Porto\nTelefone: 225512100\nFax: 225504463\nEndereço da Entidade (URL): https://portal-chsj.min-saude.pt/\nEndereço Eletrónico: geral@ulssjoao.min-saude.pt\neDelivery Gateway (URL): https://community.vortal.biz/public/\nFunção da Organização: Adquirente\nNorma jurídica da Entidade Adjudicante: Organismo de direito público\nÁrea de atividade da Autoridade Adjudicante: Saúde\n\n2 - JORNAL OFICIAL DA UNIÃO EUROPEIA\nO procedimento a que este anúncio diz respeito também é publicitado no Jornal Oficial da União Europeia? Sim\n\n3 - AVISO\nModelo de Anúncio: Concurso público\nData de Envio do Anúncio: 29-09-2025\n\n5 - PROCESSO\nTipo de Procedimento: Concurso público\nPreço base do procedimento: Sim\nValor do preço base do procedimento: 278.938,80 EUR\nProcedimento com lotes? Sim\nNº Máx. de Lotes Autorizado: 3\nNúmero máximo de lotes que podem ser adjudicados a um concorrente: 3\n\n6 - OBJETO DO CONTRATO\nNúmero de referência interna: 61001725\nDesignação do contrato: Aquisição de Louça e Talheres descartáveis para a Unidade Local de Saúde São João, EPE\nDescrição: Aquisição de Louça e Talheres descartáveis para a Unidade Local de Saúde São João, EPE\nOpções: Não\nTipo de Contrato Principal: Aquisição de Bens Móveis\nTipo de Contrato: Aquisição de Bens Móveis\nClassificação CPV (Vocabulário Comum para os Contratos Públicos)\nObjeto principal\nVocabulário Principal: 39220000\nPreço base s/IVA: 278.938,80 EUR\nLotes: \nNº: LOT-0001\nDescrição do Lote: Lote 1\nPreço base s/IVA: 202.680,00 EUR\nClassificação CPV (Vocabulário Comum para os Contratos Públicos)\nObjeto principal\nVocabulário Principal: 39220000\nNº: LOT-0002\nDescrição do Lote: Lote 2\nPreço base s/IVA: 71.415,00 EUR\nClassificação CPV (Vocabulário Comum para os Contratos Públicos)\nObjeto principal\nVocabulário Principal: 39220000\nNº: LOT-0003\nDescrição do Lote: Lote 3\nPreço base s/IVA: 4.843,80 EUR\nClassificação CPV (Vocabulário Comum para os Contratos Públicos)\nObjeto principal\nVocabulário Principal: 39220000\n\n7 - INDICAÇÕES ADICIONAIS\nO contrato envolve aquisição conjunta (satisfação de várias entidades)? Não\nO contrato é adjudicado por uma central de compras? Não\n\n8 - TÉCNICAS\nO concurso destina-se à celebração de um acordo-quadro? Inexistência de acordo-quadro\nÉ utilizado um leilão eletrónico? Não\nÉ adotada uma fase de negociação? Não\nSistema de Aquisição Dinâmico: Inexistência de sistema de aquisição dinâmico\n\n9 - LOCAL DA EXECUÇÃO DO CONTRATO\nLOCAL DA EXECUÇÃO DO CONTRATO (PROCEDIMENTO)\nPaís: Portugal\nNUT III: PT11A\nLocalidade: Área Metropolitana do Porto\nDistrito: Porto\nConcelho: Porto\nFreguesia: Freguesia de Paranhos - Porto\nLOCAL DA EXECUÇÃO DO CONTRATO (LOTE)\nIdentificador do Lote: LOT-0001; LOT-0002; LOT-0003\nPaís: Portugal\nNUT III: PT11A\nLocalidade: Área Metropolitana do Porto\nDistrito: Porto\nConcelho: Porto\nFreguesia: Freguesia de Paranhos - Porto\n\n10 - PRAZO DE EXECUÇÃO DO CONTRATO\nIdentificador do Lote: LOT-0001; LOT-0002; LOT-0003\nPrazo de execução do contrato: 36 MESES\nPrevisão de renovações: Não\n\n11 - FUNDOS EU\nIdentificador do Lote: LOT-0001; LOT-0002; LOT-0003\nTêm fundos EU? Não\n\n12 - DOCUMENTOS DE HABILITAÇÃO\nHabilitação para o exercício da atividade profissional: Não\n\n13 - CONDIÇÕES DE APRESENTAÇÃO\nPlataforma eletrónica utilizada pela entidade adjudicante: VORTAL\nURL para Apresentação: https://community.vortal.biz/public/\nAdmissibilidade da apresentação de propostas variantes: Não autorizado\nPrazo para apresentação das propostas: 31-10-2025 17:00\nPrazo durante o qual os concorrentes são obrigados a manter as respetivas propostas: 90 dias a contar do termo do prazo para a apresentação das propostas\nApresentação de Catálogo Eletrónico: Permitido\nIndicação de Subcontratação na Proposta: Inexistência de indicação de subcontratação\n\n14 - PRESTAÇÃO DE CAUÇÃO\nPrestação de caução: Não\n\n15 - FORNECIMENTO DAS PEÇAS DO CONCURSO, APRESENTAÇÃO DE PEDIDOS DE PARTICIPAÇÃO E APRESENTAÇÃO DAS PROPOSTAS\nLink para acesso às peças do concurso (URL): https://community.vortal.biz/Public/public-tender-documents/L1JrNjB3Y214Q2wxcHNFa25OYThTUlFZRzkzZEpVY2VnS21sYmJadUZLTDh2QnBnOEJvMTYwMlpmdWVBRzlvTlV6QmJGZkhZeXo5K3BOS2VlUVZ2N1E9PXVFKzNk\n\n20 - OUTROS REQUISITOS\nIdentificador do Lote: LOT-0001; LOT-0002; LOT-0003\nInformação sobre contratos reservados. Aplica-se a contratos reservados (54º-A)? Não\n\n21 - CRITÉRIO DE ADJUDICAÇÃO\nO Critério de adjudicação é diferenciado por lote? Não\nMultifator: Não\nMonofator:\nNome: Preço\n\n24 - CONDIÇÕES DO CONTRATO\nIdentificador do Lote: LOT-0001; LOT-0002; LOT-0003\nFaturação Eletrónica: Permitido\nObrigação de Subcontratação:\nCódigo da Obrigação de Subcontratação: Não é aplicável nenhuma obrigação de subcontratação.\n\n25 - COMPRA PÚBLICA ESTRATÉGICA\nCompra Pública Estratégica: Inexistência de contratação pública estratégica\n\n26 - INFORMAÇÕES ADICIONAIS\nIdentificador do Lote: LOT-0001; LOT-0002; LOT-0003\nContrato adequado para PME: Sim\nCobertura ACP (Acordo dos Contratos Públicos da Organização Mundial do Comércio): Não\n\n27 - IDENTIFICAÇÃO E CONTACTOS DO ÓRGÃO DE RECURSOS ADMINISTRATIVOS\nDesignação: Conselho Administração\nEndereço: ULS São João - Alameda Prof. Hernani Monteiro\nCódigo postal: 4200-319\nLocalidade: Porto\nTelefone: +351 225512100\nFax: +351 225025766\nEndereço eletrónico: ca@ulssjoao.min-saude.pt\n\n28 - IDENTIFICAÇÃO DO(S) AUTOR(ES) DE ANÚNCIO\nNome: Tiago Ferreira\nCargo: Diretor do Serviço de Aprovisionamento\n419587051",
    "nipc": "509821197",
    "distrito": "Porto",
    "concelho": "Porto",
    "freguesia": "Freguesia de Paranhos - Porto",
    "site": "https://portal-chsj.min-saude.pt/",
    "email": "geral@ulssjoao.min-saude.pt",
    "designacao_contrato": "Aquisição de Louça e Talheres descartáveis para a Unidade Local de Saúde São João, EPE",
    "descricao": "Aquisição de Louça e Talheres descartáveis para a Unidade Local de Saúde São João, EPE",
    "preco_base": "278.938,80 EUR",
    "prazo_execucao": "36 MESES",
    "prazo_apresentacao_propostas": "31-10-2025 17:00",
    "fundos_eu": "Não",
    "plataforma_eletronica": "VORTAL",
    "url_procedimento": "https://community.vortal.biz/public/",
    "autor_nome": "Tiago Ferreira",
    "autor_cargo": "Diretor do Serviço de Aprovisionamento"
  },
  {
    "numero_procedimento": "N/A",
    "entidade": "Unidade Local de Saúde do Algarve, E.P.E",
    "link": "https://diariodarepublica.pt/dr/detalhe/contrato-publico/25865-937614433",
    "detalhes_completos": "1 - IDENTIFICAÇÃO E CONTACTOS DA ENTIDADE ADJUDICANTE\nDesignação da entidade adjudicante: Unidade Local de Saúde do Algarve, E.P.E\nNIPC: 510745997\nEndereço: Rua Leão Penedo\nCódigo postal: 8000-386\nLocalidade: Faro\nPaís: Portugal\nNUT III: PT150\nDistrito: Faro\nConcelho: Faro\nFreguesia: União das Freguesias de Faro (Sé e São Pedro)\nTelefone: 289891100\nFax: 289891159\nEndereço da Entidade (URL): https://www.chualgarve.min-saude.pt\nEndereço Eletrónico: concursos@ulsalg.min-saude.pt\neDelivery Gateway (URL): https://community.vortal.biz/public/\nFunção da Organização: Adquirente\nNorma jurídica da Entidade Adjudicante: Organismo de direito público\nÁrea de atividade da Autoridade Adjudicante: Saúde\n\n2 - JORNAL OFICIAL DA UNIÃO EUROPEIA\nO procedimento a que este anúncio diz respeito também é publicitado no Jornal Oficial da União Europeia? Sim\n\n3 - AVISO\nModelo de Anúncio: Concurso público\nData de Envio do Anúncio: 29-09-2025\n\n5 - PROCESSO\nTipo de Procedimento: Concurso público\nPreço base do procedimento: Sim\nValor do preço base do procedimento: 493.997,40 EUR\nProcedimento com lotes? Não\n\n6 - OBJETO DO CONTRATO\nNúmero de referência interna: 11/15/2026\nDesignação do contrato: Reagentes para ImunoHistoquimica 2026-2028\nDescrição: Reagentes para ImunoHistoquimica 2026-2028\nOpções: Não\nTipo de Contrato Principal: Aquisição de Bens Móveis\nTipo de Contrato: Aquisição de Bens Móveis\nClassificação CPV (Vocabulário Comum para os Contratos Públicos)\nObjeto principal\nVocabulário Principal: 33696500\nPreço base s/IVA: 493.997,40 EUR\n\n7 - INDICAÇÕES ADICIONAIS\nO contrato envolve aquisição conjunta (satisfação de várias entidades)? Não\nO contrato é adjudicado por uma central de compras? Não\n\n8 - TÉCNICAS\nO concurso destina-se à celebração de um acordo-quadro? Inexistência de acordo-quadro\nÉ utilizado um leilão eletrónico? Não\nÉ adotada uma fase de negociação? Não\nSistema de Aquisição Dinâmico: Inexistência de sistema de aquisição dinâmico\n\n9 - LOCAL DA EXECUÇÃO DO CONTRATO\nLOCAL DA EXECUÇÃO DO CONTRATO (PROCEDIMENTO)\nPaís: Portugal\nNUT III: PT150\nLocalidade: Faro\nDistrito: Faro\nConcelho: Faro\nFreguesia: União das Freguesias de Faro (Sé e São Pedro)\n\n10 - PRAZO DE EXECUÇÃO DO CONTRATO\nPrazo de execução do contrato: 120 DIAS\nPrevisão de renovações: Não\n\n11 - FUNDOS EU\nTêm fundos EU? Não\n\n12 - DOCUMENTOS DE HABILITAÇÃO\nHabilitação para o exercício da atividade profissional: Não\n\n13 - CONDIÇÕES DE APRESENTAÇÃO\nPlataforma eletrónica utilizada pela entidade adjudicante: VORTAL\nURL para Apresentação: https://community.vortal.biz/public/\nAdmissibilidade da apresentação de propostas variantes: Não autorizado\nPrazo para apresentação das propostas: 30-10-2025 17:00\nPrazo durante o qual os concorrentes são obrigados a manter as respetivas propostas: 120 dias a contar do termo do prazo para a apresentação das propostas\nApresentação de Catálogo Eletrónico: Não autorizado\nIndicação de Subcontratação na Proposta: Inexistência de indicação de subcontratação\n\n14 - PRESTAÇÃO DE CAUÇÃO\nPrestação de caução: Não\n\n15 - FORNECIMENTO DAS PEÇAS DO CONCURSO, APRESENTAÇÃO DE PEDIDOS DE PARTICIPAÇÃO E APRESENTAÇÃO DAS PROPOSTAS\nLink para acesso às peças do concurso (URL): https://community.vortal.biz/Public/public-tender-documents/UklENzdqalFsUDRIZ251R0lyd3dmUFhwaVgyUVZJSnFUSjRjZWlmRTlMRGgzcmNPN2cxREJYV3dURTFKQkRwbE93RFhlUGNXelF2enJSRncxOWN5d3c9PTB1UmFG\n\n20 - OUTROS REQUISITOS\nInformação sobre contratos reservados. Aplica-se a contratos reservados (54º-A)? Não\n\n21 - CRITÉRIO DE ADJUDICAÇÃO\nMultifator: Sim\nFator: \nNome: Preço\nPonderação: 35%\nSubfatores: Não\nFator: \nNome: Qualidade\nPonderação: 65%\nSubfatores: Não\n\n24 - CONDIÇÕES DO CONTRATO\nFaturação Eletrónica: Permitido\nObrigação de Subcontratação:\nCódigo da Obrigação de Subcontratação: Não é aplicável nenhuma obrigação de subcontratação.\n\n25 - COMPRA PÚBLICA ESTRATÉGICA\nCompra Pública Estratégica: Inexistência de contratação pública estratégica\n\n26 - INFORMAÇÕES ADICIONAIS\nContrato adequado para PME: Sim\nCobertura ACP (Acordo dos Contratos Públicos da Organização Mundial do Comércio): Não\n\n27 - IDENTIFICAÇÃO E CONTACTOS DO ÓRGÃO DE RECURSOS ADMINISTRATIVOS\nDesignação: Unisade Local de Saude do Algarve, EPE\nEndereço: Rua Leão Penedo\nCódigo postal: 8000-386\nLocalidade: Faro\nTelefone: +351 289001964\nFax: +351 289891159\nEndereço eletrónico: csousa@ulsalg.min-saude.pt\n\n28 - IDENTIFICAÇÃO DO(S) AUTOR(ES) DE ANÚNCIO\nNome: Tiago Botelho\nCargo: Presidente do Conselho de Administração\n419587684",
    "nipc": "510745997",
    "distrito": "Faro",
    "concelho": "Faro",
    "freguesia": "União das Freguesias de Faro (Sé e São Pedro)",
    "site": "https://www.chualgarve.min-saude.pt",
    "email": "concursos@ulsalg.min-saude.pt",
    "designacao_contrato": "Reagentes para ImunoHistoquimica 2026-2028",
    "descricao": "Reagentes para ImunoHistoquimica 2026-2028",
    "preco_base": "493.997,40 EUR",
    "prazo_execucao": "120 DIAS",
    "prazo_apresentacao_propostas": "30-10-2025 17:00",
    "fundos_eu": "Não",
    "plataforma_eletronica": "VORTAL",
    "url_procedimento": "https://community.vortal.biz/public/",
    "autor_nome": "Tiago Botelho",
    "autor_cargo": "Presidente do Conselho de Administração"
  },
  {
    "numero_procedimento": "N/A",
    "entidade": "Município de Gouveia",
    "link": "https://diariodarepublica.pt/dr/detalhe/contrato-publico/25867-937614434",
    "detalhes_completos": "1 - IDENTIFICAÇÃO E CONTACTOS DA ENTIDADE ADJUDICANTE\nDesignação da entidade adjudicante: Município de Gouveia\nNIPC: 506510476\nEndereço: Av. 25 De Abril\nCódigo postal: 6290-554\nLocalidade: Guarda\nPaís: Portugal\nNUT III: PT16J\nDistrito: Guarda\nConcelho: Gouveia\nFreguesia: Freguesia de Gouveia - Gouveia\nTelefone: 238490210\nFax: 238494686\nEndereço da Entidade (URL): www.cm-gouveia.pt\nEndereço Eletrónico: aprovisionamento@cm-gouveia.pt\neDelivery Gateway (URL): https://community.vortal.biz/public/\nFunção da Organização: Adquirente\nNorma jurídica da Entidade Adjudicante: Autoridade local\nÁrea de atividade da Autoridade Adjudicante: Serviços públicos das administrações públicas\n\n2 - JORNAL OFICIAL DA UNIÃO EUROPEIA\nO procedimento a que este anúncio diz respeito também é publicitado no Jornal Oficial da União Europeia? Não\n\n3 - AVISO\nModelo de Anúncio: Concurso público\nData de Envio do Anúncio: 01-10-2025\n\n5 - PROCESSO\nTipo de Procedimento: Concurso público\nPreço base do procedimento: Sim\nValor do preço base do procedimento: 200.013,94 EUR\nProcedimento com lotes? Não\n\n6 - OBJETO DO CONTRATO\nNúmero de referência interna: 38GVA/2025\nDesignação do contrato: REQUALIFICAÇÃO DOS ARRUAMENTOS NA ENVOLVENTE ANTIGA ADEGA COOPERATIVA DE VILA NOVA DE TAZEM\nDescrição: REQUALIFICAÇÃO DOS ARRUAMENTOS NA ENVOLVENTE ANTIGA ADEGA COOPERATIVA DE VILA NOVA DE TAZEM\nTipo de Contrato Principal: Empreitada de Obras Públicas\nTipo de Contrato: Empreitada de Obras Públicas\nClassificação CPV (Vocabulário Comum para os Contratos Públicos)\nObjeto principal\nVocabulário Principal: 45232451\nPreço base s/IVA: 200.013,94 EUR\n\n7 - INDICAÇÕES ADICIONAIS\nO contrato envolve aquisição conjunta (satisfação de várias entidades)? Não\nO contrato é adjudicado por uma central de compras? Não\n\n8 - TÉCNICAS\nO concurso destina-se à celebração de um acordo-quadro? Inexistência de acordo-quadro\nÉ utilizado um leilão eletrónico? Não\nÉ adotada uma fase de negociação? Não\nSistema de Aquisição Dinâmico: Inexistência de sistema de aquisição dinâmico\n\n9 - LOCAL DA EXECUÇÃO DO CONTRATO\nLOCAL DA EXECUÇÃO DO CONTRATO (PROCEDIMENTO)\nPaís: Portugal\nNUT III: PT16J\nLocalidade: Guarda\nDistrito: Guarda\nConcelho: Gouveia\nFreguesia: Todas\n\n10 - PRAZO DE EXECUÇÃO DO CONTRATO\nPrazo de execução do contrato: 180 DIAS\nPrevisão de renovações: Não\n\n11 - FUNDOS EU\nTêm fundos EU? Não\n\n12 - DOCUMENTOS DE HABILITAÇÃO\nHabilitação para o exercício da atividade profissional: Não\n\n13 - CONDIÇÕES DE APRESENTAÇÃO\nPlataforma eletrónica utilizada pela entidade adjudicante: VORTAL\nURL para Apresentação: https://community.vortal.biz/public/\nAdmissibilidade da apresentação de propostas variantes: Não autorizado\nPrazo para apresentação das propostas: 15-10-2025 17:30\nPrazo durante o qual os concorrentes são obrigados a manter as respetivas propostas: 120 dias a contar do termo do prazo para a apresentação das propostas\nIndicação de Subcontratação na Proposta: Inexistência de indicação de subcontratação\n\n14 - PRESTAÇÃO DE CAUÇÃO\nPrestação de caução: Não\n\n15 - FORNECIMENTO DAS PEÇAS DO CONCURSO, APRESENTAÇÃO DE PEDIDOS DE PARTICIPAÇÃO E APRESENTAÇÃO DAS PROPOSTAS\nLink para acesso às peças do concurso (URL): https://community.vortal.biz/Public/public-tender-documents/dFU0Uzhud1NhMHFXRkJJcFBmVHV0WEtoRTd6a1dYODJ2S2ZQYmFCdmdvL2JZSUk2VThKdjBoMDhTVE8ySXNLbENyWGt5LzNCZUV5QXZxYmFRdllicEE9PWNzbm9n\n\n20 - OUTROS REQUISITOS\nInformação sobre contratos reservados. Aplica-se a contratos reservados (54º-A)? Não\n\n21 - CRITÉRIO DE ADJUDICAÇÃO\nMultifator: Sim\nFator: \nNome: Preço\nPonderação: 80%\nSubfatores: Não\nFator: \nNome: Qualidade\nPonderação: 20%\nSubfatores: Não\n\n24 - CONDIÇÕES DO CONTRATO\nFaturação Eletrónica: Permitido\nObrigação de Subcontratação:\nCódigo da Obrigação de Subcontratação: Não é aplicável nenhuma obrigação de subcontratação.\n\n25 - COMPRA PÚBLICA ESTRATÉGICA\nCompra Pública Estratégica: Inexistência de contratação pública estratégica\n\n26 - INFORMAÇÕES ADICIONAIS\nContrato adequado para PME: Sim\nCobertura ACP (Acordo dos Contratos Públicos da Organização Mundial do Comércio): Não\n\n27 - IDENTIFICAÇÃO E CONTACTOS DO ÓRGÃO DE RECURSOS ADMINISTRATIVOS\nDesignação: Câmara Municipal de Gouveia\nEndereço: Av. 25 de Abril\nCódigo postal: 6290-554\nLocalidade: Gouveia\nTelefone: +351 238490210\nFax: +351 000000000\nEndereço eletrónico: geral@cm-gouveia.pt\n\n28 - IDENTIFICAÇÃO DO(S) AUTOR(ES) DE ANÚNCIO\nNome: Dr. Luis Manuel Tadeu Marques\nCargo: Presidente da Câmara\n419597469",
    "nipc": "506510476",
    "distrito": "Guarda",
    "concelho": "Gouveia",
    "freguesia": "Freguesia de Gouveia - Gouveia",
    "site": "www.cm-gouveia.pt",
    "email": "aprovisionamento@cm-gouveia.pt",
    "designacao_contrato": "REQUALIFICAÇÃO DOS ARRUAMENTOS NA ENVOLVENTE ANTIGA ADEGA COOPERATIVA DE VILA NOVA DE TAZEM",
    "descricao": "REQUALIFICAÇÃO DOS ARRUAMENTOS NA ENVOLVENTE ANTIGA ADEGA COOPERATIVA DE VILA NOVA DE TAZEM",
    "preco_base": "200.013,94 EUR",
    "prazo_execucao": "180 DIAS",
    "prazo_apresentacao_propostas": "15-10-2025 17:30",
    "fundos_eu": "Não",
    "plataforma_eletronica": "VORTAL",
    "url_procedimento": "https://community.vortal.biz/public/",
    "autor_nome": "Dr. Luis Manuel Tadeu Marques",
    "autor_cargo": "Presidente da Câmara"
  },
  {
    "numero_procedimento": "N/A",
    "entidade": "Agrupamento de Escolas da Baixa da Banheira, Vale da Amoreira , Moita",
    "link": "https://diariodarepublica.pt/dr/detalhe/contrato-publico/25870-937614435",
    "detalhes_completos": "1 - IDENTIFICAÇÃO E CONTACTOS DA ENTIDADE ADJUDICANTE\nDesignação da entidade adjudicante: Agrupamento de Escolas da Baixa da Banheira, Vale da Amoreira , Moita\nNIPC: 600075010\nEndereço: Praceta Maria Helena Vieira da Silva\nCódigo postal: 2835-220\nLocalidade: Vale da Amoreira\nPaís: Portugal\nNUT III: PT170\nDistrito: Setúbal\nConcelho: Moita\nFreguesia: União das Freguesias de Baixa da Banheira e Vale da Amoreira\nTelefone: 212099970\nFax: 212099970\nEndereço da Entidade (URL): www.aebbva.pt\nEndereço Eletrónico: diretor@esbb.pt\nFunção da Organização: Adquirente\nNorma jurídica da Entidade Adjudicante: Organismo de direito público, controlado por uma autoridade da administração central\nÁrea de atividade da Autoridade Adjudicante: Educação\n\n2 - JORNAL OFICIAL DA UNIÃO EUROPEIA\nO procedimento a que este anúncio diz respeito também é publicitado no Jornal Oficial da União Europeia? Sim\n\n3 - AVISO\nModelo de Anúncio: Concurso público\nData de Envio do Anúncio: 29-09-2025\n\n5 - PROCESSO\nTipo de Procedimento: Concurso público\nPreço base do procedimento: Sim\nValor do preço base do procedimento: 1.030.000,00 EUR\nProcedimento com lotes? Sim\nNº Máx. de Lotes Autorizado: 4\nNúmero máximo de lotes que podem ser adjudicados a um concorrente: 4\n\n6 - OBJETO DO CONTRATO\nNúmero de referência interna: CPUE01/2025-CTE INF.TECHS.MED\nDesignação do contrato: Aquisição, Instalação e Configuração da Infraestrutura Tecnológica, do Hardware, do Software e do Mobiliário Educativo e Didático\nDescrição: Aquisição, Instalação e Configuração da Infraestrutura Tecnológica, do Hardware, do Software e do Mobiliário Educativo e Didático\nOpções: Não\nTipo de Contrato Principal: Aquisição de Bens Móveis\nTipo de Contrato: Aquisição de Bens Móveis\nClassificação CPV (Vocabulário Comum para os Contratos Públicos)\nObjeto Complementar\nVocabulário Principal: 31600000\nPreço base s/IVA: 60.000,00 EUR\nObjeto Complementar\nVocabulário Principal: 39100000\nPreço base s/IVA: 165.000,00 EUR\nObjeto principal\nVocabulário Principal: 30200000\nPreço base s/IVA: 655.000,00 EUR\nObjeto Complementar\nVocabulário Principal: 48800000\nPreço base s/IVA: 150.000,00 EUR\nLotes: \nNº: LOT-0001\nDescrição do Lote: Equipamento Ativo para a Rede Estruturada de Comunicações\nPreço base s/IVA: 150.000,00 EUR\nClassificação CPV (Vocabulário Comum para os Contratos Públicos)\nObjeto principal\nVocabulário Principal: 48800000\nNº: LOT-0002\nDescrição do Lote: Equipamento Informático, Equipamento Eletrónico e Software\nPreço base s/IVA: 655.000,00 EUR\nClassificação CPV (Vocabulário Comum para os Contratos Públicos)\nObjeto principal\nVocabulário Principal: 30200000\nNº: LOT-0003\nDescrição do Lote: Equipamento de Medida, Ferramentas e Outros Materiais\nPreço base s/IVA: 60.000,00 EUR\nClassificação CPV (Vocabulário Comum para os Contratos Públicos)\nObjeto principal\nVocabulário Principal: 31600000\nNº: LOT-0004\nDescrição do Lote: Mobiliário Educativo e Didático\nPreço base s/IVA: 165.000,00 EUR\nClassificação CPV (Vocabulário Comum para os Contratos Públicos)\nObjeto principal\nVocabulário Principal: 39100000\n\n7 - INDICAÇÕES ADICIONAIS\nO contrato envolve aquisição conjunta (satisfação de várias entidades)? Não\nO contrato é adjudicado por uma central de compras? Não\n\n8 - TÉCNICAS\nO concurso destina-se à celebração de um acordo-quadro? Inexistência de acordo-quadro\nÉ utilizado um leilão eletrónico? Não\nÉ adotada uma fase de negociação? Não\nSistema de Aquisição Dinâmico: Inexistência de sistema de aquisição dinâmico\n\n9 - LOCAL DA EXECUÇÃO DO CONTRATO\nLOCAL DA EXECUÇÃO DO CONTRATO (PROCEDIMENTO)\nLOCAL DA EXECUÇÃO DO CONTRATO (LOTE)\nIdentificador do Lote: LOT-0001\nPaís: Portugal\nNUT III: PT170\nLocalidade: Vale da Amoreira\nDistrito: Setúbal\nConcelho: Moita\nFreguesia: União das Freguesias de Baixa da Banheira e Vale da Amoreira\nIdentificador do Lote: LOT-0002\nPaís: Portugal\nNUT III: PT170\nLocalidade: Vale da Amoreira\nDistrito: Setúbal\nConcelho: Moita\nFreguesia: União das Freguesias de Baixa da Banheira e Vale da Amoreira\nIdentificador do Lote: LOT-0003\nPaís: Portugal\nNUT III: PT170\nLocalidade: Vale da Amoreira\nDistrito: Setúbal\nConcelho: Moita\nFreguesia: União das Freguesias de Baixa da Banheira e Vale da Amoreira\nIdentificador do Lote: LOT-0004\nPaís: Portugal\nNUT III: PT170\nLocalidade: Vale da Amoreira\nDistrito: Setúbal\nConcelho: Moita\nFreguesia: União das Freguesias de Baixa da Banheira e Vale da Amoreira\n\n10 - PRAZO DE EXECUÇÃO DO CONTRATO\nIdentificador do Lote: LOT-0001\nPrazo de execução do contrato: 120 DIAS\nPrevisão de renovações: Não\nIdentificador do Lote: LOT-0002\nPrazo de execução do contrato: 120 DIAS\nPrevisão de renovações: Não\nIdentificador do Lote: LOT-0003\nPrazo de execução do contrato: 120 DIAS\nPrevisão de renovações: Não\nIdentificador do Lote: LOT-0004\nPrazo de execução do contrato: 120 DIAS\nPrevisão de renovações: Não\n\n11 - FUNDOS EU\nIdentificador do Lote: LOT-0001; LOT-0002; LOT-0003; LOT-0004\nTêm fundos EU? Não\n\n12 - DOCUMENTOS DE HABILITAÇÃO\nHabilitação para o exercício da atividade profissional: Não\n\n13 - CONDIÇÕES DE APRESENTAÇÃO\nPlataforma eletrónica utilizada pela entidade adjudicante: ANOGOV\nURL para Apresentação: https://www.anogov.com/ae-esbb/faces/\nAdmissibilidade da apresentação de propostas variantes: Não autorizado\nPrazo para apresentação das propostas: 29-10-2025 23:59\nPrazo durante o qual os concorrentes são obrigados a manter as respetivas propostas: 66 dias a contar do termo do prazo para a apresentação das propostas\nApresentação de Catálogo Eletrónico: Necessário\nIndicação de Subcontratação na Proposta: A parte do contrato que o proponente tenciona subcontratar\n\n14 - PRESTAÇÃO DE CAUÇÃO\nPrestação de caução: Não\n\n15 - FORNECIMENTO DAS PEÇAS DO CONCURSO, APRESENTAÇÃO DE PEDIDOS DE PARTICIPAÇÃO E APRESENTAÇÃO DAS PROPOSTAS\nLink para acesso às peças do concurso (URL): https://www.anogov.com/ae-esbb/faces/app/acessoDocs.jsp?codigoAcesso=RObsAWBNRPKIGc2zNDGQhI6A4n1zB959UvbqBsl5e01eXe6NVZ\n\n20 - OUTROS REQUISITOS\nIdentificador do Lote: LOT-0001; LOT-0002; LOT-0003; LOT-0004\nInformação sobre contratos reservados. Aplica-se a contratos reservados (54º-A)? Não\n\n21 - CRITÉRIO DE ADJUDICAÇÃO\nO Critério de adjudicação é diferenciado por lote? Sim\nIdentificador do lote: LOT-0001\nMultifator: Sim\nFator: \nNome: Outros\nOutro Nome: Prazo de garantia\nPonderação: 15%\nSubfatores: Não\nFator: \nNome: Outros\nOutro Nome: Plano de Formação\nPonderação: 15%\nSubfatores: Não\nFator: \nNome: Preço\nPonderação: 70%\nSubfatores: Não\nO Critério de adjudicação é diferenciado por lote? Sim\nIdentificador do lote: LOT-0002\nMultifator: Sim\nFator: \nNome: Outros\nOutro Nome: Plano de Formação\nPonderação: 15%\nSubfatores: Não\nFator: \nNome: Outros\nOutro Nome: Prazo de garantia\nPonderação: 15%\nSubfatores: Não\nFator: \nNome: Preço\nPonderação: 70%\nSubfatores: Não\nO Critério de adjudicação é diferenciado por lote? Sim\nIdentificador do lote: LOT-0003\nMultifator: Sim\nFator: \nNome: Outros\nOutro Nome: Prazo de garantia\nPonderação: 15%\nSubfatores: Não\nFator: \nNome: Outros\nOutro Nome: Plano de Formação\nPonderação: 15%\nSubfatores: Não\nFator: \nNome: Preço\nPonderação: 70%\nSubfatores: Não\nO Critério de adjudicação é diferenciado por lote? Sim\nIdentificador do lote: LOT-0004\nMultifator: Sim\nFator: \nNome: Outros\nOutro Nome: Prazo de garantia\nPonderação: 15%\nSubfatores: Não\nFator: \nNome: Preço\nPonderação: 85%\nSubfatores: Não\n\n24 - CONDIÇÕES DO CONTRATO\nIdentificador do Lote: LOT-0001; LOT-0002; LOT-0003; LOT-0004\nFaturação Eletrónica: Permitido\nObrigação de Subcontratação:\nCódigo da Obrigação de Subcontratação: Não é aplicável nenhuma obrigação de subcontratação.\n\n25 - COMPRA PÚBLICA ESTRATÉGICA\nCompra Pública Estratégica: Inexistência de contratação pública estratégica\n\n26 - INFORMAÇÕES ADICIONAIS\nIdentificador do Lote: LOT-0001\nContrato adequado para PME: Sim\nCobertura ACP (Acordo dos Contratos Públicos da Organização Mundial do Comércio): Não\nIdentificador do Lote: LOT-0002\nContrato adequado para PME: Sim\nCobertura ACP (Acordo dos Contratos Públicos da Organização Mundial do Comércio): Não\nIdentificador do Lote: LOT-0003\nContrato adequado para PME: Sim\nCobertura ACP (Acordo dos Contratos Públicos da Organização Mundial do Comércio): Não\nIdentificador do Lote: LOT-0004\nContrato adequado para PME: Sim\nCobertura ACP (Acordo dos Contratos Públicos da Organização Mundial do Comércio): Não\n\n27 - IDENTIFICAÇÃO E CONTACTOS DO ÓRGÃO DE RECURSOS ADMINISTRATIVOS\nDesignação: Conselho Administrativo\nEndereço: Praceta Maria Helena Vieira da Silva\nCódigo postal: 2835-220\nLocalidade: Vale da Amoreira\nTelefone: 212099970\nFax: \nEndereço eletrónico: diretor@esbb.pt\nPrazo de interposição do recurso: 5 dias\n\n28 - IDENTIFICAÇÃO DO(S) AUTOR(ES) DE ANÚNCIO\nNome: António Rocha\nCargo: assessor\n419588072",
    "nipc": "600075010",
    "distrito": "Setúbal",
    "concelho": "Moita",
    "freguesia": "União das Freguesias de Baixa da Banheira e Vale da Amoreira",
    "site": "www.aebbva.pt",
    "email": "diretor@esbb.pt",
    "designacao_contrato": "Aquisição, Instalação e Configuração da Infraestrutura Tecnológica, do Hardware, do Software e do Mobiliário Educativo e Didático",
    "descricao": "Aquisição, Instalação e Configuração da Infraestrutura Tecnológica, do Hardware, do Software e do Mobiliário Educativo e Didático",
    "preco_base": "60.000,00 EUR",
    "prazo_execucao": "120 DIAS",
    "prazo_apresentacao_propostas": "29-10-2025 23:59",
    "fundos_eu": "Não",
    "plataforma_eletronica": "ANOGOV",
    "url_procedimento": "https://www.anogov.com/ae-esbb/faces/",
    "autor_nome": "António Rocha",
    "autor_cargo": "assessor"
  },
  {
    "numero_procedimento": "N/A",
    "entidade": "Câmara Municipal de Aveiro",
    "link": "https://diariodarepublica.pt/dr/detalhe/contrato-publico/25871-937614436",
    "detalhes_completos": "1 - IDENTIFICAÇÃO E CONTACTOS DA ENTIDADE ADJUDICANTE\nDesignação da entidade adjudicante: Câmara Municipal de Aveiro\nNIPC: 505931192\nServiço/Órgão/Pessoa de contacto: Obras Municipais/ Júri do procedimento\nEndereço: Praça da República - Apartado 244\nCódigo postal: 3810-156\nLocalidade: Aveiro\nPaís: Portugal\nNUT III: PT16D\nDistrito: Aveiro\nConcelho: Aveiro\nFreguesia: União das Freguesias de Glória e Vera Cruz\nTelefone: 234406300\nFax: 234406301\nEndereço da Entidade (URL): www.cm-aveiro.pt\nEndereço Eletrónico: geral@cm-aveiro.pt\neDelivery Gateway (URL): https://www.acingov.pt\nFunção da Organização: Adquirente\nNorma jurídica da Entidade Adjudicante: Organismo de direito público\nÁrea de atividade da Autoridade Adjudicante: Serviços públicos das administrações públicas\n\n2 - JORNAL OFICIAL DA UNIÃO EUROPEIA\nO procedimento a que este anúncio diz respeito também é publicitado no Jornal Oficial da União Europeia? Não\n\n3 - AVISO\nModelo de Anúncio: Concurso público\nData de Envio do Anúncio: 01-10-2025\n\n5 - PROCESSO\nTipo de Procedimento: Concurso público\nPreço base do procedimento: Sim\nValor do preço base do procedimento: 2.300.000,00 EUR\nProcedimento com lotes? Não\n\n6 - OBJETO DO CONTRATO\nNúmero de referência interna: OM/CP/39/25\nDesignação do contrato: Reabilitação e Ampliação da Escola Básica de Sarrazola\nDescrição: Reabilitação e Ampliação da Escola Básica de Sarrazola\nTipo de Contrato Principal: Empreitada de Obras Públicas\nTipo de Contrato: Empreitada de Obras Públicas\nClassificação CPV (Vocabulário Comum para os Contratos Públicos)\nObjeto principal\nVocabulário Principal: 45214200\nPreço base s/IVA: 2.300.000,00 EUR\n\n7 - INDICAÇÕES ADICIONAIS\nO contrato envolve aquisição conjunta (satisfação de várias entidades)? Não\nO contrato é adjudicado por uma central de compras? Não\n\n8 - TÉCNICAS\nO concurso destina-se à celebração de um acordo-quadro? Inexistência de acordo-quadro\nÉ utilizado um leilão eletrónico? Não\nÉ adotada uma fase de negociação? Não\nSistema de Aquisição Dinâmico: Inexistência de sistema de aquisição dinâmico\n\n9 - LOCAL DA EXECUÇÃO DO CONTRATO\nLOCAL DA EXECUÇÃO DO CONTRATO (PROCEDIMENTO)\nPaís: Portugal\nNUT III: PT16D\nLocalidade: Freguesia de Cacia\nDistrito: Aveiro\nConcelho: Aveiro\nFreguesia: Freguesia de Cacia\n\n10 - PRAZO DE EXECUÇÃO DO CONTRATO\nPrazo de execução do contrato: 540 DIAS\nPrevisão de renovações: Não\n\n11 - FUNDOS EU\nTêm fundos EU? Não\n\n12 - DOCUMENTOS DE HABILITAÇÃO\nHabilitação para o exercício da atividade profissional: Sim\nTipo: Alvará\nDescrição: - 4ª Subcategoria da 1ª Categoria, de classe correspondente ao valor global da proposta;\n- 1ª Subcategorias da 1ª Categoria, de classe correspondente ao valor parcial da proposta;\n- 5ª e 12ª Subcategorias da 4ª Categoria, de classe correspondente ao valor parcial da proposta.\n\n13 - CONDIÇÕES DE APRESENTAÇÃO\nPlataforma eletrónica utilizada pela entidade adjudicante: ACIN\nURL para Apresentação: https://www.acingov.pt\nAdmissibilidade da apresentação de propostas variantes: Não autorizado\nPrazo para apresentação das propostas: 29-10-2025 17:00\nPrazo durante o qual os concorrentes são obrigados a manter as respetivas propostas: 120 dias a contar do termo do prazo para a apresentação das propostas\nIndicação de Subcontratação na Proposta: Inexistência de indicação de subcontratação\n\n14 - PRESTAÇÃO DE CAUÇÃO\nPrestação de caução: Sim\nPercentagem: 5%\nDescrição da Garantia Exigida: O valor da caução é de 5.00% do preço contratual.\n\n15 - FORNECIMENTO DAS PEÇAS DO CONCURSO, APRESENTAÇÃO DE PEDIDOS DE PARTICIPAÇÃO E APRESENTAÇÃO DAS PROPOSTAS\nLink para acesso às peças do concurso (URL): https://www.acingov.pt/acingovprod/2/zonaPublica/zona_publica_c/donwloadProcedurePiece/OTgxNzM5\n\n20 - OUTROS REQUISITOS\nInformação sobre contratos reservados. Aplica-se a contratos reservados (54º-A)? Não\n\n21 - CRITÉRIO DE ADJUDICAÇÃO\nMultifator: Não\nMonofator:\nNome: Preço\n\n24 - CONDIÇÕES DO CONTRATO\nFaturação Eletrónica: Permitido\nObrigação de Subcontratação:\nCódigo da Obrigação de Subcontratação: Não é aplicável nenhuma obrigação de subcontratação.\n\n25 - COMPRA PÚBLICA ESTRATÉGICA\nCompra Pública Estratégica: Inexistência de contratação pública estratégica\n\n26 - INFORMAÇÕES ADICIONAIS\nContrato adequado para PME: Sim\nCobertura ACP (Acordo dos Contratos Públicos da Organização Mundial do Comércio): Não\n\n27 - IDENTIFICAÇÃO E CONTACTOS DO ÓRGÃO DE RECURSOS ADMINISTRATIVOS\nDesignação: Câmara Municipal de Aveiro\nEndereço: Praça da República - Apartado 244\nCódigo postal: 3800-156\nLocalidade: Aveiro\nTelefone: 234406300\nFax: 234406301\nEndereço eletrónico: geral@cm-aveiro.pt\nPrazo de interposição do recurso: 5 dias\n\n28 - IDENTIFICAÇÃO DO(S) AUTOR(ES) DE ANÚNCIO\nNome: José Agostinho Ribau Esteves\nCargo: Presidente\n419584184",
    "nipc": "505931192",
    "distrito": "Aveiro",
    "concelho": "Aveiro",
    "freguesia": "União das Freguesias de Glória e Vera Cruz",
    "site": "www.cm-aveiro.pt",
    "email": "geral@cm-aveiro.pt",
    "designacao_contrato": "Reabilitação e Ampliação da Escola Básica de Sarrazola",
    "descricao": "Reabilitação e Ampliação da Escola Básica de Sarrazola",
    "preco_base": "2.300.000,00 EUR",
    "prazo_execucao": "540 DIAS",
    "prazo_apresentacao_propostas": "29-10-2025 17:00",
    "fundos_eu": "Não",
    "plataforma_eletronica": "ACIN",
    "url_procedimento": "https://www.acingov.pt",
    "autor_nome": "José Agostinho Ribau Esteves",
    "autor_cargo": "Presidente"
  },
  {
    "numero_procedimento": "N/A",
    "entidade": "Companhia Carris de Ferro de Lisboa (CARRIS)",
    "link": "https://diariodarepublica.pt/dr/detalhe/contrato-publico/25872-937614437",
    "detalhes_completos": "Alteração do Anúncio de procedimento n.º 23054/2025, de 2025-08-29, com o ID 419471731\n\n1 - IDENTIFICAÇÃO E CONTACTOS DA ENTIDADE ADJUDICANTE\nDesignação da entidade adjudicante: Companhia Carris de Ferro de Lisboa (CARRIS)\nNIPC: 500595313\nEndereço: Alameda António Sérgio, N.º 62\nCódigo postal: 2795-221\nLocalidade: Lisboa\nPaís: Portugal\nNUT III: PT170\nDistrito: Lisboa\nConcelho: Lisboa\nFreguesia: Todas\nTelefone: 213613000\nEndereço da Entidade (URL): www.carris.pt\nEndereço Eletrónico: vitor.guedes@carris.pt\neDelivery Gateway (URL): https://community.vortal.biz/public/\nFunção da Organização: Adquirente\nNorma jurídica da Entidade Adjudicante: Empresa pública, controlada por uma autoridade local\nÁrea de atividade da Entidade Adjudicante: Serviços urbanos de caminho de ferro, de elétricos, de tróleis ou de autocarros\n\n2 - JORNAL OFICIAL DA UNIÃO EUROPEIA\nO procedimento a que este anúncio diz respeito também é publicitado no Jornal Oficial da União Europeia? Sim\n\n3 - AVISO\nModelo de Anúncio: Concurso público\nData de Envio do Anúncio: 29-09-2025\n\n5 - PROCESSO\nTipo de Procedimento: Concurso público\nPreço base do procedimento: Sim\nValor do preço base do procedimento: 1.785.000,00 EUR\nProcedimento com lotes? Não\n\n6 - OBJETO DO CONTRATO\nNúmero de referência interna: 032/2025\nDesignação do contrato: 032/2025 - Aquisição de Equipamentos, Serviços de Instalação e Manutenção – Paragem Digital para Painéis de Informação ao Público\nDescrição: 032/2025 - Aquisição de Equipamentos, Serviços de Instalação e Manutenção – Paragem Digital para Painéis de Informação ao Público\nOpções: Não\nTipo de Contrato Principal: Aquisição de Bens Móveis\nTipo de Contrato: Aquisição de Bens Móveis\nClassificação CPV (Vocabulário Comum para os Contratos Públicos)\nObjeto principal\nVocabulário Principal: 34924000\nPreço base s/IVA: 1.785.000,00 EUR\n\n7 - INDICAÇÕES ADICIONAIS\nO contrato envolve aquisição conjunta (satisfação de várias entidades)? Não\nO contrato é adjudicado por uma central de compras? Não\n\n8 - TÉCNICAS\nO concurso destina-se à celebração de um acordo-quadro? Inexistência de acordo-quadro\nÉ utilizado um leilão eletrónico? Não\nÉ adotada uma fase de negociação? Não\nSistema de Aquisição Dinâmico: Inexistência de sistema de aquisição dinâmico\n\n9 - LOCAL DA EXECUÇÃO DO CONTRATO\nLOCAL DA EXECUÇÃO DO CONTRATO (PROCEDIMENTO)\nPaís: Portugal\nNUT III: PT170\nLocalidade: Lisboa\nDistrito: Lisboa\nConcelho: Oeiras\nFreguesia: Todas\n\n10 - PRAZO DE EXECUÇÃO DO CONTRATO\nPrazo de execução do contrato: 67 MESES\nPrevisão de renovações: Não\n\n11 - FUNDOS EU\nTêm fundos EU? Não\n\n12 - DOCUMENTOS DE HABILITAÇÃO\nHabilitação para o exercício da atividade profissional: Não\n\n13 - CONDIÇÕES DE APRESENTAÇÃO\nPlataforma eletrónica utilizada pela entidade adjudicante: VORTAL\nURL para Apresentação: https://community.vortal.biz/public/\nAdmissibilidade da apresentação de propostas variantes: Não autorizado\nPrazo para apresentação das propostas: 13-10-2025 17:59\nPrazo durante o qual os concorrentes são obrigados a manter as respetivas propostas: 180 dias a contar do termo do prazo para a apresentação das propostas\nApresentação de Catálogo Eletrónico: Permitido\nIndicação de Subcontratação na Proposta: Inexistência de indicação de subcontratação\n\n14 - PRESTAÇÃO DE CAUÇÃO\nPrestação de caução: Sim\nPercentagem: 5%\nDescrição da Garantia Exigida: Guia de depósito, garantia bancária e seguro-caução\n\n15 - FORNECIMENTO DAS PEÇAS DO CONCURSO, APRESENTAÇÃO DE PEDIDOS DE PARTICIPAÇÃO E APRESENTAÇÃO DAS PROPOSTAS\nLink para acesso às peças do concurso (URL): https://community.vortal.biz/Public/public-tender-documents/anZ2dFBjYUEwbGgxc2Z2OFZaTlNtVndBYTRUN0pqbDk1OFQ1Um5wbklQbm0yYmtRaWNQSlZzVnNITmhMcmE0b09JOTFsejZleXJwb1N3TVRzMXM5eFE9PXJtUzkr\n\n20 - OUTROS REQUISITOS\nInformação sobre contratos reservados. Aplica-se a contratos reservados (54º-A)? Não\n\n21 - CRITÉRIO DE ADJUDICAÇÃO\nMultifator: Não\nMonofator:\nNome: Qualidade\n\n24 - CONDIÇÕES DO CONTRATO\nFaturação Eletrónica: Permitido\nObrigação de Subcontratação:\nCódigo da Obrigação de Subcontratação: Não é aplicável nenhuma obrigação de subcontratação.\n\n25 - COMPRA PÚBLICA ESTRATÉGICA\nCompra Pública Estratégica: Inexistência de contratação pública estratégica\n\n26 - INFORMAÇÕES ADICIONAIS\nContrato adequado para PME: Sim\nCobertura ACP (Acordo dos Contratos Públicos da Organização Mundial do Comércio): Não\n\n27 - IDENTIFICAÇÃO E CONTACTOS DO ÓRGÃO DE RECURSOS ADMINISTRATIVOS\nDesignação: Conselho de Administração\nEndereço: Rua 1.º de Maio, n.º 103\nCódigo postal: 1300-472\nLocalidade: Lisboa\nTelefone: +351 213613000\nFax: +351 213613000\nEndereço eletrónico: contratacaopublica@carris.pt\n\n28 - IDENTIFICAÇÃO DO(S) AUTOR(ES) DE ANÚNCIO\nNome: Ana Tomás\nCargo: Técnico Superior\n\n29 - ALTERAÇÃO\nMotivo da Alteração: Correção pelo editor\nIdentificador da Versão do Anúncio a Alterar: e87fa320-d8ac-4bdf-a6a0-41e304cbc920-01\nIdentificador das Secções Alteradas do Anúncio Anterior: Condições de Apresentação\nAlteração dos Documentos do Concurso: Não\n419590923",
    "nipc": "500595313",
    "distrito": "Lisboa",
    "concelho": "Lisboa",
    "freguesia": "Todas",
    "site": "www.carris.pt",
    "email": "vitor.guedes@carris.pt",
    "designacao_contrato": "032/2025 - Aquisição de Equipamentos, Serviços de Instalação e Manutenção – Paragem Digital para Painéis de Informação ao Público",
    "descricao": "032/2025 - Aquisição de Equipamentos, Serviços de Instalação e Manutenção – Paragem Digital para Painéis de Informação ao Público",
    "preco_base": "1.785.000,00 EUR",
    "prazo_execucao": "67 MESES",
    "prazo_apresentacao_propostas": "13-10-2025 17:59",
    "fundos_eu": "Não",
    "plataforma_eletronica": "VORTAL",
    "url_procedimento": "https://community.vortal.biz/public/",
    "autor_nome": "Ana Tomás",
    "autor_cargo": "Técnico Superior"
  },
  {
    "numero_procedimento": "N/A",
    "entidade": "Município de Cinfães",
    "link": "https://diariodarepublica.pt/dr/detalhe/contrato-publico/25873-937614441",
    "detalhes_completos": "1 - IDENTIFICAÇÃO E CONTACTOS DA ENTIDADE ADJUDICANTE\nDesignação da entidade adjudicante: Município de Cinfães\nNIPC: 506693651\nEndereço: Paços do Concelho\nCódigo postal: 4690-030\nLocalidade: Cinfães\nPaís: Portugal\nNUT III: PT11C\nDistrito: Viseu\nConcelho: Cinfães\nFreguesia: Todas\nTelefone: 255560560\nFax: 255560569\nEndereço da Entidade (URL): www.cm-cinfaes.pt\nEndereço Eletrónico: geral.vortal@cm-cinfaes.pt\neDelivery Gateway (URL): https://community.vortal.biz/public/\nFunção da Organização: Adquirente\nNorma jurídica da Entidade Adjudicante: Autoridade da administração central\nÁrea de atividade da Autoridade Adjudicante: Serviços públicos das administrações públicas\n\n2 - JORNAL OFICIAL DA UNIÃO EUROPEIA\nO procedimento a que este anúncio diz respeito também é publicitado no Jornal Oficial da União Europeia? Sim\n\n3 - AVISO\nModelo de Anúncio: Concurso público\nData de Envio do Anúncio: 29-09-2025\n\n5 - PROCESSO\nTipo de Procedimento: Concurso público\nPreço base do procedimento: Sim\nValor do preço base do procedimento: 360.000,00 EUR\nProcedimento com lotes? Não\n\n6 - OBJETO DO CONTRATO\nNúmero de referência interna: 88/2025\nDesignação do contrato: Aquisição de autocarro elétrico\nDescrição: Aquisição de autocarro elétrico\nOpções: Não\nTipo de Contrato Principal: Aquisição de Bens Móveis\nTipo de Contrato: Aquisição de Bens Móveis\nClassificação CPV (Vocabulário Comum para os Contratos Públicos)\nObjeto principal\nVocabulário Principal: 34121000\nPreço base s/IVA: 360.000,00 EUR\n\n7 - INDICAÇÕES ADICIONAIS\nO contrato envolve aquisição conjunta (satisfação de várias entidades)? Não\nO contrato é adjudicado por uma central de compras? Não\n\n8 - TÉCNICAS\nO concurso destina-se à celebração de um acordo-quadro? Inexistência de acordo-quadro\nÉ utilizado um leilão eletrónico? Não\nÉ adotada uma fase de negociação? Não\nSistema de Aquisição Dinâmico: Inexistência de sistema de aquisição dinâmico\n\n9 - LOCAL DA EXECUÇÃO DO CONTRATO\nLOCAL DA EXECUÇÃO DO CONTRATO (PROCEDIMENTO)\nPaís: Portugal\nNUT III: PT11C\nLocalidade: Viseu\nDistrito: Viseu\nConcelho: Cinfães\nFreguesia: Freguesia de Cinfães\n\n10 - PRAZO DE EXECUÇÃO DO CONTRATO\nPrazo de execução do contrato: 180 DIAS\nPrevisão de renovações: Não\n\n11 - FUNDOS EU\nTêm fundos EU? Sim\n\n12 - DOCUMENTOS DE HABILITAÇÃO\nHabilitação para o exercício da atividade profissional: Não\n\n13 - CONDIÇÕES DE APRESENTAÇÃO\nPlataforma eletrónica utilizada pela entidade adjudicante: VORTAL\nURL para Apresentação: https://community.vortal.biz/public/\nAdmissibilidade da apresentação de propostas variantes: Não autorizado\nPrazo para apresentação das propostas: 29-10-2025 17:00\nPrazo durante o qual os concorrentes são obrigados a manter as respetivas propostas: 90 dias a contar do termo do prazo para a apresentação das propostas\nApresentação de Catálogo Eletrónico: Não autorizado\nIndicação de Subcontratação na Proposta: Inexistência de indicação de subcontratação\n\n14 - PRESTAÇÃO DE CAUÇÃO\nPrestação de caução: Não\n\n15 - FORNECIMENTO DAS PEÇAS DO CONCURSO, APRESENTAÇÃO DE PEDIDOS DE PARTICIPAÇÃO E APRESENTAÇÃO DAS PROPOSTAS\nLink para acesso às peças do concurso (URL): https://community.vortal.biz/Public/public-tender-documents/NHlIcDVJckVDNUI2NW5BNTNqZVV3WVlRWENLVGYwaUwvaVVNcEMxZUgwTWkxRHVza3hDbUJ5alFDcW5EaU0vQmdYbFhNU1RxZXNFQ3ZGblRON2pSeEE9PVJLbyZ2\n\n20 - OUTROS REQUISITOS\nInformação sobre contratos reservados. Aplica-se a contratos reservados (54º-A)? Não\n\n21 - CRITÉRIO DE ADJUDICAÇÃO\nMultifator: Não\nMonofator:\nNome: Outros\nOutro nome: Preço\n\n24 - CONDIÇÕES DO CONTRATO\nFaturação Eletrónica: Permitido\nObrigação de Subcontratação:\nCódigo da Obrigação de Subcontratação: Não é aplicável nenhuma obrigação de subcontratação.\n\n25 - COMPRA PÚBLICA ESTRATÉGICA\nCompra Pública Estratégica: Redução dos impactos ambientais\nDescrição do Processo de Adjudicação Estratégico: Conforme as peças do procedimento\nCritérios de contratos Públicos Ecológicos: Critérios de contratação pública ecológica nacional\nCategorias da estratégia nacional: Transporte rodoviário\nDiretiva Veículos Não Poluentes: Não\nCritério de Acessibilidade: Os critérios de acessibilidade para as pessoas com deficiência estão incluídos\n\n26 - INFORMAÇÕES ADICIONAIS\nContrato adequado para PME: Sim\nCobertura ACP (Acordo dos Contratos Públicos da Organização Mundial do Comércio): Não\n\n27 - IDENTIFICAÇÃO E CONTACTOS DO ÓRGÃO DE RECURSOS ADMINISTRATIVOS\nDesignação: Câmara Municipal de Cinfãs\nEndereço: Praça do Município\nCódigo postal: 4690-030\nLocalidade: Cinfães\nTelefone: +351 255560560\nFax: +351 255560569\nEndereço eletrónico: aprovisionamento@cm-cinfaes.pt\n\n28 - IDENTIFICAÇÃO DO(S) AUTOR(ES) DE ANÚNCIO\nNome: Bruno Santos\nCargo: Chefe da Equipa Multidisciplinar de Contratação Estratégica e Gestão Dinâmica da Frota Municipal,\n419586363",
    "nipc": "506693651",
    "distrito": "Viseu",
    "concelho": "Cinfães",
    "freguesia": "Todas",
    "site": "www.cm-cinfaes.pt",
    "email": "geral.vortal@cm-cinfaes.pt",
    "designacao_contrato": "Aquisição de autocarro elétrico",
    "descricao": "Aquisição de autocarro elétrico",
    "preco_base": "360.000,00 EUR",
    "prazo_execucao": "180 DIAS",
    "prazo_apresentacao_propostas": "29-10-2025 17:00",
    "fundos_eu": "Sim",
    "plataforma_eletronica": "VORTAL",
    "url_procedimento": "https://community.vortal.biz/public/",
    "autor_nome": "Bruno Santos",
    "autor_cargo": "Chefe da Equipa Multidisciplinar de Contratação Estratégica e Gestão Dinâmica da Frota Municipal,"
  },
  {
    "numero_procedimento": "N/A",
    "entidade": "FUNDAÇÃO COI",
    "link": "https://diariodarepublica.pt/dr/detalhe/contrato-publico/25874-937614442",
    "detalhes_completos": "1 - IDENTIFICAÇÃO E CONTACTOS DA ENTIDADE ADJUDICANTE\nDesignação da entidade adjudicante: FUNDAÇÃO COI\nNIPC: 507411978\nServiço/Órgão/Pessoa de contacto: Conselho de Administração\nEndereço: Av. Zeca Afonso\nCódigo postal: 2955-220\nLocalidade: Setúbal\nPaís: Portugal\nNUT III: PT170\nDistrito: Setúbal\nConcelho: Palmela\nFreguesia: Freguesia de Pinhal Novo\nTelefone: 212362302 \nFax: 212387741\nEndereço da Entidade (URL): www.fundacao-coi.pt\nEndereço Eletrónico: fundacao@fundacao-coi.pt\neDelivery Gateway (URL): https://community.vortal.biz/public/\nFunção da Organização: Adquirente\nNorma jurídica da Entidade Adjudicante: Organismo de direito público\nÁrea de atividade da Autoridade Adjudicante: Habitação e equipamentos coletivos\n\n2 - JORNAL OFICIAL DA UNIÃO EUROPEIA\nO procedimento a que este anúncio diz respeito também é publicitado no Jornal Oficial da União Europeia? Não\n\n3 - AVISO\nModelo de Anúncio: Concurso público\nData de Envio do Anúncio: 01-10-2025\n\n5 - PROCESSO\nTipo de Procedimento: Concurso público\nPreço base do procedimento: Sim\nValor do preço base do procedimento: 3.600.000,00 EUR\nProcedimento com lotes? Não\n\n6 - OBJETO DO CONTRATO\nNúmero de referência interna: CP 01/2025\nDesignação do contrato: Empreitada de \"Construção de uma Unidade de Cuidados Continuados Integrados (UCCI)\" \nDescrição: Empreitada de \"Construção de uma Unidade de Cuidados Continuados Integrados (UCCI)\" \nTipo de Contrato Principal: Empreitada de Obras Públicas\nTipo de Contrato: Empreitada de Obras Públicas\nClassificação CPV (Vocabulário Comum para os Contratos Públicos)\nObjeto principal\nVocabulário Principal: 45210000\nPreço base s/IVA: 3.600.000,00 EUR\n\n7 - INDICAÇÕES ADICIONAIS\nO contrato envolve aquisição conjunta (satisfação de várias entidades)? Não\nO contrato é adjudicado por uma central de compras? Não\n\n8 - TÉCNICAS\nO concurso destina-se à celebração de um acordo-quadro? Inexistência de acordo-quadro\nÉ utilizado um leilão eletrónico? Não\nÉ adotada uma fase de negociação? Não\nSistema de Aquisição Dinâmico: Inexistência de sistema de aquisição dinâmico\n\n9 - LOCAL DA EXECUÇÃO DO CONTRATO\nLOCAL DA EXECUÇÃO DO CONTRATO (PROCEDIMENTO)\nPaís: Portugal\nNUT III: PT170\nLocalidade: Setúbal\nDistrito: Setúbal\nConcelho: Palmela\nFreguesia: Freguesia de Pinhal Novo\n\n10 - PRAZO DE EXECUÇÃO DO CONTRATO\nPrazo de execução do contrato: 365 DIAS\nPrevisão de renovações: Não\n\n11 - FUNDOS EU\nTêm fundos EU? Não\n\n12 - DOCUMENTOS DE HABILITAÇÃO\nHabilitação para o exercício da atividade profissional: Sim\nTipo: Alvará\nDescrição:  Alvarás ou os títulos de registo emitidos pelo Instituto da Construção e do Imobiliário, I. P., contendo as seguintes habilitações necessárias à execução do contrato pelo adjudicatário ou por empresa do agrupamento adjudicatário: \ni)Alvará de EOP da 1ª Subcategoria da 1ª Categoria em classe de habilitações que cubra a totalidade do valor da proposta;\nii) Restantes Alvarás e Certificados de EOP necessários para a prossecução dos trabalhos em classe de habilitações que cubram os respetivos preços parciais da proposta apresentada. \n\n13 - CONDIÇÕES DE APRESENTAÇÃO\nPlataforma eletrónica utilizada pela entidade adjudicante: VORTAL\nURL para Apresentação: https://community.vortal.biz/public/\nAdmissibilidade da apresentação de propostas variantes: Não autorizado\nPrazo para apresentação das propostas: 31-10-2025 23:59\nPrazo durante o qual os concorrentes são obrigados a manter as respetivas propostas: 90 dias a contar do termo do prazo para a apresentação das propostas\nIndicação de Subcontratação na Proposta: Inexistência de indicação de subcontratação\n\n14 - PRESTAÇÃO DE CAUÇÃO\nPrestação de caução: Sim\nPercentagem: 5%\nDescrição da Garantia Exigida: A caução  deve ser prestada por depósito em dinheiro, conforme  modelo constante no Anexo V ao presente programa do concurso, ou em títulos emitidos ou  garantidos pelo Estado, ou mediante garantia bancária autónoma e irrevogável e à primeira  solicitação, ou ainda por seguro-caução à primeira solic\n\n15 - FORNECIMENTO DAS PEÇAS DO CONCURSO, APRESENTAÇÃO DE PEDIDOS DE PARTICIPAÇÃO E APRESENTAÇÃO DAS PROPOSTAS\nLink para acesso às peças do concurso (URL): https://community.vortal.biz/Public/public-tender-documents/NVZyQzJiY2lDMjhSSGxhVEIybjNwazFveS9xa2FGWmxZQks2SWpUZ1kxVlZsN0RlMVRzZmNCOG1rdVpMeFpTelpCenVhMktTdkltWkhzY1k3eHBzZXc9PSpsTTVf\n\n20 - OUTROS REQUISITOS\nInformação sobre contratos reservados. Aplica-se a contratos reservados (54º-A)? Não\n\n21 - CRITÉRIO DE ADJUDICAÇÃO\nMultifator: Não\nMonofator:\nNome: Outros\nOutro nome: Preço\n\n24 - CONDIÇÕES DO CONTRATO\nFaturação Eletrónica: Permitido\nObrigação de Subcontratação:\nCódigo da Obrigação de Subcontratação: Não é aplicável nenhuma obrigação de subcontratação.\n\n25 - COMPRA PÚBLICA ESTRATÉGICA\nCompra Pública Estratégica: Inexistência de contratação pública estratégica\n\n26 - INFORMAÇÕES ADICIONAIS\nContrato adequado para PME: Sim\nCobertura ACP (Acordo dos Contratos Públicos da Organização Mundial do Comércio): Não\n\n27 - IDENTIFICAÇÃO E CONTACTOS DO ÓRGÃO DE RECURSOS ADMINISTRATIVOS\nDesignação: Conselho de Administração\nEndereço: Av. Zeca Afonso\nCódigo postal: 2955-220\nLocalidade: Palmela\nTelefone: +351 212362302\nFax: +351 212387741\nEndereço eletrónico: fundacao@fundacao-coi.pt\n\n28 - IDENTIFICAÇÃO DO(S) AUTOR(ES) DE ANÚNCIO\nNome: Carlos Marques Taleço\nCargo: Presidente do Conselho de Administração\n419602668",
    "nipc": "507411978",
    "distrito": "Setúbal",
    "concelho": "Palmela",
    "freguesia": "Freguesia de Pinhal Novo",
    "site": "www.fundacao-coi.pt",
    "email": "fundacao@fundacao-coi.pt",
    "designacao_contrato": "Empreitada de \"Construção de uma Unidade de Cuidados Continuados Integrados (UCCI)\"",
    "descricao": "Empreitada de \"Construção de uma Unidade de Cuidados Continuados Integrados (UCCI)\"",
    "preco_base": "3.600.000,00 EUR",
    "prazo_execucao": "365 DIAS",
    "prazo_apresentacao_propostas": "31-10-2025 23:59",
    "fundos_eu": "Não",
    "plataforma_eletronica": "VORTAL",
    "url_procedimento": "https://community.vortal.biz/public/",
    "autor_nome": "Carlos Marques Taleço",
    "autor_cargo": "Presidente do Conselho de Administração"
  },
  {
    "numero_procedimento": "N/A",
    "entidade": "Câmara Municipal de Matosinhos",
    "link": "https://diariodarepublica.pt/dr/detalhe/contrato-publico/25875-937614443",
    "detalhes_completos": "1 - IDENTIFICAÇÃO E CONTACTOS DA ENTIDADE ADJUDICANTE\nDesignação da entidade adjudicante: Câmara Municipal de Matosinhos\nNIPC: 501305912\nServiço/Órgão/Pessoa de contacto: Divisão de Contratação Pública\nEndereço: Av. D. Afonso Henriques\nCódigo postal: 4454-510\nLocalidade: Matosinhos\nPaís: Portugal\nNUT III: PT11A\nDistrito: Porto\nConcelho: Matosinhos\nFreguesia: Todas\nTelefone: 229390900\nFax: 229351645\nEndereço da Entidade (URL): http://www.cm-matosinhos.pt\nEndereço Eletrónico: contratacaopublica@cm-matosinhos.pt\neDelivery Gateway (URL): https://www.acingov.pt\nFunção da Organização: Adquirente\nSubfunção da Organização: Organização que recebe as propostas\nNorma jurídica da Entidade Adjudicante: Organismo de direito público\nÁrea de atividade da Autoridade Adjudicante: Serviços públicos das administrações públicas\n\n2 - JORNAL OFICIAL DA UNIÃO EUROPEIA\nO procedimento a que este anúncio diz respeito também é publicitado no Jornal Oficial da União Europeia? Não\n\n3 - AVISO\nModelo de Anúncio: Concurso público\nData de Envio do Anúncio: 01-10-2025\n\n5 - PROCESSO\nTipo de Procedimento: Concurso público\nPreço base do procedimento: Sim\nValor do preço base do procedimento: 43.419,20 EUR\nProcedimento com lotes? Não\n\n6 - OBJETO DO CONTRATO\nNúmero de referência interna: CP/70/2025 (EDOC/2025/27672)\nDesignação do contrato: AQUISIÇÃO DE SINALÉTICA INFORMATIVA PARA INSTALAÇÃO EM PARQUES DO CONCELHO\nDescrição: AQUISIÇÃO DE SINALÉTICA INFORMATIVA PARA INSTALAÇÃO EM PARQUES DO CONCELHO\nTipo de Contrato Principal: Aquisição de Bens Móveis\nTipo de Contrato: Aquisição de Bens Móveis\nClassificação CPV (Vocabulário Comum para os Contratos Públicos)\nObjeto principal\nVocabulário Principal: 34928000\nPreço base s/IVA: 43.419,20 EUR\n\n7 - INDICAÇÕES ADICIONAIS\nO contrato envolve aquisição conjunta (satisfação de várias entidades)? Não\nO contrato é adjudicado por uma central de compras? Não\n\n8 - TÉCNICAS\nO concurso destina-se à celebração de um acordo-quadro? Inexistência de acordo-quadro\nÉ utilizado um leilão eletrónico? Não\nÉ adotada uma fase de negociação? Não\nSistema de Aquisição Dinâmico: Inexistência de sistema de aquisição dinâmico\n\n9 - LOCAL DA EXECUÇÃO DO CONTRATO\nLOCAL DA EXECUÇÃO DO CONTRATO (PROCEDIMENTO)\nPaís: Portugal\nNUT III: PT11A\nLocalidade: Matosinhos\nDistrito: Porto\nConcelho: Matosinhos\nFreguesia: Todas\n\n10 - PRAZO DE EXECUÇÃO DO CONTRATO\nPrazo de execução do contrato: 60 DIAS\nPrevisão de renovações: Não\n\n11 - FUNDOS EU\nTêm fundos EU? Não\n\n12 - DOCUMENTOS DE HABILITAÇÃO\nHabilitação para o exercício da atividade profissional: Não\n\n13 - CONDIÇÕES DE APRESENTAÇÃO\nPlataforma eletrónica utilizada pela entidade adjudicante: ACIN\nURL para Apresentação: https://www.acingov.pt\nAdmissibilidade da apresentação de propostas variantes: Não autorizado\nPrazo para apresentação das propostas: 10-10-2025 23:59\nPrazo durante o qual os concorrentes são obrigados a manter as respetivas propostas: 66 dias a contar do termo do prazo para a apresentação das propostas\nIndicação de Subcontratação na Proposta: Inexistência de indicação de subcontratação\n\n14 - PRESTAÇÃO DE CAUÇÃO\nPrestação de caução: Não\n\n15 - FORNECIMENTO DAS PEÇAS DO CONCURSO, APRESENTAÇÃO DE PEDIDOS DE PARTICIPAÇÃO E APRESENTAÇÃO DAS PROPOSTAS\nLink para acesso às peças do concurso (URL): https://www.acingov.pt/acingovprod/2/zonaPublica/zona_publica_c/donwloadProcedurePiece/OTgyNDcz\n\n20 - OUTROS REQUISITOS\nInformação sobre contratos reservados. Aplica-se a contratos reservados (54º-A)? Não\n\n21 - CRITÉRIO DE ADJUDICAÇÃO\nMultifator: Não\nMonofator:\nNome: Preço\n\n24 - CONDIÇÕES DO CONTRATO\nFaturação Eletrónica: Não autorizado\nObrigação de Subcontratação:\nCódigo da Obrigação de Subcontratação: Não é aplicável nenhuma obrigação de subcontratação.\n\n25 - COMPRA PÚBLICA ESTRATÉGICA\nCompra Pública Estratégica: Inexistência de contratação pública estratégica\n\n26 - INFORMAÇÕES ADICIONAIS\nContrato adequado para PME: Não\nCobertura ACP (Acordo dos Contratos Públicos da Organização Mundial do Comércio): Não\n\n27 - IDENTIFICAÇÃO E CONTACTOS DO ÓRGÃO DE RECURSOS ADMINISTRATIVOS\nDesignação: Câmara Municipal\nEndereço: Av. D. Afonso Henriques\nCódigo postal: 4450-510\nLocalidade: Matosinhos\nTelefone: 229390900\nFax: \nEndereço eletrónico: contratacaopublica@cm-matosinhos.pt\nPrazo de interposição do recurso: 5 dias\n\n28 - IDENTIFICAÇÃO DO(S) AUTOR(ES) DE ANÚNCIO\nNome: Luísa Maria Neves Salgueiro\nCargo: Presidente da Câmara\n419593142",
    "nipc": "501305912",
    "distrito": "Porto",
    "concelho": "Matosinhos",
    "freguesia": "Todas",
    "site": "http://www.cm-matosinhos.pt",
    "email": "contratacaopublica@cm-matosinhos.pt",
    "designacao_contrato": "AQUISIÇÃO DE SINALÉTICA INFORMATIVA PARA INSTALAÇÃO EM PARQUES DO CONCELHO",
    "descricao": "AQUISIÇÃO DE SINALÉTICA INFORMATIVA PARA INSTALAÇÃO EM PARQUES DO CONCELHO",
    "preco_base": "43.419,20 EUR",
    "prazo_execucao": "60 DIAS",
    "prazo_apresentacao_propostas": "10-10-2025 23:59",
    "fundos_eu": "Não",
    "plataforma_eletronica": "ACIN",
    "url_procedimento": "https://www.acingov.pt",
    "autor_nome": "Luísa Maria Neves Salgueiro",
    "autor_cargo": "Presidente da Câmara"
  },
  {
    "numero_procedimento": "N/A",
    "entidade": "Unidade Local de Saúde do Alentejo Central, E.P.E",
    "link": "https://diariodarepublica.pt/dr/detalhe/contrato-publico/25876-937614444",
    "detalhes_completos": "1 - IDENTIFICAÇÃO E CONTACTOS DA ENTIDADE ADJUDICANTE\nDesignação da entidade adjudicante: Unidade Local de Saúde do Alentejo Central, E.P.E\nNIPC: 508085888\nEndereço: Largo Sr. da Pobreza\nCódigo postal: 7000-811\nLocalidade: Évora\nPaís: Portugal\nNUT III: PT187\nDistrito: Évora\nConcelho: Évora\nFreguesia: Todas\nTelefone: 266740111\nFax: 266744212\nEndereço da Entidade (URL): www.hevora.min-saude.pt\nEndereço Eletrónico: concursos.aprov@ulsac.min-saude.pt\neDelivery Gateway (URL): https://community.vortal.biz/public/\nFunção da Organização: Adquirente\nNorma jurídica da Entidade Adjudicante: Organismo de direito público\nÁrea de atividade da Autoridade Adjudicante: Saúde\n\n2 - JORNAL OFICIAL DA UNIÃO EUROPEIA\nO procedimento a que este anúncio diz respeito também é publicitado no Jornal Oficial da União Europeia? Não\n\n3 - AVISO\nModelo de Anúncio: Concurso público\nData de Envio do Anúncio: 01-10-2025\n\n5 - PROCESSO\nTipo de Procedimento: Concurso público\nPreço base do procedimento: Sim\nValor do preço base do procedimento: 124.000,00 EUR\nProcedimento com lotes? Sim\nNº Máx. de Lotes Autorizado: 3\nNúmero máximo de lotes que podem ser adjudicados a um concorrente: 3\n\n6 - OBJETO DO CONTRATO\nNúmero de referência interna: 180116.25\nDesignação do contrato: Equipamentos para Serviço de Neonatologia\nDescrição: Aquisição de Equipamentos para Serviço de Neonatologia\nTipo de Contrato Principal: Aquisição de Bens Móveis\nTipo de Contrato: Aquisição de Bens Móveis\nClassificação CPV (Vocabulário Comum para os Contratos Públicos)\nObjeto principal\nVocabulário Principal: 33100000\nPreço base s/IVA: 124.000,00 EUR\nLotes: \nNº: LOT-0001\nDescrição do Lote: Lote 1\nPreço base s/IVA: 32.000,00 EUR\nClassificação CPV (Vocabulário Comum para os Contratos Públicos)\nObjeto principal\nVocabulário Principal: 33100000\nNº: LOT-0002\nDescrição do Lote: Lote 2\nPreço base s/IVA: 32.000,00 EUR\nClassificação CPV (Vocabulário Comum para os Contratos Públicos)\nObjeto principal\nVocabulário Principal: 33100000\nNº: LOT-0003\nDescrição do Lote: Lote 3\nPreço base s/IVA: 60.000,00 EUR\nClassificação CPV (Vocabulário Comum para os Contratos Públicos)\nObjeto principal\nVocabulário Principal: 33100000\n\n7 - INDICAÇÕES ADICIONAIS\nO contrato envolve aquisição conjunta (satisfação de várias entidades)? Não\nO contrato é adjudicado por uma central de compras? Não\n\n8 - TÉCNICAS\nO concurso destina-se à celebração de um acordo-quadro? Inexistência de acordo-quadro\nÉ utilizado um leilão eletrónico? Não\nÉ adotada uma fase de negociação? Não\nSistema de Aquisição Dinâmico: Inexistência de sistema de aquisição dinâmico\n\n9 - LOCAL DA EXECUÇÃO DO CONTRATO\nLOCAL DA EXECUÇÃO DO CONTRATO (PROCEDIMENTO)\nPaís: Portugal\nNUT III: PT187\nLocalidade: Évora\nDistrito: Évora\nConcelho: Évora\nFreguesia: União das Freguesias de Évora (São Mamede, Sé, São Pedro e Santo Antão)\nLOCAL DA EXECUÇÃO DO CONTRATO (LOTE)\nIdentificador do Lote: LOT-0001; LOT-0002; LOT-0003\nPaís: Portugal\nNUT III: PT187\nLocalidade: Évora\nDistrito: Évora\nConcelho: Évora\nFreguesia: União das Freguesias de Évora (São Mamede, Sé, São Pedro e Santo Antão)\n\n10 - PRAZO DE EXECUÇÃO DO CONTRATO\nIdentificador do Lote: LOT-0001; LOT-0002; LOT-0003\nPrazo de execução do contrato: 20 DIAS\nPrevisão de renovações: Não\n\n11 - FUNDOS EU\nIdentificador do Lote: LOT-0001; LOT-0002; LOT-0003\nTêm fundos EU? Não\n\n12 - DOCUMENTOS DE HABILITAÇÃO\nHabilitação para o exercício da atividade profissional: Não\n\n13 - CONDIÇÕES DE APRESENTAÇÃO\nPlataforma eletrónica utilizada pela entidade adjudicante: VORTAL\nURL para Apresentação: https://community.vortal.biz/public/\nAdmissibilidade da apresentação de propostas variantes: Não autorizado\nPrazo para apresentação das propostas: 16-10-2025 18:00\nPrazo durante o qual os concorrentes são obrigados a manter as respetivas propostas: 120 dias a contar do termo do prazo para a apresentação das propostas\nIndicação de Subcontratação na Proposta: Inexistência de indicação de subcontratação\n\n14 - PRESTAÇÃO DE CAUÇÃO\nPrestação de caução: Não\n\n15 - FORNECIMENTO DAS PEÇAS DO CONCURSO, APRESENTAÇÃO DE PEDIDOS DE PARTICIPAÇÃO E APRESENTAÇÃO DAS PROPOSTAS\nLink para acesso às peças do concurso (URL): https://community.vortal.biz/Public/public-tender-documents/UmdNQUd0VzV3Q3NicnRzb0FjczJkTUJGcXJaaldhdUE3Mkk5NncyWFhpVkNncG9pWThZaUZWSTJPWk9RODVmQUR5WkYvdzROVCtVbWd3Ym85aVkwRnc9PSlGY01E\n\n20 - OUTROS REQUISITOS\nIdentificador do Lote: LOT-0001; LOT-0002; LOT-0003\nInformação sobre contratos reservados. Aplica-se a contratos reservados (54º-A)? Não\n\n21 - CRITÉRIO DE ADJUDICAÇÃO\nO Critério de adjudicação é diferenciado por lote? Sim\nIdentificador do lote: LOT-0001\nMultifator: Sim\nFator: \nNome: Preço\nPonderação: 60%\nSubfatores: Não\nFator: \nNome: Qualidade\nPonderação: 10%\nSubfatores: Não\nFator: \nNome: Qualidade\nPonderação: 20%\nSubfatores: Não\nFator: \nNome: Qualidade\nPonderação: 10%\nSubfatores: Não\nO Critério de adjudicação é diferenciado por lote? Sim\nIdentificador do lote: LOT-0002\nMultifator: Não\nMonofator:\nNome: Preço\nO Critério de adjudicação é diferenciado por lote? Sim\nIdentificador do lote: LOT-0003\nMultifator: Não\nMonofator:\nNome: Preço\n\n24 - CONDIÇÕES DO CONTRATO\nIdentificador do Lote: LOT-0001; LOT-0002; LOT-0003\nFaturação Eletrónica: Permitido\nObrigação de Subcontratação:\nCódigo da Obrigação de Subcontratação: Não é aplicável nenhuma obrigação de subcontratação.\n\n25 - COMPRA PÚBLICA ESTRATÉGICA\nCompra Pública Estratégica: Inexistência de contratação pública estratégica\n\n26 - INFORMAÇÕES ADICIONAIS\nIdentificador do Lote: LOT-0001; LOT-0002; LOT-0003\nContrato adequado para PME: Sim\nCobertura ACP (Acordo dos Contratos Públicos da Organização Mundial do Comércio): Não\n\n27 - IDENTIFICAÇÃO E CONTACTOS DO ÓRGÃO DE RECURSOS ADMINISTRATIVOS\nDesignação: Conselho de Administração\nEndereço: Largo Sr. da Pobreza\nCódigo postal: 7005-811\nLocalidade: Évora\nTelefone: +351 266740111\nFax: +351 266744212\nEndereço eletrónico: concursos.aprov@ulsac.min-saude.pt\n\n28 - IDENTIFICAÇÃO DO(S) AUTOR(ES) DE ANÚNCIO\nNome: Vitor Rui Gomes Fialho\nCargo: Presidente do Conselho de Administração\n419601371",
    "nipc": "508085888",
    "distrito": "Évora",
    "concelho": "Évora",
    "freguesia": "Todas",
    "site": "www.hevora.min-saude.pt",
    "email": "concursos.aprov@ulsac.min-saude.pt",
    "designacao_contrato": "Equipamentos para Serviço de Neonatologia",
    "descricao": "Aquisição de Equipamentos para Serviço de Neonatologia",
    "preco_base": "124.000,00 EUR",
    "prazo_execucao": "20 DIAS",
    "prazo_apresentacao_propostas": "16-10-2025 18:00",
    "fundos_eu": "Não",
    "plataforma_eletronica": "VORTAL",
    "url_procedimento": "https://community.vortal.biz/public/",
    "autor_nome": "Vitor Rui Gomes Fialho",
    "autor_cargo": "Presidente do Conselho de Administração"
  },
  {
    "numero_procedimento": "N/A",
    "entidade": "BIKiNNOV - BIKE VALUE INNOVATION CENTER - ASSOCIATION",
    "link": "https://diariodarepublica.pt/dr/detalhe/contrato-publico/25883-937614445",
    "detalhes_completos": "1 - IDENTIFICAÇÃO E CONTACTOS DA ENTIDADE ADJUDICANTE\nDesignação da entidade adjudicante: BIKiNNOV - BIKE VALUE INNOVATION CENTER - ASSOCIATION\nNIPC: 516839268\nServiço/Órgão/Pessoa de contacto: BIKiNNOV\nEndereço: Rua da Indústria, 369, Covão, 3750-792 Águeda\nCódigo postal: 3750-792\nLocalidade: Águeda\nPaís: Portugal\nNUT III: PT16D\nDistrito: Aveiro\nConcelho: Águeda\nFreguesia: Freguesia de Valongo do Vouga\nTelefone: 234248960\nEndereço da Entidade (URL): www.bikinnov.pt\nEndereço Eletrónico: geral@bikinnov.pt\neDelivery Gateway (URL): https://www.acingov.pt\nFunção da Organização: Adquirente\nNorma jurídica da Entidade Adjudicante: Organismo de direito público\nÁrea de atividade da Autoridade Adjudicante: Serviços públicos das administrações públicas\n\n2 - JORNAL OFICIAL DA UNIÃO EUROPEIA\nO procedimento a que este anúncio diz respeito também é publicitado no Jornal Oficial da União Europeia? Não\n\n3 - AVISO\nModelo de Anúncio: Concurso público\nData de Envio do Anúncio: 01-10-2025\n\n5 - PROCESSO\nTipo de Procedimento: Concurso público\nPreço base do procedimento: Sim\nValor do preço base do procedimento: 170.000,00 EUR\nProcedimento com lotes? Não\n\n6 - OBJETO DO CONTRATO\nNúmero de referência interna: 68-111-CTI-25\nDesignação do contrato: Eixo Materiais  Equipamentos para Ensaios de Resistência ao Impacto\nDescrição: Eixo Materiais  Equipamentos para Ensaios de Resistência ao Impacto\nTipo de Contrato Principal: Aquisição de Bens Móveis\nTipo de Contrato: Aquisição de Bens Móveis\nClassificação CPV (Vocabulário Comum para os Contratos Públicos)\nObjeto principal\nVocabulário Principal: 38900000\nPreço base s/IVA: 170.000,00 EUR\n\n7 - INDICAÇÕES ADICIONAIS\nO contrato envolve aquisição conjunta (satisfação de várias entidades)? Não\nO contrato é adjudicado por uma central de compras? Não\n\n8 - TÉCNICAS\nO concurso destina-se à celebração de um acordo-quadro? Inexistência de acordo-quadro\nÉ utilizado um leilão eletrónico? Não\nÉ adotada uma fase de negociação? Não\nSistema de Aquisição Dinâmico: Inexistência de sistema de aquisição dinâmico\n\n9 - LOCAL DA EXECUÇÃO DO CONTRATO\nLOCAL DA EXECUÇÃO DO CONTRATO (PROCEDIMENTO)\nPaís: Portugal\nNUT III: PT16D\nLocalidade: Freguesia de Valongo do Vouga\nDistrito: Aveiro\nConcelho: Águeda\nFreguesia: Freguesia de Valongo do Vouga\n\n10 - PRAZO DE EXECUÇÃO DO CONTRATO\nPrazo de execução do contrato: 6 MESES\nPrevisão de renovações: Não\n\n11 - FUNDOS EU\nTêm fundos EU? Sim\n\n12 - DOCUMENTOS DE HABILITAÇÃO\nHabilitação para o exercício da atividade profissional: Não\n\n13 - CONDIÇÕES DE APRESENTAÇÃO\nPlataforma eletrónica utilizada pela entidade adjudicante: ACIN\nURL para Apresentação: https://www.acingov.pt\nAdmissibilidade da apresentação de propostas variantes: Não autorizado\nPrazo para apresentação das propostas: 11-10-2025 17:00\nPrazo durante o qual os concorrentes são obrigados a manter as respetivas propostas: 66 dias a contar do termo do prazo para a apresentação das propostas\nIndicação de Subcontratação na Proposta: Inexistência de indicação de subcontratação\n\n14 - PRESTAÇÃO DE CAUÇÃO\nPrestação de caução: Não\n\n15 - FORNECIMENTO DAS PEÇAS DO CONCURSO, APRESENTAÇÃO DE PEDIDOS DE PARTICIPAÇÃO E APRESENTAÇÃO DAS PROPOSTAS\nLink para acesso às peças do concurso (URL): https://www.acingov.pt/acingovprod/2/zonaPublica/zona_publica_c/donwloadProcedurePiece/OTgyOTUw\n\n20 - OUTROS REQUISITOS\nInformação sobre contratos reservados. Aplica-se a contratos reservados (54º-A)? Não\n\n21 - CRITÉRIO DE ADJUDICAÇÃO\nMultifator: Não\nMonofator:\nNome: Preço\n\n24 - CONDIÇÕES DO CONTRATO\nFaturação Eletrónica: Permitido\nObrigação de Subcontratação:\nCódigo da Obrigação de Subcontratação: Não é aplicável nenhuma obrigação de subcontratação.\n\n25 - COMPRA PÚBLICA ESTRATÉGICA\nCompra Pública Estratégica: Inexistência de contratação pública estratégica\n\n26 - INFORMAÇÕES ADICIONAIS\nContrato adequado para PME: Sim\nCobertura ACP (Acordo dos Contratos Públicos da Organização Mundial do Comércio): Não\n\n27 - IDENTIFICAÇÃO E CONTACTOS DO ÓRGÃO DE RECURSOS ADMINISTRATIVOS\nDesignação: BIKiNNOV\nEndereço: Rua da Indústria, 369, Covão, 3750-792 Águeda\nCódigo postal: 3750-792\nLocalidade: Águeda\nTelefone: 234248960\nFax: \nEndereço eletrónico: geral@bikinnov.pt\nPrazo de interposição do recurso: 10 dias\n\n28 - IDENTIFICAÇÃO DO(S) AUTOR(ES) DE ANÚNCIO\nNome: Inês Tavares\nCargo: Gestora Financeira de Projetos\n419602984",
    "nipc": "516839268",
    "distrito": "Aveiro",
    "concelho": "Águeda",
    "freguesia": "Freguesia de Valongo do Vouga",
    "site": "www.bikinnov.pt",
    "email": "geral@bikinnov.pt",
    "designacao_contrato": "Eixo Materiais  Equipamentos para Ensaios de Resistência ao Impacto",
    "descricao": "Eixo Materiais  Equipamentos para Ensaios de Resistência ao Impacto",
    "preco_base": "170.000,00 EUR",
    "prazo_execucao": "6 MESES",
    "prazo_apresentacao_propostas": "11-10-2025 17:00",
    "fundos_eu": "Sim",
    "plataforma_eletronica": "ACIN",
    "url_procedimento": "https://www.acingov.pt",
    "autor_nome": "Inês Tavares",
    "autor_cargo": "Gestora Financeira de Projetos"
  },
  {
    "numero_procedimento": "N/A",
    "entidade": "Serviços de Acção Social da Universidade do Algarve",
    "link": "https://diariodarepublica.pt/dr/detalhe/contrato-publico/25877-937672804",
    "detalhes_completos": "1 - IDENTIFICAÇÃO E CONTACTOS DA ENTIDADE ADJUDICANTE\nDesignação da entidade adjudicante: Serviços de Acção Social da Universidade do Algarve\nNIPC: 600039510\nEndereço: Campus Universitário da Penha - Estrada da Penha\nCódigo postal: 8005-139\nLocalidade: Faro\nPaís: Portugal\nNUT III: PT150\nDistrito: Faro\nConcelho: Faro\nFreguesia: Todas\nTelefone: 289800102\nFax: 289800102\nEndereço da Entidade (URL): https://www.ualg.pt/acao-social\nEndereço Eletrónico: sascompras@ualg.pt\nFunção da Organização: Adquirente\nSubfunção da Organização: Líder do grupo\nNorma jurídica da Entidade Adjudicante: Autoridade da administração central\nÁrea de atividade da Entidade Adjudicante: Atividades aeroportuárias\n\n2 - JORNAL OFICIAL DA UNIÃO EUROPEIA\nO procedimento a que este anúncio diz respeito também é publicitado no Jornal Oficial da União Europeia? Não\n\n3 - AVISO\nModelo de Anúncio: Concurso público\nData de Envio do Anúncio: 01-10-2025\n\n5 - PROCESSO\nTipo de Procedimento: Concurso público\nPreço base do procedimento: Sim\nValor do preço base do procedimento: 214.492,00 EUR\nProcedimento com lotes? Sim\nNº Máx. de Lotes Autorizado: 204\nNúmero máximo de lotes que podem ser adjudicados a um concorrente: 204\n\n6 - OBJETO DO CONTRATO\nNúmero de referência interna: Concurso Público n.º 02/SAS-UAlg/2025\nDesignação do contrato: Fornecimento contínuo e faseado de Produtos Alimentares Diversos (mercearias)\nDescrição: Fornecimento contínuo e faseado de Produtos Alimentares Diversos (mercearias)\nTipo de Contrato Principal: Aquisição de Bens Móveis\nTipo de Contrato: Aquisição de Bens Móveis\nClassificação CPV (Vocabulário Comum para os Contratos Públicos)\nObjeto principal\nVocabulário Principal: 15800000\nPreço base s/IVA: 214.492,00 EUR\nLotes: \nNº: LOT-0001\nDescrição do Lote: Açafrão (embalagem 1 Kg)\nPreço base s/IVA: 14,00 EUR\nClassificação CPV (Vocabulário Comum para os Contratos Públicos)\nObjeto principal\nVocabulário Principal: 15800000\nNº: LOT-0002\nDescrição do Lote: Açúcar (embalagem 1 Kg)\nPreço base s/IVA: 760,00 EUR\nClassificação CPV (Vocabulário Comum para os Contratos Públicos)\nObjeto principal\nVocabulário Principal: 15800000\nNº: LOT-0003\nDescrição do Lote: Açucar amarelo (embalagem 1 Kg)\nPreço base s/IVA: 15,00 EUR\nClassificação CPV (Vocabulário Comum para os Contratos Públicos)\nObjeto principal\nVocabulário Principal: 15800000\nNº: LOT-0004\nDescrição do Lote: Açúcar mascavado (embalagem 500gr)\nPreço base s/IVA: 30,00 EUR\nClassificação CPV (Vocabulário Comum para os Contratos Públicos)\nObjeto principal\nVocabulário Principal: 15800000\nNº: LOT-0005\nDescrição do Lote: Açúcar em pó (embalagem 500gr)\nPreço base s/IVA: 15,00 EUR\nClassificação CPV (Vocabulário Comum para os Contratos Públicos)\nObjeto principal\nVocabulário Principal: 15800000\nNº: LOT-0006\nDescrição do Lote: Alcaparras (embalagem 180gr)\nPreço base s/IVA: 23,00 EUR\nClassificação CPV (Vocabulário Comum para os Contratos Públicos)\nObjeto principal\nVocabulário Principal: 15800000\nNº: LOT-0007\nDescrição do Lote: Alcaparras (embalagem 720gr)\nPreço base s/IVA: 48,00 EUR\nClassificação CPV (Vocabulário Comum para os Contratos Públicos)\nObjeto principal\nVocabulário Principal: 15800000\nNº: LOT-0008\nDescrição do Lote: Ameixa seca sem caroço (embalagem 1 Kg)\nPreço base s/IVA: 47,50 EUR\nClassificação CPV (Vocabulário Comum para os Contratos Públicos)\nObjeto principal\nVocabulário Principal: 15800000\nNº: LOT-0009\nDescrição do Lote: Amendoa laminada (embalagem 1 Kg)\nPreço base s/IVA: 30,00 EUR\nClassificação CPV (Vocabulário Comum para os Contratos Públicos)\nObjeto principal\nVocabulário Principal: 15800000\nNº: LOT-0010\nDescrição do Lote: Amendoa laminada (embalagem 150 gr)\nPreço base s/IVA: 35,00 EUR\nClassificação CPV (Vocabulário Comum para os Contratos Públicos)\nObjeto principal\nVocabulário Principal: 15800000\nNº: LOT-0011\nDescrição do Lote: Amendoim c/ sal (embalagem 1 kg)\nPreço base s/IVA: 27,50 EUR\nClassificação CPV (Vocabulário Comum para os Contratos Públicos)\nObjeto principal\nVocabulário Principal: 15800000\nNº: LOT-0012\nDescrição do Lote: Ananás em calda  (lata 820gr)\nPreço base s/IVA: 875,00 EUR\nClassificação CPV (Vocabulário Comum para os Contratos Públicos)\nObjeto principal\nVocabulário Principal: 15800000\nNº: LOT-0013\nDescrição do Lote: Anis estrelado (embalagem de 25gr)\nPreço base s/IVA: 28,00 EUR\nClassificação CPV (Vocabulário Comum para os Contratos Públicos)\nObjeto principal\nVocabulário Principal: 15800000\nNº: LOT-0014\nDescrição do Lote: Arroz basmati (embalagem 1 kg)\nPreço base s/IVA: 160,00 EUR\nClassificação CPV (Vocabulário Comum para os Contratos Públicos)\nObjeto principal\nVocabulário Principal: 15800000\nNº: LOT-0015\nDescrição do Lote: Arroz carolino (embalagem 1 Kg)\nPreço base s/IVA: 255,00 EUR\nClassificação CPV (Vocabulário Comum para os Contratos Públicos)\nObjeto principal\nVocabulário Principal: 15800000\nNº: LOT-0016\nDescrição do Lote: Arroz extra-longo estufado (embalagem 1 Kg)\nPreço base s/IVA: 9.350,00 EUR\nClassificação CPV (Vocabulário Comum para os Contratos Públicos)\nObjeto principal\nVocabulário Principal: 15800000\nNº: LOT-0017\nDescrição do Lote: Arroz integral (embalagem de 1 Kg)\nPreço base s/IVA: 39,00 EUR\nClassificação CPV (Vocabulário Comum para os Contratos Públicos)\nObjeto principal\nVocabulário Principal: 15800000\nNº: LOT-0018\nDescrição do Lote: Arroz risotto (embalagem 1 Kg)\nPreço base s/IVA: 155,00 EUR\nClassificação CPV (Vocabulário Comum para os Contratos Públicos)\nObjeto principal\nVocabulário Principal: 15800000\nNº: LOT-0019\nDescrição do Lote: Arroz selvagem (embalagem 2,5Kg)\nPreço base s/IVA: 200,00 EUR\nClassificação CPV (Vocabulário Comum para os Contratos Públicos)\nObjeto principal\nVocabulário Principal: 15800000\nNº: LOT-0020\nDescrição do Lote: Atum em bolsa (embalagem 1 Kg)\nPreço base s/IVA: 10.200,00 EUR\nClassificação CPV (Vocabulário Comum para os Contratos Públicos)\nObjeto principal\nVocabulário Principal: 15800000\nNº: LOT-0021\nDescrição do Lote: Azeite (embalagem 1 lt)\nPreço base s/IVA: 52.500,00 EUR\nClassificação CPV (Vocabulário Comum para os Contratos Públicos)\nObjeto principal\nVocabulário Principal: 15800000\nNº: LOT-0022\nDescrição do Lote: Azeite (embalagem inviolável 250ml)\nPreço base s/IVA: 3.200,00 EUR\nClassificação CPV (Vocabulário Comum para os Contratos Públicos)\nObjeto principal\nVocabulário Principal: 15800000\nNº: LOT-0023\nDescrição do Lote: Azeite saquetas individuais (caixa 200x10ml)\nPreço base s/IVA: 8.500,00 EUR\nClassificação CPV (Vocabulário Comum para os Contratos Públicos)\nObjeto principal\nVocabulário Principal: 15800000\nNº: LOT-0024\nDescrição do Lote: Azeitona preta (Cal 291/320 embalagem 5kg)\nPreço base s/IVA: 960,00 EUR\nClassificação CPV (Vocabulário Comum para os Contratos Públicos)\nObjeto principal\nVocabulário Principal: 15800000\nNº: LOT-0025\nDescrição do Lote: Azeitona preta sem caroço (frasco 165gr)\nPreço base s/IVA: 300,00 EUR\nClassificação CPV (Vocabulário Comum para os Contratos Públicos)\nObjeto principal\nVocabulário Principal: 15800000\nNº: LOT-0026\nDescrição do Lote: Azeitona verde (frasco 560 grs)\nPreço base s/IVA: 45,00 EUR\nClassificação CPV (Vocabulário Comum para os Contratos Públicos)\nObjeto principal\nVocabulário Principal: 15800000\nNº: LOT-0027\nDescrição do Lote: Azeitona verde sem caroço (frasco 165gr)\nPreço base s/IVA: 100,00 EUR\nClassificação CPV (Vocabulário Comum para os Contratos Públicos)\nObjeto principal\nVocabulário Principal: 15800000\nNº: LOT-0028\nDescrição do Lote: Banha de porco (embalagem 1 Kg)\nPreço base s/IVA: 350,00 EUR\nClassificação CPV (Vocabulário Comum para os Contratos Públicos)\nObjeto principal\nVocabulário Principal: 15800000\nNº: LOT-0029\nDescrição do Lote: Batata em palito pré fritas congeladas (embalagem 2,5 Kg)\nPreço base s/IVA: 720,00 EUR\nClassificação CPV (Vocabulário Comum para os Contratos Públicos)\nObjeto principal\nVocabulário Principal: 15800000\nNº: LOT-0030\nDescrição do Lote: Batata frita palha (embalagem 500gr)\nPreço base s/IVA: 400,00 EUR\nClassificação CPV (Vocabulário Comum para os Contratos Públicos)\nObjeto principal\nVocabulário Principal: 15800000\nNº: LOT-0031\nDescrição do Lote: Bicarbonato de sódio (embalagem 100 grs)\nPreço base s/IVA: 15,00 EUR\nClassificação CPV (Vocabulário Comum para os Contratos Públicos)\nObjeto principal\nVocabulário Principal: 15800000\nNº: LOT-0032\nDescrição do Lote: Bolacha água e sal (embalagem 125 grs)\nPreço base s/IVA: 22,00 EUR\nClassificação CPV (Vocabulário Comum para os Contratos Públicos)\nObjeto principal\nVocabulário Principal: 15800000\nNº: LOT-0033\nDescrição do Lote: Bolacha tipo Oreo (embalagem 440grs)\nPreço base s/IVA: 50,00 EUR\nClassificação CPV (Vocabulário Comum para os Contratos Públicos)\nObjeto principal\nVocabulário Principal: 15800000\nNº: LOT-0034\nDescrição do Lote: Bolacha tipo Maria (embalagem 200 grs)\nPreço base s/IVA: 180,00 EUR\nClassificação CPV (Vocabulário Comum para os Contratos Públicos)\nObjeto principal\nVocabulário Principal: 15800000\nNº: LOT-0035\nDescrição do Lote: Bolacha torrada (embalagem 200 grs)\nPreço base s/IVA: 240,00 EUR\nClassificação CPV (Vocabulário Comum para os Contratos Públicos)\nObjeto principal\nVocabulário Principal: 15800000\nNº: LOT-0036\nDescrição do Lote: Cacau em pó (embalagem 125grs)\nPreço base s/IVA: 18,00 EUR\nClassificação CPV (Vocabulário Comum para os Contratos Públicos)\nObjeto principal\nVocabulário Principal: 15800000\nNº: LOT-0037\nDescrição do Lote: Caju (embalagem 150 grs)\nPreço base s/IVA: 100,00 EUR\nClassificação CPV (Vocabulário Comum para os Contratos Públicos)\nObjeto principal\nVocabulário Principal: 15800000\nNº: LOT-0038\nDescrição do Lote: Caldo de carne em pasta (embalagem 1 Kg)\nPreço base s/IVA: 140,00 EUR\nClassificação CPV (Vocabulário Comum para os Contratos Públicos)\nObjeto principal\nVocabulário Principal: 15800000\nNº: LOT-0039\nDescrição do Lote: Caldo de galinha (embalagem 1 Kg)\nPreço base s/IVA: 700,00 EUR\nClassificação CPV (Vocabulário Comum para os Contratos Públicos)\nObjeto principal\nVocabulário Principal: 15800000\nNº: LOT-0040\nDescrição do Lote: Caldo de legumes (embalagem 1 Kg)\nPreço base s/IVA: 280,00 EUR\nClassificação CPV (Vocabulário Comum para os Contratos Públicos)\nObjeto principal\nVocabulário Principal: 15800000\nNº: LOT-0041\nDescrição do Lote: Caldo de peixe em pasta (embalagem 700gr)\nPreço base s/IVA: 210,00 EUR\nClassificação CPV (Vocabulário Comum para os Contratos Públicos)\nObjeto principal\nVocabulário Principal: 15800000\nNº: LOT-0042\nDescrição do Lote: Canela em pau (embalagem 1 Kg)\nPreço base s/IVA: 800,00 EUR\nClassificação CPV (Vocabulário Comum para os Contratos Públicos)\nObjeto principal\nVocabulário Principal: 15800000\nNº: LOT-0043\nDescrição do Lote: Canela moída (embalagem 1 Kg)\nPreço base s/IVA: 55,00 EUR\nClassificação CPV (Vocabulário Comum para os Contratos Públicos)\nObjeto principal\nVocabulário Principal: 15800000\nNº: LOT-0044\nDescrição do Lote: Caramelo líquido (embalagem 1,3 Kg)\nPreço base s/IVA: 225,00 EUR\nClassificação CPV (Vocabulário Comum para os Contratos Públicos)\nObjeto principal\nVocabulário Principal: 15800000\nNº: LOT-0045\nDescrição do Lote: Caril moído  (embalagem 1 Kg)\nPreço base s/IVA: 64,00 EUR\nClassificação CPV (Vocabulário Comum para os Contratos Públicos)\nObjeto principal\nVocabulário Principal: 15800000\nNº: LOT-0046\nDescrição do Lote: Carteiras de tomilho (5gr)\nPreço base s/IVA: 17,00 EUR\nClassificação CPV (Vocabulário Comum para os Contratos Públicos)\nObjeto principal\nVocabulário Principal: 15800000\nNº: LOT-0047\nDescrição do Lote: Cebolinho (embalagem 20 grs)\nPreço base s/IVA: 75,00 EUR\nClassificação CPV (Vocabulário Comum para os Contratos Públicos)\nObjeto principal\nVocabulário Principal: 15800000\nNº: LOT-0048\nDescrição do Lote: Cereais tipo Chocapic (embalagem 500grs)\nPreço base s/IVA: 250,00 EUR\nClassificação CPV (Vocabulário Comum para os Contratos Públicos)\nObjeto principal\nVocabulário Principal: 15800000\nNº: LOT-0049\nDescrição do Lote: Cereais tipo Estrelitas (embalagem 500grs)\nPreço base s/IVA: 250,00 EUR\nClassificação CPV (Vocabulário Comum para os Contratos Públicos)\nObjeto principal\nVocabulário Principal: 15800000\nNº: LOT-0050\nDescrição do Lote: Chá Camomila (embalagem 25 unidades)\nPreço base s/IVA: 102,00 EUR\nClassificação CPV (Vocabulário Comum para os Contratos Públicos)\nObjeto principal\nVocabulário Principal: 15800000\nNº: LOT-0051\nDescrição do Lote: Chá Cidreira (embalagem 25 unidades)\nPreço base s/IVA: 85,00 EUR\nClassificação CPV (Vocabulário Comum para os Contratos Públicos)\nObjeto principal\nVocabulário Principal: 15800000\nNº: LOT-0052\nDescrição do Lote: Chá Lúcia Lima (embalagem 25 unidades)\nPreço base s/IVA: 85,00 EUR\nClassificação CPV (Vocabulário Comum para os Contratos Públicos)\nObjeto principal\nVocabulário Principal: 15800000\nNº: LOT-0053\nDescrição do Lote: Chá Menta (embalagem 25 unidades)\nPreço base s/IVA: 85,00 EUR\nClassificação CPV (Vocabulário Comum para os Contratos Públicos)\nObjeto principal\nVocabulário Principal: 15800000\nNº: LOT-0054\nDescrição do Lote: Chá Preto (embalagem 25 unidades)\nPreço base s/IVA: 102,00 EUR\nClassificação CPV (Vocabulário Comum para os Contratos Públicos)\nObjeto principal\nVocabulário Principal: 15800000\nNº: LOT-0055\nDescrição do Lote: Chá Tilia (embalagem 25 unidades)\nPreço base s/IVA: 85,00 EUR\nClassificação CPV (Vocabulário Comum para os Contratos Públicos)\nObjeto principal\nVocabulário Principal: 15800000\nNº: LOT-0056\nDescrição do Lote: Chá Verde (embalagem 25 unidades)\nPreço base s/IVA: 102,00 EUR\nClassificação CPV (Vocabulário Comum para os Contratos Públicos)\nObjeto principal\nVocabulário Principal: 15800000\nNº: LOT-0057\nDescrição do Lote: Chocolate em pó (embalagem 125gr)\nPreço base s/IVA: 30,00 EUR\nClassificação CPV (Vocabulário Comum para os Contratos Públicos)\nObjeto principal\nVocabulário Principal: 15800000\nNº: LOT-0058\nDescrição do Lote: Chocolate em tablete p/ culinária (embalagem 200 gr)\nPreço base s/IVA: 150,00 EUR\nClassificação CPV (Vocabulário Comum para os Contratos Públicos)\nObjeto principal\nVocabulário Principal: 15800000\nNº: LOT-0059\nDescrição do Lote: Chouriço de soja\nPreço base s/IVA: 750,00 EUR\nClassificação CPV (Vocabulário Comum para os Contratos Públicos)\nObjeto principal\nVocabulário Principal: 15800000\nNº: LOT-0060\nDescrição do Lote: Coco ralado (embalagem 200gr)\nPreço base s/IVA: 90,00 EUR\nClassificação CPV (Vocabulário Comum para os Contratos Públicos)\nObjeto principal\nVocabulário Principal: 15800000\nNº: LOT-0061\nDescrição do Lote: Cogumelos Laminados (embalagem 2,5 Kg)\nPreço base s/IVA: 7.000,00 EUR\nClassificação CPV (Vocabulário Comum para os Contratos Públicos)\nObjeto principal\nVocabulário Principal: 15800000\nNº: LOT-0062\nDescrição do Lote: Cogumelos Laminados (embalagem 780 grs)\nPreço base s/IVA: 175,00 EUR\nClassificação CPV (Vocabulário Comum para os Contratos Públicos)\nObjeto principal\nVocabulário Principal: 15800000\nNº: LOT-0063\nDescrição do Lote: Cominhos moído (embalagem 1 Kg)\nPreço base s/IVA: 50,00 EUR\nClassificação CPV (Vocabulário Comum para os Contratos Públicos)\nObjeto principal\nVocabulário Principal: 15800000\nNº: LOT-0064\nDescrição do Lote: Concentrado de sumo abacaxi (embalagem 5 lt)\nPreço base s/IVA: 2.100,00 EUR\nClassificação CPV (Vocabulário Comum para os Contratos Públicos)\nObjeto principal\nVocabulário Principal: 15800000\nNº: LOT-0065\nDescrição do Lote: Concentrado de sumo laranja (embalagem 5 lt)\nPreço base s/IVA: 3.150,00 EUR\nClassificação CPV (Vocabulário Comum para os Contratos Públicos)\nObjeto principal\nVocabulário Principal: 15800000\nNº: LOT-0066\nDescrição do Lote: Concentrado de sumo maça (embalagem 5 lt)\nPreço base s/IVA: 1.050,00 EUR\nClassificação CPV (Vocabulário Comum para os Contratos Públicos)\nObjeto principal\nVocabulário Principal: 15800000\nNº: LOT-0067\nDescrição do Lote: Concentrado de sumo manga (embalagem 5 lt)\nPreço base s/IVA: 3.150,00 EUR\nClassificação CPV (Vocabulário Comum para os Contratos Públicos)\nObjeto principal\nVocabulário Principal: 15800000\nNº: LOT-0068\nDescrição do Lote: Concentrado de sumo maracujá (embalagem 5 lt)\nPreço base s/IVA: 3.150,00 EUR\nClassificação CPV (Vocabulário Comum para os Contratos Públicos)\nObjeto principal\nVocabulário Principal: 15800000\nNº: LOT-0069\nDescrição do Lote: Cravinho em grão (embalagem 35 grs)\nPreço base s/IVA: 25,00 EUR\nClassificação CPV (Vocabulário Comum para os Contratos Públicos)\nObjeto principal\nVocabulário Principal: 15800000\nNº: LOT-0070\nDescrição do Lote: Cravinho moído (embalagem 1 Kg)\nPreço base s/IVA: 60,00 EUR\nClassificação CPV (Vocabulário Comum para os Contratos Públicos)\nObjeto principal\nVocabulário Principal: 15800000\nNº: LOT-0071\nDescrição do Lote: Creme de marisco (embalagem 72 grs)\nPreço base s/IVA: 70,00 EUR\nClassificação CPV (Vocabulário Comum para os Contratos Públicos)\nObjeto principal\nVocabulário Principal: 15800000\nNº: LOT-0072\nDescrição do Lote: Doce de morango (caixa de 120x20grs)\nPreço base s/IVA: 85,00 EUR\nClassificação CPV (Vocabulário Comum para os Contratos Públicos)\nObjeto principal\nVocabulário Principal: 15800000\nNº: LOT-0073\nDescrição do Lote: Doce de pêssego (caixa de 120x20grs)\nPreço base s/IVA: 85,00 EUR\nClassificação CPV (Vocabulário Comum para os Contratos Públicos)\nObjeto principal\nVocabulário Principal: 15800000\nNº: LOT-0074\nDescrição do Lote: Farinha de mandioca (embalagem 500 gr)\nPreço base s/IVA: 30,00 EUR\nClassificação CPV (Vocabulário Comum para os Contratos Públicos)\nObjeto principal\nVocabulário Principal: 15800000\nNº: LOT-0075\nDescrição do Lote: Farinha de milho (embalagem 1 Kg)\nPreço base s/IVA: 75,00 EUR\nClassificação CPV (Vocabulário Comum para os Contratos Públicos)\nObjeto principal\nVocabulário Principal: 15800000\nNº: LOT-0076\nDescrição do Lote: Farinha de trigo c/ fermento (embalagem de 1 Kg)\nPreço base s/IVA: 100,00 EUR\nClassificação CPV (Vocabulário Comum para os Contratos Públicos)\nObjeto principal\nVocabulário Principal: 15800000\nNº: LOT-0077\nDescrição do Lote: Farinha de trigo s/ fermento (embalagem de 1 Kg)\nPreço base s/IVA: 500,00 EUR\nClassificação CPV (Vocabulário Comum para os Contratos Públicos)\nObjeto principal\nVocabulário Principal: 15800000\nNº: LOT-0078\nDescrição do Lote: Farinha maizena (embalagem de 2,5 Kg)\nPreço base s/IVA: 750,00 EUR\nClassificação CPV (Vocabulário Comum para os Contratos Públicos)\nObjeto principal\nVocabulário Principal: 15800000\nNº: LOT-0079\nDescrição do Lote: Feijão branco em lata (embalagem 820gr)\nPreço base s/IVA: 400,00 EUR\nClassificação CPV (Vocabulário Comum para os Contratos Públicos)\nObjeto principal\nVocabulário Principal: 15800000\nNº: LOT-0080\nDescrição do Lote: Feijão branco seco (embalagem 5 Kg)\nPreço base s/IVA: 700,00 EUR\nClassificação CPV (Vocabulário Comum para os Contratos Públicos)\nObjeto principal\nVocabulário Principal: 15800000\nNº: LOT-0081\nDescrição do Lote: Feijão catarino seco (embalagem 5 Kg)\nPreço base s/IVA: 1.120,00 EUR\nClassificação CPV (Vocabulário Comum para os Contratos Públicos)\nObjeto principal\nVocabulário Principal: 15800000\nNº: LOT-0082\nDescrição do Lote: Feijão encarnado em lata  (embalagem 820 gr)\nPreço base s/IVA: 300,00 EUR\nClassificação CPV (Vocabulário Comum para os Contratos Públicos)\nObjeto principal\nVocabulário Principal: 15800000\nNº: LOT-0083\nDescrição do Lote: Feijão encarnado seco (embalagem 5 Kg)\nPreço base s/IVA: 700,00 EUR\nClassificação CPV (Vocabulário Comum para os Contratos Públicos)\nObjeto principal\nVocabulário Principal: 15800000\nNº: LOT-0084\nDescrição do Lote: Feijão frade em lata  (embalagem 820 gr)\nPreço base s/IVA: 150,00 EUR\nClassificação CPV (Vocabulário Comum para os Contratos Públicos)\nObjeto principal\nVocabulário Principal: 15800000\nNº: LOT-0085\nDescrição do Lote: Feijão frade seco (embalagem 5 Kg)\nPreço base s/IVA: 360,00 EUR\nClassificação CPV (Vocabulário Comum para os Contratos Públicos)\nObjeto principal\nVocabulário Principal: 15800000\nNº: LOT-0086\nDescrição do Lote: Feijão manteiga em lata   (embalagem 820 gr)\nPreço base s/IVA: 300,00 EUR\nClassificação CPV (Vocabulário Comum para os Contratos Públicos)\nObjeto principal\nVocabulário Principal: 15800000\nNº: LOT-0087\nDescrição do Lote: Feijão manteiga seco (embalagem 5 Kg)\nPreço base s/IVA: 640,00 EUR\nClassificação CPV (Vocabulário Comum para os Contratos Públicos)\nObjeto principal\nVocabulário Principal: 15800000\nNº: LOT-0088\nDescrição do Lote: Feijão preto em lata   (embalagem 820 gr)\nPreço base s/IVA: 375,00 EUR\nClassificação CPV (Vocabulário Comum para os Contratos Públicos)\nObjeto principal\nVocabulário Principal: 15800000\nNº: LOT-0089\nDescrição do Lote: Feijão preto seco (embalagem 5 Kg)\nPreço base s/IVA: 75,00 EUR\nClassificação CPV (Vocabulário Comum para os Contratos Públicos)\nObjeto principal\nVocabulário Principal: 15800000\nNº: LOT-0090\nDescrição do Lote: Fermento em pó (embalagem 900gr)\nPreço base s/IVA: 65,00 EUR\nClassificação CPV (Vocabulário Comum para os Contratos Públicos)\nObjeto principal\nVocabulário Principal: 15800000\nNº: LOT-0091\nDescrição do Lote: Filetes de cavala (embalagem 120gr)\nPreço base s/IVA: 40,00 EUR\nClassificação CPV (Vocabulário Comum para os Contratos Públicos)\nObjeto principal\nVocabulário Principal: 15800000\nNº: LOT-0092\nDescrição do Lote: Filetes de anchovas (embalagem 40gr)\nPreço base s/IVA: 85,00 EUR\nClassificação CPV (Vocabulário Comum para os Contratos Públicos)\nObjeto principal\nVocabulário Principal: 15800000\nNº: LOT-0093\nDescrição do Lote: Gelatina ananás (embalagem 1,360 Kg)\nPreço base s/IVA: 378,00 EUR\nClassificação CPV (Vocabulário Comum para os Contratos Públicos)\nObjeto principal\nVocabulário Principal: 15800000\nNº: LOT-0094\nDescrição do Lote: Gelatina maracujá (embalagem 170 grs)\nPreço base s/IVA: 52,00 EUR\nClassificação CPV (Vocabulário Comum para os Contratos Públicos)\nObjeto principal\nVocabulário Principal: 15800000\nNº: LOT-0095\nDescrição do Lote: Gelatina folhas (embalagem 300 folhas - 1Kg)\nPreço base s/IVA: 300,00 EUR\nClassificação CPV (Vocabulário Comum para os Contratos Públicos)\nObjeto principal\nVocabulário Principal: 15800000\nNº: LOT-0096\nDescrição do Lote: Gelatina morango (embalagem 1,360 Kg)\nPreço base s/IVA: 560,00 EUR\nClassificação CPV (Vocabulário Comum para os Contratos Públicos)\nObjeto principal\nVocabulário Principal: 15800000\nNº: LOT-0097\nDescrição do Lote: Gelatina pêssego (embalagem 1,360 Kg)\nPreço base s/IVA: 210,00 EUR\nClassificação CPV (Vocabulário Comum para os Contratos Públicos)\nObjeto principal\nVocabulário Principal: 15800000\nNº: LOT-0098\nDescrição do Lote: Gelatina tutti-fruti (embalagem 1,360 Kg)\nPreço base s/IVA: 350,00 EUR\nClassificação CPV (Vocabulário Comum para os Contratos Públicos)\nObjeto principal\nVocabulário Principal: 15800000\nNº: LOT-0099\nDescrição do Lote: Gengibre moído (embalagem 38 grs)\nPreço base s/IVA: 25,00 EUR\nClassificação CPV (Vocabulário Comum para os Contratos Públicos)\nObjeto principal\nVocabulário Principal: 15800000\nNº: LOT-0100\nDescrição do Lote: Grao de bico cozido em lata  (embalagem 820 gr)\nPreço base s/IVA: 950,00 EUR\nClassificação CPV (Vocabulário Comum para os Contratos Públicos)\nObjeto principal\nVocabulário Principal: 15800000\nNº: LOT-0101\nDescrição do Lote: Grao de bico seco (embalagem 5 Kg)\nPreço base s/IVA: 1.040,00 EUR\nClassificação CPV (Vocabulário Comum para os Contratos Públicos)\nObjeto principal\nVocabulário Principal: 15800000\nNº: LOT-0102\nDescrição do Lote: Ketchup  (embalagem 1Kg)\nPreço base s/IVA: 150,00 EUR\nClassificação CPV (Vocabulário Comum para os Contratos Públicos)\nObjeto principal\nVocabulário Principal: 15800000\nNº: LOT-0103\nDescrição do Lote: Ketchup  (embalagem 5Kg)\nPreço base s/IVA: 400,00 EUR\nClassificação CPV (Vocabulário Comum para os Contratos Públicos)\nObjeto principal\nVocabulário Principal: 15800000\nNº: LOT-0104\nDescrição do Lote: Ketchup em saquetas individuais (caixa 240x12ml)\nPreço base s/IVA: 2.400,00 EUR\nClassificação CPV (Vocabulário Comum para os Contratos Públicos)\nObjeto principal\nVocabulário Principal: 15800000\nNº: LOT-0105\nDescrição do Lote: Leite Condensado (embalagem 397 gr)\nPreço base s/IVA: 850,00 EUR\nClassificação CPV (Vocabulário Comum para os Contratos Públicos)\nObjeto principal\nVocabulário Principal: 15800000\nNº: LOT-0106\nDescrição do Lote: Leite Condensado Cozido (embalagem 397 gr)\nPreço base s/IVA: 110,00 EUR\nClassificação CPV (Vocabulário Comum para os Contratos Públicos)\nObjeto principal\nVocabulário Principal: 15800000\nNº: LOT-0107\nDescrição do Lote: Leite Creme (embalagem 1200gr)\nPreço base s/IVA: 140,00 EUR\nClassificação CPV (Vocabulário Comum para os Contratos Públicos)\nObjeto principal\nVocabulário Principal: 15800000\nNº: LOT-0108\nDescrição do Lote: Leite de coco (embalagem 400ml)\nPreço base s/IVA: 1.200,00 EUR\nClassificação CPV (Vocabulário Comum para os Contratos Públicos)\nObjeto principal\nVocabulário Principal: 15800000\nNº: LOT-0109\nDescrição do Lote: Lentilhas s/casca (embalagem 5 Kg)\nPreço base s/IVA: 500,00 EUR\nClassificação CPV (Vocabulário Comum para os Contratos Públicos)\nObjeto principal\nVocabulário Principal: 15800000\nNº: LOT-0110\nDescrição do Lote: Maionese (embalagem 1 Kg)\nPreço base s/IVA: 250,00 EUR\nClassificação CPV (Vocabulário Comum para os Contratos Públicos)\nObjeto principal\nVocabulário Principal: 15800000\nNº: LOT-0111\nDescrição do Lote: Maionese (embalagem 5 Kg)\nPreço base s/IVA: 2.220,00 EUR\nClassificação CPV (Vocabulário Comum para os Contratos Públicos)\nObjeto principal\nVocabulário Principal: 15800000\nNº: LOT-0112\nDescrição do Lote: Maionese em saquetas individuais (caixa 240x10ml)\nPreço base s/IVA: 2.775,00 EUR\nClassificação CPV (Vocabulário Comum para os Contratos Públicos)\nObjeto principal\nVocabulário Principal: 15800000\nNº: LOT-0113\nDescrição do Lote: Manjericão (embalagem de 100 gr)\nPreço base s/IVA: 60,00 EUR\nClassificação CPV (Vocabulário Comum para os Contratos Públicos)\nObjeto principal\nVocabulário Principal: 15800000\nNº: LOT-0114\nDescrição do Lote: Massa aletria (embalagem 500gr)\nPreço base s/IVA: 16,00 EUR\nClassificação CPV (Vocabulário Comum para os Contratos Públicos)\nObjeto principal\nVocabulário Principal: 15800000\nNº: LOT-0115\nDescrição do Lote: Massa canelloni (embalagem 250gr)\nPreço base s/IVA: 32,00 EUR\nClassificação CPV (Vocabulário Comum para os Contratos Públicos)\nObjeto principal\nVocabulário Principal: 15800000\nNº: LOT-0116\nDescrição do Lote: Massa conchas (embalagem 500 gr)\nPreço base s/IVA: 24,00 EUR\nClassificação CPV (Vocabulário Comum para os Contratos Públicos)\nObjeto principal\nVocabulário Principal: 15800000\nNº: LOT-0117\nDescrição do Lote: Massa Cotovelinhos (embalagem 500 gr)\nPreço base s/IVA: 450,00 EUR\nClassificação CPV (Vocabulário Comum para os Contratos Públicos)\nObjeto principal\nVocabulário Principal: 15800000\nNº: LOT-0118\nDescrição do Lote: Massa Cotovelos (embalagem 500 gr)\nPreço base s/IVA: 150,00 EUR\nClassificação CPV (Vocabulário Comum para os Contratos Públicos)\nObjeto principal\nVocabulário Principal: 15800000\nNº: LOT-0119\nDescrição do Lote: Massa cuscuz miúda p/ acompanhamento (embalagem 1 Kg)\nPreço base s/IVA: 1.200,00 EUR\nClassificação CPV (Vocabulário Comum para os Contratos Públicos)\nObjeto principal\nVocabulário Principal: 15800000\nNº: LOT-0120\nDescrição do Lote: Massa de alho (embalagem 1,2 Kg)\nPreço base s/IVA: 145,00 EUR\nClassificação CPV (Vocabulário Comum para os Contratos Públicos)\nObjeto principal\nVocabulário Principal: 15800000\nNº: LOT-0121\nDescrição do Lote: Massa Esparguete (embalagem 1 Kg)\nPreço base s/IVA: 3.450,00 EUR\nClassificação CPV (Vocabulário Comum para os Contratos Públicos)\nObjeto principal\nVocabulário Principal: 15800000\nNº: LOT-0122\nDescrição do Lote: Massa folhada congelada (embalagem 1 Kg)\nPreço base s/IVA: 1.000,00 EUR\nClassificação CPV (Vocabulário Comum para os Contratos Públicos)\nObjeto principal\nVocabulário Principal: 15800000\nNº: LOT-0123\nDescrição do Lote: Massa folhada congelada (embalagem 300gr)\nPreço base s/IVA: 60,00 EUR\nClassificação CPV (Vocabulário Comum para os Contratos Públicos)\nObjeto principal\nVocabulário Principal: 15800000\nNº: LOT-0124\nDescrição do Lote: Massa Fusili (embalagem 500 gr)\nPreço base s/IVA: 150,00 EUR\nClassificação CPV (Vocabulário Comum para os Contratos Públicos)\nObjeto principal\nVocabulário Principal: 15800000\nNº: LOT-0125\nDescrição do Lote: Massa Fusili Tricolor  (embalagem 500 gr)\nPreço base s/IVA: 1.600,00 EUR\nClassificação CPV (Vocabulário Comum para os Contratos Públicos)\nObjeto principal\nVocabulário Principal: 15800000\nNº: LOT-0126\nDescrição do Lote: Massa Laços  (embalagem 500 gr)\nPreço base s/IVA: 80,00 EUR\nClassificação CPV (Vocabulário Comum para os Contratos Públicos)\nObjeto principal\nVocabulário Principal: 15800000\nNº: LOT-0127\nDescrição do Lote: Massa lasanha (embalagem 500gr)\nPreço base s/IVA: 75,00 EUR\nClassificação CPV (Vocabulário Comum para os Contratos Públicos)\nObjeto principal\nVocabulário Principal: 15800000\nNº: LOT-0128\nDescrição do Lote: Massa linguini (embalagem 500gr)\nPreço base s/IVA: 22,50 EUR\nClassificação CPV (Vocabulário Comum para os Contratos Públicos)\nObjeto principal\nVocabulário Principal: 15800000\nNº: LOT-0129\nDescrição do Lote: Massa Macarrão (embalagem 500 gr)\nPreço base s/IVA: 15,00 EUR\nClassificação CPV (Vocabulário Comum para os Contratos Públicos)\nObjeto principal\nVocabulário Principal: 15800000\nNº: LOT-0130\nDescrição do Lote: Massa Macarronete (embalagem 500gr)\nPreço base s/IVA: 1.050,00 EUR\nClassificação CPV (Vocabulário Comum para os Contratos Públicos)\nObjeto principal\nVocabulário Principal: 15800000\nNº: LOT-0131\nDescrição do Lote: Massa Penne (embalagem 500 gr)\nPreço base s/IVA: 80,00 EUR\nClassificação CPV (Vocabulário Comum para os Contratos Públicos)\nObjeto principal\nVocabulário Principal: 15800000\nNº: LOT-0132\nDescrição do Lote: Massa Pevide (embalagem 250 gr)\nPreço base s/IVA: 50,00 EUR\nClassificação CPV (Vocabulário Comum para os Contratos Públicos)\nObjeto principal\nVocabulário Principal: 15800000\nNº: LOT-0133\nDescrição do Lote: Massa Pimentao (embalagem 1 Kg)\nPreço base s/IVA: 70,00 EUR\nClassificação CPV (Vocabulário Comum para os Contratos Públicos)\nObjeto principal\nVocabulário Principal: 15800000\nNº: LOT-0134\nDescrição do Lote: Massa tagliatelle (embalagem 500gr)\nPreço base s/IVA: 36,00 EUR\nClassificação CPV (Vocabulário Comum para os Contratos Públicos)\nObjeto principal\nVocabulário Principal: 15800000\nNº: LOT-0135\nDescrição do Lote: Mel (embalagem 250 grs)\nPreço base s/IVA: 60,00 EUR\nClassificação CPV (Vocabulário Comum para os Contratos Públicos)\nObjeto principal\nVocabulário Principal: 15800000\nNº: LOT-0136\nDescrição do Lote: Milho conserva latas (embalagem 300gr)\nPreço base s/IVA: 375,00 EUR\nClassificação CPV (Vocabulário Comum para os Contratos Públicos)\nObjeto principal\nVocabulário Principal: 15800000\nNº: LOT-0137\nDescrição do Lote: Mini-tostas (embalagem 500 gr)\nPreço base s/IVA: 175,00 EUR\nClassificação CPV (Vocabulário Comum para os Contratos Públicos)\nObjeto principal\nVocabulário Principal: 15800000\nNº: LOT-0138\nDescrição do Lote: Miolo de amêndoa  (embalagem 1 Kg)\nPreço base s/IVA: 225,00 EUR\nClassificação CPV (Vocabulário Comum para os Contratos Públicos)\nObjeto principal\nVocabulário Principal: 15800000\nNº: LOT-0139\nDescrição do Lote: Miolo de amêndoa sem pele (embalagem 1 Kg)\nPreço base s/IVA: 75,00 EUR\nClassificação CPV (Vocabulário Comum para os Contratos Públicos)\nObjeto principal\nVocabulário Principal: 15800000\nNº: LOT-0140\nDescrição do Lote: Miolo de avelã (embalagem de 1 Kg)\nPreço base s/IVA: 75,00 EUR\nClassificação CPV (Vocabulário Comum para os Contratos Públicos)\nObjeto principal\nVocabulário Principal: 15800000\nNº: LOT-0141\nDescrição do Lote: Miolo de noz (embalagem 1 Kg)\nPreço base s/IVA: 150,00 EUR\nClassificação CPV (Vocabulário Comum para os Contratos Públicos)\nObjeto principal\nVocabulário Principal: 15800000\nNº: LOT-0142\nDescrição do Lote: Molho assado (embalagem 1 Kg)\nPreço base s/IVA: 850,00 EUR\nClassificação CPV (Vocabulário Comum para os Contratos Públicos)\nObjeto principal\nVocabulário Principal: 15800000\nNº: LOT-0143\nDescrição do Lote: Molho bechamel (embalagem 500ml)\nPreço base s/IVA: 125,00 EUR\nClassificação CPV (Vocabulário Comum para os Contratos Públicos)\nObjeto principal\nVocabulário Principal: 15800000\nNº: LOT-0144\nDescrição do Lote: Molho de soja  (embalagem 200 ml)\nPreço base s/IVA: 120,00 EUR\nClassificação CPV (Vocabulário Comum para os Contratos Públicos)\nObjeto principal\nVocabulário Principal: 15800000\nNº: LOT-0145\nDescrição do Lote: Molho demi glace (embalagem 900 grs)\nPreço base s/IVA: 80,00 EUR\nClassificação CPV (Vocabulário Comum para os Contratos Públicos)\nObjeto principal\nVocabulário Principal: 15800000\nNº: LOT-0146\nDescrição do Lote: Molho inglês  (embalagem 120 ml)\nPreço base s/IVA: 60,00 EUR\nClassificação CPV (Vocabulário Comum para os Contratos Públicos)\nObjeto principal\nVocabulário Principal: 15800000\nNº: LOT-0147\nDescrição do Lote: Molho piri-piri (embalagem 120 ml)\nPreço base s/IVA: 175,00 EUR\nClassificação CPV (Vocabulário Comum para os Contratos Públicos)\nObjeto principal\nVocabulário Principal: 15800000\nNº: LOT-0148\nDescrição do Lote: Morcela de soja\nPreço base s/IVA: 180,00 EUR\nClassificação CPV (Vocabulário Comum para os Contratos Públicos)\nObjeto principal\nVocabulário Principal: 15800000\nNº: LOT-0149\nDescrição do Lote: Mostarda Dijon (embalagem 200 grs)\nPreço base s/IVA: 35,00 EUR\nClassificação CPV (Vocabulário Comum para os Contratos Públicos)\nObjeto principal\nVocabulário Principal: 15800000\nNº: LOT-0150\nDescrição do Lote: Mostarda Top Down (embalagem 250gr)\nPreço base s/IVA: 240,00 EUR\nClassificação CPV (Vocabulário Comum para os Contratos Públicos)\nObjeto principal\nVocabulário Principal: 15800000\nNº: LOT-0151\nDescrição do Lote: Mostarda em saquetas individuais (caixa 200x10ml)\nPreço base s/IVA: 600,00 EUR\nClassificação CPV (Vocabulário Comum para os Contratos Públicos)\nObjeto principal\nVocabulário Principal: 15800000\nNº: LOT-0152\nDescrição do Lote: Mousse de chocolate  (embalagem 1,2Kg)\nPreço base s/IVA: 1.800,00 EUR\nClassificação CPV (Vocabulário Comum para os Contratos Públicos)\nObjeto principal\nVocabulário Principal: 15800000\nNº: LOT-0153\nDescrição do Lote: Noz moscada moída (embalagem 1 Kg)\nPreço base s/IVA: 176,00 EUR\nClassificação CPV (Vocabulário Comum para os Contratos Públicos)\nObjeto principal\nVocabulário Principal: 15800000\nNº: LOT-0154\nDescrição do Lote: Oleo alimentar (embalagem 5 lt)\nPreço base s/IVA: 21.000,00 EUR\nClassificação CPV (Vocabulário Comum para os Contratos Públicos)\nObjeto principal\nVocabulário Principal: 15800000\nNº: LOT-0155\nDescrição do Lote: Oleo amendoim (embalagem 1 lt)\nPreço base s/IVA: 70,00 EUR\nClassificação CPV (Vocabulário Comum para os Contratos Públicos)\nObjeto principal\nVocabulário Principal: 15800000\nNº: LOT-0156\nDescrição do Lote: Palitos de la reine (embalagem 200 grs)\nPreço base s/IVA: 35,00 EUR\nClassificação CPV (Vocabulário Comum para os Contratos Públicos)\nObjeto principal\nVocabulário Principal: 15800000\nNº: LOT-0157\nDescrição do Lote: Pão ralado (embalagem 1 kg)\nPreço base s/IVA: 875,00 EUR\nClassificação CPV (Vocabulário Comum para os Contratos Públicos)\nObjeto principal\nVocabulário Principal: 15800000\nNº: LOT-0158\nDescrição do Lote: Pasta de caril (embalagem 100 grs)\nPreço base s/IVA: 195,00 EUR\nClassificação CPV (Vocabulário Comum para os Contratos Públicos)\nObjeto principal\nVocabulário Principal: 15800000\nNº: LOT-0159\nDescrição do Lote: Pate de Atum (embalagem 22 gr)\nPreço base s/IVA: 275,00 EUR\nClassificação CPV (Vocabulário Comum para os Contratos Públicos)\nObjeto principal\nVocabulário Principal: 15800000\nNº: LOT-0160\nDescrição do Lote: Pate de Sardinha  (embalagem 22 gr)\nPreço base s/IVA: 120,00 EUR\nClassificação CPV (Vocabulário Comum para os Contratos Públicos)\nObjeto principal\nVocabulário Principal: 15800000\nNº: LOT-0161\nDescrição do Lote: Pessêgo em calda  (lata 820gr)\nPreço base s/IVA: 1.200,00 EUR\nClassificação CPV (Vocabulário Comum para os Contratos Públicos)\nObjeto principal\nVocabulário Principal: 15800000\nNº: LOT-0162\nDescrição do Lote: Pickles (embalagem 5 Kg)\nPreço base s/IVA: 350,00 EUR\nClassificação CPV (Vocabulário Comum para os Contratos Públicos)\nObjeto principal\nVocabulário Principal: 15800000\nNº: LOT-0163\nDescrição do Lote: Pimenta branca moída (embalagem 1 Kg)\nPreço base s/IVA: 225,00 EUR\nClassificação CPV (Vocabulário Comum para os Contratos Públicos)\nObjeto principal\nVocabulário Principal: 15800000\nNº: LOT-0164\nDescrição do Lote: Pimenta cayenne (embalagem 50 grs)\nPreço base s/IVA: 25,00 EUR\nClassificação CPV (Vocabulário Comum para os Contratos Públicos)\nObjeto principal\nVocabulário Principal: 15800000\nNº: LOT-0165\nDescrição do Lote: Pimenta preta moída (embalagem 17 grs)\nPreço base s/IVA: 10,00 EUR\nClassificação CPV (Vocabulário Comum para os Contratos Públicos)\nObjeto principal\nVocabulário Principal: 15800000\nNº: LOT-0166\nDescrição do Lote: Pimenta preta moída (embalagem 1 Kg)\nPreço base s/IVA: 60,00 EUR\nClassificação CPV (Vocabulário Comum para os Contratos Públicos)\nObjeto principal\nVocabulário Principal: 15800000\nNº: LOT-0167\nDescrição do Lote: Pimentão doce (embalagem 1 Kg)\nPreço base s/IVA: 350,00 EUR\nClassificação CPV (Vocabulário Comum para os Contratos Públicos)\nObjeto principal\nVocabulário Principal: 15800000\nNº: LOT-0168\nDescrição do Lote: Polpa de manga (embalagem 860gr)\nPreço base s/IVA: 120,00 EUR\nClassificação CPV (Vocabulário Comum para os Contratos Públicos)\nObjeto principal\nVocabulário Principal: 15800000\nNº: LOT-0169\nDescrição do Lote: Polpa de tomate (embalagem 1 kg)\nPreço base s/IVA: 225,00 EUR\nClassificação CPV (Vocabulário Comum para os Contratos Públicos)\nObjeto principal\nVocabulário Principal: 15800000\nNº: LOT-0170\nDescrição do Lote: Polpa de tomate (embalagem 2,5 kg)\nPreço base s/IVA: 2.700,00 EUR\nClassificação CPV (Vocabulário Comum para os Contratos Públicos)\nObjeto principal\nVocabulário Principal: 15800000\nNº: LOT-0171\nDescrição do Lote: Polpa de maracujá (embalagem 565 grs)\nPreço base s/IVA: 90,00 EUR\nClassificação CPV (Vocabulário Comum para os Contratos Públicos)\nObjeto principal\nVocabulário Principal: 15800000\nNº: LOT-0172\nDescrição do Lote: Pudim  baunilha (embalagem 800gr)\nPreço base s/IVA: 600,00 EUR\nClassificação CPV (Vocabulário Comum para os Contratos Públicos)\nObjeto principal\nVocabulário Principal: 15800000\nNº: LOT-0173\nDescrição do Lote: Pudim  caramelo (embalagem 800gr)\nPreço base s/IVA: 720,00 EUR\nClassificação CPV (Vocabulário Comum para os Contratos Públicos)\nObjeto principal\nVocabulário Principal: 15800000\nNº: LOT-0174\nDescrição do Lote: Pudim chocolate (embalagem 800gr)\nPreço base s/IVA: 400,00 EUR\nClassificação CPV (Vocabulário Comum para os Contratos Públicos)\nObjeto principal\nVocabulário Principal: 15800000\nNº: LOT-0175\nDescrição do Lote: Pudim flan (embalagem 800gr)\nPreço base s/IVA: 400,00 EUR\nClassificação CPV (Vocabulário Comum para os Contratos Públicos)\nObjeto principal\nVocabulário Principal: 15800000\nNº: LOT-0176\nDescrição do Lote: Pudim morango (embalagem 800gr)\nPreço base s/IVA: 360,00 EUR\nClassificação CPV (Vocabulário Comum para os Contratos Públicos)\nObjeto principal\nVocabulário Principal: 15800000\nNº: LOT-0177\nDescrição do Lote: Puré de batata (embalagem 5 Kg)\nPreço base s/IVA: 4.200,00 EUR\nClassificação CPV (Vocabulário Comum para os Contratos Públicos)\nObjeto principal\nVocabulário Principal: 15800000\nNº: LOT-0178\nDescrição do Lote: Quinoa\nPreço base s/IVA: 568,00 EUR\nClassificação CPV (Vocabulário Comum para os Contratos Públicos)\nObjeto principal\nVocabulário Principal: 15800000\nNº: LOT-0179\nDescrição do Lote: Sal de mesa refinado (embalagem 250gr)\nPreço base s/IVA: 70,00 EUR\nClassificação CPV (Vocabulário Comum para os Contratos Públicos)\nObjeto principal\nVocabulário Principal: 15800000\nNº: LOT-0180\nDescrição do Lote: Sal grosso (embalagem 1 Kg)\nPreço base s/IVA: 840,00 EUR\nClassificação CPV (Vocabulário Comum para os Contratos Públicos)\nObjeto principal\nVocabulário Principal: 15800000\nNº: LOT-0181\nDescrição do Lote: Sal saquetas individuais (embalagens de 1000 x 1 gr)\nPreço base s/IVA: 2.250,00 EUR\nClassificação CPV (Vocabulário Comum para os Contratos Públicos)\nObjeto principal\nVocabulário Principal: 15800000\nNº: LOT-0182\nDescrição do Lote: Salada de frutas em lata (embalagem 840gr)\nPreço base s/IVA: 510,00 EUR\nClassificação CPV (Vocabulário Comum para os Contratos Públicos)\nObjeto principal\nVocabulário Principal: 15800000\nNº: LOT-0183\nDescrição do Lote: Salsichas (lata 25 pares)\nPreço base s/IVA: 560,00 EUR\nClassificação CPV (Vocabulário Comum para os Contratos Públicos)\nObjeto principal\nVocabulário Principal: 15800000\nNº: LOT-0184\nDescrição do Lote: Salsichas (lata de 8 salsichas)\nPreço base s/IVA: 120,00 EUR\nClassificação CPV (Vocabulário Comum para os Contratos Públicos)\nObjeto principal\nVocabulário Principal: 15800000\nNº: LOT-0185\nDescrição do Lote: Seitan (embalagem 300gr)\nPreço base s/IVA: 3.300,00 EUR\nClassificação CPV (Vocabulário Comum para os Contratos Públicos)\nObjeto principal\nVocabulário Principal: 15800000\nNº: LOT-0186\nDescrição do Lote: Semola de milho (embalagem 500gr)\nPreço base s/IVA: 50,00 EUR\nClassificação CPV (Vocabulário Comum para os Contratos Públicos)\nObjeto principal\nVocabulário Principal: 15800000\nNº: LOT-0187\nDescrição do Lote: Sopa de cebola (embalagem 812 gr)\nPreço base s/IVA: 360,00 EUR\nClassificação CPV (Vocabulário Comum para os Contratos Públicos)\nObjeto principal\nVocabulário Principal: 15800000\nNº: LOT-0188\nDescrição do Lote: Sultanas (embalagem 1 Kg)\nPreço base s/IVA: 120,00 EUR\nClassificação CPV (Vocabulário Comum para os Contratos Públicos)\nObjeto principal\nVocabulário Principal: 15800000\nNº: LOT-0189\nDescrição do Lote: Tamâras sem caroço (embalagem 1 Kg)\nPreço base s/IVA: 27,50 EUR\nClassificação CPV (Vocabulário Comum para os Contratos Públicos)\nObjeto principal\nVocabulário Principal: 15800000\nNº: LOT-0190\nDescrição do Lote: Tofu  (embalagem 350 gr)\nPreço base s/IVA: 4.000,00 EUR\nClassificação CPV (Vocabulário Comum para os Contratos Públicos)\nObjeto principal\nVocabulário Principal: 15800000\nNº: LOT-0191\nDescrição do Lote: Tomate inteiro pelado (embalagem 2,5 Kg)\nPreço base s/IVA: 4.500,00 EUR\nClassificação CPV (Vocabulário Comum para os Contratos Públicos)\nObjeto principal\nVocabulário Principal: 15800000\nNº: LOT-0192\nDescrição do Lote: Tomate inteiro pelado (embalagem 780gr)\nPreço base s/IVA: 1.200,00 EUR\nClassificação CPV (Vocabulário Comum para os Contratos Públicos)\nObjeto principal\nVocabulário Principal: 15800000\nNº: LOT-0193\nDescrição do Lote: Tomate seco (embalagem 50 grs)\nPreço base s/IVA: 350,00 EUR\nClassificação CPV (Vocabulário Comum para os Contratos Públicos)\nObjeto principal\nVocabulário Principal: 15800000\nNº: LOT-0194\nDescrição do Lote: Tortilhas de milho (Wraps - embalagem 250grs)\nPreço base s/IVA: 350,00 EUR\nClassificação CPV (Vocabulário Comum para os Contratos Públicos)\nObjeto principal\nVocabulário Principal: 15800000\nNº: LOT-0195\nDescrição do Lote: Vinagre balsâmico (embalagem inviolável 250ml)\nPreço base s/IVA: 40,00 EUR\nClassificação CPV (Vocabulário Comum para os Contratos Públicos)\nObjeto principal\nVocabulário Principal: 15800000\nNº: LOT-0196\nDescrição do Lote: Vinagre de vinho (embalagem de 0,75cl)\nPreço base s/IVA: 800,00 EUR\nClassificação CPV (Vocabulário Comum para os Contratos Públicos)\nObjeto principal\nVocabulário Principal: 15800000\nNº: LOT-0197\nDescrição do Lote: Vinagre de vinho (embalagem inviolável de 250ml)\nPreço base s/IVA: 800,00 EUR\nClassificação CPV (Vocabulário Comum para os Contratos Públicos)\nObjeto principal\nVocabulário Principal: 15800000\nNº: LOT-0198\nDescrição do Lote: Vinagre saquetas individuais (caixa 220 x 15 ml)\nPreço base s/IVA: 2.000,00 EUR\nClassificação CPV (Vocabulário Comum para os Contratos Públicos)\nObjeto principal\nVocabulário Principal: 15800000\nNº: LOT-0199\nDescrição do Lote: Vinagre de cidra (embalagem 50 cl)\nPreço base s/IVA: 30,00 EUR\nClassificação CPV (Vocabulário Comum para os Contratos Públicos)\nObjeto principal\nVocabulário Principal: 15800000\nNº: LOT-0200\nDescrição do Lote: Vinha d'alho (embalagem de 200 grs)\nPreço base s/IVA: 36,00 EUR\nClassificação CPV (Vocabulário Comum para os Contratos Públicos)\nObjeto principal\nVocabulário Principal: 15800000\nNº: LOT-0201\nDescrição do Lote: Vinho branco (box 5L)\nPreço base s/IVA: 450,00 EUR\nClassificação CPV (Vocabulário Comum para os Contratos Públicos)\nObjeto principal\nVocabulário Principal: 15800000\nNº: LOT-0202\nDescrição do Lote: Vinho branco corrente para cozinhar (embalagem 1 lt)\nPreço base s/IVA: 3.900,00 EUR\nClassificação CPV (Vocabulário Comum para os Contratos Públicos)\nObjeto principal\nVocabulário Principal: 15800000\nNº: LOT-0203\nDescrição do Lote: Vinho tinto (box 5L)\nPreço base s/IVA: 450,00 EUR\nClassificação CPV (Vocabulário Comum para os Contratos Públicos)\nObjeto principal\nVocabulário Principal: 15800000\nNº: LOT-0204\nDescrição do Lote: Vinho tinto corrente para cozinhar (embalagem 1 lt)\nPreço base s/IVA: 300,00 EUR\nClassificação CPV (Vocabulário Comum para os Contratos Públicos)\nObjeto principal\nVocabulário Principal: 15800000\n\n7 - INDICAÇÕES ADICIONAIS\nO contrato envolve aquisição conjunta (satisfação de várias entidades)? Não\nO contrato é adjudicado por uma central de compras? Não\n\n8 - TÉCNICAS\nO concurso destina-se à celebração de um acordo-quadro? Inexistência de acordo-quadro\nÉ utilizado um leilão eletrónico? Não\nÉ adotada uma fase de negociação? Não\nSistema de Aquisição Dinâmico: Inexistência de sistema de aquisição dinâmico\n\n9 - LOCAL DA EXECUÇÃO DO CONTRATO\nLOCAL DA EXECUÇÃO DO CONTRATO (PROCEDIMENTO)\nLOCAL DA EXECUÇÃO DO CONTRATO (LOTE)\nIdentificador do Lote: LOT-0001\nPaís: Portugal\nNUT III: PT150\nLocalidade: Faro\nDistrito: Faro\nConcelho: Faro\nFreguesia: Todas\nIdentificador do Lote: LOT-0002\nPaís: Portugal\nNUT III: PT150\nLocalidade: Faro\nDistrito: Faro\nConcelho: Faro\nFreguesia: Todas\nIdentificador do Lote: LOT-0003\nPaís: Portugal\nNUT III: PT150\nLocalidade: Faro\nDistrito: Faro\nConcelho: Faro\nFreguesia: Todas\nIdentificador do Lote: LOT-0004\nPaís: Portugal\nNUT III: PT150\nLocalidade: Faro\nDistrito: Faro\nConcelho: Faro\nFreguesia: Todas\nIdentificador do Lote: LOT-0005\nPaís: Portugal\nNUT III: PT150\nLocalidade: Faro\nDistrito: Faro\nConcelho: Faro\nFreguesia: Todas\nIdentificador do Lote: LOT-0006\nPaís: Portugal\nNUT III: PT150\nLocalidade: Faro\nDistrito: Faro\nConcelho: Faro\nFreguesia: Todas\nIdentificador do Lote: LOT-0007\nPaís: Portugal\nNUT III: PT150\nLocalidade: Faro\nDistrito: Faro\nConcelho: Faro\nFreguesia: Todas\nIdentificador do Lote: LOT-0008\nPaís: Portugal\nNUT III: PT150\nLocalidade: Faro\nDistrito: Faro\nConcelho: Faro\nFreguesia: Todas\nIdentificador do Lote: LOT-0009\nPaís: Portugal\nNUT III: PT150\nLocalidade: Faro\nDistrito: Faro\nConcelho: Faro\nFreguesia: Todas\nIdentificador do Lote: LOT-0010\nPaís: Portugal\nNUT III: PT150\nLocalidade: Faro\nDistrito: Faro\nConcelho: Faro\nFreguesia: Todas\nIdentificador do Lote: LOT-0011\nPaís: Portugal\nNUT III: PT150\nLocalidade: Faro\nDistrito: Faro\nConcelho: Faro\nFreguesia: Todas\nIdentificador do Lote: LOT-0012\nPaís: Portugal\nNUT III: PT150\nLocalidade: Faro\nDistrito: Faro\nConcelho: Faro\nFreguesia: Todas\nIdentificador do Lote: LOT-0013\nPaís: Portugal\nNUT III: PT150\nLocalidade: Faro\nDistrito: Faro\nConcelho: Faro\nFreguesia: Todas\nIdentificador do Lote: LOT-0014\nPaís: Portugal\nNUT III: PT150\nLocalidade: Faro\nDistrito: Faro\nConcelho: Faro\nFreguesia: Todas\nIdentificador do Lote: LOT-0015\nPaís: Portugal\nNUT III: PT150\nLocalidade: Faro\nDistrito: Faro\nConcelho: Faro\nFreguesia: Todas\nIdentificador do Lote: LOT-0016\nPaís: Portugal\nNUT III: PT150\nLocalidade: Faro\nDistrito: Faro\nConcelho: Faro\nFreguesia: Todas\nIdentificador do Lote: LOT-0017\nPaís: Portugal\nNUT III: PT150\nLocalidade: Faro\nDistrito: Faro\nConcelho: Faro\nFreguesia: Todas\nIdentificador do Lote: LOT-0018\nPaís: Portugal\nNUT III: PT150\nLocalidade: Faro\nDistrito: Faro\nConcelho: Faro\nFreguesia: Todas\nIdentificador do Lote: LOT-0019\nPaís: Portugal\nNUT III: PT150\nLocalidade: Faro\nDistrito: Faro\nConcelho: Faro\nFreguesia: Todas\nIdentificador do Lote: LOT-0020\nPaís: Portugal\nNUT III: PT150\nLocalidade: Faro\nDistrito: Faro\nConcelho: Faro\nFreguesia: Todas\nIdentificador do Lote: LOT-0021\nPaís: Portugal\nNUT III: PT150\nLocalidade: Faro\nDistrito: Faro\nConcelho: Faro\nFreguesia: Todas\nIdentificador do Lote: LOT-0022\nPaís: Portugal\nNUT III: PT150\nLocalidade: Faro\nDistrito: Faro\nConcelho: Faro\nFreguesia: Todas\nIdentificador do Lote: LOT-0023\nPaís: Portugal\nNUT III: PT150\nLocalidade: Faro\nDistrito: Faro\nConcelho: Faro\nFreguesia: Todas\nIdentificador do Lote: LOT-0024\nPaís: Portugal\nNUT III: PT150\nLocalidade: Faro\nDistrito: Faro\nConcelho: Faro\nFreguesia: Todas\nIdentificador do Lote: LOT-0025\nPaís: Portugal\nNUT III: PT150\nLocalidade: Faro\nDistrito: Faro\nConcelho: Faro\nFreguesia: Todas\nIdentificador do Lote: LOT-0026\nPaís: Portugal\nNUT III: PT150\nLocalidade: Faro\nDistrito: Faro\nConcelho: Faro\nFreguesia: Todas\nIdentificador do Lote: LOT-0027\nPaís: Portugal\nNUT III: PT150\nLocalidade: Faro\nDistrito: Faro\nConcelho: Faro\nFreguesia: Todas\nIdentificador do Lote: LOT-0028\nPaís: Portugal\nNUT III: PT150\nLocalidade: Faro\nDistrito: Faro\nConcelho: Faro\nFreguesia: Todas\nIdentificador do Lote: LOT-0029\nPaís: Portugal\nNUT III: PT150\nLocalidade: Faro\nDistrito: Faro\nConcelho: Faro\nFreguesia: Todas\nIdentificador do Lote: LOT-0030\nPaís: Portugal\nNUT III: PT150\nLocalidade: Faro\nDistrito: Faro\nConcelho: Faro\nFreguesia: Todas\nIdentificador do Lote: LOT-0031\nPaís: Portugal\nNUT III: PT150\nLocalidade: Faro\nDistrito: Faro\nConcelho: Faro\nFreguesia: Todas\nIdentificador do Lote: LOT-0032\nPaís: Portugal\nNUT III: PT150\nLocalidade: Faro\nDistrito: Faro\nConcelho: Faro\nFreguesia: Todas\nIdentificador do Lote: LOT-0033\nPaís: Portugal\nNUT III: PT150\nLocalidade: Faro\nDistrito: Faro\nConcelho: Faro\nFreguesia: Todas\nIdentificador do Lote: LOT-0034\nPaís: Portugal\nNUT III: PT150\nLocalidade: Faro\nDistrito: Faro\nConcelho: Faro\nFreguesia: Todas\nIdentificador do Lote: LOT-0035\nPaís: Portugal\nNUT III: PT150\nLocalidade: Faro\nDistrito: Faro\nConcelho: Faro\nFreguesia: Todas\nIdentificador do Lote: LOT-0036\nPaís: Portugal\nNUT III: PT150\nLocalidade: Faro\nDistrito: Faro\nConcelho: Faro\nFreguesia: Todas\nIdentificador do Lote: LOT-0037\nPaís: Portugal\nNUT III: PT150\nLocalidade: Faro\nDistrito: Faro\nConcelho: Faro\nFreguesia: Todas\nIdentificador do Lote: LOT-0038\nPaís: Portugal\nNUT III: PT150\nLocalidade: Faro\nDistrito: Faro\nConcelho: Faro\nFreguesia: Todas\nIdentificador do Lote: LOT-0039\nPaís: Portugal\nNUT III: PT150\nLocalidade: Faro\nDistrito: Faro\nConcelho: Faro\nFreguesia: Todas\nIdentificador do Lote: LOT-0040\nPaís: Portugal\nNUT III: PT150\nLocalidade: Faro\nDistrito: Faro\nConcelho: Faro\nFreguesia: Todas\nIdentificador do Lote: LOT-0041\nPaís: Portugal\nNUT III: PT150\nLocalidade: Faro\nDistrito: Faro\nConcelho: Faro\nFreguesia: Todas\nIdentificador do Lote: LOT-0042\nPaís: Portugal\nNUT III: PT150\nLocalidade: Faro\nDistrito: Faro\nConcelho: Faro\nFreguesia: Todas\nIdentificador do Lote: LOT-0043\nPaís: Portugal\nNUT III: PT150\nLocalidade: Faro\nDistrito: Faro\nConcelho: Faro\nFreguesia: Todas\nIdentificador do Lote: LOT-0044\nPaís: Portugal\nNUT III: PT150\nLocalidade: Faro\nDistrito: Faro\nConcelho: Faro\nFreguesia: Todas\nIdentificador do Lote: LOT-0045\nPaís: Portugal\nNUT III: PT150\nLocalidade: Faro\nDistrito: Faro\nConcelho: Faro\nFreguesia: Todas\nIdentificador do Lote: LOT-0046\nPaís: Portugal\nNUT III: PT150\nLocalidade: Faro\nDistrito: Faro\nConcelho: Faro\nFreguesia: Todas\nIdentificador do Lote: LOT-0047\nPaís: Portugal\nNUT III: PT150\nLocalidade: Faro\nDistrito: Faro\nConcelho: Faro\nFreguesia: Todas\nIdentificador do Lote: LOT-0048\nPaís: Portugal\nNUT III: PT150\nLocalidade: Faro\nDistrito: Faro\nConcelho: Faro\nFreguesia: Todas\nIdentificador do Lote: LOT-0049\nPaís: Portugal\nNUT III: PT150\nLocalidade: Faro\nDistrito: Faro\nConcelho: Faro\nFreguesia: Todas\nIdentificador do Lote: LOT-0050\nPaís: Portugal\nNUT III: PT150\nLocalidade: Faro\nDistrito: Faro\nConcelho: Faro\nFreguesia: Todas\nIdentificador do Lote: LOT-0051\nPaís: Portugal\nNUT III: PT150\nLocalidade: Faro\nDistrito: Faro\nConcelho: Faro\nFreguesia: Todas\nIdentificador do Lote: LOT-0052\nPaís: Portugal\nNUT III: PT150\nLocalidade: Faro\nDistrito: Faro\nConcelho: Faro\nFreguesia: Todas\nIdentificador do Lote: LOT-0053\nPaís: Portugal\nNUT III: PT150\nLocalidade: Faro\nDistrito: Faro\nConcelho: Faro\nFreguesia: Todas\nIdentificador do Lote: LOT-0054\nPaís: Portugal\nNUT III: PT150\nLocalidade: Faro\nDistrito: Faro\nConcelho: Faro\nFreguesia: Todas\nIdentificador do Lote: LOT-0055\nPaís: Portugal\nNUT III: PT150\nLocalidade: Faro\nDistrito: Faro\nConcelho: Faro\nFreguesia: Todas\nIdentificador do Lote: LOT-0056\nPaís: Portugal\nNUT III: PT150\nLocalidade: Faro\nDistrito: Faro\nConcelho: Faro\nFreguesia: Todas\nIdentificador do Lote: LOT-0057\nPaís: Portugal\nNUT III: PT150\nLocalidade: Faro\nDistrito: Faro\nConcelho: Faro\nFreguesia: Todas\nIdentificador do Lote: LOT-0058\nPaís: Portugal\nNUT III: PT150\nLocalidade: Faro\nDistrito: Faro\nConcelho: Faro\nFreguesia: Todas\nIdentificador do Lote: LOT-0059\nPaís: Portugal\nNUT III: PT150\nLocalidade: Faro\nDistrito: Faro\nConcelho: Faro\nFreguesia: Todas\nIdentificador do Lote: LOT-0060\nPaís: Portugal\nNUT III: PT150\nLocalidade: Faro\nDistrito: Faro\nConcelho: Faro\nFreguesia: Todas\nIdentificador do Lote: LOT-0061\nPaís: Portugal\nNUT III: PT150\nLocalidade: Faro\nDistrito: Faro\nConcelho: Faro\nFreguesia: Todas\nIdentificador do Lote: LOT-0062\nPaís: Portugal\nNUT III: PT150\nLocalidade: Faro\nDistrito: Faro\nConcelho: Faro\nFreguesia: Todas\nIdentificador do Lote: LOT-0063\nPaís: Portugal\nNUT III: PT150\nLocalidade: Faro\nDistrito: Faro\nConcelho: Faro\nFreguesia: Todas\nIdentificador do Lote: LOT-0064\nPaís: Portugal\nNUT III: PT150\nLocalidade: Faro\nDistrito: Faro\nConcelho: Faro\nFreguesia: Todas\nIdentificador do Lote: LOT-0065\nPaís: Portugal\nNUT III: PT150\nLocalidade: Faro\nDistrito: Faro\nConcelho: Faro\nFreguesia: Todas\nIdentificador do Lote: LOT-0066\nPaís: Portugal\nNUT III: PT150\nLocalidade: Faro\nDistrito: Faro\nConcelho: Faro\nFreguesia: Todas\nIdentificador do Lote: LOT-0067\nPaís: Portugal\nNUT III: PT150\nLocalidade: Faro\nDistrito: Faro\nConcelho: Faro\nFreguesia: Todas\nIdentificador do Lote: LOT-0068\nPaís: Portugal\nNUT III: PT150\nLocalidade: Faro\nDistrito: Faro\nConcelho: Faro\nFreguesia: Todas\nIdentificador do Lote: LOT-0069\nPaís: Portugal\nNUT III: PT150\nLocalidade: Faro\nDistrito: Faro\nConcelho: Faro\nFreguesia: Todas\nIdentificador do Lote: LOT-0070\nPaís: Portugal\nNUT III: PT150\nLocalidade: Faro\nDistrito: Faro\nConcelho: Faro\nFreguesia: Todas\nIdentificador do Lote: LOT-0071\nPaís: Portugal\nNUT III: PT150\nLocalidade: Faro\nDistrito: Faro\nConcelho: Faro\nFreguesia: Todas\nIdentificador do Lote: LOT-0072\nPaís: Portugal\nNUT III: PT150\nLocalidade: Faro\nDistrito: Faro\nConcelho: Faro\nFreguesia: Todas\nIdentificador do Lote: LOT-0073\nPaís: Portugal\nNUT III: PT150\nLocalidade: Faro\nDistrito: Faro\nConcelho: Faro\nFreguesia: Todas\nIdentificador do Lote: LOT-0074\nPaís: Portugal\nNUT III: PT150\nLocalidade: Faro\nDistrito: Faro\nConcelho: Faro\nFreguesia: Todas\nIdentificador do Lote: LOT-0075\nPaís: Portugal\nNUT III: PT150\nLocalidade: Faro\nDistrito: Faro\nConcelho: Faro\nFreguesia: Todas\nIdentificador do Lote: LOT-0076\nPaís: Portugal\nNUT III: PT150\nLocalidade: Faro\nDistrito: Faro\nConcelho: Faro\nFreguesia: Todas\nIdentificador do Lote: LOT-0077\nPaís: Portugal\nNUT III: PT150\nLocalidade: Faro\nDistrito: Faro\nConcelho: Faro\nFreguesia: Todas\nIdentificador do Lote: LOT-0078\nPaís: Portugal\nNUT III: PT150\nLocalidade: Faro\nDistrito: Faro\nConcelho: Faro\nFreguesia: Todas\nIdentificador do Lote: LOT-0079\nPaís: Portugal\nNUT III: PT150\nLocalidade: Faro\nDistrito: Faro\nConcelho: Faro\nFreguesia: Todas\nIdentificador do Lote: LOT-0080\nPaís: Portugal\nNUT III: PT150\nLocalidade: Faro\nDistrito: Faro\nConcelho: Faro\nFreguesia: Todas\nIdentificador do Lote: LOT-0081\nPaís: Portugal\nNUT III: PT150\nLocalidade: Faro\nDistrito: Faro\nConcelho: Faro\nFreguesia: Todas\nIdentificador do Lote: LOT-0082\nPaís: Portugal\nNUT III: PT150\nLocalidade: Faro\nDistrito: Faro\nConcelho: Faro\nFreguesia: Todas\nIdentificador do Lote: LOT-0083\nPaís: Portugal\nNUT III: PT150\nLocalidade: Faro\nDistrito: Faro\nConcelho: Faro\nFreguesia: Todas\nIdentificador do Lote: LOT-0084\nPaís: Portugal\nNUT III: PT150\nLocalidade: Faro\nDistrito: Faro\nConcelho: Faro\nFreguesia: Todas\nIdentificador do Lote: LOT-0085\nPaís: Portugal\nNUT III: PT150\nLocalidade: Faro\nDistrito: Faro\nConcelho: Faro\nFreguesia: Todas\nIdentificador do Lote: LOT-0086\nPaís: Portugal\nNUT III: PT150\nLocalidade: Faro\nDistrito: Faro\nConcelho: Faro\nFreguesia: Todas\nIdentificador do Lote: LOT-0087\nPaís: Portugal\nNUT III: PT150\nLocalidade: Faro\nDistrito: Faro\nConcelho: Faro\nFreguesia: Todas\nIdentificador do Lote: LOT-0088\nPaís: Portugal\nNUT III: PT150\nLocalidade: Faro\nDistrito: Faro\nConcelho: Faro\nFreguesia: Todas\nIdentificador do Lote: LOT-0089\nPaís: Portugal\nNUT III: PT150\nLocalidade: Faro\nDistrito: Faro\nConcelho: Faro\nFreguesia: Todas\nIdentificador do Lote: LOT-0090\nPaís: Portugal\nNUT III: PT150\nLocalidade: Faro\nDistrito: Faro\nConcelho: Faro\nFreguesia: Todas\nIdentificador do Lote: LOT-0091\nPaís: Portugal\nNUT III: PT150\nLocalidade: Faro\nDistrito: Faro\nConcelho: Faro\nFreguesia: Todas\nIdentificador do Lote: LOT-0092\nPaís: Portugal\nNUT III: PT150\nLocalidade: Faro\nDistrito: Faro\nConcelho: Faro\nFreguesia: Todas\nIdentificador do Lote: LOT-0093\nPaís: Portugal\nNUT III: PT150\nLocalidade: Faro\nDistrito: Faro\nConcelho: Faro\nFreguesia: Todas\nIdentificador do Lote: LOT-0094\nPaís: Portugal\nNUT III: PT150\nLocalidade: Faro\nDistrito: Faro\nConcelho: Faro\nFreguesia: Todas\nIdentificador do Lote: LOT-0095\nPaís: Portugal\nNUT III: PT150\nLocalidade: Faro\nDistrito: Faro\nConcelho: Faro\nFreguesia: Todas\nIdentificador do Lote: LOT-0096\nPaís: Portugal\nNUT III: PT150\nLocalidade: Faro\nDistrito: Faro\nConcelho: Faro\nFreguesia: Todas\nIdentificador do Lote: LOT-0097\nPaís: Portugal\nNUT III: PT150\nLocalidade: Faro\nDistrito: Faro\nConcelho: Faro\nFreguesia: Todas\nIdentificador do Lote: LOT-0098\nPaís: Portugal\nNUT III: PT150\nLocalidade: Faro\nDistrito: Faro\nConcelho: Faro\nFreguesia: Todas\nIdentificador do Lote: LOT-0099\nPaís: Portugal\nNUT III: PT150\nLocalidade: Faro\nDistrito: Faro\nConcelho: Faro\nFreguesia: Todas\nIdentificador do Lote: LOT-0100\nPaís: Portugal\nNUT III: PT150\nLocalidade: Faro\nDistrito: Faro\nConcelho: Faro\nFreguesia: Todas\nIdentificador do Lote: LOT-0101\nPaís: Portugal\nNUT III: PT150\nLocalidade: Faro\nDistrito: Faro\nConcelho: Faro\nFreguesia: Todas\nIdentificador do Lote: LOT-0102\nPaís: Portugal\nNUT III: PT150\nLocalidade: Faro\nDistrito: Faro\nConcelho: Faro\nFreguesia: Todas\nIdentificador do Lote: LOT-0103\nPaís: Portugal\nNUT III: PT150\nLocalidade: Faro\nDistrito: Faro\nConcelho: Faro\nFreguesia: Todas\nIdentificador do Lote: LOT-0104\nPaís: Portugal\nNUT III: PT150\nLocalidade: Faro\nDistrito: Faro\nConcelho: Faro\nFreguesia: Todas\nIdentificador do Lote: LOT-0105\nPaís: Portugal\nNUT III: PT150\nLocalidade: Faro\nDistrito: Faro\nConcelho: Faro\nFreguesia: Todas\nIdentificador do Lote: LOT-0106\nPaís: Portugal\nNUT III: PT150\nLocalidade: Faro\nDistrito: Faro\nConcelho: Faro\nFreguesia: Todas\nIdentificador do Lote: LOT-0107\nPaís: Portugal\nNUT III: PT150\nLocalidade: Faro\nDistrito: Faro\nConcelho: Faro\nFreguesia: Todas\nIdentificador do Lote: LOT-0108\nPaís: Portugal\nNUT III: PT150\nLocalidade: Faro\nDistrito: Faro\nConcelho: Faro\nFreguesia: Todas\nIdentificador do Lote: LOT-0109\nPaís: Portugal\nNUT III: PT150\nLocalidade: Faro\nDistrito: Faro\nConcelho: Faro\nFreguesia: Todas\nIdentificador do Lote: LOT-0110\nPaís: Portugal\nNUT III: PT150\nLocalidade: Faro\nDistrito: Faro\nConcelho: Faro\nFreguesia: Todas\nIdentificador do Lote: LOT-0111\nPaís: Portugal\nNUT III: PT150\nLocalidade: Faro\nDistrito: Faro\nConcelho: Faro\nFreguesia: Todas\nIdentificador do Lote: LOT-0112\nPaís: Portugal\nNUT III: PT150\nLocalidade: Faro\nDistrito: Faro\nConcelho: Faro\nFreguesia: Todas\nIdentificador do Lote: LOT-0113\nPaís: Portugal\nNUT III: PT150\nLocalidade: Faro\nDistrito: Faro\nConcelho: Faro\nFreguesia: Todas\nIdentificador do Lote: LOT-0114\nPaís: Portugal\nNUT III: PT150\nLocalidade: Faro\nDistrito: Faro\nConcelho: Faro\nFreguesia: Todas\nIdentificador do Lote: LOT-0115\nPaís: Portugal\nNUT III: PT150\nLocalidade: Faro\nDistrito: Faro\nConcelho: Faro\nFreguesia: Todas\nIdentificador do Lote: LOT-0116\nPaís: Portugal\nNUT III: PT150\nLocalidade: Faro\nDistrito: Faro\nConcelho: Faro\nFreguesia: Todas\nIdentificador do Lote: LOT-0117\nPaís: Portugal\nNUT III: PT150\nLocalidade: Faro\nDistrito: Faro\nConcelho: Faro\nFreguesia: Todas\nIdentificador do Lote: LOT-0118\nPaís: Portugal\nNUT III: PT150\nLocalidade: Faro\nDistrito: Faro\nConcelho: Faro\nFreguesia: Todas\nIdentificador do Lote: LOT-0119\nPaís: Portugal\nNUT III: PT150\nLocalidade: Faro\nDistrito: Faro\nConcelho: Faro\nFreguesia: Todas\nIdentificador do Lote: LOT-0120\nPaís: Portugal\nNUT III: PT150\nLocalidade: Faro\nDistrito: Faro\nConcelho: Faro\nFreguesia: Todas\nIdentificador do Lote: LOT-0121\nPaís: Portugal\nNUT III: PT150\nLocalidade: Faro\nDistrito: Faro\nConcelho: Faro\nFreguesia: Todas\nIdentificador do Lote: LOT-0122\nPaís: Portugal\nNUT III: PT150\nLocalidade: Faro\nDistrito: Faro\nConcelho: Faro\nFreguesia: Todas\nIdentificador do Lote: LOT-0123\nPaís: Portugal\nNUT III: PT150\nLocalidade: Faro\nDistrito: Faro\nConcelho: Faro\nFreguesia: Todas\nIdentificador do Lote: LOT-0124\nPaís: Portugal\nNUT III: PT150\nLocalidade: Faro\nDistrito: Faro\nConcelho: Faro\nFreguesia: Todas\nIdentificador do Lote: LOT-0125\nPaís: Portugal\nNUT III: PT150\nLocalidade: Faro\nDistrito: Faro\nConcelho: Faro\nFreguesia: Todas\nIdentificador do Lote: LOT-0126\nPaís: Portugal\nNUT III: PT150\nLocalidade: Faro\nDistrito: Faro\nConcelho: Faro\nFreguesia: Todas\nIdentificador do Lote: LOT-0127\nPaís: Portugal\nNUT III: PT150\nLocalidade: Faro\nDistrito: Faro\nConcelho: Faro\nFreguesia: Todas\nIdentificador do Lote: LOT-0128\nPaís: Portugal\nNUT III: PT150\nLocalidade: Faro\nDistrito: Faro\nConcelho: Faro\nFreguesia: Todas\nIdentificador do Lote: LOT-0129\nPaís: Portugal\nNUT III: PT150\nLocalidade: Faro\nDistrito: Faro\nConcelho: Faro\nFreguesia: Todas\nIdentificador do Lote: LOT-0130\nPaís: Portugal\nNUT III: PT150\nLocalidade: Faro\nDistrito: Faro\nConcelho: Faro\nFreguesia: Todas\nIdentificador do Lote: LOT-0131\nPaís: Portugal\nNUT III: PT150\nLocalidade: Faro\nDistrito: Faro\nConcelho: Faro\nFreguesia: Todas\nIdentificador do Lote: LOT-0132\nPaís: Portugal\nNUT III: PT150\nLocalidade: Faro\nDistrito: Faro\nConcelho: Faro\nFreguesia: Todas\nIdentificador do Lote: LOT-0133\nPaís: Portugal\nNUT III: PT150\nLocalidade: Faro\nDistrito: Faro\nConcelho: Faro\nFreguesia: Todas\nIdentificador do Lote: LOT-0134\nPaís: Portugal\nNUT III: PT150\nLocalidade: Faro\nDistrito: Faro\nConcelho: Faro\nFreguesia: Todas\nIdentificador do Lote: LOT-0135\nPaís: Portugal\nNUT III: PT150\nLocalidade: Faro\nDistrito: Faro\nConcelho: Faro\nFreguesia: Todas\nIdentificador do Lote: LOT-0136\nPaís: Portugal\nNUT III: PT150\nLocalidade: Faro\nDistrito: Faro\nConcelho: Faro\nFreguesia: Todas\nIdentificador do Lote: LOT-0137\nPaís: Portugal\nNUT III: PT150\nLocalidade: Faro\nDistrito: Faro\nConcelho: Faro\nFreguesia: Todas\nIdentificador do Lote: LOT-0138\nPaís: Portugal\nNUT III: PT150\nLocalidade: Faro\nDistrito: Faro\nConcelho: Faro\nFreguesia: Todas\nIdentificador do Lote: LOT-0139\nPaís: Portugal\nNUT III: PT150\nLocalidade: Faro\nDistrito: Faro\nConcelho: Faro\nFreguesia: Todas\nIdentificador do Lote: LOT-0140\nPaís: Portugal\nNUT III: PT150\nLocalidade: Faro\nDistrito: Faro\nConcelho: Faro\nFreguesia: Todas\nIdentificador do Lote: LOT-0141\nPaís: Portugal\nNUT III: PT150\nLocalidade: Faro\nDistrito: Faro\nConcelho: Faro\nFreguesia: Todas\nIdentificador do Lote: LOT-0142\nPaís: Portugal\nNUT III: PT150\nLocalidade: Faro\nDistrito: Faro\nConcelho: Faro\nFreguesia: Todas\nIdentificador do Lote: LOT-0143\nPaís: Portugal\nNUT III: PT150\nLocalidade: Faro\nDistrito: Faro\nConcelho: Faro\nFreguesia: Todas\nIdentificador do Lote: LOT-0144\nPaís: Portugal\nNUT III: PT150\nLocalidade: Faro\nDistrito: Faro\nConcelho: Faro\nFreguesia: Todas\nIdentificador do Lote: LOT-0145\nPaís: Portugal\nNUT III: PT150\nLocalidade: Faro\nDistrito: Faro\nConcelho: Faro\nFreguesia: Todas\nIdentificador do Lote: LOT-0146\nPaís: Portugal\nNUT III: PT150\nLocalidade: Faro\nDistrito: Faro\nConcelho: Faro\nFreguesia: Todas\nIdentificador do Lote: LOT-0147\nPaís: Portugal\nNUT III: PT150\nLocalidade: Faro\nDistrito: Faro\nConcelho: Faro\nFreguesia: Todas\nIdentificador do Lote: LOT-0148\nPaís: Portugal\nNUT III: PT150\nLocalidade: Faro\nDistrito: Faro\nConcelho: Faro\nFreguesia: Todas\nIdentificador do Lote: LOT-0149\nPaís: Portugal\nNUT III: PT150\nLocalidade: Faro\nDistrito: Faro\nConcelho: Faro\nFreguesia: Todas\nIdentificador do Lote: LOT-0150\nPaís: Portugal\nNUT III: PT150\nLocalidade: Faro\nDistrito: Faro\nConcelho: Faro\nFreguesia: Todas\nIdentificador do Lote: LOT-0151\nPaís: Portugal\nNUT III: PT150\nLocalidade: Faro\nDistrito: Faro\nConcelho: Faro\nFreguesia: Todas\nIdentificador do Lote: LOT-0152\nPaís: Portugal\nNUT III: PT150\nLocalidade: Faro\nDistrito: Faro\nConcelho: Faro\nFreguesia: Todas\nIdentificador do Lote: LOT-0153\nPaís: Portugal\nNUT III: PT150\nLocalidade: Faro\nDistrito: Faro\nConcelho: Faro\nFreguesia: Todas\nIdentificador do Lote: LOT-0154\nPaís: Portugal\nNUT III: PT150\nLocalidade: Faro\nDistrito: Faro\nConcelho: Faro\nFreguesia: Todas\nIdentificador do Lote: LOT-0155\nPaís: Portugal\nNUT III: PT150\nLocalidade: Faro\nDistrito: Faro\nConcelho: Faro\nFreguesia: Todas\nIdentificador do Lote: LOT-0156\nPaís: Portugal\nNUT III: PT150\nLocalidade: Faro\nDistrito: Faro\nConcelho: Faro\nFreguesia: Todas\nIdentificador do Lote: LOT-0157\nPaís: Portugal\nNUT III: PT150\nLocalidade: Faro\nDistrito: Faro\nConcelho: Faro\nFreguesia: Todas\nIdentificador do Lote: LOT-0158\nPaís: Portugal\nNUT III: PT150\nLocalidade: Faro\nDistrito: Faro\nConcelho: Faro\nFreguesia: Todas\nIdentificador do Lote: LOT-0159\nPaís: Portugal\nNUT III: PT150\nLocalidade: Faro\nDistrito: Faro\nConcelho: Faro\nFreguesia: Todas\nIdentificador do Lote: LOT-0160\nPaís: Portugal\nNUT III: PT150\nLocalidade: Faro\nDistrito: Faro\nConcelho: Faro\nFreguesia: Todas\nIdentificador do Lote: LOT-0161\nPaís: Portugal\nNUT III: PT150\nLocalidade: Faro\nDistrito: Faro\nConcelho: Faro\nFreguesia: Todas\nIdentificador do Lote: LOT-0162\nPaís: Portugal\nNUT III: PT150\nLocalidade: Faro\nDistrito: Faro\nConcelho: Faro\nFreguesia: Todas\nIdentificador do Lote: LOT-0163\nPaís: Portugal\nNUT III: PT150\nLocalidade: Faro\nDistrito: Faro\nConcelho: Faro\nFreguesia: Todas\nIdentificador do Lote: LOT-0164\nPaís: Portugal\nNUT III: PT150\nLocalidade: Faro\nDistrito: Faro\nConcelho: Faro\nFreguesia: Todas\nIdentificador do Lote: LOT-0165\nPaís: Portugal\nNUT III: PT150\nLocalidade: Faro\nDistrito: Faro\nConcelho: Faro\nFreguesia: Todas\nIdentificador do Lote: LOT-0166\nPaís: Portugal\nNUT III: PT150\nLocalidade: Faro\nDistrito: Faro\nConcelho: Faro\nFreguesia: Todas\nIdentificador do Lote: LOT-0167\nPaís: Portugal\nNUT III: PT150\nLocalidade: Faro\nDistrito: Faro\nConcelho: Faro\nFreguesia: Todas\nIdentificador do Lote: LOT-0168\nPaís: Portugal\nNUT III: PT150\nLocalidade: Faro\nDistrito: Faro\nConcelho: Faro\nFreguesia: Todas\nIdentificador do Lote: LOT-0169\nPaís: Portugal\nNUT III: PT150\nLocalidade: Faro\nDistrito: Faro\nConcelho: Faro\nFreguesia: Todas\nIdentificador do Lote: LOT-0170\nPaís: Portugal\nNUT III: PT150\nLocalidade: Faro\nDistrito: Faro\nConcelho: Faro\nFreguesia: Todas\nIdentificador do Lote: LOT-0171\nPaís: Portugal\nNUT III: PT150\nLocalidade: Faro\nDistrito: Faro\nConcelho: Faro\nFreguesia: Todas\nIdentificador do Lote: LOT-0172\nPaís: Portugal\nNUT III: PT150\nLocalidade: Faro\nDistrito: Faro\nConcelho: Faro\nFreguesia: Todas\nIdentificador do Lote: LOT-0173\nPaís: Portugal\nNUT III: PT150\nLocalidade: Faro\nDistrito: Faro\nConcelho: Faro\nFreguesia: Todas\nIdentificador do Lote: LOT-0174\nPaís: Portugal\nNUT III: PT150\nLocalidade: Faro\nDistrito: Faro\nConcelho: Faro\nFreguesia: Todas\nIdentificador do Lote: LOT-0175\nPaís: Portugal\nNUT III: PT150\nLocalidade: Faro\nDistrito: Faro\nConcelho: Faro\nFreguesia: Todas\nIdentificador do Lote: LOT-0176\nPaís: Portugal\nNUT III: PT150\nLocalidade: Faro\nDistrito: Faro\nConcelho: Faro\nFreguesia: Todas\nIdentificador do Lote: LOT-0177\nPaís: Portugal\nNUT III: PT150\nLocalidade: Faro\nDistrito: Faro\nConcelho: Faro\nFreguesia: Todas\nIdentificador do Lote: LOT-0178\nPaís: Portugal\nNUT III: PT150\nLocalidade: Faro\nDistrito: Faro\nConcelho: Faro\nFreguesia: Todas\nIdentificador do Lote: LOT-0179\nPaís: Portugal\nNUT III: PT150\nLocalidade: Faro\nDistrito: Faro\nConcelho: Faro\nFreguesia: Todas\nIdentificador do Lote: LOT-0180\nPaís: Portugal\nNUT III: PT150\nLocalidade: Faro\nDistrito: Faro\nConcelho: Faro\nFreguesia: Todas\nIdentificador do Lote: LOT-0181\nPaís: Portugal\nNUT III: PT150\nLocalidade: Faro\nDistrito: Faro\nConcelho: Faro\nFreguesia: Todas\nIdentificador do Lote: LOT-0182\nPaís: Portugal\nNUT III: PT150\nLocalidade: Faro\nDistrito: Faro\nConcelho: Faro\nFreguesia: Todas\nIdentificador do Lote: LOT-0183\nPaís: Portugal\nNUT III: PT150\nLocalidade: Faro\nDistrito: Faro\nConcelho: Faro\nFreguesia: Todas\nIdentificador do Lote: LOT-0184\nPaís: Portugal\nNUT III: PT150\nLocalidade: Faro\nDistrito: Faro\nConcelho: Faro\nFreguesia: Todas\nIdentificador do Lote: LOT-0185\nPaís: Portugal\nNUT III: PT150\nLocalidade: Faro\nDistrito: Faro\nConcelho: Faro\nFreguesia: Todas\nIdentificador do Lote: LOT-0186\nPaís: Portugal\nNUT III: PT150\nLocalidade: Faro\nDistrito: Faro\nConcelho: Faro\nFreguesia: Todas\nIdentificador do Lote: LOT-0187\nPaís: Portugal\nNUT III: PT150\nLocalidade: Faro\nDistrito: Faro\nConcelho: Faro\nFreguesia: Todas\nIdentificador do Lote: LOT-0188\nPaís: Portugal\nNUT III: PT150\nLocalidade: Faro\nDistrito: Faro\nConcelho: Faro\nFreguesia: Todas\nIdentificador do Lote: LOT-0189\nPaís: Portugal\nNUT III: PT150\nLocalidade: Faro\nDistrito: Faro\nConcelho: Faro\nFreguesia: Todas\nIdentificador do Lote: LOT-0190\nPaís: Portugal\nNUT III: PT150\nLocalidade: Faro\nDistrito: Faro\nConcelho: Faro\nFreguesia: Todas\nIdentificador do Lote: LOT-0191\nPaís: Portugal\nNUT III: PT150\nLocalidade: Faro\nDistrito: Faro\nConcelho: Faro\nFreguesia: Todas\nIdentificador do Lote: LOT-0192\nPaís: Portugal\nNUT III: PT150\nLocalidade: Faro\nDistrito: Faro\nConcelho: Faro\nFreguesia: Todas\nIdentificador do Lote: LOT-0193\nPaís: Portugal\nNUT III: PT150\nLocalidade: Faro\nDistrito: Faro\nConcelho: Faro\nFreguesia: Todas\nIdentificador do Lote: LOT-0194\nPaís: Portugal\nNUT III: PT150\nLocalidade: Faro\nDistrito: Faro\nConcelho: Faro\nFreguesia: Todas\nIdentificador do Lote: LOT-0195\nPaís: Portugal\nNUT III: PT150\nLocalidade: Faro\nDistrito: Faro\nConcelho: Faro\nFreguesia: Todas\nIdentificador do Lote: LOT-0196\nPaís: Portugal\nNUT III: PT150\nLocalidade: Faro\nDistrito: Faro\nConcelho: Faro\nFreguesia: Todas\nIdentificador do Lote: LOT-0197\nPaís: Portugal\nNUT III: PT150\nLocalidade: Faro\nDistrito: Faro\nConcelho: Faro\nFreguesia: Todas\nIdentificador do Lote: LOT-0198\nPaís: Portugal\nNUT III: PT150\nLocalidade: Faro\nDistrito: Faro\nConcelho: Faro\nFreguesia: Todas\nIdentificador do Lote: LOT-0199\nPaís: Portugal\nNUT III: PT150\nLocalidade: Faro\nDistrito: Faro\nConcelho: Faro\nFreguesia: Todas\nIdentificador do Lote: LOT-0200\nPaís: Portugal\nNUT III: PT150\nLocalidade: Faro\nDistrito: Faro\nConcelho: Faro\nFreguesia: Todas\nIdentificador do Lote: LOT-0201\nPaís: Portugal\nNUT III: PT150\nLocalidade: Faro\nDistrito: Faro\nConcelho: Faro\nFreguesia: Todas\nIdentificador do Lote: LOT-0202\nPaís: Portugal\nNUT III: PT150\nLocalidade: Faro\nDistrito: Faro\nConcelho: Faro\nFreguesia: Todas\nIdentificador do Lote: LOT-0203\nPaís: Portugal\nNUT III: PT150\nLocalidade: Faro\nDistrito: Faro\nConcelho: Faro\nFreguesia: Todas\nIdentificador do Lote: LOT-0204\nPaís: Portugal\nNUT III: PT150\nLocalidade: Faro\nDistrito: Faro\nConcelho: Faro\nFreguesia: Todas\n\n10 - PRAZO DE EXECUÇÃO DO CONTRATO\nIdentificador do Lote: LOT-0001\nPrazo de execução do contrato: 1 ANOS\nPrevisão de renovações: Não\nIdentificador do Lote: LOT-0002\nPrazo de execução do contrato: 1 ANOS\nPrevisão de renovações: Não\nIdentificador do Lote: LOT-0003\nPrazo de execução do contrato: 1 ANOS\nPrevisão de renovações: Não\nIdentificador do Lote: LOT-0004\nPrazo de execução do contrato: 1 ANOS\nPrevisão de renovações: Não\nIdentificador do Lote: LOT-0005\nPrazo de execução do contrato: 1 ANOS\nPrevisão de renovações: Não\nIdentificador do Lote: LOT-0006\nPrazo de execução do contrato: 1 ANOS\nPrevisão de renovações: Não\nIdentificador do Lote: LOT-0007\nPrazo de execução do contrato: 1 ANOS\nPrevisão de renovações: Não\nIdentificador do Lote: LOT-0008\nPrazo de execução do contrato: 1 ANOS\nPrevisão de renovações: Não\nIdentificador do Lote: LOT-0009\nPrazo de execução do contrato: 1 ANOS\nPrevisão de renovações: Não\nIdentificador do Lote: LOT-0010\nPrazo de execução do contrato: 1 ANOS\nPrevisão de renovações: Não\nIdentificador do Lote: LOT-0011\nPrazo de execução do contrato: 1 ANOS\nPrevisão de renovações: Não\nIdentificador do Lote: LOT-0012\nPrazo de execução do contrato: 1 ANOS\nPrevisão de renovações: Não\nIdentificador do Lote: LOT-0013\nPrazo de execução do contrato: 1 ANOS\nPrevisão de renovações: Não\nIdentificador do Lote: LOT-0014\nPrazo de execução do contrato: 1 ANOS\nPrevisão de renovações: Não\nIdentificador do Lote: LOT-0015\nPrazo de execução do contrato: 1 ANOS\nPrevisão de renovações: Não\nIdentificador do Lote: LOT-0016\nPrazo de execução do contrato: 1 ANOS\nPrevisão de renovações: Não\nIdentificador do Lote: LOT-0017\nPrazo de execução do contrato: 1 ANOS\nPrevisão de renovações: Não\nIdentificador do Lote: LOT-0018\nPrazo de execução do contrato: 1 ANOS\nPrevisão de renovações: Não\nIdentificador do Lote: LOT-0019\nPrazo de execução do contrato: 1 ANOS\nPrevisão de renovações: Não\nIdentificador do Lote: LOT-0020\nPrazo de execução do contrato: 1 ANOS\nPrevisão de renovações: Não\nIdentificador do Lote: LOT-0021\nPrazo de execução do contrato: 1 ANOS\nPrevisão de renovações: Não\nIdentificador do Lote: LOT-0022\nPrazo de execução do contrato: 1 ANOS\nPrevisão de renovações: Não\nIdentificador do Lote: LOT-0023\nPrazo de execução do contrato: 1 ANOS\nPrevisão de renovações: Não\nIdentificador do Lote: LOT-0024\nPrazo de execução do contrato: 1 ANOS\nPrevisão de renovações: Não\nIdentificador do Lote: LOT-0025\nPrazo de execução do contrato: 1 ANOS\nPrevisão de renovações: Não\nIdentificador do Lote: LOT-0026\nPrazo de execução do contrato: 1 ANOS\nPrevisão de renovações: Não\nIdentificador do Lote: LOT-0027\nPrazo de execução do contrato: 1 ANOS\nPrevisão de renovações: Não\nIdentificador do Lote: LOT-0028\nPrazo de execução do contrato: 1 ANOS\nPrevisão de renovações: Não\nIdentificador do Lote: LOT-0029\nPrazo de execução do contrato: 1 ANOS\nPrevisão de renovações: Não\nIdentificador do Lote: LOT-0030\nPrazo de execução do contrato: 1 ANOS\nPrevisão de renovações: Não\nIdentificador do Lote: LOT-0031\nPrazo de execução do contrato: 1 ANOS\nPrevisão de renovações: Não\nIdentificador do Lote: LOT-0032\nPrazo de execução do contrato: 1 ANOS\nPrevisão de renovações: Não\nIdentificador do Lote: LOT-0033\nPrazo de execução do contrato: 1 ANOS\nPrevisão de renovações: Não\nIdentificador do Lote: LOT-0034\nPrazo de execução do contrato: 1 ANOS\nPrevisão de renovações: Não\nIdentificador do Lote: LOT-0035\nPrazo de execução do contrato: 1 ANOS\nPrevisão de renovações: Não\nIdentificador do Lote: LOT-0036\nPrazo de execução do contrato: 1 ANOS\nPrevisão de renovações: Não\nIdentificador do Lote: LOT-0037\nPrazo de execução do contrato: 1 ANOS\nPrevisão de renovações: Não\nIdentificador do Lote: LOT-0038\nPrazo de execução do contrato: 1 ANOS\nPrevisão de renovações: Não\nIdentificador do Lote: LOT-0039\nPrazo de execução do contrato: 1 ANOS\nPrevisão de renovações: Não\nIdentificador do Lote: LOT-0040\nPrazo de execução do contrato: 1 ANOS\nPrevisão de renovações: Não\nIdentificador do Lote: LOT-0041\nPrazo de execução do contrato: 1 ANOS\nPrevisão de renovações: Não\nIdentificador do Lote: LOT-0042\nPrazo de execução do contrato: 1 ANOS\nPrevisão de renovações: Não\nIdentificador do Lote: LOT-0043\nPrazo de execução do contrato: 1 ANOS\nPrevisão de renovações: Não\nIdentificador do Lote: LOT-0044\nPrazo de execução do contrato: 1 ANOS\nPrevisão de renovações: Não\nIdentificador do Lote: LOT-0045\nPrazo de execução do contrato: 1 ANOS\nPrevisão de renovações: Não\nIdentificador do Lote: LOT-0046\nPrazo de execução do contrato: 1 ANOS\nPrevisão de renovações: Não\nIdentificador do Lote: LOT-0047\nPrazo de execução do contrato: 1 ANOS\nPrevisão de renovações: Não\nIdentificador do Lote: LOT-0048\nPrazo de execução do contrato: 1 ANOS\nPrevisão de renovações: Não\nIdentificador do Lote: LOT-0049\nPrazo de execução do contrato: 1 ANOS\nPrevisão de renovações: Não\nIdentificador do Lote: LOT-0050\nPrazo de execução do contrato: 1 ANOS\nPrevisão de renovações: Não\nIdentificador do Lote: LOT-0051\nPrazo de execução do contrato: 1 ANOS\nPrevisão de renovações: Não\nIdentificador do Lote: LOT-0052\nPrazo de execução do contrato: 1 ANOS\nPrevisão de renovações: Não\nIdentificador do Lote: LOT-0053\nPrazo de execução do contrato: 1 ANOS\nPrevisão de renovações: Não\nIdentificador do Lote: LOT-0054\nPrazo de execução do contrato: 1 ANOS\nPrevisão de renovações: Não\nIdentificador do Lote: LOT-0055\nPrazo de execução do contrato: 1 ANOS\nPrevisão de renovações: Não\nIdentificador do Lote: LOT-0056\nPrazo de execução do contrato: 1 ANOS\nPrevisão de renovações: Não\nIdentificador do Lote: LOT-0057\nPrazo de execução do contrato: 1 ANOS\nPrevisão de renovações: Não\nIdentificador do Lote: LOT-0058\nPrazo de execução do contrato: 1 ANOS\nPrevisão de renovações: Não\nIdentificador do Lote: LOT-0059\nPrazo de execução do contrato: 1 ANOS\nPrevisão de renovações: Não\nIdentificador do Lote: LOT-0060\nPrazo de execução do contrato: 1 ANOS\nPrevisão de renovações: Não\nIdentificador do Lote: LOT-0061\nPrazo de execução do contrato: 1 ANOS\nPrevisão de renovações: Não\nIdentificador do Lote: LOT-0062\nPrazo de execução do contrato: 1 ANOS\nPrevisão de renovações: Não\nIdentificador do Lote: LOT-0063\nPrazo de execução do contrato: 1 ANOS\nPrevisão de renovações: Não\nIdentificador do Lote: LOT-0064\nPrazo de execução do contrato: 1 ANOS\nPrevisão de renovações: Não\nIdentificador do Lote: LOT-0065\nPrazo de execução do contrato: 1 ANOS\nPrevisão de renovações: Não\nIdentificador do Lote: LOT-0066\nPrazo de execução do contrato: 1 ANOS\nPrevisão de renovações: Não\nIdentificador do Lote: LOT-0067\nPrazo de execução do contrato: 1 ANOS\nPrevisão de renovações: Não\nIdentificador do Lote: LOT-0068\nPrazo de execução do contrato: 1 ANOS\nPrevisão de renovações: Não\nIdentificador do Lote: LOT-0069\nPrazo de execução do contrato: 1 ANOS\nPrevisão de renovações: Não\nIdentificador do Lote: LOT-0070\nPrazo de execução do contrato: 1 ANOS\nPrevisão de renovações: Não\nIdentificador do Lote: LOT-0071\nPrazo de execução do contrato: 1 ANOS\nPrevisão de renovações: Não\nIdentificador do Lote: LOT-0072\nPrazo de execução do contrato: 1 ANOS\nPrevisão de renovações: Não\nIdentificador do Lote: LOT-0073\nPrazo de execução do contrato: 1 ANOS\nPrevisão de renovações: Não\nIdentificador do Lote: LOT-0074\nPrazo de execução do contrato: 1 ANOS\nPrevisão de renovações: Não\nIdentificador do Lote: LOT-0075\nPrazo de execução do contrato: 1 ANOS\nPrevisão de renovações: Não\nIdentificador do Lote: LOT-0076\nPrazo de execução do contrato: 1 ANOS\nPrevisão de renovações: Não\nIdentificador do Lote: LOT-0077\nPrazo de execução do contrato: 1 ANOS\nPrevisão de renovações: Não\nIdentificador do Lote: LOT-0078\nPrazo de execução do contrato: 1 ANOS\nPrevisão de renovações: Não\nIdentificador do Lote: LOT-0079\nPrazo de execução do contrato: 1 ANOS\nPrevisão de renovações: Não\nIdentificador do Lote: LOT-0080\nPrazo de execução do contrato: 1 ANOS\nPrevisão de renovações: Não\nIdentificador do Lote: LOT-0081\nPrazo de execução do contrato: 1 ANOS\nPrevisão de renovações: Não\nIdentificador do Lote: LOT-0082\nPrazo de execução do contrato: 1 ANOS\nPrevisão de renovações: Não\nIdentificador do Lote: LOT-0083\nPrazo de execução do contrato: 1 ANOS\nPrevisão de renovações: Não\nIdentificador do Lote: LOT-0084\nPrazo de execução do contrato: 1 ANOS\nPrevisão de renovações: Não\nIdentificador do Lote: LOT-0085\nPrazo de execução do contrato: 1 ANOS\nPrevisão de renovações: Não\nIdentificador do Lote: LOT-0086\nPrazo de execução do contrato: 1 ANOS\nPrevisão de renovações: Não\nIdentificador do Lote: LOT-0087\nPrazo de execução do contrato: 1 ANOS\nPrevisão de renovações: Não\nIdentificador do Lote: LOT-0088\nPrazo de execução do contrato: 1 ANOS\nPrevisão de renovações: Não\nIdentificador do Lote: LOT-0089\nPrazo de execução do contrato: 1 ANOS\nPrevisão de renovações: Não\nIdentificador do Lote: LOT-0090\nPrazo de execução do contrato: 1 ANOS\nPrevisão de renovações: Não\nIdentificador do Lote: LOT-0091\nPrazo de execução do contrato: 1 ANOS\nPrevisão de renovações: Não\nIdentificador do Lote: LOT-0092\nPrazo de execução do contrato: 1 ANOS\nPrevisão de renovações: Não\nIdentificador do Lote: LOT-0093\nPrazo de execução do contrato: 1 ANOS\nPrevisão de renovações: Não\nIdentificador do Lote: LOT-0094\nPrazo de execução do contrato: 1 ANOS\nPrevisão de renovações: Não\nIdentificador do Lote: LOT-0095\nPrazo de execução do contrato: 1 ANOS\nPrevisão de renovações: Não\nIdentificador do Lote: LOT-0096\nPrazo de execução do contrato: 1 ANOS\nPrevisão de renovações: Não\nIdentificador do Lote: LOT-0097\nPrazo de execução do contrato: 1 ANOS\nPrevisão de renovações: Não\nIdentificador do Lote: LOT-0098\nPrazo de execução do contrato: 1 ANOS\nPrevisão de renovações: Não\nIdentificador do Lote: LOT-0099\nPrazo de execução do contrato: 1 ANOS\nPrevisão de renovações: Não\nIdentificador do Lote: LOT-0100\nPrazo de execução do contrato: 1 ANOS\nPrevisão de renovações: Não\nIdentificador do Lote: LOT-0101\nPrazo de execução do contrato: 1 ANOS\nPrevisão de renovações: Não\nIdentificador do Lote: LOT-0102\nPrazo de execução do contrato: 1 ANOS\nPrevisão de renovações: Não\nIdentificador do Lote: LOT-0103\nPrazo de execução do contrato: 1 ANOS\nPrevisão de renovações: Não\nIdentificador do Lote: LOT-0104\nPrazo de execução do contrato: 1 ANOS\nPrevisão de renovações: Não\nIdentificador do Lote: LOT-0105\nPrazo de execução do contrato: 1 ANOS\nPrevisão de renovações: Não\nIdentificador do Lote: LOT-0106\nPrazo de execução do contrato: 1 ANOS\nPrevisão de renovações: Não\nIdentificador do Lote: LOT-0107\nPrazo de execução do contrato: 1 ANOS\nPrevisão de renovações: Não\nIdentificador do Lote: LOT-0108\nPrazo de execução do contrato: 1 ANOS\nPrevisão de renovações: Não\nIdentificador do Lote: LOT-0109\nPrazo de execução do contrato: 1 ANOS\nPrevisão de renovações: Não\nIdentificador do Lote: LOT-0110\nPrazo de execução do contrato: 1 ANOS\nPrevisão de renovações: Não\nIdentificador do Lote: LOT-0111\nPrazo de execução do contrato: 1 ANOS\nPrevisão de renovações: Não\nIdentificador do Lote: LOT-0112\nPrazo de execução do contrato: 1 ANOS\nPrevisão de renovações: Não\nIdentificador do Lote: LOT-0113\nPrazo de execução do contrato: 1 ANOS\nPrevisão de renovações: Não\nIdentificador do Lote: LOT-0114\nPrazo de execução do contrato: 1 ANOS\nPrevisão de renovações: Não\nIdentificador do Lote: LOT-0115\nPrazo de execução do contrato: 1 ANOS\nPrevisão de renovações: Não\nIdentificador do Lote: LOT-0116\nPrazo de execução do contrato: 1 ANOS\nPrevisão de renovações: Não\nIdentificador do Lote: LOT-0117\nPrazo de execução do contrato: 1 ANOS\nPrevisão de renovações: Não\nIdentificador do Lote: LOT-0118\nPrazo de execução do contrato: 1 ANOS\nPrevisão de renovações: Não\nIdentificador do Lote: LOT-0119\nPrazo de execução do contrato: 1 ANOS\nPrevisão de renovações: Não\nIdentificador do Lote: LOT-0120\nPrazo de execução do contrato: 1 ANOS\nPrevisão de renovações: Não\nIdentificador do Lote: LOT-0121\nPrazo de execução do contrato: 1 ANOS\nPrevisão de renovações: Não\nIdentificador do Lote: LOT-0122\nPrazo de execução do contrato: 1 ANOS\nPrevisão de renovações: Não\nIdentificador do Lote: LOT-0123\nPrazo de execução do contrato: 1 ANOS\nPrevisão de renovações: Não\nIdentificador do Lote: LOT-0124\nPrazo de execução do contrato: 1 ANOS\nPrevisão de renovações: Não\nIdentificador do Lote: LOT-0125\nPrazo de execução do contrato: 1 ANOS\nPrevisão de renovações: Não\nIdentificador do Lote: LOT-0126\nPrazo de execução do contrato: 1 ANOS\nPrevisão de renovações: Não\nIdentificador do Lote: LOT-0127\nPrazo de execução do contrato: 1 ANOS\nPrevisão de renovações: Não\nIdentificador do Lote: LOT-0128\nPrazo de execução do contrato: 1 ANOS\nPrevisão de renovações: Não\nIdentificador do Lote: LOT-0129\nPrazo de execução do contrato: 1 ANOS\nPrevisão de renovações: Não\nIdentificador do Lote: LOT-0130\nPrazo de execução do contrato: 1 ANOS\nPrevisão de renovações: Não\nIdentificador do Lote: LOT-0131\nPrazo de execução do contrato: 1 ANOS\nPrevisão de renovações: Não\nIdentificador do Lote: LOT-0132\nPrazo de execução do contrato: 1 ANOS\nPrevisão de renovações: Não\nIdentificador do Lote: LOT-0133\nPrazo de execução do contrato: 1 ANOS\nPrevisão de renovações: Não\nIdentificador do Lote: LOT-0134\nPrazo de execução do contrato: 1 ANOS\nPrevisão de renovações: Não\nIdentificador do Lote: LOT-0135\nPrazo de execução do contrato: 1 ANOS\nPrevisão de renovações: Não\nIdentificador do Lote: LOT-0136\nPrazo de execução do contrato: 1 ANOS\nPrevisão de renovações: Não\nIdentificador do Lote: LOT-0137\nPrazo de execução do contrato: 1 ANOS\nPrevisão de renovações: Não\nIdentificador do Lote: LOT-0138\nPrazo de execução do contrato: 1 ANOS\nPrevisão de renovações: Não\nIdentificador do Lote: LOT-0139\nPrazo de execução do contrato: 1 ANOS\nPrevisão de renovações: Não\nIdentificador do Lote: LOT-0140\nPrazo de execução do contrato: 1 ANOS\nPrevisão de renovações: Não\nIdentificador do Lote: LOT-0141\nPrazo de execução do contrato: 1 ANOS\nPrevisão de renovações: Não\nIdentificador do Lote: LOT-0142\nPrazo de execução do contrato: 1 ANOS\nPrevisão de renovações: Não\nIdentificador do Lote: LOT-0143\nPrazo de execução do contrato: 1 ANOS\nPrevisão de renovações: Não\nIdentificador do Lote: LOT-0144\nPrazo de execução do contrato: 1 ANOS\nPrevisão de renovações: Não\nIdentificador do Lote: LOT-0145\nPrazo de execução do contrato: 1 ANOS\nPrevisão de renovações: Não\nIdentificador do Lote: LOT-0146\nPrazo de execução do contrato: 1 ANOS\nPrevisão de renovações: Não\nIdentificador do Lote: LOT-0147\nPrazo de execução do contrato: 1 ANOS\nPrevisão de renovações: Não\nIdentificador do Lote: LOT-0148\nPrazo de execução do contrato: 1 ANOS\nPrevisão de renovações: Não\nIdentificador do Lote: LOT-0149\nPrazo de execução do contrato: 1 ANOS\nPrevisão de renovações: Não\nIdentificador do Lote: LOT-0150\nPrazo de execução do contrato: 1 ANOS\nPrevisão de renovações: Não\nIdentificador do Lote: LOT-0151\nPrazo de execução do contrato: 1 ANOS\nPrevisão de renovações: Não\nIdentificador do Lote: LOT-0152\nPrazo de execução do contrato: 1 ANOS\nPrevisão de renovações: Não\nIdentificador do Lote: LOT-0153\nPrazo de execução do contrato: 1 ANOS\nPrevisão de renovações: Não\nIdentificador do Lote: LOT-0154\nPrazo de execução do contrato: 1 ANOS\nPrevisão de renovações: Não\nIdentificador do Lote: LOT-0155\nPrazo de execução do contrato: 1 ANOS\nPrevisão de renovações: Não\nIdentificador do Lote: LOT-0156\nPrazo de execução do contrato: 1 ANOS\nPrevisão de renovações: Não\nIdentificador do Lote: LOT-0157\nPrazo de execução do contrato: 1 ANOS\nPrevisão de renovações: Não\nIdentificador do Lote: LOT-0158\nPrazo de execução do contrato: 1 ANOS\nPrevisão de renovações: Não\nIdentificador do Lote: LOT-0159\nPrazo de execução do contrato: 1 ANOS\nPrevisão de renovações: Não\nIdentificador do Lote: LOT-0160\nPrazo de execução do contrato: 1 ANOS\nPrevisão de renovações: Não\nIdentificador do Lote: LOT-0161\nPrazo de execução do contrato: 1 ANOS\nPrevisão de renovações: Não\nIdentificador do Lote: LOT-0162\nPrazo de execução do contrato: 1 ANOS\nPrevisão de renovações: Não\nIdentificador do Lote: LOT-0163\nPrazo de execução do contrato: 1 ANOS\nPrevisão de renovações: Não\nIdentificador do Lote: LOT-0164\nPrazo de execução do contrato: 1 ANOS\nPrevisão de renovações: Não\nIdentificador do Lote: LOT-0165\nPrazo de execução do contrato: 1 ANOS\nPrevisão de renovações: Não\nIdentificador do Lote: LOT-0166\nPrazo de execução do contrato: 1 ANOS\nPrevisão de renovações: Não\nIdentificador do Lote: LOT-0167\nPrazo de execução do contrato: 1 ANOS\nPrevisão de renovações: Não\nIdentificador do Lote: LOT-0168\nPrazo de execução do contrato: 1 ANOS\nPrevisão de renovações: Não\nIdentificador do Lote: LOT-0169\nPrazo de execução do contrato: 1 ANOS\nPrevisão de renovações: Não\nIdentificador do Lote: LOT-0170\nPrazo de execução do contrato: 1 ANOS\nPrevisão de renovações: Não\nIdentificador do Lote: LOT-0171\nPrazo de execução do contrato: 1 ANOS\nPrevisão de renovações: Não\nIdentificador do Lote: LOT-0172\nPrazo de execução do contrato: 1 ANOS\nPrevisão de renovações: Não\nIdentificador do Lote: LOT-0173\nPrazo de execução do contrato: 1 ANOS\nPrevisão de renovações: Não\nIdentificador do Lote: LOT-0174\nPrazo de execução do contrato: 1 ANOS\nPrevisão de renovações: Não\nIdentificador do Lote: LOT-0175\nPrazo de execução do contrato: 1 ANOS\nPrevisão de renovações: Não\nIdentificador do Lote: LOT-0176\nPrazo de execução do contrato: 1 ANOS\nPrevisão de renovações: Não\nIdentificador do Lote: LOT-0177\nPrazo de execução do contrato: 1 ANOS\nPrevisão de renovações: Não\nIdentificador do Lote: LOT-0178\nPrazo de execução do contrato: 1 ANOS\nPrevisão de renovações: Não\nIdentificador do Lote: LOT-0179\nPrazo de execução do contrato: 1 ANOS\nPrevisão de renovações: Não\nIdentificador do Lote: LOT-0180\nPrazo de execução do contrato: 1 ANOS\nPrevisão de renovações: Não\nIdentificador do Lote: LOT-0181\nPrazo de execução do contrato: 1 ANOS\nPrevisão de renovações: Não\nIdentificador do Lote: LOT-0182\nPrazo de execução do contrato: 1 ANOS\nPrevisão de renovações: Não\nIdentificador do Lote: LOT-0183\nPrazo de execução do contrato: 1 ANOS\nPrevisão de renovações: Não\nIdentificador do Lote: LOT-0184\nPrazo de execução do contrato: 1 ANOS\nPrevisão de renovações: Não\nIdentificador do Lote: LOT-0185\nPrazo de execução do contrato: 1 ANOS\nPrevisão de renovações: Não\nIdentificador do Lote: LOT-0186\nPrazo de execução do contrato: 1 ANOS\nPrevisão de renovações: Não\nIdentificador do Lote: LOT-0187\nPrazo de execução do contrato: 1 ANOS\nPrevisão de renovações: Não\nIdentificador do Lote: LOT-0188\nPrazo de execução do contrato: 1 ANOS\nPrevisão de renovações: Não\nIdentificador do Lote: LOT-0189\nPrazo de execução do contrato: 1 ANOS\nPrevisão de renovações: Não\nIdentificador do Lote: LOT-0190\nPrazo de execução do contrato: 1 ANOS\nPrevisão de renovações: Não\nIdentificador do Lote: LOT-0191\nPrazo de execução do contrato: 1 ANOS\nPrevisão de renovações: Não\nIdentificador do Lote: LOT-0192\nPrazo de execução do contrato: 1 ANOS\nPrevisão de renovações: Não\nIdentificador do Lote: LOT-0193\nPrazo de execução do contrato: 1 ANOS\nPrevisão de renovações: Não\nIdentificador do Lote: LOT-0194\nPrazo de execução do contrato: 1 ANOS\nPrevisão de renovações: Não\nIdentificador do Lote: LOT-0195\nPrazo de execução do contrato: 1 ANOS\nPrevisão de renovações: Não\nIdentificador do Lote: LOT-0196\nPrazo de execução do contrato: 1 ANOS\nPrevisão de renovações: Não\nIdentificador do Lote: LOT-0197\nPrazo de execução do contrato: 1 ANOS\nPrevisão de renovações: Não\nIdentificador do Lote: LOT-0198\nPrazo de execução do contrato: 1 ANOS\nPrevisão de renovações: Não\nIdentificador do Lote: LOT-0199\nPrazo de execução do contrato: 1 ANOS\nPrevisão de renovações: Não\nIdentificador do Lote: LOT-0200\nPrazo de execução do contrato: 1 ANOS\nPrevisão de renovações: Não\nIdentificador do Lote: LOT-0201\nPrazo de execução do contrato: 1 ANOS\nPrevisão de renovações: Não\nIdentificador do Lote: LOT-0202\nPrazo de execução do contrato: 1 ANOS\nPrevisão de renovações: Não\nIdentificador do Lote: LOT-0203\nPrazo de execução do contrato: 1 ANOS\nPrevisão de renovações: Não\nIdentificador do Lote: LOT-0204\nPrazo de execução do contrato: 1 ANOS\nPrevisão de renovações: Não\n\n11 - FUNDOS EU\nIdentificador do Lote: LOT-0001; LOT-0002; LOT-0003; LOT-0004; LOT-0005; LOT-0006; LOT-0007; LOT-0008; LOT-0009; LOT-0010; LOT-0011; LOT-0012; LOT-0013; LOT-0014; LOT-0015; LOT-0016; LOT-0017; LOT-0018; LOT-0019; LOT-0020; LOT-0021; LOT-0022; LOT-0023; LOT-0024; LOT-0025; LOT-0026; LOT-0027; LOT-0028; LOT-0029; LOT-0030; LOT-0031; LOT-0032; LOT-0033; LOT-0034; LOT-0035; LOT-0036; LOT-0037; LOT-0038; LOT-0039; LOT-0040; LOT-0041; LOT-0042; LOT-0043; LOT-0044; LOT-0045; LOT-0046; LOT-0047; LOT-0048; LOT-0049; LOT-0050; LOT-0051; LOT-0052; LOT-0053; LOT-0054; LOT-0055; LOT-0056; LOT-0057; LOT-0058; LOT-0059; LOT-0060; LOT-0061; LOT-0062; LOT-0063; LOT-0064; LOT-0065; LOT-0066; LOT-0067; LOT-0068; LOT-0069; LOT-0070; LOT-0071; LOT-0072; LOT-0073; LOT-0074; LOT-0075; LOT-0076; LOT-0077; LOT-0078; LOT-0079; LOT-0080; LOT-0081; LOT-0082; LOT-0083; LOT-0084; LOT-0085; LOT-0086; LOT-0087; LOT-0088; LOT-0089; LOT-0090; LOT-0091; LOT-0092; LOT-0093; LOT-0094; LOT-0095; LOT-0096; LOT-0097; LOT-0098; LOT-0099; LOT-0100; LOT-0101; LOT-0102; LOT-0103; LOT-0104; LOT-0105; LOT-0106; LOT-0107; LOT-0108; LOT-0109; LOT-0110; LOT-0111; LOT-0112; LOT-0113; LOT-0114; LOT-0115; LOT-0116; LOT-0117; LOT-0118; LOT-0119; LOT-0120; LOT-0121; LOT-0122; LOT-0123; LOT-0124; LOT-0125; LOT-0126; LOT-0127; LOT-0128; LOT-0129; LOT-0130; LOT-0131; LOT-0132; LOT-0133; LOT-0134; LOT-0135; LOT-0136; LOT-0137; LOT-0138; LOT-0139; LOT-0140; LOT-0141; LOT-0142; LOT-0143; LOT-0144; LOT-0145; LOT-0146; LOT-0147; LOT-0148; LOT-0149; LOT-0150; LOT-0151; LOT-0152; LOT-0153; LOT-0154; LOT-0155; LOT-0156; LOT-0157; LOT-0158; LOT-0159; LOT-0160; LOT-0161; LOT-0162; LOT-0163; LOT-0164; LOT-0165; LOT-0166; LOT-0167; LOT-0168; LOT-0169; LOT-0170; LOT-0171; LOT-0172; LOT-0173; LOT-0174; LOT-0175; LOT-0176; LOT-0177; LOT-0178; LOT-0179; LOT-0180; LOT-0181; LOT-0182; LOT-0183; LOT-0184; LOT-0185; LOT-0186; LOT-0187; LOT-0188; LOT-0189; LOT-0190; LOT-0191; LOT-0192; LOT-0193; LOT-0194; LOT-0195; LOT-0196; LOT-0197; LOT-0198; LOT-0199; LOT-0200; LOT-0201; LOT-0202; LOT-0203; LOT-0204\nTêm fundos EU? Não\n\n12 - DOCUMENTOS DE HABILITAÇÃO\nHabilitação para o exercício da atividade profissional: Não\n\n13 - CONDIÇÕES DE APRESENTAÇÃO\nPlataforma eletrónica utilizada pela entidade adjudicante: ANOGOV\nURL para Apresentação: https://www.anogov.com/me-sasualgarve/faces/\nAdmissibilidade da apresentação de propostas variantes: Não autorizado\nPrazo para apresentação das propostas: 08-10-2025 23:59\nPrazo durante o qual os concorrentes são obrigados a manter as respetivas propostas: 66 dias a contar do termo do prazo para a apresentação das propostas\nApresentação de Catálogo Eletrónico: Permitido\nIndicação de Subcontratação na Proposta: Inexistência de indicação de subcontratação\n\n14 - PRESTAÇÃO DE CAUÇÃO\nPrestação de caução: Não\n\n15 - FORNECIMENTO DAS PEÇAS DO CONCURSO, APRESENTAÇÃO DE PEDIDOS DE PARTICIPAÇÃO E APRESENTAÇÃO DAS PROPOSTAS\nLink para acesso às peças do concurso (URL): https://www.anogov.com/me-sasualgarve/faces/app/acessoDocs.jsp?codigoAcesso=bSRcUyzzmPHMwKge7iCtnE1uJ62oLgDWlR94n4lAOBlYpNPH08\n\n20 - OUTROS REQUISITOS\nIdentificador do Lote: LOT-0001; LOT-0002; LOT-0003; LOT-0004; LOT-0005; LOT-0006; LOT-0007; LOT-0008; LOT-0009; LOT-0010; LOT-0011; LOT-0012; LOT-0013; LOT-0014; LOT-0015; LOT-0016; LOT-0017; LOT-0018; LOT-0019; LOT-0020; LOT-0021; LOT-0022; LOT-0023; LOT-0024; LOT-0025; LOT-0026; LOT-0027; LOT-0028; LOT-0029; LOT-0030; LOT-0031; LOT-0032; LOT-0033; LOT-0034; LOT-0035; LOT-0036; LOT-0037; LOT-0038; LOT-0039; LOT-0040; LOT-0041; LOT-0042; LOT-0043; LOT-0044; LOT-0045; LOT-0046; LOT-0047; LOT-0048; LOT-0049; LOT-0050; LOT-0051; LOT-0052; LOT-0053; LOT-0054; LOT-0055; LOT-0056; LOT-0057; LOT-0058; LOT-0059; LOT-0060; LOT-0061; LOT-0062; LOT-0063; LOT-0064; LOT-0065; LOT-0066; LOT-0067; LOT-0068; LOT-0069; LOT-0070; LOT-0071; LOT-0072; LOT-0073; LOT-0074; LOT-0075; LOT-0076; LOT-0077; LOT-0078; LOT-0079; LOT-0080; LOT-0081; LOT-0082; LOT-0083; LOT-0084; LOT-0085; LOT-0086; LOT-0087; LOT-0088; LOT-0089; LOT-0090; LOT-0091; LOT-0092; LOT-0093; LOT-0094; LOT-0095; LOT-0096; LOT-0097; LOT-0098; LOT-0099; LOT-0100; LOT-0101; LOT-0102; LOT-0103; LOT-0104; LOT-0105; LOT-0106; LOT-0107; LOT-0108; LOT-0109; LOT-0110; LOT-0111; LOT-0112; LOT-0113; LOT-0114; LOT-0115; LOT-0116; LOT-0117; LOT-0118; LOT-0119; LOT-0120; LOT-0121; LOT-0122; LOT-0123; LOT-0124; LOT-0125; LOT-0126; LOT-0127; LOT-0128; LOT-0129; LOT-0130; LOT-0131; LOT-0132; LOT-0133; LOT-0134; LOT-0135; LOT-0136; LOT-0137; LOT-0138; LOT-0139; LOT-0140; LOT-0141; LOT-0142; LOT-0143; LOT-0144; LOT-0145; LOT-0146; LOT-0147; LOT-0148; LOT-0149; LOT-0150; LOT-0151; LOT-0152; LOT-0153; LOT-0154; LOT-0155; LOT-0156; LOT-0157; LOT-0158; LOT-0159; LOT-0160; LOT-0161; LOT-0162; LOT-0163; LOT-0164; LOT-0165; LOT-0166; LOT-0167; LOT-0168; LOT-0169; LOT-0170; LOT-0171; LOT-0172; LOT-0173; LOT-0174; LOT-0175; LOT-0176; LOT-0177; LOT-0178; LOT-0179; LOT-0180; LOT-0181; LOT-0182; LOT-0183; LOT-0184; LOT-0185; LOT-0186; LOT-0187; LOT-0188; LOT-0189; LOT-0190; LOT-0191; LOT-0192; LOT-0193; LOT-0194; LOT-0195; LOT-0196; LOT-0197; LOT-0198; LOT-0199; LOT-0200; LOT-0201; LOT-0202; LOT-0203; LOT-0204\nInformação sobre contratos reservados. Aplica-se a contratos reservados (54º-A)? Não\n\n21 - CRITÉRIO DE ADJUDICAÇÃO\nO Critério de adjudicação é diferenciado por lote? Não\nMultifator: Não\nMonofator:\nNome: Preço\n\n24 - CONDIÇÕES DO CONTRATO\nIdentificador do Lote: LOT-0001; LOT-0002; LOT-0003; LOT-0004; LOT-0005; LOT-0006; LOT-0007; LOT-0008; LOT-0009; LOT-0010; LOT-0011; LOT-0012; LOT-0013; LOT-0014; LOT-0015; LOT-0016; LOT-0017; LOT-0018; LOT-0019; LOT-0020; LOT-0021; LOT-0022; LOT-0023; LOT-0024; LOT-0025; LOT-0026; LOT-0027; LOT-0028; LOT-0029; LOT-0030; LOT-0031; LOT-0032; LOT-0033; LOT-0034; LOT-0035; LOT-0036; LOT-0037; LOT-0038; LOT-0039; LOT-0040; LOT-0041; LOT-0042; LOT-0043; LOT-0044; LOT-0045; LOT-0046; LOT-0047; LOT-0048; LOT-0049; LOT-0050; LOT-0051; LOT-0052; LOT-0053; LOT-0054; LOT-0055; LOT-0056; LOT-0057; LOT-0058; LOT-0059; LOT-0060; LOT-0061; LOT-0062; LOT-0063; LOT-0064; LOT-0065; LOT-0066; LOT-0067; LOT-0068; LOT-0069; LOT-0070; LOT-0071; LOT-0072; LOT-0073; LOT-0074; LOT-0075; LOT-0076; LOT-0077; LOT-0078; LOT-0079; LOT-0080; LOT-0081; LOT-0082; LOT-0083; LOT-0084; LOT-0085; LOT-0086; LOT-0087; LOT-0088; LOT-0089; LOT-0090; LOT-0091; LOT-0092; LOT-0093; LOT-0094; LOT-0095; LOT-0096; LOT-0097; LOT-0098; LOT-0099; LOT-0100; LOT-0101; LOT-0102; LOT-0103; LOT-0104; LOT-0105; LOT-0106; LOT-0107; LOT-0108; LOT-0109; LOT-0110; LOT-0111; LOT-0112; LOT-0113; LOT-0114; LOT-0115; LOT-0116; LOT-0117; LOT-0118; LOT-0119; LOT-0120; LOT-0121; LOT-0122; LOT-0123; LOT-0124; LOT-0125; LOT-0126; LOT-0127; LOT-0128; LOT-0129; LOT-0130; LOT-0131; LOT-0132; LOT-0133; LOT-0134; LOT-0135; LOT-0136; LOT-0137; LOT-0138; LOT-0139; LOT-0140; LOT-0141; LOT-0142; LOT-0143; LOT-0144; LOT-0145; LOT-0146; LOT-0147; LOT-0148; LOT-0149; LOT-0150; LOT-0151; LOT-0152; LOT-0153; LOT-0154; LOT-0155; LOT-0156; LOT-0157; LOT-0158; LOT-0159; LOT-0160; LOT-0161; LOT-0162; LOT-0163; LOT-0164; LOT-0165; LOT-0166; LOT-0167; LOT-0168; LOT-0169; LOT-0170; LOT-0171; LOT-0172; LOT-0173; LOT-0174; LOT-0175; LOT-0176; LOT-0177; LOT-0178; LOT-0179; LOT-0180; LOT-0181; LOT-0182; LOT-0183; LOT-0184; LOT-0185; LOT-0186; LOT-0187; LOT-0188; LOT-0189; LOT-0190; LOT-0191; LOT-0192; LOT-0193; LOT-0194; LOT-0195; LOT-0196; LOT-0197; LOT-0198; LOT-0199; LOT-0200; LOT-0201; LOT-0202; LOT-0203; LOT-0204\nFaturação Eletrónica: Permitido\nObrigação de Subcontratação:\nCódigo da Obrigação de Subcontratação: Não é aplicável nenhuma obrigação de subcontratação.\n\n25 - COMPRA PÚBLICA ESTRATÉGICA\nCompra Pública Estratégica: Inexistência de contratação pública estratégica\n\n26 - INFORMAÇÕES ADICIONAIS\nIdentificador do Lote: LOT-0001\nContrato adequado para PME: Não\nCobertura ACP (Acordo dos Contratos Públicos da Organização Mundial do Comércio): Não\nIdentificador do Lote: LOT-0002\nContrato adequado para PME: Não\nCobertura ACP (Acordo dos Contratos Públicos da Organização Mundial do Comércio): Não\nIdentificador do Lote: LOT-0003\nContrato adequado para PME: Não\nCobertura ACP (Acordo dos Contratos Públicos da Organização Mundial do Comércio): Não\nIdentificador do Lote: LOT-0004\nContrato adequado para PME: Não\nCobertura ACP (Acordo dos Contratos Públicos da Organização Mundial do Comércio): Não\nIdentificador do Lote: LOT-0005\nContrato adequado para PME: Não\nCobertura ACP (Acordo dos Contratos Públicos da Organização Mundial do Comércio): Não\nIdentificador do Lote: LOT-0006\nContrato adequado para PME: Não\nCobertura ACP (Acordo dos Contratos Públicos da Organização Mundial do Comércio): Não\nIdentificador do Lote: LOT-0007\nContrato adequado para PME: Não\nCobertura ACP (Acordo dos Contratos Públicos da Organização Mundial do Comércio): Não\nIdentificador do Lote: LOT-0008\nContrato adequado para PME: Não\nCobertura ACP (Acordo dos Contratos Públicos da Organização Mundial do Comércio): Não\nIdentificador do Lote: LOT-0009\nContrato adequado para PME: Não\nCobertura ACP (Acordo dos Contratos Públicos da Organização Mundial do Comércio): Não\nIdentificador do Lote: LOT-0010\nContrato adequado para PME: Não\nCobertura ACP (Acordo dos Contratos Públicos da Organização Mundial do Comércio): Não\nIdentificador do Lote: LOT-0011\nContrato adequado para PME: Não\nCobertura ACP (Acordo dos Contratos Públicos da Organização Mundial do Comércio): Não\nIdentificador do Lote: LOT-0012\nContrato adequado para PME: Não\nCobertura ACP (Acordo dos Contratos Públicos da Organização Mundial do Comércio): Não\nIdentificador do Lote: LOT-0013\nContrato adequado para PME: Não\nCobertura ACP (Acordo dos Contratos Públicos da Organização Mundial do Comércio): Não\nIdentificador do Lote: LOT-0014\nContrato adequado para PME: Não\nCobertura ACP (Acordo dos Contratos Públicos da Organização Mundial do Comércio): Não\nIdentificador do Lote: LOT-0015\nContrato adequado para PME: Não\nCobertura ACP (Acordo dos Contratos Públicos da Organização Mundial do Comércio): Não\nIdentificador do Lote: LOT-0016\nContrato adequado para PME: Não\nCobertura ACP (Acordo dos Contratos Públicos da Organização Mundial do Comércio): Não\nIdentificador do Lote: LOT-0017\nContrato adequado para PME: Não\nCobertura ACP (Acordo dos Contratos Públicos da Organização Mundial do Comércio): Não\nIdentificador do Lote: LOT-0018\nContrato adequado para PME: Não\nCobertura ACP (Acordo dos Contratos Públicos da Organização Mundial do Comércio): Não\nIdentificador do Lote: LOT-0019\nContrato adequado para PME: Não\nCobertura ACP (Acordo dos Contratos Públicos da Organização Mundial do Comércio): Não\nIdentificador do Lote: LOT-0020\nContrato adequado para PME: Não\nCobertura ACP (Acordo dos Contratos Públicos da Organização Mundial do Comércio): Não\nIdentificador do Lote: LOT-0021\nContrato adequado para PME: Não\nCobertura ACP (Acordo dos Contratos Públicos da Organização Mundial do Comércio): Não\nIdentificador do Lote: LOT-0022\nContrato adequado para PME: Não\nCobertura ACP (Acordo dos Contratos Públicos da Organização Mundial do Comércio): Não\nIdentificador do Lote: LOT-0023\nContrato adequado para PME: Não\nCobertura ACP (Acordo dos Contratos Públicos da Organização Mundial do Comércio): Não\nIdentificador do Lote: LOT-0024\nContrato adequado para PME: Não\nCobertura ACP (Acordo dos Contratos Públicos da Organização Mundial do Comércio): Não\nIdentificador do Lote: LOT-0025\nContrato adequado para PME: Não\nCobertura ACP (Acordo dos Contratos Públicos da Organização Mundial do Comércio): Não\nIdentificador do Lote: LOT-0026\nContrato adequado para PME: Não\nCobertura ACP (Acordo dos Contratos Públicos da Organização Mundial do Comércio): Não\nIdentificador do Lote: LOT-0027\nContrato adequado para PME: Não\nCobertura ACP (Acordo dos Contratos Públicos da Organização Mundial do Comércio): Não\nIdentificador do Lote: LOT-0028\nContrato adequado para PME: Não\nCobertura ACP (Acordo dos Contratos Públicos da Organização Mundial do Comércio): Não\nIdentificador do Lote: LOT-0029\nContrato adequado para PME: Não\nCobertura ACP (Acordo dos Contratos Públicos da Organização Mundial do Comércio): Não\nIdentificador do Lote: LOT-0030\nContrato adequado para PME: Não\nCobertura ACP (Acordo dos Contratos Públicos da Organização Mundial do Comércio): Não\nIdentificador do Lote: LOT-0031\nContrato adequado para PME: Não\nCobertura ACP (Acordo dos Contratos Públicos da Organização Mundial do Comércio): Não\nIdentificador do Lote: LOT-0032\nContrato adequado para PME: Não\nCobertura ACP (Acordo dos Contratos Públicos da Organização Mundial do Comércio): Não\nIdentificador do Lote: LOT-0033\nContrato adequado para PME: Não\nCobertura ACP (Acordo dos Contratos Públicos da Organização Mundial do Comércio): Não\nIdentificador do Lote: LOT-0034\nContrato adequado para PME: Não\nCobertura ACP (Acordo dos Contratos Públicos da Organização Mundial do Comércio): Não\nIdentificador do Lote: LOT-0035\nContrato adequado para PME: Não\nCobertura ACP (Acordo dos Contratos Públicos da Organização Mundial do Comércio): Não\nIdentificador do Lote: LOT-0036\nContrato adequado para PME: Não\nCobertura ACP (Acordo dos Contratos Públicos da Organização Mundial do Comércio): Não\nIdentificador do Lote: LOT-0037\nContrato adequado para PME: Não\nCobertura ACP (Acordo dos Contratos Públicos da Organização Mundial do Comércio): Não\nIdentificador do Lote: LOT-0038\nContrato adequado para PME: Não\nCobertura ACP (Acordo dos Contratos Públicos da Organização Mundial do Comércio): Não\nIdentificador do Lote: LOT-0039\nContrato adequado para PME: Não\nCobertura ACP (Acordo dos Contratos Públicos da Organização Mundial do Comércio): Não\nIdentificador do Lote: LOT-0040\nContrato adequado para PME: Não\nCobertura ACP (Acordo dos Contratos Públicos da Organização Mundial do Comércio): Não\nIdentificador do Lote: LOT-0041\nContrato adequado para PME: Não\nCobertura ACP (Acordo dos Contratos Públicos da Organização Mundial do Comércio): Não\nIdentificador do Lote: LOT-0042\nContrato adequado para PME: Não\nCobertura ACP (Acordo dos Contratos Públicos da Organização Mundial do Comércio): Não\nIdentificador do Lote: LOT-0043\nContrato adequado para PME: Não\nCobertura ACP (Acordo dos Contratos Públicos da Organização Mundial do Comércio): Não\nIdentificador do Lote: LOT-0044\nContrato adequado para PME: Não\nCobertura ACP (Acordo dos Contratos Públicos da Organização Mundial do Comércio): Não\nIdentificador do Lote: LOT-0045\nContrato adequado para PME: Não\nCobertura ACP (Acordo dos Contratos Públicos da Organização Mundial do Comércio): Não\nIdentificador do Lote: LOT-0046\nContrato adequado para PME: Não\nCobertura ACP (Acordo dos Contratos Públicos da Organização Mundial do Comércio): Não\nIdentificador do Lote: LOT-0047\nContrato adequado para PME: Não\nCobertura ACP (Acordo dos Contratos Públicos da Organização Mundial do Comércio): Não\nIdentificador do Lote: LOT-0048\nContrato adequado para PME: Não\nCobertura ACP (Acordo dos Contratos Públicos da Organização Mundial do Comércio): Não\nIdentificador do Lote: LOT-0049\nContrato adequado para PME: Não\nCobertura ACP (Acordo dos Contratos Públicos da Organização Mundial do Comércio): Não\nIdentificador do Lote: LOT-0050\nContrato adequado para PME: Não\nCobertura ACP (Acordo dos Contratos Públicos da Organização Mundial do Comércio): Não\nIdentificador do Lote: LOT-0051\nContrato adequado para PME: Não\nCobertura ACP (Acordo dos Contratos Públicos da Organização Mundial do Comércio): Não\nIdentificador do Lote: LOT-0052\nContrato adequado para PME: Não\nCobertura ACP (Acordo dos Contratos Públicos da Organização Mundial do Comércio): Não\nIdentificador do Lote: LOT-0053\nContrato adequado para PME: Não\nCobertura ACP (Acordo dos Contratos Públicos da Organização Mundial do Comércio): Não\nIdentificador do Lote: LOT-0054\nContrato adequado para PME: Não\nCobertura ACP (Acordo dos Contratos Públicos da Organização Mundial do Comércio): Não\nIdentificador do Lote: LOT-0055\nContrato adequado para PME: Não\nCobertura ACP (Acordo dos Contratos Públicos da Organização Mundial do Comércio): Não\nIdentificador do Lote: LOT-0056\nContrato adequado para PME: Não\nCobertura ACP (Acordo dos Contratos Públicos da Organização Mundial do Comércio): Não\nIdentificador do Lote: LOT-0057\nContrato adequado para PME: Não\nCobertura ACP (Acordo dos Contratos Públicos da Organização Mundial do Comércio): Não\nIdentificador do Lote: LOT-0058\nContrato adequado para PME: Não\nCobertura ACP (Acordo dos Contratos Públicos da Organização Mundial do Comércio): Não\nIdentificador do Lote: LOT-0059\nContrato adequado para PME: Não\nCobertura ACP (Acordo dos Contratos Públicos da Organização Mundial do Comércio): Não\nIdentificador do Lote: LOT-0060\nContrato adequado para PME: Não\nCobertura ACP (Acordo dos Contratos Públicos da Organização Mundial do Comércio): Não\nIdentificador do Lote: LOT-0061\nContrato adequado para PME: Não\nCobertura ACP (Acordo dos Contratos Públicos da Organização Mundial do Comércio): Não\nIdentificador do Lote: LOT-0062\nContrato adequado para PME: Não\nCobertura ACP (Acordo dos Contratos Públicos da Organização Mundial do Comércio): Não\nIdentificador do Lote: LOT-0063\nContrato adequado para PME: Não\nCobertura ACP (Acordo dos Contratos Públicos da Organização Mundial do Comércio): Não\nIdentificador do Lote: LOT-0064\nContrato adequado para PME: Não\nCobertura ACP (Acordo dos Contratos Públicos da Organização Mundial do Comércio): Não\nIdentificador do Lote: LOT-0065\nContrato adequado para PME: Não\nCobertura ACP (Acordo dos Contratos Públicos da Organização Mundial do Comércio): Não\nIdentificador do Lote: LOT-0066\nContrato adequado para PME: Não\nCobertura ACP (Acordo dos Contratos Públicos da Organização Mundial do Comércio): Não\nIdentificador do Lote: LOT-0067\nContrato adequado para PME: Não\nCobertura ACP (Acordo dos Contratos Públicos da Organização Mundial do Comércio): Não\nIdentificador do Lote: LOT-0068\nContrato adequado para PME: Não\nCobertura ACP (Acordo dos Contratos Públicos da Organização Mundial do Comércio): Não\nIdentificador do Lote: LOT-0069\nContrato adequado para PME: Não\nCobertura ACP (Acordo dos Contratos Públicos da Organização Mundial do Comércio): Não\nIdentificador do Lote: LOT-0070\nContrato adequado para PME: Não\nCobertura ACP (Acordo dos Contratos Públicos da Organização Mundial do Comércio): Não\nIdentificador do Lote: LOT-0071\nContrato adequado para PME: Não\nCobertura ACP (Acordo dos Contratos Públicos da Organização Mundial do Comércio): Não\nIdentificador do Lote: LOT-0072\nContrato adequado para PME: Não\nCobertura ACP (Acordo dos Contratos Públicos da Organização Mundial do Comércio): Não\nIdentificador do Lote: LOT-0073\nContrato adequado para PME: Não\nCobertura ACP (Acordo dos Contratos Públicos da Organização Mundial do Comércio): Não\nIdentificador do Lote: LOT-0074\nContrato adequado para PME: Não\nCobertura ACP (Acordo dos Contratos Públicos da Organização Mundial do Comércio): Não\nIdentificador do Lote: LOT-0075\nContrato adequado para PME: Não\nCobertura ACP (Acordo dos Contratos Públicos da Organização Mundial do Comércio): Não\nIdentificador do Lote: LOT-0076\nContrato adequado para PME: Não\nCobertura ACP (Acordo dos Contratos Públicos da Organização Mundial do Comércio): Não\nIdentificador do Lote: LOT-0077\nContrato adequado para PME: Não\nCobertura ACP (Acordo dos Contratos Públicos da Organização Mundial do Comércio): Não\nIdentificador do Lote: LOT-0078\nContrato adequado para PME: Não\nCobertura ACP (Acordo dos Contratos Públicos da Organização Mundial do Comércio): Não\nIdentificador do Lote: LOT-0079\nContrato adequado para PME: Não\nCobertura ACP (Acordo dos Contratos Públicos da Organização Mundial do Comércio): Não\nIdentificador do Lote: LOT-0080\nContrato adequado para PME: Não\nCobertura ACP (Acordo dos Contratos Públicos da Organização Mundial do Comércio): Não\nIdentificador do Lote: LOT-0081\nContrato adequado para PME: Não\nCobertura ACP (Acordo dos Contratos Públicos da Organização Mundial do Comércio): Não\nIdentificador do Lote: LOT-0082\nContrato adequado para PME: Não\nCobertura ACP (Acordo dos Contratos Públicos da Organização Mundial do Comércio): Não\nIdentificador do Lote: LOT-0083\nContrato adequado para PME: Não\nCobertura ACP (Acordo dos Contratos Públicos da Organização Mundial do Comércio): Não\nIdentificador do Lote: LOT-0084\nContrato adequado para PME: Não\nCobertura ACP (Acordo dos Contratos Públicos da Organização Mundial do Comércio): Não\nIdentificador do Lote: LOT-0085\nContrato adequado para PME: Não\nCobertura ACP (Acordo dos Contratos Públicos da Organização Mundial do Comércio): Não\nIdentificador do Lote: LOT-0086\nContrato adequado para PME: Não\nCobertura ACP (Acordo dos Contratos Públicos da Organização Mundial do Comércio): Não\nIdentificador do Lote: LOT-0087\nContrato adequado para PME: Não\nCobertura ACP (Acordo dos Contratos Públicos da Organização Mundial do Comércio): Não\nIdentificador do Lote: LOT-0088\nContrato adequado para PME: Não\nCobertura ACP (Acordo dos Contratos Públicos da Organização Mundial do Comércio): Não\nIdentificador do Lote: LOT-0089\nContrato adequado para PME: Não\nCobertura ACP (Acordo dos Contratos Públicos da Organização Mundial do Comércio): Não\nIdentificador do Lote: LOT-0090\nContrato adequado para PME: Não\nCobertura ACP (Acordo dos Contratos Públicos da Organização Mundial do Comércio): Não\nIdentificador do Lote: LOT-0091\nContrato adequado para PME: Não\nCobertura ACP (Acordo dos Contratos Públicos da Organização Mundial do Comércio): Não\nIdentificador do Lote: LOT-0092\nContrato adequado para PME: Não\nCobertura ACP (Acordo dos Contratos Públicos da Organização Mundial do Comércio): Não\nIdentificador do Lote: LOT-0093\nContrato adequado para PME: Não\nCobertura ACP (Acordo dos Contratos Públicos da Organização Mundial do Comércio): Não\nIdentificador do Lote: LOT-0094\nContrato adequado para PME: Não\nCobertura ACP (Acordo dos Contratos Públicos da Organização Mundial do Comércio): Não\nIdentificador do Lote: LOT-0095\nContrato adequado para PME: Não\nCobertura ACP (Acordo dos Contratos Públicos da Organização Mundial do Comércio): Não\nIdentificador do Lote: LOT-0096\nContrato adequado para PME: Não\nCobertura ACP (Acordo dos Contratos Públicos da Organização Mundial do Comércio): Não\nIdentificador do Lote: LOT-0097\nContrato adequado para PME: Não\nCobertura ACP (Acordo dos Contratos Públicos da Organização Mundial do Comércio): Não\nIdentificador do Lote: LOT-0098\nContrato adequado para PME: Não\nCobertura ACP (Acordo dos Contratos Públicos da Organização Mundial do Comércio): Não\nIdentificador do Lote: LOT-0099\nContrato adequado para PME: Não\nCobertura ACP (Acordo dos Contratos Públicos da Organização Mundial do Comércio): Não\nIdentificador do Lote: LOT-0100\nContrato adequado para PME: Não\nCobertura ACP (Acordo dos Contratos Públicos da Organização Mundial do Comércio): Não\nIdentificador do Lote: LOT-0101\nContrato adequado para PME: Não\nCobertura ACP (Acordo dos Contratos Públicos da Organização Mundial do Comércio): Não\nIdentificador do Lote: LOT-0102\nContrato adequado para PME: Não\nCobertura ACP (Acordo dos Contratos Públicos da Organização Mundial do Comércio): Não\nIdentificador do Lote: LOT-0103\nContrato adequado para PME: Não\nCobertura ACP (Acordo dos Contratos Públicos da Organização Mundial do Comércio): Não\nIdentificador do Lote: LOT-0104\nContrato adequado para PME: Não\nCobertura ACP (Acordo dos Contratos Públicos da Organização Mundial do Comércio): Não\nIdentificador do Lote: LOT-0105\nContrato adequado para PME: Não\nCobertura ACP (Acordo dos Contratos Públicos da Organização Mundial do Comércio): Não\nIdentificador do Lote: LOT-0106\nContrato adequado para PME: Não\nCobertura ACP (Acordo dos Contratos Públicos da Organização Mundial do Comércio): Não\nIdentificador do Lote: LOT-0107\nContrato adequado para PME: Não\nCobertura ACP (Acordo dos Contratos Públicos da Organização Mundial do Comércio): Não\nIdentificador do Lote: LOT-0108\nContrato adequado para PME: Não\nCobertura ACP (Acordo dos Contratos Públicos da Organização Mundial do Comércio): Não\nIdentificador do Lote: LOT-0109\nContrato adequado para PME: Não\nCobertura ACP (Acordo dos Contratos Públicos da Organização Mundial do Comércio): Não\nIdentificador do Lote: LOT-0110\nContrato adequado para PME: Não\nCobertura ACP (Acordo dos Contratos Públicos da Organização Mundial do Comércio): Não\nIdentificador do Lote: LOT-0111\nContrato adequado para PME: Não\nCobertura ACP (Acordo dos Contratos Públicos da Organização Mundial do Comércio): Não\nIdentificador do Lote: LOT-0112\nContrato adequado para PME: Não\nCobertura ACP (Acordo dos Contratos Públicos da Organização Mundial do Comércio): Não\nIdentificador do Lote: LOT-0113\nContrato adequado para PME: Não\nCobertura ACP (Acordo dos Contratos Públicos da Organização Mundial do Comércio): Não\nIdentificador do Lote: LOT-0114\nContrato adequado para PME: Não\nCobertura ACP (Acordo dos Contratos Públicos da Organização Mundial do Comércio): Não\nIdentificador do Lote: LOT-0115\nContrato adequado para PME: Não\nCobertura ACP (Acordo dos Contratos Públicos da Organização Mundial do Comércio): Não\nIdentificador do Lote: LOT-0116\nContrato adequado para PME: Não\nCobertura ACP (Acordo dos Contratos Públicos da Organização Mundial do Comércio): Não\nIdentificador do Lote: LOT-0117\nContrato adequado para PME: Não\nCobertura ACP (Acordo dos Contratos Públicos da Organização Mundial do Comércio): Não\nIdentificador do Lote: LOT-0118\nContrato adequado para PME: Não\nCobertura ACP (Acordo dos Contratos Públicos da Organização Mundial do Comércio): Não\nIdentificador do Lote: LOT-0119\nContrato adequado para PME: Não\nCobertura ACP (Acordo dos Contratos Públicos da Organização Mundial do Comércio): Não\nIdentificador do Lote: LOT-0120\nContrato adequado para PME: Não\nCobertura ACP (Acordo dos Contratos Públicos da Organização Mundial do Comércio): Não\nIdentificador do Lote: LOT-0121\nContrato adequado para PME: Não\nCobertura ACP (Acordo dos Contratos Públicos da Organização Mundial do Comércio): Não\nIdentificador do Lote: LOT-0122\nContrato adequado para PME: Não\nCobertura ACP (Acordo dos Contratos Públicos da Organização Mundial do Comércio): Não\nIdentificador do Lote: LOT-0123\nContrato adequado para PME: Não\nCobertura ACP (Acordo dos Contratos Públicos da Organização Mundial do Comércio): Não\nIdentificador do Lote: LOT-0124\nContrato adequado para PME: Não\nCobertura ACP (Acordo dos Contratos Públicos da Organização Mundial do Comércio): Não\nIdentificador do Lote: LOT-0125\nContrato adequado para PME: Não\nCobertura ACP (Acordo dos Contratos Públicos da Organização Mundial do Comércio): Não\nIdentificador do Lote: LOT-0126\nContrato adequado para PME: Não\nCobertura ACP (Acordo dos Contratos Públicos da Organização Mundial do Comércio): Não\nIdentificador do Lote: LOT-0127\nContrato adequado para PME: Não\nCobertura ACP (Acordo dos Contratos Públicos da Organização Mundial do Comércio): Não\nIdentificador do Lote: LOT-0128\nContrato adequado para PME: Não\nCobertura ACP (Acordo dos Contratos Públicos da Organização Mundial do Comércio): Não\nIdentificador do Lote: LOT-0129\nContrato adequado para PME: Não\nCobertura ACP (Acordo dos Contratos Públicos da Organização Mundial do Comércio): Não\nIdentificador do Lote: LOT-0130\nContrato adequado para PME: Não\nCobertura ACP (Acordo dos Contratos Públicos da Organização Mundial do Comércio): Não\nIdentificador do Lote: LOT-0131\nContrato adequado para PME: Não\nCobertura ACP (Acordo dos Contratos Públicos da Organização Mundial do Comércio): Não\nIdentificador do Lote: LOT-0132\nContrato adequado para PME: Não\nCobertura ACP (Acordo dos Contratos Públicos da Organização Mundial do Comércio): Não\nIdentificador do Lote: LOT-0133\nContrato adequado para PME: Não\nCobertura ACP (Acordo dos Contratos Públicos da Organização Mundial do Comércio): Não\nIdentificador do Lote: LOT-0134\nContrato adequado para PME: Não\nCobertura ACP (Acordo dos Contratos Públicos da Organização Mundial do Comércio): Não\nIdentificador do Lote: LOT-0135\nContrato adequado para PME: Não\nCobertura ACP (Acordo dos Contratos Públicos da Organização Mundial do Comércio): Não\nIdentificador do Lote: LOT-0136\nContrato adequado para PME: Não\nCobertura ACP (Acordo dos Contratos Públicos da Organização Mundial do Comércio): Não\nIdentificador do Lote: LOT-0137\nContrato adequado para PME: Não\nCobertura ACP (Acordo dos Contratos Públicos da Organização Mundial do Comércio): Não\nIdentificador do Lote: LOT-0138\nContrato adequado para PME: Não\nCobertura ACP (Acordo dos Contratos Públicos da Organização Mundial do Comércio): Não\nIdentificador do Lote: LOT-0139\nContrato adequado para PME: Não\nCobertura ACP (Acordo dos Contratos Públicos da Organização Mundial do Comércio): Não\nIdentificador do Lote: LOT-0140\nContrato adequado para PME: Não\nCobertura ACP (Acordo dos Contratos Públicos da Organização Mundial do Comércio): Não\nIdentificador do Lote: LOT-0141\nContrato adequado para PME: Não\nCobertura ACP (Acordo dos Contratos Públicos da Organização Mundial do Comércio): Não\nIdentificador do Lote: LOT-0142\nContrato adequado para PME: Não\nCobertura ACP (Acordo dos Contratos Públicos da Organização Mundial do Comércio): Não\nIdentificador do Lote: LOT-0143\nContrato adequado para PME: Não\nCobertura ACP (Acordo dos Contratos Públicos da Organização Mundial do Comércio): Não\nIdentificador do Lote: LOT-0144\nContrato adequado para PME: Não\nCobertura ACP (Acordo dos Contratos Públicos da Organização Mundial do Comércio): Não\nIdentificador do Lote: LOT-0145\nContrato adequado para PME: Não\nCobertura ACP (Acordo dos Contratos Públicos da Organização Mundial do Comércio): Não\nIdentificador do Lote: LOT-0146\nContrato adequado para PME: Não\nCobertura ACP (Acordo dos Contratos Públicos da Organização Mundial do Comércio): Não\nIdentificador do Lote: LOT-0147\nContrato adequado para PME: Não\nCobertura ACP (Acordo dos Contratos Públicos da Organização Mundial do Comércio): Não\nIdentificador do Lote: LOT-0148\nContrato adequado para PME: Não\nCobertura ACP (Acordo dos Contratos Públicos da Organização Mundial do Comércio): Não\nIdentificador do Lote: LOT-0149\nContrato adequado para PME: Não\nCobertura ACP (Acordo dos Contratos Públicos da Organização Mundial do Comércio): Não\nIdentificador do Lote: LOT-0150\nContrato adequado para PME: Não\nCobertura ACP (Acordo dos Contratos Públicos da Organização Mundial do Comércio): Não\nIdentificador do Lote: LOT-0151\nContrato adequado para PME: Não\nCobertura ACP (Acordo dos Contratos Públicos da Organização Mundial do Comércio): Não\nIdentificador do Lote: LOT-0152\nContrato adequado para PME: Não\nCobertura ACP (Acordo dos Contratos Públicos da Organização Mundial do Comércio): Não\nIdentificador do Lote: LOT-0153\nContrato adequado para PME: Não\nCobertura ACP (Acordo dos Contratos Públicos da Organização Mundial do Comércio): Não\nIdentificador do Lote: LOT-0154\nContrato adequado para PME: Não\nCobertura ACP (Acordo dos Contratos Públicos da Organização Mundial do Comércio): Não\nIdentificador do Lote: LOT-0155\nContrato adequado para PME: Não\nCobertura ACP (Acordo dos Contratos Públicos da Organização Mundial do Comércio): Não\nIdentificador do Lote: LOT-0156\nContrato adequado para PME: Não\nCobertura ACP (Acordo dos Contratos Públicos da Organização Mundial do Comércio): Não\nIdentificador do Lote: LOT-0157\nContrato adequado para PME: Não\nCobertura ACP (Acordo dos Contratos Públicos da Organização Mundial do Comércio): Não\nIdentificador do Lote: LOT-0158\nContrato adequado para PME: Não\nCobertura ACP (Acordo dos Contratos Públicos da Organização Mundial do Comércio): Não\nIdentificador do Lote: LOT-0159\nContrato adequado para PME: Não\nCobertura ACP (Acordo dos Contratos Públicos da Organização Mundial do Comércio): Não\nIdentificador do Lote: LOT-0160\nContrato adequado para PME: Não\nCobertura ACP (Acordo dos Contratos Públicos da Organização Mundial do Comércio): Não\nIdentificador do Lote: LOT-0161\nContrato adequado para PME: Não\nCobertura ACP (Acordo dos Contratos Públicos da Organização Mundial do Comércio): Não\nIdentificador do Lote: LOT-0162\nContrato adequado para PME: Não\nCobertura ACP (Acordo dos Contratos Públicos da Organização Mundial do Comércio): Não\nIdentificador do Lote: LOT-0163\nContrato adequado para PME: Não\nCobertura ACP (Acordo dos Contratos Públicos da Organização Mundial do Comércio): Não\nIdentificador do Lote: LOT-0164\nContrato adequado para PME: Não\nCobertura ACP (Acordo dos Contratos Públicos da Organização Mundial do Comércio): Não\nIdentificador do Lote: LOT-0165\nContrato adequado para PME: Não\nCobertura ACP (Acordo dos Contratos Públicos da Organização Mundial do Comércio): Não\nIdentificador do Lote: LOT-0166\nContrato adequado para PME: Não\nCobertura ACP (Acordo dos Contratos Públicos da Organização Mundial do Comércio): Não\nIdentificador do Lote: LOT-0167\nContrato adequado para PME: Não\nCobertura ACP (Acordo dos Contratos Públicos da Organização Mundial do Comércio): Não\nIdentificador do Lote: LOT-0168\nContrato adequado para PME: Não\nCobertura ACP (Acordo dos Contratos Públicos da Organização Mundial do Comércio): Não\nIdentificador do Lote: LOT-0169\nContrato adequado para PME: Não\nCobertura ACP (Acordo dos Contratos Públicos da Organização Mundial do Comércio): Não\nIdentificador do Lote: LOT-0170\nContrato adequado para PME: Não\nCobertura ACP (Acordo dos Contratos Públicos da Organização Mundial do Comércio): Não\nIdentificador do Lote: LOT-0171\nContrato adequado para PME: Não\nCobertura ACP (Acordo dos Contratos Públicos da Organização Mundial do Comércio): Não\nIdentificador do Lote: LOT-0172\nContrato adequado para PME: Não\nCobertura ACP (Acordo dos Contratos Públicos da Organização Mundial do Comércio): Não\nIdentificador do Lote: LOT-0173\nContrato adequado para PME: Não\nCobertura ACP (Acordo dos Contratos Públicos da Organização Mundial do Comércio): Não\nIdentificador do Lote: LOT-0174\nContrato adequado para PME: Não\nCobertura ACP (Acordo dos Contratos Públicos da Organização Mundial do Comércio): Não\nIdentificador do Lote: LOT-0175\nContrato adequado para PME: Não\nCobertura ACP (Acordo dos Contratos Públicos da Organização Mundial do Comércio): Não\nIdentificador do Lote: LOT-0176\nContrato adequado para PME: Não\nCobertura ACP (Acordo dos Contratos Públicos da Organização Mundial do Comércio): Não\nIdentificador do Lote: LOT-0177\nContrato adequado para PME: Não\nCobertura ACP (Acordo dos Contratos Públicos da Organização Mundial do Comércio): Não\nIdentificador do Lote: LOT-0178\nContrato adequado para PME: Não\nCobertura ACP (Acordo dos Contratos Públicos da Organização Mundial do Comércio): Não\nIdentificador do Lote: LOT-0179\nContrato adequado para PME: Não\nCobertura ACP (Acordo dos Contratos Públicos da Organização Mundial do Comércio): Não\nIdentificador do Lote: LOT-0180\nContrato adequado para PME: Não\nCobertura ACP (Acordo dos Contratos Públicos da Organização Mundial do Comércio): Não\nIdentificador do Lote: LOT-0181\nContrato adequado para PME: Não\nCobertura ACP (Acordo dos Contratos Públicos da Organização Mundial do Comércio): Não\nIdentificador do Lote: LOT-0182\nContrato adequado para PME: Não\nCobertura ACP (Acordo dos Contratos Públicos da Organização Mundial do Comércio): Não\nIdentificador do Lote: LOT-0183\nContrato adequado para PME: Não\nCobertura ACP (Acordo dos Contratos Públicos da Organização Mundial do Comércio): Não\nIdentificador do Lote: LOT-0184\nContrato adequado para PME: Não\nCobertura ACP (Acordo dos Contratos Públicos da Organização Mundial do Comércio): Não\nIdentificador do Lote: LOT-0185\nContrato adequado para PME: Não\nCobertura ACP (Acordo dos Contratos Públicos da Organização Mundial do Comércio): Não\nIdentificador do Lote: LOT-0186\nContrato adequado para PME: Não\nCobertura ACP (Acordo dos Contratos Públicos da Organização Mundial do Comércio): Não\nIdentificador do Lote: LOT-0187\nContrato adequado para PME: Não\nCobertura ACP (Acordo dos Contratos Públicos da Organização Mundial do Comércio): Não\nIdentificador do Lote: LOT-0188\nContrato adequado para PME: Não\nCobertura ACP (Acordo dos Contratos Públicos da Organização Mundial do Comércio): Não\nIdentificador do Lote: LOT-0189\nContrato adequado para PME: Não\nCobertura ACP (Acordo dos Contratos Públicos da Organização Mundial do Comércio): Não\nIdentificador do Lote: LOT-0190\nContrato adequado para PME: Não\nCobertura ACP (Acordo dos Contratos Públicos da Organização Mundial do Comércio): Não\nIdentificador do Lote: LOT-0191\nContrato adequado para PME: Não\nCobertura ACP (Acordo dos Contratos Públicos da Organização Mundial do Comércio): Não\nIdentificador do Lote: LOT-0192\nContrato adequado para PME: Não\nCobertura ACP (Acordo dos Contratos Públicos da Organização Mundial do Comércio): Não\nIdentificador do Lote: LOT-0193\nContrato adequado para PME: Não\nCobertura ACP (Acordo dos Contratos Públicos da Organização Mundial do Comércio): Não\nIdentificador do Lote: LOT-0194\nContrato adequado para PME: Não\nCobertura ACP (Acordo dos Contratos Públicos da Organização Mundial do Comércio): Não\nIdentificador do Lote: LOT-0195\nContrato adequado para PME: Não\nCobertura ACP (Acordo dos Contratos Públicos da Organização Mundial do Comércio): Não\nIdentificador do Lote: LOT-0196\nContrato adequado para PME: Não\nCobertura ACP (Acordo dos Contratos Públicos da Organização Mundial do Comércio): Não\nIdentificador do Lote: LOT-0197\nContrato adequado para PME: Não\nCobertura ACP (Acordo dos Contratos Públicos da Organização Mundial do Comércio): Não\nIdentificador do Lote: LOT-0198\nContrato adequado para PME: Não\nCobertura ACP (Acordo dos Contratos Públicos da Organização Mundial do Comércio): Não\nIdentificador do Lote: LOT-0199\nContrato adequado para PME: Não\nCobertura ACP (Acordo dos Contratos Públicos da Organização Mundial do Comércio): Não\nIdentificador do Lote: LOT-0200\nContrato adequado para PME: Não\nCobertura ACP (Acordo dos Contratos Públicos da Organização Mundial do Comércio): Não\nIdentificador do Lote: LOT-0201\nContrato adequado para PME: Não\nCobertura ACP (Acordo dos Contratos Públicos da Organização Mundial do Comércio): Não\nIdentificador do Lote: LOT-0202\nContrato adequado para PME: Não\nCobertura ACP (Acordo dos Contratos Públicos da Organização Mundial do Comércio): Não\nIdentificador do Lote: LOT-0203\nContrato adequado para PME: Não\nCobertura ACP (Acordo dos Contratos Públicos da Organização Mundial do Comércio): Não\nIdentificador do Lote: LOT-0204\nContrato adequado para PME: Não\nCobertura ACP (Acordo dos Contratos Públicos da Organização Mundial do Comércio): Não\n\n27 - IDENTIFICAÇÃO E CONTACTOS DO ÓRGÃO DE RECURSOS ADMINISTRATIVOS\nDesignação: Serviços de Ação Social da Universidade do Algarve\nEndereço: Estrada da Penha - Campus Universitário da Penha\nCódigo postal: 8005-139\nLocalidade: Faro\nEndereço eletrónico: sas@ualg.pt\n\n28 - IDENTIFICAÇÃO DO(S) AUTOR(ES) DE ANÚNCIO\nNome: António Joaquim Godinho Cabecinha\nCargo: Administrador dos SAS da Universidade do Algarve\n419601711",
    "nipc": "600039510",
    "distrito": "Faro",
    "concelho": "Faro",
    "freguesia": "Todas",
    "site": "https://www.ualg.pt/acao-social",
    "email": "sascompras@ualg.pt",
    "designacao_contrato": "Fornecimento contínuo e faseado de Produtos Alimentares Diversos (mercearias)",
    "descricao": "Fornecimento contínuo e faseado de Produtos Alimentares Diversos (mercearias)",
    "preco_base": "214.492,00 EUR",
    "prazo_execucao": "1 ANOS",
    "prazo_apresentacao_propostas": "08-10-2025 23:59",
    "fundos_eu": "Não",
    "plataforma_eletronica": "ANOGOV",
    "url_procedimento": "https://www.anogov.com/me-sasualgarve/faces/",
    "autor_nome": "António Joaquim Godinho Cabecinha",
    "autor_cargo": "Administrador dos SAS da Universidade do Algarve"
  },
  {
    "numero_procedimento": "N/A",
    "entidade": "Serviços de Acção Social da Universidade do Algarve",
    "link": "https://diariodarepublica.pt/dr/detalhe/contrato-publico/25878-937672805",
    "detalhes_completos": "1 - IDENTIFICAÇÃO E CONTACTOS DA ENTIDADE ADJUDICANTE\nDesignação da entidade adjudicante: Serviços de Acção Social da Universidade do Algarve\nNIPC: 600039510\nEndereço: Campus Universitário da Penha - Estrada da Penha\nCódigo postal: 8005-139\nLocalidade: Faro\nPaís: Portugal\nNUT III: PT150\nDistrito: Faro\nConcelho: Faro\nFreguesia: Todas\nTelefone: 289800102\nFax: 289800102\nEndereço da Entidade (URL): https://www.ualg.pt/acao-social\nEndereço Eletrónico: sascompras@ualg.pt\nFunção da Organização: Adquirente\nSubfunção da Organização: Líder do grupo\nNorma jurídica da Entidade Adjudicante: Autoridade da administração central\nÁrea de atividade da Entidade Adjudicante: Atividades aeroportuárias\n\n2 - JORNAL OFICIAL DA UNIÃO EUROPEIA\nO procedimento a que este anúncio diz respeito também é publicitado no Jornal Oficial da União Europeia? Não\n\n3 - AVISO\nModelo de Anúncio: Concurso público\nData de Envio do Anúncio: 01-10-2025\n\n5 - PROCESSO\nTipo de Procedimento: Concurso público\nPreço base do procedimento: Sim\nValor do preço base do procedimento: 213.966,50 EUR\nProcedimento com lotes? Sim\nNº Máx. de Lotes Autorizado: 109\nNúmero máximo de lotes que podem ser adjudicados a um concorrente: 109\n\n6 - OBJETO DO CONTRATO\nNúmero de referência interna: Concurso Público n.º 03/SAS-UAlg/2025\nDesignação do contrato: Fornecimento contínuo e faseado de Fruta e Legumes Frescos e Legumes Congelados\nDescrição: Fornecimento contínuo e faseado de Fruta e Legumes Frescos e Legumes Congelados\nTipo de Contrato Principal: Aquisição de Bens Móveis\nTipo de Contrato: Aquisição de Bens Móveis\nClassificação CPV (Vocabulário Comum para os Contratos Públicos)\nObjeto principal\nVocabulário Principal: 15300000\nPreço base s/IVA: 213.966,50 EUR\nLotes: \nNº: LOT-0001\nDescrição do Lote: Abacaxi\nPreço base s/IVA: 6.000,00 EUR\nClassificação CPV (Vocabulário Comum para os Contratos Públicos)\nObjeto principal\nVocabulário Principal: 15300000\nNº: LOT-0002\nDescrição do Lote: Acelga\nPreço base s/IVA: 40,00 EUR\nClassificação CPV (Vocabulário Comum para os Contratos Públicos)\nObjeto principal\nVocabulário Principal: 15300000\nNº: LOT-0003\nDescrição do Lote: Agrião\nPreço base s/IVA: 525,00 EUR\nClassificação CPV (Vocabulário Comum para os Contratos Públicos)\nObjeto principal\nVocabulário Principal: 15300000\nNº: LOT-0004\nDescrição do Lote: Aipo\nPreço base s/IVA: 21,00 EUR\nClassificação CPV (Vocabulário Comum para os Contratos Públicos)\nObjeto principal\nVocabulário Principal: 15300000\nNº: LOT-0005\nDescrição do Lote: Alecrim (unidades de 100gr)\nPreço base s/IVA: 150,00 EUR\nClassificação CPV (Vocabulário Comum para os Contratos Públicos)\nObjeto principal\nVocabulário Principal: 15300000\nNº: LOT-0006\nDescrição do Lote: Alface\nPreço base s/IVA: 8.750,00 EUR\nClassificação CPV (Vocabulário Comum para os Contratos Públicos)\nObjeto principal\nVocabulário Principal: 15300000\nNº: LOT-0007\nDescrição do Lote: Alface iceberg\nPreço base s/IVA: 48,00 EUR\nClassificação CPV (Vocabulário Comum para os Contratos Públicos)\nObjeto principal\nVocabulário Principal: 15300000\nNº: LOT-0008\nDescrição do Lote: Alho francês\nPreço base s/IVA: 2.000,00 EUR\nClassificação CPV (Vocabulário Comum para os Contratos Públicos)\nObjeto principal\nVocabulário Principal: 15300000\nNº: LOT-0009\nDescrição do Lote: Alhos\nPreço base s/IVA: 3.700,00 EUR\nClassificação CPV (Vocabulário Comum para os Contratos Públicos)\nObjeto principal\nVocabulário Principal: 15300000\nNº: LOT-0010\nDescrição do Lote: Ameixa\nPreço base s/IVA: 300,00 EUR\nClassificação CPV (Vocabulário Comum para os Contratos Públicos)\nObjeto principal\nVocabulário Principal: 15300000\nNº: LOT-0011\nDescrição do Lote: Amora \nPreço base s/IVA: 60,00 EUR\nClassificação CPV (Vocabulário Comum para os Contratos Públicos)\nObjeto principal\nVocabulário Principal: 15300000\nNº: LOT-0012\nDescrição do Lote: Banana\nPreço base s/IVA: 4.200,00 EUR\nClassificação CPV (Vocabulário Comum para os Contratos Públicos)\nObjeto principal\nVocabulário Principal: 15300000\nNº: LOT-0013\nDescrição do Lote: Batata\nPreço base s/IVA: 36.000,00 EUR\nClassificação CPV (Vocabulário Comum para os Contratos Públicos)\nObjeto principal\nVocabulário Principal: 15300000\nNº: LOT-0014\nDescrição do Lote: Batata branca miúda lavada\nPreço base s/IVA: 5.600,00 EUR\nClassificação CPV (Vocabulário Comum para os Contratos Públicos)\nObjeto principal\nVocabulário Principal: 15300000\nNº: LOT-0015\nDescrição do Lote: Batata doce\nPreço base s/IVA: 6.000,00 EUR\nClassificação CPV (Vocabulário Comum para os Contratos Públicos)\nObjeto principal\nVocabulário Principal: 15300000\nNº: LOT-0016\nDescrição do Lote: Beringelas\nPreço base s/IVA: 1.200,00 EUR\nClassificação CPV (Vocabulário Comum para os Contratos Públicos)\nObjeto principal\nVocabulário Principal: 15300000\nNº: LOT-0017\nDescrição do Lote: Beterraba\nPreço base s/IVA: 300,00 EUR\nClassificação CPV (Vocabulário Comum para os Contratos Públicos)\nObjeto principal\nVocabulário Principal: 15300000\nNº: LOT-0018\nDescrição do Lote: Bróculos\nPreço base s/IVA: 4.500,00 EUR\nClassificação CPV (Vocabulário Comum para os Contratos Públicos)\nObjeto principal\nVocabulário Principal: 15300000\nNº: LOT-0019\nDescrição do Lote: Caldo verde\nPreço base s/IVA: 240,00 EUR\nClassificação CPV (Vocabulário Comum para os Contratos Públicos)\nObjeto principal\nVocabulário Principal: 15300000\nNº: LOT-0020\nDescrição do Lote: Castanha\nPreço base s/IVA: 220,00 EUR\nClassificação CPV (Vocabulário Comum para os Contratos Públicos)\nObjeto principal\nVocabulário Principal: 15300000\nNº: LOT-0021\nDescrição do Lote: Castanha congelada\nPreço base s/IVA: 1.350,00 EUR\nClassificação CPV (Vocabulário Comum para os Contratos Públicos)\nObjeto principal\nVocabulário Principal: 15300000\nNº: LOT-0022\nDescrição do Lote: Cebola cal. 85+\nPreço base s/IVA: 12.000,00 EUR\nClassificação CPV (Vocabulário Comum para os Contratos Públicos)\nObjeto principal\nVocabulário Principal: 15300000\nNº: LOT-0023\nDescrição do Lote: Cebola roxa\nPreço base s/IVA: 114,00 EUR\nClassificação CPV (Vocabulário Comum para os Contratos Públicos)\nObjeto principal\nVocabulário Principal: 15300000\nNº: LOT-0024\nDescrição do Lote: Chalota (cebolinha)\nPreço base s/IVA: 135,00 EUR\nClassificação CPV (Vocabulário Comum para os Contratos Públicos)\nObjeto principal\nVocabulário Principal: 15300000\nNº: LOT-0025\nDescrição do Lote: Cebolinho (unidades de 100 gr)\nPreço base s/IVA: 150,00 EUR\nClassificação CPV (Vocabulário Comum para os Contratos Públicos)\nObjeto principal\nVocabulário Principal: 15300000\nNº: LOT-0026\nDescrição do Lote: Cenouras\nPreço base s/IVA: 16.800,00 EUR\nClassificação CPV (Vocabulário Comum para os Contratos Públicos)\nObjeto principal\nVocabulário Principal: 15300000\nNº: LOT-0027\nDescrição do Lote: Clementina\nPreço base s/IVA: 1.200,00 EUR\nClassificação CPV (Vocabulário Comum para os Contratos Públicos)\nObjeto principal\nVocabulário Principal: 15300000\nNº: LOT-0028\nDescrição do Lote: Coentros\nPreço base s/IVA: 880,00 EUR\nClassificação CPV (Vocabulário Comum para os Contratos Públicos)\nObjeto principal\nVocabulário Principal: 15300000\nNº: LOT-0029\nDescrição do Lote: Cogumelos frescos\nPreço base s/IVA: 1.890,00 EUR\nClassificação CPV (Vocabulário Comum para os Contratos Públicos)\nObjeto principal\nVocabulário Principal: 15300000\nNº: LOT-0030\nDescrição do Lote: Courgete\nPreço base s/IVA: 2.400,00 EUR\nClassificação CPV (Vocabulário Comum para os Contratos Públicos)\nObjeto principal\nVocabulário Principal: 15300000\nNº: LOT-0031\nDescrição do Lote: Couve chinesa\nPreço base s/IVA: 168,00 EUR\nClassificação CPV (Vocabulário Comum para os Contratos Públicos)\nObjeto principal\nVocabulário Principal: 15300000\nNº: LOT-0032\nDescrição do Lote: Couve de bruxelas congelada\nPreço base s/IVA: 100,00 EUR\nClassificação CPV (Vocabulário Comum para os Contratos Públicos)\nObjeto principal\nVocabulário Principal: 15300000\nNº: LOT-0033\nDescrição do Lote: Couve coração boi c/ folhas\nPreço base s/IVA: 285,00 EUR\nClassificação CPV (Vocabulário Comum para os Contratos Públicos)\nObjeto principal\nVocabulário Principal: 15300000\nNº: LOT-0034\nDescrição do Lote: Couve flor\nPreço base s/IVA: 3.360,00 EUR\nClassificação CPV (Vocabulário Comum para os Contratos Públicos)\nObjeto principal\nVocabulário Principal: 15300000\nNº: LOT-0035\nDescrição do Lote: Couve lombardo\nPreço base s/IVA: 1.080,00 EUR\nClassificação CPV (Vocabulário Comum para os Contratos Públicos)\nObjeto principal\nVocabulário Principal: 15300000\nNº: LOT-0036\nDescrição do Lote: Couve portuguesa\nPreço base s/IVA: 300,00 EUR\nClassificação CPV (Vocabulário Comum para os Contratos Públicos)\nObjeto principal\nVocabulário Principal: 15300000\nNº: LOT-0037\nDescrição do Lote: Couve Roxa c/ Folhas\nPreço base s/IVA: 3.420,00 EUR\nClassificação CPV (Vocabulário Comum para os Contratos Públicos)\nObjeto principal\nVocabulário Principal: 15300000\nNº: LOT-0038\nDescrição do Lote: Ervilhas congeladas\nPreço base s/IVA: 1.530,00 EUR\nClassificação CPV (Vocabulário Comum para os Contratos Públicos)\nObjeto principal\nVocabulário Principal: 15300000\nNº: LOT-0039\nDescrição do Lote: Espargos verdes\nPreço base s/IVA: 250,00 EUR\nClassificação CPV (Vocabulário Comum para os Contratos Públicos)\nObjeto principal\nVocabulário Principal: 15300000\nNº: LOT-0040\nDescrição do Lote: Esparregado congelado\nPreço base s/IVA: 560,00 EUR\nClassificação CPV (Vocabulário Comum para os Contratos Públicos)\nObjeto principal\nVocabulário Principal: 15300000\nNº: LOT-0041\nDescrição do Lote: Espinafre\nPreço base s/IVA: 1.800,00 EUR\nClassificação CPV (Vocabulário Comum para os Contratos Públicos)\nObjeto principal\nVocabulário Principal: 15300000\nNº: LOT-0042\nDescrição do Lote: Espinafre francês\nPreço base s/IVA: 1.050,00 EUR\nClassificação CPV (Vocabulário Comum para os Contratos Públicos)\nObjeto principal\nVocabulário Principal: 15300000\nNº: LOT-0043\nDescrição do Lote: Favas congeladas\nPreço base s/IVA: 750,00 EUR\nClassificação CPV (Vocabulário Comum para os Contratos Públicos)\nObjeto principal\nVocabulário Principal: 15300000\nNº: LOT-0044\nDescrição do Lote: Feijão verde\nPreço base s/IVA: 2.475,00 EUR\nClassificação CPV (Vocabulário Comum para os Contratos Públicos)\nObjeto principal\nVocabulário Principal: 15300000\nNº: LOT-0045\nDescrição do Lote: Frade / abóbora\nPreço base s/IVA: 3.380,00 EUR\nClassificação CPV (Vocabulário Comum para os Contratos Públicos)\nObjeto principal\nVocabulário Principal: 15300000\nNº: LOT-0046\nDescrição do Lote: Framboesa\nPreço base s/IVA: 15,00 EUR\nClassificação CPV (Vocabulário Comum para os Contratos Públicos)\nObjeto principal\nVocabulário Principal: 15300000\nNº: LOT-0047\nDescrição do Lote: Frutos vermelhos congelados\nPreço base s/IVA: 110,00 EUR\nClassificação CPV (Vocabulário Comum para os Contratos Públicos)\nObjeto principal\nVocabulário Principal: 15300000\nNº: LOT-0048\nDescrição do Lote: Funcho\nPreço base s/IVA: 42,00 EUR\nClassificação CPV (Vocabulário Comum para os Contratos Públicos)\nObjeto principal\nVocabulário Principal: 15300000\nNº: LOT-0049\nDescrição do Lote: Gengibre fresco\nPreço base s/IVA: 67,50 EUR\nClassificação CPV (Vocabulário Comum para os Contratos Públicos)\nObjeto principal\nVocabulário Principal: 15300000\nNº: LOT-0050\nDescrição do Lote: Grelos de Couve\nPreço base s/IVA: 735,00 EUR\nClassificação CPV (Vocabulário Comum para os Contratos Públicos)\nObjeto principal\nVocabulário Principal: 15300000\nNº: LOT-0051\nDescrição do Lote: Grelos de Nabo\nPreço base s/IVA: 127,50 EUR\nClassificação CPV (Vocabulário Comum para os Contratos Públicos)\nObjeto principal\nVocabulário Principal: 15300000\nNº: LOT-0052\nDescrição do Lote: Hortelã\nPreço base s/IVA: 240,00 EUR\nClassificação CPV (Vocabulário Comum para os Contratos Públicos)\nObjeto principal\nVocabulário Principal: 15300000\nNº: LOT-0053\nDescrição do Lote: Jardineira congelada 3 legumes (ervilha, cenoura e feijão verde)\nPreço base s/IVA: 3.300,00 EUR\nClassificação CPV (Vocabulário Comum para os Contratos Públicos)\nObjeto principal\nVocabulário Principal: 15300000\nNº: LOT-0054\nDescrição do Lote: Kiwi\nPreço base s/IVA: 770,00 EUR\nClassificação CPV (Vocabulário Comum para os Contratos Públicos)\nObjeto principal\nVocabulário Principal: 15300000\nNº: LOT-0055\nDescrição do Lote: Laranja 70/75\nPreço base s/IVA: 4.500,00 EUR\nClassificação CPV (Vocabulário Comum para os Contratos Públicos)\nObjeto principal\nVocabulário Principal: 15300000\nNº: LOT-0056\nDescrição do Lote: Lasanha de legumes\nPreço base s/IVA: 950,00 EUR\nClassificação CPV (Vocabulário Comum para os Contratos Públicos)\nObjeto principal\nVocabulário Principal: 15300000\nNº: LOT-0057\nDescrição do Lote: Limão\nPreço base s/IVA: 1.800,00 EUR\nClassificação CPV (Vocabulário Comum para os Contratos Públicos)\nObjeto principal\nVocabulário Principal: 15300000\nNº: LOT-0058\nDescrição do Lote: Limas\nPreço base s/IVA: 78,00 EUR\nClassificação CPV (Vocabulário Comum para os Contratos Públicos)\nObjeto principal\nVocabulário Principal: 15300000\nNº: LOT-0059\nDescrição do Lote: Louro (molho)\nPreço base s/IVA: 168,00 EUR\nClassificação CPV (Vocabulário Comum para os Contratos Públicos)\nObjeto principal\nVocabulário Principal: 15300000\nNº: LOT-0060\nDescrição do Lote: Maçã fuji\nPreço base s/IVA: 60,00 EUR\nClassificação CPV (Vocabulário Comum para os Contratos Públicos)\nObjeto principal\nVocabulário Principal: 15300000\nNº: LOT-0061\nDescrição do Lote: Maçã golden 70/75\nPreço base s/IVA: 4.200,00 EUR\nClassificação CPV (Vocabulário Comum para os Contratos Públicos)\nObjeto principal\nVocabulário Principal: 15300000\nNº: LOT-0062\nDescrição do Lote: Maçã golden 80/85\nPreço base s/IVA: 525,00 EUR\nClassificação CPV (Vocabulário Comum para os Contratos Públicos)\nObjeto principal\nVocabulário Principal: 15300000\nNº: LOT-0063\nDescrição do Lote: Maçã jona gold 70/75\nPreço base s/IVA: 16,00 EUR\nClassificação CPV (Vocabulário Comum para os Contratos Públicos)\nObjeto principal\nVocabulário Principal: 15300000\nNº: LOT-0064\nDescrição do Lote: Maçã reineta 80+\nPreço base s/IVA: 63,00 EUR\nClassificação CPV (Vocabulário Comum para os Contratos Públicos)\nObjeto principal\nVocabulário Principal: 15300000\nNº: LOT-0065\nDescrição do Lote: Maçã royal gala 70/75\nPreço base s/IVA: 90,00 EUR\nClassificação CPV (Vocabulário Comum para os Contratos Públicos)\nObjeto principal\nVocabulário Principal: 15300000\nNº: LOT-0066\nDescrição do Lote: Maçã starking 70/75\nPreço base s/IVA: 2.880,00 EUR\nClassificação CPV (Vocabulário Comum para os Contratos Públicos)\nObjeto principal\nVocabulário Principal: 15300000\nNº: LOT-0067\nDescrição do Lote: Maçã starking 75/80\nPreço base s/IVA: 95,00 EUR\nClassificação CPV (Vocabulário Comum para os Contratos Públicos)\nObjeto principal\nVocabulário Principal: 15300000\nNº: LOT-0068\nDescrição do Lote: Mandioca\nPreço base s/IVA: 15,00 EUR\nClassificação CPV (Vocabulário Comum para os Contratos Públicos)\nObjeto principal\nVocabulário Principal: 15300000\nNº: LOT-0069\nDescrição do Lote: Manga\nPreço base s/IVA: 900,00 EUR\nClassificação CPV (Vocabulário Comum para os Contratos Públicos)\nObjeto principal\nVocabulário Principal: 15300000\nNº: LOT-0070\nDescrição do Lote: Manjericão\nPreço base s/IVA: 46,00 EUR\nClassificação CPV (Vocabulário Comum para os Contratos Públicos)\nObjeto principal\nVocabulário Principal: 15300000\nNº: LOT-0071\nDescrição do Lote: Marmelos\nPreço base s/IVA: 26,00 EUR\nClassificação CPV (Vocabulário Comum para os Contratos Públicos)\nObjeto principal\nVocabulário Principal: 15300000\nNº: LOT-0072\nDescrição do Lote: Melancia\nPreço base s/IVA: 700,00 EUR\nClassificação CPV (Vocabulário Comum para os Contratos Públicos)\nObjeto principal\nVocabulário Principal: 15300000\nNº: LOT-0073\nDescrição do Lote: Melão\nPreço base s/IVA: 5.980,00 EUR\nClassificação CPV (Vocabulário Comum para os Contratos Públicos)\nObjeto principal\nVocabulário Principal: 15300000\nNº: LOT-0074\nDescrição do Lote: Milho doce congelado \nPreço base s/IVA: 23,50 EUR\nClassificação CPV (Vocabulário Comum para os Contratos Públicos)\nObjeto principal\nVocabulário Principal: 15300000\nNº: LOT-0075\nDescrição do Lote: Mirtilos \nPreço base s/IVA: 20,00 EUR\nClassificação CPV (Vocabulário Comum para os Contratos Públicos)\nObjeto principal\nVocabulário Principal: 15300000\nNº: LOT-0076\nDescrição do Lote: Mistura de legumes chineses congelada\nPreço base s/IVA: 105,00 EUR\nClassificação CPV (Vocabulário Comum para os Contratos Públicos)\nObjeto principal\nVocabulário Principal: 15300000\nNº: LOT-0077\nDescrição do Lote: Morango\nPreço base s/IVA: 1.750,00 EUR\nClassificação CPV (Vocabulário Comum para os Contratos Públicos)\nObjeto principal\nVocabulário Principal: 15300000\nNº: LOT-0078\nDescrição do Lote: Nabiça\nPreço base s/IVA: 500,00 EUR\nClassificação CPV (Vocabulário Comum para os Contratos Públicos)\nObjeto principal\nVocabulário Principal: 15300000\nNº: LOT-0079\nDescrição do Lote: Nabos\nPreço base s/IVA: 1.950,00 EUR\nClassificação CPV (Vocabulário Comum para os Contratos Públicos)\nObjeto principal\nVocabulário Principal: 15300000\nNº: LOT-0080\nDescrição do Lote: Nectarina\nPreço base s/IVA: 155,00 EUR\nClassificação CPV (Vocabulário Comum para os Contratos Públicos)\nObjeto principal\nVocabulário Principal: 15300000\nNº: LOT-0081\nDescrição do Lote: Oregãos verdes\nPreço base s/IVA: 220,00 EUR\nClassificação CPV (Vocabulário Comum para os Contratos Públicos)\nObjeto principal\nVocabulário Principal: 15300000\nNº: LOT-0082\nDescrição do Lote: Papaia\nPreço base s/IVA: 2.310,00 EUR\nClassificação CPV (Vocabulário Comum para os Contratos Públicos)\nObjeto principal\nVocabulário Principal: 15300000\nNº: LOT-0083\nDescrição do Lote: Pepino\nPreço base s/IVA: 750,00 EUR\nClassificação CPV (Vocabulário Comum para os Contratos Públicos)\nObjeto principal\nVocabulário Principal: 15300000\nNº: LOT-0084\nDescrição do Lote: Pêra abacate\nPreço base s/IVA: 180,00 EUR\nClassificação CPV (Vocabulário Comum para os Contratos Públicos)\nObjeto principal\nVocabulário Principal: 15300000\nNº: LOT-0085\nDescrição do Lote: Pêra rocha 70/75\nPreço base s/IVA: 4.370,00 EUR\nClassificação CPV (Vocabulário Comum para os Contratos Públicos)\nObjeto principal\nVocabulário Principal: 15300000\nNº: LOT-0086\nDescrição do Lote: Pêssego\nPreço base s/IVA: 390,00 EUR\nClassificação CPV (Vocabulário Comum para os Contratos Públicos)\nObjeto principal\nVocabulário Principal: 15300000\nNº: LOT-0087\nDescrição do Lote: Pimento amarelo\nPreço base s/IVA: 420,00 EUR\nClassificação CPV (Vocabulário Comum para os Contratos Públicos)\nObjeto principal\nVocabulário Principal: 15300000\nNº: LOT-0088\nDescrição do Lote: Pimento verde\nPreço base s/IVA: 2.100,00 EUR\nClassificação CPV (Vocabulário Comum para os Contratos Públicos)\nObjeto principal\nVocabulário Principal: 15300000\nNº: LOT-0089\nDescrição do Lote: Pimento vermelho\nPreço base s/IVA: 2.275,00 EUR\nClassificação CPV (Vocabulário Comum para os Contratos Públicos)\nObjeto principal\nVocabulário Principal: 15300000\nNº: LOT-0090\nDescrição do Lote: Rabanetes\nPreço base s/IVA: 200,00 EUR\nClassificação CPV (Vocabulário Comum para os Contratos Públicos)\nObjeto principal\nVocabulário Principal: 15300000\nNº: LOT-0091\nDescrição do Lote: Repolho\nPreço base s/IVA: 60,00 EUR\nClassificação CPV (Vocabulário Comum para os Contratos Públicos)\nObjeto principal\nVocabulário Principal: 15300000\nNº: LOT-0092\nDescrição do Lote: Rúcula\nPreço base s/IVA: 480,00 EUR\nClassificação CPV (Vocabulário Comum para os Contratos Públicos)\nObjeto principal\nVocabulário Principal: 15300000\nNº: LOT-0093\nDescrição do Lote: Salsa\nPreço base s/IVA: 700,00 EUR\nClassificação CPV (Vocabulário Comum para os Contratos Públicos)\nObjeto principal\nVocabulário Principal: 15300000\nNº: LOT-0094\nDescrição do Lote: Soja fina (embalagem 400gr)\nPreço base s/IVA: 375,00 EUR\nClassificação CPV (Vocabulário Comum para os Contratos Públicos)\nObjeto principal\nVocabulário Principal: 15300000\nNº: LOT-0095\nDescrição do Lote: Soja grossa (embalagem 400gr)\nPreço base s/IVA: 300,00 EUR\nClassificação CPV (Vocabulário Comum para os Contratos Públicos)\nObjeto principal\nVocabulário Principal: 15300000\nNº: LOT-0096\nDescrição do Lote: Sopa de alho francês\nPreço base s/IVA: 400,00 EUR\nClassificação CPV (Vocabulário Comum para os Contratos Públicos)\nObjeto principal\nVocabulário Principal: 15300000\nNº: LOT-0097\nDescrição do Lote: Sopa feijão verde\nPreço base s/IVA: 464,00 EUR\nClassificação CPV (Vocabulário Comum para os Contratos Públicos)\nObjeto principal\nVocabulário Principal: 15300000\nNº: LOT-0098\nDescrição do Lote: Sopa juliana\nPreço base s/IVA: 320,00 EUR\nClassificação CPV (Vocabulário Comum para os Contratos Públicos)\nObjeto principal\nVocabulário Principal: 15300000\nNº: LOT-0099\nDescrição do Lote: Sopa paisana\nPreço base s/IVA: 200,00 EUR\nClassificação CPV (Vocabulário Comum para os Contratos Públicos)\nObjeto principal\nVocabulário Principal: 15300000\nNº: LOT-0100\nDescrição do Lote: Sopa portuguesa\nPreço base s/IVA: 40,00 EUR\nClassificação CPV (Vocabulário Comum para os Contratos Públicos)\nObjeto principal\nVocabulário Principal: 15300000\nNº: LOT-0101\nDescrição do Lote: Tangera\nPreço base s/IVA: 160,00 EUR\nClassificação CPV (Vocabulário Comum para os Contratos Públicos)\nObjeto principal\nVocabulário Principal: 15300000\nNº: LOT-0102\nDescrição do Lote: Tangerina\nPreço base s/IVA: 200,00 EUR\nClassificação CPV (Vocabulário Comum para os Contratos Públicos)\nObjeto principal\nVocabulário Principal: 15300000\nNº: LOT-0103\nDescrição do Lote: Tomate 67/82\nPreço base s/IVA: 21.250,00 EUR\nClassificação CPV (Vocabulário Comum para os Contratos Públicos)\nObjeto principal\nVocabulário Principal: 15300000\nNº: LOT-0104\nDescrição do Lote: Tomate cereja\nPreço base s/IVA: 342,00 EUR\nClassificação CPV (Vocabulário Comum para os Contratos Públicos)\nObjeto principal\nVocabulário Principal: 15300000\nNº: LOT-0105\nDescrição do Lote: Tomilho\nPreço base s/IVA: 32,00 EUR\nClassificação CPV (Vocabulário Comum para os Contratos Públicos)\nObjeto principal\nVocabulário Principal: 15300000\nNº: LOT-0106\nDescrição do Lote: Tomilho (unidade 100gr)\nPreço base s/IVA: 175,00 EUR\nClassificação CPV (Vocabulário Comum para os Contratos Públicos)\nObjeto principal\nVocabulário Principal: 15300000\nNº: LOT-0107\nDescrição do Lote: Uvas\nPreço base s/IVA: 190,00 EUR\nClassificação CPV (Vocabulário Comum para os Contratos Públicos)\nObjeto principal\nVocabulário Principal: 15300000\nNº: LOT-0108\nDescrição do Lote: Uvas red globe\nPreço base s/IVA: 4.180,00 EUR\nClassificação CPV (Vocabulário Comum para os Contratos Públicos)\nObjeto principal\nVocabulário Principal: 15300000\nNº: LOT-0109\nDescrição do Lote: Xuxu\nPreço base s/IVA: 600,00 EUR\nClassificação CPV (Vocabulário Comum para os Contratos Públicos)\nObjeto principal\nVocabulário Principal: 15300000\n\n7 - INDICAÇÕES ADICIONAIS\nO contrato envolve aquisição conjunta (satisfação de várias entidades)? Não\nO contrato é adjudicado por uma central de compras? Não\n\n8 - TÉCNICAS\nO concurso destina-se à celebração de um acordo-quadro? Inexistência de acordo-quadro\nÉ utilizado um leilão eletrónico? Não\nÉ adotada uma fase de negociação? Não\nSistema de Aquisição Dinâmico: Inexistência de sistema de aquisição dinâmico\n\n9 - LOCAL DA EXECUÇÃO DO CONTRATO\nLOCAL DA EXECUÇÃO DO CONTRATO (PROCEDIMENTO)\nLOCAL DA EXECUÇÃO DO CONTRATO (LOTE)\nIdentificador do Lote: LOT-0001\nPaís: Portugal\nNUT III: PT150\nLocalidade: Faro\nDistrito: Faro\nConcelho: Faro\nFreguesia: Todas\nIdentificador do Lote: LOT-0002\nPaís: Portugal\nNUT III: PT150\nLocalidade: Faro\nDistrito: Faro\nConcelho: Faro\nFreguesia: Todas\nIdentificador do Lote: LOT-0003\nPaís: Portugal\nNUT III: PT150\nLocalidade: Faro\nDistrito: Faro\nConcelho: Faro\nFreguesia: Todas\nIdentificador do Lote: LOT-0004\nPaís: Portugal\nNUT III: PT150\nLocalidade: Faro\nDistrito: Faro\nConcelho: Faro\nFreguesia: Todas\nIdentificador do Lote: LOT-0005\nPaís: Portugal\nNUT III: PT150\nLocalidade: Faro\nDistrito: Faro\nConcelho: Faro\nFreguesia: Todas\nIdentificador do Lote: LOT-0006\nPaís: Portugal\nNUT III: PT150\nLocalidade: Faro\nDistrito: Faro\nConcelho: Faro\nFreguesia: Todas\nIdentificador do Lote: LOT-0007\nPaís: Portugal\nNUT III: PT150\nLocalidade: Faro\nDistrito: Faro\nConcelho: Faro\nFreguesia: Todas\nIdentificador do Lote: LOT-0008\nPaís: Portugal\nNUT III: PT150\nLocalidade: Faro\nDistrito: Faro\nConcelho: Faro\nFreguesia: Todas\nIdentificador do Lote: LOT-0009\nPaís: Portugal\nNUT III: PT150\nLocalidade: Faro\nDistrito: Faro\nConcelho: Faro\nFreguesia: Todas\nIdentificador do Lote: LOT-0010\nPaís: Portugal\nNUT III: PT150\nLocalidade: Faro\nDistrito: Faro\nConcelho: Faro\nFreguesia: Todas\nIdentificador do Lote: LOT-0011\nPaís: Portugal\nNUT III: PT150\nLocalidade: Faro\nDistrito: Faro\nConcelho: Faro\nFreguesia: Todas\nIdentificador do Lote: LOT-0012\nPaís: Portugal\nNUT III: PT150\nLocalidade: Faro\nDistrito: Faro\nConcelho: Faro\nFreguesia: Todas\nIdentificador do Lote: LOT-0013\nPaís: Portugal\nNUT III: PT150\nLocalidade: Faro\nDistrito: Faro\nConcelho: Faro\nFreguesia: Todas\nIdentificador do Lote: LOT-0014\nPaís: Portugal\nNUT III: PT150\nLocalidade: Faro\nDistrito: Faro\nConcelho: Faro\nFreguesia: Todas\nIdentificador do Lote: LOT-0015\nPaís: Portugal\nNUT III: PT150\nLocalidade: Faro\nDistrito: Faro\nConcelho: Faro\nFreguesia: Todas\nIdentificador do Lote: LOT-0016\nPaís: Portugal\nNUT III: PT150\nLocalidade: Faro\nDistrito: Faro\nConcelho: Faro\nFreguesia: Todas\nIdentificador do Lote: LOT-0017\nPaís: Portugal\nNUT III: PT150\nLocalidade: Faro\nDistrito: Faro\nConcelho: Faro\nFreguesia: Todas\nIdentificador do Lote: LOT-0018\nPaís: Portugal\nNUT III: PT150\nLocalidade: Faro\nDistrito: Faro\nConcelho: Faro\nFreguesia: Todas\nIdentificador do Lote: LOT-0019\nPaís: Portugal\nNUT III: PT150\nLocalidade: Faro\nDistrito: Faro\nConcelho: Faro\nFreguesia: Todas\nIdentificador do Lote: LOT-0020\nPaís: Portugal\nNUT III: PT150\nLocalidade: Faro\nDistrito: Faro\nConcelho: Faro\nFreguesia: Todas\nIdentificador do Lote: LOT-0021\nPaís: Portugal\nNUT III: PT150\nLocalidade: Faro\nDistrito: Faro\nConcelho: Faro\nFreguesia: Todas\nIdentificador do Lote: LOT-0022\nPaís: Portugal\nNUT III: PT150\nLocalidade: Faro\nDistrito: Faro\nConcelho: Faro\nFreguesia: Todas\nIdentificador do Lote: LOT-0023\nPaís: Portugal\nNUT III: PT150\nLocalidade: Faro\nDistrito: Faro\nConcelho: Faro\nFreguesia: Todas\nIdentificador do Lote: LOT-0024\nPaís: Portugal\nNUT III: PT150\nLocalidade: Faro\nDistrito: Faro\nConcelho: Faro\nFreguesia: Todas\nIdentificador do Lote: LOT-0025\nPaís: Portugal\nNUT III: PT150\nLocalidade: Faro\nDistrito: Faro\nConcelho: Faro\nFreguesia: Todas\nIdentificador do Lote: LOT-0026\nPaís: Portugal\nNUT III: PT150\nLocalidade: Faro\nDistrito: Faro\nConcelho: Faro\nFreguesia: Todas\nIdentificador do Lote: LOT-0027\nPaís: Portugal\nNUT III: PT150\nLocalidade: Faro\nDistrito: Faro\nConcelho: Faro\nFreguesia: Todas\nIdentificador do Lote: LOT-0028\nPaís: Portugal\nNUT III: PT150\nLocalidade: Faro\nDistrito: Faro\nConcelho: Faro\nFreguesia: Todas\nIdentificador do Lote: LOT-0029\nPaís: Portugal\nNUT III: PT150\nLocalidade: Faro\nDistrito: Faro\nConcelho: Faro\nFreguesia: Todas\nIdentificador do Lote: LOT-0030\nPaís: Portugal\nNUT III: PT150\nLocalidade: Faro\nDistrito: Faro\nConcelho: Faro\nFreguesia: Todas\nIdentificador do Lote: LOT-0031\nPaís: Portugal\nNUT III: PT150\nLocalidade: Faro\nDistrito: Faro\nConcelho: Faro\nFreguesia: Todas\nIdentificador do Lote: LOT-0032\nPaís: Portugal\nNUT III: PT150\nLocalidade: Faro\nDistrito: Faro\nConcelho: Faro\nFreguesia: Todas\nIdentificador do Lote: LOT-0033\nPaís: Portugal\nNUT III: PT150\nLocalidade: Faro\nDistrito: Faro\nConcelho: Faro\nFreguesia: Todas\nIdentificador do Lote: LOT-0034\nPaís: Portugal\nNUT III: PT150\nLocalidade: Faro\nDistrito: Faro\nConcelho: Faro\nFreguesia: Todas\nIdentificador do Lote: LOT-0035\nPaís: Portugal\nNUT III: PT150\nLocalidade: Faro\nDistrito: Faro\nConcelho: Faro\nFreguesia: Todas\nIdentificador do Lote: LOT-0036\nPaís: Portugal\nNUT III: PT150\nLocalidade: Faro\nDistrito: Faro\nConcelho: Faro\nFreguesia: Todas\nIdentificador do Lote: LOT-0037\nPaís: Portugal\nNUT III: PT150\nLocalidade: Faro\nDistrito: Faro\nConcelho: Faro\nFreguesia: Todas\nIdentificador do Lote: LOT-0038\nPaís: Portugal\nNUT III: PT150\nLocalidade: Faro\nDistrito: Faro\nConcelho: Faro\nFreguesia: Todas\nIdentificador do Lote: LOT-0039\nPaís: Portugal\nNUT III: PT150\nLocalidade: Faro\nDistrito: Faro\nConcelho: Faro\nFreguesia: Todas\nIdentificador do Lote: LOT-0040\nPaís: Portugal\nNUT III: PT150\nLocalidade: Faro\nDistrito: Faro\nConcelho: Faro\nFreguesia: Todas\nIdentificador do Lote: LOT-0041\nPaís: Portugal\nNUT III: PT150\nLocalidade: Faro\nDistrito: Faro\nConcelho: Faro\nFreguesia: Todas\nIdentificador do Lote: LOT-0042\nPaís: Portugal\nNUT III: PT150\nLocalidade: Faro\nDistrito: Faro\nConcelho: Faro\nFreguesia: Todas\nIdentificador do Lote: LOT-0043\nPaís: Portugal\nNUT III: PT150\nLocalidade: Faro\nDistrito: Faro\nConcelho: Faro\nFreguesia: Todas\nIdentificador do Lote: LOT-0044\nPaís: Portugal\nNUT III: PT150\nLocalidade: Faro\nDistrito: Faro\nConcelho: Faro\nFreguesia: Todas\nIdentificador do Lote: LOT-0045\nPaís: Portugal\nNUT III: PT150\nLocalidade: Faro\nDistrito: Faro\nConcelho: Faro\nFreguesia: Todas\nIdentificador do Lote: LOT-0046\nPaís: Portugal\nNUT III: PT150\nLocalidade: Faro\nDistrito: Faro\nConcelho: Faro\nFreguesia: Todas\nIdentificador do Lote: LOT-0047\nPaís: Portugal\nNUT III: PT150\nLocalidade: Faro\nDistrito: Faro\nConcelho: Faro\nFreguesia: Todas\nIdentificador do Lote: LOT-0048\nPaís: Portugal\nNUT III: PT150\nLocalidade: Faro\nDistrito: Faro\nConcelho: Faro\nFreguesia: Todas\nIdentificador do Lote: LOT-0049\nPaís: Portugal\nNUT III: PT150\nLocalidade: Faro\nDistrito: Faro\nConcelho: Faro\nFreguesia: Todas\nIdentificador do Lote: LOT-0050\nPaís: Portugal\nNUT III: PT150\nLocalidade: Faro\nDistrito: Faro\nConcelho: Faro\nFreguesia: Todas\nIdentificador do Lote: LOT-0051\nPaís: Portugal\nNUT III: PT150\nLocalidade: Faro\nDistrito: Faro\nConcelho: Faro\nFreguesia: Todas\nIdentificador do Lote: LOT-0052\nPaís: Portugal\nNUT III: PT150\nLocalidade: Faro\nDistrito: Faro\nConcelho: Faro\nFreguesia: Todas\nIdentificador do Lote: LOT-0053\nPaís: Portugal\nNUT III: PT150\nLocalidade: Faro\nDistrito: Faro\nConcelho: Faro\nFreguesia: Todas\nIdentificador do Lote: LOT-0054\nPaís: Portugal\nNUT III: PT150\nLocalidade: Faro\nDistrito: Faro\nConcelho: Faro\nFreguesia: Todas\nIdentificador do Lote: LOT-0055\nPaís: Portugal\nNUT III: PT150\nLocalidade: Faro\nDistrito: Faro\nConcelho: Faro\nFreguesia: Todas\nIdentificador do Lote: LOT-0056\nPaís: Portugal\nNUT III: PT150\nLocalidade: Faro\nDistrito: Faro\nConcelho: Faro\nFreguesia: Todas\nIdentificador do Lote: LOT-0057\nPaís: Portugal\nNUT III: PT150\nLocalidade: Faro\nDistrito: Faro\nConcelho: Faro\nFreguesia: Todas\nIdentificador do Lote: LOT-0058\nPaís: Portugal\nNUT III: PT150\nLocalidade: Faro\nDistrito: Faro\nConcelho: Faro\nFreguesia: Todas\nIdentificador do Lote: LOT-0059\nPaís: Portugal\nNUT III: PT150\nLocalidade: Faro\nDistrito: Faro\nConcelho: Faro\nFreguesia: Todas\nIdentificador do Lote: LOT-0060\nPaís: Portugal\nNUT III: PT150\nLocalidade: Faro\nDistrito: Faro\nConcelho: Faro\nFreguesia: Todas\nIdentificador do Lote: LOT-0061\nPaís: Portugal\nNUT III: PT150\nLocalidade: Faro\nDistrito: Faro\nConcelho: Faro\nFreguesia: Todas\nIdentificador do Lote: LOT-0062\nPaís: Portugal\nNUT III: PT150\nLocalidade: Faro\nDistrito: Faro\nConcelho: Faro\nFreguesia: Todas\nIdentificador do Lote: LOT-0063\nPaís: Portugal\nNUT III: PT150\nLocalidade: Faro\nDistrito: Faro\nConcelho: Faro\nFreguesia: Todas\nIdentificador do Lote: LOT-0064\nPaís: Portugal\nNUT III: PT150\nLocalidade: Faro\nDistrito: Faro\nConcelho: Faro\nFreguesia: Todas\nIdentificador do Lote: LOT-0065\nPaís: Portugal\nNUT III: PT150\nLocalidade: Faro\nDistrito: Faro\nConcelho: Faro\nFreguesia: Todas\nIdentificador do Lote: LOT-0066\nPaís: Portugal\nNUT III: PT150\nLocalidade: Faro\nDistrito: Faro\nConcelho: Faro\nFreguesia: Todas\nIdentificador do Lote: LOT-0067\nPaís: Portugal\nNUT III: PT150\nLocalidade: Faro\nDistrito: Faro\nConcelho: Faro\nFreguesia: Todas\nIdentificador do Lote: LOT-0068\nPaís: Portugal\nNUT III: PT150\nLocalidade: Faro\nDistrito: Faro\nConcelho: Faro\nFreguesia: Todas\nIdentificador do Lote: LOT-0069\nPaís: Portugal\nNUT III: PT150\nLocalidade: Faro\nDistrito: Faro\nConcelho: Faro\nFreguesia: Todas\nIdentificador do Lote: LOT-0070\nPaís: Portugal\nNUT III: PT150\nLocalidade: Faro\nDistrito: Faro\nConcelho: Faro\nFreguesia: Todas\nIdentificador do Lote: LOT-0071\nPaís: Portugal\nNUT III: PT150\nLocalidade: Faro\nDistrito: Faro\nConcelho: Faro\nFreguesia: Todas\nIdentificador do Lote: LOT-0072\nPaís: Portugal\nNUT III: PT150\nLocalidade: Faro\nDistrito: Faro\nConcelho: Faro\nFreguesia: Todas\nIdentificador do Lote: LOT-0073\nPaís: Portugal\nNUT III: PT150\nLocalidade: Faro\nDistrito: Faro\nConcelho: Faro\nFreguesia: Todas\nIdentificador do Lote: LOT-0074\nPaís: Portugal\nNUT III: PT150\nLocalidade: Faro\nDistrito: Faro\nConcelho: Faro\nFreguesia: Todas\nIdentificador do Lote: LOT-0075\nPaís: Portugal\nNUT III: PT150\nLocalidade: Faro\nDistrito: Faro\nConcelho: Faro\nFreguesia: Todas\nIdentificador do Lote: LOT-0076\nPaís: Portugal\nNUT III: PT150\nLocalidade: Faro\nDistrito: Faro\nConcelho: Faro\nFreguesia: Todas\nIdentificador do Lote: LOT-0077\nPaís: Portugal\nNUT III: PT150\nLocalidade: Faro\nDistrito: Faro\nConcelho: Faro\nFreguesia: Todas\nIdentificador do Lote: LOT-0078\nPaís: Portugal\nNUT III: PT150\nLocalidade: Faro\nDistrito: Faro\nConcelho: Faro\nFreguesia: Todas\nIdentificador do Lote: LOT-0079\nPaís: Portugal\nNUT III: PT150\nLocalidade: Faro\nDistrito: Faro\nConcelho: Faro\nFreguesia: Todas\nIdentificador do Lote: LOT-0080\nPaís: Portugal\nNUT III: PT150\nLocalidade: Faro\nDistrito: Faro\nConcelho: Faro\nFreguesia: Todas\nIdentificador do Lote: LOT-0081\nPaís: Portugal\nNUT III: PT150\nLocalidade: Faro\nDistrito: Faro\nConcelho: Faro\nFreguesia: Todas\nIdentificador do Lote: LOT-0082\nPaís: Portugal\nNUT III: PT150\nLocalidade: Faro\nDistrito: Faro\nConcelho: Faro\nFreguesia: Todas\nIdentificador do Lote: LOT-0083\nPaís: Portugal\nNUT III: PT150\nLocalidade: Faro\nDistrito: Faro\nConcelho: Faro\nFreguesia: Todas\nIdentificador do Lote: LOT-0084\nPaís: Portugal\nNUT III: PT150\nLocalidade: Faro\nDistrito: Faro\nConcelho: Faro\nFreguesia: Todas\nIdentificador do Lote: LOT-0085\nPaís: Portugal\nNUT III: PT150\nLocalidade: Faro\nDistrito: Faro\nConcelho: Faro\nFreguesia: Todas\nIdentificador do Lote: LOT-0086\nPaís: Portugal\nNUT III: PT150\nLocalidade: Faro\nDistrito: Faro\nConcelho: Faro\nFreguesia: Todas\nIdentificador do Lote: LOT-0087\nPaís: Portugal\nNUT III: PT150\nLocalidade: Faro\nDistrito: Faro\nConcelho: Faro\nFreguesia: Todas\nIdentificador do Lote: LOT-0088\nPaís: Portugal\nNUT III: PT150\nLocalidade: Faro\nDistrito: Faro\nConcelho: Faro\nFreguesia: Todas\nIdentificador do Lote: LOT-0089\nPaís: Portugal\nNUT III: PT150\nLocalidade: Faro\nDistrito: Faro\nConcelho: Faro\nFreguesia: Todas\nIdentificador do Lote: LOT-0090\nPaís: Portugal\nNUT III: PT150\nLocalidade: Faro\nDistrito: Faro\nConcelho: Faro\nFreguesia: Todas\nIdentificador do Lote: LOT-0091\nPaís: Portugal\nNUT III: PT150\nLocalidade: Faro\nDistrito: Faro\nConcelho: Faro\nFreguesia: Todas\nIdentificador do Lote: LOT-0092\nPaís: Portugal\nNUT III: PT150\nLocalidade: Faro\nDistrito: Faro\nConcelho: Faro\nFreguesia: Todas\nIdentificador do Lote: LOT-0093\nPaís: Portugal\nNUT III: PT150\nLocalidade: Faro\nDistrito: Faro\nConcelho: Faro\nFreguesia: Todas\nIdentificador do Lote: LOT-0094\nPaís: Portugal\nNUT III: PT150\nLocalidade: Faro\nDistrito: Faro\nConcelho: Faro\nFreguesia: Todas\nIdentificador do Lote: LOT-0095\nPaís: Portugal\nNUT III: PT150\nLocalidade: Faro\nDistrito: Faro\nConcelho: Faro\nFreguesia: Todas\nIdentificador do Lote: LOT-0096\nPaís: Portugal\nNUT III: PT150\nLocalidade: Faro\nDistrito: Faro\nConcelho: Faro\nFreguesia: Todas\nIdentificador do Lote: LOT-0097\nPaís: Portugal\nNUT III: PT150\nLocalidade: Faro\nDistrito: Faro\nConcelho: Faro\nFreguesia: Todas\nIdentificador do Lote: LOT-0098\nPaís: Portugal\nNUT III: PT150\nLocalidade: Faro\nDistrito: Faro\nConcelho: Faro\nFreguesia: Todas\nIdentificador do Lote: LOT-0099\nPaís: Portugal\nNUT III: PT150\nLocalidade: Faro\nDistrito: Faro\nConcelho: Faro\nFreguesia: Todas\nIdentificador do Lote: LOT-0100\nPaís: Portugal\nNUT III: PT150\nLocalidade: Faro\nDistrito: Faro\nConcelho: Faro\nFreguesia: Todas\nIdentificador do Lote: LOT-0101\nPaís: Portugal\nNUT III: PT150\nLocalidade: Faro\nDistrito: Faro\nConcelho: Faro\nFreguesia: Todas\nIdentificador do Lote: LOT-0102\nPaís: Portugal\nNUT III: PT150\nLocalidade: Faro\nDistrito: Faro\nConcelho: Faro\nFreguesia: Todas\nIdentificador do Lote: LOT-0103\nPaís: Portugal\nNUT III: PT150\nLocalidade: Faro\nDistrito: Faro\nConcelho: Faro\nFreguesia: Todas\nIdentificador do Lote: LOT-0104\nPaís: Portugal\nNUT III: PT150\nLocalidade: Faro\nDistrito: Faro\nConcelho: Faro\nFreguesia: Todas\nIdentificador do Lote: LOT-0105\nPaís: Portugal\nNUT III: PT150\nLocalidade: Faro\nDistrito: Faro\nConcelho: Faro\nFreguesia: Todas\nIdentificador do Lote: LOT-0106\nPaís: Portugal\nNUT III: PT150\nLocalidade: Faro\nDistrito: Faro\nConcelho: Faro\nFreguesia: Todas\nIdentificador do Lote: LOT-0107\nPaís: Portugal\nNUT III: PT150\nLocalidade: Faro\nDistrito: Faro\nConcelho: Faro\nFreguesia: Todas\nIdentificador do Lote: LOT-0108\nPaís: Portugal\nNUT III: PT150\nLocalidade: Faro\nDistrito: Faro\nConcelho: Faro\nFreguesia: Todas\nIdentificador do Lote: LOT-0109\nPaís: Portugal\nNUT III: PT150\nLocalidade: Faro\nDistrito: Faro\nConcelho: Faro\nFreguesia: Todas\n\n10 - PRAZO DE EXECUÇÃO DO CONTRATO\nIdentificador do Lote: LOT-0001\nPrazo de execução do contrato: 1 ANOS\nPrevisão de renovações: Não\nIdentificador do Lote: LOT-0002\nPrazo de execução do contrato: 1 ANOS\nPrevisão de renovações: Não\nIdentificador do Lote: LOT-0003\nPrazo de execução do contrato: 1 ANOS\nPrevisão de renovações: Não\nIdentificador do Lote: LOT-0004\nPrazo de execução do contrato: 1 ANOS\nPrevisão de renovações: Não\nIdentificador do Lote: LOT-0005\nPrazo de execução do contrato: 1 ANOS\nPrevisão de renovações: Não\nIdentificador do Lote: LOT-0006\nPrazo de execução do contrato: 1 ANOS\nPrevisão de renovações: Não\nIdentificador do Lote: LOT-0007\nPrazo de execução do contrato: 1 ANOS\nPrevisão de renovações: Não\nIdentificador do Lote: LOT-0008\nPrazo de execução do contrato: 1 ANOS\nPrevisão de renovações: Não\nIdentificador do Lote: LOT-0009\nPrazo de execução do contrato: 1 ANOS\nPrevisão de renovações: Não\nIdentificador do Lote: LOT-0010\nPrazo de execução do contrato: 1 ANOS\nPrevisão de renovações: Não\nIdentificador do Lote: LOT-0011\nPrazo de execução do contrato: 1 ANOS\nPrevisão de renovações: Não\nIdentificador do Lote: LOT-0012\nPrazo de execução do contrato: 1 ANOS\nPrevisão de renovações: Não\nIdentificador do Lote: LOT-0013\nPrazo de execução do contrato: 1 ANOS\nPrevisão de renovações: Não\nIdentificador do Lote: LOT-0014\nPrazo de execução do contrato: 1 ANOS\nPrevisão de renovações: Não\nIdentificador do Lote: LOT-0015\nPrazo de execução do contrato: 1 ANOS\nPrevisão de renovações: Não\nIdentificador do Lote: LOT-0016\nPrazo de execução do contrato: 1 ANOS\nPrevisão de renovações: Não\nIdentificador do Lote: LOT-0017\nPrazo de execução do contrato: 1 ANOS\nPrevisão de renovações: Não\nIdentificador do Lote: LOT-0018\nPrazo de execução do contrato: 1 ANOS\nPrevisão de renovações: Não\nIdentificador do Lote: LOT-0019\nPrazo de execução do contrato: 1 ANOS\nPrevisão de renovações: Não\nIdentificador do Lote: LOT-0020\nPrazo de execução do contrato: 1 ANOS\nPrevisão de renovações: Não\nIdentificador do Lote: LOT-0021\nPrazo de execução do contrato: 1 ANOS\nPrevisão de renovações: Não\nIdentificador do Lote: LOT-0022\nPrazo de execução do contrato: 1 ANOS\nPrevisão de renovações: Não\nIdentificador do Lote: LOT-0023\nPrazo de execução do contrato: 1 ANOS\nPrevisão de renovações: Não\nIdentificador do Lote: LOT-0024\nPrazo de execução do contrato: 1 ANOS\nPrevisão de renovações: Não\nIdentificador do Lote: LOT-0025\nPrazo de execução do contrato: 1 ANOS\nPrevisão de renovações: Não\nIdentificador do Lote: LOT-0026\nPrazo de execução do contrato: 1 ANOS\nPrevisão de renovações: Não\nIdentificador do Lote: LOT-0027\nPrazo de execução do contrato: 1 ANOS\nPrevisão de renovações: Não\nIdentificador do Lote: LOT-0028\nPrazo de execução do contrato: 1 ANOS\nPrevisão de renovações: Não\nIdentificador do Lote: LOT-0029\nPrazo de execução do contrato: 1 ANOS\nPrevisão de renovações: Não\nIdentificador do Lote: LOT-0030\nPrazo de execução do contrato: 1 ANOS\nPrevisão de renovações: Não\nIdentificador do Lote: LOT-0031\nPrazo de execução do contrato: 1 ANOS\nPrevisão de renovações: Não\nIdentificador do Lote: LOT-0032\nPrazo de execução do contrato: 1 ANOS\nPrevisão de renovações: Não\nIdentificador do Lote: LOT-0033\nPrazo de execução do contrato: 1 ANOS\nPrevisão de renovações: Não\nIdentificador do Lote: LOT-0034\nPrazo de execução do contrato: 1 ANOS\nPrevisão de renovações: Não\nIdentificador do Lote: LOT-0035\nPrazo de execução do contrato: 1 ANOS\nPrevisão de renovações: Não\nIdentificador do Lote: LOT-0036\nPrazo de execução do contrato: 1 ANOS\nPrevisão de renovações: Não\nIdentificador do Lote: LOT-0037\nPrazo de execução do contrato: 1 ANOS\nPrevisão de renovações: Não\nIdentificador do Lote: LOT-0038\nPrazo de execução do contrato: 1 ANOS\nPrevisão de renovações: Não\nIdentificador do Lote: LOT-0039\nPrazo de execução do contrato: 1 ANOS\nPrevisão de renovações: Não\nIdentificador do Lote: LOT-0040\nPrazo de execução do contrato: 1 ANOS\nPrevisão de renovações: Não\nIdentificador do Lote: LOT-0041\nPrazo de execução do contrato: 1 ANOS\nPrevisão de renovações: Não\nIdentificador do Lote: LOT-0042\nPrazo de execução do contrato: 1 ANOS\nPrevisão de renovações: Não\nIdentificador do Lote: LOT-0043\nPrazo de execução do contrato: 1 ANOS\nPrevisão de renovações: Não\nIdentificador do Lote: LOT-0044\nPrazo de execução do contrato: 1 ANOS\nPrevisão de renovações: Não\nIdentificador do Lote: LOT-0045\nPrazo de execução do contrato: 1 ANOS\nPrevisão de renovações: Não\nIdentificador do Lote: LOT-0046\nPrazo de execução do contrato: 1 ANOS\nPrevisão de renovações: Não\nIdentificador do Lote: LOT-0047\nPrazo de execução do contrato: 1 ANOS\nPrevisão de renovações: Não\nIdentificador do Lote: LOT-0048\nPrazo de execução do contrato: 1 ANOS\nPrevisão de renovações: Não\nIdentificador do Lote: LOT-0049\nPrazo de execução do contrato: 1 ANOS\nPrevisão de renovações: Não\nIdentificador do Lote: LOT-0050\nPrazo de execução do contrato: 1 ANOS\nPrevisão de renovações: Não\nIdentificador do Lote: LOT-0051\nPrazo de execução do contrato: 1 ANOS\nPrevisão de renovações: Não\nIdentificador do Lote: LOT-0052\nPrazo de execução do contrato: 1 ANOS\nPrevisão de renovações: Não\nIdentificador do Lote: LOT-0053\nPrazo de execução do contrato: 1 ANOS\nPrevisão de renovações: Não\nIdentificador do Lote: LOT-0054\nPrazo de execução do contrato: 1 ANOS\nPrevisão de renovações: Não\nIdentificador do Lote: LOT-0055\nPrazo de execução do contrato: 1 ANOS\nPrevisão de renovações: Não\nIdentificador do Lote: LOT-0056\nPrazo de execução do contrato: 1 ANOS\nPrevisão de renovações: Não\nIdentificador do Lote: LOT-0057\nPrazo de execução do contrato: 1 ANOS\nPrevisão de renovações: Não\nIdentificador do Lote: LOT-0058\nPrazo de execução do contrato: 1 ANOS\nPrevisão de renovações: Não\nIdentificador do Lote: LOT-0059\nPrazo de execução do contrato: 1 ANOS\nPrevisão de renovações: Não\nIdentificador do Lote: LOT-0060\nPrazo de execução do contrato: 1 ANOS\nPrevisão de renovações: Não\nIdentificador do Lote: LOT-0061\nPrazo de execução do contrato: 1 ANOS\nPrevisão de renovações: Não\nIdentificador do Lote: LOT-0062\nPrazo de execução do contrato: 1 ANOS\nPrevisão de renovações: Não\nIdentificador do Lote: LOT-0063\nPrazo de execução do contrato: 1 ANOS\nPrevisão de renovações: Não\nIdentificador do Lote: LOT-0064\nPrazo de execução do contrato: 1 ANOS\nPrevisão de renovações: Não\nIdentificador do Lote: LOT-0065\nPrazo de execução do contrato: 1 ANOS\nPrevisão de renovações: Não\nIdentificador do Lote: LOT-0066\nPrazo de execução do contrato: 1 ANOS\nPrevisão de renovações: Não\nIdentificador do Lote: LOT-0067\nPrazo de execução do contrato: 1 ANOS\nPrevisão de renovações: Não\nIdentificador do Lote: LOT-0068\nPrazo de execução do contrato: 1 ANOS\nPrevisão de renovações: Não\nIdentificador do Lote: LOT-0069\nPrazo de execução do contrato: 1 ANOS\nPrevisão de renovações: Não\nIdentificador do Lote: LOT-0070\nPrazo de execução do contrato: 1 ANOS\nPrevisão de renovações: Não\nIdentificador do Lote: LOT-0071\nPrazo de execução do contrato: 1 ANOS\nPrevisão de renovações: Não\nIdentificador do Lote: LOT-0072\nPrazo de execução do contrato: 1 ANOS\nPrevisão de renovações: Não\nIdentificador do Lote: LOT-0073\nPrazo de execução do contrato: 1 ANOS\nPrevisão de renovações: Não\nIdentificador do Lote: LOT-0074\nPrazo de execução do contrato: 1 ANOS\nPrevisão de renovações: Não\nIdentificador do Lote: LOT-0075\nPrazo de execução do contrato: 1 ANOS\nPrevisão de renovações: Não\nIdentificador do Lote: LOT-0076\nPrazo de execução do contrato: 1 ANOS\nPrevisão de renovações: Não\nIdentificador do Lote: LOT-0077\nPrazo de execução do contrato: 1 ANOS\nPrevisão de renovações: Não\nIdentificador do Lote: LOT-0078\nPrazo de execução do contrato: 1 ANOS\nPrevisão de renovações: Não\nIdentificador do Lote: LOT-0079\nPrazo de execução do contrato: 1 ANOS\nPrevisão de renovações: Não\nIdentificador do Lote: LOT-0080\nPrazo de execução do contrato: 1 ANOS\nPrevisão de renovações: Não\nIdentificador do Lote: LOT-0081\nPrazo de execução do contrato: 1 ANOS\nPrevisão de renovações: Não\nIdentificador do Lote: LOT-0082\nPrazo de execução do contrato: 1 ANOS\nPrevisão de renovações: Não\nIdentificador do Lote: LOT-0083\nPrazo de execução do contrato: 1 ANOS\nPrevisão de renovações: Não\nIdentificador do Lote: LOT-0084\nPrazo de execução do contrato: 1 ANOS\nPrevisão de renovações: Não\nIdentificador do Lote: LOT-0085\nPrazo de execução do contrato: 1 ANOS\nPrevisão de renovações: Não\nIdentificador do Lote: LOT-0086\nPrazo de execução do contrato: 1 ANOS\nPrevisão de renovações: Não\nIdentificador do Lote: LOT-0087\nPrazo de execução do contrato: 1 ANOS\nPrevisão de renovações: Não\nIdentificador do Lote: LOT-0088\nPrazo de execução do contrato: 1 ANOS\nPrevisão de renovações: Não\nIdentificador do Lote: LOT-0089\nPrazo de execução do contrato: 1 ANOS\nPrevisão de renovações: Não\nIdentificador do Lote: LOT-0090\nPrazo de execução do contrato: 1 ANOS\nPrevisão de renovações: Não\nIdentificador do Lote: LOT-0091\nPrazo de execução do contrato: 1 ANOS\nPrevisão de renovações: Não\nIdentificador do Lote: LOT-0092\nPrazo de execução do contrato: 1 ANOS\nPrevisão de renovações: Não\nIdentificador do Lote: LOT-0093\nPrazo de execução do contrato: 1 ANOS\nPrevisão de renovações: Não\nIdentificador do Lote: LOT-0094\nPrazo de execução do contrato: 1 ANOS\nPrevisão de renovações: Não\nIdentificador do Lote: LOT-0095\nPrazo de execução do contrato: 1 ANOS\nPrevisão de renovações: Não\nIdentificador do Lote: LOT-0096\nPrazo de execução do contrato: 1 ANOS\nPrevisão de renovações: Não\nIdentificador do Lote: LOT-0097\nPrazo de execução do contrato: 1 ANOS\nPrevisão de renovações: Não\nIdentificador do Lote: LOT-0098\nPrazo de execução do contrato: 1 ANOS\nPrevisão de renovações: Não\nIdentificador do Lote: LOT-0099\nPrazo de execução do contrato: 1 ANOS\nPrevisão de renovações: Não\nIdentificador do Lote: LOT-0100\nPrazo de execução do contrato: 1 ANOS\nPrevisão de renovações: Não\nIdentificador do Lote: LOT-0101\nPrazo de execução do contrato: 1 ANOS\nPrevisão de renovações: Não\nIdentificador do Lote: LOT-0102\nPrazo de execução do contrato: 1 ANOS\nPrevisão de renovações: Não\nIdentificador do Lote: LOT-0103\nPrazo de execução do contrato: 1 ANOS\nPrevisão de renovações: Não\nIdentificador do Lote: LOT-0104\nPrazo de execução do contrato: 1 ANOS\nPrevisão de renovações: Não\nIdentificador do Lote: LOT-0105\nPrazo de execução do contrato: 1 ANOS\nPrevisão de renovações: Não\nIdentificador do Lote: LOT-0106\nPrazo de execução do contrato: 1 ANOS\nPrevisão de renovações: Não\nIdentificador do Lote: LOT-0107\nPrazo de execução do contrato: 1 ANOS\nPrevisão de renovações: Não\nIdentificador do Lote: LOT-0108\nPrazo de execução do contrato: 1 ANOS\nPrevisão de renovações: Não\nIdentificador do Lote: LOT-0109\nPrazo de execução do contrato: 1 ANOS\nPrevisão de renovações: Não\n\n11 - FUNDOS EU\nIdentificador do Lote: LOT-0001; LOT-0002; LOT-0003; LOT-0004; LOT-0005; LOT-0006; LOT-0007; LOT-0008; LOT-0009; LOT-0010; LOT-0011; LOT-0012; LOT-0013; LOT-0014; LOT-0015; LOT-0016; LOT-0017; LOT-0018; LOT-0019; LOT-0020; LOT-0021; LOT-0022; LOT-0023; LOT-0024; LOT-0025; LOT-0026; LOT-0027; LOT-0028; LOT-0029; LOT-0030; LOT-0031; LOT-0032; LOT-0033; LOT-0034; LOT-0035; LOT-0036; LOT-0037; LOT-0038; LOT-0039; LOT-0040; LOT-0041; LOT-0042; LOT-0043; LOT-0044; LOT-0045; LOT-0046; LOT-0047; LOT-0048; LOT-0049; LOT-0050; LOT-0051; LOT-0052; LOT-0053; LOT-0054; LOT-0055; LOT-0056; LOT-0057; LOT-0058; LOT-0059; LOT-0060; LOT-0061; LOT-0062; LOT-0063; LOT-0064; LOT-0065; LOT-0066; LOT-0067; LOT-0068; LOT-0069; LOT-0070; LOT-0071; LOT-0072; LOT-0073; LOT-0074; LOT-0075; LOT-0076; LOT-0077; LOT-0078; LOT-0079; LOT-0080; LOT-0081; LOT-0082; LOT-0083; LOT-0084; LOT-0085; LOT-0086; LOT-0087; LOT-0088; LOT-0089; LOT-0090; LOT-0091; LOT-0092; LOT-0093; LOT-0094; LOT-0095; LOT-0096; LOT-0097; LOT-0098; LOT-0099; LOT-0100; LOT-0101; LOT-0102; LOT-0103; LOT-0104; LOT-0105; LOT-0106; LOT-0107; LOT-0108; LOT-0109\nTêm fundos EU? Não\n\n12 - DOCUMENTOS DE HABILITAÇÃO\nHabilitação para o exercício da atividade profissional: Não\n\n13 - CONDIÇÕES DE APRESENTAÇÃO\nPlataforma eletrónica utilizada pela entidade adjudicante: ANOGOV\nURL para Apresentação: https://www.anogov.com/me-sasualgarve/faces/\nAdmissibilidade da apresentação de propostas variantes: Não autorizado\nPrazo para apresentação das propostas: 08-10-2025 23:59\nPrazo durante o qual os concorrentes são obrigados a manter as respetivas propostas: 66 dias a contar do termo do prazo para a apresentação das propostas\nApresentação de Catálogo Eletrónico: Permitido\nIndicação de Subcontratação na Proposta: Inexistência de indicação de subcontratação\n\n14 - PRESTAÇÃO DE CAUÇÃO\nPrestação de caução: Não\n\n15 - FORNECIMENTO DAS PEÇAS DO CONCURSO, APRESENTAÇÃO DE PEDIDOS DE PARTICIPAÇÃO E APRESENTAÇÃO DAS PROPOSTAS\nLink para acesso às peças do concurso (URL): https://www.anogov.com/me-sasualgarve/faces/app/acessoDocs.jsp?codigoAcesso=jei9iQob40I68vECrwY7cRVorQK83cwiUNv8fLapZIVQXnPhre\n\n20 - OUTROS REQUISITOS\nIdentificador do Lote: LOT-0001; LOT-0002; LOT-0003; LOT-0004; LOT-0005; LOT-0006; LOT-0007; LOT-0008; LOT-0009; LOT-0010; LOT-0011; LOT-0012; LOT-0013; LOT-0014; LOT-0015; LOT-0016; LOT-0017; LOT-0018; LOT-0019; LOT-0020; LOT-0021; LOT-0022; LOT-0023; LOT-0024; LOT-0025; LOT-0026; LOT-0027; LOT-0028; LOT-0029; LOT-0030; LOT-0031; LOT-0032; LOT-0033; LOT-0034; LOT-0035; LOT-0036; LOT-0037; LOT-0038; LOT-0039; LOT-0040; LOT-0041; LOT-0042; LOT-0043; LOT-0044; LOT-0045; LOT-0046; LOT-0047; LOT-0048; LOT-0049; LOT-0050; LOT-0051; LOT-0052; LOT-0053; LOT-0054; LOT-0055; LOT-0056; LOT-0057; LOT-0058; LOT-0059; LOT-0060; LOT-0061; LOT-0062; LOT-0063; LOT-0064; LOT-0065; LOT-0066; LOT-0067; LOT-0068; LOT-0069; LOT-0070; LOT-0071; LOT-0072; LOT-0073; LOT-0074; LOT-0075; LOT-0076; LOT-0077; LOT-0078; LOT-0079; LOT-0080; LOT-0081; LOT-0082; LOT-0083; LOT-0084; LOT-0085; LOT-0086; LOT-0087; LOT-0088; LOT-0089; LOT-0090; LOT-0091; LOT-0092; LOT-0093; LOT-0094; LOT-0095; LOT-0096; LOT-0097; LOT-0098; LOT-0099; LOT-0100; LOT-0101; LOT-0102; LOT-0103; LOT-0104; LOT-0105; LOT-0106; LOT-0107; LOT-0108; LOT-0109\nInformação sobre contratos reservados. Aplica-se a contratos reservados (54º-A)? Não\n\n21 - CRITÉRIO DE ADJUDICAÇÃO\nO Critério de adjudicação é diferenciado por lote? Não\nMultifator: Sim\nFator: \nNome: Preço\nPonderação: 90%\nSubfatores: Não\nFator: \nNome: Outros\nOutro Nome: Origem e Impacto Ambiental: A produção tenha todas as suas fases no Algarve\nPonderação: 10%\nSubfatores: Não\n\n24 - CONDIÇÕES DO CONTRATO\nIdentificador do Lote: LOT-0001; LOT-0002; LOT-0003; LOT-0004; LOT-0005; LOT-0006; LOT-0007; LOT-0008; LOT-0009; LOT-0010; LOT-0011; LOT-0012; LOT-0013; LOT-0014; LOT-0015; LOT-0016; LOT-0017; LOT-0018; LOT-0019; LOT-0020; LOT-0021; LOT-0022; LOT-0023; LOT-0024; LOT-0025; LOT-0026; LOT-0027; LOT-0028; LOT-0029; LOT-0030; LOT-0031; LOT-0032; LOT-0033; LOT-0034; LOT-0035; LOT-0036; LOT-0037; LOT-0038; LOT-0039; LOT-0040; LOT-0041; LOT-0042; LOT-0043; LOT-0044; LOT-0045; LOT-0046; LOT-0047; LOT-0048; LOT-0049; LOT-0050; LOT-0051; LOT-0052; LOT-0053; LOT-0054; LOT-0055; LOT-0056; LOT-0057; LOT-0058; LOT-0059; LOT-0060; LOT-0061; LOT-0062; LOT-0063; LOT-0064; LOT-0065; LOT-0066; LOT-0067; LOT-0068; LOT-0069; LOT-0070; LOT-0071; LOT-0072; LOT-0073; LOT-0074; LOT-0075; LOT-0076; LOT-0077; LOT-0078; LOT-0079; LOT-0080; LOT-0081; LOT-0082; LOT-0083; LOT-0084; LOT-0085; LOT-0086; LOT-0087; LOT-0088; LOT-0089; LOT-0090; LOT-0091; LOT-0092; LOT-0093; LOT-0094; LOT-0095; LOT-0096; LOT-0097; LOT-0098; LOT-0099; LOT-0100; LOT-0101; LOT-0102; LOT-0103; LOT-0104; LOT-0105; LOT-0106; LOT-0107; LOT-0108; LOT-0109\nFaturação Eletrónica: Permitido\nObrigação de Subcontratação:\nCódigo da Obrigação de Subcontratação: Não é aplicável nenhuma obrigação de subcontratação.\n\n25 - COMPRA PÚBLICA ESTRATÉGICA\nCompra Pública Estratégica: Redução dos impactos ambientais\nDescrição do Processo de Adjudicação Estratégico: Origem e Impacto Ambiental: A produção tenha todas as suas fases no Algarve\nCritérios de contratos Públicos Ecológicos: Critérios de contratação pública ecológica da UE\nCategorias da estratégia nacional: Produtos alimentares, serviços de assistência de restauração (catering) e máquinas de distribuição automática\nContratos Públicos Ecológicos: Outros\nDiretiva Veículos Não Poluentes: Não\nCritério de Acessibilidade: Os critérios de acessibilidade para as pessoas com deficiência não estão incluídos porque o contrato não se destina a pessoas singulares\n\n26 - INFORMAÇÕES ADICIONAIS\nIdentificador do Lote: LOT-0001\nContrato adequado para PME: Não\nCobertura ACP (Acordo dos Contratos Públicos da Organização Mundial do Comércio): Não\nIdentificador do Lote: LOT-0002\nContrato adequado para PME: Não\nCobertura ACP (Acordo dos Contratos Públicos da Organização Mundial do Comércio): Não\nIdentificador do Lote: LOT-0003\nContrato adequado para PME: Não\nCobertura ACP (Acordo dos Contratos Públicos da Organização Mundial do Comércio): Não\nIdentificador do Lote: LOT-0004\nContrato adequado para PME: Não\nCobertura ACP (Acordo dos Contratos Públicos da Organização Mundial do Comércio): Não\nIdentificador do Lote: LOT-0005\nContrato adequado para PME: Não\nCobertura ACP (Acordo dos Contratos Públicos da Organização Mundial do Comércio): Não\nIdentificador do Lote: LOT-0006\nContrato adequado para PME: Não\nCobertura ACP (Acordo dos Contratos Públicos da Organização Mundial do Comércio): Não\nIdentificador do Lote: LOT-0007\nContrato adequado para PME: Não\nCobertura ACP (Acordo dos Contratos Públicos da Organização Mundial do Comércio): Não\nIdentificador do Lote: LOT-0008\nContrato adequado para PME: Não\nCobertura ACP (Acordo dos Contratos Públicos da Organização Mundial do Comércio): Não\nIdentificador do Lote: LOT-0009\nContrato adequado para PME: Não\nCobertura ACP (Acordo dos Contratos Públicos da Organização Mundial do Comércio): Não\nIdentificador do Lote: LOT-0010\nContrato adequado para PME: Não\nCobertura ACP (Acordo dos Contratos Públicos da Organização Mundial do Comércio): Não\nIdentificador do Lote: LOT-0011\nContrato adequado para PME: Não\nCobertura ACP (Acordo dos Contratos Públicos da Organização Mundial do Comércio): Não\nIdentificador do Lote: LOT-0012\nContrato adequado para PME: Não\nCobertura ACP (Acordo dos Contratos Públicos da Organização Mundial do Comércio): Não\nIdentificador do Lote: LOT-0013\nContrato adequado para PME: Não\nCobertura ACP (Acordo dos Contratos Públicos da Organização Mundial do Comércio): Não\nIdentificador do Lote: LOT-0014\nContrato adequado para PME: Não\nCobertura ACP (Acordo dos Contratos Públicos da Organização Mundial do Comércio): Não\nIdentificador do Lote: LOT-0015\nContrato adequado para PME: Não\nCobertura ACP (Acordo dos Contratos Públicos da Organização Mundial do Comércio): Não\nIdentificador do Lote: LOT-0016\nContrato adequado para PME: Não\nCobertura ACP (Acordo dos Contratos Públicos da Organização Mundial do Comércio): Não\nIdentificador do Lote: LOT-0017\nContrato adequado para PME: Não\nCobertura ACP (Acordo dos Contratos Públicos da Organização Mundial do Comércio): Não\nIdentificador do Lote: LOT-0018\nContrato adequado para PME: Não\nCobertura ACP (Acordo dos Contratos Públicos da Organização Mundial do Comércio): Não\nIdentificador do Lote: LOT-0019\nContrato adequado para PME: Não\nCobertura ACP (Acordo dos Contratos Públicos da Organização Mundial do Comércio): Não\nIdentificador do Lote: LOT-0020\nContrato adequado para PME: Não\nCobertura ACP (Acordo dos Contratos Públicos da Organização Mundial do Comércio): Não\nIdentificador do Lote: LOT-0021\nContrato adequado para PME: Não\nCobertura ACP (Acordo dos Contratos Públicos da Organização Mundial do Comércio): Não\nIdentificador do Lote: LOT-0022\nContrato adequado para PME: Não\nCobertura ACP (Acordo dos Contratos Públicos da Organização Mundial do Comércio): Não\nIdentificador do Lote: LOT-0023\nContrato adequado para PME: Não\nCobertura ACP (Acordo dos Contratos Públicos da Organização Mundial do Comércio): Não\nIdentificador do Lote: LOT-0024\nContrato adequado para PME: Não\nCobertura ACP (Acordo dos Contratos Públicos da Organização Mundial do Comércio): Não\nIdentificador do Lote: LOT-0025\nContrato adequado para PME: Não\nCobertura ACP (Acordo dos Contratos Públicos da Organização Mundial do Comércio): Não\nIdentificador do Lote: LOT-0026\nContrato adequado para PME: Não\nCobertura ACP (Acordo dos Contratos Públicos da Organização Mundial do Comércio): Não\nIdentificador do Lote: LOT-0027\nContrato adequado para PME: Não\nCobertura ACP (Acordo dos Contratos Públicos da Organização Mundial do Comércio): Não\nIdentificador do Lote: LOT-0028\nContrato adequado para PME: Não\nCobertura ACP (Acordo dos Contratos Públicos da Organização Mundial do Comércio): Não\nIdentificador do Lote: LOT-0029\nContrato adequado para PME: Não\nCobertura ACP (Acordo dos Contratos Públicos da Organização Mundial do Comércio): Não\nIdentificador do Lote: LOT-0030\nContrato adequado para PME: Não\nCobertura ACP (Acordo dos Contratos Públicos da Organização Mundial do Comércio): Não\nIdentificador do Lote: LOT-0031\nContrato adequado para PME: Não\nCobertura ACP (Acordo dos Contratos Públicos da Organização Mundial do Comércio): Não\nIdentificador do Lote: LOT-0032\nContrato adequado para PME: Não\nCobertura ACP (Acordo dos Contratos Públicos da Organização Mundial do Comércio): Não\nIdentificador do Lote: LOT-0033\nContrato adequado para PME: Não\nCobertura ACP (Acordo dos Contratos Públicos da Organização Mundial do Comércio): Não\nIdentificador do Lote: LOT-0034\nContrato adequado para PME: Não\nCobertura ACP (Acordo dos Contratos Públicos da Organização Mundial do Comércio): Não\nIdentificador do Lote: LOT-0035\nContrato adequado para PME: Não\nCobertura ACP (Acordo dos Contratos Públicos da Organização Mundial do Comércio): Não\nIdentificador do Lote: LOT-0036\nContrato adequado para PME: Não\nCobertura ACP (Acordo dos Contratos Públicos da Organização Mundial do Comércio): Não\nIdentificador do Lote: LOT-0037\nContrato adequado para PME: Não\nCobertura ACP (Acordo dos Contratos Públicos da Organização Mundial do Comércio): Não\nIdentificador do Lote: LOT-0038\nContrato adequado para PME: Não\nCobertura ACP (Acordo dos Contratos Públicos da Organização Mundial do Comércio): Não\nIdentificador do Lote: LOT-0039\nContrato adequado para PME: Não\nCobertura ACP (Acordo dos Contratos Públicos da Organização Mundial do Comércio): Não\nIdentificador do Lote: LOT-0040\nContrato adequado para PME: Não\nCobertura ACP (Acordo dos Contratos Públicos da Organização Mundial do Comércio): Não\nIdentificador do Lote: LOT-0041\nContrato adequado para PME: Não\nCobertura ACP (Acordo dos Contratos Públicos da Organização Mundial do Comércio): Não\nIdentificador do Lote: LOT-0042\nContrato adequado para PME: Não\nCobertura ACP (Acordo dos Contratos Públicos da Organização Mundial do Comércio): Não\nIdentificador do Lote: LOT-0043\nContrato adequado para PME: Não\nCobertura ACP (Acordo dos Contratos Públicos da Organização Mundial do Comércio): Não\nIdentificador do Lote: LOT-0044\nContrato adequado para PME: Não\nCobertura ACP (Acordo dos Contratos Públicos da Organização Mundial do Comércio): Não\nIdentificador do Lote: LOT-0045\nContrato adequado para PME: Não\nCobertura ACP (Acordo dos Contratos Públicos da Organização Mundial do Comércio): Não\nIdentificador do Lote: LOT-0046\nContrato adequado para PME: Não\nCobertura ACP (Acordo dos Contratos Públicos da Organização Mundial do Comércio): Não\nIdentificador do Lote: LOT-0047\nContrato adequado para PME: Não\nCobertura ACP (Acordo dos Contratos Públicos da Organização Mundial do Comércio): Não\nIdentificador do Lote: LOT-0048\nContrato adequado para PME: Não\nCobertura ACP (Acordo dos Contratos Públicos da Organização Mundial do Comércio): Não\nIdentificador do Lote: LOT-0049\nContrato adequado para PME: Não\nCobertura ACP (Acordo dos Contratos Públicos da Organização Mundial do Comércio): Não\nIdentificador do Lote: LOT-0050\nContrato adequado para PME: Não\nCobertura ACP (Acordo dos Contratos Públicos da Organização Mundial do Comércio): Não\nIdentificador do Lote: LOT-0051\nContrato adequado para PME: Não\nCobertura ACP (Acordo dos Contratos Públicos da Organização Mundial do Comércio): Não\nIdentificador do Lote: LOT-0052\nContrato adequado para PME: Não\nCobertura ACP (Acordo dos Contratos Públicos da Organização Mundial do Comércio): Não\nIdentificador do Lote: LOT-0053\nContrato adequado para PME: Não\nCobertura ACP (Acordo dos Contratos Públicos da Organização Mundial do Comércio): Não\nIdentificador do Lote: LOT-0054\nContrato adequado para PME: Não\nCobertura ACP (Acordo dos Contratos Públicos da Organização Mundial do Comércio): Não\nIdentificador do Lote: LOT-0055\nContrato adequado para PME: Não\nCobertura ACP (Acordo dos Contratos Públicos da Organização Mundial do Comércio): Não\nIdentificador do Lote: LOT-0056\nContrato adequado para PME: Não\nCobertura ACP (Acordo dos Contratos Públicos da Organização Mundial do Comércio): Não\nIdentificador do Lote: LOT-0057\nContrato adequado para PME: Não\nCobertura ACP (Acordo dos Contratos Públicos da Organização Mundial do Comércio): Não\nIdentificador do Lote: LOT-0058\nContrato adequado para PME: Não\nCobertura ACP (Acordo dos Contratos Públicos da Organização Mundial do Comércio): Não\nIdentificador do Lote: LOT-0059\nContrato adequado para PME: Não\nCobertura ACP (Acordo dos Contratos Públicos da Organização Mundial do Comércio): Não\nIdentificador do Lote: LOT-0060\nContrato adequado para PME: Não\nCobertura ACP (Acordo dos Contratos Públicos da Organização Mundial do Comércio): Não\nIdentificador do Lote: LOT-0061\nContrato adequado para PME: Não\nCobertura ACP (Acordo dos Contratos Públicos da Organização Mundial do Comércio): Não\nIdentificador do Lote: LOT-0062\nContrato adequado para PME: Não\nCobertura ACP (Acordo dos Contratos Públicos da Organização Mundial do Comércio): Não\nIdentificador do Lote: LOT-0063\nContrato adequado para PME: Não\nCobertura ACP (Acordo dos Contratos Públicos da Organização Mundial do Comércio): Não\nIdentificador do Lote: LOT-0064\nContrato adequado para PME: Não\nCobertura ACP (Acordo dos Contratos Públicos da Organização Mundial do Comércio): Não\nIdentificador do Lote: LOT-0065\nContrato adequado para PME: Não\nCobertura ACP (Acordo dos Contratos Públicos da Organização Mundial do Comércio): Não\nIdentificador do Lote: LOT-0066\nContrato adequado para PME: Não\nCobertura ACP (Acordo dos Contratos Públicos da Organização Mundial do Comércio): Não\nIdentificador do Lote: LOT-0067\nContrato adequado para PME: Não\nCobertura ACP (Acordo dos Contratos Públicos da Organização Mundial do Comércio): Não\nIdentificador do Lote: LOT-0068\nContrato adequado para PME: Não\nCobertura ACP (Acordo dos Contratos Públicos da Organização Mundial do Comércio): Não\nIdentificador do Lote: LOT-0069\nContrato adequado para PME: Não\nCobertura ACP (Acordo dos Contratos Públicos da Organização Mundial do Comércio): Não\nIdentificador do Lote: LOT-0070\nContrato adequado para PME: Não\nCobertura ACP (Acordo dos Contratos Públicos da Organização Mundial do Comércio): Não\nIdentificador do Lote: LOT-0071\nContrato adequado para PME: Não\nCobertura ACP (Acordo dos Contratos Públicos da Organização Mundial do Comércio): Não\nIdentificador do Lote: LOT-0072\nContrato adequado para PME: Não\nCobertura ACP (Acordo dos Contratos Públicos da Organização Mundial do Comércio): Não\nIdentificador do Lote: LOT-0073\nContrato adequado para PME: Não\nCobertura ACP (Acordo dos Contratos Públicos da Organização Mundial do Comércio): Não\nIdentificador do Lote: LOT-0074\nContrato adequado para PME: Não\nCobertura ACP (Acordo dos Contratos Públicos da Organização Mundial do Comércio): Não\nIdentificador do Lote: LOT-0075\nContrato adequado para PME: Não\nCobertura ACP (Acordo dos Contratos Públicos da Organização Mundial do Comércio): Não\nIdentificador do Lote: LOT-0076\nContrato adequado para PME: Não\nCobertura ACP (Acordo dos Contratos Públicos da Organização Mundial do Comércio): Não\nIdentificador do Lote: LOT-0077\nContrato adequado para PME: Não\nCobertura ACP (Acordo dos Contratos Públicos da Organização Mundial do Comércio): Não\nIdentificador do Lote: LOT-0078\nContrato adequado para PME: Não\nCobertura ACP (Acordo dos Contratos Públicos da Organização Mundial do Comércio): Não\nIdentificador do Lote: LOT-0079\nContrato adequado para PME: Não\nCobertura ACP (Acordo dos Contratos Públicos da Organização Mundial do Comércio): Não\nIdentificador do Lote: LOT-0080\nContrato adequado para PME: Não\nCobertura ACP (Acordo dos Contratos Públicos da Organização Mundial do Comércio): Não\nIdentificador do Lote: LOT-0081\nContrato adequado para PME: Não\nCobertura ACP (Acordo dos Contratos Públicos da Organização Mundial do Comércio): Não\nIdentificador do Lote: LOT-0082\nContrato adequado para PME: Não\nCobertura ACP (Acordo dos Contratos Públicos da Organização Mundial do Comércio): Não\nIdentificador do Lote: LOT-0083\nContrato adequado para PME: Não\nCobertura ACP (Acordo dos Contratos Públicos da Organização Mundial do Comércio): Não\nIdentificador do Lote: LOT-0084\nContrato adequado para PME: Não\nCobertura ACP (Acordo dos Contratos Públicos da Organização Mundial do Comércio): Não\nIdentificador do Lote: LOT-0085\nContrato adequado para PME: Não\nCobertura ACP (Acordo dos Contratos Públicos da Organização Mundial do Comércio): Não\nIdentificador do Lote: LOT-0086\nContrato adequado para PME: Não\nCobertura ACP (Acordo dos Contratos Públicos da Organização Mundial do Comércio): Não\nIdentificador do Lote: LOT-0087\nContrato adequado para PME: Não\nCobertura ACP (Acordo dos Contratos Públicos da Organização Mundial do Comércio): Não\nIdentificador do Lote: LOT-0088\nContrato adequado para PME: Não\nCobertura ACP (Acordo dos Contratos Públicos da Organização Mundial do Comércio): Não\nIdentificador do Lote: LOT-0089\nContrato adequado para PME: Não\nCobertura ACP (Acordo dos Contratos Públicos da Organização Mundial do Comércio): Não\nIdentificador do Lote: LOT-0090\nContrato adequado para PME: Não\nCobertura ACP (Acordo dos Contratos Públicos da Organização Mundial do Comércio): Não\nIdentificador do Lote: LOT-0091\nContrato adequado para PME: Não\nCobertura ACP (Acordo dos Contratos Públicos da Organização Mundial do Comércio): Não\nIdentificador do Lote: LOT-0092\nContrato adequado para PME: Não\nCobertura ACP (Acordo dos Contratos Públicos da Organização Mundial do Comércio): Não\nIdentificador do Lote: LOT-0093\nContrato adequado para PME: Não\nCobertura ACP (Acordo dos Contratos Públicos da Organização Mundial do Comércio): Não\nIdentificador do Lote: LOT-0094\nContrato adequado para PME: Não\nCobertura ACP (Acordo dos Contratos Públicos da Organização Mundial do Comércio): Não\nIdentificador do Lote: LOT-0095\nContrato adequado para PME: Não\nCobertura ACP (Acordo dos Contratos Públicos da Organização Mundial do Comércio): Não\nIdentificador do Lote: LOT-0096\nContrato adequado para PME: Não\nCobertura ACP (Acordo dos Contratos Públicos da Organização Mundial do Comércio): Não\nIdentificador do Lote: LOT-0097\nContrato adequado para PME: Não\nCobertura ACP (Acordo dos Contratos Públicos da Organização Mundial do Comércio): Não\nIdentificador do Lote: LOT-0098\nContrato adequado para PME: Não\nCobertura ACP (Acordo dos Contratos Públicos da Organização Mundial do Comércio): Não\nIdentificador do Lote: LOT-0099\nContrato adequado para PME: Não\nCobertura ACP (Acordo dos Contratos Públicos da Organização Mundial do Comércio): Não\nIdentificador do Lote: LOT-0100\nContrato adequado para PME: Não\nCobertura ACP (Acordo dos Contratos Públicos da Organização Mundial do Comércio): Não\nIdentificador do Lote: LOT-0101\nContrato adequado para PME: Não\nCobertura ACP (Acordo dos Contratos Públicos da Organização Mundial do Comércio): Não\nIdentificador do Lote: LOT-0102\nContrato adequado para PME: Não\nCobertura ACP (Acordo dos Contratos Públicos da Organização Mundial do Comércio): Não\nIdentificador do Lote: LOT-0103\nContrato adequado para PME: Não\nCobertura ACP (Acordo dos Contratos Públicos da Organização Mundial do Comércio): Não\nIdentificador do Lote: LOT-0104\nContrato adequado para PME: Não\nCobertura ACP (Acordo dos Contratos Públicos da Organização Mundial do Comércio): Não\nIdentificador do Lote: LOT-0105\nContrato adequado para PME: Não\nCobertura ACP (Acordo dos Contratos Públicos da Organização Mundial do Comércio): Não\nIdentificador do Lote: LOT-0106\nContrato adequado para PME: Não\nCobertura ACP (Acordo dos Contratos Públicos da Organização Mundial do Comércio): Não\nIdentificador do Lote: LOT-0107\nContrato adequado para PME: Não\nCobertura ACP (Acordo dos Contratos Públicos da Organização Mundial do Comércio): Não\nIdentificador do Lote: LOT-0108\nContrato adequado para PME: Não\nCobertura ACP (Acordo dos Contratos Públicos da Organização Mundial do Comércio): Não\nIdentificador do Lote: LOT-0109\nContrato adequado para PME: Não\nCobertura ACP (Acordo dos Contratos Públicos da Organização Mundial do Comércio): Não\n\n27 - IDENTIFICAÇÃO E CONTACTOS DO ÓRGÃO DE RECURSOS ADMINISTRATIVOS\nDesignação: Serviços de Ação Social da Universidade do Algarve\nEndereço: Estrada da Penha - Campus Universitário da Penha\nCódigo postal: 8005-139\nLocalidade: Faro\nEndereço eletrónico: sas@ualg.pt\n\n28 - IDENTIFICAÇÃO DO(S) AUTOR(ES) DE ANÚNCIO\nNome: António Joaquim Godinho Cabecinha\nCargo: Administrador dos SAS da Universidade do Algarve\n419602027",
    "nipc": "600039510",
    "distrito": "Faro",
    "concelho": "Faro",
    "freguesia": "Todas",
    "site": "https://www.ualg.pt/acao-social",
    "email": "sascompras@ualg.pt",
    "designacao_contrato": "Fornecimento contínuo e faseado de Fruta e Legumes Frescos e Legumes Congelados",
    "descricao": "Fornecimento contínuo e faseado de Fruta e Legumes Frescos e Legumes Congelados",
    "preco_base": "213.966,50 EUR",
    "prazo_execucao": "1 ANOS",
    "prazo_apresentacao_propostas": "08-10-2025 23:59",
    "fundos_eu": "Não",
    "plataforma_eletronica": "ANOGOV",
    "url_procedimento": "https://www.anogov.com/me-sasualgarve/faces/",
    "autor_nome": "António Joaquim Godinho Cabecinha",
    "autor_cargo": "Administrador dos SAS da Universidade do Algarve"
  },
  {
    "numero_procedimento": "N/A",
    "entidade": "Serviços de Acção Social da Universidade do Algarve",
    "link": "https://diariodarepublica.pt/dr/detalhe/contrato-publico/25879-937672806",
    "detalhes_completos": "1 - IDENTIFICAÇÃO E CONTACTOS DA ENTIDADE ADJUDICANTE\nDesignação da entidade adjudicante: Serviços de Acção Social da Universidade do Algarve\nNIPC: 600039510\nEndereço: Campus Universitário da Penha - Estrada da Penha\nCódigo postal: 8005-139\nLocalidade: Faro\nPaís: Portugal\nNUT III: PT150\nDistrito: Faro\nConcelho: Faro\nFreguesia: Todas\nTelefone: 289800102\nFax: 289800102\nEndereço da Entidade (URL): https://www.ualg.pt/acao-social\nEndereço Eletrónico: sascompras@ualg.pt\nFunção da Organização: Adquirente\nSubfunção da Organização: Líder do grupo\nNorma jurídica da Entidade Adjudicante: Autoridade da administração central\nÁrea de atividade da Entidade Adjudicante: Atividades aeroportuárias\n\n2 - JORNAL OFICIAL DA UNIÃO EUROPEIA\nO procedimento a que este anúncio diz respeito também é publicitado no Jornal Oficial da União Europeia? Não\n\n3 - AVISO\nModelo de Anúncio: Concurso público\nData de Envio do Anúncio: 01-10-2025\n\n5 - PROCESSO\nTipo de Procedimento: Concurso público\nPreço base do procedimento: Sim\nValor do preço base do procedimento: 214.700,00 EUR\nProcedimento com lotes? Sim\nNº Máx. de Lotes Autorizado: 93\nNúmero máximo de lotes que podem ser adjudicados a um concorrente: 93\n\n6 - OBJETO DO CONTRATO\nNúmero de referência interna: Concurso Público n.º 04/SAS-UAlg/2025\nDesignação do contrato: Aquisição contínua e parcelar de carne fresca e congelada\nDescrição: Aquisição contínua e parcelar de carne fresca e congelada\nTipo de Contrato Principal: Aquisição de Bens Móveis\nTipo de Contrato: Aquisição de Bens Móveis\nClassificação CPV (Vocabulário Comum para os Contratos Públicos)\nObjeto principal\nVocabulário Principal: 15100000\nPreço base s/IVA: 214.700,00 EUR\nLotes: \nNº: LOT-0001\nDescrição do Lote: Bochechas de porco frescas\nPreço base s/IVA: 1.800,00 EUR\nClassificação CPV (Vocabulário Comum para os Contratos Públicos)\nObjeto principal\nVocabulário Principal: 15100000\nNº: LOT-0002\nDescrição do Lote: Carne picada de porco fresca\nPreço base s/IVA: 2.800,00 EUR\nClassificação CPV (Vocabulário Comum para os Contratos Públicos)\nObjeto principal\nVocabulário Principal: 15100000\nNº: LOT-0003\nDescrição do Lote: Chispe de porco fresco\nPreço base s/IVA: 30,00 EUR\nClassificação CPV (Vocabulário Comum para os Contratos Públicos)\nObjeto principal\nVocabulário Principal: 15100000\nNº: LOT-0004\nDescrição do Lote: Costeleta de porco do cachaço frescas\nPreço base s/IVA: 2.000,00 EUR\nClassificação CPV (Vocabulário Comum para os Contratos Públicos)\nObjeto principal\nVocabulário Principal: 15100000\nNº: LOT-0005\nDescrição do Lote: Costeleta de porco do lombo frescas\nPreço base s/IVA: 2.500,00 EUR\nClassificação CPV (Vocabulário Comum para os Contratos Públicos)\nObjeto principal\nVocabulário Principal: 15100000\nNº: LOT-0006\nDescrição do Lote: Entrecosto fresco\nPreço base s/IVA: 110,00 EUR\nClassificação CPV (Vocabulário Comum para os Contratos Públicos)\nObjeto principal\nVocabulário Principal: 15100000\nNº: LOT-0007\nDescrição do Lote: Entrecosto piano fresco\nPreço base s/IVA: 2.100,00 EUR\nClassificação CPV (Vocabulário Comum para os Contratos Públicos)\nObjeto principal\nVocabulário Principal: 15100000\nNº: LOT-0008\nDescrição do Lote: Entremeada fatiada fresca\nPreço base s/IVA: 1.800,00 EUR\nClassificação CPV (Vocabulário Comum para os Contratos Públicos)\nObjeto principal\nVocabulário Principal: 15100000\nNº: LOT-0009\nDescrição do Lote: Entremeada com entrecosto fresca\nPreço base s/IVA: 210,00 EUR\nClassificação CPV (Vocabulário Comum para os Contratos Públicos)\nObjeto principal\nVocabulário Principal: 15100000\nNº: LOT-0010\nDescrição do Lote: Espetada de porco fresca\nPreço base s/IVA: 900,00 EUR\nClassificação CPV (Vocabulário Comum para os Contratos Públicos)\nObjeto principal\nVocabulário Principal: 15100000\nNº: LOT-0011\nDescrição do Lote: Febras da perna frescas\nPreço base s/IVA: 4.000,00 EUR\nClassificação CPV (Vocabulário Comum para os Contratos Públicos)\nObjeto principal\nVocabulário Principal: 15100000\nNº: LOT-0012\nDescrição do Lote: Fígado de porco (iscas) fresco\nPreço base s/IVA: 50,00 EUR\nClassificação CPV (Vocabulário Comum para os Contratos Públicos)\nObjeto principal\nVocabulário Principal: 15100000\nNº: LOT-0013\nDescrição do Lote: Lombinho de porco fresco\nPreço base s/IVA: 1.050,00 EUR\nClassificação CPV (Vocabulário Comum para os Contratos Públicos)\nObjeto principal\nVocabulário Principal: 15100000\nNº: LOT-0014\nDescrição do Lote: Lombo de porco fresco\nPreço base s/IVA: 4.400,00 EUR\nClassificação CPV (Vocabulário Comum para os Contratos Públicos)\nObjeto principal\nVocabulário Principal: 15100000\nNº: LOT-0015\nDescrição do Lote: Orelha de  porco fresca\nPreço base s/IVA: 105,00 EUR\nClassificação CPV (Vocabulário Comum para os Contratos Públicos)\nObjeto principal\nVocabulário Principal: 15100000\nNº: LOT-0016\nDescrição do Lote: Pá de porco sem osso fresca\nPreço base s/IVA: 7.500,00 EUR\nClassificação CPV (Vocabulário Comum para os Contratos Públicos)\nObjeto principal\nVocabulário Principal: 15100000\nNº: LOT-0017\nDescrição do Lote: Perna de porco sem osso fresca\nPreço base s/IVA: 900,00 EUR\nClassificação CPV (Vocabulário Comum para os Contratos Públicos)\nObjeto principal\nVocabulário Principal: 15100000\nNº: LOT-0018\nDescrição do Lote: Rojões frescos\nPreço base s/IVA: 9.400,00 EUR\nClassificação CPV (Vocabulário Comum para os Contratos Públicos)\nObjeto principal\nVocabulário Principal: 15100000\nNº: LOT-0019\nDescrição do Lote: Strogonoff de porco fresco\nPreço base s/IVA: 480,00 EUR\nClassificação CPV (Vocabulário Comum para os Contratos Públicos)\nObjeto principal\nVocabulário Principal: 15100000\nNº: LOT-0020\nDescrição do Lote: Secretos de porco preto cortados\nPreço base s/IVA: 1.800,00 EUR\nClassificação CPV (Vocabulário Comum para os Contratos Públicos)\nObjeto principal\nVocabulário Principal: 15100000\nNº: LOT-0021\nDescrição do Lote: Pernil de porco\nPreço base s/IVA: 40,00 EUR\nClassificação CPV (Vocabulário Comum para os Contratos Públicos)\nObjeto principal\nVocabulário Principal: 15100000\nNº: LOT-0022\nDescrição do Lote: Cachaço de porco sem osso\nPreço base s/IVA: 100,00 EUR\nClassificação CPV (Vocabulário Comum para os Contratos Públicos)\nObjeto principal\nVocabulário Principal: 15100000\nNº: LOT-0023\nDescrição do Lote: Lagartinhos\nPreço base s/IVA: 1.400,00 EUR\nClassificação CPV (Vocabulário Comum para os Contratos Públicos)\nObjeto principal\nVocabulário Principal: 15100000\nNº: LOT-0024\nDescrição do Lote: Bife de vitela pojadouro fresco\nPreço base s/IVA: 9.000,00 EUR\nClassificação CPV (Vocabulário Comum para os Contratos Públicos)\nObjeto principal\nVocabulário Principal: 15100000\nNº: LOT-0025\nDescrição do Lote: Bife de vitela da vazia fresco\nPreço base s/IVA: 200,00 EUR\nClassificação CPV (Vocabulário Comum para os Contratos Públicos)\nObjeto principal\nVocabulário Principal: 15100000\nNº: LOT-0026\nDescrição do Lote: Bife de vitela alcatra\nPreço base s/IVA: 200,00 EUR\nClassificação CPV (Vocabulário Comum para os Contratos Públicos)\nObjeto principal\nVocabulário Principal: 15100000\nNº: LOT-0027\nDescrição do Lote: Carne picada vaca fresca\nPreço base s/IVA: 2.100,00 EUR\nClassificação CPV (Vocabulário Comum para os Contratos Públicos)\nObjeto principal\nVocabulário Principal: 15100000\nNº: LOT-0028\nDescrição do Lote: Carne vitela para cozer/estufar fresca\nPreço base s/IVA: 180,00 EUR\nClassificação CPV (Vocabulário Comum para os Contratos Públicos)\nObjeto principal\nVocabulário Principal: 15100000\nNº: LOT-0029\nDescrição do Lote: Chambão de novilho fresco\nPreço base s/IVA: 1.840,00 EUR\nClassificação CPV (Vocabulário Comum para os Contratos Públicos)\nObjeto principal\nVocabulário Principal: 15100000\nNº: LOT-0030\nDescrição do Lote: Dobrada fresca\nPreço base s/IVA: 60,00 EUR\nClassificação CPV (Vocabulário Comum para os Contratos Públicos)\nObjeto principal\nVocabulário Principal: 15100000\nNº: LOT-0031\nDescrição do Lote: Escalopes de vitela frescos\nPreço base s/IVA: 45,00 EUR\nClassificação CPV (Vocabulário Comum para os Contratos Públicos)\nObjeto principal\nVocabulário Principal: 15100000\nNº: LOT-0032\nDescrição do Lote: Jardineira de novilho fresca\nPreço base s/IVA: 9.000,00 EUR\nClassificação CPV (Vocabulário Comum para os Contratos Públicos)\nObjeto principal\nVocabulário Principal: 15100000\nNº: LOT-0033\nDescrição do Lote: Maminha fresca\nPreço base s/IVA: 1.035,00 EUR\nClassificação CPV (Vocabulário Comum para os Contratos Públicos)\nObjeto principal\nVocabulário Principal: 15100000\nNº: LOT-0034\nDescrição do Lote: Ossobuco fresco\nPreço base s/IVA: 825,00 EUR\nClassificação CPV (Vocabulário Comum para os Contratos Públicos)\nObjeto principal\nVocabulário Principal: 15100000\nNº: LOT-0035\nDescrição do Lote: Picanha fresca\nPreço base s/IVA: 55,00 EUR\nClassificação CPV (Vocabulário Comum para os Contratos Públicos)\nObjeto principal\nVocabulário Principal: 15100000\nNº: LOT-0036\nDescrição do Lote: Strogonoff de vitela fresco\nPreço base s/IVA: 5.000,00 EUR\nClassificação CPV (Vocabulário Comum para os Contratos Públicos)\nObjeto principal\nVocabulário Principal: 15100000\nNº: LOT-0037\nDescrição do Lote: Tranches de vitela frescas\nPreço base s/IVA: 7.000,00 EUR\nClassificação CPV (Vocabulário Comum para os Contratos Públicos)\nObjeto principal\nVocabulário Principal: 15100000\nNº: LOT-0038\nDescrição do Lote: Borrego para assar/estufar fresco\nPreço base s/IVA: 3.800,00 EUR\nClassificação CPV (Vocabulário Comum para os Contratos Públicos)\nObjeto principal\nVocabulário Principal: 15100000\nNº: LOT-0039\nDescrição do Lote: Mão de borrego c/ osso fresca\nPreço base s/IVA: 95,00 EUR\nClassificação CPV (Vocabulário Comum para os Contratos Públicos)\nObjeto principal\nVocabulário Principal: 15100000\nNº: LOT-0040\nDescrição do Lote: Perna de borrego fresca\nPreço base s/IVA: 3.150,00 EUR\nClassificação CPV (Vocabulário Comum para os Contratos Públicos)\nObjeto principal\nVocabulário Principal: 15100000\nNº: LOT-0041\nDescrição do Lote: Perna de borrego sem osso fresca\nPreço base s/IVA: 105,00 EUR\nClassificação CPV (Vocabulário Comum para os Contratos Públicos)\nObjeto principal\nVocabulário Principal: 15100000\nNº: LOT-0042\nDescrição do Lote: Bife de peru fresco\nPreço base s/IVA: 17.500,00 EUR\nClassificação CPV (Vocabulário Comum para os Contratos Públicos)\nObjeto principal\nVocabulário Principal: 15100000\nNº: LOT-0043\nDescrição do Lote: Espetada de peru fresca\nPreço base s/IVA: 5.500,00 EUR\nClassificação CPV (Vocabulário Comum para os Contratos Públicos)\nObjeto principal\nVocabulário Principal: 15100000\nNº: LOT-0044\nDescrição do Lote: Frango coto\nPreço base s/IVA: 10,00 EUR\nClassificação CPV (Vocabulário Comum para os Contratos Públicos)\nObjeto principal\nVocabulário Principal: 15100000\nNº: LOT-0045\nDescrição do Lote: Frango do campo fresco c/ sangue\nPreço base s/IVA: 660,00 EUR\nClassificação CPV (Vocabulário Comum para os Contratos Públicos)\nObjeto principal\nVocabulário Principal: 15100000\nNº: LOT-0046\nDescrição do Lote: Frango Fresco Classe A1100 / 1200\nPreço base s/IVA: 23.250,00 EUR\nClassificação CPV (Vocabulário Comum para os Contratos Públicos)\nObjeto principal\nVocabulário Principal: 15100000\nNº: LOT-0047\nDescrição do Lote: Galinha fresca inteira c/ miúdos\nPreço base s/IVA: 250,00 EUR\nClassificação CPV (Vocabulário Comum para os Contratos Públicos)\nObjeto principal\nVocabulário Principal: 15100000\nNº: LOT-0048\nDescrição do Lote: Moelas de frango frescas\nPreço base s/IVA: 75,00 EUR\nClassificação CPV (Vocabulário Comum para os Contratos Públicos)\nObjeto principal\nVocabulário Principal: 15100000\nNº: LOT-0049\nDescrição do Lote: Ovo Cozido Balde 70 Un.\nPreço base s/IVA: 3.420,00 EUR\nClassificação CPV (Vocabulário Comum para os Contratos Públicos)\nObjeto principal\nVocabulário Principal: 15100000\nNº: LOT-0050\nDescrição do Lote: Ovo Liquido Pasteurizado Inteiro Fresco 1Kg\nPreço base s/IVA: 2.460,00 EUR\nClassificação CPV (Vocabulário Comum para os Contratos Públicos)\nObjeto principal\nVocabulário Principal: 15100000\nNº: LOT-0051\nDescrição do Lote: Ovos frescos classe M\nPreço base s/IVA: 460,00 EUR\nClassificação CPV (Vocabulário Comum para os Contratos Públicos)\nObjeto principal\nVocabulário Principal: 15100000\nNº: LOT-0052\nDescrição do Lote: Ovos frescos classe L\nPreço base s/IVA: 500,00 EUR\nClassificação CPV (Vocabulário Comum para os Contratos Públicos)\nObjeto principal\nVocabulário Principal: 15100000\nNº: LOT-0053\nDescrição do Lote: Pato inteiro fresco\nPreço base s/IVA: 4.080,00 EUR\nClassificação CPV (Vocabulário Comum para os Contratos Públicos)\nObjeto principal\nVocabulário Principal: 15100000\nNº: LOT-0054\nDescrição do Lote: Bife de frango fresco\nPreço base s/IVA: 2.100,00 EUR\nClassificação CPV (Vocabulário Comum para os Contratos Públicos)\nObjeto principal\nVocabulário Principal: 15100000\nNº: LOT-0055\nDescrição do Lote: Peito de frango congelado\nPreço base s/IVA: 550,00 EUR\nClassificação CPV (Vocabulário Comum para os Contratos Públicos)\nObjeto principal\nVocabulário Principal: 15100000\nNº: LOT-0056\nDescrição do Lote: Peito de frango fresco\nPreço base s/IVA: 600,00 EUR\nClassificação CPV (Vocabulário Comum para os Contratos Públicos)\nObjeto principal\nVocabulário Principal: 15100000\nNº: LOT-0057\nDescrição do Lote: Peito de peru fresco\nPreço base s/IVA: 7.650,00 EUR\nClassificação CPV (Vocabulário Comum para os Contratos Públicos)\nObjeto principal\nVocabulário Principal: 15100000\nNº: LOT-0058\nDescrição do Lote: Perna de frango congelada\nPreço base s/IVA: 250,00 EUR\nClassificação CPV (Vocabulário Comum para os Contratos Públicos)\nObjeto principal\nVocabulário Principal: 15100000\nNº: LOT-0059\nDescrição do Lote: Perna de frango fresca\nPreço base s/IVA: 128,00 EUR\nClassificação CPV (Vocabulário Comum para os Contratos Públicos)\nObjeto principal\nVocabulário Principal: 15100000\nNº: LOT-0060\nDescrição do Lote: Perna de peru fresca\nPreço base s/IVA: 13.750,00 EUR\nClassificação CPV (Vocabulário Comum para os Contratos Públicos)\nObjeto principal\nVocabulário Principal: 15100000\nNº: LOT-0061\nDescrição do Lote: Strogonoff de frango fresco\nPreço base s/IVA: 3.500,00 EUR\nClassificação CPV (Vocabulário Comum para os Contratos Públicos)\nObjeto principal\nVocabulário Principal: 15100000\nNº: LOT-0062\nDescrição do Lote: Strogonoff de peru fresco\nPreço base s/IVA: 3.700,00 EUR\nClassificação CPV (Vocabulário Comum para os Contratos Públicos)\nObjeto principal\nVocabulário Principal: 15100000\nNº: LOT-0063\nDescrição do Lote: Coelho inteiro fresco\nPreço base s/IVA: 700,00 EUR\nClassificação CPV (Vocabulário Comum para os Contratos Públicos)\nObjeto principal\nVocabulário Principal: 15100000\nNº: LOT-0064\nDescrição do Lote: Chouriço carne extra\nPreço base s/IVA: 48,00 EUR\nClassificação CPV (Vocabulário Comum para os Contratos Públicos)\nObjeto principal\nVocabulário Principal: 15100000\nNº: LOT-0065\nDescrição do Lote: Toucinho\nPreço base s/IVA: 27,50 EUR\nClassificação CPV (Vocabulário Comum para os Contratos Públicos)\nObjeto principal\nVocabulário Principal: 15100000\nNº: LOT-0066\nDescrição do Lote: Paio York\nPreço base s/IVA: 30,00 EUR\nClassificação CPV (Vocabulário Comum para os Contratos Públicos)\nObjeto principal\nVocabulário Principal: 15100000\nNº: LOT-0067\nDescrição do Lote: Morcela de sangue\nPreço base s/IVA: 55,00 EUR\nClassificação CPV (Vocabulário Comum para os Contratos Públicos)\nObjeto principal\nVocabulário Principal: 15100000\nNº: LOT-0068\nDescrição do Lote: Presunto fatiado emb. 200gr \nPreço base s/IVA: 26,50 EUR\nClassificação CPV (Vocabulário Comum para os Contratos Públicos)\nObjeto principal\nVocabulário Principal: 15100000\nNº: LOT-0069\nDescrição do Lote: Chouriço preto\nPreço base s/IVA: 210,00 EUR\nClassificação CPV (Vocabulário Comum para os Contratos Públicos)\nObjeto principal\nVocabulário Principal: 15100000\nNº: LOT-0070\nDescrição do Lote: Chourição\nPreço base s/IVA: 225,00 EUR\nClassificação CPV (Vocabulário Comum para os Contratos Públicos)\nObjeto principal\nVocabulário Principal: 15100000\nNº: LOT-0071\nDescrição do Lote: Bacon fatiado emb. 500gr\nPreço base s/IVA: 168,00 EUR\nClassificação CPV (Vocabulário Comum para os Contratos Públicos)\nObjeto principal\nVocabulário Principal: 15100000\nNº: LOT-0072\nDescrição do Lote: Presunto fatiado emb. 500gr \nPreço base s/IVA: 2.520,00 EUR\nClassificação CPV (Vocabulário Comum para os Contratos Públicos)\nObjeto principal\nVocabulário Principal: 15100000\nNº: LOT-0073\nDescrição do Lote: Farinheira\nPreço base s/IVA: 270,00 EUR\nClassificação CPV (Vocabulário Comum para os Contratos Públicos)\nObjeto principal\nVocabulário Principal: 15100000\nNº: LOT-0074\nDescrição do Lote: Alheira\nPreço base s/IVA: 700,00 EUR\nClassificação CPV (Vocabulário Comum para os Contratos Públicos)\nObjeto principal\nVocabulário Principal: 15100000\nNº: LOT-0075\nDescrição do Lote: Presunto s/ osso\nPreço base s/IVA: 280,00 EUR\nClassificação CPV (Vocabulário Comum para os Contratos Públicos)\nObjeto principal\nVocabulário Principal: 15100000\nNº: LOT-0076\nDescrição do Lote: Bacon\nPreço base s/IVA: 845,00 EUR\nClassificação CPV (Vocabulário Comum para os Contratos Públicos)\nObjeto principal\nVocabulário Principal: 15100000\nNº: LOT-0077\nDescrição do Lote: Chouriço corrente\nPreço base s/IVA: 800,00 EUR\nClassificação CPV (Vocabulário Comum para os Contratos Públicos)\nObjeto principal\nVocabulário Principal: 15100000\nNº: LOT-0078\nDescrição do Lote: Fiambre da perna\nPreço base s/IVA: 9.350,00 EUR\nClassificação CPV (Vocabulário Comum para os Contratos Públicos)\nObjeto principal\nVocabulário Principal: 15100000\nNº: LOT-0079\nDescrição do Lote: Almôndegas de bovino frescas\nPreço base s/IVA: 60,00 EUR\nClassificação CPV (Vocabulário Comum para os Contratos Públicos)\nObjeto principal\nVocabulário Principal: 15100000\nNº: LOT-0080\nDescrição do Lote: Almôndegas de aves frescas\nPreço base s/IVA: 2.250,00 EUR\nClassificação CPV (Vocabulário Comum para os Contratos Públicos)\nObjeto principal\nVocabulário Principal: 15100000\nNº: LOT-0081\nDescrição do Lote: Carne moída mista fresca (suíno e bovino)\nPreço base s/IVA: 26,00 EUR\nClassificação CPV (Vocabulário Comum para os Contratos Públicos)\nObjeto principal\nVocabulário Principal: 15100000\nNº: LOT-0082\nDescrição do Lote: Chamuça congelada miniatura cx de 200 unidades \nPreço base s/IVA: 2.695,00 EUR\nClassificação CPV (Vocabulário Comum para os Contratos Públicos)\nObjeto principal\nVocabulário Principal: 15100000\nNº: LOT-0083\nDescrição do Lote: Croquetes carne miniatura cx de 150 unidades \nPreço base s/IVA: 1.250,00 EUR\nClassificação CPV (Vocabulário Comum para os Contratos Públicos)\nObjeto principal\nVocabulário Principal: 15100000\nNº: LOT-0084\nDescrição do Lote: Croquetes carne miniatura cx de 200 unidades\nPreço base s/IVA: 1.200,00 EUR\nClassificação CPV (Vocabulário Comum para os Contratos Públicos)\nObjeto principal\nVocabulário Principal: 15100000\nNº: LOT-0085\nDescrição do Lote: Croquetes congelados (cantina)  cx de 125 unidades \nPreço base s/IVA: 720,00 EUR\nClassificação CPV (Vocabulário Comum para os Contratos Públicos)\nObjeto principal\nVocabulário Principal: 15100000\nNº: LOT-0086\nDescrição do Lote: Croquetes congelados (cantina)  cx de 50 unidades \nPreço base s/IVA: 200,00 EUR\nClassificação CPV (Vocabulário Comum para os Contratos Públicos)\nObjeto principal\nVocabulário Principal: 15100000\nNº: LOT-0087\nDescrição do Lote: Hamburgers de aves\nPreço base s/IVA: 2.700,00 EUR\nClassificação CPV (Vocabulário Comum para os Contratos Públicos)\nObjeto principal\nVocabulário Principal: 15100000\nNº: LOT-0088\nDescrição do Lote: Lasanha de carne CX 6 KG\nPreço base s/IVA: 5.800,00 EUR\nClassificação CPV (Vocabulário Comum para os Contratos Públicos)\nObjeto principal\nVocabulário Principal: 15100000\nNº: LOT-0089\nDescrição do Lote: Rissóis de carne (cantina) cx de 100 unidades \nPreço base s/IVA: 460,00 EUR\nClassificação CPV (Vocabulário Comum para os Contratos Públicos)\nObjeto principal\nVocabulário Principal: 15100000\nNº: LOT-0090\nDescrição do Lote: Rissóis de carne miniatura cx de 150 unidades\nPreço base s/IVA: 480,00 EUR\nClassificação CPV (Vocabulário Comum para os Contratos Públicos)\nObjeto principal\nVocabulário Principal: 15100000\nNº: LOT-0091\nDescrição do Lote: Salsicha Toscana fresca\nPreço base s/IVA: 500,00 EUR\nClassificação CPV (Vocabulário Comum para os Contratos Públicos)\nObjeto principal\nVocabulário Principal: 15100000\nNº: LOT-0092\nDescrição do Lote: Salsichas frescas de aves\nPreço base s/IVA: 450,00 EUR\nClassificação CPV (Vocabulário Comum para os Contratos Públicos)\nObjeto principal\nVocabulário Principal: 15100000\nNº: LOT-0093\nDescrição do Lote: Salsichas frescas de porco\nPreço base s/IVA: 96,00 EUR\nClassificação CPV (Vocabulário Comum para os Contratos Públicos)\nObjeto principal\nVocabulário Principal: 15100000\n\n7 - INDICAÇÕES ADICIONAIS\nO contrato envolve aquisição conjunta (satisfação de várias entidades)? Não\nO contrato é adjudicado por uma central de compras? Não\n\n8 - TÉCNICAS\nO concurso destina-se à celebração de um acordo-quadro? Inexistência de acordo-quadro\nÉ utilizado um leilão eletrónico? Não\nÉ adotada uma fase de negociação? Não\nSistema de Aquisição Dinâmico: Inexistência de sistema de aquisição dinâmico\n\n9 - LOCAL DA EXECUÇÃO DO CONTRATO\nLOCAL DA EXECUÇÃO DO CONTRATO (PROCEDIMENTO)\nLOCAL DA EXECUÇÃO DO CONTRATO (LOTE)\nIdentificador do Lote: LOT-0001\nPaís: Portugal\nNUT III: PT150\nLocalidade: Faro\nDistrito: Faro\nConcelho: Faro\nFreguesia: Todas\nIdentificador do Lote: LOT-0002\nPaís: Portugal\nNUT III: PT150\nLocalidade: Faro\nDistrito: Faro\nConcelho: Faro\nFreguesia: Todas\nIdentificador do Lote: LOT-0003\nPaís: Portugal\nNUT III: PT150\nLocalidade: Faro\nDistrito: Faro\nConcelho: Faro\nFreguesia: Todas\nIdentificador do Lote: LOT-0004\nPaís: Portugal\nNUT III: PT150\nLocalidade: Faro\nDistrito: Faro\nConcelho: Faro\nFreguesia: Todas\nIdentificador do Lote: LOT-0005\nPaís: Portugal\nNUT III: PT150\nLocalidade: Faro\nDistrito: Faro\nConcelho: Faro\nFreguesia: Todas\nIdentificador do Lote: LOT-0006\nPaís: Portugal\nNUT III: PT150\nLocalidade: Faro\nDistrito: Faro\nConcelho: Faro\nFreguesia: Todas\nIdentificador do Lote: LOT-0007\nPaís: Portugal\nNUT III: PT150\nLocalidade: Faro\nDistrito: Faro\nConcelho: Faro\nFreguesia: Todas\nIdentificador do Lote: LOT-0008\nPaís: Portugal\nNUT III: PT150\nLocalidade: Faro\nDistrito: Faro\nConcelho: Faro\nFreguesia: Todas\nIdentificador do Lote: LOT-0009\nPaís: Portugal\nNUT III: PT150\nLocalidade: Faro\nDistrito: Faro\nConcelho: Faro\nFreguesia: Todas\nIdentificador do Lote: LOT-0010\nPaís: Portugal\nNUT III: PT150\nLocalidade: Faro\nDistrito: Faro\nConcelho: Faro\nFreguesia: Todas\nIdentificador do Lote: LOT-0011\nPaís: Portugal\nNUT III: PT150\nLocalidade: Faro\nDistrito: Faro\nConcelho: Faro\nFreguesia: Todas\nIdentificador do Lote: LOT-0012\nPaís: Portugal\nNUT III: PT150\nLocalidade: Faro\nDistrito: Faro\nConcelho: Faro\nFreguesia: Todas\nIdentificador do Lote: LOT-0013\nPaís: Portugal\nNUT III: PT150\nLocalidade: Faro\nDistrito: Faro\nConcelho: Faro\nFreguesia: Todas\nIdentificador do Lote: LOT-0014\nPaís: Portugal\nNUT III: PT150\nLocalidade: Faro\nDistrito: Faro\nConcelho: Faro\nFreguesia: Todas\nIdentificador do Lote: LOT-0015\nPaís: Portugal\nNUT III: PT150\nLocalidade: Faro\nDistrito: Faro\nConcelho: Faro\nFreguesia: Todas\nIdentificador do Lote: LOT-0016\nPaís: Portugal\nNUT III: PT150\nLocalidade: Faro\nDistrito: Faro\nConcelho: Faro\nFreguesia: Todas\nIdentificador do Lote: LOT-0017\nPaís: Portugal\nNUT III: PT150\nLocalidade: Faro\nDistrito: Faro\nConcelho: Faro\nFreguesia: Todas\nIdentificador do Lote: LOT-0018\nPaís: Portugal\nNUT III: PT150\nLocalidade: Faro\nDistrito: Faro\nConcelho: Faro\nFreguesia: Todas\nIdentificador do Lote: LOT-0019\nPaís: Portugal\nNUT III: PT150\nLocalidade: Faro\nDistrito: Faro\nConcelho: Faro\nFreguesia: Todas\nIdentificador do Lote: LOT-0020\nPaís: Portugal\nNUT III: PT150\nLocalidade: Faro\nDistrito: Faro\nConcelho: Faro\nFreguesia: Todas\nIdentificador do Lote: LOT-0021\nPaís: Portugal\nNUT III: PT150\nLocalidade: Faro\nDistrito: Faro\nConcelho: Faro\nFreguesia: Todas\nIdentificador do Lote: LOT-0022\nPaís: Portugal\nNUT III: PT150\nLocalidade: Faro\nDistrito: Faro\nConcelho: Faro\nFreguesia: Todas\nIdentificador do Lote: LOT-0023\nPaís: Portugal\nNUT III: PT150\nLocalidade: Faro\nDistrito: Faro\nConcelho: Faro\nFreguesia: Todas\nIdentificador do Lote: LOT-0024\nPaís: Portugal\nNUT III: PT150\nLocalidade: Faro\nDistrito: Faro\nConcelho: Faro\nFreguesia: Todas\nIdentificador do Lote: LOT-0025\nPaís: Portugal\nNUT III: PT150\nLocalidade: Faro\nDistrito: Faro\nConcelho: Faro\nFreguesia: Todas\nIdentificador do Lote: LOT-0026\nPaís: Portugal\nNUT III: PT150\nLocalidade: Faro\nDistrito: Faro\nConcelho: Faro\nFreguesia: Todas\nIdentificador do Lote: LOT-0027\nPaís: Portugal\nNUT III: PT150\nLocalidade: Faro\nDistrito: Faro\nConcelho: Faro\nFreguesia: Todas\nIdentificador do Lote: LOT-0028\nPaís: Portugal\nNUT III: PT150\nLocalidade: Faro\nDistrito: Faro\nConcelho: Faro\nFreguesia: Todas\nIdentificador do Lote: LOT-0029\nPaís: Portugal\nNUT III: PT150\nLocalidade: Faro\nDistrito: Faro\nConcelho: Faro\nFreguesia: Todas\nIdentificador do Lote: LOT-0030\nPaís: Portugal\nNUT III: PT150\nLocalidade: Faro\nDistrito: Faro\nConcelho: Faro\nFreguesia: Todas\nIdentificador do Lote: LOT-0031\nPaís: Portugal\nNUT III: PT150\nLocalidade: Faro\nDistrito: Faro\nConcelho: Faro\nFreguesia: Todas\nIdentificador do Lote: LOT-0032\nPaís: Portugal\nNUT III: PT150\nLocalidade: Faro\nDistrito: Faro\nConcelho: Faro\nFreguesia: Todas\nIdentificador do Lote: LOT-0033\nPaís: Portugal\nNUT III: PT150\nLocalidade: Faro\nDistrito: Faro\nConcelho: Faro\nFreguesia: Todas\nIdentificador do Lote: LOT-0034\nPaís: Portugal\nNUT III: PT150\nLocalidade: Faro\nDistrito: Faro\nConcelho: Faro\nFreguesia: Todas\nIdentificador do Lote: LOT-0035\nPaís: Portugal\nNUT III: PT150\nLocalidade: Faro\nDistrito: Faro\nConcelho: Faro\nFreguesia: Todas\nIdentificador do Lote: LOT-0036\nPaís: Portugal\nNUT III: PT150\nLocalidade: Faro\nDistrito: Faro\nConcelho: Faro\nFreguesia: Todas\nIdentificador do Lote: LOT-0037\nPaís: Portugal\nNUT III: PT150\nLocalidade: Faro\nDistrito: Faro\nConcelho: Faro\nFreguesia: Todas\nIdentificador do Lote: LOT-0038\nPaís: Portugal\nNUT III: PT150\nLocalidade: Faro\nDistrito: Faro\nConcelho: Faro\nFreguesia: Todas\nIdentificador do Lote: LOT-0039\nPaís: Portugal\nNUT III: PT150\nLocalidade: Faro\nDistrito: Faro\nConcelho: Faro\nFreguesia: Todas\nIdentificador do Lote: LOT-0040\nPaís: Portugal\nNUT III: PT150\nLocalidade: Faro\nDistrito: Faro\nConcelho: Faro\nFreguesia: Todas\nIdentificador do Lote: LOT-0041\nPaís: Portugal\nNUT III: PT150\nLocalidade: Faro\nDistrito: Faro\nConcelho: Faro\nFreguesia: Todas\nIdentificador do Lote: LOT-0042\nPaís: Portugal\nNUT III: PT150\nLocalidade: Faro\nDistrito: Faro\nConcelho: Faro\nFreguesia: Todas\nIdentificador do Lote: LOT-0043\nPaís: Portugal\nNUT III: PT150\nLocalidade: Faro\nDistrito: Faro\nConcelho: Faro\nFreguesia: Todas\nIdentificador do Lote: LOT-0044\nPaís: Portugal\nNUT III: PT150\nLocalidade: Faro\nDistrito: Faro\nConcelho: Faro\nFreguesia: Todas\nIdentificador do Lote: LOT-0045\nPaís: Portugal\nNUT III: PT150\nLocalidade: Faro\nDistrito: Faro\nConcelho: Faro\nFreguesia: Todas\nIdentificador do Lote: LOT-0046\nPaís: Portugal\nNUT III: PT150\nLocalidade: Faro\nDistrito: Faro\nConcelho: Faro\nFreguesia: Todas\nIdentificador do Lote: LOT-0047\nPaís: Portugal\nNUT III: PT150\nLocalidade: Faro\nDistrito: Faro\nConcelho: Faro\nFreguesia: Todas\nIdentificador do Lote: LOT-0048\nPaís: Portugal\nNUT III: PT150\nLocalidade: Faro\nDistrito: Faro\nConcelho: Faro\nFreguesia: Todas\nIdentificador do Lote: LOT-0049\nPaís: Portugal\nNUT III: PT150\nLocalidade: Faro\nDistrito: Faro\nConcelho: Faro\nFreguesia: Todas\nIdentificador do Lote: LOT-0050\nPaís: Portugal\nNUT III: PT150\nLocalidade: Faro\nDistrito: Faro\nConcelho: Faro\nFreguesia: Todas\nIdentificador do Lote: LOT-0051\nPaís: Portugal\nNUT III: PT150\nLocalidade: Faro\nDistrito: Faro\nConcelho: Faro\nFreguesia: Todas\nIdentificador do Lote: LOT-0052\nPaís: Portugal\nNUT III: PT150\nLocalidade: Faro\nDistrito: Faro\nConcelho: Faro\nFreguesia: Todas\nIdentificador do Lote: LOT-0053\nPaís: Portugal\nNUT III: PT150\nLocalidade: Faro\nDistrito: Faro\nConcelho: Faro\nFreguesia: Todas\nIdentificador do Lote: LOT-0054\nPaís: Portugal\nNUT III: PT150\nLocalidade: Faro\nDistrito: Faro\nConcelho: Faro\nFreguesia: Todas\nIdentificador do Lote: LOT-0055\nPaís: Portugal\nNUT III: PT150\nLocalidade: Faro\nDistrito: Faro\nConcelho: Faro\nFreguesia: Todas\nIdentificador do Lote: LOT-0056\nPaís: Portugal\nNUT III: PT150\nLocalidade: Faro\nDistrito: Faro\nConcelho: Faro\nFreguesia: Todas\nIdentificador do Lote: LOT-0057\nPaís: Portugal\nNUT III: PT150\nLocalidade: Faro\nDistrito: Faro\nConcelho: Faro\nFreguesia: Todas\nIdentificador do Lote: LOT-0058\nPaís: Portugal\nNUT III: PT150\nLocalidade: Faro\nDistrito: Faro\nConcelho: Faro\nFreguesia: Todas\nIdentificador do Lote: LOT-0059\nPaís: Portugal\nNUT III: PT150\nLocalidade: Faro\nDistrito: Faro\nConcelho: Faro\nFreguesia: Todas\nIdentificador do Lote: LOT-0060\nPaís: Portugal\nNUT III: PT150\nLocalidade: Faro\nDistrito: Faro\nConcelho: Faro\nFreguesia: Todas\nIdentificador do Lote: LOT-0061\nPaís: Portugal\nNUT III: PT150\nLocalidade: Faro\nDistrito: Faro\nConcelho: Faro\nFreguesia: Todas\nIdentificador do Lote: LOT-0062\nPaís: Portugal\nNUT III: PT150\nLocalidade: Faro\nDistrito: Faro\nConcelho: Faro\nFreguesia: Todas\nIdentificador do Lote: LOT-0063\nPaís: Portugal\nNUT III: PT150\nLocalidade: Faro\nDistrito: Faro\nConcelho: Faro\nFreguesia: Todas\nIdentificador do Lote: LOT-0064\nPaís: Portugal\nNUT III: PT150\nLocalidade: Faro\nDistrito: Faro\nConcelho: Faro\nFreguesia: Todas\nIdentificador do Lote: LOT-0065\nPaís: Portugal\nNUT III: PT150\nLocalidade: Faro\nDistrito: Faro\nConcelho: Faro\nFreguesia: Todas\nIdentificador do Lote: LOT-0066\nPaís: Portugal\nNUT III: PT150\nLocalidade: Faro\nDistrito: Faro\nConcelho: Faro\nFreguesia: Todas\nIdentificador do Lote: LOT-0067\nPaís: Portugal\nNUT III: PT150\nLocalidade: Faro\nDistrito: Faro\nConcelho: Faro\nFreguesia: Todas\nIdentificador do Lote: LOT-0068\nPaís: Portugal\nNUT III: PT150\nLocalidade: Faro\nDistrito: Faro\nConcelho: Faro\nFreguesia: Todas\nIdentificador do Lote: LOT-0069\nPaís: Portugal\nNUT III: PT150\nLocalidade: Faro\nDistrito: Faro\nConcelho: Faro\nFreguesia: Todas\nIdentificador do Lote: LOT-0070\nPaís: Portugal\nNUT III: PT150\nLocalidade: Faro\nDistrito: Faro\nConcelho: Faro\nFreguesia: Todas\nIdentificador do Lote: LOT-0071\nPaís: Portugal\nNUT III: PT150\nLocalidade: Faro\nDistrito: Faro\nConcelho: Faro\nFreguesia: Todas\nIdentificador do Lote: LOT-0072\nPaís: Portugal\nNUT III: PT150\nLocalidade: Faro\nDistrito: Faro\nConcelho: Faro\nFreguesia: Todas\nIdentificador do Lote: LOT-0073\nPaís: Portugal\nNUT III: PT150\nLocalidade: Faro\nDistrito: Faro\nConcelho: Faro\nFreguesia: Todas\nIdentificador do Lote: LOT-0074\nPaís: Portugal\nNUT III: PT150\nLocalidade: Faro\nDistrito: Faro\nConcelho: Faro\nFreguesia: Todas\nIdentificador do Lote: LOT-0075\nPaís: Portugal\nNUT III: PT150\nLocalidade: Faro\nDistrito: Faro\nConcelho: Faro\nFreguesia: Todas\nIdentificador do Lote: LOT-0076\nPaís: Portugal\nNUT III: PT150\nLocalidade: Faro\nDistrito: Faro\nConcelho: Faro\nFreguesia: Todas\nIdentificador do Lote: LOT-0077\nPaís: Portugal\nNUT III: PT150\nLocalidade: Faro\nDistrito: Faro\nConcelho: Faro\nFreguesia: Todas\nIdentificador do Lote: LOT-0078\nPaís: Portugal\nNUT III: PT150\nLocalidade: Faro\nDistrito: Faro\nConcelho: Faro\nFreguesia: Todas\nIdentificador do Lote: LOT-0079\nPaís: Portugal\nNUT III: PT150\nLocalidade: Faro\nDistrito: Faro\nConcelho: Faro\nFreguesia: Todas\nIdentificador do Lote: LOT-0080\nPaís: Portugal\nNUT III: PT150\nLocalidade: Faro\nDistrito: Faro\nConcelho: Faro\nFreguesia: Todas\nIdentificador do Lote: LOT-0081\nPaís: Portugal\nNUT III: PT150\nLocalidade: Faro\nDistrito: Faro\nConcelho: Faro\nFreguesia: Todas\nIdentificador do Lote: LOT-0082\nPaís: Portugal\nNUT III: PT150\nLocalidade: Faro\nDistrito: Faro\nConcelho: Faro\nFreguesia: Todas\nIdentificador do Lote: LOT-0083\nPaís: Portugal\nNUT III: PT150\nLocalidade: Faro\nDistrito: Faro\nConcelho: Faro\nFreguesia: Todas\nIdentificador do Lote: LOT-0084\nPaís: Portugal\nNUT III: PT150\nLocalidade: Faro\nDistrito: Faro\nConcelho: Faro\nFreguesia: Todas\nIdentificador do Lote: LOT-0085\nPaís: Portugal\nNUT III: PT150\nLocalidade: Faro\nDistrito: Faro\nConcelho: Faro\nFreguesia: Todas\nIdentificador do Lote: LOT-0086\nPaís: Portugal\nNUT III: PT150\nLocalidade: Faro\nDistrito: Faro\nConcelho: Faro\nFreguesia: Todas\nIdentificador do Lote: LOT-0087\nPaís: Portugal\nNUT III: PT150\nLocalidade: Faro\nDistrito: Faro\nConcelho: Faro\nFreguesia: Todas\nIdentificador do Lote: LOT-0088\nPaís: Portugal\nNUT III: PT150\nLocalidade: Faro\nDistrito: Faro\nConcelho: Faro\nFreguesia: Todas\nIdentificador do Lote: LOT-0089\nPaís: Portugal\nNUT III: PT150\nLocalidade: Faro\nDistrito: Faro\nConcelho: Faro\nFreguesia: Todas\nIdentificador do Lote: LOT-0090\nPaís: Portugal\nNUT III: PT150\nLocalidade: Faro\nDistrito: Faro\nConcelho: Faro\nFreguesia: Todas\nIdentificador do Lote: LOT-0091\nPaís: Portugal\nNUT III: PT150\nLocalidade: Faro\nDistrito: Faro\nConcelho: Faro\nFreguesia: Todas\nIdentificador do Lote: LOT-0092\nPaís: Portugal\nNUT III: PT150\nLocalidade: Faro\nDistrito: Faro\nConcelho: Faro\nFreguesia: Todas\nIdentificador do Lote: LOT-0093\nPaís: Portugal\nNUT III: PT150\nLocalidade: Faro\nDistrito: Faro\nConcelho: Faro\nFreguesia: Todas\n\n10 - PRAZO DE EXECUÇÃO DO CONTRATO\nIdentificador do Lote: LOT-0001\nPrazo de execução do contrato: 1 ANOS\nPrevisão de renovações: Não\nIdentificador do Lote: LOT-0002\nPrazo de execução do contrato: 1 ANOS\nPrevisão de renovações: Não\nIdentificador do Lote: LOT-0003\nPrazo de execução do contrato: 1 ANOS\nPrevisão de renovações: Não\nIdentificador do Lote: LOT-0004\nPrazo de execução do contrato: 1 ANOS\nPrevisão de renovações: Não\nIdentificador do Lote: LOT-0005\nPrazo de execução do contrato: 1 ANOS\nPrevisão de renovações: Não\nIdentificador do Lote: LOT-0006\nPrazo de execução do contrato: 1 ANOS\nPrevisão de renovações: Não\nIdentificador do Lote: LOT-0007\nPrazo de execução do contrato: 1 ANOS\nPrevisão de renovações: Não\nIdentificador do Lote: LOT-0008\nPrazo de execução do contrato: 1 ANOS\nPrevisão de renovações: Não\nIdentificador do Lote: LOT-0009\nPrazo de execução do contrato: 1 ANOS\nPrevisão de renovações: Não\nIdentificador do Lote: LOT-0010\nPrazo de execução do contrato: 1 ANOS\nPrevisão de renovações: Não\nIdentificador do Lote: LOT-0011\nPrazo de execução do contrato: 1 ANOS\nPrevisão de renovações: Não\nIdentificador do Lote: LOT-0012\nPrazo de execução do contrato: 1 ANOS\nPrevisão de renovações: Não\nIdentificador do Lote: LOT-0013\nPrazo de execução do contrato: 1 ANOS\nPrevisão de renovações: Não\nIdentificador do Lote: LOT-0014\nPrazo de execução do contrato: 1 ANOS\nPrevisão de renovações: Não\nIdentificador do Lote: LOT-0015\nPrazo de execução do contrato: 1 ANOS\nPrevisão de renovações: Não\nIdentificador do Lote: LOT-0016\nPrazo de execução do contrato: 1 ANOS\nPrevisão de renovações: Não\nIdentificador do Lote: LOT-0017\nPrazo de execução do contrato: 1 ANOS\nPrevisão de renovações: Não\nIdentificador do Lote: LOT-0018\nPrazo de execução do contrato: 1 ANOS\nPrevisão de renovações: Não\nIdentificador do Lote: LOT-0019\nPrazo de execução do contrato: 1 ANOS\nPrevisão de renovações: Não\nIdentificador do Lote: LOT-0020\nPrazo de execução do contrato: 1 ANOS\nPrevisão de renovações: Não\nIdentificador do Lote: LOT-0021\nPrazo de execução do contrato: 1 ANOS\nPrevisão de renovações: Não\nIdentificador do Lote: LOT-0022\nPrazo de execução do contrato: 1 ANOS\nPrevisão de renovações: Não\nIdentificador do Lote: LOT-0023\nPrazo de execução do contrato: 1 ANOS\nPrevisão de renovações: Não\nIdentificador do Lote: LOT-0024\nPrazo de execução do contrato: 1 ANOS\nPrevisão de renovações: Não\nIdentificador do Lote: LOT-0025\nPrazo de execução do contrato: 1 ANOS\nPrevisão de renovações: Não\nIdentificador do Lote: LOT-0026\nPrazo de execução do contrato: 1 ANOS\nPrevisão de renovações: Não\nIdentificador do Lote: LOT-0027\nPrazo de execução do contrato: 1 ANOS\nPrevisão de renovações: Não\nIdentificador do Lote: LOT-0028\nPrazo de execução do contrato: 1 ANOS\nPrevisão de renovações: Não\nIdentificador do Lote: LOT-0029\nPrazo de execução do contrato: 1 ANOS\nPrevisão de renovações: Não\nIdentificador do Lote: LOT-0030\nPrazo de execução do contrato: 1 ANOS\nPrevisão de renovações: Não\nIdentificador do Lote: LOT-0031\nPrazo de execução do contrato: 1 ANOS\nPrevisão de renovações: Não\nIdentificador do Lote: LOT-0032\nPrazo de execução do contrato: 1 ANOS\nPrevisão de renovações: Não\nIdentificador do Lote: LOT-0033\nPrazo de execução do contrato: 1 ANOS\nPrevisão de renovações: Não\nIdentificador do Lote: LOT-0034\nPrazo de execução do contrato: 1 ANOS\nPrevisão de renovações: Não\nIdentificador do Lote: LOT-0035\nPrazo de execução do contrato: 1 ANOS\nPrevisão de renovações: Não\nIdentificador do Lote: LOT-0036\nPrazo de execução do contrato: 1 ANOS\nPrevisão de renovações: Não\nIdentificador do Lote: LOT-0037\nPrazo de execução do contrato: 1 ANOS\nPrevisão de renovações: Não\nIdentificador do Lote: LOT-0038\nPrazo de execução do contrato: 1 ANOS\nPrevisão de renovações: Não\nIdentificador do Lote: LOT-0039\nPrazo de execução do contrato: 1 ANOS\nPrevisão de renovações: Não\nIdentificador do Lote: LOT-0040\nPrazo de execução do contrato: 1 ANOS\nPrevisão de renovações: Não\nIdentificador do Lote: LOT-0041\nPrazo de execução do contrato: 1 ANOS\nPrevisão de renovações: Não\nIdentificador do Lote: LOT-0042\nPrazo de execução do contrato: 1 ANOS\nPrevisão de renovações: Não\nIdentificador do Lote: LOT-0043\nPrazo de execução do contrato: 1 ANOS\nPrevisão de renovações: Não\nIdentificador do Lote: LOT-0044\nPrazo de execução do contrato: 1 ANOS\nPrevisão de renovações: Não\nIdentificador do Lote: LOT-0045\nPrazo de execução do contrato: 1 ANOS\nPrevisão de renovações: Não\nIdentificador do Lote: LOT-0046\nPrazo de execução do contrato: 1 ANOS\nPrevisão de renovações: Não\nIdentificador do Lote: LOT-0047\nPrazo de execução do contrato: 1 ANOS\nPrevisão de renovações: Não\nIdentificador do Lote: LOT-0048\nPrazo de execução do contrato: 1 ANOS\nPrevisão de renovações: Não\nIdentificador do Lote: LOT-0049\nPrazo de execução do contrato: 1 ANOS\nPrevisão de renovações: Não\nIdentificador do Lote: LOT-0050\nPrazo de execução do contrato: 1 ANOS\nPrevisão de renovações: Não\nIdentificador do Lote: LOT-0051\nPrazo de execução do contrato: 1 ANOS\nPrevisão de renovações: Não\nIdentificador do Lote: LOT-0052\nPrazo de execução do contrato: 1 ANOS\nPrevisão de renovações: Não\nIdentificador do Lote: LOT-0053\nPrazo de execução do contrato: 1 ANOS\nPrevisão de renovações: Não\nIdentificador do Lote: LOT-0054\nPrazo de execução do contrato: 1 ANOS\nPrevisão de renovações: Não\nIdentificador do Lote: LOT-0055\nPrazo de execução do contrato: 1 ANOS\nPrevisão de renovações: Não\nIdentificador do Lote: LOT-0056\nPrazo de execução do contrato: 1 ANOS\nPrevisão de renovações: Não\nIdentificador do Lote: LOT-0057\nPrazo de execução do contrato: 1 ANOS\nPrevisão de renovações: Não\nIdentificador do Lote: LOT-0058\nPrazo de execução do contrato: 1 ANOS\nPrevisão de renovações: Não\nIdentificador do Lote: LOT-0059\nPrazo de execução do contrato: 1 ANOS\nPrevisão de renovações: Não\nIdentificador do Lote: LOT-0060\nPrazo de execução do contrato: 1 ANOS\nPrevisão de renovações: Não\nIdentificador do Lote: LOT-0061\nPrazo de execução do contrato: 1 ANOS\nPrevisão de renovações: Não\nIdentificador do Lote: LOT-0062\nPrazo de execução do contrato: 1 ANOS\nPrevisão de renovações: Não\nIdentificador do Lote: LOT-0063\nPrazo de execução do contrato: 1 ANOS\nPrevisão de renovações: Não\nIdentificador do Lote: LOT-0064\nPrazo de execução do contrato: 1 ANOS\nPrevisão de renovações: Não\nIdentificador do Lote: LOT-0065\nPrazo de execução do contrato: 1 ANOS\nPrevisão de renovações: Não\nIdentificador do Lote: LOT-0066\nPrazo de execução do contrato: 1 ANOS\nPrevisão de renovações: Não\nIdentificador do Lote: LOT-0067\nPrazo de execução do contrato: 1 ANOS\nPrevisão de renovações: Não\nIdentificador do Lote: LOT-0068\nPrazo de execução do contrato: 1 ANOS\nPrevisão de renovações: Não\nIdentificador do Lote: LOT-0069\nPrazo de execução do contrato: 1 ANOS\nPrevisão de renovações: Não\nIdentificador do Lote: LOT-0070\nPrazo de execução do contrato: 1 ANOS\nPrevisão de renovações: Não\nIdentificador do Lote: LOT-0071\nPrazo de execução do contrato: 1 ANOS\nPrevisão de renovações: Não\nIdentificador do Lote: LOT-0072\nPrazo de execução do contrato: 1 ANOS\nPrevisão de renovações: Não\nIdentificador do Lote: LOT-0073\nPrazo de execução do contrato: 1 ANOS\nPrevisão de renovações: Não\nIdentificador do Lote: LOT-0074\nPrazo de execução do contrato: 1 ANOS\nPrevisão de renovações: Não\nIdentificador do Lote: LOT-0075\nPrazo de execução do contrato: 1 ANOS\nPrevisão de renovações: Não\nIdentificador do Lote: LOT-0076\nPrazo de execução do contrato: 1 ANOS\nPrevisão de renovações: Não\nIdentificador do Lote: LOT-0077\nPrazo de execução do contrato: 1 ANOS\nPrevisão de renovações: Não\nIdentificador do Lote: LOT-0078\nPrazo de execução do contrato: 1 ANOS\nPrevisão de renovações: Não\nIdentificador do Lote: LOT-0079\nPrazo de execução do contrato: 1 ANOS\nPrevisão de renovações: Não\nIdentificador do Lote: LOT-0080\nPrazo de execução do contrato: 1 ANOS\nPrevisão de renovações: Não\nIdentificador do Lote: LOT-0081\nPrazo de execução do contrato: 1 ANOS\nPrevisão de renovações: Não\nIdentificador do Lote: LOT-0082\nPrazo de execução do contrato: 1 ANOS\nPrevisão de renovações: Não\nIdentificador do Lote: LOT-0083\nPrazo de execução do contrato: 1 ANOS\nPrevisão de renovações: Não\nIdentificador do Lote: LOT-0084\nPrazo de execução do contrato: 1 ANOS\nPrevisão de renovações: Não\nIdentificador do Lote: LOT-0085\nPrazo de execução do contrato: 1 ANOS\nPrevisão de renovações: Não\nIdentificador do Lote: LOT-0086\nPrazo de execução do contrato: 1 ANOS\nPrevisão de renovações: Não\nIdentificador do Lote: LOT-0087\nPrazo de execução do contrato: 1 ANOS\nPrevisão de renovações: Não\nIdentificador do Lote: LOT-0088\nPrazo de execução do contrato: 1 ANOS\nPrevisão de renovações: Não\nIdentificador do Lote: LOT-0089\nPrazo de execução do contrato: 1 ANOS\nPrevisão de renovações: Não\nIdentificador do Lote: LOT-0090\nPrazo de execução do contrato: 1 ANOS\nPrevisão de renovações: Não\nIdentificador do Lote: LOT-0091\nPrazo de execução do contrato: 1 ANOS\nPrevisão de renovações: Não\nIdentificador do Lote: LOT-0092\nPrazo de execução do contrato: 1 ANOS\nPrevisão de renovações: Não\nIdentificador do Lote: LOT-0093\nPrazo de execução do contrato: 1 ANOS\nPrevisão de renovações: Não\n\n11 - FUNDOS EU\nIdentificador do Lote: LOT-0001; LOT-0002; LOT-0003; LOT-0004; LOT-0005; LOT-0006; LOT-0007; LOT-0008; LOT-0009; LOT-0010; LOT-0011; LOT-0012; LOT-0013; LOT-0014; LOT-0015; LOT-0016; LOT-0017; LOT-0018; LOT-0019; LOT-0020; LOT-0021; LOT-0022; LOT-0023; LOT-0024; LOT-0025; LOT-0026; LOT-0027; LOT-0028; LOT-0029; LOT-0030; LOT-0031; LOT-0032; LOT-0033; LOT-0034; LOT-0035; LOT-0036; LOT-0037; LOT-0038; LOT-0039; LOT-0040; LOT-0041; LOT-0042; LOT-0043; LOT-0044; LOT-0045; LOT-0046; LOT-0047; LOT-0048; LOT-0049; LOT-0050; LOT-0051; LOT-0052; LOT-0053; LOT-0054; LOT-0055; LOT-0056; LOT-0057; LOT-0058; LOT-0059; LOT-0060; LOT-0061; LOT-0062; LOT-0063; LOT-0064; LOT-0065; LOT-0066; LOT-0067; LOT-0068; LOT-0069; LOT-0070; LOT-0071; LOT-0072; LOT-0073; LOT-0074; LOT-0075; LOT-0076; LOT-0077; LOT-0078; LOT-0079; LOT-0080; LOT-0081; LOT-0082; LOT-0083; LOT-0084; LOT-0085; LOT-0086; LOT-0087; LOT-0088; LOT-0089; LOT-0090; LOT-0091; LOT-0092; LOT-0093\nTêm fundos EU? Não\n\n12 - DOCUMENTOS DE HABILITAÇÃO\nHabilitação para o exercício da atividade profissional: Não\n\n13 - CONDIÇÕES DE APRESENTAÇÃO\nPlataforma eletrónica utilizada pela entidade adjudicante: ANOGOV\nURL para Apresentação: https://www.anogov.com/me-sasualgarve/faces/\nAdmissibilidade da apresentação de propostas variantes: Não autorizado\nPrazo para apresentação das propostas: 08-10-2025 23:59\nPrazo durante o qual os concorrentes são obrigados a manter as respetivas propostas: 66 dias a contar do termo do prazo para a apresentação das propostas\nApresentação de Catálogo Eletrónico: Permitido\nIndicação de Subcontratação na Proposta: Inexistência de indicação de subcontratação\n\n14 - PRESTAÇÃO DE CAUÇÃO\nPrestação de caução: Não\n\n15 - FORNECIMENTO DAS PEÇAS DO CONCURSO, APRESENTAÇÃO DE PEDIDOS DE PARTICIPAÇÃO E APRESENTAÇÃO DAS PROPOSTAS\nLink para acesso às peças do concurso (URL): https://www.anogov.com/me-sasualgarve/faces/app/acessoDocs.jsp?codigoAcesso=Sg1MI1MYJEkPoUmMEUj1DOEWPWkeOAB0C0ZVzVocF8JQyOyXeN\n\n20 - OUTROS REQUISITOS\nIdentificador do Lote: LOT-0001; LOT-0002; LOT-0003; LOT-0004; LOT-0005; LOT-0006; LOT-0007; LOT-0008; LOT-0009; LOT-0010; LOT-0011; LOT-0012; LOT-0013; LOT-0014; LOT-0015; LOT-0016; LOT-0017; LOT-0018; LOT-0019; LOT-0020; LOT-0021; LOT-0022; LOT-0023; LOT-0024; LOT-0025; LOT-0026; LOT-0027; LOT-0028; LOT-0029; LOT-0030; LOT-0031; LOT-0032; LOT-0033; LOT-0034; LOT-0035; LOT-0036; LOT-0037; LOT-0038; LOT-0039; LOT-0040; LOT-0041; LOT-0042; LOT-0043; LOT-0044; LOT-0045; LOT-0046; LOT-0047; LOT-0048; LOT-0049; LOT-0050; LOT-0051; LOT-0052; LOT-0053; LOT-0054; LOT-0055; LOT-0056; LOT-0057; LOT-0058; LOT-0059; LOT-0060; LOT-0061; LOT-0062; LOT-0063; LOT-0064; LOT-0065; LOT-0066; LOT-0067; LOT-0068; LOT-0069; LOT-0070; LOT-0071; LOT-0072; LOT-0073; LOT-0074; LOT-0075; LOT-0076; LOT-0077; LOT-0078; LOT-0079; LOT-0080; LOT-0081; LOT-0082; LOT-0083; LOT-0084; LOT-0085; LOT-0086; LOT-0087; LOT-0088; LOT-0089; LOT-0090; LOT-0091; LOT-0092; LOT-0093\nInformação sobre contratos reservados. Aplica-se a contratos reservados (54º-A)? Não\n\n21 - CRITÉRIO DE ADJUDICAÇÃO\nO Critério de adjudicação é diferenciado por lote? Não\nMultifator: Sim\nFator: \nNome: Preço\nPonderação: 90%\nSubfatores: Não\nFator: \nNome: Outros\nOutro Nome: Origem e Impacto Ambiental: A produção tenha todas as suas fases no Algarve\nPonderação: 10%\nSubfatores: Não\n\n24 - CONDIÇÕES DO CONTRATO\nIdentificador do Lote: LOT-0001; LOT-0002; LOT-0003; LOT-0004; LOT-0005; LOT-0006; LOT-0007; LOT-0008; LOT-0009; LOT-0010; LOT-0011; LOT-0012; LOT-0013; LOT-0014; LOT-0015; LOT-0016; LOT-0017; LOT-0018; LOT-0019; LOT-0020; LOT-0021; LOT-0022; LOT-0023; LOT-0024; LOT-0025; LOT-0026; LOT-0027; LOT-0028; LOT-0029; LOT-0030; LOT-0031; LOT-0032; LOT-0033; LOT-0034; LOT-0035; LOT-0036; LOT-0037; LOT-0038; LOT-0039; LOT-0040; LOT-0041; LOT-0042; LOT-0043; LOT-0044; LOT-0045; LOT-0046; LOT-0047; LOT-0048; LOT-0049; LOT-0050; LOT-0051; LOT-0052; LOT-0053; LOT-0054; LOT-0055; LOT-0056; LOT-0057; LOT-0058; LOT-0059; LOT-0060; LOT-0061; LOT-0062; LOT-0063; LOT-0064; LOT-0065; LOT-0066; LOT-0067; LOT-0068; LOT-0069; LOT-0070; LOT-0071; LOT-0072; LOT-0073; LOT-0074; LOT-0075; LOT-0076; LOT-0077; LOT-0078; LOT-0079; LOT-0080; LOT-0081; LOT-0082; LOT-0083; LOT-0084; LOT-0085; LOT-0086; LOT-0087; LOT-0088; LOT-0089; LOT-0090; LOT-0091; LOT-0092; LOT-0093\nFaturação Eletrónica: Permitido\nObrigação de Subcontratação:\nCódigo da Obrigação de Subcontratação: Não é aplicável nenhuma obrigação de subcontratação.\n\n25 - COMPRA PÚBLICA ESTRATÉGICA\nCompra Pública Estratégica: Redução dos impactos ambientais\nDescrição do Processo de Adjudicação Estratégico: Origem e Impacto Ambiental: A produção tenha todas as suas fases no Algarve\nCritérios de contratos Públicos Ecológicos: Critérios de contratação pública ecológica da UE\nCategorias da estratégia nacional: Produtos alimentares, serviços de assistência de restauração (catering) e máquinas de distribuição automática\nContratos Públicos Ecológicos: Outros\nDiretiva Veículos Não Poluentes: Não\nCritério de Acessibilidade: Os critérios de acessibilidade para as pessoas com deficiência não estão incluídos porque o contrato não se destina a pessoas singulares\n\n26 - INFORMAÇÕES ADICIONAIS\nIdentificador do Lote: LOT-0001\nContrato adequado para PME: Não\nCobertura ACP (Acordo dos Contratos Públicos da Organização Mundial do Comércio): Não\nIdentificador do Lote: LOT-0002\nContrato adequado para PME: Não\nCobertura ACP (Acordo dos Contratos Públicos da Organização Mundial do Comércio): Não\nIdentificador do Lote: LOT-0003\nContrato adequado para PME: Não\nCobertura ACP (Acordo dos Contratos Públicos da Organização Mundial do Comércio): Não\nIdentificador do Lote: LOT-0004\nContrato adequado para PME: Não\nCobertura ACP (Acordo dos Contratos Públicos da Organização Mundial do Comércio): Não\nIdentificador do Lote: LOT-0005\nContrato adequado para PME: Não\nCobertura ACP (Acordo dos Contratos Públicos da Organização Mundial do Comércio): Não\nIdentificador do Lote: LOT-0006\nContrato adequado para PME: Não\nCobertura ACP (Acordo dos Contratos Públicos da Organização Mundial do Comércio): Não\nIdentificador do Lote: LOT-0007\nContrato adequado para PME: Não\nCobertura ACP (Acordo dos Contratos Públicos da Organização Mundial do Comércio): Não\nIdentificador do Lote: LOT-0008\nContrato adequado para PME: Não\nCobertura ACP (Acordo dos Contratos Públicos da Organização Mundial do Comércio): Não\nIdentificador do Lote: LOT-0009\nContrato adequado para PME: Não\nCobertura ACP (Acordo dos Contratos Públicos da Organização Mundial do Comércio): Não\nIdentificador do Lote: LOT-0010\nContrato adequado para PME: Não\nCobertura ACP (Acordo dos Contratos Públicos da Organização Mundial do Comércio): Não\nIdentificador do Lote: LOT-0011\nContrato adequado para PME: Não\nCobertura ACP (Acordo dos Contratos Públicos da Organização Mundial do Comércio): Não\nIdentificador do Lote: LOT-0012\nContrato adequado para PME: Não\nCobertura ACP (Acordo dos Contratos Públicos da Organização Mundial do Comércio): Não\nIdentificador do Lote: LOT-0013\nContrato adequado para PME: Não\nCobertura ACP (Acordo dos Contratos Públicos da Organização Mundial do Comércio): Não\nIdentificador do Lote: LOT-0014\nContrato adequado para PME: Não\nCobertura ACP (Acordo dos Contratos Públicos da Organização Mundial do Comércio): Não\nIdentificador do Lote: LOT-0015\nContrato adequado para PME: Não\nCobertura ACP (Acordo dos Contratos Públicos da Organização Mundial do Comércio): Não\nIdentificador do Lote: LOT-0016\nContrato adequado para PME: Não\nCobertura ACP (Acordo dos Contratos Públicos da Organização Mundial do Comércio): Não\nIdentificador do Lote: LOT-0017\nContrato adequado para PME: Não\nCobertura ACP (Acordo dos Contratos Públicos da Organização Mundial do Comércio): Não\nIdentificador do Lote: LOT-0018\nContrato adequado para PME: Não\nCobertura ACP (Acordo dos Contratos Públicos da Organização Mundial do Comércio): Não\nIdentificador do Lote: LOT-0019\nContrato adequado para PME: Não\nCobertura ACP (Acordo dos Contratos Públicos da Organização Mundial do Comércio): Não\nIdentificador do Lote: LOT-0020\nContrato adequado para PME: Não\nCobertura ACP (Acordo dos Contratos Públicos da Organização Mundial do Comércio): Não\nIdentificador do Lote: LOT-0021\nContrato adequado para PME: Não\nCobertura ACP (Acordo dos Contratos Públicos da Organização Mundial do Comércio): Não\nIdentificador do Lote: LOT-0022\nContrato adequado para PME: Não\nCobertura ACP (Acordo dos Contratos Públicos da Organização Mundial do Comércio): Não\nIdentificador do Lote: LOT-0023\nContrato adequado para PME: Não\nCobertura ACP (Acordo dos Contratos Públicos da Organização Mundial do Comércio): Não\nIdentificador do Lote: LOT-0024\nContrato adequado para PME: Não\nCobertura ACP (Acordo dos Contratos Públicos da Organização Mundial do Comércio): Não\nIdentificador do Lote: LOT-0025\nContrato adequado para PME: Não\nCobertura ACP (Acordo dos Contratos Públicos da Organização Mundial do Comércio): Não\nIdentificador do Lote: LOT-0026\nContrato adequado para PME: Não\nCobertura ACP (Acordo dos Contratos Públicos da Organização Mundial do Comércio): Não\nIdentificador do Lote: LOT-0027\nContrato adequado para PME: Não\nCobertura ACP (Acordo dos Contratos Públicos da Organização Mundial do Comércio): Não\nIdentificador do Lote: LOT-0028\nContrato adequado para PME: Não\nCobertura ACP (Acordo dos Contratos Públicos da Organização Mundial do Comércio): Não\nIdentificador do Lote: LOT-0029\nContrato adequado para PME: Não\nCobertura ACP (Acordo dos Contratos Públicos da Organização Mundial do Comércio): Não\nIdentificador do Lote: LOT-0030\nContrato adequado para PME: Não\nCobertura ACP (Acordo dos Contratos Públicos da Organização Mundial do Comércio): Não\nIdentificador do Lote: LOT-0031\nContrato adequado para PME: Não\nCobertura ACP (Acordo dos Contratos Públicos da Organização Mundial do Comércio): Não\nIdentificador do Lote: LOT-0032\nContrato adequado para PME: Não\nCobertura ACP (Acordo dos Contratos Públicos da Organização Mundial do Comércio): Não\nIdentificador do Lote: LOT-0033\nContrato adequado para PME: Não\nCobertura ACP (Acordo dos Contratos Públicos da Organização Mundial do Comércio): Não\nIdentificador do Lote: LOT-0034\nContrato adequado para PME: Não\nCobertura ACP (Acordo dos Contratos Públicos da Organização Mundial do Comércio): Não\nIdentificador do Lote: LOT-0035\nContrato adequado para PME: Não\nCobertura ACP (Acordo dos Contratos Públicos da Organização Mundial do Comércio): Não\nIdentificador do Lote: LOT-0036\nContrato adequado para PME: Não\nCobertura ACP (Acordo dos Contratos Públicos da Organização Mundial do Comércio): Não\nIdentificador do Lote: LOT-0037\nContrato adequado para PME: Não\nCobertura ACP (Acordo dos Contratos Públicos da Organização Mundial do Comércio): Não\nIdentificador do Lote: LOT-0038\nContrato adequado para PME: Não\nCobertura ACP (Acordo dos Contratos Públicos da Organização Mundial do Comércio): Não\nIdentificador do Lote: LOT-0039\nContrato adequado para PME: Não\nCobertura ACP (Acordo dos Contratos Públicos da Organização Mundial do Comércio): Não\nIdentificador do Lote: LOT-0040\nContrato adequado para PME: Não\nCobertura ACP (Acordo dos Contratos Públicos da Organização Mundial do Comércio): Não\nIdentificador do Lote: LOT-0041\nContrato adequado para PME: Não\nCobertura ACP (Acordo dos Contratos Públicos da Organização Mundial do Comércio): Não\nIdentificador do Lote: LOT-0042\nContrato adequado para PME: Não\nCobertura ACP (Acordo dos Contratos Públicos da Organização Mundial do Comércio): Não\nIdentificador do Lote: LOT-0043\nContrato adequado para PME: Não\nCobertura ACP (Acordo dos Contratos Públicos da Organização Mundial do Comércio): Não\nIdentificador do Lote: LOT-0044\nContrato adequado para PME: Não\nCobertura ACP (Acordo dos Contratos Públicos da Organização Mundial do Comércio): Não\nIdentificador do Lote: LOT-0045\nContrato adequado para PME: Não\nCobertura ACP (Acordo dos Contratos Públicos da Organização Mundial do Comércio): Não\nIdentificador do Lote: LOT-0046\nContrato adequado para PME: Não\nCobertura ACP (Acordo dos Contratos Públicos da Organização Mundial do Comércio): Não\nIdentificador do Lote: LOT-0047\nContrato adequado para PME: Não\nCobertura ACP (Acordo dos Contratos Públicos da Organização Mundial do Comércio): Não\nIdentificador do Lote: LOT-0048\nContrato adequado para PME: Não\nCobertura ACP (Acordo dos Contratos Públicos da Organização Mundial do Comércio): Não\nIdentificador do Lote: LOT-0049\nContrato adequado para PME: Não\nCobertura ACP (Acordo dos Contratos Públicos da Organização Mundial do Comércio): Não\nIdentificador do Lote: LOT-0050\nContrato adequado para PME: Não\nCobertura ACP (Acordo dos Contratos Públicos da Organização Mundial do Comércio): Não\nIdentificador do Lote: LOT-0051\nContrato adequado para PME: Não\nCobertura ACP (Acordo dos Contratos Públicos da Organização Mundial do Comércio): Não\nIdentificador do Lote: LOT-0052\nContrato adequado para PME: Não\nCobertura ACP (Acordo dos Contratos Públicos da Organização Mundial do Comércio): Não\nIdentificador do Lote: LOT-0053\nContrato adequado para PME: Não\nCobertura ACP (Acordo dos Contratos Públicos da Organização Mundial do Comércio): Não\nIdentificador do Lote: LOT-0054\nContrato adequado para PME: Não\nCobertura ACP (Acordo dos Contratos Públicos da Organização Mundial do Comércio): Não\nIdentificador do Lote: LOT-0055\nContrato adequado para PME: Não\nCobertura ACP (Acordo dos Contratos Públicos da Organização Mundial do Comércio): Não\nIdentificador do Lote: LOT-0056\nContrato adequado para PME: Não\nCobertura ACP (Acordo dos Contratos Públicos da Organização Mundial do Comércio): Não\nIdentificador do Lote: LOT-0057\nContrato adequado para PME: Não\nCobertura ACP (Acordo dos Contratos Públicos da Organização Mundial do Comércio): Não\nIdentificador do Lote: LOT-0058\nContrato adequado para PME: Não\nCobertura ACP (Acordo dos Contratos Públicos da Organização Mundial do Comércio): Não\nIdentificador do Lote: LOT-0059\nContrato adequado para PME: Não\nCobertura ACP (Acordo dos Contratos Públicos da Organização Mundial do Comércio): Não\nIdentificador do Lote: LOT-0060\nContrato adequado para PME: Não\nCobertura ACP (Acordo dos Contratos Públicos da Organização Mundial do Comércio): Não\nIdentificador do Lote: LOT-0061\nContrato adequado para PME: Não\nCobertura ACP (Acordo dos Contratos Públicos da Organização Mundial do Comércio): Não\nIdentificador do Lote: LOT-0062\nContrato adequado para PME: Não\nCobertura ACP (Acordo dos Contratos Públicos da Organização Mundial do Comércio): Não\nIdentificador do Lote: LOT-0063\nContrato adequado para PME: Não\nCobertura ACP (Acordo dos Contratos Públicos da Organização Mundial do Comércio): Não\nIdentificador do Lote: LOT-0064\nContrato adequado para PME: Não\nCobertura ACP (Acordo dos Contratos Públicos da Organização Mundial do Comércio): Não\nIdentificador do Lote: LOT-0065\nContrato adequado para PME: Não\nCobertura ACP (Acordo dos Contratos Públicos da Organização Mundial do Comércio): Não\nIdentificador do Lote: LOT-0066\nContrato adequado para PME: Não\nCobertura ACP (Acordo dos Contratos Públicos da Organização Mundial do Comércio): Não\nIdentificador do Lote: LOT-0067\nContrato adequado para PME: Não\nCobertura ACP (Acordo dos Contratos Públicos da Organização Mundial do Comércio): Não\nIdentificador do Lote: LOT-0068\nContrato adequado para PME: Não\nCobertura ACP (Acordo dos Contratos Públicos da Organização Mundial do Comércio): Não\nIdentificador do Lote: LOT-0069\nContrato adequado para PME: Não\nCobertura ACP (Acordo dos Contratos Públicos da Organização Mundial do Comércio): Não\nIdentificador do Lote: LOT-0070\nContrato adequado para PME: Não\nCobertura ACP (Acordo dos Contratos Públicos da Organização Mundial do Comércio): Não\nIdentificador do Lote: LOT-0071\nContrato adequado para PME: Não\nCobertura ACP (Acordo dos Contratos Públicos da Organização Mundial do Comércio): Não\nIdentificador do Lote: LOT-0072\nContrato adequado para PME: Não\nCobertura ACP (Acordo dos Contratos Públicos da Organização Mundial do Comércio): Não\nIdentificador do Lote: LOT-0073\nContrato adequado para PME: Não\nCobertura ACP (Acordo dos Contratos Públicos da Organização Mundial do Comércio): Não\nIdentificador do Lote: LOT-0074\nContrato adequado para PME: Não\nCobertura ACP (Acordo dos Contratos Públicos da Organização Mundial do Comércio): Não\nIdentificador do Lote: LOT-0075\nContrato adequado para PME: Não\nCobertura ACP (Acordo dos Contratos Públicos da Organização Mundial do Comércio): Não\nIdentificador do Lote: LOT-0076\nContrato adequado para PME: Não\nCobertura ACP (Acordo dos Contratos Públicos da Organização Mundial do Comércio): Não\nIdentificador do Lote: LOT-0077\nContrato adequado para PME: Não\nCobertura ACP (Acordo dos Contratos Públicos da Organização Mundial do Comércio): Não\nIdentificador do Lote: LOT-0078\nContrato adequado para PME: Não\nCobertura ACP (Acordo dos Contratos Públicos da Organização Mundial do Comércio): Não\nIdentificador do Lote: LOT-0079\nContrato adequado para PME: Não\nCobertura ACP (Acordo dos Contratos Públicos da Organização Mundial do Comércio): Não\nIdentificador do Lote: LOT-0080\nContrato adequado para PME: Não\nCobertura ACP (Acordo dos Contratos Públicos da Organização Mundial do Comércio): Não\nIdentificador do Lote: LOT-0081\nContrato adequado para PME: Não\nCobertura ACP (Acordo dos Contratos Públicos da Organização Mundial do Comércio): Não\nIdentificador do Lote: LOT-0082\nContrato adequado para PME: Não\nCobertura ACP (Acordo dos Contratos Públicos da Organização Mundial do Comércio): Não\nIdentificador do Lote: LOT-0083\nContrato adequado para PME: Não\nCobertura ACP (Acordo dos Contratos Públicos da Organização Mundial do Comércio): Não\nIdentificador do Lote: LOT-0084\nContrato adequado para PME: Não\nCobertura ACP (Acordo dos Contratos Públicos da Organização Mundial do Comércio): Não\nIdentificador do Lote: LOT-0085\nContrato adequado para PME: Não\nCobertura ACP (Acordo dos Contratos Públicos da Organização Mundial do Comércio): Não\nIdentificador do Lote: LOT-0086\nContrato adequado para PME: Não\nCobertura ACP (Acordo dos Contratos Públicos da Organização Mundial do Comércio): Não\nIdentificador do Lote: LOT-0087\nContrato adequado para PME: Não\nCobertura ACP (Acordo dos Contratos Públicos da Organização Mundial do Comércio): Não\nIdentificador do Lote: LOT-0088\nContrato adequado para PME: Não\nCobertura ACP (Acordo dos Contratos Públicos da Organização Mundial do Comércio): Não\nIdentificador do Lote: LOT-0089\nContrato adequado para PME: Não\nCobertura ACP (Acordo dos Contratos Públicos da Organização Mundial do Comércio): Não\nIdentificador do Lote: LOT-0090\nContrato adequado para PME: Não\nCobertura ACP (Acordo dos Contratos Públicos da Organização Mundial do Comércio): Não\nIdentificador do Lote: LOT-0091\nContrato adequado para PME: Não\nCobertura ACP (Acordo dos Contratos Públicos da Organização Mundial do Comércio): Não\nIdentificador do Lote: LOT-0092\nContrato adequado para PME: Não\nCobertura ACP (Acordo dos Contratos Públicos da Organização Mundial do Comércio): Não\nIdentificador do Lote: LOT-0093\nContrato adequado para PME: Não\nCobertura ACP (Acordo dos Contratos Públicos da Organização Mundial do Comércio): Não\n\n27 - IDENTIFICAÇÃO E CONTACTOS DO ÓRGÃO DE RECURSOS ADMINISTRATIVOS\nDesignação: Serviços de Ação Social da Universidade do Algarve\nEndereço: Estrada da Penha - Campus Universitário da Penha\nCódigo postal: 8005-139\nLocalidade: Faro\nEndereço eletrónico: sas@ualg.pt\n\n28 - IDENTIFICAÇÃO DO(S) AUTOR(ES) DE ANÚNCIO\nNome: António Joaquim Godinho Cabecinha\nCargo: Administrador dos SAS da Universidade do Algarve\n419602238",
    "nipc": "600039510",
    "distrito": "Faro",
    "concelho": "Faro",
    "freguesia": "Todas",
    "site": "https://www.ualg.pt/acao-social",
    "email": "sascompras@ualg.pt",
    "designacao_contrato": "Aquisição contínua e parcelar de carne fresca e congelada",
    "descricao": "Aquisição contínua e parcelar de carne fresca e congelada",
    "preco_base": "214.700,00 EUR",
    "prazo_execucao": "1 ANOS",
    "prazo_apresentacao_propostas": "08-10-2025 23:59",
    "fundos_eu": "Não",
    "plataforma_eletronica": "ANOGOV",
    "url_procedimento": "https://www.anogov.com/me-sasualgarve/faces/",
    "autor_nome": "António Joaquim Godinho Cabecinha",
    "autor_cargo": "Administrador dos SAS da Universidade do Algarve"
  },
  {
    "numero_procedimento": "N/A",
    "entidade": "Instituto Superior de Engenharia do Porto",
    "link": "https://diariodarepublica.pt/dr/detalhe/contrato-publico/25880-937672807",
    "detalhes_completos": "1 - IDENTIFICAÇÃO E CONTACTOS DA ENTIDADE ADJUDICANTE\nDesignação da entidade adjudicante: Instituto Superior de Engenharia do Porto\nNIPC: 501540709\nServiço/Órgão/Pessoa de contacto: Serviços Economico-financeiros\nEndereço: Rua Dr. António Bernardino de Almeida, 431\nCódigo postal: 4249-015\nLocalidade: PORTO\nPaís: Portugal\nNUT III: PT11A\nDistrito: Porto\nConcelho: Porto\nFreguesia: Freguesia de Paranhos - Porto\nTelefone: 228340500\nFax: 228321159\nEndereço da Entidade (URL): https://www.isep.ipp.pt\nEndereço Eletrónico: info-sef@isep.ipp.pt\neDelivery Gateway (URL): https://www.acingov.pt\nFunção da Organização: Adquirente\nNorma jurídica da Entidade Adjudicante: Organismo de direito público\nÁrea de atividade da Autoridade Adjudicante: Educação\n\n2 - JORNAL OFICIAL DA UNIÃO EUROPEIA\nO procedimento a que este anúncio diz respeito também é publicitado no Jornal Oficial da União Europeia? Não\n\n3 - AVISO\nModelo de Anúncio: Concurso público\nData de Envio do Anúncio: 01-10-2025\n\n5 - PROCESSO\nTipo de Procedimento: Concurso público\nPreço base do procedimento: Sim\nValor do preço base do procedimento: 46.800,00 EUR\nProcedimento com lotes? Sim\nNº Máx. de Lotes Autorizado: 8\nNúmero máximo de lotes que podem ser adjudicados a um concorrente: 8\n\n6 - OBJETO DO CONTRATO\nNúmero de referência interna: 92/2025\nDesignação do contrato: Contratação de Serviços de Formação a realizar no âmbito da Pós-Graduação em BigData & Decision Making, promovida pelo Departamento de Engenharia Informática do ISEP - Instituto Superior de Engenharia do Porto\nDescrição: Contratação de Serviços de Formação a realizar no âmbito da Pós-Graduação em BigData & Decision Making, promovida pelo Departamento de Engenharia Informática do ISEP - Instituto Superior de Engenharia do Porto\nTipo de Contrato Principal: Aquisição de Serviços\nTipo de Contrato: Aquisição de Serviços\nClassificação CPV (Vocabulário Comum para os Contratos Públicos)\nObjeto principal\nVocabulário Principal: 80300000\nPreço base s/IVA: 46.800,00 EUR\nLotes: \nNº: LOT-0001\nDescrição do Lote: Lote 1\nPreço base s/IVA: 5.850,00 EUR\nClassificação CPV (Vocabulário Comum para os Contratos Públicos)\nObjeto principal\nVocabulário Principal: 80300000\nNº: LOT-0002\nDescrição do Lote: Lote 2\nPreço base s/IVA: 5.850,00 EUR\nClassificação CPV (Vocabulário Comum para os Contratos Públicos)\nObjeto principal\nVocabulário Principal: 80300000\nNº: LOT-0003\nDescrição do Lote: Lote 3\nPreço base s/IVA: 5.850,00 EUR\nClassificação CPV (Vocabulário Comum para os Contratos Públicos)\nObjeto principal\nVocabulário Principal: 80300000\nNº: LOT-0004\nDescrição do Lote: Lote 4\nPreço base s/IVA: 5.850,00 EUR\nClassificação CPV (Vocabulário Comum para os Contratos Públicos)\nObjeto principal\nVocabulário Principal: 80300000\nNº: LOT-0005\nDescrição do Lote: Lote 5\nPreço base s/IVA: 5.850,00 EUR\nClassificação CPV (Vocabulário Comum para os Contratos Públicos)\nObjeto principal\nVocabulário Principal: 80300000\nNº: LOT-0006\nDescrição do Lote: Lote 6\nPreço base s/IVA: 5.850,00 EUR\nClassificação CPV (Vocabulário Comum para os Contratos Públicos)\nObjeto principal\nVocabulário Principal: 80300000\nNº: LOT-0007\nDescrição do Lote: Lote 7\nPreço base s/IVA: 5.850,00 EUR\nClassificação CPV (Vocabulário Comum para os Contratos Públicos)\nObjeto principal\nVocabulário Principal: 80300000\nNº: LOT-0008\nDescrição do Lote: Lote 8\nPreço base s/IVA: 5.850,00 EUR\nClassificação CPV (Vocabulário Comum para os Contratos Públicos)\nObjeto principal\nVocabulário Principal: 80300000\n\n7 - INDICAÇÕES ADICIONAIS\nO contrato envolve aquisição conjunta (satisfação de várias entidades)? Não\nO contrato é adjudicado por uma central de compras? Não\n\n8 - TÉCNICAS\nO concurso destina-se à celebração de um acordo-quadro? Inexistência de acordo-quadro\nÉ utilizado um leilão eletrónico? Não\nÉ adotada uma fase de negociação? Não\nSistema de Aquisição Dinâmico: Inexistência de sistema de aquisição dinâmico\n\n9 - LOCAL DA EXECUÇÃO DO CONTRATO\nLOCAL DA EXECUÇÃO DO CONTRATO (PROCEDIMENTO)\nPaís: Portugal\nNUT III: PT11A\nLocalidade: Freguesia de Paranhos - Porto\nDistrito: Porto\nConcelho: Porto\nFreguesia: Freguesia de Paranhos - Porto\nLOCAL DA EXECUÇÃO DO CONTRATO (LOTE)\nIdentificador do Lote: LOT-0001; LOT-0002; LOT-0003; LOT-0004; LOT-0005; LOT-0006; LOT-0007; LOT-0008\nPaís: Portugal\nNUT III: PT11A\nLocalidade: Freguesia de Paranhos - Porto\nDistrito: Porto\nConcelho: Porto\nFreguesia: Freguesia de Paranhos - Porto\n\n10 - PRAZO DE EXECUÇÃO DO CONTRATO\nIdentificador do Lote: LOT-0001; LOT-0002; LOT-0003; LOT-0004; LOT-0005; LOT-0006; LOT-0007; LOT-0008\nPrazo de execução do contrato: 1095 DIAS\nPrevisão de renovações: Sim\nIndicar número máximo de renovações: 2\nPrazo de renovações diferente do prazo inicial: Não\n\n11 - FUNDOS EU\nIdentificador do Lote: LOT-0001; LOT-0002; LOT-0003; LOT-0004; LOT-0005; LOT-0006; LOT-0007; LOT-0008\nTêm fundos EU? Não\n\n12 - DOCUMENTOS DE HABILITAÇÃO\nHabilitação para o exercício da atividade profissional: Não\n\n13 - CONDIÇÕES DE APRESENTAÇÃO\nPlataforma eletrónica utilizada pela entidade adjudicante: ACIN\nURL para Apresentação: https://www.acingov.pt\nAdmissibilidade da apresentação de propostas variantes: Não autorizado\nPrazo para apresentação das propostas: 07-10-2025 17:00\nPrazo durante o qual os concorrentes são obrigados a manter as respetivas propostas: 90 dias a contar do termo do prazo para a apresentação das propostas\nIndicação de Subcontratação na Proposta: Inexistência de indicação de subcontratação\n\n14 - PRESTAÇÃO DE CAUÇÃO\nPrestação de caução: Não\n\n15 - FORNECIMENTO DAS PEÇAS DO CONCURSO, APRESENTAÇÃO DE PEDIDOS DE PARTICIPAÇÃO E APRESENTAÇÃO DAS PROPOSTAS\nLink para acesso às peças do concurso (URL): https://www.acingov.pt/acingovprod/2/zonaPublica/zona_publica_c/donwloadProcedurePiece/OTgxNTIw\n\n20 - OUTROS REQUISITOS\nIdentificador do Lote: LOT-0001; LOT-0002; LOT-0003; LOT-0004; LOT-0005; LOT-0006; LOT-0007; LOT-0008\nInformação sobre contratos reservados. Aplica-se a contratos reservados (54º-A)? Não\n\n21 - CRITÉRIO DE ADJUDICAÇÃO\nO Critério de adjudicação é diferenciado por lote? Não\nMultifator: Não\nMonofator:\nNome: Preço\n\n24 - CONDIÇÕES DO CONTRATO\nIdentificador do Lote: LOT-0001; LOT-0002; LOT-0003; LOT-0004; LOT-0005; LOT-0006; LOT-0007; LOT-0008\nFaturação Eletrónica: Permitido\nObrigação de Subcontratação:\nCódigo da Obrigação de Subcontratação: Não é aplicável nenhuma obrigação de subcontratação.\n\n25 - COMPRA PÚBLICA ESTRATÉGICA\nCompra Pública Estratégica: Inexistência de contratação pública estratégica\n\n26 - INFORMAÇÕES ADICIONAIS\nIdentificador do Lote: LOT-0001; LOT-0002; LOT-0003; LOT-0004; LOT-0005; LOT-0006; LOT-0007; LOT-0008\nContrato adequado para PME: Sim\nCobertura ACP (Acordo dos Contratos Públicos da Organização Mundial do Comércio): Não\n\n27 - IDENTIFICAÇÃO E CONTACTOS DO ÓRGÃO DE RECURSOS ADMINISTRATIVOS\nDesignação: Presidente\nEndereço: Rua Dr. António Bernardino de Almeida, 431\nCódigo postal: 4249-015\nLocalidade: PORTO\nTelefone: 228340500\nFax: 228321159\nEndereço eletrónico: info-sef@isep.ipp.pt\nPrazo de interposição do recurso: 5 dias\n\n28 - IDENTIFICAÇÃO DO(S) AUTOR(ES) DE ANÚNCIO\nNome: Carla Maria Oliveira Martins\nCargo: Assistente Técnico\n419602813",
    "nipc": "501540709",
    "distrito": "Porto",
    "concelho": "Porto",
    "freguesia": "Freguesia de Paranhos - Porto",
    "site": "https://www.isep.ipp.pt",
    "email": "info-sef@isep.ipp.pt",
    "designacao_contrato": "Contratação de Serviços de Formação a realizar no âmbito da Pós-Graduação em BigData & Decision Making, promovida pelo Departamento de Engenharia Informática do ISEP - Instituto Superior de Engenharia do Porto",
    "descricao": "Contratação de Serviços de Formação a realizar no âmbito da Pós-Graduação em BigData & Decision Making, promovida pelo Departamento de Engenharia Informática do ISEP - Instituto Superior de Engenharia do Porto",
    "preco_base": "46.800,00 EUR",
    "prazo_execucao": "1095 DIAS",
    "prazo_apresentacao_propostas": "07-10-2025 17:00",
    "fundos_eu": "Não",
    "plataforma_eletronica": "ACIN",
    "url_procedimento": "https://www.acingov.pt",
    "autor_nome": "Carla Maria Oliveira Martins",
    "autor_cargo": "Assistente Técnico"
  },
  {
    "numero_procedimento": "N/A",
    "entidade": "Instituto Superior de Engenharia do Porto",
    "link": "https://diariodarepublica.pt/dr/detalhe/contrato-publico/25881-937672808",
    "detalhes_completos": "1 - IDENTIFICAÇÃO E CONTACTOS DA ENTIDADE ADJUDICANTE\nDesignação da entidade adjudicante: Instituto Superior de Engenharia do Porto\nNIPC: 501540709\nServiço/Órgão/Pessoa de contacto: Serviços Economico-financeiros\nEndereço: Rua Dr. António Bernardino de Almeida, 431\nCódigo postal: 4249-015\nLocalidade: PORTO\nPaís: Portugal\nNUT III: PT11A\nDistrito: Porto\nConcelho: Porto\nFreguesia: Freguesia de Paranhos - Porto\nTelefone: 228340500\nFax: 228321159\nEndereço da Entidade (URL): https://www.isep.ipp.pt\nEndereço Eletrónico: info-sef@isep.ipp.pt\neDelivery Gateway (URL): https://www.acingov.pt\nFunção da Organização: Adquirente\nNorma jurídica da Entidade Adjudicante: Organismo de direito público\nÁrea de atividade da Autoridade Adjudicante: Educação\n\n2 - JORNAL OFICIAL DA UNIÃO EUROPEIA\nO procedimento a que este anúncio diz respeito também é publicitado no Jornal Oficial da União Europeia? Não\n\n3 - AVISO\nModelo de Anúncio: Concurso público\nData de Envio do Anúncio: 01-10-2025\n\n5 - PROCESSO\nTipo de Procedimento: Concurso público\nPreço base do procedimento: Sim\nValor do preço base do procedimento: 5.268,24 EUR\nProcedimento com lotes? Não\n\n6 - OBJETO DO CONTRATO\nNúmero de referência interna: 91/2025\nDesignação do contrato: Contratação de Serviços de Formação a realizar no âmbito da Pós-Graduação em Logística & SCM, promovida pelo Departamento de Engenharia Mecânica do ISEP - Instituto Superior de Engenharia do Porto\nDescrição: Contratação de Serviços de Formação a realizar no âmbito da Pós-Graduação em Logística & SCM, promovida pelo Departamento de Engenharia Mecânica do ISEP - Instituto Superior de Engenharia do Porto\nTipo de Contrato Principal: Aquisição de Serviços\nTipo de Contrato: Aquisição de Serviços\nClassificação CPV (Vocabulário Comum para os Contratos Públicos)\nObjeto principal\nVocabulário Principal: 80300000\nPreço base s/IVA: 5.268,24 EUR\n\n7 - INDICAÇÕES ADICIONAIS\nO contrato envolve aquisição conjunta (satisfação de várias entidades)? Não\nO contrato é adjudicado por uma central de compras? Não\n\n8 - TÉCNICAS\nO concurso destina-se à celebração de um acordo-quadro? Inexistência de acordo-quadro\nÉ utilizado um leilão eletrónico? Não\nÉ adotada uma fase de negociação? Não\nSistema de Aquisição Dinâmico: Inexistência de sistema de aquisição dinâmico\n\n9 - LOCAL DA EXECUÇÃO DO CONTRATO\nLOCAL DA EXECUÇÃO DO CONTRATO (PROCEDIMENTO)\nPaís: Portugal\nNUT III: PT11A\nLocalidade: Freguesia de Paranhos - Porto\nDistrito: Porto\nConcelho: Porto\nFreguesia: Freguesia de Paranhos - Porto\n\n10 - PRAZO DE EXECUÇÃO DO CONTRATO\nPrazo de execução do contrato: 822 DIAS\nPrevisão de renovações: Sim\nIndicar número máximo de renovações: 2\nPrazo de renovações diferente do prazo inicial: Sim\nIndicar o prazo de execução da renovação do contrato: 365 DIAS\n\n11 - FUNDOS EU\nTêm fundos EU? Não\n\n12 - DOCUMENTOS DE HABILITAÇÃO\nHabilitação para o exercício da atividade profissional: Não\n\n13 - CONDIÇÕES DE APRESENTAÇÃO\nPlataforma eletrónica utilizada pela entidade adjudicante: ACIN\nURL para Apresentação: https://www.acingov.pt\nAdmissibilidade da apresentação de propostas variantes: Não autorizado\nPrazo para apresentação das propostas: 07-10-2025 17:00\nPrazo durante o qual os concorrentes são obrigados a manter as respetivas propostas: 90 dias a contar do termo do prazo para a apresentação das propostas\nIndicação de Subcontratação na Proposta: Inexistência de indicação de subcontratação\n\n14 - PRESTAÇÃO DE CAUÇÃO\nPrestação de caução: Não\n\n15 - FORNECIMENTO DAS PEÇAS DO CONCURSO, APRESENTAÇÃO DE PEDIDOS DE PARTICIPAÇÃO E APRESENTAÇÃO DAS PROPOSTAS\nLink para acesso às peças do concurso (URL): https://www.acingov.pt/acingovprod/2/zonaPublica/zona_publica_c/donwloadProcedurePiece/OTgxNDM3\n\n20 - OUTROS REQUISITOS\nInformação sobre contratos reservados. Aplica-se a contratos reservados (54º-A)? Não\n\n21 - CRITÉRIO DE ADJUDICAÇÃO\nMultifator: Não\nMonofator:\nNome: Preço\n\n24 - CONDIÇÕES DO CONTRATO\nFaturação Eletrónica: Permitido\nObrigação de Subcontratação:\nCódigo da Obrigação de Subcontratação: Não é aplicável nenhuma obrigação de subcontratação.\n\n25 - COMPRA PÚBLICA ESTRATÉGICA\nCompra Pública Estratégica: Inexistência de contratação pública estratégica\n\n26 - INFORMAÇÕES ADICIONAIS\nContrato adequado para PME: Sim\nCobertura ACP (Acordo dos Contratos Públicos da Organização Mundial do Comércio): Não\n\n27 - IDENTIFICAÇÃO E CONTACTOS DO ÓRGÃO DE RECURSOS ADMINISTRATIVOS\nDesignação: Presidente\nEndereço: Rua Dr. António Bernardino de Almeida, 431\nCódigo postal: 4249-015\nLocalidade: PORTO\nTelefone: 228340500\nFax: 228321159\nEndereço eletrónico: info-sef@isep.ipp.pt\nPrazo de interposição do recurso: 5 dias\n\n28 - IDENTIFICAÇÃO DO(S) AUTOR(ES) DE ANÚNCIO\nNome: Carla Maria Oliveira Martins\nCargo: Assistente Técnico\n419602716",
    "nipc": "501540709",
    "distrito": "Porto",
    "concelho": "Porto",
    "freguesia": "Freguesia de Paranhos - Porto",
    "site": "https://www.isep.ipp.pt",
    "email": "info-sef@isep.ipp.pt",
    "designacao_contrato": "Contratação de Serviços de Formação a realizar no âmbito da Pós-Graduação em Logística & SCM, promovida pelo Departamento de Engenharia Mecânica do ISEP - Instituto Superior de Engenharia do Porto",
    "descricao": "Contratação de Serviços de Formação a realizar no âmbito da Pós-Graduação em Logística & SCM, promovida pelo Departamento de Engenharia Mecânica do ISEP - Instituto Superior de Engenharia do Porto",
    "preco_base": "5.268,24 EUR",
    "prazo_execucao": "822 DIAS",
    "prazo_apresentacao_propostas": "07-10-2025 17:00",
    "fundos_eu": "Não",
    "plataforma_eletronica": "ACIN",
    "url_procedimento": "https://www.acingov.pt",
    "autor_nome": "Carla Maria Oliveira Martins",
    "autor_cargo": "Assistente Técnico"
  },
  {
    "numero_procedimento": "N/A",
    "entidade": "Instituto Superior de Engenharia do Porto",
    "link": "https://diariodarepublica.pt/dr/detalhe/contrato-publico/25882-937672809",
    "detalhes_completos": "1 - IDENTIFICAÇÃO E CONTACTOS DA ENTIDADE ADJUDICANTE\nDesignação da entidade adjudicante: Instituto Superior de Engenharia do Porto\nNIPC: 501540709\nServiço/Órgão/Pessoa de contacto: Serviços Economico-financeiros\nEndereço: Rua Dr. António Bernardino de Almeida, 431\nCódigo postal: 4249-015\nLocalidade: PORTO\nPaís: Portugal\nNUT III: PT11A\nDistrito: Porto\nConcelho: Porto\nFreguesia: Freguesia de Paranhos - Porto\nTelefone: 228340500\nFax: 228321159\nEndereço da Entidade (URL): https://www.isep.ipp.pt\nEndereço Eletrónico: info-sef@isep.ipp.pt\neDelivery Gateway (URL): https://www.acingov.pt\nFunção da Organização: Adquirente\nNorma jurídica da Entidade Adjudicante: Organismo de direito público\nÁrea de atividade da Autoridade Adjudicante: Educação\n\n2 - JORNAL OFICIAL DA UNIÃO EUROPEIA\nO procedimento a que este anúncio diz respeito também é publicitado no Jornal Oficial da União Europeia? Não\n\n3 - AVISO\nModelo de Anúncio: Concurso público\nData de Envio do Anúncio: 01-10-2025\n\n5 - PROCESSO\nTipo de Procedimento: Concurso público\nPreço base do procedimento: Sim\nValor do preço base do procedimento: 38.220,00 EUR\nProcedimento com lotes? Sim\nNº Máx. de Lotes Autorizado: 11\nNúmero máximo de lotes que podem ser adjudicados a um concorrente: 11\n\n6 - OBJETO DO CONTRATO\nNúmero de referência interna: 93/2025\nDesignação do contrato: Contratação de Serviços de Formação a realizar no âmbito da Pós-Graduação em Segurança de Informação, Cibersegurança e Privacidade do ISEP - Instituto Superior de Engenharia do Porto\nDescrição: Contratação de Serviços de Formação a realizar no âmbito da Pós-Graduação em Segurança de Informação, Cibersegurança e Privacidade do ISEP - Instituto Superior de Engenharia do Porto\nTipo de Contrato Principal: Aquisição de Serviços\nTipo de Contrato: Aquisição de Serviços\nClassificação CPV (Vocabulário Comum para os Contratos Públicos)\nObjeto principal\nVocabulário Principal: 80300000\nPreço base s/IVA: 38.220,00 EUR\nLotes: \nNº: LOT-0001\nDescrição do Lote: LOTE 1\nPreço base s/IVA: 6.300,00 EUR\nClassificação CPV (Vocabulário Comum para os Contratos Públicos)\nObjeto principal\nVocabulário Principal: 80300000\nNº: LOT-0002\nDescrição do Lote: LOTE 2\nPreço base s/IVA: 2.940,00 EUR\nClassificação CPV (Vocabulário Comum para os Contratos Públicos)\nObjeto principal\nVocabulário Principal: 80300000\nNº: LOT-0003\nDescrição do Lote: LOTE 3\nPreço base s/IVA: 3.360,00 EUR\nClassificação CPV (Vocabulário Comum para os Contratos Públicos)\nObjeto principal\nVocabulário Principal: 80300000\nNº: LOT-0004\nDescrição do Lote: LOTE 4\nPreço base s/IVA: 2.940,00 EUR\nClassificação CPV (Vocabulário Comum para os Contratos Públicos)\nObjeto principal\nVocabulário Principal: 80300000\nNº: LOT-0005\nDescrição do Lote: LOTE 5\nPreço base s/IVA: 3.360,00 EUR\nClassificação CPV (Vocabulário Comum para os Contratos Públicos)\nObjeto principal\nVocabulário Principal: 80300000\nNº: LOT-0006\nDescrição do Lote: LOTE 6\nPreço base s/IVA: 2.940,00 EUR\nClassificação CPV (Vocabulário Comum para os Contratos Públicos)\nObjeto principal\nVocabulário Principal: 80300000\nNº: LOT-0007\nDescrição do Lote: LOTE 7\nPreço base s/IVA: 6.300,00 EUR\nClassificação CPV (Vocabulário Comum para os Contratos Públicos)\nObjeto principal\nVocabulário Principal: 80300000\nNº: LOT-0008\nDescrição do Lote: LOTE 8\nPreço base s/IVA: 6.300,00 EUR\nClassificação CPV (Vocabulário Comum para os Contratos Públicos)\nObjeto principal\nVocabulário Principal: 80300000\nNº: LOT-0009\nDescrição do Lote: LOTE 9\nPreço base s/IVA: 1.260,00 EUR\nClassificação CPV (Vocabulário Comum para os Contratos Públicos)\nObjeto principal\nVocabulário Principal: 80300000\nNº: LOT-0010\nDescrição do Lote: LOTE 10\nPreço base s/IVA: 1.260,00 EUR\nClassificação CPV (Vocabulário Comum para os Contratos Públicos)\nObjeto principal\nVocabulário Principal: 80300000\nNº: LOT-0011\nDescrição do Lote: LOTE 11\nPreço base s/IVA: 1.260,00 EUR\nClassificação CPV (Vocabulário Comum para os Contratos Públicos)\nObjeto principal\nVocabulário Principal: 80300000\n\n7 - INDICAÇÕES ADICIONAIS\nO contrato envolve aquisição conjunta (satisfação de várias entidades)? Não\nO contrato é adjudicado por uma central de compras? Não\n\n8 - TÉCNICAS\nO concurso destina-se à celebração de um acordo-quadro? Inexistência de acordo-quadro\nÉ utilizado um leilão eletrónico? Não\nÉ adotada uma fase de negociação? Não\nSistema de Aquisição Dinâmico: Inexistência de sistema de aquisição dinâmico\n\n9 - LOCAL DA EXECUÇÃO DO CONTRATO\nLOCAL DA EXECUÇÃO DO CONTRATO (PROCEDIMENTO)\nPaís: Portugal\nNUT III: PT11A\nLocalidade: Freguesia de Paranhos - Porto\nDistrito: Porto\nConcelho: Porto\nFreguesia: Freguesia de Paranhos - Porto\nLOCAL DA EXECUÇÃO DO CONTRATO (LOTE)\nIdentificador do Lote: LOT-0001; LOT-0002; LOT-0003; LOT-0004; LOT-0005; LOT-0006; LOT-0007; LOT-0008; LOT-0009; LOT-0010; LOT-0011\nPaís: Portugal\nNUT III: PT11A\nLocalidade: Freguesia de Paranhos - Porto\nDistrito: Porto\nConcelho: Porto\nFreguesia: Freguesia de Paranhos - Porto\n\n10 - PRAZO DE EXECUÇÃO DO CONTRATO\nIdentificador do Lote: LOT-0001; LOT-0002; LOT-0003; LOT-0004; LOT-0005; LOT-0006; LOT-0007; LOT-0008; LOT-0009; LOT-0010; LOT-0011\nPrazo de execução do contrato: 1095 DIAS\nPrevisão de renovações: Sim\nIndicar número máximo de renovações: 2\nPrazo de renovações diferente do prazo inicial: Não\n\n11 - FUNDOS EU\nIdentificador do Lote: LOT-0001; LOT-0002; LOT-0003; LOT-0004; LOT-0005; LOT-0006; LOT-0007; LOT-0008; LOT-0009; LOT-0010; LOT-0011\nTêm fundos EU? Não\n\n12 - DOCUMENTOS DE HABILITAÇÃO\nHabilitação para o exercício da atividade profissional: Não\n\n13 - CONDIÇÕES DE APRESENTAÇÃO\nPlataforma eletrónica utilizada pela entidade adjudicante: ACIN\nURL para Apresentação: https://www.acingov.pt\nAdmissibilidade da apresentação de propostas variantes: Não autorizado\nPrazo para apresentação das propostas: 07-10-2025 17:00\nPrazo durante o qual os concorrentes são obrigados a manter as respetivas propostas: 90 dias a contar do termo do prazo para a apresentação das propostas\nIndicação de Subcontratação na Proposta: Inexistência de indicação de subcontratação\n\n14 - PRESTAÇÃO DE CAUÇÃO\nPrestação de caução: Não\n\n15 - FORNECIMENTO DAS PEÇAS DO CONCURSO, APRESENTAÇÃO DE PEDIDOS DE PARTICIPAÇÃO E APRESENTAÇÃO DAS PROPOSTAS\nLink para acesso às peças do concurso (URL): https://www.acingov.pt/acingovprod/2/zonaPublica/zona_publica_c/donwloadProcedurePiece/OTgxNzA2\n\n20 - OUTROS REQUISITOS\nIdentificador do Lote: LOT-0001; LOT-0002; LOT-0003; LOT-0004; LOT-0005; LOT-0006; LOT-0007; LOT-0008; LOT-0009; LOT-0010; LOT-0011\nInformação sobre contratos reservados. Aplica-se a contratos reservados (54º-A)? Não\n\n21 - CRITÉRIO DE ADJUDICAÇÃO\nO Critério de adjudicação é diferenciado por lote? Não\nMultifator: Não\nMonofator:\nNome: Preço\n\n24 - CONDIÇÕES DO CONTRATO\nIdentificador do Lote: LOT-0001; LOT-0002; LOT-0003; LOT-0004; LOT-0005; LOT-0006; LOT-0007; LOT-0008; LOT-0009; LOT-0010; LOT-0011\nFaturação Eletrónica: Permitido\nObrigação de Subcontratação:\nCódigo da Obrigação de Subcontratação: Não é aplicável nenhuma obrigação de subcontratação.\n\n25 - COMPRA PÚBLICA ESTRATÉGICA\nCompra Pública Estratégica: Inexistência de contratação pública estratégica\n\n26 - INFORMAÇÕES ADICIONAIS\nIdentificador do Lote: LOT-0001; LOT-0002; LOT-0003; LOT-0004; LOT-0005; LOT-0006; LOT-0007; LOT-0008; LOT-0009; LOT-0010; LOT-0011\nContrato adequado para PME: Sim\nCobertura ACP (Acordo dos Contratos Públicos da Organização Mundial do Comércio): Não\n\n27 - IDENTIFICAÇÃO E CONTACTOS DO ÓRGÃO DE RECURSOS ADMINISTRATIVOS\nDesignação: Presidente\nEndereço: Rua Dr. António Bernardino de Almeida, 431\nCódigo postal: 4249-015\nLocalidade: PORTO\nTelefone: 228340500\nFax: 228321159\nEndereço eletrónico: info-sef@isep.ipp.pt\nPrazo de interposição do recurso: 5 dias\n\n28 - IDENTIFICAÇÃO DO(S) AUTOR(ES) DE ANÚNCIO\nNome: Carla Maria Oliveira Martins\nCargo: Assistente Técnico\n419602821",
    "nipc": "501540709",
    "distrito": "Porto",
    "concelho": "Porto",
    "freguesia": "Freguesia de Paranhos - Porto",
    "site": "https://www.isep.ipp.pt",
    "email": "info-sef@isep.ipp.pt",
    "designacao_contrato": "Contratação de Serviços de Formação a realizar no âmbito da Pós-Graduação em Segurança de Informação, Cibersegurança e Privacidade do ISEP - Instituto Superior de Engenharia do Porto",
    "descricao": "Contratação de Serviços de Formação a realizar no âmbito da Pós-Graduação em Segurança de Informação, Cibersegurança e Privacidade do ISEP - Instituto Superior de Engenharia do Porto",
    "preco_base": "38.220,00 EUR",
    "prazo_execucao": "1095 DIAS",
    "prazo_apresentacao_propostas": "07-10-2025 17:00",
    "fundos_eu": "Não",
    "plataforma_eletronica": "ACIN",
    "url_procedimento": "https://www.acingov.pt",
    "autor_nome": "Carla Maria Oliveira Martins",
    "autor_cargo": "Assistente Técnico"
  },
  {
    "numero_procedimento": "N/A",
    "entidade": "Município de Chaves",
    "link": "https://diariodarepublica.pt/dr/detalhe/contrato-publico/25884-937672810",
    "detalhes_completos": "1 - IDENTIFICAÇÃO E CONTACTOS DA ENTIDADE ADJUDICANTE\nDesignação da entidade adjudicante: Município de Chaves\nNIPC: 501205551\nEndereço: Praça de Camões\nCódigo postal: 5400-150\nLocalidade: Vila Real\nPaís: Portugal\nNUT III: PT11B\nDistrito: Vila Real\nConcelho: Chaves\nFreguesia: Freguesia de Santa Maria Maior - Chaves\nTelefone: 276340500\nFax: 276327724\nEndereço da Entidade (URL): www.chaves.pt\nEndereço Eletrónico: municipio@chaves.pt\neDelivery Gateway (URL): https://community.vortal.biz/public/\nFunção da Organização: Adquirente\nNorma jurídica da Entidade Adjudicante: Autoridade local\nÁrea de atividade da Autoridade Adjudicante: Serviços públicos das administrações públicas\n\n2 - JORNAL OFICIAL DA UNIÃO EUROPEIA\nO procedimento a que este anúncio diz respeito também é publicitado no Jornal Oficial da União Europeia? Não\n\n3 - AVISO\nModelo de Anúncio: Concurso público\nData de Envio do Anúncio: 01-10-2025\n\n5 - PROCESSO\nTipo de Procedimento: Concurso público\nPreço base do procedimento: Sim\nValor do preço base do procedimento: 125.800,00 EUR\nProcedimento com lotes? Não\n\n6 - OBJETO DO CONTRATO\nNúmero de referência interna: CP 24/DCP/2025\nDesignação do contrato: Prestação de serviços de aluguer, montagem e desmontagem da iluminação de Natal para o ano 2025\nDescrição: Prestação de serviços de aluguer, montagem e desmontagem da iluminação de Natal para o ano 2025\nTipo de Contrato Principal: Aquisição de Serviços\nTipo de Contrato: Aquisição de Serviços\nClassificação CPV (Vocabulário Comum para os Contratos Públicos)\nObjeto principal\nVocabulário Principal: 71318100\nPreço base s/IVA: 125.800,00 EUR\n\n7 - INDICAÇÕES ADICIONAIS\nO contrato envolve aquisição conjunta (satisfação de várias entidades)? Não\nO contrato é adjudicado por uma central de compras? Não\n\n8 - TÉCNICAS\nO concurso destina-se à celebração de um acordo-quadro? Inexistência de acordo-quadro\nÉ utilizado um leilão eletrónico? Não\nÉ adotada uma fase de negociação? Não\nSistema de Aquisição Dinâmico: Inexistência de sistema de aquisição dinâmico\n\n9 - LOCAL DA EXECUÇÃO DO CONTRATO\nLOCAL DA EXECUÇÃO DO CONTRATO (PROCEDIMENTO)\nPaís: Portugal\nNUT III: PT11B\nLocalidade: Vila Real\nDistrito: Vila Real\nConcelho: Chaves\nFreguesia: Freguesia de Santa Maria Maior - Chaves\n\n10 - PRAZO DE EXECUÇÃO DO CONTRATO\nPrazo de execução do contrato: 91 DIAS\nPrevisão de renovações: Não\n\n11 - FUNDOS EU\nTêm fundos EU? Não\n\n12 - DOCUMENTOS DE HABILITAÇÃO\nHabilitação para o exercício da atividade profissional: Não\n\n13 - CONDIÇÕES DE APRESENTAÇÃO\nPlataforma eletrónica utilizada pela entidade adjudicante: VORTAL\nURL para Apresentação: https://community.vortal.biz/public/\nAdmissibilidade da apresentação de propostas variantes: Não autorizado\nPrazo para apresentação das propostas: 07-10-2025 17:30\nPrazo durante o qual os concorrentes são obrigados a manter as respetivas propostas: 66 dias a contar do termo do prazo para a apresentação das propostas\nIndicação de Subcontratação na Proposta: Inexistência de indicação de subcontratação\n\n14 - PRESTAÇÃO DE CAUÇÃO\nPrestação de caução: Não\n\n15 - FORNECIMENTO DAS PEÇAS DO CONCURSO, APRESENTAÇÃO DE PEDIDOS DE PARTICIPAÇÃO E APRESENTAÇÃO DAS PROPOSTAS\nLink para acesso às peças do concurso (URL): https://community.vortal.biz/Public/public-tender-documents/dlB1US9WMmlHNTFUSkdkL0FjZVdJWkVVWkpDOGFvblhTd3MvaDBNampaT0cxL3NKS2UvUUpFeGl1Q0J3YUh0bFBuZERLZnUySWR1Mm1nTkZ0MWRTblE9PUpfa29f\n\n20 - OUTROS REQUISITOS\nInformação sobre contratos reservados. Aplica-se a contratos reservados (54º-A)? Não\n\n21 - CRITÉRIO DE ADJUDICAÇÃO\nMultifator: Não\nMonofator:\nNome: Preço\n\n24 - CONDIÇÕES DO CONTRATO\nFaturação Eletrónica: Permitido\nObrigação de Subcontratação:\nCódigo da Obrigação de Subcontratação: Não é aplicável nenhuma obrigação de subcontratação.\n\n25 - COMPRA PÚBLICA ESTRATÉGICA\nCompra Pública Estratégica: Inexistência de contratação pública estratégica\n\n26 - INFORMAÇÕES ADICIONAIS\nContrato adequado para PME: Sim\nCobertura ACP (Acordo dos Contratos Públicos da Organização Mundial do Comércio): Não\n\n27 - IDENTIFICAÇÃO E CONTACTOS DO ÓRGÃO DE RECURSOS ADMINISTRATIVOS\nDesignação: Presidente da Câmara Municipal de Chaves\nEndereço: Praça de Camões.\nCódigo postal: 5400-150\nLocalidade: Chaves\nTelefone: +351 276340500\nFax: +351 276340500\nEndereço eletrónico: municipio@chaves.pt\n\n28 - IDENTIFICAÇÃO DO(S) AUTOR(ES) DE ANÚNCIO\nNome: Nuno Vaz Ribeiro \nCargo: Presidente da Câmara Municipal \n419599834",
    "nipc": "501205551",
    "distrito": "Vila Real",
    "concelho": "Chaves",
    "freguesia": "Freguesia de Santa Maria Maior - Chaves",
    "site": "www.chaves.pt",
    "email": "municipio@chaves.pt",
    "designacao_contrato": "Prestação de serviços de aluguer, montagem e desmontagem da iluminação de Natal para o ano 2025",
    "descricao": "Prestação de serviços de aluguer, montagem e desmontagem da iluminação de Natal para o ano 2025",
    "preco_base": "125.800,00 EUR",
    "prazo_execucao": "91 DIAS",
    "prazo_apresentacao_propostas": "07-10-2025 17:30",
    "fundos_eu": "Não",
    "plataforma_eletronica": "VORTAL",
    "url_procedimento": "https://community.vortal.biz/public/",
    "autor_nome": "Nuno Vaz Ribeiro",
    "autor_cargo": "Presidente da Câmara Municipal"
  },
  {
    "numero_procedimento": "N/A",
    "entidade": "Teatro Nacional São João, E.P.E.",
    "link": "https://diariodarepublica.pt/dr/detalhe/contrato-publico/25885-937675907",
    "detalhes_completos": "Alteração do Anúncio de procedimento n.º 24821/2025, de 2025-09-19, com o ID 419556506\n\n1 - IDENTIFICAÇÃO E CONTACTOS DA ENTIDADE ADJUDICANTE\nDesignação da entidade adjudicante: Teatro Nacional São João, E.P.E.\nNIPC: 503966908\nServiço/Órgão/Pessoa de contacto: Departamento de Contratação Pública\nEndereço: Praça da Batalha\nCódigo postal: 4000-102\nLocalidade: Porto\nPaís: Portugal\nNUT III: PT11A\nDistrito: Porto\nConcelho: Porto\nFreguesia: União das Freguesias de Cedofeita, Santo Ildefonso, Sé, Miragaia, São Nicolau e Vitória\nTelefone: 223401900\nFax: 222003449\nEndereço da Entidade (URL): https://www.acingov.pt\nEndereço Eletrónico: geral@tnsj.pt\neDelivery Gateway (URL): https://www.acingov.pt\nFunção da Organização: Adquirente\nNorma jurídica da Entidade Adjudicante: Empresa pública, controlada por uma autoridade da administração central\nÁrea de atividade da Autoridade Adjudicante: Atividades recreativas, culturais e religiosas\n\n2 - JORNAL OFICIAL DA UNIÃO EUROPEIA\nO procedimento a que este anúncio diz respeito também é publicitado no Jornal Oficial da União Europeia? Não\n\n3 - AVISO\nModelo de Anúncio: Concurso público\nData de Envio do Anúncio: 01-10-2025\n\n5 - PROCESSO\nTipo de Procedimento: Concurso público\nPreço base do procedimento: Sim\nValor do preço base do procedimento: 3.443.798,58 EUR\nProcedimento com lotes? Não\n\n6 - OBJETO DO CONTRATO\nNúmero de referência interna: 91/CPN/2025\nDesignação do contrato: Empreitada de Requalificação das Coberturas do Mosteiro de S. Bento da Vitória e Outros Trabalhos\nDescrição: Empreitada de Requalificação das Coberturas do Mosteiro de S. Bento da Vitória e Outros Trabalhos\nTipo de Contrato Principal: Empreitada de Obras Públicas\nTipo de Contrato: Empreitada de Obras Públicas\nClassificação CPV (Vocabulário Comum para os Contratos Públicos)\nObjeto principal\nVocabulário Principal: 45453100\nPreço base s/IVA: 3.443.798,58 EUR\n\n7 - INDICAÇÕES ADICIONAIS\nO contrato envolve aquisição conjunta (satisfação de várias entidades)? Não\nO contrato é adjudicado por uma central de compras? Não\n\n8 - TÉCNICAS\nO concurso destina-se à celebração de um acordo-quadro? Inexistência de acordo-quadro\nÉ utilizado um leilão eletrónico? Não\nÉ adotada uma fase de negociação? Não\nSistema de Aquisição Dinâmico: Inexistência de sistema de aquisição dinâmico\n\n9 - LOCAL DA EXECUÇÃO DO CONTRATO\nLOCAL DA EXECUÇÃO DO CONTRATO (PROCEDIMENTO)\nPaís: Portugal\nNUT III: PT11A\nLocalidade: União das Freguesias de Cedofeita, Santo Ildefonso, Sé, Miragaia, São Nicolau e Vitória\nDistrito: Porto\nConcelho: Porto\nFreguesia: União das Freguesias de Cedofeita, Santo Ildefonso, Sé, Miragaia, São Nicolau e Vitória\n\n10 - PRAZO DE EXECUÇÃO DO CONTRATO\nPrazo de execução do contrato: 240 DIAS\nPrevisão de renovações: Não\n\n11 - FUNDOS EU\nTêm fundos EU? Sim\n\n12 - DOCUMENTOS DE HABILITAÇÃO\nHabilitação para o exercício da atividade profissional: Sim\nTipo: Alvará\nDescrição: A Subcategoria 5 da 1.ª Categoria (Edifícios e Património Construído), em classe correspondente ao valor global da proposta;\nAs Subcategorias 1, 2, 4, 6, 7 e 8 da 1.ª Categoria (Edifícios e Património Construído), da classe correspondente ao valor dos trabalhos especializados que lhes correspondam;\nAs Subcategorias 3, 9, 10, 11, 12 e 18 da 4.ª Categoria (Instalações Elétricas e Mecânicas), da classe correspondente ao valor dos trabalhos especializados que lhes correspondam;\nAs Subcategorias 1, 2, 5, 8, 9, 10, 11 e 12 da 5.ª Categoria (Outros Trabalhos), da classe correspondente ao valor dos trabalhos especializados que lhes correspondam.\n\n13 - CONDIÇÕES DE APRESENTAÇÃO\nPlataforma eletrónica utilizada pela entidade adjudicante: ACIN\nURL para Apresentação: https://www.acingov.pt\nAdmissibilidade da apresentação de propostas variantes: Não autorizado\nPrazo para apresentação das propostas: 25-10-2025 10:00\nPrazo durante o qual os concorrentes são obrigados a manter as respetivas propostas: 90 dias a contar do termo do prazo para a apresentação das propostas\nIndicação de Subcontratação na Proposta: A parte do contrato que o proponente tenciona subcontratar\n\n14 - PRESTAÇÃO DE CAUÇÃO\nPrestação de caução: Sim\nPercentagem: 5%\nDescrição da Garantia Exigida: O valor da caução é de 5.00% do preço contratual.\n\n15 - FORNECIMENTO DAS PEÇAS DO CONCURSO, APRESENTAÇÃO DE PEDIDOS DE PARTICIPAÇÃO E APRESENTAÇÃO DAS PROPOSTAS\nLink para acesso às peças do concurso (URL): https://www.acingov.pt/acingovprod/2/zonaPublica/zona_publica_c/donwloadProcedurePiece/OTc3NzEz\n\n20 - OUTROS REQUISITOS\nInformação sobre contratos reservados. Aplica-se a contratos reservados (54º-A)? Não\n\n21 - CRITÉRIO DE ADJUDICAÇÃO\nMultifator: Não\nMonofator:\nNome: Preço\n\n24 - CONDIÇÕES DO CONTRATO\nFaturação Eletrónica: Necessário\nObrigação de Subcontratação:\nCódigo da Obrigação de Subcontratação: Não é aplicável nenhuma obrigação de subcontratação.\n\n25 - COMPRA PÚBLICA ESTRATÉGICA\nCompra Pública Estratégica: Inexistência de contratação pública estratégica\n\n26 - INFORMAÇÕES ADICIONAIS\nContrato adequado para PME: Sim\nCobertura ACP (Acordo dos Contratos Públicos da Organização Mundial do Comércio): Sim\n\n27 - IDENTIFICAÇÃO E CONTACTOS DO ÓRGÃO DE RECURSOS ADMINISTRATIVOS\nDesignação: Conselho de Administração do TNSJ\nEndereço: Praça da Batalha\nCódigo postal: 4000-102\nLocalidade: Porto\nTelefone: 223401900\nFax: 222003449\nEndereço eletrónico: contratacaopublica@tnsj.pt\n\n28 - IDENTIFICAÇÃO DO(S) AUTOR(ES) DE ANÚNCIO\nNome: Pedro Sobrado\nCargo: Presidente do Conselho de Administração\n\n29 - ALTERAÇÃO\nMotivo da Alteração: Correção pelo adquirente\nIdentificador da Versão do Anúncio a Alterar: 516d0d8b-0792-4f93-a466-a8ccec37f840-01\nIdentificador das Secções Alteradas do Anúncio Anterior: Documentos de habilitação; Condições de Apresentação\nDescrição das Alterações: Modificação do prazo para a apresentação de propostas; Documentos de habilitação (Alvarás exigíveis)\nAlteração dos Documentos do Concurso: Sim\nData de alteração dos documentos do concurso: 01-10-2025\n419602902",
    "nipc": "503966908",
    "distrito": "Porto",
    "concelho": "Porto",
    "freguesia": "União das Freguesias de Cedofeita, Santo Ildefonso, Sé, Miragaia, São Nicolau e Vitória",
    "site": "https://www.acingov.pt",
    "email": "geral@tnsj.pt",
    "designacao_contrato": "Empreitada de Requalificação das Coberturas do Mosteiro de S. Bento da Vitória e Outros Trabalhos",
    "descricao": "Empreitada de Requalificação das Coberturas do Mosteiro de S. Bento da Vitória e Outros Trabalhos",
    "preco_base": "3.443.798,58 EUR",
    "prazo_execucao": "240 DIAS",
    "prazo_apresentacao_propostas": "25-10-2025 10:00",
    "fundos_eu": "Sim",
    "plataforma_eletronica": "ACIN",
    "url_procedimento": "https://www.acingov.pt",
    "autor_nome": "Pedro Sobrado",
    "autor_cargo": "Presidente do Conselho de Administração"
  },
  {
    "numero_procedimento": "N/A",
    "entidade": "Águas do Norte, S.A.",
    "link": "https://diariodarepublica.pt/dr/detalhe/contrato-publico/25886-937675908",
    "detalhes_completos": "1 - IDENTIFICAÇÃO E CONTACTOS DA ENTIDADE ADJUDICANTE\nDesignação da entidade adjudicante: Águas do Norte, S.A.\nNIPC: 513606084\nEndereço: Rua Dom Pedro de Castro, N.º 1A\nCódigo postal: 5000-669\nLocalidade: Vila Real\nPaís: Portugal\nNUT III: PT11D\nDistrito: Vila Real\nConcelho: Vila Real\nFreguesia: Todas\nTelefone: 259309370\nFax: 259309371\nEndereço da Entidade (URL): www.adnorte.pt\nEndereço Eletrónico: geral.adnorte@adp.pt\neDelivery Gateway (URL): https://www.acingov.pt\nFunção da Organização: Adquirente\nNorma jurídica da Entidade Adjudicante: Organismo de direito público\nÁrea de atividade da Autoridade Adjudicante: Serviços públicos das administrações públicas\n\n2 - JORNAL OFICIAL DA UNIÃO EUROPEIA\nO procedimento a que este anúncio diz respeito também é publicitado no Jornal Oficial da União Europeia? Não\n\n3 - AVISO\nModelo de Anúncio: Concurso público\nData de Envio do Anúncio: 02-10-2025\n\n5 - PROCESSO\nTipo de Procedimento: Concurso público\nPreço base do procedimento: Não\nProcedimento com lotes? Não\n\n6 - OBJETO DO CONTRATO\nNúmero de referência interna: PRC_0301/2025_GAE-O1266\nDesignação do contrato: PRC_0301/2025_GAE-O1266 - Acordo-Quadro para Empreitada Geral para Intervenções de Manutenção e Reparação nos SAA e SAR em Alta da Águas do Norte, S.A. e Outras Intervenções no Alto Tâmega e Douro Norte\nDescrição: PRC_0301/2025_GAE-O1266 - Acordo-Quadro para Empreitada Geral para Intervenções de Manutenção e Reparação nos SAA e SAR em Alta da Águas do Norte, S.A. e Outras Intervenções no Alto Tâmega e Douro Norte\nTipo de Contrato Principal: Empreitada de Obras Públicas\nTipo de Contrato: Empreitada de Obras Públicas\nClassificação CPV (Vocabulário Comum para os Contratos Públicos)\nObjeto principal\nVocabulário Principal: 45232000\n\n7 - INDICAÇÕES ADICIONAIS\nO contrato envolve aquisição conjunta (satisfação de várias entidades)? Não\nO contrato é adjudicado por uma central de compras? Não\n\n8 - TÉCNICAS\nO concurso destina-se à celebração de um acordo-quadro? Acordo-quadro, sem reabertura de concurso\nModalidade: Com uma entidade\nPrazo de vigência: 36 meses\nValor estimado: Sim\nPara Acordo-Quadro — valor total máximo estimado para toda a duração do Acordo-Quadro: 300.000,00 EUR\nÉ utilizado um leilão eletrónico? Não\nÉ adotada uma fase de negociação? Não\nSistema de Aquisição Dinâmico: Inexistência de sistema de aquisição dinâmico\n\n9 - LOCAL DA EXECUÇÃO DO CONTRATO\nLOCAL DA EXECUÇÃO DO CONTRATO (PROCEDIMENTO)\nPaís: Portugal\nNUT III: PT11D\nLocalidade: Alijó\nDistrito: Vila Real\nConcelho: Alijó\nFreguesia: Todas\nPaís: Portugal\nNUT III: PT11B\nLocalidade: Boticas\nDistrito: Vila Real\nConcelho: Boticas\nFreguesia: Todas\nPaís: Portugal\nNUT III: PT11B\nLocalidade: Chaves\nDistrito: Vila Real\nConcelho: Chaves\nFreguesia: Todas\nPaís: Portugal\nNUT III: PT11D\nLocalidade: Mesão Frio\nDistrito: Vila Real\nConcelho: Mesão Frio\nFreguesia: Todas\nPaís: Portugal\nNUT III: PT11B\nLocalidade: Montalegre\nDistrito: Vila Real\nConcelho: Montalegre\nFreguesia: Todas\nPaís: Portugal\nNUT III: PT11D\nLocalidade: Murça\nDistrito: Vila Real\nConcelho: Murça\nFreguesia: Todas\nPaís: Portugal\nNUT III: PT11D\nLocalidade: Peso da Régua\nDistrito: Vila Real\nConcelho: Peso da Régua\nFreguesia: Todas\nPaís: Portugal\nNUT III: PT11B\nLocalidade: Ribeira de Pena\nDistrito: Vila Real\nConcelho: Ribeira de Pena\nFreguesia: Todas\nPaís: Portugal\nNUT III: PT11D\nLocalidade: Sabrosa\nDistrito: Vila Real\nConcelho: Sabrosa\nFreguesia: Todas\nPaís: Portugal\nNUT III: PT11B\nLocalidade: Valpaços\nDistrito: Vila Real\nConcelho: Valpaços\nFreguesia: Todas\nPaís: Portugal\nNUT III: PT11B\nLocalidade: Vila Pouca de Aguiar\nDistrito: Vila Real\nConcelho: Vila Pouca de Aguiar\nFreguesia: Todas\nPaís: Portugal\nNUT III: PT11D\nLocalidade: Vila Real\nDistrito: Vila Real\nConcelho: Vila Real\nFreguesia: Todas\nPaís: Portugal\nNUT III: PT11D\nLocalidade: Santa Marta de Penaguião\nDistrito: Vila Real\nConcelho: Sta Marta de Penaguião\nFreguesia: Todas\n\n10 - PRAZO DE EXECUÇÃO DO CONTRATO\nPrazo de execução do contrato: 1095 DIAS\nPrevisão de renovações: Não\n\n11 - FUNDOS EU\nTêm fundos EU? Não\n\n12 - DOCUMENTOS DE HABILITAÇÃO\nHabilitação para o exercício da atividade profissional: Sim\nTipo: Alvará\nDescrição: Documentos de Habilitação\n\n13 - CONDIÇÕES DE APRESENTAÇÃO\nPlataforma eletrónica utilizada pela entidade adjudicante: ACIN\nURL para Apresentação: https://www.acingov.pt\nAdmissibilidade da apresentação de propostas variantes: Não autorizado\nPrazo para apresentação das propostas: 16-10-2025 17:00\nPrazo durante o qual os concorrentes são obrigados a manter as respetivas propostas: 90 dias a contar do termo do prazo para a apresentação das propostas\nIndicação de Subcontratação na Proposta: Inexistência de indicação de subcontratação\n\n14 - PRESTAÇÃO DE CAUÇÃO\nPrestação de caução: Sim\nPercentagem: 1.67%\nDescrição da Garantia Exigida: O valor da caução será de 5.000,00 EUROS\n\n15 - FORNECIMENTO DAS PEÇAS DO CONCURSO, APRESENTAÇÃO DE PEDIDOS DE PARTICIPAÇÃO E APRESENTAÇÃO DAS PROPOSTAS\nLink para acesso às peças do concurso (URL): https://www.acingov.pt/acingovprod/2/zonaPublica/zona_publica_c/donwloadProcedurePiece/OTgyNjY4\n\n20 - OUTROS REQUISITOS\nInformação sobre contratos reservados. Aplica-se a contratos reservados (54º-A)? Não\n\n21 - CRITÉRIO DE ADJUDICAÇÃO\nMultifator: Não\nMonofator:\nNome: Preço\n\n24 - CONDIÇÕES DO CONTRATO\nFaturação Eletrónica: Permitido\nObrigação de Subcontratação:\nCódigo da Obrigação de Subcontratação: Não é aplicável nenhuma obrigação de subcontratação.\n\n25 - COMPRA PÚBLICA ESTRATÉGICA\nCompra Pública Estratégica: Inexistência de contratação pública estratégica\n\n26 - INFORMAÇÕES ADICIONAIS\nContrato adequado para PME: Não\nCobertura ACP (Acordo dos Contratos Públicos da Organização Mundial do Comércio): Não\n\n27 - IDENTIFICAÇÃO E CONTACTOS DO ÓRGÃO DE RECURSOS ADMINISTRATIVOS\nDesignação: Conselho de Administração da Águas do Norte, S.A.\nEndereço: Rua Dom Pedro de Castro, N.º 1A\nCódigo postal: 5000-669\nLocalidade: Vila Real\nTelefone: 259309370\nFax: 259309371\nEndereço eletrónico: geral.adnorte@adp.pt\nPrazo de interposição do recurso: 5 dias\n\n28 - IDENTIFICAÇÃO DO(S) AUTOR(ES) DE ANÚNCIO\nNome: Alexandra Bezelga\nCargo: Técnica Superior de Gestão de Ativos e Engenharia\n419598432",
    "nipc": "513606084",
    "distrito": "Vila Real",
    "concelho": "Vila Real",
    "freguesia": "Todas",
    "site": "www.adnorte.pt",
    "email": "geral.adnorte@adp.pt",
    "designacao_contrato": "PRC_0301/2025_GAE-O1266 - Acordo-Quadro para Empreitada Geral para Intervenções de Manutenção e Reparação nos SAA e SAR em Alta da Águas do Norte, S.A. e Outras Intervenções no Alto Tâmega e Douro Norte",
    "descricao": "PRC_0301/2025_GAE-O1266 - Acordo-Quadro para Empreitada Geral para Intervenções de Manutenção e Reparação nos SAA e SAR em Alta da Águas do Norte, S.A. e Outras Intervenções no Alto Tâmega e Douro Norte",
    "preco_base": null,
    "prazo_execucao": "1095 DIAS",
    "prazo_apresentacao_propostas": "16-10-2025 17:00",
    "fundos_eu": "Não",
    "plataforma_eletronica": "ACIN",
    "url_procedimento": "https://www.acingov.pt",
    "autor_nome": "Alexandra Bezelga",
    "autor_cargo": "Técnica Superior de Gestão de Ativos e Engenharia"
  },
  {
    "numero_procedimento": "N/A",
    "entidade": "Comunidade Intermunicipal da Região de Coimbra",
    "link": "https://diariodarepublica.pt/dr/detalhe/contrato-publico/25887-937675909",
    "detalhes_completos": "1 - IDENTIFICAÇÃO E CONTACTOS DA ENTIDADE ADJUDICANTE\nDesignação da entidade adjudicante: Comunidade Intermunicipal da Região de Coimbra\nNIPC: 508354617\nEndereço: Rua do Brasil, 131\nCódigo postal: 3030-175\nLocalidade: Coimbra\nPaís: Portugal\nNUT III: PTZZZ\nDistrito: Todos\nConcelho: Todos\nFreguesia: Todas\nTelefone: 239795200\nEndereço da Entidade (URL): https://cim-regiaodecoimbra.pt\nEndereço Eletrónico: geral@cim-regiaodecoimbra.pt\neDelivery Gateway (URL): https://www.acingov.pt\nFunção da Organização: Adquirente\nNorma jurídica da Entidade Adjudicante: Organismo de direito público\nÁrea de atividade da Autoridade Adjudicante: Serviços públicos das administrações públicas\n\n2 - JORNAL OFICIAL DA UNIÃO EUROPEIA\nO procedimento a que este anúncio diz respeito também é publicitado no Jornal Oficial da União Europeia? Sim\n\n3 - AVISO\nModelo de Anúncio: Concurso público\nData de Envio do Anúncio: 30-09-2025\n\n5 - PROCESSO\nTipo de Procedimento: Concurso público\nPreço base do procedimento: Sim\nValor do preço base do procedimento: 1.037.735,85 EUR\nProcedimento com lotes? Sim\nNº Máx. de Lotes Autorizado: 4\nNúmero máximo de lotes que podem ser adjudicados a um concorrente: 4\n\n6 - OBJETO DO CONTRATO\nNúmero de referência interna: CP19/2025\nDesignação do contrato: CP19/2025 - Aquisição de Veículos Multilift e respetivos Módulos\nDescrição: CP19/2025 - Aquisição de Veículos Multilift e respetivos Módulos\nOpções: Não\nTipo de Contrato Principal: Aquisição de Bens Móveis\nTipo de Contrato: Aquisição de Bens Móveis\nClassificação CPV (Vocabulário Comum para os Contratos Públicos)\nObjeto principal\nVocabulário Principal: 34144210\nPreço base s/IVA: 1.037.735,85 EUR\nLotes: \nNº: LOT-0001\nDescrição do Lote: Aquisição de 2 Veículos Multilift\nPreço base s/IVA: 471.698,10 EUR\nClassificação CPV (Vocabulário Comum para os Contratos Públicos)\nObjeto principal\nVocabulário Principal: 34144210\nNº: LOT-0002\nDescrição do Lote: Aquisição de 1 Módulo Energético\nPreço base s/IVA: 188.679,25 EUR\nClassificação CPV (Vocabulário Comum para os Contratos Públicos)\nObjeto principal\nVocabulário Principal: 34144210\nNº: LOT-0003\nDescrição do Lote: Aquisição de 1 Módulo de Cheias e Inundações\nPreço base s/IVA: 188.679,25 EUR\nClassificação CPV (Vocabulário Comum para os Contratos Públicos)\nObjeto principal\nVocabulário Principal: 34144210\nNº: LOT-0004\nDescrição do Lote: Aquisição de 2 Módulos de Incêndios Rurais\nPreço base s/IVA: 188.679,25 EUR\nClassificação CPV (Vocabulário Comum para os Contratos Públicos)\nObjeto principal\nVocabulário Principal: 34144210\n\n7 - INDICAÇÕES ADICIONAIS\nO contrato envolve aquisição conjunta (satisfação de várias entidades)? Não\nO contrato é adjudicado por uma central de compras? Não\n\n8 - TÉCNICAS\nO concurso destina-se à celebração de um acordo-quadro? Inexistência de acordo-quadro\nÉ utilizado um leilão eletrónico? Não\nÉ adotada uma fase de negociação? Não\nSistema de Aquisição Dinâmico: Inexistência de sistema de aquisição dinâmico\n\n9 - LOCAL DA EXECUÇÃO DO CONTRATO\nLOCAL DA EXECUÇÃO DO CONTRATO (PROCEDIMENTO)\nPaís: Portugal\nNUT III: PT16E\nLocalidade: Freguesia de Santo António dos Olivais\nDistrito: Coimbra\nConcelho: Coimbra\nFreguesia: Freguesia de Santo António dos Olivais\nLOCAL DA EXECUÇÃO DO CONTRATO (LOTE)\nIdentificador do Lote: LOT-0001; LOT-0002; LOT-0003; LOT-0004\nPaís: Portugal\nNUT III: PT16E\nLocalidade: Freguesia de Santo António dos Olivais\nDistrito: Coimbra\nConcelho: Coimbra\nFreguesia: Freguesia de Santo António dos Olivais\n\n10 - PRAZO DE EXECUÇÃO DO CONTRATO\nIdentificador do Lote: LOT-0001; LOT-0002; LOT-0003; LOT-0004\nPrazo de execução do contrato: 395 DIAS\nPrevisão de renovações: Não\n\n11 - FUNDOS EU\nIdentificador do Lote: LOT-0001; LOT-0002; LOT-0003; LOT-0004\nTêm fundos EU? Sim\n\n12 - DOCUMENTOS DE HABILITAÇÃO\nHabilitação para o exercício da atividade profissional: Não\n\n13 - CONDIÇÕES DE APRESENTAÇÃO\nPlataforma eletrónica utilizada pela entidade adjudicante: ACIN\nURL para Apresentação: https://www.acingov.pt\nAdmissibilidade da apresentação de propostas variantes: Não autorizado\nPrazo para apresentação das propostas: 31-10-2025 23:59\nPrazo durante o qual os concorrentes são obrigados a manter as respetivas propostas: 120 dias a contar do termo do prazo para a apresentação das propostas\nApresentação de Catálogo Eletrónico: Permitido\nIndicação de Subcontratação na Proposta: Inexistência de indicação de subcontratação\n\n14 - PRESTAÇÃO DE CAUÇÃO\nPrestação de caução: Sim\nPercentagem: 5%\nDescrição da Garantia Exigida: O valor da caução é de 5.00% do preço contratual.\n\n15 - FORNECIMENTO DAS PEÇAS DO CONCURSO, APRESENTAÇÃO DE PEDIDOS DE PARTICIPAÇÃO E APRESENTAÇÃO DAS PROPOSTAS\nLink para acesso às peças do concurso (URL): https://www.acingov.pt/acingovprod/2/zonaPublica/zona_publica_c/donwloadProcedurePiece/OTgyMDEx\n\n20 - OUTROS REQUISITOS\nIdentificador do Lote: LOT-0001; LOT-0002; LOT-0003; LOT-0004\nInformação sobre contratos reservados. Aplica-se a contratos reservados (54º-A)? Não\n\n21 - CRITÉRIO DE ADJUDICAÇÃO\nO Critério de adjudicação é diferenciado por lote? Não\nMultifator: Sim\nFator: \nNome: Outros\nOutro Nome: Número total de dias (NTD)\nPonderação: 70%\nSubfatores: Não\nFator: \nNome: Outros\nOutro Nome: Valor da proposta de acordo com o Anexo III\nPonderação: 30%\nSubfatores: Não\n\n24 - CONDIÇÕES DO CONTRATO\nIdentificador do Lote: LOT-0001; LOT-0002; LOT-0003; LOT-0004\nFaturação Eletrónica: Permitido\nObrigação de Subcontratação:\nCódigo da Obrigação de Subcontratação: Não é aplicável nenhuma obrigação de subcontratação.\n\n25 - COMPRA PÚBLICA ESTRATÉGICA\nCompra Pública Estratégica: Inexistência de contratação pública estratégica\n\n26 - INFORMAÇÕES ADICIONAIS\nIdentificador do Lote: LOT-0001; LOT-0002; LOT-0003; LOT-0004\nContrato adequado para PME: Sim\nCobertura ACP (Acordo dos Contratos Públicos da Organização Mundial do Comércio): Não\n\n27 - IDENTIFICAÇÃO E CONTACTOS DO ÓRGÃO DE RECURSOS ADMINISTRATIVOS\nDesignação: Conselho Intermunicipal da Comunidade Intermunicipal da Região de Coimbra\nEndereço: Rua do Brasil, 131\nCódigo postal: 3030-175\nLocalidade: Coimbra\nTelefone: 239795200\nFax: 000000000\nEndereço eletrónico: geral@cim-regiaodecoimbra.pt\nPrazo de interposição do recurso: 5 dias\n\n28 - IDENTIFICAÇÃO DO(S) AUTOR(ES) DE ANÚNCIO\nNome: Jorge Brito\nCargo: Secretário Executivo Intermunicipal\n419587205",
    "nipc": "508354617",
    "distrito": "Todos",
    "concelho": "Todos",
    "freguesia": "Todas",
    "site": "https://cim-regiaodecoimbra.pt",
    "email": "geral@cim-regiaodecoimbra.pt",
    "designacao_contrato": "CP19/2025 - Aquisição de Veículos Multilift e respetivos Módulos",
    "descricao": "CP19/2025 - Aquisição de Veículos Multilift e respetivos Módulos",
    "preco_base": "1.037.735,85 EUR",
    "prazo_execucao": "395 DIAS",
    "prazo_apresentacao_propostas": "31-10-2025 23:59",
    "fundos_eu": "Sim",
    "plataforma_eletronica": "ACIN",
    "url_procedimento": "https://www.acingov.pt",
    "autor_nome": "Jorge Brito",
    "autor_cargo": "Secretário Executivo Intermunicipal"
  }
]