[
  {
    "numero_procedimento": "N/A",
    "entidade": "AnÃºncio de procedimento  n.Âº 25982/2025  -  DiÃ¡rio da RepÃºblica n.Âº 191/2025, SÃ©rie II de 2025-10-03",
    "link": "https://diariodarepublica.pt/dr/detalhe/contrato-publico/25982-937820799"
  },
  {
    "numero_procedimento": "N/A",
    "entidade": "AnÃºncio de procedimento  n.Âº 25983/2025  -  DiÃ¡rio da RepÃºblica n.Âº 191/2025, SÃ©rie II de 2025-10-03",
    "link": "https://diariodarepublica.pt/dr/detalhe/contrato-publico/25983-937820800"
  },
  {
    "numero_procedimento": "N/A",
    "entidade": "AnÃºncio de procedimento  n.Âº 25984/2025  -  DiÃ¡rio da RepÃºblica n.Âº 191/2025, SÃ©rie II de 2025-10-03",
    "link": "https://diariodarepublica.pt/dr/detalhe/contrato-publico/25984-937820801"
  },
  {
    "numero_procedimento": "N/A",
    "entidade": "AnÃºncio de procedimento  n.Âº 25985/2025  -  DiÃ¡rio da RepÃºblica n.Âº 191/2025, SÃ©rie II de 2025-10-03",
    "link": "https://diariodarepublica.pt/dr/detalhe/contrato-publico/25985-937820802"
  },
  {
    "numero_procedimento": "N/A",
    "entidade": "AnÃºncio de procedimento  n.Âº 25986/2025  -  DiÃ¡rio da RepÃºblica n.Âº 191/2025, SÃ©rie II de 2025-10-03",
    "link": "https://diariodarepublica.pt/dr/detalhe/contrato-publico/25986-937820803"
  },
  {
    "numero_procedimento": "N/A",
    "entidade": "AnÃºncio de procedimento  n.Âº 25987/2025  -  DiÃ¡rio da RepÃºblica n.Âº 191/2025, SÃ©rie II de 2025-10-03",
    "link": "https://diariodarepublica.pt/dr/detalhe/contrato-publico/25987-937820804"
  },
  {
    "numero_procedimento": "N/A",
    "entidade": "AnÃºncio de procedimento  n.Âº 25988/2025  -  DiÃ¡rio da RepÃºblica n.Âº 191/2025, SÃ©rie II de 2025-10-03",
    "link": "https://diariodarepublica.pt/dr/detalhe/contrato-publico/25988-937820806"
  },
  {
    "numero_procedimento": "N/A",
    "entidade": "AnÃºncio de procedimento  n.Âº 25990/2025  -  DiÃ¡rio da RepÃºblica n.Âº 191/2025, SÃ©rie II de 2025-10-03",
    "link": "https://diariodarepublica.pt/dr/detalhe/contrato-publico/25990-937820807"
  },
  {
    "numero_procedimento": "N/A",
    "entidade": "AnÃºncio de procedimento  n.Âº 25992/2025  -  DiÃ¡rio da RepÃºblica n.Âº 191/2025, SÃ©rie II de 2025-10-03",
    "link": "https://diariodarepublica.pt/dr/detalhe/contrato-publico/25992-937820808"
  },
  {
    "numero_procedimento": "N/A",
    "entidade": "AnÃºncio de procedimento  n.Âº 25995/2025  -  DiÃ¡rio da RepÃºblica n.Âº 191/2025, SÃ©rie II de 2025-10-03",
    "link": "https://diariodarepublica.pt/dr/detalhe/contrato-publico/25995-937820809"
  },
  {
    "numero_procedimento": "N/A",
    "entidade": "AnÃºncio de procedimento  n.Âº 25998/2025  -  DiÃ¡rio da RepÃºblica n.Âº 191/2025, SÃ©rie II de 2025-10-03",
    "link": "https://diariodarepublica.pt/dr/detalhe/contrato-publico/25998-937820819"
  },
  {
    "numero_procedimento": "N/A",
    "entidade": "AnÃºncio de procedimento  n.Âº 25999/2025  -  DiÃ¡rio da RepÃºblica n.Âº 191/2025, SÃ©rie II de 2025-10-03",
    "link": "https://diariodarepublica.pt/dr/detalhe/contrato-publico/25999-937820820"
  },
  {
    "numero_procedimento": "N/A",
    "entidade": "AnÃºncio de procedimento  n.Âº 26000/2025  -  DiÃ¡rio da RepÃºblica n.Âº 191/2025, SÃ©rie II de 2025-10-03",
    "link": "https://diariodarepublica.pt/dr/detalhe/contrato-publico/26000-937820821"
  },
  {
    "numero_procedimento": "N/A",
    "entidade": "AnÃºncio de procedimento  n.Âº 25981/2025  -  DiÃ¡rio da RepÃºblica n.Âº 191/2025, SÃ©rie II de 2025-10-03",
    "link": "https://diariodarepublica.pt/dr/detalhe/contrato-publico/25981-937877784"
  },
  {
    "numero_procedimento": "N/A",
    "entidade": "AnÃºncio de procedimento  n.Âº 25989/2025  -  DiÃ¡rio da RepÃºblica n.Âº 191/2025, SÃ©rie II de 2025-10-03",
    "link": "https://diariodarepublica.pt/dr/detalhe/contrato-publico/25989-937877786"
  },
  {
    "numero_procedimento": "N/A",
    "entidade": "AnÃºncio de procedimento  n.Âº 25991/2025  -  DiÃ¡rio da RepÃºblica n.Âº 191/2025, SÃ©rie II de 2025-10-03",
    "link": "https://diariodarepublica.pt/dr/detalhe/contrato-publico/25991-937877787"
  },
  {
    "numero_procedimento": "N/A",
    "entidade": "AnÃºncio de procedimento  n.Âº 25993/2025  -  DiÃ¡rio da RepÃºblica n.Âº 191/2025, SÃ©rie II de 2025-10-03",
    "link": "https://diariodarepublica.pt/dr/detalhe/contrato-publico/25993-937877788"
  },
  {
    "numero_procedimento": "N/A",
    "entidade": "Ordem dos Contabilistas Certificados",
    "link": "https://diariodarepublica.pt/dr/detalhe/contrato-publico/25994-937877789",
    "detalhes_completos": "Alteração do Anúncio de procedimento n.º 25468/2025, de 2025-09-26, com o ID 419569645\n\n1 - IDENTIFICAÇÃO E CONTACTOS DA ENTIDADE ADJUDICANTE\nDesignação da entidade adjudicante: Ordem dos Contabilistas Certificados\nNIPC: 503692310\nServiço/Órgão/Pessoa de contacto: Bastonária\nEndereço: Av. Barbosa du Bocage, 45 \nCódigo postal: 1049-013\nLocalidade: Lisboa\nPaís: Portugal\nNUT III: PT187\nDistrito: Lisboa\nConcelho: Lisboa\nFreguesia: Freguesia de Avenidas Novas\nTelefone: 217999800\nFax: 217957332\nEndereço da Entidade (URL): www.occ.pt\nEndereço Eletrónico: compras@occ.pt\nFunção da Organização: Adquirente\nNorma jurídica da Entidade Adjudicante: Autoridade da administração central\nÁrea de atividade da Entidade Adjudicante: Atividades aeroportuárias\nÁrea de atividade da Autoridade Adjudicante: Assuntos económicos\n\n2 - JORNAL OFICIAL DA UNIÃO EUROPEIA\nO procedimento a que este anúncio diz respeito também é publicitado no Jornal Oficial da União Europeia? Sim\n\n3 - AVISO\nModelo de Anúncio: Concurso público\nData de Envio do Anúncio: 30-09-2025\n\n5 - PROCESSO\nTipo de Procedimento: Concurso público\nPreço base do procedimento: Sim\nValor do preço base do procedimento: 680.000,00 EUR\nProcedimento com lotes? Sim\nNº Máx. de Lotes Autorizado: 3\nNúmero máximo de lotes que podem ser adjudicados a um concorrente: 3\n\n6 - OBJETO DO CONTRATO\nNúmero de referência interna: 0107-2025\nDesignação do contrato: Concurso Público com Publicidade Internacional tendente à celebração de contrato para a aquisição de serviços de gestão de Pagamentos Eletrónicos em tempo real por Intermédio de Gateway de Pagamentos\nDescrição: Aquisição de Serviços de Gestão de Pagamentos Eletrónicos em tempo real por Intermédio de Gateway de Pagamentos\nOpções: Não\nTipo de Contrato Principal: Aquisição de Serviços\nTipo de Contrato: Aquisição de Serviços\nClassificação CPV (Vocabulário Comum para os Contratos Públicos)\nObjeto principal\nVocabulário Principal: 66110000\nPreço base s/IVA: 680.000,00 EUR\nLotes: \nNº: LOT-0001\nDescrição do Lote: Lote1\nPreço base s/IVA: 476.000,00 EUR\nClassificação CPV (Vocabulário Comum para os Contratos Públicos)\nObjeto principal\nVocabulário Principal: 66110000\nNº: LOT-0002\nDescrição do Lote: Lote 2\nPreço base s/IVA: 34.000,00 EUR\nClassificação CPV (Vocabulário Comum para os Contratos Públicos)\nObjeto principal\nVocabulário Principal: 66110000\nNº: LOT-0003\nDescrição do Lote: Lote 3\nPreço base s/IVA: 170.000,00 EUR\nClassificação CPV (Vocabulário Comum para os Contratos Públicos)\nObjeto principal\nVocabulário Principal: 66110000\n\n7 - INDICAÇÕES ADICIONAIS\nO contrato envolve aquisição conjunta (satisfação de várias entidades)? Não\nO contrato é adjudicado por uma central de compras? Não\n\n8 - TÉCNICAS\nO concurso destina-se à celebração de um acordo-quadro? Inexistência de acordo-quadro\nÉ utilizado um leilão eletrónico? Não\nÉ adotada uma fase de negociação? Não\nSistema de Aquisição Dinâmico: Inexistência de sistema de aquisição dinâmico\n\n9 - LOCAL DA EXECUÇÃO DO CONTRATO\nLOCAL DA EXECUÇÃO DO CONTRATO (PROCEDIMENTO)\nLOCAL DA EXECUÇÃO DO CONTRATO (LOTE)\nIdentificador do Lote: LOT-0001\nPaís: Portugal\nNUT III: PT170\nLocalidade: Campo Pequeno\nDistrito: Lisboa\nConcelho: Lisboa\nFreguesia: Freguesia de Avenidas Novas\nIdentificador do Lote: LOT-0002\nPaís: Portugal\nNUT III: PT170\nLocalidade: Campo Pequeno\nDistrito: Lisboa\nConcelho: Lisboa\nFreguesia: Freguesia de Avenidas Novas\nIdentificador do Lote: LOT-0003\nPaís: Portugal\nNUT III: PT170\nLocalidade: Campo Pequeno\nDistrito: Lisboa\nConcelho: Lisboa\nFreguesia: Freguesia de Avenidas Novas\n\n10 - PRAZO DE EXECUÇÃO DO CONTRATO\nIdentificador do Lote: LOT-0001\nPrazo de execução do contrato: 12 MESES\nPrevisão de renovações: Sim\nIndicar número máximo de renovações: 2\nPrazo de renovações diferente do prazo inicial: Não\nIdentificador do Lote: LOT-0002\nPrazo de execução do contrato: 12 MESES\nPrevisão de renovações: Sim\nIndicar número máximo de renovações: 2\nPrazo de renovações diferente do prazo inicial: Não\nIdentificador do Lote: LOT-0003\nPrazo de execução do contrato: 12 MESES\nPrevisão de renovações: Sim\nIndicar número máximo de renovações: 2\nPrazo de renovações diferente do prazo inicial: Não\n\n11 - FUNDOS EU\nIdentificador do Lote: LOT-0001; LOT-0002; LOT-0003\nTêm fundos EU? Não\n\n12 - DOCUMENTOS DE HABILITAÇÃO\nHabilitação para o exercício da atividade profissional: Não\n\n13 - CONDIÇÕES DE APRESENTAÇÃO\nPlataforma eletrónica utilizada pela entidade adjudicante: ANOGOV\nURL para Apresentação: https://www.anogov.com/ap-otoc/faces/\nAdmissibilidade da apresentação de propostas variantes: Não autorizado\nPrazo para apresentação das propostas: 27-10-2025 23:59\nPrazo durante o qual os concorrentes são obrigados a manter as respetivas propostas: 90 dias a contar do termo do prazo para a apresentação das propostas\nApresentação de Catálogo Eletrónico: Não autorizado\nIndicação de Subcontratação na Proposta: Inexistência de indicação de subcontratação\n\n14 - PRESTAÇÃO DE CAUÇÃO\nPrestação de caução: Sim\nPercentagem: 5%\nDescrição da Garantia Exigida: Nos termos do artigo 27.º do Programa \n\n15 - FORNECIMENTO DAS PEÇAS DO CONCURSO, APRESENTAÇÃO DE PEDIDOS DE PARTICIPAÇÃO E APRESENTAÇÃO DAS PROPOSTAS\nLink para acesso às peças do concurso (URL): https://www.anogov.com/ap-otoc/faces/app/acessoDocs.jsp?codigoAcesso=qptFsM2mshVNTU9lik1ISAeefiYtOCH6WLuGBPGds6XVIljRH3\n\n20 - OUTROS REQUISITOS\nIdentificador do Lote: LOT-0001; LOT-0002; LOT-0003\nInformação sobre contratos reservados. Aplica-se a contratos reservados (54º-A)? Não\n\n21 - CRITÉRIO DE ADJUDICAÇÃO\nO Critério de adjudicação é diferenciado por lote? Não\nMultifator: Não\nMonofator:\nNome: Preço\n\n24 - CONDIÇÕES DO CONTRATO\nIdentificador do Lote: LOT-0001; LOT-0002; LOT-0003\nFaturação Eletrónica: Permitido\nObrigação de Subcontratação:\nCódigo da Obrigação de Subcontratação: Não é aplicável nenhuma obrigação de subcontratação.\n\n25 - COMPRA PÚBLICA ESTRATÉGICA\nCompra Pública Estratégica: Inexistência de contratação pública estratégica\n\n26 - INFORMAÇÕES ADICIONAIS\nIdentificador do Lote: LOT-0001\nContrato adequado para PME: Não\nCobertura ACP (Acordo dos Contratos Públicos da Organização Mundial do Comércio): Não\nIdentificador do Lote: LOT-0002\nContrato adequado para PME: Não\nCobertura ACP (Acordo dos Contratos Públicos da Organização Mundial do Comércio): Não\nIdentificador do Lote: LOT-0003\nContrato adequado para PME: Não\nCobertura ACP (Acordo dos Contratos Públicos da Organização Mundial do Comércio): Não\n\n27 - IDENTIFICAÇÃO E CONTACTOS DO ÓRGÃO DE RECURSOS ADMINISTRATIVOS\nDesignação: Conselho Diretivo da Ordem dos Contabilistas Certificados\nEndereço: Avenida Barbosa du Bocage,45\nCódigo postal: 1049-013\nLocalidade: Lisboa\nEndereço eletrónico: compras@occ.pt\n\n28 - IDENTIFICAÇÃO DO(S) AUTOR(ES) DE ANÚNCIO\nNome: Paula Maria Pires de Oliveira e Silva Laia Franco\nCargo: Bastonária\n\n29 - ALTERAÇÃO\nMotivo da Alteração: Informações atualizadas\nIdentificador da Versão do Anúncio a Alterar: 1e28277e-068d-4648-ae22-ebd7cbe30e34-01\nIdentificador das Secções Alteradas do Anúncio Anterior: Prazo de execução do contrato\nDescrição das Alterações: Correção do prazo de execução do contrato para 12 meses\nAlteração dos Documentos do Concurso: Não\n419591669",
    "nipc": "503692310",
    "distrito": "Lisboa",
    "concelho": "Lisboa",
    "freguesia": "Freguesia de Avenidas Novas",
    "site": "www.occ.pt",
    "email": "compras@occ.pt",
    "designacao_contrato": "Concurso Público com Publicidade Internacional tendente à celebração de contrato para a aquisição de serviços de gestão de Pagamentos Eletrónicos em tempo real por Intermédio de Gateway de Pagamentos",
    "descricao": "Aquisição de Serviços de Gestão de Pagamentos Eletrónicos em tempo real por Intermédio de Gateway de Pagamentos",
    "preco_base": "680.000,00 EUR",
    "prazo_execucao": "12 MESES",
    "prazo_apresentacao_propostas": "27-10-2025 23:59",
    "fundos_eu": "Não",
    "plataforma_eletronica": "ANOGOV",
    "url_procedimento": "https://www.anogov.com/ap-otoc/faces/",
    "autor_nome": "Paula Maria Pires de Oliveira e Silva Laia Franco",
    "autor_cargo": "Bastonária"
  },
  {
    "numero_procedimento": "N/A",
    "entidade": "AnÃºncio de procedimento  n.Âº 25996/2025  -  DiÃ¡rio da RepÃºblica n.Âº 191/2025, SÃ©rie II de 2025-10-03",
    "link": "https://diariodarepublica.pt/dr/detalhe/contrato-publico/25996-937877790"
  },
  {
    "numero_procedimento": "N/A",
    "entidade": "AnÃºncio de procedimento  n.Âº 25997/2025  -  DiÃ¡rio da RepÃºblica n.Âº 191/2025, SÃ©rie II de 2025-10-03",
    "link": "https://diariodarepublica.pt/dr/detalhe/contrato-publico/25997-937877791"
  },
  {
    "numero_procedimento": "N/A",
    "entidade": "AnÃºncio de procedimento  n.Âº 26001/2025  -  DiÃ¡rio da RepÃºblica n.Âº 191/2025, SÃ©rie II de 2025-10-03",
    "link": "https://diariodarepublica.pt/dr/detalhe/contrato-publico/26001-937877792"
  },
  {
    "numero_procedimento": "N/A",
    "entidade": "AnÃºncio de procedimento  n.Âº 26002/2025  -  DiÃ¡rio da RepÃºblica n.Âº 191/2025, SÃ©rie II de 2025-10-03",
    "link": "https://diariodarepublica.pt/dr/detalhe/contrato-publico/26002-937940466"
  },
  {
    "numero_procedimento": "N/A",
    "entidade": "AnÃºncio de procedimento  n.Âº 26003/2025  -  DiÃ¡rio da RepÃºblica n.Âº 191/2025, SÃ©rie II de 2025-10-03",
    "link": "https://diariodarepublica.pt/dr/detalhe/contrato-publico/26003-937940467"
  }
]