[
  {
    "numero_procedimento": "N/A",
    "entidade": "INSIGNARE-Associação de Ensino e Formação",
    "link": "https://diariodarepublica.pt/dr/detalhe/contrato-publico/25982-937820799",
    "detalhes_completos": "1 - IDENTIFICAÇÃO E CONTACTOS DA ENTIDADE ADJUDICANTE\nDesignação da entidade adjudicante: INSIGNARE-Associação de Ensino e Formação\nNIPC: 502964685\nServiço/Órgão/Pessoa de contacto: Gabinete Administrativo e Financeiro\nEndereço: Avenida Dom Nuno Álvares Pereira n.º 69\nCódigo postal: 2490-483\nLocalidade: Ourém\nPaís: Portugal\nNUT III: PT16I\nDistrito: Santarém\nConcelho: Ourém\nFreguesia: Freguesia de Nossa Senhora da Piedade\nTelefone: 249545721\nFax: 249540399\nEndereço da Entidade (URL): https://www.insignare.pt/pt/\nEndereço Eletrónico: sec@insignare.pt\neDelivery Gateway (URL): https://www.acingov.pt\nFunção da Organização: Adquirente\nNorma jurídica da Entidade Adjudicante: Organismo de direito público\nÁrea de atividade da Autoridade Adjudicante: Serviços públicos das administrações públicas\n\n2 - JORNAL OFICIAL DA UNIÃO EUROPEIA\nO procedimento a que este anúncio diz respeito também é publicitado no Jornal Oficial da União Europeia? Não\n\n3 - AVISO\nModelo de Anúncio: Concurso público\nData de Envio do Anúncio: 02-10-2025\n\n5 - PROCESSO\nTipo de Procedimento: Concurso público\nPreço base do procedimento: Sim\nValor do preço base do procedimento: 176.908,20 EUR\nProcedimento com lotes? Não\n\n6 - OBJETO DO CONTRATO\nNúmero de referência interna: CP011/2025/GAF\nDesignação do contrato: Empreitada de ampliação do restaurante de aplicação e da sala de enologia e bar da Escola Profissional de Hotelaria de Fátima no âmbito do Centro Tecnológico Especializado - V2\nDescrição: Empreitada de ampliação do restaurante de aplicação e da sala de enologia e bar da Escola Profissional de Hotelaria de Fátima no âmbito do Centro Tecnológico Especializado - V2\nTipo de Contrato Principal: Empreitada de Obras Públicas\nTipo de Contrato: Empreitada de Obras Públicas\nClassificação CPV (Vocabulário Comum para os Contratos Públicos)\nObjeto principal\nVocabulário Principal: 45214200\nPreço base s/IVA: 176.908,20 EUR\n\n7 - INDICAÇÕES ADICIONAIS\nO contrato envolve aquisição conjunta (satisfação de várias entidades)? Não\nO contrato é adjudicado por uma central de compras? Não\n\n8 - TÉCNICAS\nO concurso destina-se à celebração de um acordo-quadro? Inexistência de acordo-quadro\nÉ utilizado um leilão eletrónico? Não\nÉ adotada uma fase de negociação? Não\nSistema de Aquisição Dinâmico: Inexistência de sistema de aquisição dinâmico\n\n9 - LOCAL DA EXECUÇÃO DO CONTRATO\nLOCAL DA EXECUÇÃO DO CONTRATO (PROCEDIMENTO)\nPaís: Portugal\nNUT III: PT16I\nLocalidade: Freguesia de Fátima\nDistrito: Santarém\nConcelho: Ourém\nFreguesia: Freguesia de Fátima\n\n10 - PRAZO DE EXECUÇÃO DO CONTRATO\nPrazo de execução do contrato: 90 DIAS\nPrevisão de renovações: Não\n\n11 - FUNDOS EU\nTêm fundos EU? Sim\n\n12 - DOCUMENTOS DE HABILITAÇÃO\nHabilitação para o exercício da atividade profissional: Sim\nTipo: Alvará\nDescrição: Alvarás ou os títulos de registo emitidos pelo Instituto da Construção e do Imobiliário, I. P., contendo as seguintes habilitações necessárias à execução do contrato pelo adjudicatário ou por empresa do agrupamento adjudicatário, nos termos dos Anexos I e II à Lei 41/2015 de 3 de junho: \n- A classificação na 1ª subcategoria (Estruturas e elementos de betão) da 1ª categoria (Edifícios e Património construído) em classe correspondente ao valor da proposta.\nE nas classes correspondentes à parte dos trabalhos a que respeitem as seguintes subcategorias:\n- A 2ª subcategoria (Estruturas metálicas) da 1ª categoria (Edifícios e património construído);\n- A 4ª subcategoria (Alvenarias, rebocos e assentamento de cantarias) da 1ª categoria (Edifícios e património construído);\n- A 5ª subcategoria (Estuques, pinturas e outros revestimentos) da 1ª categoria (Edifícios e património construído);\n- A 1ª subcategoria (Instalações Elétricas de utilização de baixa tensão) da 4ª categoria (Instalações elétricas e mecânicas);\n- A 12ª subcategoria (Aquecimento, ventilação, ar condicionado e refrigeração) da 4ª categoria (Instalações elétricas e mecânicas);\n\n13 - CONDIÇÕES DE APRESENTAÇÃO\nPlataforma eletrónica utilizada pela entidade adjudicante: ACIN\nURL para Apresentação: https://www.acingov.pt\nAdmissibilidade da apresentação de propostas variantes: Não autorizado\nPrazo para apresentação das propostas: 11-10-2025 23:59\nPrazo durante o qual os concorrentes são obrigados a manter as respetivas propostas: 90 dias a contar do termo do prazo para a apresentação das propostas\nIndicação de Subcontratação na Proposta: Inexistência de indicação de subcontratação\n\n14 - PRESTAÇÃO DE CAUÇÃO\nPrestação de caução: Não\n\n15 - FORNECIMENTO DAS PEÇAS DO CONCURSO, APRESENTAÇÃO DE PEDIDOS DE PARTICIPAÇÃO E APRESENTAÇÃO DAS PROPOSTAS\nLink para acesso às peças do concurso (URL): https://www.acingov.pt/acingovprod/2/zonaPublica/zona_publica_c/donwloadProcedurePiece/OTgzMTE0\n\n20 - OUTROS REQUISITOS\nInformação sobre contratos reservados. Aplica-se a contratos reservados (54º-A)? Não\n\n21 - CRITÉRIO DE ADJUDICAÇÃO\nMultifator: Não\nMonofator:\nNome: Preço\n\n24 - CONDIÇÕES DO CONTRATO\nFaturação Eletrónica: Não autorizado\nObrigação de Subcontratação:\nCódigo da Obrigação de Subcontratação: Não é aplicável nenhuma obrigação de subcontratação.\n\n25 - COMPRA PÚBLICA ESTRATÉGICA\nCompra Pública Estratégica: Inexistência de contratação pública estratégica\n\n26 - INFORMAÇÕES ADICIONAIS\nContrato adequado para PME: Sim\nCobertura ACP (Acordo dos Contratos Públicos da Organização Mundial do Comércio): Não\n\n27 - IDENTIFICAÇÃO E CONTACTOS DO ÓRGÃO DE RECURSOS ADMINISTRATIVOS\nDesignação: Direção da INSIGNARE\nEndereço: Avenida Dom Nuno Álvares Pereira n.º 69\nCódigo postal: 2490-483\nLocalidade: Ourém\nTelefone: 249545721\nFax: \nEndereço eletrónico: dir@inisgnare.pt\nPrazo de interposição do recurso: 2 dias\n\n28 - IDENTIFICAÇÃO DO(S) AUTOR(ES) DE ANÚNCIO\nNome: Pedro Miguel Major da Silva\nCargo: Diretor Executivo\n419607333",
    "nipc": "502964685",
    "distrito": "Santarém",
    "concelho": "Ourém",
    "freguesia": "Freguesia de Nossa Senhora da Piedade",
    "site": "https://www.insignare.pt/pt/",
    "email": "sec@insignare.pt",
    "designacao_contrato": "Empreitada de ampliação do restaurante de aplicação e da sala de enologia e bar da Escola Profissional de Hotelaria de Fátima no âmbito do Centro Tecnológico Especializado - V2",
    "descricao": "Empreitada de ampliação do restaurante de aplicação e da sala de enologia e bar da Escola Profissional de Hotelaria de Fátima no âmbito do Centro Tecnológico Especializado - V2",
    "preco_base": "176.908,20 EUR",
    "prazo_execucao": "90 DIAS",
    "prazo_apresentacao_propostas": "11-10-2025 23:59",
    "fundos_eu": "Sim",
    "plataforma_eletronica": "ACIN",
    "url_procedimento": "https://www.acingov.pt",
    "autor_nome": "Pedro Miguel Major da Silva",
    "autor_cargo": "Diretor Executivo"
  },
  {
    "numero_procedimento": "N/A",
    "entidade": "AnÃºncio de procedimento  n.Âº 25983/2025  -  DiÃ¡rio da RepÃºblica n.Âº 191/2025, SÃ©rie II de 2025-10-03",
    "link": "https://diariodarepublica.pt/dr/detalhe/contrato-publico/25983-937820800"
  },
  {
    "numero_procedimento": "N/A",
    "entidade": "Município de Ílhavo",
    "link": "https://diariodarepublica.pt/dr/detalhe/contrato-publico/25984-937820801",
    "detalhes_completos": "1 - IDENTIFICAÇÃO E CONTACTOS DA ENTIDADE ADJUDICANTE\nDesignação da entidade adjudicante: Município de Ílhavo\nNIPC: 506920887\nServiço/Órgão/Pessoa de contacto: Divisão de Administração Geral\nEndereço: Avenida 25 de Abril\nCódigo postal: 3830-044\nLocalidade: Ílhavo\nPaís: Portugal\nNUT III: PT16D\nDistrito: Aveiro\nConcelho: Ílhavo\nFreguesia: Todas\nTelefone: 234329600\nFax: 234329601\nEndereço da Entidade (URL): www.cm-ilhavo.pt\nEndereço Eletrónico: geralcmi@cm-ilhavo.pt\neDelivery Gateway (URL): https://www.acingov.pt\nFunção da Organização: Adquirente\nSubfunção da Organização: Organização que recebe as propostas\nNorma jurídica da Entidade Adjudicante: Organismo de direito público\nÁrea de atividade da Autoridade Adjudicante: Serviços públicos das administrações públicas\n\n2 - JORNAL OFICIAL DA UNIÃO EUROPEIA\nO procedimento a que este anúncio diz respeito também é publicitado no Jornal Oficial da União Europeia? Sim\n\n3 - AVISO\nModelo de Anúncio: Concurso público\nData de Envio do Anúncio: 30-09-2025\n\n5 - PROCESSO\nTipo de Procedimento: Concurso público\nPreço base do procedimento: Sim\nValor do preço base do procedimento: 344.800,00 EUR\nProcedimento com lotes? Não\n\n6 - OBJETO DO CONTRATO\nNúmero de referência interna: 10/H/S/25\nDesignação do contrato: Prestação de serviços de docência, em regime de outsourcing, para as piscinas municipais, programa Maiores no Movimento e eventos desportivos\nDescrição: Prestação de serviços de docência, em regime de outsourcing, para as piscinas municipais, programa Maiores no Movimento e eventos desportivos\nOpções: Não\nTipo de Contrato Principal: Aquisição de Serviços\nTipo de Contrato: Aquisição de Serviços\nClassificação CPV (Vocabulário Comum para os Contratos Públicos)\nObjeto principal\nVocabulário Principal: 92600000\nPreço base s/IVA: 344.800,00 EUR\n\n7 - INDICAÇÕES ADICIONAIS\nO contrato envolve aquisição conjunta (satisfação de várias entidades)? Não\nO contrato é adjudicado por uma central de compras? Não\n\n8 - TÉCNICAS\nO concurso destina-se à celebração de um acordo-quadro? Inexistência de acordo-quadro\nÉ utilizado um leilão eletrónico? Não\nÉ adotada uma fase de negociação? Não\nSistema de Aquisição Dinâmico: Inexistência de sistema de aquisição dinâmico\n\n9 - LOCAL DA EXECUÇÃO DO CONTRATO\nLOCAL DA EXECUÇÃO DO CONTRATO (PROCEDIMENTO)\nPaís: Portugal\nNUT III: PT16D\nLocalidade: Ílhavo\nDistrito: Aveiro\nConcelho: Ílhavo\nFreguesia: Todas\n\n10 - PRAZO DE EXECUÇÃO DO CONTRATO\nPrazo de execução do contrato: 24 MESES\nPrevisão de renovações: Não\n\n11 - FUNDOS EU\nTêm fundos EU? Não\n\n12 - DOCUMENTOS DE HABILITAÇÃO\nHabilitação para o exercício da atividade profissional: Não\n\n13 - CONDIÇÕES DE APRESENTAÇÃO\nPlataforma eletrónica utilizada pela entidade adjudicante: ACIN\nURL para Apresentação: https://www.acingov.pt\nAdmissibilidade da apresentação de propostas variantes: Não autorizado\nPrazo para apresentação das propostas: 31-10-2025 17:59\nPrazo durante o qual os concorrentes são obrigados a manter as respetivas propostas: 66 dias a contar do termo do prazo para a apresentação das propostas\nApresentação de Catálogo Eletrónico: Permitido\nIndicação de Subcontratação na Proposta: Inexistência de indicação de subcontratação\n\n14 - PRESTAÇÃO DE CAUÇÃO\nPrestação de caução: Não\n\n15 - FORNECIMENTO DAS PEÇAS DO CONCURSO, APRESENTAÇÃO DE PEDIDOS DE PARTICIPAÇÃO E APRESENTAÇÃO DAS PROPOSTAS\nLink para acesso às peças do concurso (URL): https://www.acingov.pt/acingovprod/2/zonaPublica/zona_publica_c/donwloadProcedurePiece/OTgxNzQx\n\n20 - OUTROS REQUISITOS\nInformação sobre contratos reservados. Aplica-se a contratos reservados (54º-A)? Não\n\n21 - CRITÉRIO DE ADJUDICAÇÃO\nMultifator: Não\nMonofator:\nNome: Preço\n\n24 - CONDIÇÕES DO CONTRATO\nFaturação Eletrónica: Permitido\nObrigação de Subcontratação:\nCódigo da Obrigação de Subcontratação: Não é aplicável nenhuma obrigação de subcontratação.\n\n25 - COMPRA PÚBLICA ESTRATÉGICA\nCompra Pública Estratégica: Inexistência de contratação pública estratégica\n\n26 - INFORMAÇÕES ADICIONAIS\nContrato adequado para PME: Não\nCobertura ACP (Acordo dos Contratos Públicos da Organização Mundial do Comércio): Não\n\n27 - IDENTIFICAÇÃO E CONTACTOS DO ÓRGÃO DE RECURSOS ADMINISTRATIVOS\nDesignação: Presidente da Câmara Municipal\nEndereço: Av. 25 de abril\nCódigo postal: 3830-044\nLocalidade: Ílhavo\nTelefone: 234329600\nFax: \nEndereço eletrónico: geralcmi@cm-ilhavo.pt\n\n28 - IDENTIFICAÇÃO DO(S) AUTOR(ES) DE ANÚNCIO\nNome: João António Filipe Campolargo\nCargo: Presidente da Câmara de Ílhavo\n419589044",
    "nipc": "506920887",
    "distrito": "Aveiro",
    "concelho": "Ílhavo",
    "freguesia": "Todas",
    "site": "www.cm-ilhavo.pt",
    "email": "geralcmi@cm-ilhavo.pt",
    "designacao_contrato": "Prestação de serviços de docência, em regime de outsourcing, para as piscinas municipais, programa Maiores no Movimento e eventos desportivos",
    "descricao": "Prestação de serviços de docência, em regime de outsourcing, para as piscinas municipais, programa Maiores no Movimento e eventos desportivos",
    "preco_base": "344.800,00 EUR",
    "prazo_execucao": "24 MESES",
    "prazo_apresentacao_propostas": "31-10-2025 17:59",
    "fundos_eu": "Não",
    "plataforma_eletronica": "ACIN",
    "url_procedimento": "https://www.acingov.pt",
    "autor_nome": "João António Filipe Campolargo",
    "autor_cargo": "Presidente da Câmara de Ílhavo"
  },
  {
    "numero_procedimento": "N/A",
    "entidade": "AnÃºncio de procedimento  n.Âº 25985/2025  -  DiÃ¡rio da RepÃºblica n.Âº 191/2025, SÃ©rie II de 2025-10-03",
    "link": "https://diariodarepublica.pt/dr/detalhe/contrato-publico/25985-937820802"
  },
  {
    "numero_procedimento": "N/A",
    "entidade": "AnÃºncio de procedimento  n.Âº 25986/2025  -  DiÃ¡rio da RepÃºblica n.Âº 191/2025, SÃ©rie II de 2025-10-03",
    "link": "https://diariodarepublica.pt/dr/detalhe/contrato-publico/25986-937820803"
  },
  {
    "numero_procedimento": "N/A",
    "entidade": "MUNICÍPIO DE LOULÉ",
    "link": "https://diariodarepublica.pt/dr/detalhe/contrato-publico/25987-937820804",
    "detalhes_completos": "1 - IDENTIFICAÇÃO E CONTACTOS DA ENTIDADE ADJUDICANTE\nDesignação da entidade adjudicante: MUNICÍPIO DE LOULÉ\nNIPC: 502098139\nEndereço: Praça da República\nCódigo postal: 8104-001\nLocalidade: Faro\nPaís: Portugal\nNUT III: PT150\nDistrito: Faro\nConcelho: Loulé\nFreguesia: Todas\nTelefone: 289400834\nFax: 289415557\nEndereço da Entidade (URL): www.cm-loule.pt\nEndereço Eletrónico: aprovisionamento@cm-loule.pt\neDelivery Gateway (URL): https://community.vortal.biz/public/\nFunção da Organização: Adquirente\nNorma jurídica da Entidade Adjudicante: Organismo de direito público\nÁrea de atividade da Autoridade Adjudicante: Serviços públicos das administrações públicas\n\n2 - JORNAL OFICIAL DA UNIÃO EUROPEIA\nO procedimento a que este anúncio diz respeito também é publicitado no Jornal Oficial da União Europeia? Sim\n\n3 - AVISO\nModelo de Anúncio: Concurso público\nData de Envio do Anúncio: 30-09-2025\n\n5 - PROCESSO\nTipo de Procedimento: Concurso público\nPreço base do procedimento: Sim\nValor do preço base do procedimento: 121.200,00 EUR\nProcedimento com lotes? Sim\nNº Máx. de Lotes Autorizado: 6\nNúmero máximo de lotes que podem ser adjudicados a um concorrente: 6\n\n6 - OBJETO DO CONTRATO\nNúmero de referência interna: FM-2025-420 DACP\nDesignação do contrato: CONTRATAÇÃO DA PRESTAÇÃO DE SERVIÇOS DE MANUTENÇÃO DOS ESPAÇOS VERDES \nDescrição: CONTRATAÇÃO DA PRESTAÇÃO DE SERVIÇOS DE MANUTENÇÃO DOS ESPAÇOS VERDES NAS ESCOLAS BÁSICAS 2º E 3º CICLOS E SECUNDÁRIA DE QUARTEIRA, LOULÉ, SALIR, ALMANCIL, BOLIQUEIME, CENTRO DE SAÚDE DE LOULÉ E URBANIZAÇÃO DO CREST\nOpções: Não\nTipo de Contrato Principal: Aquisição de Serviços\nTipo de Contrato: Aquisição de Serviços\nClassificação CPV (Vocabulário Comum para os Contratos Públicos)\nObjeto principal\nVocabulário Principal: 77310000\nPreço base s/IVA: 121.200,00 EUR\nLotes: \nNº: LOT-0001\nDescrição do Lote: LOTE 1 \nPreço base s/IVA: 16.800,00 EUR\nClassificação CPV (Vocabulário Comum para os Contratos Públicos)\nObjeto principal\nVocabulário Principal: 77310000\nNº: LOT-0002\nDescrição do Lote: LOTE 2 \nPreço base s/IVA: 21.600,00 EUR\nClassificação CPV (Vocabulário Comum para os Contratos Públicos)\nObjeto principal\nVocabulário Principal: 77310000\nNº: LOT-0003\nDescrição do Lote: LOTE 3 \nPreço base s/IVA: 21.600,00 EUR\nClassificação CPV (Vocabulário Comum para os Contratos Públicos)\nObjeto principal\nVocabulário Principal: 77310000\nNº: LOT-0004\nDescrição do Lote: LOTE 4 \nPreço base s/IVA: 24.000,00 EUR\nClassificação CPV (Vocabulário Comum para os Contratos Públicos)\nObjeto principal\nVocabulário Principal: 77310000\nNº: LOT-0005\nDescrição do Lote: LOTE 5 \nPreço base s/IVA: 18.000,00 EUR\nClassificação CPV (Vocabulário Comum para os Contratos Públicos)\nObjeto principal\nVocabulário Principal: 77310000\nNº: LOT-0006\nDescrição do Lote: LOTE 6\nPreço base s/IVA: 19.200,00 EUR\nClassificação CPV (Vocabulário Comum para os Contratos Públicos)\nObjeto principal\nVocabulário Principal: 77310000\n\n7 - INDICAÇÕES ADICIONAIS\nO contrato envolve aquisição conjunta (satisfação de várias entidades)? Não\nO contrato é adjudicado por uma central de compras? Não\n\n8 - TÉCNICAS\nO concurso destina-se à celebração de um acordo-quadro? Inexistência de acordo-quadro\nÉ utilizado um leilão eletrónico? Não\nÉ adotada uma fase de negociação? Não\nSistema de Aquisição Dinâmico: Inexistência de sistema de aquisição dinâmico\n\n9 - LOCAL DA EXECUÇÃO DO CONTRATO\nLOCAL DA EXECUÇÃO DO CONTRATO (PROCEDIMENTO)\nPaís: Portugal\nNUT III: PT150\nLocalidade: Loulé\nDistrito: Faro\nConcelho: Loulé\nFreguesia: Freguesia de Loulé (São Clemente)\nLOCAL DA EXECUÇÃO DO CONTRATO (LOTE)\nIdentificador do Lote: LOT-0001; LOT-0002; LOT-0003; LOT-0004; LOT-0005; LOT-0006\nPaís: Portugal\nNUT III: PT150\nLocalidade: Faro\nDistrito: Faro\nConcelho: Loulé\nFreguesia: Freguesia de Loulé (São Clemente)\n\n10 - PRAZO DE EXECUÇÃO DO CONTRATO\nIdentificador do Lote: LOT-0001; LOT-0002; LOT-0003; LOT-0004; LOT-0005; LOT-0006\nPrazo de execução do contrato: 12 MESES\nPrevisão de renovações: Não\n\n11 - FUNDOS EU\nIdentificador do Lote: LOT-0001; LOT-0002; LOT-0003; LOT-0004; LOT-0005; LOT-0006\nTêm fundos EU? Não\n\n12 - DOCUMENTOS DE HABILITAÇÃO\nHabilitação para o exercício da atividade profissional: Não\n\n13 - CONDIÇÕES DE APRESENTAÇÃO\nPlataforma eletrónica utilizada pela entidade adjudicante: VORTAL\nURL para Apresentação: https://community.vortal.biz/public/\nAdmissibilidade da apresentação de propostas variantes: Não autorizado\nPrazo para apresentação das propostas: 04-11-2025 18:00\nPrazo durante o qual os concorrentes são obrigados a manter as respetivas propostas: 90 dias a contar do termo do prazo para a apresentação das propostas\nApresentação de Catálogo Eletrónico: Não autorizado\nIndicação de Subcontratação na Proposta: Inexistência de indicação de subcontratação\n\n14 - PRESTAÇÃO DE CAUÇÃO\nPrestação de caução: Não\n\n15 - FORNECIMENTO DAS PEÇAS DO CONCURSO, APRESENTAÇÃO DE PEDIDOS DE PARTICIPAÇÃO E APRESENTAÇÃO DAS PROPOSTAS\nLink para acesso às peças do concurso (URL): https://community.vortal.biz/Public/public-tender-documents/OVl3ZkhNb1hLVEROYlVXbC9kT3c5bmtTSVVaUkZnNGQ5dnY5UG9BQnUyM2dxZjJQNXQxemlkQkE5cnVwY3NodzhydUE2bkFZQ09RSXQ4WVNjc05Xdmc9PUtYKnFQ\n\n20 - OUTROS REQUISITOS\nIdentificador do Lote: LOT-0001; LOT-0002; LOT-0003; LOT-0004; LOT-0005; LOT-0006\nInformação sobre contratos reservados. Aplica-se a contratos reservados (54º-A)? Não\n\n21 - CRITÉRIO DE ADJUDICAÇÃO\nO Critério de adjudicação é diferenciado por lote? Não\nMultifator: Não\nMonofator:\nNome: Preço\n\n24 - CONDIÇÕES DO CONTRATO\nIdentificador do Lote: LOT-0001; LOT-0002; LOT-0003; LOT-0004; LOT-0005; LOT-0006\nFaturação Eletrónica: Permitido\nObrigação de Subcontratação:\nCódigo da Obrigação de Subcontratação: Não é aplicável nenhuma obrigação de subcontratação.\n\n25 - COMPRA PÚBLICA ESTRATÉGICA\nCompra Pública Estratégica: Inexistência de contratação pública estratégica\n\n26 - INFORMAÇÕES ADICIONAIS\nIdentificador do Lote: LOT-0001; LOT-0002; LOT-0003; LOT-0004; LOT-0005; LOT-0006\nContrato adequado para PME: Sim\nCobertura ACP (Acordo dos Contratos Públicos da Organização Mundial do Comércio): Não\n\n27 - IDENTIFICAÇÃO E CONTACTOS DO ÓRGÃO DE RECURSOS ADMINISTRATIVOS\nDesignação: Câmara Municipal de Loulé\nEndereço: Praça da República\nCódigo postal: 8101-004\nLocalidade: Loulé\nTelefone: +351 289400600\nFax: +351 289415557\nEndereço eletrónico: geral@cm-loule.pt\n\n28 - IDENTIFICAÇÃO DO(S) AUTOR(ES) DE ANÚNCIO\nNome: Vítor Manuel Gonçalves Aleixo\nCargo: Presidente da Câmara Municipal\n419594033",
    "nipc": "502098139",
    "distrito": "Faro",
    "concelho": "Loulé",
    "freguesia": "Todas",
    "site": "www.cm-loule.pt",
    "email": "aprovisionamento@cm-loule.pt",
    "designacao_contrato": "CONTRATAÇÃO DA PRESTAÇÃO DE SERVIÇOS DE MANUTENÇÃO DOS ESPAÇOS VERDES",
    "descricao": "CONTRATAÇÃO DA PRESTAÇÃO DE SERVIÇOS DE MANUTENÇÃO DOS ESPAÇOS VERDES NAS ESCOLAS BÁSICAS 2º E 3º CICLOS E SECUNDÁRIA DE QUARTEIRA, LOULÉ, SALIR, ALMANCIL, BOLIQUEIME, CENTRO DE SAÚDE DE LOULÉ E URBANIZAÇÃO DO CREST",
    "preco_base": "121.200,00 EUR",
    "prazo_execucao": "12 MESES",
    "prazo_apresentacao_propostas": "04-11-2025 18:00",
    "fundos_eu": "Não",
    "plataforma_eletronica": "VORTAL",
    "url_procedimento": "https://community.vortal.biz/public/",
    "autor_nome": "Vítor Manuel Gonçalves Aleixo",
    "autor_cargo": "Presidente da Câmara Municipal"
  },
  {
    "numero_procedimento": "N/A",
    "entidade": "Freguesia de São Domingos de Benfica",
    "link": "https://diariodarepublica.pt/dr/detalhe/contrato-publico/25988-937820806",
    "detalhes_completos": "1 - IDENTIFICAÇÃO E CONTACTOS DA ENTIDADE ADJUDICANTE\nDesignação da entidade adjudicante: Freguesia de São Domingos de Benfica\nNIPC: 505203731\nEndereço: Rua António Saúde, 11 - 13\nCódigo postal: 1500-048\nLocalidade: Lisboa\nPaís: Portugal\nNUT III: PT170\nDistrito: Lisboa\nConcelho: Lisboa\nFreguesia: Freguesia de São Domingos de Benfica\nTelefone: 217248610\nFax: 217248611\nEndereço Eletrónico: geral@jf-sdomingosbenfica.pt\neDelivery Gateway (URL): https://community.vortal.biz/public/\nFunção da Organização: Adquirente\nNorma jurídica da Entidade Adjudicante: Autoridade local\nÁrea de atividade da Autoridade Adjudicante: Serviços públicos das administrações públicas\n\n2 - JORNAL OFICIAL DA UNIÃO EUROPEIA\nO procedimento a que este anúncio diz respeito também é publicitado no Jornal Oficial da União Europeia? Não\n\n3 - AVISO\nModelo de Anúncio: Concurso público\nData de Envio do Anúncio: 02-10-2025\n\n5 - PROCESSO\nTipo de Procedimento: Concurso público\nPreço base do procedimento: Sim\nValor do preço base do procedimento: 400,00 EUR\nProcedimento com lotes? Não\n\n6 - OBJETO DO CONTRATO\nNúmero de referência interna: Conc. Púb. Concessão p/ exploração Bar/Caf./Merc.\nDesignação do contrato: Concurso Público, para exploração de Bar/Cafetaria/Mercearia, destinado a estabelecimento de bebidas e produtos e com área esplanada, localizado na Sala Polivalente do Sítio do Calhau\nDescrição: Concurso Público, para exploração de Bar/Cafetaria/Mercearia, destinado a estabelecimento de bebidas e produtos e com área esplanada, localizado na Sala Polivalente do Sítio do Calhau, sito na Rua António Macedo n.º 1, 1500-045 Lisboa\nTipo de Contrato Principal: Concessão de Serviços Públicos\nTipo de Contrato: Concessão de Serviços Públicos\nClassificação CPV (Vocabulário Comum para os Contratos Públicos)\nObjeto principal\nVocabulário Principal: 55330000\nPreço base s/IVA: 400,00 EUR\n\n7 - INDICAÇÕES ADICIONAIS\nO contrato envolve aquisição conjunta (satisfação de várias entidades)? Não\nO contrato é adjudicado por uma central de compras? Não\n\n8 - TÉCNICAS\nO concurso destina-se à celebração de um acordo-quadro? Inexistência de acordo-quadro\nÉ utilizado um leilão eletrónico? Não\nÉ adotada uma fase de negociação? Não\nSistema de Aquisição Dinâmico: Inexistência de sistema de aquisição dinâmico\n\n9 - LOCAL DA EXECUÇÃO DO CONTRATO\nLOCAL DA EXECUÇÃO DO CONTRATO (PROCEDIMENTO)\nPaís: Portugal\nNUT III: PT170\nLocalidade: Lisboa\nDistrito: Lisboa\nConcelho: Lisboa\nFreguesia: Freguesia de São Domingos de Benfica\n\n10 - PRAZO DE EXECUÇÃO DO CONTRATO\nPrazo de execução do contrato: 3 ANOS\nPrevisão de renovações: Sim\nIndicar número máximo de renovações: 3\nPrazo de renovações diferente do prazo inicial: Não\n\n11 - FUNDOS EU\nTêm fundos EU? Não\n\n12 - DOCUMENTOS DE HABILITAÇÃO\nHabilitação para o exercício da atividade profissional: Não\n\n13 - CONDIÇÕES DE APRESENTAÇÃO\nPlataforma eletrónica utilizada pela entidade adjudicante: VORTAL\nURL para Apresentação: https://community.vortal.biz/public/\nAdmissibilidade da apresentação de propostas variantes: Não autorizado\nPrazo para apresentação das propostas: 08-10-2025 23:59\nPrazo durante o qual os concorrentes são obrigados a manter as respetivas propostas: 120 dias a contar do termo do prazo para a apresentação das propostas\nIndicação de Subcontratação na Proposta: Inexistência de indicação de subcontratação\n\n14 - PRESTAÇÃO DE CAUÇÃO\nPrestação de caução: Sim\nPercentagem: 2%\nDescrição da Garantia Exigida: Vide cláusula 23.ª do Programa do Procedimento\n\n15 - FORNECIMENTO DAS PEÇAS DO CONCURSO, APRESENTAÇÃO DE PEDIDOS DE PARTICIPAÇÃO E APRESENTAÇÃO DAS PROPOSTAS\nLink para acesso às peças do concurso (URL): https://community.vortal.biz/Public/public-tender-documents/MmZXRERsSElkb0V0eDVEMnV1NmFIanYyU01sV3l6RysvR1VzL0ZsbWlQRm5BVlRpZEFFbW5KT1hmU1YzQkdKQlRLWnZyY2wwREREKzgxakRWQ1ZnTlE9PUVRVmNM\n\n20 - OUTROS REQUISITOS\nInformação sobre contratos reservados. Aplica-se a contratos reservados (54º-A)? Não\n\n21 - CRITÉRIO DE ADJUDICAÇÃO\nMultifator: Não\nMonofator:\nNome: Preço\n\n24 - CONDIÇÕES DO CONTRATO\nFaturação Eletrónica: Permitido\nObrigação de Subcontratação:\nCódigo da Obrigação de Subcontratação: Não é aplicável nenhuma obrigação de subcontratação.\n\n25 - COMPRA PÚBLICA ESTRATÉGICA\nCompra Pública Estratégica: Inexistência de contratação pública estratégica\n\n26 - INFORMAÇÕES ADICIONAIS\nContrato adequado para PME: Sim\nCobertura ACP (Acordo dos Contratos Públicos da Organização Mundial do Comércio): Não\n\n27 - IDENTIFICAÇÃO E CONTACTOS DO ÓRGÃO DE RECURSOS ADMINISTRATIVOS\nDesignação: Junta de Freguesia de São Domingos de Benfica\nEndereço: Rua António Saúde, 11 - 13\nCódigo postal: 1500-048\nLocalidade: Lisboa\nTelefone: +351 217248610\nFax: +351 217248610\nEndereço eletrónico: geral@jf-sdomingosbenfica.pt\n\n28 - IDENTIFICAÇÃO DO(S) AUTOR(ES) DE ANÚNCIO\nNome: Luis Vilas Boas\nCargo: Técnico Superior\n419606256",
    "nipc": "505203731",
    "distrito": "Lisboa",
    "concelho": "Lisboa",
    "freguesia": "Freguesia de São Domingos de Benfica",
    "site": null,
    "email": "geral@jf-sdomingosbenfica.pt",
    "designacao_contrato": "Concurso Público, para exploração de Bar/Cafetaria/Mercearia, destinado a estabelecimento de bebidas e produtos e com área esplanada, localizado na Sala Polivalente do Sítio do Calhau",
    "descricao": "Concurso Público, para exploração de Bar/Cafetaria/Mercearia, destinado a estabelecimento de bebidas e produtos e com área esplanada, localizado na Sala Polivalente do Sítio do Calhau, sito na Rua António Macedo n.º 1, 1500-045 Lisboa",
    "preco_base": "400,00 EUR",
    "prazo_execucao": "3 ANOS",
    "prazo_apresentacao_propostas": "08-10-2025 23:59",
    "fundos_eu": "Não",
    "plataforma_eletronica": "VORTAL",
    "url_procedimento": "https://community.vortal.biz/public/",
    "autor_nome": "Luis Vilas Boas",
    "autor_cargo": "Técnico Superior"
  },
  {
    "numero_procedimento": "N/A",
    "entidade": "Município de Vila Nova de Foz Côa",
    "link": "https://diariodarepublica.pt/dr/detalhe/contrato-publico/25990-937820807",
    "detalhes_completos": "1 - IDENTIFICAÇÃO E CONTACTOS DA ENTIDADE ADJUDICANTE\nDesignação da entidade adjudicante: Município de Vila Nova de Foz Côa\nNIPC: 506829197\nServiço/Órgão/Pessoa de contacto: Divisão de Obras Municipais e Infraestruturas\nEndereço: PRAÇA DO MUNICÍPIO\nCódigo postal: 5150-642\nLocalidade: VILA NOVA DE FOZ CÔA\nPaís: Portugal\nNUT III: PT11D\nDistrito: Guarda\nConcelho: Vila Nova de Foz Coa\nFreguesia: Freguesia de Vila Nova de Foz Côa\nTelefone: 279760400\nFax: 279760438\nEndereço da Entidade (URL): http://cm-fozcoa.pt/\nEndereço Eletrónico: correio@cm-fozcoa.pt\neDelivery Gateway (URL): https://www.acingov.pt\nFunção da Organização: Adquirente\nNorma jurídica da Entidade Adjudicante: Organismo de direito público\nÁrea de atividade da Autoridade Adjudicante: Serviços públicos das administrações públicas\n\n2 - JORNAL OFICIAL DA UNIÃO EUROPEIA\nO procedimento a que este anúncio diz respeito também é publicitado no Jornal Oficial da União Europeia? Não\n\n3 - AVISO\nModelo de Anúncio: Concurso público\nData de Envio do Anúncio: 02-10-2025\n\n5 - PROCESSO\nTipo de Procedimento: Concurso público\nPreço base do procedimento: Sim\nValor do preço base do procedimento: 147.292,15 EUR\nProcedimento com lotes? Não\n\n6 - OBJETO DO CONTRATO\nNúmero de referência interna: 36/25\nDesignação do contrato: 36/25 - Remodelação do edifício na rua Fundo da Vila em Cedovim - 1º Direito\nDescrição: Remodelação do edifício na rua Fundo da Vila em Cedovim - 1º Direito\nTipo de Contrato Principal: Empreitada de Obras Públicas\nTipo de Contrato: Empreitada de Obras Públicas\nClassificação CPV (Vocabulário Comum para os Contratos Públicos)\nObjeto principal\nVocabulário Principal: 45210000\nPreço base s/IVA: 147.292,15 EUR\n\n7 - INDICAÇÕES ADICIONAIS\nO contrato envolve aquisição conjunta (satisfação de várias entidades)? Não\nO contrato é adjudicado por uma central de compras? Não\n\n8 - TÉCNICAS\nO concurso destina-se à celebração de um acordo-quadro? Inexistência de acordo-quadro\nÉ utilizado um leilão eletrónico? Não\nÉ adotada uma fase de negociação? Não\nSistema de Aquisição Dinâmico: Inexistência de sistema de aquisição dinâmico\n\n9 - LOCAL DA EXECUÇÃO DO CONTRATO\nLOCAL DA EXECUÇÃO DO CONTRATO (PROCEDIMENTO)\nPaís: Portugal\nNUT III: PT11D\nLocalidade: Freguesia de Cedovim\nDistrito: Guarda\nConcelho: Vila Nova de Foz Coa\nFreguesia: Freguesia de Cedovim\n\n10 - PRAZO DE EXECUÇÃO DO CONTRATO\nPrazo de execução do contrato: 270 DIAS\nPrevisão de renovações: Não\n\n11 - FUNDOS EU\nTêm fundos EU? Sim\n\n12 - DOCUMENTOS DE HABILITAÇÃO\nHabilitação para o exercício da atividade profissional: Sim\nTipo: Alvará\nDescrição: Alvará de empreiteiro: 1ª subcategoria da 1ª categoria do valor total da obra 1ª, 5ª e 6ª subcategoria da 1ª categoria, 1ª subcategoria da 4ª categoria do valor dos trabalhos a que dizem respeito\n\n13 - CONDIÇÕES DE APRESENTAÇÃO\nPlataforma eletrónica utilizada pela entidade adjudicante: ACIN\nURL para Apresentação: https://www.acingov.pt\nAdmissibilidade da apresentação de propostas variantes: Não autorizado\nPrazo para apresentação das propostas: 16-10-2025 23:59\nPrazo durante o qual os concorrentes são obrigados a manter as respetivas propostas: 88 dias a contar do termo do prazo para a apresentação das propostas\nIndicação de Subcontratação na Proposta: Inexistência de indicação de subcontratação\n\n14 - PRESTAÇÃO DE CAUÇÃO\nPrestação de caução: Não\n\n15 - FORNECIMENTO DAS PEÇAS DO CONCURSO, APRESENTAÇÃO DE PEDIDOS DE PARTICIPAÇÃO E APRESENTAÇÃO DAS PROPOSTAS\nLink para acesso às peças do concurso (URL): https://www.acingov.pt/acingovprod/2/zonaPublica/zona_publica_c/donwloadProcedurePiece/OTgwMjQ3\n\n20 - OUTROS REQUISITOS\nInformação sobre contratos reservados. Aplica-se a contratos reservados (54º-A)? Não\n\n21 - CRITÉRIO DE ADJUDICAÇÃO\nMultifator: Não\nMonofator:\nNome: Preço\n\n24 - CONDIÇÕES DO CONTRATO\nFaturação Eletrónica: Permitido\nObrigação de Subcontratação:\nCódigo da Obrigação de Subcontratação: Não é aplicável nenhuma obrigação de subcontratação.\n\n25 - COMPRA PÚBLICA ESTRATÉGICA\nCompra Pública Estratégica: Inexistência de contratação pública estratégica\n\n26 - INFORMAÇÕES ADICIONAIS\nContrato adequado para PME: Não\nCobertura ACP (Acordo dos Contratos Públicos da Organização Mundial do Comércio): Não\n\n27 - IDENTIFICAÇÃO E CONTACTOS DO ÓRGÃO DE RECURSOS ADMINISTRATIVOS\nDesignação: Presidente da Câmara Municipal\nEndereço: Câmara Municipal - Praça do Munícipio\nCódigo postal: 5150-642\nLocalidade: VILA NOVA DE FOZ CÔA\nTelefone: 279760400\nFax: \nEndereço eletrónico: correio@cm-fozcoa.pt\n\n28 - IDENTIFICAÇÃO DO(S) AUTOR(ES) DE ANÚNCIO\nNome: Pedro Miguel de Carvalho Duarte\nCargo: Presidente da Câmara Municipal\n419602538",
    "nipc": "506829197",
    "distrito": "Guarda",
    "concelho": "Vila Nova de Foz Coa",
    "freguesia": "Freguesia de Vila Nova de Foz Côa",
    "site": "http://cm-fozcoa.pt/",
    "email": "correio@cm-fozcoa.pt",
    "designacao_contrato": "36/25 - Remodelação do edifício na rua Fundo da Vila em Cedovim - 1º Direito",
    "descricao": "Remodelação do edifício na rua Fundo da Vila em Cedovim - 1º Direito",
    "preco_base": "147.292,15 EUR",
    "prazo_execucao": "270 DIAS",
    "prazo_apresentacao_propostas": "16-10-2025 23:59",
    "fundos_eu": "Sim",
    "plataforma_eletronica": "ACIN",
    "url_procedimento": "https://www.acingov.pt",
    "autor_nome": "Pedro Miguel de Carvalho Duarte",
    "autor_cargo": "Presidente da Câmara Municipal"
  },
  {
    "numero_procedimento": "N/A",
    "entidade": "AnÃºncio de procedimento  n.Âº 25992/2025  -  DiÃ¡rio da RepÃºblica n.Âº 191/2025, SÃ©rie II de 2025-10-03",
    "link": "https://diariodarepublica.pt/dr/detalhe/contrato-publico/25992-937820808"
  },
  {
    "numero_procedimento": "N/A",
    "entidade": "SERVIÇOS MUNICIPALIZADOS DE ÁGUAS E SANEAMENTO DE MAFRA - SMAS DE MAFRA",
    "link": "https://diariodarepublica.pt/dr/detalhe/contrato-publico/25995-937820809",
    "detalhes_completos": "1 - IDENTIFICAÇÃO E CONTACTOS DA ENTIDADE ADJUDICANTE\nDesignação da entidade adjudicante: SERVIÇOS MUNICIPALIZADOS DE ÁGUAS E SANEAMENTO DE MAFRA - SMAS DE MAFRA\nNIPC: 600087247\nEndereço: R. Constância Maria Rodrigues n.º 19\nCódigo postal: 2640-389\nLocalidade: Lisboa\nPaís: Portugal\nNUT III: PT170\nDistrito: Lisboa\nConcelho: Mafra\nFreguesia: Freguesia de Mafra\nTelefone: 261816650\nFax: 261816659\nEndereço da Entidade (URL): www.smas-mafra.pt\nEndereço Eletrónico: geral@smas-mafra.pt\neDelivery Gateway (URL): https://community.vortal.biz/public/\nFunção da Organização: Adquirente\nNorma jurídica da Entidade Adjudicante: Organismo de direito público\nÁrea de atividade da Autoridade Adjudicante: Serviços públicos das administrações públicas\n\n2 - JORNAL OFICIAL DA UNIÃO EUROPEIA\nO procedimento a que este anúncio diz respeito também é publicitado no Jornal Oficial da União Europeia? Sim\n\n3 - AVISO\nModelo de Anúncio: Concurso público\nData de Envio do Anúncio: 30-09-2025\n\n5 - PROCESSO\nTipo de Procedimento: Concurso público\nPreço base do procedimento: Sim\nValor do preço base do procedimento: 376.320,00 EUR\nProcedimento com lotes? Não\n\n6 - OBJETO DO CONTRATO\nNúmero de referência interna: 374/SMAS/2025\nDesignação do contrato: Prestação de serviços de esvaziamento de fossas séticas para 18 meses\nDescrição: Prestação de serviços de esvaziamento de fossas séticas para 18 meses\nOpções: Não\nTipo de Contrato Principal: Aquisição de Serviços\nTipo de Contrato: Aquisição de Serviços\nClassificação CPV (Vocabulário Comum para os Contratos Públicos)\nObjeto principal\nVocabulário Principal: 90460000\nPreço base s/IVA: 376.320,00 EUR\n\n7 - INDICAÇÕES ADICIONAIS\nO contrato envolve aquisição conjunta (satisfação de várias entidades)? Não\nO contrato é adjudicado por uma central de compras? Não\n\n8 - TÉCNICAS\nO concurso destina-se à celebração de um acordo-quadro? Inexistência de acordo-quadro\nÉ utilizado um leilão eletrónico? Não\nÉ adotada uma fase de negociação? Não\nSistema de Aquisição Dinâmico: Inexistência de sistema de aquisição dinâmico\n\n9 - LOCAL DA EXECUÇÃO DO CONTRATO\nLOCAL DA EXECUÇÃO DO CONTRATO (PROCEDIMENTO)\nPaís: Portugal\nNUT III: PT170\nLocalidade: Lisboa\nDistrito: Lisboa\nConcelho: Mafra\nFreguesia: Freguesia de Mafra\n\n10 - PRAZO DE EXECUÇÃO DO CONTRATO\nPrazo de execução do contrato: 18 MESES\nPrevisão de renovações: Não\n\n11 - FUNDOS EU\nTêm fundos EU? Não\n\n12 - DOCUMENTOS DE HABILITAÇÃO\nHabilitação para o exercício da atividade profissional: Não\n\n13 - CONDIÇÕES DE APRESENTAÇÃO\nPlataforma eletrónica utilizada pela entidade adjudicante: VORTAL\nURL para Apresentação: https://community.vortal.biz/public/\nAdmissibilidade da apresentação de propostas variantes: Não autorizado\nPrazo para apresentação das propostas: 12-11-2025 23:59\nPrazo durante o qual os concorrentes são obrigados a manter as respetivas propostas: 66 dias a contar do termo do prazo para a apresentação das propostas\nApresentação de Catálogo Eletrónico: Não autorizado\nIndicação de Subcontratação na Proposta: Inexistência de indicação de subcontratação\n\n14 - PRESTAÇÃO DE CAUÇÃO\nPrestação de caução: Sim\nPercentagem: 5%\nDescrição da Garantia Exigida: A caução é prestada por depósito em dinheiro ou em títulos emitidos ou garantidos pelo Estado, ou mediante garantia bancária ou seguro de caução, conforme escolha do adjudicatário.\n\n15 - FORNECIMENTO DAS PEÇAS DO CONCURSO, APRESENTAÇÃO DE PEDIDOS DE PARTICIPAÇÃO E APRESENTAÇÃO DAS PROPOSTAS\nLink para acesso às peças do concurso (URL): https://community.vortal.biz/Public/public-tender-documents/VXJJWEJvSHVKNDhLYjc4a1dzTmR6U2FDR3JQaStHV1lHV1l5NTM5d1NpT09KSEgzZ3RWYzhNdU1hbzRuNFozdGNvNE02dERxTGdCc0ZaQ3l2Z3dnZWc9PSVmIVhH\n\n20 - OUTROS REQUISITOS\nInformação sobre contratos reservados. Aplica-se a contratos reservados (54º-A)? Não\n\n21 - CRITÉRIO DE ADJUDICAÇÃO\nMultifator: Não\nMonofator:\nNome: Preço\n\n24 - CONDIÇÕES DO CONTRATO\nFaturação Eletrónica: Permitido\nObrigação de Subcontratação:\nCódigo da Obrigação de Subcontratação: Não é aplicável nenhuma obrigação de subcontratação.\n\n25 - COMPRA PÚBLICA ESTRATÉGICA\nCompra Pública Estratégica: Inexistência de contratação pública estratégica\n\n26 - INFORMAÇÕES ADICIONAIS\nContrato adequado para PME: Sim\nCobertura ACP (Acordo dos Contratos Públicos da Organização Mundial do Comércio): Não\n\n27 - IDENTIFICAÇÃO E CONTACTOS DO ÓRGÃO DE RECURSOS ADMINISTRATIVOS\nDesignação: Conselho de Administração dos SMAS de Mafra\nEndereço: R. Constância Maria Rodrigues n.º 19\nCódigo postal: 2640-389\nLocalidade: Mafra\nTelefone: +351 261816650\nFax: +351 261816659\nEndereço eletrónico: geral@smas-mafra.pt\n\n28 - IDENTIFICAÇÃO DO(S) AUTOR(ES) DE ANÚNCIO\nNome: Hugo Moreira Luís\nCargo: Presidente do Conselho de Administração dos SMAS de Mafra\n419590891",
    "nipc": "600087247",
    "distrito": "Lisboa",
    "concelho": "Mafra",
    "freguesia": "Freguesia de Mafra",
    "site": "www.smas-mafra.pt",
    "email": "geral@smas-mafra.pt",
    "designacao_contrato": "Prestação de serviços de esvaziamento de fossas séticas para 18 meses",
    "descricao": "Prestação de serviços de esvaziamento de fossas séticas para 18 meses",
    "preco_base": "376.320,00 EUR",
    "prazo_execucao": "18 MESES",
    "prazo_apresentacao_propostas": "12-11-2025 23:59",
    "fundos_eu": "Não",
    "plataforma_eletronica": "VORTAL",
    "url_procedimento": "https://community.vortal.biz/public/",
    "autor_nome": "Hugo Moreira Luís",
    "autor_cargo": "Presidente do Conselho de Administração dos SMAS de Mafra"
  },
  {
    "numero_procedimento": "N/A",
    "entidade": "Ceprof - Centros Escolares de Ensino Profissional Lda",
    "link": "https://diariodarepublica.pt/dr/detalhe/contrato-publico/25998-937820819",
    "detalhes_completos": "1 - IDENTIFICAÇÃO E CONTACTOS DA ENTIDADE ADJUDICANTE\nDesignação da entidade adjudicante: Ceprof - Centros Escolares de Ensino Profissional Lda\nNIPC: 504453211\nEndereço: Rua Vinte e Sete, Número 847\nCódigo postal: 4500-287\nLocalidade: Aveiro\nPaís: Portugal\nNUT III: PT11A\nDistrito: Aveiro\nConcelho: Espinho\nFreguesia: Freguesia de Espinho - Espinho\nTelefone: 227330430\nFax: NA\nEndereço da Entidade (URL): https://espe.pt/\nEndereço Eletrónico: geral@espe.pt\neDelivery Gateway (URL): https://community.vortal.biz/public/\nFunção da Organização: Adquirente\nNorma jurídica da Entidade Adjudicante: Autoridade da administração central\nÁrea de atividade da Autoridade Adjudicante: Educação\n\n2 - JORNAL OFICIAL DA UNIÃO EUROPEIA\nO procedimento a que este anúncio diz respeito também é publicitado no Jornal Oficial da União Europeia? Não\n\n3 - AVISO\nModelo de Anúncio: Concurso público\nData de Envio do Anúncio: 02-10-2025\n\n5 - PROCESSO\nTipo de Procedimento: Concurso público\nPreço base do procedimento: Sim\nValor do preço base do procedimento: 127.000,00 EUR\nProcedimento com lotes? Sim\nNº Máx. de Lotes Autorizado: 5\nNúmero máximo de lotes que podem ser adjudicados a um concorrente: 5\n\n6 - OBJETO DO CONTRATO\nNúmero de referência interna: CTE - 08.10.2025\nDesignação do contrato: Aquisição de Tecnologias de suporte à Inovação e Aprendizagem para o CTE Industrial da Escola Profissional de Espinho\nDescrição: Aquisição de Tecnologias de suporte à Inovação e Aprendizagem para o CTE Industrial da Escola Profissional de Espinho\nTipo de Contrato Principal: Aquisição de Bens Móveis\nTipo de Contrato: Aquisição de Bens Móveis\nClassificação CPV (Vocabulário Comum para os Contratos Públicos)\nObjeto principal\nVocabulário Principal: 31710000\nPreço base s/IVA: 127.000,00 EUR\nLotes: \nNº: LOT-0001\nDescrição do Lote: Lote 1 - Kits de Microcontrolo\nPreço base s/IVA: 14.000,00 EUR\nClassificação CPV (Vocabulário Comum para os Contratos Públicos)\nObjeto principal\nVocabulário Principal: 31710000\nNº: LOT-0002\nDescrição do Lote: Lote 2 - Kits de Realidade Virtual e Inteligência Artificial\nPreço base s/IVA: 26.500,00 EUR\nClassificação CPV (Vocabulário Comum para os Contratos Públicos)\nObjeto principal\nVocabulário Principal: 31710000\nNº: LOT-0003\nDescrição do Lote: Lote 3 - Kits de Automação\nPreço base s/IVA: 55.000,00 EUR\nClassificação CPV (Vocabulário Comum para os Contratos Públicos)\nObjeto principal\nVocabulário Principal: 31710000\nNº: LOT-0004\nDescrição do Lote: Lote 4 - Material de Multimédia e Conferência\nPreço base s/IVA: 6.500,00 EUR\nClassificação CPV (Vocabulário Comum para os Contratos Públicos)\nObjeto principal\nVocabulário Principal: 31710000\nNº: LOT-0005\nDescrição do Lote: Lote 5 - Equipamentos informáticos de processamento de dados\nPreço base s/IVA: 25.000,00 EUR\nClassificação CPV (Vocabulário Comum para os Contratos Públicos)\nObjeto principal\nVocabulário Principal: 31710000\n\n7 - INDICAÇÕES ADICIONAIS\nO contrato envolve aquisição conjunta (satisfação de várias entidades)? Não\nO contrato é adjudicado por uma central de compras? Não\n\n8 - TÉCNICAS\nO concurso destina-se à celebração de um acordo-quadro? Inexistência de acordo-quadro\nÉ utilizado um leilão eletrónico? Não\nÉ adotada uma fase de negociação? Não\nSistema de Aquisição Dinâmico: Inexistência de sistema de aquisição dinâmico\n\n9 - LOCAL DA EXECUÇÃO DO CONTRATO\nLOCAL DA EXECUÇÃO DO CONTRATO (PROCEDIMENTO)\nPaís: Portugal\nNUT III: PT11A\nLocalidade: Aveiro\nDistrito: Aveiro\nConcelho: Espinho\nFreguesia: Freguesia de Espinho - Espinho\nLOCAL DA EXECUÇÃO DO CONTRATO (LOTE)\nIdentificador do Lote: LOT-0001; LOT-0002; LOT-0003; LOT-0004; LOT-0005\nPaís: Portugal\nNUT III: PT11A\nLocalidade: Aveiro\nDistrito: Aveiro\nConcelho: Espinho\nFreguesia: Freguesia de Espinho - Espinho\n\n10 - PRAZO DE EXECUÇÃO DO CONTRATO\nIdentificador do Lote: LOT-0001; LOT-0002; LOT-0003; LOT-0004; LOT-0005\nPrazo de execução do contrato: 45 DIAS\nPrevisão de renovações: Não\n\n11 - FUNDOS EU\nIdentificador do Lote: LOT-0001; LOT-0002; LOT-0003; LOT-0004; LOT-0005\nTêm fundos EU? Sim\n\n12 - DOCUMENTOS DE HABILITAÇÃO\nHabilitação para o exercício da atividade profissional: Não\n\n13 - CONDIÇÕES DE APRESENTAÇÃO\nPlataforma eletrónica utilizada pela entidade adjudicante: VORTAL\nURL para Apresentação: https://community.vortal.biz/public/\nAdmissibilidade da apresentação de propostas variantes: Não autorizado\nPrazo para apresentação das propostas: 20-10-2025 23:59\nPrazo durante o qual os concorrentes são obrigados a manter as respetivas propostas: 66 dias a contar do termo do prazo para a apresentação das propostas\nIndicação de Subcontratação na Proposta: Inexistência de indicação de subcontratação\n\n14 - PRESTAÇÃO DE CAUÇÃO\nPrestação de caução: Não\n\n15 - FORNECIMENTO DAS PEÇAS DO CONCURSO, APRESENTAÇÃO DE PEDIDOS DE PARTICIPAÇÃO E APRESENTAÇÃO DAS PROPOSTAS\nLink para acesso às peças do concurso (URL): https://community.vortal.biz/Public/public-tender-documents/VFlJMVVtaFRvZ21zeFhzUk53dDRkbDNjd0lNMFMvcW5IUlVJdEpyRjVuL1hVQXk5ZHIyUnRhL3Vsc1BmMDNpMmRGRjBGdGtKMGltcmNqZXFWVHpNa3c9PUlQc0Qz\n\n20 - OUTROS REQUISITOS\nIdentificador do Lote: LOT-0001; LOT-0002; LOT-0003; LOT-0004; LOT-0005\nInformação sobre contratos reservados. Aplica-se a contratos reservados (54º-A)? Não\n\n21 - CRITÉRIO DE ADJUDICAÇÃO\nO Critério de adjudicação é diferenciado por lote? Não\nMultifator: Não\nMonofator:\nNome: Preço\n\n24 - CONDIÇÕES DO CONTRATO\nIdentificador do Lote: LOT-0001; LOT-0002; LOT-0003; LOT-0004; LOT-0005\nFaturação Eletrónica: Permitido\nObrigação de Subcontratação:\nCódigo da Obrigação de Subcontratação: Não é aplicável nenhuma obrigação de subcontratação.\n\n25 - COMPRA PÚBLICA ESTRATÉGICA\nCompra Pública Estratégica: Inexistência de contratação pública estratégica\n\n26 - INFORMAÇÕES ADICIONAIS\nIdentificador do Lote: LOT-0001; LOT-0002; LOT-0003; LOT-0004; LOT-0005\nContrato adequado para PME: Sim\nCobertura ACP (Acordo dos Contratos Públicos da Organização Mundial do Comércio): Não\n\n27 - IDENTIFICAÇÃO E CONTACTOS DO ÓRGÃO DE RECURSOS ADMINISTRATIVOS\nDesignação: Sofia Oliveira Martins\nEndereço: Rua Vinte e Sete, Número 847\nCódigo postal: 4500-287\nLocalidade: Espinho\nTelefone: +351 227330430\nFax: +351 227330430\nEndereço eletrónico: sofiamartins@espe.pt\n\n28 - IDENTIFICAÇÃO DO(S) AUTOR(ES) DE ANÚNCIO\nNome: Sofia Oliveira Martins\nCargo: Diretora\n419607747",
    "nipc": "504453211",
    "distrito": "Aveiro",
    "concelho": "Espinho",
    "freguesia": "Freguesia de Espinho - Espinho",
    "site": "https://espe.pt/",
    "email": "geral@espe.pt",
    "designacao_contrato": "Aquisição de Tecnologias de suporte à Inovação e Aprendizagem para o CTE Industrial da Escola Profissional de Espinho",
    "descricao": "Aquisição de Tecnologias de suporte à Inovação e Aprendizagem para o CTE Industrial da Escola Profissional de Espinho",
    "preco_base": "127.000,00 EUR",
    "prazo_execucao": "45 DIAS",
    "prazo_apresentacao_propostas": "20-10-2025 23:59",
    "fundos_eu": "Sim",
    "plataforma_eletronica": "VORTAL",
    "url_procedimento": "https://community.vortal.biz/public/",
    "autor_nome": "Sofia Oliveira Martins",
    "autor_cargo": "Diretora"
  },
  {
    "numero_procedimento": "N/A",
    "entidade": "AnÃºncio de procedimento  n.Âº 25999/2025  -  DiÃ¡rio da RepÃºblica n.Âº 191/2025, SÃ©rie II de 2025-10-03",
    "link": "https://diariodarepublica.pt/dr/detalhe/contrato-publico/25999-937820820"
  },
  {
    "numero_procedimento": "N/A",
    "entidade": "EPAL - Empresa Portuguesa das Águas Livres, S. A.",
    "link": "https://diariodarepublica.pt/dr/detalhe/contrato-publico/26000-937820821",
    "detalhes_completos": "Alteração do Anúncio de procedimento n.º 24206/2025, de 2025-09-12, com o ID 419528975\n\n1 - IDENTIFICAÇÃO E CONTACTOS DA ENTIDADE ADJUDICANTE\nDesignação da entidade adjudicante: EPAL - Empresa Portuguesa das Águas Livres, S. A.\nNIPC: 500906840\nServiço/Órgão/Pessoa de contacto: Direção de Engenharia\nEndereço: Avenida da Liberdade, 24\nCódigo postal: 1250-144\nLocalidade: Lisboa\nPaís: Portugal\nNUT III: PT170\nDistrito: Lisboa\nConcelho: Lisboa\nFreguesia: Freguesia de Santo António - Lisboa\nTelefone: 213251000\nEndereço Eletrónico: epal@adp.pt\nFunção da Organização: Adquirente\nNorma jurídica da Entidade Adjudicante: Empresa pública\nÁrea de atividade da Entidade Adjudicante: Atividades relacionadas com a água\n\n2 - JORNAL OFICIAL DA UNIÃO EUROPEIA\nO procedimento a que este anúncio diz respeito também é publicitado no Jornal Oficial da União Europeia? Não\n\n3 - AVISO\nModelo de Anúncio: Concurso público\nData de Envio do Anúncio: 02-10-2025\n\n5 - PROCESSO\nTipo de Procedimento: Concurso público\nPreço base do procedimento: Sim\nValor do preço base do procedimento: 2.000.000,00 EUR\nProcedimento com lotes? Não\n\n6 - OBJETO DO CONTRATO\nNúmero de referência interna: ENG24049\nDesignação do contrato: Reabilitação dos edifícios B, C, E, F e G - Recinto do Arco \nDescrição: Realização de trabalhos de reabilitação de edifícios no Recinto do Arco, sito na Rua das Amoreiras 101, Lisboa\nTipo de Contrato Principal: Empreitada de Obras Públicas\nTipo de Contrato: Empreitada de Obras Públicas\nClassificação CPV (Vocabulário Comum para os Contratos Públicos)\nObjeto principal\nVocabulário Principal: 45400000\nPreço base s/IVA: 2.000.000,00 EUR\n\n7 - INDICAÇÕES ADICIONAIS\nO contrato envolve aquisição conjunta (satisfação de várias entidades)? Não\nO contrato é adjudicado por uma central de compras? Não\n\n8 - TÉCNICAS\nO concurso destina-se à celebração de um acordo-quadro? Inexistência de acordo-quadro\nÉ utilizado um leilão eletrónico? Não\nÉ adotada uma fase de negociação? Não\nSistema de Aquisição Dinâmico: Inexistência de sistema de aquisição dinâmico\n\n9 - LOCAL DA EXECUÇÃO DO CONTRATO\nLOCAL DA EXECUÇÃO DO CONTRATO (PROCEDIMENTO)\nPaís: Portugal\nNUT III: PT170\nLocalidade: Lisboa\nDistrito: Lisboa\nConcelho: Lisboa\nFreguesia: Freguesia de Santo António - Lisboa\n\n10 - PRAZO DE EXECUÇÃO DO CONTRATO\nPrazo de execução do contrato: 540 DIAS\nPrevisão de renovações: Não\n\n11 - FUNDOS EU\nTêm fundos EU? Não\n\n12 - DOCUMENTOS DE HABILITAÇÃO\nHabilitação para o exercício da atividade profissional: Sim\nTipo: Alvará\nDescrição: Alvarás, certificados ou declarações, emitidos pelo Instituto dos Mercados Públicos, do Imobiliário e da Construção, I.P. (IMPIC), contendo as habilitações adequadas e necessárias à execução da obra a realizar, designadamente:\ni.\t2.ª Subcategoria (Estruturas metálicas) da 1.ª categoria (Edifícios e Património Construído) e da classe correspondente ao valor global da proposta;\nii.\t1.ª Subcategoria (Estruturas e elementos de betão) da 1.ª categoria (Edifícios e Património Construído) e da classe correspondente à parte dos trabalhos a que respeita;\niii.\t5.ª Subcategoria (Estuques, pinturas e outros revestimentos) da 1.ª categoria (Edifícios e Património Construído) e da classe correspondente à parte dos trabalhos a que respeita;\niv.\t3.ª Subcategoria (Estruturas de madeira) da 1.ª categoria (Edifícios e Património Construído) e da classe correspondente à parte dos trabalhos a que respeita.\n13 - CONDIÇÕES DE APRESENTAÇÃO\nPlataforma eletrónica utilizada pela entidade adjudicante: ACIN\nURL para Apresentação: http://www.acingov.pt\nAdmissibilidade da apresentação de propostas variantes: Não autorizado\nPrazo para apresentação das propostas: 22-10-2025 18:00\nPrazo durante o qual os concorrentes são obrigados a manter as respetivas propostas: 120 dias a contar do termo do prazo para a apresentação das propostas\nApresentação de Catálogo Eletrónico: Permitido\nIndicação de Subcontratação na Proposta: A parte do contrato que o proponente tenciona subcontratar\n\n14 - PRESTAÇÃO DE CAUÇÃO\nPrestação de caução: Sim\nPercentagem: 5%\nDescrição da Garantia Exigida: A caução deve ser prestada:\na)\tPor depósito em dinheiro ou em títulos emitidos ou garantidos pelo Estado Português à ordem da EPAL nos termos do modelo constante do Anexo 4 do Programa ou\nb)\tMediante garantia bancária ou seguro-caução, nos termos dos modelos constantes do Anexo 5 do Programa.\n15 - FORNECIMENTO DAS PEÇAS DO CONCURSO, APRESENTAÇÃO DE PEDIDOS DE PARTICIPAÇÃO E APRESENTAÇÃO DAS PROPOSTAS\nLink para acesso às peças do concurso (URL): http://www.acingov.pt\n\n20 - OUTROS REQUISITOS\nInformação sobre contratos reservados. Aplica-se a contratos reservados (54º-A)? Não\n\n21 - CRITÉRIO DE ADJUDICAÇÃO\nMultifator: Não\nMonofator:\nNome: Preço\n\n24 - CONDIÇÕES DO CONTRATO\nFaturação Eletrónica: Necessário\nObrigação de Subcontratação:\nCódigo da Obrigação de Subcontratação: O contratante tem de indicar qualquer mudança de subcontratantes durante a execução do contrato.\n\n25 - COMPRA PÚBLICA ESTRATÉGICA\nCompra Pública Estratégica: Inexistência de contratação pública estratégica\n\n26 - INFORMAÇÕES ADICIONAIS\nContrato adequado para PME: Sim\nCobertura ACP (Acordo dos Contratos Públicos da Organização Mundial do Comércio): Não\n\n27 - IDENTIFICAÇÃO E CONTACTOS DO ÓRGÃO DE RECURSOS ADMINISTRATIVOS\nDesignação: Conselho de Administração da EPAL, S.A.\nEndereço: Avenida da Liberdade, 24\nCódigo postal: 1250-144\nLocalidade: Lisboa\nTelefone: 213251000\nFax: \nEndereço eletrónico: epal@adp.pt\nPrazo de interposição do recurso: 5 dias\n\n28 - IDENTIFICAÇÃO DO(S) AUTOR(ES) DE ANÚNCIO\nNome: José Manuel Leitão Sardinha\nCargo: Presidente do Conselho de Administração\n\n29 - ALTERAÇÃO\nMotivo da Alteração: Correção pelo editor\nIdentificador da Versão do Anúncio a Alterar: 53da8d18-81fa-484f-8ea5-076f00eef320-04\nIdentificador das Secções Alteradas do Anúncio Anterior: Condições de Apresentação\nDescrição das Alterações: Alteração do prazo das propostas para o dia 22 de outubro até às 18h00.\nAlteração dos Documentos do Concurso: Sim\nData de alteração dos documentos do concurso: 02-10-2025\n419608095",
    "nipc": "500906840",
    "distrito": "Lisboa",
    "concelho": "Lisboa",
    "freguesia": "Freguesia de Santo António - Lisboa",
    "site": null,
    "email": "epal@adp.pt",
    "designacao_contrato": "Reabilitação dos edifícios B, C, E, F e G - Recinto do Arco",
    "descricao": "Realização de trabalhos de reabilitação de edifícios no Recinto do Arco, sito na Rua das Amoreiras 101, Lisboa",
    "preco_base": "2.000.000,00 EUR",
    "prazo_execucao": "540 DIAS",
    "prazo_apresentacao_propostas": "22-10-2025 18:00",
    "fundos_eu": "Não",
    "plataforma_eletronica": "ACIN",
    "url_procedimento": "http://www.acingov.pt",
    "autor_nome": "José Manuel Leitão Sardinha",
    "autor_cargo": "Presidente do Conselho de Administração"
  },
  {
    "numero_procedimento": "N/A",
    "entidade": "Município de Sobral de Monte Agraço",
    "link": "https://diariodarepublica.pt/dr/detalhe/contrato-publico/25981-937877784",
    "detalhes_completos": "1 - IDENTIFICAÇÃO E CONTACTOS DA ENTIDADE ADJUDICANTE\nDesignação da entidade adjudicante: Município de Sobral de Monte Agraço\nNIPC: 505410850\nServiço/Órgão/Pessoa de contacto: Divisão Administrativa e Financeira\nEndereço: Praça Dr. Eugénio Dias, n.º 4\nCódigo postal: 2590-016\nLocalidade: Sobral de Monte Agraço\nPaís: Portugal\nNUT III: PT16B\nDistrito: Lisboa\nConcelho: Sobral de Monte Agraço\nFreguesia: Freguesia de Sobral de Monte Agraço\nTelefone: 261940300\nFax: 261940310\nEndereço da Entidade (URL): www.cm-sobral.pt\nEndereço Eletrónico: geral@cm-sobral.pt\neDelivery Gateway (URL): https://www.acingov.pt\nFunção da Organização: Adquirente\nNorma jurídica da Entidade Adjudicante: Organismo de direito público\nÁrea de atividade da Autoridade Adjudicante: Serviços públicos das administrações públicas\n\n2 - JORNAL OFICIAL DA UNIÃO EUROPEIA\nO procedimento a que este anúncio diz respeito também é publicitado no Jornal Oficial da União Europeia? Sim\n\n3 - AVISO\nModelo de Anúncio: Concurso público\nData de Envio do Anúncio: 30-09-2025\n\n5 - PROCESSO\nTipo de Procedimento: Concurso público\nPreço base do procedimento: Sim\nValor do preço base do procedimento: 258.130,00 EUR\nProcedimento com lotes? Não\n\n6 - OBJETO DO CONTRATO\nNúmero de referência interna: CPI/1/2025\nDesignação do contrato: Aquisição de Veículo Tanque Tático Florestal\nDescrição: Aquisição de Veículo Tanque Tático Florestal\nOpções: Não\nTipo de Contrato Principal: Aquisição de Bens Móveis\nTipo de Contrato: Aquisição de Bens Móveis\nClassificação CPV (Vocabulário Comum para os Contratos Públicos)\nObjeto principal\nVocabulário Principal: 34133100\nPreço base s/IVA: 258.130,00 EUR\n\n7 - INDICAÇÕES ADICIONAIS\nO contrato envolve aquisição conjunta (satisfação de várias entidades)? Não\nO contrato é adjudicado por uma central de compras? Não\n\n8 - TÉCNICAS\nO concurso destina-se à celebração de um acordo-quadro? Inexistência de acordo-quadro\nÉ utilizado um leilão eletrónico? Não\nÉ adotada uma fase de negociação? Não\nSistema de Aquisição Dinâmico: Inexistência de sistema de aquisição dinâmico\n\n9 - LOCAL DA EXECUÇÃO DO CONTRATO\nLOCAL DA EXECUÇÃO DO CONTRATO (PROCEDIMENTO)\nPaís: Portugal\nNUT III: PT16B\nLocalidade: Freguesia de Sobral de Monte Agraço\nDistrito: Lisboa\nConcelho: Sobral de Monte Agraço\nFreguesia: Freguesia de Sobral de Monte Agraço\n\n10 - PRAZO DE EXECUÇÃO DO CONTRATO\nPrazo de execução do contrato: 180 DIAS\nPrevisão de renovações: Não\n\n11 - FUNDOS EU\nTêm fundos EU? Não\n\n12 - DOCUMENTOS DE HABILITAÇÃO\nHabilitação para o exercício da atividade profissional: Não\n\n13 - CONDIÇÕES DE APRESENTAÇÃO\nPlataforma eletrónica utilizada pela entidade adjudicante: ACIN\nURL para Apresentação: https://www.acingov.pt\nAdmissibilidade da apresentação de propostas variantes: Não autorizado\nPrazo para apresentação das propostas: 30-10-2025 23:59\nPrazo durante o qual os concorrentes são obrigados a manter as respetivas propostas: 66 dias a contar do termo do prazo para a apresentação das propostas\nApresentação de Catálogo Eletrónico: Permitido\nIndicação de Subcontratação na Proposta: Inexistência de indicação de subcontratação\n\n14 - PRESTAÇÃO DE CAUÇÃO\nPrestação de caução: Não\n\n15 - FORNECIMENTO DAS PEÇAS DO CONCURSO, APRESENTAÇÃO DE PEDIDOS DE PARTICIPAÇÃO E APRESENTAÇÃO DAS PROPOSTAS\nLink para acesso às peças do concurso (URL): https://www.acingov.pt/acingovprod/2/zonaPublica/zona_publica_c/donwloadProcedurePiece/OTgyNDI3\n\n20 - OUTROS REQUISITOS\nInformação sobre contratos reservados. Aplica-se a contratos reservados (54º-A)? Não\n\n21 - CRITÉRIO DE ADJUDICAÇÃO\nMultifator: Não\nMonofator:\nNome: Preço\n\n24 - CONDIÇÕES DO CONTRATO\nFaturação Eletrónica: Permitido\nObrigação de Subcontratação:\nCódigo da Obrigação de Subcontratação: Não é aplicável nenhuma obrigação de subcontratação.\n\n25 - COMPRA PÚBLICA ESTRATÉGICA\nCompra Pública Estratégica: Inexistência de contratação pública estratégica\n\n26 - INFORMAÇÕES ADICIONAIS\nContrato adequado para PME: Não\nCobertura ACP (Acordo dos Contratos Públicos da Organização Mundial do Comércio): Não\n\n27 - IDENTIFICAÇÃO E CONTACTOS DO ÓRGÃO DE RECURSOS ADMINISTRATIVOS\nDesignação: Câmara Municipal de Sobral de Monte Agraço\nEndereço: Praça Dr. Eugénio Dias, n.º 4\nCódigo postal: 2590-016\nLocalidade: Sobral de Monte Agraço\nTelefone: 261940300\nFax: \nEndereço eletrónico: geral@cm-sobral.pt\nPrazo de interposição do recurso: 2 dias\n\n28 - IDENTIFICAÇÃO DO(S) AUTOR(ES) DE ANÚNCIO\nNome: Luís Miguel Henriques Soares\nCargo: Presidente da Câmara Municipal\n419593531",
    "nipc": "505410850",
    "distrito": "Lisboa",
    "concelho": "Sobral de Monte Agraço",
    "freguesia": "Freguesia de Sobral de Monte Agraço",
    "site": "www.cm-sobral.pt",
    "email": "geral@cm-sobral.pt",
    "designacao_contrato": "Aquisição de Veículo Tanque Tático Florestal",
    "descricao": "Aquisição de Veículo Tanque Tático Florestal",
    "preco_base": "258.130,00 EUR",
    "prazo_execucao": "180 DIAS",
    "prazo_apresentacao_propostas": "30-10-2025 23:59",
    "fundos_eu": "Não",
    "plataforma_eletronica": "ACIN",
    "url_procedimento": "https://www.acingov.pt",
    "autor_nome": "Luís Miguel Henriques Soares",
    "autor_cargo": "Presidente da Câmara Municipal"
  },
  {
    "numero_procedimento": "N/A",
    "entidade": "AR - Águas do Ribatejo, EIM, SA",
    "link": "https://diariodarepublica.pt/dr/detalhe/contrato-publico/25989-937877786",
    "detalhes_completos": "1 - IDENTIFICAÇÃO E CONTACTOS DA ENTIDADE ADJUDICANTE\nDesignação da entidade adjudicante: AR - Águas do Ribatejo, EIM, SA\nNIPC: 508345464\nEndereço: Rua Gaspar Costa Ramalho, nº38\nCódigo postal: 2120-098\nLocalidade: Santarém\nPaís: Portugal\nNUT III: PT185\nDistrito: Santarém\nConcelho: Salvaterra de Magos\nFreguesia: União das Freguesias de Salvaterra de Magos e Foros de Salvaterra\nTelefone: 243303240\nEndereço da Entidade (URL): www.aguasdoribatejo.com\nEndereço Eletrónico: geral@aguasdoribatejo.com\neDelivery Gateway (URL): https://community.vortal.biz/public/\nFunção da Organização: Adquirente\nNorma jurídica da Entidade Adjudicante: Empresa pública, controlada por uma autoridade local\nÁrea de atividade da Autoridade Adjudicante: Proteção ambiental\n\n2 - JORNAL OFICIAL DA UNIÃO EUROPEIA\nO procedimento a que este anúncio diz respeito também é publicitado no Jornal Oficial da União Europeia? Sim\n\n3 - AVISO\nModelo de Anúncio: Concurso público\nData de Envio do Anúncio: 30-09-2025\n\n5 - PROCESSO\nTipo de Procedimento: Concurso público\nPreço base do procedimento: Sim\nValor do preço base do procedimento: 90.000,00 EUR\nProcedimento com lotes? Não\n\n6 - OBJETO DO CONTRATO\nNúmero de referência interna: FPS/044/2025\nDesignação do contrato: Fiscalização da empreitada de execução da ampliação do sistema de abastecimento de Fazendas de Almeirim – Condutas de distribuição até à Z.I. de Almeirim\nDescrição: Prestação de serviços para a fiscalização da empreitada de execução da ampliação do sistema de abastecimento de Fazendas de Almeirim – Condutas de distribuição até à Z.I. de Almeirim\nOpções: Não\nTipo de Contrato Principal: Aquisição de Serviços\nTipo de Contrato: Aquisição de Serviços\nClassificação CPV (Vocabulário Comum para os Contratos Públicos)\nObjeto principal\nVocabulário Principal: 71247000\nPreço base s/IVA: 90.000,00 EUR\n\n7 - INDICAÇÕES ADICIONAIS\nO contrato envolve aquisição conjunta (satisfação de várias entidades)? Não\nO contrato é adjudicado por uma central de compras? Não\n\n8 - TÉCNICAS\nO concurso destina-se à celebração de um acordo-quadro? Inexistência de acordo-quadro\nÉ utilizado um leilão eletrónico? Não\nÉ adotada uma fase de negociação? Não\nSistema de Aquisição Dinâmico: Inexistência de sistema de aquisição dinâmico\n\n9 - LOCAL DA EXECUÇÃO DO CONTRATO\nLOCAL DA EXECUÇÃO DO CONTRATO (PROCEDIMENTO)\nPaís: Portugal\nNUT III: PT185\nLocalidade: Almeirim\nDistrito: Santarém\nConcelho: Almeirim\nFreguesia: Freguesia de Almeirim\n\n10 - PRAZO DE EXECUÇÃO DO CONTRATO\nPrazo de execução do contrato: 20 MESES\nPrevisão de renovações: Não\n\n11 - FUNDOS EU\nTêm fundos EU? Sim\n\n12 - DOCUMENTOS DE HABILITAÇÃO\nHabilitação para o exercício da atividade profissional: Sim\nTipo: Outros\nDescrição - Outros: Conforme programa de concurso.\nDescrição: Conforme programa do concurso.\n\n13 - CONDIÇÕES DE APRESENTAÇÃO\nPlataforma eletrónica utilizada pela entidade adjudicante: VORTAL\nURL para Apresentação: https://community.vortal.biz/public/\nAdmissibilidade da apresentação de propostas variantes: Não autorizado\nPrazo para apresentação das propostas: 30-10-2025 23:59\nPrazo durante o qual os concorrentes são obrigados a manter as respetivas propostas: 180 dias a contar do termo do prazo para a apresentação das propostas\nApresentação de Catálogo Eletrónico: Permitido\nIndicação de Subcontratação na Proposta: Inexistência de indicação de subcontratação\n\n14 - PRESTAÇÃO DE CAUÇÃO\nPrestação de caução: Sim\nPercentagem: 5%\nDescrição da Garantia Exigida: Conforme programa do concurso.\n\n15 - FORNECIMENTO DAS PEÇAS DO CONCURSO, APRESENTAÇÃO DE PEDIDOS DE PARTICIPAÇÃO E APRESENTAÇÃO DAS PROPOSTAS\nLink para acesso às peças do concurso (URL): https://community.vortal.biz/Public/public-tender-documents/VkVkNjBHZTBycUZJVkFqWC9LYjFZUjY1NllzS1dONnUrcHdnbTZoYzZzZHpPMEJoWjFCbGRPU1NRd2hiWWM4VFBrL2ErS2s4Mjl1RWwyREpJZjM3MkE9PUtuZWJ1\n\n20 - OUTROS REQUISITOS\nInformação sobre contratos reservados. Aplica-se a contratos reservados (54º-A)? Não\n\n21 - CRITÉRIO DE ADJUDICAÇÃO\nMultifator: Não\nMonofator:\nNome: Preço\n\n24 - CONDIÇÕES DO CONTRATO\nFaturação Eletrónica: Permitido\nObrigação de Subcontratação:\nCódigo da Obrigação de Subcontratação: Não é aplicável nenhuma obrigação de subcontratação.\n\n25 - COMPRA PÚBLICA ESTRATÉGICA\nCompra Pública Estratégica: Inexistência de contratação pública estratégica\n\n26 - INFORMAÇÕES ADICIONAIS\nContrato adequado para PME: Sim\nCobertura ACP (Acordo dos Contratos Públicos da Organização Mundial do Comércio): Não\n\n27 - IDENTIFICAÇÃO E CONTACTOS DO ÓRGÃO DE RECURSOS ADMINISTRATIVOS\nDesignação: Conselho de Administração da AR - Águas do Ribatejo, EIM, SA\nEndereço: Rua Gaspar Costa Ramalho, 38\nCódigo postal: 2120-098\nLocalidade: Salvaterra de Magos\nTelefone: +351 263509400\nFax: +351 263509499\nEndereço eletrónico: geral@aguasdoribatejo.com\n\n28 - IDENTIFICAÇÃO DO(S) AUTOR(ES) DE ANÚNCIO\nNome: Francisco Silvestre de Oliveira\nCargo: Presidente do Conselho de Administração\n419595005",
    "nipc": "508345464",
    "distrito": "Santarém",
    "concelho": "Salvaterra de Magos",
    "freguesia": "União das Freguesias de Salvaterra de Magos e Foros de Salvaterra",
    "site": "www.aguasdoribatejo.com",
    "email": "geral@aguasdoribatejo.com",
    "designacao_contrato": "Fiscalização da empreitada de execução da ampliação do sistema de abastecimento de Fazendas de Almeirim – Condutas de distribuição até à Z.I. de Almeirim",
    "descricao": "Prestação de serviços para a fiscalização da empreitada de execução da ampliação do sistema de abastecimento de Fazendas de Almeirim – Condutas de distribuição até à Z.I. de Almeirim",
    "preco_base": "90.000,00 EUR",
    "prazo_execucao": "20 MESES",
    "prazo_apresentacao_propostas": "30-10-2025 23:59",
    "fundos_eu": "Sim",
    "plataforma_eletronica": "VORTAL",
    "url_procedimento": "https://community.vortal.biz/public/",
    "autor_nome": "Francisco Silvestre de Oliveira",
    "autor_cargo": "Presidente do Conselho de Administração"
  },
  {
    "numero_procedimento": "N/A",
    "entidade": "AnÃºncio de procedimento  n.Âº 25991/2025  -  DiÃ¡rio da RepÃºblica n.Âº 191/2025, SÃ©rie II de 2025-10-03",
    "link": "https://diariodarepublica.pt/dr/detalhe/contrato-publico/25991-937877787"
  },
  {
    "numero_procedimento": "N/A",
    "entidade": "Escola Prof.Agricultura Desenv.o Rural de Vagos",
    "link": "https://diariodarepublica.pt/dr/detalhe/contrato-publico/25993-937877788",
    "detalhes_completos": "1 - IDENTIFICAÇÃO E CONTACTOS DA ENTIDADE ADJUDICANTE\nDesignação da entidade adjudicante: Escola Prof.Agricultura Desenv.o Rural de Vagos\nNIPC: 600067998\nEndereço: Estrada Florestal\nCódigo postal: 3840-254\nLocalidade: Aveiro\nPaís: Portugal\nNUT III: PT16D\nDistrito: Aveiro\nConcelho: Vagos\nFreguesia: Freguesia de Gafanha da Boa Hora\nTelefone: 234799830\nFax: 234799830\nEndereço da Entidade (URL): www.epadrv.pt\nEndereço Eletrónico: ep.adruralvagos@escolas.min-edu.pt\neDelivery Gateway (URL): https://community.vortal.biz/public/\nFunção da Organização: Adquirente\nNorma jurídica da Entidade Adjudicante: Organismo de direito público\nÁrea de atividade da Autoridade Adjudicante: Educação\n\n2 - JORNAL OFICIAL DA UNIÃO EUROPEIA\nO procedimento a que este anúncio diz respeito também é publicitado no Jornal Oficial da União Europeia? Sim\n\n3 - AVISO\nModelo de Anúncio: Concurso público\nData de Envio do Anúncio: 30-09-2025\n\n5 - PROCESSO\nTipo de Procedimento: Concurso público\nPreço base do procedimento: Sim\nValor do preço base do procedimento: 1.478.874,71 EUR\nProcedimento com lotes? Sim\nNº Máx. de Lotes Autorizado: 4\nNúmero máximo de lotes que podem ser adjudicados a um concorrente: 4\n\n6 - OBJETO DO CONTRATO\nNúmero de referência interna: EPADRV-PB01/2025(CTEi)\nDesignação do contrato: Equipamentos no âmbito do projeto CTE Industrial\nDescrição: Equipamentos no âmbito do projeto CTE Industrial\nOpções: Não\nTipo de Contrato Principal: Aquisição de Bens Móveis\nTipo de Contrato: Aquisição de Bens Móveis\nClassificação CPV (Vocabulário Comum para os Contratos Públicos)\nObjeto principal\nVocabulário Principal: 16600000\nPreço base s/IVA: 1.478.874,71 EUR\nLotes: \nNº: LOT-0001\nDescrição do Lote: LOTE 1\nPreço base s/IVA: 281.601,93 EUR\nClassificação CPV (Vocabulário Comum para os Contratos Públicos)\nObjeto principal\nVocabulário Principal: 16600000\nNº: LOT-0002\nDescrição do Lote: LOTE 2\nPreço base s/IVA: 493.196,59 EUR\nClassificação CPV (Vocabulário Comum para os Contratos Públicos)\nObjeto principal\nVocabulário Principal: 16600000\nNº: LOT-0003\nDescrição do Lote: LOTE 3\nPreço base s/IVA: 439.750,95 EUR\nClassificação CPV (Vocabulário Comum para os Contratos Públicos)\nObjeto principal\nVocabulário Principal: 16600000\nNº: LOT-0004\nDescrição do Lote: LOTE 4\nPreço base s/IVA: 264.325,24 EUR\nClassificação CPV (Vocabulário Comum para os Contratos Públicos)\nObjeto principal\nVocabulário Principal: 16600000\n\n7 - INDICAÇÕES ADICIONAIS\nO contrato envolve aquisição conjunta (satisfação de várias entidades)? Não\nO contrato é adjudicado por uma central de compras? Não\n\n8 - TÉCNICAS\nO concurso destina-se à celebração de um acordo-quadro? Inexistência de acordo-quadro\nÉ utilizado um leilão eletrónico? Não\nÉ adotada uma fase de negociação? Não\nSistema de Aquisição Dinâmico: Inexistência de sistema de aquisição dinâmico\n\n9 - LOCAL DA EXECUÇÃO DO CONTRATO\nLOCAL DA EXECUÇÃO DO CONTRATO (PROCEDIMENTO)\nPaís: Portugal\nNUT III: PT16D\nLocalidade: Aveiro\nDistrito: Aveiro\nConcelho: Vagos\nFreguesia: Todas\nLOCAL DA EXECUÇÃO DO CONTRATO (LOTE)\nIdentificador do Lote: LOT-0001; LOT-0002; LOT-0003; LOT-0004\nPaís: Portugal\nNUT III: PT16D\nLocalidade: Aveiro\nDistrito: Aveiro\nConcelho: Vagos\nFreguesia: Todas\n\n10 - PRAZO DE EXECUÇÃO DO CONTRATO\nIdentificador do Lote: LOT-0001; LOT-0002; LOT-0003; LOT-0004\nPrazo de execução do contrato: 120 DIAS\nPrevisão de renovações: Não\n\n11 - FUNDOS EU\nIdentificador do Lote: LOT-0001; LOT-0002; LOT-0003; LOT-0004\nTêm fundos EU? Sim\n\n12 - DOCUMENTOS DE HABILITAÇÃO\nHabilitação para o exercício da atividade profissional: Não\n\n13 - CONDIÇÕES DE APRESENTAÇÃO\nPlataforma eletrónica utilizada pela entidade adjudicante: VORTAL\nURL para Apresentação: https://community.vortal.biz/public/\nAdmissibilidade da apresentação de propostas variantes: Não autorizado\nPrazo para apresentação das propostas: 30-10-2025 18:00\nPrazo durante o qual os concorrentes são obrigados a manter as respetivas propostas: 66 dias a contar do termo do prazo para a apresentação das propostas\nApresentação de Catálogo Eletrónico: Não autorizado\nIndicação de Subcontratação na Proposta: Inexistência de indicação de subcontratação\n\n14 - PRESTAÇÃO DE CAUÇÃO\nPrestação de caução: Sim\nPercentagem: 5%\nDescrição da Garantia Exigida: Garantia Bancária\n\n15 - FORNECIMENTO DAS PEÇAS DO CONCURSO, APRESENTAÇÃO DE PEDIDOS DE PARTICIPAÇÃO E APRESENTAÇÃO DAS PROPOSTAS\nLink para acesso às peças do concurso (URL): https://community.vortal.biz/Public/public-tender-documents/SFUvSGNMeUZhdTFzdGkrNmFxWVRaMkxaM2hLQUFBUGY3cHU1SGk4c1M1bzlKSjZCZTFOZWVBN0VFQm9XUTlxb2tRKzV0VmhaSUVFdmNmUEt1U1NySkE9PWwmcThY\n\n20 - OUTROS REQUISITOS\nIdentificador do Lote: LOT-0001; LOT-0002; LOT-0003; LOT-0004\nInformação sobre contratos reservados. Aplica-se a contratos reservados (54º-A)? Não\n\n21 - CRITÉRIO DE ADJUDICAÇÃO\nO Critério de adjudicação é diferenciado por lote? Não\nMultifator: Sim\nFator: \nNome: Preço\nPonderação: 50%\nSubfatores: Não\nFator: \nNome: Qualidade\nPonderação: 50%\nSubfatores: Não\n\n24 - CONDIÇÕES DO CONTRATO\nIdentificador do Lote: LOT-0001; LOT-0002; LOT-0003; LOT-0004\nFaturação Eletrónica: Permitido\nObrigação de Subcontratação:\nCódigo da Obrigação de Subcontratação: Não é aplicável nenhuma obrigação de subcontratação.\n\n25 - COMPRA PÚBLICA ESTRATÉGICA\nCompra Pública Estratégica: Redução dos impactos ambientais\nDescrição do Processo de Adjudicação Estratégico: Conforme as peças do procedimento\nCritérios de contratos Públicos Ecológicos: Critérios de contratação pública ecológica nacional\nCategorias da estratégia nacional: Outros\nOutra categoria (Descrição): n.a.\nDiretiva Veículos Não Poluentes: Não\nCritério de Acessibilidade: Os critérios de acessibilidade para as pessoas com deficiência não estão incluídos porque o contrato não se destina a pessoas singulares\n\n26 - INFORMAÇÕES ADICIONAIS\nIdentificador do Lote: LOT-0001; LOT-0002; LOT-0003; LOT-0004\nContrato adequado para PME: Sim\nCobertura ACP (Acordo dos Contratos Públicos da Organização Mundial do Comércio): Não\n\n27 - IDENTIFICAÇÃO E CONTACTOS DO ÓRGÃO DE RECURSOS ADMINISTRATIVOS\nDesignação: Conselho Administrativo\nEndereço: Estrada Florestal\nCódigo postal: 3840-254\nLocalidade: Vagos\nTelefone: +351 234799830\nFax: +351 234799830\nEndereço eletrónico: contratacaopublica@epadrv.edu.pt\n\n28 - IDENTIFICAÇÃO DO(S) AUTOR(ES) DE ANÚNCIO\nNome: Paulo Jorge Ramalho Alves\nCargo: Diretor\n419596359",
    "nipc": "600067998",
    "distrito": "Aveiro",
    "concelho": "Vagos",
    "freguesia": "Freguesia de Gafanha da Boa Hora",
    "site": "www.epadrv.pt",
    "email": "ep.adruralvagos@escolas.min-edu.pt",
    "designacao_contrato": "Equipamentos no âmbito do projeto CTE Industrial",
    "descricao": "Equipamentos no âmbito do projeto CTE Industrial",
    "preco_base": "1.478.874,71 EUR",
    "prazo_execucao": "120 DIAS",
    "prazo_apresentacao_propostas": "30-10-2025 18:00",
    "fundos_eu": "Sim",
    "plataforma_eletronica": "VORTAL",
    "url_procedimento": "https://community.vortal.biz/public/",
    "autor_nome": "Paulo Jorge Ramalho Alves",
    "autor_cargo": "Diretor"
  },
  {
    "numero_procedimento": "N/A",
    "entidade": "Ordem dos Contabilistas Certificados",
    "link": "https://diariodarepublica.pt/dr/detalhe/contrato-publico/25994-937877789",
    "detalhes_completos": "Alteração do Anúncio de procedimento n.º 25468/2025, de 2025-09-26, com o ID 419569645\n\n1 - IDENTIFICAÇÃO E CONTACTOS DA ENTIDADE ADJUDICANTE\nDesignação da entidade adjudicante: Ordem dos Contabilistas Certificados\nNIPC: 503692310\nServiço/Órgão/Pessoa de contacto: Bastonária\nEndereço: Av. Barbosa du Bocage, 45 \nCódigo postal: 1049-013\nLocalidade: Lisboa\nPaís: Portugal\nNUT III: PT187\nDistrito: Lisboa\nConcelho: Lisboa\nFreguesia: Freguesia de Avenidas Novas\nTelefone: 217999800\nFax: 217957332\nEndereço da Entidade (URL): www.occ.pt\nEndereço Eletrónico: compras@occ.pt\nFunção da Organização: Adquirente\nNorma jurídica da Entidade Adjudicante: Autoridade da administração central\nÁrea de atividade da Entidade Adjudicante: Atividades aeroportuárias\nÁrea de atividade da Autoridade Adjudicante: Assuntos económicos\n\n2 - JORNAL OFICIAL DA UNIÃO EUROPEIA\nO procedimento a que este anúncio diz respeito também é publicitado no Jornal Oficial da União Europeia? Sim\n\n3 - AVISO\nModelo de Anúncio: Concurso público\nData de Envio do Anúncio: 30-09-2025\n\n5 - PROCESSO\nTipo de Procedimento: Concurso público\nPreço base do procedimento: Sim\nValor do preço base do procedimento: 680.000,00 EUR\nProcedimento com lotes? Sim\nNº Máx. de Lotes Autorizado: 3\nNúmero máximo de lotes que podem ser adjudicados a um concorrente: 3\n\n6 - OBJETO DO CONTRATO\nNúmero de referência interna: 0107-2025\nDesignação do contrato: Concurso Público com Publicidade Internacional tendente à celebração de contrato para a aquisição de serviços de gestão de Pagamentos Eletrónicos em tempo real por Intermédio de Gateway de Pagamentos\nDescrição: Aquisição de Serviços de Gestão de Pagamentos Eletrónicos em tempo real por Intermédio de Gateway de Pagamentos\nOpções: Não\nTipo de Contrato Principal: Aquisição de Serviços\nTipo de Contrato: Aquisição de Serviços\nClassificação CPV (Vocabulário Comum para os Contratos Públicos)\nObjeto principal\nVocabulário Principal: 66110000\nPreço base s/IVA: 680.000,00 EUR\nLotes: \nNº: LOT-0001\nDescrição do Lote: Lote1\nPreço base s/IVA: 476.000,00 EUR\nClassificação CPV (Vocabulário Comum para os Contratos Públicos)\nObjeto principal\nVocabulário Principal: 66110000\nNº: LOT-0002\nDescrição do Lote: Lote 2\nPreço base s/IVA: 34.000,00 EUR\nClassificação CPV (Vocabulário Comum para os Contratos Públicos)\nObjeto principal\nVocabulário Principal: 66110000\nNº: LOT-0003\nDescrição do Lote: Lote 3\nPreço base s/IVA: 170.000,00 EUR\nClassificação CPV (Vocabulário Comum para os Contratos Públicos)\nObjeto principal\nVocabulário Principal: 66110000\n\n7 - INDICAÇÕES ADICIONAIS\nO contrato envolve aquisição conjunta (satisfação de várias entidades)? Não\nO contrato é adjudicado por uma central de compras? Não\n\n8 - TÉCNICAS\nO concurso destina-se à celebração de um acordo-quadro? Inexistência de acordo-quadro\nÉ utilizado um leilão eletrónico? Não\nÉ adotada uma fase de negociação? Não\nSistema de Aquisição Dinâmico: Inexistência de sistema de aquisição dinâmico\n\n9 - LOCAL DA EXECUÇÃO DO CONTRATO\nLOCAL DA EXECUÇÃO DO CONTRATO (PROCEDIMENTO)\nLOCAL DA EXECUÇÃO DO CONTRATO (LOTE)\nIdentificador do Lote: LOT-0001\nPaís: Portugal\nNUT III: PT170\nLocalidade: Campo Pequeno\nDistrito: Lisboa\nConcelho: Lisboa\nFreguesia: Freguesia de Avenidas Novas\nIdentificador do Lote: LOT-0002\nPaís: Portugal\nNUT III: PT170\nLocalidade: Campo Pequeno\nDistrito: Lisboa\nConcelho: Lisboa\nFreguesia: Freguesia de Avenidas Novas\nIdentificador do Lote: LOT-0003\nPaís: Portugal\nNUT III: PT170\nLocalidade: Campo Pequeno\nDistrito: Lisboa\nConcelho: Lisboa\nFreguesia: Freguesia de Avenidas Novas\n\n10 - PRAZO DE EXECUÇÃO DO CONTRATO\nIdentificador do Lote: LOT-0001\nPrazo de execução do contrato: 12 MESES\nPrevisão de renovações: Sim\nIndicar número máximo de renovações: 2\nPrazo de renovações diferente do prazo inicial: Não\nIdentificador do Lote: LOT-0002\nPrazo de execução do contrato: 12 MESES\nPrevisão de renovações: Sim\nIndicar número máximo de renovações: 2\nPrazo de renovações diferente do prazo inicial: Não\nIdentificador do Lote: LOT-0003\nPrazo de execução do contrato: 12 MESES\nPrevisão de renovações: Sim\nIndicar número máximo de renovações: 2\nPrazo de renovações diferente do prazo inicial: Não\n\n11 - FUNDOS EU\nIdentificador do Lote: LOT-0001; LOT-0002; LOT-0003\nTêm fundos EU? Não\n\n12 - DOCUMENTOS DE HABILITAÇÃO\nHabilitação para o exercício da atividade profissional: Não\n\n13 - CONDIÇÕES DE APRESENTAÇÃO\nPlataforma eletrónica utilizada pela entidade adjudicante: ANOGOV\nURL para Apresentação: https://www.anogov.com/ap-otoc/faces/\nAdmissibilidade da apresentação de propostas variantes: Não autorizado\nPrazo para apresentação das propostas: 27-10-2025 23:59\nPrazo durante o qual os concorrentes são obrigados a manter as respetivas propostas: 90 dias a contar do termo do prazo para a apresentação das propostas\nApresentação de Catálogo Eletrónico: Não autorizado\nIndicação de Subcontratação na Proposta: Inexistência de indicação de subcontratação\n\n14 - PRESTAÇÃO DE CAUÇÃO\nPrestação de caução: Sim\nPercentagem: 5%\nDescrição da Garantia Exigida: Nos termos do artigo 27.º do Programa \n\n15 - FORNECIMENTO DAS PEÇAS DO CONCURSO, APRESENTAÇÃO DE PEDIDOS DE PARTICIPAÇÃO E APRESENTAÇÃO DAS PROPOSTAS\nLink para acesso às peças do concurso (URL): https://www.anogov.com/ap-otoc/faces/app/acessoDocs.jsp?codigoAcesso=qptFsM2mshVNTU9lik1ISAeefiYtOCH6WLuGBPGds6XVIljRH3\n\n20 - OUTROS REQUISITOS\nIdentificador do Lote: LOT-0001; LOT-0002; LOT-0003\nInformação sobre contratos reservados. Aplica-se a contratos reservados (54º-A)? Não\n\n21 - CRITÉRIO DE ADJUDICAÇÃO\nO Critério de adjudicação é diferenciado por lote? Não\nMultifator: Não\nMonofator:\nNome: Preço\n\n24 - CONDIÇÕES DO CONTRATO\nIdentificador do Lote: LOT-0001; LOT-0002; LOT-0003\nFaturação Eletrónica: Permitido\nObrigação de Subcontratação:\nCódigo da Obrigação de Subcontratação: Não é aplicável nenhuma obrigação de subcontratação.\n\n25 - COMPRA PÚBLICA ESTRATÉGICA\nCompra Pública Estratégica: Inexistência de contratação pública estratégica\n\n26 - INFORMAÇÕES ADICIONAIS\nIdentificador do Lote: LOT-0001\nContrato adequado para PME: Não\nCobertura ACP (Acordo dos Contratos Públicos da Organização Mundial do Comércio): Não\nIdentificador do Lote: LOT-0002\nContrato adequado para PME: Não\nCobertura ACP (Acordo dos Contratos Públicos da Organização Mundial do Comércio): Não\nIdentificador do Lote: LOT-0003\nContrato adequado para PME: Não\nCobertura ACP (Acordo dos Contratos Públicos da Organização Mundial do Comércio): Não\n\n27 - IDENTIFICAÇÃO E CONTACTOS DO ÓRGÃO DE RECURSOS ADMINISTRATIVOS\nDesignação: Conselho Diretivo da Ordem dos Contabilistas Certificados\nEndereço: Avenida Barbosa du Bocage,45\nCódigo postal: 1049-013\nLocalidade: Lisboa\nEndereço eletrónico: compras@occ.pt\n\n28 - IDENTIFICAÇÃO DO(S) AUTOR(ES) DE ANÚNCIO\nNome: Paula Maria Pires de Oliveira e Silva Laia Franco\nCargo: Bastonária\n\n29 - ALTERAÇÃO\nMotivo da Alteração: Informações atualizadas\nIdentificador da Versão do Anúncio a Alterar: 1e28277e-068d-4648-ae22-ebd7cbe30e34-01\nIdentificador das Secções Alteradas do Anúncio Anterior: Prazo de execução do contrato\nDescrição das Alterações: Correção do prazo de execução do contrato para 12 meses\nAlteração dos Documentos do Concurso: Não\n419591669",
    "nipc": "503692310",
    "distrito": "Lisboa",
    "concelho": "Lisboa",
    "freguesia": "Freguesia de Avenidas Novas",
    "site": "www.occ.pt",
    "email": "compras@occ.pt",
    "designacao_contrato": "Concurso Público com Publicidade Internacional tendente à celebração de contrato para a aquisição de serviços de gestão de Pagamentos Eletrónicos em tempo real por Intermédio de Gateway de Pagamentos",
    "descricao": "Aquisição de Serviços de Gestão de Pagamentos Eletrónicos em tempo real por Intermédio de Gateway de Pagamentos",
    "preco_base": "680.000,00 EUR",
    "prazo_execucao": "12 MESES",
    "prazo_apresentacao_propostas": "27-10-2025 23:59",
    "fundos_eu": "Não",
    "plataforma_eletronica": "ANOGOV",
    "url_procedimento": "https://www.anogov.com/ap-otoc/faces/",
    "autor_nome": "Paula Maria Pires de Oliveira e Silva Laia Franco",
    "autor_cargo": "Bastonária"
  },
  {
    "numero_procedimento": "N/A",
    "entidade": "FEIRA VIVA - CULTURA E DESPORTO, E.M.",
    "link": "https://diariodarepublica.pt/dr/detalhe/contrato-publico/25996-937877790",
    "detalhes_completos": "1 - IDENTIFICAÇÃO E CONTACTOS DA ENTIDADE ADJUDICANTE\nDesignação da entidade adjudicante: FEIRA VIVA - CULTURA E DESPORTO, E.M.\nNIPC: 505120151\nEndereço: Rua Interior do Europarque\nCódigo postal: 4520-153\nLocalidade: Aveiro\nPaís: Portugal\nNUT III: PT11A\nDistrito: Aveiro\nConcelho: Santa Maria da Feira\nFreguesia: União das Freguesias de Santa Maria da Feira, Travanca, Sanfins e Espargo\nTelefone: 256330900\nFax: 256330909\nEndereço Eletrónico: procedimentos@feiraviva.com\neDelivery Gateway (URL): https://community.vortal.biz/public/\nFunção da Organização: Adquirente\nNorma jurídica da Entidade Adjudicante: Autoridade da administração central\nÁrea de atividade da Autoridade Adjudicante: Serviços públicos das administrações públicas\n\n2 - JORNAL OFICIAL DA UNIÃO EUROPEIA\nO procedimento a que este anúncio diz respeito também é publicitado no Jornal Oficial da União Europeia? Não\n\n3 - AVISO\nModelo de Anúncio: Concurso público\nData de Envio do Anúncio: 02-10-2025\n\n5 - PROCESSO\nTipo de Procedimento: Concurso público\nPreço base do procedimento: Sim\nValor do preço base do procedimento: 19.600,00 EUR\nProcedimento com lotes? Não\n\n6 - OBJETO DO CONTRATO\nNúmero de referência interna: 308_2025_CP_BS\nDesignação do contrato: 308_2025_CP_BS - Aluguer de Rampa de Boias para o Evento Perlim\nDescrição: 308_2025_CP_BS - Aluguer de Rampa de Boias para o Evento Perlim\nTipo de Contrato Principal: Aquisição de Serviços\nTipo de Contrato: Aquisição de Serviços\nClassificação CPV (Vocabulário Comum para os Contratos Públicos)\nObjeto principal\nVocabulário Principal: 92330000\nPreço base s/IVA: 19.600,00 EUR\n\n7 - INDICAÇÕES ADICIONAIS\nO contrato envolve aquisição conjunta (satisfação de várias entidades)? Não\nO contrato é adjudicado por uma central de compras? Não\n\n8 - TÉCNICAS\nO concurso destina-se à celebração de um acordo-quadro? Inexistência de acordo-quadro\nÉ utilizado um leilão eletrónico? Não\nÉ adotada uma fase de negociação? Não\nSistema de Aquisição Dinâmico: Inexistência de sistema de aquisição dinâmico\n\n9 - LOCAL DA EXECUÇÃO DO CONTRATO\nLOCAL DA EXECUÇÃO DO CONTRATO (PROCEDIMENTO)\nPaís: Portugal\nNUT III: PT11A\nLocalidade: Aveiro\nDistrito: Aveiro\nConcelho: Santa Maria da Feira\nFreguesia: Todas\n\n10 - PRAZO DE EXECUÇÃO DO CONTRATO\nPrazo de execução do contrato: 75 DIAS\nPrevisão de renovações: Não\n\n11 - FUNDOS EU\nTêm fundos EU? Não\n\n12 - DOCUMENTOS DE HABILITAÇÃO\nHabilitação para o exercício da atividade profissional: Não\n\n13 - CONDIÇÕES DE APRESENTAÇÃO\nPlataforma eletrónica utilizada pela entidade adjudicante: VORTAL\nURL para Apresentação: https://community.vortal.biz/public/\nAdmissibilidade da apresentação de propostas variantes: Não autorizado\nPrazo para apresentação das propostas: 08-10-2025 23:59\nPrazo durante o qual os concorrentes são obrigados a manter as respetivas propostas: 120 dias a contar do termo do prazo para a apresentação das propostas\nIndicação de Subcontratação na Proposta: Inexistência de indicação de subcontratação\n\n14 - PRESTAÇÃO DE CAUÇÃO\nPrestação de caução: Não\n\n15 - FORNECIMENTO DAS PEÇAS DO CONCURSO, APRESENTAÇÃO DE PEDIDOS DE PARTICIPAÇÃO E APRESENTAÇÃO DAS PROPOSTAS\nLink para acesso às peças do concurso (URL): https://community.vortal.biz/Public/public-tender-documents/WEVWVlRsTHcwZHduMmQ4S3J2b2dUbnhVdmZFb3l5dWQ4YzFrN3QxVmdYNzVHL21SNm5pSG0yMExrOHhWMHdTLzkwSkFBVmlEejBaT1NSZlg5OVRwdkE9PUNpWHow\n\n20 - OUTROS REQUISITOS\nInformação sobre contratos reservados. Aplica-se a contratos reservados (54º-A)? Não\n\n21 - CRITÉRIO DE ADJUDICAÇÃO\nMultifator: Não\nMonofator:\nNome: Preço\n\n24 - CONDIÇÕES DO CONTRATO\nFaturação Eletrónica: Permitido\nObrigação de Subcontratação:\nCódigo da Obrigação de Subcontratação: Não é aplicável nenhuma obrigação de subcontratação.\n\n25 - COMPRA PÚBLICA ESTRATÉGICA\nCompra Pública Estratégica: Inexistência de contratação pública estratégica\n\n26 - INFORMAÇÕES ADICIONAIS\nContrato adequado para PME: Sim\nCobertura ACP (Acordo dos Contratos Públicos da Organização Mundial do Comércio): Não\n\n27 - IDENTIFICAÇÃO E CONTACTOS DO ÓRGÃO DE RECURSOS ADMINISTRATIVOS\nDesignação: Conselho de Administração Feira Viva Cultura e Desporto, E.M\nEndereço: Rua Interior do Europarque, Apartado 160\nCódigo postal: 4520-153\nLocalidade: Santa Maria da Feira\nTelefone: +351 256330900\nFax: +351 256330900\nEndereço eletrónico: procedimentos@feiraviva.com\n\n28 - IDENTIFICAÇÃO DO(S) AUTOR(ES) DE ANÚNCIO\nNome: Paulo Sérgio Pais\nCargo: Diretor Geral\n419608013",
    "nipc": "505120151",
    "distrito": "Aveiro",
    "concelho": "Santa Maria da Feira",
    "freguesia": "União das Freguesias de Santa Maria da Feira, Travanca, Sanfins e Espargo",
    "site": null,
    "email": "procedimentos@feiraviva.com",
    "designacao_contrato": "308_2025_CP_BS - Aluguer de Rampa de Boias para o Evento Perlim",
    "descricao": "308_2025_CP_BS - Aluguer de Rampa de Boias para o Evento Perlim",
    "preco_base": "19.600,00 EUR",
    "prazo_execucao": "75 DIAS",
    "prazo_apresentacao_propostas": "08-10-2025 23:59",
    "fundos_eu": "Não",
    "plataforma_eletronica": "VORTAL",
    "url_procedimento": "https://community.vortal.biz/public/",
    "autor_nome": "Paulo Sérgio Pais",
    "autor_cargo": "Diretor Geral"
  },
  {
    "numero_procedimento": "N/A",
    "entidade": "AnÃºncio de procedimento  n.Âº 25997/2025  -  DiÃ¡rio da RepÃºblica n.Âº 191/2025, SÃ©rie II de 2025-10-03",
    "link": "https://diariodarepublica.pt/dr/detalhe/contrato-publico/25997-937877791"
  },
  {
    "numero_procedimento": "N/A",
    "entidade": "AnÃºncio de procedimento  n.Âº 26001/2025  -  DiÃ¡rio da RepÃºblica n.Âº 191/2025, SÃ©rie II de 2025-10-03",
    "link": "https://diariodarepublica.pt/dr/detalhe/contrato-publico/26001-937877792"
  },
  {
    "numero_procedimento": "N/A",
    "entidade": "Municipio de Carregal do Sal",
    "link": "https://diariodarepublica.pt/dr/detalhe/contrato-publico/26005-937877793",
    "detalhes_completos": "Alteração do Anúncio de procedimento n.º 24928/2025, de 2025-09-22, com o ID 419548074\n\n1 - IDENTIFICAÇÃO E CONTACTOS DA ENTIDADE ADJUDICANTE\nDesignação da entidade adjudicante: Municipio de Carregal do Sal\nNIPC: 506684920\nServiço/Órgão/Pessoa de contacto: Presidente da Câmara\nEndereço: Praça do Município\nCódigo postal: 3430-167\nLocalidade: Carregal do sal\nPaís: Portugal\nNUT III: PT16G\nDistrito: Viseu\nConcelho: Carregal do Sal\nFreguesia: Freguesia de Oliveira do Conde\nTelefone: 232960400\nFax: 23296409\nEndereço da Entidade (URL): https://www.cm-carregal.pt/\nEndereço Eletrónico: geral@cm-carregal.pt\neDelivery Gateway (URL): https://www.acingov.pt\nFunção da Organização: Adquirente\nNorma jurídica da Entidade Adjudicante: Organismo de direito público\nÁrea de atividade da Autoridade Adjudicante: Serviços públicos das administrações públicas\n\n2 - JORNAL OFICIAL DA UNIÃO EUROPEIA\nO procedimento a que este anúncio diz respeito também é publicitado no Jornal Oficial da União Europeia? Não\n\n3 - AVISO\nModelo de Anúncio: Concurso público\nData de Envio do Anúncio: 03-10-2025\n\n5 - PROCESSO\nTipo de Procedimento: Concurso público\nPreço base do procedimento: Sim\nValor do preço base do procedimento: 490.000,00 EUR\nProcedimento com lotes? Não\n\n6 - OBJETO DO CONTRATO\nNúmero de referência interna: 15/2025\nDesignação do contrato: BNAUT  ALTERAÇÃO E AMPLIAÇÃO DA ANTIGA ESCOLA E CRECHE DE VILA MEÃ.\nDescrição: BNAUT  ALTERAÇÃO E AMPLIAÇÃO DA ANTIGA ESCOLA E CRECHE DE VILA MEÃ.\nTipo de Contrato Principal: Empreitada de Obras Públicas\nTipo de Contrato: Empreitada de Obras Públicas\nClassificação CPV (Vocabulário Comum para os Contratos Públicos)\nObjeto principal\nVocabulário Principal: 45262700\nPreço base s/IVA: 490.000,00 EUR\n\n7 - INDICAÇÕES ADICIONAIS\nO contrato envolve aquisição conjunta (satisfação de várias entidades)? Não\nO contrato é adjudicado por uma central de compras? Não\n\n8 - TÉCNICAS\nO concurso destina-se à celebração de um acordo-quadro? Inexistência de acordo-quadro\nÉ utilizado um leilão eletrónico? Não\nÉ adotada uma fase de negociação? Não\nSistema de Aquisição Dinâmico: Inexistência de sistema de aquisição dinâmico\n\n9 - LOCAL DA EXECUÇÃO DO CONTRATO\nLOCAL DA EXECUÇÃO DO CONTRATO (PROCEDIMENTO)\nPaís: Portugal\nNUT III: PT16G\nLocalidade: Vila Meã\nDistrito: Viseu\nConcelho: Carregal do Sal\nFreguesia: Freguesia de Oliveira do Conde\n\n10 - PRAZO DE EXECUÇÃO DO CONTRATO\nPrazo de execução do contrato: 270 DIAS\nPrevisão de renovações: Não\n\n11 - FUNDOS EU\nTêm fundos EU? Sim\n\n12 - DOCUMENTOS DE HABILITAÇÃO\nHabilitação para o exercício da atividade profissional: Sim\nTipo: Alvará\nDescrição: a) A 1ª subcategoria da 1ª categoria, em classe correspondente ao valor da proposta;\nb) A 4ª, 5ª, 6ª, 7ª, 8ª e 9ª subcategorias da 1ª categoria e 1ª, 6ª, 9ª, 10ª e 12ª subcategorias da 4ª categoria e 1ª, 2ª, 8ª, 10ª, 11ª e 12ª subcategorias da 5ª categoria as quias têm de ser de classe correspondente à parte dos trabalhos a que respeitem;\n\n13 - CONDIÇÕES DE APRESENTAÇÃO\nPlataforma eletrónica utilizada pela entidade adjudicante: ACIN\nURL para Apresentação: https://www.acingov.pt\nAdmissibilidade da apresentação de propostas variantes: Não autorizado\nPrazo para apresentação das propostas: 17-10-2025 23:59\nPrazo durante o qual os concorrentes são obrigados a manter as respetivas propostas: 120 dias a contar do termo do prazo para a apresentação das propostas\nIndicação de Subcontratação na Proposta: Inexistência de indicação de subcontratação\n\n14 - PRESTAÇÃO DE CAUÇÃO\nPrestação de caução: Sim\nPercentagem: 5%\nDescrição da Garantia Exigida: O valor da caução é de 5.00% do preço contratual.\n\n15 - FORNECIMENTO DAS PEÇAS DO CONCURSO, APRESENTAÇÃO DE PEDIDOS DE PARTICIPAÇÃO E APRESENTAÇÃO DAS PROPOSTAS\nLink para acesso às peças do concurso (URL): https://www.acingov.pt/acingovprod/2/zonaPublica/zona_publica_c/donwloadProcedurePiece/OTc4NzE1\n\n20 - OUTROS REQUISITOS\nInformação sobre contratos reservados. Aplica-se a contratos reservados (54º-A)? Não\n\n21 - CRITÉRIO DE ADJUDICAÇÃO\nMultifator: Não\nMonofator:\nNome: Preço\n\n24 - CONDIÇÕES DO CONTRATO\nFaturação Eletrónica: Permitido\nObrigação de Subcontratação:\nCódigo da Obrigação de Subcontratação: Não é aplicável nenhuma obrigação de subcontratação.\n\n25 - COMPRA PÚBLICA ESTRATÉGICA\nCompra Pública Estratégica: Inexistência de contratação pública estratégica\n\n26 - INFORMAÇÕES ADICIONAIS\nContrato adequado para PME: Não\nCobertura ACP (Acordo dos Contratos Públicos da Organização Mundial do Comércio): Não\n\n27 - IDENTIFICAÇÃO E CONTACTOS DO ÓRGÃO DE RECURSOS ADMINISTRATIVOS\nDesignação: Presidente da Câmara\nEndereço: Praça do Município Apartado 90\nCódigo postal: 3430-167\nLocalidade: Carregal do Sal\nTelefone: 232960400\nFax: 232960409\nEndereço eletrónico: geral@cm-carregal.pt\nPrazo de interposição do recurso: 5 dias\n\n28 - IDENTIFICAÇÃO DO(S) AUTOR(ES) DE ANÚNCIO\nNome: Paulo Jorge Catalino de Almeida Ferraz\nCargo: Presidente da Câmara\n\n29 - ALTERAÇÃO\nMotivo da Alteração: Correção pelo adquirente\nIdentificador da Versão do Anúncio a Alterar: bcd5d1fe-7468-45e1-9b02-cd3a48d3b341-01\nIdentificador das Secções Alteradas do Anúncio Anterior: Condições de Apresentação; Identificação do(s) autor(es) do anúncio\nDescrição das Alterações: Modificação do prazo para a apresentação de propostas Atualização do(s) autor(es) do anúncio\nAlteração dos Documentos do Concurso: Não\n419605284",
    "nipc": "506684920",
    "distrito": "Viseu",
    "concelho": "Carregal do Sal",
    "freguesia": "Freguesia de Oliveira do Conde",
    "site": "https://www.cm-carregal.pt/",
    "email": "geral@cm-carregal.pt",
    "designacao_contrato": "BNAUT  ALTERAÇÃO E AMPLIAÇÃO DA ANTIGA ESCOLA E CRECHE DE VILA MEÃ.",
    "descricao": "BNAUT  ALTERAÇÃO E AMPLIAÇÃO DA ANTIGA ESCOLA E CRECHE DE VILA MEÃ.",
    "preco_base": "490.000,00 EUR",
    "prazo_execucao": "270 DIAS",
    "prazo_apresentacao_propostas": "17-10-2025 23:59",
    "fundos_eu": "Sim",
    "plataforma_eletronica": "ACIN",
    "url_procedimento": "https://www.acingov.pt",
    "autor_nome": "Paulo Jorge Catalino de Almeida Ferraz",
    "autor_cargo": "Presidente da Câmara"
  },
  {
    "numero_procedimento": "N/A",
    "entidade": "Município de Sintra",
    "link": "https://diariodarepublica.pt/dr/detalhe/contrato-publico/26007-937877794",
    "detalhes_completos": "1 - IDENTIFICAÇÃO E CONTACTOS DA ENTIDADE ADJUDICANTE\nDesignação da entidade adjudicante: Município de Sintra\nNIPC: 500051062\nEndereço: Largo Doutor Virgílio Horta\nCódigo postal: 2710-501\nLocalidade: Lisboa\nPaís: Portugal\nNUT III: PT170\nDistrito: Lisboa\nConcelho: Sintra\nFreguesia: União das Freguesias de Sintra (Santa Maria e São Miguel, São Martinho e São Pedro de Penaferrim)\nTelefone: 219238749\nFax: 219238790\nEndereço da Entidade (URL): www.cm-sintra.pt\nEndereço Eletrónico: dcp@cm-sintra.pt\neDelivery Gateway (URL): https://community.vortal.biz/public/\nFunção da Organização: Adquirente\nNorma jurídica da Entidade Adjudicante: Autoridade local\nÁrea de atividade da Autoridade Adjudicante: Serviços públicos das administrações públicas\n\n2 - JORNAL OFICIAL DA UNIÃO EUROPEIA\nO procedimento a que este anúncio diz respeito também é publicitado no Jornal Oficial da União Europeia? Não\n\n3 - AVISO\nModelo de Anúncio: Concurso público\nData de Envio do Anúncio: 03-10-2025\n\n5 - PROCESSO\nTipo de Procedimento: Concurso público\nPreço base do procedimento: Sim\nValor do preço base do procedimento: 89.700,00 EUR\nProcedimento com lotes? Não\n\n6 - OBJETO DO CONTRATO\nNúmero de referência interna: EM-25/00095\nDesignação do contrato: EM-25/00095 - Empreitada de Conservação e Beneficiação JI do Ral - V2\nDescrição: EM-25/00095 - Empreitada de Conservação e Beneficiação JI do Ral - V2\nTipo de Contrato Principal: Empreitada de Obras Públicas\nTipo de Contrato: Empreitada de Obras Públicas\nClassificação CPV (Vocabulário Comum para os Contratos Públicos)\nObjeto principal\nVocabulário Principal: 45421110\nPreço base s/IVA: 89.700,00 EUR\n\n7 - INDICAÇÕES ADICIONAIS\nO contrato envolve aquisição conjunta (satisfação de várias entidades)? Não\nO contrato é adjudicado por uma central de compras? Não\n\n8 - TÉCNICAS\nO concurso destina-se à celebração de um acordo-quadro? Inexistência de acordo-quadro\nÉ utilizado um leilão eletrónico? Não\nÉ adotada uma fase de negociação? Não\nSistema de Aquisição Dinâmico: Inexistência de sistema de aquisição dinâmico\n\n9 - LOCAL DA EXECUÇÃO DO CONTRATO\nLOCAL DA EXECUÇÃO DO CONTRATO (PROCEDIMENTO)\nPaís: Portugal\nNUT III: PT170\nLocalidade: Lisboa\nDistrito: Lisboa\nConcelho: Sintra\nFreguesia: União das Freguesias de Sintra (Santa Maria e São Miguel, São Martinho e São Pedro de Penaferrim)\n\n10 - PRAZO DE EXECUÇÃO DO CONTRATO\nPrazo de execução do contrato: 90 DIAS\nPrevisão de renovações: Não\n\n11 - FUNDOS EU\nTêm fundos EU? Não\n\n12 - DOCUMENTOS DE HABILITAÇÃO\nHabilitação para o exercício da atividade profissional: Sim\nTipo: Alvará\nDescrição: Alvará de Empreiteiro de Obras Públicas - 7.ª subcategoria da 1.ª categoria com a classe correspondente ao valor total da proposta;\n5ª subcategoria 1ª categoria com a classe correspondente ao valor total dos trabalhos a que respeitam.\n13 - CONDIÇÕES DE APRESENTAÇÃO\nPlataforma eletrónica utilizada pela entidade adjudicante: VORTAL\nURL para Apresentação: https://community.vortal.biz/public/\nAdmissibilidade da apresentação de propostas variantes: Não autorizado\nPrazo para apresentação das propostas: 24-10-2025 23:59\nPrazo durante o qual os concorrentes são obrigados a manter as respetivas propostas: 120 dias a contar do termo do prazo para a apresentação das propostas\nIndicação de Subcontratação na Proposta: Inexistência de indicação de subcontratação\n\n14 - PRESTAÇÃO DE CAUÇÃO\nPrestação de caução: Não\n\n15 - FORNECIMENTO DAS PEÇAS DO CONCURSO, APRESENTAÇÃO DE PEDIDOS DE PARTICIPAÇÃO E APRESENTAÇÃO DAS PROPOSTAS\nLink para acesso às peças do concurso (URL): https://community.vortal.biz/Public/public-tender-documents/cGIvZnVWUXg5WW12SlpYTkxhazM2WkpmaHNRa0FaaU9WQ2VwdFdpVWdBZ0R0cU5BTm5RUFlBTFU2aVErQjFjNGFRYlhNNnJzbk8xajYxOW1rMUhYdGc9PTV1TkBr\n\n20 - OUTROS REQUISITOS\nInformação sobre contratos reservados. Aplica-se a contratos reservados (54º-A)? Não\n\n21 - CRITÉRIO DE ADJUDICAÇÃO\nMultifator: Não\nMonofator:\nNome: Preço\n\n24 - CONDIÇÕES DO CONTRATO\nFaturação Eletrónica: Permitido\nObrigação de Subcontratação:\nCódigo da Obrigação de Subcontratação: Não é aplicável nenhuma obrigação de subcontratação.\n\n25 - COMPRA PÚBLICA ESTRATÉGICA\nCompra Pública Estratégica: Inexistência de contratação pública estratégica\n\n26 - INFORMAÇÕES ADICIONAIS\nContrato adequado para PME: Sim\nCobertura ACP (Acordo dos Contratos Públicos da Organização Mundial do Comércio): Não\n\n27 - IDENTIFICAÇÃO E CONTACTOS DO ÓRGÃO DE RECURSOS ADMINISTRATIVOS\nDesignação: Presidente da Câmara Municipal de Sintra\nEndereço: Largo Vergílio Horta\nCódigo postal: 2710-510\nLocalidade: Sintra\nTelefone: +351 219238612\nFax: +351 219238743\nEndereço eletrónico: demp@cm-sintra.pt\n\n28 - IDENTIFICAÇÃO DO(S) AUTOR(ES) DE ANÚNCIO\nNome: Basílio Horta\nCargo: Presidente da Câmara Municipal de Sintra\n419605487",
    "nipc": "500051062",
    "distrito": "Lisboa",
    "concelho": "Sintra",
    "freguesia": "União das Freguesias de Sintra (Santa Maria e São Miguel, São Martinho e São Pedro de Penaferrim)",
    "site": "www.cm-sintra.pt",
    "email": "dcp@cm-sintra.pt",
    "designacao_contrato": "EM-25/00095 - Empreitada de Conservação e Beneficiação JI do Ral - V2",
    "descricao": "EM-25/00095 - Empreitada de Conservação e Beneficiação JI do Ral - V2",
    "preco_base": "89.700,00 EUR",
    "prazo_execucao": "90 DIAS",
    "prazo_apresentacao_propostas": "24-10-2025 23:59",
    "fundos_eu": "Não",
    "plataforma_eletronica": "VORTAL",
    "url_procedimento": "https://community.vortal.biz/public/",
    "autor_nome": "Basílio Horta",
    "autor_cargo": "Presidente da Câmara Municipal de Sintra"
  },
  {
    "numero_procedimento": "N/A",
    "entidade": "AnÃºncio de procedimento  n.Âº 26008/2025  -  DiÃ¡rio da RepÃºblica n.Âº 191/2025, SÃ©rie II de 2025-10-03",
    "link": "https://diariodarepublica.pt/dr/detalhe/contrato-publico/26008-937877795"
  },
  {
    "numero_procedimento": "N/A",
    "entidade": "AnÃºncio de procedimento  n.Âº 26009/2025  -  DiÃ¡rio da RepÃºblica n.Âº 191/2025, SÃ©rie II de 2025-10-03",
    "link": "https://diariodarepublica.pt/dr/detalhe/contrato-publico/26009-937877796"
  },
  {
    "numero_procedimento": "N/A",
    "entidade": "AnÃºncio de procedimento  n.Âº 26010/2025  -  DiÃ¡rio da RepÃºblica n.Âº 191/2025, SÃ©rie II de 2025-10-03",
    "link": "https://diariodarepublica.pt/dr/detalhe/contrato-publico/26010-937877797"
  },
  {
    "numero_procedimento": "N/A",
    "entidade": "AnÃºncio de procedimento  n.Âº 26011/2025  -  DiÃ¡rio da RepÃºblica n.Âº 191/2025, SÃ©rie II de 2025-10-03",
    "link": "https://diariodarepublica.pt/dr/detalhe/contrato-publico/26011-937877798"
  },
  {
    "numero_procedimento": "N/A",
    "entidade": "Município de Vila Nova de Gaia",
    "link": "https://diariodarepublica.pt/dr/detalhe/contrato-publico/26013-937877799",
    "detalhes_completos": "1 - IDENTIFICAÇÃO E CONTACTOS DA ENTIDADE ADJUDICANTE\nDesignação da entidade adjudicante: Município de Vila Nova de Gaia\nNIPC: 505335018\nServiço/Órgão/Pessoa de contacto: Divisão de Aquisição de Bens e Serviços\nEndereço: Rua Álvares Cabral\nCódigo postal: 4400-017\nLocalidade: Vila Nova de Gaia\nPaís: Portugal\nNUT III: PT11A\nDistrito: Porto\nConcelho: Vila Nova de Gaia\nFreguesia: União das Freguesias de Mafamude e Vilar do Paraíso\nTelefone: 223742400\nFax: 223742430\nEndereço da Entidade (URL): https://www.cm-gaia.pt/pt/\nEndereço Eletrónico: geraldabs@cm-gaia.pt\neDelivery Gateway (URL): https://www.acingov.pt\nFunção da Organização: Adquirente\nNorma jurídica da Entidade Adjudicante: Organismo de direito público\nÁrea de atividade da Autoridade Adjudicante: Serviços públicos das administrações públicas\n\n2 - JORNAL OFICIAL DA UNIÃO EUROPEIA\nO procedimento a que este anúncio diz respeito também é publicitado no Jornal Oficial da União Europeia? Sim\n\n3 - AVISO\nModelo de Anúncio: Concurso público\nData de Envio do Anúncio: 01-10-2025\n\n5 - PROCESSO\nTipo de Procedimento: Concurso público\nPreço base do procedimento: Não\nProcedimento com lotes? Sim\nNº Máx. de Lotes Autorizado: 2\nNúmero máximo de lotes que podem ser adjudicados a um concorrente: 1\n\n6 - OBJETO DO CONTRATO\nNúmero de referência interna: CPI/CON/01/2025\nDesignação do contrato: Concurso público para concessão da utilização do espaço do domínio público do Município de Vila Nova de Gaia para a instalação e operação de um sistema partilhado de trotinetes com motor sem doca\nDescrição: Concurso público para concessão da utilização do espaço do domínio público do Município de Vila Nova de Gaia para a instalação e operação de um sistema partilhado de trotinetes com motor sem doca\nOpções: Não\nTipo de Contrato Principal: Concessão de Serviços Públicos\nTipo de Contrato: Concessão de Serviços Públicos\nClassificação CPV (Vocabulário Comum para os Contratos Públicos)\nObjeto principal\nVocabulário Principal: 51110000\nLotes: \nNº: LOT-0001\nDescrição do Lote: Lote 1 - Oeste\nClassificação CPV (Vocabulário Comum para os Contratos Públicos)\nObjeto principal\nVocabulário Principal: 51110000\nNº: LOT-0002\nDescrição do Lote: Lote 2 - Este\nClassificação CPV (Vocabulário Comum para os Contratos Públicos)\nObjeto principal\nVocabulário Principal: 51110000\n\n7 - INDICAÇÕES ADICIONAIS\nO contrato envolve aquisição conjunta (satisfação de várias entidades)? Não\nO contrato é adjudicado por uma central de compras? Não\n\n8 - TÉCNICAS\nO concurso destina-se à celebração de um acordo-quadro? Inexistência de acordo-quadro\nÉ utilizado um leilão eletrónico? Não\nÉ adotada uma fase de negociação? Não\nSistema de Aquisição Dinâmico: Inexistência de sistema de aquisição dinâmico\n\n9 - LOCAL DA EXECUÇÃO DO CONTRATO\nLOCAL DA EXECUÇÃO DO CONTRATO (PROCEDIMENTO)\nPaís: Portugal\nNUT III: PT11A\nLocalidade: União das Freguesias de Mafamude e Vilar do Paraíso\nDistrito: Porto\nConcelho: Vila Nova de Gaia\nFreguesia: União das Freguesias de Mafamude e Vilar do Paraíso\nLOCAL DA EXECUÇÃO DO CONTRATO (LOTE)\nIdentificador do Lote: LOT-0001; LOT-0002\nPaís: Portugal\nNUT III: PT11A\nLocalidade: União das Freguesias de Mafamude e Vilar do Paraíso\nDistrito: Porto\nConcelho: Vila Nova de Gaia\nFreguesia: União das Freguesias de Mafamude e Vilar do Paraíso\n\n10 - PRAZO DE EXECUÇÃO DO CONTRATO\nIdentificador do Lote: LOT-0001; LOT-0002\nPrazo de execução do contrato: 12 MESES\nPrevisão de renovações: Sim\nIndicar número máximo de renovações: 2\nPrazo de renovações diferente do prazo inicial: Não\n\n11 - FUNDOS EU\nIdentificador do Lote: LOT-0001; LOT-0002\nTêm fundos EU? Não\n\n12 - DOCUMENTOS DE HABILITAÇÃO\nHabilitação para o exercício da atividade profissional: Não\n\n13 - CONDIÇÕES DE APRESENTAÇÃO\nPlataforma eletrónica utilizada pela entidade adjudicante: ACIN\nURL para Apresentação: https://www.acingov.pt\nAdmissibilidade da apresentação de propostas variantes: Não autorizado\nPrazo para apresentação das propostas: 09-12-2025 23:59\nPrazo durante o qual os concorrentes são obrigados a manter as respetivas propostas: 120 dias a contar do termo do prazo para a apresentação das propostas\nApresentação de Catálogo Eletrónico: Não autorizado\nIndicação de Subcontratação na Proposta: Inexistência de indicação de subcontratação\n\n14 - PRESTAÇÃO DE CAUÇÃO\nPrestação de caução: Não\n\n15 - FORNECIMENTO DAS PEÇAS DO CONCURSO, APRESENTAÇÃO DE PEDIDOS DE PARTICIPAÇÃO E APRESENTAÇÃO DAS PROPOSTAS\nLink para acesso às peças do concurso (URL): https://www.acingov.pt/acingovprod/2/zonaPublica/zona_publica_c/donwloadProcedurePiece/OTgxNzc4\n\n20 - OUTROS REQUISITOS\nIdentificador do Lote: LOT-0001; LOT-0002\nInformação sobre contratos reservados. Aplica-se a contratos reservados (54º-A)? Não\n\n21 - CRITÉRIO DE ADJUDICAÇÃO\nO Critério de adjudicação é diferenciado por lote? Não\nMultifator: Sim\nFator: \nNome: Outros\nOutro Nome: Fator Renda\nPonderação: 40%\nSubfatores: Não\nFator: \nNome: Outros\nOutro Nome: Valia Técnica\nPonderação: 60%\nSubfatores: Não\n\n24 - CONDIÇÕES DO CONTRATO\nIdentificador do Lote: LOT-0001; LOT-0002\nFaturação Eletrónica: Permitido\nObrigação de Subcontratação:\nCódigo da Obrigação de Subcontratação: Não é aplicável nenhuma obrigação de subcontratação.\n\n25 - COMPRA PÚBLICA ESTRATÉGICA\nCompra Pública Estratégica: Inexistência de contratação pública estratégica\n\n26 - INFORMAÇÕES ADICIONAIS\nIdentificador do Lote: LOT-0001; LOT-0002\nContrato adequado para PME: Sim\nCobertura ACP (Acordo dos Contratos Públicos da Organização Mundial do Comércio): Não\n\n27 - IDENTIFICAÇÃO E CONTACTOS DO ÓRGÃO DE RECURSOS ADMINISTRATIVOS\nDesignação: Câmara Municipal de Vila Nova de Gaia\nEndereço: Rua Álvares Cabral\nCódigo postal: 4400-017\nLocalidade: Vila Nova de Gaia\nTelefone: 223742400\nFax: 223742430\nEndereço eletrónico: geral@cm-gaia.pt\n\n28 - IDENTIFICAÇÃO DO(S) AUTOR(ES) DE ANÚNCIO\nNome: Dr.ª Marina Mendes\nCargo: Presidente da Câmara Municipal de Vila Nova de Gaia\n419594796",
    "nipc": "505335018",
    "distrito": "Porto",
    "concelho": "Vila Nova de Gaia",
    "freguesia": "União das Freguesias de Mafamude e Vilar do Paraíso",
    "site": "https://www.cm-gaia.pt/pt/",
    "email": "geraldabs@cm-gaia.pt",
    "designacao_contrato": "Concurso público para concessão da utilização do espaço do domínio público do Município de Vila Nova de Gaia para a instalação e operação de um sistema partilhado de trotinetes com motor sem doca",
    "descricao": "Concurso público para concessão da utilização do espaço do domínio público do Município de Vila Nova de Gaia para a instalação e operação de um sistema partilhado de trotinetes com motor sem doca",
    "preco_base": null,
    "prazo_execucao": "12 MESES",
    "prazo_apresentacao_propostas": "09-12-2025 23:59",
    "fundos_eu": "Não",
    "plataforma_eletronica": "ACIN",
    "url_procedimento": "https://www.acingov.pt",
    "autor_nome": "Dr.ª Marina Mendes",
    "autor_cargo": "Presidente da Câmara Municipal de Vila Nova de Gaia"
  },
  {
    "numero_procedimento": "N/A",
    "entidade": "AnÃºncio de procedimento  n.Âº 26014/2025  -  DiÃ¡rio da RepÃºblica n.Âº 191/2025, SÃ©rie II de 2025-10-03",
    "link": "https://diariodarepublica.pt/dr/detalhe/contrato-publico/26014-937877800"
  },
  {
    "numero_procedimento": "N/A",
    "entidade": "AnÃºncio de procedimento  n.Âº 26015/2025  -  DiÃ¡rio da RepÃºblica n.Âº 191/2025, SÃ©rie II de 2025-10-03",
    "link": "https://diariodarepublica.pt/dr/detalhe/contrato-publico/26015-937877801"
  },
  {
    "numero_procedimento": "N/A",
    "entidade": "AnÃºncio de procedimento  n.Âº 26017/2025  -  DiÃ¡rio da RepÃºblica n.Âº 191/2025, SÃ©rie II de 2025-10-03",
    "link": "https://diariodarepublica.pt/dr/detalhe/contrato-publico/26017-937877802"
  },
  {
    "numero_procedimento": "N/A",
    "entidade": "Município de Santa Maria da Feira",
    "link": "https://diariodarepublica.pt/dr/detalhe/contrato-publico/26019-937877803",
    "detalhes_completos": "1 - IDENTIFICAÇÃO E CONTACTOS DA ENTIDADE ADJUDICANTE\nDesignação da entidade adjudicante: Município de Santa Maria da Feira\nNIPC: 501157280\nServiço/Órgão/Pessoa de contacto: Câmara Municipal de Santa Maria da Feira\nEndereço: Praça da República, 135\nCódigo postal: 4520-174\nLocalidade: Santa Maria da Feira\nPaís: Portugal\nNUT III: PT11A\nDistrito: Aveiro\nConcelho: Santa Maria da Feira\nFreguesia: União das Freguesias de Santa Maria da Feira, Travanca, Sanfins e Espargo\nTelefone: 256370800\nFax: 256370807\nEndereço da Entidade (URL): www.cm-feira.pt\nEndereço Eletrónico: central.compras@cm-feira.pt\nFunção da Organização: Adquirente\nNorma jurídica da Entidade Adjudicante: Autoridade local\nÁrea de atividade da Entidade Adjudicante: Atividades aeroportuárias\n\n2 - JORNAL OFICIAL DA UNIÃO EUROPEIA\nO procedimento a que este anúncio diz respeito também é publicitado no Jornal Oficial da União Europeia? Não\n\n3 - AVISO\nModelo de Anúncio: Concurso público\nData de Envio do Anúncio: 03-10-2025\n\n5 - PROCESSO\nTipo de Procedimento: Concurso público\nPreço base do procedimento: Sim\nValor do preço base do procedimento: 51.000,00 EUR\nProcedimento com lotes? Não\n\n6 - OBJETO DO CONTRATO\nNúmero de referência interna: SMF/0003228/CPN/B/25-2025\nDesignação do contrato: Aquisição de 4 Módulos Pré-Fabricados para Apoio ao Zoo de Lourosa\nDescrição: Aquisição de 4 Módulos Pré-Fabricados para Apoio ao Zoo de Lourosa\nTipo de Contrato Principal: Aquisição de Bens Móveis\nTipo de Contrato: Aquisição de Bens Móveis\nClassificação CPV (Vocabulário Comum para os Contratos Públicos)\nObjeto principal\nVocabulário Principal: 39200000\nPreço base s/IVA: 51.000,00 EUR\n\n7 - INDICAÇÕES ADICIONAIS\nO contrato envolve aquisição conjunta (satisfação de várias entidades)? Não\nO contrato é adjudicado por uma central de compras? Não\n\n8 - TÉCNICAS\nO concurso destina-se à celebração de um acordo-quadro? Inexistência de acordo-quadro\nÉ utilizado um leilão eletrónico? Não\nÉ adotada uma fase de negociação? Não\nSistema de Aquisição Dinâmico: Inexistência de sistema de aquisição dinâmico\n\n9 - LOCAL DA EXECUÇÃO DO CONTRATO\nLOCAL DA EXECUÇÃO DO CONTRATO (PROCEDIMENTO)\nPaís: Portugal\nNUT III: PT11A\nLocalidade: Lourosa\nDistrito: Aveiro\nConcelho: Santa Maria da Feira\nFreguesia: Freguesia de Lourosa - Santa Maria da Feira\n\n10 - PRAZO DE EXECUÇÃO DO CONTRATO\nPrazo de execução do contrato: 90 DIAS\nPrevisão de renovações: Não\n\n11 - FUNDOS EU\nTêm fundos EU? Não\n\n12 - DOCUMENTOS DE HABILITAÇÃO\nHabilitação para o exercício da atividade profissional: Não\n\n13 - CONDIÇÕES DE APRESENTAÇÃO\nPlataforma eletrónica utilizada pela entidade adjudicante: ANOGOV\nURL para Apresentação: https://www.anogov.com/cm-smfeira/faces/\nAdmissibilidade da apresentação de propostas variantes: Não autorizado\nPrazo para apresentação das propostas: 21-10-2025 23:59\nPrazo durante o qual os concorrentes são obrigados a manter as respetivas propostas: 66 dias a contar do termo do prazo para a apresentação das propostas\nApresentação de Catálogo Eletrónico: Não autorizado\nIndicação de Subcontratação na Proposta: Inexistência de indicação de subcontratação\n\n14 - PRESTAÇÃO DE CAUÇÃO\nPrestação de caução: Não\n\n15 - FORNECIMENTO DAS PEÇAS DO CONCURSO, APRESENTAÇÃO DE PEDIDOS DE PARTICIPAÇÃO E APRESENTAÇÃO DAS PROPOSTAS\nLink para acesso às peças do concurso (URL): https://www.anogov.com/cm-smfeira/faces/app/acessoDocs.jsp?codigoAcesso=ihrRjJM8djoz5jRo745CXFWzRF5RAK7eRiSUxkh9zcNagkIO80\n\n20 - OUTROS REQUISITOS\nInformação sobre contratos reservados. Aplica-se a contratos reservados (54º-A)? Não\n\n21 - CRITÉRIO DE ADJUDICAÇÃO\nMultifator: Não\nMonofator:\nNome: Preço\n\n24 - CONDIÇÕES DO CONTRATO\nFaturação Eletrónica: Permitido\nObrigação de Subcontratação:\nCódigo da Obrigação de Subcontratação: Não é aplicável nenhuma obrigação de subcontratação.\n\n25 - COMPRA PÚBLICA ESTRATÉGICA\nCompra Pública Estratégica: Inexistência de contratação pública estratégica\n\n26 - INFORMAÇÕES ADICIONAIS\nContrato adequado para PME: Não\nCobertura ACP (Acordo dos Contratos Públicos da Organização Mundial do Comércio): Não\n\n27 - IDENTIFICAÇÃO E CONTACTOS DO ÓRGÃO DE RECURSOS ADMINISTRATIVOS\nDesignação: Câmara Municipal de Santa Maria da Feira\nEndereço: Praça da República\nCódigo postal: 4520-174\nLocalidade: Santa Maria da Feira\nTelefone: 256370800\nFax: \nEndereço eletrónico: central.compras@cm-feira.pt\nPrazo de interposição do recurso: 5 dias\n\n28 - IDENTIFICAÇÃO DO(S) AUTOR(ES) DE ANÚNCIO\nNome: Sónia Azevedo\nCargo: Ver.Pel.Adminst.Finanças e Modernização Administrativa\n419608638",
    "nipc": "501157280",
    "distrito": "Aveiro",
    "concelho": "Santa Maria da Feira",
    "freguesia": "União das Freguesias de Santa Maria da Feira, Travanca, Sanfins e Espargo",
    "site": "www.cm-feira.pt",
    "email": "central.compras@cm-feira.pt",
    "designacao_contrato": "Aquisição de 4 Módulos Pré-Fabricados para Apoio ao Zoo de Lourosa",
    "descricao": "Aquisição de 4 Módulos Pré-Fabricados para Apoio ao Zoo de Lourosa",
    "preco_base": "51.000,00 EUR",
    "prazo_execucao": "90 DIAS",
    "prazo_apresentacao_propostas": "21-10-2025 23:59",
    "fundos_eu": "Não",
    "plataforma_eletronica": "ANOGOV",
    "url_procedimento": "https://www.anogov.com/cm-smfeira/faces/",
    "autor_nome": "Sónia Azevedo",
    "autor_cargo": "Ver.Pel.Adminst.Finanças e Modernização Administrativa"
  },
  {
    "numero_procedimento": "N/A",
    "entidade": "AnÃºncio de procedimento  n.Âº 26030/2025  -  DiÃ¡rio da RepÃºblica n.Âº 191/2025, SÃ©rie II de 2025-10-03",
    "link": "https://diariodarepublica.pt/dr/detalhe/contrato-publico/26030-937877805"
  },
  {
    "numero_procedimento": "N/A",
    "entidade": "Município da Maia",
    "link": "https://diariodarepublica.pt/dr/detalhe/contrato-publico/26032-937877806",
    "detalhes_completos": "Alteração do Anúncio de procedimento n.º 25261/2025, de 2025-09-25, com o ID 419574164\n\n1 - IDENTIFICAÇÃO E CONTACTOS DA ENTIDADE ADJUDICANTE\nDesignação da entidade adjudicante: Município da Maia\nNIPC: 505387131\nServiço/Órgão/Pessoa de contacto: Presidente da Câmara\nEndereço: Praça Dr. José Vieira de Carvalho\nCódigo postal: 4470-202\nLocalidade: Maia\nPaís: Portugal\nNUT III: PT11A\nDistrito: Porto\nConcelho: Maia\nFreguesia: Todas\nTelefone: 229408600\nFax: 229418411\nEndereço da Entidade (URL): www.cm-maia.pt\nEndereço Eletrónico: geral@cm-maia.pt\neDelivery Gateway (URL): https://www.acingov.pt\nFunção da Organização: Adquirente\nSubfunção da Organização: Organização que recebe as propostas\nNorma jurídica da Entidade Adjudicante: Autoridade local\nÁrea de atividade da Autoridade Adjudicante: Serviços públicos das administrações públicas\n\n2 - JORNAL OFICIAL DA UNIÃO EUROPEIA\nO procedimento a que este anúncio diz respeito também é publicitado no Jornal Oficial da União Europeia? Não\n\n3 - AVISO\nModelo de Anúncio: Concurso público\nData de Envio do Anúncio: 03-10-2025\n\n5 - PROCESSO\nTipo de Procedimento: Concurso público\nPreço base do procedimento: Sim\nValor do preço base do procedimento: 183.000,00 EUR\nProcedimento com lotes? Sim\nNº Máx. de Lotes Autorizado: 2\nNúmero máximo de lotes que podem ser adjudicados a um concorrente: 2\n\n6 - OBJETO DO CONTRATO\nNúmero de referência interna: 891/2025\nDesignação do contrato: PROCEDIMENTO N.º 891/2025 - PRESTAÇÃO DE SERVIÇOS DE MANUTENÇÃO PREVENTIVA E CORRETIVA DOS SISTEMAS DOS SISTEMAS DE AQUECIMENTO, VENTILAÇÃO E AR CONDICIONADO AVAC, AQS (GÁS E CALOR) E REFRIGERAÇÃO, EM DIVERSAS INSTALAÇÕES DO CONCELHO (ESCOLAS, INSTALAÇÕES DESPORTIVAS E PARTE DOS EDIFICIOS MUNICIPAIS), PELO PERÍODO DE TRÊS MESES, RENOVÁVEL AUTOMATICAMENTE POR IGUAIS PERÍODOS ATÉ AO MÁXIMO DE 12 MESES\nDescrição: PROCEDIMENTO N.º 891/2025 - PRESTAÇÃO DE SERVIÇOS DE MANUTENÇÃO PREVENTIVA E CORRETIVA DOS SISTEMAS DOS SISTEMAS DE AQUECIMENTO, VENTILAÇÃO E AR CONDICIONADO AVAC, AQS (GÁS E CALOR) E REFRIGERAÇÃO, EM DIVERSAS INSTALAÇÕES DO CONCELHO (ESCOLAS, INSTALAÇÕES DESPORTIVAS E PARTE DOS EDIFICIOS MUNICIPAIS), PELO PERÍODO DE TRÊS MESES, RENOVÁVEL AUTOMATICAMENTE POR IGUAIS PERÍODOS ATÉ AO MÁXIMO DE 12 MESES\nTipo de Contrato Principal: Aquisição de Serviços\nTipo de Contrato: Aquisição de Serviços\nClassificação CPV (Vocabulário Comum para os Contratos Públicos)\nObjeto principal\nVocabulário Principal: 71356200\nPreço base s/IVA: 183.000,00 EUR\nLotes: \nNº: LOT-0001\nDescrição do Lote: PROCEDIMENTO N.º 891/2025 - PRESTAÇÃO DE SERVIÇOS DE MANUTENÇÃO PREVENTIVA E CORRETIVA DOS SISTEMAS DOS SISTEMAS DE AQUECIMENTO, VENTILAÇÃO E AR CONDICIONADO AVAC, AQS (GÁS E CALOR) E REFRIGERAÇÃO, EM DIVERSAS INSTALAÇÕES DO CONCELHO (ESCOLAS, INSTALAÇÕES DESPORTIVAS E PARTE DOS EDIFICIOS MUNICIPAIS), PELO PERÍODO DE TRÊS MESES, RENOVÁVEL AUTOMATICAMENTE POR IGUAIS PERÍOD...\nPreço base s/IVA: 91.500,00 EUR\nClassificação CPV (Vocabulário Comum para os Contratos Públicos)\nObjeto principal\nVocabulário Principal: 71356200\nNº: LOT-0002\nDescrição do Lote: PROCEDIMENTO N.º 891/2025 - PRESTAÇÃO DE SERVIÇOS DE MANUTENÇÃO PREVENTIVA E CORRETIVA DOS SISTEMAS DOS SISTEMAS DE AQUECIMENTO, VENTILAÇÃO E AR CONDICIONADO AVAC, AQS (GÁS E CALOR) E REFRIGERAÇÃO, EM DIVERSAS INSTALAÇÕES DO CONCELHO (ESCOLAS, INSTALAÇÕES DESPORTIVAS E PARTE DOS EDIFICIOS MUNICIPAIS), PELO PERÍODO DE TRÊS MESES, RENOVÁVEL AUTOMATICAMENTE POR IGUAIS PERÍOD...\nPreço base s/IVA: 91.500,00 EUR\nClassificação CPV (Vocabulário Comum para os Contratos Públicos)\nObjeto principal\nVocabulário Principal: 71356200\n\n7 - INDICAÇÕES ADICIONAIS\nO contrato envolve aquisição conjunta (satisfação de várias entidades)? Não\nO contrato é adjudicado por uma central de compras? Não\n\n8 - TÉCNICAS\nO concurso destina-se à celebração de um acordo-quadro? Inexistência de acordo-quadro\nÉ utilizado um leilão eletrónico? Não\nÉ adotada uma fase de negociação? Não\nSistema de Aquisição Dinâmico: Inexistência de sistema de aquisição dinâmico\n\n9 - LOCAL DA EXECUÇÃO DO CONTRATO\nLOCAL DA EXECUÇÃO DO CONTRATO (PROCEDIMENTO)\nPaís: Portugal\nNUT III: PT11A\nLocalidade: Cidade da Maia\nDistrito: Porto\nConcelho: Maia\nFreguesia: Todas\nLOCAL DA EXECUÇÃO DO CONTRATO (LOTE)\nIdentificador do Lote: LOT-0001; LOT-0002\nPaís: Portugal\nNUT III: PT11A\nLocalidade: Cidade da Maia\nDistrito: Porto\nConcelho: Maia\nFreguesia: Todas\n\n10 - PRAZO DE EXECUÇÃO DO CONTRATO\nIdentificador do Lote: LOT-0001; LOT-0002\nPrazo de execução do contrato: 12 MESES\nPrevisão de renovações: Não\n\n11 - FUNDOS EU\nIdentificador do Lote: LOT-0001; LOT-0002\nTêm fundos EU? Não\n\n12 - DOCUMENTOS DE HABILITAÇÃO\nHabilitação para o exercício da atividade profissional: Não\n\n13 - CONDIÇÕES DE APRESENTAÇÃO\nPlataforma eletrónica utilizada pela entidade adjudicante: ACIN\nURL para Apresentação: https://www.acingov.pt\nAdmissibilidade da apresentação de propostas variantes: Não autorizado\nPrazo para apresentação das propostas: 13-10-2025 23:59\nPrazo durante o qual os concorrentes são obrigados a manter as respetivas propostas: 66 dias a contar do termo do prazo para a apresentação das propostas\nIndicação de Subcontratação na Proposta: Inexistência de indicação de subcontratação\n\n14 - PRESTAÇÃO DE CAUÇÃO\nPrestação de caução: Não\n\n15 - FORNECIMENTO DAS PEÇAS DO CONCURSO, APRESENTAÇÃO DE PEDIDOS DE PARTICIPAÇÃO E APRESENTAÇÃO DAS PROPOSTAS\nLink para acesso às peças do concurso (URL): https://www.acingov.pt/acingovprod/2/zonaPublica/zona_publica_c/donwloadProcedurePiece/OTgxMDUz\n\n20 - OUTROS REQUISITOS\nIdentificador do Lote: LOT-0001; LOT-0002\nInformação sobre contratos reservados. Aplica-se a contratos reservados (54º-A)? Não\n\n21 - CRITÉRIO DE ADJUDICAÇÃO\nO Critério de adjudicação é diferenciado por lote? Não\nMultifator: Não\nMonofator:\nNome: Preço\n\n24 - CONDIÇÕES DO CONTRATO\nIdentificador do Lote: LOT-0001; LOT-0002\nFaturação Eletrónica: Permitido\nObrigação de Subcontratação:\nCódigo da Obrigação de Subcontratação: Não é aplicável nenhuma obrigação de subcontratação.\n\n25 - COMPRA PÚBLICA ESTRATÉGICA\nCompra Pública Estratégica: Inexistência de contratação pública estratégica\n\n26 - INFORMAÇÕES ADICIONAIS\nIdentificador do Lote: LOT-0001; LOT-0002\nContrato adequado para PME: Sim\nCobertura ACP (Acordo dos Contratos Públicos da Organização Mundial do Comércio): Não\n\n27 - IDENTIFICAÇÃO E CONTACTOS DO ÓRGÃO DE RECURSOS ADMINISTRATIVOS\nDesignação: Presidente da Câmara Municipal da Maia no âmbito da delegação de competências\nEndereço: Praça do Dr. José Vieira de Carvalho\nCódigo postal: 4474-006\nLocalidade: Maia\nTelefone: 351229408600\nFax: 351229480901\nEndereço eletrónico: presidencia@cm-maia.pt\nPrazo de interposição do recurso: 5 dias\n\n28 - IDENTIFICAÇÃO DO(S) AUTOR(ES) DE ANÚNCIO\nNome: António Domingos da Silva Tiago\nCargo: Presidente da Câmara Municipal da Maia\n\n29 - ALTERAÇÃO\nMotivo da Alteração: Correção pelo adquirente\nIdentificador da Versão do Anúncio a Alterar: ed52eaad-4704-43e1-92a4-56d95499f97e-01\nIdentificador das Secções Alteradas do Anúncio Anterior: Condições de Apresentação\nDescrição das Alterações: Modificação do prazo para a apresentação de propostas\nAlteração dos Documentos do Concurso: Sim\nData de alteração dos documentos do concurso: 03-10-2025\n419610508",
    "nipc": "505387131",
    "distrito": "Porto",
    "concelho": "Maia",
    "freguesia": "Todas",
    "site": "www.cm-maia.pt",
    "email": "geral@cm-maia.pt",
    "designacao_contrato": "PROCEDIMENTO N.º 891/2025 - PRESTAÇÃO DE SERVIÇOS DE MANUTENÇÃO PREVENTIVA E CORRETIVA DOS SISTEMAS DOS SISTEMAS DE AQUECIMENTO, VENTILAÇÃO E AR CONDICIONADO AVAC, AQS (GÁS E CALOR) E REFRIGERAÇÃO, EM DIVERSAS INSTALAÇÕES DO CONCELHO (ESCOLAS, INSTALAÇÕES DESPORTIVAS E PARTE DOS EDIFICIOS MUNICIPAIS), PELO PERÍODO DE TRÊS MESES, RENOVÁVEL AUTOMATICAMENTE POR IGUAIS PERÍODOS ATÉ AO MÁXIMO DE 12 MESES",
    "descricao": "PROCEDIMENTO N.º 891/2025 - PRESTAÇÃO DE SERVIÇOS DE MANUTENÇÃO PREVENTIVA E CORRETIVA DOS SISTEMAS DOS SISTEMAS DE AQUECIMENTO, VENTILAÇÃO E AR CONDICIONADO AVAC, AQS (GÁS E CALOR) E REFRIGERAÇÃO, EM DIVERSAS INSTALAÇÕES DO CONCELHO (ESCOLAS, INSTALAÇÕES DESPORTIVAS E PARTE DOS EDIFICIOS MUNICIPAIS), PELO PERÍODO DE TRÊS MESES, RENOVÁVEL AUTOMATICAMENTE POR IGUAIS PERÍODOS ATÉ AO MÁXIMO DE 12 MESES",
    "preco_base": "183.000,00 EUR",
    "prazo_execucao": "12 MESES",
    "prazo_apresentacao_propostas": "13-10-2025 23:59",
    "fundos_eu": "Não",
    "plataforma_eletronica": "ACIN",
    "url_procedimento": "https://www.acingov.pt",
    "autor_nome": "António Domingos da Silva Tiago",
    "autor_cargo": "Presidente da Câmara Municipal da Maia"
  },
  {
    "numero_procedimento": "N/A",
    "entidade": "AnÃºncio de procedimento  n.Âº 26033/2025  -  DiÃ¡rio da RepÃºblica n.Âº 191/2025, SÃ©rie II de 2025-10-03",
    "link": "https://diariodarepublica.pt/dr/detalhe/contrato-publico/26033-937877807"
  },
  {
    "numero_procedimento": "N/A",
    "entidade": "AnÃºncio de procedimento  n.Âº 26040/2025  -  DiÃ¡rio da RepÃºblica n.Âº 191/2025, SÃ©rie II de 2025-10-03",
    "link": "https://diariodarepublica.pt/dr/detalhe/contrato-publico/26040-937877809"
  },
  {
    "numero_procedimento": "N/A",
    "entidade": "AnÃºncio de procedimento  n.Âº 26041/2025  -  DiÃ¡rio da RepÃºblica n.Âº 191/2025, SÃ©rie II de 2025-10-03",
    "link": "https://diariodarepublica.pt/dr/detalhe/contrato-publico/26041-937877810"
  },
  {
    "numero_procedimento": "N/A",
    "entidade": "Unidade Local de Saúde de Coimbra, E. P. E.",
    "link": "https://diariodarepublica.pt/dr/detalhe/contrato-publico/26043-937877811",
    "detalhes_completos": "1 - IDENTIFICAÇÃO E CONTACTOS DA ENTIDADE ADJUDICANTE\nDesignação da entidade adjudicante: Unidade Local de Saúde de Coimbra, E. P. E.\nNIPC: 510103448\nEndereço: Praceta Prof. Mota Pinto\nCódigo postal: 3004-561\nLocalidade: Coimbra\nPaís: Portugal\nNUT III: PT16E\nDistrito: Coimbra\nConcelho: Coimbra\nFreguesia: Todas\nTelefone: 239400605\nFax: 239400605\nEndereço da Entidade (URL): https://www.chuc.min-saude.pt\nEndereço Eletrónico: ana.rosete@ulscoimbra.min-saude.pt\neDelivery Gateway (URL): https://community.vortal.biz/public/\nFunção da Organização: Adquirente\nNorma jurídica da Entidade Adjudicante: Organismo de direito público\nÁrea de atividade da Autoridade Adjudicante: Saúde\n\n2 - JORNAL OFICIAL DA UNIÃO EUROPEIA\nO procedimento a que este anúncio diz respeito também é publicitado no Jornal Oficial da União Europeia? Não\n\n3 - AVISO\nModelo de Anúncio: Concurso público\nData de Envio do Anúncio: 03-10-2025\n\n5 - PROCESSO\nTipo de Procedimento: Concurso público\nPreço base do procedimento: Sim\nValor do preço base do procedimento: 230.825,71 EUR\nProcedimento com lotes? Não\n\n6 - OBJETO DO CONTRATO\nNúmero de referência interna: 010900732025\nDesignação do contrato: Empreitada de Remodelação do Átrio das Consultas Externas para Área de Contingência do Serviço de Urgência, no Polo HUC da Unidade Local de Saúde de Coimbra, E.P.E.\nDescrição: Empreitada de Remodelação do Átrio das Consultas Externas para Área de Contingência do Serviço de Urgência, no Polo HUC da Unidade Local de Saúde de Coimbra, E.P.E.\nTipo de Contrato Principal: Empreitada de Obras Públicas\nTipo de Contrato: Empreitada de Obras Públicas\nClassificação CPV (Vocabulário Comum para os Contratos Públicos)\nObjeto principal\nVocabulário Principal: 45200000\nPreço base s/IVA: 230.825,71 EUR\n\n7 - INDICAÇÕES ADICIONAIS\nO contrato envolve aquisição conjunta (satisfação de várias entidades)? Não\nO contrato é adjudicado por uma central de compras? Não\n\n8 - TÉCNICAS\nO concurso destina-se à celebração de um acordo-quadro? Inexistência de acordo-quadro\nÉ utilizado um leilão eletrónico? Não\nÉ adotada uma fase de negociação? Não\nSistema de Aquisição Dinâmico: Inexistência de sistema de aquisição dinâmico\n\n9 - LOCAL DA EXECUÇÃO DO CONTRATO\nLOCAL DA EXECUÇÃO DO CONTRATO (PROCEDIMENTO)\nPaís: Portugal\nNUT III: PT16E\nLocalidade: Coimbra\nDistrito: Coimbra\nConcelho: Coimbra\nFreguesia: Freguesia de Santo António dos Olivais\n\n10 - PRAZO DE EXECUÇÃO DO CONTRATO\nPrazo de execução do contrato: 75 DIAS\nPrevisão de renovações: Não\n\n11 - FUNDOS EU\nTêm fundos EU? Não\n\n12 - DOCUMENTOS DE HABILITAÇÃO\nHabilitação para o exercício da atividade profissional: Não\n\n13 - CONDIÇÕES DE APRESENTAÇÃO\nPlataforma eletrónica utilizada pela entidade adjudicante: VORTAL\nURL para Apresentação: https://community.vortal.biz/public/\nAdmissibilidade da apresentação de propostas variantes: Não autorizado\nPrazo para apresentação das propostas: 24-10-2025 17:00\nPrazo durante o qual os concorrentes são obrigados a manter as respetivas propostas: 90 dias a contar do termo do prazo para a apresentação das propostas\nIndicação de Subcontratação na Proposta: Inexistência de indicação de subcontratação\n\n14 - PRESTAÇÃO DE CAUÇÃO\nPrestação de caução: Não\n\n15 - FORNECIMENTO DAS PEÇAS DO CONCURSO, APRESENTAÇÃO DE PEDIDOS DE PARTICIPAÇÃO E APRESENTAÇÃO DAS PROPOSTAS\nLink para acesso às peças do concurso (URL): https://community.vortal.biz/Public/public-tender-documents/NHlNU3NrdytKcC9qTWRJRHA5NTBOYml3SXlhanh1UU9GVEhWRHdqRjRoNXIzS2J1NzFsZ0VQbFJWODhReXVIby9mTmlUYWZ6L3NBdXVtcFNRWlRpcFE9PSloK2Uz\n\n20 - OUTROS REQUISITOS\nInformação sobre contratos reservados. Aplica-se a contratos reservados (54º-A)? Não\n\n21 - CRITÉRIO DE ADJUDICAÇÃO\nMultifator: Não\nMonofator:\nNome: Preço\n\n24 - CONDIÇÕES DO CONTRATO\nFaturação Eletrónica: Permitido\nObrigação de Subcontratação:\nCódigo da Obrigação de Subcontratação: Não é aplicável nenhuma obrigação de subcontratação.\n\n25 - COMPRA PÚBLICA ESTRATÉGICA\nCompra Pública Estratégica: Inexistência de contratação pública estratégica\n\n26 - INFORMAÇÕES ADICIONAIS\nContrato adequado para PME: Sim\nCobertura ACP (Acordo dos Contratos Públicos da Organização Mundial do Comércio): Não\n\n27 - IDENTIFICAÇÃO E CONTACTOS DO ÓRGÃO DE RECURSOS ADMINISTRATIVOS\nDesignação: Conselho de Administração da Unidade Local de Saúde de Coimbra, E.P.E.\nEndereço: Praceta Prof. Mota Pinto\nCódigo postal: 3004-561\nLocalidade: Coimbra\nTelefone: +351 239400400\nFax: +351 239400400\nEndereço eletrónico: casec@ulscoimbra.min-saude.pt\n\n28 - IDENTIFICAÇÃO DO(S) AUTOR(ES) DE ANÚNCIO\nNome: Rui Gonçalves Silvestre\nCargo: Técnico Superior\n419610524",
    "nipc": "510103448",
    "distrito": "Coimbra",
    "concelho": "Coimbra",
    "freguesia": "Todas",
    "site": "https://www.chuc.min-saude.pt",
    "email": "ana.rosete@ulscoimbra.min-saude.pt",
    "designacao_contrato": "Empreitada de Remodelação do Átrio das Consultas Externas para Área de Contingência do Serviço de Urgência, no Polo HUC da Unidade Local de Saúde de Coimbra, E.P.E.",
    "descricao": "Empreitada de Remodelação do Átrio das Consultas Externas para Área de Contingência do Serviço de Urgência, no Polo HUC da Unidade Local de Saúde de Coimbra, E.P.E.",
    "preco_base": "230.825,71 EUR",
    "prazo_execucao": "75 DIAS",
    "prazo_apresentacao_propostas": "24-10-2025 17:00",
    "fundos_eu": "Não",
    "plataforma_eletronica": "VORTAL",
    "url_procedimento": "https://community.vortal.biz/public/",
    "autor_nome": "Rui Gonçalves Silvestre",
    "autor_cargo": "Técnico Superior"
  },
  {
    "numero_procedimento": "N/A",
    "entidade": "AnÃºncio de procedimento  n.Âº 26044/2025  -  DiÃ¡rio da RepÃºblica n.Âº 191/2025, SÃ©rie II de 2025-10-03",
    "link": "https://diariodarepublica.pt/dr/detalhe/contrato-publico/26044-937877812"
  },
  {
    "numero_procedimento": "N/A",
    "entidade": "AnÃºncio de procedimento  n.Âº 26045/2025  -  DiÃ¡rio da RepÃºblica n.Âº 191/2025, SÃ©rie II de 2025-10-03",
    "link": "https://diariodarepublica.pt/dr/detalhe/contrato-publico/26045-937877813"
  },
  {
    "numero_procedimento": "N/A",
    "entidade": "AnÃºncio de procedimento  n.Âº 26046/2025  -  DiÃ¡rio da RepÃºblica n.Âº 191/2025, SÃ©rie II de 2025-10-03",
    "link": "https://diariodarepublica.pt/dr/detalhe/contrato-publico/26046-937877814"
  },
  {
    "numero_procedimento": "N/A",
    "entidade": "AnÃºncio de procedimento  n.Âº 26047/2025  -  DiÃ¡rio da RepÃºblica n.Âº 191/2025, SÃ©rie II de 2025-10-03",
    "link": "https://diariodarepublica.pt/dr/detalhe/contrato-publico/26047-937877815"
  },
  {
    "numero_procedimento": "N/A",
    "entidade": "AnÃºncio de procedimento  n.Âº 26049/2025  -  DiÃ¡rio da RepÃºblica n.Âº 191/2025, SÃ©rie II de 2025-10-03",
    "link": "https://diariodarepublica.pt/dr/detalhe/contrato-publico/26049-937877818"
  },
  {
    "numero_procedimento": "N/A",
    "entidade": "Câmara Municipal do Funchal",
    "link": "https://diariodarepublica.pt/dr/detalhe/contrato-publico/26051-937877819",
    "detalhes_completos": "Alteração do Anúncio de procedimento n.º 24282/2025, de 2025-09-15, com o ID 419524251\n\n1 - IDENTIFICAÇÃO E CONTACTOS DA ENTIDADE ADJUDICANTE\nDesignação da entidade adjudicante: Câmara Municipal do Funchal\nNIPC: 511217315\nServiço/Órgão/Pessoa de contacto: Divisão de Contratação Pública\nEndereço: Praça do Município\nCódigo postal: 9004-512\nLocalidade: Funchal\nPaís: Portugal\nNUT III: PT300\nDistrito: Região Autónoma da Madeira\nConcelho: Funchal\nFreguesia: Freguesia de Sé (Funchal)\nTelefone: 291211000\nFax: 291211000\nEndereço da Entidade (URL): www.acingov.pt\nEndereço Eletrónico: dcpa@funchal.pt\neDelivery Gateway (URL): https://www.acingov.pt\nFunção da Organização: Adquirente\nSubfunção da Organização: Organização cujo orçamento é utilizado para pagar o contrato; Organização que executa o pagamento; Organização que fornece informações adicionais sobre o processo de adjudicação; Organização responsável pelo tratamento das propostas; Organização que recebe as propostas; Organização que trata os pedidos de participação; Organização que recebe pedidos de participação; Organização que assina o contrato\nNorma jurídica da Entidade Adjudicante: Organismo de direito público\nÁrea de atividade da Autoridade Adjudicante: Serviços públicos das administrações públicas\n\n2 - JORNAL OFICIAL DA UNIÃO EUROPEIA\nO procedimento a que este anúncio diz respeito também é publicitado no Jornal Oficial da União Europeia? Sim\n\n3 - AVISO\nModelo de Anúncio: Concurso público\nData de Envio do Anúncio: 01-10-2025\n\n5 - PROCESSO\nTipo de Procedimento: Concurso público\nPreço base do procedimento: Sim\nValor do preço base do procedimento: 498.294,89 EUR\nProcedimento com lotes? Sim\nNº Máx. de Lotes Autorizado: 9\nNúmero máximo de lotes que podem ser adjudicados a um concorrente: 9\n\n6 - OBJETO DO CONTRATO\nNúmero de referência interna: 77/DCP/2025\nDesignação do contrato: Prestação de Serviços de Seguros do Município do Funchal para 2026\nDescrição: Prestação de Serviços de Seguros do Município do Funchal para 2025\nOpções: Não\nTipo de Contrato Principal: Aquisição de Serviços\nTipo de Contrato: Aquisição de Serviços\nClassificação CPV (Vocabulário Comum para os Contratos Públicos)\nObjeto principal\nVocabulário Principal: 66510000\nPreço base s/IVA: 498.294,89 EUR\nLotes: \nNº: LOT-0001\nDescrição do Lote: Ramo Automóvel\nPreço base s/IVA: 96.896,23 EUR\nClassificação CPV (Vocabulário Comum para os Contratos Públicos)\nObjeto principal\nVocabulário Principal: 66516100\nNº: LOT-0002\nDescrição do Lote: Multirriscos\nPreço base s/IVA: 37.124,10 EUR\nClassificação CPV (Vocabulário Comum para os Contratos Públicos)\nObjeto principal\nVocabulário Principal: 66515200\nNº: LOT-0003\nDescrição do Lote: Bombeiros Sapadores (BS-CGA)\nPreço base s/IVA: 77.860,00 EUR\nClassificação CPV (Vocabulário Comum para os Contratos Públicos)\nObjeto principal\nVocabulário Principal: 66512100\nNº: LOT-0004\nDescrição do Lote: Acidentes de trabalho\nPreço base s/IVA: 251.042,55 EUR\nClassificação CPV (Vocabulário Comum para os Contratos Públicos)\nObjeto principal\nVocabulário Principal: 66512100\nNº: LOT-0005\nDescrição do Lote: Responsabilidade Ambiental\nPreço base s/IVA: 2.880,00 EUR\nClassificação CPV (Vocabulário Comum para os Contratos Públicos)\nObjeto principal\nVocabulário Principal: 66516000\nNº: LOT-0006\nDescrição do Lote: Bombeiros Sapadores e Voluntários\nPreço base s/IVA: 12.994,04 EUR\nClassificação CPV (Vocabulário Comum para os Contratos Públicos)\nObjeto principal\nVocabulário Principal: 66512100\nNº: LOT-0007\nDescrição do Lote: Trabalhadores Parques de Estacionamento\nPreço base s/IVA: 3.402,00 EUR\nClassificação CPV (Vocabulário Comum para os Contratos Públicos)\nObjeto principal\nVocabulário Principal: 66512100\nNº: LOT-0008\nDescrição do Lote: Postos de Carregamentos para veículos elétricos\nPreço base s/IVA: 1.200,00 EUR\nClassificação CPV (Vocabulário Comum para os Contratos Públicos)\nObjeto principal\nVocabulário Principal: 66516000\nNº: LOT-0009\nDescrição do Lote: Apólices Diversas\nPreço base s/IVA: 14.895,97 EUR\nClassificação CPV (Vocabulário Comum para os Contratos Públicos)\nObjeto principal\nVocabulário Principal: 66510000\n\n7 - INDICAÇÕES ADICIONAIS\nO contrato envolve aquisição conjunta (satisfação de várias entidades)? Não\nO contrato é adjudicado por uma central de compras? Não\n\n8 - TÉCNICAS\nO concurso destina-se à celebração de um acordo-quadro? Inexistência de acordo-quadro\nÉ utilizado um leilão eletrónico? Não\nÉ adotada uma fase de negociação? Não\nSistema de Aquisição Dinâmico: Inexistência de sistema de aquisição dinâmico\n\n9 - LOCAL DA EXECUÇÃO DO CONTRATO\nLOCAL DA EXECUÇÃO DO CONTRATO (PROCEDIMENTO)\nPaís: Portugal\nNUT III: PT300\nLocalidade: Freguesia de Sé (Funchal)\nDistrito: Região Autónoma da Madeira\nConcelho: Funchal\nFreguesia: Freguesia de Sé (Funchal)\nLOCAL DA EXECUÇÃO DO CONTRATO (LOTE)\nIdentificador do Lote: LOT-0001; LOT-0002; LOT-0003; LOT-0004; LOT-0005; LOT-0006; LOT-0007; LOT-0008; LOT-0009\nPaís: Portugal\nNUT III: PT300\nLocalidade: Freguesia de Sé (Funchal)\nDistrito: Região Autónoma da Madeira\nConcelho: Funchal\nFreguesia: Freguesia de Sé (Funchal)\n\n10 - PRAZO DE EXECUÇÃO DO CONTRATO\nIdentificador do Lote: LOT-0001; LOT-0002; LOT-0003; LOT-0004; LOT-0005; LOT-0006; LOT-0007; LOT-0008; LOT-0009\nPrazo de execução do contrato: 1 ANOS\nPrevisão de renovações: Não\n\n11 - FUNDOS EU\nIdentificador do Lote: LOT-0001; LOT-0002; LOT-0003; LOT-0004; LOT-0005; LOT-0006; LOT-0007; LOT-0008; LOT-0009\nTêm fundos EU? Não\n\n12 - DOCUMENTOS DE HABILITAÇÃO\nHabilitação para o exercício da atividade profissional: Sim\nTipo: Certificado\nDescrição: Documento comprovativo da titularidade das habilitações legalmente exigidas para a prestação dos serviços dos serviços em causa, nomeadamente, seguradoras ou mediadores (conforme o caso) autorizadas pelo Instituto de Seguros de Portugal para o exercício da atividade de seguros, designadamente, com certificado de registo na ASF  Autoridade de Supervisão de Seguros e Fundos de Pensões.\n\n13 - CONDIÇÕES DE APRESENTAÇÃO\nPlataforma eletrónica utilizada pela entidade adjudicante: ACIN\nURL para Apresentação: https://www.acingov.pt\nAdmissibilidade da apresentação de propostas variantes: Não autorizado\nPrazo para apresentação das propostas: 27-10-2025 23:59\nPrazo durante o qual os concorrentes são obrigados a manter as respetivas propostas: 120 dias a contar do termo do prazo para a apresentação das propostas\nApresentação de Catálogo Eletrónico: Permitido\nIndicação de Subcontratação na Proposta: Inexistência de indicação de subcontratação\n\n14 - PRESTAÇÃO DE CAUÇÃO\nPrestação de caução: Não\n\n15 - FORNECIMENTO DAS PEÇAS DO CONCURSO, APRESENTAÇÃO DE PEDIDOS DE PARTICIPAÇÃO E APRESENTAÇÃO DAS PROPOSTAS\nLink para acesso às peças do concurso (URL): https://www.acingov.pt/acingovprod/2/zonaPublica/zona_publica_c/donwloadProcedurePiece/OTc2OTIz\n\n20 - OUTROS REQUISITOS\nIdentificador do Lote: LOT-0001; LOT-0002; LOT-0003; LOT-0004; LOT-0005; LOT-0006; LOT-0007; LOT-0008; LOT-0009\nInformação sobre contratos reservados. Aplica-se a contratos reservados (54º-A)? Não\n\n21 - CRITÉRIO DE ADJUDICAÇÃO\nO Critério de adjudicação é diferenciado por lote? Não\nMultifator: Não\nMonofator:\nNome: Preço\n\n24 - CONDIÇÕES DO CONTRATO\nIdentificador do Lote: LOT-0001; LOT-0002; LOT-0003; LOT-0004; LOT-0005; LOT-0006; LOT-0007; LOT-0008; LOT-0009\nFaturação Eletrónica: Permitido\nObrigação de Subcontratação:\nCódigo da Obrigação de Subcontratação: Não é aplicável nenhuma obrigação de subcontratação.\n\n25 - COMPRA PÚBLICA ESTRATÉGICA\nCompra Pública Estratégica: Inexistência de contratação pública estratégica\n\n26 - INFORMAÇÕES ADICIONAIS\nIdentificador do Lote: LOT-0002; LOT-0005\nContrato adequado para PME: Não\nCobertura ACP (Acordo dos Contratos Públicos da Organização Mundial do Comércio): Não\nIdentificador do Lote: LOT-0001; LOT-0003; LOT-0004; LOT-0006; LOT-0007; LOT-0008; LOT-0009\nContrato adequado para PME: Não\nCobertura ACP (Acordo dos Contratos Públicos da Organização Mundial do Comércio): Não\n\n27 - IDENTIFICAÇÃO E CONTACTOS DO ÓRGÃO DE RECURSOS ADMINISTRATIVOS\nDesignação: Júri\nEndereço: Praça do Município\nCódigo postal: 9004-512\nLocalidade: Funchal\nTelefone: 291211000\nFax: 291211000\nEndereço eletrónico: dcpa@funchal.pt\nPrazo de interposição do recurso: 10 dias\n\n28 - IDENTIFICAÇÃO DO(S) AUTOR(ES) DE ANÚNCIO\nNome: Ana Bracamonte\nCargo: Vereadora da Câmara Municipal do Funchal\n\n29 - ALTERAÇÃO\nMotivo da Alteração: Correção pelo eSender\nIdentificador da Versão do Anúncio a Alterar: 704f7800-f967-4b40-ae58-b097c2d3aece-01\nIdentificador das Secções Alteradas do Anúncio Anterior: Condições de Apresentação; Alteração\nDescrição das Alterações: Modificação do prazo para a apresentação de propostas\nAlteração dos Documentos do Concurso: Sim\nData de alteração dos documentos do concurso: 30-09-2025\n419598895",
    "nipc": "511217315",
    "distrito": "Região Autónoma da Madeira",
    "concelho": "Funchal",
    "freguesia": "Freguesia de Sé (Funchal)",
    "site": "www.acingov.pt",
    "email": "dcpa@funchal.pt",
    "designacao_contrato": "Prestação de Serviços de Seguros do Município do Funchal para 2026",
    "descricao": "Prestação de Serviços de Seguros do Município do Funchal para 2025",
    "preco_base": "498.294,89 EUR",
    "prazo_execucao": "1 ANOS",
    "prazo_apresentacao_propostas": "27-10-2025 23:59",
    "fundos_eu": "Não",
    "plataforma_eletronica": "ACIN",
    "url_procedimento": "https://www.acingov.pt",
    "autor_nome": "Ana Bracamonte",
    "autor_cargo": "Vereadora da Câmara Municipal do Funchal"
  },
  {
    "numero_procedimento": "N/A",
    "entidade": "AnÃºncio de procedimento  n.Âº 26053/2025  -  DiÃ¡rio da RepÃºblica n.Âº 191/2025, SÃ©rie II de 2025-10-03",
    "link": "https://diariodarepublica.pt/dr/detalhe/contrato-publico/26053-937877822"
  },
  {
    "numero_procedimento": "N/A",
    "entidade": "AGERE – Emp. Águas, Efluentes e Resíduos de Braga",
    "link": "https://diariodarepublica.pt/dr/detalhe/contrato-publico/26055-937877824",
    "detalhes_completos": "1 - IDENTIFICAÇÃO E CONTACTOS DA ENTIDADE ADJUDICANTE\nDesignação da entidade adjudicante: AGERE – Emp. Águas, Efluentes e Resíduos de Braga\nNIPC: 504807692\nEndereço: Praça Conde de Agrolongo, 115\nCódigo postal: 4700-312\nLocalidade: Braga\nPaís: Portugal\nNUT III: PT112\nDistrito: Braga\nConcelho: Braga\nFreguesia: Todas\nTelefone: 253205000\nFax: 253205075\nEndereço da Entidade (URL): www.agere.pt\nEndereço Eletrónico: agere@agere.pt\neDelivery Gateway (URL): https://community.vortal.biz/public/\nFunção da Organização: Adquirente\nNorma jurídica da Entidade Adjudicante: Empresa pública\nÁrea de atividade da Entidade Adjudicante: Serviços urbanos de caminho de ferro, de elétricos, de tróleis ou de autocarros\n\n2 - JORNAL OFICIAL DA UNIÃO EUROPEIA\nO procedimento a que este anúncio diz respeito também é publicitado no Jornal Oficial da União Europeia? Sim\n\n3 - AVISO\nModelo de Anúncio: Concurso público\nData de Envio do Anúncio: 01-10-2025\n\n5 - PROCESSO\nTipo de Procedimento: Concurso público\nPreço base do procedimento: Sim\nValor do preço base do procedimento: 15.294.098,54 EUR\nProcedimento com lotes? Não\n\n6 - OBJETO DO CONTRATO\nNúmero de referência interna: CPI DC 08/2025\nDesignação do contrato: FORNECIMENTO, INSTALAÇÃO E MANUTENÇÃO DE REDE DE TELEMETRIA, SOFTWARE DE GESTÃO DO PARQUE DE CONTADORES E DA REDE A INSTALAR E FORNECIMENTO DE CONTADORES ULTRASSÓNICOS COM TELEMETRIA INCORPORADA\nDescrição: FORNECIMENTO, INSTALAÇÃO E MANUTENÇÃO DE REDE DE TELEMETRIA, SOFTWARE DE GESTÃO DO PARQUE DE CONTADORES E DA REDE A INSTALAR E FORNECIMENTO DE CONTADORES ULTRASSÓNICOS COM TELEMETRIA INCORPORADA\nOpções: Não\nTipo de Contrato Principal: Aquisição de Bens Móveis\nTipo de Contrato: Aquisição de Bens Móveis\nClassificação CPV (Vocabulário Comum para os Contratos Públicos)\nObjeto principal\nVocabulário Principal: 38421100\nPreço base s/IVA: 15.294.098,54 EUR\n\n7 - INDICAÇÕES ADICIONAIS\nO contrato envolve aquisição conjunta (satisfação de várias entidades)? Não\nO contrato é adjudicado por uma central de compras? Não\n\n8 - TÉCNICAS\nO concurso destina-se à celebração de um acordo-quadro? Inexistência de acordo-quadro\nÉ utilizado um leilão eletrónico? Não\nÉ adotada uma fase de negociação? Não\nSistema de Aquisição Dinâmico: Inexistência de sistema de aquisição dinâmico\n\n9 - LOCAL DA EXECUÇÃO DO CONTRATO\nLOCAL DA EXECUÇÃO DO CONTRATO (PROCEDIMENTO)\nPaís: Portugal\nNUT III: PT112\nLocalidade: Braga\nDistrito: Braga\nConcelho: Braga\nFreguesia: União das Freguesias de Braga (São José de São Lázaro e São João do Souto)\n\n10 - PRAZO DE EXECUÇÃO DO CONTRATO\nPrazo de execução do contrato: 162 MESES\nPrevisão de renovações: Não\n\n11 - FUNDOS EU\nTêm fundos EU? Não\n\n12 - DOCUMENTOS DE HABILITAÇÃO\nHabilitação para o exercício da atividade profissional: Não\n\n13 - CONDIÇÕES DE APRESENTAÇÃO\nPlataforma eletrónica utilizada pela entidade adjudicante: VORTAL\nURL para Apresentação: https://community.vortal.biz/public/\nAdmissibilidade da apresentação de propostas variantes: Não autorizado\nPrazo para apresentação das propostas: 03-11-2025 17:00\nPrazo durante o qual os concorrentes são obrigados a manter as respetivas propostas: 66 dias a contar do termo do prazo para a apresentação das propostas\nApresentação de Catálogo Eletrónico: Não autorizado\nIndicação de Subcontratação na Proposta: Inexistência de indicação de subcontratação\n\n14 - PRESTAÇÃO DE CAUÇÃO\nPrestação de caução: Sim\nPercentagem: 5%\nDescrição da Garantia Exigida: definido no Programa de Procedimentos \n\n15 - FORNECIMENTO DAS PEÇAS DO CONCURSO, APRESENTAÇÃO DE PEDIDOS DE PARTICIPAÇÃO E APRESENTAÇÃO DAS PROPOSTAS\nLink para acesso às peças do concurso (URL): https://community.vortal.biz/Public/public-tender-documents/YVFVTVFvbkVvSUcvcUVaaWcwYmZkbGhVUVFLYWN6UGxGbU1HTnhMRG90ZXBEbU1saHZUcVpEMnlYekE0RGlFSEs5YmxKSVplcTIwMnJkcWpDVGd2V0E9PW8pZHhz\n\n20 - OUTROS REQUISITOS\nInformação sobre contratos reservados. Aplica-se a contratos reservados (54º-A)? Não\n\n21 - CRITÉRIO DE ADJUDICAÇÃO\nMultifator: Sim\nFator: \nNome: Preço\nPonderação: 50%\nSubfatores: Sim\nSubfatores: \nNome: Fornecimento de Contadores Ultrassónicos com Telemetria incorporada\nPonderação : 50%; \nNome: Fornecimento, Instalação e Manutenção de Rede de Telemetria, Software de Gestão, Gestão de Leituras e supervisão do Parque de Contadores e Rede a Instalar\nPonderação : 50%; \nFator: \nNome: Qualidade\nPonderação: 45%\nSubfatores: Sim\nSubfatores: \nNome: Características Técnicas dos Contadores\nPonderação : 50%; \nNome: Caracteristicas Técnicas da Rede de Telemática\nPonderação : 20%; \nNome: Caracteristicas Técnicas do Software de Gestão\nPonderação : 20%; \nNome: Meios Afetos à Execução do Serviço\nPonderação : 10%; \nFator: \nNome: Qualidade\nPonderação: 5%\nSubfatores: Sim\nSubfatores: \nNome: Primeiro Fornecimento\nPonderação : 100%; \n\n24 - CONDIÇÕES DO CONTRATO\nFaturação Eletrónica: Permitido\nObrigação de Subcontratação:\nCódigo da Obrigação de Subcontratação: Não é aplicável nenhuma obrigação de subcontratação.\n\n25 - COMPRA PÚBLICA ESTRATÉGICA\nCompra Pública Estratégica: Inexistência de contratação pública estratégica\n\n26 - INFORMAÇÕES ADICIONAIS\nContrato adequado para PME: Sim\nCobertura ACP (Acordo dos Contratos Públicos da Organização Mundial do Comércio): Não\n\n27 - IDENTIFICAÇÃO E CONTACTOS DO ÓRGÃO DE RECURSOS ADMINISTRATIVOS\nDesignação: Conselho de Administração da AGERE EM\nEndereço: Praça Conde de Agrolongo nº115\nCódigo postal: 4700-312\nLocalidade: Braga\nTelefone: +351 253205001\nFax: +351 253205075\nEndereço eletrónico: administracao@agere.pt\n\n28 - IDENTIFICAÇÃO DO(S) AUTOR(ES) DE ANÚNCIO\nNome: Engª Paula Campos\nCargo: Administradora Executiva\n419600497",
    "nipc": "504807692",
    "distrito": "Braga",
    "concelho": "Braga",
    "freguesia": "Todas",
    "site": "www.agere.pt",
    "email": "agere@agere.pt",
    "designacao_contrato": "FORNECIMENTO, INSTALAÇÃO E MANUTENÇÃO DE REDE DE TELEMETRIA, SOFTWARE DE GESTÃO DO PARQUE DE CONTADORES E DA REDE A INSTALAR E FORNECIMENTO DE CONTADORES ULTRASSÓNICOS COM TELEMETRIA INCORPORADA",
    "descricao": "FORNECIMENTO, INSTALAÇÃO E MANUTENÇÃO DE REDE DE TELEMETRIA, SOFTWARE DE GESTÃO DO PARQUE DE CONTADORES E DA REDE A INSTALAR E FORNECIMENTO DE CONTADORES ULTRASSÓNICOS COM TELEMETRIA INCORPORADA",
    "preco_base": "15.294.098,54 EUR",
    "prazo_execucao": "162 MESES",
    "prazo_apresentacao_propostas": "03-11-2025 17:00",
    "fundos_eu": "Não",
    "plataforma_eletronica": "VORTAL",
    "url_procedimento": "https://community.vortal.biz/public/",
    "autor_nome": "Engª Paula Campos",
    "autor_cargo": "Administradora Executiva"
  },
  {
    "numero_procedimento": "N/A",
    "entidade": "AnÃºncio de procedimento  n.Âº 26056/2025  -  DiÃ¡rio da RepÃºblica n.Âº 191/2025, SÃ©rie II de 2025-10-03",
    "link": "https://diariodarepublica.pt/dr/detalhe/contrato-publico/26056-937877826"
  },
  {
    "numero_procedimento": "N/A",
    "entidade": "AnÃºncio de procedimento  n.Âº 26059/2025  -  DiÃ¡rio da RepÃºblica n.Âº 191/2025, SÃ©rie II de 2025-10-03",
    "link": "https://diariodarepublica.pt/dr/detalhe/contrato-publico/26059-937877828"
  },
  {
    "numero_procedimento": "N/A",
    "entidade": "AnÃºncio de procedimento  n.Âº 26060/2025  -  DiÃ¡rio da RepÃºblica n.Âº 191/2025, SÃ©rie II de 2025-10-03",
    "link": "https://diariodarepublica.pt/dr/detalhe/contrato-publico/26060-937877830"
  },
  {
    "numero_procedimento": "N/A",
    "entidade": "Docapesca - Portos e Lotas, S. A.",
    "link": "https://diariodarepublica.pt/dr/detalhe/contrato-publico/26062-937877831",
    "detalhes_completos": "1 - IDENTIFICAÇÃO E CONTACTOS DA ENTIDADE ADJUDICANTE\nDesignação da entidade adjudicante: Docapesca - Portos e Lotas, S. A.\nNIPC: 500086826\nEndereço: Av. Brasilia - Porta ES 7 - Pedrouços\nCódigo postal: 1400-038\nLocalidade: Lisboa\nPaís: Portugal\nNUT III: PT170\nDistrito: Lisboa\nConcelho: Lisboa\nFreguesia: Todas\nTelefone: 213936100\nFax: 213936101\nEndereço da Entidade (URL): www.docapesca.pt\nEndereço Eletrónico: docapesca@docapesca.pt\neDelivery Gateway (URL): https://community.vortal.biz/public/\nFunção da Organização: Adquirente\nNorma jurídica da Entidade Adjudicante: Autoridade da administração central\nÁrea de atividade da Entidade Adjudicante: Atividades portuárias\n\n2 - JORNAL OFICIAL DA UNIÃO EUROPEIA\nO procedimento a que este anúncio diz respeito também é publicitado no Jornal Oficial da União Europeia? Não\n\n3 - AVISO\nModelo de Anúncio: Concurso limitado por prévia qualificação\nData de Envio do Anúncio: 03-10-2025\n\n5 - PROCESSO\nTipo de Procedimento: Concurso limitado por prévia qualificação\nPreço base do procedimento: Sim\nValor do preço base do procedimento: 123.330,00 EUR\nProcedimento com lotes? Sim\nNº Máx. de Lotes Autorizado: 3\nNúmero máximo de lotes que podem ser adjudicados a um concorrente: 3\n\n6 - OBJETO DO CONTRATO\nNúmero de referência interna: DSM-1578-CL-2025\nDesignação do contrato: Manutenção preventiva e assistência técnica a instalações frigoríficas\nDescrição: Manutenção preventiva e assistência técnica a instalações frigoríficas\nTipo de Contrato Principal: Aquisição de Serviços\nTipo de Contrato: Aquisição de Serviços\nClassificação CPV (Vocabulário Comum para os Contratos Públicos)\nObjeto principal\nVocabulário Principal: 50730000\nPreço base s/IVA: 123.330,00 EUR\nLotes: \nNº: LOT-0001\nDescrição do Lote: Lote 1 - Norte\nPreço base s/IVA: 26.750,00 EUR\nClassificação CPV (Vocabulário Comum para os Contratos Públicos)\nObjeto principal\nVocabulário Principal: 50730000\nNº: LOT-0002\nDescrição do Lote: Lote 2 - Centro e Centro Sul\nPreço base s/IVA: 46.630,00 EUR\nClassificação CPV (Vocabulário Comum para os Contratos Públicos)\nObjeto principal\nVocabulário Principal: 50730000\nNº: LOT-0003\nDescrição do Lote: Lote 3 - Sul\nPreço base s/IVA: 49.950,00 EUR\nClassificação CPV (Vocabulário Comum para os Contratos Públicos)\nObjeto principal\nVocabulário Principal: 50730000\n\n7 - INDICAÇÕES ADICIONAIS\nO contrato envolve aquisição conjunta (satisfação de várias entidades)? Não\nO contrato é adjudicado por uma central de compras? Não\n\n8 - TÉCNICAS\nO concurso destina-se à celebração de um acordo-quadro? Inexistência de acordo-quadro\nÉ utilizado um leilão eletrónico? Não\nSistema de Aquisição Dinâmico: Inexistência de sistema de aquisição dinâmico\n\n9 - LOCAL DA EXECUÇÃO DO CONTRATO\nLOCAL DA EXECUÇÃO DO CONTRATO (PROCEDIMENTO)\nPaís: Portugal\nNUT III: PT170\nLocalidade: Lisboa\nDistrito: Lisboa\nConcelho: Lisboa\nFreguesia: Freguesia de Belém\nLOCAL DA EXECUÇÃO DO CONTRATO (LOTE)\nIdentificador do Lote: LOT-0001; LOT-0002; LOT-0003\nPaís: Portugal\nNUT III: PT170\nLocalidade: Lisboa\nDistrito: Lisboa\nConcelho: Lisboa\nFreguesia: Freguesia de Belém\n\n10 - PRAZO DE EXECUÇÃO DO CONTRATO\nIdentificador do Lote: LOT-0001; LOT-0002; LOT-0003\nPrazo de execução do contrato: 1 ANOS\nPrevisão de renovações: Sim\nIndicar número máximo de renovações: 1\nPrazo de renovações diferente do prazo inicial: Não\n\n11 - FUNDOS EU\nIdentificador do Lote: LOT-0001; LOT-0002; LOT-0003\nTêm fundos EU? Não\n\n12 - DOCUMENTOS DE HABILITAÇÃO\nHabilitação para o exercício da atividade profissional: Não\n\n13 - CONDIÇÕES DE APRESENTAÇÃO\nPlataforma eletrónica utilizada pela entidade adjudicante: VORTAL\nURL para Apresentação: https://community.vortal.biz/public/\nAdmissibilidade da apresentação de propostas variantes: Não autorizado\nPrazo para apresentação das candidaturas: 13-10-2025 18:00\nRequisitos mínimos \nRequisitos mínimos de capacidade técnica: Conforme as peças do procedimento\nRequisitos mínimos de capacidade financeira: Conforme as peças do procedimento\nPrazo durante o qual os concorrentes são obrigados a manter as respetivas propostas: 66 dias a contar do termo do prazo para a apresentação das propostas\nIndicação de Subcontratação na Proposta: Inexistência de indicação de subcontratação\n\n14 - PRESTAÇÃO DE CAUÇÃO\nPrestação de caução: Não\n\n15 - FORNECIMENTO DAS PEÇAS DO CONCURSO, APRESENTAÇÃO DE PEDIDOS DE PARTICIPAÇÃO E APRESENTAÇÃO DAS PROPOSTAS\nLink para acesso às peças do concurso (URL): https://community.vortal.biz/Public/public-tender-documents/RzcxTTI0MGZibmdpNHh2OGMraFpLMDVIOVVhOXR4Yk5ZSytjcVZkNVhFdkN2Y1lKUTNOdzkyUTBWSWlBTWsxUXVMZTRVSXRLTktkd0dweCt1YjhXanc9PUdkdm5a\n\n20 - OUTROS REQUISITOS\nIdentificador do Lote: LOT-0001; LOT-0002; LOT-0003\nInformação sobre contratos reservados. Aplica-se a contratos reservados (54º-A)? Não\n\n21 - CRITÉRIO DE ADJUDICAÇÃO\nO Critério de adjudicação é diferenciado por lote? Não\nMultifator: Sim\nFator: \nNome: Preço\nPonderação: 30%\nSubfatores: Não\nFator: \nNome: Qualidade\nPonderação: 70%\nSubfatores: Não\n\n24 - CONDIÇÕES DO CONTRATO\nIdentificador do Lote: LOT-0001; LOT-0002; LOT-0003\nFaturação Eletrónica: Permitido\nObrigação de Subcontratação:\nCódigo da Obrigação de Subcontratação: Não é aplicável nenhuma obrigação de subcontratação.\n\n25 - COMPRA PÚBLICA ESTRATÉGICA\nCompra Pública Estratégica: Inexistência de contratação pública estratégica\n\n26 - INFORMAÇÕES ADICIONAIS\nIdentificador do Lote: LOT-0001; LOT-0002; LOT-0003\nContrato adequado para PME: Sim\nCobertura ACP (Acordo dos Contratos Públicos da Organização Mundial do Comércio): Não\n\n27 - IDENTIFICAÇÃO E CONTACTOS DO ÓRGÃO DE RECURSOS ADMINISTRATIVOS\nDesignação: Direção de Segurança e Manutenção\nEndereço: Avenida Brasília, ES 7\nCódigo postal: 1400-038\nLocalidade: Lisboa\nTelefone: +351 213936100\nFax: +351 213936100\nEndereço eletrónico: dsm.cp@docapesca.pt\n\n28 - IDENTIFICAÇÃO DO(S) AUTOR(ES) DE ANÚNCIO\nNome: Afonso Gonçalves da Silva Oliveira\nCargo: Presidente do Conselho de Administração\n419610127",
    "nipc": "500086826",
    "distrito": "Lisboa",
    "concelho": "Lisboa",
    "freguesia": "Todas",
    "site": "www.docapesca.pt",
    "email": "docapesca@docapesca.pt",
    "designacao_contrato": "Manutenção preventiva e assistência técnica a instalações frigoríficas",
    "descricao": "Manutenção preventiva e assistência técnica a instalações frigoríficas",
    "preco_base": "123.330,00 EUR",
    "prazo_execucao": "1 ANOS",
    "prazo_apresentacao_propostas": null,
    "fundos_eu": "Não",
    "plataforma_eletronica": "VORTAL",
    "url_procedimento": "https://community.vortal.biz/public/",
    "autor_nome": "Afonso Gonçalves da Silva Oliveira",
    "autor_cargo": "Presidente do Conselho de Administração"
  },
  {
    "numero_procedimento": "N/A",
    "entidade": "Município de Braga",
    "link": "https://diariodarepublica.pt/dr/detalhe/contrato-publico/26065-937877835",
    "detalhes_completos": "Alteração do Anúncio de procedimento n.º 25382/2025, de 2025-09-26, com o ID 419571159\n\n1 - IDENTIFICAÇÃO E CONTACTOS DA ENTIDADE ADJUDICANTE\nDesignação da entidade adjudicante: Município de Braga\nNIPC: 506901173\nEndereço: Praça do Municípal\nCódigo postal: 4700-435\nLocalidade: Braga\nPaís: Portugal\nNUT III: PT112\nDistrito: Braga\nConcelho: Braga\nFreguesia: União das Freguesias de Braga (Maximinos, Sé e Cividade)\nTelefone: 253616060\nFax: 253203151\nEndereço da Entidade (URL): www.cm-braga.pt\nEndereço Eletrónico: contratacao.publica@cm-braga.pt\neDelivery Gateway (URL): https://community.vortal.biz/public/\nFunção da Organização: Adquirente\nNorma jurídica da Entidade Adjudicante: Autoridade local\nÁrea de atividade da Autoridade Adjudicante: Serviços públicos das administrações públicas\n\n2 - JORNAL OFICIAL DA UNIÃO EUROPEIA\nO procedimento a que este anúncio diz respeito também é publicitado no Jornal Oficial da União Europeia? Sim\n\n3 - AVISO\nModelo de Anúncio: Concurso público\nData de Envio do Anúncio: 01-10-2025\n\n5 - PROCESSO\nTipo de Procedimento: Concurso público\nPreço base do procedimento: Sim\nValor do preço base do procedimento: 13.529.300,00 EUR\nProcedimento com lotes? Não\n\n6 - OBJETO DO CONTRATO\nNúmero de referência interna: CPE.20.25.DMOSM \nDesignação do contrato: CPE.20.25.DMOSM_\"CINETEATRO SÃO GERALDO, BRAGA MEDIA ARTS\".                                                                                                                \nDescrição: CPE.20.25.DMOSM_\"CINETEATRO SÃO GERALDO, BRAGA MEDIA ARTS\".   \nOpções: Não\nTipo de Contrato Principal: Empreitada de Obras Públicas\nTipo de Contrato: Empreitada de Obras Públicas\nClassificação CPV (Vocabulário Comum para os Contratos Públicos)\nObjeto principal\nVocabulário Principal: 45453000\nPreço base s/IVA: 13.529.300,00 EUR\n\n7 - INDICAÇÕES ADICIONAIS\nO contrato envolve aquisição conjunta (satisfação de várias entidades)? Não\nO contrato é adjudicado por uma central de compras? Não\n\n8 - TÉCNICAS\nO concurso destina-se à celebração de um acordo-quadro? Inexistência de acordo-quadro\nÉ utilizado um leilão eletrónico? Não\nÉ adotada uma fase de negociação? Não\nSistema de Aquisição Dinâmico: Inexistência de sistema de aquisição dinâmico\n\n9 - LOCAL DA EXECUÇÃO DO CONTRATO\nLOCAL DA EXECUÇÃO DO CONTRATO (PROCEDIMENTO)\nPaís: Portugal\nNUT III: PT112\nLocalidade: Braga\nDistrito: Braga\nConcelho: Braga\nFreguesia: Todas\n\n10 - PRAZO DE EXECUÇÃO DO CONTRATO\nPrazo de execução do contrato: 730 DIAS\nPrevisão de renovações: Não\n\n11 - FUNDOS EU\nTêm fundos EU? Sim\n\n12 - DOCUMENTOS DE HABILITAÇÃO\nHabilitação para o exercício da atividade profissional: Não\n\n13 - CONDIÇÕES DE APRESENTAÇÃO\nPlataforma eletrónica utilizada pela entidade adjudicante: VORTAL\nURL para Apresentação: https://community.vortal.biz/public/\nAdmissibilidade da apresentação de propostas variantes: Não autorizado\nPrazo para apresentação das propostas: 20-11-2025 18:00\nPrazo durante o qual os concorrentes são obrigados a manter as respetivas propostas: 120 dias a contar do termo do prazo para a apresentação das propostas\nApresentação de Catálogo Eletrónico: Permitido\nIndicação de Subcontratação na Proposta: Inexistência de indicação de subcontratação\n\n14 - PRESTAÇÃO DE CAUÇÃO\nPrestação de caução: Sim\nPercentagem: 5%\nDescrição da Garantia Exigida: De acordo com o artigo 24.º do Programa do Concurso\n\n15 - FORNECIMENTO DAS PEÇAS DO CONCURSO, APRESENTAÇÃO DE PEDIDOS DE PARTICIPAÇÃO E APRESENTAÇÃO DAS PROPOSTAS\nLink para acesso às peças do concurso (URL): https://community.vortal.biz/Public/public-tender-documents/UHgybzZLSld4UnN3WGVxdllPQlJZbm1HYVBXTU8wYWlXTWM5VmhBdjBrempNZWJLWmN6dW03ZGtkc1g2TjlQdXhDY2tGU2MzSC9WVlpXdVJ6d0hEaWc9PVBfVkNk\n\n20 - OUTROS REQUISITOS\nInformação sobre contratos reservados. Aplica-se a contratos reservados (54º-A)? Não\n\n21 - CRITÉRIO DE ADJUDICAÇÃO\nMultifator: Sim\nFator: \nNome: Preço\nPonderação: 70%\nSubfatores: Não\nFator: \nNome: Outros\nOutro Nome: Prazo\nPonderação: 30%\nSubfatores: Não\n\n24 - CONDIÇÕES DO CONTRATO\nFaturação Eletrónica: Permitido\nObrigação de Subcontratação:\nCódigo da Obrigação de Subcontratação: Não é aplicável nenhuma obrigação de subcontratação.\n\n25 - COMPRA PÚBLICA ESTRATÉGICA\nCompra Pública Estratégica: Inexistência de contratação pública estratégica\n\n26 - INFORMAÇÕES ADICIONAIS\nContrato adequado para PME: Sim\nCobertura ACP (Acordo dos Contratos Públicos da Organização Mundial do Comércio): Não\n\n27 - IDENTIFICAÇÃO E CONTACTOS DO ÓRGÃO DE RECURSOS ADMINISTRATIVOS\nDesignação: Presidente da Câmara Municipal de Braga\nEndereço: Praça Municipal\nCódigo postal: 4700-435\nLocalidade: Braga\nTelefone: +351 253616060\nFax: +351 253203151\nEndereço eletrónico: contratacao.empreitadas@cm-braga.pt\n\n28 - IDENTIFICAÇÃO DO(S) AUTOR(ES) DE ANÚNCIO\nNome: Valéria de Araújo Borges\nCargo: Chefe da Unidade de Apoio à Contratação\n\n29 - ALTERAÇÃO\nMotivo da Alteração: Informações agora disponíveis\nIdentificador da Versão do Anúncio a Alterar: c1e98523-f6b5-49fc-ba5c-0f4435557656-01\nIdentificador das Secções Alteradas do Anúncio Anterior: Condições de Apresentação\nDescrição das Alterações: Prorrogação do prazo até dia 20/11/2025.\nAlteração dos Documentos do Concurso: Não\n419594999",
    "nipc": "506901173",
    "distrito": "Braga",
    "concelho": "Braga",
    "freguesia": "União das Freguesias de Braga (Maximinos, Sé e Cividade)",
    "site": "www.cm-braga.pt",
    "email": "contratacao.publica@cm-braga.pt",
    "designacao_contrato": "CPE.20.25.DMOSM_\"CINETEATRO SÃO GERALDO, BRAGA MEDIA ARTS\".",
    "descricao": "CPE.20.25.DMOSM_\"CINETEATRO SÃO GERALDO, BRAGA MEDIA ARTS\".",
    "preco_base": "13.529.300,00 EUR",
    "prazo_execucao": "730 DIAS",
    "prazo_apresentacao_propostas": "20-11-2025 18:00",
    "fundos_eu": "Sim",
    "plataforma_eletronica": "VORTAL",
    "url_procedimento": "https://community.vortal.biz/public/",
    "autor_nome": "Valéria de Araújo Borges",
    "autor_cargo": "Chefe da Unidade de Apoio à Contratação"
  },
  {
    "numero_procedimento": "N/A",
    "entidade": "Escola Secundária José Régio, Vila do Conde",
    "link": "https://diariodarepublica.pt/dr/detalhe/contrato-publico/26068-937877836",
    "detalhes_completos": "Alteração do Anúncio de procedimento n.º 23426/2025, de 2025-09-03, com o ID 419488012\n\n1 - IDENTIFICAÇÃO E CONTACTOS DA ENTIDADE ADJUDICANTE\nDesignação da entidade adjudicante: Escola Secundária José Régio, Vila do Conde\nNIPC: 600013804\nEndereço: Alameda Afonso Betote\nCódigo postal: 4480-794\nLocalidade: Área Metropolitana do Porto\nPaís: Portugal\nNUT III: PT11A\nDistrito: Porto\nConcelho: Porto\nFreguesia: Todas\nTelefone: 252640400\nFax: 252640400\nEndereço da Entidade (URL): https://www.esc-joseregio.pt/\nEndereço Eletrónico: direcao@oges.esc-joseregio.pt\neDelivery Gateway (URL): https://community.vortal.biz/public/\nFunção da Organização: Adquirente\nNorma jurídica da Entidade Adjudicante: Organismo de direito público\nÁrea de atividade da Autoridade Adjudicante: Educação\n\n2 - JORNAL OFICIAL DA UNIÃO EUROPEIA\nO procedimento a que este anúncio diz respeito também é publicitado no Jornal Oficial da União Europeia? Sim\n\n3 - AVISO\nModelo de Anúncio: Concurso público\nData de Envio do Anúncio: 01-10-2025\n\n5 - PROCESSO\nTipo de Procedimento: Concurso público\nPreço base do procedimento: Sim\nValor do preço base do procedimento: 1.607.793,45 EUR\nProcedimento com lotes? Sim\nNº Máx. de Lotes Autorizado: 2\nNúmero máximo de lotes que podem ser adjudicados a um concorrente: 2\n\n6 - OBJETO DO CONTRATO\nNúmero de referência interna: CP 001/2025\nDesignação do contrato: Aquisição de Bens no âmbito do Centro Tecnológico Especializado Industrial\nDescrição: Aquisição de Bens no âmbito do Centro Tecnológico Especializado Industrial da Escola Secundária José Régio\nOpções: Não\nTipo de Contrato Principal: Aquisição de Bens Móveis\nTipo de Contrato: Aquisição de Bens Móveis\nClassificação CPV (Vocabulário Comum para os Contratos Públicos)\nObjeto principal\nVocabulário Principal: 30200000\nPreço base s/IVA: 1.434.016,00 EUR\nObjeto Complementar\nVocabulário Principal: 39160000\nPreço base s/IVA: 173.777,45 EUR\nLotes: \nNº: LOT-0001\nDescrição do Lote: Lote 1\nPreço base s/IVA: 173.777,45 EUR\nClassificação CPV (Vocabulário Comum para os Contratos Públicos)\nObjeto principal\nVocabulário Principal: 30200000\nObjeto Complementar\nVocabulário Principal: 39160000\nNº: LOT-0002\nDescrição do Lote: Lote 2\nPreço base s/IVA: 1.434.016,00 EUR\nClassificação CPV (Vocabulário Comum para os Contratos Públicos)\nObjeto principal\nVocabulário Principal: 30200000\nObjeto Complementar\nVocabulário Principal: 39160000\n\n7 - INDICAÇÕES ADICIONAIS\nO contrato envolve aquisição conjunta (satisfação de várias entidades)? Não\nO contrato é adjudicado por uma central de compras? Não\n\n8 - TÉCNICAS\nO concurso destina-se à celebração de um acordo-quadro? Inexistência de acordo-quadro\nÉ utilizado um leilão eletrónico? Não\nÉ adotada uma fase de negociação? Não\nSistema de Aquisição Dinâmico: Inexistência de sistema de aquisição dinâmico\n\n9 - LOCAL DA EXECUÇÃO DO CONTRATO\nLOCAL DA EXECUÇÃO DO CONTRATO (PROCEDIMENTO)\nPaís: Portugal\nNUT III: PT11A\nLocalidade: Área Metropolitana do Porto\nDistrito: Porto\nConcelho: Vila do Conde\nFreguesia: Todas\nLOCAL DA EXECUÇÃO DO CONTRATO (LOTE)\nIdentificador do Lote: LOT-0001; LOT-0002\nPaís: Portugal\nNUT III: PT11A\nLocalidade: Área Metropolitana do Porto\nDistrito: Porto\nConcelho: Vila do Conde\nFreguesia: Todas\n\n10 - PRAZO DE EXECUÇÃO DO CONTRATO\nIdentificador do Lote: LOT-0001; LOT-0002\nPrazo de execução do contrato: 2 MESES\nPrevisão de renovações: Não\n\n11 - FUNDOS EU\nIdentificador do Lote: LOT-0001; LOT-0002\nTêm fundos EU? Sim\n\n12 - DOCUMENTOS DE HABILITAÇÃO\nHabilitação para o exercício da atividade profissional: Não\n\n13 - CONDIÇÕES DE APRESENTAÇÃO\nPlataforma eletrónica utilizada pela entidade adjudicante: VORTAL\nURL para Apresentação: https://community.vortal.biz/public/\nAdmissibilidade da apresentação de propostas variantes: Não autorizado\nPrazo para apresentação das propostas: 02-10-2025 18:00\nPrazo durante o qual os concorrentes são obrigados a manter as respetivas propostas: 66 dias a contar do termo do prazo para a apresentação das propostas\nApresentação de Catálogo Eletrónico: Permitido\nIndicação de Subcontratação na Proposta: Inexistência de indicação de subcontratação\n\n14 - PRESTAÇÃO DE CAUÇÃO\nPrestação de caução: Sim\nPercentagem: 5%\nDescrição da Garantia Exigida: prestada por depósito em dinheiro ou em títulos emitidos ou garantidos pelo Estado, ou mediante garantia bancária ou seguro-caução, nos termos definidos no artigo 90.º do CCP, devendo ser adotado, para o efeito, um dos modelos do Anexo VII.\n\n15 - FORNECIMENTO DAS PEÇAS DO CONCURSO, APRESENTAÇÃO DE PEDIDOS DE PARTICIPAÇÃO E APRESENTAÇÃO DAS PROPOSTAS\nLink para acesso às peças do concurso (URL): https://community.vortal.biz/Public/public-tender-documents/Qmd0bWY1WlpZclQ2b1RneE9wd0ZGcml2YXRUY3g4VUhsWmh4UjdvUUZMWGo2UnZsTHhVM1hnODNBbnZGSnV2Qzgrck5obDZVMSt5TE05aXBvTTVoSUE9PVBeR1FW\n\n20 - OUTROS REQUISITOS\nIdentificador do Lote: LOT-0001; LOT-0002\nInformação sobre contratos reservados. Aplica-se a contratos reservados (54º-A)? Não\n\n21 - CRITÉRIO DE ADJUDICAÇÃO\nO Critério de adjudicação é diferenciado por lote? Sim\nIdentificador do lote: LOT-0001\nMultifator: Sim\nFator: \nNome: Preço\nPonderação: 55%\nSubfatores: Não\nFator: \nNome: Qualidade\nPonderação: 20%\nSubfatores: Não\nFator: \nNome: Qualidade\nPonderação: 25%\nSubfatores: Não\nO Critério de adjudicação é diferenciado por lote? Sim\nIdentificador do lote: LOT-0002\nMultifator: Sim\nFator: \nNome: Preço\nPonderação: 55%\nSubfatores: Não\nFator: \nNome: Qualidade\nPonderação: 10%\nSubfatores: Não\nFator: \nNome: Qualidade\nPonderação: 10%\nSubfatores: Não\nFator: \nNome: Qualidade\nPonderação: 10%\nSubfatores: Não\nFator: \nNome: Qualidade\nPonderação: 5%\nSubfatores: Não\nFator: \nNome: Qualidade\nPonderação: 10%\nSubfatores: Não\n\n24 - CONDIÇÕES DO CONTRATO\nIdentificador do Lote: LOT-0001; LOT-0002\nFaturação Eletrónica: Permitido\nObrigação de Subcontratação:\nCódigo da Obrigação de Subcontratação: Não é aplicável nenhuma obrigação de subcontratação.\n\n25 - COMPRA PÚBLICA ESTRATÉGICA\nCompra Pública Estratégica: Redução dos impactos ambientais\nDescrição do Processo de Adjudicação Estratégico: Conforme as peças do procedimento\nCritérios de contratos Públicos Ecológicos: Critérios de contratação pública ecológica nacional\nCategorias da estratégia nacional: Computadores, monitores, tabletes e telemóveis inteligentes\nContratos Públicos Ecológicos: Outros\nDiretiva Veículos Não Poluentes: Não\nCritério de Acessibilidade: Os critérios de acessibilidade para as pessoas com deficiência estão incluídos\n\n26 - INFORMAÇÕES ADICIONAIS\nIdentificador do Lote: LOT-0001; LOT-0002\nContrato adequado para PME: Sim\nCobertura ACP (Acordo dos Contratos Públicos da Organização Mundial do Comércio): Não\n\n27 - IDENTIFICAÇÃO E CONTACTOS DO ÓRGÃO DE RECURSOS ADMINISTRATIVOS\nDesignação: Maria Celeste Moreira Novo Ribeiro\nEndereço: Alameda Afonso Betote\nCódigo postal: 4480-794\nLocalidade: Vila do Conde\nTelefone: +351 252640400\nFax: +351 252640400\nEndereço eletrónico: diretora@oges.esc-joseregio.pt\n\n28 - IDENTIFICAÇÃO DO(S) AUTOR(ES) DE ANÚNCIO\nNome: Maria Celeste Moreira Novo Ribeiro\nCargo: Diretora\n\n29 - ALTERAÇÃO\nMotivo da Alteração: Informações atualizadas\nIdentificador da Versão do Anúncio a Alterar: 14a450a9-7449-43ac-b7fb-a4675ee57dab-01\nIdentificador das Secções Alteradas do Anúncio Anterior: Informações adicionais\nDescrição das Alterações: Publicação da Lista de Erros e Omissões \nAlteração dos Documentos do Concurso: Sim\nData de alteração dos documentos do concurso: 18-09-2025\n419600148",
    "nipc": "600013804",
    "distrito": "Porto",
    "concelho": "Porto",
    "freguesia": "Todas",
    "site": "https://www.esc-joseregio.pt/",
    "email": "direcao@oges.esc-joseregio.pt",
    "designacao_contrato": "Aquisição de Bens no âmbito do Centro Tecnológico Especializado Industrial",
    "descricao": "Aquisição de Bens no âmbito do Centro Tecnológico Especializado Industrial da Escola Secundária José Régio",
    "preco_base": "1.434.016,00 EUR",
    "prazo_execucao": "2 MESES",
    "prazo_apresentacao_propostas": "02-10-2025 18:00",
    "fundos_eu": "Sim",
    "plataforma_eletronica": "VORTAL",
    "url_procedimento": "https://community.vortal.biz/public/",
    "autor_nome": "Maria Celeste Moreira Novo Ribeiro",
    "autor_cargo": "Diretora"
  },
  {
    "numero_procedimento": "N/A",
    "entidade": "Município de Leiria",
    "link": "https://diariodarepublica.pt/dr/detalhe/contrato-publico/26073-937877841",
    "detalhes_completos": "1 - IDENTIFICAÇÃO E CONTACTOS DA ENTIDADE ADJUDICANTE\nDesignação da entidade adjudicante: Município de Leiria\nNIPC: 505181266\nEndereço: Largo da República\nCódigo postal: 2414-006\nLocalidade: Leiria\nPaís: Portugal\nNUT III: PT16F\nDistrito: Leiria\nConcelho: Leiria\nFreguesia: União das Freguesias de Leiria, Pousos, Barreira e Cortes\nTelefone: 244839500\nFax: 244839500\nEndereço da Entidade (URL): www.cm-leiria.pt\nEndereço Eletrónico: cmleiria@cm-leiria.pt\nFunção da Organização: Adquirente\nNorma jurídica da Entidade Adjudicante: Autoridade local\nÁrea de atividade da Autoridade Adjudicante: Serviços públicos das administrações públicas\n\n2 - JORNAL OFICIAL DA UNIÃO EUROPEIA\nO procedimento a que este anúncio diz respeito também é publicitado no Jornal Oficial da União Europeia? Não\n\n3 - AVISO\nModelo de Anúncio: Concurso público\nData de Envio do Anúncio: 03-10-2025\n\n5 - PROCESSO\nTipo de Procedimento: Concurso público\nPreço base do procedimento: Sim\nValor do preço base do procedimento: 96.200,00 EUR\nProcedimento com lotes? Não\n\n6 - OBJETO DO CONTRATO\nNúmero de referência interna: CPN 109/2025\nDesignação do contrato: CPN 109/2025 - Serviços de conservação e manutenção corrente do relvado natural do Estádio Municipal de Leiria (EML) - Dr. Magalhães Pessoa, na modalidade de prestação de serviços contínua\nDescrição: CPN 109/2025 - Serviços conserv. manut. corrente do relvado natural do Estádio Municipal Leiria - Dr. Magalhães Pessoa, na mod. prest. serv. contínua\nTipo de Contrato Principal: Aquisição de Serviços\nTipo de Contrato: Aquisição de Serviços\nClassificação CPV (Vocabulário Comum para os Contratos Públicos)\nObjeto principal\nVocabulário Principal: 77320000\nPreço base s/IVA: 96.200,00 EUR\n\n7 - INDICAÇÕES ADICIONAIS\nO contrato envolve aquisição conjunta (satisfação de várias entidades)? Não\nO contrato é adjudicado por uma central de compras? Não\n\n8 - TÉCNICAS\nO concurso destina-se à celebração de um acordo-quadro? Inexistência de acordo-quadro\nÉ utilizado um leilão eletrónico? Não\nÉ adotada uma fase de negociação? Não\nSistema de Aquisição Dinâmico: Inexistência de sistema de aquisição dinâmico\n\n9 - LOCAL DA EXECUÇÃO DO CONTRATO\nLOCAL DA EXECUÇÃO DO CONTRATO (PROCEDIMENTO)\nPaís: Portugal\nNUT III: PT16F\nLocalidade: Leiria\nDistrito: Leiria\nConcelho: Leiria\nFreguesia: União das Freguesias de Leiria, Pousos, Barreira e Cortes\n\n10 - PRAZO DE EXECUÇÃO DO CONTRATO\nPrazo de execução do contrato: 365 DIAS\nPrevisão de renovações: Não\n\n11 - FUNDOS EU\nTêm fundos EU? Não\n\n12 - DOCUMENTOS DE HABILITAÇÃO\nHabilitação para o exercício da atividade profissional: Não\n\n13 - CONDIÇÕES DE APRESENTAÇÃO\nPlataforma eletrónica utilizada pela entidade adjudicante: ANOGOV\nURL para Apresentação: https://www.anogov.com/cm-leiria/faces/\nAdmissibilidade da apresentação de propostas variantes: Não autorizado\nPrazo para apresentação das propostas: 10-10-2025 23:59\nPrazo durante o qual os concorrentes são obrigados a manter as respetivas propostas: 120 dias a contar do termo do prazo para a apresentação das propostas\nApresentação de Catálogo Eletrónico: Não autorizado\nIndicação de Subcontratação na Proposta: Inexistência de indicação de subcontratação\n\n14 - PRESTAÇÃO DE CAUÇÃO\nPrestação de caução: Não\n\n15 - FORNECIMENTO DAS PEÇAS DO CONCURSO, APRESENTAÇÃO DE PEDIDOS DE PARTICIPAÇÃO E APRESENTAÇÃO DAS PROPOSTAS\nLink para acesso às peças do concurso (URL): https://www.anogov.com/cm-leiria/faces/app/acessoDocs.jsp?codigoAcesso=kccJTtMOPmaJnSfKOJQURPsDNNhSgWJdcgLwBXBzyORGWTRtz4\n\n20 - OUTROS REQUISITOS\nInformação sobre contratos reservados. Aplica-se a contratos reservados (54º-A)? Não\n\n21 - CRITÉRIO DE ADJUDICAÇÃO\nMultifator: Não\nMonofator:\nNome: Preço\n\n24 - CONDIÇÕES DO CONTRATO\nFaturação Eletrónica: Permitido\nObrigação de Subcontratação:\nCódigo da Obrigação de Subcontratação: Não é aplicável nenhuma obrigação de subcontratação.\n\n25 - COMPRA PÚBLICA ESTRATÉGICA\nCompra Pública Estratégica: Inexistência de contratação pública estratégica\n\n26 - INFORMAÇÕES ADICIONAIS\nContrato adequado para PME: Sim\nCobertura ACP (Acordo dos Contratos Públicos da Organização Mundial do Comércio): Não\n\n27 - IDENTIFICAÇÃO E CONTACTOS DO ÓRGÃO DE RECURSOS ADMINISTRATIVOS\nDesignação: Presidente da Câmara Municipal de Leiria\nEndereço: Largo da República\nCódigo postal: 2414-006\nLocalidade: Leiria\nEndereço eletrónico: cmleiria@cm-leiria.pt\n\n28 - IDENTIFICAÇÃO DO(S) AUTOR(ES) DE ANÚNCIO\nNome: Gonçalo Lopes\nCargo: Presidente da Câmara Municipal de Leiria\n419604303",
    "nipc": "505181266",
    "distrito": "Leiria",
    "concelho": "Leiria",
    "freguesia": "União das Freguesias de Leiria, Pousos, Barreira e Cortes",
    "site": "www.cm-leiria.pt",
    "email": "cmleiria@cm-leiria.pt",
    "designacao_contrato": "CPN 109/2025 - Serviços de conservação e manutenção corrente do relvado natural do Estádio Municipal de Leiria (EML) - Dr. Magalhães Pessoa, na modalidade de prestação de serviços contínua",
    "descricao": "CPN 109/2025 - Serviços conserv. manut. corrente do relvado natural do Estádio Municipal Leiria - Dr. Magalhães Pessoa, na mod. prest. serv. contínua",
    "preco_base": "96.200,00 EUR",
    "prazo_execucao": "365 DIAS",
    "prazo_apresentacao_propostas": "10-10-2025 23:59",
    "fundos_eu": "Não",
    "plataforma_eletronica": "ANOGOV",
    "url_procedimento": "https://www.anogov.com/cm-leiria/faces/",
    "autor_nome": "Gonçalo Lopes",
    "autor_cargo": "Presidente da Câmara Municipal de Leiria"
  },
  {
    "numero_procedimento": "N/A",
    "entidade": "AnÃºncio de procedimento  n.Âº 26075/2025  -  DiÃ¡rio da RepÃºblica n.Âº 191/2025, SÃ©rie II de 2025-10-03",
    "link": "https://diariodarepublica.pt/dr/detalhe/contrato-publico/26075-937877842"
  },
  {
    "numero_procedimento": "N/A",
    "entidade": "AnÃºncio de procedimento  n.Âº 26077/2025  -  DiÃ¡rio da RepÃºblica n.Âº 191/2025, SÃ©rie II de 2025-10-03",
    "link": "https://diariodarepublica.pt/dr/detalhe/contrato-publico/26077-937877843"
  },
  {
    "numero_procedimento": "N/A",
    "entidade": "Ministério da Defesa Nacional - Marinha",
    "link": "https://diariodarepublica.pt/dr/detalhe/contrato-publico/26082-937877844",
    "detalhes_completos": "1 - IDENTIFICAÇÃO E CONTACTOS DA ENTIDADE ADJUDICANTE\nDesignação da entidade adjudicante: Ministério da Defesa Nacional - Marinha\nNIPC: 600012662\nServiço/Órgão/Pessoa de contacto: MDN - Marinha - SM - Direção de Infraestruturas m4a11524@marinha.pt\nEndereço: Praça do Comércio\nCódigo postal: 1100-148\nLocalidade: Lisboa\nPaís: Portugal\nNUT III: PT170\nDistrito: Lisboa\nConcelho: Lisboa\nFreguesia: Freguesia de Santa Maria Maior - Lisboa\nTelefone: 211903442\nFax: 213255518\nEndereço da Entidade (URL): https://www.marinha.pt/pt\nEndereço Eletrónico: m4a11524@marinha.pt\neDelivery Gateway (URL): https://www.acingov.pt\nFunção da Organização: Adquirente\nNorma jurídica da Entidade Adjudicante: Autoridade da administração central\nÁrea de atividade da Entidade Adjudicante: Atividades portuárias\n\n2 - JORNAL OFICIAL DA UNIÃO EUROPEIA\nO procedimento a que este anúncio diz respeito também é publicitado no Jornal Oficial da União Europeia? Não\n\n3 - AVISO\nModelo de Anúncio: Concurso público\nData de Envio do Anúncio: 03-10-2025\n\n5 - PROCESSO\nTipo de Procedimento: Concurso público\nPreço base do procedimento: Sim\nValor do preço base do procedimento: 50.800,00 EUR\nProcedimento com lotes? Não\n\n6 - OBJETO DO CONTRATO\nNúmero de referência interna: 3025008720_1478_DI\nDesignação do contrato: 3025008720_1478_DI - Fornecimento e Instalação de Estrutura Modular 6,2m x 7,3m,\nDescrição: 3025008720_1478_DI - Fornecimento e Instalação de Estrutura Modular 6,2m x 7,3m,\nTipo de Contrato Principal: Aquisição de Bens Móveis\nTipo de Contrato: Aquisição de Bens Móveis\nClassificação CPV (Vocabulário Comum para os Contratos Públicos)\nObjeto principal\nVocabulário Principal: 34221000\nPreço base s/IVA: 50.800,00 EUR\n\n7 - INDICAÇÕES ADICIONAIS\nO contrato envolve aquisição conjunta (satisfação de várias entidades)? Não\nO contrato é adjudicado por uma central de compras? Não\n\n8 - TÉCNICAS\nO concurso destina-se à celebração de um acordo-quadro? Inexistência de acordo-quadro\nÉ utilizado um leilão eletrónico? Não\nÉ adotada uma fase de negociação? Não\nSistema de Aquisição Dinâmico: Inexistência de sistema de aquisição dinâmico\n\n9 - LOCAL DA EXECUÇÃO DO CONTRATO\nLOCAL DA EXECUÇÃO DO CONTRATO (PROCEDIMENTO)\nPaís: Portugal\nNUT III: PT170\nLocalidade: União das Freguesias de Almada, Cova da Piedade, Pragal e Cacilhas\nDistrito: Setúbal\nConcelho: Almada\nFreguesia: União das Freguesias de Almada, Cova da Piedade, Pragal e Cacilhas\n\n10 - PRAZO DE EXECUÇÃO DO CONTRATO\nPrazo de execução do contrato: 45 DIAS\nPrevisão de renovações: Não\n\n11 - FUNDOS EU\nTêm fundos EU? Não\n\n12 - DOCUMENTOS DE HABILITAÇÃO\nHabilitação para o exercício da atividade profissional: Não\n\n13 - CONDIÇÕES DE APRESENTAÇÃO\nPlataforma eletrónica utilizada pela entidade adjudicante: ACIN\nURL para Apresentação: https://www.acingov.pt\nAdmissibilidade da apresentação de propostas variantes: Não autorizado\nPrazo para apresentação das propostas: 18-10-2025 23:59\nPrazo durante o qual os concorrentes são obrigados a manter as respetivas propostas: 90 dias a contar do termo do prazo para a apresentação das propostas\nIndicação de Subcontratação na Proposta: Inexistência de indicação de subcontratação\n\n14 - PRESTAÇÃO DE CAUÇÃO\nPrestação de caução: Não\n\n15 - FORNECIMENTO DAS PEÇAS DO CONCURSO, APRESENTAÇÃO DE PEDIDOS DE PARTICIPAÇÃO E APRESENTAÇÃO DAS PROPOSTAS\nLink para acesso às peças do concurso (URL): https://www.acingov.pt/acingovprod/2/zonaPublica/zona_publica_c/donwloadProcedurePiece/OTMzMDI4\n\n20 - OUTROS REQUISITOS\nInformação sobre contratos reservados. Aplica-se a contratos reservados (54º-A)? Não\n\n21 - CRITÉRIO DE ADJUDICAÇÃO\nMultifator: Não\nMonofator:\nNome: Preço\n\n24 - CONDIÇÕES DO CONTRATO\nFaturação Eletrónica: Permitido\nObrigação de Subcontratação:\nCódigo da Obrigação de Subcontratação: Não é aplicável nenhuma obrigação de subcontratação.\n\n25 - COMPRA PÚBLICA ESTRATÉGICA\nCompra Pública Estratégica: Inexistência de contratação pública estratégica\n\n26 - INFORMAÇÕES ADICIONAIS\nContrato adequado para PME: Não\nCobertura ACP (Acordo dos Contratos Públicos da Organização Mundial do Comércio): Não\n\n27 - IDENTIFICAÇÃO E CONTACTOS DO ÓRGÃO DE RECURSOS ADMINISTRATIVOS\nDesignação: SM - Direção de Infraestruturas\nEndereço: Praça do Comércio\nCódigo postal: 1100-148\nLocalidade: Lisboa\nTelefone: 211903442\nFax: 213255518\nEndereço eletrónico: m4a11524@marinha.pt\nPrazo de interposição do recurso: 5 dias\n\n28 - IDENTIFICAÇÃO DO(S) AUTOR(ES) DE ANÚNCIO\nNome: José António de Brito Pereira Cavaco\nCargo: Diretor DI\n419610727",
    "nipc": "600012662",
    "distrito": "Lisboa",
    "concelho": "Lisboa",
    "freguesia": "Freguesia de Santa Maria Maior - Lisboa",
    "site": "https://www.marinha.pt/pt",
    "email": "m4a11524@marinha.pt",
    "designacao_contrato": "3025008720_1478_DI - Fornecimento e Instalação de Estrutura Modular 6,2m x 7,3m,",
    "descricao": "3025008720_1478_DI - Fornecimento e Instalação de Estrutura Modular 6,2m x 7,3m,",
    "preco_base": "50.800,00 EUR",
    "prazo_execucao": "45 DIAS",
    "prazo_apresentacao_propostas": "18-10-2025 23:59",
    "fundos_eu": "Não",
    "plataforma_eletronica": "ACIN",
    "url_procedimento": "https://www.acingov.pt",
    "autor_nome": "José António de Brito Pereira Cavaco",
    "autor_cargo": "Diretor DI"
  },
  {
    "numero_procedimento": "N/A",
    "entidade": "AnÃºncio de procedimento  n.Âº 26083/2025  -  DiÃ¡rio da RepÃºblica n.Âº 191/2025, SÃ©rie II de 2025-10-03",
    "link": "https://diariodarepublica.pt/dr/detalhe/contrato-publico/26083-937877845"
  },
  {
    "numero_procedimento": "N/A",
    "entidade": "AnÃºncio de procedimento  n.Âº 26002/2025  -  DiÃ¡rio da RepÃºblica n.Âº 191/2025, SÃ©rie II de 2025-10-03",
    "link": "https://diariodarepublica.pt/dr/detalhe/contrato-publico/26002-937940466"
  },
  {
    "numero_procedimento": "N/A",
    "entidade": "AnÃºncio de procedimento  n.Âº 26003/2025  -  DiÃ¡rio da RepÃºblica n.Âº 191/2025, SÃ©rie II de 2025-10-03",
    "link": "https://diariodarepublica.pt/dr/detalhe/contrato-publico/26003-937940467"
  },
  {
    "numero_procedimento": "N/A",
    "entidade": "Universidade Nova de Lisboa - Reitoria",
    "link": "https://diariodarepublica.pt/dr/detalhe/contrato-publico/26004-937940468",
    "detalhes_completos": "1 - IDENTIFICAÇÃO E CONTACTOS DA ENTIDADE ADJUDICANTE\nDesignação da entidade adjudicante: Universidade Nova de Lisboa - Reitoria\nNIPC: 501559094\nServiço/Órgão/Pessoa de contacto: DCP - Divisão de Contratação Pública\nEndereço: Campus de Campolide\nCódigo postal: 1099-085\nLocalidade: Lisboa\nPaís: Portugal\nNUT III: PTZZZ\nDistrito: Todos\nConcelho: Todos\nFreguesia: Todas\nTelefone: 213715600\nFax: 213715614\nEndereço da Entidade (URL): www.unl.pt\nEndereço Eletrónico: reitoria@unl.pt\neDelivery Gateway (URL): https://www.acingov.pt\nFunção da Organização: Adquirente\nNorma jurídica da Entidade Adjudicante: Organismo de direito público\nÁrea de atividade da Autoridade Adjudicante: Serviços públicos das administrações públicas\n\n2 - JORNAL OFICIAL DA UNIÃO EUROPEIA\nO procedimento a que este anúncio diz respeito também é publicitado no Jornal Oficial da União Europeia? Não\n\n3 - AVISO\nModelo de Anúncio: Concurso público\nData de Envio do Anúncio: 03-10-2025\n\n5 - PROCESSO\nTipo de Procedimento: Concurso público\nPreço base do procedimento: Sim\nValor do preço base do procedimento: 173.073,60 EUR\nProcedimento com lotes? Não\n\n6 - OBJETO DO CONTRATO\nNúmero de referência interna: CP/3/2025\nDesignação do contrato: Renovação do Serviço de Comunicações de dados da Universidade NOVA - (Integração das comunicações de dados entre Unidades Orgânicas e Serviços Centrais da Reitoria e das 3 residências dos SASNOVA)\nDescrição: Renovação do Serviço de Comunicações de dados da Universidade NOVA - (Integração das comunicações de dados entre Unidades Orgânicas e Serviços Centrais da Reitoria e das 3 residências dos SASNOVA)\nTipo de Contrato Principal: Aquisição de Serviços\nTipo de Contrato: Aquisição de Serviços\nClassificação CPV (Vocabulário Comum para os Contratos Públicos)\nObjeto principal\nVocabulário Principal: 72500000\nPreço base s/IVA: 173.073,60 EUR\n\n7 - INDICAÇÕES ADICIONAIS\nO contrato envolve aquisição conjunta (satisfação de várias entidades)? Não\nO contrato é adjudicado por uma central de compras? Não\n\n8 - TÉCNICAS\nO concurso destina-se à celebração de um acordo-quadro? Inexistência de acordo-quadro\nÉ utilizado um leilão eletrónico? Não\nÉ adotada uma fase de negociação? Não\nSistema de Aquisição Dinâmico: Inexistência de sistema de aquisição dinâmico\n\n9 - LOCAL DA EXECUÇÃO DO CONTRATO\nLOCAL DA EXECUÇÃO DO CONTRATO (PROCEDIMENTO)\nPaís: Portugal\nNUT III: PT170\nLocalidade: Todas\nDistrito: Lisboa\nConcelho: Todos\nFreguesia: Todas\n\n10 - PRAZO DE EXECUÇÃO DO CONTRATO\nPrazo de execução do contrato: 12 MESES\nPrevisão de renovações: Sim\nIndicar número máximo de renovações: 2\nPrazo de renovações diferente do prazo inicial: Não\n\n11 - FUNDOS EU\nTêm fundos EU? Não\n\n12 - DOCUMENTOS DE HABILITAÇÃO\nHabilitação para o exercício da atividade profissional: Não\n\n13 - CONDIÇÕES DE APRESENTAÇÃO\nPlataforma eletrónica utilizada pela entidade adjudicante: ACIN\nURL para Apresentação: https://www.acingov.pt\nAdmissibilidade da apresentação de propostas variantes: Não autorizado\nPrazo para apresentação das propostas: 17-10-2025 23:59\nPrazo durante o qual os concorrentes são obrigados a manter as respetivas propostas: 120 dias a contar do termo do prazo para a apresentação das propostas\nIndicação de Subcontratação na Proposta: Inexistência de indicação de subcontratação\n\n14 - PRESTAÇÃO DE CAUÇÃO\nPrestação de caução: Não\n\n15 - FORNECIMENTO DAS PEÇAS DO CONCURSO, APRESENTAÇÃO DE PEDIDOS DE PARTICIPAÇÃO E APRESENTAÇÃO DAS PROPOSTAS\nLink para acesso às peças do concurso (URL): https://www.acingov.pt/acingovprod/2/zonaPublica/zona_publica_c/donwloadProcedurePiece/OTgzMzM1\n\n20 - OUTROS REQUISITOS\nInformação sobre contratos reservados. Aplica-se a contratos reservados (54º-A)? Não\n\n21 - CRITÉRIO DE ADJUDICAÇÃO\nMultifator: Não\nMonofator:\nNome: Preço\n\n24 - CONDIÇÕES DO CONTRATO\nFaturação Eletrónica: Permitido\nObrigação de Subcontratação:\nCódigo da Obrigação de Subcontratação: Não é aplicável nenhuma obrigação de subcontratação.\n\n25 - COMPRA PÚBLICA ESTRATÉGICA\nCompra Pública Estratégica: Inexistência de contratação pública estratégica\n\n26 - INFORMAÇÕES ADICIONAIS\nContrato adequado para PME: Não\nCobertura ACP (Acordo dos Contratos Públicos da Organização Mundial do Comércio): Não\n\n27 - IDENTIFICAÇÃO E CONTACTOS DO ÓRGÃO DE RECURSOS ADMINISTRATIVOS\nDesignação: Reitor da UNL\nEndereço: Campus de Campolide\nCódigo postal: 1099-085\nLocalidade: Lisboa\nTelefone: 213715600\nFax: \nEndereço eletrónico: dcp.fundacao@unl.pt\n\n28 - IDENTIFICAÇÃO DO(S) AUTOR(ES) DE ANÚNCIO\nNome: Luis Valadas\nCargo: Técnico Contratação Publica\n419607058",
    "nipc": "501559094",
    "distrito": "Todos",
    "concelho": "Todos",
    "freguesia": "Todas",
    "site": "www.unl.pt",
    "email": "reitoria@unl.pt",
    "designacao_contrato": "Renovação do Serviço de Comunicações de dados da Universidade NOVA - (Integração das comunicações de dados entre Unidades Orgânicas e Serviços Centrais da Reitoria e das 3 residências dos SASNOVA)",
    "descricao": "Renovação do Serviço de Comunicações de dados da Universidade NOVA - (Integração das comunicações de dados entre Unidades Orgânicas e Serviços Centrais da Reitoria e das 3 residências dos SASNOVA)",
    "preco_base": "173.073,60 EUR",
    "prazo_execucao": "12 MESES",
    "prazo_apresentacao_propostas": "17-10-2025 23:59",
    "fundos_eu": "Não",
    "plataforma_eletronica": "ACIN",
    "url_procedimento": "https://www.acingov.pt",
    "autor_nome": "Luis Valadas",
    "autor_cargo": "Técnico Contratação Publica"
  },
  {
    "numero_procedimento": "N/A",
    "entidade": "AnÃºncio de procedimento  n.Âº 26006/2025  -  DiÃ¡rio da RepÃºblica n.Âº 191/2025, SÃ©rie II de 2025-10-03",
    "link": "https://diariodarepublica.pt/dr/detalhe/contrato-publico/26006-937940469"
  },
  {
    "numero_procedimento": "N/A",
    "entidade": "AnÃºncio de procedimento  n.Âº 26012/2025  -  DiÃ¡rio da RepÃºblica n.Âº 191/2025, SÃ©rie II de 2025-10-03",
    "link": "https://diariodarepublica.pt/dr/detalhe/contrato-publico/26012-937940471"
  },
  {
    "numero_procedimento": "N/A",
    "entidade": "AnÃºncio de procedimento  n.Âº 26016/2025  -  DiÃ¡rio da RepÃºblica n.Âº 191/2025, SÃ©rie II de 2025-10-03",
    "link": "https://diariodarepublica.pt/dr/detalhe/contrato-publico/26016-938020016"
  },
  {
    "numero_procedimento": "N/A",
    "entidade": "AnÃºncio de procedimento  n.Âº 26018/2025  -  DiÃ¡rio da RepÃºblica n.Âº 191/2025, SÃ©rie II de 2025-10-03",
    "link": "https://diariodarepublica.pt/dr/detalhe/contrato-publico/26018-938020017"
  },
  {
    "numero_procedimento": "N/A",
    "entidade": "AnÃºncio de procedimento  n.Âº 26020/2025  -  DiÃ¡rio da RepÃºblica n.Âº 191/2025, SÃ©rie II de 2025-10-03",
    "link": "https://diariodarepublica.pt/dr/detalhe/contrato-publico/26020-938020018"
  },
  {
    "numero_procedimento": "N/A",
    "entidade": "AIDA CCI - Câmara de Comércio e Indústria do Distrito de Aveiro",
    "link": "https://diariodarepublica.pt/dr/detalhe/contrato-publico/26021-938020019",
    "detalhes_completos": "1 - IDENTIFICAÇÃO E CONTACTOS DA ENTIDADE ADJUDICANTE\nDesignação da entidade adjudicante: AIDA CCI - Câmara de Comércio e Indústria do Distrito de Aveiro\nNIPC: 501668454\nEndereço: Rua da Boavista, Zona Industrial da Taboeira - Alagoas\nCódigo postal: 3800-115\nLocalidade: Aveiro\nPaís: Portugal\nNUT III: PT16D\nDistrito: Aveiro\nConcelho: Aveiro\nFreguesia: Freguesia de Esgueira\nTelefone: 234302490\nFax: 234302490\nEndereço da Entidade (URL): www.aida.pt\nEndereço Eletrónico: aida@aida.pt\nFunção da Organização: Adquirente\nNorma jurídica da Entidade Adjudicante: Organismo de direito público\nÁrea de atividade da Autoridade Adjudicante: Assuntos económicos\n\n2 - JORNAL OFICIAL DA UNIÃO EUROPEIA\nO procedimento a que este anúncio diz respeito também é publicitado no Jornal Oficial da União Europeia? Não\n\n3 - AVISO\nModelo de Anúncio: Concurso público\nData de Envio do Anúncio: 03-10-2025\n\n5 - PROCESSO\nTipo de Procedimento: Concurso público\nPreço base do procedimento: Sim\nValor do preço base do procedimento: 73.401,00 EUR\nProcedimento com lotes? Não\n\n6 - OBJETO DO CONTRATO\nNúmero de referência interna: 7/2025\nDesignação do contrato: Serviços no âmbito da qualificação de PME para o projeto nº 17658\nDescrição: Serviços de implementação das diversas atividades de qualificação de PME para o projeto nº 17658 \nTipo de Contrato Principal: Aquisição de Serviços\nTipo de Contrato: Aquisição de Serviços\nClassificação CPV (Vocabulário Comum para os Contratos Públicos)\nObjeto principal\nVocabulário Principal: 72224000\nPreço base s/IVA: 73.401,00 EUR\n\n7 - INDICAÇÕES ADICIONAIS\nO contrato envolve aquisição conjunta (satisfação de várias entidades)? Não\nO contrato é adjudicado por uma central de compras? Não\n\n8 - TÉCNICAS\nO concurso destina-se à celebração de um acordo-quadro? Inexistência de acordo-quadro\nÉ utilizado um leilão eletrónico? Não\nÉ adotada uma fase de negociação? Não\nSistema de Aquisição Dinâmico: Inexistência de sistema de aquisição dinâmico\n\n9 - LOCAL DA EXECUÇÃO DO CONTRATO\nLOCAL DA EXECUÇÃO DO CONTRATO (PROCEDIMENTO)\nPaís: Portugal\nNUT III: PT16D\nLocalidade: Aveiro\nDistrito: Aveiro\nConcelho: Aveiro\nFreguesia: Freguesia de Esgueira\n\n10 - PRAZO DE EXECUÇÃO DO CONTRATO\nPrazo de execução do contrato: 12 MESES\nPrevisão de renovações: Não\n\n11 - FUNDOS EU\nTêm fundos EU? Não\n\n12 - DOCUMENTOS DE HABILITAÇÃO\nHabilitação para o exercício da atividade profissional: Não\n\n13 - CONDIÇÕES DE APRESENTAÇÃO\nPlataforma eletrónica utilizada pela entidade adjudicante: COMPRASPT\nURL para Apresentação: https://www.compraspt.com/cpt-aida/faces/\nAdmissibilidade da apresentação de propostas variantes: Não autorizado\nPrazo para apresentação das propostas: 13-10-2025 23:59\nPrazo durante o qual os concorrentes são obrigados a manter as respetivas propostas: 100 dias a contar do termo do prazo para a apresentação das propostas\nApresentação de Catálogo Eletrónico: Permitido\nIndicação de Subcontratação na Proposta: Inexistência de indicação de subcontratação\n\n14 - PRESTAÇÃO DE CAUÇÃO\nPrestação de caução: Sim\nPercentagem: 5%\nDescrição da Garantia Exigida: Conforme peças do procedimento\n\n15 - FORNECIMENTO DAS PEÇAS DO CONCURSO, APRESENTAÇÃO DE PEDIDOS DE PARTICIPAÇÃO E APRESENTAÇÃO DAS PROPOSTAS\nLink para acesso às peças do concurso (URL): https://www.compraspt.com/cpt-aida/faces/app/acessoDocs.jsp?codigoAcesso=4jU1HKSE84pUduMH9194MBAYcd7VgSyKY8mQUiRLUGt1j8Np96\n\n20 - OUTROS REQUISITOS\nInformação sobre contratos reservados. Aplica-se a contratos reservados (54º-A)? Não\n\n21 - CRITÉRIO DE ADJUDICAÇÃO\nMultifator: Sim\nFator: \nNome: Preço\nPonderação: 10%\nSubfatores: Não\nFator: \nNome: Qualidade\nPonderação: 40%\nSubfatores: Não\nFator: \nNome: Organização, qualificações e experiência do pessoal encarregado\nPonderação: 50%\nSubfatores: Não\n\n24 - CONDIÇÕES DO CONTRATO\nFaturação Eletrónica: Permitido\nObrigação de Subcontratação:\nCódigo da Obrigação de Subcontratação: Não é aplicável nenhuma obrigação de subcontratação.\n\n25 - COMPRA PÚBLICA ESTRATÉGICA\nCompra Pública Estratégica: Inexistência de contratação pública estratégica\n\n26 - INFORMAÇÕES ADICIONAIS\nContrato adequado para PME: Sim\nCobertura ACP (Acordo dos Contratos Públicos da Organização Mundial do Comércio): Não\n\n27 - IDENTIFICAÇÃO E CONTACTOS DO ÓRGÃO DE RECURSOS ADMINISTRATIVOS\nDesignação: Direção\nEndereço: Rua da Boavista ¿ Zona Industrial de Taboeira ¿ Alagoas\nCódigo postal: 3800-115\nLocalidade: Aveiro\nEndereço eletrónico: aida@aida.pt\nPrazo de interposição do recurso: 5 dias\n\n28 - IDENTIFICAÇÃO DO(S) AUTOR(ES) DE ANÚNCIO\nNome: Fernando Paiva de Castro\nCargo: Presidente da Direção\n419603104",
    "nipc": "501668454",
    "distrito": "Aveiro",
    "concelho": "Aveiro",
    "freguesia": "Freguesia de Esgueira",
    "site": "www.aida.pt",
    "email": "aida@aida.pt",
    "designacao_contrato": "Serviços no âmbito da qualificação de PME para o projeto nº 17658",
    "descricao": "Serviços de implementação das diversas atividades de qualificação de PME para o projeto nº 17658",
    "preco_base": "73.401,00 EUR",
    "prazo_execucao": "12 MESES",
    "prazo_apresentacao_propostas": "13-10-2025 23:59",
    "fundos_eu": "Não",
    "plataforma_eletronica": "COMPRASPT",
    "url_procedimento": "https://www.compraspt.com/cpt-aida/faces/",
    "autor_nome": "Fernando Paiva de Castro",
    "autor_cargo": "Presidente da Direção"
  },
  {
    "numero_procedimento": "N/A",
    "entidade": "AnÃºncio de procedimento  n.Âº 26022/2025  -  DiÃ¡rio da RepÃºblica n.Âº 191/2025, SÃ©rie II de 2025-10-03",
    "link": "https://diariodarepublica.pt/dr/detalhe/contrato-publico/26022-938020020"
  },
  {
    "numero_procedimento": "N/A",
    "entidade": "Unidade Local de Saúde de São José, E. P. E.",
    "link": "https://diariodarepublica.pt/dr/detalhe/contrato-publico/26023-938020021",
    "detalhes_completos": "Alteração do Anúncio de procedimento n.º 25615/2025, de 2025-09-29, com o ID 419589117\n\n1 - IDENTIFICAÇÃO E CONTACTOS DA ENTIDADE ADJUDICANTE\nDesignação da entidade adjudicante: Unidade Local de Saúde de São José, E. P. E.\nNIPC: 508080142\nEndereço: Rua José António Serrano\nCódigo postal: 1150-199\nLocalidade: Lisboa\nPaís: Portugal\nNUT III: PT170\nDistrito: Lisboa\nConcelho: Lisboa\nFreguesia: Freguesia de Arroios - Lisboa\nTelefone: 218841403\nFax: 218841025\nEndereço da Entidade (URL): www.chlc.min-saude.pt\nEndereço Eletrónico: geral@chlc.min-saude.pt\neDelivery Gateway (URL): https://community.vortal.biz/public/\nFunção da Organização: Adquirente\nNorma jurídica da Entidade Adjudicante: Organismo de direito público\nÁrea de atividade da Autoridade Adjudicante: Saúde\n\n2 - JORNAL OFICIAL DA UNIÃO EUROPEIA\nO procedimento a que este anúncio diz respeito também é publicitado no Jornal Oficial da União Europeia? Não\n\n3 - AVISO\nModelo de Anúncio: Concurso público\nData de Envio do Anúncio: 03-10-2025\n\n5 - PROCESSO\nTipo de Procedimento: Concurso público\nPreço base do procedimento: Sim\nValor do preço base do procedimento: 204.683,00 EUR\nProcedimento com lotes? Sim\nNº Máx. de Lotes Autorizado: 13\nNúmero máximo de lotes que podem ser adjudicados a um concorrente: 13\n\n6 - OBJETO DO CONTRATO\nNúmero de referência interna: 12026125\nDesignação do contrato: Aquisição de Próteses Vasculares, para a ULS São José, EPE\nDescrição: Aquisição de Próteses Vasculares, para a ULS São José, EPE\nTipo de Contrato Principal: Aquisição de Bens Móveis\nTipo de Contrato: Aquisição de Bens Móveis\nClassificação CPV (Vocabulário Comum para os Contratos Públicos)\nObjeto principal\nVocabulário Principal: 33140000\nPreço base s/IVA: 204.683,00 EUR\nLotes: \nNº: LOT-0001\nDescrição do Lote: Lote 1\nPreço base s/IVA: 13.825,00 EUR\nClassificação CPV (Vocabulário Comum para os Contratos Públicos)\nObjeto principal\nVocabulário Principal: 33140000\nNº: LOT-0002\nDescrição do Lote: Lote 2\nPreço base s/IVA: 18.450,00 EUR\nClassificação CPV (Vocabulário Comum para os Contratos Públicos)\nObjeto principal\nVocabulário Principal: 33140000\nNº: LOT-0003\nDescrição do Lote: Lote 3\nPreço base s/IVA: 5.600,00 EUR\nClassificação CPV (Vocabulário Comum para os Contratos Públicos)\nObjeto principal\nVocabulário Principal: 33140000\nNº: LOT-0004\nDescrição do Lote: Lote 4\nPreço base s/IVA: 24.000,00 EUR\nClassificação CPV (Vocabulário Comum para os Contratos Públicos)\nObjeto principal\nVocabulário Principal: 33140000\nNº: LOT-0005\nDescrição do Lote: Lote 5\nPreço base s/IVA: 10.500,00 EUR\nClassificação CPV (Vocabulário Comum para os Contratos Públicos)\nObjeto principal\nVocabulário Principal: 33140000\nNº: LOT-0006\nDescrição do Lote: Lote 6\nPreço base s/IVA: 8.310,00 EUR\nClassificação CPV (Vocabulário Comum para os Contratos Públicos)\nObjeto principal\nVocabulário Principal: 33140000\nNº: LOT-0007\nDescrição do Lote: Lote 7\nPreço base s/IVA: 6.993,00 EUR\nClassificação CPV (Vocabulário Comum para os Contratos Públicos)\nObjeto principal\nVocabulário Principal: 33140000\nNº: LOT-0008\nDescrição do Lote: Lote 8\nPreço base s/IVA: 28.080,00 EUR\nClassificação CPV (Vocabulário Comum para os Contratos Públicos)\nObjeto principal\nVocabulário Principal: 33140000\nNº: LOT-0009\nDescrição do Lote: Lote 9\nPreço base s/IVA: 3.600,00 EUR\nClassificação CPV (Vocabulário Comum para os Contratos Públicos)\nObjeto principal\nVocabulário Principal: 33140000\nNº: LOT-0010\nDescrição do Lote: Lote 10\nPreço base s/IVA: 29.875,00 EUR\nClassificação CPV (Vocabulário Comum para os Contratos Públicos)\nObjeto principal\nVocabulário Principal: 33140000\nNº: LOT-0011\nDescrição do Lote: Lote 11\nPreço base s/IVA: 1.380,00 EUR\nClassificação CPV (Vocabulário Comum para os Contratos Públicos)\nObjeto principal\nVocabulário Principal: 33140000\nNº: LOT-0012\nDescrição do Lote: Lote 12\nPreço base s/IVA: 6.000,00 EUR\nClassificação CPV (Vocabulário Comum para os Contratos Públicos)\nObjeto principal\nVocabulário Principal: 33140000\nNº: LOT-0013\nDescrição do Lote: Lote 13\nPreço base s/IVA: 48.070,00 EUR\nClassificação CPV (Vocabulário Comum para os Contratos Públicos)\nObjeto principal\nVocabulário Principal: 33140000\n\n7 - INDICAÇÕES ADICIONAIS\nO contrato envolve aquisição conjunta (satisfação de várias entidades)? Não\nO contrato é adjudicado por uma central de compras? Não\n\n8 - TÉCNICAS\nO concurso destina-se à celebração de um acordo-quadro? Inexistência de acordo-quadro\nÉ utilizado um leilão eletrónico? Não\nÉ adotada uma fase de negociação? Não\nSistema de Aquisição Dinâmico: Inexistência de sistema de aquisição dinâmico\n\n9 - LOCAL DA EXECUÇÃO DO CONTRATO\nLOCAL DA EXECUÇÃO DO CONTRATO (PROCEDIMENTO)\nPaís: Portugal\nNUT III: PT170\nLocalidade: Lisboa\nDistrito: Lisboa\nConcelho: Lisboa\nFreguesia: Freguesia de Arroios - Lisboa\nLOCAL DA EXECUÇÃO DO CONTRATO (LOTE)\nIdentificador do Lote: LOT-0001; LOT-0002; LOT-0003; LOT-0004; LOT-0005; LOT-0006; LOT-0007; LOT-0008; LOT-0009; LOT-0010; LOT-0011; LOT-0012; LOT-0013\nPaís: Portugal\nNUT III: PT170\nLocalidade: Lisboa\nDistrito: Lisboa\nConcelho: Lisboa\nFreguesia: Freguesia de Arroios - Lisboa\n\n10 - PRAZO DE EXECUÇÃO DO CONTRATO\nIdentificador do Lote: LOT-0001; LOT-0002; LOT-0003; LOT-0004; LOT-0005; LOT-0006; LOT-0007; LOT-0008; LOT-0009; LOT-0010; LOT-0011; LOT-0012; LOT-0013\nPrazo de execução do contrato: 93 DIAS\nPrevisão de renovações: Não\n\n11 - FUNDOS EU\nIdentificador do Lote: LOT-0001; LOT-0002; LOT-0003; LOT-0004; LOT-0005; LOT-0006; LOT-0007; LOT-0008; LOT-0009; LOT-0010; LOT-0011; LOT-0012; LOT-0013\nTêm fundos EU? Não\n\n12 - DOCUMENTOS DE HABILITAÇÃO\nHabilitação para o exercício da atividade profissional: Não\n\n13 - CONDIÇÕES DE APRESENTAÇÃO\nPlataforma eletrónica utilizada pela entidade adjudicante: VORTAL\nURL para Apresentação: https://community.vortal.biz/public/\nAdmissibilidade da apresentação de propostas variantes: Não autorizado\nPrazo para apresentação das propostas: 11-10-2025 23:59\nPrazo durante o qual os concorrentes são obrigados a manter as respetivas propostas: 120 dias a contar do termo do prazo para a apresentação das propostas\nIndicação de Subcontratação na Proposta: Inexistência de indicação de subcontratação\n\n14 - PRESTAÇÃO DE CAUÇÃO\nPrestação de caução: Não\n\n15 - FORNECIMENTO DAS PEÇAS DO CONCURSO, APRESENTAÇÃO DE PEDIDOS DE PARTICIPAÇÃO E APRESENTAÇÃO DAS PROPOSTAS\nLink para acesso às peças do concurso (URL): https://community.vortal.biz/Public/public-tender-documents/SmJGUVlmaVRYYmJnMDFuWUpROHVBcFd1SmJid1lkL3UxeG5URWIvSHpGT3JpVG5UL21zZkNQSWc1cDMyY0dXbE8rRnlIcDdBdVBlMnd0OXlWRzNnWEE9PUBEdWIj\n\n20 - OUTROS REQUISITOS\nIdentificador do Lote: LOT-0001; LOT-0002; LOT-0003; LOT-0004; LOT-0005; LOT-0006; LOT-0007; LOT-0008; LOT-0009; LOT-0010; LOT-0011; LOT-0012; LOT-0013\nInformação sobre contratos reservados. Aplica-se a contratos reservados (54º-A)? Não\n\n21 - CRITÉRIO DE ADJUDICAÇÃO\nO Critério de adjudicação é diferenciado por lote? Não\nMultifator: Não\nMonofator:\nNome: Preço\n\n24 - CONDIÇÕES DO CONTRATO\nIdentificador do Lote: LOT-0001; LOT-0002; LOT-0003; LOT-0004; LOT-0005; LOT-0006; LOT-0007; LOT-0008; LOT-0009; LOT-0010; LOT-0011; LOT-0012; LOT-0013\nFaturação Eletrónica: Permitido\nObrigação de Subcontratação:\nCódigo da Obrigação de Subcontratação: Não é aplicável nenhuma obrigação de subcontratação.\n\n25 - COMPRA PÚBLICA ESTRATÉGICA\nCompra Pública Estratégica: Inexistência de contratação pública estratégica\n\n26 - INFORMAÇÕES ADICIONAIS\nIdentificador do Lote: LOT-0001; LOT-0002; LOT-0003; LOT-0004; LOT-0005; LOT-0006; LOT-0007; LOT-0008; LOT-0009; LOT-0010; LOT-0011; LOT-0012; LOT-0013\nContrato adequado para PME: Sim\nCobertura ACP (Acordo dos Contratos Públicos da Organização Mundial do Comércio): Não\n\n27 - IDENTIFICAÇÃO E CONTACTOS DO ÓRGÃO DE RECURSOS ADMINISTRATIVOS\nDesignação: Conselho de Administração\nEndereço: Rua José António Serrano s/n\nCódigo postal: 1150-199\nLocalidade: Lisboa\nTelefone: +351 218841000\nFax: +351 218841023\nEndereço eletrónico: sec.vca@ulssjose.min-saude.pt\n\n28 - IDENTIFICAÇÃO DO(S) AUTOR(ES) DE ANÚNCIO\nNome: Área de Gestão de Compras\nCargo: Área de Gestão de Compras\n\n29 - ALTERAÇÃO\nMotivo da Alteração: Correção pelo adquirente\nIdentificador da Versão do Anúncio a Alterar: 3b7509c3-f776-4ef0-9d7b-56f968c17101-01\nIdentificador das Secções Alteradas do Anúncio Anterior: Acesso às peças do concurso, pedidos de participação e apresentação das propostas\nDescrição das Alterações: Foi detectado um lapso na descrição dos artigos e nas especificações técnicas dos lotes 1 e 4, e o Júri procedeu a alterações de descrição e requisitos obrigatórios destes mesmos lotes 1 e 4. \n\nTorna-se necessário retificar o Anexo I do Programa do procedimento e os anexos I e II do Caderno de Encargos, no que respeito às descrições dos artigos e especificações técnicas do referido nos lotes 1 e 4.\n\nAlteração dos Documentos do Concurso: Sim\nData de alteração dos documentos do concurso: 02-10-2025\n419606718",
    "nipc": "508080142",
    "distrito": "Lisboa",
    "concelho": "Lisboa",
    "freguesia": "Freguesia de Arroios - Lisboa",
    "site": "www.chlc.min-saude.pt",
    "email": "geral@chlc.min-saude.pt",
    "designacao_contrato": "Aquisição de Próteses Vasculares, para a ULS São José, EPE",
    "descricao": "Aquisição de Próteses Vasculares, para a ULS São José, EPE",
    "preco_base": "204.683,00 EUR",
    "prazo_execucao": "93 DIAS",
    "prazo_apresentacao_propostas": "11-10-2025 23:59",
    "fundos_eu": "Não",
    "plataforma_eletronica": "VORTAL",
    "url_procedimento": "https://community.vortal.biz/public/",
    "autor_nome": "Área de Gestão de Compras",
    "autor_cargo": "Área de Gestão de Compras"
  },
  {
    "numero_procedimento": "N/A",
    "entidade": "AnÃºncio de procedimento  n.Âº 26024/2025  -  DiÃ¡rio da RepÃºblica n.Âº 191/2025, SÃ©rie II de 2025-10-03",
    "link": "https://diariodarepublica.pt/dr/detalhe/contrato-publico/26024-938020022"
  },
  {
    "numero_procedimento": "N/A",
    "entidade": "AnÃºncio de procedimento  n.Âº 26025/2025  -  DiÃ¡rio da RepÃºblica n.Âº 191/2025, SÃ©rie II de 2025-10-03",
    "link": "https://diariodarepublica.pt/dr/detalhe/contrato-publico/26025-938020023"
  },
  {
    "numero_procedimento": "N/A",
    "entidade": "AnÃºncio de procedimento  n.Âº 26026/2025  -  DiÃ¡rio da RepÃºblica n.Âº 191/2025, SÃ©rie II de 2025-10-03",
    "link": "https://diariodarepublica.pt/dr/detalhe/contrato-publico/26026-938020024"
  },
  {
    "numero_procedimento": "N/A",
    "entidade": "AnÃºncio de procedimento  n.Âº 26027/2025  -  DiÃ¡rio da RepÃºblica n.Âº 191/2025, SÃ©rie II de 2025-10-03",
    "link": "https://diariodarepublica.pt/dr/detalhe/contrato-publico/26027-938020025"
  },
  {
    "numero_procedimento": "N/A",
    "entidade": "Município de Vieira do Minho",
    "link": "https://diariodarepublica.pt/dr/detalhe/contrato-publico/26028-938020026",
    "detalhes_completos": "1 - IDENTIFICAÇÃO E CONTACTOS DA ENTIDADE ADJUDICANTE\nDesignação da entidade adjudicante: Município de Vieira do Minho\nNIPC: 506659682\nEndereço: Praça Guilherme de Abreu\nCódigo postal: 4850-527\nLocalidade: Vieira do Minho\nPaís: Portugal\nNUT III: PT119\nDistrito: Braga\nConcelho: Vieira do Minho\nFreguesia: Freguesia de Vieira do Minho\nTelefone: 253649270\nEndereço Eletrónico: geral@cm-vminho.pt\nFunção da Organização: Adquirente\nNorma jurídica da Entidade Adjudicante: Autoridade local\nÁrea de atividade da Autoridade Adjudicante: Serviços públicos das administrações públicas\n\n2 - JORNAL OFICIAL DA UNIÃO EUROPEIA\nO procedimento a que este anúncio diz respeito também é publicitado no Jornal Oficial da União Europeia? Não\n\n3 - AVISO\nModelo de Anúncio: Concurso público\nData de Envio do Anúncio: 03-10-2025\n\n5 - PROCESSO\nTipo de Procedimento: Concurso público\nPreço base do procedimento: Sim\nValor do preço base do procedimento: 177.440,76 EUR\nProcedimento com lotes? Não\n\n6 - OBJETO DO CONTRATO\nNúmero de referência interna: PROC_141/2025\nDesignação do contrato: MODERNIZAÇÃO DA INFRAESTRUTURA DOS SISTEMAS INFORMÁTICOS MUNICIPAIS NO ÂMBITO DA DIGITALIZAÇÃO DA ADMINISTRAÇÃO PÚBLICA LOCAL\nDescrição: MODERNIZAÇÃO DA INFRAESTRUTURA DOS SISTEMAS INFORMÁTICOS MUNICIPAIS NO ÂMBITO DA DIGITALIZAÇÃO DA ADMINISTRAÇÃO PÚBLICA LOCAL\nTipo de Contrato Principal: Aquisição de Bens Móveis\nTipo de Contrato: Aquisição de Bens Móveis\nClassificação CPV (Vocabulário Comum para os Contratos Públicos)\nObjeto principal\nVocabulário Principal: 48900000\nPreço base s/IVA: 177.440,76 EUR\n\n7 - INDICAÇÕES ADICIONAIS\nO contrato envolve aquisição conjunta (satisfação de várias entidades)? Não\nO contrato é adjudicado por uma central de compras? Não\n\n8 - TÉCNICAS\nO concurso destina-se à celebração de um acordo-quadro? Inexistência de acordo-quadro\nÉ utilizado um leilão eletrónico? Não\nÉ adotada uma fase de negociação? Não\nSistema de Aquisição Dinâmico: Inexistência de sistema de aquisição dinâmico\n\n9 - LOCAL DA EXECUÇÃO DO CONTRATO\nLOCAL DA EXECUÇÃO DO CONTRATO (PROCEDIMENTO)\nPaís: Portugal\nNUT III: PT119\nLocalidade: Vieira do Minho\nDistrito: Braga\nConcelho: Vieira do Minho\nFreguesia: Freguesia de Vieira do Minho\n\n10 - PRAZO DE EXECUÇÃO DO CONTRATO\nPrazo de execução do contrato: 60 DIAS\nPrevisão de renovações: Não\n\n11 - FUNDOS EU\nTêm fundos EU? Sim\n\n12 - DOCUMENTOS DE HABILITAÇÃO\nHabilitação para o exercício da atividade profissional: Não\n\n13 - CONDIÇÕES DE APRESENTAÇÃO\nPlataforma eletrónica utilizada pela entidade adjudicante: VORTAL\nURL para Apresentação: https://community.vortal.biz\nAdmissibilidade da apresentação de propostas variantes: Não autorizado\nPrazo para apresentação das propostas: 13-10-2025 18:00\nPrazo durante o qual os concorrentes são obrigados a manter as respetivas propostas: 66 dias a contar do termo do prazo para a apresentação das propostas\nIndicação de Subcontratação na Proposta: Inexistência de indicação de subcontratação\n\n14 - PRESTAÇÃO DE CAUÇÃO\nPrestação de caução: Não\n\n15 - FORNECIMENTO DAS PEÇAS DO CONCURSO, APRESENTAÇÃO DE PEDIDOS DE PARTICIPAÇÃO E APRESENTAÇÃO DAS PROPOSTAS\nLink para acesso às peças do concurso (URL): https://community.vortal.biz\n\n20 - OUTROS REQUISITOS\nInformação sobre contratos reservados. Aplica-se a contratos reservados (54º-A)? Não\n\n21 - CRITÉRIO DE ADJUDICAÇÃO\nMultifator: Não\nMonofator:\nNome: Preço\n\n24 - CONDIÇÕES DO CONTRATO\nFaturação Eletrónica: Necessário\n\n25 - COMPRA PÚBLICA ESTRATÉGICA\nCompra Pública Estratégica: Inexistência de contratação pública estratégica\n\n26 - INFORMAÇÕES ADICIONAIS\nContrato adequado para PME: Sim\nCobertura ACP (Acordo dos Contratos Públicos da Organização Mundial do Comércio): Não\n\n27 - IDENTIFICAÇÃO E CONTACTOS DO ÓRGÃO DE RECURSOS ADMINISTRATIVOS\nDesignação: Município de Vieira do Minho\nEndereço: Praça Guilherme de Abreu\nCódigo postal: 4850-527\nLocalidade: Vieira do Minho\nEndereço eletrónico: geral@cm-vminho.pt\n\n28 - IDENTIFICAÇÃO DO(S) AUTOR(ES) DE ANÚNCIO\nNome: Elsa Carla Monteiro Pereira Ribeiro\nCargo: Presidente da Câmara\n419609642",
    "nipc": "506659682",
    "distrito": "Braga",
    "concelho": "Vieira do Minho",
    "freguesia": "Freguesia de Vieira do Minho",
    "site": null,
    "email": "geral@cm-vminho.pt",
    "designacao_contrato": "MODERNIZAÇÃO DA INFRAESTRUTURA DOS SISTEMAS INFORMÁTICOS MUNICIPAIS NO ÂMBITO DA DIGITALIZAÇÃO DA ADMINISTRAÇÃO PÚBLICA LOCAL",
    "descricao": "MODERNIZAÇÃO DA INFRAESTRUTURA DOS SISTEMAS INFORMÁTICOS MUNICIPAIS NO ÂMBITO DA DIGITALIZAÇÃO DA ADMINISTRAÇÃO PÚBLICA LOCAL",
    "preco_base": "177.440,76 EUR",
    "prazo_execucao": "60 DIAS",
    "prazo_apresentacao_propostas": "13-10-2025 18:00",
    "fundos_eu": "Sim",
    "plataforma_eletronica": "VORTAL",
    "url_procedimento": "https://community.vortal.biz",
    "autor_nome": "Elsa Carla Monteiro Pereira Ribeiro",
    "autor_cargo": "Presidente da Câmara"
  },
  {
    "numero_procedimento": "N/A",
    "entidade": "AnÃºncio de procedimento  n.Âº 26029/2025  -  DiÃ¡rio da RepÃºblica n.Âº 191/2025, SÃ©rie II de 2025-10-03",
    "link": "https://diariodarepublica.pt/dr/detalhe/contrato-publico/26029-938020027"
  },
  {
    "numero_procedimento": "N/A",
    "entidade": "AnÃºncio de procedimento  n.Âº 26031/2025  -  DiÃ¡rio da RepÃºblica n.Âº 191/2025, SÃ©rie II de 2025-10-03",
    "link": "https://diariodarepublica.pt/dr/detalhe/contrato-publico/26031-938020028"
  },
  {
    "numero_procedimento": "N/A",
    "entidade": "Serviços de Acção Social da Universidade do Algarve",
    "link": "https://diariodarepublica.pt/dr/detalhe/contrato-publico/26034-938020030",
    "detalhes_completos": "Alteração do Anúncio de procedimento n.º 25879/2025, de 2025-10-02, com o ID 419602238\n\n1 - IDENTIFICAÇÃO E CONTACTOS DA ENTIDADE ADJUDICANTE\nDesignação da entidade adjudicante: Serviços de Acção Social da Universidade do Algarve\nNIPC: 600039510\nEndereço: Campus Universitário da Penha - Estrada da Penha\nCódigo postal: 8005-139\nLocalidade: Faro\nPaís: Portugal\nNUT III: PT150\nDistrito: Faro\nConcelho: Faro\nFreguesia: Todas\nTelefone: 289800102\nFax: 289800102\nEndereço da Entidade (URL): https://www.ualg.pt/acao-social\nEndereço Eletrónico: sascompras@ualg.pt\nFunção da Organização: Adquirente\nSubfunção da Organização: Líder do grupo\nNorma jurídica da Entidade Adjudicante: Autoridade da administração central\nÁrea de atividade da Entidade Adjudicante: Atividades aeroportuárias\n\n2 - JORNAL OFICIAL DA UNIÃO EUROPEIA\nO procedimento a que este anúncio diz respeito também é publicitado no Jornal Oficial da União Europeia? Não\n\n3 - AVISO\nModelo de Anúncio: Concurso público\nData de Envio do Anúncio: 03-10-2025\n\n5 - PROCESSO\nTipo de Procedimento: Concurso público\nPreço base do procedimento: Sim\nValor do preço base do procedimento: 214.700,00 EUR\nProcedimento com lotes? Sim\nNº Máx. de Lotes Autorizado: 93\nNúmero máximo de lotes que podem ser adjudicados a um concorrente: 93\n\n6 - OBJETO DO CONTRATO\nNúmero de referência interna: Concurso Público n.º 04/SAS-UAlg/2025\nDesignação do contrato: Aquisição contínua e parcelar de carne fresca e congelada\nDescrição: Aquisição contínua e parcelar de carne fresca e congelada\nTipo de Contrato Principal: Aquisição de Bens Móveis\nTipo de Contrato: Aquisição de Bens Móveis\nClassificação CPV (Vocabulário Comum para os Contratos Públicos)\nObjeto principal\nVocabulário Principal: 15100000\nPreço base s/IVA: 214.700,00 EUR\nLotes: \nNº: LOT-0001\nDescrição do Lote: Bochechas de porco frescas\nPreço base s/IVA: 1.800,00 EUR\nClassificação CPV (Vocabulário Comum para os Contratos Públicos)\nObjeto principal\nVocabulário Principal: 15100000\nNº: LOT-0002\nDescrição do Lote: Carne picada de porco fresca\nPreço base s/IVA: 2.800,00 EUR\nClassificação CPV (Vocabulário Comum para os Contratos Públicos)\nObjeto principal\nVocabulário Principal: 15100000\nNº: LOT-0003\nDescrição do Lote: Chispe de porco fresco\nPreço base s/IVA: 30,00 EUR\nClassificação CPV (Vocabulário Comum para os Contratos Públicos)\nObjeto principal\nVocabulário Principal: 15100000\nNº: LOT-0004\nDescrição do Lote: Costeleta de porco do cachaço frescas\nPreço base s/IVA: 2.000,00 EUR\nClassificação CPV (Vocabulário Comum para os Contratos Públicos)\nObjeto principal\nVocabulário Principal: 15100000\nNº: LOT-0005\nDescrição do Lote: Costeleta de porco do lombo frescas\nPreço base s/IVA: 2.500,00 EUR\nClassificação CPV (Vocabulário Comum para os Contratos Públicos)\nObjeto principal\nVocabulário Principal: 15100000\nNº: LOT-0006\nDescrição do Lote: Entrecosto fresco\nPreço base s/IVA: 110,00 EUR\nClassificação CPV (Vocabulário Comum para os Contratos Públicos)\nObjeto principal\nVocabulário Principal: 15100000\nNº: LOT-0007\nDescrição do Lote: Entrecosto piano fresco\nPreço base s/IVA: 2.100,00 EUR\nClassificação CPV (Vocabulário Comum para os Contratos Públicos)\nObjeto principal\nVocabulário Principal: 15100000\nNº: LOT-0008\nDescrição do Lote: Entremeada fatiada fresca\nPreço base s/IVA: 1.800,00 EUR\nClassificação CPV (Vocabulário Comum para os Contratos Públicos)\nObjeto principal\nVocabulário Principal: 15100000\nNº: LOT-0009\nDescrição do Lote: Entremeada com entrecosto fresca\nPreço base s/IVA: 210,00 EUR\nClassificação CPV (Vocabulário Comum para os Contratos Públicos)\nObjeto principal\nVocabulário Principal: 15100000\nNº: LOT-0010\nDescrição do Lote: Espetada de porco fresca\nPreço base s/IVA: 900,00 EUR\nClassificação CPV (Vocabulário Comum para os Contratos Públicos)\nObjeto principal\nVocabulário Principal: 15100000\nNº: LOT-0011\nDescrição do Lote: Febras da perna frescas\nPreço base s/IVA: 4.000,00 EUR\nClassificação CPV (Vocabulário Comum para os Contratos Públicos)\nObjeto principal\nVocabulário Principal: 15100000\nNº: LOT-0012\nDescrição do Lote: Fígado de porco (iscas) fresco\nPreço base s/IVA: 50,00 EUR\nClassificação CPV (Vocabulário Comum para os Contratos Públicos)\nObjeto principal\nVocabulário Principal: 15100000\nNº: LOT-0013\nDescrição do Lote: Lombinho de porco fresco\nPreço base s/IVA: 1.050,00 EUR\nClassificação CPV (Vocabulário Comum para os Contratos Públicos)\nObjeto principal\nVocabulário Principal: 15100000\nNº: LOT-0014\nDescrição do Lote: Lombo de porco fresco\nPreço base s/IVA: 4.400,00 EUR\nClassificação CPV (Vocabulário Comum para os Contratos Públicos)\nObjeto principal\nVocabulário Principal: 15100000\nNº: LOT-0015\nDescrição do Lote: Orelha de  porco fresca\nPreço base s/IVA: 105,00 EUR\nClassificação CPV (Vocabulário Comum para os Contratos Públicos)\nObjeto principal\nVocabulário Principal: 15100000\nNº: LOT-0016\nDescrição do Lote: Pá de porco sem osso fresca\nPreço base s/IVA: 7.500,00 EUR\nClassificação CPV (Vocabulário Comum para os Contratos Públicos)\nObjeto principal\nVocabulário Principal: 15100000\nNº: LOT-0017\nDescrição do Lote: Perna de porco sem osso fresca\nPreço base s/IVA: 900,00 EUR\nClassificação CPV (Vocabulário Comum para os Contratos Públicos)\nObjeto principal\nVocabulário Principal: 15100000\nNº: LOT-0018\nDescrição do Lote: Rojões frescos\nPreço base s/IVA: 9.400,00 EUR\nClassificação CPV (Vocabulário Comum para os Contratos Públicos)\nObjeto principal\nVocabulário Principal: 15100000\nNº: LOT-0019\nDescrição do Lote: Strogonoff de porco fresco\nPreço base s/IVA: 480,00 EUR\nClassificação CPV (Vocabulário Comum para os Contratos Públicos)\nObjeto principal\nVocabulário Principal: 15100000\nNº: LOT-0020\nDescrição do Lote: Secretos de porco preto cortados\nPreço base s/IVA: 1.800,00 EUR\nClassificação CPV (Vocabulário Comum para os Contratos Públicos)\nObjeto principal\nVocabulário Principal: 15100000\nNº: LOT-0021\nDescrição do Lote: Pernil de porco\nPreço base s/IVA: 40,00 EUR\nClassificação CPV (Vocabulário Comum para os Contratos Públicos)\nObjeto principal\nVocabulário Principal: 15100000\nNº: LOT-0022\nDescrição do Lote: Cachaço de porco sem osso\nPreço base s/IVA: 100,00 EUR\nClassificação CPV (Vocabulário Comum para os Contratos Públicos)\nObjeto principal\nVocabulário Principal: 15100000\nNº: LOT-0023\nDescrição do Lote: Lagartinhos\nPreço base s/IVA: 1.400,00 EUR\nClassificação CPV (Vocabulário Comum para os Contratos Públicos)\nObjeto principal\nVocabulário Principal: 15100000\nNº: LOT-0024\nDescrição do Lote: Bife de vitela pojadouro fresco\nPreço base s/IVA: 9.000,00 EUR\nClassificação CPV (Vocabulário Comum para os Contratos Públicos)\nObjeto principal\nVocabulário Principal: 15100000\nNº: LOT-0025\nDescrição do Lote: Bife de vitela da vazia fresco\nPreço base s/IVA: 200,00 EUR\nClassificação CPV (Vocabulário Comum para os Contratos Públicos)\nObjeto principal\nVocabulário Principal: 15100000\nNº: LOT-0026\nDescrição do Lote: Bife de vitela alcatra\nPreço base s/IVA: 200,00 EUR\nClassificação CPV (Vocabulário Comum para os Contratos Públicos)\nObjeto principal\nVocabulário Principal: 15100000\nNº: LOT-0027\nDescrição do Lote: Carne picada vaca fresca\nPreço base s/IVA: 2.100,00 EUR\nClassificação CPV (Vocabulário Comum para os Contratos Públicos)\nObjeto principal\nVocabulário Principal: 15100000\nNº: LOT-0028\nDescrição do Lote: Carne vitela para cozer/estufar fresca\nPreço base s/IVA: 180,00 EUR\nClassificação CPV (Vocabulário Comum para os Contratos Públicos)\nObjeto principal\nVocabulário Principal: 15100000\nNº: LOT-0029\nDescrição do Lote: Chambão de novilho fresco\nPreço base s/IVA: 1.840,00 EUR\nClassificação CPV (Vocabulário Comum para os Contratos Públicos)\nObjeto principal\nVocabulário Principal: 15100000\nNº: LOT-0030\nDescrição do Lote: Dobrada fresca\nPreço base s/IVA: 60,00 EUR\nClassificação CPV (Vocabulário Comum para os Contratos Públicos)\nObjeto principal\nVocabulário Principal: 15100000\nNº: LOT-0031\nDescrição do Lote: Escalopes de vitela frescos\nPreço base s/IVA: 45,00 EUR\nClassificação CPV (Vocabulário Comum para os Contratos Públicos)\nObjeto principal\nVocabulário Principal: 15100000\nNº: LOT-0032\nDescrição do Lote: Jardineira de novilho fresca\nPreço base s/IVA: 9.000,00 EUR\nClassificação CPV (Vocabulário Comum para os Contratos Públicos)\nObjeto principal\nVocabulário Principal: 15100000\nNº: LOT-0033\nDescrição do Lote: Maminha fresca\nPreço base s/IVA: 1.035,00 EUR\nClassificação CPV (Vocabulário Comum para os Contratos Públicos)\nObjeto principal\nVocabulário Principal: 15100000\nNº: LOT-0034\nDescrição do Lote: Ossobuco fresco\nPreço base s/IVA: 825,00 EUR\nClassificação CPV (Vocabulário Comum para os Contratos Públicos)\nObjeto principal\nVocabulário Principal: 15100000\nNº: LOT-0035\nDescrição do Lote: Picanha fresca\nPreço base s/IVA: 55,00 EUR\nClassificação CPV (Vocabulário Comum para os Contratos Públicos)\nObjeto principal\nVocabulário Principal: 15100000\nNº: LOT-0036\nDescrição do Lote: Strogonoff de vitela fresco\nPreço base s/IVA: 5.000,00 EUR\nClassificação CPV (Vocabulário Comum para os Contratos Públicos)\nObjeto principal\nVocabulário Principal: 15100000\nNº: LOT-0037\nDescrição do Lote: Tranches de vitela frescas\nPreço base s/IVA: 7.000,00 EUR\nClassificação CPV (Vocabulário Comum para os Contratos Públicos)\nObjeto principal\nVocabulário Principal: 15100000\nNº: LOT-0038\nDescrição do Lote: Borrego para assar/estufar fresco\nPreço base s/IVA: 3.800,00 EUR\nClassificação CPV (Vocabulário Comum para os Contratos Públicos)\nObjeto principal\nVocabulário Principal: 15100000\nNº: LOT-0039\nDescrição do Lote: Mão de borrego c/ osso fresca\nPreço base s/IVA: 95,00 EUR\nClassificação CPV (Vocabulário Comum para os Contratos Públicos)\nObjeto principal\nVocabulário Principal: 15100000\nNº: LOT-0040\nDescrição do Lote: Perna de borrego fresca\nPreço base s/IVA: 3.150,00 EUR\nClassificação CPV (Vocabulário Comum para os Contratos Públicos)\nObjeto principal\nVocabulário Principal: 15100000\nNº: LOT-0041\nDescrição do Lote: Perna de borrego sem osso fresca\nPreço base s/IVA: 105,00 EUR\nClassificação CPV (Vocabulário Comum para os Contratos Públicos)\nObjeto principal\nVocabulário Principal: 15100000\nNº: LOT-0042\nDescrição do Lote: Bife de peru fresco\nPreço base s/IVA: 17.500,00 EUR\nClassificação CPV (Vocabulário Comum para os Contratos Públicos)\nObjeto principal\nVocabulário Principal: 15100000\nNº: LOT-0043\nDescrição do Lote: Espetada de peru fresca\nPreço base s/IVA: 5.500,00 EUR\nClassificação CPV (Vocabulário Comum para os Contratos Públicos)\nObjeto principal\nVocabulário Principal: 15100000\nNº: LOT-0044\nDescrição do Lote: Frango coto\nPreço base s/IVA: 10,00 EUR\nClassificação CPV (Vocabulário Comum para os Contratos Públicos)\nObjeto principal\nVocabulário Principal: 15100000\nNº: LOT-0045\nDescrição do Lote: Frango do campo fresco c/ sangue\nPreço base s/IVA: 660,00 EUR\nClassificação CPV (Vocabulário Comum para os Contratos Públicos)\nObjeto principal\nVocabulário Principal: 15100000\nNº: LOT-0046\nDescrição do Lote: Frango Fresco Classe A1100 / 1200\nPreço base s/IVA: 23.250,00 EUR\nClassificação CPV (Vocabulário Comum para os Contratos Públicos)\nObjeto principal\nVocabulário Principal: 15100000\nNº: LOT-0047\nDescrição do Lote: Galinha fresca inteira c/ miúdos\nPreço base s/IVA: 250,00 EUR\nClassificação CPV (Vocabulário Comum para os Contratos Públicos)\nObjeto principal\nVocabulário Principal: 15100000\nNº: LOT-0048\nDescrição do Lote: Moelas de frango frescas\nPreço base s/IVA: 75,00 EUR\nClassificação CPV (Vocabulário Comum para os Contratos Públicos)\nObjeto principal\nVocabulário Principal: 15100000\nNº: LOT-0049\nDescrição do Lote: Ovo Cozido Balde 70 Un.\nPreço base s/IVA: 3.420,00 EUR\nClassificação CPV (Vocabulário Comum para os Contratos Públicos)\nObjeto principal\nVocabulário Principal: 15100000\nNº: LOT-0050\nDescrição do Lote: Ovo Liquido Pasteurizado Inteiro Fresco 1Kg\nPreço base s/IVA: 2.460,00 EUR\nClassificação CPV (Vocabulário Comum para os Contratos Públicos)\nObjeto principal\nVocabulário Principal: 15100000\nNº: LOT-0051\nDescrição do Lote: Ovos frescos classe M\nPreço base s/IVA: 460,00 EUR\nClassificação CPV (Vocabulário Comum para os Contratos Públicos)\nObjeto principal\nVocabulário Principal: 15100000\nNº: LOT-0052\nDescrição do Lote: Ovos frescos classe L\nPreço base s/IVA: 500,00 EUR\nClassificação CPV (Vocabulário Comum para os Contratos Públicos)\nObjeto principal\nVocabulário Principal: 15100000\nNº: LOT-0053\nDescrição do Lote: Pato inteiro fresco\nPreço base s/IVA: 4.080,00 EUR\nClassificação CPV (Vocabulário Comum para os Contratos Públicos)\nObjeto principal\nVocabulário Principal: 15100000\nNº: LOT-0054\nDescrição do Lote: Bife de frango fresco\nPreço base s/IVA: 2.100,00 EUR\nClassificação CPV (Vocabulário Comum para os Contratos Públicos)\nObjeto principal\nVocabulário Principal: 15100000\nNº: LOT-0055\nDescrição do Lote: Peito de frango congelado\nPreço base s/IVA: 550,00 EUR\nClassificação CPV (Vocabulário Comum para os Contratos Públicos)\nObjeto principal\nVocabulário Principal: 15100000\nNº: LOT-0056\nDescrição do Lote: Peito de frango fresco\nPreço base s/IVA: 600,00 EUR\nClassificação CPV (Vocabulário Comum para os Contratos Públicos)\nObjeto principal\nVocabulário Principal: 15100000\nNº: LOT-0057\nDescrição do Lote: Peito de peru fresco\nPreço base s/IVA: 7.650,00 EUR\nClassificação CPV (Vocabulário Comum para os Contratos Públicos)\nObjeto principal\nVocabulário Principal: 15100000\nNº: LOT-0058\nDescrição do Lote: Perna de frango congelada\nPreço base s/IVA: 250,00 EUR\nClassificação CPV (Vocabulário Comum para os Contratos Públicos)\nObjeto principal\nVocabulário Principal: 15100000\nNº: LOT-0059\nDescrição do Lote: Perna de frango fresca\nPreço base s/IVA: 128,00 EUR\nClassificação CPV (Vocabulário Comum para os Contratos Públicos)\nObjeto principal\nVocabulário Principal: 15100000\nNº: LOT-0060\nDescrição do Lote: Perna de peru fresca\nPreço base s/IVA: 13.750,00 EUR\nClassificação CPV (Vocabulário Comum para os Contratos Públicos)\nObjeto principal\nVocabulário Principal: 15100000\nNº: LOT-0061\nDescrição do Lote: Strogonoff de frango fresco\nPreço base s/IVA: 3.500,00 EUR\nClassificação CPV (Vocabulário Comum para os Contratos Públicos)\nObjeto principal\nVocabulário Principal: 15100000\nNº: LOT-0062\nDescrição do Lote: Strogonoff de peru fresco\nPreço base s/IVA: 3.700,00 EUR\nClassificação CPV (Vocabulário Comum para os Contratos Públicos)\nObjeto principal\nVocabulário Principal: 15100000\nNº: LOT-0063\nDescrição do Lote: Coelho inteiro fresco\nPreço base s/IVA: 700,00 EUR\nClassificação CPV (Vocabulário Comum para os Contratos Públicos)\nObjeto principal\nVocabulário Principal: 15100000\nNº: LOT-0064\nDescrição do Lote: Chouriço carne extra\nPreço base s/IVA: 48,00 EUR\nClassificação CPV (Vocabulário Comum para os Contratos Públicos)\nObjeto principal\nVocabulário Principal: 15100000\nNº: LOT-0065\nDescrição do Lote: Toucinho\nPreço base s/IVA: 27,50 EUR\nClassificação CPV (Vocabulário Comum para os Contratos Públicos)\nObjeto principal\nVocabulário Principal: 15100000\nNº: LOT-0066\nDescrição do Lote: Paio York\nPreço base s/IVA: 30,00 EUR\nClassificação CPV (Vocabulário Comum para os Contratos Públicos)\nObjeto principal\nVocabulário Principal: 15100000\nNº: LOT-0067\nDescrição do Lote: Morcela de sangue\nPreço base s/IVA: 55,00 EUR\nClassificação CPV (Vocabulário Comum para os Contratos Públicos)\nObjeto principal\nVocabulário Principal: 15100000\nNº: LOT-0068\nDescrição do Lote: Presunto fatiado emb. 200gr \nPreço base s/IVA: 26,50 EUR\nClassificação CPV (Vocabulário Comum para os Contratos Públicos)\nObjeto principal\nVocabulário Principal: 15100000\nNº: LOT-0069\nDescrição do Lote: Chouriço preto\nPreço base s/IVA: 210,00 EUR\nClassificação CPV (Vocabulário Comum para os Contratos Públicos)\nObjeto principal\nVocabulário Principal: 15100000\nNº: LOT-0070\nDescrição do Lote: Chourição\nPreço base s/IVA: 225,00 EUR\nClassificação CPV (Vocabulário Comum para os Contratos Públicos)\nObjeto principal\nVocabulário Principal: 15100000\nNº: LOT-0071\nDescrição do Lote: Bacon fatiado emb. 500gr\nPreço base s/IVA: 168,00 EUR\nClassificação CPV (Vocabulário Comum para os Contratos Públicos)\nObjeto principal\nVocabulário Principal: 15100000\nNº: LOT-0072\nDescrição do Lote: Presunto fatiado emb. 500gr \nPreço base s/IVA: 2.520,00 EUR\nClassificação CPV (Vocabulário Comum para os Contratos Públicos)\nObjeto principal\nVocabulário Principal: 15100000\nNº: LOT-0073\nDescrição do Lote: Farinheira\nPreço base s/IVA: 270,00 EUR\nClassificação CPV (Vocabulário Comum para os Contratos Públicos)\nObjeto principal\nVocabulário Principal: 15100000\nNº: LOT-0074\nDescrição do Lote: Alheira\nPreço base s/IVA: 700,00 EUR\nClassificação CPV (Vocabulário Comum para os Contratos Públicos)\nObjeto principal\nVocabulário Principal: 15100000\nNº: LOT-0075\nDescrição do Lote: Presunto s/ osso\nPreço base s/IVA: 280,00 EUR\nClassificação CPV (Vocabulário Comum para os Contratos Públicos)\nObjeto principal\nVocabulário Principal: 15100000\nNº: LOT-0076\nDescrição do Lote: Bacon\nPreço base s/IVA: 845,00 EUR\nClassificação CPV (Vocabulário Comum para os Contratos Públicos)\nObjeto principal\nVocabulário Principal: 15100000\nNº: LOT-0077\nDescrição do Lote: Chouriço corrente\nPreço base s/IVA: 800,00 EUR\nClassificação CPV (Vocabulário Comum para os Contratos Públicos)\nObjeto principal\nVocabulário Principal: 15100000\nNº: LOT-0078\nDescrição do Lote: Fiambre da perna\nPreço base s/IVA: 9.350,00 EUR\nClassificação CPV (Vocabulário Comum para os Contratos Públicos)\nObjeto principal\nVocabulário Principal: 15100000\nNº: LOT-0079\nDescrição do Lote: Almôndegas de bovino frescas\nPreço base s/IVA: 60,00 EUR\nClassificação CPV (Vocabulário Comum para os Contratos Públicos)\nObjeto principal\nVocabulário Principal: 15100000\nNº: LOT-0080\nDescrição do Lote: Almôndegas de aves frescas\nPreço base s/IVA: 2.250,00 EUR\nClassificação CPV (Vocabulário Comum para os Contratos Públicos)\nObjeto principal\nVocabulário Principal: 15100000\nNº: LOT-0081\nDescrição do Lote: Carne moída mista fresca (suíno e bovino)\nPreço base s/IVA: 26,00 EUR\nClassificação CPV (Vocabulário Comum para os Contratos Públicos)\nObjeto principal\nVocabulário Principal: 15100000\nNº: LOT-0082\nDescrição do Lote: Chamuça congelada miniatura cx de 200 unidades \nPreço base s/IVA: 2.695,00 EUR\nClassificação CPV (Vocabulário Comum para os Contratos Públicos)\nObjeto principal\nVocabulário Principal: 15100000\nNº: LOT-0083\nDescrição do Lote: Croquetes carne miniatura cx de 150 unidades \nPreço base s/IVA: 1.250,00 EUR\nClassificação CPV (Vocabulário Comum para os Contratos Públicos)\nObjeto principal\nVocabulário Principal: 15100000\nNº: LOT-0084\nDescrição do Lote: Croquetes carne miniatura cx de 200 unidades\nPreço base s/IVA: 1.200,00 EUR\nClassificação CPV (Vocabulário Comum para os Contratos Públicos)\nObjeto principal\nVocabulário Principal: 15100000\nNº: LOT-0085\nDescrição do Lote: Croquetes congelados (cantina)  cx de 125 unidades \nPreço base s/IVA: 720,00 EUR\nClassificação CPV (Vocabulário Comum para os Contratos Públicos)\nObjeto principal\nVocabulário Principal: 15100000\nNº: LOT-0086\nDescrição do Lote: Croquetes congelados (cantina)  cx de 50 unidades \nPreço base s/IVA: 200,00 EUR\nClassificação CPV (Vocabulário Comum para os Contratos Públicos)\nObjeto principal\nVocabulário Principal: 15100000\nNº: LOT-0087\nDescrição do Lote: Hamburgers de aves\nPreço base s/IVA: 2.700,00 EUR\nClassificação CPV (Vocabulário Comum para os Contratos Públicos)\nObjeto principal\nVocabulário Principal: 15100000\nNº: LOT-0088\nDescrição do Lote: Lasanha de carne CX 6 KG\nPreço base s/IVA: 5.800,00 EUR\nClassificação CPV (Vocabulário Comum para os Contratos Públicos)\nObjeto principal\nVocabulário Principal: 15100000\nNº: LOT-0089\nDescrição do Lote: Rissóis de carne (cantina) cx de 100 unidades \nPreço base s/IVA: 460,00 EUR\nClassificação CPV (Vocabulário Comum para os Contratos Públicos)\nObjeto principal\nVocabulário Principal: 15100000\nNº: LOT-0090\nDescrição do Lote: Rissóis de carne miniatura cx de 150 unidades\nPreço base s/IVA: 480,00 EUR\nClassificação CPV (Vocabulário Comum para os Contratos Públicos)\nObjeto principal\nVocabulário Principal: 15100000\nNº: LOT-0091\nDescrição do Lote: Salsicha Toscana fresca\nPreço base s/IVA: 500,00 EUR\nClassificação CPV (Vocabulário Comum para os Contratos Públicos)\nObjeto principal\nVocabulário Principal: 15100000\nNº: LOT-0092\nDescrição do Lote: Salsichas frescas de aves\nPreço base s/IVA: 450,00 EUR\nClassificação CPV (Vocabulário Comum para os Contratos Públicos)\nObjeto principal\nVocabulário Principal: 15100000\nNº: LOT-0093\nDescrição do Lote: Salsichas frescas de porco\nPreço base s/IVA: 96,00 EUR\nClassificação CPV (Vocabulário Comum para os Contratos Públicos)\nObjeto principal\nVocabulário Principal: 15100000\n\n7 - INDICAÇÕES ADICIONAIS\nO contrato envolve aquisição conjunta (satisfação de várias entidades)? Não\nO contrato é adjudicado por uma central de compras? Não\n\n8 - TÉCNICAS\nO concurso destina-se à celebração de um acordo-quadro? Inexistência de acordo-quadro\nÉ utilizado um leilão eletrónico? Não\nÉ adotada uma fase de negociação? Não\nSistema de Aquisição Dinâmico: Inexistência de sistema de aquisição dinâmico\n\n9 - LOCAL DA EXECUÇÃO DO CONTRATO\nLOCAL DA EXECUÇÃO DO CONTRATO (PROCEDIMENTO)\nLOCAL DA EXECUÇÃO DO CONTRATO (LOTE)\nIdentificador do Lote: LOT-0001\nPaís: Portugal\nNUT III: PT150\nLocalidade: Faro\nDistrito: Faro\nConcelho: Faro\nFreguesia: Todas\nIdentificador do Lote: LOT-0002\nPaís: Portugal\nNUT III: PT150\nLocalidade: Faro\nDistrito: Faro\nConcelho: Faro\nFreguesia: Todas\nIdentificador do Lote: LOT-0003\nPaís: Portugal\nNUT III: PT150\nLocalidade: Faro\nDistrito: Faro\nConcelho: Faro\nFreguesia: Todas\nIdentificador do Lote: LOT-0004\nPaís: Portugal\nNUT III: PT150\nLocalidade: Faro\nDistrito: Faro\nConcelho: Faro\nFreguesia: Todas\nIdentificador do Lote: LOT-0005\nPaís: Portugal\nNUT III: PT150\nLocalidade: Faro\nDistrito: Faro\nConcelho: Faro\nFreguesia: Todas\nIdentificador do Lote: LOT-0006\nPaís: Portugal\nNUT III: PT150\nLocalidade: Faro\nDistrito: Faro\nConcelho: Faro\nFreguesia: Todas\nIdentificador do Lote: LOT-0007\nPaís: Portugal\nNUT III: PT150\nLocalidade: Faro\nDistrito: Faro\nConcelho: Faro\nFreguesia: Todas\nIdentificador do Lote: LOT-0008\nPaís: Portugal\nNUT III: PT150\nLocalidade: Faro\nDistrito: Faro\nConcelho: Faro\nFreguesia: Todas\nIdentificador do Lote: LOT-0009\nPaís: Portugal\nNUT III: PT150\nLocalidade: Faro\nDistrito: Faro\nConcelho: Faro\nFreguesia: Todas\nIdentificador do Lote: LOT-0010\nPaís: Portugal\nNUT III: PT150\nLocalidade: Faro\nDistrito: Faro\nConcelho: Faro\nFreguesia: Todas\nIdentificador do Lote: LOT-0011\nPaís: Portugal\nNUT III: PT150\nLocalidade: Faro\nDistrito: Faro\nConcelho: Faro\nFreguesia: Todas\nIdentificador do Lote: LOT-0012\nPaís: Portugal\nNUT III: PT150\nLocalidade: Faro\nDistrito: Faro\nConcelho: Faro\nFreguesia: Todas\nIdentificador do Lote: LOT-0013\nPaís: Portugal\nNUT III: PT150\nLocalidade: Faro\nDistrito: Faro\nConcelho: Faro\nFreguesia: Todas\nIdentificador do Lote: LOT-0014\nPaís: Portugal\nNUT III: PT150\nLocalidade: Faro\nDistrito: Faro\nConcelho: Faro\nFreguesia: Todas\nIdentificador do Lote: LOT-0015\nPaís: Portugal\nNUT III: PT150\nLocalidade: Faro\nDistrito: Faro\nConcelho: Faro\nFreguesia: Todas\nIdentificador do Lote: LOT-0016\nPaís: Portugal\nNUT III: PT150\nLocalidade: Faro\nDistrito: Faro\nConcelho: Faro\nFreguesia: Todas\nIdentificador do Lote: LOT-0017\nPaís: Portugal\nNUT III: PT150\nLocalidade: Faro\nDistrito: Faro\nConcelho: Faro\nFreguesia: Todas\nIdentificador do Lote: LOT-0018\nPaís: Portugal\nNUT III: PT150\nLocalidade: Faro\nDistrito: Faro\nConcelho: Faro\nFreguesia: Todas\nIdentificador do Lote: LOT-0019\nPaís: Portugal\nNUT III: PT150\nLocalidade: Faro\nDistrito: Faro\nConcelho: Faro\nFreguesia: Todas\nIdentificador do Lote: LOT-0020\nPaís: Portugal\nNUT III: PT150\nLocalidade: Faro\nDistrito: Faro\nConcelho: Faro\nFreguesia: Todas\nIdentificador do Lote: LOT-0021\nPaís: Portugal\nNUT III: PT150\nLocalidade: Faro\nDistrito: Faro\nConcelho: Faro\nFreguesia: Todas\nIdentificador do Lote: LOT-0022\nPaís: Portugal\nNUT III: PT150\nLocalidade: Faro\nDistrito: Faro\nConcelho: Faro\nFreguesia: Todas\nIdentificador do Lote: LOT-0023\nPaís: Portugal\nNUT III: PT150\nLocalidade: Faro\nDistrito: Faro\nConcelho: Faro\nFreguesia: Todas\nIdentificador do Lote: LOT-0024\nPaís: Portugal\nNUT III: PT150\nLocalidade: Faro\nDistrito: Faro\nConcelho: Faro\nFreguesia: Todas\nIdentificador do Lote: LOT-0025\nPaís: Portugal\nNUT III: PT150\nLocalidade: Faro\nDistrito: Faro\nConcelho: Faro\nFreguesia: Todas\nIdentificador do Lote: LOT-0026\nPaís: Portugal\nNUT III: PT150\nLocalidade: Faro\nDistrito: Faro\nConcelho: Faro\nFreguesia: Todas\nIdentificador do Lote: LOT-0027\nPaís: Portugal\nNUT III: PT150\nLocalidade: Faro\nDistrito: Faro\nConcelho: Faro\nFreguesia: Todas\nIdentificador do Lote: LOT-0028\nPaís: Portugal\nNUT III: PT150\nLocalidade: Faro\nDistrito: Faro\nConcelho: Faro\nFreguesia: Todas\nIdentificador do Lote: LOT-0029\nPaís: Portugal\nNUT III: PT150\nLocalidade: Faro\nDistrito: Faro\nConcelho: Faro\nFreguesia: Todas\nIdentificador do Lote: LOT-0030\nPaís: Portugal\nNUT III: PT150\nLocalidade: Faro\nDistrito: Faro\nConcelho: Faro\nFreguesia: Todas\nIdentificador do Lote: LOT-0031\nPaís: Portugal\nNUT III: PT150\nLocalidade: Faro\nDistrito: Faro\nConcelho: Faro\nFreguesia: Todas\nIdentificador do Lote: LOT-0032\nPaís: Portugal\nNUT III: PT150\nLocalidade: Faro\nDistrito: Faro\nConcelho: Faro\nFreguesia: Todas\nIdentificador do Lote: LOT-0033\nPaís: Portugal\nNUT III: PT150\nLocalidade: Faro\nDistrito: Faro\nConcelho: Faro\nFreguesia: Todas\nIdentificador do Lote: LOT-0034\nPaís: Portugal\nNUT III: PT150\nLocalidade: Faro\nDistrito: Faro\nConcelho: Faro\nFreguesia: Todas\nIdentificador do Lote: LOT-0035\nPaís: Portugal\nNUT III: PT150\nLocalidade: Faro\nDistrito: Faro\nConcelho: Faro\nFreguesia: Todas\nIdentificador do Lote: LOT-0036\nPaís: Portugal\nNUT III: PT150\nLocalidade: Faro\nDistrito: Faro\nConcelho: Faro\nFreguesia: Todas\nIdentificador do Lote: LOT-0037\nPaís: Portugal\nNUT III: PT150\nLocalidade: Faro\nDistrito: Faro\nConcelho: Faro\nFreguesia: Todas\nIdentificador do Lote: LOT-0038\nPaís: Portugal\nNUT III: PT150\nLocalidade: Faro\nDistrito: Faro\nConcelho: Faro\nFreguesia: Todas\nIdentificador do Lote: LOT-0039\nPaís: Portugal\nNUT III: PT150\nLocalidade: Faro\nDistrito: Faro\nConcelho: Faro\nFreguesia: Todas\nIdentificador do Lote: LOT-0040\nPaís: Portugal\nNUT III: PT150\nLocalidade: Faro\nDistrito: Faro\nConcelho: Faro\nFreguesia: Todas\nIdentificador do Lote: LOT-0041\nPaís: Portugal\nNUT III: PT150\nLocalidade: Faro\nDistrito: Faro\nConcelho: Faro\nFreguesia: Todas\nIdentificador do Lote: LOT-0042\nPaís: Portugal\nNUT III: PT150\nLocalidade: Faro\nDistrito: Faro\nConcelho: Faro\nFreguesia: Todas\nIdentificador do Lote: LOT-0043\nPaís: Portugal\nNUT III: PT150\nLocalidade: Faro\nDistrito: Faro\nConcelho: Faro\nFreguesia: Todas\nIdentificador do Lote: LOT-0044\nPaís: Portugal\nNUT III: PT150\nLocalidade: Faro\nDistrito: Faro\nConcelho: Faro\nFreguesia: Todas\nIdentificador do Lote: LOT-0045\nPaís: Portugal\nNUT III: PT150\nLocalidade: Faro\nDistrito: Faro\nConcelho: Faro\nFreguesia: Todas\nIdentificador do Lote: LOT-0046\nPaís: Portugal\nNUT III: PT150\nLocalidade: Faro\nDistrito: Faro\nConcelho: Faro\nFreguesia: Todas\nIdentificador do Lote: LOT-0047\nPaís: Portugal\nNUT III: PT150\nLocalidade: Faro\nDistrito: Faro\nConcelho: Faro\nFreguesia: Todas\nIdentificador do Lote: LOT-0048\nPaís: Portugal\nNUT III: PT150\nLocalidade: Faro\nDistrito: Faro\nConcelho: Faro\nFreguesia: Todas\nIdentificador do Lote: LOT-0049\nPaís: Portugal\nNUT III: PT150\nLocalidade: Faro\nDistrito: Faro\nConcelho: Faro\nFreguesia: Todas\nIdentificador do Lote: LOT-0050\nPaís: Portugal\nNUT III: PT150\nLocalidade: Faro\nDistrito: Faro\nConcelho: Faro\nFreguesia: Todas\nIdentificador do Lote: LOT-0051\nPaís: Portugal\nNUT III: PT150\nLocalidade: Faro\nDistrito: Faro\nConcelho: Faro\nFreguesia: Todas\nIdentificador do Lote: LOT-0052\nPaís: Portugal\nNUT III: PT150\nLocalidade: Faro\nDistrito: Faro\nConcelho: Faro\nFreguesia: Todas\nIdentificador do Lote: LOT-0053\nPaís: Portugal\nNUT III: PT150\nLocalidade: Faro\nDistrito: Faro\nConcelho: Faro\nFreguesia: Todas\nIdentificador do Lote: LOT-0054\nPaís: Portugal\nNUT III: PT150\nLocalidade: Faro\nDistrito: Faro\nConcelho: Faro\nFreguesia: Todas\nIdentificador do Lote: LOT-0055\nPaís: Portugal\nNUT III: PT150\nLocalidade: Faro\nDistrito: Faro\nConcelho: Faro\nFreguesia: Todas\nIdentificador do Lote: LOT-0056\nPaís: Portugal\nNUT III: PT150\nLocalidade: Faro\nDistrito: Faro\nConcelho: Faro\nFreguesia: Todas\nIdentificador do Lote: LOT-0057\nPaís: Portugal\nNUT III: PT150\nLocalidade: Faro\nDistrito: Faro\nConcelho: Faro\nFreguesia: Todas\nIdentificador do Lote: LOT-0058\nPaís: Portugal\nNUT III: PT150\nLocalidade: Faro\nDistrito: Faro\nConcelho: Faro\nFreguesia: Todas\nIdentificador do Lote: LOT-0059\nPaís: Portugal\nNUT III: PT150\nLocalidade: Faro\nDistrito: Faro\nConcelho: Faro\nFreguesia: Todas\nIdentificador do Lote: LOT-0060\nPaís: Portugal\nNUT III: PT150\nLocalidade: Faro\nDistrito: Faro\nConcelho: Faro\nFreguesia: Todas\nIdentificador do Lote: LOT-0061\nPaís: Portugal\nNUT III: PT150\nLocalidade: Faro\nDistrito: Faro\nConcelho: Faro\nFreguesia: Todas\nIdentificador do Lote: LOT-0062\nPaís: Portugal\nNUT III: PT150\nLocalidade: Faro\nDistrito: Faro\nConcelho: Faro\nFreguesia: Todas\nIdentificador do Lote: LOT-0063\nPaís: Portugal\nNUT III: PT150\nLocalidade: Faro\nDistrito: Faro\nConcelho: Faro\nFreguesia: Todas\nIdentificador do Lote: LOT-0064\nPaís: Portugal\nNUT III: PT150\nLocalidade: Faro\nDistrito: Faro\nConcelho: Faro\nFreguesia: Todas\nIdentificador do Lote: LOT-0065\nPaís: Portugal\nNUT III: PT150\nLocalidade: Faro\nDistrito: Faro\nConcelho: Faro\nFreguesia: Todas\nIdentificador do Lote: LOT-0066\nPaís: Portugal\nNUT III: PT150\nLocalidade: Faro\nDistrito: Faro\nConcelho: Faro\nFreguesia: Todas\nIdentificador do Lote: LOT-0067\nPaís: Portugal\nNUT III: PT150\nLocalidade: Faro\nDistrito: Faro\nConcelho: Faro\nFreguesia: Todas\nIdentificador do Lote: LOT-0068\nPaís: Portugal\nNUT III: PT150\nLocalidade: Faro\nDistrito: Faro\nConcelho: Faro\nFreguesia: Todas\nIdentificador do Lote: LOT-0069\nPaís: Portugal\nNUT III: PT150\nLocalidade: Faro\nDistrito: Faro\nConcelho: Faro\nFreguesia: Todas\nIdentificador do Lote: LOT-0070\nPaís: Portugal\nNUT III: PT150\nLocalidade: Faro\nDistrito: Faro\nConcelho: Faro\nFreguesia: Todas\nIdentificador do Lote: LOT-0071\nPaís: Portugal\nNUT III: PT150\nLocalidade: Faro\nDistrito: Faro\nConcelho: Faro\nFreguesia: Todas\nIdentificador do Lote: LOT-0072\nPaís: Portugal\nNUT III: PT150\nLocalidade: Faro\nDistrito: Faro\nConcelho: Faro\nFreguesia: Todas\nIdentificador do Lote: LOT-0073\nPaís: Portugal\nNUT III: PT150\nLocalidade: Faro\nDistrito: Faro\nConcelho: Faro\nFreguesia: Todas\nIdentificador do Lote: LOT-0074\nPaís: Portugal\nNUT III: PT150\nLocalidade: Faro\nDistrito: Faro\nConcelho: Faro\nFreguesia: Todas\nIdentificador do Lote: LOT-0075\nPaís: Portugal\nNUT III: PT150\nLocalidade: Faro\nDistrito: Faro\nConcelho: Faro\nFreguesia: Todas\nIdentificador do Lote: LOT-0076\nPaís: Portugal\nNUT III: PT150\nLocalidade: Faro\nDistrito: Faro\nConcelho: Faro\nFreguesia: Todas\nIdentificador do Lote: LOT-0077\nPaís: Portugal\nNUT III: PT150\nLocalidade: Faro\nDistrito: Faro\nConcelho: Faro\nFreguesia: Todas\nIdentificador do Lote: LOT-0078\nPaís: Portugal\nNUT III: PT150\nLocalidade: Faro\nDistrito: Faro\nConcelho: Faro\nFreguesia: Todas\nIdentificador do Lote: LOT-0079\nPaís: Portugal\nNUT III: PT150\nLocalidade: Faro\nDistrito: Faro\nConcelho: Faro\nFreguesia: Todas\nIdentificador do Lote: LOT-0080\nPaís: Portugal\nNUT III: PT150\nLocalidade: Faro\nDistrito: Faro\nConcelho: Faro\nFreguesia: Todas\nIdentificador do Lote: LOT-0081\nPaís: Portugal\nNUT III: PT150\nLocalidade: Faro\nDistrito: Faro\nConcelho: Faro\nFreguesia: Todas\nIdentificador do Lote: LOT-0082\nPaís: Portugal\nNUT III: PT150\nLocalidade: Faro\nDistrito: Faro\nConcelho: Faro\nFreguesia: Todas\nIdentificador do Lote: LOT-0083\nPaís: Portugal\nNUT III: PT150\nLocalidade: Faro\nDistrito: Faro\nConcelho: Faro\nFreguesia: Todas\nIdentificador do Lote: LOT-0084\nPaís: Portugal\nNUT III: PT150\nLocalidade: Faro\nDistrito: Faro\nConcelho: Faro\nFreguesia: Todas\nIdentificador do Lote: LOT-0085\nPaís: Portugal\nNUT III: PT150\nLocalidade: Faro\nDistrito: Faro\nConcelho: Faro\nFreguesia: Todas\nIdentificador do Lote: LOT-0086\nPaís: Portugal\nNUT III: PT150\nLocalidade: Faro\nDistrito: Faro\nConcelho: Faro\nFreguesia: Todas\nIdentificador do Lote: LOT-0087\nPaís: Portugal\nNUT III: PT150\nLocalidade: Faro\nDistrito: Faro\nConcelho: Faro\nFreguesia: Todas\nIdentificador do Lote: LOT-0088\nPaís: Portugal\nNUT III: PT150\nLocalidade: Faro\nDistrito: Faro\nConcelho: Faro\nFreguesia: Todas\nIdentificador do Lote: LOT-0089\nPaís: Portugal\nNUT III: PT150\nLocalidade: Faro\nDistrito: Faro\nConcelho: Faro\nFreguesia: Todas\nIdentificador do Lote: LOT-0090\nPaís: Portugal\nNUT III: PT150\nLocalidade: Faro\nDistrito: Faro\nConcelho: Faro\nFreguesia: Todas\nIdentificador do Lote: LOT-0091\nPaís: Portugal\nNUT III: PT150\nLocalidade: Faro\nDistrito: Faro\nConcelho: Faro\nFreguesia: Todas\nIdentificador do Lote: LOT-0092\nPaís: Portugal\nNUT III: PT150\nLocalidade: Faro\nDistrito: Faro\nConcelho: Faro\nFreguesia: Todas\nIdentificador do Lote: LOT-0093\nPaís: Portugal\nNUT III: PT150\nLocalidade: Faro\nDistrito: Faro\nConcelho: Faro\nFreguesia: Todas\n\n10 - PRAZO DE EXECUÇÃO DO CONTRATO\nIdentificador do Lote: LOT-0001\nPrazo de execução do contrato: 1 ANOS\nPrevisão de renovações: Não\nIdentificador do Lote: LOT-0002\nPrazo de execução do contrato: 1 ANOS\nPrevisão de renovações: Não\nIdentificador do Lote: LOT-0003\nPrazo de execução do contrato: 1 ANOS\nPrevisão de renovações: Não\nIdentificador do Lote: LOT-0004\nPrazo de execução do contrato: 1 ANOS\nPrevisão de renovações: Não\nIdentificador do Lote: LOT-0005\nPrazo de execução do contrato: 1 ANOS\nPrevisão de renovações: Não\nIdentificador do Lote: LOT-0006\nPrazo de execução do contrato: 1 ANOS\nPrevisão de renovações: Não\nIdentificador do Lote: LOT-0007\nPrazo de execução do contrato: 1 ANOS\nPrevisão de renovações: Não\nIdentificador do Lote: LOT-0008\nPrazo de execução do contrato: 1 ANOS\nPrevisão de renovações: Não\nIdentificador do Lote: LOT-0009\nPrazo de execução do contrato: 1 ANOS\nPrevisão de renovações: Não\nIdentificador do Lote: LOT-0010\nPrazo de execução do contrato: 1 ANOS\nPrevisão de renovações: Não\nIdentificador do Lote: LOT-0011\nPrazo de execução do contrato: 1 ANOS\nPrevisão de renovações: Não\nIdentificador do Lote: LOT-0012\nPrazo de execução do contrato: 1 ANOS\nPrevisão de renovações: Não\nIdentificador do Lote: LOT-0013\nPrazo de execução do contrato: 1 ANOS\nPrevisão de renovações: Não\nIdentificador do Lote: LOT-0014\nPrazo de execução do contrato: 1 ANOS\nPrevisão de renovações: Não\nIdentificador do Lote: LOT-0015\nPrazo de execução do contrato: 1 ANOS\nPrevisão de renovações: Não\nIdentificador do Lote: LOT-0016\nPrazo de execução do contrato: 1 ANOS\nPrevisão de renovações: Não\nIdentificador do Lote: LOT-0017\nPrazo de execução do contrato: 1 ANOS\nPrevisão de renovações: Não\nIdentificador do Lote: LOT-0018\nPrazo de execução do contrato: 1 ANOS\nPrevisão de renovações: Não\nIdentificador do Lote: LOT-0019\nPrazo de execução do contrato: 1 ANOS\nPrevisão de renovações: Não\nIdentificador do Lote: LOT-0020\nPrazo de execução do contrato: 1 ANOS\nPrevisão de renovações: Não\nIdentificador do Lote: LOT-0021\nPrazo de execução do contrato: 1 ANOS\nPrevisão de renovações: Não\nIdentificador do Lote: LOT-0022\nPrazo de execução do contrato: 1 ANOS\nPrevisão de renovações: Não\nIdentificador do Lote: LOT-0023\nPrazo de execução do contrato: 1 ANOS\nPrevisão de renovações: Não\nIdentificador do Lote: LOT-0024\nPrazo de execução do contrato: 1 ANOS\nPrevisão de renovações: Não\nIdentificador do Lote: LOT-0025\nPrazo de execução do contrato: 1 ANOS\nPrevisão de renovações: Não\nIdentificador do Lote: LOT-0026\nPrazo de execução do contrato: 1 ANOS\nPrevisão de renovações: Não\nIdentificador do Lote: LOT-0027\nPrazo de execução do contrato: 1 ANOS\nPrevisão de renovações: Não\nIdentificador do Lote: LOT-0028\nPrazo de execução do contrato: 1 ANOS\nPrevisão de renovações: Não\nIdentificador do Lote: LOT-0029\nPrazo de execução do contrato: 1 ANOS\nPrevisão de renovações: Não\nIdentificador do Lote: LOT-0030\nPrazo de execução do contrato: 1 ANOS\nPrevisão de renovações: Não\nIdentificador do Lote: LOT-0031\nPrazo de execução do contrato: 1 ANOS\nPrevisão de renovações: Não\nIdentificador do Lote: LOT-0032\nPrazo de execução do contrato: 1 ANOS\nPrevisão de renovações: Não\nIdentificador do Lote: LOT-0033\nPrazo de execução do contrato: 1 ANOS\nPrevisão de renovações: Não\nIdentificador do Lote: LOT-0034\nPrazo de execução do contrato: 1 ANOS\nPrevisão de renovações: Não\nIdentificador do Lote: LOT-0035\nPrazo de execução do contrato: 1 ANOS\nPrevisão de renovações: Não\nIdentificador do Lote: LOT-0036\nPrazo de execução do contrato: 1 ANOS\nPrevisão de renovações: Não\nIdentificador do Lote: LOT-0037\nPrazo de execução do contrato: 1 ANOS\nPrevisão de renovações: Não\nIdentificador do Lote: LOT-0038\nPrazo de execução do contrato: 1 ANOS\nPrevisão de renovações: Não\nIdentificador do Lote: LOT-0039\nPrazo de execução do contrato: 1 ANOS\nPrevisão de renovações: Não\nIdentificador do Lote: LOT-0040\nPrazo de execução do contrato: 1 ANOS\nPrevisão de renovações: Não\nIdentificador do Lote: LOT-0041\nPrazo de execução do contrato: 1 ANOS\nPrevisão de renovações: Não\nIdentificador do Lote: LOT-0042\nPrazo de execução do contrato: 1 ANOS\nPrevisão de renovações: Não\nIdentificador do Lote: LOT-0043\nPrazo de execução do contrato: 1 ANOS\nPrevisão de renovações: Não\nIdentificador do Lote: LOT-0044\nPrazo de execução do contrato: 1 ANOS\nPrevisão de renovações: Não\nIdentificador do Lote: LOT-0045\nPrazo de execução do contrato: 1 ANOS\nPrevisão de renovações: Não\nIdentificador do Lote: LOT-0046\nPrazo de execução do contrato: 1 ANOS\nPrevisão de renovações: Não\nIdentificador do Lote: LOT-0047\nPrazo de execução do contrato: 1 ANOS\nPrevisão de renovações: Não\nIdentificador do Lote: LOT-0048\nPrazo de execução do contrato: 1 ANOS\nPrevisão de renovações: Não\nIdentificador do Lote: LOT-0049\nPrazo de execução do contrato: 1 ANOS\nPrevisão de renovações: Não\nIdentificador do Lote: LOT-0050\nPrazo de execução do contrato: 1 ANOS\nPrevisão de renovações: Não\nIdentificador do Lote: LOT-0051\nPrazo de execução do contrato: 1 ANOS\nPrevisão de renovações: Não\nIdentificador do Lote: LOT-0052\nPrazo de execução do contrato: 1 ANOS\nPrevisão de renovações: Não\nIdentificador do Lote: LOT-0053\nPrazo de execução do contrato: 1 ANOS\nPrevisão de renovações: Não\nIdentificador do Lote: LOT-0054\nPrazo de execução do contrato: 1 ANOS\nPrevisão de renovações: Não\nIdentificador do Lote: LOT-0055\nPrazo de execução do contrato: 1 ANOS\nPrevisão de renovações: Não\nIdentificador do Lote: LOT-0056\nPrazo de execução do contrato: 1 ANOS\nPrevisão de renovações: Não\nIdentificador do Lote: LOT-0057\nPrazo de execução do contrato: 1 ANOS\nPrevisão de renovações: Não\nIdentificador do Lote: LOT-0058\nPrazo de execução do contrato: 1 ANOS\nPrevisão de renovações: Não\nIdentificador do Lote: LOT-0059\nPrazo de execução do contrato: 1 ANOS\nPrevisão de renovações: Não\nIdentificador do Lote: LOT-0060\nPrazo de execução do contrato: 1 ANOS\nPrevisão de renovações: Não\nIdentificador do Lote: LOT-0061\nPrazo de execução do contrato: 1 ANOS\nPrevisão de renovações: Não\nIdentificador do Lote: LOT-0062\nPrazo de execução do contrato: 1 ANOS\nPrevisão de renovações: Não\nIdentificador do Lote: LOT-0063\nPrazo de execução do contrato: 1 ANOS\nPrevisão de renovações: Não\nIdentificador do Lote: LOT-0064\nPrazo de execução do contrato: 1 ANOS\nPrevisão de renovações: Não\nIdentificador do Lote: LOT-0065\nPrazo de execução do contrato: 1 ANOS\nPrevisão de renovações: Não\nIdentificador do Lote: LOT-0066\nPrazo de execução do contrato: 1 ANOS\nPrevisão de renovações: Não\nIdentificador do Lote: LOT-0067\nPrazo de execução do contrato: 1 ANOS\nPrevisão de renovações: Não\nIdentificador do Lote: LOT-0068\nPrazo de execução do contrato: 1 ANOS\nPrevisão de renovações: Não\nIdentificador do Lote: LOT-0069\nPrazo de execução do contrato: 1 ANOS\nPrevisão de renovações: Não\nIdentificador do Lote: LOT-0070\nPrazo de execução do contrato: 1 ANOS\nPrevisão de renovações: Não\nIdentificador do Lote: LOT-0071\nPrazo de execução do contrato: 1 ANOS\nPrevisão de renovações: Não\nIdentificador do Lote: LOT-0072\nPrazo de execução do contrato: 1 ANOS\nPrevisão de renovações: Não\nIdentificador do Lote: LOT-0073\nPrazo de execução do contrato: 1 ANOS\nPrevisão de renovações: Não\nIdentificador do Lote: LOT-0074\nPrazo de execução do contrato: 1 ANOS\nPrevisão de renovações: Não\nIdentificador do Lote: LOT-0075\nPrazo de execução do contrato: 1 ANOS\nPrevisão de renovações: Não\nIdentificador do Lote: LOT-0076\nPrazo de execução do contrato: 1 ANOS\nPrevisão de renovações: Não\nIdentificador do Lote: LOT-0077\nPrazo de execução do contrato: 1 ANOS\nPrevisão de renovações: Não\nIdentificador do Lote: LOT-0078\nPrazo de execução do contrato: 1 ANOS\nPrevisão de renovações: Não\nIdentificador do Lote: LOT-0079\nPrazo de execução do contrato: 1 ANOS\nPrevisão de renovações: Não\nIdentificador do Lote: LOT-0080\nPrazo de execução do contrato: 1 ANOS\nPrevisão de renovações: Não\nIdentificador do Lote: LOT-0081\nPrazo de execução do contrato: 1 ANOS\nPrevisão de renovações: Não\nIdentificador do Lote: LOT-0082\nPrazo de execução do contrato: 1 ANOS\nPrevisão de renovações: Não\nIdentificador do Lote: LOT-0083\nPrazo de execução do contrato: 1 ANOS\nPrevisão de renovações: Não\nIdentificador do Lote: LOT-0084\nPrazo de execução do contrato: 1 ANOS\nPrevisão de renovações: Não\nIdentificador do Lote: LOT-0085\nPrazo de execução do contrato: 1 ANOS\nPrevisão de renovações: Não\nIdentificador do Lote: LOT-0086\nPrazo de execução do contrato: 1 ANOS\nPrevisão de renovações: Não\nIdentificador do Lote: LOT-0087\nPrazo de execução do contrato: 1 ANOS\nPrevisão de renovações: Não\nIdentificador do Lote: LOT-0088\nPrazo de execução do contrato: 1 ANOS\nPrevisão de renovações: Não\nIdentificador do Lote: LOT-0089\nPrazo de execução do contrato: 1 ANOS\nPrevisão de renovações: Não\nIdentificador do Lote: LOT-0090\nPrazo de execução do contrato: 1 ANOS\nPrevisão de renovações: Não\nIdentificador do Lote: LOT-0091\nPrazo de execução do contrato: 1 ANOS\nPrevisão de renovações: Não\nIdentificador do Lote: LOT-0092\nPrazo de execução do contrato: 1 ANOS\nPrevisão de renovações: Não\nIdentificador do Lote: LOT-0093\nPrazo de execução do contrato: 1 ANOS\nPrevisão de renovações: Não\n\n11 - FUNDOS EU\nIdentificador do Lote: LOT-0001; LOT-0002; LOT-0003; LOT-0004; LOT-0005; LOT-0006; LOT-0007; LOT-0008; LOT-0009; LOT-0010; LOT-0011; LOT-0012; LOT-0013; LOT-0014; LOT-0015; LOT-0016; LOT-0017; LOT-0018; LOT-0019; LOT-0020; LOT-0021; LOT-0022; LOT-0023; LOT-0024; LOT-0025; LOT-0026; LOT-0027; LOT-0028; LOT-0029; LOT-0030; LOT-0031; LOT-0032; LOT-0033; LOT-0034; LOT-0035; LOT-0036; LOT-0037; LOT-0038; LOT-0039; LOT-0040; LOT-0041; LOT-0042; LOT-0043; LOT-0044; LOT-0045; LOT-0046; LOT-0047; LOT-0048; LOT-0049; LOT-0050; LOT-0051; LOT-0052; LOT-0053; LOT-0054; LOT-0055; LOT-0056; LOT-0057; LOT-0058; LOT-0059; LOT-0060; LOT-0061; LOT-0062; LOT-0063; LOT-0064; LOT-0065; LOT-0066; LOT-0067; LOT-0068; LOT-0069; LOT-0070; LOT-0071; LOT-0072; LOT-0073; LOT-0074; LOT-0075; LOT-0076; LOT-0077; LOT-0078; LOT-0079; LOT-0080; LOT-0081; LOT-0082; LOT-0083; LOT-0084; LOT-0085; LOT-0086; LOT-0087; LOT-0088; LOT-0089; LOT-0090; LOT-0091; LOT-0092; LOT-0093\nTêm fundos EU? Não\n\n12 - DOCUMENTOS DE HABILITAÇÃO\nHabilitação para o exercício da atividade profissional: Não\n\n13 - CONDIÇÕES DE APRESENTAÇÃO\nPlataforma eletrónica utilizada pela entidade adjudicante: ANOGOV\nURL para Apresentação: https://www.anogov.com/me-sasualgarve/faces/\nAdmissibilidade da apresentação de propostas variantes: Não autorizado\nPrazo para apresentação das propostas: 10-10-2025 23:59\nPrazo durante o qual os concorrentes são obrigados a manter as respetivas propostas: 66 dias a contar do termo do prazo para a apresentação das propostas\nApresentação de Catálogo Eletrónico: Permitido\nIndicação de Subcontratação na Proposta: Inexistência de indicação de subcontratação\n\n14 - PRESTAÇÃO DE CAUÇÃO\nPrestação de caução: Não\n\n15 - FORNECIMENTO DAS PEÇAS DO CONCURSO, APRESENTAÇÃO DE PEDIDOS DE PARTICIPAÇÃO E APRESENTAÇÃO DAS PROPOSTAS\nLink para acesso às peças do concurso (URL): https://www.anogov.com/me-sasualgarve/faces/app/acessoDocs.jsp?codigoAcesso=Sg1MI1MYJEkPoUmMEUj1DOEWPWkeOAB0C0ZVzVocF8JQyOyXeN\n\n20 - OUTROS REQUISITOS\nIdentificador do Lote: LOT-0001; LOT-0002; LOT-0003; LOT-0004; LOT-0005; LOT-0006; LOT-0007; LOT-0008; LOT-0009; LOT-0010; LOT-0011; LOT-0012; LOT-0013; LOT-0014; LOT-0015; LOT-0016; LOT-0017; LOT-0018; LOT-0019; LOT-0020; LOT-0021; LOT-0022; LOT-0023; LOT-0024; LOT-0025; LOT-0026; LOT-0027; LOT-0028; LOT-0029; LOT-0030; LOT-0031; LOT-0032; LOT-0033; LOT-0034; LOT-0035; LOT-0036; LOT-0037; LOT-0038; LOT-0039; LOT-0040; LOT-0041; LOT-0042; LOT-0043; LOT-0044; LOT-0045; LOT-0046; LOT-0047; LOT-0048; LOT-0049; LOT-0050; LOT-0051; LOT-0052; LOT-0053; LOT-0054; LOT-0055; LOT-0056; LOT-0057; LOT-0058; LOT-0059; LOT-0060; LOT-0061; LOT-0062; LOT-0063; LOT-0064; LOT-0065; LOT-0066; LOT-0067; LOT-0068; LOT-0069; LOT-0070; LOT-0071; LOT-0072; LOT-0073; LOT-0074; LOT-0075; LOT-0076; LOT-0077; LOT-0078; LOT-0079; LOT-0080; LOT-0081; LOT-0082; LOT-0083; LOT-0084; LOT-0085; LOT-0086; LOT-0087; LOT-0088; LOT-0089; LOT-0090; LOT-0091; LOT-0092; LOT-0093\nInformação sobre contratos reservados. Aplica-se a contratos reservados (54º-A)? Não\n\n21 - CRITÉRIO DE ADJUDICAÇÃO\nO Critério de adjudicação é diferenciado por lote? Não\nMultifator: Sim\nFator: \nNome: Preço\nPonderação: 90%\nSubfatores: Não\nFator: \nNome: Outros\nOutro Nome: Origem e Impacto Ambiental: A produção tenha todas as suas fases no Algarve\nPonderação: 10%\nSubfatores: Não\n\n24 - CONDIÇÕES DO CONTRATO\nIdentificador do Lote: LOT-0001; LOT-0002; LOT-0003; LOT-0004; LOT-0005; LOT-0006; LOT-0007; LOT-0008; LOT-0009; LOT-0010; LOT-0011; LOT-0012; LOT-0013; LOT-0014; LOT-0015; LOT-0016; LOT-0017; LOT-0018; LOT-0019; LOT-0020; LOT-0021; LOT-0022; LOT-0023; LOT-0024; LOT-0025; LOT-0026; LOT-0027; LOT-0028; LOT-0029; LOT-0030; LOT-0031; LOT-0032; LOT-0033; LOT-0034; LOT-0035; LOT-0036; LOT-0037; LOT-0038; LOT-0039; LOT-0040; LOT-0041; LOT-0042; LOT-0043; LOT-0044; LOT-0045; LOT-0046; LOT-0047; LOT-0048; LOT-0049; LOT-0050; LOT-0051; LOT-0052; LOT-0053; LOT-0054; LOT-0055; LOT-0056; LOT-0057; LOT-0058; LOT-0059; LOT-0060; LOT-0061; LOT-0062; LOT-0063; LOT-0064; LOT-0065; LOT-0066; LOT-0067; LOT-0068; LOT-0069; LOT-0070; LOT-0071; LOT-0072; LOT-0073; LOT-0074; LOT-0075; LOT-0076; LOT-0077; LOT-0078; LOT-0079; LOT-0080; LOT-0081; LOT-0082; LOT-0083; LOT-0084; LOT-0085; LOT-0086; LOT-0087; LOT-0088; LOT-0089; LOT-0090; LOT-0091; LOT-0092; LOT-0093\nFaturação Eletrónica: Permitido\nObrigação de Subcontratação:\nCódigo da Obrigação de Subcontratação: Não é aplicável nenhuma obrigação de subcontratação.\n\n25 - COMPRA PÚBLICA ESTRATÉGICA\nCompra Pública Estratégica: Redução dos impactos ambientais\nDescrição do Processo de Adjudicação Estratégico: Origem e Impacto Ambiental: A produção tenha todas as suas fases no Algarve\nCritérios de contratos Públicos Ecológicos: Critérios de contratação pública ecológica da UE\nCategorias da estratégia nacional: Produtos alimentares, serviços de assistência de restauração (catering) e máquinas de distribuição automática\nContratos Públicos Ecológicos: Outros\nDiretiva Veículos Não Poluentes: Não\nCritério de Acessibilidade: Os critérios de acessibilidade para as pessoas com deficiência não estão incluídos porque o contrato não se destina a pessoas singulares\n\n26 - INFORMAÇÕES ADICIONAIS\nIdentificador do Lote: LOT-0001\nContrato adequado para PME: Não\nCobertura ACP (Acordo dos Contratos Públicos da Organização Mundial do Comércio): Não\nIdentificador do Lote: LOT-0002\nContrato adequado para PME: Não\nCobertura ACP (Acordo dos Contratos Públicos da Organização Mundial do Comércio): Não\nIdentificador do Lote: LOT-0003\nContrato adequado para PME: Não\nCobertura ACP (Acordo dos Contratos Públicos da Organização Mundial do Comércio): Não\nIdentificador do Lote: LOT-0004\nContrato adequado para PME: Não\nCobertura ACP (Acordo dos Contratos Públicos da Organização Mundial do Comércio): Não\nIdentificador do Lote: LOT-0005\nContrato adequado para PME: Não\nCobertura ACP (Acordo dos Contratos Públicos da Organização Mundial do Comércio): Não\nIdentificador do Lote: LOT-0006\nContrato adequado para PME: Não\nCobertura ACP (Acordo dos Contratos Públicos da Organização Mundial do Comércio): Não\nIdentificador do Lote: LOT-0007\nContrato adequado para PME: Não\nCobertura ACP (Acordo dos Contratos Públicos da Organização Mundial do Comércio): Não\nIdentificador do Lote: LOT-0008\nContrato adequado para PME: Não\nCobertura ACP (Acordo dos Contratos Públicos da Organização Mundial do Comércio): Não\nIdentificador do Lote: LOT-0009\nContrato adequado para PME: Não\nCobertura ACP (Acordo dos Contratos Públicos da Organização Mundial do Comércio): Não\nIdentificador do Lote: LOT-0010\nContrato adequado para PME: Não\nCobertura ACP (Acordo dos Contratos Públicos da Organização Mundial do Comércio): Não\nIdentificador do Lote: LOT-0011\nContrato adequado para PME: Não\nCobertura ACP (Acordo dos Contratos Públicos da Organização Mundial do Comércio): Não\nIdentificador do Lote: LOT-0012\nContrato adequado para PME: Não\nCobertura ACP (Acordo dos Contratos Públicos da Organização Mundial do Comércio): Não\nIdentificador do Lote: LOT-0013\nContrato adequado para PME: Não\nCobertura ACP (Acordo dos Contratos Públicos da Organização Mundial do Comércio): Não\nIdentificador do Lote: LOT-0014\nContrato adequado para PME: Não\nCobertura ACP (Acordo dos Contratos Públicos da Organização Mundial do Comércio): Não\nIdentificador do Lote: LOT-0015\nContrato adequado para PME: Não\nCobertura ACP (Acordo dos Contratos Públicos da Organização Mundial do Comércio): Não\nIdentificador do Lote: LOT-0016\nContrato adequado para PME: Não\nCobertura ACP (Acordo dos Contratos Públicos da Organização Mundial do Comércio): Não\nIdentificador do Lote: LOT-0017\nContrato adequado para PME: Não\nCobertura ACP (Acordo dos Contratos Públicos da Organização Mundial do Comércio): Não\nIdentificador do Lote: LOT-0018\nContrato adequado para PME: Não\nCobertura ACP (Acordo dos Contratos Públicos da Organização Mundial do Comércio): Não\nIdentificador do Lote: LOT-0019\nContrato adequado para PME: Não\nCobertura ACP (Acordo dos Contratos Públicos da Organização Mundial do Comércio): Não\nIdentificador do Lote: LOT-0020\nContrato adequado para PME: Não\nCobertura ACP (Acordo dos Contratos Públicos da Organização Mundial do Comércio): Não\nIdentificador do Lote: LOT-0021\nContrato adequado para PME: Não\nCobertura ACP (Acordo dos Contratos Públicos da Organização Mundial do Comércio): Não\nIdentificador do Lote: LOT-0022\nContrato adequado para PME: Não\nCobertura ACP (Acordo dos Contratos Públicos da Organização Mundial do Comércio): Não\nIdentificador do Lote: LOT-0023\nContrato adequado para PME: Não\nCobertura ACP (Acordo dos Contratos Públicos da Organização Mundial do Comércio): Não\nIdentificador do Lote: LOT-0024\nContrato adequado para PME: Não\nCobertura ACP (Acordo dos Contratos Públicos da Organização Mundial do Comércio): Não\nIdentificador do Lote: LOT-0025\nContrato adequado para PME: Não\nCobertura ACP (Acordo dos Contratos Públicos da Organização Mundial do Comércio): Não\nIdentificador do Lote: LOT-0026\nContrato adequado para PME: Não\nCobertura ACP (Acordo dos Contratos Públicos da Organização Mundial do Comércio): Não\nIdentificador do Lote: LOT-0027\nContrato adequado para PME: Não\nCobertura ACP (Acordo dos Contratos Públicos da Organização Mundial do Comércio): Não\nIdentificador do Lote: LOT-0028\nContrato adequado para PME: Não\nCobertura ACP (Acordo dos Contratos Públicos da Organização Mundial do Comércio): Não\nIdentificador do Lote: LOT-0029\nContrato adequado para PME: Não\nCobertura ACP (Acordo dos Contratos Públicos da Organização Mundial do Comércio): Não\nIdentificador do Lote: LOT-0030\nContrato adequado para PME: Não\nCobertura ACP (Acordo dos Contratos Públicos da Organização Mundial do Comércio): Não\nIdentificador do Lote: LOT-0031\nContrato adequado para PME: Não\nCobertura ACP (Acordo dos Contratos Públicos da Organização Mundial do Comércio): Não\nIdentificador do Lote: LOT-0032\nContrato adequado para PME: Não\nCobertura ACP (Acordo dos Contratos Públicos da Organização Mundial do Comércio): Não\nIdentificador do Lote: LOT-0033\nContrato adequado para PME: Não\nCobertura ACP (Acordo dos Contratos Públicos da Organização Mundial do Comércio): Não\nIdentificador do Lote: LOT-0034\nContrato adequado para PME: Não\nCobertura ACP (Acordo dos Contratos Públicos da Organização Mundial do Comércio): Não\nIdentificador do Lote: LOT-0035\nContrato adequado para PME: Não\nCobertura ACP (Acordo dos Contratos Públicos da Organização Mundial do Comércio): Não\nIdentificador do Lote: LOT-0036\nContrato adequado para PME: Não\nCobertura ACP (Acordo dos Contratos Públicos da Organização Mundial do Comércio): Não\nIdentificador do Lote: LOT-0037\nContrato adequado para PME: Não\nCobertura ACP (Acordo dos Contratos Públicos da Organização Mundial do Comércio): Não\nIdentificador do Lote: LOT-0038\nContrato adequado para PME: Não\nCobertura ACP (Acordo dos Contratos Públicos da Organização Mundial do Comércio): Não\nIdentificador do Lote: LOT-0039\nContrato adequado para PME: Não\nCobertura ACP (Acordo dos Contratos Públicos da Organização Mundial do Comércio): Não\nIdentificador do Lote: LOT-0040\nContrato adequado para PME: Não\nCobertura ACP (Acordo dos Contratos Públicos da Organização Mundial do Comércio): Não\nIdentificador do Lote: LOT-0041\nContrato adequado para PME: Não\nCobertura ACP (Acordo dos Contratos Públicos da Organização Mundial do Comércio): Não\nIdentificador do Lote: LOT-0042\nContrato adequado para PME: Não\nCobertura ACP (Acordo dos Contratos Públicos da Organização Mundial do Comércio): Não\nIdentificador do Lote: LOT-0043\nContrato adequado para PME: Não\nCobertura ACP (Acordo dos Contratos Públicos da Organização Mundial do Comércio): Não\nIdentificador do Lote: LOT-0044\nContrato adequado para PME: Não\nCobertura ACP (Acordo dos Contratos Públicos da Organização Mundial do Comércio): Não\nIdentificador do Lote: LOT-0045\nContrato adequado para PME: Não\nCobertura ACP (Acordo dos Contratos Públicos da Organização Mundial do Comércio): Não\nIdentificador do Lote: LOT-0046\nContrato adequado para PME: Não\nCobertura ACP (Acordo dos Contratos Públicos da Organização Mundial do Comércio): Não\nIdentificador do Lote: LOT-0047\nContrato adequado para PME: Não\nCobertura ACP (Acordo dos Contratos Públicos da Organização Mundial do Comércio): Não\nIdentificador do Lote: LOT-0048\nContrato adequado para PME: Não\nCobertura ACP (Acordo dos Contratos Públicos da Organização Mundial do Comércio): Não\nIdentificador do Lote: LOT-0049\nContrato adequado para PME: Não\nCobertura ACP (Acordo dos Contratos Públicos da Organização Mundial do Comércio): Não\nIdentificador do Lote: LOT-0050\nContrato adequado para PME: Não\nCobertura ACP (Acordo dos Contratos Públicos da Organização Mundial do Comércio): Não\nIdentificador do Lote: LOT-0051\nContrato adequado para PME: Não\nCobertura ACP (Acordo dos Contratos Públicos da Organização Mundial do Comércio): Não\nIdentificador do Lote: LOT-0052\nContrato adequado para PME: Não\nCobertura ACP (Acordo dos Contratos Públicos da Organização Mundial do Comércio): Não\nIdentificador do Lote: LOT-0053\nContrato adequado para PME: Não\nCobertura ACP (Acordo dos Contratos Públicos da Organização Mundial do Comércio): Não\nIdentificador do Lote: LOT-0054\nContrato adequado para PME: Não\nCobertura ACP (Acordo dos Contratos Públicos da Organização Mundial do Comércio): Não\nIdentificador do Lote: LOT-0055\nContrato adequado para PME: Não\nCobertura ACP (Acordo dos Contratos Públicos da Organização Mundial do Comércio): Não\nIdentificador do Lote: LOT-0056\nContrato adequado para PME: Não\nCobertura ACP (Acordo dos Contratos Públicos da Organização Mundial do Comércio): Não\nIdentificador do Lote: LOT-0057\nContrato adequado para PME: Não\nCobertura ACP (Acordo dos Contratos Públicos da Organização Mundial do Comércio): Não\nIdentificador do Lote: LOT-0058\nContrato adequado para PME: Não\nCobertura ACP (Acordo dos Contratos Públicos da Organização Mundial do Comércio): Não\nIdentificador do Lote: LOT-0059\nContrato adequado para PME: Não\nCobertura ACP (Acordo dos Contratos Públicos da Organização Mundial do Comércio): Não\nIdentificador do Lote: LOT-0060\nContrato adequado para PME: Não\nCobertura ACP (Acordo dos Contratos Públicos da Organização Mundial do Comércio): Não\nIdentificador do Lote: LOT-0061\nContrato adequado para PME: Não\nCobertura ACP (Acordo dos Contratos Públicos da Organização Mundial do Comércio): Não\nIdentificador do Lote: LOT-0062\nContrato adequado para PME: Não\nCobertura ACP (Acordo dos Contratos Públicos da Organização Mundial do Comércio): Não\nIdentificador do Lote: LOT-0063\nContrato adequado para PME: Não\nCobertura ACP (Acordo dos Contratos Públicos da Organização Mundial do Comércio): Não\nIdentificador do Lote: LOT-0064\nContrato adequado para PME: Não\nCobertura ACP (Acordo dos Contratos Públicos da Organização Mundial do Comércio): Não\nIdentificador do Lote: LOT-0065\nContrato adequado para PME: Não\nCobertura ACP (Acordo dos Contratos Públicos da Organização Mundial do Comércio): Não\nIdentificador do Lote: LOT-0066\nContrato adequado para PME: Não\nCobertura ACP (Acordo dos Contratos Públicos da Organização Mundial do Comércio): Não\nIdentificador do Lote: LOT-0067\nContrato adequado para PME: Não\nCobertura ACP (Acordo dos Contratos Públicos da Organização Mundial do Comércio): Não\nIdentificador do Lote: LOT-0068\nContrato adequado para PME: Não\nCobertura ACP (Acordo dos Contratos Públicos da Organização Mundial do Comércio): Não\nIdentificador do Lote: LOT-0069\nContrato adequado para PME: Não\nCobertura ACP (Acordo dos Contratos Públicos da Organização Mundial do Comércio): Não\nIdentificador do Lote: LOT-0070\nContrato adequado para PME: Não\nCobertura ACP (Acordo dos Contratos Públicos da Organização Mundial do Comércio): Não\nIdentificador do Lote: LOT-0071\nContrato adequado para PME: Não\nCobertura ACP (Acordo dos Contratos Públicos da Organização Mundial do Comércio): Não\nIdentificador do Lote: LOT-0072\nContrato adequado para PME: Não\nCobertura ACP (Acordo dos Contratos Públicos da Organização Mundial do Comércio): Não\nIdentificador do Lote: LOT-0073\nContrato adequado para PME: Não\nCobertura ACP (Acordo dos Contratos Públicos da Organização Mundial do Comércio): Não\nIdentificador do Lote: LOT-0074\nContrato adequado para PME: Não\nCobertura ACP (Acordo dos Contratos Públicos da Organização Mundial do Comércio): Não\nIdentificador do Lote: LOT-0075\nContrato adequado para PME: Não\nCobertura ACP (Acordo dos Contratos Públicos da Organização Mundial do Comércio): Não\nIdentificador do Lote: LOT-0076\nContrato adequado para PME: Não\nCobertura ACP (Acordo dos Contratos Públicos da Organização Mundial do Comércio): Não\nIdentificador do Lote: LOT-0077\nContrato adequado para PME: Não\nCobertura ACP (Acordo dos Contratos Públicos da Organização Mundial do Comércio): Não\nIdentificador do Lote: LOT-0078\nContrato adequado para PME: Não\nCobertura ACP (Acordo dos Contratos Públicos da Organização Mundial do Comércio): Não\nIdentificador do Lote: LOT-0079\nContrato adequado para PME: Não\nCobertura ACP (Acordo dos Contratos Públicos da Organização Mundial do Comércio): Não\nIdentificador do Lote: LOT-0080\nContrato adequado para PME: Não\nCobertura ACP (Acordo dos Contratos Públicos da Organização Mundial do Comércio): Não\nIdentificador do Lote: LOT-0081\nContrato adequado para PME: Não\nCobertura ACP (Acordo dos Contratos Públicos da Organização Mundial do Comércio): Não\nIdentificador do Lote: LOT-0082\nContrato adequado para PME: Não\nCobertura ACP (Acordo dos Contratos Públicos da Organização Mundial do Comércio): Não\nIdentificador do Lote: LOT-0083\nContrato adequado para PME: Não\nCobertura ACP (Acordo dos Contratos Públicos da Organização Mundial do Comércio): Não\nIdentificador do Lote: LOT-0084\nContrato adequado para PME: Não\nCobertura ACP (Acordo dos Contratos Públicos da Organização Mundial do Comércio): Não\nIdentificador do Lote: LOT-0085\nContrato adequado para PME: Não\nCobertura ACP (Acordo dos Contratos Públicos da Organização Mundial do Comércio): Não\nIdentificador do Lote: LOT-0086\nContrato adequado para PME: Não\nCobertura ACP (Acordo dos Contratos Públicos da Organização Mundial do Comércio): Não\nIdentificador do Lote: LOT-0087\nContrato adequado para PME: Não\nCobertura ACP (Acordo dos Contratos Públicos da Organização Mundial do Comércio): Não\nIdentificador do Lote: LOT-0088\nContrato adequado para PME: Não\nCobertura ACP (Acordo dos Contratos Públicos da Organização Mundial do Comércio): Não\nIdentificador do Lote: LOT-0089\nContrato adequado para PME: Não\nCobertura ACP (Acordo dos Contratos Públicos da Organização Mundial do Comércio): Não\nIdentificador do Lote: LOT-0090\nContrato adequado para PME: Não\nCobertura ACP (Acordo dos Contratos Públicos da Organização Mundial do Comércio): Não\nIdentificador do Lote: LOT-0091\nContrato adequado para PME: Não\nCobertura ACP (Acordo dos Contratos Públicos da Organização Mundial do Comércio): Não\nIdentificador do Lote: LOT-0092\nContrato adequado para PME: Não\nCobertura ACP (Acordo dos Contratos Públicos da Organização Mundial do Comércio): Não\nIdentificador do Lote: LOT-0093\nContrato adequado para PME: Não\nCobertura ACP (Acordo dos Contratos Públicos da Organização Mundial do Comércio): Não\n\n27 - IDENTIFICAÇÃO E CONTACTOS DO ÓRGÃO DE RECURSOS ADMINISTRATIVOS\nDesignação: Serviços de Ação Social da Universidade do Algarve\nEndereço: Estrada da Penha - Campus Universitário da Penha\nCódigo postal: 8005-139\nLocalidade: Faro\nEndereço eletrónico: sas@ualg.pt\n\n28 - IDENTIFICAÇÃO DO(S) AUTOR(ES) DE ANÚNCIO\nNome: António Joaquim Godinho Cabecinha\nCargo: Administrador dos SAS da Universidade do Algarve\n\n29 - ALTERAÇÃO\nMotivo da Alteração: Informações atualizadas\nIdentificador da Versão do Anúncio a Alterar: a84d74c8-dc5e-42ea-b337-44ea56f28800-01\nIdentificador das Secções Alteradas do Anúncio Anterior: Alteração\nDescrição das Alterações: Alteração da data limite de apresentação de propostas\nAlteração dos Documentos do Concurso: Não\n419608338",
    "nipc": "600039510",
    "distrito": "Faro",
    "concelho": "Faro",
    "freguesia": "Todas",
    "site": "https://www.ualg.pt/acao-social",
    "email": "sascompras@ualg.pt",
    "designacao_contrato": "Aquisição contínua e parcelar de carne fresca e congelada",
    "descricao": "Aquisição contínua e parcelar de carne fresca e congelada",
    "preco_base": "214.700,00 EUR",
    "prazo_execucao": "1 ANOS",
    "prazo_apresentacao_propostas": "10-10-2025 23:59",
    "fundos_eu": "Não",
    "plataforma_eletronica": "ANOGOV",
    "url_procedimento": "https://www.anogov.com/me-sasualgarve/faces/",
    "autor_nome": "António Joaquim Godinho Cabecinha",
    "autor_cargo": "Administrador dos SAS da Universidade do Algarve"
  },
  {
    "numero_procedimento": "N/A",
    "entidade": "AnÃºncio de procedimento  n.Âº 26035/2025  -  DiÃ¡rio da RepÃºblica n.Âº 191/2025, SÃ©rie II de 2025-10-03",
    "link": "https://diariodarepublica.pt/dr/detalhe/contrato-publico/26035-938020031"
  },
  {
    "numero_procedimento": "N/A",
    "entidade": "AnÃºncio de procedimento  n.Âº 26036/2025  -  DiÃ¡rio da RepÃºblica n.Âº 191/2025, SÃ©rie II de 2025-10-03",
    "link": "https://diariodarepublica.pt/dr/detalhe/contrato-publico/26036-938020032"
  },
  {
    "numero_procedimento": "N/A",
    "entidade": "AnÃºncio de procedimento  n.Âº 26037/2025  -  DiÃ¡rio da RepÃºblica n.Âº 191/2025, SÃ©rie II de 2025-10-03",
    "link": "https://diariodarepublica.pt/dr/detalhe/contrato-publico/26037-938020033"
  },
  {
    "numero_procedimento": "N/A",
    "entidade": "Município de Ribeira de Pena",
    "link": "https://diariodarepublica.pt/dr/detalhe/contrato-publico/26038-938020034",
    "detalhes_completos": "1 - IDENTIFICAÇÃO E CONTACTOS DA ENTIDADE ADJUDICANTE\nDesignação da entidade adjudicante: Município de Ribeira de Pena\nNIPC: 506818098\nEndereço: Praça do Município n.º1\nCódigo postal: 4870-152\nLocalidade: Ribeira de Pena\nPaís: Portugal\nNUT III: PT11B\nDistrito: Vila Real\nConcelho: Ribeira de Pena\nFreguesia: Todas\nTelefone: 259490500\nEndereço da Entidade (URL): www.cm-rpena.pt\nEndereço Eletrónico: contratacao.publica@cm-rpena.pt\neDelivery Gateway (URL): https://community.vortal.biz/public/\nFunção da Organização: Adquirente\nNorma jurídica da Entidade Adjudicante: Autoridade local\nÁrea de atividade da Autoridade Adjudicante: Serviços públicos das administrações públicas\n\n2 - JORNAL OFICIAL DA UNIÃO EUROPEIA\nO procedimento a que este anúncio diz respeito também é publicitado no Jornal Oficial da União Europeia? Não\n\n3 - AVISO\nModelo de Anúncio: Concurso público\nData de Envio do Anúncio: 03-10-2025\n\n5 - PROCESSO\nTipo de Procedimento: Concurso público\nPreço base do procedimento: Sim\nValor do preço base do procedimento: 51.153,92 EUR\nProcedimento com lotes? Não\n\n6 - OBJETO DO CONTRATO\nNúmero de referência interna: 69/GCP/2025\nDesignação do contrato: Fornecimento Contínuo de Mistura Betuminosa\nDescrição: Fornecimento Contínuo de Mistura Betuminosa\nTipo de Contrato Principal: Aquisição de Bens Móveis\nTipo de Contrato: Aquisição de Bens Móveis\nClassificação CPV (Vocabulário Comum para os Contratos Públicos)\nObjeto principal\nVocabulário Principal: 44113610\nPreço base s/IVA: 51.153,92 EUR\n\n7 - INDICAÇÕES ADICIONAIS\nO contrato envolve aquisição conjunta (satisfação de várias entidades)? Não\nO contrato é adjudicado por uma central de compras? Não\n\n8 - TÉCNICAS\nO concurso destina-se à celebração de um acordo-quadro? Inexistência de acordo-quadro\nÉ utilizado um leilão eletrónico? Não\nÉ adotada uma fase de negociação? Não\nSistema de Aquisição Dinâmico: Inexistência de sistema de aquisição dinâmico\n\n9 - LOCAL DA EXECUÇÃO DO CONTRATO\nLOCAL DA EXECUÇÃO DO CONTRATO (PROCEDIMENTO)\nPaís: Portugal\nNUT III: PT11B\nLocalidade: Vila Real\nDistrito: Vila Real\nConcelho: Ribeira de Pena\nFreguesia: Todas\n\n10 - PRAZO DE EXECUÇÃO DO CONTRATO\nPrazo de execução do contrato: 2 ANOS\nPrevisão de renovações: Não\n\n11 - FUNDOS EU\nTêm fundos EU? Não\n\n12 - DOCUMENTOS DE HABILITAÇÃO\nHabilitação para o exercício da atividade profissional: Não\n\n13 - CONDIÇÕES DE APRESENTAÇÃO\nPlataforma eletrónica utilizada pela entidade adjudicante: VORTAL\nURL para Apresentação: https://community.vortal.biz/public/\nAdmissibilidade da apresentação de propostas variantes: Não autorizado\nPrazo para apresentação das propostas: 09-10-2025 23:59\nPrazo durante o qual os concorrentes são obrigados a manter as respetivas propostas: 120 dias a contar do termo do prazo para a apresentação das propostas\nIndicação de Subcontratação na Proposta: Inexistência de indicação de subcontratação\n\n14 - PRESTAÇÃO DE CAUÇÃO\nPrestação de caução: Não\n\n15 - FORNECIMENTO DAS PEÇAS DO CONCURSO, APRESENTAÇÃO DE PEDIDOS DE PARTICIPAÇÃO E APRESENTAÇÃO DAS PROPOSTAS\nLink para acesso às peças do concurso (URL): https://community.vortal.biz/Public/public-tender-documents/RDJMcldwcEtmV05hUlpVUFB5bzVCd0ltU0tVTnd3bkxaWUpCeXgxUWkzSEtlK1FFVGtxSnBsQW1oRVB1YWlZelVkUFd5bmc2QnoxTU5STXFnTDdRelE9PTVRbVBO\n\n20 - OUTROS REQUISITOS\nInformação sobre contratos reservados. Aplica-se a contratos reservados (54º-A)? Não\n\n21 - CRITÉRIO DE ADJUDICAÇÃO\nMultifator: Não\nMonofator:\nNome: Qualidade\n\n24 - CONDIÇÕES DO CONTRATO\nFaturação Eletrónica: Permitido\nObrigação de Subcontratação:\nCódigo da Obrigação de Subcontratação: Não é aplicável nenhuma obrigação de subcontratação.\n\n25 - COMPRA PÚBLICA ESTRATÉGICA\nCompra Pública Estratégica: Inexistência de contratação pública estratégica\n\n26 - INFORMAÇÕES ADICIONAIS\nContrato adequado para PME: Sim\nCobertura ACP (Acordo dos Contratos Públicos da Organização Mundial do Comércio): Não\n\n27 - IDENTIFICAÇÃO E CONTACTOS DO ÓRGÃO DE RECURSOS ADMINISTRATIVOS\nDesignação: Municipio de Ribeira de Pena\nEndereço: Praça do Municipio, nº 1\nCódigo postal: 4870-152\nLocalidade: Ribeira de Pena\nTelefone: +351 359490500\nFax: +351 259493520\nEndereço eletrónico: geral@cm-rpena.pt\n\n28 - IDENTIFICAÇÃO DO(S) AUTOR(ES) DE ANÚNCIO\nNome: João Noronha\nCargo: Presidente da Câmara\n419610492",
    "nipc": "506818098",
    "distrito": "Vila Real",
    "concelho": "Ribeira de Pena",
    "freguesia": "Todas",
    "site": "www.cm-rpena.pt",
    "email": "contratacao.publica@cm-rpena.pt",
    "designacao_contrato": "Fornecimento Contínuo de Mistura Betuminosa",
    "descricao": "Fornecimento Contínuo de Mistura Betuminosa",
    "preco_base": "51.153,92 EUR",
    "prazo_execucao": "2 ANOS",
    "prazo_apresentacao_propostas": "09-10-2025 23:59",
    "fundos_eu": "Não",
    "plataforma_eletronica": "VORTAL",
    "url_procedimento": "https://community.vortal.biz/public/",
    "autor_nome": "João Noronha",
    "autor_cargo": "Presidente da Câmara"
  },
  {
    "numero_procedimento": "N/A",
    "entidade": "AnÃºncio de procedimento  n.Âº 26039/2025  -  DiÃ¡rio da RepÃºblica n.Âº 191/2025, SÃ©rie II de 2025-10-03",
    "link": "https://diariodarepublica.pt/dr/detalhe/contrato-publico/26039-938020035"
  },
  {
    "numero_procedimento": "N/A",
    "entidade": "AnÃºncio de procedimento  n.Âº 26042/2025  -  DiÃ¡rio da RepÃºblica n.Âº 191/2025, SÃ©rie II de 2025-10-03",
    "link": "https://diariodarepublica.pt/dr/detalhe/contrato-publico/26042-938020036"
  },
  {
    "numero_procedimento": "N/A",
    "entidade": "AnÃºncio de procedimento  n.Âº 26048/2025  -  DiÃ¡rio da RepÃºblica n.Âº 191/2025, SÃ©rie II de 2025-10-03",
    "link": "https://diariodarepublica.pt/dr/detalhe/contrato-publico/26048-938020046"
  },
  {
    "numero_procedimento": "N/A",
    "entidade": "Sicó Formação - Sociedade de Ensino Profissional, S.A",
    "link": "https://diariodarepublica.pt/dr/detalhe/contrato-publico/26050-938020049",
    "detalhes_completos": "1 - IDENTIFICAÇÃO E CONTACTOS DA ENTIDADE ADJUDICANTE\nDesignação da entidade adjudicante: Sicó Formação - Sociedade de Ensino Profissional, S.A\nNIPC: 504600109\nServiço/Órgão/Pessoa de contacto: Serviços Administrativos\nEndereço: Rua Armando Moreira, n.º186\nCódigo postal: 3240-311\nLocalidade: Avelar\nPaís: Portugal\nNUT III: PT16F\nDistrito: Leiria\nConcelho: Ansião\nFreguesia: Freguesia de Avelar\nTelefone: 236620500\nFax: 236620509\nEndereço da Entidade (URL): www.etpsico.pt\nEndereço Eletrónico: sico@etpsico.pt\neDelivery Gateway (URL): https://www.acingov.pt\nFunção da Organização: Adquirente\nNorma jurídica da Entidade Adjudicante: Organismo de direito público\nÁrea de atividade da Autoridade Adjudicante: Educação\n\n2 - JORNAL OFICIAL DA UNIÃO EUROPEIA\nO procedimento a que este anúncio diz respeito também é publicitado no Jornal Oficial da União Europeia? Sim\n\n3 - AVISO\nModelo de Anúncio: Concurso público\nData de Envio do Anúncio: 01-10-2025\n\n5 - PROCESSO\nTipo de Procedimento: Concurso público\nPreço base do procedimento: Sim\nValor do preço base do procedimento: 1.449.400,00 EUR\nProcedimento com lotes? Sim\nNº Máx. de Lotes Autorizado: 6\nNúmero máximo de lotes que podem ser adjudicados a um concorrente: 6\n\n6 - OBJETO DO CONTRATO\nNúmero de referência interna: CPI/2/2025\nDesignação do contrato: CPi002/SICO/2025 - Aquisição de Equipamento laboratorial no âmbito do Projeto CTE 3887 com financiamento PRR. Investimento RE-C06-i01 - Modernização da Oferta dos Estabelecimentos de Ensino e da Formação Profissional do Plano de Recuperação e Resiliência.\nDescrição: Aquisição de Equipamento laboratorial no âmbito do Projeto CTE 3887 com financiamento PRR. Investimento RE-C06-i01 - Modernização da Oferta dos Estabelecimentos de Ensino e da Formação Profissional do Plano de Recuperação e Resiliência.\nOpções: Não\nTipo de Contrato Principal: Aquisição de Bens Móveis\nTipo de Contrato: Aquisição de Bens Móveis\nClassificação CPV (Vocabulário Comum para os Contratos Públicos)\nObjeto principal\nVocabulário Principal: 31710000\nPreço base s/IVA: 1.300.150,00 EUR\nObjeto Complementar\nVocabulário Principal: 42600000\nPreço base s/IVA: 142.000,00 EUR\nObjeto Complementar\nVocabulário Principal: 48100000\nPreço base s/IVA: 7.250,00 EUR\nLotes: \nNº: LOT-0001\nDescrição do Lote: Fornecimento e instalação de equipamento laboratorial e Fornecimento e instalação de software\nPreço base s/IVA: 865.000,00 EUR\nClassificação CPV (Vocabulário Comum para os Contratos Públicos)\nObjeto principal\nVocabulário Principal: 31710000\nNº: LOT-0002\nDescrição do Lote: Fornecimento e instalação de Equipamentos e máquinas industriais\nPreço base s/IVA: 142.000,00 EUR\nClassificação CPV (Vocabulário Comum para os Contratos Públicos)\nObjeto principal\nVocabulário Principal: 42600000\nNº: LOT-0003\nDescrição do Lote: Fornecimento e instalação de equipamento laboratorial e Fornecimento e instalação de software\nPreço base s/IVA: 98.400,00 EUR\nClassificação CPV (Vocabulário Comum para os Contratos Públicos)\nObjeto principal\nVocabulário Principal: 31710000\nNº: LOT-0004\nDescrição do Lote: Fornecimento e instalação de Robô pack de Ensino\nPreço base s/IVA: 108.000,00 EUR\nClassificação CPV (Vocabulário Comum para os Contratos Públicos)\nObjeto principal\nVocabulário Principal: 31710000\nNº: LOT-0005\nDescrição do Lote: Fornecimento e instalação de equipamento laboratorial de instrumentação e medida\nPreço base s/IVA: 198.000,00 EUR\nClassificação CPV (Vocabulário Comum para os Contratos Públicos)\nObjeto principal\nVocabulário Principal: 31710000\nNº: LOT-0006\nDescrição do Lote: Fornecimento e instalação de equipamento laboratorial para laboratório de ensaios e Fornecimento e instalação de software\nPreço base s/IVA: 38.000,00 EUR\nClassificação CPV (Vocabulário Comum para os Contratos Públicos)\nObjeto principal\nVocabulário Principal: 31710000\n\n7 - INDICAÇÕES ADICIONAIS\nO contrato envolve aquisição conjunta (satisfação de várias entidades)? Não\nO contrato é adjudicado por uma central de compras? Não\n\n8 - TÉCNICAS\nO concurso destina-se à celebração de um acordo-quadro? Inexistência de acordo-quadro\nÉ utilizado um leilão eletrónico? Não\nÉ adotada uma fase de negociação? Não\nSistema de Aquisição Dinâmico: Inexistência de sistema de aquisição dinâmico\n\n9 - LOCAL DA EXECUÇÃO DO CONTRATO\nLOCAL DA EXECUÇÃO DO CONTRATO (PROCEDIMENTO)\nPaís: Portugal\nNUT III: PT16F\nLocalidade: Freguesia de Avelar\nDistrito: Leiria\nConcelho: Ansião\nFreguesia: Freguesia de Avelar\nLOCAL DA EXECUÇÃO DO CONTRATO (LOTE)\nIdentificador do Lote: LOT-0001; LOT-0002; LOT-0003; LOT-0004; LOT-0005; LOT-0006\nPaís: Portugal\nNUT III: PT16F\nLocalidade: Freguesia de Avelar\nDistrito: Leiria\nConcelho: Ansião\nFreguesia: Freguesia de Avelar\n\n10 - PRAZO DE EXECUÇÃO DO CONTRATO\nIdentificador do Lote: LOT-0001; LOT-0002; LOT-0003; LOT-0004; LOT-0005; LOT-0006\nData de Início: 03-12-2025\nData de Fim: 31-03-2026\nPrevisão de renovações: Não\n\n11 - FUNDOS EU\nIdentificador do Lote: LOT-0001; LOT-0002; LOT-0003; LOT-0004; LOT-0005; LOT-0006\nTêm fundos EU? Sim\n\n12 - DOCUMENTOS DE HABILITAÇÃO\nHabilitação para o exercício da atividade profissional: Não\n\n13 - CONDIÇÕES DE APRESENTAÇÃO\nPlataforma eletrónica utilizada pela entidade adjudicante: ACIN\nURL para Apresentação: https://www.acingov.pt\nAdmissibilidade da apresentação de propostas variantes: Não autorizado\nPrazo para apresentação das propostas: 31-10-2025 17:59\nPrazo durante o qual os concorrentes são obrigados a manter as respetivas propostas: 90 dias a contar do termo do prazo para a apresentação das propostas\nApresentação de Catálogo Eletrónico: Permitido\nIndicação de Subcontratação na Proposta: Inexistência de indicação de subcontratação\n\n14 - PRESTAÇÃO DE CAUÇÃO\nPrestação de caução: Sim\nPercentagem: 5%\nDescrição da Garantia Exigida: O valor da caução é de 5.00% do preço contratual.\n\n15 - FORNECIMENTO DAS PEÇAS DO CONCURSO, APRESENTAÇÃO DE PEDIDOS DE PARTICIPAÇÃO E APRESENTAÇÃO DAS PROPOSTAS\nLink para acesso às peças do concurso (URL): https://www.acingov.pt/acingovprod/2/zonaPublica/zona_publica_c/donwloadProcedurePiece/OTgyNzcy\n\n20 - OUTROS REQUISITOS\nIdentificador do Lote: LOT-0001; LOT-0002; LOT-0003; LOT-0004; LOT-0005; LOT-0006\nInformação sobre contratos reservados. Aplica-se a contratos reservados (54º-A)? Não\n\n21 - CRITÉRIO DE ADJUDICAÇÃO\nO Critério de adjudicação é diferenciado por lote? Não\nMultifator: Sim\nFator: \nNome: Preço\nPonderação: 50%\nSubfatores: Não\nFator: \nNome: Outros\nOutro Nome: Tempo de garantia prestada nos equipamentos a adquirir\nPonderação: 30%\nSubfatores: Não\nFator: \nNome: Outros\nOutro Nome: Prazo de entrega e instalação dos equipamentos\nPonderação: 20%\nSubfatores: Não\n\n24 - CONDIÇÕES DO CONTRATO\nIdentificador do Lote: LOT-0001; LOT-0002; LOT-0003; LOT-0004; LOT-0005; LOT-0006\nFaturação Eletrónica: Permitido\nObrigação de Subcontratação:\nCódigo da Obrigação de Subcontratação: Não é aplicável nenhuma obrigação de subcontratação.\n\n25 - COMPRA PÚBLICA ESTRATÉGICA\nCompra Pública Estratégica: Inexistência de contratação pública estratégica\n\n26 - INFORMAÇÕES ADICIONAIS\nIdentificador do Lote: LOT-0001; LOT-0002; LOT-0003; LOT-0004; LOT-0005; LOT-0006\nContrato adequado para PME: Sim\nCobertura ACP (Acordo dos Contratos Públicos da Organização Mundial do Comércio): Não\n\n27 - IDENTIFICAÇÃO E CONTACTOS DO ÓRGÃO DE RECURSOS ADMINISTRATIVOS\nDesignação: Comissão Executiva\nEndereço: Rua Armando Moreira, n.º186\nCódigo postal: 3240-311\nLocalidade: Avelar\nTelefone: 236620500\nFax: 236620509\nEndereço eletrónico: sico@etpsico.pt\nPrazo de interposição do recurso: 5 dias\n\n28 - IDENTIFICAÇÃO DO(S) AUTOR(ES) DE ANÚNCIO\nNome: Cristina Maria Mineiro Arsénio\nCargo: Chefe de Serviços Administrativos\n419600286",
    "nipc": "504600109",
    "distrito": "Leiria",
    "concelho": "Ansião",
    "freguesia": "Freguesia de Avelar",
    "site": "www.etpsico.pt",
    "email": "sico@etpsico.pt",
    "designacao_contrato": "CPi002/SICO/2025 - Aquisição de Equipamento laboratorial no âmbito do Projeto CTE 3887 com financiamento PRR. Investimento RE-C06-i01 - Modernização da Oferta dos Estabelecimentos de Ensino e da Formação Profissional do Plano de Recuperação e Resiliência.",
    "descricao": "Aquisição de Equipamento laboratorial no âmbito do Projeto CTE 3887 com financiamento PRR. Investimento RE-C06-i01 - Modernização da Oferta dos Estabelecimentos de Ensino e da Formação Profissional do Plano de Recuperação e Resiliência.",
    "preco_base": "1.300.150,00 EUR",
    "prazo_execucao": null,
    "prazo_apresentacao_propostas": "31-10-2025 17:59",
    "fundos_eu": "Sim",
    "plataforma_eletronica": "ACIN",
    "url_procedimento": "https://www.acingov.pt",
    "autor_nome": "Cristina Maria Mineiro Arsénio",
    "autor_cargo": "Chefe de Serviços Administrativos"
  },
  {
    "numero_procedimento": "N/A",
    "entidade": "AnÃºncio de procedimento  n.Âº 26052/2025  -  DiÃ¡rio da RepÃºblica n.Âº 191/2025, SÃ©rie II de 2025-10-03",
    "link": "https://diariodarepublica.pt/dr/detalhe/contrato-publico/26052-938020050"
  },
  {
    "numero_procedimento": "N/A",
    "entidade": "CÂMARA MUNICIPAL DE ALMADA",
    "link": "https://diariodarepublica.pt/dr/detalhe/contrato-publico/26054-938020054",
    "detalhes_completos": "Alteração do Anúncio de procedimento n.º 25199/2025, de 2025-09-24, com o ID 419563489\n\n1 - IDENTIFICAÇÃO E CONTACTOS DA ENTIDADE ADJUDICANTE\nDesignação da entidade adjudicante: CÂMARA MUNICIPAL DE ALMADA\nNIPC: 500051054\nEndereço: Largo Luís de Camões\nCódigo postal: 2800-158\nLocalidade: Setúbal\nPaís: Portugal\nNUT III: PT170\nDistrito: Setúbal\nConcelho: Almada\nFreguesia: União das Freguesias de Almada, Cova da Piedade, Pragal e Cacilhas\nTelefone: 212724000\nFax: 212724599\nEndereço da Entidade (URL): www.m-almada.pt\nEndereço Eletrónico: almadainforma@cma.m-almada.pt\neDelivery Gateway (URL): https://community.vortal.biz/public/\nFunção da Organização: Adquirente\nNorma jurídica da Entidade Adjudicante: Autoridade local\nÁrea de atividade da Autoridade Adjudicante: Serviços públicos das administrações públicas\n\n2 - JORNAL OFICIAL DA UNIÃO EUROPEIA\nO procedimento a que este anúncio diz respeito também é publicitado no Jornal Oficial da União Europeia? Sim\n\n3 - AVISO\nModelo de Anúncio: Concurso público\nData de Envio do Anúncio: 01-10-2025\n\n5 - PROCESSO\nTipo de Procedimento: Concurso público\nPreço base do procedimento: Sim\nValor do preço base do procedimento: 1.168.308,98 EUR\nProcedimento com lotes? Não\n\n6 - OBJETO DO CONTRATO\nNúmero de referência interna: CPN00415S2025\nDesignação do contrato: Aquisição de serviços de cópia e impressão, em regime de outsourcing, para serviços municipais, e escolas do 1º ciclo, 3º ciclo e ensino secundário, pelo prazo de 3 anos\nDescrição: Aquisição de serviços de cópia e impressão, em regime de outsourcing, para serviços municipais, e escolas do 1º ciclo, 3º ciclo e ensino secundário, pelo prazo de 3 anos\nOpções: Não\nTipo de Contrato Principal: Aquisição de Serviços\nTipo de Contrato: Aquisição de Serviços\nClassificação CPV (Vocabulário Comum para os Contratos Públicos)\nObjeto principal\nVocabulário Principal: 79820000\nPreço base s/IVA: 1.168.308,98 EUR\n\n7 - INDICAÇÕES ADICIONAIS\nO contrato envolve aquisição conjunta (satisfação de várias entidades)? Não\nO contrato é adjudicado por uma central de compras? Não\n\n8 - TÉCNICAS\nO concurso destina-se à celebração de um acordo-quadro? Inexistência de acordo-quadro\nÉ utilizado um leilão eletrónico? Não\nÉ adotada uma fase de negociação? Não\nSistema de Aquisição Dinâmico: Inexistência de sistema de aquisição dinâmico\n\n9 - LOCAL DA EXECUÇÃO DO CONTRATO\nLOCAL DA EXECUÇÃO DO CONTRATO (PROCEDIMENTO)\nPaís: Portugal\nNUT III: PT170\nLocalidade: Setúbal\nDistrito: Setúbal\nConcelho: Almada\nFreguesia: Todas\n\n10 - PRAZO DE EXECUÇÃO DO CONTRATO\nPrazo de execução do contrato: 3 ANOS\nPrevisão de renovações: Não\n\n11 - FUNDOS EU\nTêm fundos EU? Não\n\n12 - DOCUMENTOS DE HABILITAÇÃO\nHabilitação para o exercício da atividade profissional: Sim\nTipo: Outros\nDescrição - Outros: Não aplicável\nDescrição: Não Aplicável\n\n13 - CONDIÇÕES DE APRESENTAÇÃO\nPlataforma eletrónica utilizada pela entidade adjudicante: VORTAL\nURL para Apresentação: https://community.vortal.biz/public/\nAdmissibilidade da apresentação de propostas variantes: Não autorizado\nPrazo para apresentação das propostas: 06-11-2025 23:59\nPrazo durante o qual os concorrentes são obrigados a manter as respetivas propostas: 120 dias a contar do termo do prazo para a apresentação das propostas\nApresentação de Catálogo Eletrónico: Não autorizado\nIndicação de Subcontratação na Proposta: Inexistência de indicação de subcontratação\n\n14 - PRESTAÇÃO DE CAUÇÃO\nPrestação de caução: Sim\nPercentagem: 5%\nDescrição da Garantia Exigida: Depósito em dinheiro ou em títulos emitidos ou garantidos pelo Estado, ou mediante garantia bancária ou seguro-caução\n\n15 - FORNECIMENTO DAS PEÇAS DO CONCURSO, APRESENTAÇÃO DE PEDIDOS DE PARTICIPAÇÃO E APRESENTAÇÃO DAS PROPOSTAS\nLink para acesso às peças do concurso (URL): https://community.vortal.biz/Public/public-tender-documents/NnJjOGkyVVBMTWtUZ256UXBNNVkxTDFreHJHejNhVHpGbXdpOEprOEgxK2NiMXIzTTc1VG0zenBveEhpcGs3TTFkL04rNkFxY2xNOVJWMUhHenE4QlE9PTRzaURL\n\n20 - OUTROS REQUISITOS\nInformação sobre contratos reservados. Aplica-se a contratos reservados (54º-A)? Não\n\n21 - CRITÉRIO DE ADJUDICAÇÃO\nMultifator: Sim\nFator: \nNome: Preço\nPonderação: 60%\nSubfatores: Não\nFator: \nNome: Qualidade\nPonderação: 40%\nSubfatores: Não\n\n24 - CONDIÇÕES DO CONTRATO\nFaturação Eletrónica: Permitido\nObrigação de Subcontratação:\nCódigo da Obrigação de Subcontratação: Não é aplicável nenhuma obrigação de subcontratação.\n\n25 - COMPRA PÚBLICA ESTRATÉGICA\nCompra Pública Estratégica: Inexistência de contratação pública estratégica\n\n26 - INFORMAÇÕES ADICIONAIS\nContrato adequado para PME: Sim\nCobertura ACP (Acordo dos Contratos Públicos da Organização Mundial do Comércio): Não\n\n27 - IDENTIFICAÇÃO E CONTACTOS DO ÓRGÃO DE RECURSOS ADMINISTRATIVOS\nDesignação: Município de Almada\nEndereço: Largo Luís Camões\nCódigo postal: 2800-158\nLocalidade: Almada\nTelefone: +351 212724000\nFax: +351 212724000\nEndereço eletrónico: gab.presidencia@cma.m-almada.pt\n\n28 - IDENTIFICAÇÃO DO(S) AUTOR(ES) DE ANÚNCIO\nNome: Inês de Medeiros\nCargo: Presidente da Câmara Municipal de Almada\n\n29 - ALTERAÇÃO\nMotivo da Alteração: Correção pelo adquirente\nIdentificador da Versão do Anúncio a Alterar: a465b45a-19ca-4ac9-84a8-5a5d1a17dea9-01\nIdentificador das Secções Alteradas do Anúncio Anterior: Condições de Apresentação\nDescrição das Alterações: Prorrogação do prazo para apresentação das propostas\nAlteração dos Documentos do Concurso: Não\n419600375",
    "nipc": "500051054",
    "distrito": "Setúbal",
    "concelho": "Almada",
    "freguesia": "União das Freguesias de Almada, Cova da Piedade, Pragal e Cacilhas",
    "site": "www.m-almada.pt",
    "email": "almadainforma@cma.m-almada.pt",
    "designacao_contrato": "Aquisição de serviços de cópia e impressão, em regime de outsourcing, para serviços municipais, e escolas do 1º ciclo, 3º ciclo e ensino secundário, pelo prazo de 3 anos",
    "descricao": "Aquisição de serviços de cópia e impressão, em regime de outsourcing, para serviços municipais, e escolas do 1º ciclo, 3º ciclo e ensino secundário, pelo prazo de 3 anos",
    "preco_base": "1.168.308,98 EUR",
    "prazo_execucao": "3 ANOS",
    "prazo_apresentacao_propostas": "06-11-2025 23:59",
    "fundos_eu": "Não",
    "plataforma_eletronica": "VORTAL",
    "url_procedimento": "https://community.vortal.biz/public/",
    "autor_nome": "Inês de Medeiros",
    "autor_cargo": "Presidente da Câmara Municipal de Almada"
  },
  {
    "numero_procedimento": "N/A",
    "entidade": "AnÃºncio de procedimento  n.Âº 26057/2025  -  DiÃ¡rio da RepÃºblica n.Âº 191/2025, SÃ©rie II de 2025-10-03",
    "link": "https://diariodarepublica.pt/dr/detalhe/contrato-publico/26057-938020058"
  },
  {
    "numero_procedimento": "N/A",
    "entidade": "Santa Casa da Misericórdia de Lisboa",
    "link": "https://diariodarepublica.pt/dr/detalhe/contrato-publico/26058-938020063",
    "detalhes_completos": "1 - IDENTIFICAÇÃO E CONTACTOS DA ENTIDADE ADJUDICANTE\nDesignação da entidade adjudicante: Santa Casa da Misericórdia de Lisboa\nNIPC: 500745471\nServiço/Órgão/Pessoa de contacto: Exma. Mesa\nEndereço: Largo Trindade Coelho\nCódigo postal: 1200-470\nLocalidade: Lisboa\nPaís: Portugal\nNUT III: PT170\nDistrito: Lisboa\nConcelho: Todos\nFreguesia: Todas\nTelefone: 213235000\nFax: 213235013\nEndereço da Entidade (URL): http://www.scml.pt/\nEndereço Eletrónico: compras@scml.pt\neDelivery Gateway (URL): https://www.acingov.pt\nFunção da Organização: Adquirente\nSubfunção da Organização: Organização cujo orçamento é utilizado para pagar o contrato; Organização que executa o pagamento; Organização que fornece informações adicionais sobre o processo de adjudicação; Organização que fornece mais informações sobre os prazos dos procedimentos de recurso; Organização que fornece acesso fora de linha aos documentos do concurso; Organização responsável pelo tratamento das propostas; Organização que recebe as propostas; Organização que trata os pedidos de participação; Organização que recebe pedidos de participação; Organização que fornece mais informações sobre os procedimentos de recurso; Organização que assina o contrato\nNorma jurídica da Entidade Adjudicante: Organismo de direito público, controlado por uma autoridade da administração central\nÁrea de atividade da Autoridade Adjudicante: Proteção social\n\n2 - JORNAL OFICIAL DA UNIÃO EUROPEIA\nO procedimento a que este anúncio diz respeito também é publicitado no Jornal Oficial da União Europeia? Não\n\n3 - AVISO\nModelo de Anúncio: Concurso público\nData de Envio do Anúncio: 03-10-2025\n\n5 - PROCESSO\nTipo de Procedimento: Concurso público\nPreço base do procedimento: Sim\nValor do preço base do procedimento: 97.980,00 EUR\nProcedimento com lotes? Não\n\n6 - OBJETO DO CONTRATO\nNúmero de referência interna: 25DC39CP031\nDesignação do contrato: Aquisição de compactadores de papel/cartão incluindo a sua manutenção técnica\nDescrição: Aquisição de compactadores de papel/cartão incluindo a sua manutenção técnica\nTipo de Contrato Principal: Aquisição de Bens Móveis\nTipo de Contrato: Aquisição de Bens Móveis; Aquisição de Serviços\nClassificação CPV (Vocabulário Comum para os Contratos Públicos)\nObjeto principal\nVocabulário Principal: 39713300\nPreço base s/IVA: 97.980,00 EUR\n\n7 - INDICAÇÕES ADICIONAIS\nO contrato envolve aquisição conjunta (satisfação de várias entidades)? Não\nO contrato é adjudicado por uma central de compras? Não\n\n8 - TÉCNICAS\nO concurso destina-se à celebração de um acordo-quadro? Inexistência de acordo-quadro\nÉ utilizado um leilão eletrónico? Não\nÉ adotada uma fase de negociação? Não\nSistema de Aquisição Dinâmico: Inexistência de sistema de aquisição dinâmico\n\n9 - LOCAL DA EXECUÇÃO DO CONTRATO\nLOCAL DA EXECUÇÃO DO CONTRATO (PROCEDIMENTO)\nPaís: Portugal\nNUT III: PT170\nLocalidade: Freguesia de Misericórdia\nDistrito: Lisboa\nConcelho: Lisboa\nFreguesia: Freguesia de Misericórdia\n\n10 - PRAZO DE EXECUÇÃO DO CONTRATO\nPrazo de execução do contrato: 36 MESES\nPrevisão de renovações: Não\n\n11 - FUNDOS EU\nTêm fundos EU? Não\n\n12 - DOCUMENTOS DE HABILITAÇÃO\nHabilitação para o exercício da atividade profissional: Não\n\n13 - CONDIÇÕES DE APRESENTAÇÃO\nPlataforma eletrónica utilizada pela entidade adjudicante: ACIN\nURL para Apresentação: https://www.acingov.pt\nAdmissibilidade da apresentação de propostas variantes: Não autorizado\nPrazo para apresentação das propostas: 18-10-2025 17:00\nPrazo durante o qual os concorrentes são obrigados a manter as respetivas propostas: 120 dias a contar do termo do prazo para a apresentação das propostas\nIndicação de Subcontratação na Proposta: Inexistência de indicação de subcontratação\n\n14 - PRESTAÇÃO DE CAUÇÃO\nPrestação de caução: Não\n\n15 - FORNECIMENTO DAS PEÇAS DO CONCURSO, APRESENTAÇÃO DE PEDIDOS DE PARTICIPAÇÃO E APRESENTAÇÃO DAS PROPOSTAS\nLink para acesso às peças do concurso (URL): https://www.acingov.pt/acingovprod/2/zonaPublica/zona_publica_c/donwloadProcedurePiece/OTgzNDY5\n\n20 - OUTROS REQUISITOS\nInformação sobre contratos reservados. Aplica-se a contratos reservados (54º-A)? Não\n\n21 - CRITÉRIO DE ADJUDICAÇÃO\nMultifator: Sim\nFator: \nNome: Outros\nOutro Nome: Multifator\nPonderação: 100%\nSubfatores: Não\n\n24 - CONDIÇÕES DO CONTRATO\nFaturação Eletrónica: Necessário\nObrigação de Subcontratação:\nCódigo da Obrigação de Subcontratação: Não é aplicável nenhuma obrigação de subcontratação.\n\n25 - COMPRA PÚBLICA ESTRATÉGICA\nCompra Pública Estratégica: Inexistência de contratação pública estratégica\n\n26 - INFORMAÇÕES ADICIONAIS\nContrato adequado para PME: Sim\nCobertura ACP (Acordo dos Contratos Públicos da Organização Mundial do Comércio): Não\n\n27 - IDENTIFICAÇÃO E CONTACTOS DO ÓRGÃO DE RECURSOS ADMINISTRATIVOS\nDesignação: Direção de Compras\nEndereço: Largo Trindade Coelho\nCódigo postal: 1200-470\nLocalidade: Lisboa\nTelefone: 213235000\nFax: \nEndereço eletrónico: dicom.neei@scml.pt\nPrazo de interposição do recurso: 10 dias\n\n28 - IDENTIFICAÇÃO DO(S) AUTOR(ES) DE ANÚNCIO\nNome: Vanda Simão\nCargo: Diretora da Direção de Compras\n419611415",
    "nipc": "500745471",
    "distrito": "Lisboa",
    "concelho": "Todos",
    "freguesia": "Todas",
    "site": "http://www.scml.pt/",
    "email": "compras@scml.pt",
    "designacao_contrato": "Aquisição de compactadores de papel/cartão incluindo a sua manutenção técnica",
    "descricao": "Aquisição de compactadores de papel/cartão incluindo a sua manutenção técnica",
    "preco_base": "97.980,00 EUR",
    "prazo_execucao": "36 MESES",
    "prazo_apresentacao_propostas": "18-10-2025 17:00",
    "fundos_eu": "Não",
    "plataforma_eletronica": "ACIN",
    "url_procedimento": "https://www.acingov.pt",
    "autor_nome": "Vanda Simão",
    "autor_cargo": "Diretora da Direção de Compras"
  },
  {
    "numero_procedimento": "N/A",
    "entidade": "Município de Armamar",
    "link": "https://diariodarepublica.pt/dr/detalhe/contrato-publico/26061-938020071",
    "detalhes_completos": "1 - IDENTIFICAÇÃO E CONTACTOS DA ENTIDADE ADJUDICANTE\nDesignação da entidade adjudicante: Município de Armamar\nNIPC: 506843190\nServiço/Órgão/Pessoa de contacto: Divisão Municipal de Gestão Urbanística e Ambiente\nEndereço: Praça da República\nCódigo postal: 5110-127\nLocalidade: Armamar\nPaís: Portugal\nNUT III: PT11D\nDistrito: Viseu\nConcelho: Armamar\nFreguesia: Todas\nTelefone: 254850800\nEndereço da Entidade (URL): https://www.cm-armamar.pt/\nEndereço Eletrónico: geral@cm-armamar.pt\neDelivery Gateway (URL): https://www.acingov.pt\nFunção da Organização: Adquirente\nNorma jurídica da Entidade Adjudicante: Organismo de direito público\nÁrea de atividade da Autoridade Adjudicante: Serviços públicos das administrações públicas\n\n2 - JORNAL OFICIAL DA UNIÃO EUROPEIA\nO procedimento a que este anúncio diz respeito também é publicitado no Jornal Oficial da União Europeia? Não\n\n3 - AVISO\nModelo de Anúncio: Concurso público\nData de Envio do Anúncio: 03-10-2025\n\n5 - PROCESSO\nTipo de Procedimento: Concurso público\nPreço base do procedimento: Sim\nValor do preço base do procedimento: 208.038,09 EUR\nProcedimento com lotes? Não\n\n6 - OBJETO DO CONTRATO\nNúmero de referência interna: 90MUNAMM25\nDesignação do contrato: Empreitada de Execução do Centro de Estudos Gomes Teixeira\nDescrição: Empreitada de Execução do Centro de Estudos Gomes Teixeira\nTipo de Contrato Principal: Empreitada de Obras Públicas\nTipo de Contrato: Empreitada de Obras Públicas\nClassificação CPV (Vocabulário Comum para os Contratos Públicos)\nObjeto principal\nVocabulário Principal: 45262700\nPreço base s/IVA: 208.038,09 EUR\n\n7 - INDICAÇÕES ADICIONAIS\nO contrato envolve aquisição conjunta (satisfação de várias entidades)? Não\nO contrato é adjudicado por uma central de compras? Não\n\n8 - TÉCNICAS\nO concurso destina-se à celebração de um acordo-quadro? Inexistência de acordo-quadro\nÉ utilizado um leilão eletrónico? Não\nÉ adotada uma fase de negociação? Não\nSistema de Aquisição Dinâmico: Inexistência de sistema de aquisição dinâmico\n\n9 - LOCAL DA EXECUÇÃO DO CONTRATO\nLOCAL DA EXECUÇÃO DO CONTRATO (PROCEDIMENTO)\nPaís: Portugal\nNUT III: PT11D\nLocalidade: São Cosmado\nDistrito: Viseu\nConcelho: Armamar\nFreguesia: Freguesia de São Cosmado\n\n10 - PRAZO DE EXECUÇÃO DO CONTRATO\nPrazo de execução do contrato: 300 DIAS\nPrevisão de renovações: Não\n\n11 - FUNDOS EU\nTêm fundos EU? Sim\n\n12 - DOCUMENTOS DE HABILITAÇÃO\nHabilitação para o exercício da atividade profissional: Sim\nTipo: Alvará\nDescrição: 1.ª, 2.ª, 4ª, 5.º, 6.ª e 8.º, subcategorias da 1.º categoria;\n1.ª, 7.ª, 8.ª, e 10.ª subcategorias da 4.ª categoria;\n1.ª, 9.ª, 10.ª, 11.ª e 12.ª subcategorias da 5.ª categoria.\n\n13 - CONDIÇÕES DE APRESENTAÇÃO\nPlataforma eletrónica utilizada pela entidade adjudicante: ACIN\nURL para Apresentação: https://www.acingov.pt\nAdmissibilidade da apresentação de propostas variantes: Não autorizado\nPrazo para apresentação das propostas: 28-10-2025 23:59\nPrazo durante o qual os concorrentes são obrigados a manter as respetivas propostas: 66 dias a contar do termo do prazo para a apresentação das propostas\nIndicação de Subcontratação na Proposta: Inexistência de indicação de subcontratação\n\n14 - PRESTAÇÃO DE CAUÇÃO\nPrestação de caução: Sim\nPercentagem: 5%\nDescrição da Garantia Exigida: O valor da caução é de 5.00% do preço contratual.\n\n15 - FORNECIMENTO DAS PEÇAS DO CONCURSO, APRESENTAÇÃO DE PEDIDOS DE PARTICIPAÇÃO E APRESENTAÇÃO DAS PROPOSTAS\nLink para acesso às peças do concurso (URL): https://www.acingov.pt/acingovprod/2/zonaPublica/zona_publica_c/donwloadProcedurePiece/OTgzNTU1\n\n20 - OUTROS REQUISITOS\nInformação sobre contratos reservados. Aplica-se a contratos reservados (54º-A)? Não\n\n21 - CRITÉRIO DE ADJUDICAÇÃO\nMultifator: Não\nMonofator:\nNome: Preço\n\n24 - CONDIÇÕES DO CONTRATO\nFaturação Eletrónica: Permitido\nObrigação de Subcontratação:\nCódigo da Obrigação de Subcontratação: Não é aplicável nenhuma obrigação de subcontratação.\n\n25 - COMPRA PÚBLICA ESTRATÉGICA\nCompra Pública Estratégica: Inexistência de contratação pública estratégica\n\n26 - INFORMAÇÕES ADICIONAIS\nContrato adequado para PME: Sim\nCobertura ACP (Acordo dos Contratos Públicos da Organização Mundial do Comércio): Não\n\n27 - IDENTIFICAÇÃO E CONTACTOS DO ÓRGÃO DE RECURSOS ADMINISTRATIVOS\nDesignação: Câmara Municipal de Armamar\nEndereço: Praça da República\nCódigo postal: 5110-127\nLocalidade: Armamar\nTelefone: 254850800\nFax: \nEndereço eletrónico: geral@cm-armamar.pt\n\n28 - IDENTIFICAÇÃO DO(S) AUTOR(ES) DE ANÚNCIO\nNome: João Paulo Soares Carvalho Pereira da Fonseca\nCargo: Presidente da Câmara Municipal\n419611367",
    "nipc": "506843190",
    "distrito": "Viseu",
    "concelho": "Armamar",
    "freguesia": "Todas",
    "site": "https://www.cm-armamar.pt/",
    "email": "geral@cm-armamar.pt",
    "designacao_contrato": "Empreitada de Execução do Centro de Estudos Gomes Teixeira",
    "descricao": "Empreitada de Execução do Centro de Estudos Gomes Teixeira",
    "preco_base": "208.038,09 EUR",
    "prazo_execucao": "300 DIAS",
    "prazo_apresentacao_propostas": "28-10-2025 23:59",
    "fundos_eu": "Sim",
    "plataforma_eletronica": "ACIN",
    "url_procedimento": "https://www.acingov.pt",
    "autor_nome": "João Paulo Soares Carvalho Pereira da Fonseca",
    "autor_cargo": "Presidente da Câmara Municipal"
  },
  {
    "numero_procedimento": "N/A",
    "entidade": "Município de Coruche",
    "link": "https://diariodarepublica.pt/dr/detalhe/contrato-publico/26063-938108777",
    "detalhes_completos": "1 - IDENTIFICAÇÃO E CONTACTOS DA ENTIDADE ADJUDICANTE\nDesignação da entidade adjudicante: Município de Coruche\nNIPC: 506722422\nServiço/Órgão/Pessoa de contacto: Serviço de Contratação Pública\nEndereço: Edifício dos Paços do Concelho Praça da Liberdade\nCódigo postal: 2100-121\nLocalidade: Coruche\nPaís: Portugal\nNUT III: PT185\nDistrito: Santarém\nConcelho: Coruche\nFreguesia: União das Freguesias de Coruche, Fajarda e Erra\nTelefone: 243610200\nEndereço da Entidade (URL): www.cm-coruche.pt\nEndereço Eletrónico: geral@cm-coruche.pt\neDelivery Gateway (URL): https://www.acingov.pt\nFunção da Organização: Adquirente\nNorma jurídica da Entidade Adjudicante: Organismo de direito público\nÁrea de atividade da Autoridade Adjudicante: Serviços públicos das administrações públicas\n\n2 - JORNAL OFICIAL DA UNIÃO EUROPEIA\nO procedimento a que este anúncio diz respeito também é publicitado no Jornal Oficial da União Europeia? Não\n\n3 - AVISO\nModelo de Anúncio: Concurso público\nData de Envio do Anúncio: 03-10-2025\n\n5 - PROCESSO\nTipo de Procedimento: Concurso público\nPreço base do procedimento: Sim\nValor do preço base do procedimento: 15.767,99 EUR\nProcedimento com lotes? Não\n\n6 - OBJETO DO CONTRATO\nNúmero de referência interna: CP52/2025\nDesignação do contrato: Aquisição de dois módulos pré-fabricados para o Centro de Recolha Oficial de Coruche\nDescrição: Aquisição de dois módulos pré-fabricados para o Centro de Recolha Oficial de Coruche\nTipo de Contrato Principal: Aquisição de Bens Móveis\nTipo de Contrato: Aquisição de Bens Móveis\nClassificação CPV (Vocabulário Comum para os Contratos Públicos)\nObjeto principal\nVocabulário Principal: 44211100\nPreço base s/IVA: 15.767,99 EUR\n\n7 - INDICAÇÕES ADICIONAIS\nO contrato envolve aquisição conjunta (satisfação de várias entidades)? Não\nO contrato é adjudicado por uma central de compras? Não\n\n8 - TÉCNICAS\nO concurso destina-se à celebração de um acordo-quadro? Inexistência de acordo-quadro\nÉ utilizado um leilão eletrónico? Não\nÉ adotada uma fase de negociação? Não\nSistema de Aquisição Dinâmico: Inexistência de sistema de aquisição dinâmico\n\n9 - LOCAL DA EXECUÇÃO DO CONTRATO\nLOCAL DA EXECUÇÃO DO CONTRATO (PROCEDIMENTO)\nPaís: Portugal\nNUT III: PT185\nLocalidade: Coruche\nDistrito: Santarém\nConcelho: Coruche\nFreguesia: União das Freguesias de Coruche, Fajarda e Erra\n\n10 - PRAZO DE EXECUÇÃO DO CONTRATO\nPrazo de execução do contrato: 90 DIAS\nPrevisão de renovações: Não\n\n11 - FUNDOS EU\nTêm fundos EU? Sim\n\n12 - DOCUMENTOS DE HABILITAÇÃO\nHabilitação para o exercício da atividade profissional: Não\n\n13 - CONDIÇÕES DE APRESENTAÇÃO\nPlataforma eletrónica utilizada pela entidade adjudicante: ACIN\nURL para Apresentação: https://www.acingov.pt\nAdmissibilidade da apresentação de propostas variantes: Não autorizado\nPrazo para apresentação das propostas: 15-10-2025 23:59\nPrazo durante o qual os concorrentes são obrigados a manter as respetivas propostas: 120 dias a contar do termo do prazo para a apresentação das propostas\nIndicação de Subcontratação na Proposta: Inexistência de indicação de subcontratação\n\n14 - PRESTAÇÃO DE CAUÇÃO\nPrestação de caução: Não\n\n15 - FORNECIMENTO DAS PEÇAS DO CONCURSO, APRESENTAÇÃO DE PEDIDOS DE PARTICIPAÇÃO E APRESENTAÇÃO DAS PROPOSTAS\nLink para acesso às peças do concurso (URL): https://www.acingov.pt/acingovprod/2/zonaPublica/zona_publica_c/donwloadProcedurePiece/OTgzNDY2\n\n20 - OUTROS REQUISITOS\nInformação sobre contratos reservados. Aplica-se a contratos reservados (54º-A)? Não\n\n21 - CRITÉRIO DE ADJUDICAÇÃO\nMultifator: Não\nMonofator:\nNome: Outros\nOutro nome: Fator Preço\n\n24 - CONDIÇÕES DO CONTRATO\nFaturação Eletrónica: Permitido\nObrigação de Subcontratação:\nCódigo da Obrigação de Subcontratação: Não é aplicável nenhuma obrigação de subcontratação.\n\n25 - COMPRA PÚBLICA ESTRATÉGICA\nCompra Pública Estratégica: Inexistência de contratação pública estratégica\n\n26 - INFORMAÇÕES ADICIONAIS\nContrato adequado para PME: Sim\nCobertura ACP (Acordo dos Contratos Públicos da Organização Mundial do Comércio): Não\n\n27 - IDENTIFICAÇÃO E CONTACTOS DO ÓRGÃO DE RECURSOS ADMINISTRATIVOS\nDesignação: Câmara Municipal de Coruche\nEndereço: Edifício dos Paços do Concelho Praça da Liberdade\nCódigo postal: 2100-121\nLocalidade: Coruche\nTelefone: 243610200\nFax: \nEndereço eletrónico: geral@cm-coruche.pt\nPrazo de interposição do recurso: 30 dias\n\n28 - IDENTIFICAÇÃO DO(S) AUTOR(ES) DE ANÚNCIO\nNome: Francisco Silvestre de Oliveira\nCargo: Presidente da Câmara Municipal de Coruche\n419610143",
    "nipc": "506722422",
    "distrito": "Santarém",
    "concelho": "Coruche",
    "freguesia": "União das Freguesias de Coruche, Fajarda e Erra",
    "site": "www.cm-coruche.pt",
    "email": "geral@cm-coruche.pt",
    "designacao_contrato": "Aquisição de dois módulos pré-fabricados para o Centro de Recolha Oficial de Coruche",
    "descricao": "Aquisição de dois módulos pré-fabricados para o Centro de Recolha Oficial de Coruche",
    "preco_base": "15.767,99 EUR",
    "prazo_execucao": "90 DIAS",
    "prazo_apresentacao_propostas": "15-10-2025 23:59",
    "fundos_eu": "Sim",
    "plataforma_eletronica": "ACIN",
    "url_procedimento": "https://www.acingov.pt",
    "autor_nome": "Francisco Silvestre de Oliveira",
    "autor_cargo": "Presidente da Câmara Municipal de Coruche"
  },
  {
    "numero_procedimento": "N/A",
    "entidade": "AnÃºncio de procedimento  n.Âº 26064/2025  -  DiÃ¡rio da RepÃºblica n.Âº 191/2025, SÃ©rie II de 2025-10-03",
    "link": "https://diariodarepublica.pt/dr/detalhe/contrato-publico/26064-938108780"
  },
  {
    "numero_procedimento": "N/A",
    "entidade": "AnÃºncio de procedimento  n.Âº 26066/2025  -  DiÃ¡rio da RepÃºblica n.Âº 191/2025, SÃ©rie II de 2025-10-03",
    "link": "https://diariodarepublica.pt/dr/detalhe/contrato-publico/26066-938108781"
  },
  {
    "numero_procedimento": "N/A",
    "entidade": "AnÃºncio de procedimento  n.Âº 26067/2025  -  DiÃ¡rio da RepÃºblica n.Âº 191/2025, SÃ©rie II de 2025-10-03",
    "link": "https://diariodarepublica.pt/dr/detalhe/contrato-publico/26067-938108782"
  },
  {
    "numero_procedimento": "N/A",
    "entidade": "Empreendimentos Hidroeléctr.A.Tâmega e Barroso,SA",
    "link": "https://diariodarepublica.pt/dr/detalhe/contrato-publico/26069-938108783",
    "detalhes_completos": "Alteração do Anúncio de procedimento n.º 25999/2025, de 2025-10-03, com o ID 419595095\n\n1 - IDENTIFICAÇÃO E CONTACTOS DA ENTIDADE ADJUDICANTE\nDesignação da entidade adjudicante: Empreendimentos Hidroeléctr.A.Tâmega e Barroso,SA\nNIPC: 502227842\nEndereço: Rua D. Nuno Álvares Pereira\nCódigo postal: 4870-160\nLocalidade: Ribeira de Pena\nPaís: Portugal\nNUT III: PT11B\nDistrito: Vila Real\nConcelho: Ribeira de Pena\nFreguesia: Todas\nTelefone: 259490420\nFax: 259490429\nEndereço Eletrónico: inesferreira@ehatb.pt\neDelivery Gateway (URL): https://community.vortal.biz/public/\nFunção da Organização: Adquirente\nNorma jurídica da Entidade Adjudicante: Autoridade da administração central\nÁrea de atividade da Autoridade Adjudicante: Serviços públicos das administrações públicas\n\n2 - JORNAL OFICIAL DA UNIÃO EUROPEIA\nO procedimento a que este anúncio diz respeito também é publicitado no Jornal Oficial da União Europeia? Não\n\n3 - AVISO\nModelo de Anúncio: Concurso público\nData de Envio do Anúncio: 03-10-2025\n\n5 - PROCESSO\nTipo de Procedimento: Concurso público\nPreço base do procedimento: Sim\nValor do preço base do procedimento: 36.378,00 EUR\nProcedimento com lotes? Não\n\n6 - OBJETO DO CONTRATO\nNúmero de referência interna: Concurso Público nº 134-CP-nº6/2025\nDesignação do contrato: Locação de equipamentos (stands, tendas e outros) para o evento “Feira da Castanha”, em Carrazedo Montenegro -Valpaços \nDescrição: Locação de equipamentos (stands, tendas e outros) para o evento “Feira da Castanha”, em Carrazedo Montenegro - Valpaços \nTipo de Contrato Principal: Locação de Bens Móveis\nTipo de Contrato: Locação de Bens Móveis\nClassificação CPV (Vocabulário Comum para os Contratos Públicos)\nObjeto principal\nVocabulário Principal: 39154100\nPreço base s/IVA: 36.378,00 EUR\n\n7 - INDICAÇÕES ADICIONAIS\nO contrato envolve aquisição conjunta (satisfação de várias entidades)? Não\nO contrato é adjudicado por uma central de compras? Não\n\n8 - TÉCNICAS\nO concurso destina-se à celebração de um acordo-quadro? Inexistência de acordo-quadro\nÉ utilizado um leilão eletrónico? Não\nÉ adotada uma fase de negociação? Não\nSistema de Aquisição Dinâmico: Inexistência de sistema de aquisição dinâmico\n\n9 - LOCAL DA EXECUÇÃO DO CONTRATO\nLOCAL DA EXECUÇÃO DO CONTRATO (PROCEDIMENTO)\nPaís: Portugal\nNUT III: PT11B\nLocalidade: Vila Real\nDistrito: Vila Real\nConcelho: Valpaços\nFreguesia: Freguesia de Carrazedo de Montenegro e Curros\n\n10 - PRAZO DE EXECUÇÃO DO CONTRATO\nPrazo de execução do contrato: 15 DIAS\nPrevisão de renovações: Não\n\n11 - FUNDOS EU\nTêm fundos EU? Não\n\n12 - DOCUMENTOS DE HABILITAÇÃO\nHabilitação para o exercício da atividade profissional: Não\n\n13 - CONDIÇÕES DE APRESENTAÇÃO\nPlataforma eletrónica utilizada pela entidade adjudicante: VORTAL\nURL para Apresentação: https://community.vortal.biz/public/\nAdmissibilidade da apresentação de propostas variantes: Não autorizado\nPrazo para apresentação das propostas: 09-10-2025 17:00\nPrazo durante o qual os concorrentes são obrigados a manter as respetivas propostas: 66 dias a contar do termo do prazo para a apresentação das propostas\nIndicação de Subcontratação na Proposta: Inexistência de indicação de subcontratação\n\n14 - PRESTAÇÃO DE CAUÇÃO\nPrestação de caução: Não\n\n15 - FORNECIMENTO DAS PEÇAS DO CONCURSO, APRESENTAÇÃO DE PEDIDOS DE PARTICIPAÇÃO E APRESENTAÇÃO DAS PROPOSTAS\nLink para acesso às peças do concurso (URL): https://community.vortal.biz/Public/public-tender-documents/aEh6U1czamxzVlRhdCtZYlRUYW5NS3ozSGZVWHAxeUJ2Z3ZMRk44bHVVajd1bGFuTmdFY1p6NEtsMlcrd2NiL3l6VFNYS05Qb1gxWTZsUW5OSmp4VWc9PTdVcEo5\n\n20 - OUTROS REQUISITOS\nInformação sobre contratos reservados. Aplica-se a contratos reservados (54º-A)? Não\n\n21 - CRITÉRIO DE ADJUDICAÇÃO\nMultifator: Não\nMonofator:\nNome: Outros\nOutro nome: Preço\n\n24 - CONDIÇÕES DO CONTRATO\nFaturação Eletrónica: Permitido\nObrigação de Subcontratação:\nCódigo da Obrigação de Subcontratação: Não é aplicável nenhuma obrigação de subcontratação.\n\n25 - COMPRA PÚBLICA ESTRATÉGICA\nCompra Pública Estratégica: Inexistência de contratação pública estratégica\n\n26 - INFORMAÇÕES ADICIONAIS\nContrato adequado para PME: Sim\nCobertura ACP (Acordo dos Contratos Públicos da Organização Mundial do Comércio): Não\n\n27 - IDENTIFICAÇÃO E CONTACTOS DO ÓRGÃO DE RECURSOS ADMINISTRATIVOS\nDesignação: Empreendimentos Hidroelétricos do Alto Tâmega e Barroso, EIM, SA\nEndereço: Rua D. Nuno Alvares Pereira nº 12 A\nCódigo postal: 4870-160\nLocalidade: Ribeira de Pena\nTelefone: +351 276351468\nFax: +351 276351470\nEndereço eletrónico: geral@ehatb.pt\n\n28 - IDENTIFICAÇÃO DO(S) AUTOR(ES) DE ANÚNCIO\nNome: Maria de Fátima Pereira Fernandes Alves\nCargo: Presidente do Conselho de Administração\n\n29 - ALTERAÇÃO\nMotivo da Alteração: Informações atualizadas\nIdentificador da Versão do Anúncio a Alterar: 6e2e7bbd-be9b-446a-a3f9-285d13a92c4e-01\nIdentificador das Secções Alteradas do Anúncio Anterior: Condições de Apresentação\nDescrição das Alterações: Correção do prazo para apresentação das propostas\nAlteração dos Documentos do Concurso: Não\n419612817",
    "nipc": "502227842",
    "distrito": "Vila Real",
    "concelho": "Ribeira de Pena",
    "freguesia": "Todas",
    "site": null,
    "email": "inesferreira@ehatb.pt",
    "designacao_contrato": "Locação de equipamentos (stands, tendas e outros) para o evento “Feira da Castanha”, em Carrazedo Montenegro -Valpaços",
    "descricao": "Locação de equipamentos (stands, tendas e outros) para o evento “Feira da Castanha”, em Carrazedo Montenegro - Valpaços",
    "preco_base": "36.378,00 EUR",
    "prazo_execucao": "15 DIAS",
    "prazo_apresentacao_propostas": "09-10-2025 17:00",
    "fundos_eu": "Não",
    "plataforma_eletronica": "VORTAL",
    "url_procedimento": "https://community.vortal.biz/public/",
    "autor_nome": "Maria de Fátima Pereira Fernandes Alves",
    "autor_cargo": "Presidente do Conselho de Administração"
  },
  {
    "numero_procedimento": "N/A",
    "entidade": "AnÃºncio de procedimento  n.Âº 26070/2025  -  DiÃ¡rio da RepÃºblica n.Âº 191/2025, SÃ©rie II de 2025-10-03",
    "link": "https://diariodarepublica.pt/dr/detalhe/contrato-publico/26070-938108784"
  },
  {
    "numero_procedimento": "N/A",
    "entidade": "AnÃºncio de procedimento  n.Âº 26071/2025  -  DiÃ¡rio da RepÃºblica n.Âº 191/2025, SÃ©rie II de 2025-10-03",
    "link": "https://diariodarepublica.pt/dr/detalhe/contrato-publico/26071-938108785"
  },
  {
    "numero_procedimento": "N/A",
    "entidade": "AnÃºncio de procedimento  n.Âº 26072/2025  -  DiÃ¡rio da RepÃºblica n.Âº 191/2025, SÃ©rie II de 2025-10-03",
    "link": "https://diariodarepublica.pt/dr/detalhe/contrato-publico/26072-938108786"
  },
  {
    "numero_procedimento": "N/A",
    "entidade": "AnÃºncio de procedimento  n.Âº 26074/2025  -  DiÃ¡rio da RepÃºblica n.Âº 191/2025, SÃ©rie II de 2025-10-03",
    "link": "https://diariodarepublica.pt/dr/detalhe/contrato-publico/26074-938108787"
  },
  {
    "numero_procedimento": "N/A",
    "entidade": "AnÃºncio de procedimento  n.Âº 26076/2025  -  DiÃ¡rio da RepÃºblica n.Âº 191/2025, SÃ©rie II de 2025-10-03",
    "link": "https://diariodarepublica.pt/dr/detalhe/contrato-publico/26076-938108788"
  },
  {
    "numero_procedimento": "N/A",
    "entidade": "AnÃºncio de procedimento  n.Âº 26078/2025  -  DiÃ¡rio da RepÃºblica n.Âº 191/2025, SÃ©rie II de 2025-10-03",
    "link": "https://diariodarepublica.pt/dr/detalhe/contrato-publico/26078-938108789"
  },
  {
    "numero_procedimento": "N/A",
    "entidade": "AnÃºncio de procedimento  n.Âº 26079/2025  -  DiÃ¡rio da RepÃºblica n.Âº 191/2025, SÃ©rie II de 2025-10-03",
    "link": "https://diariodarepublica.pt/dr/detalhe/contrato-publico/26079-938108790"
  },
  {
    "numero_procedimento": "N/A",
    "entidade": "AnÃºncio de procedimento  n.Âº 26080/2025  -  DiÃ¡rio da RepÃºblica n.Âº 191/2025, SÃ©rie II de 2025-10-03",
    "link": "https://diariodarepublica.pt/dr/detalhe/contrato-publico/26080-938108791"
  },
  {
    "numero_procedimento": "N/A",
    "entidade": "AnÃºncio de procedimento  n.Âº 26081/2025  -  DiÃ¡rio da RepÃºblica n.Âº 191/2025, SÃ©rie II de 2025-10-03",
    "link": "https://diariodarepublica.pt/dr/detalhe/contrato-publico/26081-938108795"
  },
  {
    "numero_procedimento": "N/A",
    "entidade": "AnÃºncio de procedimento  n.Âº 26084/2025  -  DiÃ¡rio da RepÃºblica n.Âº 191/2025, SÃ©rie II de 2025-10-03",
    "link": "https://diariodarepublica.pt/dr/detalhe/contrato-publico/26084-938108796"
  }
]