[
  {
    "numero_procedimento": "N/A",
    "entidade": "Município de Monção",
    "link": "https://diariodarepublica.pt/dr/detalhe/contrato-publico/23586-934278905",
    "detalhes_completos": "1 - IDENTIFICAÇÃO E CONTACTOS DA ENTIDADE ADJUDICANTE\nDesignação da entidade adjudicante: Município de Monção\nNIPC: 501937471\nEndereço: Edifício Loreto\nCódigo postal: 4950-480\nLocalidade: Viana do Castelo\nPaís: Portugal\nNUT III: PT111\nDistrito: Viana do Castelo\nConcelho: Monção\nFreguesia: Todas\nTelefone: 251649000\nFax: 251649010\nEndereço da Entidade (URL): www.cm-moncao.pt\nEndereço Eletrónico: gap@cm-moncao.pt\neDelivery Gateway (URL): https://community.vortal.biz/public/\nFunção da Organização: Adquirente\nNorma jurídica da Entidade Adjudicante: Autoridade local\nÁrea de atividade da Autoridade Adjudicante: Serviços públicos das administrações públicas\n\n2 - JORNAL OFICIAL DA UNIÃO EUROPEIA\nO procedimento a que este anúncio diz respeito também é publicitado no Jornal Oficial da União Europeia? Não\n\n3 - AVISO\nModelo de Anúncio: Concurso público\nData de Envio do Anúncio: 04-09-2025\n\n5 - PROCESSO\nTipo de Procedimento: Concurso público\nPreço base do procedimento: Sim\nValor do preço base do procedimento: 205.285,00 EUR\nProcedimento com lotes? Não\n\n6 - OBJETO DO CONTRATO\nNúmero de referência interna: 17_578_5_DPOP\nDesignação do contrato: Aquisição de serviços para aluguer de instalações provisórias para o Centro de Saúde de Monção\nDescrição: Aquisição de serviços para aluguer de instalações provisórias para o Centro de Saúde de Monção\nTipo de Contrato Principal: Aquisição de Serviços\nTipo de Contrato: Aquisição de Serviços\nClassificação CPV (Vocabulário Comum para os Contratos Públicos)\nObjeto principal\nVocabulário Principal: 55250000\nPreço base s/IVA: 205.285,00 EUR\n\n7 - INDICAÇÕES ADICIONAIS\nO contrato envolve aquisição conjunta (satisfação de várias entidades)? Não\nO contrato é adjudicado por uma central de compras? Não\n\n8 - TÉCNICAS\nO concurso destina-se à celebração de um acordo-quadro? Inexistência de acordo-quadro\nÉ utilizado um leilão eletrónico? Não\nÉ adotada uma fase de negociação? Não\nSistema de Aquisição Dinâmico: Inexistência de sistema de aquisição dinâmico\n\n9 - LOCAL DA EXECUÇÃO DO CONTRATO\nLOCAL DA EXECUÇÃO DO CONTRATO (PROCEDIMENTO)\nPaís: Portugal\nNUT III: PT111\nLocalidade: Viana do Castelo\nDistrito: Viana do Castelo\nConcelho: Monção\nFreguesia: União das Freguesias de Monção e Troviscoso\n\n10 - PRAZO DE EXECUÇÃO DO CONTRATO\nPrazo de execução do contrato: 480 DIAS\nPrevisão de renovações: Não\n\n11 - FUNDOS EU\nTêm fundos EU? Não\n\n12 - DOCUMENTOS DE HABILITAÇÃO\nHabilitação para o exercício da atividade profissional: Não\n\n13 - CONDIÇÕES DE APRESENTAÇÃO\nPlataforma eletrónica utilizada pela entidade adjudicante: VORTAL\nURL para Apresentação: https://community.vortal.biz/public/\nAdmissibilidade da apresentação de propostas variantes: Não autorizado\nPrazo para apresentação das propostas: 10-09-2025 16:15\nPrazo durante o qual os concorrentes são obrigados a manter as respetivas propostas: 66 dias a contar do termo do prazo para a apresentação das propostas\nIndicação de Subcontratação na Proposta: Inexistência de indicação de subcontratação\n\n14 - PRESTAÇÃO DE CAUÇÃO\nPrestação de caução: Não\n\n15 - FORNECIMENTO DAS PEÇAS DO CONCURSO, APRESENTAÇÃO DE PEDIDOS DE PARTICIPAÇÃO E APRESENTAÇÃO DAS PROPOSTAS\nLink para acesso às peças do concurso (URL): https://community.vortal.biz/Public/public-tender-documents/NCtPZUhwQzcxYnNXR3FvSnpFQ2d0V2paeGF6dVl4Y1R6ZW5aSnN3UFpyUnUrdldHaHVFUDBjT1ZZZnpCRnV0eXFlRDNaVEpvckZiUmZEREd1TjJQT0E9PSQ4dHRa\n\n20 - OUTROS REQUISITOS\nInformação sobre contratos reservados. Aplica-se a contratos reservados (54º-A)? Não\n\n21 - CRITÉRIO DE ADJUDICAÇÃO\nMultifator: Não\nMonofator:\nNome: Preço\n\n24 - CONDIÇÕES DO CONTRATO\nFaturação Eletrónica: Permitido\nObrigação de Subcontratação:\nCódigo da Obrigação de Subcontratação: Não é aplicável nenhuma obrigação de subcontratação.\n\n25 - COMPRA PÚBLICA ESTRATÉGICA\nCompra Pública Estratégica: Inexistência de contratação pública estratégica\n\n26 - INFORMAÇÕES ADICIONAIS\nContrato adequado para PME: Sim\nCobertura ACP (Acordo dos Contratos Públicos da Organização Mundial do Comércio): Não\n\n27 - IDENTIFICAÇÃO E CONTACTOS DO ÓRGÃO DE RECURSOS ADMINISTRATIVOS\nDesignação: Câmara Municipal de Monção\nEndereço: Largo do Loreto n. 60\nCódigo postal: 4950-480\nLocalidade: Monção\nTelefone: +351 251649000\nFax: +351 251649000\nEndereço eletrónico: gap@cm-moncao.pt\n\n28 - IDENTIFICAÇÃO DO(S) AUTOR(ES) DE ANÚNCIO\nNome: António José Fernandes Barbosa\nCargo: Presidente da Câmara Municipal\n419503612",
    "nipc": "501937471",
    "distrito": "Viana do Castelo",
    "concelho": "Monção",
    "freguesia": "Todas",
    "site": "www.cm-moncao.pt",
    "email": "gap@cm-moncao.pt",
    "designacao_contrato": "Aquisição de serviços para aluguer de instalações provisórias para o Centro de Saúde de Monção",
    "descricao": "Aquisição de serviços para aluguer de instalações provisórias para o Centro de Saúde de Monção",
    "preco_base": "205.285,00 EUR",
    "prazo_execucao": "480 DIAS",
    "prazo_apresentacao_propostas": "10-09-2025 16:15",
    "fundos_eu": "Não",
    "plataforma_eletronica": "VORTAL",
    "url_procedimento": "https://community.vortal.biz/public/",
    "autor_nome": "António José Fernandes Barbosa",
    "autor_cargo": "Presidente da Câmara Municipal"
  },
  {
    "numero_procedimento": "N/A",
    "entidade": "Lar de Santa Estefânia",
    "link": "https://diariodarepublica.pt/dr/detalhe/contrato-publico/23588-934278907",
    "detalhes_completos": "Alteração do Anúncio de procedimento n.º 22436/2025, de 2025-08-21, com o ID 419456617\n\n1 - IDENTIFICAÇÃO E CONTACTOS DA ENTIDADE ADJUDICANTE\nDesignação da entidade adjudicante: Lar de Santa Estefânia\nNIPC: 500905657\nServiço/Órgão/Pessoa de contacto: Direção do Lar de Santa Estefânia\nEndereço: Largo Martins Sarmento, 50\nCódigo postal: 4800-432\nLocalidade: Guimarães\nPaís: Portugal\nNUT III: PT119\nDistrito: Braga\nConcelho: Guimarães\nFreguesia: União das Freguesias de Oliveira, São Paio e São Sebastião\nTelefone: 253415119\nFax: 253415119\nEndereço da Entidade (URL): www.santaestefania.pt\nEndereço Eletrónico: larsantaestefania@gmail.com\neDelivery Gateway (URL): https://www.acingov.pt\nFunção da Organização: Adquirente\nSubfunção da Organização: Organização que recebe as propostas\nNorma jurídica da Entidade Adjudicante: Organismo de direito público\nÁrea de atividade da Autoridade Adjudicante: Serviços públicos das administrações públicas\n\n2 - JORNAL OFICIAL DA UNIÃO EUROPEIA\nO procedimento a que este anúncio diz respeito também é publicitado no Jornal Oficial da União Europeia? Não\n\n3 - AVISO\nModelo de Anúncio: Concurso público\nData de Envio do Anúncio: 04-09-2025\n\n5 - PROCESSO\nTipo de Procedimento: Concurso público\nPreço base do procedimento: Não\nProcedimento com lotes? Não\n\n6 - OBJETO DO CONTRATO\nNúmero de referência interna: CP/1/2025\nDesignação do contrato: Alteração de parte de um edificado para adaptação a um estabelecimento de apoio social (Creche). Os espaços já se encontram edificados alterando-se as compartimentações conforme o estabelecido na legislação para este tipo de edificado.\nDescrição: Alteração de parte de um edificado para adaptação a um estabelecimento de apoio social (Creche). Os espaços já se encontram edificados alterando-se as compartimentações conforme o estabelecido na legislação para este tipo de edificado.\nTipo de Contrato Principal: Concessão de Obras Públicas\nTipo de Contrato: Concessão de Obras Públicas\nClassificação CPV (Vocabulário Comum para os Contratos Públicos)\nObjeto principal\nVocabulário Principal: 45000000\n\n7 - INDICAÇÕES ADICIONAIS\nO contrato envolve aquisição conjunta (satisfação de várias entidades)? Não\nO contrato é adjudicado por uma central de compras? Não\n\n8 - TÉCNICAS\nO concurso destina-se à celebração de um acordo-quadro? Inexistência de acordo-quadro\nÉ utilizado um leilão eletrónico? Não\nÉ adotada uma fase de negociação? Não\nSistema de Aquisição Dinâmico: Inexistência de sistema de aquisição dinâmico\n\n9 - LOCAL DA EXECUÇÃO DO CONTRATO\nLOCAL DA EXECUÇÃO DO CONTRATO (PROCEDIMENTO)\nPaís: Portugal\nNUT III: PT119\nLocalidade: União das Freguesias de Oliveira, São Paio e São Sebastião\nDistrito: Braga\nConcelho: Guimarães\nFreguesia: União das Freguesias de Oliveira, São Paio e São Sebastião\n\n10 - PRAZO DE EXECUÇÃO DO CONTRATO\nPrazo de execução do contrato: 6 MESES\nPrevisão de renovações: Não\n\n11 - FUNDOS EU\nTêm fundos EU? Sim\n\n12 - DOCUMENTOS DE HABILITAÇÃO\nHabilitação para o exercício da atividade profissional: Sim\nTipo: Alvará\nDescrição: Documentos de Habilitação\n\n13 - CONDIÇÕES DE APRESENTAÇÃO\nPlataforma eletrónica utilizada pela entidade adjudicante: ACIN\nURL para Apresentação: https://www.acingov.pt\nAdmissibilidade da apresentação de propostas variantes: Não autorizado\nPrazo para apresentação das propostas: 17-09-2025 00:00\nPrazo durante o qual os concorrentes são obrigados a manter as respetivas propostas: 66 dias a contar do termo do prazo para a apresentação das propostas\nIndicação de Subcontratação na Proposta: Inexistência de indicação de subcontratação\n\n14 - PRESTAÇÃO DE CAUÇÃO\nPrestação de caução: Não\n\n15 - FORNECIMENTO DAS PEÇAS DO CONCURSO, APRESENTAÇÃO DE PEDIDOS DE PARTICIPAÇÃO E APRESENTAÇÃO DAS PROPOSTAS\nLink para acesso às peças do concurso (URL): https://www.acingov.pt/acingovprod/2/zonaPublica/zona_publica_c/donwloadProcedurePiece/OTM0NTcy\n\n20 - OUTROS REQUISITOS\nInformação sobre contratos reservados. Aplica-se a contratos reservados (54º-A)? Não\n\n21 - CRITÉRIO DE ADJUDICAÇÃO\nMultifator: Não\nMonofator:\nNome: Preço\n\n24 - CONDIÇÕES DO CONTRATO\nFaturação Eletrónica: Não autorizado\nObrigação de Subcontratação:\nCódigo da Obrigação de Subcontratação: Não é aplicável nenhuma obrigação de subcontratação.\n\n25 - COMPRA PÚBLICA ESTRATÉGICA\nCompra Pública Estratégica: Inexistência de contratação pública estratégica\n\n26 - INFORMAÇÕES ADICIONAIS\nContrato adequado para PME: Não\nCobertura ACP (Acordo dos Contratos Públicos da Organização Mundial do Comércio): Não\n\n27 - IDENTIFICAÇÃO E CONTACTOS DO ÓRGÃO DE RECURSOS ADMINISTRATIVOS\nDesignação: Lar de Santa Estefânia\nEndereço: Largo Martins Sarmento, 50 4800-432\nCódigo postal: 4800-432\nLocalidade: Oliveira do Castelo\nTelefone: 253415119\nFax: \nEndereço eletrónico: larsantaestefania@gmail.com\n\n28 - IDENTIFICAÇÃO DO(S) AUTOR(ES) DE ANÚNCIO\nNome: José Fernando Rodrigues Alves Pinto\nCargo: Presidente da Direção\n\n29 - ALTERAÇÃO\nMotivo da Alteração: Informações atualizadas\nIdentificador da Versão do Anúncio a Alterar: f4dfb1d4-481f-4c22-aeb5-8d1b92202519-01\nIdentificador das Secções Alteradas do Anúncio Anterior: Condições de Apresentação\nDescrição das Alterações: Modificação do prazo para a apresentação de propostas\nAlteração dos Documentos do Concurso: Sim\nData de alteração dos documentos do concurso: 02-09-2025\n419505338",
    "nipc": "500905657",
    "distrito": "Braga",
    "concelho": "Guimarães",
    "freguesia": "União das Freguesias de Oliveira, São Paio e São Sebastião",
    "site": "www.santaestefania.pt",
    "email": "larsantaestefania@gmail.com",
    "designacao_contrato": "Alteração de parte de um edificado para adaptação a um estabelecimento de apoio social (Creche). Os espaços já se encontram edificados alterando-se as compartimentações conforme o estabelecido na legislação para este tipo de edificado.",
    "descricao": "Alteração de parte de um edificado para adaptação a um estabelecimento de apoio social (Creche). Os espaços já se encontram edificados alterando-se as compartimentações conforme o estabelecido na legislação para este tipo de edificado.",
    "preco_base": null,
    "prazo_execucao": "6 MESES",
    "prazo_apresentacao_propostas": "17-09-2025 00:00",
    "fundos_eu": "Sim",
    "plataforma_eletronica": "ACIN",
    "url_procedimento": "https://www.acingov.pt",
    "autor_nome": "José Fernando Rodrigues Alves Pinto",
    "autor_cargo": "Presidente da Direção"
  },
  {
    "numero_procedimento": "N/A",
    "entidade": "Município de Ansião",
    "link": "https://diariodarepublica.pt/dr/detalhe/contrato-publico/23589-934278909",
    "detalhes_completos": "Alteração do Anúncio de procedimento n.º 21481/2025, de 2025-08-08, com o ID 419415971\n\n1 - IDENTIFICAÇÃO E CONTACTOS DA ENTIDADE ADJUDICANTE\nDesignação da entidade adjudicante: Município de Ansião\nNIPC: 506605930\nServiço/Órgão/Pessoa de contacto: Câmara Municipal de Ansião\nEndereço: Praça do Município\nCódigo postal: 3240-143\nLocalidade: Ansião\nPaís: Portugal\nNUT III: PTZZZ\nDistrito: Todos\nConcelho: Todos\nFreguesia: Todas\nTelefone: 236670200\nFax: 236677481\nEndereço da Entidade (URL): www.cm-ansiao.pt\nEndereço Eletrónico: compraspublicas@cm-ansiao.pt\neDelivery Gateway (URL): https://www.acingov.pt\nFunção da Organização: Adquirente\nNorma jurídica da Entidade Adjudicante: Organismo de direito público\nÁrea de atividade da Autoridade Adjudicante: Serviços públicos das administrações públicas\n\n2 - JORNAL OFICIAL DA UNIÃO EUROPEIA\nO procedimento a que este anúncio diz respeito também é publicitado no Jornal Oficial da União Europeia? Não\n\n3 - AVISO\nModelo de Anúncio: Concurso público\nData de Envio do Anúncio: 04-09-2025\n\n5 - PROCESSO\nTipo de Procedimento: Concurso público\nPreço base do procedimento: Sim\nValor do preço base do procedimento: 1.882.900,00 EUR\nProcedimento com lotes? Não\n\n6 - OBJETO DO CONTRATO\nNúmero de referência interna: MUST-570\nDesignação do contrato: Reabilitação do Mercado Municipal de Ansião\nDescrição: Reabilitação do Mercado Municipal de Ansião\nTipo de Contrato Principal: Empreitada de Obras Públicas\nTipo de Contrato: Empreitada de Obras Públicas\nClassificação CPV (Vocabulário Comum para os Contratos Públicos)\nObjeto principal\nVocabulário Principal: 45213141\nPreço base s/IVA: 1.882.900,00 EUR\n\n7 - INDICAÇÕES ADICIONAIS\nO contrato envolve aquisição conjunta (satisfação de várias entidades)? Não\nO contrato é adjudicado por uma central de compras? Não\n\n8 - TÉCNICAS\nO concurso destina-se à celebração de um acordo-quadro? Inexistência de acordo-quadro\nÉ utilizado um leilão eletrónico? Não\nÉ adotada uma fase de negociação? Não\nSistema de Aquisição Dinâmico: Inexistência de sistema de aquisição dinâmico\n\n9 - LOCAL DA EXECUÇÃO DO CONTRATO\nLOCAL DA EXECUÇÃO DO CONTRATO (PROCEDIMENTO)\nPaís: Portugal\nNUT III: PT16F\nLocalidade: Freguesia de Ansião\nDistrito: Leiria\nConcelho: Ansião\nFreguesia: Freguesia de Ansião\n\n10 - PRAZO DE EXECUÇÃO DO CONTRATO\nPrazo de execução do contrato: 540 DIAS\nPrevisão de renovações: Não\n\n11 - FUNDOS EU\nTêm fundos EU? Não\n\n12 - DOCUMENTOS DE HABILITAÇÃO\nHabilitação para o exercício da atividade profissional: Sim\nTipo: Alvará\nDescrição: 1ª subcategoria da 1ª categoria (Estruturas e Elementos de betão) / no valor da proposta;\n4ª subcategoria da 1ª categoria (Alvenarias, rebocos e assentamento de cantarias);\n4ª subcategoria da 4ª categoria (Redes e instalações elétricas de tensão de serviço até 30 KV).\n\n13 - CONDIÇÕES DE APRESENTAÇÃO\nPlataforma eletrónica utilizada pela entidade adjudicante: ACIN\nURL para Apresentação: https://www.acingov.pt\nAdmissibilidade da apresentação de propostas variantes: Não autorizado\nPrazo para apresentação das propostas: 15-09-2025 23:59\nPrazo durante o qual os concorrentes são obrigados a manter as respetivas propostas: 66 dias a contar do termo do prazo para a apresentação das propostas\nIndicação de Subcontratação na Proposta: Inexistência de indicação de subcontratação\n\n14 - PRESTAÇÃO DE CAUÇÃO\nPrestação de caução: Sim\nPercentagem: 5%\nDescrição da Garantia Exigida: O valor da caução é de 5.00% do preço contratual.\n\n15 - FORNECIMENTO DAS PEÇAS DO CONCURSO, APRESENTAÇÃO DE PEDIDOS DE PARTICIPAÇÃO E APRESENTAÇÃO DAS PROPOSTAS\nLink para acesso às peças do concurso (URL): https://www.acingov.pt/acingovprod/2/zonaPublica/zona_publica_c/donwloadProcedurePiece/OTMyNjk2\n\n20 - OUTROS REQUISITOS\nInformação sobre contratos reservados. Aplica-se a contratos reservados (54º-A)? Não\n\n21 - CRITÉRIO DE ADJUDICAÇÃO\nMultifator: Não\nMonofator:\nNome: Preço\n\n24 - CONDIÇÕES DO CONTRATO\nFaturação Eletrónica: Permitido\nObrigação de Subcontratação:\nCódigo da Obrigação de Subcontratação: Não é aplicável nenhuma obrigação de subcontratação.\n\n25 - COMPRA PÚBLICA ESTRATÉGICA\nCompra Pública Estratégica: Inexistência de contratação pública estratégica\n\n26 - INFORMAÇÕES ADICIONAIS\nContrato adequado para PME: Não\nCobertura ACP (Acordo dos Contratos Públicos da Organização Mundial do Comércio): Não\n\n27 - IDENTIFICAÇÃO E CONTACTOS DO ÓRGÃO DE RECURSOS ADMINISTRATIVOS\nDesignação: Câmara Municipal de Ansião\nEndereço: Praça do Município\nCódigo postal: 3240-143\nLocalidade: Ansião\nTelefone: 236670200\nFax: \nEndereço eletrónico: geral@cm-ansiao.pt\n\n28 - IDENTIFICAÇÃO DO(S) AUTOR(ES) DE ANÚNCIO\nNome: António José Vicente Domingues\nCargo: Presidente da Cãmara\n\n29 - ALTERAÇÃO\nMotivo da Alteração: Correção pelo editor\nIdentificador da Versão do Anúncio a Alterar: deb9af45-d25a-466d-b613-2bd119be8c40-01\nIdentificador das Secções Alteradas do Anúncio Anterior: Condições de Apresentação; Identificação do(s) autor(es) do anúncio\nDescrição das Alterações: Modificação do prazo para a apresentação de propostas Atualização do(s) autor(es) do anúncio\nAlteração dos Documentos do Concurso: Não\n419505468",
    "nipc": "506605930",
    "distrito": "Todos",
    "concelho": "Todos",
    "freguesia": "Todas",
    "site": "www.cm-ansiao.pt",
    "email": "compraspublicas@cm-ansiao.pt",
    "designacao_contrato": "Reabilitação do Mercado Municipal de Ansião",
    "descricao": "Reabilitação do Mercado Municipal de Ansião",
    "preco_base": "1.882.900,00 EUR",
    "prazo_execucao": "540 DIAS",
    "prazo_apresentacao_propostas": "15-09-2025 23:59",
    "fundos_eu": "Não",
    "plataforma_eletronica": "ACIN",
    "url_procedimento": "https://www.acingov.pt",
    "autor_nome": "António José Vicente Domingues",
    "autor_cargo": "Presidente da Cãmara"
  },
  {
    "numero_procedimento": "N/A",
    "entidade": "Fundação INATEL",
    "link": "https://diariodarepublica.pt/dr/detalhe/contrato-publico/23594-934278912",
    "detalhes_completos": "1 - IDENTIFICAÇÃO E CONTACTOS DA ENTIDADE ADJUDICANTE\nDesignação da entidade adjudicante: Fundação INATEL\nNIPC: 500122237\nServiço/Órgão/Pessoa de contacto: Conselho de Administração\nEndereço: Calçada de Santana, nº 180\nCódigo postal: 1169-062\nLocalidade: Lisboa\nPaís: Portugal\nNUT III: PT170\nDistrito: Lisboa\nConcelho: Lisboa\nFreguesia: Freguesia de Arroios - Lisboa\nTelefone: 210027000\nFax: 210027000\nEndereço da Entidade (URL): https://www.inatel.pt\nEndereço Eletrónico: fundacao.inatel@inatel.pt\neDelivery Gateway (URL): https://www.acingov.pt\nFunção da Organização: Adquirente\nSubfunção da Organização: Organização cujo orçamento é utilizado para pagar o contrato; Organização que executa o pagamento; Organização que fornece informações adicionais sobre o processo de adjudicação; Organização que fornece mais informações sobre os prazos dos procedimentos de recurso; Organização que fornece acesso fora de linha aos documentos do concurso; Organização responsável pelo tratamento das propostas; Organização que recebe as propostas; Organização que trata os pedidos de participação; Organização que recebe pedidos de participação; Organização que fornece mais informações sobre os procedimentos de recurso; Organização que assina o contrato\nNorma jurídica da Entidade Adjudicante: Organismo de direito público\nÁrea de atividade da Autoridade Adjudicante: Atividades recreativas, culturais e religiosas\n\n2 - JORNAL OFICIAL DA UNIÃO EUROPEIA\nO procedimento a que este anúncio diz respeito também é publicitado no Jornal Oficial da União Europeia? Sim\n\n3 - AVISO\nModelo de Anúncio: Concurso público\nData de Envio do Anúncio: 02-09-2025\n\n5 - PROCESSO\nTipo de Procedimento: Concurso público\nPreço base do procedimento: Sim\nValor do preço base do procedimento: 168.343,34 EUR\nProcedimento com lotes? Sim\nNº Máx. de Lotes Autorizado: 28\nNúmero máximo de lotes que podem ser adjudicados a um concorrente: 28\n\n6 - OBJETO DO CONTRATO\nNúmero de referência interna: P.25.179/NCP\nDesignação do contrato: Aquisição de produtos de hotelaria não alimentar para as diversas Unidades Orgânicas da Fundação INATEL em Portugal Continental e nas Regiões Autónomas da Madeira e dos Açores\nDescrição: Aquisição de produtos de hotelaria não alimentar para as diversas Unidades Orgânicas da Fundação INATEL em Portugal Continental e nas Regiões Autónomas da Madeira e dos Açores\nOpções: Não\nTipo de Contrato Principal: Aquisição de Bens Móveis\nTipo de Contrato: Aquisição de Bens Móveis\nClassificação CPV (Vocabulário Comum para os Contratos Públicos)\nObjeto principal\nVocabulário Principal: 19640000\nPreço base s/IVA: 168.343,34 EUR\nLotes: \nNº: LOT-0001\nDescrição do Lote: Hotéis INATEL Continente (Sacos)\nPreço base s/IVA: 50.004,74 EUR\nClassificação CPV (Vocabulário Comum para os Contratos Públicos)\nObjeto principal\nVocabulário Principal: 19640000\nNº: LOT-0002\nDescrição do Lote: Hotel INATEL Porto Santo (Sacos)\nPreço base s/IVA: 9.025,52 EUR\nClassificação CPV (Vocabulário Comum para os Contratos Públicos)\nObjeto principal\nVocabulário Principal: 19640000\nNº: LOT-0003\nDescrição do Lote: Delegações INATEL Continente (Sacos)\nPreço base s/IVA: 1.686,51 EUR\nClassificação CPV (Vocabulário Comum para os Contratos Públicos)\nObjeto principal\nVocabulário Principal: 19640000\nNº: LOT-0004\nDescrição do Lote: Parque de Jogos 1.º de maio\nPreço base s/IVA: 533,61 EUR\nClassificação CPV (Vocabulário Comum para os Contratos Públicos)\nObjeto principal\nVocabulário Principal: 19640000\nNº: LOT-0005\nDescrição do Lote: Teatro da Trindade INATEL\nPreço base s/IVA: 109,24 EUR\nClassificação CPV (Vocabulário Comum para os Contratos Públicos)\nObjeto principal\nVocabulário Principal: 19640000\nNº: LOT-0006\nDescrição do Lote: Espaço INATEL Mouraria\nPreço base s/IVA: 65,37 EUR\nClassificação CPV (Vocabulário Comum para os Contratos Públicos)\nObjeto principal\nVocabulário Principal: 19640000\nNº: LOT-0007\nDescrição do Lote: Delegações INATEL Açores (Sacos)\nPreço base s/IVA: 28,55 EUR\nClassificação CPV (Vocabulário Comum para os Contratos Públicos)\nObjeto principal\nVocabulário Principal: 19640000\nNº: LOT-0008\nDescrição do Lote: Hotéis INATEL Continente (Descartáveis)\nPreço base s/IVA: 33.629,96 EUR\nClassificação CPV (Vocabulário Comum para os Contratos Públicos)\nObjeto principal\nVocabulário Principal: 19640000\nNº: LOT-0009\nDescrição do Lote: Hotel INATEL Porto Santo (Descartáveis)\nPreço base s/IVA: 1.720,05 EUR\nClassificação CPV (Vocabulário Comum para os Contratos Públicos)\nObjeto principal\nVocabulário Principal: 19640000\nNº: LOT-0010\nDescrição do Lote: Delegações INATEL Continente (Descartáveis)\nPreço base s/IVA: 667,92 EUR\nClassificação CPV (Vocabulário Comum para os Contratos Públicos)\nObjeto principal\nVocabulário Principal: 19640000\nNº: LOT-0011\nDescrição do Lote: Parque de Jogos 1.º de maio\nPreço base s/IVA: 221,30 EUR\nClassificação CPV (Vocabulário Comum para os Contratos Públicos)\nObjeto principal\nVocabulário Principal: 19640000\nNº: LOT-0012\nDescrição do Lote: Teatro da Trindade\nPreço base s/IVA: 161,45 EUR\nClassificação CPV (Vocabulário Comum para os Contratos Públicos)\nObjeto principal\nVocabulário Principal: 19640000\nNº: LOT-0013\nDescrição do Lote: Espaço INATEL Mouraria\nPreço base s/IVA: 4,84 EUR\nClassificação CPV (Vocabulário Comum para os Contratos Públicos)\nObjeto principal\nVocabulário Principal: 19640000\nNº: LOT-0014\nDescrição do Lote: Delegações INATEL Açores (Descartáveis)\nPreço base s/IVA: 40,30 EUR\nClassificação CPV (Vocabulário Comum para os Contratos Públicos)\nObjeto principal\nVocabulário Principal: 19640000\nNº: LOT-0015\nDescrição do Lote: Hotéis INATEL Continente (Descartáveis biodegradáveis / ecológicos)\nPreço base s/IVA: 33.050,94 EUR\nClassificação CPV (Vocabulário Comum para os Contratos Públicos)\nObjeto principal\nVocabulário Principal: 19640000\nNº: LOT-0016\nDescrição do Lote: Hotel INATEL Porto Santo (Descartáveis biodegradáveis/ ecológicos)\nPreço base s/IVA: 166,70 EUR\nClassificação CPV (Vocabulário Comum para os Contratos Públicos)\nObjeto principal\nVocabulário Principal: 19640000\nNº: LOT-0017\nDescrição do Lote: Hotéis INATEL Continente (Produtos Diversos I)\nPreço base s/IVA: 12.278,23 EUR\nClassificação CPV (Vocabulário Comum para os Contratos Públicos)\nObjeto principal\nVocabulário Principal: 19640000\nNº: LOT-0018\nDescrição do Lote: Hotel INATEL Porto Santo (Produtos Diversos I)\nPreço base s/IVA: 738,25 EUR\nClassificação CPV (Vocabulário Comum para os Contratos Públicos)\nObjeto principal\nVocabulário Principal: 19640000\nNº: LOT-0019\nDescrição do Lote: Delegações INATEL Continente (Produtos Diversos I)\nPreço base s/IVA: 545,14 EUR\nClassificação CPV (Vocabulário Comum para os Contratos Públicos)\nObjeto principal\nVocabulário Principal: 19640000\nNº: LOT-0020\nDescrição do Lote: Parque de Jogos 1.º de maio\nPreço base s/IVA: 128,15 EUR\nClassificação CPV (Vocabulário Comum para os Contratos Públicos)\nObjeto principal\nVocabulário Principal: 19640000\nNº: LOT-0021\nDescrição do Lote: Espaço INATEL Mouraria\nPreço base s/IVA: 37,06 EUR\nClassificação CPV (Vocabulário Comum para os Contratos Públicos)\nObjeto principal\nVocabulário Principal: 19640000\nNº: LOT-0022\nDescrição do Lote: Delegações INATEL Açores (Produtos Diversos I)\nPreço base s/IVA: 34,64 EUR\nClassificação CPV (Vocabulário Comum para os Contratos Públicos)\nObjeto principal\nVocabulário Principal: 19640000\nNº: LOT-0023\nDescrição do Lote: Hotéis INATEL Continente (Produtos Diversos II)\nPreço base s/IVA: 21.516,05 EUR\nClassificação CPV (Vocabulário Comum para os Contratos Públicos)\nObjeto principal\nVocabulário Principal: 19640000\nNº: LOT-0024\nDescrição do Lote: Hotel INATEL Porto Santo (Produtos Diversos II)\nPreço base s/IVA: 928,77 EUR\nClassificação CPV (Vocabulário Comum para os Contratos Públicos)\nObjeto principal\nVocabulário Principal: 19640000\nNº: LOT-0025\nDescrição do Lote: Delegações INATEL Continente (Produtos Diversos II)\nPreço base s/IVA: 709,78 EUR\nClassificação CPV (Vocabulário Comum para os Contratos Públicos)\nObjeto principal\nVocabulário Principal: 19640000\nNº: LOT-0026\nDescrição do Lote: Parque de Jogos 1.º de Maio\nPreço base s/IVA: 238,31 EUR\nClassificação CPV (Vocabulário Comum para os Contratos Públicos)\nObjeto principal\nVocabulário Principal: 19640000\nNº: LOT-0027\nDescrição do Lote: Espaço INATEL Mouraria\nPreço base s/IVA: 24,04 EUR\nClassificação CPV (Vocabulário Comum para os Contratos Públicos)\nObjeto principal\nVocabulário Principal: 19640000\nNº: LOT-0028\nDescrição do Lote: Delegações INATEL Açores (Produtos Diversos II)\nPreço base s/IVA: 47,92 EUR\nClassificação CPV (Vocabulário Comum para os Contratos Públicos)\nObjeto principal\nVocabulário Principal: 19640000\n\n7 - INDICAÇÕES ADICIONAIS\nO contrato envolve aquisição conjunta (satisfação de várias entidades)? Não\nO contrato é adjudicado por uma central de compras? Não\n\n8 - TÉCNICAS\nO concurso destina-se à celebração de um acordo-quadro? Inexistência de acordo-quadro\nÉ utilizado um leilão eletrónico? Não\nÉ adotada uma fase de negociação? Não\nSistema de Aquisição Dinâmico: Inexistência de sistema de aquisição dinâmico\n\n9 - LOCAL DA EXECUÇÃO DO CONTRATO\nLOCAL DA EXECUÇÃO DO CONTRATO (PROCEDIMENTO)\nPaís: Portugal\nNUT III: PTZZZ\nLocalidade: Lisboa\nDistrito: Todos\nConcelho: Todos\nFreguesia: Todas\nLOCAL DA EXECUÇÃO DO CONTRATO (LOTE)\nIdentificador do Lote: LOT-0001; LOT-0002; LOT-0003; LOT-0004; LOT-0005; LOT-0006; LOT-0007; LOT-0008; LOT-0009; LOT-0010; LOT-0011; LOT-0012; LOT-0013; LOT-0014; LOT-0015; LOT-0016; LOT-0017; LOT-0018; LOT-0019; LOT-0020; LOT-0021; LOT-0022; LOT-0023; LOT-0024; LOT-0025; LOT-0026; LOT-0027; LOT-0028\nPaís: Portugal\nNUT III: PTZZZ\nLocalidade: Lisboa\nDistrito: Todos\nConcelho: Todos\nFreguesia: Todas\n\n10 - PRAZO DE EXECUÇÃO DO CONTRATO\nIdentificador do Lote: LOT-0001; LOT-0002; LOT-0003; LOT-0004; LOT-0005; LOT-0006; LOT-0007; LOT-0008; LOT-0009; LOT-0010; LOT-0011; LOT-0012; LOT-0013; LOT-0014; LOT-0015; LOT-0016; LOT-0017; LOT-0018; LOT-0019; LOT-0020; LOT-0021; LOT-0022; LOT-0023; LOT-0024; LOT-0025; LOT-0026; LOT-0027; LOT-0028\nPrazo de execução do contrato: 12 MESES\nPrevisão de renovações: Não\n\n11 - FUNDOS EU\nIdentificador do Lote: LOT-0001; LOT-0002; LOT-0003; LOT-0004; LOT-0005; LOT-0006; LOT-0007; LOT-0008; LOT-0009; LOT-0010; LOT-0011; LOT-0012; LOT-0013; LOT-0014; LOT-0015; LOT-0016; LOT-0017; LOT-0018; LOT-0019; LOT-0020; LOT-0021; LOT-0022; LOT-0023; LOT-0024; LOT-0025; LOT-0026; LOT-0027; LOT-0028\nTêm fundos EU? Não\n\n12 - DOCUMENTOS DE HABILITAÇÃO\nHabilitação para o exercício da atividade profissional: Não\n\n13 - CONDIÇÕES DE APRESENTAÇÃO\nPlataforma eletrónica utilizada pela entidade adjudicante: ACIN\nURL para Apresentação: https://www.acingov.pt\nAdmissibilidade da apresentação de propostas variantes: Não autorizado\nPrazo para apresentação das propostas: 02-10-2025 23:59\nPrazo durante o qual os concorrentes são obrigados a manter as respetivas propostas: 66 dias a contar do termo do prazo para a apresentação das propostas\nApresentação de Catálogo Eletrónico: Permitido\nIndicação de Subcontratação na Proposta: Inexistência de indicação de subcontratação\n\n14 - PRESTAÇÃO DE CAUÇÃO\nPrestação de caução: Não\n\n15 - FORNECIMENTO DAS PEÇAS DO CONCURSO, APRESENTAÇÃO DE PEDIDOS DE PARTICIPAÇÃO E APRESENTAÇÃO DAS PROPOSTAS\nLink para acesso às peças do concurso (URL): https://www.acingov.pt/acingovprod/2/zonaPublica/zona_publica_c/donwloadProcedurePiece/OTczNjkw\n\n20 - OUTROS REQUISITOS\nIdentificador do Lote: LOT-0001; LOT-0002; LOT-0003; LOT-0004; LOT-0005; LOT-0006; LOT-0007; LOT-0008; LOT-0009; LOT-0010; LOT-0011; LOT-0012; LOT-0013; LOT-0014; LOT-0015; LOT-0016; LOT-0017; LOT-0018; LOT-0019; LOT-0020; LOT-0021; LOT-0022; LOT-0023; LOT-0024; LOT-0025; LOT-0026; LOT-0027; LOT-0028\nInformação sobre contratos reservados. Aplica-se a contratos reservados (54º-A)? Não\n\n21 - CRITÉRIO DE ADJUDICAÇÃO\nO Critério de adjudicação é diferenciado por lote? Não\nMultifator: Não\nMonofator:\nNome: Preço\n\n24 - CONDIÇÕES DO CONTRATO\nIdentificador do Lote: LOT-0001; LOT-0002; LOT-0003; LOT-0004; LOT-0005; LOT-0006; LOT-0007; LOT-0008; LOT-0009; LOT-0010; LOT-0011; LOT-0012; LOT-0013; LOT-0014; LOT-0015; LOT-0016; LOT-0017; LOT-0018; LOT-0019; LOT-0020; LOT-0021; LOT-0022; LOT-0023; LOT-0024; LOT-0025; LOT-0026; LOT-0027; LOT-0028\nFaturação Eletrónica: Permitido\nObrigação de Subcontratação:\nCódigo da Obrigação de Subcontratação: Não é aplicável nenhuma obrigação de subcontratação.\n\n25 - COMPRA PÚBLICA ESTRATÉGICA\nCompra Pública Estratégica: Inexistência de contratação pública estratégica\n\n26 - INFORMAÇÕES ADICIONAIS\nIdentificador do Lote: LOT-0001; LOT-0002; LOT-0003; LOT-0004; LOT-0005; LOT-0006; LOT-0007; LOT-0008; LOT-0009; LOT-0010; LOT-0011; LOT-0012; LOT-0013; LOT-0014; LOT-0015; LOT-0016; LOT-0017; LOT-0018; LOT-0019; LOT-0020; LOT-0021; LOT-0022; LOT-0023; LOT-0024; LOT-0025; LOT-0026; LOT-0027; LOT-0028\nContrato adequado para PME: Não\nCobertura ACP (Acordo dos Contratos Públicos da Organização Mundial do Comércio): Não\n\n27 - IDENTIFICAÇÃO E CONTACTOS DO ÓRGÃO DE RECURSOS ADMINISTRATIVOS\nDesignação: Conselho de Administração\nEndereço: Calçada de Santana, nº 180\nCódigo postal: 1169-062\nLocalidade: Lisboa\nTelefone: 210027000\nFax: 210027000\nEndereço eletrónico: NCP-Procedimentos@inatel.pt\nPrazo de interposição do recurso: 5 dias\n\n28 - IDENTIFICAÇÃO DO(S) AUTOR(ES) DE ANÚNCIO\nNome: Rita Martins Marques Canas\nCargo: Técnico\n419495992",
    "nipc": "500122237",
    "distrito": "Lisboa",
    "concelho": "Lisboa",
    "freguesia": "Freguesia de Arroios - Lisboa",
    "site": "https://www.inatel.pt",
    "email": "fundacao.inatel@inatel.pt",
    "designacao_contrato": "Aquisição de produtos de hotelaria não alimentar para as diversas Unidades Orgânicas da Fundação INATEL em Portugal Continental e nas Regiões Autónomas da Madeira e dos Açores",
    "descricao": "Aquisição de produtos de hotelaria não alimentar para as diversas Unidades Orgânicas da Fundação INATEL em Portugal Continental e nas Regiões Autónomas da Madeira e dos Açores",
    "preco_base": "168.343,34 EUR",
    "prazo_execucao": "12 MESES",
    "prazo_apresentacao_propostas": "02-10-2025 23:59",
    "fundos_eu": "Não",
    "plataforma_eletronica": "ACIN",
    "url_procedimento": "https://www.acingov.pt",
    "autor_nome": "Rita Martins Marques Canas",
    "autor_cargo": "Técnico"
  },
  {
    "numero_procedimento": "N/A",
    "entidade": "Câmara Municipal de Peso da Régua.",
    "link": "https://diariodarepublica.pt/dr/detalhe/contrato-publico/23595-934278913",
    "detalhes_completos": "Alteração do Anúncio de procedimento n.º 23424/2025, de 2025-09-03, com o ID 419499248\n\n1 - IDENTIFICAÇÃO E CONTACTOS DA ENTIDADE ADJUDICANTE\nDesignação da entidade adjudicante: Câmara Municipal de Peso da Régua.\nNIPC: 506829260\nServiço/Órgão/Pessoa de contacto: José Manuel Gonçalves\nEndereço: Praça do Município\nCódigo postal: 5050-224\nLocalidade: Vila Real\nPaís: Portugal\nNUT III: PT11D\nDistrito: Vila Real\nConcelho: Peso da Régua\nFreguesia: União das Freguesias de Peso da Régua e Godim\nTelefone: 254320230\nFax: 254314365\nEndereço Eletrónico: cmregua@cmpr.pt\neDelivery Gateway (URL): https://community.vortal.biz/public/\nFunção da Organização: Adquirente\nNorma jurídica da Entidade Adjudicante: Autoridade local\nÁrea de atividade da Autoridade Adjudicante: Serviços públicos das administrações públicas\n\n2 - JORNAL OFICIAL DA UNIÃO EUROPEIA\nO procedimento a que este anúncio diz respeito também é publicitado no Jornal Oficial da União Europeia? Não\n\n3 - AVISO\nModelo de Anúncio: Concurso público\nData de Envio do Anúncio: 04-09-2025\n\n5 - PROCESSO\nTipo de Procedimento: Concurso público\nPreço base do procedimento: Sim\nValor do preço base do procedimento: 424.077,39 EUR\nProcedimento com lotes? Não\n\n6 - OBJETO DO CONTRATO\nNúmero de referência interna: 33/2025\nDesignação do contrato: REABILITAÇÃO DE PARQUES INFANTIS – PESO DA RÉGUA\nDescrição: REABILITAÇÃO DE PARQUES INFANTIS – PESO DA RÉGUA\nTipo de Contrato Principal: Empreitada de Obras Públicas\nTipo de Contrato: Empreitada de Obras Públicas\nClassificação CPV (Vocabulário Comum para os Contratos Públicos)\nObjeto principal\nVocabulário Principal: 45236210\nPreço base s/IVA: 424.077,39 EUR\n\n7 - INDICAÇÕES ADICIONAIS\nO contrato envolve aquisição conjunta (satisfação de várias entidades)? Não\nO contrato é adjudicado por uma central de compras? Não\n\n8 - TÉCNICAS\nO concurso destina-se à celebração de um acordo-quadro? Inexistência de acordo-quadro\nÉ utilizado um leilão eletrónico? Não\nÉ adotada uma fase de negociação? Não\nSistema de Aquisição Dinâmico: Inexistência de sistema de aquisição dinâmico\n\n9 - LOCAL DA EXECUÇÃO DO CONTRATO\nLOCAL DA EXECUÇÃO DO CONTRATO (PROCEDIMENTO)\nPaís: Portugal\nNUT III: PTZZZ\nLocalidade: PORTUGAL\nDistrito: Todos\nConcelho: Todos\nFreguesia: Todas\n\n10 - PRAZO DE EXECUÇÃO DO CONTRATO\nPrazo de execução do contrato: 10 MESES\nPrevisão de renovações: Não\n\n11 - FUNDOS EU\nTêm fundos EU? Não\n\n12 - DOCUMENTOS DE HABILITAÇÃO\nHabilitação para o exercício da atividade profissional: Sim\nTipo: Alvará\nDescrição: 10ª subcategoria da 2ª categoria, da classe correspondente ao valor global da proposta.\n\n13 - CONDIÇÕES DE APRESENTAÇÃO\nPlataforma eletrónica utilizada pela entidade adjudicante: VORTAL\nURL para Apresentação: https://community.vortal.biz/public/\nAdmissibilidade da apresentação de propostas variantes: Não autorizado\nPrazo para apresentação das propostas: 06-09-2025 17:00\nPrazo durante o qual os concorrentes são obrigados a manter as respetivas propostas: 66 dias a contar do termo do prazo para a apresentação das propostas\nIndicação de Subcontratação na Proposta: Inexistência de indicação de subcontratação\n\n14 - PRESTAÇÃO DE CAUÇÃO\nPrestação de caução: Não\n\n15 - FORNECIMENTO DAS PEÇAS DO CONCURSO, APRESENTAÇÃO DE PEDIDOS DE PARTICIPAÇÃO E APRESENTAÇÃO DAS PROPOSTAS\nLink para acesso às peças do concurso (URL): https://community.vortal.biz/Public/public-tender-documents/Rk02Yi9FMFBRWVlPbnk2eGdRUUg1eUo5WXZ0b0FhempFb1BteFlNTzA5QS93T080WW90WXQxN25nR2lUSGpBVm5xYmk5c3JKSVdwU1hyc2c2MWp6M0E9PUBKczQz\n\n20 - OUTROS REQUISITOS\nInformação sobre contratos reservados. Aplica-se a contratos reservados (54º-A)? Não\n\n21 - CRITÉRIO DE ADJUDICAÇÃO\nMultifator: Não\nMonofator:\nNome: Preço\n\n24 - CONDIÇÕES DO CONTRATO\nFaturação Eletrónica: Permitido\nObrigação de Subcontratação:\nCódigo da Obrigação de Subcontratação: Não é aplicável nenhuma obrigação de subcontratação.\n\n25 - COMPRA PÚBLICA ESTRATÉGICA\nCompra Pública Estratégica: Inexistência de contratação pública estratégica\n\n26 - INFORMAÇÕES ADICIONAIS\nContrato adequado para PME: Sim\nCobertura ACP (Acordo dos Contratos Públicos da Organização Mundial do Comércio): Não\n\n27 - IDENTIFICAÇÃO E CONTACTOS DO ÓRGÃO DE RECURSOS ADMINISTRATIVOS\nDesignação: Câmara Municipal do Peso da Régua\nEndereço: Praça do Município\nCódigo postal: 5054-003\nLocalidade: Peso da Régua\nTelefone: +351 254320230\nFax: +351 254314365\nEndereço eletrónico: cmregua@cmpr.pt\n\n28 - IDENTIFICAÇÃO DO(S) AUTOR(ES) DE ANÚNCIO\nNome: José Manuel Gonçalves\nCargo: Presidente do Município\n\n29 - ALTERAÇÃO\nMotivo da Alteração: Correção pelo editor\nIdentificador da Versão do Anúncio a Alterar: da2099a1-6676-45a7-8b8c-7b11abd0ed29-02\nIdentificador das Secções Alteradas do Anúncio Anterior: Alteração\nDescrição das Alterações: Trata-se de alteração do prazo de entrega de propostas\nAlteração dos Documentos do Concurso: Não\n419505395",
    "nipc": "506829260",
    "distrito": "Vila Real",
    "concelho": "Peso da Régua",
    "freguesia": "União das Freguesias de Peso da Régua e Godim",
    "site": null,
    "email": "cmregua@cmpr.pt",
    "designacao_contrato": "REABILITAÇÃO DE PARQUES INFANTIS – PESO DA RÉGUA",
    "descricao": "REABILITAÇÃO DE PARQUES INFANTIS – PESO DA RÉGUA",
    "preco_base": "424.077,39 EUR",
    "prazo_execucao": "10 MESES",
    "prazo_apresentacao_propostas": "06-09-2025 17:00",
    "fundos_eu": "Não",
    "plataforma_eletronica": "VORTAL",
    "url_procedimento": "https://community.vortal.biz/public/",
    "autor_nome": "José Manuel Gonçalves",
    "autor_cargo": "Presidente do Município"
  },
  {
    "numero_procedimento": "N/A",
    "entidade": "CP Comboios de Portugal E.P.E",
    "link": "https://diariodarepublica.pt/dr/detalhe/contrato-publico/23603-934278918",
    "detalhes_completos": "Alteração do Anúncio de procedimento n.º 22008/2025, de 2025-08-18, com o ID 419429814\n\n1 - IDENTIFICAÇÃO E CONTACTOS DA ENTIDADE ADJUDICANTE\nDesignação da entidade adjudicante: CP Comboios de Portugal E.P.E\nNIPC: 500498601\nServiço/Órgão/Pessoa de contacto: Compras e Logística\nEndereço: Calçada do Duque nº20\nCódigo postal: 1249-109\nLocalidade: Lisboa\nPaís: Portugal\nNUT III: PT170\nDistrito: Lisboa\nConcelho: Lisboa\nFreguesia: Todas\nTelefone: 211023839\nFax: 211023839\nEndereço da Entidade (URL): www.cp.pt\nEndereço Eletrónico: compras@cp.pt\neDelivery Gateway (URL): https://www.acingov.pt\nFunção da Organização: Adquirente\nNorma jurídica da Entidade Adjudicante: Organismo de direito público\nÁrea de atividade da Entidade Adjudicante: Serviços urbanos de caminho de ferro, de elétricos, de tróleis ou de autocarros\nÁrea de atividade da Autoridade Adjudicante: Serviços públicos das administrações públicas\n\n2 - JORNAL OFICIAL DA UNIÃO EUROPEIA\nO procedimento a que este anúncio diz respeito também é publicitado no Jornal Oficial da União Europeia? Sim\n\n3 - AVISO\nModelo de Anúncio: Concurso limitado por prévia qualificação\nData de Envio do Anúncio: 02-09-2025\n\n5 - PROCESSO\nTipo de Procedimento: Concurso limitado por prévia qualificação\nPreço base do procedimento: Sim\nValor do preço base do procedimento: 2.192.976,76 EUR\nProcedimento com lotes? Não\n\n6 - OBJETO DO CONTRATO\nNúmero de referência interna: 827114\nDesignação do contrato: Aquisição da prestação de serviços de consultoria e assessoria técnica aos Sistemas de Venda da CP, manutenção preventiva, corretiva e evolutiva nos sistemas Bilhética sem Contacto (BSC) e reserva MBBilhete, desenvolvimento de novas soluções e apoio funcional e à utilização, nos termos definidos no presente caderno de encargos- condições particulares e seus anexos\nDescrição: Aquisição da prestação de serviços de consultoria e assessoria técnica aos Sistemas de Venda da CP, manutenção preventiva, corretiva e evolutiva nos sistemas Bilhética sem Contacto (BSC) e reserva MBBilhete, desenvolvimento de novas soluções e apoio funcional e à utilização, nos termos definidos no presente caderno de encargos- condições particulares e seus anexos\nOpções: Não\nTipo de Contrato Principal: Aquisição de Serviços\nTipo de Contrato: Aquisição de Serviços\nClassificação CPV (Vocabulário Comum para os Contratos Públicos)\nObjeto principal\nVocabulário Principal: 72262000\nPreço base s/IVA: 2.192.976,76 EUR\n\n7 - INDICAÇÕES ADICIONAIS\nO contrato envolve aquisição conjunta (satisfação de várias entidades)? Não\nO contrato é adjudicado por uma central de compras? Não\n\n8 - TÉCNICAS\nO concurso destina-se à celebração de um acordo-quadro? Inexistência de acordo-quadro\nÉ utilizado um leilão eletrónico? Não\nSistema de Aquisição Dinâmico: Inexistência de sistema de aquisição dinâmico\n\n9 - LOCAL DA EXECUÇÃO DO CONTRATO\nLOCAL DA EXECUÇÃO DO CONTRATO (PROCEDIMENTO)\nPaís: Portugal\nNUT III: PTZZZ\nLocalidade: Reboleira - Amadora\nDistrito: Todos\nConcelho: Todos\nFreguesia: Todas\n\n10 - PRAZO DE EXECUÇÃO DO CONTRATO\nPrazo de execução do contrato: 26 MESES\nPrevisão de renovações: Não\n\n11 - FUNDOS EU\nTêm fundos EU? Não\n\n12 - DOCUMENTOS DE HABILITAÇÃO\nHabilitação para o exercício da atividade profissional: Não\n\n13 - CONDIÇÕES DE APRESENTAÇÃO\nPlataforma eletrónica utilizada pela entidade adjudicante: ACIN\nURL para Apresentação: https://www.acingov.pt\nAdmissibilidade da apresentação de propostas variantes: Não autorizado\nPrazo para apresentação das candidaturas: 19-09-2025 23:59\nPrazo para a decisão de qualificação: 44 dias a contar do termo do prazo para a apresentação das candidaturas\nRequisitos mínimos \nRequisitos mínimos de capacidade técnica: 11.1 do Programa de Concurso\nRequisitos mínimos de capacidade financeira: 11.2 Programa de Concurso\nModelo de qualificação: Modelo complexo\nSegunda Fase \nNúmero de candidatos a qualificar: 5\nNº Mínimo de Candidatos: 5\nIndicador de Nº Máx. de Candidatos: Sim\nNº Máx. de Candidatos: 5\nCritério de seleção: \nFatores - Tipo: Qualificações académicas e profissionais relevantes\nCritérios de Seleção Utilizados: Ainda não conhecido\nFatores - Nome: Outros\nFatores - Outro Nome: Capacidade e experiência das equipas\nFatores - Ponderação: 40%\nFatores - Subfatores? Sim\nSubfatores: \nSubfatores - Nome: Experiência da equipa residente em projetos semelhantes\nSubfatores - Ponderação: 62.5%\nSubfatores - Nome: Experiência da equipa de projeto em projetos semelhantes\nSubfatores - Ponderação: 37.5%\nCritérios de Seleção do Convite para a Segunda Fase? Não\nCritério de seleção: \nFatores - Tipo: Rácio financeiro\nCritérios de Seleção Utilizados: Ainda não conhecido\nFatores - Nome: Outros\nFatores - Outro Nome: Capacidade financeira\nFatores - Ponderação: 30%\nFatores - Subfatores? Não\nCritérios de Seleção do Convite para a Segunda Fase? Não\nCritério de seleção: \nFatores - Tipo: Referências sobre serviços especificados\nCritérios de Seleção Utilizados: Ainda não conhecido\nFatores - Nome: Outros\nFatores - Outro Nome: Experiência do candidato na prestação de serviços em soluções de Bilhética sem contacto equiparáveis à da CP\nFatores - Ponderação: 30%\nFatores - Subfatores? Não\nCritérios de Seleção do Convite para a Segunda Fase? Não\nPrazo durante o qual os concorrentes são obrigados a manter as respetivas propostas: 180 dias a contar do termo do prazo para a apresentação das propostas\nApresentação de Catálogo Eletrónico: Permitido\nIndicação de Subcontratação na Proposta: Inexistência de indicação de subcontratação\n\n14 - PRESTAÇÃO DE CAUÇÃO\nPrestação de caução: Sim\nPercentagem: 5%\nDescrição da Garantia Exigida: O valor da caução é de 5.00% do preço contratual.\n\n15 - FORNECIMENTO DAS PEÇAS DO CONCURSO, APRESENTAÇÃO DE PEDIDOS DE PARTICIPAÇÃO E APRESENTAÇÃO DAS PROPOSTAS\nLink para acesso às peças do concurso (URL): https://www.acingov.pt/acingovprod/2/zonaPublica/zona_publica_c/donwloadProcedurePiece/OTI2Nzk0\n\n20 - OUTROS REQUISITOS\nInformação sobre contratos reservados. Aplica-se a contratos reservados (54º-A)? Não\n\n21 - CRITÉRIO DE ADJUDICAÇÃO\nMultifator: Sim\nFator: \nNome: Preço\nPonderação: 40%\nSubfatores: Não\nFator: \nNome: Outros\nOutro Nome: Metodologia\nPonderação: 20%\nSubfatores: Não\nFator: \nNome: Outros\nOutro Nome: Caracterização das equipas a afetar à prestação de serviços\nPonderação: 40%\nSubfatores: Não\n\n24 - CONDIÇÕES DO CONTRATO\nFaturação Eletrónica: Necessário\nObrigação de Subcontratação:\nCódigo da Obrigação de Subcontratação: Não é aplicável nenhuma obrigação de subcontratação.\n\n25 - COMPRA PÚBLICA ESTRATÉGICA\nCompra Pública Estratégica: Inexistência de contratação pública estratégica\n\n26 - INFORMAÇÕES ADICIONAIS\nContrato adequado para PME: Não\nCobertura ACP (Acordo dos Contratos Públicos da Organização Mundial do Comércio): Não\n\n27 - IDENTIFICAÇÃO E CONTACTOS DO ÓRGÃO DE RECURSOS ADMINISTRATIVOS\nDesignação: Conselho de Administração da CP\nEndereço: Calçada do Duque nº20\nCódigo postal: 1249-109\nLocalidade: Lisboa\nTelefone: 211378399\nFax: 211378399\nEndereço eletrónico: compras@cp.pt\n\n28 - IDENTIFICAÇÃO DO(S) AUTOR(ES) DE ANÚNCIO\nNome: Pedro Miguel Sousa Pereira Guedes Moreira/João António Gomes Claro\nCargo: Presidente do Conselho de Administração/Vogal do CA\n\n29 - ALTERAÇÃO\nMotivo da Alteração: Informações atualizadas\nIdentificador da Versão do Anúncio a Alterar: 8921a551-0c7c-46c3-bebb-f901d671db90-01\nIdentificador das Secções Alteradas do Anúncio Anterior: Condições de Apresentação\nDescrição das Alterações: Prorrogado o prazo de apresentação de candidaturas\nAlteração dos Documentos do Concurso: Não\n419495149",
    "nipc": "500498601",
    "distrito": "Lisboa",
    "concelho": "Lisboa",
    "freguesia": "Todas",
    "site": "www.cp.pt",
    "email": "compras@cp.pt",
    "designacao_contrato": "Aquisição da prestação de serviços de consultoria e assessoria técnica aos Sistemas de Venda da CP, manutenção preventiva, corretiva e evolutiva nos sistemas Bilhética sem Contacto (BSC) e reserva MBBilhete, desenvolvimento de novas soluções e apoio funcional e à utilização, nos termos definidos no presente caderno de encargos- condições particulares e seus anexos",
    "descricao": "Aquisição da prestação de serviços de consultoria e assessoria técnica aos Sistemas de Venda da CP, manutenção preventiva, corretiva e evolutiva nos sistemas Bilhética sem Contacto (BSC) e reserva MBBilhete, desenvolvimento de novas soluções e apoio funcional e à utilização, nos termos definidos no presente caderno de encargos- condições particulares e seus anexos",
    "preco_base": "2.192.976,76 EUR",
    "prazo_execucao": "26 MESES",
    "prazo_apresentacao_propostas": null,
    "fundos_eu": "Não",
    "plataforma_eletronica": "ACIN",
    "url_procedimento": "https://www.acingov.pt",
    "autor_nome": "Pedro Miguel Sousa Pereira Guedes Moreira/João António Gomes Claro",
    "autor_cargo": "Presidente do Conselho de Administração/Vogal do CA"
  },
  {
    "numero_procedimento": "N/A",
    "entidade": "Município do Montijo",
    "link": "https://diariodarepublica.pt/dr/detalhe/contrato-publico/23587-934287215",
    "detalhes_completos": "1 - IDENTIFICAÇÃO E CONTACTOS DA ENTIDADE ADJUDICANTE\nDesignação da entidade adjudicante: Município do Montijo\nNIPC: 502834846\nEndereço: Rua Manuel Neves Nunes de Almeida\nCódigo postal: 2870-352\nLocalidade: Setúbal\nPaís: Portugal\nNUT III: PT170\nDistrito: Setúbal\nConcelho: Montijo\nFreguesia: Todas\nTelefone: 212327600\nFax: 212327600\nEndereço da Entidade (URL): www.mun-montijo.pt\nEndereço Eletrónico: geral@mun-montijo.pt\neDelivery Gateway (URL): https://community.vortal.biz/public/\nFunção da Organização: Adquirente\nNorma jurídica da Entidade Adjudicante: Autoridade local\nÁrea de atividade da Autoridade Adjudicante: Serviços públicos das administrações públicas\n\n2 - JORNAL OFICIAL DA UNIÃO EUROPEIA\nO procedimento a que este anúncio diz respeito também é publicitado no Jornal Oficial da União Europeia? Sim\n\n3 - AVISO\nModelo de Anúncio: Concurso público\nData de Envio do Anúncio: 02-09-2025\n\n5 - PROCESSO\nTipo de Procedimento: Concurso público\nPreço base do procedimento: Sim\nValor do preço base do procedimento: 16.880,00 EUR\nProcedimento com lotes? Não\n\n6 - OBJETO DO CONTRATO\nNúmero de referência interna: 294/2025\nDesignação do contrato: Aquisição de serviços de segurança humana na Divisão de Desenvolvimento Social e Promoção da Saúde.\nDescrição: Aquisição de serviços de segurança humana na Divisão de Desenvolvimento Social e Promoção da Saúde.\nOpções: Não\nTipo de Contrato Principal: Aquisição de Serviços\nTipo de Contrato: Aquisição de Serviços\nClassificação CPV (Vocabulário Comum para os Contratos Públicos)\nObjeto principal\nVocabulário Principal: 79714000\nPreço base s/IVA: 16.880,00 EUR\n\n7 - INDICAÇÕES ADICIONAIS\nO contrato envolve aquisição conjunta (satisfação de várias entidades)? Não\nO contrato é adjudicado por uma central de compras? Não\n\n8 - TÉCNICAS\nO concurso destina-se à celebração de um acordo-quadro? Inexistência de acordo-quadro\nÉ utilizado um leilão eletrónico? Não\nÉ adotada uma fase de negociação? Não\nSistema de Aquisição Dinâmico: Inexistência de sistema de aquisição dinâmico\n\n9 - LOCAL DA EXECUÇÃO DO CONTRATO\nLOCAL DA EXECUÇÃO DO CONTRATO (PROCEDIMENTO)\nPaís: Portugal\nNUT III: PT170\nLocalidade: Montijo\nDistrito: Setúbal\nConcelho: Montijo\nFreguesia: União das Freguesias de Montijo e Afonsoeiro\n\n10 - PRAZO DE EXECUÇÃO DO CONTRATO\nPrazo de execução do contrato: 1 ANOS\nPrevisão de renovações: Não\n\n11 - FUNDOS EU\nTêm fundos EU? Não\n\n12 - DOCUMENTOS DE HABILITAÇÃO\nHabilitação para o exercício da atividade profissional: Não\n\n13 - CONDIÇÕES DE APRESENTAÇÃO\nPlataforma eletrónica utilizada pela entidade adjudicante: VORTAL\nURL para Apresentação: https://community.vortal.biz/public/\nAdmissibilidade da apresentação de propostas variantes: Não autorizado\nPrazo para apresentação das propostas: 02-10-2025 18:00\nPrazo durante o qual os concorrentes são obrigados a manter as respetivas propostas: 120 dias a contar do termo do prazo para a apresentação das propostas\nApresentação de Catálogo Eletrónico: Não autorizado\nIndicação de Subcontratação na Proposta: Inexistência de indicação de subcontratação\n\n14 - PRESTAÇÃO DE CAUÇÃO\nPrestação de caução: Não\n\n15 - FORNECIMENTO DAS PEÇAS DO CONCURSO, APRESENTAÇÃO DE PEDIDOS DE PARTICIPAÇÃO E APRESENTAÇÃO DAS PROPOSTAS\nLink para acesso às peças do concurso (URL): https://community.vortal.biz/Public/public-tender-documents/d3c5STlERlBJcUVkK1phbkVocjVQeVlqbzRMR2dJRG9NeWhVUlBEY05iaDgxSUJHSzdrNTh0YWFyY0dDUFl4Z2RBVVFYU2psV0lXN3lZNEVnUThrT2c9PSQ3S21R\n\n20 - OUTROS REQUISITOS\nInformação sobre contratos reservados. Aplica-se a contratos reservados (54º-A)? Não\n\n21 - CRITÉRIO DE ADJUDICAÇÃO\nMultifator: Não\nMonofator:\nNome: Outros\nOutro nome: Preço\n\n24 - CONDIÇÕES DO CONTRATO\nFaturação Eletrónica: Permitido\nObrigação de Subcontratação:\nCódigo da Obrigação de Subcontratação: Não é aplicável nenhuma obrigação de subcontratação.\n\n25 - COMPRA PÚBLICA ESTRATÉGICA\nCompra Pública Estratégica: Inexistência de contratação pública estratégica\n\n26 - INFORMAÇÕES ADICIONAIS\nContrato adequado para PME: Sim\nCobertura ACP (Acordo dos Contratos Públicos da Organização Mundial do Comércio): Não\n\n27 - IDENTIFICAÇÃO E CONTACTOS DO ÓRGÃO DE RECURSOS ADMINISTRATIVOS\nDesignação: Município do Montijo- Câmara Municipal\nEndereço: Rua Dr.Manuel Neves Nunes de Almeida\nCódigo postal: 2870-352\nLocalidade: Montijo\nTelefone: +351 212327600\nFax: +351 212327600\nEndereço eletrónico: dgfp.contratacaopublica@mun-montijo.pt\n\n28 - IDENTIFICAÇÃO DO(S) AUTOR(ES) DE ANÚNCIO\nNome: Maria Clara Silva\nCargo: Presidente da Câmara Municipal\n419489788",
    "nipc": "502834846",
    "distrito": "Setúbal",
    "concelho": "Montijo",
    "freguesia": "Todas",
    "site": "www.mun-montijo.pt",
    "email": "geral@mun-montijo.pt",
    "designacao_contrato": "Aquisição de serviços de segurança humana na Divisão de Desenvolvimento Social e Promoção da Saúde.",
    "descricao": "Aquisição de serviços de segurança humana na Divisão de Desenvolvimento Social e Promoção da Saúde.",
    "preco_base": "16.880,00 EUR",
    "prazo_execucao": "1 ANOS",
    "prazo_apresentacao_propostas": "02-10-2025 18:00",
    "fundos_eu": "Não",
    "plataforma_eletronica": "VORTAL",
    "url_procedimento": "https://community.vortal.biz/public/",
    "autor_nome": "Maria Clara Silva",
    "autor_cargo": "Presidente da Câmara Municipal"
  },
  {
    "numero_procedimento": "N/A",
    "entidade": "REN - Serviços, S. A.",
    "link": "https://diariodarepublica.pt/dr/detalhe/contrato-publico/23590-934287216",
    "detalhes_completos": "Alteração do Anúncio de procedimento n.º 27109/2024, de 2024-12-13, com o ID 418436479\n\n1 - IDENTIFICAÇÃO E CONTACTOS DA ENTIDADE ADJUDICANTE\nDesignação da entidade adjudicante: REN - Serviços, S. A.\nNIPC: 508195390\nServiço/Órgão/Pessoa de contacto: Direção de Compras da REN\nEndereço: Avenida dos Estados Unidos da América, 55\nCódigo postal: 1749-061\nLocalidade: Lisboa\nPaís: Portugal\nNUT III: PT170\nDistrito: Lisboa\nConcelho: Lisboa\nFreguesia: Freguesia de Alvalade - Lisboa\nTelefone: 210013500\nEndereço da Entidade (URL): https://www.ren.pt\nEndereço Eletrónico: source.qualificacao@ren.pt\nFunção da Organização: Adquirente\nNorma jurídica da Entidade Adjudicante: Entidade com direitos especiais ou exclusivos\nÁrea de atividade da Entidade Adjudicante: Atividades relacionadas com a eletricidade\n\n2 - JORNAL OFICIAL DA UNIÃO EUROPEIA\nO procedimento a que este anúncio diz respeito também é publicitado no Jornal Oficial da União Europeia? Sim\n\n3 - AVISO\nModelo de Anúncio: Instituição de um sistema de qualificação\nData de Envio do Anúncio: 02-09-2025\n\n5 - PROCESSO\nTipo de Procedimento: Concurso limitado por prévia qualificação\nPreço base do procedimento: Não\nProcedimento com lotes? Não\n\n6 - OBJETO DO CONTRATO\nNúmero de referência interna: Não aplicável\nDesignação do contrato: Sistema de Qualificação de Fornecedores do Grupo REN\nDescrição: O sistema de qualificação de fornecedores destina-se a criar e gerir listas de fornecedores qualificados, com vista à seleção de concorrentes ou participantes, respetivamente, em concursos limitados por prévia qualificação ou em procedimentos de negociação, envolvendo as seguintes subcategorias de compra:\n100201 Cabos Nus para Linhas e Subestações MAT\n100204 Cabos Isolados MAT\n100401 Apoios para Linhas Aéreas\n100501 Sistemas de Controlo e Proteção (SCP)\n100502 Sistemas de Comando e Controlo, Infra-estruturas Gás (SCC G)\n100602 Plataformas de Operação de Mercados de Energia Elétrica\n100603 Sistemas de Monitorização de Ativos Primários da Eléctrica\n100604 Atualização de Sistemas de Acesso de Terceiros à Rede (ATR)\n100702 Autotransformadores, Transformadores de Potência MAT, Reactâncias SHUNT e Autotransformadores Desfasadores\n100801 Transformadores de Medição\n100803 Disjuntores\n100804 Seccionadores\n100805 Descarregadores de Sobretensão\n100806 Equipamento Blindado MAT e AT\n101301 Sistemas de Alimentação - Baterias, Retificadores, UPS e Onduladores\n101304 Sistemas Sustentáveis dos Serviços Auxiliares (3SA)\n101401 Serviços de Projeto de Linhas Elétricas\n101406 Serviços de Projeto de Engenharia Civil - Instalações Elétricas MAT\n101502 Empreitada para Construção, Remodelação e Manutenção de Linhas Eléctricas MAT\n101503 Empreitadas para Construção e Remodelação de Edifícios e Infraestruturas\n101504 Instalação Eléctrica Geral (IEG)\n101509 Empreitada para Construção, Remodelação e Manutenção de Linhas Eléctricas MAT- TET\n101512 Empreitada para Construção de Infraestruturas de GN Alta Pressão (AP)\n101702 Manutenção de Servidões e Património (terrenos)\n101703 Estabelecimento de Servidões\n101704 Máquinas para Gestão de Vegetação\n101804 Serviços de Supervisão Integrada QAS\n200106 Serviços de Cartografia e Topografia\n200203 Serviços de Manutenção e Gestão de Edifícios e Infra-estruturas\n200204 Serviços de Limpeza de Instalações\n200206 Serviços de Vigilância e Segurança Física\n200606 Gestão Aplicacional e Implementação de Projetos em SAP\n200607 Gestão Aplicacional e Implementação de Projetos em SharePoint, K2, .NET e Outsystems\n200704 Sistemas de Voz Industrial\n200705 Sistemas SDH/DWDM\n200706 Sistemas de Transmissão IP/MPLS Cisco\n200801 Deslocações e Estadas\n200902 Combustíveis\n201601 Prestação de serviços de Contact Center e Operações de Ciclo Comercial\nOpções: Não\nTipo de Contrato Principal: Empreitada de Obras Públicas\nTipo de Contrato: Empreitada de Obras Públicas; Aquisição de Bens Móveis; Aquisição de Bens Móveis; Aquisição de Serviços\nClassificação CPV (Vocabulário Comum para os Contratos Públicos)\nObjeto principal\nVocabulário Principal: 45000000\nObjeto Complementar\nVocabulário Principal: 09000000\nObjeto Complementar\nVocabulário Principal: 31000000\nObjeto Complementar\nVocabulário Principal: 32000000\nObjeto Complementar\nVocabulário Principal: 44000000\nObjeto Complementar\nVocabulário Principal: 50000000\nObjeto Complementar\nVocabulário Principal: 51000000\nObjeto Complementar\nVocabulário Principal: 63000000\nObjeto Complementar\nVocabulário Principal: 71000000\nObjeto Complementar\nVocabulário Principal: 72000000\nObjeto Complementar\nVocabulário Principal: 77000000\nObjeto Complementar\nVocabulário Principal: 79512000\n\n7 - INDICAÇÕES ADICIONAIS\nO contrato envolve aquisição conjunta (satisfação de várias entidades)? Sim\nA entidade adjudicante atua como compradora no procedimento? Sim\nNIPC: 508195390\nDesignação da entidade adjudicante: REN - Serviços, S. A.\nUnidades Orgânicas: Não aplicável\nPercentagem: 10%\nNIPC: 503264032\nDesignação da entidade adjudicante: REN - Redes Energéticas Nacionais, SGPS, S. A.\nUnidades Orgânicas: Não aplicável\nPercentagem: 5%\nNIPC: 509596479\nDesignação da entidade adjudicante: Enondas, Energia das Ondas, S. A.\nUnidades Orgânicas: Não aplicável\nPercentagem: 15%\nNIPC: 507725441\nDesignação da entidade adjudicante: REN - Armazenagem, S. A.\nUnidades Orgânicas: Não aplicável\nPercentagem: 15%\nNIPC: 504346261\nDesignação da entidade adjudicante: REN Atlântico - Terminal de GNL, S. A.\nUnidades Orgânicas: Não aplicável\nPercentagem: 15%\nNIPC: 507725689\nDesignação da entidade adjudicante: REN - Gasodutos, S. A.\nUnidades Orgânicas: Não aplicável\nPercentagem: 15%\nNIPC: 507866673\nDesignação da entidade adjudicante: REN - Rede Eléctrica Nacional, S. A.\nUnidades Orgânicas: Não aplicável\nPercentagem: 25%\n\n8 - TÉCNICAS\nSistema de Aquisição Dinâmico: Inexistência de sistema de aquisição dinâmico\n\n9 - LOCAL DA EXECUÇÃO DO CONTRATO\nLOCAL DA EXECUÇÃO DO CONTRATO (PROCEDIMENTO)\nPaís: Portugal\nNUT III: PTZZZ\nLocalidade: Portugal Continental\nDistrito: Todos\nConcelho: Todos\nFreguesia: Todas\n\n11 - FUNDOS EU\nTêm fundos EU? Não\n\n13 - CONDIÇÕES DE APRESENTAÇÃO\nPlataforma eletrónica utilizada pela entidade adjudicante: VORTAL\nURL para Apresentação: https://source360.ren.pt/login\nRequisitos mínimos \nRequisitos mínimos de capacidade técnica: Conforme o definido no Anexo 3 do Programa de Qualificação de Fornecedores\nRequisitos mínimos de capacidade financeira: Conforme o definido no Anexo 3 do Programa de Qualificação de Fornecedores\nPrazo para apresentação das propostas: 31-12-2025 23:59\nPrazo durante o qual os concorrentes são obrigados a manter as respetivas propostas: 365 dias a contar do termo do prazo para a apresentação das propostas\nApresentação de Catálogo Eletrónico: Não autorizado\nIndicação de Subcontratação na Proposta: Inexistência de indicação de subcontratação\n\n15 - FORNECIMENTO DAS PEÇAS DO CONCURSO, APRESENTAÇÃO DE PEDIDOS DE PARTICIPAÇÃO E APRESENTAÇÃO DAS PROPOSTAS\nLink para acesso às peças do concurso (URL): https://source360.ren.pt/login\n\n18 -  DURAÇÃO DO SISTEMA DE QUALIFICAÇÃO\nAté: 31-12-2025\nDuração superior a 3 anos? Sim\nNúmero do anúncio inicial0\n\n20 - OUTROS REQUISITOS\nInformação sobre contratos reservados. Aplica-se a contratos reservados (54º-A)? Não\n\n21 - CRITÉRIO DE ADJUDICAÇÃO\nMultifator: Não\nMonofator:\nNome: Outros\nOutro nome: Não aplicável\n\n24 - CONDIÇÕES DO CONTRATO\nFaturação Eletrónica: Permitido\n\n25 - COMPRA PÚBLICA ESTRATÉGICA\nCompra Pública Estratégica: Inexistência de contratação pública estratégica\n\n26 - INFORMAÇÕES ADICIONAIS\nContrato adequado para PME: Sim\nCobertura ACP (Acordo dos Contratos Públicos da Organização Mundial do Comércio): Sim\n\n27 - IDENTIFICAÇÃO E CONTACTOS DO ÓRGÃO DE RECURSOS ADMINISTRATIVOS\nDesignação: REN Serviços, S. A.\nEndereço: Avenida dos Estados Unidos da América, 55\nCódigo postal: 1749-061\nLocalidade: Lisboa\nEndereço eletrónico: source.qualificacao@ren.pt\n\n28 - IDENTIFICAÇÃO DO(S) AUTOR(ES) DE ANÚNCIO\nNome: Rodrigo Camacho Pestana\nCargo: Quadro Técnico\n\n29 - ALTERAÇÃO\nMotivo da Alteração: Correção pelo adquirente\nIdentificador da Versão do Anúncio a Alterar: a5cad285-9eae-4139-90dc-4f7122edf850-01\nIdentificador das Secções Alteradas do Anúncio Anterior: Objeto do contrato\nDescrição das Alterações: Adição da subcategoria 101304 Sistemas Sustentáveis dos Serviços Auxiliares (3SA) ao sistema de qualificação existente.\nAlteração dos Documentos do Concurso: Sim\nData de alteração dos documentos do concurso: 01-09-2025\n418981885",
    "nipc": "508195390",
    "distrito": "Lisboa",
    "concelho": "Lisboa",
    "freguesia": "Freguesia de Alvalade - Lisboa",
    "site": "https://www.ren.pt",
    "email": "source.qualificacao@ren.pt",
    "designacao_contrato": "Sistema de Qualificação de Fornecedores do Grupo REN",
    "descricao": "O sistema de qualificação de fornecedores destina-se a criar e gerir listas de fornecedores qualificados, com vista à seleção de concorrentes ou participantes, respetivamente, em concursos limitados por prévia qualificação ou em procedimentos de negociação, envolvendo as seguintes subcategorias de compra:",
    "preco_base": null,
    "prazo_execucao": null,
    "prazo_apresentacao_propostas": "31-12-2025 23:59",
    "fundos_eu": "Não",
    "plataforma_eletronica": "VORTAL",
    "url_procedimento": "https://source360.ren.pt/login",
    "autor_nome": "Rodrigo Camacho Pestana",
    "autor_cargo": "Quadro Técnico"
  },
  {
    "numero_procedimento": "N/A",
    "entidade": "Município de Monchique",
    "link": "https://diariodarepublica.pt/dr/detalhe/contrato-publico/23591-934287217",
    "detalhes_completos": "1 - IDENTIFICAÇÃO E CONTACTOS DA ENTIDADE ADJUDICANTE\nDesignação da entidade adjudicante: Município de Monchique\nNIPC: 506826961\nServiço/Órgão/Pessoa de contacto: Vice Presidente\nEndereço: Travessa da Portela, nº2\nCódigo postal: 8550-470\nLocalidade: Monchique\nPaís: Portugal\nNUT III: PT150\nDistrito: Faro\nConcelho: Monchique\nFreguesia: Freguesia de Monchique\nTelefone: 282910200\nFax: 282910299\nEndereço da Entidade (URL): https://www.cm-monchique.pt/\nEndereço Eletrónico: geral@cm-monchique.pt\neDelivery Gateway (URL): https://www.acingov.pt\nFunção da Organização: Adquirente\nSubfunção da Organização: Organização cujo orçamento é utilizado para pagar o contrato; Organização que executa o pagamento; Organização que fornece informações adicionais sobre o processo de adjudicação; Organização que fornece mais informações sobre os prazos dos procedimentos de recurso; Organização que fornece acesso fora de linha aos documentos do concurso; Organização responsável pelo tratamento das propostas; Organização que recebe as propostas; Organização que trata os pedidos de participação; Organização que recebe pedidos de participação; Organização que fornece mais informações sobre os procedimentos de recurso; Organização que assina o contrato\nNorma jurídica da Entidade Adjudicante: Organismo de direito público\nÁrea de atividade da Autoridade Adjudicante: Serviços públicos das administrações públicas\n\n2 - JORNAL OFICIAL DA UNIÃO EUROPEIA\nO procedimento a que este anúncio diz respeito também é publicitado no Jornal Oficial da União Europeia? Não\n\n3 - AVISO\nModelo de Anúncio: Concurso público\nData de Envio do Anúncio: 04-09-2025\n\n5 - PROCESSO\nTipo de Procedimento: Concurso público\nPreço base do procedimento: Sim\nValor do preço base do procedimento: 142.400,00 EUR\nProcedimento com lotes? Sim\nNº Máx. de Lotes Autorizado: 3\nNúmero máximo de lotes que podem ser adjudicados a um concorrente: 3\n\n6 - OBJETO DO CONTRATO\nNúmero de referência interna: DDR CPU01/2025\nDesignação do contrato: Prestação de serviços para instalação da faixa de gestão combustível referente ao Condomínio de Aldeia de Alcaria do Peso, Peso e Relva de Trás, no âmbito do Sistema de Gestão Integrada de Fogos Rurais (SGIFR) no Concelho de Monchique.\nDescrição: Prestação de serviços para instalação da faixa de gestão combustível referente ao Condomínio de Aldeia de Alcaria do Peso, Peso e Relva de Trás, no âmbito do Sistema de Gestão Integrada de Fogos Rurais (SGIFR) no Concelho de Monchique\nTipo de Contrato Principal: Aquisição de Serviços\nTipo de Contrato: Aquisição de Serviços\nClassificação CPV (Vocabulário Comum para os Contratos Públicos)\nObjeto principal\nVocabulário Principal: 77210000\nPreço base s/IVA: 142.400,00 EUR\nLotes: \nNº: LOT-0001\nDescrição do Lote: Execução da Faixa Secundária de Gestão de Combustível do Condomínio de aldeia de «Alcaria do Peso»\nPreço base s/IVA: 48.350,00 EUR\nClassificação CPV (Vocabulário Comum para os Contratos Públicos)\nObjeto principal\nVocabulário Principal: 77200000\nNº: LOT-0002\nDescrição do Lote: Execução da Faixa Secundária de Gestão de Combustível do Condomínio de Aldeia de «Peso»\nPreço base s/IVA: 49.150,00 EUR\nClassificação CPV (Vocabulário Comum para os Contratos Públicos)\nObjeto principal\nVocabulário Principal: 77200000\nNº: LOT-0003\nDescrição do Lote: Execução da Faixa Secundária de Gestão de Combustível do Condomínio de Aldeia de «Relva de Trás»\nPreço base s/IVA: 44.900,00 EUR\nClassificação CPV (Vocabulário Comum para os Contratos Públicos)\nObjeto principal\nVocabulário Principal: 77200000\n\n7 - INDICAÇÕES ADICIONAIS\nO contrato envolve aquisição conjunta (satisfação de várias entidades)? Não\nO contrato é adjudicado por uma central de compras? Não\n\n8 - TÉCNICAS\nO concurso destina-se à celebração de um acordo-quadro? Inexistência de acordo-quadro\nÉ utilizado um leilão eletrónico? Não\nÉ adotada uma fase de negociação? Não\nSistema de Aquisição Dinâmico: Inexistência de sistema de aquisição dinâmico\n\n9 - LOCAL DA EXECUÇÃO DO CONTRATO\nLOCAL DA EXECUÇÃO DO CONTRATO (PROCEDIMENTO)\nPaís: Portugal\nNUT III: PT150\nLocalidade: Monchique\nDistrito: Faro\nConcelho: Monchique\nFreguesia: Freguesia de Monchique\nLOCAL DA EXECUÇÃO DO CONTRATO (LOTE)\nIdentificador do Lote: LOT-0001; LOT-0002; LOT-0003\nPaís: Portugal\nNUT III: PT150\nLocalidade: Monchique\nDistrito: Faro\nConcelho: Monchique\nFreguesia: Freguesia de Monchique\n\n10 - PRAZO DE EXECUÇÃO DO CONTRATO\nIdentificador do Lote: LOT-0001; LOT-0002; LOT-0003\nPrazo de execução do contrato: 150 DIAS\nPrevisão de renovações: Não\n\n11 - FUNDOS EU\nIdentificador do Lote: LOT-0001; LOT-0002; LOT-0003\nTêm fundos EU? Sim\n\n12 - DOCUMENTOS DE HABILITAÇÃO\nHabilitação para o exercício da atividade profissional: Não\n\n13 - CONDIÇÕES DE APRESENTAÇÃO\nPlataforma eletrónica utilizada pela entidade adjudicante: ACIN\nURL para Apresentação: https://www.acingov.pt\nAdmissibilidade da apresentação de propostas variantes: Não autorizado\nPrazo para apresentação das propostas: 15-09-2025 23:59\nPrazo durante o qual os concorrentes são obrigados a manter as respetivas propostas: 120 dias a contar do termo do prazo para a apresentação das propostas\nIndicação de Subcontratação na Proposta: Inexistência de indicação de subcontratação\n\n14 - PRESTAÇÃO DE CAUÇÃO\nPrestação de caução: Não\n\n15 - FORNECIMENTO DAS PEÇAS DO CONCURSO, APRESENTAÇÃO DE PEDIDOS DE PARTICIPAÇÃO E APRESENTAÇÃO DAS PROPOSTAS\nLink para acesso às peças do concurso (URL): https://www.acingov.pt/acingovprod/2/zonaPublica/zona_publica_c/donwloadProcedurePiece/OTc1MDc3\n\n20 - OUTROS REQUISITOS\nIdentificador do Lote: LOT-0001; LOT-0002; LOT-0003\nInformação sobre contratos reservados. Aplica-se a contratos reservados (54º-A)? Não\n\n21 - CRITÉRIO DE ADJUDICAÇÃO\nO Critério de adjudicação é diferenciado por lote? Não\nMultifator: Não\nMonofator:\nNome: Preço\n\n24 - CONDIÇÕES DO CONTRATO\nIdentificador do Lote: LOT-0001; LOT-0002; LOT-0003\nFaturação Eletrónica: Permitido\nObrigação de Subcontratação:\nCódigo da Obrigação de Subcontratação: Não é aplicável nenhuma obrigação de subcontratação.\n\n25 - COMPRA PÚBLICA ESTRATÉGICA\nCompra Pública Estratégica: Inexistência de contratação pública estratégica\n\n26 - INFORMAÇÕES ADICIONAIS\nIdentificador do Lote: LOT-0001; LOT-0002; LOT-0003\nContrato adequado para PME: Sim\nCobertura ACP (Acordo dos Contratos Públicos da Organização Mundial do Comércio): Não\n\n27 - IDENTIFICAÇÃO E CONTACTOS DO ÓRGÃO DE RECURSOS ADMINISTRATIVOS\nDesignação: Tribunal Administrativo Fiscal de Loulé\nEndereço: Rua Drª Laura Aires 4\nCódigo postal: 8100-851\nLocalidade: Loulé\nTelefone: 289400390\nFax: 213506010\nEndereço eletrónico: loule.taf@tribunais.org.pt\n\n28 - IDENTIFICAÇÃO DO(S) AUTOR(ES) DE ANÚNCIO\nNome: Humberto Fernandes Sério\nCargo: Vice Presidente\n419499167",
    "nipc": "506826961",
    "distrito": "Faro",
    "concelho": "Monchique",
    "freguesia": "Freguesia de Monchique",
    "site": "https://www.cm-monchique.pt/",
    "email": "geral@cm-monchique.pt",
    "designacao_contrato": "Prestação de serviços para instalação da faixa de gestão combustível referente ao Condomínio de Aldeia de Alcaria do Peso, Peso e Relva de Trás, no âmbito do Sistema de Gestão Integrada de Fogos Rurais (SGIFR) no Concelho de Monchique.",
    "descricao": "Prestação de serviços para instalação da faixa de gestão combustível referente ao Condomínio de Aldeia de Alcaria do Peso, Peso e Relva de Trás, no âmbito do Sistema de Gestão Integrada de Fogos Rurais (SGIFR) no Concelho de Monchique",
    "preco_base": "142.400,00 EUR",
    "prazo_execucao": "150 DIAS",
    "prazo_apresentacao_propostas": "15-09-2025 23:59",
    "fundos_eu": "Sim",
    "plataforma_eletronica": "ACIN",
    "url_procedimento": "https://www.acingov.pt",
    "autor_nome": "Humberto Fernandes Sério",
    "autor_cargo": "Vice Presidente"
  },
  {
    "numero_procedimento": "N/A",
    "entidade": "Município de Oliveira de Frades",
    "link": "https://diariodarepublica.pt/dr/detalhe/contrato-publico/23592-934287218",
    "detalhes_completos": "1 - IDENTIFICAÇÃO E CONTACTOS DA ENTIDADE ADJUDICANTE\nDesignação da entidade adjudicante: Município de Oliveira de Frades\nNIPC: 501306234\nServiço/Órgão/Pessoa de contacto: Unidade Flexível de 2º Grau de Ordenamento, Urbanismo, Obras Municipais, Ambiente e Serviços Urbanos\nEndereço: Largo Dr. Joaquim de Almeida\nCódigo postal: 3680-111\nLocalidade: Oliveira de Frades\nPaís: Portugal\nNUT III: PT16G\nDistrito: Viseu\nConcelho: Oliveira de Frades\nFreguesia: União das Freguesias de Oliveira de Frades, Souto de Lafões e Sejães\nTelefone: 232760300\nFax: 232761727\nEndereço da Entidade (URL): www.cm-ofrades.pt\nEndereço Eletrónico: geral@cm-ofrades.pt\neDelivery Gateway (URL): https://www.acingov.pt\nFunção da Organização: Adquirente\nNorma jurídica da Entidade Adjudicante: Organismo de direito público\nÁrea de atividade da Autoridade Adjudicante: Serviços públicos das administrações públicas\n\n2 - JORNAL OFICIAL DA UNIÃO EUROPEIA\nO procedimento a que este anúncio diz respeito também é publicitado no Jornal Oficial da União Europeia? Não\n\n3 - AVISO\nModelo de Anúncio: Concurso público\nData de Envio do Anúncio: 04-09-2025\n\n5 - PROCESSO\nTipo de Procedimento: Concurso público\nPreço base do procedimento: Sim\nValor do preço base do procedimento: 1.048.620,64 EUR\nProcedimento com lotes? Não\n\n6 - OBJETO DO CONTRATO\nNúmero de referência interna: CP/81/2025\nDesignação do contrato: Reabilitação e Ampliação de Edifício para Habitação Multifamiliar\nDescrição: Reabilitação e Ampliação de Edifício para Habitação Multifamiliar\nTipo de Contrato Principal: Empreitada de Obras Públicas\nTipo de Contrato: Empreitada de Obras Públicas\nClassificação CPV (Vocabulário Comum para os Contratos Públicos)\nObjeto principal\nVocabulário Principal: 45453000\nPreço base s/IVA: 1.048.620,64 EUR\n\n7 - INDICAÇÕES ADICIONAIS\nO contrato envolve aquisição conjunta (satisfação de várias entidades)? Não\nO contrato é adjudicado por uma central de compras? Não\n\n8 - TÉCNICAS\nO concurso destina-se à celebração de um acordo-quadro? Inexistência de acordo-quadro\nÉ utilizado um leilão eletrónico? Não\nÉ adotada uma fase de negociação? Não\nSistema de Aquisição Dinâmico: Inexistência de sistema de aquisição dinâmico\n\n9 - LOCAL DA EXECUÇÃO DO CONTRATO\nLOCAL DA EXECUÇÃO DO CONTRATO (PROCEDIMENTO)\nPaís: Portugal\nNUT III: PT16G\nLocalidade: União das Freguesias de Oliveira de Frades Souto de Lafões e Sejães\nDistrito: Viseu\nConcelho: Oliveira de Frades\nFreguesia: União das Freguesias de Oliveira de Frades, Souto de Lafões e Sejães\n\n10 - PRAZO DE EXECUÇÃO DO CONTRATO\nPrazo de execução do contrato: 12 MESES\nPrevisão de renovações: Não\n\n11 - FUNDOS EU\nTêm fundos EU? Sim\n\n12 - DOCUMENTOS DE HABILITAÇÃO\nHabilitação para o exercício da atividade profissional: Sim\nTipo: Alvará\nDescrição: Artigo 2.º - Requisitos de habilitação dos concorrentes\n1 - São requisitos de habilitação do(s) concorrente(s), sob pena de caducidade da adjudicação, a titularidade de Alvará emitido pelo Instituto dos Mercados Públicos do Imobiliário e da Construção - IMPIC, titulando as autorizações seguintes, sem prejuízo do disposto no artigo 8.º da Lei n.º 41/2015, de 3 de junho, a saber:\na) A 1ª subcategoria da 1ª categoria, em classe que cubra o valor global da proposta e integrar-se na categoria em que o tipo de obra se enquadra, a 4ª, 5ª, 6ª e a 8ª subcategorias da 1ª categoria, a 5ª, 9ª e a 12ª subcategorias da 4ª categoria, a 1ª, 2ª e a 11ª subcategorias da 5ª categoria, em classe correspondente, cada uma, ao valor dos trabalhos especializados que lhe respeitem;\nb) A inexistência de qualquer impedimento, nos termos enunciados no artigo 55.º e 55º-A do CCP - Código dos Contratos Públicos.\n\n13 - CONDIÇÕES DE APRESENTAÇÃO\nPlataforma eletrónica utilizada pela entidade adjudicante: ACIN\nURL para Apresentação: https://www.acingov.pt\nAdmissibilidade da apresentação de propostas variantes: Não autorizado\nPrazo para apresentação das propostas: 25-09-2025 18:30\nPrazo durante o qual os concorrentes são obrigados a manter as respetivas propostas: 180 dias a contar do termo do prazo para a apresentação das propostas\nIndicação de Subcontratação na Proposta: Inexistência de indicação de subcontratação\n\n14 - PRESTAÇÃO DE CAUÇÃO\nPrestação de caução: Sim\nPercentagem: 5%\nDescrição da Garantia Exigida: O valor da caução é de 5.00% do preço contratual.\n\n15 - FORNECIMENTO DAS PEÇAS DO CONCURSO, APRESENTAÇÃO DE PEDIDOS DE PARTICIPAÇÃO E APRESENTAÇÃO DAS PROPOSTAS\nLink para acesso às peças do concurso (URL): https://www.acingov.pt/acingovprod/2/zonaPublica/zona_publica_c/donwloadProcedurePiece/OTcwOTMx\n\n20 - OUTROS REQUISITOS\nInformação sobre contratos reservados. Aplica-se a contratos reservados (54º-A)? Não\n\n21 - CRITÉRIO DE ADJUDICAÇÃO\nMultifator: Não\nMonofator:\nNome: Preço\n\n24 - CONDIÇÕES DO CONTRATO\nFaturação Eletrónica: Permitido\nObrigação de Subcontratação:\nCódigo da Obrigação de Subcontratação: Não é aplicável nenhuma obrigação de subcontratação.\n\n25 - COMPRA PÚBLICA ESTRATÉGICA\nCompra Pública Estratégica: Inexistência de contratação pública estratégica\n\n26 - INFORMAÇÕES ADICIONAIS\nContrato adequado para PME: Sim\nCobertura ACP (Acordo dos Contratos Públicos da Organização Mundial do Comércio): Não\n\n27 - IDENTIFICAÇÃO E CONTACTOS DO ÓRGÃO DE RECURSOS ADMINISTRATIVOS\nDesignação: Câmara Municipal de Oliveira de Frades\nEndereço: Largo Dr. Joaquim de Almeida\nCódigo postal: 3680-111\nLocalidade: Oliveira de Frades\nTelefone: 232760300\nFax: 232761727\nEndereço eletrónico: geral@cm-ofrades.pt\nPrazo de interposição do recurso: 5 dias\n\n28 - IDENTIFICAÇÃO DO(S) AUTOR(ES) DE ANÚNCIO\nNome: João Carlos Ferreira Valério\nCargo: Presidente da Câmara Municipal\n419493212",
    "nipc": "501306234",
    "distrito": "Viseu",
    "concelho": "Oliveira de Frades",
    "freguesia": "União das Freguesias de Oliveira de Frades, Souto de Lafões e Sejães",
    "site": "www.cm-ofrades.pt",
    "email": "geral@cm-ofrades.pt",
    "designacao_contrato": "Reabilitação e Ampliação de Edifício para Habitação Multifamiliar",
    "descricao": "Reabilitação e Ampliação de Edifício para Habitação Multifamiliar",
    "preco_base": "1.048.620,64 EUR",
    "prazo_execucao": "12 MESES",
    "prazo_apresentacao_propostas": "25-09-2025 18:30",
    "fundos_eu": "Sim",
    "plataforma_eletronica": "ACIN",
    "url_procedimento": "https://www.acingov.pt",
    "autor_nome": "João Carlos Ferreira Valério",
    "autor_cargo": "Presidente da Câmara Municipal"
  },
  {
    "numero_procedimento": "N/A",
    "entidade": "AHBV Trofa",
    "link": "https://diariodarepublica.pt/dr/detalhe/contrato-publico/23593-934287219",
    "detalhes_completos": "1 - IDENTIFICAÇÃO E CONTACTOS DA ENTIDADE ADJUDICANTE\nDesignação da entidade adjudicante: AHBV Trofa\nNIPC: 501424229\nEndereço: Rua D. Pedro V\nCódigo postal: 4785-302\nLocalidade: Área Metropolitana do Porto\nPaís: Portugal\nNUT III: PT11A\nDistrito: Porto\nConcelho: Trofa\nFreguesia: União das Freguesias de Bougado (São Martinho e Santiago)\nTelefone: 252400700\nFax: 252400709\nEndereço Eletrónico: direccao@bombeirostrofa.pt\neDelivery Gateway (URL): https://community.vortal.biz/public/\nFunção da Organização: Adquirente\nNorma jurídica da Entidade Adjudicante: Organismo de direito público\nÁrea de atividade da Autoridade Adjudicante: Proteção ambiental\n\n2 - JORNAL OFICIAL DA UNIÃO EUROPEIA\nO procedimento a que este anúncio diz respeito também é publicitado no Jornal Oficial da União Europeia? Não\n\n3 - AVISO\nModelo de Anúncio: Concurso público\nData de Envio do Anúncio: 04-09-2025\n\n5 - PROCESSO\nTipo de Procedimento: Concurso público\nPreço base do procedimento: Sim\nValor do preço base do procedimento: 148.777,21 EUR\nProcedimento com lotes? Não\n\n6 - OBJETO DO CONTRATO\nNúmero de referência interna: CP01_2025\nDesignação do contrato: Aquisição de Equipamentos de Proteção Individual\nDescrição: Aquisição de Equipamentos de Proteção Individual (EPIS)\nTipo de Contrato Principal: Aquisição de Bens Móveis\nTipo de Contrato: Aquisição de Bens Móveis\nClassificação CPV (Vocabulário Comum para os Contratos Públicos)\nObjeto principal\nVocabulário Principal: 35800000\nPreço base s/IVA: 148.777,21 EUR\n\n7 - INDICAÇÕES ADICIONAIS\nO contrato envolve aquisição conjunta (satisfação de várias entidades)? Não\nO contrato é adjudicado por uma central de compras? Não\n\n8 - TÉCNICAS\nO concurso destina-se à celebração de um acordo-quadro? Inexistência de acordo-quadro\nÉ utilizado um leilão eletrónico? Não\nÉ adotada uma fase de negociação? Não\nSistema de Aquisição Dinâmico: Inexistência de sistema de aquisição dinâmico\n\n9 - LOCAL DA EXECUÇÃO DO CONTRATO\nLOCAL DA EXECUÇÃO DO CONTRATO (PROCEDIMENTO)\nPaís: Portugal\nNUT III: PT11A\nLocalidade: Área Metropolitana do Porto\nDistrito: Porto\nConcelho: Trofa\nFreguesia: União das Freguesias de Bougado (São Martinho e Santiago)\n\n10 - PRAZO DE EXECUÇÃO DO CONTRATO\nPrazo de execução do contrato: 12 MESES\nPrevisão de renovações: Não\n\n11 - FUNDOS EU\nTêm fundos EU? Não\n\n12 - DOCUMENTOS DE HABILITAÇÃO\nHabilitação para o exercício da atividade profissional: Não\n\n13 - CONDIÇÕES DE APRESENTAÇÃO\nPlataforma eletrónica utilizada pela entidade adjudicante: VORTAL\nURL para Apresentação: https://community.vortal.biz/public/\nAdmissibilidade da apresentação de propostas variantes: Não autorizado\nPrazo para apresentação das propostas: 19-09-2025 23:59\nPrazo durante o qual os concorrentes são obrigados a manter as respetivas propostas: 66 dias a contar do termo do prazo para a apresentação das propostas\nIndicação de Subcontratação na Proposta: Inexistência de indicação de subcontratação\n\n14 - PRESTAÇÃO DE CAUÇÃO\nPrestação de caução: Não\n\n15 - FORNECIMENTO DAS PEÇAS DO CONCURSO, APRESENTAÇÃO DE PEDIDOS DE PARTICIPAÇÃO E APRESENTAÇÃO DAS PROPOSTAS\nLink para acesso às peças do concurso (URL): https://community.vortal.biz/Public/public-tender-documents/M0lBZmRjdlNWaTRBdVdxTnNFcUFMRUtSUUtPeS9TQiszME1VR25ObkxpM3YrdVFjOXFLcjdKWkhHMDVNdTdRVXNvRXpubUdCaHhjWFp3bnQzVE9YNHc9PWhUa1Yj\n\n20 - OUTROS REQUISITOS\nInformação sobre contratos reservados. Aplica-se a contratos reservados (54º-A)? Não\n\n21 - CRITÉRIO DE ADJUDICAÇÃO\nMultifator: Sim\nFator: \nNome: Outros\nOutro Nome: Qualidade de Conceção\nPonderação: 50%\nSubfatores: Não\nFator: \nNome: Qualidade\nPonderação: 10%\nSubfatores: Não\nFator: \nNome: Qualidade\nPonderação: 10%\nSubfatores: Não\nFator: \nNome: Qualidade\nPonderação: 30%\nSubfatores: Não\n\n24 - CONDIÇÕES DO CONTRATO\nFaturação Eletrónica: Permitido\nObrigação de Subcontratação:\nCódigo da Obrigação de Subcontratação: Não é aplicável nenhuma obrigação de subcontratação.\n\n25 - COMPRA PÚBLICA ESTRATÉGICA\nCompra Pública Estratégica: Inexistência de contratação pública estratégica\n\n26 - INFORMAÇÕES ADICIONAIS\nContrato adequado para PME: Sim\nCobertura ACP (Acordo dos Contratos Públicos da Organização Mundial do Comércio): Não\n\n27 - IDENTIFICAÇÃO E CONTACTOS DO ÓRGÃO DE RECURSOS ADMINISTRATIVOS\nDesignação: Associação Humanitária dos Bombeiros Voluntários da Trofa\nEndereço: Rua D. Pedro V\nCódigo postal: 4785-306\nLocalidade: Trofa\nTelefone: +351 252400700\nFax: +351 252400709\nEndereço eletrónico: direccao@bombeirostrofa.pt\n\n28 - IDENTIFICAÇÃO DO(S) AUTOR(ES) DE ANÚNCIO\nNome: Associação Humanitária dos Bombeiros Voluntários da Trofa\nCargo: Presidente\n419504917",
    "nipc": "501424229",
    "distrito": "Porto",
    "concelho": "Trofa",
    "freguesia": "União das Freguesias de Bougado (São Martinho e Santiago)",
    "site": null,
    "email": "direccao@bombeirostrofa.pt",
    "designacao_contrato": "Aquisição de Equipamentos de Proteção Individual",
    "descricao": "Aquisição de Equipamentos de Proteção Individual (EPIS)",
    "preco_base": "148.777,21 EUR",
    "prazo_execucao": "12 MESES",
    "prazo_apresentacao_propostas": "19-09-2025 23:59",
    "fundos_eu": "Não",
    "plataforma_eletronica": "VORTAL",
    "url_procedimento": "https://community.vortal.biz/public/",
    "autor_nome": "Associação Humanitária dos Bombeiros Voluntários da Trofa",
    "autor_cargo": "Presidente"
  },
  {
    "numero_procedimento": "N/A",
    "entidade": "Escola Básica dos 2º e 3º Ciclos Dr. Horácio Bento de Gouveia",
    "link": "https://diariodarepublica.pt/dr/detalhe/contrato-publico/23596-934287220",
    "detalhes_completos": "1 - IDENTIFICAÇÃO E CONTACTOS DA ENTIDADE ADJUDICANTE\nDesignação da entidade adjudicante: Escola Básica dos 2º e 3º Ciclos Dr. Horácio Bento de Gouveia\nNIPC: 671000225\nServiço/Órgão/Pessoa de contacto: Escola Básica dos 2º e 3º Ciclos Dr. Horácio Bento de Gouveia\nEndereço: Estrada da Liberdade nº 1\nCódigo postal: 9004-524\nLocalidade: Funchal\nPaís: Portugal\nNUT III: PT300\nDistrito: Região Autónoma da Madeira\nConcelho: Funchal\nFreguesia: Freguesia de São Pedro (Funchal)\nTelefone: (+351) 291 740 010\nFax: 351291624347\nEndereço da Entidade (URL): www.hbg.pt\nEndereço Eletrónico: ebdhbgouveia@edu.madeira.gov.pt\neDelivery Gateway (URL): https://www.acingov.pt\nFunção da Organização: Adquirente\nNorma jurídica da Entidade Adjudicante: Organismo de direito público\nÁrea de atividade da Autoridade Adjudicante: Educação\n\n2 - JORNAL OFICIAL DA UNIÃO EUROPEIA\nO procedimento a que este anúncio diz respeito também é publicitado no Jornal Oficial da União Europeia? Não\n\n3 - AVISO\nModelo de Anúncio: Concurso público\nData de Envio do Anúncio: 04-09-2025\n\n5 - PROCESSO\nTipo de Procedimento: Concurso público\nPreço base do procedimento: Sim\nValor do preço base do procedimento: 113.561,30 EUR\nProcedimento com lotes? Não\n\n6 - OBJETO DO CONTRATO\nNúmero de referência interna: CP 03/2025\nDesignação do contrato: Aquisição de serviços de fornecimento de Refeição à Cantina da Escola Básica dos 2º e 3º Ciclos Dr. Horácio Bento de Gouveia\nDescrição: Aquisição de serviços de fornecimento de Refeição à Cantina da Escola Básica dos 2º e 3º Ciclos Dr. Horácio Bento de Gouveia\nTipo de Contrato Principal: Aquisição de Serviços\nTipo de Contrato: Aquisição de Serviços\nClassificação CPV (Vocabulário Comum para os Contratos Públicos)\nObjeto principal\nVocabulário Principal: 55524000\nPreço base s/IVA: 113.561,30 EUR\n\n7 - INDICAÇÕES ADICIONAIS\nO contrato envolve aquisição conjunta (satisfação de várias entidades)? Não\nO contrato é adjudicado por uma central de compras? Não\n\n8 - TÉCNICAS\nO concurso destina-se à celebração de um acordo-quadro? Inexistência de acordo-quadro\nÉ utilizado um leilão eletrónico? Não\nÉ adotada uma fase de negociação? Não\nSistema de Aquisição Dinâmico: Inexistência de sistema de aquisição dinâmico\n\n9 - LOCAL DA EXECUÇÃO DO CONTRATO\nLOCAL DA EXECUÇÃO DO CONTRATO (PROCEDIMENTO)\nPaís: Portugal\nNUT III: PT111\nLocalidade: Freguesia de São Pedro (Funchal)\nDistrito: Região Autónoma da Madeira\nConcelho: Funchal\nFreguesia: Freguesia de São Pedro (Funchal)\n\n10 - PRAZO DE EXECUÇÃO DO CONTRATO\nData de Início: 23-09-2025\nData de Fim: 31-07-2026\nPrevisão de renovações: Não\n\n11 - FUNDOS EU\nTêm fundos EU? Não\n\n12 - DOCUMENTOS DE HABILITAÇÃO\nHabilitação para o exercício da atividade profissional: Não\n\n13 - CONDIÇÕES DE APRESENTAÇÃO\nPlataforma eletrónica utilizada pela entidade adjudicante: ACIN\nURL para Apresentação: https://www.acingov.pt\nAdmissibilidade da apresentação de propostas variantes: Não autorizado\nPrazo para apresentação das propostas: 10-09-2025 23:59\nPrazo durante o qual os concorrentes são obrigados a manter as respetivas propostas: 66 dias a contar do termo do prazo para a apresentação das propostas\nIndicação de Subcontratação na Proposta: Inexistência de indicação de subcontratação\n\n14 - PRESTAÇÃO DE CAUÇÃO\nPrestação de caução: Não\n\n15 - FORNECIMENTO DAS PEÇAS DO CONCURSO, APRESENTAÇÃO DE PEDIDOS DE PARTICIPAÇÃO E APRESENTAÇÃO DAS PROPOSTAS\nLink para acesso às peças do concurso (URL): https://www.acingov.pt/acingovprod/2/zonaPublica/zona_publica_c/donwloadProcedurePiece/OTc1MjYw\n\n20 - OUTROS REQUISITOS\nInformação sobre contratos reservados. Aplica-se a contratos reservados (54º-A)? Não\n\n21 - CRITÉRIO DE ADJUDICAÇÃO\nMultifator: Não\nMonofator:\nNome: Outros\nOutro nome: Fator Preço\n\n24 - CONDIÇÕES DO CONTRATO\nFaturação Eletrónica: Permitido\nObrigação de Subcontratação:\nCódigo da Obrigação de Subcontratação: Não é aplicável nenhuma obrigação de subcontratação.\n\n25 - COMPRA PÚBLICA ESTRATÉGICA\nCompra Pública Estratégica: Inexistência de contratação pública estratégica\n\n26 - INFORMAÇÕES ADICIONAIS\nContrato adequado para PME: Não\nCobertura ACP (Acordo dos Contratos Públicos da Organização Mundial do Comércio): Não\n\n27 - IDENTIFICAÇÃO E CONTACTOS DO ÓRGÃO DE RECURSOS ADMINISTRATIVOS\nDesignação: Secretário Regional\nEndereço: Estrada da Liberdade nº 1\nCódigo postal: 9004-524\nLocalidade: Funchal\nTelefone: 351291740010\nFax: \nEndereço eletrónico: ebdhbgouveia@edu.madeira.gov.pt\n\n28 - IDENTIFICAÇÃO DO(S) AUTOR(ES) DE ANÚNCIO\nNome: Edgar Vieira Jardim\nCargo: Vice Presidente do Conselho Executivo\n419505719",
    "nipc": "671000225",
    "distrito": "Região Autónoma da Madeira",
    "concelho": "Funchal",
    "freguesia": "Freguesia de São Pedro (Funchal)",
    "site": "www.hbg.pt",
    "email": "ebdhbgouveia@edu.madeira.gov.pt",
    "designacao_contrato": "Aquisição de serviços de fornecimento de Refeição à Cantina da Escola Básica dos 2º e 3º Ciclos Dr. Horácio Bento de Gouveia",
    "descricao": "Aquisição de serviços de fornecimento de Refeição à Cantina da Escola Básica dos 2º e 3º Ciclos Dr. Horácio Bento de Gouveia",
    "preco_base": "113.561,30 EUR",
    "prazo_execucao": null,
    "prazo_apresentacao_propostas": "10-09-2025 23:59",
    "fundos_eu": "Não",
    "plataforma_eletronica": "ACIN",
    "url_procedimento": "https://www.acingov.pt",
    "autor_nome": "Edgar Vieira Jardim",
    "autor_cargo": "Vice Presidente do Conselho Executivo"
  },
  {
    "numero_procedimento": "N/A",
    "entidade": "Serviços Municipalizados de Água e Saneamento de Almada",
    "link": "https://diariodarepublica.pt/dr/detalhe/contrato-publico/23597-934287221",
    "detalhes_completos": "1 - IDENTIFICAÇÃO E CONTACTOS DA ENTIDADE ADJUDICANTE\nDesignação da entidade adjudicante: Serviços Municipalizados de Água e Saneamento de Almada\nNIPC: 680017763\nEndereço: Praceta Ricardo Jorge, n.º2 Pragal\nCódigo postal: 2804-543\nLocalidade: Setúbal\nPaís: Portugal\nNUT III: PT170\nDistrito: Setúbal\nConcelho: Almada\nFreguesia: Todas\nTelefone: 212726000\nFax: 212721629\nEndereço da Entidade (URL): www.smasalmada.pt\nEndereço Eletrónico: geral@smasalmada.pt\neDelivery Gateway (URL): https://community.vortal.biz/public/\nFunção da Organização: Adquirente\nNorma jurídica da Entidade Adjudicante: Organismo de direito público, controlado por uma autoridade local\nÁrea de atividade da Autoridade Adjudicante: Serviços públicos das administrações públicas\n\n2 - JORNAL OFICIAL DA UNIÃO EUROPEIA\nO procedimento a que este anúncio diz respeito também é publicitado no Jornal Oficial da União Europeia? Não\n\n3 - AVISO\nModelo de Anúncio: Concurso público\nData de Envio do Anúncio: 04-09-2025\n\n5 - PROCESSO\nTipo de Procedimento: Concurso público\nPreço base do procedimento: Sim\nValor do preço base do procedimento: 275.500,00 EUR\nProcedimento com lotes? Não\n\n6 - OBJETO DO CONTRATO\nNúmero de referência interna: PCP/30/2025/EOP/DO\nDesignação do contrato: PCP/30/2025/EOP/DO -Execução de pequenas intervenções na rede de drenagem -2025\nDescrição: Execução de pequenas intervenções na rede de drenagem -2025\nTipo de Contrato Principal: Empreitada de Obras Públicas\nTipo de Contrato: Empreitada de Obras Públicas\nClassificação CPV (Vocabulário Comum para os Contratos Públicos)\nObjeto principal\nVocabulário Principal: 45231300\nPreço base s/IVA: 275.500,00 EUR\n\n7 - INDICAÇÕES ADICIONAIS\nO contrato envolve aquisição conjunta (satisfação de várias entidades)? Não\nO contrato é adjudicado por uma central de compras? Não\n\n8 - TÉCNICAS\nO concurso destina-se à celebração de um acordo-quadro? Inexistência de acordo-quadro\nÉ utilizado um leilão eletrónico? Não\nÉ adotada uma fase de negociação? Não\nSistema de Aquisição Dinâmico: Inexistência de sistema de aquisição dinâmico\n\n9 - LOCAL DA EXECUÇÃO DO CONTRATO\nLOCAL DA EXECUÇÃO DO CONTRATO (PROCEDIMENTO)\nPaís: Portugal\nNUT III: PT170\nLocalidade: Setúbal\nDistrito: Setúbal\nConcelho: Almada\nFreguesia: Todas\n\n10 - PRAZO DE EXECUÇÃO DO CONTRATO\nPrazo de execução do contrato: 365 DIAS\nPrevisão de renovações: Não\n\n11 - FUNDOS EU\nTêm fundos EU? Não\n\n12 - DOCUMENTOS DE HABILITAÇÃO\nHabilitação para o exercício da atividade profissional: Sim\nTipo: Alvará\nDescrição: Alvará contendo as seguintes habilitações: 1.ª e 6.ª Subcategorias da 2.ª Categoria, e Classe  correspondente ao Valor da Proposta\n\n13 - CONDIÇÕES DE APRESENTAÇÃO\nPlataforma eletrónica utilizada pela entidade adjudicante: VORTAL\nURL para Apresentação: https://community.vortal.biz/public/\nAdmissibilidade da apresentação de propostas variantes: Não autorizado\nPrazo para apresentação das propostas: 14-09-2025 23:59\nPrazo durante o qual os concorrentes são obrigados a manter as respetivas propostas: 66 dias a contar do termo do prazo para a apresentação das propostas\nIndicação de Subcontratação na Proposta: Inexistência de indicação de subcontratação\n\n14 - PRESTAÇÃO DE CAUÇÃO\nPrestação de caução: Sim\nPercentagem: 5%\nDescrição da Garantia Exigida: Prestada nos termos dos anexos V, VI e VII do programa de procedimento\n\n15 - FORNECIMENTO DAS PEÇAS DO CONCURSO, APRESENTAÇÃO DE PEDIDOS DE PARTICIPAÇÃO E APRESENTAÇÃO DAS PROPOSTAS\nLink para acesso às peças do concurso (URL): https://community.vortal.biz/Public/public-tender-documents/Tmt2VjBrQ1daYzkyUS9zdERSN0NBYXdhRGQvUGI0QmJqNTg4MFlhenQxSUorLzJTb29YYm01M1hsc0Fhc1VSMGkydHgrSUFVVHVwalZWODJoUnUwdGc9PV5LNVEp\n\n20 - OUTROS REQUISITOS\nInformação sobre contratos reservados. Aplica-se a contratos reservados (54º-A)? Não\n\n21 - CRITÉRIO DE ADJUDICAÇÃO\nMultifator: Não\nMonofator:\nNome: Outros\nOutro nome: Preço\n\n24 - CONDIÇÕES DO CONTRATO\nFaturação Eletrónica: Permitido\nObrigação de Subcontratação:\nCódigo da Obrigação de Subcontratação: Não é aplicável nenhuma obrigação de subcontratação.\n\n25 - COMPRA PÚBLICA ESTRATÉGICA\nCompra Pública Estratégica: Inexistência de contratação pública estratégica\n\n26 - INFORMAÇÕES ADICIONAIS\nContrato adequado para PME: Sim\nCobertura ACP (Acordo dos Contratos Públicos da Organização Mundial do Comércio): Não\n\n27 - IDENTIFICAÇÃO E CONTACTOS DO ÓRGÃO DE RECURSOS ADMINISTRATIVOS\nDesignação: Município de Almada - Câmara Municipal de Almada, Presidência\nEndereço: Largo Luís de Camões\nCódigo postal: 2800-513\nLocalidade: Almada\nTelefone: +351 212724500\nFax: +351 212744545\nEndereço eletrónico: gab.presidencia@cma.m-almada.pt\n\n28 - IDENTIFICAÇÃO DO(S) AUTOR(ES) DE ANÚNCIO\nNome: José Pedro Ribeiro\nCargo: Presidente do Conselho de Administração dos SMAS Almada\n419504755",
    "nipc": "680017763",
    "distrito": "Setúbal",
    "concelho": "Almada",
    "freguesia": "Todas",
    "site": "www.smasalmada.pt",
    "email": "geral@smasalmada.pt",
    "designacao_contrato": "PCP/30/2025/EOP/DO -Execução de pequenas intervenções na rede de drenagem -2025",
    "descricao": "Execução de pequenas intervenções na rede de drenagem -2025",
    "preco_base": "275.500,00 EUR",
    "prazo_execucao": "365 DIAS",
    "prazo_apresentacao_propostas": "14-09-2025 23:59",
    "fundos_eu": "Não",
    "plataforma_eletronica": "VORTAL",
    "url_procedimento": "https://community.vortal.biz/public/",
    "autor_nome": "José Pedro Ribeiro",
    "autor_cargo": "Presidente do Conselho de Administração dos SMAS Almada"
  },
  {
    "numero_procedimento": "N/A",
    "entidade": "Município de Santo Tirso",
    "link": "https://diariodarepublica.pt/dr/detalhe/contrato-publico/23598-934287222",
    "detalhes_completos": "1 - IDENTIFICAÇÃO E CONTACTOS DA ENTIDADE ADJUDICANTE\nDesignação da entidade adjudicante: Município de Santo Tirso\nNIPC: 501306870\nServiço/Órgão/Pessoa de contacto: Serviço de Compras\nEndereço: Praça 25 de Abril\nCódigo postal: 4780-373\nLocalidade: Área Metropolitana do Porto\nPaís: Portugal\nNUT III: PT11A\nDistrito: Porto\nConcelho: Santo Tirso\nFreguesia: União das Freguesias de Santo Tirso, Couto (Santa Cristina e São Miguel) e Burgães\nTelefone: 252830400\nFax: 252856534\nEndereço da Entidade (URL): www.cm-stirso.pt\nEndereço Eletrónico: santotirso@cm-stirso.pt\neDelivery Gateway (URL): https://community.vortal.biz/public/\nFunção da Organização: Adquirente\nNorma jurídica da Entidade Adjudicante: Autoridade local\nÁrea de atividade da Autoridade Adjudicante: Serviços públicos das administrações públicas\n\n2 - JORNAL OFICIAL DA UNIÃO EUROPEIA\nO procedimento a que este anúncio diz respeito também é publicitado no Jornal Oficial da União Europeia? Não\n\n3 - AVISO\nModelo de Anúncio: Concurso público\nData de Envio do Anúncio: 04-09-2025\n\n5 - PROCESSO\nTipo de Procedimento: Concurso público\nPreço base do procedimento: Sim\nValor do preço base do procedimento: 67.557,00 EUR\nProcedimento com lotes? Não\n\n6 - OBJETO DO CONTRATO\nNúmero de referência interna: 778/CPN/B/2025\nDesignação do contrato: Fornecimento e entrega de equipamentos de 40 lt e 120lt para recolha de Biorresiduos no concelho de Santo Tirso\nDescrição: Fornecimento e entrega de equipamentos de 40 lt e 120lt para recolha de Biorresiduos no concelho de Santo Tirso\nTipo de Contrato Principal: Aquisição de Bens Móveis\nTipo de Contrato: Aquisição de Bens Móveis\nClassificação CPV (Vocabulário Comum para os Contratos Públicos)\nObjeto principal\nVocabulário Principal: 44613800\nPreço base s/IVA: 67.557,00 EUR\n\n7 - INDICAÇÕES ADICIONAIS\nO contrato envolve aquisição conjunta (satisfação de várias entidades)? Não\nO contrato é adjudicado por uma central de compras? Não\n\n8 - TÉCNICAS\nO concurso destina-se à celebração de um acordo-quadro? Inexistência de acordo-quadro\nÉ utilizado um leilão eletrónico? Não\nÉ adotada uma fase de negociação? Não\nSistema de Aquisição Dinâmico: Inexistência de sistema de aquisição dinâmico\n\n9 - LOCAL DA EXECUÇÃO DO CONTRATO\nLOCAL DA EXECUÇÃO DO CONTRATO (PROCEDIMENTO)\nPaís: Portugal\nNUT III: PT11A\nLocalidade: Área Metropolitana do Porto\nDistrito: Porto\nConcelho: Santo Tirso\nFreguesia: União das Freguesias de Santo Tirso, Couto (Santa Cristina e São Miguel) e Burgães\n\n10 - PRAZO DE EXECUÇÃO DO CONTRATO\nPrazo de execução do contrato: 30 DIAS\nPrevisão de renovações: Não\n\n11 - FUNDOS EU\nTêm fundos EU? Sim\n\n12 - DOCUMENTOS DE HABILITAÇÃO\nHabilitação para o exercício da atividade profissional: Não\n\n13 - CONDIÇÕES DE APRESENTAÇÃO\nPlataforma eletrónica utilizada pela entidade adjudicante: VORTAL\nURL para Apresentação: https://community.vortal.biz/public/\nAdmissibilidade da apresentação de propostas variantes: Não autorizado\nPrazo para apresentação das propostas: 16-09-2025 17:30\nPrazo durante o qual os concorrentes são obrigados a manter as respetivas propostas: 66 dias a contar do termo do prazo para a apresentação das propostas\nIndicação de Subcontratação na Proposta: Inexistência de indicação de subcontratação\n\n14 - PRESTAÇÃO DE CAUÇÃO\nPrestação de caução: Não\n\n15 - FORNECIMENTO DAS PEÇAS DO CONCURSO, APRESENTAÇÃO DE PEDIDOS DE PARTICIPAÇÃO E APRESENTAÇÃO DAS PROPOSTAS\nLink para acesso às peças do concurso (URL): https://community.vortal.biz/Public/public-tender-documents/Y2d5ZWloTmxveEtGMzVhTFFSczI1azcxem1hQlNwUUwwR2dGR1hnVGhJQUFGUG1nN2UzNTVwU2J2ZnJmWitqb2JLTmtScEtUY3dudmFlMzkzcEJyeVE9PU5DNVQp\n\n20 - OUTROS REQUISITOS\nInformação sobre contratos reservados. Aplica-se a contratos reservados (54º-A)? Não\n\n21 - CRITÉRIO DE ADJUDICAÇÃO\nMultifator: Não\nMonofator:\nNome: Preço\n\n24 - CONDIÇÕES DO CONTRATO\nFaturação Eletrónica: Permitido\nObrigação de Subcontratação:\nCódigo da Obrigação de Subcontratação: Não é aplicável nenhuma obrigação de subcontratação.\n\n25 - COMPRA PÚBLICA ESTRATÉGICA\nCompra Pública Estratégica: Inexistência de contratação pública estratégica\n\n26 - INFORMAÇÕES ADICIONAIS\nContrato adequado para PME: Sim\nCobertura ACP (Acordo dos Contratos Públicos da Organização Mundial do Comércio): Não\n\n27 - IDENTIFICAÇÃO E CONTACTOS DO ÓRGÃO DE RECURSOS ADMINISTRATIVOS\nDesignação: Câmara Municipal de Santo Tirso\nEndereço: Praça 25 de abril\nCódigo postal: 4780-373\nLocalidade: Santo Tirso\nTelefone: +351 252830400\nFax: +351 252830400\nEndereço eletrónico: santotirso@cm-stirso.pt\n\n28 - IDENTIFICAÇÃO DO(S) AUTOR(ES) DE ANÚNCIO\nNome: Alberto Manuel Martins da Costa\nCargo: Presidente da Câmara Municipal de Santo Tirso\n419504041",
    "nipc": "501306870",
    "distrito": "Porto",
    "concelho": "Santo Tirso",
    "freguesia": "União das Freguesias de Santo Tirso, Couto (Santa Cristina e São Miguel) e Burgães",
    "site": "www.cm-stirso.pt",
    "email": "santotirso@cm-stirso.pt",
    "designacao_contrato": "Fornecimento e entrega de equipamentos de 40 lt e 120lt para recolha de Biorresiduos no concelho de Santo Tirso",
    "descricao": "Fornecimento e entrega de equipamentos de 40 lt e 120lt para recolha de Biorresiduos no concelho de Santo Tirso",
    "preco_base": "67.557,00 EUR",
    "prazo_execucao": "30 DIAS",
    "prazo_apresentacao_propostas": "16-09-2025 17:30",
    "fundos_eu": "Sim",
    "plataforma_eletronica": "VORTAL",
    "url_procedimento": "https://community.vortal.biz/public/",
    "autor_nome": "Alberto Manuel Martins da Costa",
    "autor_cargo": "Presidente da Câmara Municipal de Santo Tirso"
  },
  {
    "numero_procedimento": "N/A",
    "entidade": "Serviços Municipalizados de Água e Saneamento de Almada",
    "link": "https://diariodarepublica.pt/dr/detalhe/contrato-publico/23599-934287223",
    "detalhes_completos": "1 - IDENTIFICAÇÃO E CONTACTOS DA ENTIDADE ADJUDICANTE\nDesignação da entidade adjudicante: Serviços Municipalizados de Água e Saneamento de Almada\nNIPC: 680017763\nEndereço: Praceta Ricardo Jorge, n.º2 Pragal\nCódigo postal: 2804-543\nLocalidade: Setúbal\nPaís: Portugal\nNUT III: PT170\nDistrito: Setúbal\nConcelho: Almada\nFreguesia: Todas\nTelefone: 212726000\nFax: 212721629\nEndereço da Entidade (URL): www.smasalmada.pt\nEndereço Eletrónico: geral@smasalmada.pt\neDelivery Gateway (URL): https://community.vortal.biz/public/\nFunção da Organização: Adquirente\nNorma jurídica da Entidade Adjudicante: Organismo de direito público, controlado por uma autoridade local\nÁrea de atividade da Autoridade Adjudicante: Serviços públicos das administrações públicas\n\n2 - JORNAL OFICIAL DA UNIÃO EUROPEIA\nO procedimento a que este anúncio diz respeito também é publicitado no Jornal Oficial da União Europeia? Não\n\n3 - AVISO\nModelo de Anúncio: Concurso público\nData de Envio do Anúncio: 04-09-2025\n\n5 - PROCESSO\nTipo de Procedimento: Concurso público\nPreço base do procedimento: Sim\nValor do preço base do procedimento: 320.000,00 EUR\nProcedimento com lotes? Não\n\n6 - OBJETO DO CONTRATO\nNúmero de referência interna: PCP/27/2025/EOP/DO\nDesignação do contrato: Procedimento Nº PCP/27/2025/EOP/DO - \"Execução de Condutas de Água e VRP na Fomega, Pragal e Porto Brandão\"\nDescrição: Execução de Condutas de Água e VRP na Fomega, Pragal e Porto Brandão\nTipo de Contrato Principal: Empreitada de Obras Públicas\nTipo de Contrato: Empreitada de Obras Públicas\nClassificação CPV (Vocabulário Comum para os Contratos Públicos)\nObjeto principal\nVocabulário Principal: 45232151\nPreço base s/IVA: 320.000,00 EUR\n\n7 - INDICAÇÕES ADICIONAIS\nO contrato envolve aquisição conjunta (satisfação de várias entidades)? Não\nO contrato é adjudicado por uma central de compras? Não\n\n8 - TÉCNICAS\nO concurso destina-se à celebração de um acordo-quadro? Inexistência de acordo-quadro\nÉ utilizado um leilão eletrónico? Não\nÉ adotada uma fase de negociação? Não\nSistema de Aquisição Dinâmico: Inexistência de sistema de aquisição dinâmico\n\n9 - LOCAL DA EXECUÇÃO DO CONTRATO\nLOCAL DA EXECUÇÃO DO CONTRATO (PROCEDIMENTO)\nPaís: Portugal\nNUT III: PT170\nLocalidade: Setúbal\nDistrito: Setúbal\nConcelho: Almada\nFreguesia: Todas\n\n10 - PRAZO DE EXECUÇÃO DO CONTRATO\nPrazo de execução do contrato: 180 DIAS\nPrevisão de renovações: Não\n\n11 - FUNDOS EU\nTêm fundos EU? Não\n\n12 - DOCUMENTOS DE HABILITAÇÃO\nHabilitação para o exercício da atividade profissional: Sim\nTipo: Alvará\nDescrição: Alvará contendo as seguintes habilitações: 6.ª Subcategoria da 2.ª Categoria, e Classe correspondente ao Valor da Proposta\n\n13 - CONDIÇÕES DE APRESENTAÇÃO\nPlataforma eletrónica utilizada pela entidade adjudicante: VORTAL\nURL para Apresentação: https://community.vortal.biz/public/\nAdmissibilidade da apresentação de propostas variantes: Não autorizado\nPrazo para apresentação das propostas: 14-09-2025 23:59\nPrazo durante o qual os concorrentes são obrigados a manter as respetivas propostas: 66 dias a contar do termo do prazo para a apresentação das propostas\nIndicação de Subcontratação na Proposta: Inexistência de indicação de subcontratação\n\n14 - PRESTAÇÃO DE CAUÇÃO\nPrestação de caução: Sim\nPercentagem: 5%\nDescrição da Garantia Exigida: Prestada nos termos dos anexos V, VI e VII do programa de procedimento\n\n15 - FORNECIMENTO DAS PEÇAS DO CONCURSO, APRESENTAÇÃO DE PEDIDOS DE PARTICIPAÇÃO E APRESENTAÇÃO DAS PROPOSTAS\nLink para acesso às peças do concurso (URL): https://community.vortal.biz/Public/public-tender-documents/MDgxYzArMjBxb2Nvdzd4UzRjNlJlbUVDSTJ4RnBwSXhvTnFHdlh3bVhUSTZIR2oyV0JYUjQ1TU11R0dRVDFmT2h6aFFWR2tOVEh6NWRQcnBVK3NveVE9PUo5ekxK\n\n20 - OUTROS REQUISITOS\nInformação sobre contratos reservados. Aplica-se a contratos reservados (54º-A)? Não\n\n21 - CRITÉRIO DE ADJUDICAÇÃO\nMultifator: Sim\nFator: \nNome: Preço\nPonderação: 60%\nSubfatores: Não\nFator: \nNome: Qualidade\nPonderação: 40%\nSubfatores: Não\n\n24 - CONDIÇÕES DO CONTRATO\nFaturação Eletrónica: Permitido\nObrigação de Subcontratação:\nCódigo da Obrigação de Subcontratação: Não é aplicável nenhuma obrigação de subcontratação.\n\n25 - COMPRA PÚBLICA ESTRATÉGICA\nCompra Pública Estratégica: Inexistência de contratação pública estratégica\n\n26 - INFORMAÇÕES ADICIONAIS\nContrato adequado para PME: Sim\nCobertura ACP (Acordo dos Contratos Públicos da Organização Mundial do Comércio): Não\n\n27 - IDENTIFICAÇÃO E CONTACTOS DO ÓRGÃO DE RECURSOS ADMINISTRATIVOS\nDesignação: Município de Almada - Câmara Municipal de Almada, Presidência\nEndereço: Largo Luís de Camões\nCódigo postal: 2800-513\nLocalidade: Almada\nTelefone: +351 212724500\nFax: +351 212744545\nEndereço eletrónico: gab.presidencia@cma.m-almada.pt\n\n28 - IDENTIFICAÇÃO DO(S) AUTOR(ES) DE ANÚNCIO\nNome: José Pedro Ribeiro\nCargo: Presidente do Conselho de Administração dos SMAS Almada\n419503045",
    "nipc": "680017763",
    "distrito": "Setúbal",
    "concelho": "Almada",
    "freguesia": "Todas",
    "site": "www.smasalmada.pt",
    "email": "geral@smasalmada.pt",
    "designacao_contrato": "Procedimento Nº PCP/27/2025/EOP/DO - \"Execução de Condutas de Água e VRP na Fomega, Pragal e Porto Brandão\"",
    "descricao": "Execução de Condutas de Água e VRP na Fomega, Pragal e Porto Brandão",
    "preco_base": "320.000,00 EUR",
    "prazo_execucao": "180 DIAS",
    "prazo_apresentacao_propostas": "14-09-2025 23:59",
    "fundos_eu": "Não",
    "plataforma_eletronica": "VORTAL",
    "url_procedimento": "https://community.vortal.biz/public/",
    "autor_nome": "José Pedro Ribeiro",
    "autor_cargo": "Presidente do Conselho de Administração dos SMAS Almada"
  },
  {
    "numero_procedimento": "N/A",
    "entidade": "Serviços Municipalizados de Água e Saneamento de Almada",
    "link": "https://diariodarepublica.pt/dr/detalhe/contrato-publico/23600-934287224",
    "detalhes_completos": "1 - IDENTIFICAÇÃO E CONTACTOS DA ENTIDADE ADJUDICANTE\nDesignação da entidade adjudicante: Serviços Municipalizados de Água e Saneamento de Almada\nNIPC: 680017763\nServiço/Órgão/Pessoa de contacto: Gabinete de Compras\nEndereço: Praceta Ricardo Jorge, n.º2 Pragal\nCódigo postal: 2804-543\nLocalidade: Setúbal\nPaís: Portugal\nNUT III: PT170\nDistrito: Setúbal\nConcelho: Almada\nFreguesia: Todas\nTelefone: 212726000\nFax: 212721629\nEndereço da Entidade (URL): www.smasalmada.pt\nEndereço Eletrónico: geral@smasalmada.pt\neDelivery Gateway (URL): https://community.vortal.biz/public/\nFunção da Organização: Adquirente\nNorma jurídica da Entidade Adjudicante: Organismo de direito público, controlado por uma autoridade local\nÁrea de atividade da Autoridade Adjudicante: Serviços públicos das administrações públicas\n\n2 - JORNAL OFICIAL DA UNIÃO EUROPEIA\nO procedimento a que este anúncio diz respeito também é publicitado no Jornal Oficial da União Europeia? Não\n\n3 - AVISO\nModelo de Anúncio: Concurso público\nData de Envio do Anúncio: 04-09-2025\n\n5 - PROCESSO\nTipo de Procedimento: Concurso público\nPreço base do procedimento: Sim\nValor do preço base do procedimento: 128.207,52 EUR\nProcedimento com lotes? Não\n\n6 - OBJETO DO CONTRATO\nNúmero de referência interna: CP 70/2025\nDesignação do contrato: Serviços de Manutenção de Espaços Verdes das ETAR's dos SMAS de Almada\nDescrição: Serviços de Manutenção de Espaços Verdes das ETAR's dos SMAS de Almada\nTipo de Contrato Principal: Aquisição de Serviços\nTipo de Contrato: Aquisição de Serviços\nClassificação CPV (Vocabulário Comum para os Contratos Públicos)\nObjeto principal\nVocabulário Principal: 77310000\nPreço base s/IVA: 128.207,52 EUR\n\n7 - INDICAÇÕES ADICIONAIS\nO contrato envolve aquisição conjunta (satisfação de várias entidades)? Não\nO contrato é adjudicado por uma central de compras? Não\n\n8 - TÉCNICAS\nO concurso destina-se à celebração de um acordo-quadro? Inexistência de acordo-quadro\nÉ utilizado um leilão eletrónico? Não\nÉ adotada uma fase de negociação? Não\nSistema de Aquisição Dinâmico: Inexistência de sistema de aquisição dinâmico\n\n9 - LOCAL DA EXECUÇÃO DO CONTRATO\nLOCAL DA EXECUÇÃO DO CONTRATO (PROCEDIMENTO)\nPaís: Portugal\nNUT III: PT170\nLocalidade: Setúbal\nDistrito: Setúbal\nConcelho: Almada\nFreguesia: União das Freguesias de Almada, Cova da Piedade, Pragal e Cacilhas\n\n10 - PRAZO DE EXECUÇÃO DO CONTRATO\nPrazo de execução do contrato: 3 ANOS\nPrevisão de renovações: Não\n\n11 - FUNDOS EU\nTêm fundos EU? Não\n\n12 - DOCUMENTOS DE HABILITAÇÃO\nHabilitação para o exercício da atividade profissional: Não\n\n13 - CONDIÇÕES DE APRESENTAÇÃO\nPlataforma eletrónica utilizada pela entidade adjudicante: VORTAL\nURL para Apresentação: https://community.vortal.biz/public/\nAdmissibilidade da apresentação de propostas variantes: Não autorizado\nPrazo para apresentação das propostas: 18-09-2025 23:59\nPrazo durante o qual os concorrentes são obrigados a manter as respetivas propostas: 180 dias a contar do termo do prazo para a apresentação das propostas\nIndicação de Subcontratação na Proposta: Inexistência de indicação de subcontratação\n\n14 - PRESTAÇÃO DE CAUÇÃO\nPrestação de caução: Não\n\n15 - FORNECIMENTO DAS PEÇAS DO CONCURSO, APRESENTAÇÃO DE PEDIDOS DE PARTICIPAÇÃO E APRESENTAÇÃO DAS PROPOSTAS\nLink para acesso às peças do concurso (URL): https://community.vortal.biz/Public/public-tender-documents/Mk1uVGtyTXF0SjZxb21LTENZZFAwa290L0x6OFlZdVpOYXBxUGtaQjJEb0pOOUJBY3o1aCtCMHozRVhyM3RROTI0RzI0MnIyclYyaU1UaHMrMjFmSFE9PW4yMkJ2\n\n20 - OUTROS REQUISITOS\nInformação sobre contratos reservados. Aplica-se a contratos reservados (54º-A)? Não\n\n21 - CRITÉRIO DE ADJUDICAÇÃO\nMultifator: Não\nMonofator:\nNome: Preço\n\n24 - CONDIÇÕES DO CONTRATO\nFaturação Eletrónica: Permitido\nObrigação de Subcontratação:\nCódigo da Obrigação de Subcontratação: Não é aplicável nenhuma obrigação de subcontratação.\n\n25 - COMPRA PÚBLICA ESTRATÉGICA\nCompra Pública Estratégica: Inexistência de contratação pública estratégica\n\n26 - INFORMAÇÕES ADICIONAIS\nContrato adequado para PME: Sim\nCobertura ACP (Acordo dos Contratos Públicos da Organização Mundial do Comércio): Não\n\n27 - IDENTIFICAÇÃO E CONTACTOS DO ÓRGÃO DE RECURSOS ADMINISTRATIVOS\nDesignação: Câmara Municipal de Almada\nEndereço: Câmara Municipal de Almada - Largo Luís de Camões\nCódigo postal: 2800-158\nLocalidade: Almada\nTelefone: +351 212724534\nFax: +351 212724555\nEndereço eletrónico: gab.presidencia@cma.m-almada.pt\nPrazo de interposição do recurso: 30 dias\n\n28 - IDENTIFICAÇÃO DO(S) AUTOR(ES) DE ANÚNCIO\nNome: José Pedro Ribeiro\nCargo: Presidente do Conselho de Administração\n419504496",
    "nipc": "680017763",
    "distrito": "Setúbal",
    "concelho": "Almada",
    "freguesia": "Todas",
    "site": "www.smasalmada.pt",
    "email": "geral@smasalmada.pt",
    "designacao_contrato": "Serviços de Manutenção de Espaços Verdes das ETAR's dos SMAS de Almada",
    "descricao": "Serviços de Manutenção de Espaços Verdes das ETAR's dos SMAS de Almada",
    "preco_base": "128.207,52 EUR",
    "prazo_execucao": "3 ANOS",
    "prazo_apresentacao_propostas": "18-09-2025 23:59",
    "fundos_eu": "Não",
    "plataforma_eletronica": "VORTAL",
    "url_procedimento": "https://community.vortal.biz/public/",
    "autor_nome": "José Pedro Ribeiro",
    "autor_cargo": "Presidente do Conselho de Administração"
  },
  {
    "numero_procedimento": "N/A",
    "entidade": "Instituto Vaz Serra, Sociedade de Ensino, Cultura e Recreio, S.A.",
    "link": "https://diariodarepublica.pt/dr/detalhe/contrato-publico/23601-934287225",
    "detalhes_completos": "1 - IDENTIFICAÇÃO E CONTACTOS DA ENTIDADE ADJUDICANTE\nDesignação da entidade adjudicante: Instituto Vaz Serra, Sociedade de Ensino, Cultura e Recreio, S.A.\nNIPC: 501536965\nEndereço: Rua Libânio Vaz Serra\nCódigo postal: 6100-268\nLocalidade: Cernache do Bonjardim\nPaís: Portugal\nNUT III: PT16H\nDistrito: Castelo Branco\nConcelho: Sertã\nFreguesia: União das Freguesias de Cernache do Bonjardim, Nesperal e Palhais\nTelefone: 274800060\nFax: 000000000\nEndereço da Entidade (URL): www.ivs.pt\nEndereço Eletrónico: geral@ivs.pt\nFunção da Organização: Adquirente\nNorma jurídica da Entidade Adjudicante: Entidade com direitos especiais ou exclusivos\nÁrea de atividade da Autoridade Adjudicante: Educação\n\n2 - JORNAL OFICIAL DA UNIÃO EUROPEIA\nO procedimento a que este anúncio diz respeito também é publicitado no Jornal Oficial da União Europeia? Sim\n\n3 - AVISO\nModelo de Anúncio: Concurso público\nData de Envio do Anúncio: 02-09-2025\n\n5 - PROCESSO\nTipo de Procedimento: Concurso público\nPreço base do procedimento: Sim\nValor do preço base do procedimento: 894.397,71 EUR\nProcedimento com lotes? Sim\nNº Máx. de Lotes Autorizado: 2\nNúmero máximo de lotes que podem ser adjudicados a um concorrente: 2\n\n6 - OBJETO DO CONTRATO\nNúmero de referência interna: IVS_CTE_CPi03/2526\nDesignação do contrato: Aquisição e instalação de equipamento didático e de equipamento informático, para a escola Instituto Vaz Serra, propriedade da sociedade Instituto Vaz Serra, Sociedade de Ensino, Cultura e Recreio, S.A., Projeto nº 11014-CTE Informática.\nDescrição: Aquisição e instalação de equipamento didático e de equipamento informático, para a escola Instituto Vaz Serra, propriedade da sociedade Instituto Vaz Serra, Sociedade de Ensino, Cultura e Recreio, S.A., Projeto nº 11014-CTE Informática.\nOpções: Não\nTipo de Contrato Principal: Aquisição de Bens Móveis\nTipo de Contrato: Aquisição de Bens Móveis\nClassificação CPV (Vocabulário Comum para os Contratos Públicos)\nObjeto principal\nVocabulário Principal: 39162000\nPreço base s/IVA: 729.974,67 EUR\nObjeto Complementar\nVocabulário Principal: 39160000\nPreço base s/IVA: 164.423,04 EUR\nLotes: \nNº: LOT-0001\nDescrição do Lote: Lote 1 - Equipamento Didático\nPreço base s/IVA: 729.974,67 EUR\nClassificação CPV (Vocabulário Comum para os Contratos Públicos)\nObjeto principal\nVocabulário Principal: 39162000\nNº: LOT-0002\nDescrição do Lote: Lote 2 - Mobiliário\nPreço base s/IVA: 164.423,04 EUR\nClassificação CPV (Vocabulário Comum para os Contratos Públicos)\nObjeto principal\nVocabulário Principal: 39160000\n\n7 - INDICAÇÕES ADICIONAIS\nO contrato envolve aquisição conjunta (satisfação de várias entidades)? Não\nO contrato é adjudicado por uma central de compras? Não\n\n8 - TÉCNICAS\nO concurso destina-se à celebração de um acordo-quadro? Inexistência de acordo-quadro\nÉ utilizado um leilão eletrónico? Não\nÉ adotada uma fase de negociação? Não\nSistema de Aquisição Dinâmico: Inexistência de sistema de aquisição dinâmico\n\n9 - LOCAL DA EXECUÇÃO DO CONTRATO\nLOCAL DA EXECUÇÃO DO CONTRATO (PROCEDIMENTO)\nLOCAL DA EXECUÇÃO DO CONTRATO (LOTE)\nIdentificador do Lote: LOT-0001\nPaís: Portugal\nNUT III: PT16H\nLocalidade: Cernache do Bonjardim\nDistrito: Castelo Branco\nConcelho: Sertã\nFreguesia: União das Freguesias de Cernache do Bonjardim, Nesperal e Palhais\nIdentificador do Lote: LOT-0002\nPaís: Portugal\nNUT III: PT16H\nLocalidade: Cernache do Bonjardim\nDistrito: Castelo Branco\nConcelho: Sertã\nFreguesia: União das Freguesias de Cernache do Bonjardim, Nesperal e Palhais\n\n10 - PRAZO DE EXECUÇÃO DO CONTRATO\nIdentificador do Lote: LOT-0001\nPrazo de execução do contrato: 90 DIAS\nPrevisão de renovações: Não\nIdentificador do Lote: LOT-0002\nPrazo de execução do contrato: 90 DIAS\nPrevisão de renovações: Não\n\n11 - FUNDOS EU\nIdentificador do Lote: LOT-0001; LOT-0002\nTêm fundos EU? Sim\n\n12 - DOCUMENTOS DE HABILITAÇÃO\nHabilitação para o exercício da atividade profissional: Não\n\n13 - CONDIÇÕES DE APRESENTAÇÃO\nPlataforma eletrónica utilizada pela entidade adjudicante: ANOGOV\nURL para Apresentação: https://www.anogov.com/me-ivs/faces/\nAdmissibilidade da apresentação de propostas variantes: Não autorizado\nPrazo para apresentação das propostas: 02-10-2025 23:59\nPrazo durante o qual os concorrentes são obrigados a manter as respetivas propostas: 66 dias a contar do termo do prazo para a apresentação das propostas\nApresentação de Catálogo Eletrónico: Necessário\nIndicação de Subcontratação na Proposta: A parte do contrato que o proponente tenciona subcontratar\n\n14 - PRESTAÇÃO DE CAUÇÃO\nPrestação de caução: Sim\nPercentagem: 3%\nDescrição da Garantia Exigida: Depósito em dinheiro ou em títulos emitidos ou garantidos pelo Estado ou mediante garantia bancária, ou ainda por seguro-caução.\n\n15 - FORNECIMENTO DAS PEÇAS DO CONCURSO, APRESENTAÇÃO DE PEDIDOS DE PARTICIPAÇÃO E APRESENTAÇÃO DAS PROPOSTAS\nLink para acesso às peças do concurso (URL): https://www.anogov.com/me-ivs/faces/app/acessoDocs.jsp?codigoAcesso=UtRwlhi6IwLqAB81CUSc7C8l2mB7qBPIyDUtrSVlWUS26tYZeS\n\n20 - OUTROS REQUISITOS\nIdentificador do Lote: LOT-0001; LOT-0002\nInformação sobre contratos reservados. Aplica-se a contratos reservados (54º-A)? Não\n\n21 - CRITÉRIO DE ADJUDICAÇÃO\nO Critério de adjudicação é diferenciado por lote? Não\nMultifator: Não\nMonofator:\nNome: Preço\n\n24 - CONDIÇÕES DO CONTRATO\nIdentificador do Lote: LOT-0001; LOT-0002\nFaturação Eletrónica: Necessário\nObrigação de Subcontratação:\nCódigo da Obrigação de Subcontratação: Não é aplicável nenhuma obrigação de subcontratação.\n\n25 - COMPRA PÚBLICA ESTRATÉGICA\nCompra Pública Estratégica: Inexistência de contratação pública estratégica\n\n26 - INFORMAÇÕES ADICIONAIS\nIdentificador do Lote: LOT-0001\nContrato adequado para PME: Sim\nCobertura ACP (Acordo dos Contratos Públicos da Organização Mundial do Comércio): Não\nIdentificador do Lote: LOT-0002\nContrato adequado para PME: Sim\nCobertura ACP (Acordo dos Contratos Públicos da Organização Mundial do Comércio): Não\n\n27 - IDENTIFICAÇÃO E CONTACTOS DO ÓRGÃO DE RECURSOS ADMINISTRATIVOS\nDesignação: Instituto Vaz Serra, Sociedade de Ensino, Cultura e Recreio, S.A.\nEndereço: Rua Libânio Vaz Serra\nCódigo postal: 6100-268\nLocalidade: Cernache do Bonjardim\nEndereço eletrónico: contratacao@ivs.pt\n\n28 - IDENTIFICAÇÃO DO(S) AUTOR(ES) DE ANÚNCIO\nNome: Nuno Madama\nCargo: Administrador\n419494899",
    "nipc": "501536965",
    "distrito": "Castelo Branco",
    "concelho": "Sertã",
    "freguesia": "União das Freguesias de Cernache do Bonjardim, Nesperal e Palhais",
    "site": "www.ivs.pt",
    "email": "geral@ivs.pt",
    "designacao_contrato": "Aquisição e instalação de equipamento didático e de equipamento informático, para a escola Instituto Vaz Serra, propriedade da sociedade Instituto Vaz Serra, Sociedade de Ensino, Cultura e Recreio, S.A., Projeto nº 11014-CTE Informática.",
    "descricao": "Aquisição e instalação de equipamento didático e de equipamento informático, para a escola Instituto Vaz Serra, propriedade da sociedade Instituto Vaz Serra, Sociedade de Ensino, Cultura e Recreio, S.A., Projeto nº 11014-CTE Informática.",
    "preco_base": "729.974,67 EUR",
    "prazo_execucao": "90 DIAS",
    "prazo_apresentacao_propostas": "02-10-2025 23:59",
    "fundos_eu": "Sim",
    "plataforma_eletronica": "ANOGOV",
    "url_procedimento": "https://www.anogov.com/me-ivs/faces/",
    "autor_nome": "Nuno Madama",
    "autor_cargo": "Administrador"
  },
  {
    "numero_procedimento": "N/A",
    "entidade": "Taviraverde, Empresa Municipal de Ambiente, E.M.",
    "link": "https://diariodarepublica.pt/dr/detalhe/contrato-publico/23602-934287226",
    "detalhes_completos": "1 - IDENTIFICAÇÃO E CONTACTOS DA ENTIDADE ADJUDICANTE\nDesignação da entidade adjudicante: Taviraverde, Empresa Municipal de Ambiente, E.M.\nNIPC: 507236335\nServiço/Órgão/Pessoa de contacto: DML/DRLV\nEndereço: Largo Tabira de Pernambuco, n.º 1\nCódigo postal: 8800-456\nLocalidade: Tavira\nPaís: Portugal\nNUT III: PT150\nDistrito: Faro\nConcelho: Tavira\nFreguesia: Todas\nTelefone: 281380620\nFax: 281380629\nEndereço da Entidade (URL): www.taviraverde.pt\nEndereço Eletrónico: geral@taviraverde.pt\neDelivery Gateway (URL): https://www.acingov.pt\nFunção da Organização: Adquirente\nNorma jurídica da Entidade Adjudicante: Organismo de direito público\nÁrea de atividade da Autoridade Adjudicante: Serviços públicos das administrações públicas\n\n2 - JORNAL OFICIAL DA UNIÃO EUROPEIA\nO procedimento a que este anúncio diz respeito também é publicitado no Jornal Oficial da União Europeia? Sim\n\n3 - AVISO\nModelo de Anúncio: Concurso público\nData de Envio do Anúncio: 02-09-2025\n\n5 - PROCESSO\nTipo de Procedimento: Concurso público\nPreço base do procedimento: Sim\nValor do preço base do procedimento: 278.500,00 EUR\nProcedimento com lotes? Não\n\n6 - OBJETO DO CONTRATO\nNúmero de referência interna: CP/3900/2025\nDesignação do contrato: Aquisição de Varredoura Aspiradora Compacta de 2m3\nDescrição: Aquisição de Varredoura Aspiradora Compacta de 2m3\nOpções: Não\nTipo de Contrato Principal: Aquisição de Bens Móveis\nTipo de Contrato: Aquisição de Bens Móveis\nClassificação CPV (Vocabulário Comum para os Contratos Públicos)\nObjeto principal\nVocabulário Principal: 34144511\nPreço base s/IVA: 278.500,00 EUR\n\n7 - INDICAÇÕES ADICIONAIS\nO contrato envolve aquisição conjunta (satisfação de várias entidades)? Não\nO contrato é adjudicado por uma central de compras? Não\n\n8 - TÉCNICAS\nO concurso destina-se à celebração de um acordo-quadro? Inexistência de acordo-quadro\nÉ utilizado um leilão eletrónico? Não\nÉ adotada uma fase de negociação? Não\nSistema de Aquisição Dinâmico: Inexistência de sistema de aquisição dinâmico\n\n9 - LOCAL DA EXECUÇÃO DO CONTRATO\nLOCAL DA EXECUÇÃO DO CONTRATO (PROCEDIMENTO)\nPaís: Portugal\nNUT III: PT150\nLocalidade: Tavira\nDistrito: Faro\nConcelho: Tavira\nFreguesia: Todas\n\n10 - PRAZO DE EXECUÇÃO DO CONTRATO\nPrazo de execução do contrato: 90 DIAS\nPrevisão de renovações: Não\n\n11 - FUNDOS EU\nTêm fundos EU? Não\n\n12 - DOCUMENTOS DE HABILITAÇÃO\nHabilitação para o exercício da atividade profissional: Não\n\n13 - CONDIÇÕES DE APRESENTAÇÃO\nPlataforma eletrónica utilizada pela entidade adjudicante: ACIN\nURL para Apresentação: https://www.acingov.pt\nAdmissibilidade da apresentação de propostas variantes: Não autorizado\nPrazo para apresentação das propostas: 02-10-2025 23:59\nPrazo durante o qual os concorrentes são obrigados a manter as respetivas propostas: 66 dias a contar do termo do prazo para a apresentação das propostas\nApresentação de Catálogo Eletrónico: Permitido\nIndicação de Subcontratação na Proposta: Inexistência de indicação de subcontratação\n\n14 - PRESTAÇÃO DE CAUÇÃO\nPrestação de caução: Não\n\n15 - FORNECIMENTO DAS PEÇAS DO CONCURSO, APRESENTAÇÃO DE PEDIDOS DE PARTICIPAÇÃO E APRESENTAÇÃO DAS PROPOSTAS\nLink para acesso às peças do concurso (URL): https://www.acingov.pt/acingovprod/2/zonaPublica/zona_publica_c/donwloadProcedurePiece/OTc0Nzkz\n\n20 - OUTROS REQUISITOS\nInformação sobre contratos reservados. Aplica-se a contratos reservados (54º-A)? Não\n\n21 - CRITÉRIO DE ADJUDICAÇÃO\nMultifator: Não\nMonofator:\nNome: Preço\n\n24 - CONDIÇÕES DO CONTRATO\nFaturação Eletrónica: Permitido\nObrigação de Subcontratação:\nCódigo da Obrigação de Subcontratação: Não é aplicável nenhuma obrigação de subcontratação.\n\n25 - COMPRA PÚBLICA ESTRATÉGICA\nCompra Pública Estratégica: Inexistência de contratação pública estratégica\n\n26 - INFORMAÇÕES ADICIONAIS\nContrato adequado para PME: Sim\nCobertura ACP (Acordo dos Contratos Públicos da Organização Mundial do Comércio): Não\n\n27 - IDENTIFICAÇÃO E CONTACTOS DO ÓRGÃO DE RECURSOS ADMINISTRATIVOS\nDesignação: Administração\nEndereço: Largo Tabira de Pernambuco, n.º 1\nCódigo postal: 8800-456\nLocalidade: Tavira\nTelefone: 281380620\nFax: \nEndereço eletrónico: geral@taviraverde.pt\n\n28 - IDENTIFICAÇÃO DO(S) AUTOR(ES) DE ANÚNCIO\nNome: Virgínia Ramos\nCargo: Gestora Jurídica\n419496161",
    "nipc": "507236335",
    "distrito": "Faro",
    "concelho": "Tavira",
    "freguesia": "Todas",
    "site": "www.taviraverde.pt",
    "email": "geral@taviraverde.pt",
    "designacao_contrato": "Aquisição de Varredoura Aspiradora Compacta de 2m3",
    "descricao": "Aquisição de Varredoura Aspiradora Compacta de 2m3",
    "preco_base": "278.500,00 EUR",
    "prazo_execucao": "90 DIAS",
    "prazo_apresentacao_propostas": "02-10-2025 23:59",
    "fundos_eu": "Não",
    "plataforma_eletronica": "ACIN",
    "url_procedimento": "https://www.acingov.pt",
    "autor_nome": "Virgínia Ramos",
    "autor_cargo": "Gestora Jurídica"
  },
  {
    "numero_procedimento": "N/A",
    "entidade": "Secretaria-Geral do Governo",
    "link": "https://diariodarepublica.pt/dr/detalhe/contrato-publico/23604-934287227",
    "detalhes_completos": "1 - IDENTIFICAÇÃO E CONTACTOS DA ENTIDADE ADJUDICANTE\nDesignação da entidade adjudicante: Secretaria-Geral do Governo\nNIPC: 600088103\nServiço/Órgão/Pessoa de contacto: Divisão de Compras Públicas\nEndereço: Avenida João XXI, 63\nCódigo postal: 1000-300\nLocalidade: Lisboa\nPaís: Portugal\nNUT III: PT170\nDistrito: Lisboa\nConcelho: Todos\nFreguesia: Todas\nTelefone: 969762129\nEndereço da Entidade (URL): https://www.sg.pcm.gov.pt\nEndereço Eletrónico: joanar@sg.pcm.gov.pt\neDelivery Gateway (URL): https://www.acingov.pt\nFunção da Organização: Adquirente\nSubfunção da Organização: Organização cujo orçamento é utilizado para pagar o contrato; Organização que executa o pagamento; Organização que fornece informações adicionais sobre o processo de adjudicação; Organização que fornece mais informações sobre os prazos dos procedimentos de recurso; Organização responsável pelo tratamento das propostas; Organização que recebe as propostas; Organização que trata os pedidos de participação; Organização que recebe pedidos de participação; Organização que fornece mais informações sobre os procedimentos de recurso; Organização que assina o contrato\nNorma jurídica da Entidade Adjudicante: Organismo de direito público\nÁrea de atividade da Autoridade Adjudicante: Serviços públicos das administrações públicas\n\n2 - JORNAL OFICIAL DA UNIÃO EUROPEIA\nO procedimento a que este anúncio diz respeito também é publicitado no Jornal Oficial da União Europeia? Não\n\n3 - AVISO\nModelo de Anúncio: Concurso público\nData de Envio do Anúncio: 04-09-2025\n\n5 - PROCESSO\nTipo de Procedimento: Concurso público\nPreço base do procedimento: Sim\nValor do preço base do procedimento: 105.930,00 EUR\nProcedimento com lotes? Não\n\n6 - OBJETO DO CONTRATO\nNúmero de referência interna: 116/UMC/2025\nDesignação do contrato: Aquisição de diverso equipamento informático\nDescrição: Aquisição de diverso equipamento informático\nTipo de Contrato Principal: Aquisição de Bens Móveis\nTipo de Contrato: Aquisição de Bens Móveis\nClassificação CPV (Vocabulário Comum para os Contratos Públicos)\nObjeto principal\nVocabulário Principal: 30200000\nPreço base s/IVA: 105.930,00 EUR\n\n7 - INDICAÇÕES ADICIONAIS\nO contrato envolve aquisição conjunta (satisfação de várias entidades)? Não\nO contrato é adjudicado por uma central de compras? Não\n\n8 - TÉCNICAS\nO concurso destina-se à celebração de um acordo-quadro? Inexistência de acordo-quadro\nÉ utilizado um leilão eletrónico? Não\nÉ adotada uma fase de negociação? Não\nSistema de Aquisição Dinâmico: Inexistência de sistema de aquisição dinâmico\n\n9 - LOCAL DA EXECUÇÃO DO CONTRATO\nLOCAL DA EXECUÇÃO DO CONTRATO (PROCEDIMENTO)\nPaís: Portugal\nNUT III: PT170\nLocalidade: Lisboa\nDistrito: Lisboa\nConcelho: Lisboa\nFreguesia: Freguesia de Areeiro\n\n10 - PRAZO DE EXECUÇÃO DO CONTRATO\nPrazo de execução do contrato: 60 DIAS\nPrevisão de renovações: Não\n\n11 - FUNDOS EU\nTêm fundos EU? Não\n\n12 - DOCUMENTOS DE HABILITAÇÃO\nHabilitação para o exercício da atividade profissional: Não\n\n13 - CONDIÇÕES DE APRESENTAÇÃO\nPlataforma eletrónica utilizada pela entidade adjudicante: ACIN\nURL para Apresentação: https://www.acingov.pt\nAdmissibilidade da apresentação de propostas variantes: Não autorizado\nPrazo para apresentação das propostas: 17-09-2025 23:59\nPrazo durante o qual os concorrentes são obrigados a manter as respetivas propostas: 66 dias a contar do termo do prazo para a apresentação das propostas\nIndicação de Subcontratação na Proposta: Inexistência de indicação de subcontratação\n\n14 - PRESTAÇÃO DE CAUÇÃO\nPrestação de caução: Não\n\n15 - FORNECIMENTO DAS PEÇAS DO CONCURSO, APRESENTAÇÃO DE PEDIDOS DE PARTICIPAÇÃO E APRESENTAÇÃO DAS PROPOSTAS\nLink para acesso às peças do concurso (URL): https://www.acingov.pt/acingovprod/2/zonaPublica/zona_publica_c/donwloadProcedurePiece/OTc1MzA4\n\n20 - OUTROS REQUISITOS\nInformação sobre contratos reservados. Aplica-se a contratos reservados (54º-A)? Não\n\n21 - CRITÉRIO DE ADJUDICAÇÃO\nMultifator: Sim\nFator: \nNome: Outros\nOutro Nome: Multifator\nPonderação: 100%\nSubfatores: Não\n\n24 - CONDIÇÕES DO CONTRATO\nFaturação Eletrónica: Permitido\nObrigação de Subcontratação:\nCódigo da Obrigação de Subcontratação: Não é aplicável nenhuma obrigação de subcontratação.\n\n25 - COMPRA PÚBLICA ESTRATÉGICA\nCompra Pública Estratégica: Redução dos impactos ambientais\nDescrição do Processo de Adjudicação Estratégico: Conforme consta nas peças do procedimento\nCritérios de contratos Públicos Ecológicos: Critérios de contratação pública ecológica nacional\nCategorias da estratégia nacional: Computadores, monitores, tabletes e telemóveis inteligentes\nContratos Públicos Ecológicos: A mitigação das alterações climáticas; A prevenção e o controlo da poluição\nDiretiva Veículos Não Poluentes: Não\nCritério de Acessibilidade: Os critérios de acessibilidade para as pessoas com deficiência não estão incluídos porque o contrato não se destina a pessoas singulares\n\n26 - INFORMAÇÕES ADICIONAIS\nContrato adequado para PME: Sim\nCobertura ACP (Acordo dos Contratos Públicos da Organização Mundial do Comércio): Não\n\n27 - IDENTIFICAÇÃO E CONTACTOS DO ÓRGÃO DE RECURSOS ADMINISTRATIVOS\nDesignação: Gabinete do Ministro da Presidência\nEndereço: Avenida João XXI, 63\nCódigo postal: 1000-300\nLocalidade: Lisboa\nTelefone: 969762129\nFax: \nEndereço eletrónico: julieta.carvalho@sggoverno.gov.pt\nPrazo de interposição do recurso: 10 dias\n\n28 - IDENTIFICAÇÃO DO(S) AUTOR(ES) DE ANÚNCIO\nNome: Rui Rodrigues\nCargo: Tecnico Superior\n419504844",
    "nipc": "600088103",
    "distrito": "Lisboa",
    "concelho": "Todos",
    "freguesia": "Todas",
    "site": "https://www.sg.pcm.gov.pt",
    "email": "joanar@sg.pcm.gov.pt",
    "designacao_contrato": "Aquisição de diverso equipamento informático",
    "descricao": "Aquisição de diverso equipamento informático",
    "preco_base": "105.930,00 EUR",
    "prazo_execucao": "60 DIAS",
    "prazo_apresentacao_propostas": "17-09-2025 23:59",
    "fundos_eu": "Não",
    "plataforma_eletronica": "ACIN",
    "url_procedimento": "https://www.acingov.pt",
    "autor_nome": "Rui Rodrigues",
    "autor_cargo": "Tecnico Superior"
  },
  {
    "numero_procedimento": "N/A",
    "entidade": "Serviços Municipalizados de Água e Saneamento de Viseu",
    "link": "https://diariodarepublica.pt/dr/detalhe/contrato-publico/23605-934287232",
    "detalhes_completos": "1 - IDENTIFICAÇÃO E CONTACTOS DA ENTIDADE ADJUDICANTE\nDesignação da entidade adjudicante: Serviços Municipalizados de Água e Saneamento de Viseu\nNIPC: 680020063\nEndereço: Rua Conselheiro Afonso de Melo\nCódigo postal: 3510-024\nLocalidade: Viseu\nPaís: Portugal\nNUT III: PT16G\nDistrito: Viseu\nConcelho: Viseu\nFreguesia: Freguesia de Viseu\nTelefone: 232470670\nFax: 232424080\nEndereço da Entidade (URL): www.smasviseu.pt\nEndereço Eletrónico: geral@smasviseu.pt\neDelivery Gateway (URL): https://www.acingov.pt\nFunção da Organização: Adquirente\nNorma jurídica da Entidade Adjudicante: Autoridade local\nÁrea de atividade da Autoridade Adjudicante: Serviços públicos das administrações públicas\n\n2 - JORNAL OFICIAL DA UNIÃO EUROPEIA\nO procedimento a que este anúncio diz respeito também é publicitado no Jornal Oficial da União Europeia? Não\n\n3 - AVISO\nModelo de Anúncio: Concurso público\nData de Envio do Anúncio: 05-09-2025\n\n5 - PROCESSO\nTipo de Procedimento: Concurso público\nPreço base do procedimento: Sim\nValor do preço base do procedimento: 21.000,00 EUR\nProcedimento com lotes? Não\n\n6 - OBJETO DO CONTRATO\nNúmero de referência interna: ABS2025-092\nDesignação do contrato: Aquisição de Polímero de Floculação para a ETA de Fagilde - 2026\nDescrição: Aquisição de Polímero de Floculação para a ETA de Fagilde - 2026\nTipo de Contrato Principal: Aquisição de Bens Móveis\nTipo de Contrato: Aquisição de Bens Móveis\nClassificação CPV (Vocabulário Comum para os Contratos Públicos)\nObjeto principal\nVocabulário Principal: 24520000\nPreço base s/IVA: 21.000,00 EUR\n\n7 - INDICAÇÕES ADICIONAIS\nO contrato envolve aquisição conjunta (satisfação de várias entidades)? Não\nO contrato é adjudicado por uma central de compras? Não\n\n8 - TÉCNICAS\nO concurso destina-se à celebração de um acordo-quadro? Inexistência de acordo-quadro\nÉ utilizado um leilão eletrónico? Não\nÉ adotada uma fase de negociação? Não\nSistema de Aquisição Dinâmico: Inexistência de sistema de aquisição dinâmico\n\n9 - LOCAL DA EXECUÇÃO DO CONTRATO\nLOCAL DA EXECUÇÃO DO CONTRATO (PROCEDIMENTO)\nPaís: Portugal\nNUT III: PT16G\nLocalidade: Freguesia de Viseu\nDistrito: Viseu\nConcelho: Viseu\nFreguesia: Freguesia de Viseu\n\n10 - PRAZO DE EXECUÇÃO DO CONTRATO\nPrazo de execução do contrato: 12 MESES\nPrevisão de renovações: Não\n\n11 - FUNDOS EU\nTêm fundos EU? Não\n\n12 - DOCUMENTOS DE HABILITAÇÃO\nHabilitação para o exercício da atividade profissional: Não\n\n13 - CONDIÇÕES DE APRESENTAÇÃO\nPlataforma eletrónica utilizada pela entidade adjudicante: ACIN\nURL para Apresentação: https://www.acingov.pt\nAdmissibilidade da apresentação de propostas variantes: Não autorizado\nPrazo para apresentação das propostas: 20-09-2025 23:59\nPrazo durante o qual os concorrentes são obrigados a manter as respetivas propostas: 66 dias a contar do termo do prazo para a apresentação das propostas\nIndicação de Subcontratação na Proposta: Inexistência de indicação de subcontratação\n\n14 - PRESTAÇÃO DE CAUÇÃO\nPrestação de caução: Não\n\n15 - FORNECIMENTO DAS PEÇAS DO CONCURSO, APRESENTAÇÃO DE PEDIDOS DE PARTICIPAÇÃO E APRESENTAÇÃO DAS PROPOSTAS\nLink para acesso às peças do concurso (URL): https://www.acingov.pt/acingovprod/2/zonaPublica/zona_publica_c/donwloadProcedurePiece/OTcyOTkz\n\n20 - OUTROS REQUISITOS\nInformação sobre contratos reservados. Aplica-se a contratos reservados (54º-A)? Não\n\n21 - CRITÉRIO DE ADJUDICAÇÃO\nMultifator: Não\nMonofator:\nNome: Preço\n\n24 - CONDIÇÕES DO CONTRATO\nFaturação Eletrónica: Permitido\nObrigação de Subcontratação:\nCódigo da Obrigação de Subcontratação: Não é aplicável nenhuma obrigação de subcontratação.\n\n25 - COMPRA PÚBLICA ESTRATÉGICA\nCompra Pública Estratégica: Inexistência de contratação pública estratégica\n\n26 - INFORMAÇÕES ADICIONAIS\nContrato adequado para PME: Sim\nCobertura ACP (Acordo dos Contratos Públicos da Organização Mundial do Comércio): Não\n\n27 - IDENTIFICAÇÃO E CONTACTOS DO ÓRGÃO DE RECURSOS ADMINISTRATIVOS\nDesignação: Serviços Municipalizados de Viseu\nEndereço: Rua Conselheiro Afonso de Melo\nCódigo postal: 3510-024\nLocalidade: Viseu\nTelefone: 00351232470670\nFax: 00351232424080\nEndereço eletrónico: geral@smasviseu.pt\nPrazo de interposição do recurso: 5 dias\n\n28 - IDENTIFICAÇÃO DO(S) AUTOR(ES) DE ANÚNCIO\nNome: João Paulo Lopes Gouveia\nCargo: Vogal do Conselho de Administração\n419490142",
    "nipc": "680020063",
    "distrito": "Viseu",
    "concelho": "Viseu",
    "freguesia": "Freguesia de Viseu",
    "site": "www.smasviseu.pt",
    "email": "geral@smasviseu.pt",
    "designacao_contrato": "Aquisição de Polímero de Floculação para a ETA de Fagilde - 2026",
    "descricao": "Aquisição de Polímero de Floculação para a ETA de Fagilde - 2026",
    "preco_base": "21.000,00 EUR",
    "prazo_execucao": "12 MESES",
    "prazo_apresentacao_propostas": "20-09-2025 23:59",
    "fundos_eu": "Não",
    "plataforma_eletronica": "ACIN",
    "url_procedimento": "https://www.acingov.pt",
    "autor_nome": "João Paulo Lopes Gouveia",
    "autor_cargo": "Vogal do Conselho de Administração"
  },
  {
    "numero_procedimento": "N/A",
    "entidade": "Serviços Municipalizados de Água e Saneamento de Viseu",
    "link": "https://diariodarepublica.pt/dr/detalhe/contrato-publico/23607-934287233",
    "detalhes_completos": "1 - IDENTIFICAÇÃO E CONTACTOS DA ENTIDADE ADJUDICANTE\nDesignação da entidade adjudicante: Serviços Municipalizados de Água e Saneamento de Viseu\nNIPC: 680020063\nEndereço: Rua Conselheiro Afonso de Melo\nCódigo postal: 3510-024\nLocalidade: Viseu\nPaís: Portugal\nNUT III: PT16G\nDistrito: Viseu\nConcelho: Viseu\nFreguesia: Freguesia de Viseu\nTelefone: 232470670\nFax: 232424080\nEndereço da Entidade (URL): www.smasviseu.pt\nEndereço Eletrónico: geral@smasviseu.pt\neDelivery Gateway (URL): https://www.acingov.pt\nFunção da Organização: Adquirente\nNorma jurídica da Entidade Adjudicante: Autoridade local\nÁrea de atividade da Autoridade Adjudicante: Serviços públicos das administrações públicas\n\n2 - JORNAL OFICIAL DA UNIÃO EUROPEIA\nO procedimento a que este anúncio diz respeito também é publicitado no Jornal Oficial da União Europeia? Não\n\n3 - AVISO\nModelo de Anúncio: Concurso público\nData de Envio do Anúncio: 05-09-2025\n\n5 - PROCESSO\nTipo de Procedimento: Concurso público\nPreço base do procedimento: Sim\nValor do preço base do procedimento: 54.000,00 EUR\nProcedimento com lotes? Não\n\n6 - OBJETO DO CONTRATO\nNúmero de referência interna: ABS2025-091\nDesignação do contrato: Aquisição de Cal Hidratada a Granel para a ETA Fagilde - 2026\nDescrição: Aquisição de Cal Hidratada a Granel para a ETA Fagilde - 2026\nTipo de Contrato Principal: Aquisição de Bens Móveis\nTipo de Contrato: Aquisição de Bens Móveis\nClassificação CPV (Vocabulário Comum para os Contratos Públicos)\nObjeto principal\nVocabulário Principal: 24213000\nPreço base s/IVA: 54.000,00 EUR\n\n7 - INDICAÇÕES ADICIONAIS\nO contrato envolve aquisição conjunta (satisfação de várias entidades)? Não\nO contrato é adjudicado por uma central de compras? Não\n\n8 - TÉCNICAS\nO concurso destina-se à celebração de um acordo-quadro? Inexistência de acordo-quadro\nÉ utilizado um leilão eletrónico? Não\nÉ adotada uma fase de negociação? Não\nSistema de Aquisição Dinâmico: Inexistência de sistema de aquisição dinâmico\n\n9 - LOCAL DA EXECUÇÃO DO CONTRATO\nLOCAL DA EXECUÇÃO DO CONTRATO (PROCEDIMENTO)\nPaís: Portugal\nNUT III: PT16G\nLocalidade: Freguesia de Viseu\nDistrito: Viseu\nConcelho: Viseu\nFreguesia: Freguesia de Viseu\n\n10 - PRAZO DE EXECUÇÃO DO CONTRATO\nPrazo de execução do contrato: 365 DIAS\nPrevisão de renovações: Não\n\n11 - FUNDOS EU\nTêm fundos EU? Não\n\n12 - DOCUMENTOS DE HABILITAÇÃO\nHabilitação para o exercício da atividade profissional: Não\n\n13 - CONDIÇÕES DE APRESENTAÇÃO\nPlataforma eletrónica utilizada pela entidade adjudicante: ACIN\nURL para Apresentação: https://www.acingov.pt\nAdmissibilidade da apresentação de propostas variantes: Não autorizado\nPrazo para apresentação das propostas: 22-09-2025 23:59\nPrazo durante o qual os concorrentes são obrigados a manter as respetivas propostas: 120 dias a contar do termo do prazo para a apresentação das propostas\nIndicação de Subcontratação na Proposta: Inexistência de indicação de subcontratação\n\n14 - PRESTAÇÃO DE CAUÇÃO\nPrestação de caução: Não\n\n15 - FORNECIMENTO DAS PEÇAS DO CONCURSO, APRESENTAÇÃO DE PEDIDOS DE PARTICIPAÇÃO E APRESENTAÇÃO DAS PROPOSTAS\nLink para acesso às peças do concurso (URL): https://www.acingov.pt/acingovprod/2/zonaPublica/zona_publica_c/donwloadProcedurePiece/OTcyNDQ3\n\n20 - OUTROS REQUISITOS\nInformação sobre contratos reservados. Aplica-se a contratos reservados (54º-A)? Não\n\n21 - CRITÉRIO DE ADJUDICAÇÃO\nMultifator: Não\nMonofator:\nNome: Preço\n\n24 - CONDIÇÕES DO CONTRATO\nFaturação Eletrónica: Permitido\nObrigação de Subcontratação:\nCódigo da Obrigação de Subcontratação: Não é aplicável nenhuma obrigação de subcontratação.\n\n25 - COMPRA PÚBLICA ESTRATÉGICA\nCompra Pública Estratégica: Inexistência de contratação pública estratégica\n\n26 - INFORMAÇÕES ADICIONAIS\nContrato adequado para PME: Sim\nCobertura ACP (Acordo dos Contratos Públicos da Organização Mundial do Comércio): Não\n\n27 - IDENTIFICAÇÃO E CONTACTOS DO ÓRGÃO DE RECURSOS ADMINISTRATIVOS\nDesignação: Serviços Municipalizados de Viseu\nEndereço: Rua Conselheiro Afonso de Melo\nCódigo postal: 3510-024\nLocalidade: Viseu\nTelefone: 00351232470670\nFax: 00351232424080\nEndereço eletrónico: geral@smasviseu.pt\nPrazo de interposição do recurso: 5 dias\n\n28 - IDENTIFICAÇÃO DO(S) AUTOR(ES) DE ANÚNCIO\nNome: João Paulo Lopes Gouveia\nCargo: Vogal do Conselho de Administração\n419490531",
    "nipc": "680020063",
    "distrito": "Viseu",
    "concelho": "Viseu",
    "freguesia": "Freguesia de Viseu",
    "site": "www.smasviseu.pt",
    "email": "geral@smasviseu.pt",
    "designacao_contrato": "Aquisição de Cal Hidratada a Granel para a ETA Fagilde - 2026",
    "descricao": "Aquisição de Cal Hidratada a Granel para a ETA Fagilde - 2026",
    "preco_base": "54.000,00 EUR",
    "prazo_execucao": "365 DIAS",
    "prazo_apresentacao_propostas": "22-09-2025 23:59",
    "fundos_eu": "Não",
    "plataforma_eletronica": "ACIN",
    "url_procedimento": "https://www.acingov.pt",
    "autor_nome": "João Paulo Lopes Gouveia",
    "autor_cargo": "Vogal do Conselho de Administração"
  },
  {
    "numero_procedimento": "N/A",
    "entidade": "Instituto Português de Oncologia de Lisboa FG, E.P.E.",
    "link": "https://diariodarepublica.pt/dr/detalhe/contrato-publico/23609-934287234",
    "detalhes_completos": "1 - IDENTIFICAÇÃO E CONTACTOS DA ENTIDADE ADJUDICANTE\nDesignação da entidade adjudicante: Instituto Português de Oncologia de Lisboa FG, E.P.E.\nNIPC: 506361616\nEndereço: Rua Profº Lima Basto\nCódigo postal: 1099-023\nLocalidade: Lisboa\nPaís: Portugal\nNUT III: PT170\nDistrito: Lisboa\nConcelho: Lisboa\nFreguesia: Todas\nTelefone: 217229800\nFax: 217229880\nEndereço da Entidade (URL): www.ipolisboa.min-saude.pt/\nEndereço Eletrónico: ipofg@ipolisboa.min-saude.pt\neDelivery Gateway (URL): https://community.vortal.biz/public/\nFunção da Organização: Adquirente\nNorma jurídica da Entidade Adjudicante: Organismo de direito público\nÁrea de atividade da Autoridade Adjudicante: Saúde\n\n2 - JORNAL OFICIAL DA UNIÃO EUROPEIA\nO procedimento a que este anúncio diz respeito também é publicitado no Jornal Oficial da União Europeia? Não\n\n3 - AVISO\nModelo de Anúncio: Concurso público urgente\nData de Envio do Anúncio: 05-09-2025 08:36:00\n\n5 - PROCESSO\nTipo de Procedimento: Concurso público\nPreço base do procedimento: Sim\nValor do preço base do procedimento: 180.463,16 EUR\nProcedimento com lotes? Sim\nNº Máx. de Lotes Autorizado: 2\nNúmero máximo de lotes que podem ser adjudicados a um concorrente: 2\n\n6 - OBJETO DO CONTRATO\nNúmero de referência interna: PU/2584/2025\nDesignação do contrato: FORNECIMENTO DE REAGENTES E TECNOLOGIA PARA REALIZAR ANÁLISES NO LABORATÓRIO DE MICROBIOLOGIA\nDescrição: FORNECIMENTO DE REAGENTES E TECNOLOGIA PARA REALIZAR ANÁLISES NO LABORATÓRIO DE MICROBIOLOGIA\nTipo de Contrato Principal: Aquisição de Bens Móveis\nTipo de Contrato: Aquisição de Bens Móveis\nClassificação CPV (Vocabulário Comum para os Contratos Públicos)\nObjeto principal\nVocabulário Principal: 33696500\nPreço base s/IVA: 180.463,16 EUR\nLotes: \nNº: LOT-0001\nDescrição do Lote: Lote 1\nPreço base s/IVA: 94.088,16 EUR\nClassificação CPV (Vocabulário Comum para os Contratos Públicos)\nObjeto principal\nVocabulário Principal: 33696500\nNº: LOT-0002\nDescrição do Lote: Lote 2\nPreço base s/IVA: 86.375,00 EUR\nClassificação CPV (Vocabulário Comum para os Contratos Públicos)\nObjeto principal\nVocabulário Principal: 33696500\n\n7 - INDICAÇÕES ADICIONAIS\nO contrato envolve aquisição conjunta (satisfação de várias entidades)? Não\nO contrato é adjudicado por uma central de compras? Não\n\n8 - TÉCNICAS\nO concurso destina-se à celebração de um acordo-quadro? Inexistência de acordo-quadro\nÉ utilizado um leilão eletrónico? Não\nÉ adotada uma fase de negociação? Não\nSistema de Aquisição Dinâmico: Inexistência de sistema de aquisição dinâmico\n\n9 - LOCAL DA EXECUÇÃO DO CONTRATO\nLOCAL DA EXECUÇÃO DO CONTRATO (PROCEDIMENTO)\nPaís: Portugal\nNUT III: PT170\nLocalidade: Lisboa\nDistrito: Lisboa\nConcelho: Lisboa\nFreguesia: Freguesia de São Domingos de Benfica\nLOCAL DA EXECUÇÃO DO CONTRATO (LOTE)\nIdentificador do Lote: LOT-0001; LOT-0002\nPaís: Portugal\nNUT III: PT170\nLocalidade: Lisboa\nDistrito: Lisboa\nConcelho: Lisboa\nFreguesia: Freguesia de São Domingos de Benfica\n\n10 - PRAZO DE EXECUÇÃO DO CONTRATO\nIdentificador do Lote: LOT-0001; LOT-0002\nPrazo de execução do contrato: 3 MESES\nPrevisão de renovações: Não\n\n11 - FUNDOS EU\nIdentificador do Lote: LOT-0001; LOT-0002\nTêm fundos EU? Não\n\n12 - DOCUMENTOS DE HABILITAÇÃO\nHabilitação para o exercício da atividade profissional: Não\n\n13 - CONDIÇÕES DE APRESENTAÇÃO\nPlataforma eletrónica utilizada pela entidade adjudicante: VORTAL\nURL para Apresentação: https://community.vortal.biz/public/\nAdmissibilidade da apresentação de propostas variantes: Não autorizado\nPrazo para apresentação das propostas: 08-09-2025 17:59\nPrazo durante o qual os concorrentes são obrigados a manter as respetivas propostas: 10 dias a contar do termo do prazo para a apresentação das propostas\nIndicação de Subcontratação na Proposta: Inexistência de indicação de subcontratação\n\n14 - PRESTAÇÃO DE CAUÇÃO\nPrestação de caução: Não\n\n15 - FORNECIMENTO DAS PEÇAS DO CONCURSO, APRESENTAÇÃO DE PEDIDOS DE PARTICIPAÇÃO E APRESENTAÇÃO DAS PROPOSTAS\nLink para acesso às peças do concurso (URL): https://community.vortal.biz/Public/public-tender-documents/dk9QU0FxYldhVHN5RGd4UElrMnZzYXg2VC93SFQvWWM2N1d5MGdJajRpUFYyTlZuUUl3WnFxS3htRzBNNDRhRWNGcnBkWE5iRm5iNlZZWU1lYTFMbHc9PWd2WiN4\n\n20 - OUTROS REQUISITOS\nIdentificador do Lote: LOT-0001; LOT-0002\nInformação sobre contratos reservados. Aplica-se a contratos reservados (54º-A)? Não\n\n21 - CRITÉRIO DE ADJUDICAÇÃO\nO Critério de adjudicação é diferenciado por lote? Não\nMultifator: Não\nMonofator:\nNome: Preço\n\n24 - CONDIÇÕES DO CONTRATO\nIdentificador do Lote: LOT-0001; LOT-0002\nFaturação Eletrónica: Permitido\nObrigação de Subcontratação:\nCódigo da Obrigação de Subcontratação: Não é aplicável nenhuma obrigação de subcontratação.\n\n25 - COMPRA PÚBLICA ESTRATÉGICA\nCompra Pública Estratégica: Inexistência de contratação pública estratégica\n\n26 - INFORMAÇÕES ADICIONAIS\nIdentificador do Lote: LOT-0001; LOT-0002\nContrato adequado para PME: Sim\nCobertura ACP (Acordo dos Contratos Públicos da Organização Mundial do Comércio): Não\n\n27 - IDENTIFICAÇÃO E CONTACTOS DO ÓRGÃO DE RECURSOS ADMINISTRATIVOS\nDesignação: Conselho de Administração\nEndereço: Rua Profesor Lima Basto\nCódigo postal: 1099-023\nLocalidade: Lisboa\nTelefone: +351 217229832\nFax: +351 217229833\nEndereço eletrónico: ipofg@ipolisboa.min-saude.pt\n\n28 - IDENTIFICAÇÃO DO(S) AUTOR(ES) DE ANÚNCIO\nNome: Marta Miranda\nCargo: Assistente Técnico\n419505581",
    "nipc": "506361616",
    "distrito": "Lisboa",
    "concelho": "Lisboa",
    "freguesia": "Todas",
    "site": "www.ipolisboa.min-saude.pt/",
    "email": "ipofg@ipolisboa.min-saude.pt",
    "designacao_contrato": "FORNECIMENTO DE REAGENTES E TECNOLOGIA PARA REALIZAR ANÁLISES NO LABORATÓRIO DE MICROBIOLOGIA",
    "descricao": "FORNECIMENTO DE REAGENTES E TECNOLOGIA PARA REALIZAR ANÁLISES NO LABORATÓRIO DE MICROBIOLOGIA",
    "preco_base": "180.463,16 EUR",
    "prazo_execucao": "3 MESES",
    "prazo_apresentacao_propostas": "08-09-2025 17:59",
    "fundos_eu": "Não",
    "plataforma_eletronica": "VORTAL",
    "url_procedimento": "https://community.vortal.biz/public/",
    "autor_nome": "Marta Miranda",
    "autor_cargo": "Assistente Técnico"
  },
  {
    "numero_procedimento": "N/A",
    "entidade": "Serviços Municipalizados de Água e Saneamento de Viseu",
    "link": "https://diariodarepublica.pt/dr/detalhe/contrato-publico/23606-934323825",
    "detalhes_completos": "1 - IDENTIFICAÇÃO E CONTACTOS DA ENTIDADE ADJUDICANTE\nDesignação da entidade adjudicante: Serviços Municipalizados de Água e Saneamento de Viseu\nNIPC: 680020063\nEndereço: Rua Conselheiro Afonso de Melo\nCódigo postal: 3510-024\nLocalidade: Viseu\nPaís: Portugal\nNUT III: PT16G\nDistrito: Viseu\nConcelho: Viseu\nFreguesia: Freguesia de Viseu\nTelefone: 232470670\nFax: 232424080\nEndereço da Entidade (URL): www.smasviseu.pt\nEndereço Eletrónico: geral@smasviseu.pt\neDelivery Gateway (URL): https://www.acingov.pt\nFunção da Organização: Adquirente\nNorma jurídica da Entidade Adjudicante: Autoridade local\nÁrea de atividade da Autoridade Adjudicante: Serviços públicos das administrações públicas\n\n2 - JORNAL OFICIAL DA UNIÃO EUROPEIA\nO procedimento a que este anúncio diz respeito também é publicitado no Jornal Oficial da União Europeia? Não\n\n3 - AVISO\nModelo de Anúncio: Concurso público\nData de Envio do Anúncio: 05-09-2025\n\n5 - PROCESSO\nTipo de Procedimento: Concurso público\nPreço base do procedimento: Sim\nValor do preço base do procedimento: 81.000,00 EUR\nProcedimento com lotes? Não\n\n6 - OBJETO DO CONTRATO\nNúmero de referência interna: ABS2025-093\nDesignação do contrato: Aquisição de Hipoclorito de Sódio a 13% em (IBC) para a ETA de Fagilde-2026\nDescrição: Aquisição de Hipoclorito de Sódio a 13% em (IBC) para a ETA de Fagilde-2026\nTipo de Contrato Principal: Aquisição de Bens Móveis\nTipo de Contrato: Aquisição de Bens Móveis\nClassificação CPV (Vocabulário Comum para os Contratos Públicos)\nObjeto principal\nVocabulário Principal: 24312220\nPreço base s/IVA: 81.000,00 EUR\n\n7 - INDICAÇÕES ADICIONAIS\nO contrato envolve aquisição conjunta (satisfação de várias entidades)? Não\nO contrato é adjudicado por uma central de compras? Não\n\n8 - TÉCNICAS\nO concurso destina-se à celebração de um acordo-quadro? Inexistência de acordo-quadro\nÉ utilizado um leilão eletrónico? Não\nÉ adotada uma fase de negociação? Não\nSistema de Aquisição Dinâmico: Inexistência de sistema de aquisição dinâmico\n\n9 - LOCAL DA EXECUÇÃO DO CONTRATO\nLOCAL DA EXECUÇÃO DO CONTRATO (PROCEDIMENTO)\nPaís: Portugal\nNUT III: PT16G\nLocalidade: Freguesia de Viseu\nDistrito: Viseu\nConcelho: Viseu\nFreguesia: Freguesia de Viseu\n\n10 - PRAZO DE EXECUÇÃO DO CONTRATO\nPrazo de execução do contrato: 12 MESES\nPrevisão de renovações: Não\n\n11 - FUNDOS EU\nTêm fundos EU? Não\n\n12 - DOCUMENTOS DE HABILITAÇÃO\nHabilitação para o exercício da atividade profissional: Não\n\n13 - CONDIÇÕES DE APRESENTAÇÃO\nPlataforma eletrónica utilizada pela entidade adjudicante: ACIN\nURL para Apresentação: https://www.acingov.pt\nAdmissibilidade da apresentação de propostas variantes: Não autorizado\nPrazo para apresentação das propostas: 23-09-2025 23:59\nPrazo durante o qual os concorrentes são obrigados a manter as respetivas propostas: 66 dias a contar do termo do prazo para a apresentação das propostas\nIndicação de Subcontratação na Proposta: Inexistência de indicação de subcontratação\n\n14 - PRESTAÇÃO DE CAUÇÃO\nPrestação de caução: Não\n\n15 - FORNECIMENTO DAS PEÇAS DO CONCURSO, APRESENTAÇÃO DE PEDIDOS DE PARTICIPAÇÃO E APRESENTAÇÃO DAS PROPOSTAS\nLink para acesso às peças do concurso (URL): https://www.acingov.pt/acingovprod/2/zonaPublica/zona_publica_c/donwloadProcedurePiece/OTczNzEx\n\n20 - OUTROS REQUISITOS\nInformação sobre contratos reservados. Aplica-se a contratos reservados (54º-A)? Não\n\n21 - CRITÉRIO DE ADJUDICAÇÃO\nMultifator: Não\nMonofator:\nNome: Preço\n\n24 - CONDIÇÕES DO CONTRATO\nFaturação Eletrónica: Permitido\nObrigação de Subcontratação:\nCódigo da Obrigação de Subcontratação: Não é aplicável nenhuma obrigação de subcontratação.\n\n25 - COMPRA PÚBLICA ESTRATÉGICA\nCompra Pública Estratégica: Inexistência de contratação pública estratégica\n\n26 - INFORMAÇÕES ADICIONAIS\nContrato adequado para PME: Sim\nCobertura ACP (Acordo dos Contratos Públicos da Organização Mundial do Comércio): Não\n\n27 - IDENTIFICAÇÃO E CONTACTOS DO ÓRGÃO DE RECURSOS ADMINISTRATIVOS\nDesignação: Serviços Municipalizados de Viseu\nEndereço: Rua Conselheiro Afonso de Melo\nCódigo postal: 3510-024\nLocalidade: Viseu\nTelefone: 00351232470670\nFax: 00351232424080\nEndereço eletrónico: geral@smasviseu.pt\nPrazo de interposição do recurso: 5 dias\n\n28 - IDENTIFICAÇÃO DO(S) AUTOR(ES) DE ANÚNCIO\nNome: João Paulo Lopes Gouveia\nCargo: Vogal do Conselho de Administração\n419490248",
    "nipc": "680020063",
    "distrito": "Viseu",
    "concelho": "Viseu",
    "freguesia": "Freguesia de Viseu",
    "site": "www.smasviseu.pt",
    "email": "geral@smasviseu.pt",
    "designacao_contrato": "Aquisição de Hipoclorito de Sódio a 13% em (IBC) para a ETA de Fagilde-2026",
    "descricao": "Aquisição de Hipoclorito de Sódio a 13% em (IBC) para a ETA de Fagilde-2026",
    "preco_base": "81.000,00 EUR",
    "prazo_execucao": "12 MESES",
    "prazo_apresentacao_propostas": "23-09-2025 23:59",
    "fundos_eu": "Não",
    "plataforma_eletronica": "ACIN",
    "url_procedimento": "https://www.acingov.pt",
    "autor_nome": "João Paulo Lopes Gouveia",
    "autor_cargo": "Vogal do Conselho de Administração"
  },
  {
    "numero_procedimento": "N/A",
    "entidade": "Serviços Municipalizados de Água e Saneamento de Viseu",
    "link": "https://diariodarepublica.pt/dr/detalhe/contrato-publico/23608-934323826",
    "detalhes_completos": "1 - IDENTIFICAÇÃO E CONTACTOS DA ENTIDADE ADJUDICANTE\nDesignação da entidade adjudicante: Serviços Municipalizados de Água e Saneamento de Viseu\nNIPC: 680020063\nEndereço: Rua Conselheiro Afonso de Melo\nCódigo postal: 3510-024\nLocalidade: Viseu\nPaís: Portugal\nNUT III: PT16G\nDistrito: Viseu\nConcelho: Viseu\nFreguesia: Freguesia de Viseu\nTelefone: 232470670\nFax: 232424080\nEndereço da Entidade (URL): www.smasviseu.pt\nEndereço Eletrónico: geral@smasviseu.pt\neDelivery Gateway (URL): https://www.acingov.pt\nFunção da Organização: Adquirente\nNorma jurídica da Entidade Adjudicante: Autoridade local\nÁrea de atividade da Autoridade Adjudicante: Serviços públicos das administrações públicas\n\n2 - JORNAL OFICIAL DA UNIÃO EUROPEIA\nO procedimento a que este anúncio diz respeito também é publicitado no Jornal Oficial da União Europeia? Não\n\n3 - AVISO\nModelo de Anúncio: Concurso público\nData de Envio do Anúncio: 05-09-2025\n\n5 - PROCESSO\nTipo de Procedimento: Concurso público\nPreço base do procedimento: Sim\nValor do preço base do procedimento: 110.000,00 EUR\nProcedimento com lotes? Não\n\n6 - OBJETO DO CONTRATO\nNúmero de referência interna: ABS2025-090\nDesignação do contrato: Aquisição de Sulfato de Alumínio Líquido para a ETA de Fagilde - 2026\nDescrição: Aquisição de Sulfato de Alumínio Líquido para a ETA de Fagilde - 2026\nTipo de Contrato Principal: Aquisição de Bens Móveis\nTipo de Contrato: Aquisição de Bens Móveis\nClassificação CPV (Vocabulário Comum para os Contratos Públicos)\nObjeto principal\nVocabulário Principal: 24313123\nPreço base s/IVA: 110.000,00 EUR\n\n7 - INDICAÇÕES ADICIONAIS\nO contrato envolve aquisição conjunta (satisfação de várias entidades)? Não\nO contrato é adjudicado por uma central de compras? Não\n\n8 - TÉCNICAS\nO concurso destina-se à celebração de um acordo-quadro? Inexistência de acordo-quadro\nÉ utilizado um leilão eletrónico? Não\nÉ adotada uma fase de negociação? Não\nSistema de Aquisição Dinâmico: Inexistência de sistema de aquisição dinâmico\n\n9 - LOCAL DA EXECUÇÃO DO CONTRATO\nLOCAL DA EXECUÇÃO DO CONTRATO (PROCEDIMENTO)\nPaís: Portugal\nNUT III: PT16G\nLocalidade: Freguesia de Viseu\nDistrito: Viseu\nConcelho: Viseu\nFreguesia: Freguesia de Viseu\n\n10 - PRAZO DE EXECUÇÃO DO CONTRATO\nPrazo de execução do contrato: 12 MESES\nPrevisão de renovações: Não\n\n11 - FUNDOS EU\nTêm fundos EU? Não\n\n12 - DOCUMENTOS DE HABILITAÇÃO\nHabilitação para o exercício da atividade profissional: Não\n\n13 - CONDIÇÕES DE APRESENTAÇÃO\nPlataforma eletrónica utilizada pela entidade adjudicante: ACIN\nURL para Apresentação: https://www.acingov.pt\nAdmissibilidade da apresentação de propostas variantes: Não autorizado\nPrazo para apresentação das propostas: 22-09-2025 23:59\nPrazo durante o qual os concorrentes são obrigados a manter as respetivas propostas: 120 dias a contar do termo do prazo para a apresentação das propostas\nIndicação de Subcontratação na Proposta: Inexistência de indicação de subcontratação\n\n14 - PRESTAÇÃO DE CAUÇÃO\nPrestação de caução: Não\n\n15 - FORNECIMENTO DAS PEÇAS DO CONCURSO, APRESENTAÇÃO DE PEDIDOS DE PARTICIPAÇÃO E APRESENTAÇÃO DAS PROPOSTAS\nLink para acesso às peças do concurso (URL): https://www.acingov.pt/acingovprod/2/zonaPublica/zona_publica_c/donwloadProcedurePiece/OTcyMzc0\n\n20 - OUTROS REQUISITOS\nInformação sobre contratos reservados. Aplica-se a contratos reservados (54º-A)? Não\n\n21 - CRITÉRIO DE ADJUDICAÇÃO\nMultifator: Não\nMonofator:\nNome: Preço\n\n24 - CONDIÇÕES DO CONTRATO\nFaturação Eletrónica: Permitido\nObrigação de Subcontratação:\nCódigo da Obrigação de Subcontratação: Não é aplicável nenhuma obrigação de subcontratação.\n\n25 - COMPRA PÚBLICA ESTRATÉGICA\nCompra Pública Estratégica: Inexistência de contratação pública estratégica\n\n26 - INFORMAÇÕES ADICIONAIS\nContrato adequado para PME: Sim\nCobertura ACP (Acordo dos Contratos Públicos da Organização Mundial do Comércio): Não\n\n27 - IDENTIFICAÇÃO E CONTACTOS DO ÓRGÃO DE RECURSOS ADMINISTRATIVOS\nDesignação: Serviços Municipalizados de Viseu\nEndereço: Rua Conselheiro Afonso de Melo\nCódigo postal: 3510-024\nLocalidade: Viseu\nTelefone: 00351232470670\nFax: 00351232424080\nEndereço eletrónico: geral@smasviseu.pt\nPrazo de interposição do recurso: 5 dias\n\n28 - IDENTIFICAÇÃO DO(S) AUTOR(ES) DE ANÚNCIO\nNome: João Paulo Lopes Gouveia\nCargo: Vogal do Conselho de Administração\n419490345",
    "nipc": "680020063",
    "distrito": "Viseu",
    "concelho": "Viseu",
    "freguesia": "Freguesia de Viseu",
    "site": "www.smasviseu.pt",
    "email": "geral@smasviseu.pt",
    "designacao_contrato": "Aquisição de Sulfato de Alumínio Líquido para a ETA de Fagilde - 2026",
    "descricao": "Aquisição de Sulfato de Alumínio Líquido para a ETA de Fagilde - 2026",
    "preco_base": "110.000,00 EUR",
    "prazo_execucao": "12 MESES",
    "prazo_apresentacao_propostas": "22-09-2025 23:59",
    "fundos_eu": "Não",
    "plataforma_eletronica": "ACIN",
    "url_procedimento": "https://www.acingov.pt",
    "autor_nome": "João Paulo Lopes Gouveia",
    "autor_cargo": "Vogal do Conselho de Administração"
  }
]