[
  {
    "numero_procedimento": "N/A",
    "entidade": "Município de S. João da Pesqueira",
    "link": "https://diariodarepublica.pt/dr/detalhe/contrato-publico/21004-927729743",
    "detalhes_completos": "1 - IDENTIFICAÇÃO E CONTACTOS DA ENTIDADE ADJUDICANTE\nDesignação da entidade adjudicante: Município de S. João da Pesqueira\nNIPC: 506892646\nServiço/Órgão/Pessoa de contacto: DPOAU\nEndereço: Avenida Marquês de Soveral, n.º 67\nCódigo postal: 5130-321\nLocalidade: S. João da Pesqueira\nPaís: Portugal\nNUT III: PT11D\nDistrito: Viseu\nConcelho: São João da Pesqueira\nFreguesia: União das Freguesias de São João da Pesqueira e Várzea de Trevões\nTelefone: 254489999\nFax: 254489999\nEndereço da Entidade (URL): www.sjpesqueira.pt\nEndereço Eletrónico: cmsjp@sjpesqueira.pt\neDelivery Gateway (URL): https://www.acingov.pt\nFunção da Organização: Adquirente\nNorma jurídica da Entidade Adjudicante: Organismo de direito público\nÁrea de atividade da Autoridade Adjudicante: Serviços públicos das administrações públicas\n\n2 - JORNAL OFICIAL DA UNIÃO EUROPEIA\nO procedimento a que este anúncio diz respeito também é publicitado no Jornal Oficial da União Europeia? Não\n\n3 - AVISO\nModelo de Anúncio: Concurso público\nData de Envio do Anúncio: 04-08-2025\n\n5 - PROCESSO\nTipo de Procedimento: Concurso público\nPreço base do procedimento: Sim\nValor do preço base do procedimento: 255.742,08 EUR\nProcedimento com lotes? Não\n\n6 - OBJETO DO CONTRATO\nNúmero de referência interna: CP/11/2025\nDesignação do contrato: Demolições, movimentos de terras, trabalhos auxiliares, betões, estrutura metálica, lintéis, massame e betonilhas, impermeabilizações, isolamentos térmicos, cobertura, alvenarias, gesso cartonado, pavimentos, revestimentos de paredes, testos falsos, pinturas, caixilharias e fornecimento de mobiliário, serralharias e equipamentos sanitários.\nDescrição: Remodelação do antigo Matadouro Municipal de São João da Pesqueira, para duas frações de habitação.\nTipo de Contrato Principal: Empreitada de Obras Públicas\nTipo de Contrato: Empreitada de Obras Públicas\nClassificação CPV (Vocabulário Comum para os Contratos Públicos)\nObjeto principal\nVocabulário Principal: 45200000\nPreço base s/IVA: 255.742,08 EUR\n\n7 - INDICAÇÕES ADICIONAIS\nO contrato envolve aquisição conjunta (satisfação de várias entidades)? Não\nO contrato é adjudicado por uma central de compras? Não\n\n8 - TÉCNICAS\nO concurso destina-se à celebração de um acordo-quadro? Inexistência de acordo-quadro\nÉ utilizado um leilão eletrónico? Não\nÉ adotada uma fase de negociação? Não\nSistema de Aquisição Dinâmico: Inexistência de sistema de aquisição dinâmico\n\n9 - LOCAL DA EXECUÇÃO DO CONTRATO\nLOCAL DA EXECUÇÃO DO CONTRATO (PROCEDIMENTO)\nPaís: Portugal\nNUT III: PT11D\nLocalidade: União das Freguesias de São João da Pesqueira e Várzea de Trevões\nDistrito: Viseu\nConcelho: São João da Pesqueira\nFreguesia: União das Freguesias de São João da Pesqueira e Várzea de Trevões\n\n10 - PRAZO DE EXECUÇÃO DO CONTRATO\nPrazo de execução do contrato: 270 DIAS\nPrevisão de renovações: Não\n\n11 - FUNDOS EU\nTêm fundos EU? Sim\n\n12 - DOCUMENTOS DE HABILITAÇÃO\nHabilitação para o exercício da atividade profissional: Sim\nTipo: Alvará\nDescrição: 1ª categoria (Edifícios e Património Construído), da qual deve ser da classe corresponde ao valor dos trabalhos a que respeita, a proposta; e a 1. ª subcategoria da 1.ª categoria, (Estruturas e elementos de betão), da qual deve ser da classe que cubra o valor global dos trabalhos; 1.ª subcategoria da 4.ª categoria, (Instalações elétricas de utilização de baixa tensão), da qual deve ser da classe que cubra o valor global dos trabalhos; e a 7.ª subcategoria da 4.ª categoria, (Infraestruturas de telecomunicações), da qual deve ser da classe que cubra o valor global dos trabalhos; e a 10.ª subcategoria da 4.ª categoria, (Aquecimento, ventilação, ar condicionado e refrigeração), da qual deve ser da classe que cubra o valor global dos trabalhos.\n\n13 - CONDIÇÕES DE APRESENTAÇÃO\nPlataforma eletrónica utilizada pela entidade adjudicante: ACIN\nURL para Apresentação: https://www.acingov.pt\nAdmissibilidade da apresentação de propostas variantes: Não autorizado\nPrazo para apresentação das propostas: 14-08-2025 23:59\nPrazo durante o qual os concorrentes são obrigados a manter as respetivas propostas: 90 dias a contar do termo do prazo para a apresentação das propostas\nIndicação de Subcontratação na Proposta: Inexistência de indicação de subcontratação\n\n14 - PRESTAÇÃO DE CAUÇÃO\nPrestação de caução: Não\n\n15 - FORNECIMENTO DAS PEÇAS DO CONCURSO, APRESENTAÇÃO DE PEDIDOS DE PARTICIPAÇÃO E APRESENTAÇÃO DAS PROPOSTAS\nLink para acesso às peças do concurso (URL): https://www.acingov.pt/acingovprod/2/zonaPublica/zona_publica_c/donwloadProcedurePiece/OTMxMjgw\n\n20 - OUTROS REQUISITOS\nInformação sobre contratos reservados. Aplica-se a contratos reservados (54º-A)? Não\n\n21 - CRITÉRIO DE ADJUDICAÇÃO\nMultifator: Não\nMonofator:\nNome: Preço\n\n24 - CONDIÇÕES DO CONTRATO\nFaturação Eletrónica: Permitido\nObrigação de Subcontratação:\nCódigo da Obrigação de Subcontratação: Não é aplicável nenhuma obrigação de subcontratação.\n\n25 - COMPRA PÚBLICA ESTRATÉGICA\nCompra Pública Estratégica: Inexistência de contratação pública estratégica\n\n26 - INFORMAÇÕES ADICIONAIS\nContrato adequado para PME: Sim\nCobertura ACP (Acordo dos Contratos Públicos da Organização Mundial do Comércio): Não\n\n27 - IDENTIFICAÇÃO E CONTACTOS DO ÓRGÃO DE RECURSOS ADMINISTRATIVOS\nDesignação: Câmara Municipal\nEndereço: Avenida Marquês de Soveral, n.º 67\nCódigo postal: 5130-321\nLocalidade: S. João da Pesqueira\nTelefone: 254489999\nFax: 254489999\nEndereço eletrónico: cmsjp@sjpesqueira.pt\nPrazo de interposição do recurso: 5 dias\n\n28 - IDENTIFICAÇÃO DO(S) AUTOR(ES) DE ANÚNCIO\nNome: Manuel António Natário Cordeiro\nCargo: Presidente\n419395876",
    "nipc": "506892646",
    "distrito": "Viseu",
    "concelho": "São João da Pesqueira",
    "freguesia": "União das Freguesias de São João da Pesqueira e Várzea de Trevões",
    "site": "www.sjpesqueira.pt",
    "email": "cmsjp@sjpesqueira.pt",
    "designacao_contrato": "Demolições, movimentos de terras, trabalhos auxiliares, betões, estrutura metálica, lintéis, massame e betonilhas, impermeabilizações, isolamentos térmicos, cobertura, alvenarias, gesso cartonado, pavimentos, revestimentos de paredes, testos falsos, pinturas, caixilharias e fornecimento de mobiliário, serralharias e equipamentos sanitários.",
    "descricao": "Remodelação do antigo Matadouro Municipal de São João da Pesqueira, para duas frações de habitação.",
    "preco_base": "255.742,08 EUR",
    "prazo_execucao": "270 DIAS",
    "prazo_apresentacao_propostas": "14-08-2025 23:59",
    "fundos_eu": "Sim",
    "plataforma_eletronica": "ACIN",
    "url_procedimento": "https://www.acingov.pt",
    "autor_nome": "Manuel António Natário Cordeiro",
    "autor_cargo": "Presidente"
  },
  {
    "numero_procedimento": "N/A",
    "entidade": "Infraestruturas de Portugal",
    "link": "https://diariodarepublica.pt/dr/detalhe/contrato-publico/21005-927729744",
    "detalhes_completos": "1 - IDENTIFICAÇÃO E CONTACTOS DA ENTIDADE ADJUDICANTE\nDesignação da entidade adjudicante: Infraestruturas de Portugal\nNIPC: 503933813\nServiço/Órgão/Pessoa de contacto: Direção de Compras e Logística - Departamento de Compras - Edifício 2\nEndereço: Praça da Portagem\nCódigo postal: 2809-013\nLocalidade: Almada\nPaís: Portugal\nNUT III: PT170\nDistrito: Setúbal\nConcelho: Almada\nFreguesia: União das Freguesias de Almada, Cova da Piedade, Pragal e Cacilhas\nTelefone:  212 879 300 \nFax: 21 287 90 00\nEndereço da Entidade (URL): www.infraestruturasdeportugal.pt\nEndereço Eletrónico: dcl@infraestruturasdeportugal.pt\nFunção da Organização: Adquirente\nNorma jurídica da Entidade Adjudicante: Organismo de direito público\nÁrea de atividade da Entidade Adjudicante: Serviços ferroviários\n\n2 - JORNAL OFICIAL DA UNIÃO EUROPEIA\nO procedimento a que este anúncio diz respeito também é publicitado no Jornal Oficial da União Europeia? Não\n\n3 - AVISO\nModelo de Anúncio: Concurso público\nData de Envio do Anúncio: 04-08-2025\n\n5 - PROCESSO\nTipo de Procedimento: Concurso público\nPreço base do procedimento: Sim\nValor do preço base do procedimento: 400.000,00 EUR\nProcedimento com lotes? Não\n\n6 - OBJETO DO CONTRATO\nNúmero de referência interna: 10019059\nDesignação do contrato: Empreitada - EN106 - PASSAGEM HIDRÁULICA (KM 17+950) - REABILITAÇÃO E REFORÇO DA OBRA DE ARTE\nDescrição:  EN106 - PASSAGEM HIDRÁULICA (KM 17+950) - REABILITAÇÃO E REFORÇO DA OBRA DE ARTE\nTipo de Contrato Principal: Empreitada de Obras Públicas\nTipo de Contrato: Empreitada de Obras Públicas\nClassificação CPV (Vocabulário Comum para os Contratos Públicos)\nObjeto principal\nVocabulário Principal: 45221119\nPreço base s/IVA: 400.000,00 EUR\n\n7 - INDICAÇÕES ADICIONAIS\nO contrato envolve aquisição conjunta (satisfação de várias entidades)? Não\nO contrato é adjudicado por uma central de compras? Não\n\n8 - TÉCNICAS\nO concurso destina-se à celebração de um acordo-quadro? Inexistência de acordo-quadro\nÉ utilizado um leilão eletrónico? Não\nÉ adotada uma fase de negociação? Não\nSistema de Aquisição Dinâmico: Inexistência de sistema de aquisição dinâmico\n\n9 - LOCAL DA EXECUÇÃO DO CONTRATO\nLOCAL DA EXECUÇÃO DO CONTRATO (PROCEDIMENTO)\nPaís: Portugal\nNUT III: PT11C\nLocalidade: UF de Cristelos, Boim e Ordem\nDistrito: Porto\nConcelho: Lousada\nFreguesia: União das Freguesias de Cristelos, Boim e Ordem\n\n10 - PRAZO DE EXECUÇÃO DO CONTRATO\nPrazo de execução do contrato: 150 DIAS\nPrevisão de renovações: Não\n\n11 - FUNDOS EU\nTêm fundos EU? Não\n\n12 - DOCUMENTOS DE HABILITAÇÃO\nHabilitação para o exercício da atividade profissional: Sim\nTipo: Alvará\nDescrição: Alvará de construção a apresentar pelo adjudicatário, emitido pelo Instituto dos Mercados Públicos, do Imobiliário e da Construção, I.P.: 1.ª Subcategoria da 2.ª Categoria e da classe que cubra o valor global da proposta; 5.ª Subcategoria da 2.ª Categoria deve cobrir o valor dos trabalhos correspondentes\n\n13 - CONDIÇÕES DE APRESENTAÇÃO\nPlataforma eletrónica utilizada pela entidade adjudicante: ANOGOV\nURL para Apresentação: https://www.anogov.com/infraestruturasdeportugal-ip/faces/\nAdmissibilidade da apresentação de propostas variantes: Não autorizado\nPrazo para apresentação das propostas: 28-08-2025 17:00\nPrazo durante o qual os concorrentes são obrigados a manter as respetivas propostas: 120 dias a contar do termo do prazo para a apresentação das propostas\nApresentação de Catálogo Eletrónico: Não autorizado\nIndicação de Subcontratação na Proposta: Inexistência de indicação de subcontratação\n\n14 - PRESTAÇÃO DE CAUÇÃO\nPrestação de caução: Sim\nPercentagem: 5%\nDescrição da Garantia Exigida: 5% do preço contratual\n\n15 - FORNECIMENTO DAS PEÇAS DO CONCURSO, APRESENTAÇÃO DE PEDIDOS DE PARTICIPAÇÃO E APRESENTAÇÃO DAS PROPOSTAS\nLink para acesso às peças do concurso (URL): https://www.anogov.com/infraestruturasdeportugal-ip/faces/app/acessoDocs.jsp?codigoAcesso=q6PEoARDQrW0GnjYMSnUl5IOMu9ijCY0ybMflHB6P5BaarBRDv\n\n20 - OUTROS REQUISITOS\nInformação sobre contratos reservados. Aplica-se a contratos reservados (54º-A)? Não\n\n21 - CRITÉRIO DE ADJUDICAÇÃO\nMultifator: Sim\nFator: \nNome: Preço\nPonderação: 80%\nSubfatores: Não\nFator: \nNome: Qualidade\nPonderação: 20%\nSubfatores: SimSubfatores: \nNome: Memória descritiva e justificativa\nPonderação : 30%; \nNome: Programa de trabalhos\nPonderação : 60%; \nNome: Cronograma Financeiro\nPonderação : 10%; \n\n24 - CONDIÇÕES DO CONTRATO\nFaturação Eletrónica: Permitido\nObrigação de Subcontratação:\nCódigo da Obrigação de Subcontratação: Não é aplicável nenhuma obrigação de subcontratação.\n\n25 - COMPRA PÚBLICA ESTRATÉGICA\nCompra Pública Estratégica: Redução dos impactos ambientais\nDescrição do Processo de Adjudicação Estratégico: De acordo com as peças de concurso\nCritérios de contratos Públicos Ecológicos: Critérios de contratação pública ecológica nacional\nCategorias da estratégia nacional: Conceção, construção, reabilitação e conservação de estradas\nDiretiva Veículos Não Poluentes: Não\nCritério de Acessibilidade: Os critérios de acessibilidade para as pessoas com deficiência não estão incluídos porque o contrato não se destina a pessoas singulares\n\n26 - INFORMAÇÕES ADICIONAIS\nContrato adequado para PME: Sim\nCobertura ACP (Acordo dos Contratos Públicos da Organização Mundial do Comércio): Não\n\n27 - IDENTIFICAÇÃO E CONTACTOS DO ÓRGÃO DE RECURSOS ADMINISTRATIVOS\nDesignação: Conselho de Administração da Infraestruturas de Portugal, S.A.\nEndereço: Praça da Portagem\nCódigo postal: 2809-013\nLocalidade: Almada\nEndereço eletrónico: contratos@infraestruturasdeportugal.pt\n\n28 - IDENTIFICAÇÃO DO(S) AUTOR(ES) DE ANÚNCIO\nNome: Margarida Veloso\nCargo: Diretora Adjunta de Compras e Logística (em acumulação Dir. Departamento de Compras)\n419394911",
    "nipc": "503933813",
    "distrito": "Setúbal",
    "concelho": "Almada",
    "freguesia": "União das Freguesias de Almada, Cova da Piedade, Pragal e Cacilhas",
    "site": "www.infraestruturasdeportugal.pt",
    "email": "dcl@infraestruturasdeportugal.pt",
    "designacao_contrato": "Empreitada - EN106 - PASSAGEM HIDRÁULICA (KM 17+950) - REABILITAÇÃO E REFORÇO DA OBRA DE ARTE",
    "descricao": "EN106 - PASSAGEM HIDRÁULICA (KM 17+950) - REABILITAÇÃO E REFORÇO DA OBRA DE ARTE",
    "preco_base": "400.000,00 EUR",
    "prazo_execucao": "150 DIAS",
    "prazo_apresentacao_propostas": "28-08-2025 17:00",
    "fundos_eu": "Não",
    "plataforma_eletronica": "ANOGOV",
    "url_procedimento": "https://www.anogov.com/infraestruturasdeportugal-ip/faces/",
    "autor_nome": "Margarida Veloso",
    "autor_cargo": "Diretora Adjunta de Compras e Logística (em acumulação Dir. Departamento de Compras)"
  },
  {
    "numero_procedimento": "N/A",
    "entidade": "Unidade Local de Saúde do Baixo Alentejo, E.P.E.",
    "link": "https://diariodarepublica.pt/dr/detalhe/contrato-publico/21006-927729745",
    "detalhes_completos": "1 - IDENTIFICAÇÃO E CONTACTOS DA ENTIDADE ADJUDICANTE\nDesignação da entidade adjudicante: Unidade Local de Saúde do Baixo Alentejo, E.P.E.\nNIPC: 508754275\nEndereço: Rua Dr. António Fernando Covas Lima\nCódigo postal: 7801-849\nLocalidade: Beja\nPaís: Portugal\nNUT III: PT184\nDistrito: Beja\nConcelho: Beja\nFreguesia: União das Freguesias de Beja (Santiago Maior e São João Baptista)\nTelefone: 284310201\nFax: 284310201\nEndereço da Entidade (URL): www.ulsba.min-saude.pt\nEndereço Eletrónico: concursos@ulsba.min-saude.pt\neDelivery Gateway (URL): https://community.vortal.biz/public/\nFunção da Organização: Adquirente\nNorma jurídica da Entidade Adjudicante: Organismo de direito público\nÁrea de atividade da Autoridade Adjudicante: Saúde\n\n2 - JORNAL OFICIAL DA UNIÃO EUROPEIA\nO procedimento a que este anúncio diz respeito também é publicitado no Jornal Oficial da União Europeia? Não\n\n3 - AVISO\nModelo de Anúncio: Concurso público\nData de Envio do Anúncio: 04-08-2025\n\n5 - PROCESSO\nTipo de Procedimento: Concurso público\nPreço base do procedimento: Sim\nValor do preço base do procedimento: 30.600,00 EUR\nProcedimento com lotes? Não\n\n6 - OBJETO DO CONTRATO\nNúmero de referência interna: 92001825\nDesignação do contrato: FIBRAS DE LASER DíODO COM FORNECIMENTOS DE EQUIPAMENTO\nDescrição: AQUISIÇÃO DE FIBRAS DE LASER DíODO COM FORNECIMENTOS DE EQUIPAMENTO\nTipo de Contrato Principal: Aquisição de Bens Móveis\nTipo de Contrato: Aquisição de Bens Móveis\nClassificação CPV (Vocabulário Comum para os Contratos Públicos)\nObjeto principal\nVocabulário Principal: 33100000\nPreço base s/IVA: 30.600,00 EUR\n\n7 - INDICAÇÕES ADICIONAIS\nO contrato envolve aquisição conjunta (satisfação de várias entidades)? Não\nO contrato é adjudicado por uma central de compras? Não\n\n8 - TÉCNICAS\nO concurso destina-se à celebração de um acordo-quadro? Inexistência de acordo-quadro\nÉ utilizado um leilão eletrónico? Não\nÉ adotada uma fase de negociação? Não\nSistema de Aquisição Dinâmico: Inexistência de sistema de aquisição dinâmico\n\n9 - LOCAL DA EXECUÇÃO DO CONTRATO\nLOCAL DA EXECUÇÃO DO CONTRATO (PROCEDIMENTO)\nPaís: Portugal\nNUT III: PT184\nLocalidade: Beja\nDistrito: Beja\nConcelho: Beja\nFreguesia: União das Freguesias de Beja (Santiago Maior e São João Baptista)\n\n10 - PRAZO DE EXECUÇÃO DO CONTRATO\nPrazo de execução do contrato: 5 MESES\nPrevisão de renovações: Não\n\n11 - FUNDOS EU\nTêm fundos EU? Não\n\n12 - DOCUMENTOS DE HABILITAÇÃO\nHabilitação para o exercício da atividade profissional: Não\n\n13 - CONDIÇÕES DE APRESENTAÇÃO\nPlataforma eletrónica utilizada pela entidade adjudicante: VORTAL\nURL para Apresentação: https://community.vortal.biz/public/\nAdmissibilidade da apresentação de propostas variantes: Não autorizado\nPrazo para apresentação das propostas: 13-08-2025 23:00\nPrazo durante o qual os concorrentes são obrigados a manter as respetivas propostas: 90 dias a contar do termo do prazo para a apresentação das propostas\nIndicação de Subcontratação na Proposta: Inexistência de indicação de subcontratação\n\n14 - PRESTAÇÃO DE CAUÇÃO\nPrestação de caução: Não\n\n15 - FORNECIMENTO DAS PEÇAS DO CONCURSO, APRESENTAÇÃO DE PEDIDOS DE PARTICIPAÇÃO E APRESENTAÇÃO DAS PROPOSTAS\nLink para acesso às peças do concurso (URL): https://community.vortal.biz/Public/public-tender-documents/U09hMGtyQkpiYXVUODNYK1MyWnhMSjJRcy9EL2dRS1VlLy9pZnExUWd6LzZ5aHQ0RmYxSDdMMzZtRVFJWHJDQXlkY1ptZUl3cnM4U001LzBReVdmZUE9PSMqUWRR\n\n20 - OUTROS REQUISITOS\nInformação sobre contratos reservados. Aplica-se a contratos reservados (54º-A)? Não\n\n21 - CRITÉRIO DE ADJUDICAÇÃO\nMultifator: Não\nMonofator:\nNome: Preço\n\n24 - CONDIÇÕES DO CONTRATO\nFaturação Eletrónica: Permitido\nObrigação de Subcontratação:\nCódigo da Obrigação de Subcontratação: Não é aplicável nenhuma obrigação de subcontratação.\n\n25 - COMPRA PÚBLICA ESTRATÉGICA\nCompra Pública Estratégica: Inexistência de contratação pública estratégica\n\n26 - INFORMAÇÕES ADICIONAIS\nContrato adequado para PME: Sim\nCobertura ACP (Acordo dos Contratos Públicos da Organização Mundial do Comércio): Não\n\n27 - IDENTIFICAÇÃO E CONTACTOS DO ÓRGÃO DE RECURSOS ADMINISTRATIVOS\nDesignação: Unidade Local de Saúde do Baixo Alentejo\nEndereço: R. Dr. Antonio Fernando Covas Lima\nCódigo postal: 7801-849\nLocalidade: Beja\nTelefone: +351 284310200\nFax: +351 284310200\nEndereço eletrónico: ca@ulsba.min-saude.pt\n\n28 - IDENTIFICAÇÃO DO(S) AUTOR(ES) DE ANÚNCIO\nNome: Helena Isabel Graça\nCargo: Diretora do Serviço de Aprovisionamento e Logistica\n419395795",
    "nipc": "508754275",
    "distrito": "Beja",
    "concelho": "Beja",
    "freguesia": "União das Freguesias de Beja (Santiago Maior e São João Baptista)",
    "site": "www.ulsba.min-saude.pt",
    "email": "concursos@ulsba.min-saude.pt",
    "designacao_contrato": "FIBRAS DE LASER DíODO COM FORNECIMENTOS DE EQUIPAMENTO",
    "descricao": "AQUISIÇÃO DE FIBRAS DE LASER DíODO COM FORNECIMENTOS DE EQUIPAMENTO",
    "preco_base": "30.600,00 EUR",
    "prazo_execucao": "5 MESES",
    "prazo_apresentacao_propostas": "13-08-2025 23:00",
    "fundos_eu": "Não",
    "plataforma_eletronica": "VORTAL",
    "url_procedimento": "https://community.vortal.biz/public/",
    "autor_nome": "Helena Isabel Graça",
    "autor_cargo": "Diretora do Serviço de Aprovisionamento e Logistica"
  },
  {
    "numero_procedimento": "N/A",
    "entidade": "Serviços Municipalizados de Água e Saneamento de Almada",
    "link": "https://diariodarepublica.pt/dr/detalhe/contrato-publico/21007-927729746",
    "detalhes_completos": "1 - IDENTIFICAÇÃO E CONTACTOS DA ENTIDADE ADJUDICANTE\nDesignação da entidade adjudicante: Serviços Municipalizados de Água e Saneamento de Almada\nNIPC: 680017763\nEndereço: Praceta Ricardo Jorge, n.º2 Pragal\nCódigo postal: 2804-543\nLocalidade: Setúbal\nPaís: Portugal\nNUT III: PT170\nDistrito: Setúbal\nConcelho: Almada\nFreguesia: Todas\nTelefone: 212726000\nFax: 212721629\nEndereço da Entidade (URL): www.smasalmada.pt\nEndereço Eletrónico: geral@smasalmada.pt\neDelivery Gateway (URL): https://community.vortal.biz/public/\nFunção da Organização: Adquirente\nNorma jurídica da Entidade Adjudicante: Organismo de direito público, controlado por uma autoridade local\nÁrea de atividade da Autoridade Adjudicante: Serviços públicos das administrações públicas\n\n2 - JORNAL OFICIAL DA UNIÃO EUROPEIA\nO procedimento a que este anúncio diz respeito também é publicitado no Jornal Oficial da União Europeia? Não\n\n3 - AVISO\nModelo de Anúncio: Concurso público\nData de Envio do Anúncio: 04-08-2025\n\n5 - PROCESSO\nTipo de Procedimento: Concurso público\nPreço base do procedimento: Sim\nValor do preço base do procedimento: 145.000,00 EUR\nProcedimento com lotes? Não\n\n6 - OBJETO DO CONTRATO\nNúmero de referência interna: PCP/29/2025/EOP/DO\nDesignação do contrato: Procedimento nº PCP/29/2025/EOP/DO - Construção de Redes de Drenagem na Rua Quinta do Bico e Outras em Almada\nDescrição: Construção de Redes de Drenagem na Rua Quinta do Bico e Outras em Almada\nTipo de Contrato Principal: Empreitada de Obras Públicas\nTipo de Contrato: Empreitada de Obras Públicas\nClassificação CPV (Vocabulário Comum para os Contratos Públicos)\nObjeto principal\nVocabulário Principal: 45231300\nPreço base s/IVA: 145.000,00 EUR\n\n7 - INDICAÇÕES ADICIONAIS\nO contrato envolve aquisição conjunta (satisfação de várias entidades)? Não\nO contrato é adjudicado por uma central de compras? Não\n\n8 - TÉCNICAS\nO concurso destina-se à celebração de um acordo-quadro? Inexistência de acordo-quadro\nÉ utilizado um leilão eletrónico? Não\nÉ adotada uma fase de negociação? Não\nSistema de Aquisição Dinâmico: Inexistência de sistema de aquisição dinâmico\n\n9 - LOCAL DA EXECUÇÃO DO CONTRATO\nLOCAL DA EXECUÇÃO DO CONTRATO (PROCEDIMENTO)\nPaís: Portugal\nNUT III: PT170\nLocalidade: Setúbal\nDistrito: Setúbal\nConcelho: Almada\nFreguesia: Todas\n\n10 - PRAZO DE EXECUÇÃO DO CONTRATO\nPrazo de execução do contrato: 120 DIAS\nPrevisão de renovações: Não\n\n11 - FUNDOS EU\nTêm fundos EU? Não\n\n12 - DOCUMENTOS DE HABILITAÇÃO\nHabilitação para o exercício da atividade profissional: Sim\nTipo: Alvará\nDescrição: Alvará contendo as seguintes habilitações: 6.ª Subcategoria da 2.ª Categoria, e Classe correspondente ao Valor da Proposta.\n13 - CONDIÇÕES DE APRESENTAÇÃO\nPlataforma eletrónica utilizada pela entidade adjudicante: VORTAL\nURL para Apresentação: https://community.vortal.biz/public/\nAdmissibilidade da apresentação de propostas variantes: Não autorizado\nPrazo para apresentação das propostas: 21-08-2025 23:59\nPrazo durante o qual os concorrentes são obrigados a manter as respetivas propostas: 66 dias a contar do termo do prazo para a apresentação das propostas\nIndicação de Subcontratação na Proposta: Inexistência de indicação de subcontratação\n\n14 - PRESTAÇÃO DE CAUÇÃO\nPrestação de caução: Sim\nPercentagem: 5%\nDescrição da Garantia Exigida: Prestada nos termos dos anexos V, VI e VII do programa de procedimento.\n\n15 - FORNECIMENTO DAS PEÇAS DO CONCURSO, APRESENTAÇÃO DE PEDIDOS DE PARTICIPAÇÃO E APRESENTAÇÃO DAS PROPOSTAS\nLink para acesso às peças do concurso (URL): https://community.vortal.biz/Public/public-tender-documents/bGZaNmVoaDd6cTJkUENGb2VjSkxsajEzeTNadW5MVThzMS8zQ2hLTjlYcnZ5V2d3dWpvdWJDa2NONS9NcXVoVmZTWlV5dHk1eWpIWkNQazVZMHRyMXc9PTNTV3Jk\n\n20 - OUTROS REQUISITOS\nInformação sobre contratos reservados. Aplica-se a contratos reservados (54º-A)? Não\n\n21 - CRITÉRIO DE ADJUDICAÇÃO\nMultifator: Não\nMonofator:\nNome: Outros\nOutro nome: Preço\n\n24 - CONDIÇÕES DO CONTRATO\nFaturação Eletrónica: Permitido\nObrigação de Subcontratação:\nCódigo da Obrigação de Subcontratação: Não é aplicável nenhuma obrigação de subcontratação.\n\n25 - COMPRA PÚBLICA ESTRATÉGICA\nCompra Pública Estratégica: Inexistência de contratação pública estratégica\n\n26 - INFORMAÇÕES ADICIONAIS\nContrato adequado para PME: Sim\nCobertura ACP (Acordo dos Contratos Públicos da Organização Mundial do Comércio): Não\n\n27 - IDENTIFICAÇÃO E CONTACTOS DO ÓRGÃO DE RECURSOS ADMINISTRATIVOS\nDesignação: Município de Almada - Câmara Municipal de Almada, Presidência\nEndereço: Largo Luís de Camões\nCódigo postal: 2800-513\nLocalidade: Almada\nTelefone: +351 212724500\nFax: +351 212744545\nEndereço eletrónico: gab.presidencia@cma.m-almada.pt\n\n28 - IDENTIFICAÇÃO DO(S) AUTOR(ES) DE ANÚNCIO\nNome: José Pedro Ribeiro\nCargo: Presidente do Conselho de Administração dos SMAS Almada\n419390545",
    "nipc": "680017763",
    "distrito": "Setúbal",
    "concelho": "Almada",
    "freguesia": "Todas",
    "site": "www.smasalmada.pt",
    "email": "geral@smasalmada.pt",
    "designacao_contrato": "Procedimento nº PCP/29/2025/EOP/DO - Construção de Redes de Drenagem na Rua Quinta do Bico e Outras em Almada",
    "descricao": "Construção de Redes de Drenagem na Rua Quinta do Bico e Outras em Almada",
    "preco_base": "145.000,00 EUR",
    "prazo_execucao": "120 DIAS",
    "prazo_apresentacao_propostas": "21-08-2025 23:59",
    "fundos_eu": "Não",
    "plataforma_eletronica": "VORTAL",
    "url_procedimento": "https://community.vortal.biz/public/",
    "autor_nome": "José Pedro Ribeiro",
    "autor_cargo": "Presidente do Conselho de Administração dos SMAS Almada"
  },
  {
    "numero_procedimento": "N/A",
    "entidade": "Municipio de Ourém",
    "link": "https://diariodarepublica.pt/dr/detalhe/contrato-publico/21008-927729747",
    "detalhes_completos": "1 - IDENTIFICAÇÃO E CONTACTOS DA ENTIDADE ADJUDICANTE\nDesignação da entidade adjudicante: Municipio de Ourém\nNIPC: 501280740\nServiço/Órgão/Pessoa de contacto: Serviço de Contratação Pública e Aprovisionamento\nEndereço: Praça D. Maria II, nº 1\nCódigo postal: 2490-499\nLocalidade: Ourém\nPaís: Portugal\nNUT III: PT16I\nDistrito: Santarém\nConcelho: Ourém\nFreguesia: Freguesia de Fátima\nTelefone: 249540900\nFax: 249540908\nEndereço da Entidade (URL): www.ourem.pt\nEndereço Eletrónico: eva.reis@mail.cm-ourem.pt\neDelivery Gateway (URL): https://www.acingov.pt\nFunção da Organização: Adquirente\nNorma jurídica da Entidade Adjudicante: Autoridade local\nÁrea de atividade da Autoridade Adjudicante: Serviços públicos das administrações públicas\n\n2 - JORNAL OFICIAL DA UNIÃO EUROPEIA\nO procedimento a que este anúncio diz respeito também é publicitado no Jornal Oficial da União Europeia? Não\n\n3 - AVISO\nModelo de Anúncio: Concurso público\nData de Envio do Anúncio: 04-08-2025\n\n5 - PROCESSO\nTipo de Procedimento: Concurso público\nPreço base do procedimento: Sim\nValor do preço base do procedimento: 91.892,20 EUR\nProcedimento com lotes? Sim\nNº Máx. de Lotes Autorizado: 2\nNúmero máximo de lotes que podem ser adjudicados a um concorrente: 2\n\n6 - OBJETO DO CONTRATO\nNúmero de referência interna: P203/2025\nDesignação do contrato: P203/2025 - Aquisição de Equipamento Médico (Lote 1) e Mobiliário (Lote 2) para a Unidade de Saúde de Fátima (MGD 69900/2025)\nDescrição: P203/2025 - Aquisição de Equipamento Médico (Lote 1) e Mobiliário (Lote 2) para a Unidade de Saúde de Fátima (MGD 69900/2025)\n\nTipo de Contrato Principal: Aquisição de Bens Móveis\nTipo de Contrato: Aquisição de Bens Móveis\nClassificação CPV (Vocabulário Comum para os Contratos Públicos)\nObjeto principal\nVocabulário Principal: 33190000\nPreço base s/IVA: 91.892,20 EUR\nLotes: \nNº: LOT-0001\nDescrição do Lote: Lote 1 - Equipamento Médico\nPreço base s/IVA: 53.209,00 EUR\nClassificação CPV (Vocabulário Comum para os Contratos Públicos)\nObjeto principal\nVocabulário Principal: 33190000\nNº: LOT-0002\nDescrição do Lote: Lote 2 - Mobiliário\nPreço base s/IVA: 38.683,20 EUR\nClassificação CPV (Vocabulário Comum para os Contratos Públicos)\nObjeto principal\nVocabulário Principal: 33190000\n\n7 - INDICAÇÕES ADICIONAIS\nO contrato envolve aquisição conjunta (satisfação de várias entidades)? Não\nO contrato é adjudicado por uma central de compras? Não\n\n8 - TÉCNICAS\nO concurso destina-se à celebração de um acordo-quadro? Inexistência de acordo-quadro\nÉ utilizado um leilão eletrónico? Não\nÉ adotada uma fase de negociação? Não\nSistema de Aquisição Dinâmico: Inexistência de sistema de aquisição dinâmico\n\n9 - LOCAL DA EXECUÇÃO DO CONTRATO\nLOCAL DA EXECUÇÃO DO CONTRATO (PROCEDIMENTO)\nPaís: Portugal\nNUT III: PT16I\nLocalidade: Freguesia de Fátima\nDistrito: Santarém\nConcelho: Ourém\nFreguesia: Freguesia de Fátima\nLOCAL DA EXECUÇÃO DO CONTRATO (LOTE)\nIdentificador do Lote: LOT-0001; LOT-0002\nPaís: Portugal\nNUT III: PT16I\nLocalidade: Freguesia de Fátima\nDistrito: Santarém\nConcelho: Ourém\nFreguesia: Freguesia de Fátima\n\n10 - PRAZO DE EXECUÇÃO DO CONTRATO\nIdentificador do Lote: LOT-0001; LOT-0002\nPrazo de execução do contrato: 90 DIAS\nPrevisão de renovações: Não\n\n11 - FUNDOS EU\nIdentificador do Lote: LOT-0001; LOT-0002\nTêm fundos EU? Sim\n\n12 - DOCUMENTOS DE HABILITAÇÃO\nHabilitação para o exercício da atividade profissional: Sim\nTipo: Outros\nDescrição - Outros: Documentos de Habilitação\nDescrição: Documentos de Habilitação\n\n13 - CONDIÇÕES DE APRESENTAÇÃO\nPlataforma eletrónica utilizada pela entidade adjudicante: ACIN\nURL para Apresentação: https://www.acingov.pt\nAdmissibilidade da apresentação de propostas variantes: Não autorizado\nPrazo para apresentação das propostas: 22-08-2025 23:59\nPrazo durante o qual os concorrentes são obrigados a manter as respetivas propostas: 150 dias a contar do termo do prazo para a apresentação das propostas\nIndicação de Subcontratação na Proposta: Inexistência de indicação de subcontratação\n\n14 - PRESTAÇÃO DE CAUÇÃO\nPrestação de caução: Sim\nPercentagem: 5%\nDescrição da Garantia Exigida: O valor da caução é de 5.00% do preço contratual.\n\n15 - FORNECIMENTO DAS PEÇAS DO CONCURSO, APRESENTAÇÃO DE PEDIDOS DE PARTICIPAÇÃO E APRESENTAÇÃO DAS PROPOSTAS\nLink para acesso às peças do concurso (URL): https://www.acingov.pt/acingovprod/2/zonaPublica/zona_publica_c/donwloadProcedurePiece/OTMwOTEw\n\n20 - OUTROS REQUISITOS\nIdentificador do Lote: LOT-0001; LOT-0002\nInformação sobre contratos reservados. Aplica-se a contratos reservados (54º-A)? Não\n\n21 - CRITÉRIO DE ADJUDICAÇÃO\nO Critério de adjudicação é diferenciado por lote? Não\nMultifator: Não\nMonofator:\nNome: Preço\n\n24 - CONDIÇÕES DO CONTRATO\nIdentificador do Lote: LOT-0001; LOT-0002\nFaturação Eletrónica: Permitido\nObrigação de Subcontratação:\nCódigo da Obrigação de Subcontratação: Não é aplicável nenhuma obrigação de subcontratação.\n\n25 - COMPRA PÚBLICA ESTRATÉGICA\nCompra Pública Estratégica: Inexistência de contratação pública estratégica\n\n26 - INFORMAÇÕES ADICIONAIS\nIdentificador do Lote: LOT-0001; LOT-0002\nContrato adequado para PME: Sim\nCobertura ACP (Acordo dos Contratos Públicos da Organização Mundial do Comércio): Não\n\n27 - IDENTIFICAÇÃO E CONTACTOS DO ÓRGÃO DE RECURSOS ADMINISTRATIVOS\nDesignação: Municipio de Ourém\nEndereço: Praça D. Maria II, nº 1\nCódigo postal: 2490-499\nLocalidade: Ourém\nTelefone: 249540900\nFax: 249540908\nEndereço eletrónico: geral@mail.cm-ourem.pt\nPrazo de interposição do recurso: 5 dias\n\n28 - IDENTIFICAÇÃO DO(S) AUTOR(ES) DE ANÚNCIO\nNome: Luís Miguel Albuquerque\nCargo: Presidente da Câmara\n419392019",
    "nipc": "501280740",
    "distrito": "Santarém",
    "concelho": "Ourém",
    "freguesia": "Freguesia de Fátima",
    "site": "www.ourem.pt",
    "email": "eva.reis@mail.cm-ourem.pt",
    "designacao_contrato": "P203/2025 - Aquisição de Equipamento Médico (Lote 1) e Mobiliário (Lote 2) para a Unidade de Saúde de Fátima (MGD 69900/2025)",
    "descricao": "P203/2025 - Aquisição de Equipamento Médico (Lote 1) e Mobiliário (Lote 2) para a Unidade de Saúde de Fátima (MGD 69900/2025)",
    "preco_base": "91.892,20 EUR",
    "prazo_execucao": "90 DIAS",
    "prazo_apresentacao_propostas": "22-08-2025 23:59",
    "fundos_eu": "Sim",
    "plataforma_eletronica": "ACIN",
    "url_procedimento": "https://www.acingov.pt",
    "autor_nome": "Luís Miguel Albuquerque",
    "autor_cargo": "Presidente da Câmara"
  },
  {
    "numero_procedimento": "N/A",
    "entidade": "Municipio de Ourém",
    "link": "https://diariodarepublica.pt/dr/detalhe/contrato-publico/21010-927729748",
    "detalhes_completos": "1 - IDENTIFICAÇÃO E CONTACTOS DA ENTIDADE ADJUDICANTE\nDesignação da entidade adjudicante: Municipio de Ourém\nNIPC: 501280740\nServiço/Órgão/Pessoa de contacto: Serviço de Contratação Pública e Aprovisionamento\nEndereço: Praça D. Maria II, nº 1\nCódigo postal: 2490-499\nLocalidade: Ourém\nPaís: Portugal\nNUT III: PT16I\nDistrito: Santarém\nConcelho: Ourém\nFreguesia: Freguesia de Nossa Senhora da Piedade\nTelefone: 249540900\nFax: 249540908\nEndereço da Entidade (URL): www.ourem.pt\nEndereço Eletrónico: geral@mail.cm-ourem.pt\neDelivery Gateway (URL): https://www.acingov.pt\nFunção da Organização: Adquirente\nNorma jurídica da Entidade Adjudicante: Autoridade local\nÁrea de atividade da Autoridade Adjudicante: Serviços públicos das administrações públicas\n\n2 - JORNAL OFICIAL DA UNIÃO EUROPEIA\nO procedimento a que este anúncio diz respeito também é publicitado no Jornal Oficial da União Europeia? Não\n\n3 - AVISO\nModelo de Anúncio: Concurso público\nData de Envio do Anúncio: 04-08-2025\n\n5 - PROCESSO\nTipo de Procedimento: Concurso público\nPreço base do procedimento: Sim\nValor do preço base do procedimento: 12.845,52 EUR\nProcedimento com lotes? Não\n\n6 - OBJETO DO CONTRATO\nNúmero de referência interna: P177/2025\nDesignação do contrato: P177/2025 - Aquisição de 4 Motociclos para a Guarda Nacional Republicana (GNR) de Ourém e Fátima (43077/2025)\nDescrição: P177/2025 - Aquisição de 4 Motociclos para a Guarda Nacional Republicana (GNR) de Ourém e Fátima (43077/2025)\nTipo de Contrato Principal: Aquisição de Bens Móveis\nTipo de Contrato: Aquisição de Bens Móveis\nClassificação CPV (Vocabulário Comum para os Contratos Públicos)\nObjeto principal\nVocabulário Principal: 34410000\nPreço base s/IVA: 12.845,52 EUR\n\n7 - INDICAÇÕES ADICIONAIS\nO contrato envolve aquisição conjunta (satisfação de várias entidades)? Não\nO contrato é adjudicado por uma central de compras? Não\n\n8 - TÉCNICAS\nO concurso destina-se à celebração de um acordo-quadro? Inexistência de acordo-quadro\nÉ utilizado um leilão eletrónico? Não\nÉ adotada uma fase de negociação? Não\nSistema de Aquisição Dinâmico: Inexistência de sistema de aquisição dinâmico\n\n9 - LOCAL DA EXECUÇÃO DO CONTRATO\nLOCAL DA EXECUÇÃO DO CONTRATO (PROCEDIMENTO)\nPaís: Portugal\nNUT III: PT16I\nLocalidade: Freguesia de Nossa Senhora da Piedade\nDistrito: Santarém\nConcelho: Ourém\nFreguesia: Freguesia de Nossa Senhora da Piedade\nPaís: Portugal\nNUT III: PT16I\nLocalidade: Freguesia de Fátima\nDistrito: Santarém\nConcelho: Ourém\nFreguesia: Freguesia de Fátima\n\n10 - PRAZO DE EXECUÇÃO DO CONTRATO\nPrazo de execução do contrato: 30 DIAS\nPrevisão de renovações: Não\n\n11 - FUNDOS EU\nTêm fundos EU? Não\n\n12 - DOCUMENTOS DE HABILITAÇÃO\nHabilitação para o exercício da atividade profissional: Sim\nTipo: Outros\nDescrição - Outros: Documentos de Habilitação\nDescrição: Documentos de Habilitação\n\n13 - CONDIÇÕES DE APRESENTAÇÃO\nPlataforma eletrónica utilizada pela entidade adjudicante: ACIN\nURL para Apresentação: https://www.acingov.pt\nAdmissibilidade da apresentação de propostas variantes: Não autorizado\nPrazo para apresentação das propostas: 16-08-2025 23:59\nPrazo durante o qual os concorrentes são obrigados a manter as respetivas propostas: 66 dias a contar do termo do prazo para a apresentação das propostas\nIndicação de Subcontratação na Proposta: Inexistência de indicação de subcontratação\n\n14 - PRESTAÇÃO DE CAUÇÃO\nPrestação de caução: Sim\nPercentagem: 5%\nDescrição da Garantia Exigida: O valor da caução é de 5.00% do preço contratual.\n\n15 - FORNECIMENTO DAS PEÇAS DO CONCURSO, APRESENTAÇÃO DE PEDIDOS DE PARTICIPAÇÃO E APRESENTAÇÃO DAS PROPOSTAS\nLink para acesso às peças do concurso (URL): https://www.acingov.pt/acingovprod/2/zonaPublica/zona_publica_c/donwloadProcedurePiece/OTMwODQ0\n\n20 - OUTROS REQUISITOS\nInformação sobre contratos reservados. Aplica-se a contratos reservados (54º-A)? Não\n\n21 - CRITÉRIO DE ADJUDICAÇÃO\nMultifator: Não\nMonofator:\nNome: Preço\n\n24 - CONDIÇÕES DO CONTRATO\nFaturação Eletrónica: Permitido\nObrigação de Subcontratação:\nCódigo da Obrigação de Subcontratação: Não é aplicável nenhuma obrigação de subcontratação.\n\n25 - COMPRA PÚBLICA ESTRATÉGICA\nCompra Pública Estratégica: Inexistência de contratação pública estratégica\n\n26 - INFORMAÇÕES ADICIONAIS\nContrato adequado para PME: Sim\nCobertura ACP (Acordo dos Contratos Públicos da Organização Mundial do Comércio): Não\n\n27 - IDENTIFICAÇÃO E CONTACTOS DO ÓRGÃO DE RECURSOS ADMINISTRATIVOS\nDesignação: Municipio de Ourém\nEndereço: Praça D. Maria II, nº 1\nCódigo postal: 2490-499\nLocalidade: Ourém\nTelefone: 249540900\nFax: 249540908\nEndereço eletrónico: geral@mail.cm-ourem.pt\nPrazo de interposição do recurso: 5 dias\n\n28 - IDENTIFICAÇÃO DO(S) AUTOR(ES) DE ANÚNCIO\nNome: Luís Miguel Albuquerque\nCargo: Presidente da Câmara\n419392084",
    "nipc": "501280740",
    "distrito": "Santarém",
    "concelho": "Ourém",
    "freguesia": "Freguesia de Nossa Senhora da Piedade",
    "site": "www.ourem.pt",
    "email": "geral@mail.cm-ourem.pt",
    "designacao_contrato": "P177/2025 - Aquisição de 4 Motociclos para a Guarda Nacional Republicana (GNR) de Ourém e Fátima (43077/2025)",
    "descricao": "P177/2025 - Aquisição de 4 Motociclos para a Guarda Nacional Republicana (GNR) de Ourém e Fátima (43077/2025)",
    "preco_base": "12.845,52 EUR",
    "prazo_execucao": "30 DIAS",
    "prazo_apresentacao_propostas": "16-08-2025 23:59",
    "fundos_eu": "Não",
    "plataforma_eletronica": "ACIN",
    "url_procedimento": "https://www.acingov.pt",
    "autor_nome": "Luís Miguel Albuquerque",
    "autor_cargo": "Presidente da Câmara"
  },
  {
    "numero_procedimento": "N/A",
    "entidade": "ASSOCIAÇÃO DE BOMBEIROS VOLUNTÁRIOS DE PORTALEGRE",
    "link": "https://diariodarepublica.pt/dr/detalhe/contrato-publico/21013-927729749",
    "detalhes_completos": "1 - IDENTIFICAÇÃO E CONTACTOS DA ENTIDADE ADJUDICANTE\nDesignação da entidade adjudicante: ASSOCIAÇÃO DE BOMBEIROS VOLUNTÁRIOS DE PORTALEGRE\nNIPC: 501177922\nEndereço: AVENIDA DA EXTREMADURA ESPANHOLA Nº 23\nCódigo postal: 7300-051\nLocalidade: Portalegre\nPaís: Portugal\nNUT III: PT186\nDistrito: Portalegre\nConcelho: Portalegre\nFreguesia: União das Freguesias da Sé e São Lourenço\nTelefone: 245307000\nEndereço Eletrónico: secretaria@bvportalegre.pt\neDelivery Gateway (URL): https://community.vortal.biz/public/\nFunção da Organização: Adquirente\nNorma jurídica da Entidade Adjudicante: Autoridade da administração central\nÁrea de atividade da Autoridade Adjudicante: Proteção ambiental\n\n2 - JORNAL OFICIAL DA UNIÃO EUROPEIA\nO procedimento a que este anúncio diz respeito também é publicitado no Jornal Oficial da União Europeia? Não\n\n3 - AVISO\nModelo de Anúncio: Concurso público\nData de Envio do Anúncio: 04-08-2025\n\n5 - PROCESSO\nTipo de Procedimento: Concurso público\nPreço base do procedimento: Sim\nValor do preço base do procedimento: 39.945,00 EUR\nProcedimento com lotes? Não\n\n6 - OBJETO DO CONTRATO\nNúmero de referência interna: 1./2025\nDesignação do contrato: Melhoria da Eficiência Energética do edifício da Associação Humanitária de Bombeiros Voluntários de Portalegre \nDescrição: Melhoria da Eficiência Energética do edifício da Associação Humanitária de Bombeiros Voluntários de Portalegre\nTipo de Contrato Principal: Aquisição de Bens Móveis\nTipo de Contrato: Aquisição de Bens Móveis\nClassificação CPV (Vocabulário Comum para os Contratos Públicos)\nObjeto principal\nVocabulário Principal: 09330000\nPreço base s/IVA: 39.945,00 EUR\n\n7 - INDICAÇÕES ADICIONAIS\nO contrato envolve aquisição conjunta (satisfação de várias entidades)? Não\nO contrato é adjudicado por uma central de compras? Não\n\n8 - TÉCNICAS\nO concurso destina-se à celebração de um acordo-quadro? Inexistência de acordo-quadro\nÉ utilizado um leilão eletrónico? Não\nÉ adotada uma fase de negociação? Não\nSistema de Aquisição Dinâmico: Inexistência de sistema de aquisição dinâmico\n\n9 - LOCAL DA EXECUÇÃO DO CONTRATO\nLOCAL DA EXECUÇÃO DO CONTRATO (PROCEDIMENTO)\nPaís: Portugal\nNUT III: PT186\nLocalidade: Portalegre\nDistrito: Portalegre\nConcelho: Portalegre\nFreguesia: União das Freguesias da Sé e São Lourenço\n\n10 - PRAZO DE EXECUÇÃO DO CONTRATO\nPrazo de execução do contrato: 120 DIAS\nPrevisão de renovações: Não\n\n11 - FUNDOS EU\nTêm fundos EU? Sim\n\n12 - DOCUMENTOS DE HABILITAÇÃO\nHabilitação para o exercício da atividade profissional: Não\n\n13 - CONDIÇÕES DE APRESENTAÇÃO\nPlataforma eletrónica utilizada pela entidade adjudicante: VORTAL\nURL para Apresentação: https://community.vortal.biz/public/\nAdmissibilidade da apresentação de propostas variantes: Não autorizado\nPrazo para apresentação das propostas: 13-08-2025 23:59\nPrazo durante o qual os concorrentes são obrigados a manter as respetivas propostas: 66 dias a contar do termo do prazo para a apresentação das propostas\nIndicação de Subcontratação na Proposta: Inexistência de indicação de subcontratação\n\n14 - PRESTAÇÃO DE CAUÇÃO\nPrestação de caução: Não\n\n15 - FORNECIMENTO DAS PEÇAS DO CONCURSO, APRESENTAÇÃO DE PEDIDOS DE PARTICIPAÇÃO E APRESENTAÇÃO DAS PROPOSTAS\nLink para acesso às peças do concurso (URL): https://community.vortal.biz/Public/public-tender-documents/ZWRoZFRTdWRnbVJLMmM2QlhxcGVLekRCNk5jNHdYUmJPQnRMb29uTkU3QThRYUdVUWtPQm5kcjZMb01BRTBpdytVZEovSFBWZ1hJc2dSM0F1MVBaZ1E9PXkkQGlA\n\n20 - OUTROS REQUISITOS\nInformação sobre contratos reservados. Aplica-se a contratos reservados (54º-A)? Não\n\n21 - CRITÉRIO DE ADJUDICAÇÃO\nMultifator: Não\nMonofator:\nNome: Outros\nOutro nome: Preço\n\n24 - CONDIÇÕES DO CONTRATO\nFaturação Eletrónica: Permitido\nObrigação de Subcontratação:\nCódigo da Obrigação de Subcontratação: Não é aplicável nenhuma obrigação de subcontratação.\n\n25 - COMPRA PÚBLICA ESTRATÉGICA\nCompra Pública Estratégica: Inexistência de contratação pública estratégica\n\n26 - INFORMAÇÕES ADICIONAIS\nContrato adequado para PME: Sim\nCobertura ACP (Acordo dos Contratos Públicos da Organização Mundial do Comércio): Não\n\n27 - IDENTIFICAÇÃO E CONTACTOS DO ÓRGÃO DE RECURSOS ADMINISTRATIVOS\nDesignação: Associação Humanitária de  Bombeiros Voluntários de Portalegre\nEndereço: Av. Estremadura Espanhola, 23\nCódigo postal: 7300-051\nLocalidade: Portalegre\nTelefone: +351 245307005\nFax: +351 245307005\nEndereço eletrónico: direcao@bvportalegre.pt\n\n28 - IDENTIFICAÇÃO DO(S) AUTOR(ES) DE ANÚNCIO\nNome: João António Mota Lourenço\nCargo: Presidente da Direção\n419394506",
    "nipc": "501177922",
    "distrito": "Portalegre",
    "concelho": "Portalegre",
    "freguesia": "União das Freguesias da Sé e São Lourenço",
    "site": null,
    "email": "secretaria@bvportalegre.pt",
    "designacao_contrato": "Melhoria da Eficiência Energética do edifício da Associação Humanitária de Bombeiros Voluntários de Portalegre",
    "descricao": "Melhoria da Eficiência Energética do edifício da Associação Humanitária de Bombeiros Voluntários de Portalegre",
    "preco_base": "39.945,00 EUR",
    "prazo_execucao": "120 DIAS",
    "prazo_apresentacao_propostas": "13-08-2025 23:59",
    "fundos_eu": "Sim",
    "plataforma_eletronica": "VORTAL",
    "url_procedimento": "https://community.vortal.biz/public/",
    "autor_nome": "João António Mota Lourenço",
    "autor_cargo": "Presidente da Direção"
  },
  {
    "numero_procedimento": "N/A",
    "entidade": "Agrupamento de Escolas da Moita",
    "link": "https://diariodarepublica.pt/dr/detalhe/contrato-publico/21015-927729750",
    "detalhes_completos": "Alteração do Anúncio de procedimento n.º 19657/2025, de 2025-07-23, com o ID 419341329\n\n1 - IDENTIFICAÇÃO E CONTACTOS DA ENTIDADE ADJUDICANTE\nDesignação da entidade adjudicante: Agrupamento de Escolas da Moita\nNIPC: 600084329\nEndereço: Largo da Juventude, Alto S.Sebastião, S/N\nCódigo postal: 2864-004\nLocalidade: Moita\nPaís: Portugal\nNUT III: PT170\nDistrito: Setúbal\nConcelho: Moita\nFreguesia: Freguesia de Moita - Moita\nTelefone: 918479100\nFax: 918479100\nEndereço da Entidade (URL): https://aemoita.pt/aemoita/\nEndereço Eletrónico: geral@aemoita.pt\nFunção da Organização: Adquirente\nNorma jurídica da Entidade Adjudicante: Organismo de direito público\nÁrea de atividade da Autoridade Adjudicante: Educação\n\n2 - JORNAL OFICIAL DA UNIÃO EUROPEIA\nO procedimento a que este anúncio diz respeito também é publicitado no Jornal Oficial da União Europeia? Não\n\n3 - AVISO\nModelo de Anúncio: Concurso público\nData de Envio do Anúncio: 04-08-2025\n\n5 - PROCESSO\nTipo de Procedimento: Concurso público\nPreço base do procedimento: Não\nProcedimento com lotes? Sim\nNº Máx. de Lotes Autorizado: 1\nNúmero máximo de lotes que podem ser adjudicados a um concorrente: 1\n\n6 - OBJETO DO CONTRATO\nNúmero de referência interna: CTE2025\nDesignação do contrato: Implementação de um CTE de Informática\nDescrição: Aquisição, instalação e configuração da infraestrutura tecnológica, do hardware, software e do mobiliário educativo e didático - ¿Implementação de um CTE de Informática¿\nTipo de Contrato Principal: Aquisição de Bens Móveis\nTipo de Contrato: Aquisição de Bens Móveis\nClassificação CPV (Vocabulário Comum para os Contratos Públicos)\nObjeto principal\nVocabulário Principal: 30000000\nLotes: \nNº: LOT-0001\nDescrição do Lote: Lote UNICO\nClassificação CPV (Vocabulário Comum para os Contratos Públicos)\nObjeto principal\nVocabulário Principal: 30000000\n\n7 - INDICAÇÕES ADICIONAIS\nO contrato envolve aquisição conjunta (satisfação de várias entidades)? Não\nO contrato é adjudicado por uma central de compras? Não\n\n8 - TÉCNICAS\nO concurso destina-se à celebração de um acordo-quadro? Inexistência de acordo-quadro\nÉ utilizado um leilão eletrónico? Não\nÉ adotada uma fase de negociação? Não\nSistema de Aquisição Dinâmico: Inexistência de sistema de aquisição dinâmico\n\n9 - LOCAL DA EXECUÇÃO DO CONTRATO\nLOCAL DA EXECUÇÃO DO CONTRATO (PROCEDIMENTO)\nLOCAL DA EXECUÇÃO DO CONTRATO (LOTE)\nIdentificador do Lote: LOT-0001\nPaís: Portugal\nNUT III: PT170\nLocalidade: Moita\nDistrito: Setúbal\nConcelho: Moita\nFreguesia: Freguesia de Moita - Moita\n\n10 - PRAZO DE EXECUÇÃO DO CONTRATO\nIdentificador do Lote: LOT-0001\nPrazo de execução do contrato: 1 ANOS\nPrevisão de renovações: Não\n\n11 - FUNDOS EU\nIdentificador do Lote: LOT-0001\nTêm fundos EU? Sim\n\n12 - DOCUMENTOS DE HABILITAÇÃO\nHabilitação para o exercício da atividade profissional: Não\n\n13 - CONDIÇÕES DE APRESENTAÇÃO\nPlataforma eletrónica utilizada pela entidade adjudicante: ANOGOV\nURL para Apresentação: https://www.anogov.com/ae-moita/faces/\nAdmissibilidade da apresentação de propostas variantes: Não autorizado\nPrazo para apresentação das propostas: 21-08-2025 23:59\nPrazo durante o qual os concorrentes são obrigados a manter as respetivas propostas: 66 dias a contar do termo do prazo para a apresentação das propostas\nApresentação de Catálogo Eletrónico: Permitido\nIndicação de Subcontratação na Proposta: O(s) subcontratante(s) proposto(s) necessário(s) para cumprir a obrigação de subcontratar uma percentagem mínima do contrato\n\n14 - PRESTAÇÃO DE CAUÇÃO\nPrestação de caução: Não\n\n15 - FORNECIMENTO DAS PEÇAS DO CONCURSO, APRESENTAÇÃO DE PEDIDOS DE PARTICIPAÇÃO E APRESENTAÇÃO DAS PROPOSTAS\nLink para acesso às peças do concurso (URL): https://www.anogov.com/ae-moita/faces/app/acessoDocs.jsp?codigoAcesso=elxh9WzpB1saStGT14TKaGxLVd9zn40hQdLcnTQ4EE13mWnodg\n\n20 - OUTROS REQUISITOS\nIdentificador do Lote: LOT-0001\nInformação sobre contratos reservados. Aplica-se a contratos reservados (54º-A)? Não\n\n21 - CRITÉRIO DE ADJUDICAÇÃO\nO Critério de adjudicação é diferenciado por lote? Não\nMultifator: Sim\nFator: \nNome: Qualidade\nPonderação: 50%\nSubfatores: Não\nFator: \nNome: Preço\nPonderação: 50%\nSubfatores: Não\n\n24 - CONDIÇÕES DO CONTRATO\nIdentificador do Lote: LOT-0001\nFaturação Eletrónica: Permitido\nObrigação de Subcontratação:\nCódigo da Obrigação de Subcontratação: Não é aplicável nenhuma obrigação de subcontratação.\n\n25 - COMPRA PÚBLICA ESTRATÉGICA\nCompra Pública Estratégica: Inexistência de contratação pública estratégica\n\n26 - INFORMAÇÕES ADICIONAIS\nIdentificador do Lote: LOT-0001\nContrato adequado para PME: Sim\nCobertura ACP (Acordo dos Contratos Públicos da Organização Mundial do Comércio): Não\n\n27 - IDENTIFICAÇÃO E CONTACTOS DO ÓRGÃO DE RECURSOS ADMINISTRATIVOS\nDesignação: Agrupamento de Escolas da Moita\nEndereço: Largo da Juventude, Alto S. Sebastião\nCódigo postal: 2864-004\nLocalidade: Moita\nEndereço eletrónico: concursos@aemoita.pt\nPrazo de interposição do recurso: 5 dias\n\n28 - IDENTIFICAÇÃO DO(S) AUTOR(ES) DE ANÚNCIO\nNome: João Carlos Lopes\nCargo: Diretor\n\n29 - ALTERAÇÃO\nMotivo da Alteração: Informações atualizadas\nIdentificador da Versão do Anúncio a Alterar: 49bdd91c-ffb3-494f-810e-fdf15faab8dc-01\nIdentificador das Secções Alteradas do Anúncio Anterior: O procedimento a que este anúncio diz respeito também é publicitado no Jornal Oficial da União Europeia?\nDescrição das Alterações: Anúncio anulado\nAlteração dos Documentos do Concurso: Não\n419396856",
    "nipc": "600084329",
    "distrito": "Setúbal",
    "concelho": "Moita",
    "freguesia": "Freguesia de Moita - Moita",
    "site": "https://aemoita.pt/aemoita/",
    "email": "geral@aemoita.pt",
    "designacao_contrato": "Implementação de um CTE de Informática",
    "descricao": "Aquisição, instalação e configuração da infraestrutura tecnológica, do hardware, software e do mobiliário educativo e didático - ¿Implementação de um CTE de Informática¿",
    "preco_base": null,
    "prazo_execucao": "1 ANOS",
    "prazo_apresentacao_propostas": "21-08-2025 23:59",
    "fundos_eu": "Sim",
    "plataforma_eletronica": "ANOGOV",
    "url_procedimento": "https://www.anogov.com/ae-moita/faces/",
    "autor_nome": "João Carlos Lopes",
    "autor_cargo": "Diretor"
  },
  {
    "numero_procedimento": "N/A",
    "entidade": "Unidade Local de Saúde da Arrábida, E. P. E.",
    "link": "https://diariodarepublica.pt/dr/detalhe/contrato-publico/21016-927729753",
    "detalhes_completos": "1 - IDENTIFICAÇÃO E CONTACTOS DA ENTIDADE ADJUDICANTE\nDesignação da entidade adjudicante: Unidade Local de Saúde da Arrábida, E. P. E.\nNIPC: 507606787\nEndereço: Rua Camilo Castelo Branco, Aptd. 140, Setúbal\nCódigo postal: 2910-443\nLocalidade: Setúbal\nPaís: Portugal\nNUT III: PT170\nDistrito: Setúbal\nConcelho: Setúbal\nFreguesia: Todas\nTelefone: 265549000\nFax: 265238066\nEndereço da Entidade (URL): www.hsb-setubal.min-sau\nEndereço Eletrónico: geral@chs.min-saude.pt\neDelivery Gateway (URL): https://community.vortal.biz/public/\nFunção da Organização: Adquirente\nNorma jurídica da Entidade Adjudicante: Empresa pública\nÁrea de atividade da Autoridade Adjudicante: Saúde\n\n2 - JORNAL OFICIAL DA UNIÃO EUROPEIA\nO procedimento a que este anúncio diz respeito também é publicitado no Jornal Oficial da União Europeia? Não\n\n3 - AVISO\nModelo de Anúncio: Concurso público\nData de Envio do Anúncio: 04-08-2025\n\n5 - PROCESSO\nTipo de Procedimento: Concurso público\nPreço base do procedimento: Sim\nValor do preço base do procedimento: 264.225,00 EUR\nProcedimento com lotes? Não\n\n6 - OBJETO DO CONTRATO\nNúmero de referência interna: 28001325\nDesignação do contrato: Aluguer Contentores para instalações provisórias\nDescrição: Aluguer, montagem e desmontagem módulos contentores para instalações provisorias da saúde ocupacional\nTipo de Contrato Principal: Aquisição de Serviços\nTipo de Contrato: Aquisição de Serviços\nClassificação CPV (Vocabulário Comum para os Contratos Públicos)\nObjeto principal\nVocabulário Principal: 55250000\nPreço base s/IVA: 264.225,00 EUR\n\n7 - INDICAÇÕES ADICIONAIS\nO contrato envolve aquisição conjunta (satisfação de várias entidades)? Não\nO contrato é adjudicado por uma central de compras? Não\n\n8 - TÉCNICAS\nO concurso destina-se à celebração de um acordo-quadro? Inexistência de acordo-quadro\nÉ utilizado um leilão eletrónico? Não\nÉ adotada uma fase de negociação? Não\nSistema de Aquisição Dinâmico: Inexistência de sistema de aquisição dinâmico\n\n9 - LOCAL DA EXECUÇÃO DO CONTRATO\nLOCAL DA EXECUÇÃO DO CONTRATO (PROCEDIMENTO)\nPaís: Portugal\nNUT III: PTZZZ\nLocalidade: PORTUGAL\nDistrito: Todos\nConcelho: Todos\nFreguesia: Todas\n\n10 - PRAZO DE EXECUÇÃO DO CONTRATO\nPrazo de execução do contrato: 36 MESES\nPrevisão de renovações: Não\n\n11 - FUNDOS EU\nTêm fundos EU? Não\n\n12 - DOCUMENTOS DE HABILITAÇÃO\nHabilitação para o exercício da atividade profissional: Não\n\n13 - CONDIÇÕES DE APRESENTAÇÃO\nPlataforma eletrónica utilizada pela entidade adjudicante: VORTAL\nURL para Apresentação: https://community.vortal.biz/public/\nAdmissibilidade da apresentação de propostas variantes: Não autorizado\nPrazo para apresentação das propostas: 11-08-2025 17:00\nPrazo durante o qual os concorrentes são obrigados a manter as respetivas propostas: 66 dias a contar do termo do prazo para a apresentação das propostas\nIndicação de Subcontratação na Proposta: Inexistência de indicação de subcontratação\n\n14 - PRESTAÇÃO DE CAUÇÃO\nPrestação de caução: Não\n\n15 - FORNECIMENTO DAS PEÇAS DO CONCURSO, APRESENTAÇÃO DE PEDIDOS DE PARTICIPAÇÃO E APRESENTAÇÃO DAS PROPOSTAS\nLink para acesso às peças do concurso (URL): https://community.vortal.biz/Public/public-tender-documents/MFRHUS9jTjlqNVJzR043eEg5VktXb3A0RFIvVGg0dGNwZ0wrVk9lNytIL3VXVzhueGlDZDhvRmNPSHRBcFpQdktjNkJBS2ZsZzRzbjVGcFFVWGRhSGc9PVYmJk1L\n\n20 - OUTROS REQUISITOS\nInformação sobre contratos reservados. Aplica-se a contratos reservados (54º-A)? Não\n\n21 - CRITÉRIO DE ADJUDICAÇÃO\nMultifator: Sim\nFator: \nNome: Qualidade\nPonderação: 15%\nSubfatores: Não\nFator: \nNome: Preço\nPonderação: 55%\nSubfatores: Não\nFator: \nNome: Qualidade\nPonderação: 30%\nSubfatores: Não\n\n24 - CONDIÇÕES DO CONTRATO\nFaturação Eletrónica: Permitido\nObrigação de Subcontratação:\nCódigo da Obrigação de Subcontratação: Não é aplicável nenhuma obrigação de subcontratação.\n\n25 - COMPRA PÚBLICA ESTRATÉGICA\nCompra Pública Estratégica: Inexistência de contratação pública estratégica\n\n26 - INFORMAÇÕES ADICIONAIS\nContrato adequado para PME: Sim\nCobertura ACP (Acordo dos Contratos Públicos da Organização Mundial do Comércio): Não\n\n27 - IDENTIFICAÇÃO E CONTACTOS DO ÓRGÃO DE RECURSOS ADMINISTRATIVOS\nDesignação: Unidade Local Saúde da Arrábida EPE\nEndereço: Rua Camilo Castelo Branco, Aptd. 140, Setúbal\nCódigo postal: 2910-443\nLocalidade: Setúbal\nTelefone: +351 265549528\nFax: +351 265532546\nEndereço eletrónico: geral@ulsa.min-saude.pt\n\n28 - IDENTIFICAÇÃO DO(S) AUTOR(ES) DE ANÚNCIO\nNome: Luis Filipe Henriques Pombo\nCargo: Presidente Conselho Administração\n419393923",
    "nipc": "507606787",
    "distrito": "Setúbal",
    "concelho": "Setúbal",
    "freguesia": "Todas",
    "site": "www.hsb-setubal.min-sau",
    "email": "geral@chs.min-saude.pt",
    "designacao_contrato": "Aluguer Contentores para instalações provisórias",
    "descricao": "Aluguer, montagem e desmontagem módulos contentores para instalações provisorias da saúde ocupacional",
    "preco_base": "264.225,00 EUR",
    "prazo_execucao": "36 MESES",
    "prazo_apresentacao_propostas": "11-08-2025 17:00",
    "fundos_eu": "Não",
    "plataforma_eletronica": "VORTAL",
    "url_procedimento": "https://community.vortal.biz/public/",
    "autor_nome": "Luis Filipe Henriques Pombo",
    "autor_cargo": "Presidente Conselho Administração"
  },
  {
    "numero_procedimento": "N/A",
    "entidade": "Unidade Local de Saúde da Arrábida, E. P. E.",
    "link": "https://diariodarepublica.pt/dr/detalhe/contrato-publico/21017-927729754",
    "detalhes_completos": "1 - IDENTIFICAÇÃO E CONTACTOS DA ENTIDADE ADJUDICANTE\nDesignação da entidade adjudicante: Unidade Local de Saúde da Arrábida, E. P. E.\nNIPC: 507606787\nEndereço: Rua Camilo Castelo Branco, Aptd. 140, Setúbal\nCódigo postal: 2910-443\nLocalidade: Setúbal\nPaís: Portugal\nNUT III: PT170\nDistrito: Setúbal\nConcelho: Setúbal\nFreguesia: Todas\nTelefone: 265549000\nFax: 265238066\nEndereço da Entidade (URL): www.hsb-setubal.min-sau\nEndereço Eletrónico: geral@chs.min-saude.pt\neDelivery Gateway (URL): https://community.vortal.biz/public/\nFunção da Organização: Adquirente\nNorma jurídica da Entidade Adjudicante: Empresa pública\nÁrea de atividade da Autoridade Adjudicante: Saúde\n\n2 - JORNAL OFICIAL DA UNIÃO EUROPEIA\nO procedimento a que este anúncio diz respeito também é publicitado no Jornal Oficial da União Europeia? Não\n\n3 - AVISO\nModelo de Anúncio: Concurso público\nData de Envio do Anúncio: 04-08-2025\n\n5 - PROCESSO\nTipo de Procedimento: Concurso público\nPreço base do procedimento: Sim\nValor do preço base do procedimento: 250.000,00 EUR\nProcedimento com lotes? Não\n\n6 - OBJETO DO CONTRATO\nNúmero de referência interna: 28001225\nDesignação do contrato: Aluguer Contentores Instalações Provisórias_ Consultas Ginecologia Obstetrícia\nDescrição: Aluguer Contentores Instalações Provisórias_ área consultas externas_ Ginecologia/Obstetrícia\nTipo de Contrato Principal: Aquisição de Serviços\nTipo de Contrato: Aquisição de Serviços\nClassificação CPV (Vocabulário Comum para os Contratos Públicos)\nObjeto principal\nVocabulário Principal: 55250000\nPreço base s/IVA: 250.000,00 EUR\n\n7 - INDICAÇÕES ADICIONAIS\nO contrato envolve aquisição conjunta (satisfação de várias entidades)? Não\nO contrato é adjudicado por uma central de compras? Não\n\n8 - TÉCNICAS\nO concurso destina-se à celebração de um acordo-quadro? Inexistência de acordo-quadro\nÉ utilizado um leilão eletrónico? Não\nÉ adotada uma fase de negociação? Não\nSistema de Aquisição Dinâmico: Inexistência de sistema de aquisição dinâmico\n\n9 - LOCAL DA EXECUÇÃO DO CONTRATO\nLOCAL DA EXECUÇÃO DO CONTRATO (PROCEDIMENTO)\nPaís: Portugal\nNUT III: PTZZZ\nLocalidade: PORTUGAL\nDistrito: Todos\nConcelho: Todos\nFreguesia: Todas\n\n10 - PRAZO DE EXECUÇÃO DO CONTRATO\nPrazo de execução do contrato: 24 MESES\nPrevisão de renovações: Não\n\n11 - FUNDOS EU\nTêm fundos EU? Não\n\n12 - DOCUMENTOS DE HABILITAÇÃO\nHabilitação para o exercício da atividade profissional: Não\n\n13 - CONDIÇÕES DE APRESENTAÇÃO\nPlataforma eletrónica utilizada pela entidade adjudicante: VORTAL\nURL para Apresentação: https://community.vortal.biz/public/\nAdmissibilidade da apresentação de propostas variantes: Não autorizado\nPrazo para apresentação das propostas: 11-08-2025 17:00\nPrazo durante o qual os concorrentes são obrigados a manter as respetivas propostas: 66 dias a contar do termo do prazo para a apresentação das propostas\nIndicação de Subcontratação na Proposta: Inexistência de indicação de subcontratação\n\n14 - PRESTAÇÃO DE CAUÇÃO\nPrestação de caução: Não\n\n15 - FORNECIMENTO DAS PEÇAS DO CONCURSO, APRESENTAÇÃO DE PEDIDOS DE PARTICIPAÇÃO E APRESENTAÇÃO DAS PROPOSTAS\nLink para acesso às peças do concurso (URL): https://community.vortal.biz/Public/public-tender-documents/NjdzU3pWaWxMcEpybGNlWmZwTDExT0dad2VTbWFMdnVjeExRVW11VmFNY01kMG1weUQ3MjN5dXNGTXJYbHluSzF6NE5BVFVHVnpMQXRqaTIwZUVHSVE9PUc5K2Uh\n\n20 - OUTROS REQUISITOS\nInformação sobre contratos reservados. Aplica-se a contratos reservados (54º-A)? Não\n\n21 - CRITÉRIO DE ADJUDICAÇÃO\nMultifator: Sim\nFator: \nNome: Qualidade\nPonderação: 15%\nSubfatores: Não\nFator: \nNome: Preço\nPonderação: 55%\nSubfatores: Não\nFator: \nNome: Qualidade\nPonderação: 30%\nSubfatores: Não\n\n24 - CONDIÇÕES DO CONTRATO\nFaturação Eletrónica: Permitido\nObrigação de Subcontratação:\nCódigo da Obrigação de Subcontratação: Não é aplicável nenhuma obrigação de subcontratação.\n\n25 - COMPRA PÚBLICA ESTRATÉGICA\nCompra Pública Estratégica: Inexistência de contratação pública estratégica\n\n26 - INFORMAÇÕES ADICIONAIS\nContrato adequado para PME: Sim\nCobertura ACP (Acordo dos Contratos Públicos da Organização Mundial do Comércio): Não\n\n27 - IDENTIFICAÇÃO E CONTACTOS DO ÓRGÃO DE RECURSOS ADMINISTRATIVOS\nDesignação: Unidade Local Saúde da Arrábida EPE\nEndereço: Rua Camilo Castelo Branco, Aptd. 140, Setúbal\nCódigo postal: 2910-443\nLocalidade: Setúbal\nTelefone: +351 265549528\nFax: +351 265532546\nEndereço eletrónico: geral@ulsa.min-saude.pt\n\n28 - IDENTIFICAÇÃO DO(S) AUTOR(ES) DE ANÚNCIO\nNome: Luis Filipe Henriques Pombo\nCargo: Presidente do Conselho de Administração\n419393486",
    "nipc": "507606787",
    "distrito": "Setúbal",
    "concelho": "Setúbal",
    "freguesia": "Todas",
    "site": "www.hsb-setubal.min-sau",
    "email": "geral@chs.min-saude.pt",
    "designacao_contrato": "Aluguer Contentores Instalações Provisórias_ Consultas Ginecologia Obstetrícia",
    "descricao": "Aluguer Contentores Instalações Provisórias_ área consultas externas_ Ginecologia/Obstetrícia",
    "preco_base": "250.000,00 EUR",
    "prazo_execucao": "24 MESES",
    "prazo_apresentacao_propostas": "11-08-2025 17:00",
    "fundos_eu": "Não",
    "plataforma_eletronica": "VORTAL",
    "url_procedimento": "https://community.vortal.biz/public/",
    "autor_nome": "Luis Filipe Henriques Pombo",
    "autor_cargo": "Presidente do Conselho de Administração"
  },
  {
    "numero_procedimento": "N/A",
    "entidade": "Parques de Sintra-Monte da Lua, SA",
    "link": "https://diariodarepublica.pt/dr/detalhe/contrato-publico/21019-927729755",
    "detalhes_completos": "1 - IDENTIFICAÇÃO E CONTACTOS DA ENTIDADE ADJUDICANTE\nDesignação da entidade adjudicante: Parques de Sintra-Monte da Lua, SA\nNIPC: 505174839\nEndereço: ESTRADA MONSERRATE, PARQUE DE MONSERRATE\nCódigo postal: 2710-405\nLocalidade: Sintra\nPaís: Portugal\nNUT III: PT170\nDistrito: Lisboa\nConcelho: Sintra\nFreguesia: Todas\nTelefone: 219237300\nFax: 219237350\nEndereço da Entidade (URL): www.parquesdesintra.pt/pt/\nEndereço Eletrónico: viviane.crouzier@parquesdesintra.pt\neDelivery Gateway (URL): https://community.vortal.biz/public/\nFunção da Organização: Adquirente\nNorma jurídica da Entidade Adjudicante: Autoridade da administração central\nÁrea de atividade da Autoridade Adjudicante: Serviços públicos das administrações públicas\n\n2 - JORNAL OFICIAL DA UNIÃO EUROPEIA\nO procedimento a que este anúncio diz respeito também é publicitado no Jornal Oficial da União Europeia? Não\n\n3 - AVISO\nModelo de Anúncio: Concurso público\nData de Envio do Anúncio: 04-08-2025\n\n5 - PROCESSO\nTipo de Procedimento: Concurso público\nPreço base do procedimento: Sim\nValor do preço base do procedimento: 910.000,00 EUR\nProcedimento com lotes? Não\n\n6 - OBJETO DO CONTRATO\nNúmero de referência interna: 01306.2025\nDesignação do contrato: Reforço estrutural do muro exterior da Mata do Palácio Nacional de Sintra\nDescrição: Reforço estrutural do muro exterior da Mata do Palácio Nacional de Sintra\nTipo de Contrato Principal: Empreitada de Obras Públicas\nTipo de Contrato: Empreitada de Obras Públicas\nClassificação CPV (Vocabulário Comum para os Contratos Públicos)\nObjeto principal\nVocabulário Principal: 45453000\nPreço base s/IVA: 910.000,00 EUR\n\n7 - INDICAÇÕES ADICIONAIS\nO contrato envolve aquisição conjunta (satisfação de várias entidades)? Não\nO contrato é adjudicado por uma central de compras? Não\n\n8 - TÉCNICAS\nO concurso destina-se à celebração de um acordo-quadro? Inexistência de acordo-quadro\nÉ utilizado um leilão eletrónico? Não\nÉ adotada uma fase de negociação? Não\nSistema de Aquisição Dinâmico: Inexistência de sistema de aquisição dinâmico\n\n9 - LOCAL DA EXECUÇÃO DO CONTRATO\nLOCAL DA EXECUÇÃO DO CONTRATO (PROCEDIMENTO)\nPaís: Portugal\nNUT III: PT170\nLocalidade: Lisboa\nDistrito: Lisboa\nConcelho: Sintra\nFreguesia: Todas\n\n10 - PRAZO DE EXECUÇÃO DO CONTRATO\nPrazo de execução do contrato: 8 MESES\nPrevisão de renovações: Não\n\n11 - FUNDOS EU\nTêm fundos EU? Não\n\n12 - DOCUMENTOS DE HABILITAÇÃO\nHabilitação para o exercício da atividade profissional: Não\n\n13 - CONDIÇÕES DE APRESENTAÇÃO\nPlataforma eletrónica utilizada pela entidade adjudicante: VORTAL\nURL para Apresentação: https://community.vortal.biz/public/\nAdmissibilidade da apresentação de propostas variantes: Não autorizado\nPrazo para apresentação das propostas: 03-09-2025 23:59\nPrazo durante o qual os concorrentes são obrigados a manter as respetivas propostas: 66 dias a contar do termo do prazo para a apresentação das propostas\nIndicação de Subcontratação na Proposta: Inexistência de indicação de subcontratação\n\n14 - PRESTAÇÃO DE CAUÇÃO\nPrestação de caução: Não\n\n15 - FORNECIMENTO DAS PEÇAS DO CONCURSO, APRESENTAÇÃO DE PEDIDOS DE PARTICIPAÇÃO E APRESENTAÇÃO DAS PROPOSTAS\nLink para acesso às peças do concurso (URL): https://community.vortal.biz/Public/public-tender-documents/VCs0OTdXNWZ4eTc0ZWZtTUIzbUhJNzdqSGxpaFd6bUxLQnVnejc1UWVQNkxSS3lwWkdiWlM3THRLQk9ObzNUWWJSNks5T1psc0phcEJsbnM3NGM0b2c9PXZ4SFV5\n\n20 - OUTROS REQUISITOS\nInformação sobre contratos reservados. Aplica-se a contratos reservados (54º-A)? Não\n\n21 - CRITÉRIO DE ADJUDICAÇÃO\nMultifator: Não\nMonofator:\nNome: Outros\nOutro nome: Preço\n\n24 - CONDIÇÕES DO CONTRATO\nFaturação Eletrónica: Permitido\nObrigação de Subcontratação:\nCódigo da Obrigação de Subcontratação: Não é aplicável nenhuma obrigação de subcontratação.\n\n25 - COMPRA PÚBLICA ESTRATÉGICA\nCompra Pública Estratégica: Inexistência de contratação pública estratégica\n\n26 - INFORMAÇÕES ADICIONAIS\nContrato adequado para PME: Sim\nCobertura ACP (Acordo dos Contratos Públicos da Organização Mundial do Comércio): Não\n\n27 - IDENTIFICAÇÃO E CONTACTOS DO ÓRGÃO DE RECURSOS ADMINISTRATIVOS\nDesignação: Conselho de Administração\nEndereço: ESTRADA MONSERRATE, PARQUE DE MONSERRATE\nCódigo postal: 2710-405\nLocalidade: Sintra\nTelefone: +351 219237300\nFax: +351 219237300\nEndereço eletrónico: info@parquesdesintra.pt\n\n28 - IDENTIFICAÇÃO DO(S) AUTOR(ES) DE ANÚNCIO\nNome: Viviane Crouzier\nCargo: Departamento jurídico\n419397188",
    "nipc": "505174839",
    "distrito": "Lisboa",
    "concelho": "Sintra",
    "freguesia": "Todas",
    "site": "www.parquesdesintra.pt/pt/",
    "email": "viviane.crouzier@parquesdesintra.pt",
    "designacao_contrato": "Reforço estrutural do muro exterior da Mata do Palácio Nacional de Sintra",
    "descricao": "Reforço estrutural do muro exterior da Mata do Palácio Nacional de Sintra",
    "preco_base": "910.000,00 EUR",
    "prazo_execucao": "8 MESES",
    "prazo_apresentacao_propostas": "03-09-2025 23:59",
    "fundos_eu": "Não",
    "plataforma_eletronica": "VORTAL",
    "url_procedimento": "https://community.vortal.biz/public/",
    "autor_nome": "Viviane Crouzier",
    "autor_cargo": "Departamento jurídico"
  },
  {
    "numero_procedimento": "N/A",
    "entidade": "Semi Internato Nossa Senhora da Encarnação",
    "link": "https://diariodarepublica.pt/dr/detalhe/contrato-publico/21020-927729756",
    "detalhes_completos": "1 - IDENTIFICAÇÃO E CONTACTOS DA ENTIDADE ADJUDICANTE\nDesignação da entidade adjudicante: Semi Internato Nossa Senhora da Encarnação\nNIPC: 500875847\nServiço/Órgão/Pessoa de contacto: Maria Goreti Pereira Pedrosa\nEndereço: Rua Francisco da Silva, n.º 9\nCódigo postal: 7350-272\nLocalidade: Elvas\nPaís: Portugal\nNUT III: PT186\nDistrito: Portalegre\nConcelho: Elvas\nFreguesia: Freguesia de Caia, São Pedro e Alcáçova\nTelefone: 268636430\nEndereço da Entidade (URL): www.concepcionistas.pt\nEndereço Eletrónico: sinsencarnacao@sapo.pt\neDelivery Gateway (URL): https://www.acingov.pt\nFunção da Organização: Adquirente\nSubfunção da Organização: Organização cujo orçamento é utilizado para pagar o contrato; Organização que executa o pagamento; Organização que fornece informações adicionais sobre o processo de adjudicação; Organização que fornece mais informações sobre os prazos dos procedimentos de recurso; Organização responsável pelo tratamento das propostas; Organização que recebe as propostas; Organização que trata os pedidos de participação; Organização que recebe pedidos de participação; Organização que fornece mais informações sobre os procedimentos de recurso; Organização que assina o contrato\nNorma jurídica da Entidade Adjudicante: Organismo de direito público\nÁrea de atividade da Autoridade Adjudicante: Serviços públicos das administrações públicas\n\n2 - JORNAL OFICIAL DA UNIÃO EUROPEIA\nO procedimento a que este anúncio diz respeito também é publicitado no Jornal Oficial da União Europeia? Não\n\n3 - AVISO\nModelo de Anúncio: Concurso público\nData de Envio do Anúncio: 04-08-2025\n\n5 - PROCESSO\nTipo de Procedimento: Concurso público\nPreço base do procedimento: Sim\nValor do preço base do procedimento: 1.114.760,26 EUR\nProcedimento com lotes? Não\n\n6 - OBJETO DO CONTRATO\nNúmero de referência interna: CP/01/2025\nDesignação do contrato: Empreitada de Requalificação / Remodelação da Creche do Semi internato Nossa Senhora Encarnação, financiada pela candidatura n.º PRR-RE-C03-i01-09-000308\nDescrição: Requalificação / Remodelação da Creche do Semi internato Nossa Senhora Encarnação, financiada pela candidatura n.º PRR-RE-C03-i01-09-000308\nTipo de Contrato Principal: Empreitada de Obras Públicas\nTipo de Contrato: Empreitada de Obras Públicas\nClassificação CPV (Vocabulário Comum para os Contratos Públicos)\nObjeto principal\nVocabulário Principal: 45215215\nPreço base s/IVA: 1.114.760,26 EUR\n\n7 - INDICAÇÕES ADICIONAIS\nO contrato envolve aquisição conjunta (satisfação de várias entidades)? Não\nO contrato é adjudicado por uma central de compras? Não\n\n8 - TÉCNICAS\nO concurso destina-se à celebração de um acordo-quadro? Inexistência de acordo-quadro\nÉ utilizado um leilão eletrónico? Não\nÉ adotada uma fase de negociação? Não\nSistema de Aquisição Dinâmico: Inexistência de sistema de aquisição dinâmico\n\n9 - LOCAL DA EXECUÇÃO DO CONTRATO\nLOCAL DA EXECUÇÃO DO CONTRATO (PROCEDIMENTO)\nPaís: Portugal\nNUT III: PT186\nLocalidade: Freguesia de Caia, São Pedro e Alcáçova\nDistrito: Portalegre\nConcelho: Elvas\nFreguesia: Freguesia de Caia, São Pedro e Alcáçova\n\n10 - PRAZO DE EXECUÇÃO DO CONTRATO\nPrazo de execução do contrato: 9 MESES\nPrevisão de renovações: Não\n\n11 - FUNDOS EU\nTêm fundos EU? Sim\n\n12 - DOCUMENTOS DE HABILITAÇÃO\nHabilitação para o exercício da atividade profissional: Sim\nTipo: Alvará\nDescrição: 1.ª  Estruturas e elementos de betão, 4.ª - Alvenarias, rebocos e assentamento de cantarias, 5.ª - Estuques, pinturas e outros revestimentos, 8.ª - Canalizações e condutas em edifícios Subcategorias da 1.ª Categoria - Edifícios e património construído; das 1.ª - Instalações elétricas de utilização de baixa tensão com potência até 50 kVA e 12.ª - Aquecimento, ventilação, ar condicionado e refrigeração Subcategorias da 4ª Categoria - Instalações elétricas e mecânica; e das 1.ª  Demolições e 12.ª  Andaimes e outras estruturas provisórias Subcategorias da 5ª Categoria - Outros trabalhos e da 4.ª - Alvenarias, rebocos e assentamento de cantarias Subcategoria da 1.ª Categoria - Edifícios e património construído, a qual tem de ser de classe que cubra o valor global da proposta\n\n13 - CONDIÇÕES DE APRESENTAÇÃO\nPlataforma eletrónica utilizada pela entidade adjudicante: ACIN\nURL para Apresentação: https://www.acingov.pt\nAdmissibilidade da apresentação de propostas variantes: Não autorizado\nPrazo para apresentação das propostas: 16-08-2025 23:59\nPrazo durante o qual os concorrentes são obrigados a manter as respetivas propostas: 66 dias a contar do termo do prazo para a apresentação das propostas\nIndicação de Subcontratação na Proposta: Inexistência de indicação de subcontratação\n\n14 - PRESTAÇÃO DE CAUÇÃO\nPrestação de caução: Sim\nPercentagem: 5%\nDescrição da Garantia Exigida: O valor da caução é de 5.00% do preço contratual.\n\n15 - FORNECIMENTO DAS PEÇAS DO CONCURSO, APRESENTAÇÃO DE PEDIDOS DE PARTICIPAÇÃO E APRESENTAÇÃO DAS PROPOSTAS\nLink para acesso às peças do concurso (URL): https://www.acingov.pt/acingovprod/2/zonaPublica/zona_publica_c/donwloadProcedurePiece/ODIyMDk4\n\n20 - OUTROS REQUISITOS\nInformação sobre contratos reservados. Aplica-se a contratos reservados (54º-A)? Não\n\n21 - CRITÉRIO DE ADJUDICAÇÃO\nMultifator: Sim\nFator: \nNome: Preço\nPonderação: 70%\nSubfatores: Não\nFator: \nNome: Outros\nOutro Nome: Valia Técnica\nPonderação: 30%\nSubfatores: SimSubfatores: \nNome: Metodologia de execução da obra (inclui avaliação da utilização de materiais reutilizados ou reciclados)\nPonderação : 30%; \nNome: Detalhe e consistência do Plano de Trabalhos (Plano de trabalhos)\nPonderação : 52.5%; \nNome: Detalhe e consistência do Plano de Trabalhos (Plano de meios)\nPonderação : 17.5%; \n\n24 - CONDIÇÕES DO CONTRATO\nFaturação Eletrónica: Permitido\nObrigação de Subcontratação:\nCódigo da Obrigação de Subcontratação: Não é aplicável nenhuma obrigação de subcontratação.\n\n25 - COMPRA PÚBLICA ESTRATÉGICA\nCompra Pública Estratégica: Inexistência de contratação pública estratégica\n\n26 - INFORMAÇÕES ADICIONAIS\nContrato adequado para PME: Sim\nCobertura ACP (Acordo dos Contratos Públicos da Organização Mundial do Comércio): Não\n\n27 - IDENTIFICAÇÃO E CONTACTOS DO ÓRGÃO DE RECURSOS ADMINISTRATIVOS\nDesignação: Semi Internato Nossa Senhora da Encarnação\nEndereço: Rua Francisco da Silva, n.º 9\nCódigo postal: 7350-272\nLocalidade: Elvas\nTelefone: 268636430\nFax: \nEndereço eletrónico: sinsencarnacao@sapo.pt\nPrazo de interposição do recurso: 5 dias\n\n28 - IDENTIFICAÇÃO DO(S) AUTOR(ES) DE ANÚNCIO\nNome: Maria Goreti Pereira Pedrosa\nCargo: Presidente do Conselho de Administração\n419388301",
    "nipc": "500875847",
    "distrito": "Portalegre",
    "concelho": "Elvas",
    "freguesia": "Freguesia de Caia, São Pedro e Alcáçova",
    "site": "www.concepcionistas.pt",
    "email": "sinsencarnacao@sapo.pt",
    "designacao_contrato": "Empreitada de Requalificação / Remodelação da Creche do Semi internato Nossa Senhora Encarnação, financiada pela candidatura n.º PRR-RE-C03-i01-09-000308",
    "descricao": "Requalificação / Remodelação da Creche do Semi internato Nossa Senhora Encarnação, financiada pela candidatura n.º PRR-RE-C03-i01-09-000308",
    "preco_base": "1.114.760,26 EUR",
    "prazo_execucao": "9 MESES",
    "prazo_apresentacao_propostas": "16-08-2025 23:59",
    "fundos_eu": "Sim",
    "plataforma_eletronica": "ACIN",
    "url_procedimento": "https://www.acingov.pt",
    "autor_nome": "Maria Goreti Pereira Pedrosa",
    "autor_cargo": "Presidente do Conselho de Administração"
  },
  {
    "numero_procedimento": "N/A",
    "entidade": "Junta de Freguesia de Alvalade",
    "link": "https://diariodarepublica.pt/dr/detalhe/contrato-publico/21021-927729757",
    "detalhes_completos": "1 - IDENTIFICAÇÃO E CONTACTOS DA ENTIDADE ADJUDICANTE\nDesignação da entidade adjudicante: Junta de Freguesia de Alvalade\nNIPC: 510832806\nEndereço: Largo Machado de Assis, S/N \nCódigo postal: 1700-116\nLocalidade: Lisboa\nPaís: Portugal\nNUT III: PT170\nDistrito: Lisboa\nConcelho: Lisboa\nFreguesia: Freguesia de Alvalade - Lisboa\nTelefone: 218428370\nEndereço Eletrónico: geral@jf-alvalade.pt\neDelivery Gateway (URL): https://community.vortal.biz/public/\nFunção da Organização: Adquirente\nNorma jurídica da Entidade Adjudicante: Organismo de direito público\nÁrea de atividade da Autoridade Adjudicante: Serviços públicos das administrações públicas\n\n2 - JORNAL OFICIAL DA UNIÃO EUROPEIA\nO procedimento a que este anúncio diz respeito também é publicitado no Jornal Oficial da União Europeia? Não\n\n3 - AVISO\nModelo de Anúncio: Concurso público\nData de Envio do Anúncio: 04-08-2025\n\n5 - PROCESSO\nTipo de Procedimento: Concurso público\nPreço base do procedimento: Sim\nValor do preço base do procedimento: 195.000,00 EUR\nProcedimento com lotes? Não\n\n6 - OBJETO DO CONTRATO\nNúmero de referência interna: Processo n.º 59/CP/JFA/2025\nDesignação do contrato: Fornecimento de energia elétrica em baixa tensão especial e baixa tensão normal para as instalações da Freguesia de Alvalade” - Processo n.º 59/CP/JFA/2025\nDescrição: Fornecimento de energia elétrica em baixa tensão especial e baixa tensão normal para as instalações da Freguesia de Alvalade” - Processo n.º 59/CP/JFA/2025\nTipo de Contrato Principal: Aquisição de Bens Móveis\nTipo de Contrato: Aquisição de Bens Móveis\nClassificação CPV (Vocabulário Comum para os Contratos Públicos)\nObjeto principal\nVocabulário Principal: 09310000\nPreço base s/IVA: 195.000,00 EUR\n\n7 - INDICAÇÕES ADICIONAIS\nO contrato envolve aquisição conjunta (satisfação de várias entidades)? Não\nO contrato é adjudicado por uma central de compras? Não\n\n8 - TÉCNICAS\nO concurso destina-se à celebração de um acordo-quadro? Inexistência de acordo-quadro\nÉ utilizado um leilão eletrónico? Não\nÉ adotada uma fase de negociação? Não\nSistema de Aquisição Dinâmico: Inexistência de sistema de aquisição dinâmico\n\n9 - LOCAL DA EXECUÇÃO DO CONTRATO\nLOCAL DA EXECUÇÃO DO CONTRATO (PROCEDIMENTO)\nPaís: Portugal\nNUT III: PT170\nLocalidade: Lisboa\nDistrito: Lisboa\nConcelho: Lisboa\nFreguesia: Freguesia de Alvalade - Lisboa\n\n10 - PRAZO DE EXECUÇÃO DO CONTRATO\nPrazo de execução do contrato: 10 MESES\nPrevisão de renovações: Não\n\n11 - FUNDOS EU\nTêm fundos EU? Não\n\n12 - DOCUMENTOS DE HABILITAÇÃO\nHabilitação para o exercício da atividade profissional: Sim\nTipo: Outros\nDescrição - Outros: Autorização comercializador de energia \nDescrição: Comercializador de energia elétrica \n\n13 - CONDIÇÕES DE APRESENTAÇÃO\nPlataforma eletrónica utilizada pela entidade adjudicante: VORTAL\nURL para Apresentação: https://community.vortal.biz/public/\nAdmissibilidade da apresentação de propostas variantes: Não autorizado\nPrazo para apresentação das propostas: 13-08-2025 23:59\nPrazo durante o qual os concorrentes são obrigados a manter as respetivas propostas: 66 dias a contar do termo do prazo para a apresentação das propostas\nIndicação de Subcontratação na Proposta: Inexistência de indicação de subcontratação\n\n14 - PRESTAÇÃO DE CAUÇÃO\nPrestação de caução: Não\n\n15 - FORNECIMENTO DAS PEÇAS DO CONCURSO, APRESENTAÇÃO DE PEDIDOS DE PARTICIPAÇÃO E APRESENTAÇÃO DAS PROPOSTAS\nLink para acesso às peças do concurso (URL): https://community.vortal.biz/Public/public-tender-documents/V0RzQXZVeFdZNE5yUXNOUTVWM240cFYvckxTQTF3eWc5dnUrb2hMMGRBTnAyOUp0bFNkNm5mZ1Uxd0xhWkNDS0dUemtveG5HMEpkVmE1bEFkemUxY0E9PVRITEhh\n\n20 - OUTROS REQUISITOS\nInformação sobre contratos reservados. Aplica-se a contratos reservados (54º-A)? Não\n\n21 - CRITÉRIO DE ADJUDICAÇÃO\nMultifator: Não\nMonofator:\nNome: Preço\n\n24 - CONDIÇÕES DO CONTRATO\nFaturação Eletrónica: Permitido\nObrigação de Subcontratação:\nCódigo da Obrigação de Subcontratação: Não é aplicável nenhuma obrigação de subcontratação.\n\n25 - COMPRA PÚBLICA ESTRATÉGICA\nCompra Pública Estratégica: Inexistência de contratação pública estratégica\n\n26 - INFORMAÇÕES ADICIONAIS\nContrato adequado para PME: Sim\nCobertura ACP (Acordo dos Contratos Públicos da Organização Mundial do Comércio): Não\n\n27 - IDENTIFICAÇÃO E CONTACTOS DO ÓRGÃO DE RECURSOS ADMINISTRATIVOS\nDesignação: Junta de Freguesia de Alvalade\nEndereço: Largo Machado de Assis, S/N\nCódigo postal: 1700-116\nLocalidade: Lisboa\nTelefone: +351 218428370\nFax: +351 218428399\nEndereço eletrónico: geral@jf-alvalade.pt\n\n28 - IDENTIFICAÇÃO DO(S) AUTOR(ES) DE ANÚNCIO\nNome: Miguel Tomás Cabral Gonçalves\nCargo: Presidente da Junta de Freguesia de Alvalade \n419391306",
    "nipc": "510832806",
    "distrito": "Lisboa",
    "concelho": "Lisboa",
    "freguesia": "Freguesia de Alvalade - Lisboa",
    "site": null,
    "email": "geral@jf-alvalade.pt",
    "designacao_contrato": "Fornecimento de energia elétrica em baixa tensão especial e baixa tensão normal para as instalações da Freguesia de Alvalade” - Processo n.º 59/CP/JFA/2025",
    "descricao": "Fornecimento de energia elétrica em baixa tensão especial e baixa tensão normal para as instalações da Freguesia de Alvalade” - Processo n.º 59/CP/JFA/2025",
    "preco_base": "195.000,00 EUR",
    "prazo_execucao": "10 MESES",
    "prazo_apresentacao_propostas": "13-08-2025 23:59",
    "fundos_eu": "Não",
    "plataforma_eletronica": "VORTAL",
    "url_procedimento": "https://community.vortal.biz/public/",
    "autor_nome": "Miguel Tomás Cabral Gonçalves",
    "autor_cargo": "Presidente da Junta de Freguesia de Alvalade"
  },
  {
    "numero_procedimento": "N/A",
    "entidade": "Faculdade de Medicina Veterinária da Universidade de Lisboa",
    "link": "https://diariodarepublica.pt/dr/detalhe/contrato-publico/21022-927729758",
    "detalhes_completos": "Alteração do Anúncio de procedimento n.º 19899/2025, de 2025-07-24, com o ID 419351624\n\n1 - IDENTIFICAÇÃO E CONTACTOS DA ENTIDADE ADJUDICANTE\nDesignação da entidade adjudicante: Faculdade de Medicina Veterinária da Universidade de Lisboa\nNIPC: 502286326\nServiço/Órgão/Pessoa de contacto: Gabinete de Aprovisionamento e Património da FMV\nEndereço: Av.ª da Universidade Técnica\nCódigo postal: 1300-477\nLocalidade: LISBOA\nPaís: Portugal\nNUT III: PT170\nDistrito: Lisboa\nConcelho: Lisboa\nFreguesia: Freguesia de Ajuda\nTelefone: 213652800\nEndereço da Entidade (URL): http://www.fmv.ulisboa.pt/pt\nEndereço Eletrónico: cg@fmv.ulisboa.pt\neDelivery Gateway (URL): https://www.acingov.pt\nFunção da Organização: Adquirente\nNorma jurídica da Entidade Adjudicante: Organismo de direito público\nÁrea de atividade da Autoridade Adjudicante: Serviços públicos das administrações públicas\n\n2 - JORNAL OFICIAL DA UNIÃO EUROPEIA\nO procedimento a que este anúncio diz respeito também é publicitado no Jornal Oficial da União Europeia? Não\n\n3 - AVISO\nModelo de Anúncio: Concurso público\nData de Envio do Anúncio: 04-08-2025\n\n5 - PROCESSO\nTipo de Procedimento: Concurso público\nPreço base do procedimento: Sim\nValor do preço base do procedimento: 118.126,50 EUR\nProcedimento com lotes? Sim\nNº Máx. de Lotes Autorizado: 4\nNúmero máximo de lotes que podem ser adjudicados a um concorrente: 4\n\n6 - OBJETO DO CONTRATO\nNúmero de referência interna: Concurso Público 08/FMV/2025\nDesignação do contrato: Concurso Público 08/FMV/2025 - AQUISIÇÃO DE EQUIPAMENTOS PARA IMPLEMENTAÇÃO DA UIT - CIISA\nDescrição: Concurso Público 08/FMV/2025 - AQUISIÇÃO DE EQUIPAMENTOS PARA IMPLEMENTAÇÃO DA UIT - CIISA\nTipo de Contrato Principal: Aquisição de Bens Móveis\nTipo de Contrato: Aquisição de Bens Móveis\nClassificação CPV (Vocabulário Comum para os Contratos Públicos)\nObjeto principal\nVocabulário Principal: 33100000\nPreço base s/IVA: 118.126,50 EUR\nLotes: \nNº: LOT-0001\nDescrição do Lote: CÂMARAS DE FLUXO\nPreço base s/IVA: 13.060,00 EUR\nClassificação CPV (Vocabulário Comum para os Contratos Públicos)\nObjeto principal\nVocabulário Principal: 33100000\nNº: LOT-0002\nDescrição do Lote: INCUBADORA DE CO₂\nPreço base s/IVA: 6.292,00 EUR\nClassificação CPV (Vocabulário Comum para os Contratos Públicos)\nObjeto principal\nVocabulário Principal: 33100000\nNº: LOT-0003\nDescrição do Lote: SISTEMA DE CROMATOGRAFIA LÍQUIDA MODULAR\nPreço base s/IVA: 68.592,00 EUR\nClassificação CPV (Vocabulário Comum para os Contratos Públicos)\nObjeto principal\nVocabulário Principal: 33100000\nNº: LOT-0004\nDescrição do Lote: LOTE 4  PEQUENOS EQUIPAMENTOS DE LABORATÓRIO\nPreço base s/IVA: 30.182,50 EUR\nClassificação CPV (Vocabulário Comum para os Contratos Públicos)\nObjeto principal\nVocabulário Principal: 33100000\n\n7 - INDICAÇÕES ADICIONAIS\nO contrato envolve aquisição conjunta (satisfação de várias entidades)? Não\nO contrato é adjudicado por uma central de compras? Não\n\n8 - TÉCNICAS\nO concurso destina-se à celebração de um acordo-quadro? Inexistência de acordo-quadro\nÉ utilizado um leilão eletrónico? Não\nÉ adotada uma fase de negociação? Não\nSistema de Aquisição Dinâmico: Inexistência de sistema de aquisição dinâmico\n\n9 - LOCAL DA EXECUÇÃO DO CONTRATO\nLOCAL DA EXECUÇÃO DO CONTRATO (PROCEDIMENTO)\nPaís: Portugal\nNUT III: PT170\nLocalidade: Freguesia de Ajuda\nDistrito: Lisboa\nConcelho: Lisboa\nFreguesia: Freguesia de Ajuda\nLOCAL DA EXECUÇÃO DO CONTRATO (LOTE)\nIdentificador do Lote: LOT-0001; LOT-0002; LOT-0003; LOT-0004\nPaís: Portugal\nNUT III: PT170\nLocalidade: Freguesia de Ajuda\nDistrito: Lisboa\nConcelho: Lisboa\nFreguesia: Freguesia de Ajuda\n\n10 - PRAZO DE EXECUÇÃO DO CONTRATO\nIdentificador do Lote: LOT-0001; LOT-0002; LOT-0003; LOT-0004\nPrazo de execução do contrato: 15 DIAS\nPrevisão de renovações: Não\n\n11 - FUNDOS EU\nIdentificador do Lote: LOT-0001; LOT-0002; LOT-0003; LOT-0004\nTêm fundos EU? Não\n\n12 - DOCUMENTOS DE HABILITAÇÃO\nHabilitação para o exercício da atividade profissional: Não\n\n13 - CONDIÇÕES DE APRESENTAÇÃO\nPlataforma eletrónica utilizada pela entidade adjudicante: ACIN\nURL para Apresentação: https://www.acingov.pt\nAdmissibilidade da apresentação de propostas variantes: Não autorizado\nPrazo para apresentação das propostas: 08-08-2025 23:59\nPrazo durante o qual os concorrentes são obrigados a manter as respetivas propostas: 66 dias a contar do termo do prazo para a apresentação das propostas\nIndicação de Subcontratação na Proposta: Inexistência de indicação de subcontratação\n\n14 - PRESTAÇÃO DE CAUÇÃO\nPrestação de caução: Não\n\n15 - FORNECIMENTO DAS PEÇAS DO CONCURSO, APRESENTAÇÃO DE PEDIDOS DE PARTICIPAÇÃO E APRESENTAÇÃO DAS PROPOSTAS\nLink para acesso às peças do concurso (URL): https://www.acingov.pt/acingovprod/2/zonaPublica/zona_publica_c/donwloadProcedurePiece/OTI3MzMy\n\n20 - OUTROS REQUISITOS\nIdentificador do Lote: LOT-0001; LOT-0002; LOT-0003; LOT-0004\nInformação sobre contratos reservados. Aplica-se a contratos reservados (54º-A)? Não\n\n21 - CRITÉRIO DE ADJUDICAÇÃO\nO Critério de adjudicação é diferenciado por lote? Não\nMultifator: Não\nMonofator:\nNome: Preço\n\n24 - CONDIÇÕES DO CONTRATO\nIdentificador do Lote: LOT-0001; LOT-0002; LOT-0003; LOT-0004\nFaturação Eletrónica: Permitido\nObrigação de Subcontratação:\nCódigo da Obrigação de Subcontratação: Não é aplicável nenhuma obrigação de subcontratação.\n\n25 - COMPRA PÚBLICA ESTRATÉGICA\nCompra Pública Estratégica: Inexistência de contratação pública estratégica\n\n26 - INFORMAÇÕES ADICIONAIS\nIdentificador do Lote: LOT-0001; LOT-0002; LOT-0003; LOT-0004\nContrato adequado para PME: Não\nCobertura ACP (Acordo dos Contratos Públicos da Organização Mundial do Comércio): Não\n\n27 - IDENTIFICAÇÃO E CONTACTOS DO ÓRGÃO DE RECURSOS ADMINISTRATIVOS\nDesignação: Faculdade de Medicina Veterinária - ULisboa\nEndereço: Av.ª da Universidade Técnica\nCódigo postal: 1300-477\nLocalidade: Lisboa\nTelefone: 213652800\nFax: 213652800\nEndereço eletrónico: cg@fmv.ulisboa.pt\nPrazo de interposição do recurso: 10 dias\n\n28 - IDENTIFICAÇÃO DO(S) AUTOR(ES) DE ANÚNCIO\nNome: Fábio Jorge Carvalho Costa\nCargo: Técnico Superior\n\n29 - ALTERAÇÃO\nMotivo da Alteração: Correção pelo editor\nIdentificador da Versão do Anúncio a Alterar: acf4a9db-3292-4780-987a-62234cc2012b-01\nIdentificador das Secções Alteradas do Anúncio Anterior: Prazo de execução do contrato\nDescrição das Alterações: Na página 3 (três) do Caderno de Encargos, no n.º 1 da Cláusula 3.ª: Onde se lê (?) num prazo máximo de 15 dias. (?) Deverá passar a ler-se (?) num prazo máximo de 30 (trinta) dias. (?).\nAlteração dos Documentos do Concurso: Não\n419389939",
    "nipc": "502286326",
    "distrito": "Lisboa",
    "concelho": "Lisboa",
    "freguesia": "Freguesia de Ajuda",
    "site": "http://www.fmv.ulisboa.pt/pt",
    "email": "cg@fmv.ulisboa.pt",
    "designacao_contrato": "Concurso Público 08/FMV/2025 - AQUISIÇÃO DE EQUIPAMENTOS PARA IMPLEMENTAÇÃO DA UIT - CIISA",
    "descricao": "Concurso Público 08/FMV/2025 - AQUISIÇÃO DE EQUIPAMENTOS PARA IMPLEMENTAÇÃO DA UIT - CIISA",
    "preco_base": "118.126,50 EUR",
    "prazo_execucao": "15 DIAS",
    "prazo_apresentacao_propostas": "08-08-2025 23:59",
    "fundos_eu": "Não",
    "plataforma_eletronica": "ACIN",
    "url_procedimento": "https://www.acingov.pt",
    "autor_nome": "Fábio Jorge Carvalho Costa",
    "autor_cargo": "Técnico Superior"
  },
  {
    "numero_procedimento": "N/A",
    "entidade": "GEBALIS - Gestão do Arrendamento da Habitação Municipal de Lisboa, E.M., S.A.",
    "link": "https://diariodarepublica.pt/dr/detalhe/contrato-publico/21023-927729759",
    "detalhes_completos": "1 - IDENTIFICAÇÃO E CONTACTOS DA ENTIDADE ADJUDICANTE\nDesignação da entidade adjudicante: GEBALIS - Gestão do Arrendamento da Habitação Municipal de Lisboa, E.M., S.A.\nNIPC: 503541567\nServiço/Órgão/Pessoa de contacto: Joana Pereira\nEndereço: Rua Laura Alves, n.º 12, 7º Piso\nCódigo postal: 1050-138\nLocalidade: Lisboa\nPaís: Portugal\nNUT III: PT170\nDistrito: Lisboa\nConcelho: Lisboa\nFreguesia: Freguesia de Avenidas Novas\nTelefone: 217511000\nFax: 217511000\nEndereço da Entidade (URL): www.gebalis.pt\nEndereço Eletrónico: contratacao.publica@gebalis.pt\nFunção da Organização: Adquirente\nNorma jurídica da Entidade Adjudicante: Empresa pública, controlada por uma autoridade local\nÁrea de atividade da Autoridade Adjudicante: Habitação e equipamentos coletivos\n\n2 - JORNAL OFICIAL DA UNIÃO EUROPEIA\nO procedimento a que este anúncio diz respeito também é publicitado no Jornal Oficial da União Europeia? Não\n\n3 - AVISO\nModelo de Anúncio: Concurso público\nData de Envio do Anúncio: 05-08-2025\n\n5 - PROCESSO\nTipo de Procedimento: Concurso público\nPreço base do procedimento: Sim\nValor do preço base do procedimento: 4.547.285,81 EUR\nProcedimento com lotes? Não\n\n6 - OBJETO DO CONTRATO\nNúmero de referência interna: Empreitada 55/Gebalis/2025 \nDesignação do contrato: Empreitada 55/GEBALIS/2025 - Bairro do Condado ¿ Obras de reabilitação e conservação de edifícios\nDescrição: Empreitada 55/GEBALIS/2025 - Bairro do Condado ¿ Obras de reabilitação e conservação de edifícios\nTipo de Contrato Principal: Empreitada de Obras Públicas\nTipo de Contrato: Empreitada de Obras Públicas\nClassificação CPV (Vocabulário Comum para os Contratos Públicos)\nObjeto principal\nVocabulário Principal: 45453100\nPreço base s/IVA: 4.547.285,81 EUR\n\n7 - INDICAÇÕES ADICIONAIS\nO contrato envolve aquisição conjunta (satisfação de várias entidades)? Não\nO contrato é adjudicado por uma central de compras? Não\n\n8 - TÉCNICAS\nO concurso destina-se à celebração de um acordo-quadro? Inexistência de acordo-quadro\nÉ utilizado um leilão eletrónico? Não\nÉ adotada uma fase de negociação? Não\nSistema de Aquisição Dinâmico: Inexistência de sistema de aquisição dinâmico\n\n9 - LOCAL DA EXECUÇÃO DO CONTRATO\nLOCAL DA EXECUÇÃO DO CONTRATO (PROCEDIMENTO)\nPaís: Portugal\nNUT III: PT170\nLocalidade: Lisboa\nDistrito: Lisboa\nConcelho: Lisboa\nFreguesia: Freguesia de Marvila - Lisboa\n\n10 - PRAZO DE EXECUÇÃO DO CONTRATO\nPrazo de execução do contrato: 12 MESES\nPrevisão de renovações: Não\n\n11 - FUNDOS EU\nTêm fundos EU? Não\n\n12 - DOCUMENTOS DE HABILITAÇÃO\nHabilitação para o exercício da atividade profissional: Sim\nTipo: Alvará\nDescrição: Conforme Programa de Concurso\n\n13 - CONDIÇÕES DE APRESENTAÇÃO\nPlataforma eletrónica utilizada pela entidade adjudicante: ANOGOV\nURL para Apresentação: https://www.anogov.com/em-gebalis/faces/\nAdmissibilidade da apresentação de propostas variantes: Não autorizado\nPrazo para apresentação das propostas: 26-08-2025 23:59\nPrazo durante o qual os concorrentes são obrigados a manter as respetivas propostas: 180 dias a contar do termo do prazo para a apresentação das propostas\nApresentação de Catálogo Eletrónico: Permitido\nIndicação de Subcontratação na Proposta: Inexistência de indicação de subcontratação\n\n14 - PRESTAÇÃO DE CAUÇÃO\nPrestação de caução: Sim\nPercentagem: 5%\nDescrição da Garantia Exigida: Ponto 21 Programa Concurso\n\n15 - FORNECIMENTO DAS PEÇAS DO CONCURSO, APRESENTAÇÃO DE PEDIDOS DE PARTICIPAÇÃO E APRESENTAÇÃO DAS PROPOSTAS\nLink para acesso às peças do concurso (URL): https://www.anogov.com/em-gebalis/faces/app/acessoDocs.jsp?codigoAcesso=pg6mhT6wbJmXaNUD695A5zVXlrAirDRMbl4t1MnSQxVbFlqjp3\n\n20 - OUTROS REQUISITOS\nInformação sobre contratos reservados. Aplica-se a contratos reservados (54º-A)? Não\n\n21 - CRITÉRIO DE ADJUDICAÇÃO\nMultifator: Sim\nFator: \nNome: Qualidade\nPonderação: 30%\nSubfatores: Não\nFator: \nNome: Outros\nOutro Nome: Prazo\nPonderação: 10%\nSubfatores: Não\nFator: \nNome: Preço\nPonderação: 60%\nSubfatores: Não\n\n24 - CONDIÇÕES DO CONTRATO\nFaturação Eletrónica: Permitido\nObrigação de Subcontratação:\nCódigo da Obrigação de Subcontratação: Não é aplicável nenhuma obrigação de subcontratação.\n\n25 - COMPRA PÚBLICA ESTRATÉGICA\nCompra Pública Estratégica: Inexistência de contratação pública estratégica\n\n26 - INFORMAÇÕES ADICIONAIS\nContrato adequado para PME: Não\nCobertura ACP (Acordo dos Contratos Públicos da Organização Mundial do Comércio): Não\n\n27 - IDENTIFICAÇÃO E CONTACTOS DO ÓRGÃO DE RECURSOS ADMINISTRATIVOS\nDesignação: Conselho de Administração\nEndereço: Rua Laura Alves, 12, 7º\nCódigo postal: 1050-138\nLocalidade: Lisboa\nEndereço eletrónico: contratacao.publica@gebalis.pt\n\n28 - IDENTIFICAÇÃO DO(S) AUTOR(ES) DE ANÚNCIO\nNome: Miguel Silva Pereira\nCargo: Vogal Conselho de Administração\n419396272",
    "nipc": "503541567",
    "distrito": "Lisboa",
    "concelho": "Lisboa",
    "freguesia": "Freguesia de Avenidas Novas",
    "site": "www.gebalis.pt",
    "email": "contratacao.publica@gebalis.pt",
    "designacao_contrato": "Empreitada 55/GEBALIS/2025 - Bairro do Condado ¿ Obras de reabilitação e conservação de edifícios",
    "descricao": "Empreitada 55/GEBALIS/2025 - Bairro do Condado ¿ Obras de reabilitação e conservação de edifícios",
    "preco_base": "4.547.285,81 EUR",
    "prazo_execucao": "12 MESES",
    "prazo_apresentacao_propostas": "26-08-2025 23:59",
    "fundos_eu": "Não",
    "plataforma_eletronica": "ANOGOV",
    "url_procedimento": "https://www.anogov.com/em-gebalis/faces/",
    "autor_nome": "Miguel Silva Pereira",
    "autor_cargo": "Vogal Conselho de Administração"
  },
  {
    "numero_procedimento": "N/A",
    "entidade": "Município da Guarda",
    "link": "https://diariodarepublica.pt/dr/detalhe/contrato-publico/21000-927882298",
    "detalhes_completos": "1 - IDENTIFICAÇÃO E CONTACTOS DA ENTIDADE ADJUDICANTE\nDesignação da entidade adjudicante: Município da Guarda\nNIPC: 501131140\nEndereço: Praça do Município, nº 1\nCódigo postal: 6301-854\nLocalidade: Guarda\nPaís: Portugal\nNUT III: PT16J\nDistrito: Guarda\nConcelho: Guarda\nFreguesia: Freguesia de Guarda\nTelefone: 271220200\nFax: 271220280\nEndereço da Entidade (URL): www.mun-guarda.pt\nEndereço Eletrónico: geral@mun-guarda.pt\neDelivery Gateway (URL): https://community.vortal.biz/public/\nFunção da Organização: Adquirente\nNorma jurídica da Entidade Adjudicante: Autoridade da administração central\nÁrea de atividade da Autoridade Adjudicante: Serviços públicos das administrações públicas\n\n2 - JORNAL OFICIAL DA UNIÃO EUROPEIA\nO procedimento a que este anúncio diz respeito também é publicitado no Jornal Oficial da União Europeia? Não\n\n3 - AVISO\nModelo de Anúncio: Concurso público\nData de Envio do Anúncio: 04-08-2025\n\n5 - PROCESSO\nTipo de Procedimento: Concurso público\nPreço base do procedimento: Sim\nValor do preço base do procedimento: 660.799,75 EUR\nProcedimento com lotes? Não\n\n6 - OBJETO DO CONTRATO\nNúmero de referência interna: DAM/PI-2025-26\nDesignação do contrato: Instalação de 5 Espaços de Jogo e Recreio Infantil\nDescrição: Instalação de 5 Espaços de Jogo e Recreio Infantil\nTipo de Contrato Principal: Empreitada de Obras Públicas\nTipo de Contrato: Empreitada de Obras Públicas\nClassificação CPV (Vocabulário Comum para os Contratos Públicos)\nObjeto principal\nVocabulário Principal: 45112720\nPreço base s/IVA: 660.799,75 EUR\n\n7 - INDICAÇÕES ADICIONAIS\nO contrato envolve aquisição conjunta (satisfação de várias entidades)? Não\nO contrato é adjudicado por uma central de compras? Não\n\n8 - TÉCNICAS\nO concurso destina-se à celebração de um acordo-quadro? Inexistência de acordo-quadro\nÉ utilizado um leilão eletrónico? Não\nÉ adotada uma fase de negociação? Não\nSistema de Aquisição Dinâmico: Inexistência de sistema de aquisição dinâmico\n\n9 - LOCAL DA EXECUÇÃO DO CONTRATO\nLOCAL DA EXECUÇÃO DO CONTRATO (PROCEDIMENTO)\nPaís: Portugal\nNUT III: PT16J\nLocalidade: Guarda\nDistrito: Guarda\nConcelho: Guarda\nFreguesia: Freguesia de Guarda\n\n10 - PRAZO DE EXECUÇÃO DO CONTRATO\nPrazo de execução do contrato: 180 DIAS\nPrevisão de renovações: Não\n\n11 - FUNDOS EU\nTêm fundos EU? Não\n\n12 - DOCUMENTOS DE HABILITAÇÃO\nHabilitação para o exercício da atividade profissional: Não\n\n13 - CONDIÇÕES DE APRESENTAÇÃO\nPlataforma eletrónica utilizada pela entidade adjudicante: VORTAL\nURL para Apresentação: https://community.vortal.biz/public/\nAdmissibilidade da apresentação de propostas variantes: Não autorizado\nPrazo para apresentação das propostas: 04-09-2025 16:00\nPrazo durante o qual os concorrentes são obrigados a manter as respetivas propostas: 66 dias a contar do termo do prazo para a apresentação das propostas\nIndicação de Subcontratação na Proposta: Inexistência de indicação de subcontratação\n\n14 - PRESTAÇÃO DE CAUÇÃO\nPrestação de caução: Sim\nPercentagem: 5%\nDescrição da Garantia Exigida: Conforme anexos ao programa de procedimento\n\n15 - FORNECIMENTO DAS PEÇAS DO CONCURSO, APRESENTAÇÃO DE PEDIDOS DE PARTICIPAÇÃO E APRESENTAÇÃO DAS PROPOSTAS\nLink para acesso às peças do concurso (URL): https://community.vortal.biz/Public/public-tender-documents/UGxoaVlvbVZEYnBUNVJDNkE0aHFLZ0ZsV2k1U041WkdhSENveHJJOVVhK2xYT0pGUWtnT293RzBKSk5LWGxBemEyN1VvMVdpSjdCcUxiYURRVXV1UFE9PVdhZ1py\n\n20 - OUTROS REQUISITOS\nInformação sobre contratos reservados. Aplica-se a contratos reservados (54º-A)? Não\n\n21 - CRITÉRIO DE ADJUDICAÇÃO\nMultifator: Sim\nFator: \nNome: Preço\nPonderação: 50%\nSubfatores: Não\nFator: \nNome: Qualidade\nPonderação: 50%\nSubfatores: SimSubfatores: \nNome: Adequação ao Conceito\nPonderação : 40%; \nNome: Equipa Técnica\nPonderação : 35%; \nNome: Prazo de Garantia e de Manutenção\nPonderação : 25%; \n\n24 - CONDIÇÕES DO CONTRATO\nFaturação Eletrónica: Permitido\nObrigação de Subcontratação:\nCódigo da Obrigação de Subcontratação: Não é aplicável nenhuma obrigação de subcontratação.\n\n25 - COMPRA PÚBLICA ESTRATÉGICA\nCompra Pública Estratégica: Inexistência de contratação pública estratégica\n\n26 - INFORMAÇÕES ADICIONAIS\nContrato adequado para PME: Sim\nCobertura ACP (Acordo dos Contratos Públicos da Organização Mundial do Comércio): Não\n\n27 - IDENTIFICAÇÃO E CONTACTOS DO ÓRGÃO DE RECURSOS ADMINISTRATIVOS\nDesignação: Presidente da Câmara Municipal da Guarda\nEndereço: Praça do Municipio.\nCódigo postal: 6301-854\nLocalidade: Guarda\nTelefone: +351 271220200\nFax: +351 271220280\nEndereço eletrónico: contratacaopublica@mun-guarda.pt\n\n28 - IDENTIFICAÇÃO DO(S) AUTOR(ES) DE ANÚNCIO\nNome: Sérgio Fernando da Silva Costa\nCargo: O Presidente da Câmara Municipal da Guarda\n419393518",
    "nipc": "501131140",
    "distrito": "Guarda",
    "concelho": "Guarda",
    "freguesia": "Freguesia de Guarda",
    "site": "www.mun-guarda.pt",
    "email": "geral@mun-guarda.pt",
    "designacao_contrato": "Instalação de 5 Espaços de Jogo e Recreio Infantil",
    "descricao": "Instalação de 5 Espaços de Jogo e Recreio Infantil",
    "preco_base": "660.799,75 EUR",
    "prazo_execucao": "180 DIAS",
    "prazo_apresentacao_propostas": "04-09-2025 16:00",
    "fundos_eu": "Não",
    "plataforma_eletronica": "VORTAL",
    "url_procedimento": "https://community.vortal.biz/public/",
    "autor_nome": "Sérgio Fernando da Silva Costa",
    "autor_cargo": "O Presidente da Câmara Municipal da Guarda"
  },
  {
    "numero_procedimento": "N/A",
    "entidade": "Unidade Local de Saúde de Entre O Douro e Vouga, E.P.E",
    "link": "https://diariodarepublica.pt/dr/detalhe/contrato-publico/21001-927882299",
    "detalhes_completos": "1 - IDENTIFICAÇÃO E CONTACTOS DA ENTIDADE ADJUDICANTE\nDesignação da entidade adjudicante: Unidade Local de Saúde de Entre O Douro e Vouga, E.P.E\nNIPC: 508878462\nEndereço: RUA DOUTOR CÂNDIDO DE PINHO\nCódigo postal: 4520-211\nLocalidade: Aveiro\nPaís: Portugal\nNUT III: PT11A\nDistrito: Aveiro\nConcelho: Santa Maria da Feira\nFreguesia: União das Freguesias de Santa Maria da Feira, Travanca, Sanfins e Espargo\nTelefone: 256379735\nEndereço da Entidade (URL): www.ulsedv.min-saude.pt\nEndereço Eletrónico: concursos@ulsedv.min-saude.pt\neDelivery Gateway (URL): https://community.vortal.biz/public/\nFunção da Organização: Adquirente\nNorma jurídica da Entidade Adjudicante: Organismo de direito público\nÁrea de atividade da Autoridade Adjudicante: Saúde\n\n2 - JORNAL OFICIAL DA UNIÃO EUROPEIA\nO procedimento a que este anúncio diz respeito também é publicitado no Jornal Oficial da União Europeia? Não\n\n3 - AVISO\nModelo de Anúncio: Concurso público\nData de Envio do Anúncio: 04-08-2025\n\n5 - PROCESSO\nTipo de Procedimento: Concurso público\nPreço base do procedimento: Sim\nValor do preço base do procedimento: 39.180,00 EUR\nProcedimento com lotes? Não\n\n6 - OBJETO DO CONTRATO\nNúmero de referência interna: 02/03329.62/2025\nDesignação do contrato: Aquisição de ofertas para Programa \"Prescrição de Saúde e Bem-Estar\"\nDescrição: Aquisição de ofertas para Programa \"Prescrição de Saúde e Bem-Estar\"\nTipo de Contrato Principal: Aquisição de Serviços\nTipo de Contrato: Aquisição de Serviços\nClassificação CPV (Vocabulário Comum para os Contratos Públicos)\nObjeto principal\nVocabulário Principal: 79340000\nPreço base s/IVA: 39.180,00 EUR\n\n7 - INDICAÇÕES ADICIONAIS\nO contrato envolve aquisição conjunta (satisfação de várias entidades)? Não\nO contrato é adjudicado por uma central de compras? Não\n\n8 - TÉCNICAS\nO concurso destina-se à celebração de um acordo-quadro? Inexistência de acordo-quadro\nÉ utilizado um leilão eletrónico? Não\nÉ adotada uma fase de negociação? Não\nSistema de Aquisição Dinâmico: Inexistência de sistema de aquisição dinâmico\n\n9 - LOCAL DA EXECUÇÃO DO CONTRATO\nLOCAL DA EXECUÇÃO DO CONTRATO (PROCEDIMENTO)\nPaís: Portugal\nNUT III: PT11A\nLocalidade: Aveiro\nDistrito: Aveiro\nConcelho: Santa Maria da Feira\nFreguesia: União das Freguesias de Santa Maria da Feira, Travanca, Sanfins e Espargo\n\n10 - PRAZO DE EXECUÇÃO DO CONTRATO\nPrazo de execução do contrato: 60 DIAS\nPrevisão de renovações: Não\n\n11 - FUNDOS EU\nTêm fundos EU? Sim\n\n12 - DOCUMENTOS DE HABILITAÇÃO\nHabilitação para o exercício da atividade profissional: Não\n\n13 - CONDIÇÕES DE APRESENTAÇÃO\nPlataforma eletrónica utilizada pela entidade adjudicante: VORTAL\nURL para Apresentação: https://community.vortal.biz/public/\nAdmissibilidade da apresentação de propostas variantes: Não autorizado\nPrazo para apresentação das propostas: 14-08-2025 17:00\nPrazo durante o qual os concorrentes são obrigados a manter as respetivas propostas: 90 dias a contar do termo do prazo para a apresentação das propostas\nIndicação de Subcontratação na Proposta: Inexistência de indicação de subcontratação\n\n14 - PRESTAÇÃO DE CAUÇÃO\nPrestação de caução: Não\n\n15 - FORNECIMENTO DAS PEÇAS DO CONCURSO, APRESENTAÇÃO DE PEDIDOS DE PARTICIPAÇÃO E APRESENTAÇÃO DAS PROPOSTAS\nLink para acesso às peças do concurso (URL): https://community.vortal.biz/Public/public-tender-documents/aVZLUjRJR1J0TVYxeEd4YitGUkxKbEtsSEd2b2NqWlBpamFZbm5tRTFkTUplRmExVDBqdDhxNFdRMElqSHhoZ1lsTURLWk9TR0ZtU2xOVlVmelFlZlE9PU0lS05N\n\n20 - OUTROS REQUISITOS\nInformação sobre contratos reservados. Aplica-se a contratos reservados (54º-A)? Não\n\n21 - CRITÉRIO DE ADJUDICAÇÃO\nMultifator: Não\nMonofator:\nNome: Preço\n\n24 - CONDIÇÕES DO CONTRATO\nFaturação Eletrónica: Permitido\nObrigação de Subcontratação:\nCódigo da Obrigação de Subcontratação: Não é aplicável nenhuma obrigação de subcontratação.\n\n25 - COMPRA PÚBLICA ESTRATÉGICA\nCompra Pública Estratégica: Inexistência de contratação pública estratégica\n\n26 - INFORMAÇÕES ADICIONAIS\nContrato adequado para PME: Sim\nCobertura ACP (Acordo dos Contratos Públicos da Organização Mundial do Comércio): Não\n\n27 - IDENTIFICAÇÃO E CONTACTOS DO ÓRGÃO DE RECURSOS ADMINISTRATIVOS\nDesignação: Conselho de Administração da ULSEDV, EPE\nEndereço: Rua Dr. Cândido de Pinho, 4520-211 Santa Maria da Feira,\nCódigo postal: 4520-211\nLocalidade: Santa Maria da Feira\nTelefone: +351 256379700\nFax: +351 256379778\nEndereço eletrónico: geral@ulsedv.min-saude.pt\n\n28 - IDENTIFICAÇÃO DO(S) AUTOR(ES) DE ANÚNCIO\nNome: Teresa Dias\nCargo: Assistente Técnica\n419395673",
    "nipc": "508878462",
    "distrito": "Aveiro",
    "concelho": "Santa Maria da Feira",
    "freguesia": "União das Freguesias de Santa Maria da Feira, Travanca, Sanfins e Espargo",
    "site": "www.ulsedv.min-saude.pt",
    "email": "concursos@ulsedv.min-saude.pt",
    "designacao_contrato": "Aquisição de ofertas para Programa \"Prescrição de Saúde e Bem-Estar\"",
    "descricao": "Aquisição de ofertas para Programa \"Prescrição de Saúde e Bem-Estar\"",
    "preco_base": "39.180,00 EUR",
    "prazo_execucao": "60 DIAS",
    "prazo_apresentacao_propostas": "14-08-2025 17:00",
    "fundos_eu": "Sim",
    "plataforma_eletronica": "VORTAL",
    "url_procedimento": "https://community.vortal.biz/public/",
    "autor_nome": "Teresa Dias",
    "autor_cargo": "Assistente Técnica"
  },
  {
    "numero_procedimento": "N/A",
    "entidade": "Município da Guarda",
    "link": "https://diariodarepublica.pt/dr/detalhe/contrato-publico/21002-927882300",
    "detalhes_completos": "Alteração do Anúncio de procedimento n.º 19664/2025, de 2025-07-23, com o ID 419342593\n\n1 - IDENTIFICAÇÃO E CONTACTOS DA ENTIDADE ADJUDICANTE\nDesignação da entidade adjudicante: Município da Guarda\nNIPC: 501131140\nEndereço: Praça do Município, nº 1\nCódigo postal: 6301-854\nLocalidade: Guarda\nPaís: Portugal\nNUT III: PT16J\nDistrito: Guarda\nConcelho: Guarda\nFreguesia: Freguesia de Guarda\nTelefone: 271220200\nFax: 271220280\nEndereço da Entidade (URL): www.mun-guarda.pt\nEndereço Eletrónico: geral@mun-guarda.pt\neDelivery Gateway (URL): https://community.vortal.biz/public/\nFunção da Organização: Adquirente\nNorma jurídica da Entidade Adjudicante: Autoridade da administração central\nÁrea de atividade da Autoridade Adjudicante: Serviços públicos das administrações públicas\n\n2 - JORNAL OFICIAL DA UNIÃO EUROPEIA\nO procedimento a que este anúncio diz respeito também é publicitado no Jornal Oficial da União Europeia? Não\n\n3 - AVISO\nModelo de Anúncio: Concurso público\nData de Envio do Anúncio: 04-08-2025\n\n5 - PROCESSO\nTipo de Procedimento: Concurso público\nPreço base do procedimento: Sim\nValor do preço base do procedimento: 520.974,47 EUR\nProcedimento com lotes? Não\n\n6 - OBJETO DO CONTRATO\nNúmero de referência interna: DOPEI/CD-2025-25\nDesignação do contrato: Equipamentos e Infraestruturas do Ecossistema do Bairro Comercial Digital da Guarda - Zona Alta\nDescrição: Equipamentos e Infraestruturas do Ecossistema do Bairro Comercial Digital da Guarda - Zona Alta\nTipo de Contrato Principal: Empreitada de Obras Públicas\nTipo de Contrato: Empreitada de Obras Públicas\nClassificação CPV (Vocabulário Comum para os Contratos Públicos)\nObjeto principal\nVocabulário Principal: 45220000\nPreço base s/IVA: 520.974,47 EUR\n\n7 - INDICAÇÕES ADICIONAIS\nO contrato envolve aquisição conjunta (satisfação de várias entidades)? Não\nO contrato é adjudicado por uma central de compras? Não\n\n8 - TÉCNICAS\nO concurso destina-se à celebração de um acordo-quadro? Inexistência de acordo-quadro\nÉ utilizado um leilão eletrónico? Não\nÉ adotada uma fase de negociação? Não\nSistema de Aquisição Dinâmico: Inexistência de sistema de aquisição dinâmico\n\n9 - LOCAL DA EXECUÇÃO DO CONTRATO\nLOCAL DA EXECUÇÃO DO CONTRATO (PROCEDIMENTO)\nPaís: Portugal\nNUT III: PT16J\nLocalidade: Guarda\nDistrito: Guarda\nConcelho: Guarda\nFreguesia: Freguesia de Guarda\n\n10 - PRAZO DE EXECUÇÃO DO CONTRATO\nPrazo de execução do contrato: 120 DIAS\nPrevisão de renovações: Não\n\n11 - FUNDOS EU\nTêm fundos EU? Não\n\n12 - DOCUMENTOS DE HABILITAÇÃO\nHabilitação para o exercício da atividade profissional: Sim\nTipo: Outros\nDescrição - Outros: Constante das peças procedimentais\nDescrição: Constante das peças procedimentais.\n\n13 - CONDIÇÕES DE APRESENTAÇÃO\nPlataforma eletrónica utilizada pela entidade adjudicante: VORTAL\nURL para Apresentação: https://community.vortal.biz/public/\nAdmissibilidade da apresentação de propostas variantes: Não autorizado\nPrazo para apresentação das propostas: 10-08-2025 17:00\nPrazo durante o qual os concorrentes são obrigados a manter as respetivas propostas: 66 dias a contar do termo do prazo para a apresentação das propostas\nIndicação de Subcontratação na Proposta: Inexistência de indicação de subcontratação\n\n14 - PRESTAÇÃO DE CAUÇÃO\nPrestação de caução: Sim\nPercentagem: 5%\nDescrição da Garantia Exigida: Em conformidade com o artigo 45º do programa de procedimento\n\n15 - FORNECIMENTO DAS PEÇAS DO CONCURSO, APRESENTAÇÃO DE PEDIDOS DE PARTICIPAÇÃO E APRESENTAÇÃO DAS PROPOSTAS\nLink para acesso às peças do concurso (URL): https://community.vortal.biz/Public/public-tender-documents/Mk9ENlc2MURlcVFIRXEwMWNOOWNGNWtJM2JuUXFiN0pUTEg4STF5ODZYRHFuL2psQ0hqTjBWZmtiZk52VndOTmxlc2VUSGpnUDEyeFBaNzRYcTAycUE9PUNiNkNC\n\n20 - OUTROS REQUISITOS\nInformação sobre contratos reservados. Aplica-se a contratos reservados (54º-A)? Não\n\n21 - CRITÉRIO DE ADJUDICAÇÃO\nMultifator: Não\nMonofator:\nNome: Preço\n\n24 - CONDIÇÕES DO CONTRATO\nFaturação Eletrónica: Permitido\nObrigação de Subcontratação:\nCódigo da Obrigação de Subcontratação: Não é aplicável nenhuma obrigação de subcontratação.\n\n25 - COMPRA PÚBLICA ESTRATÉGICA\nCompra Pública Estratégica: Inexistência de contratação pública estratégica\n\n26 - INFORMAÇÕES ADICIONAIS\nContrato adequado para PME: Sim\nCobertura ACP (Acordo dos Contratos Públicos da Organização Mundial do Comércio): Não\n\n27 - IDENTIFICAÇÃO E CONTACTOS DO ÓRGÃO DE RECURSOS ADMINISTRATIVOS\nDesignação: Presidente da Câmara Municipal\nEndereço: Praça do Municipio.\nCódigo postal: 6301-854\nLocalidade: Guarda\nTelefone: +351 271220200\nFax: +351 271220280\nEndereço eletrónico: contratacaopublica@mun-guarda.pt\n\n28 - IDENTIFICAÇÃO DO(S) AUTOR(ES) DE ANÚNCIO\nNome: Sérgio Fernando da Silva Costa\nCargo: Presidente da Câmara Municipal da Guarda\n\n29 - ALTERAÇÃO\nMotivo da Alteração: Correção pelo adquirente\nIdentificador da Versão do Anúncio a Alterar: 37a3e361-ca69-41de-b780-a4aefb0a22af-01\nIdentificador das Secções Alteradas do Anúncio Anterior: Condições de Apresentação\nDescrição das Alterações: Prorrogação de prazo\nAlteração dos Documentos do Concurso: Não\n419393689",
    "nipc": "501131140",
    "distrito": "Guarda",
    "concelho": "Guarda",
    "freguesia": "Freguesia de Guarda",
    "site": "www.mun-guarda.pt",
    "email": "geral@mun-guarda.pt",
    "designacao_contrato": "Equipamentos e Infraestruturas do Ecossistema do Bairro Comercial Digital da Guarda - Zona Alta",
    "descricao": "Equipamentos e Infraestruturas do Ecossistema do Bairro Comercial Digital da Guarda - Zona Alta",
    "preco_base": "520.974,47 EUR",
    "prazo_execucao": "120 DIAS",
    "prazo_apresentacao_propostas": "10-08-2025 17:00",
    "fundos_eu": "Não",
    "plataforma_eletronica": "VORTAL",
    "url_procedimento": "https://community.vortal.biz/public/",
    "autor_nome": "Sérgio Fernando da Silva Costa",
    "autor_cargo": "Presidente da Câmara Municipal da Guarda"
  },
  {
    "numero_procedimento": "N/A",
    "entidade": "Instituto Português de Oncologia de Lisboa FG, E.P.E.",
    "link": "https://diariodarepublica.pt/dr/detalhe/contrato-publico/21003-927882301",
    "detalhes_completos": "1 - IDENTIFICAÇÃO E CONTACTOS DA ENTIDADE ADJUDICANTE\nDesignação da entidade adjudicante: Instituto Português de Oncologia de Lisboa FG, E.P.E.\nNIPC: 506361616\nEndereço: Rua Profº Lima Basto\nCódigo postal: 1099-023\nLocalidade: Lisboa\nPaís: Portugal\nNUT III: PT170\nDistrito: Lisboa\nConcelho: Lisboa\nFreguesia: Todas\nTelefone: 217229800\nFax: 217229880\nEndereço da Entidade (URL): www.ipolisboa.min-saude.pt/\nEndereço Eletrónico: ipofg@ipolisboa.min-saude.pt\neDelivery Gateway (URL): https://community.vortal.biz/public/\nFunção da Organização: Adquirente\nNorma jurídica da Entidade Adjudicante: Organismo de direito público\nÁrea de atividade da Autoridade Adjudicante: Saúde\n\n2 - JORNAL OFICIAL DA UNIÃO EUROPEIA\nO procedimento a que este anúncio diz respeito também é publicitado no Jornal Oficial da União Europeia? Não\n\n3 - AVISO\nModelo de Anúncio: Concurso público\nData de Envio do Anúncio: 04-08-2025\n\n5 - PROCESSO\nTipo de Procedimento: Concurso público\nPreço base do procedimento: Sim\nValor do preço base do procedimento: 30.910,00 EUR\nProcedimento com lotes? Não\n\n6 - OBJETO DO CONTRATO\nNúmero de referência interna: PN/2331/2025\nDesignação do contrato: Aquisição de Ecógrafo Cutâneo\nDescrição: Aquisição de Ecógrafo Cutâneo\nTipo de Contrato Principal: Aquisição de Bens Móveis\nTipo de Contrato: Aquisição de Bens Móveis\nClassificação CPV (Vocabulário Comum para os Contratos Públicos)\nObjeto principal\nVocabulário Principal: 33100000\nPreço base s/IVA: 30.910,00 EUR\n\n7 - INDICAÇÕES ADICIONAIS\nO contrato envolve aquisição conjunta (satisfação de várias entidades)? Não\nO contrato é adjudicado por uma central de compras? Não\n\n8 - TÉCNICAS\nO concurso destina-se à celebração de um acordo-quadro? Inexistência de acordo-quadro\nÉ utilizado um leilão eletrónico? Não\nÉ adotada uma fase de negociação? Não\nSistema de Aquisição Dinâmico: Inexistência de sistema de aquisição dinâmico\n\n9 - LOCAL DA EXECUÇÃO DO CONTRATO\nLOCAL DA EXECUÇÃO DO CONTRATO (PROCEDIMENTO)\nPaís: Portugal\nNUT III: PT170\nLocalidade: Lisboa\nDistrito: Lisboa\nConcelho: Lisboa\nFreguesia: Freguesia de São Domingos de Benfica\n\n10 - PRAZO DE EXECUÇÃO DO CONTRATO\nPrazo de execução do contrato: 30 DIAS\nPrevisão de renovações: Não\n\n11 - FUNDOS EU\nTêm fundos EU? Não\n\n12 - DOCUMENTOS DE HABILITAÇÃO\nHabilitação para o exercício da atividade profissional: Não\n\n13 - CONDIÇÕES DE APRESENTAÇÃO\nPlataforma eletrónica utilizada pela entidade adjudicante: VORTAL\nURL para Apresentação: https://community.vortal.biz/public/\nAdmissibilidade da apresentação de propostas variantes: Não autorizado\nPrazo para apresentação das propostas: 13-08-2025 17:59\nPrazo durante o qual os concorrentes são obrigados a manter as respetivas propostas: 90 dias a contar do termo do prazo para a apresentação das propostas\nIndicação de Subcontratação na Proposta: Inexistência de indicação de subcontratação\n\n14 - PRESTAÇÃO DE CAUÇÃO\nPrestação de caução: Não\n\n15 - FORNECIMENTO DAS PEÇAS DO CONCURSO, APRESENTAÇÃO DE PEDIDOS DE PARTICIPAÇÃO E APRESENTAÇÃO DAS PROPOSTAS\nLink para acesso às peças do concurso (URL): https://community.vortal.biz/Public/public-tender-documents/NkNBb015YXpyWThVSWFzRS9pS25uZHRCcW5xZlkrQ0hTRzVma0wyQ0tEcGowNnBtMVZ2ZThBOGdiMkoralc3MTVNVGhvZHZXNWtvVFlRUFNic1hYR0E9PVljSVNe\n\n20 - OUTROS REQUISITOS\nInformação sobre contratos reservados. Aplica-se a contratos reservados (54º-A)? Não\n\n21 - CRITÉRIO DE ADJUDICAÇÃO\nMultifator: Não\nMonofator:\nNome: Preço\n\n24 - CONDIÇÕES DO CONTRATO\nFaturação Eletrónica: Permitido\nObrigação de Subcontratação:\nCódigo da Obrigação de Subcontratação: Não é aplicável nenhuma obrigação de subcontratação.\n\n25 - COMPRA PÚBLICA ESTRATÉGICA\nCompra Pública Estratégica: Inexistência de contratação pública estratégica\n\n26 - INFORMAÇÕES ADICIONAIS\nContrato adequado para PME: Sim\nCobertura ACP (Acordo dos Contratos Públicos da Organização Mundial do Comércio): Não\n\n27 - IDENTIFICAÇÃO E CONTACTOS DO ÓRGÃO DE RECURSOS ADMINISTRATIVOS\nDesignação: Conselho de Administração\nEndereço: Rua Professor Lima Basto\nCódigo postal: 1099-023\nLocalidade: Lisboa\nTelefone: +351 217229800\nFax: +351 217229880\nEndereço eletrónico: ipofg@ipolisboa.min-saude.pt\n\n28 - IDENTIFICAÇÃO DO(S) AUTOR(ES) DE ANÚNCIO\nNome: Ricardo Costa\nCargo: Técnico Superior\n419392068",
    "nipc": "506361616",
    "distrito": "Lisboa",
    "concelho": "Lisboa",
    "freguesia": "Todas",
    "site": "www.ipolisboa.min-saude.pt/",
    "email": "ipofg@ipolisboa.min-saude.pt",
    "designacao_contrato": "Aquisição de Ecógrafo Cutâneo",
    "descricao": "Aquisição de Ecógrafo Cutâneo",
    "preco_base": "30.910,00 EUR",
    "prazo_execucao": "30 DIAS",
    "prazo_apresentacao_propostas": "13-08-2025 17:59",
    "fundos_eu": "Não",
    "plataforma_eletronica": "VORTAL",
    "url_procedimento": "https://community.vortal.biz/public/",
    "autor_nome": "Ricardo Costa",
    "autor_cargo": "Técnico Superior"
  },
  {
    "numero_procedimento": "N/A",
    "entidade": "Municipio de Ourém",
    "link": "https://diariodarepublica.pt/dr/detalhe/contrato-publico/21009-927882306",
    "detalhes_completos": "1 - IDENTIFICAÇÃO E CONTACTOS DA ENTIDADE ADJUDICANTE\nDesignação da entidade adjudicante: Municipio de Ourém\nNIPC: 501280740\nServiço/Órgão/Pessoa de contacto: Serviço de Contratação Pública e Aprovisionamento\nEndereço: Praça D. Maria II, nº 1\nCódigo postal: 2490-499\nLocalidade: Ourém\nPaís: Portugal\nNUT III: PT16I\nDistrito: Santarém\nConcelho: Ourém\nFreguesia: Freguesia de Fátima\nTelefone: 249540900\nFax: 249540908\nEndereço da Entidade (URL): www.ourem.pt\nEndereço Eletrónico: geral@mail.cm-ourem.pt\neDelivery Gateway (URL): https://www.acingov.pt\nFunção da Organização: Adquirente\nNorma jurídica da Entidade Adjudicante: Autoridade local\nÁrea de atividade da Autoridade Adjudicante: Serviços públicos das administrações públicas\n\n2 - JORNAL OFICIAL DA UNIÃO EUROPEIA\nO procedimento a que este anúncio diz respeito também é publicitado no Jornal Oficial da União Europeia? Não\n\n3 - AVISO\nModelo de Anúncio: Concurso público\nData de Envio do Anúncio: 04-08-2025\n\n5 - PROCESSO\nTipo de Procedimento: Concurso público\nPreço base do procedimento: Sim\nValor do preço base do procedimento: 19.569,00 EUR\nProcedimento com lotes? Não\n\n6 - OBJETO DO CONTRATO\nNúmero de referência interna: P186/2025\nDesignação do contrato: P186/2025 - Aquisição de Material Informático para a Unidade de Saúde Familiar de Fátima (37693/2025)\nDescrição: P186/2025 - Aquisição de Material Informático para a Unidade de Saúde Familiar de Fátima (37693/2025)\n\nTipo de Contrato Principal: Aquisição de Bens Móveis\nTipo de Contrato: Aquisição de Bens Móveis\nClassificação CPV (Vocabulário Comum para os Contratos Públicos)\nObjeto principal\nVocabulário Principal: 30200000\nPreço base s/IVA: 19.569,00 EUR\n\n7 - INDICAÇÕES ADICIONAIS\nO contrato envolve aquisição conjunta (satisfação de várias entidades)? Não\nO contrato é adjudicado por uma central de compras? Não\n\n8 - TÉCNICAS\nO concurso destina-se à celebração de um acordo-quadro? Inexistência de acordo-quadro\nÉ utilizado um leilão eletrónico? Não\nÉ adotada uma fase de negociação? Não\nSistema de Aquisição Dinâmico: Inexistência de sistema de aquisição dinâmico\n\n9 - LOCAL DA EXECUÇÃO DO CONTRATO\nLOCAL DA EXECUÇÃO DO CONTRATO (PROCEDIMENTO)\nPaís: Portugal\nNUT III: PT16I\nLocalidade: Freguesia de Fátima\nDistrito: Santarém\nConcelho: Ourém\nFreguesia: Freguesia de Fátima\n\n10 - PRAZO DE EXECUÇÃO DO CONTRATO\nPrazo de execução do contrato: 30 DIAS\nPrevisão de renovações: Não\n\n11 - FUNDOS EU\nTêm fundos EU? Não\n\n12 - DOCUMENTOS DE HABILITAÇÃO\nHabilitação para o exercício da atividade profissional: Sim\nTipo: Outros\nDescrição - Outros: Documentos de Habilitação\nDescrição: Documentos de Habilitação\n\n13 - CONDIÇÕES DE APRESENTAÇÃO\nPlataforma eletrónica utilizada pela entidade adjudicante: ACIN\nURL para Apresentação: https://www.acingov.pt\nAdmissibilidade da apresentação de propostas variantes: Não autorizado\nPrazo para apresentação das propostas: 16-08-2025 23:59\nPrazo durante o qual os concorrentes são obrigados a manter as respetivas propostas: 66 dias a contar do termo do prazo para a apresentação das propostas\nIndicação de Subcontratação na Proposta: Inexistência de indicação de subcontratação\n\n14 - PRESTAÇÃO DE CAUÇÃO\nPrestação de caução: Sim\nPercentagem: 5%\nDescrição da Garantia Exigida: O valor da caução é de 5.00% do preço contratual.\n\n15 - FORNECIMENTO DAS PEÇAS DO CONCURSO, APRESENTAÇÃO DE PEDIDOS DE PARTICIPAÇÃO E APRESENTAÇÃO DAS PROPOSTAS\nLink para acesso às peças do concurso (URL): https://www.acingov.pt/acingovprod/2/zonaPublica/zona_publica_c/donwloadProcedurePiece/OTMwODIy\n\n20 - OUTROS REQUISITOS\nInformação sobre contratos reservados. Aplica-se a contratos reservados (54º-A)? Não\n\n21 - CRITÉRIO DE ADJUDICAÇÃO\nMultifator: Não\nMonofator:\nNome: Preço\n\n24 - CONDIÇÕES DO CONTRATO\nFaturação Eletrónica: Permitido\nObrigação de Subcontratação:\nCódigo da Obrigação de Subcontratação: Não é aplicável nenhuma obrigação de subcontratação.\n\n25 - COMPRA PÚBLICA ESTRATÉGICA\nCompra Pública Estratégica: Inexistência de contratação pública estratégica\n\n26 - INFORMAÇÕES ADICIONAIS\nContrato adequado para PME: Sim\nCobertura ACP (Acordo dos Contratos Públicos da Organização Mundial do Comércio): Não\n\n27 - IDENTIFICAÇÃO E CONTACTOS DO ÓRGÃO DE RECURSOS ADMINISTRATIVOS\nDesignação: Municipio de Ourém\nEndereço: Praça D. Maria II, nº 1\nCódigo postal: 2490-499\nLocalidade: Ourém\nTelefone: 249540900\nFax: 249540908\nEndereço eletrónico: geral@mail.cm-ourem.pt\nPrazo de interposição do recurso: 5 dias\n\n28 - IDENTIFICAÇÃO DO(S) AUTOR(ES) DE ANÚNCIO\nNome: Luís Miguel Albuquerque\nCargo: Presidente da Câmara\n419392238",
    "nipc": "501280740",
    "distrito": "Santarém",
    "concelho": "Ourém",
    "freguesia": "Freguesia de Fátima",
    "site": "www.ourem.pt",
    "email": "geral@mail.cm-ourem.pt",
    "designacao_contrato": "P186/2025 - Aquisição de Material Informático para a Unidade de Saúde Familiar de Fátima (37693/2025)",
    "descricao": "P186/2025 - Aquisição de Material Informático para a Unidade de Saúde Familiar de Fátima (37693/2025)",
    "preco_base": "19.569,00 EUR",
    "prazo_execucao": "30 DIAS",
    "prazo_apresentacao_propostas": "16-08-2025 23:59",
    "fundos_eu": "Não",
    "plataforma_eletronica": "ACIN",
    "url_procedimento": "https://www.acingov.pt",
    "autor_nome": "Luís Miguel Albuquerque",
    "autor_cargo": "Presidente da Câmara"
  },
  {
    "numero_procedimento": "N/A",
    "entidade": "Municipio de Ourém",
    "link": "https://diariodarepublica.pt/dr/detalhe/contrato-publico/21011-927882307",
    "detalhes_completos": "1 - IDENTIFICAÇÃO E CONTACTOS DA ENTIDADE ADJUDICANTE\nDesignação da entidade adjudicante: Municipio de Ourém\nNIPC: 501280740\nServiço/Órgão/Pessoa de contacto: Serviço de Contratação Pública e Aprovisionamento\nEndereço: Praça D. Maria II, nº 1\nCódigo postal: 2490-499\nLocalidade: Ourém\nPaís: Portugal\nNUT III: PT16I\nDistrito: Santarém\nConcelho: Ourém\nFreguesia: Todas\nTelefone: 249540900\nFax: 249540908\nEndereço da Entidade (URL): www.ourem.pt\nEndereço Eletrónico: geral@mail.cm-ourem.pt\neDelivery Gateway (URL): https://www.acingov.pt\nFunção da Organização: Adquirente\nNorma jurídica da Entidade Adjudicante: Autoridade local\nÁrea de atividade da Autoridade Adjudicante: Serviços públicos das administrações públicas\n\n2 - JORNAL OFICIAL DA UNIÃO EUROPEIA\nO procedimento a que este anúncio diz respeito também é publicitado no Jornal Oficial da União Europeia? Não\n\n3 - AVISO\nModelo de Anúncio: Concurso público\nData de Envio do Anúncio: 04-08-2025\n\n5 - PROCESSO\nTipo de Procedimento: Concurso público\nPreço base do procedimento: Sim\nValor do preço base do procedimento: 115.651,48 EUR\nProcedimento com lotes? Não\n\n6 - OBJETO DO CONTRATO\nNúmero de referência interna: P209/2025\nDesignação do contrato: P209/2025 - Fornecimento e Montagem de Luminárias LED na Passagem Desnivelada de Fátima, incluindo Gateway - LoRaWAN (17376/2025)\nDescrição: P209/2025 - Fornecimento e Montagem de Luminárias LED na Passagem Desnivelada de Fátima, incluindo Gateway - LoRaWAN (17376/2025)\n\nTipo de Contrato Principal: Aquisição de Bens Móveis\nTipo de Contrato: Aquisição de Bens Móveis\nClassificação CPV (Vocabulário Comum para os Contratos Públicos)\nObjeto principal\nVocabulário Principal: 31500000\nPreço base s/IVA: 115.651,48 EUR\n\n7 - INDICAÇÕES ADICIONAIS\nO contrato envolve aquisição conjunta (satisfação de várias entidades)? Não\nO contrato é adjudicado por uma central de compras? Não\n\n8 - TÉCNICAS\nO concurso destina-se à celebração de um acordo-quadro? Inexistência de acordo-quadro\nÉ utilizado um leilão eletrónico? Não\nÉ adotada uma fase de negociação? Não\nSistema de Aquisição Dinâmico: Inexistência de sistema de aquisição dinâmico\n\n9 - LOCAL DA EXECUÇÃO DO CONTRATO\nLOCAL DA EXECUÇÃO DO CONTRATO (PROCEDIMENTO)\nPaís: Portugal\nNUT III: PT16I\nLocalidade: Freguesia de Fátima\nDistrito: Santarém\nConcelho: Ourém\nFreguesia: Freguesia de Fátima\n\n10 - PRAZO DE EXECUÇÃO DO CONTRATO\nPrazo de execução do contrato: 120 DIAS\nPrevisão de renovações: Não\n\n11 - FUNDOS EU\nTêm fundos EU? Não\n\n12 - DOCUMENTOS DE HABILITAÇÃO\nHabilitação para o exercício da atividade profissional: Não\n\n13 - CONDIÇÕES DE APRESENTAÇÃO\nPlataforma eletrónica utilizada pela entidade adjudicante: ACIN\nURL para Apresentação: https://www.acingov.pt\nAdmissibilidade da apresentação de propostas variantes: Não autorizado\nPrazo para apresentação das propostas: 16-08-2025 23:59\nPrazo durante o qual os concorrentes são obrigados a manter as respetivas propostas: 66 dias a contar do termo do prazo para a apresentação das propostas\nIndicação de Subcontratação na Proposta: Inexistência de indicação de subcontratação\n\n14 - PRESTAÇÃO DE CAUÇÃO\nPrestação de caução: Sim\nPercentagem: 5%\nDescrição da Garantia Exigida: O valor da caução é de 5.00% do preço contratual.\n\n15 - FORNECIMENTO DAS PEÇAS DO CONCURSO, APRESENTAÇÃO DE PEDIDOS DE PARTICIPAÇÃO E APRESENTAÇÃO DAS PROPOSTAS\nLink para acesso às peças do concurso (URL): https://www.acingov.pt/acingovprod/2/zonaPublica/zona_publica_c/donwloadProcedurePiece/OTMwODgy\n\n20 - OUTROS REQUISITOS\nInformação sobre contratos reservados. Aplica-se a contratos reservados (54º-A)? Não\n\n21 - CRITÉRIO DE ADJUDICAÇÃO\nMultifator: Não\nMonofator:\nNome: Preço\n\n24 - CONDIÇÕES DO CONTRATO\nFaturação Eletrónica: Permitido\nObrigação de Subcontratação:\nCódigo da Obrigação de Subcontratação: Não é aplicável nenhuma obrigação de subcontratação.\n\n25 - COMPRA PÚBLICA ESTRATÉGICA\nCompra Pública Estratégica: Inexistência de contratação pública estratégica\n\n26 - INFORMAÇÕES ADICIONAIS\nContrato adequado para PME: Sim\nCobertura ACP (Acordo dos Contratos Públicos da Organização Mundial do Comércio): Não\n\n27 - IDENTIFICAÇÃO E CONTACTOS DO ÓRGÃO DE RECURSOS ADMINISTRATIVOS\nDesignação: Municipio de Ourém\nEndereço: Praça D. Maria II, nº 1\nCódigo postal: 2490-499\nLocalidade: Ourém\nTelefone: 249540900\nFax: 249540908\nEndereço eletrónico: geral@mail.cm-ourem.pt\nPrazo de interposição do recurso: 5 dias\n\n28 - IDENTIFICAÇÃO DO(S) AUTOR(ES) DE ANÚNCIO\nNome: Luís Miguel Albuquerque\nCargo: Presidente da Câmara\n419392043",
    "nipc": "501280740",
    "distrito": "Santarém",
    "concelho": "Ourém",
    "freguesia": "Todas",
    "site": "www.ourem.pt",
    "email": "geral@mail.cm-ourem.pt",
    "designacao_contrato": "P209/2025 - Fornecimento e Montagem de Luminárias LED na Passagem Desnivelada de Fátima, incluindo Gateway - LoRaWAN (17376/2025)",
    "descricao": "P209/2025 - Fornecimento e Montagem de Luminárias LED na Passagem Desnivelada de Fátima, incluindo Gateway - LoRaWAN (17376/2025)",
    "preco_base": "115.651,48 EUR",
    "prazo_execucao": "120 DIAS",
    "prazo_apresentacao_propostas": "16-08-2025 23:59",
    "fundos_eu": "Não",
    "plataforma_eletronica": "ACIN",
    "url_procedimento": "https://www.acingov.pt",
    "autor_nome": "Luís Miguel Albuquerque",
    "autor_cargo": "Presidente da Câmara"
  },
  {
    "numero_procedimento": "N/A",
    "entidade": "MUNICÍPIO DE LOULÉ",
    "link": "https://diariodarepublica.pt/dr/detalhe/contrato-publico/21012-927882311",
    "detalhes_completos": "1 - IDENTIFICAÇÃO E CONTACTOS DA ENTIDADE ADJUDICANTE\nDesignação da entidade adjudicante: MUNICÍPIO DE LOULÉ\nNIPC: 502098139\nEndereço: Praça da República\nCódigo postal: 8104-001\nLocalidade: Faro\nPaís: Portugal\nNUT III: PT150\nDistrito: Faro\nConcelho: Loulé\nFreguesia: Todas\nTelefone: 289400834\nFax: 289415557\nEndereço da Entidade (URL): www.cm-loule.pt\nEndereço Eletrónico: aprovisionamento@cm-loule.pt\neDelivery Gateway (URL): https://community.vortal.biz/public/\nFunção da Organização: Adquirente\nNorma jurídica da Entidade Adjudicante: Organismo de direito público\nÁrea de atividade da Autoridade Adjudicante: Serviços públicos das administrações públicas\n\n2 - JORNAL OFICIAL DA UNIÃO EUROPEIA\nO procedimento a que este anúncio diz respeito também é publicitado no Jornal Oficial da União Europeia? Não\n\n3 - AVISO\nModelo de Anúncio: Concurso público\nData de Envio do Anúncio: 04-08-2025\n\n5 - PROCESSO\nTipo de Procedimento: Concurso público\nPreço base do procedimento: Sim\nValor do preço base do procedimento: 134.509,70 EUR\nProcedimento com lotes? Sim\nNº Máx. de Lotes Autorizado: 2\nNúmero máximo de lotes que podem ser adjudicados a um concorrente: 2\n\n6 - OBJETO DO CONTRATO\nNúmero de referência interna: FM-2025-364 DACP\nDesignação do contrato: CONTRATAÇÃO DA AQUISIÇÃO DE BRINDES PUBLICITÁRIOS E MERCHANDISING PARA APOIO AOS EVENTOS DO MUNICÍPIO, PARA 2025 E 2026\nDescrição: CONTRATAÇÃO DA AQUISIÇÃO DE BRINDES PUBLICITÁRIOS E MERCHANDISING PARA APOIO AOS EVENTOS DO MUNICÍPIO, PARA 2025 E 2026\nTipo de Contrato Principal: Aquisição de Bens Móveis\nTipo de Contrato: Aquisição de Bens Móveis\nClassificação CPV (Vocabulário Comum para os Contratos Públicos)\nObjeto principal\nVocabulário Principal: 18530000\nPreço base s/IVA: 134.509,70 EUR\nLotes: \nNº: LOT-0001\nDescrição do Lote: LOTE 1 \nPreço base s/IVA: 37.672,00 EUR\nClassificação CPV (Vocabulário Comum para os Contratos Públicos)\nObjeto principal\nVocabulário Principal: 18530000\nNº: LOT-0002\nDescrição do Lote: LOTE 2\nPreço base s/IVA: 96.837,70 EUR\nClassificação CPV (Vocabulário Comum para os Contratos Públicos)\nObjeto principal\nVocabulário Principal: 18530000\n\n7 - INDICAÇÕES ADICIONAIS\nO contrato envolve aquisição conjunta (satisfação de várias entidades)? Não\nO contrato é adjudicado por uma central de compras? Não\n\n8 - TÉCNICAS\nO concurso destina-se à celebração de um acordo-quadro? Inexistência de acordo-quadro\nÉ utilizado um leilão eletrónico? Não\nÉ adotada uma fase de negociação? Não\nSistema de Aquisição Dinâmico: Inexistência de sistema de aquisição dinâmico\n\n9 - LOCAL DA EXECUÇÃO DO CONTRATO\nLOCAL DA EXECUÇÃO DO CONTRATO (PROCEDIMENTO)\nPaís: Portugal\nNUT III: PT150\nLocalidade: Faro\nDistrito: Faro\nConcelho: Loulé\nFreguesia: Todas\nLOCAL DA EXECUÇÃO DO CONTRATO (LOTE)\nIdentificador do Lote: LOT-0001; LOT-0002\nPaís: Portugal\nNUT III: PT150\nLocalidade: Faro\nDistrito: Faro\nConcelho: Loulé\nFreguesia: Todas\n\n10 - PRAZO DE EXECUÇÃO DO CONTRATO\nIdentificador do Lote: LOT-0001; LOT-0002\nPrazo de execução do contrato: 16 MESES\nPrevisão de renovações: Não\n\n11 - FUNDOS EU\nIdentificador do Lote: LOT-0001; LOT-0002\nTêm fundos EU? Não\n\n12 - DOCUMENTOS DE HABILITAÇÃO\nHabilitação para o exercício da atividade profissional: Não\n\n13 - CONDIÇÕES DE APRESENTAÇÃO\nPlataforma eletrónica utilizada pela entidade adjudicante: VORTAL\nURL para Apresentação: https://community.vortal.biz/public/\nAdmissibilidade da apresentação de propostas variantes: Não autorizado\nPrazo para apresentação das propostas: 08-09-2025 18:00\nPrazo durante o qual os concorrentes são obrigados a manter as respetivas propostas: 90 dias a contar do termo do prazo para a apresentação das propostas\nIndicação de Subcontratação na Proposta: Inexistência de indicação de subcontratação\n\n14 - PRESTAÇÃO DE CAUÇÃO\nPrestação de caução: Não\n\n15 - FORNECIMENTO DAS PEÇAS DO CONCURSO, APRESENTAÇÃO DE PEDIDOS DE PARTICIPAÇÃO E APRESENTAÇÃO DAS PROPOSTAS\nLink para acesso às peças do concurso (URL): https://community.vortal.biz/Public/public-tender-documents/Y0dZZEYwRUZMaVZiRVNOTU9PSzMwcjgxeFZhK29VeFowaEI4US9hUEVaSmU0R1BXb0lIYkJhMDZOMFc5cFRudFE3MnJ1aWdmUVFKeDYvYW1iNlpqTWc9PSlEV0Y0\n\n20 - OUTROS REQUISITOS\nIdentificador do Lote: LOT-0001; LOT-0002\nInformação sobre contratos reservados. Aplica-se a contratos reservados (54º-A)? Não\n\n21 - CRITÉRIO DE ADJUDICAÇÃO\nO Critério de adjudicação é diferenciado por lote? Não\nMultifator: Não\nMonofator:\nNome: Preço\n\n24 - CONDIÇÕES DO CONTRATO\nIdentificador do Lote: LOT-0001; LOT-0002\nFaturação Eletrónica: Permitido\nObrigação de Subcontratação:\nCódigo da Obrigação de Subcontratação: Não é aplicável nenhuma obrigação de subcontratação.\n\n25 - COMPRA PÚBLICA ESTRATÉGICA\nCompra Pública Estratégica: Inexistência de contratação pública estratégica\n\n26 - INFORMAÇÕES ADICIONAIS\nIdentificador do Lote: LOT-0001; LOT-0002\nContrato adequado para PME: Sim\nCobertura ACP (Acordo dos Contratos Públicos da Organização Mundial do Comércio): Não\n\n27 - IDENTIFICAÇÃO E CONTACTOS DO ÓRGÃO DE RECURSOS ADMINISTRATIVOS\nDesignação: Câmara Municipal de Loulé\nEndereço: Praça da República\nCódigo postal: 8104-001\nLocalidade: Loulé\nTelefone: +351 289400600\nFax: +351 289415557\nEndereço eletrónico: geral@cm-loule.pt\n\n28 - IDENTIFICAÇÃO DO(S) AUTOR(ES) DE ANÚNCIO\nNome: Vítor Manuel Gonçalves Aleixo\nCargo: Presidente da Câmara Municipal\n419394944",
    "nipc": "502098139",
    "distrito": "Faro",
    "concelho": "Loulé",
    "freguesia": "Todas",
    "site": "www.cm-loule.pt",
    "email": "aprovisionamento@cm-loule.pt",
    "designacao_contrato": "CONTRATAÇÃO DA AQUISIÇÃO DE BRINDES PUBLICITÁRIOS E MERCHANDISING PARA APOIO AOS EVENTOS DO MUNICÍPIO, PARA 2025 E 2026",
    "descricao": "CONTRATAÇÃO DA AQUISIÇÃO DE BRINDES PUBLICITÁRIOS E MERCHANDISING PARA APOIO AOS EVENTOS DO MUNICÍPIO, PARA 2025 E 2026",
    "preco_base": "134.509,70 EUR",
    "prazo_execucao": "16 MESES",
    "prazo_apresentacao_propostas": "08-09-2025 18:00",
    "fundos_eu": "Não",
    "plataforma_eletronica": "VORTAL",
    "url_procedimento": "https://community.vortal.biz/public/",
    "autor_nome": "Vítor Manuel Gonçalves Aleixo",
    "autor_cargo": "Presidente da Câmara Municipal"
  },
  {
    "numero_procedimento": "N/A",
    "entidade": "Município de Aguiar da Beira",
    "link": "https://diariodarepublica.pt/dr/detalhe/contrato-publico/21014-927882312",
    "detalhes_completos": "1 - IDENTIFICAÇÃO E CONTACTOS DA ENTIDADE ADJUDICANTE\nDesignação da entidade adjudicante: Município de Aguiar da Beira\nNIPC: 506809307\nServiço/Órgão/Pessoa de contacto: Câmara Municipal de Aguiar da Beira\nEndereço: Av. da Liberdade n.º21\nCódigo postal: 3570-018\nLocalidade: AGUIAR DA BEIRA\nPaís: Portugal\nNUT III: PT16G\nDistrito: Guarda\nConcelho: Aguiar da Beira\nFreguesia: Todas\nTelefone: 232689100\nFax: 000\nEndereço da Entidade (URL): https://www.cm-aguiardabeira.pt/\nEndereço Eletrónico: geral@cm-aguiardabeira.pt\neDelivery Gateway (URL): https://www.acingov.pt\nFunção da Organização: Adquirente\nSubfunção da Organização: Organização que recebe as propostas\nNorma jurídica da Entidade Adjudicante: Organismo de direito público\nÁrea de atividade da Entidade Adjudicante: Atividades relacionadas com a água\n\n2 - JORNAL OFICIAL DA UNIÃO EUROPEIA\nO procedimento a que este anúncio diz respeito também é publicitado no Jornal Oficial da União Europeia? Não\n\n3 - AVISO\nModelo de Anúncio: Concurso público\nData de Envio do Anúncio: 04-08-2025\n\n5 - PROCESSO\nTipo de Procedimento: Concurso público\nPreço base do procedimento: Sim\nValor do preço base do procedimento: 24.292,68 EUR\nProcedimento com lotes? Não\n\n6 - OBJETO DO CONTRATO\nNúmero de referência interna: 2025/300.10.005/979\nDesignação do contrato: Aquisição de Seguro para Frota Automóvel 2025\nDescrição: Aquisição de Seguro para Frota Automóvel 2025\nTipo de Contrato Principal: Aquisição de Serviços\nTipo de Contrato: Aquisição de Serviços\nClassificação CPV (Vocabulário Comum para os Contratos Públicos)\nObjeto principal\nVocabulário Principal: 66514110\nPreço base s/IVA: 24.292,68 EUR\n\n7 - INDICAÇÕES ADICIONAIS\nO contrato envolve aquisição conjunta (satisfação de várias entidades)? Não\nO contrato é adjudicado por uma central de compras? Não\n\n8 - TÉCNICAS\nO concurso destina-se à celebração de um acordo-quadro? Inexistência de acordo-quadro\nÉ utilizado um leilão eletrónico? Não\nÉ adotada uma fase de negociação? Não\nSistema de Aquisição Dinâmico: Inexistência de sistema de aquisição dinâmico\n\n9 - LOCAL DA EXECUÇÃO DO CONTRATO\nLOCAL DA EXECUÇÃO DO CONTRATO (PROCEDIMENTO)\nPaís: Portugal\nNUT III: PT16G\nLocalidade: AGUIAR DA BEIRA\nDistrito: Guarda\nConcelho: Aguiar da Beira\nFreguesia: Todas\n\n10 - PRAZO DE EXECUÇÃO DO CONTRATO\nPrazo de execução do contrato: 365 DIAS\nPrevisão de renovações: Não\n\n11 - FUNDOS EU\nTêm fundos EU? Não\n\n12 - DOCUMENTOS DE HABILITAÇÃO\nHabilitação para o exercício da atividade profissional: Não\n\n13 - CONDIÇÕES DE APRESENTAÇÃO\nPlataforma eletrónica utilizada pela entidade adjudicante: ACIN\nURL para Apresentação: https://www.acingov.pt\nAdmissibilidade da apresentação de propostas variantes: Não autorizado\nPrazo para apresentação das propostas: 10-08-2025 23:59\nPrazo durante o qual os concorrentes são obrigados a manter as respetivas propostas: 66 dias a contar do termo do prazo para a apresentação das propostas\nIndicação de Subcontratação na Proposta: Inexistência de indicação de subcontratação\n\n14 - PRESTAÇÃO DE CAUÇÃO\nPrestação de caução: Não\n\n15 - FORNECIMENTO DAS PEÇAS DO CONCURSO, APRESENTAÇÃO DE PEDIDOS DE PARTICIPAÇÃO E APRESENTAÇÃO DAS PROPOSTAS\nLink para acesso às peças do concurso (URL): https://www.acingov.pt/acingovprod/2/zonaPublica/zona_publica_c/donwloadProcedurePiece/OTI5MTA4\n\n20 - OUTROS REQUISITOS\nInformação sobre contratos reservados. Aplica-se a contratos reservados (54º-A)? Não\n\n21 - CRITÉRIO DE ADJUDICAÇÃO\nMultifator: Não\nMonofator:\nNome: Outros\nOutro nome: Fator Preço\n\n24 - CONDIÇÕES DO CONTRATO\nFaturação Eletrónica: Permitido\nObrigação de Subcontratação:\nCódigo da Obrigação de Subcontratação: Não é aplicável nenhuma obrigação de subcontratação.\n\n25 - COMPRA PÚBLICA ESTRATÉGICA\nCompra Pública Estratégica: Inexistência de contratação pública estratégica\n\n26 - INFORMAÇÕES ADICIONAIS\nContrato adequado para PME: Sim\nCobertura ACP (Acordo dos Contratos Públicos da Organização Mundial do Comércio): Não\n\n27 - IDENTIFICAÇÃO E CONTACTOS DO ÓRGÃO DE RECURSOS ADMINISTRATIVOS\nDesignação: Câmara Municipal de Aguiar da Beira\nEndereço: Av. da Liberdade n.º21\nCódigo postal: 3570-018\nLocalidade: AGUIAR DA BEIRA\nTelefone: 232689100\nFax: \nEndereço eletrónico: geral@cm-aguiardabeira.pt\n\n28 - IDENTIFICAÇÃO DO(S) AUTOR(ES) DE ANÚNCIO\nNome: Ana Filipa Lopes Andrade\nCargo: Técnica Superior\n419387346",
    "nipc": "506809307",
    "distrito": "Guarda",
    "concelho": "Aguiar da Beira",
    "freguesia": "Todas",
    "site": "https://www.cm-aguiardabeira.pt/",
    "email": "geral@cm-aguiardabeira.pt",
    "designacao_contrato": "Aquisição de Seguro para Frota Automóvel 2025",
    "descricao": "Aquisição de Seguro para Frota Automóvel 2025",
    "preco_base": "24.292,68 EUR",
    "prazo_execucao": "365 DIAS",
    "prazo_apresentacao_propostas": "10-08-2025 23:59",
    "fundos_eu": "Não",
    "plataforma_eletronica": "ACIN",
    "url_procedimento": "https://www.acingov.pt",
    "autor_nome": "Ana Filipa Lopes Andrade",
    "autor_cargo": "Técnica Superior"
  },
  {
    "numero_procedimento": "N/A",
    "entidade": "Parques de Sintra-Monte da Lua, SA",
    "link": "https://diariodarepublica.pt/dr/detalhe/contrato-publico/21018-927882313",
    "detalhes_completos": "1 - IDENTIFICAÇÃO E CONTACTOS DA ENTIDADE ADJUDICANTE\nDesignação da entidade adjudicante: Parques de Sintra-Monte da Lua, SA\nNIPC: 505174839\nEndereço: ESTRADA MONSERRATE, PARQUE DE MONSERRATE\nCódigo postal: 2710-405\nLocalidade: Sintra\nPaís: Portugal\nNUT III: PT170\nDistrito: Lisboa\nConcelho: Sintra\nFreguesia: Todas\nTelefone: 219237300\nFax: 219237350\nEndereço da Entidade (URL): www.parquesdesintra.pt/pt/\nEndereço Eletrónico: viviane.crouzier@parquesdesintra.pt\neDelivery Gateway (URL): https://community.vortal.biz/public/\nFunção da Organização: Adquirente\nNorma jurídica da Entidade Adjudicante: Autoridade da administração central\nÁrea de atividade da Autoridade Adjudicante: Serviços públicos das administrações públicas\n\n2 - JORNAL OFICIAL DA UNIÃO EUROPEIA\nO procedimento a que este anúncio diz respeito também é publicitado no Jornal Oficial da União Europeia? Não\n\n3 - AVISO\nModelo de Anúncio: Concurso público\nData de Envio do Anúncio: 04-08-2025\n\n5 - PROCESSO\nTipo de Procedimento: Concurso público\nPreço base do procedimento: Sim\nValor do preço base do procedimento: 99.000,00 EUR\nProcedimento com lotes? Não\n\n6 - OBJETO DO CONTRATO\nNúmero de referência interna: 01249.2025\nDesignação do contrato: Aquisição de equipamentos, materiais e consumíveis e uso comum para as áreas de Conservação Preventiva e Conservação e Restauro na Parques de Sintra – Monte da Lua, SA.\nDescrição: Aquisição de equipamentos, materiais e consumíveis e uso comum para as áreas de Conservação Preventiva e Conservação e Restauro na Parques de Sintra – Monte da Lua, SA.\nTipo de Contrato Principal: Aquisição de Bens Móveis\nTipo de Contrato: Aquisição de Bens Móveis\nClassificação CPV (Vocabulário Comum para os Contratos Públicos)\nObjeto principal\nVocabulário Principal: 44500000\nPreço base s/IVA: 99.000,00 EUR\n\n7 - INDICAÇÕES ADICIONAIS\nO contrato envolve aquisição conjunta (satisfação de várias entidades)? Não\nO contrato é adjudicado por uma central de compras? Não\n\n8 - TÉCNICAS\nO concurso destina-se à celebração de um acordo-quadro? Inexistência de acordo-quadro\nÉ utilizado um leilão eletrónico? Não\nÉ adotada uma fase de negociação? Não\nSistema de Aquisição Dinâmico: Inexistência de sistema de aquisição dinâmico\n\n9 - LOCAL DA EXECUÇÃO DO CONTRATO\nLOCAL DA EXECUÇÃO DO CONTRATO (PROCEDIMENTO)\nPaís: Portugal\nNUT III: PT170\nLocalidade: Lisboa\nDistrito: Lisboa\nConcelho: Sintra\nFreguesia: Todas\n\n10 - PRAZO DE EXECUÇÃO DO CONTRATO\nPrazo de execução do contrato: 3 ANOS\nPrevisão de renovações: Não\n\n11 - FUNDOS EU\nTêm fundos EU? Não\n\n12 - DOCUMENTOS DE HABILITAÇÃO\nHabilitação para o exercício da atividade profissional: Não\n\n13 - CONDIÇÕES DE APRESENTAÇÃO\nPlataforma eletrónica utilizada pela entidade adjudicante: VORTAL\nURL para Apresentação: https://community.vortal.biz/public/\nAdmissibilidade da apresentação de propostas variantes: Não autorizado\nPrazo para apresentação das propostas: 19-08-2025 23:59\nPrazo durante o qual os concorrentes são obrigados a manter as respetivas propostas: 66 dias a contar do termo do prazo para a apresentação das propostas\nIndicação de Subcontratação na Proposta: Inexistência de indicação de subcontratação\n\n14 - PRESTAÇÃO DE CAUÇÃO\nPrestação de caução: Não\n\n15 - FORNECIMENTO DAS PEÇAS DO CONCURSO, APRESENTAÇÃO DE PEDIDOS DE PARTICIPAÇÃO E APRESENTAÇÃO DAS PROPOSTAS\nLink para acesso às peças do concurso (URL): https://community.vortal.biz/Public/public-tender-documents/ajgvYkdZbnFreHJCUmpmOE11UHhxdUw4cTZndXBxTDY2NW5WRmpzb1N1ckRZamFncW84Rk4zRkltc3FibnJBbkp1d1MrVEhsRXoxUkJNTjVrdXIvaEE9PURZV2Yz\n\n20 - OUTROS REQUISITOS\nInformação sobre contratos reservados. Aplica-se a contratos reservados (54º-A)? Não\n\n21 - CRITÉRIO DE ADJUDICAÇÃO\nMultifator: Não\nMonofator:\nNome: Outros\nOutro nome: Preço\n\n24 - CONDIÇÕES DO CONTRATO\nFaturação Eletrónica: Permitido\nObrigação de Subcontratação:\nCódigo da Obrigação de Subcontratação: Não é aplicável nenhuma obrigação de subcontratação.\n\n25 - COMPRA PÚBLICA ESTRATÉGICA\nCompra Pública Estratégica: Inexistência de contratação pública estratégica\n\n26 - INFORMAÇÕES ADICIONAIS\nContrato adequado para PME: Sim\nCobertura ACP (Acordo dos Contratos Públicos da Organização Mundial do Comércio): Não\n\n27 - IDENTIFICAÇÃO E CONTACTOS DO ÓRGÃO DE RECURSOS ADMINISTRATIVOS\nDesignação: Conselho de Administração\nEndereço: ESTRADA MONSERRATE, PARQUE DE MONSERRATE\nCódigo postal: 2710-405\nLocalidade: Sintra\nTelefone: +351 219237300\nFax: +351 219237300\nEndereço eletrónico: info@parquesdesintra.pt\n\n28 - IDENTIFICAÇÃO DO(S) AUTOR(ES) DE ANÚNCIO\nNome: Viviane Crouzier\nCargo: Departamento Jurídico \n419395235",
    "nipc": "505174839",
    "distrito": "Lisboa",
    "concelho": "Sintra",
    "freguesia": "Todas",
    "site": "www.parquesdesintra.pt/pt/",
    "email": "viviane.crouzier@parquesdesintra.pt",
    "designacao_contrato": "Aquisição de equipamentos, materiais e consumíveis e uso comum para as áreas de Conservação Preventiva e Conservação e Restauro na Parques de Sintra – Monte da Lua, SA.",
    "descricao": "Aquisição de equipamentos, materiais e consumíveis e uso comum para as áreas de Conservação Preventiva e Conservação e Restauro na Parques de Sintra – Monte da Lua, SA.",
    "preco_base": "99.000,00 EUR",
    "prazo_execucao": "3 ANOS",
    "prazo_apresentacao_propostas": "19-08-2025 23:59",
    "fundos_eu": "Não",
    "plataforma_eletronica": "VORTAL",
    "url_procedimento": "https://community.vortal.biz/public/",
    "autor_nome": "Viviane Crouzier",
    "autor_cargo": "Departamento Jurídico"
  }
]