[
  {
    "numero_procedimento": "N/A",
    "entidade": "AnÃºncio de procedimento  n.Âº 23586/2025  -  DiÃ¡rio da RepÃºblica n.Âº 171/2025, SÃ©rie II de 2025-09-05",
    "link": "https://diariodarepublica.pt/dr/detalhe/contrato-publico/23586-934278905"
  },
  {
    "numero_procedimento": "N/A",
    "entidade": "AnÃºncio de procedimento  n.Âº 23588/2025  -  DiÃ¡rio da RepÃºblica n.Âº 171/2025, SÃ©rie II de 2025-09-05",
    "link": "https://diariodarepublica.pt/dr/detalhe/contrato-publico/23588-934278907"
  },
  {
    "numero_procedimento": "N/A",
    "entidade": "AnÃºncio de procedimento  n.Âº 23589/2025  -  DiÃ¡rio da RepÃºblica n.Âº 171/2025, SÃ©rie II de 2025-09-05",
    "link": "https://diariodarepublica.pt/dr/detalhe/contrato-publico/23589-934278909"
  },
  {
    "numero_procedimento": "N/A",
    "entidade": "AnÃºncio de procedimento  n.Âº 23594/2025  -  DiÃ¡rio da RepÃºblica n.Âº 171/2025, SÃ©rie II de 2025-09-05",
    "link": "https://diariodarepublica.pt/dr/detalhe/contrato-publico/23594-934278912"
  },
  {
    "numero_procedimento": "N/A",
    "entidade": "AnÃºncio de procedimento  n.Âº 23595/2025  -  DiÃ¡rio da RepÃºblica n.Âº 171/2025, SÃ©rie II de 2025-09-05",
    "link": "https://diariodarepublica.pt/dr/detalhe/contrato-publico/23595-934278913"
  },
  {
    "numero_procedimento": "N/A",
    "entidade": "AnÃºncio de procedimento  n.Âº 23603/2025  -  DiÃ¡rio da RepÃºblica n.Âº 171/2025, SÃ©rie II de 2025-09-05",
    "link": "https://diariodarepublica.pt/dr/detalhe/contrato-publico/23603-934278918"
  },
  {
    "numero_procedimento": "N/A",
    "entidade": "AnÃºncio de procedimento  n.Âº 23587/2025  -  DiÃ¡rio da RepÃºblica n.Âº 171/2025, SÃ©rie II de 2025-09-05",
    "link": "https://diariodarepublica.pt/dr/detalhe/contrato-publico/23587-934287215"
  },
  {
    "numero_procedimento": "N/A",
    "entidade": "AnÃºncio de procedimento  n.Âº 23590/2025  -  DiÃ¡rio da RepÃºblica n.Âº 171/2025, SÃ©rie II de 2025-09-05",
    "link": "https://diariodarepublica.pt/dr/detalhe/contrato-publico/23590-934287216"
  },
  {
    "numero_procedimento": "N/A",
    "entidade": "Município de Monchique",
    "link": "https://diariodarepublica.pt/dr/detalhe/contrato-publico/23591-934287217",
    "detalhes_completos": "1 - IDENTIFICAÇÃO E CONTACTOS DA ENTIDADE ADJUDICANTE\nDesignação da entidade adjudicante: Município de Monchique\nNIPC: 506826961\nServiço/Órgão/Pessoa de contacto: Vice Presidente\nEndereço: Travessa da Portela, nº2\nCódigo postal: 8550-470\nLocalidade: Monchique\nPaís: Portugal\nNUT III: PT150\nDistrito: Faro\nConcelho: Monchique\nFreguesia: Freguesia de Monchique\nTelefone: 282910200\nFax: 282910299\nEndereço da Entidade (URL): https://www.cm-monchique.pt/\nEndereço Eletrónico: geral@cm-monchique.pt\neDelivery Gateway (URL): https://www.acingov.pt\nFunção da Organização: Adquirente\nSubfunção da Organização: Organização cujo orçamento é utilizado para pagar o contrato; Organização que executa o pagamento; Organização que fornece informações adicionais sobre o processo de adjudicação; Organização que fornece mais informações sobre os prazos dos procedimentos de recurso; Organização que fornece acesso fora de linha aos documentos do concurso; Organização responsável pelo tratamento das propostas; Organização que recebe as propostas; Organização que trata os pedidos de participação; Organização que recebe pedidos de participação; Organização que fornece mais informações sobre os procedimentos de recurso; Organização que assina o contrato\nNorma jurídica da Entidade Adjudicante: Organismo de direito público\nÁrea de atividade da Autoridade Adjudicante: Serviços públicos das administrações públicas\n\n2 - JORNAL OFICIAL DA UNIÃO EUROPEIA\nO procedimento a que este anúncio diz respeito também é publicitado no Jornal Oficial da União Europeia? Não\n\n3 - AVISO\nModelo de Anúncio: Concurso público\nData de Envio do Anúncio: 04-09-2025\n\n5 - PROCESSO\nTipo de Procedimento: Concurso público\nPreço base do procedimento: Sim\nValor do preço base do procedimento: 142.400,00 EUR\nProcedimento com lotes? Sim\nNº Máx. de Lotes Autorizado: 3\nNúmero máximo de lotes que podem ser adjudicados a um concorrente: 3\n\n6 - OBJETO DO CONTRATO\nNúmero de referência interna: DDR CPU01/2025\nDesignação do contrato: Prestação de serviços para instalação da faixa de gestão combustível referente ao Condomínio de Aldeia de Alcaria do Peso, Peso e Relva de Trás, no âmbito do Sistema de Gestão Integrada de Fogos Rurais (SGIFR) no Concelho de Monchique.\nDescrição: Prestação de serviços para instalação da faixa de gestão combustível referente ao Condomínio de Aldeia de Alcaria do Peso, Peso e Relva de Trás, no âmbito do Sistema de Gestão Integrada de Fogos Rurais (SGIFR) no Concelho de Monchique\nTipo de Contrato Principal: Aquisição de Serviços\nTipo de Contrato: Aquisição de Serviços\nClassificação CPV (Vocabulário Comum para os Contratos Públicos)\nObjeto principal\nVocabulário Principal: 77210000\nPreço base s/IVA: 142.400,00 EUR\nLotes: \nNº: LOT-0001\nDescrição do Lote: Execução da Faixa Secundária de Gestão de Combustível do Condomínio de aldeia de «Alcaria do Peso»\nPreço base s/IVA: 48.350,00 EUR\nClassificação CPV (Vocabulário Comum para os Contratos Públicos)\nObjeto principal\nVocabulário Principal: 77200000\nNº: LOT-0002\nDescrição do Lote: Execução da Faixa Secundária de Gestão de Combustível do Condomínio de Aldeia de «Peso»\nPreço base s/IVA: 49.150,00 EUR\nClassificação CPV (Vocabulário Comum para os Contratos Públicos)\nObjeto principal\nVocabulário Principal: 77200000\nNº: LOT-0003\nDescrição do Lote: Execução da Faixa Secundária de Gestão de Combustível do Condomínio de Aldeia de «Relva de Trás»\nPreço base s/IVA: 44.900,00 EUR\nClassificação CPV (Vocabulário Comum para os Contratos Públicos)\nObjeto principal\nVocabulário Principal: 77200000\n\n7 - INDICAÇÕES ADICIONAIS\nO contrato envolve aquisição conjunta (satisfação de várias entidades)? Não\nO contrato é adjudicado por uma central de compras? Não\n\n8 - TÉCNICAS\nO concurso destina-se à celebração de um acordo-quadro? Inexistência de acordo-quadro\nÉ utilizado um leilão eletrónico? Não\nÉ adotada uma fase de negociação? Não\nSistema de Aquisição Dinâmico: Inexistência de sistema de aquisição dinâmico\n\n9 - LOCAL DA EXECUÇÃO DO CONTRATO\nLOCAL DA EXECUÇÃO DO CONTRATO (PROCEDIMENTO)\nPaís: Portugal\nNUT III: PT150\nLocalidade: Monchique\nDistrito: Faro\nConcelho: Monchique\nFreguesia: Freguesia de Monchique\nLOCAL DA EXECUÇÃO DO CONTRATO (LOTE)\nIdentificador do Lote: LOT-0001; LOT-0002; LOT-0003\nPaís: Portugal\nNUT III: PT150\nLocalidade: Monchique\nDistrito: Faro\nConcelho: Monchique\nFreguesia: Freguesia de Monchique\n\n10 - PRAZO DE EXECUÇÃO DO CONTRATO\nIdentificador do Lote: LOT-0001; LOT-0002; LOT-0003\nPrazo de execução do contrato: 150 DIAS\nPrevisão de renovações: Não\n\n11 - FUNDOS EU\nIdentificador do Lote: LOT-0001; LOT-0002; LOT-0003\nTêm fundos EU? Sim\n\n12 - DOCUMENTOS DE HABILITAÇÃO\nHabilitação para o exercício da atividade profissional: Não\n\n13 - CONDIÇÕES DE APRESENTAÇÃO\nPlataforma eletrónica utilizada pela entidade adjudicante: ACIN\nURL para Apresentação: https://www.acingov.pt\nAdmissibilidade da apresentação de propostas variantes: Não autorizado\nPrazo para apresentação das propostas: 15-09-2025 23:59\nPrazo durante o qual os concorrentes são obrigados a manter as respetivas propostas: 120 dias a contar do termo do prazo para a apresentação das propostas\nIndicação de Subcontratação na Proposta: Inexistência de indicação de subcontratação\n\n14 - PRESTAÇÃO DE CAUÇÃO\nPrestação de caução: Não\n\n15 - FORNECIMENTO DAS PEÇAS DO CONCURSO, APRESENTAÇÃO DE PEDIDOS DE PARTICIPAÇÃO E APRESENTAÇÃO DAS PROPOSTAS\nLink para acesso às peças do concurso (URL): https://www.acingov.pt/acingovprod/2/zonaPublica/zona_publica_c/donwloadProcedurePiece/OTc1MDc3\n\n20 - OUTROS REQUISITOS\nIdentificador do Lote: LOT-0001; LOT-0002; LOT-0003\nInformação sobre contratos reservados. Aplica-se a contratos reservados (54º-A)? Não\n\n21 - CRITÉRIO DE ADJUDICAÇÃO\nO Critério de adjudicação é diferenciado por lote? Não\nMultifator: Não\nMonofator:\nNome: Preço\n\n24 - CONDIÇÕES DO CONTRATO\nIdentificador do Lote: LOT-0001; LOT-0002; LOT-0003\nFaturação Eletrónica: Permitido\nObrigação de Subcontratação:\nCódigo da Obrigação de Subcontratação: Não é aplicável nenhuma obrigação de subcontratação.\n\n25 - COMPRA PÚBLICA ESTRATÉGICA\nCompra Pública Estratégica: Inexistência de contratação pública estratégica\n\n26 - INFORMAÇÕES ADICIONAIS\nIdentificador do Lote: LOT-0001; LOT-0002; LOT-0003\nContrato adequado para PME: Sim\nCobertura ACP (Acordo dos Contratos Públicos da Organização Mundial do Comércio): Não\n\n27 - IDENTIFICAÇÃO E CONTACTOS DO ÓRGÃO DE RECURSOS ADMINISTRATIVOS\nDesignação: Tribunal Administrativo Fiscal de Loulé\nEndereço: Rua Drª Laura Aires 4\nCódigo postal: 8100-851\nLocalidade: Loulé\nTelefone: 289400390\nFax: 213506010\nEndereço eletrónico: loule.taf@tribunais.org.pt\n\n28 - IDENTIFICAÇÃO DO(S) AUTOR(ES) DE ANÚNCIO\nNome: Humberto Fernandes Sério\nCargo: Vice Presidente\n419499167",
    "nipc": "506826961",
    "distrito": "Faro",
    "concelho": "Monchique",
    "freguesia": "Freguesia de Monchique",
    "site": "https://www.cm-monchique.pt/",
    "email": "geral@cm-monchique.pt",
    "designacao_contrato": "Prestação de serviços para instalação da faixa de gestão combustível referente ao Condomínio de Aldeia de Alcaria do Peso, Peso e Relva de Trás, no âmbito do Sistema de Gestão Integrada de Fogos Rurais (SGIFR) no Concelho de Monchique.",
    "descricao": "Prestação de serviços para instalação da faixa de gestão combustível referente ao Condomínio de Aldeia de Alcaria do Peso, Peso e Relva de Trás, no âmbito do Sistema de Gestão Integrada de Fogos Rurais (SGIFR) no Concelho de Monchique",
    "preco_base": "142.400,00 EUR",
    "prazo_execucao": "150 DIAS",
    "prazo_apresentacao_propostas": "15-09-2025 23:59",
    "fundos_eu": "Sim",
    "plataforma_eletronica": "ACIN",
    "url_procedimento": "https://www.acingov.pt",
    "autor_nome": "Humberto Fernandes Sério",
    "autor_cargo": "Vice Presidente"
  },
  {
    "numero_procedimento": "N/A",
    "entidade": "AnÃºncio de procedimento  n.Âº 23592/2025  -  DiÃ¡rio da RepÃºblica n.Âº 171/2025, SÃ©rie II de 2025-09-05",
    "link": "https://diariodarepublica.pt/dr/detalhe/contrato-publico/23592-934287218"
  },
  {
    "numero_procedimento": "N/A",
    "entidade": "AnÃºncio de procedimento  n.Âº 23593/2025  -  DiÃ¡rio da RepÃºblica n.Âº 171/2025, SÃ©rie II de 2025-09-05",
    "link": "https://diariodarepublica.pt/dr/detalhe/contrato-publico/23593-934287219"
  },
  {
    "numero_procedimento": "N/A",
    "entidade": "AnÃºncio de procedimento  n.Âº 23596/2025  -  DiÃ¡rio da RepÃºblica n.Âº 171/2025, SÃ©rie II de 2025-09-05",
    "link": "https://diariodarepublica.pt/dr/detalhe/contrato-publico/23596-934287220"
  },
  {
    "numero_procedimento": "N/A",
    "entidade": "AnÃºncio de procedimento  n.Âº 23597/2025  -  DiÃ¡rio da RepÃºblica n.Âº 171/2025, SÃ©rie II de 2025-09-05",
    "link": "https://diariodarepublica.pt/dr/detalhe/contrato-publico/23597-934287221"
  },
  {
    "numero_procedimento": "N/A",
    "entidade": "AnÃºncio de procedimento  n.Âº 23598/2025  -  DiÃ¡rio da RepÃºblica n.Âº 171/2025, SÃ©rie II de 2025-09-05",
    "link": "https://diariodarepublica.pt/dr/detalhe/contrato-publico/23598-934287222"
  },
  {
    "numero_procedimento": "N/A",
    "entidade": "AnÃºncio de procedimento  n.Âº 23599/2025  -  DiÃ¡rio da RepÃºblica n.Âº 171/2025, SÃ©rie II de 2025-09-05",
    "link": "https://diariodarepublica.pt/dr/detalhe/contrato-publico/23599-934287223"
  },
  {
    "numero_procedimento": "N/A",
    "entidade": "AnÃºncio de procedimento  n.Âº 23600/2025  -  DiÃ¡rio da RepÃºblica n.Âº 171/2025, SÃ©rie II de 2025-09-05",
    "link": "https://diariodarepublica.pt/dr/detalhe/contrato-publico/23600-934287224"
  },
  {
    "numero_procedimento": "N/A",
    "entidade": "Instituto Vaz Serra, Sociedade de Ensino, Cultura e Recreio, S.A.",
    "link": "https://diariodarepublica.pt/dr/detalhe/contrato-publico/23601-934287225",
    "detalhes_completos": "1 - IDENTIFICAÇÃO E CONTACTOS DA ENTIDADE ADJUDICANTE\nDesignação da entidade adjudicante: Instituto Vaz Serra, Sociedade de Ensino, Cultura e Recreio, S.A.\nNIPC: 501536965\nEndereço: Rua Libânio Vaz Serra\nCódigo postal: 6100-268\nLocalidade: Cernache do Bonjardim\nPaís: Portugal\nNUT III: PT16H\nDistrito: Castelo Branco\nConcelho: Sertã\nFreguesia: União das Freguesias de Cernache do Bonjardim, Nesperal e Palhais\nTelefone: 274800060\nFax: 000000000\nEndereço da Entidade (URL): www.ivs.pt\nEndereço Eletrónico: geral@ivs.pt\nFunção da Organização: Adquirente\nNorma jurídica da Entidade Adjudicante: Entidade com direitos especiais ou exclusivos\nÁrea de atividade da Autoridade Adjudicante: Educação\n\n2 - JORNAL OFICIAL DA UNIÃO EUROPEIA\nO procedimento a que este anúncio diz respeito também é publicitado no Jornal Oficial da União Europeia? Sim\n\n3 - AVISO\nModelo de Anúncio: Concurso público\nData de Envio do Anúncio: 02-09-2025\n\n5 - PROCESSO\nTipo de Procedimento: Concurso público\nPreço base do procedimento: Sim\nValor do preço base do procedimento: 894.397,71 EUR\nProcedimento com lotes? Sim\nNº Máx. de Lotes Autorizado: 2\nNúmero máximo de lotes que podem ser adjudicados a um concorrente: 2\n\n6 - OBJETO DO CONTRATO\nNúmero de referência interna: IVS_CTE_CPi03/2526\nDesignação do contrato: Aquisição e instalação de equipamento didático e de equipamento informático, para a escola Instituto Vaz Serra, propriedade da sociedade Instituto Vaz Serra, Sociedade de Ensino, Cultura e Recreio, S.A., Projeto nº 11014-CTE Informática.\nDescrição: Aquisição e instalação de equipamento didático e de equipamento informático, para a escola Instituto Vaz Serra, propriedade da sociedade Instituto Vaz Serra, Sociedade de Ensino, Cultura e Recreio, S.A., Projeto nº 11014-CTE Informática.\nOpções: Não\nTipo de Contrato Principal: Aquisição de Bens Móveis\nTipo de Contrato: Aquisição de Bens Móveis\nClassificação CPV (Vocabulário Comum para os Contratos Públicos)\nObjeto principal\nVocabulário Principal: 39162000\nPreço base s/IVA: 729.974,67 EUR\nObjeto Complementar\nVocabulário Principal: 39160000\nPreço base s/IVA: 164.423,04 EUR\nLotes: \nNº: LOT-0001\nDescrição do Lote: Lote 1 - Equipamento Didático\nPreço base s/IVA: 729.974,67 EUR\nClassificação CPV (Vocabulário Comum para os Contratos Públicos)\nObjeto principal\nVocabulário Principal: 39162000\nNº: LOT-0002\nDescrição do Lote: Lote 2 - Mobiliário\nPreço base s/IVA: 164.423,04 EUR\nClassificação CPV (Vocabulário Comum para os Contratos Públicos)\nObjeto principal\nVocabulário Principal: 39160000\n\n7 - INDICAÇÕES ADICIONAIS\nO contrato envolve aquisição conjunta (satisfação de várias entidades)? Não\nO contrato é adjudicado por uma central de compras? Não\n\n8 - TÉCNICAS\nO concurso destina-se à celebração de um acordo-quadro? Inexistência de acordo-quadro\nÉ utilizado um leilão eletrónico? Não\nÉ adotada uma fase de negociação? Não\nSistema de Aquisição Dinâmico: Inexistência de sistema de aquisição dinâmico\n\n9 - LOCAL DA EXECUÇÃO DO CONTRATO\nLOCAL DA EXECUÇÃO DO CONTRATO (PROCEDIMENTO)\nLOCAL DA EXECUÇÃO DO CONTRATO (LOTE)\nIdentificador do Lote: LOT-0001\nPaís: Portugal\nNUT III: PT16H\nLocalidade: Cernache do Bonjardim\nDistrito: Castelo Branco\nConcelho: Sertã\nFreguesia: União das Freguesias de Cernache do Bonjardim, Nesperal e Palhais\nIdentificador do Lote: LOT-0002\nPaís: Portugal\nNUT III: PT16H\nLocalidade: Cernache do Bonjardim\nDistrito: Castelo Branco\nConcelho: Sertã\nFreguesia: União das Freguesias de Cernache do Bonjardim, Nesperal e Palhais\n\n10 - PRAZO DE EXECUÇÃO DO CONTRATO\nIdentificador do Lote: LOT-0001\nPrazo de execução do contrato: 90 DIAS\nPrevisão de renovações: Não\nIdentificador do Lote: LOT-0002\nPrazo de execução do contrato: 90 DIAS\nPrevisão de renovações: Não\n\n11 - FUNDOS EU\nIdentificador do Lote: LOT-0001; LOT-0002\nTêm fundos EU? Sim\n\n12 - DOCUMENTOS DE HABILITAÇÃO\nHabilitação para o exercício da atividade profissional: Não\n\n13 - CONDIÇÕES DE APRESENTAÇÃO\nPlataforma eletrónica utilizada pela entidade adjudicante: ANOGOV\nURL para Apresentação: https://www.anogov.com/me-ivs/faces/\nAdmissibilidade da apresentação de propostas variantes: Não autorizado\nPrazo para apresentação das propostas: 02-10-2025 23:59\nPrazo durante o qual os concorrentes são obrigados a manter as respetivas propostas: 66 dias a contar do termo do prazo para a apresentação das propostas\nApresentação de Catálogo Eletrónico: Necessário\nIndicação de Subcontratação na Proposta: A parte do contrato que o proponente tenciona subcontratar\n\n14 - PRESTAÇÃO DE CAUÇÃO\nPrestação de caução: Sim\nPercentagem: 3%\nDescrição da Garantia Exigida: Depósito em dinheiro ou em títulos emitidos ou garantidos pelo Estado ou mediante garantia bancária, ou ainda por seguro-caução.\n\n15 - FORNECIMENTO DAS PEÇAS DO CONCURSO, APRESENTAÇÃO DE PEDIDOS DE PARTICIPAÇÃO E APRESENTAÇÃO DAS PROPOSTAS\nLink para acesso às peças do concurso (URL): https://www.anogov.com/me-ivs/faces/app/acessoDocs.jsp?codigoAcesso=UtRwlhi6IwLqAB81CUSc7C8l2mB7qBPIyDUtrSVlWUS26tYZeS\n\n20 - OUTROS REQUISITOS\nIdentificador do Lote: LOT-0001; LOT-0002\nInformação sobre contratos reservados. Aplica-se a contratos reservados (54º-A)? Não\n\n21 - CRITÉRIO DE ADJUDICAÇÃO\nO Critério de adjudicação é diferenciado por lote? Não\nMultifator: Não\nMonofator:\nNome: Preço\n\n24 - CONDIÇÕES DO CONTRATO\nIdentificador do Lote: LOT-0001; LOT-0002\nFaturação Eletrónica: Necessário\nObrigação de Subcontratação:\nCódigo da Obrigação de Subcontratação: Não é aplicável nenhuma obrigação de subcontratação.\n\n25 - COMPRA PÚBLICA ESTRATÉGICA\nCompra Pública Estratégica: Inexistência de contratação pública estratégica\n\n26 - INFORMAÇÕES ADICIONAIS\nIdentificador do Lote: LOT-0001\nContrato adequado para PME: Sim\nCobertura ACP (Acordo dos Contratos Públicos da Organização Mundial do Comércio): Não\nIdentificador do Lote: LOT-0002\nContrato adequado para PME: Sim\nCobertura ACP (Acordo dos Contratos Públicos da Organização Mundial do Comércio): Não\n\n27 - IDENTIFICAÇÃO E CONTACTOS DO ÓRGÃO DE RECURSOS ADMINISTRATIVOS\nDesignação: Instituto Vaz Serra, Sociedade de Ensino, Cultura e Recreio, S.A.\nEndereço: Rua Libânio Vaz Serra\nCódigo postal: 6100-268\nLocalidade: Cernache do Bonjardim\nEndereço eletrónico: contratacao@ivs.pt\n\n28 - IDENTIFICAÇÃO DO(S) AUTOR(ES) DE ANÚNCIO\nNome: Nuno Madama\nCargo: Administrador\n419494899",
    "nipc": "501536965",
    "distrito": "Castelo Branco",
    "concelho": "Sertã",
    "freguesia": "União das Freguesias de Cernache do Bonjardim, Nesperal e Palhais",
    "site": "www.ivs.pt",
    "email": "geral@ivs.pt",
    "designacao_contrato": "Aquisição e instalação de equipamento didático e de equipamento informático, para a escola Instituto Vaz Serra, propriedade da sociedade Instituto Vaz Serra, Sociedade de Ensino, Cultura e Recreio, S.A., Projeto nº 11014-CTE Informática.",
    "descricao": "Aquisição e instalação de equipamento didático e de equipamento informático, para a escola Instituto Vaz Serra, propriedade da sociedade Instituto Vaz Serra, Sociedade de Ensino, Cultura e Recreio, S.A., Projeto nº 11014-CTE Informática.",
    "preco_base": "729.974,67 EUR",
    "prazo_execucao": "90 DIAS",
    "prazo_apresentacao_propostas": "02-10-2025 23:59",
    "fundos_eu": "Sim",
    "plataforma_eletronica": "ANOGOV",
    "url_procedimento": "https://www.anogov.com/me-ivs/faces/",
    "autor_nome": "Nuno Madama",
    "autor_cargo": "Administrador"
  },
  {
    "numero_procedimento": "N/A",
    "entidade": "Taviraverde, Empresa Municipal de Ambiente, E.M.",
    "link": "https://diariodarepublica.pt/dr/detalhe/contrato-publico/23602-934287226",
    "detalhes_completos": "1 - IDENTIFICAÇÃO E CONTACTOS DA ENTIDADE ADJUDICANTE\nDesignação da entidade adjudicante: Taviraverde, Empresa Municipal de Ambiente, E.M.\nNIPC: 507236335\nServiço/Órgão/Pessoa de contacto: DML/DRLV\nEndereço: Largo Tabira de Pernambuco, n.º 1\nCódigo postal: 8800-456\nLocalidade: Tavira\nPaís: Portugal\nNUT III: PT150\nDistrito: Faro\nConcelho: Tavira\nFreguesia: Todas\nTelefone: 281380620\nFax: 281380629\nEndereço da Entidade (URL): www.taviraverde.pt\nEndereço Eletrónico: geral@taviraverde.pt\neDelivery Gateway (URL): https://www.acingov.pt\nFunção da Organização: Adquirente\nNorma jurídica da Entidade Adjudicante: Organismo de direito público\nÁrea de atividade da Autoridade Adjudicante: Serviços públicos das administrações públicas\n\n2 - JORNAL OFICIAL DA UNIÃO EUROPEIA\nO procedimento a que este anúncio diz respeito também é publicitado no Jornal Oficial da União Europeia? Sim\n\n3 - AVISO\nModelo de Anúncio: Concurso público\nData de Envio do Anúncio: 02-09-2025\n\n5 - PROCESSO\nTipo de Procedimento: Concurso público\nPreço base do procedimento: Sim\nValor do preço base do procedimento: 278.500,00 EUR\nProcedimento com lotes? Não\n\n6 - OBJETO DO CONTRATO\nNúmero de referência interna: CP/3900/2025\nDesignação do contrato: Aquisição de Varredoura Aspiradora Compacta de 2m3\nDescrição: Aquisição de Varredoura Aspiradora Compacta de 2m3\nOpções: Não\nTipo de Contrato Principal: Aquisição de Bens Móveis\nTipo de Contrato: Aquisição de Bens Móveis\nClassificação CPV (Vocabulário Comum para os Contratos Públicos)\nObjeto principal\nVocabulário Principal: 34144511\nPreço base s/IVA: 278.500,00 EUR\n\n7 - INDICAÇÕES ADICIONAIS\nO contrato envolve aquisição conjunta (satisfação de várias entidades)? Não\nO contrato é adjudicado por uma central de compras? Não\n\n8 - TÉCNICAS\nO concurso destina-se à celebração de um acordo-quadro? Inexistência de acordo-quadro\nÉ utilizado um leilão eletrónico? Não\nÉ adotada uma fase de negociação? Não\nSistema de Aquisição Dinâmico: Inexistência de sistema de aquisição dinâmico\n\n9 - LOCAL DA EXECUÇÃO DO CONTRATO\nLOCAL DA EXECUÇÃO DO CONTRATO (PROCEDIMENTO)\nPaís: Portugal\nNUT III: PT150\nLocalidade: Tavira\nDistrito: Faro\nConcelho: Tavira\nFreguesia: Todas\n\n10 - PRAZO DE EXECUÇÃO DO CONTRATO\nPrazo de execução do contrato: 90 DIAS\nPrevisão de renovações: Não\n\n11 - FUNDOS EU\nTêm fundos EU? Não\n\n12 - DOCUMENTOS DE HABILITAÇÃO\nHabilitação para o exercício da atividade profissional: Não\n\n13 - CONDIÇÕES DE APRESENTAÇÃO\nPlataforma eletrónica utilizada pela entidade adjudicante: ACIN\nURL para Apresentação: https://www.acingov.pt\nAdmissibilidade da apresentação de propostas variantes: Não autorizado\nPrazo para apresentação das propostas: 02-10-2025 23:59\nPrazo durante o qual os concorrentes são obrigados a manter as respetivas propostas: 66 dias a contar do termo do prazo para a apresentação das propostas\nApresentação de Catálogo Eletrónico: Permitido\nIndicação de Subcontratação na Proposta: Inexistência de indicação de subcontratação\n\n14 - PRESTAÇÃO DE CAUÇÃO\nPrestação de caução: Não\n\n15 - FORNECIMENTO DAS PEÇAS DO CONCURSO, APRESENTAÇÃO DE PEDIDOS DE PARTICIPAÇÃO E APRESENTAÇÃO DAS PROPOSTAS\nLink para acesso às peças do concurso (URL): https://www.acingov.pt/acingovprod/2/zonaPublica/zona_publica_c/donwloadProcedurePiece/OTc0Nzkz\n\n20 - OUTROS REQUISITOS\nInformação sobre contratos reservados. Aplica-se a contratos reservados (54º-A)? Não\n\n21 - CRITÉRIO DE ADJUDICAÇÃO\nMultifator: Não\nMonofator:\nNome: Preço\n\n24 - CONDIÇÕES DO CONTRATO\nFaturação Eletrónica: Permitido\nObrigação de Subcontratação:\nCódigo da Obrigação de Subcontratação: Não é aplicável nenhuma obrigação de subcontratação.\n\n25 - COMPRA PÚBLICA ESTRATÉGICA\nCompra Pública Estratégica: Inexistência de contratação pública estratégica\n\n26 - INFORMAÇÕES ADICIONAIS\nContrato adequado para PME: Sim\nCobertura ACP (Acordo dos Contratos Públicos da Organização Mundial do Comércio): Não\n\n27 - IDENTIFICAÇÃO E CONTACTOS DO ÓRGÃO DE RECURSOS ADMINISTRATIVOS\nDesignação: Administração\nEndereço: Largo Tabira de Pernambuco, n.º 1\nCódigo postal: 8800-456\nLocalidade: Tavira\nTelefone: 281380620\nFax: \nEndereço eletrónico: geral@taviraverde.pt\n\n28 - IDENTIFICAÇÃO DO(S) AUTOR(ES) DE ANÚNCIO\nNome: Virgínia Ramos\nCargo: Gestora Jurídica\n419496161",
    "nipc": "507236335",
    "distrito": "Faro",
    "concelho": "Tavira",
    "freguesia": "Todas",
    "site": "www.taviraverde.pt",
    "email": "geral@taviraverde.pt",
    "designacao_contrato": "Aquisição de Varredoura Aspiradora Compacta de 2m3",
    "descricao": "Aquisição de Varredoura Aspiradora Compacta de 2m3",
    "preco_base": "278.500,00 EUR",
    "prazo_execucao": "90 DIAS",
    "prazo_apresentacao_propostas": "02-10-2025 23:59",
    "fundos_eu": "Não",
    "plataforma_eletronica": "ACIN",
    "url_procedimento": "https://www.acingov.pt",
    "autor_nome": "Virgínia Ramos",
    "autor_cargo": "Gestora Jurídica"
  },
  {
    "numero_procedimento": "N/A",
    "entidade": "AnÃºncio de procedimento  n.Âº 23604/2025  -  DiÃ¡rio da RepÃºblica n.Âº 171/2025, SÃ©rie II de 2025-09-05",
    "link": "https://diariodarepublica.pt/dr/detalhe/contrato-publico/23604-934287227"
  },
  {
    "numero_procedimento": "N/A",
    "entidade": "AnÃºncio de procedimento  n.Âº 23605/2025  -  DiÃ¡rio da RepÃºblica n.Âº 171/2025, SÃ©rie II de 2025-09-05",
    "link": "https://diariodarepublica.pt/dr/detalhe/contrato-publico/23605-934287232"
  },
  {
    "numero_procedimento": "N/A",
    "entidade": "AnÃºncio de procedimento  n.Âº 23607/2025  -  DiÃ¡rio da RepÃºblica n.Âº 171/2025, SÃ©rie II de 2025-09-05",
    "link": "https://diariodarepublica.pt/dr/detalhe/contrato-publico/23607-934287233"
  },
  {
    "numero_procedimento": "N/A",
    "entidade": "AnÃºncio de procedimento  n.Âº 23609/2025  -  DiÃ¡rio da RepÃºblica n.Âº 171/2025, SÃ©rie II de 2025-09-05",
    "link": "https://diariodarepublica.pt/dr/detalhe/contrato-publico/23609-934287234"
  },
  {
    "numero_procedimento": "N/A",
    "entidade": "AnÃºncio de procedimento  n.Âº 23611/2025  -  DiÃ¡rio da RepÃºblica n.Âº 171/2025, SÃ©rie II de 2025-09-05",
    "link": "https://diariodarepublica.pt/dr/detalhe/contrato-publico/23611-934287235"
  },
  {
    "numero_procedimento": "N/A",
    "entidade": "AnÃºncio de procedimento  n.Âº 23613/2025  -  DiÃ¡rio da RepÃºblica n.Âº 171/2025, SÃ©rie II de 2025-09-05",
    "link": "https://diariodarepublica.pt/dr/detalhe/contrato-publico/23613-934287236"
  },
  {
    "numero_procedimento": "N/A",
    "entidade": "AnÃºncio de procedimento  n.Âº 23615/2025  -  DiÃ¡rio da RepÃºblica n.Âº 171/2025, SÃ©rie II de 2025-09-05",
    "link": "https://diariodarepublica.pt/dr/detalhe/contrato-publico/23615-934287237"
  },
  {
    "numero_procedimento": "N/A",
    "entidade": "AnÃºncio de procedimento  n.Âº 23606/2025  -  DiÃ¡rio da RepÃºblica n.Âº 171/2025, SÃ©rie II de 2025-09-05",
    "link": "https://diariodarepublica.pt/dr/detalhe/contrato-publico/23606-934323825"
  },
  {
    "numero_procedimento": "N/A",
    "entidade": "AnÃºncio de procedimento  n.Âº 23608/2025  -  DiÃ¡rio da RepÃºblica n.Âº 171/2025, SÃ©rie II de 2025-09-05",
    "link": "https://diariodarepublica.pt/dr/detalhe/contrato-publico/23608-934323826"
  },
  {
    "numero_procedimento": "N/A",
    "entidade": "AnÃºncio de procedimento  n.Âº 23612/2025  -  DiÃ¡rio da RepÃºblica n.Âº 171/2025, SÃ©rie II de 2025-09-05",
    "link": "https://diariodarepublica.pt/dr/detalhe/contrato-publico/23612-934323827"
  },
  {
    "numero_procedimento": "N/A",
    "entidade": "AnÃºncio de procedimento  n.Âº 23614/2025  -  DiÃ¡rio da RepÃºblica n.Âº 171/2025, SÃ©rie II de 2025-09-05",
    "link": "https://diariodarepublica.pt/dr/detalhe/contrato-publico/23614-934323828"
  },
  {
    "numero_procedimento": "N/A",
    "entidade": "AnÃºncio de procedimento  n.Âº 23619/2025  -  DiÃ¡rio da RepÃºblica n.Âº 171/2025, SÃ©rie II de 2025-09-05",
    "link": "https://diariodarepublica.pt/dr/detalhe/contrato-publico/23619-934323872"
  },
  {
    "numero_procedimento": "N/A",
    "entidade": "AnÃºncio de procedimento  n.Âº 23628/2025  -  DiÃ¡rio da RepÃºblica n.Âº 171/2025, SÃ©rie II de 2025-09-05",
    "link": "https://diariodarepublica.pt/dr/detalhe/contrato-publico/23628-934323873"
  },
  {
    "numero_procedimento": "N/A",
    "entidade": "AnÃºncio de procedimento  n.Âº 23616/2025  -  DiÃ¡rio da RepÃºblica n.Âº 171/2025, SÃ©rie II de 2025-09-05",
    "link": "https://diariodarepublica.pt/dr/detalhe/contrato-publico/23616-934359378"
  },
  {
    "numero_procedimento": "N/A",
    "entidade": "AnÃºncio de procedimento  n.Âº 23617/2025  -  DiÃ¡rio da RepÃºblica n.Âº 171/2025, SÃ©rie II de 2025-09-05",
    "link": "https://diariodarepublica.pt/dr/detalhe/contrato-publico/23617-934359379"
  },
  {
    "numero_procedimento": "N/A",
    "entidade": "AnÃºncio de procedimento  n.Âº 23618/2025  -  DiÃ¡rio da RepÃºblica n.Âº 171/2025, SÃ©rie II de 2025-09-05",
    "link": "https://diariodarepublica.pt/dr/detalhe/contrato-publico/23618-934359380"
  },
  {
    "numero_procedimento": "N/A",
    "entidade": "AnÃºncio de procedimento  n.Âº 23620/2025  -  DiÃ¡rio da RepÃºblica n.Âº 171/2025, SÃ©rie II de 2025-09-05",
    "link": "https://diariodarepublica.pt/dr/detalhe/contrato-publico/23620-934359382"
  },
  {
    "numero_procedimento": "N/A",
    "entidade": "AnÃºncio de procedimento  n.Âº 23621/2025  -  DiÃ¡rio da RepÃºblica n.Âº 171/2025, SÃ©rie II de 2025-09-05",
    "link": "https://diariodarepublica.pt/dr/detalhe/contrato-publico/23621-934359383"
  },
  {
    "numero_procedimento": "N/A",
    "entidade": "AnÃºncio de procedimento  n.Âº 23610/2025  -  DiÃ¡rio da RepÃºblica n.Âº 171/2025, SÃ©rie II de 2025-09-05",
    "link": "https://diariodarepublica.pt/dr/detalhe/contrato-publico/23610-934359384"
  },
  {
    "numero_procedimento": "N/A",
    "entidade": "AnÃºncio de procedimento  n.Âº 23622/2025  -  DiÃ¡rio da RepÃºblica n.Âº 171/2025, SÃ©rie II de 2025-09-05",
    "link": "https://diariodarepublica.pt/dr/detalhe/contrato-publico/23622-934359387"
  },
  {
    "numero_procedimento": "N/A",
    "entidade": "AnÃºncio de procedimento  n.Âº 23623/2025  -  DiÃ¡rio da RepÃºblica n.Âº 171/2025, SÃ©rie II de 2025-09-05",
    "link": "https://diariodarepublica.pt/dr/detalhe/contrato-publico/23623-934359388"
  },
  {
    "numero_procedimento": "N/A",
    "entidade": "AnÃºncio de procedimento  n.Âº 23624/2025  -  DiÃ¡rio da RepÃºblica n.Âº 171/2025, SÃ©rie II de 2025-09-05",
    "link": "https://diariodarepublica.pt/dr/detalhe/contrato-publico/23624-934359389"
  },
  {
    "numero_procedimento": "N/A",
    "entidade": "AnÃºncio de procedimento  n.Âº 23625/2025  -  DiÃ¡rio da RepÃºblica n.Âº 171/2025, SÃ©rie II de 2025-09-05",
    "link": "https://diariodarepublica.pt/dr/detalhe/contrato-publico/23625-934359390"
  },
  {
    "numero_procedimento": "N/A",
    "entidade": "AnÃºncio de procedimento  n.Âº 23626/2025  -  DiÃ¡rio da RepÃºblica n.Âº 171/2025, SÃ©rie II de 2025-09-05",
    "link": "https://diariodarepublica.pt/dr/detalhe/contrato-publico/23626-934359391"
  },
  {
    "numero_procedimento": "N/A",
    "entidade": "AnÃºncio de procedimento  n.Âº 23627/2025  -  DiÃ¡rio da RepÃºblica n.Âº 171/2025, SÃ©rie II de 2025-09-05",
    "link": "https://diariodarepublica.pt/dr/detalhe/contrato-publico/23627-934359392"
  },
  {
    "numero_procedimento": "N/A",
    "entidade": "AnÃºncio de procedimento  n.Âº 23630/2025  -  DiÃ¡rio da RepÃºblica n.Âº 171/2025, SÃ©rie II de 2025-09-05",
    "link": "https://diariodarepublica.pt/dr/detalhe/contrato-publico/23630-934359395"
  },
  {
    "numero_procedimento": "N/A",
    "entidade": "AnÃºncio de procedimento  n.Âº 23632/2025  -  DiÃ¡rio da RepÃºblica n.Âº 171/2025, SÃ©rie II de 2025-09-05",
    "link": "https://diariodarepublica.pt/dr/detalhe/contrato-publico/23632-934359396"
  },
  {
    "numero_procedimento": "N/A",
    "entidade": "AnÃºncio de procedimento  n.Âº 23638/2025  -  DiÃ¡rio da RepÃºblica n.Âº 171/2025, SÃ©rie II de 2025-09-05",
    "link": "https://diariodarepublica.pt/dr/detalhe/contrato-publico/23638-934359398"
  },
  {
    "numero_procedimento": "N/A",
    "entidade": "AnÃºncio de procedimento  n.Âº 23640/2025  -  DiÃ¡rio da RepÃºblica n.Âº 171/2025, SÃ©rie II de 2025-09-05",
    "link": "https://diariodarepublica.pt/dr/detalhe/contrato-publico/23640-934359399"
  },
  {
    "numero_procedimento": "N/A",
    "entidade": "AnÃºncio de procedimento  n.Âº 23642/2025  -  DiÃ¡rio da RepÃºblica n.Âº 171/2025, SÃ©rie II de 2025-09-05",
    "link": "https://diariodarepublica.pt/dr/detalhe/contrato-publico/23642-934359400"
  },
  {
    "numero_procedimento": "N/A",
    "entidade": "SIMDOURO - Saneamento do Grande Porto, S.A.",
    "link": "https://diariodarepublica.pt/dr/detalhe/contrato-publico/23643-934359401",
    "detalhes_completos": "1 - IDENTIFICAÇÃO E CONTACTOS DA ENTIDADE ADJUDICANTE\nDesignação da entidade adjudicante: SIMDOURO - Saneamento do Grande Porto, S.A.\nNIPC: 514310103\nServiço/Órgão/Pessoa de contacto: SIMDOURO - Saneamento do Grande Porto, S.A.\nEndereço: ETAR de Gaia Litoral Rua Alto das Chaquedas, S/N\nCódigo postal: 4400-356\nLocalidade: Vila Nova de Gaia\nPaís: Portugal\nNUT III: PT11A\nDistrito: Porto\nConcelho: Vila Nova de Gaia\nFreguesia: Freguesia de Canidelo - Vila Nova de Gaia\nTelefone: 226059300\nFax: 220109301\nEndereço da Entidade (URL): www.simdouro.pt\nEndereço Eletrónico: geral@simdouro.pt\neDelivery Gateway (URL): https://www.acingov.pt\nFunção da Organização: Adquirente\nNorma jurídica da Entidade Adjudicante: Organismo de direito público\nÁrea de atividade da Entidade Adjudicante: Atividades relacionadas com a água\n\n2 - JORNAL OFICIAL DA UNIÃO EUROPEIA\nO procedimento a que este anúncio diz respeito também é publicitado no Jornal Oficial da União Europeia? Não\n\n3 - AVISO\nModelo de Anúncio: Concurso público\nData de Envio do Anúncio: 05-09-2025\n\n5 - PROCESSO\nTipo de Procedimento: Concurso público\nPreço base do procedimento: Sim\nValor do preço base do procedimento: 50.000,00 EUR\nProcedimento com lotes? Não\n\n6 - OBJETO DO CONTRATO\nNúmero de referência interna: PROC-SD-46/2025\nDesignação do contrato: Aquisição de Equipamentos de Proteção Individual pela SIMDOURO\nDescrição: Aquisição de Equipamentos de Proteção Individual pela SIMDOURO\nTipo de Contrato Principal: Aquisição de Bens Móveis\nTipo de Contrato: Aquisição de Bens Móveis\nClassificação CPV (Vocabulário Comum para os Contratos Públicos)\nObjeto principal\nVocabulário Principal: 18143000\nPreço base s/IVA: 50.000,00 EUR\n\n7 - INDICAÇÕES ADICIONAIS\nO contrato envolve aquisição conjunta (satisfação de várias entidades)? Não\nO contrato é adjudicado por uma central de compras? Não\n\n8 - TÉCNICAS\nO concurso destina-se à celebração de um acordo-quadro? Inexistência de acordo-quadro\nÉ utilizado um leilão eletrónico? Não\nÉ adotada uma fase de negociação? Não\nSistema de Aquisição Dinâmico: Inexistência de sistema de aquisição dinâmico\n\n9 - LOCAL DA EXECUÇÃO DO CONTRATO\nLOCAL DA EXECUÇÃO DO CONTRATO (PROCEDIMENTO)\nPaís: Portugal\nNUT III: PT11A\nLocalidade: Freguesia de Canidelo - Vila Nova de Gaia\nDistrito: Porto\nConcelho: Vila Nova de Gaia\nFreguesia: Freguesia de Canidelo - Vila Nova de Gaia\n\n10 - PRAZO DE EXECUÇÃO DO CONTRATO\nPrazo de execução do contrato: 1 ANOS\nPrevisão de renovações: Sim\nIndicar número máximo de renovações: 2\nPrazo de renovações diferente do prazo inicial: Não\n\n11 - FUNDOS EU\nTêm fundos EU? Não\n\n12 - DOCUMENTOS DE HABILITAÇÃO\nHabilitação para o exercício da atividade profissional: Não\n\n13 - CONDIÇÕES DE APRESENTAÇÃO\nPlataforma eletrónica utilizada pela entidade adjudicante: ACIN\nURL para Apresentação: https://www.acingov.pt\nAdmissibilidade da apresentação de propostas variantes: Não autorizado\nPrazo para apresentação das propostas: 17-09-2025 23:59\nPrazo durante o qual os concorrentes são obrigados a manter as respetivas propostas: 90 dias a contar do termo do prazo para a apresentação das propostas\nIndicação de Subcontratação na Proposta: Inexistência de indicação de subcontratação\n\n14 - PRESTAÇÃO DE CAUÇÃO\nPrestação de caução: Não\n\n15 - FORNECIMENTO DAS PEÇAS DO CONCURSO, APRESENTAÇÃO DE PEDIDOS DE PARTICIPAÇÃO E APRESENTAÇÃO DAS PROPOSTAS\nLink para acesso às peças do concurso (URL): https://www.acingov.pt/acingovprod/2/zonaPublica/zona_publica_c/donwloadProcedurePiece/OTc1NDgx\n\n20 - OUTROS REQUISITOS\nInformação sobre contratos reservados. Aplica-se a contratos reservados (54º-A)? Não\n\n21 - CRITÉRIO DE ADJUDICAÇÃO\nMultifator: Não\nMonofator:\nNome: Preço\n\n24 - CONDIÇÕES DO CONTRATO\nFaturação Eletrónica: Necessário\nObrigação de Subcontratação:\nCódigo da Obrigação de Subcontratação: Não é aplicável nenhuma obrigação de subcontratação.\n\n25 - COMPRA PÚBLICA ESTRATÉGICA\nCompra Pública Estratégica: Inexistência de contratação pública estratégica\n\n26 - INFORMAÇÕES ADICIONAIS\nContrato adequado para PME: Sim\nCobertura ACP (Acordo dos Contratos Públicos da Organização Mundial do Comércio): Não\n\n27 - IDENTIFICAÇÃO E CONTACTOS DO ÓRGÃO DE RECURSOS ADMINISTRATIVOS\nDesignação: Conselho de Administração da SIMDOURO - Saneamento do Grande Porto, S.A.\nEndereço: ETAR de Gaia Litoral Rua Alto das Chaquedas, S/N\nCódigo postal: 4400-356\nLocalidade: Vila Nova de Gaia\nTelefone: 226059300\nFax: \nEndereço eletrónico: geral@simdouro.pt\n\n28 - IDENTIFICAÇÃO DO(S) AUTOR(ES) DE ANÚNCIO\nNome: Ana Maria Rocha Dias\nCargo: Gestora do Procedimento\n419507509",
    "nipc": "514310103",
    "distrito": "Porto",
    "concelho": "Vila Nova de Gaia",
    "freguesia": "Freguesia de Canidelo - Vila Nova de Gaia",
    "site": "www.simdouro.pt",
    "email": "geral@simdouro.pt",
    "designacao_contrato": "Aquisição de Equipamentos de Proteção Individual pela SIMDOURO",
    "descricao": "Aquisição de Equipamentos de Proteção Individual pela SIMDOURO",
    "preco_base": "50.000,00 EUR",
    "prazo_execucao": "1 ANOS",
    "prazo_apresentacao_propostas": "17-09-2025 23:59",
    "fundos_eu": "Não",
    "plataforma_eletronica": "ACIN",
    "url_procedimento": "https://www.acingov.pt",
    "autor_nome": "Ana Maria Rocha Dias",
    "autor_cargo": "Gestora do Procedimento"
  },
  {
    "numero_procedimento": "N/A",
    "entidade": "MUNICÍPIO DE LOULÉ",
    "link": "https://diariodarepublica.pt/dr/detalhe/contrato-publico/23646-934359402",
    "detalhes_completos": "Alteração do Anúncio de procedimento n.º 20678/2025, de 2025-08-01, com o ID 419365232\n\n1 - IDENTIFICAÇÃO E CONTACTOS DA ENTIDADE ADJUDICANTE\nDesignação da entidade adjudicante: MUNICÍPIO DE LOULÉ\nNIPC: 502098139\nEndereço: Praça da República\nCódigo postal: 8104-001\nLocalidade: Faro\nPaís: Portugal\nNUT III: PT150\nDistrito: Faro\nConcelho: Loulé\nFreguesia: Todas\nTelefone: 289400834\nFax: 289415557\nEndereço da Entidade (URL): www.cm-loule.pt\nEndereço Eletrónico: aprovisionamento@cm-loule.pt\neDelivery Gateway (URL): https://community.vortal.biz/public/\nFunção da Organização: Adquirente\nNorma jurídica da Entidade Adjudicante: Organismo de direito público\nÁrea de atividade da Autoridade Adjudicante: Serviços públicos das administrações públicas\n\n2 - JORNAL OFICIAL DA UNIÃO EUROPEIA\nO procedimento a que este anúncio diz respeito também é publicitado no Jornal Oficial da União Europeia? Sim\n\n3 - AVISO\nModelo de Anúncio: Concurso público\nData de Envio do Anúncio: 03-09-2025\n\n5 - PROCESSO\nTipo de Procedimento: Concurso público\nPreço base do procedimento: Sim\nValor do preço base do procedimento: 68.632,00 EUR\nProcedimento com lotes? Sim\nNº Máx. de Lotes Autorizado: 5\nNúmero máximo de lotes que podem ser adjudicados a um concorrente: 5\n\n6 - OBJETO DO CONTRATO\nNúmero de referência interna: FM-2025-317 DACP\nDesignação do contrato: CONTRATAÇÃO DO FORNECIMENTO CONTÍNUO DE FARDAMENTO, EQUIPAMENTOS DE PROTEÇÃO INDIVIDUAL (EPIS) E MATERIAL PARA INCÊNDIOS RURAIS PARA A DIVISÃO DE AMBIENTE (DA) E EQUIPAMENTOS DE PROTEÇÃO INDIVIDUAL (E\nDescrição: CONTRATAÇÃO DO FORNECIMENTO CONTÍNUO DE FARDAMENTO, EQUIPAMENTOS DE PROTEÇÃO INDIVIDUAL (EPIS) E MATERIAL PARA INCÊNDIOS RURAIS PARA A DIVISÃO DE AMBIENTE (DA) E EQUIPAMENTOS DE PROTEÇÃO INDIVIDUAL (EPIS) PARA A UNIDADE OPERACIONAL DE ESPAÇOS VERDES E JARDINS (UOEVJ)\nOpções: Não\nTipo de Contrato Principal: Aquisição de Bens Móveis\nTipo de Contrato: Aquisição de Bens Móveis\nClassificação CPV (Vocabulário Comum para os Contratos Públicos)\nObjeto principal\nVocabulário Principal: 35110000\nPreço base s/IVA: 68.632,00 EUR\nLotes: \nNº: LOT-0001\nDescrição do Lote: LOTE 1 \nPreço base s/IVA: 15.480,00 EUR\nClassificação CPV (Vocabulário Comum para os Contratos Públicos)\nObjeto principal\nVocabulário Principal: 35110000\nNº: LOT-0002\nDescrição do Lote: LOTE 2 \nPreço base s/IVA: 17.652,00 EUR\nClassificação CPV (Vocabulário Comum para os Contratos Públicos)\nObjeto principal\nVocabulário Principal: 35110000\nNº: LOT-0003\nDescrição do Lote: LOTE 3\nPreço base s/IVA: 13.440,00 EUR\nClassificação CPV (Vocabulário Comum para os Contratos Públicos)\nObjeto principal\nVocabulário Principal: 35110000\nNº: LOT-0004\nDescrição do Lote: LOTE 4\nPreço base s/IVA: 10.370,00 EUR\nClassificação CPV (Vocabulário Comum para os Contratos Públicos)\nObjeto principal\nVocabulário Principal: 35110000\nNº: LOT-0005\nDescrição do Lote: LOTE 5\nPreço base s/IVA: 11.690,00 EUR\nClassificação CPV (Vocabulário Comum para os Contratos Públicos)\nObjeto principal\nVocabulário Principal: 35110000\n\n7 - INDICAÇÕES ADICIONAIS\nO contrato envolve aquisição conjunta (satisfação de várias entidades)? Não\nO contrato é adjudicado por uma central de compras? Não\n\n8 - TÉCNICAS\nO concurso destina-se à celebração de um acordo-quadro? Inexistência de acordo-quadro\nÉ utilizado um leilão eletrónico? Não\nÉ adotada uma fase de negociação? Não\nSistema de Aquisição Dinâmico: Inexistência de sistema de aquisição dinâmico\n\n9 - LOCAL DA EXECUÇÃO DO CONTRATO\nLOCAL DA EXECUÇÃO DO CONTRATO (PROCEDIMENTO)\nPaís: Portugal\nNUT III: PT150\nLocalidade: Faro\nDistrito: Faro\nConcelho: Loulé\nFreguesia: Todas\nLOCAL DA EXECUÇÃO DO CONTRATO (LOTE)\nIdentificador do Lote: LOT-0001; LOT-0002; LOT-0003; LOT-0004; LOT-0005\nPaís: Portugal\nNUT III: PT150\nLocalidade: Faro\nDistrito: Faro\nConcelho: Loulé\nFreguesia: Todas\n\n10 - PRAZO DE EXECUÇÃO DO CONTRATO\nIdentificador do Lote: LOT-0001; LOT-0002; LOT-0003; LOT-0004; LOT-0005\nPrazo de execução do contrato: 16 MESES\nPrevisão de renovações: Não\n\n11 - FUNDOS EU\nIdentificador do Lote: LOT-0001; LOT-0002; LOT-0003; LOT-0004; LOT-0005\nTêm fundos EU? Não\n\n12 - DOCUMENTOS DE HABILITAÇÃO\nHabilitação para o exercício da atividade profissional: Não\n\n13 - CONDIÇÕES DE APRESENTAÇÃO\nPlataforma eletrónica utilizada pela entidade adjudicante: VORTAL\nURL para Apresentação: https://community.vortal.biz/public/\nAdmissibilidade da apresentação de propostas variantes: Não autorizado\nPrazo para apresentação das propostas: 25-09-2025 18:00\nPrazo durante o qual os concorrentes são obrigados a manter as respetivas propostas: 90 dias a contar do termo do prazo para a apresentação das propostas\nApresentação de Catálogo Eletrónico: Não autorizado\nIndicação de Subcontratação na Proposta: Inexistência de indicação de subcontratação\n\n14 - PRESTAÇÃO DE CAUÇÃO\nPrestação de caução: Não\n\n15 - FORNECIMENTO DAS PEÇAS DO CONCURSO, APRESENTAÇÃO DE PEDIDOS DE PARTICIPAÇÃO E APRESENTAÇÃO DAS PROPOSTAS\nLink para acesso às peças do concurso (URL): https://community.vortal.biz/Public/public-tender-documents/SVRBM0lIMDNZMzk4dnRxakZTdm44eGg1b0pGYUN2Rng5SU5LQ3A2eHZTTFM0QVFOeG5lT1Y2QnNkSEQyVHNibDVLd1B1d1paRno0R0hGdXB5T1d6V1E9PU9OI0lO\n\n20 - OUTROS REQUISITOS\nIdentificador do Lote: LOT-0001; LOT-0002; LOT-0003; LOT-0004; LOT-0005\nInformação sobre contratos reservados. Aplica-se a contratos reservados (54º-A)? Não\n\n21 - CRITÉRIO DE ADJUDICAÇÃO\nO Critério de adjudicação é diferenciado por lote? Não\nMultifator: Não\nMonofator:\nNome: Preço\n\n24 - CONDIÇÕES DO CONTRATO\nIdentificador do Lote: LOT-0001; LOT-0002; LOT-0003; LOT-0004; LOT-0005\nFaturação Eletrónica: Permitido\nObrigação de Subcontratação:\nCódigo da Obrigação de Subcontratação: Não é aplicável nenhuma obrigação de subcontratação.\n\n25 - COMPRA PÚBLICA ESTRATÉGICA\nCompra Pública Estratégica: Inexistência de contratação pública estratégica\n\n26 - INFORMAÇÕES ADICIONAIS\nIdentificador do Lote: LOT-0001; LOT-0002; LOT-0003; LOT-0004; LOT-0005\nContrato adequado para PME: Sim\nCobertura ACP (Acordo dos Contratos Públicos da Organização Mundial do Comércio): Não\n\n27 - IDENTIFICAÇÃO E CONTACTOS DO ÓRGÃO DE RECURSOS ADMINISTRATIVOS\nDesignação: Câmara Municipal de Loulé\nEndereço: Praça da República\nCódigo postal: 8104-001\nLocalidade: Loulé\nTelefone: +351 289400600\nFax: +351 289415557\nEndereço eletrónico: geral@cm-loule.pt\n\n28 - IDENTIFICAÇÃO DO(S) AUTOR(ES) DE ANÚNCIO\nNome: Vítor Manuel Gonçalves Aleixo\nCargo: Presidente da Câmara Municipal\n\n29 - ALTERAÇÃO\nMotivo da Alteração: Informações atualizadas\nIdentificador da Versão do Anúncio a Alterar: 1dc48df9-440f-4871-b7b8-e5e3d9c16a41-01\nIdentificador das Secções Alteradas do Anúncio Anterior: Processo\nDescrição das Alterações: Alteração do Prazo para apresentação das propostas (BT-131(d)-Procedure) de 03-09-2025 pelas 18:00, para 25-09-2025, pelas 18:00\nAlteração dos Documentos do Concurso: Não\n419496112",
    "nipc": "502098139",
    "distrito": "Faro",
    "concelho": "Loulé",
    "freguesia": "Todas",
    "site": "www.cm-loule.pt",
    "email": "aprovisionamento@cm-loule.pt",
    "designacao_contrato": "CONTRATAÇÃO DO FORNECIMENTO CONTÍNUO DE FARDAMENTO, EQUIPAMENTOS DE PROTEÇÃO INDIVIDUAL (EPIS) E MATERIAL PARA INCÊNDIOS RURAIS PARA A DIVISÃO DE AMBIENTE (DA) E EQUIPAMENTOS DE PROTEÇÃO INDIVIDUAL (E",
    "descricao": "CONTRATAÇÃO DO FORNECIMENTO CONTÍNUO DE FARDAMENTO, EQUIPAMENTOS DE PROTEÇÃO INDIVIDUAL (EPIS) E MATERIAL PARA INCÊNDIOS RURAIS PARA A DIVISÃO DE AMBIENTE (DA) E EQUIPAMENTOS DE PROTEÇÃO INDIVIDUAL (EPIS) PARA A UNIDADE OPERACIONAL DE ESPAÇOS VERDES E JARDINS (UOEVJ)",
    "preco_base": "68.632,00 EUR",
    "prazo_execucao": "16 MESES",
    "prazo_apresentacao_propostas": "25-09-2025 18:00",
    "fundos_eu": "Não",
    "plataforma_eletronica": "VORTAL",
    "url_procedimento": "https://community.vortal.biz/public/",
    "autor_nome": "Vítor Manuel Gonçalves Aleixo",
    "autor_cargo": "Presidente da Câmara Municipal"
  },
  {
    "numero_procedimento": "N/A",
    "entidade": "AnÃºncio de procedimento  n.Âº 23648/2025  -  DiÃ¡rio da RepÃºblica n.Âº 171/2025, SÃ©rie II de 2025-09-05",
    "link": "https://diariodarepublica.pt/dr/detalhe/contrato-publico/23648-934359403"
  },
  {
    "numero_procedimento": "N/A",
    "entidade": "EPF - Ensino Profissional de Felgueiras, E.M. Unipessoal Lda",
    "link": "https://diariodarepublica.pt/dr/detalhe/contrato-publico/23629-934420375",
    "detalhes_completos": "1 - IDENTIFICAÇÃO E CONTACTOS DA ENTIDADE ADJUDICANTE\nDesignação da entidade adjudicante: EPF - Ensino Profissional de Felgueiras, E.M. Unipessoal Lda\nNIPC: 504575848\nServiço/Órgão/Pessoa de contacto: Gerência\nEndereço: Rua dos Bombeiros Voluntários de Felgueiras 104\nCódigo postal: 4610-165\nLocalidade: Felgueiras\nPaís: Portugal\nNUT III: PT11C\nDistrito: Porto\nConcelho: Felgueiras\nFreguesia: União das Freguesias de Margaride (Santa Eulália), Várzea, Lagares, Varziela e Moure\nTelefone: 255312492\nFax: 255312419\nEndereço da Entidade (URL): www.epfelgueiras.pt\nEndereço Eletrónico: epf@epfelgueiras.pt\neDelivery Gateway (URL): https://www.acingov.pt\nFunção da Organização: Adquirente\nNorma jurídica da Entidade Adjudicante: Organismo de direito público\nÁrea de atividade da Autoridade Adjudicante: Serviços públicos das administrações públicas\n\n2 - JORNAL OFICIAL DA UNIÃO EUROPEIA\nO procedimento a que este anúncio diz respeito também é publicitado no Jornal Oficial da União Europeia? Não\n\n3 - AVISO\nModelo de Anúncio: Concurso público\nData de Envio do Anúncio: 05-09-2025\n\n5 - PROCESSO\nTipo de Procedimento: Concurso público\nPreço base do procedimento: Sim\nValor do preço base do procedimento: 8.850,00 EUR\nProcedimento com lotes? Não\n\n6 - OBJETO DO CONTRATO\nNúmero de referência interna: CoP004/2025\nDesignação do contrato: Serviço de transporte de táxi ou equivalente diário destinado a alunos para o ano letivo 2025/2026\nDescrição: Serviço de transporte de táxi ou equivalente diário destinado a alunos para o ano letivo 2025/2026\nTipo de Contrato Principal: Aquisição de Serviços\nTipo de Contrato: Aquisição de Serviços\nClassificação CPV (Vocabulário Comum para os Contratos Públicos)\nObjeto principal\nVocabulário Principal: 60140000\nPreço base s/IVA: 8.850,00 EUR\n\n7 - INDICAÇÕES ADICIONAIS\nO contrato envolve aquisição conjunta (satisfação de várias entidades)? Não\nO contrato é adjudicado por uma central de compras? Não\n\n8 - TÉCNICAS\nO concurso destina-se à celebração de um acordo-quadro? Inexistência de acordo-quadro\nÉ utilizado um leilão eletrónico? Não\nÉ adotada uma fase de negociação? Não\nSistema de Aquisição Dinâmico: Inexistência de sistema de aquisição dinâmico\n\n9 - LOCAL DA EXECUÇÃO DO CONTRATO\nLOCAL DA EXECUÇÃO DO CONTRATO (PROCEDIMENTO)\nPaís: Portugal\nNUT III: PT11C\nLocalidade: União das Freguesias de Margaride (Santa Eulália), Várzea, Lagares, Varziela e Moure\nDistrito: Porto\nConcelho: Felgueiras\nFreguesia: União das Freguesias de Margaride (Santa Eulália), Várzea, Lagares, Varziela e Moure\n\n10 - PRAZO DE EXECUÇÃO DO CONTRATO\nPrazo de execução do contrato: 283 DIAS\nPrevisão de renovações: Não\n\n11 - FUNDOS EU\nTêm fundos EU? Não\n\n12 - DOCUMENTOS DE HABILITAÇÃO\nHabilitação para o exercício da atividade profissional: Não\n\n13 - CONDIÇÕES DE APRESENTAÇÃO\nPlataforma eletrónica utilizada pela entidade adjudicante: ACIN\nURL para Apresentação: https://www.acingov.pt\nAdmissibilidade da apresentação de propostas variantes: Não autorizado\nPrazo para apresentação das propostas: 11-09-2025 23:59\nPrazo durante o qual os concorrentes são obrigados a manter as respetivas propostas: 66 dias a contar do termo do prazo para a apresentação das propostas\nIndicação de Subcontratação na Proposta: Inexistência de indicação de subcontratação\n\n14 - PRESTAÇÃO DE CAUÇÃO\nPrestação de caução: Não\n\n15 - FORNECIMENTO DAS PEÇAS DO CONCURSO, APRESENTAÇÃO DE PEDIDOS DE PARTICIPAÇÃO E APRESENTAÇÃO DAS PROPOSTAS\nLink para acesso às peças do concurso (URL): https://www.acingov.pt/acingovprod/2/zonaPublica/zona_publica_c/donwloadProcedurePiece/OTc1NDQy\n\n20 - OUTROS REQUISITOS\nInformação sobre contratos reservados. Aplica-se a contratos reservados (54º-A)? Não\n\n21 - CRITÉRIO DE ADJUDICAÇÃO\nMultifator: Não\nMonofator:\nNome: Outros\nOutro nome: Fator Preço\n\n24 - CONDIÇÕES DO CONTRATO\nFaturação Eletrónica: Necessário\nObrigação de Subcontratação:\nCódigo da Obrigação de Subcontratação: Não é aplicável nenhuma obrigação de subcontratação.\n\n25 - COMPRA PÚBLICA ESTRATÉGICA\nCompra Pública Estratégica: Inexistência de contratação pública estratégica\n\n26 - INFORMAÇÕES ADICIONAIS\nContrato adequado para PME: Não\nCobertura ACP (Acordo dos Contratos Públicos da Organização Mundial do Comércio): Não\n\n27 - IDENTIFICAÇÃO E CONTACTOS DO ÓRGÃO DE RECURSOS ADMINISTRATIVOS\nDesignação: Gerência\nEndereço: Rua dos Bombeiros Voluntários de Felgueiras Unipessoal Lda\nCódigo postal: 4610-165\nLocalidade: Felgueiras\nTelefone: 255312482\nFax: 255312419\nEndereço eletrónico: epf@epfelgueiras.pt\nPrazo de interposição do recurso: 5 dias\n\n28 - IDENTIFICAÇÃO DO(S) AUTOR(ES) DE ANÚNCIO\nNome: Vera Lúcia Ribeiro Sampaio\nCargo: Gerente\n419506894",
    "nipc": "504575848",
    "distrito": "Porto",
    "concelho": "Felgueiras",
    "freguesia": "União das Freguesias de Margaride (Santa Eulália), Várzea, Lagares, Varziela e Moure",
    "site": "www.epfelgueiras.pt",
    "email": "epf@epfelgueiras.pt",
    "designacao_contrato": "Serviço de transporte de táxi ou equivalente diário destinado a alunos para o ano letivo 2025/2026",
    "descricao": "Serviço de transporte de táxi ou equivalente diário destinado a alunos para o ano letivo 2025/2026",
    "preco_base": "8.850,00 EUR",
    "prazo_execucao": "283 DIAS",
    "prazo_apresentacao_propostas": "11-09-2025 23:59",
    "fundos_eu": "Não",
    "plataforma_eletronica": "ACIN",
    "url_procedimento": "https://www.acingov.pt",
    "autor_nome": "Vera Lúcia Ribeiro Sampaio",
    "autor_cargo": "Gerente"
  },
  {
    "numero_procedimento": "N/A",
    "entidade": "AnÃºncio de procedimento  n.Âº 23631/2025  -  DiÃ¡rio da RepÃºblica n.Âº 171/2025, SÃ©rie II de 2025-09-05",
    "link": "https://diariodarepublica.pt/dr/detalhe/contrato-publico/23631-934420376"
  },
  {
    "numero_procedimento": "N/A",
    "entidade": "AnÃºncio de procedimento  n.Âº 23633/2025  -  DiÃ¡rio da RepÃºblica n.Âº 171/2025, SÃ©rie II de 2025-09-05",
    "link": "https://diariodarepublica.pt/dr/detalhe/contrato-publico/23633-934420377"
  },
  {
    "numero_procedimento": "N/A",
    "entidade": "AnÃºncio de procedimento  n.Âº 23634/2025  -  DiÃ¡rio da RepÃºblica n.Âº 171/2025, SÃ©rie II de 2025-09-05",
    "link": "https://diariodarepublica.pt/dr/detalhe/contrato-publico/23634-934420378"
  },
  {
    "numero_procedimento": "N/A",
    "entidade": "AnÃºncio de procedimento  n.Âº 23635/2025  -  DiÃ¡rio da RepÃºblica n.Âº 171/2025, SÃ©rie II de 2025-09-05",
    "link": "https://diariodarepublica.pt/dr/detalhe/contrato-publico/23635-934420379"
  },
  {
    "numero_procedimento": "N/A",
    "entidade": "AnÃºncio de procedimento  n.Âº 23636/2025  -  DiÃ¡rio da RepÃºblica n.Âº 171/2025, SÃ©rie II de 2025-09-05",
    "link": "https://diariodarepublica.pt/dr/detalhe/contrato-publico/23636-934420380"
  },
  {
    "numero_procedimento": "N/A",
    "entidade": "AnÃºncio de procedimento  n.Âº 23637/2025  -  DiÃ¡rio da RepÃºblica n.Âº 171/2025, SÃ©rie II de 2025-09-05",
    "link": "https://diariodarepublica.pt/dr/detalhe/contrato-publico/23637-934420381"
  },
  {
    "numero_procedimento": "N/A",
    "entidade": "AnÃºncio de procedimento  n.Âº 23639/2025  -  DiÃ¡rio da RepÃºblica n.Âº 171/2025, SÃ©rie II de 2025-09-05",
    "link": "https://diariodarepublica.pt/dr/detalhe/contrato-publico/23639-934420382"
  },
  {
    "numero_procedimento": "N/A",
    "entidade": "AnÃºncio de procedimento  n.Âº 23641/2025  -  DiÃ¡rio da RepÃºblica n.Âº 171/2025, SÃ©rie II de 2025-09-05",
    "link": "https://diariodarepublica.pt/dr/detalhe/contrato-publico/23641-934420383"
  },
  {
    "numero_procedimento": "N/A",
    "entidade": "AnÃºncio de procedimento  n.Âº 23644/2025  -  DiÃ¡rio da RepÃºblica n.Âº 171/2025, SÃ©rie II de 2025-09-05",
    "link": "https://diariodarepublica.pt/dr/detalhe/contrato-publico/23644-934420384"
  },
  {
    "numero_procedimento": "N/A",
    "entidade": "AnÃºncio de procedimento  n.Âº 23645/2025  -  DiÃ¡rio da RepÃºblica n.Âº 171/2025, SÃ©rie II de 2025-09-05",
    "link": "https://diariodarepublica.pt/dr/detalhe/contrato-publico/23645-934420385"
  },
  {
    "numero_procedimento": "N/A",
    "entidade": "AnÃºncio de procedimento  n.Âº 23647/2025  -  DiÃ¡rio da RepÃºblica n.Âº 171/2025, SÃ©rie II de 2025-09-05",
    "link": "https://diariodarepublica.pt/dr/detalhe/contrato-publico/23647-934420395"
  },
  {
    "numero_procedimento": "N/A",
    "entidade": "AnÃºncio de procedimento  n.Âº 23649/2025  -  DiÃ¡rio da RepÃºblica n.Âº 171/2025, SÃ©rie II de 2025-09-05",
    "link": "https://diariodarepublica.pt/dr/detalhe/contrato-publico/23649-934420396"
  },
  {
    "numero_procedimento": "N/A",
    "entidade": "AnÃºncio de procedimento  n.Âº 23650/2025  -  DiÃ¡rio da RepÃºblica n.Âº 171/2025, SÃ©rie II de 2025-09-05",
    "link": "https://diariodarepublica.pt/dr/detalhe/contrato-publico/23650-934420397"
  },
  {
    "numero_procedimento": "N/A",
    "entidade": "AnÃºncio de procedimento  n.Âº 23654/2025  -  DiÃ¡rio da RepÃºblica n.Âº 171/2025, SÃ©rie II de 2025-09-05",
    "link": "https://diariodarepublica.pt/dr/detalhe/contrato-publico/23654-934420399"
  },
  {
    "numero_procedimento": "N/A",
    "entidade": "AnÃºncio de procedimento  n.Âº 23655/2025  -  DiÃ¡rio da RepÃºblica n.Âº 171/2025, SÃ©rie II de 2025-09-05",
    "link": "https://diariodarepublica.pt/dr/detalhe/contrato-publico/23655-934420400"
  },
  {
    "numero_procedimento": "N/A",
    "entidade": "AnÃºncio de procedimento  n.Âº 23656/2025  -  DiÃ¡rio da RepÃºblica n.Âº 171/2025, SÃ©rie II de 2025-09-05",
    "link": "https://diariodarepublica.pt/dr/detalhe/contrato-publico/23656-934420401"
  },
  {
    "numero_procedimento": "N/A",
    "entidade": "AnÃºncio de procedimento  n.Âº 23657/2025  -  DiÃ¡rio da RepÃºblica n.Âº 171/2025, SÃ©rie II de 2025-09-05",
    "link": "https://diariodarepublica.pt/dr/detalhe/contrato-publico/23657-934420402"
  },
  {
    "numero_procedimento": "N/A",
    "entidade": "AnÃºncio de procedimento  n.Âº 23660/2025  -  DiÃ¡rio da RepÃºblica n.Âº 171/2025, SÃ©rie II de 2025-09-05",
    "link": "https://diariodarepublica.pt/dr/detalhe/contrato-publico/23660-934420403"
  },
  {
    "numero_procedimento": "N/A",
    "entidade": "AnÃºncio de procedimento  n.Âº 23663/2025  -  DiÃ¡rio da RepÃºblica n.Âº 171/2025, SÃ©rie II de 2025-09-05",
    "link": "https://diariodarepublica.pt/dr/detalhe/contrato-publico/23663-934420404"
  },
  {
    "numero_procedimento": "N/A",
    "entidade": "AnÃºncio de procedimento  n.Âº 23664/2025  -  DiÃ¡rio da RepÃºblica n.Âº 171/2025, SÃ©rie II de 2025-09-05",
    "link": "https://diariodarepublica.pt/dr/detalhe/contrato-publico/23664-934420405"
  },
  {
    "numero_procedimento": "N/A",
    "entidade": "AnÃºncio de procedimento  n.Âº 23665/2025  -  DiÃ¡rio da RepÃºblica n.Âº 171/2025, SÃ©rie II de 2025-09-05",
    "link": "https://diariodarepublica.pt/dr/detalhe/contrato-publico/23665-934420406"
  },
  {
    "numero_procedimento": "N/A",
    "entidade": "AnÃºncio de procedimento  n.Âº 23667/2025  -  DiÃ¡rio da RepÃºblica n.Âº 171/2025, SÃ©rie II de 2025-09-05",
    "link": "https://diariodarepublica.pt/dr/detalhe/contrato-publico/23667-934420407"
  },
  {
    "numero_procedimento": "N/A",
    "entidade": "AnÃºncio de procedimento  n.Âº 23668/2025  -  DiÃ¡rio da RepÃºblica n.Âº 171/2025, SÃ©rie II de 2025-09-05",
    "link": "https://diariodarepublica.pt/dr/detalhe/contrato-publico/23668-934420408"
  },
  {
    "numero_procedimento": "N/A",
    "entidade": "AnÃºncio de procedimento  n.Âº 23669/2025  -  DiÃ¡rio da RepÃºblica n.Âº 171/2025, SÃ©rie II de 2025-09-05",
    "link": "https://diariodarepublica.pt/dr/detalhe/contrato-publico/23669-934420409"
  },
  {
    "numero_procedimento": "N/A",
    "entidade": "AnÃºncio de procedimento  n.Âº 23670/2025  -  DiÃ¡rio da RepÃºblica n.Âº 171/2025, SÃ©rie II de 2025-09-05",
    "link": "https://diariodarepublica.pt/dr/detalhe/contrato-publico/23670-934420410"
  },
  {
    "numero_procedimento": "N/A",
    "entidade": "AnÃºncio de procedimento  n.Âº 23671/2025  -  DiÃ¡rio da RepÃºblica n.Âº 171/2025, SÃ©rie II de 2025-09-05",
    "link": "https://diariodarepublica.pt/dr/detalhe/contrato-publico/23671-934420411"
  },
  {
    "numero_procedimento": "N/A",
    "entidade": "AnÃºncio de procedimento  n.Âº 23676/2025  -  DiÃ¡rio da RepÃºblica n.Âº 171/2025, SÃ©rie II de 2025-09-05",
    "link": "https://diariodarepublica.pt/dr/detalhe/contrato-publico/23676-934420412"
  },
  {
    "numero_procedimento": "N/A",
    "entidade": "AnÃºncio de procedimento  n.Âº 23677/2025  -  DiÃ¡rio da RepÃºblica n.Âº 171/2025, SÃ©rie II de 2025-09-05",
    "link": "https://diariodarepublica.pt/dr/detalhe/contrato-publico/23677-934420413"
  },
  {
    "numero_procedimento": "N/A",
    "entidade": "AnÃºncio de procedimento  n.Âº 23682/2025  -  DiÃ¡rio da RepÃºblica n.Âº 171/2025, SÃ©rie II de 2025-09-05",
    "link": "https://diariodarepublica.pt/dr/detalhe/contrato-publico/23682-934420428"
  },
  {
    "numero_procedimento": "N/A",
    "entidade": "AnÃºncio de procedimento  n.Âº 23683/2025  -  DiÃ¡rio da RepÃºblica n.Âº 171/2025, SÃ©rie II de 2025-09-05",
    "link": "https://diariodarepublica.pt/dr/detalhe/contrato-publico/23683-934420429"
  },
  {
    "numero_procedimento": "N/A",
    "entidade": "AnÃºncio de procedimento  n.Âº 23685/2025  -  DiÃ¡rio da RepÃºblica n.Âº 171/2025, SÃ©rie II de 2025-09-05",
    "link": "https://diariodarepublica.pt/dr/detalhe/contrato-publico/23685-934420430"
  },
  {
    "numero_procedimento": "N/A",
    "entidade": "AnÃºncio de procedimento  n.Âº 23686/2025  -  DiÃ¡rio da RepÃºblica n.Âº 171/2025, SÃ©rie II de 2025-09-05",
    "link": "https://diariodarepublica.pt/dr/detalhe/contrato-publico/23686-934420431"
  },
  {
    "numero_procedimento": "N/A",
    "entidade": "AnÃºncio de procedimento  n.Âº 23689/2025  -  DiÃ¡rio da RepÃºblica n.Âº 171/2025, SÃ©rie II de 2025-09-05",
    "link": "https://diariodarepublica.pt/dr/detalhe/contrato-publico/23689-934420432"
  },
  {
    "numero_procedimento": "N/A",
    "entidade": "AnÃºncio de procedimento  n.Âº 23690/2025  -  DiÃ¡rio da RepÃºblica n.Âº 171/2025, SÃ©rie II de 2025-09-05",
    "link": "https://diariodarepublica.pt/dr/detalhe/contrato-publico/23690-934420433"
  },
  {
    "numero_procedimento": "N/A",
    "entidade": "AnÃºncio de procedimento  n.Âº 23691/2025  -  DiÃ¡rio da RepÃºblica n.Âº 171/2025, SÃ©rie II de 2025-09-05",
    "link": "https://diariodarepublica.pt/dr/detalhe/contrato-publico/23691-934420434"
  },
  {
    "numero_procedimento": "N/A",
    "entidade": "AnÃºncio de procedimento  n.Âº 23692/2025  -  DiÃ¡rio da RepÃºblica n.Âº 171/2025, SÃ©rie II de 2025-09-05",
    "link": "https://diariodarepublica.pt/dr/detalhe/contrato-publico/23692-934420435"
  },
  {
    "numero_procedimento": "N/A",
    "entidade": "AnÃºncio de procedimento  n.Âº 23694/2025  -  DiÃ¡rio da RepÃºblica n.Âº 171/2025, SÃ©rie II de 2025-09-05",
    "link": "https://diariodarepublica.pt/dr/detalhe/contrato-publico/23694-934420436"
  },
  {
    "numero_procedimento": "N/A",
    "entidade": "AnÃºncio de procedimento  n.Âº 23651/2025  -  DiÃ¡rio da RepÃºblica n.Âº 171/2025, SÃ©rie II de 2025-09-05",
    "link": "https://diariodarepublica.pt/dr/detalhe/contrato-publico/23651-934422109"
  },
  {
    "numero_procedimento": "N/A",
    "entidade": "AnÃºncio de procedimento  n.Âº 23652/2025  -  DiÃ¡rio da RepÃºblica n.Âº 171/2025, SÃ©rie II de 2025-09-05",
    "link": "https://diariodarepublica.pt/dr/detalhe/contrato-publico/23652-934422110"
  },
  {
    "numero_procedimento": "N/A",
    "entidade": "AnÃºncio de procedimento  n.Âº 23653/2025  -  DiÃ¡rio da RepÃºblica n.Âº 171/2025, SÃ©rie II de 2025-09-05",
    "link": "https://diariodarepublica.pt/dr/detalhe/contrato-publico/23653-934422111"
  },
  {
    "numero_procedimento": "N/A",
    "entidade": "AnÃºncio de procedimento  n.Âº 23658/2025  -  DiÃ¡rio da RepÃºblica n.Âº 171/2025, SÃ©rie II de 2025-09-05",
    "link": "https://diariodarepublica.pt/dr/detalhe/contrato-publico/23658-934422112"
  },
  {
    "numero_procedimento": "N/A",
    "entidade": "AnÃºncio de procedimento  n.Âº 23659/2025  -  DiÃ¡rio da RepÃºblica n.Âº 171/2025, SÃ©rie II de 2025-09-05",
    "link": "https://diariodarepublica.pt/dr/detalhe/contrato-publico/23659-934422113"
  },
  {
    "numero_procedimento": "N/A",
    "entidade": "Imprensa Nacional-Casa da Moeda, S.A.",
    "link": "https://diariodarepublica.pt/dr/detalhe/contrato-publico/23661-934422114",
    "detalhes_completos": "1 - IDENTIFICAÇÃO E CONTACTOS DA ENTIDADE ADJUDICANTE\nDesignação da entidade adjudicante: Imprensa Nacional-Casa da Moeda, S.A.\nNIPC: 500792887\nServiço/Órgão/Pessoa de contacto: INCM\nEndereço: Av. António José de Almeida\nCódigo postal: 1000-042\nLocalidade: Lisboa\nPaís: Portugal\nNUT III: PT170\nDistrito: Lisboa\nConcelho: Lisboa\nFreguesia: Freguesia de Avenidas Novas\nTelefone: 217810700\nFax: 217810700\nEndereço da Entidade (URL): www.incm.pt\nEndereço Eletrónico: compras@incm.pt\neDelivery Gateway (URL): https://www.acingov.pt\nFunção da Organização: Adquirente\nNorma jurídica da Entidade Adjudicante: Organismo de direito público\nÁrea de atividade da Autoridade Adjudicante: Serviços públicos das administrações públicas\n\n2 - JORNAL OFICIAL DA UNIÃO EUROPEIA\nO procedimento a que este anúncio diz respeito também é publicitado no Jornal Oficial da União Europeia? Não\n\n3 - AVISO\nModelo de Anúncio: Concurso público\nData de Envio do Anúncio: 05-09-2025\n\n5 - PROCESSO\nTipo de Procedimento: Concurso público\nPreço base do procedimento: Sim\nValor do preço base do procedimento: 150.000,00 EUR\nProcedimento com lotes? Sim\nNº Máx. de Lotes Autorizado: 2\nNúmero máximo de lotes que podem ser adjudicados a um concorrente: 2\n\n6 - OBJETO DO CONTRATO\nNúmero de referência interna: 167/2025\nDesignação do contrato: Aquisição de Serviços de Transporte e Mudanças\nDescrição: Aquisição de Serviços de Transporte e Mudanças\nTipo de Contrato Principal: Aquisição de Serviços\nTipo de Contrato: Aquisição de Serviços\nClassificação CPV (Vocabulário Comum para os Contratos Públicos)\nObjeto principal\nVocabulário Principal: 60000000\nPreço base s/IVA: 150.000,00 EUR\nLotes: \nNº: LOT-0001\nDescrição do Lote: Transporte e Mudanças_Centro\nPreço base s/IVA: 105.000,00 EUR\nClassificação CPV (Vocabulário Comum para os Contratos Públicos)\nObjeto principal\nVocabulário Principal: 60000000\nNº: LOT-0002\nDescrição do Lote: Transporte e Mudanças_Norte\nPreço base s/IVA: 45.000,00 EUR\nClassificação CPV (Vocabulário Comum para os Contratos Públicos)\nObjeto principal\nVocabulário Principal: 60000000\n\n7 - INDICAÇÕES ADICIONAIS\nO contrato envolve aquisição conjunta (satisfação de várias entidades)? Não\nO contrato é adjudicado por uma central de compras? Não\n\n8 - TÉCNICAS\nO concurso destina-se à celebração de um acordo-quadro? Inexistência de acordo-quadro\nÉ utilizado um leilão eletrónico? Não\nÉ adotada uma fase de negociação? Não\nSistema de Aquisição Dinâmico: Inexistência de sistema de aquisição dinâmico\n\n9 - LOCAL DA EXECUÇÃO DO CONTRATO\nLOCAL DA EXECUÇÃO DO CONTRATO (PROCEDIMENTO)\nPaís: Portugal\nNUT III: PT170\nLocalidade: Freguesia de Avenidas Novas\nDistrito: Lisboa\nConcelho: Lisboa\nFreguesia: Freguesia de Avenidas Novas\nLOCAL DA EXECUÇÃO DO CONTRATO (LOTE)\nIdentificador do Lote: LOT-0001; LOT-0002\nPaís: Portugal\nNUT III: PT170\nLocalidade: Freguesia de Avenidas Novas\nDistrito: Lisboa\nConcelho: Lisboa\nFreguesia: Freguesia de Avenidas Novas\n\n10 - PRAZO DE EXECUÇÃO DO CONTRATO\nIdentificador do Lote: LOT-0001; LOT-0002\nPrazo de execução do contrato: 36 MESES\nPrevisão de renovações: Sim\nIndicar número máximo de renovações: 2\nPrazo de renovações diferente do prazo inicial: Não\n\n11 - FUNDOS EU\nIdentificador do Lote: LOT-0001; LOT-0002\nTêm fundos EU? Não\n\n12 - DOCUMENTOS DE HABILITAÇÃO\nHabilitação para o exercício da atividade profissional: Não\n\n13 - CONDIÇÕES DE APRESENTAÇÃO\nPlataforma eletrónica utilizada pela entidade adjudicante: ACIN\nURL para Apresentação: https://www.acingov.pt\nAdmissibilidade da apresentação de propostas variantes: Não autorizado\nPrazo para apresentação das propostas: 15-09-2025 17:59\nPrazo durante o qual os concorrentes são obrigados a manter as respetivas propostas: 66 dias a contar do termo do prazo para a apresentação das propostas\nIndicação de Subcontratação na Proposta: Inexistência de indicação de subcontratação\n\n14 - PRESTAÇÃO DE CAUÇÃO\nPrestação de caução: Não\n\n15 - FORNECIMENTO DAS PEÇAS DO CONCURSO, APRESENTAÇÃO DE PEDIDOS DE PARTICIPAÇÃO E APRESENTAÇÃO DAS PROPOSTAS\nLink para acesso às peças do concurso (URL): https://www.acingov.pt/acingovprod/2/zonaPublica/zona_publica_c/donwloadProcedurePiece/OTc1Njcw\n\n20 - OUTROS REQUISITOS\nIdentificador do Lote: LOT-0001; LOT-0002\nInformação sobre contratos reservados. Aplica-se a contratos reservados (54º-A)? Não\n\n21 - CRITÉRIO DE ADJUDICAÇÃO\nO Critério de adjudicação é diferenciado por lote? Não\nMultifator: Não\nMonofator:\nNome: Preço\n\n24 - CONDIÇÕES DO CONTRATO\nIdentificador do Lote: LOT-0001; LOT-0002\nFaturação Eletrónica: Permitido\nObrigação de Subcontratação:\nCódigo da Obrigação de Subcontratação: Não é aplicável nenhuma obrigação de subcontratação.\n\n25 - COMPRA PÚBLICA ESTRATÉGICA\nCompra Pública Estratégica: Inexistência de contratação pública estratégica\n\n26 - INFORMAÇÕES ADICIONAIS\nIdentificador do Lote: LOT-0001; LOT-0002\nContrato adequado para PME: Não\nCobertura ACP (Acordo dos Contratos Públicos da Organização Mundial do Comércio): Não\n\n27 - IDENTIFICAÇÃO E CONTACTOS DO ÓRGÃO DE RECURSOS ADMINISTRATIVOS\nDesignação: INCM\nEndereço: Av. Antonio José Almeida\nCódigo postal: 1000-042\nLocalidade: Lisboa\nTelefone: 217810700\nFax: 217810700\nEndereço eletrónico: compras@incm.pt\n\n28 - IDENTIFICAÇÃO DO(S) AUTOR(ES) DE ANÚNCIO\nNome: Dora Moita\nCargo: Presidente\n419507793",
    "nipc": "500792887",
    "distrito": "Lisboa",
    "concelho": "Lisboa",
    "freguesia": "Freguesia de Avenidas Novas",
    "site": "www.incm.pt",
    "email": "compras@incm.pt",
    "designacao_contrato": "Aquisição de Serviços de Transporte e Mudanças",
    "descricao": "Aquisição de Serviços de Transporte e Mudanças",
    "preco_base": "150.000,00 EUR",
    "prazo_execucao": "36 MESES",
    "prazo_apresentacao_propostas": "15-09-2025 17:59",
    "fundos_eu": "Não",
    "plataforma_eletronica": "ACIN",
    "url_procedimento": "https://www.acingov.pt",
    "autor_nome": "Dora Moita",
    "autor_cargo": "Presidente"
  },
  {
    "numero_procedimento": "N/A",
    "entidade": "AnÃºncio de procedimento  n.Âº 23662/2025  -  DiÃ¡rio da RepÃºblica n.Âº 171/2025, SÃ©rie II de 2025-09-05",
    "link": "https://diariodarepublica.pt/dr/detalhe/contrato-publico/23662-934422115"
  },
  {
    "numero_procedimento": "N/A",
    "entidade": "AnÃºncio de procedimento  n.Âº 23666/2025  -  DiÃ¡rio da RepÃºblica n.Âº 171/2025, SÃ©rie II de 2025-09-05",
    "link": "https://diariodarepublica.pt/dr/detalhe/contrato-publico/23666-934422116"
  },
  {
    "numero_procedimento": "N/A",
    "entidade": "AnÃºncio de procedimento  n.Âº 23672/2025  -  DiÃ¡rio da RepÃºblica n.Âº 171/2025, SÃ©rie II de 2025-09-05",
    "link": "https://diariodarepublica.pt/dr/detalhe/contrato-publico/23672-934422120"
  },
  {
    "numero_procedimento": "N/A",
    "entidade": "AnÃºncio de procedimento  n.Âº 23673/2025  -  DiÃ¡rio da RepÃºblica n.Âº 171/2025, SÃ©rie II de 2025-09-05",
    "link": "https://diariodarepublica.pt/dr/detalhe/contrato-publico/23673-934422121"
  },
  {
    "numero_procedimento": "N/A",
    "entidade": "AnÃºncio de procedimento  n.Âº 23674/2025  -  DiÃ¡rio da RepÃºblica n.Âº 171/2025, SÃ©rie II de 2025-09-05",
    "link": "https://diariodarepublica.pt/dr/detalhe/contrato-publico/23674-934422122"
  },
  {
    "numero_procedimento": "N/A",
    "entidade": "AnÃºncio de procedimento  n.Âº 23675/2025  -  DiÃ¡rio da RepÃºblica n.Âº 171/2025, SÃ©rie II de 2025-09-05",
    "link": "https://diariodarepublica.pt/dr/detalhe/contrato-publico/23675-934422123"
  },
  {
    "numero_procedimento": "N/A",
    "entidade": "AnÃºncio de procedimento  n.Âº 23678/2025  -  DiÃ¡rio da RepÃºblica n.Âº 171/2025, SÃ©rie II de 2025-09-05",
    "link": "https://diariodarepublica.pt/dr/detalhe/contrato-publico/23678-934422124"
  },
  {
    "numero_procedimento": "N/A",
    "entidade": "AnÃºncio de procedimento  n.Âº 23679/2025  -  DiÃ¡rio da RepÃºblica n.Âº 171/2025, SÃ©rie II de 2025-09-05",
    "link": "https://diariodarepublica.pt/dr/detalhe/contrato-publico/23679-934422125"
  },
  {
    "numero_procedimento": "N/A",
    "entidade": "AnÃºncio de procedimento  n.Âº 23680/2025  -  DiÃ¡rio da RepÃºblica n.Âº 171/2025, SÃ©rie II de 2025-09-05",
    "link": "https://diariodarepublica.pt/dr/detalhe/contrato-publico/23680-934422126"
  },
  {
    "numero_procedimento": "N/A",
    "entidade": "AnÃºncio de procedimento  n.Âº 23681/2025  -  DiÃ¡rio da RepÃºblica n.Âº 171/2025, SÃ©rie II de 2025-09-05",
    "link": "https://diariodarepublica.pt/dr/detalhe/contrato-publico/23681-934422127"
  },
  {
    "numero_procedimento": "N/A",
    "entidade": "AnÃºncio de procedimento  n.Âº 23684/2025  -  DiÃ¡rio da RepÃºblica n.Âº 171/2025, SÃ©rie II de 2025-09-05",
    "link": "https://diariodarepublica.pt/dr/detalhe/contrato-publico/23684-934422128"
  },
  {
    "numero_procedimento": "N/A",
    "entidade": "AnÃºncio de procedimento  n.Âº 23687/2025  -  DiÃ¡rio da RepÃºblica n.Âº 171/2025, SÃ©rie II de 2025-09-05",
    "link": "https://diariodarepublica.pt/dr/detalhe/contrato-publico/23687-934422129"
  },
  {
    "numero_procedimento": "N/A",
    "entidade": "AnÃºncio de procedimento  n.Âº 23688/2025  -  DiÃ¡rio da RepÃºblica n.Âº 171/2025, SÃ©rie II de 2025-09-05",
    "link": "https://diariodarepublica.pt/dr/detalhe/contrato-publico/23688-934422130"
  },
  {
    "numero_procedimento": "N/A",
    "entidade": "AnÃºncio de procedimento  n.Âº 23693/2025  -  DiÃ¡rio da RepÃºblica n.Âº 171/2025, SÃ©rie II de 2025-09-05",
    "link": "https://diariodarepublica.pt/dr/detalhe/contrato-publico/23693-934422142"
  }
]