[
  {
    "numero_procedimento": "N/A",
    "entidade": "AnÃºncio de procedimento  n.Âº 26092/2025  -  DiÃ¡rio da RepÃºblica n.Âº 192/2025, SÃ©rie II de 2025-10-06",
    "link": "https://diariodarepublica.pt/dr/detalhe/contrato-publico/26092-937877846"
  },
  {
    "numero_procedimento": "N/A",
    "entidade": "AnÃºncio de procedimento  n.Âº 26093/2025  -  DiÃ¡rio da RepÃºblica n.Âº 192/2025, SÃ©rie II de 2025-10-06",
    "link": "https://diariodarepublica.pt/dr/detalhe/contrato-publico/26093-937877847"
  },
  {
    "numero_procedimento": "N/A",
    "entidade": "AnÃºncio de procedimento  n.Âº 26094/2025  -  DiÃ¡rio da RepÃºblica n.Âº 192/2025, SÃ©rie II de 2025-10-06",
    "link": "https://diariodarepublica.pt/dr/detalhe/contrato-publico/26094-937877848"
  },
  {
    "numero_procedimento": "N/A",
    "entidade": "AnÃºncio de procedimento  n.Âº 26096/2025  -  DiÃ¡rio da RepÃºblica n.Âº 192/2025, SÃ©rie II de 2025-10-06",
    "link": "https://diariodarepublica.pt/dr/detalhe/contrato-publico/26096-937877849"
  },
  {
    "numero_procedimento": "N/A",
    "entidade": "AnÃºncio de procedimento  n.Âº 26099/2025  -  DiÃ¡rio da RepÃºblica n.Âº 192/2025, SÃ©rie II de 2025-10-06",
    "link": "https://diariodarepublica.pt/dr/detalhe/contrato-publico/26099-937877850"
  },
  {
    "numero_procedimento": "N/A",
    "entidade": "AnÃºncio de procedimento  n.Âº 26101/2025  -  DiÃ¡rio da RepÃºblica n.Âº 192/2025, SÃ©rie II de 2025-10-06",
    "link": "https://diariodarepublica.pt/dr/detalhe/contrato-publico/26101-937877851"
  },
  {
    "numero_procedimento": "N/A",
    "entidade": "AnÃºncio de procedimento  n.Âº 26103/2025  -  DiÃ¡rio da RepÃºblica n.Âº 192/2025, SÃ©rie II de 2025-10-06",
    "link": "https://diariodarepublica.pt/dr/detalhe/contrato-publico/26103-937877866"
  },
  {
    "numero_procedimento": "N/A",
    "entidade": "AnÃºncio de procedimento  n.Âº 26107/2025  -  DiÃ¡rio da RepÃºblica n.Âº 192/2025, SÃ©rie II de 2025-10-06",
    "link": "https://diariodarepublica.pt/dr/detalhe/contrato-publico/26107-937877867"
  },
  {
    "numero_procedimento": "N/A",
    "entidade": "AnÃºncio de procedimento  n.Âº 26110/2025  -  DiÃ¡rio da RepÃºblica n.Âº 192/2025, SÃ©rie II de 2025-10-06",
    "link": "https://diariodarepublica.pt/dr/detalhe/contrato-publico/26110-937877868"
  },
  {
    "numero_procedimento": "N/A",
    "entidade": "AnÃºncio de procedimento  n.Âº 26112/2025  -  DiÃ¡rio da RepÃºblica n.Âº 192/2025, SÃ©rie II de 2025-10-06",
    "link": "https://diariodarepublica.pt/dr/detalhe/contrato-publico/26112-937877869"
  },
  {
    "numero_procedimento": "N/A",
    "entidade": "AnÃºncio de procedimento  n.Âº 26113/2025  -  DiÃ¡rio da RepÃºblica n.Âº 192/2025, SÃ©rie II de 2025-10-06",
    "link": "https://diariodarepublica.pt/dr/detalhe/contrato-publico/26113-937877870"
  },
  {
    "numero_procedimento": "N/A",
    "entidade": "AnÃºncio de procedimento  n.Âº 26115/2025  -  DiÃ¡rio da RepÃºblica n.Âº 192/2025, SÃ©rie II de 2025-10-06",
    "link": "https://diariodarepublica.pt/dr/detalhe/contrato-publico/26115-937877871"
  },
  {
    "numero_procedimento": "N/A",
    "entidade": "AnÃºncio de procedimento  n.Âº 26116/2025  -  DiÃ¡rio da RepÃºblica n.Âº 192/2025, SÃ©rie II de 2025-10-06",
    "link": "https://diariodarepublica.pt/dr/detalhe/contrato-publico/26116-937877872"
  },
  {
    "numero_procedimento": "N/A",
    "entidade": "AnÃºncio de procedimento  n.Âº 26117/2025  -  DiÃ¡rio da RepÃºblica n.Âº 192/2025, SÃ©rie II de 2025-10-06",
    "link": "https://diariodarepublica.pt/dr/detalhe/contrato-publico/26117-937877873"
  },
  {
    "numero_procedimento": "N/A",
    "entidade": "AnÃºncio de procedimento  n.Âº 26120/2025  -  DiÃ¡rio da RepÃºblica n.Âº 192/2025, SÃ©rie II de 2025-10-06",
    "link": "https://diariodarepublica.pt/dr/detalhe/contrato-publico/26120-937877874"
  },
  {
    "numero_procedimento": "N/A",
    "entidade": "AnÃºncio de procedimento  n.Âº 26085/2025  -  DiÃ¡rio da RepÃºblica n.Âº 192/2025, SÃ©rie II de 2025-10-06",
    "link": "https://diariodarepublica.pt/dr/detalhe/contrato-publico/26085-938108797"
  },
  {
    "numero_procedimento": "N/A",
    "entidade": "AnÃºncio de procedimento  n.Âº 26086/2025  -  DiÃ¡rio da RepÃºblica n.Âº 192/2025, SÃ©rie II de 2025-10-06",
    "link": "https://diariodarepublica.pt/dr/detalhe/contrato-publico/26086-938108798"
  },
  {
    "numero_procedimento": "N/A",
    "entidade": "AnÃºncio de procedimento  n.Âº 26087/2025  -  DiÃ¡rio da RepÃºblica n.Âº 192/2025, SÃ©rie II de 2025-10-06",
    "link": "https://diariodarepublica.pt/dr/detalhe/contrato-publico/26087-938108799"
  },
  {
    "numero_procedimento": "N/A",
    "entidade": "AnÃºncio de procedimento  n.Âº 26088/2025  -  DiÃ¡rio da RepÃºblica n.Âº 192/2025, SÃ©rie II de 2025-10-06",
    "link": "https://diariodarepublica.pt/dr/detalhe/contrato-publico/26088-938108800"
  },
  {
    "numero_procedimento": "N/A",
    "entidade": "AnÃºncio de procedimento  n.Âº 26089/2025  -  DiÃ¡rio da RepÃºblica n.Âº 192/2025, SÃ©rie II de 2025-10-06",
    "link": "https://diariodarepublica.pt/dr/detalhe/contrato-publico/26089-938108801"
  },
  {
    "numero_procedimento": "N/A",
    "entidade": "AnÃºncio de procedimento  n.Âº 26090/2025  -  DiÃ¡rio da RepÃºblica n.Âº 192/2025, SÃ©rie II de 2025-10-06",
    "link": "https://diariodarepublica.pt/dr/detalhe/contrato-publico/26090-938108802"
  },
  {
    "numero_procedimento": "N/A",
    "entidade": "AnÃºncio de procedimento  n.Âº 26091/2025  -  DiÃ¡rio da RepÃºblica n.Âº 192/2025, SÃ©rie II de 2025-10-06",
    "link": "https://diariodarepublica.pt/dr/detalhe/contrato-publico/26091-938108803"
  },
  {
    "numero_procedimento": "N/A",
    "entidade": "AnÃºncio de procedimento  n.Âº 26095/2025  -  DiÃ¡rio da RepÃºblica n.Âº 192/2025, SÃ©rie II de 2025-10-06",
    "link": "https://diariodarepublica.pt/dr/detalhe/contrato-publico/26095-938108805"
  },
  {
    "numero_procedimento": "N/A",
    "entidade": "AnÃºncio de procedimento  n.Âº 26097/2025  -  DiÃ¡rio da RepÃºblica n.Âº 192/2025, SÃ©rie II de 2025-10-06",
    "link": "https://diariodarepublica.pt/dr/detalhe/contrato-publico/26097-938108806"
  },
  {
    "numero_procedimento": "N/A",
    "entidade": "AnÃºncio de procedimento  n.Âº 26098/2025  -  DiÃ¡rio da RepÃºblica n.Âº 192/2025, SÃ©rie II de 2025-10-06",
    "link": "https://diariodarepublica.pt/dr/detalhe/contrato-publico/26098-938108807"
  },
  {
    "numero_procedimento": "N/A",
    "entidade": "AnÃºncio de procedimento  n.Âº 26100/2025  -  DiÃ¡rio da RepÃºblica n.Âº 192/2025, SÃ©rie II de 2025-10-06",
    "link": "https://diariodarepublica.pt/dr/detalhe/contrato-publico/26100-938108808"
  },
  {
    "numero_procedimento": "N/A",
    "entidade": "AnÃºncio de procedimento  n.Âº 26102/2025  -  DiÃ¡rio da RepÃºblica n.Âº 192/2025, SÃ©rie II de 2025-10-06",
    "link": "https://diariodarepublica.pt/dr/detalhe/contrato-publico/26102-938108812"
  },
  {
    "numero_procedimento": "N/A",
    "entidade": "AnÃºncio de procedimento  n.Âº 26104/2025  -  DiÃ¡rio da RepÃºblica n.Âº 192/2025, SÃ©rie II de 2025-10-06",
    "link": "https://diariodarepublica.pt/dr/detalhe/contrato-publico/26104-938108816"
  },
  {
    "numero_procedimento": "N/A",
    "entidade": "AnÃºncio de procedimento  n.Âº 26105/2025  -  DiÃ¡rio da RepÃºblica n.Âº 192/2025, SÃ©rie II de 2025-10-06",
    "link": "https://diariodarepublica.pt/dr/detalhe/contrato-publico/26105-938108817"
  },
  {
    "numero_procedimento": "N/A",
    "entidade": "AnÃºncio de procedimento  n.Âº 26106/2025  -  DiÃ¡rio da RepÃºblica n.Âº 192/2025, SÃ©rie II de 2025-10-06",
    "link": "https://diariodarepublica.pt/dr/detalhe/contrato-publico/26106-938137358"
  },
  {
    "numero_procedimento": "N/A",
    "entidade": "AnÃºncio de procedimento  n.Âº 26108/2025  -  DiÃ¡rio da RepÃºblica n.Âº 192/2025, SÃ©rie II de 2025-10-06",
    "link": "https://diariodarepublica.pt/dr/detalhe/contrato-publico/26108-938137359"
  },
  {
    "numero_procedimento": "N/A",
    "entidade": "AnÃºncio de procedimento  n.Âº 26109/2025  -  DiÃ¡rio da RepÃºblica n.Âº 192/2025, SÃ©rie II de 2025-10-06",
    "link": "https://diariodarepublica.pt/dr/detalhe/contrato-publico/26109-938137360"
  },
  {
    "numero_procedimento": "N/A",
    "entidade": "AnÃºncio de procedimento  n.Âº 26111/2025  -  DiÃ¡rio da RepÃºblica n.Âº 192/2025, SÃ©rie II de 2025-10-06",
    "link": "https://diariodarepublica.pt/dr/detalhe/contrato-publico/26111-938137361"
  },
  {
    "numero_procedimento": "N/A",
    "entidade": "AnÃºncio de procedimento  n.Âº 26114/2025  -  DiÃ¡rio da RepÃºblica n.Âº 192/2025, SÃ©rie II de 2025-10-06",
    "link": "https://diariodarepublica.pt/dr/detalhe/contrato-publico/26114-938137362"
  },
  {
    "numero_procedimento": "N/A",
    "entidade": "AnÃºncio de procedimento  n.Âº 26118/2025  -  DiÃ¡rio da RepÃºblica n.Âº 192/2025, SÃ©rie II de 2025-10-06",
    "link": "https://diariodarepublica.pt/dr/detalhe/contrato-publico/26118-938137363"
  },
  {
    "numero_procedimento": "N/A",
    "entidade": "AnÃºncio de procedimento  n.Âº 26119/2025  -  DiÃ¡rio da RepÃºblica n.Âº 192/2025, SÃ©rie II de 2025-10-06",
    "link": "https://diariodarepublica.pt/dr/detalhe/contrato-publico/26119-938137364"
  },
  {
    "numero_procedimento": "N/A",
    "entidade": "AnÃºncio de procedimento  n.Âº 26121/2025  -  DiÃ¡rio da RepÃºblica n.Âº 192/2025, SÃ©rie II de 2025-10-06",
    "link": "https://diariodarepublica.pt/dr/detalhe/contrato-publico/26121-938137365"
  },
  {
    "numero_procedimento": "N/A",
    "entidade": "AnÃºncio de procedimento  n.Âº 26122/2025  -  DiÃ¡rio da RepÃºblica n.Âº 192/2025, SÃ©rie II de 2025-10-06",
    "link": "https://diariodarepublica.pt/dr/detalhe/contrato-publico/26122-938137366"
  },
  {
    "numero_procedimento": "N/A",
    "entidade": "AnÃºncio de procedimento  n.Âº 26123/2025  -  DiÃ¡rio da RepÃºblica n.Âº 192/2025, SÃ©rie II de 2025-10-06",
    "link": "https://diariodarepublica.pt/dr/detalhe/contrato-publico/26123-938137367"
  },
  {
    "numero_procedimento": "N/A",
    "entidade": "AnÃºncio de procedimento  n.Âº 26126/2025  -  DiÃ¡rio da RepÃºblica n.Âº 192/2025, SÃ©rie II de 2025-10-06",
    "link": "https://diariodarepublica.pt/dr/detalhe/contrato-publico/26126-938137368"
  },
  {
    "numero_procedimento": "N/A",
    "entidade": "AnÃºncio de procedimento  n.Âº 26127/2025  -  DiÃ¡rio da RepÃºblica n.Âº 192/2025, SÃ©rie II de 2025-10-06",
    "link": "https://diariodarepublica.pt/dr/detalhe/contrato-publico/26127-938137369"
  },
  {
    "numero_procedimento": "N/A",
    "entidade": "AnÃºncio de procedimento  n.Âº 26129/2025  -  DiÃ¡rio da RepÃºblica n.Âº 192/2025, SÃ©rie II de 2025-10-06",
    "link": "https://diariodarepublica.pt/dr/detalhe/contrato-publico/26129-938137370"
  },
  {
    "numero_procedimento": "N/A",
    "entidade": "AnÃºncio de procedimento  n.Âº 26135/2025  -  DiÃ¡rio da RepÃºblica n.Âº 192/2025, SÃ©rie II de 2025-10-06",
    "link": "https://diariodarepublica.pt/dr/detalhe/contrato-publico/26135-938137371"
  },
  {
    "numero_procedimento": "N/A",
    "entidade": "AnÃºncio de procedimento  n.Âº 26136/2025  -  DiÃ¡rio da RepÃºblica n.Âº 192/2025, SÃ©rie II de 2025-10-06",
    "link": "https://diariodarepublica.pt/dr/detalhe/contrato-publico/26136-938137372"
  },
  {
    "numero_procedimento": "N/A",
    "entidade": "AnÃºncio de procedimento  n.Âº 26138/2025  -  DiÃ¡rio da RepÃºblica n.Âº 192/2025, SÃ©rie II de 2025-10-06",
    "link": "https://diariodarepublica.pt/dr/detalhe/contrato-publico/26138-938137373"
  },
  {
    "numero_procedimento": "N/A",
    "entidade": "AnÃºncio de procedimento  n.Âº 26141/2025  -  DiÃ¡rio da RepÃºblica n.Âº 192/2025, SÃ©rie II de 2025-10-06",
    "link": "https://diariodarepublica.pt/dr/detalhe/contrato-publico/26141-938137374"
  },
  {
    "numero_procedimento": "N/A",
    "entidade": "AnÃºncio de procedimento  n.Âº 26124/2025  -  DiÃ¡rio da RepÃºblica n.Âº 192/2025, SÃ©rie II de 2025-10-06",
    "link": "https://diariodarepublica.pt/dr/detalhe/contrato-publico/26124-938138775"
  },
  {
    "numero_procedimento": "N/A",
    "entidade": "AnÃºncio de procedimento  n.Âº 26125/2025  -  DiÃ¡rio da RepÃºblica n.Âº 192/2025, SÃ©rie II de 2025-10-06",
    "link": "https://diariodarepublica.pt/dr/detalhe/contrato-publico/26125-938138776"
  },
  {
    "numero_procedimento": "N/A",
    "entidade": "AnÃºncio de procedimento  n.Âº 26128/2025  -  DiÃ¡rio da RepÃºblica n.Âº 192/2025, SÃ©rie II de 2025-10-06",
    "link": "https://diariodarepublica.pt/dr/detalhe/contrato-publico/26128-938138777"
  },
  {
    "numero_procedimento": "N/A",
    "entidade": "AnÃºncio de procedimento  n.Âº 26130/2025  -  DiÃ¡rio da RepÃºblica n.Âº 192/2025, SÃ©rie II de 2025-10-06",
    "link": "https://diariodarepublica.pt/dr/detalhe/contrato-publico/26130-938138778"
  },
  {
    "numero_procedimento": "N/A",
    "entidade": "AnÃºncio de procedimento  n.Âº 26131/2025  -  DiÃ¡rio da RepÃºblica n.Âº 192/2025, SÃ©rie II de 2025-10-06",
    "link": "https://diariodarepublica.pt/dr/detalhe/contrato-publico/26131-938138779"
  },
  {
    "numero_procedimento": "N/A",
    "entidade": "AnÃºncio de procedimento  n.Âº 26132/2025  -  DiÃ¡rio da RepÃºblica n.Âº 192/2025, SÃ©rie II de 2025-10-06",
    "link": "https://diariodarepublica.pt/dr/detalhe/contrato-publico/26132-938138780"
  },
  {
    "numero_procedimento": "N/A",
    "entidade": "AnÃºncio de procedimento  n.Âº 26133/2025  -  DiÃ¡rio da RepÃºblica n.Âº 192/2025, SÃ©rie II de 2025-10-06",
    "link": "https://diariodarepublica.pt/dr/detalhe/contrato-publico/26133-938138781"
  },
  {
    "numero_procedimento": "N/A",
    "entidade": "AnÃºncio de procedimento  n.Âº 26134/2025  -  DiÃ¡rio da RepÃºblica n.Âº 192/2025, SÃ©rie II de 2025-10-06",
    "link": "https://diariodarepublica.pt/dr/detalhe/contrato-publico/26134-938138782"
  },
  {
    "numero_procedimento": "N/A",
    "entidade": "AnÃºncio de procedimento  n.Âº 26137/2025  -  DiÃ¡rio da RepÃºblica n.Âº 192/2025, SÃ©rie II de 2025-10-06",
    "link": "https://diariodarepublica.pt/dr/detalhe/contrato-publico/26137-938138783"
  },
  {
    "numero_procedimento": "N/A",
    "entidade": "AnÃºncio de procedimento  n.Âº 26139/2025  -  DiÃ¡rio da RepÃºblica n.Âº 192/2025, SÃ©rie II de 2025-10-06",
    "link": "https://diariodarepublica.pt/dr/detalhe/contrato-publico/26139-938138784"
  },
  {
    "numero_procedimento": "N/A",
    "entidade": "AnÃºncio de procedimento  n.Âº 26140/2025  -  DiÃ¡rio da RepÃºblica n.Âº 192/2025, SÃ©rie II de 2025-10-06",
    "link": "https://diariodarepublica.pt/dr/detalhe/contrato-publico/26140-938138785"
  },
  {
    "numero_procedimento": "N/A",
    "entidade": "AnÃºncio de procedimento  n.Âº 26143/2025  -  DiÃ¡rio da RepÃºblica n.Âº 192/2025, SÃ©rie II de 2025-10-06",
    "link": "https://diariodarepublica.pt/dr/detalhe/contrato-publico/26143-938138786"
  },
  {
    "numero_procedimento": "N/A",
    "entidade": "AnÃºncio de procedimento  n.Âº 26144/2025  -  DiÃ¡rio da RepÃºblica n.Âº 192/2025, SÃ©rie II de 2025-10-06",
    "link": "https://diariodarepublica.pt/dr/detalhe/contrato-publico/26144-938138787"
  },
  {
    "numero_procedimento": "N/A",
    "entidade": "AnÃºncio de procedimento  n.Âº 26146/2025  -  DiÃ¡rio da RepÃºblica n.Âº 192/2025, SÃ©rie II de 2025-10-06",
    "link": "https://diariodarepublica.pt/dr/detalhe/contrato-publico/26146-938138788"
  },
  {
    "numero_procedimento": "N/A",
    "entidade": "AnÃºncio de procedimento  n.Âº 26148/2025  -  DiÃ¡rio da RepÃºblica n.Âº 192/2025, SÃ©rie II de 2025-10-06",
    "link": "https://diariodarepublica.pt/dr/detalhe/contrato-publico/26148-938138789"
  },
  {
    "numero_procedimento": "N/A",
    "entidade": "AnÃºncio de procedimento  n.Âº 26149/2025  -  DiÃ¡rio da RepÃºblica n.Âº 192/2025, SÃ©rie II de 2025-10-06",
    "link": "https://diariodarepublica.pt/dr/detalhe/contrato-publico/26149-938138790"
  },
  {
    "numero_procedimento": "N/A",
    "entidade": "AnÃºncio de procedimento  n.Âº 26151/2025  -  DiÃ¡rio da RepÃºblica n.Âº 192/2025, SÃ©rie II de 2025-10-06",
    "link": "https://diariodarepublica.pt/dr/detalhe/contrato-publico/26151-938138791"
  },
  {
    "numero_procedimento": "N/A",
    "entidade": "AnÃºncio de procedimento  n.Âº 26152/2025  -  DiÃ¡rio da RepÃºblica n.Âº 192/2025, SÃ©rie II de 2025-10-06",
    "link": "https://diariodarepublica.pt/dr/detalhe/contrato-publico/26152-938138792"
  },
  {
    "numero_procedimento": "N/A",
    "entidade": "AnÃºncio de procedimento  n.Âº 26154/2025  -  DiÃ¡rio da RepÃºblica n.Âº 192/2025, SÃ©rie II de 2025-10-06",
    "link": "https://diariodarepublica.pt/dr/detalhe/contrato-publico/26154-938138793"
  },
  {
    "numero_procedimento": "N/A",
    "entidade": "AnÃºncio de procedimento  n.Âº 26155/2025  -  DiÃ¡rio da RepÃºblica n.Âº 192/2025, SÃ©rie II de 2025-10-06",
    "link": "https://diariodarepublica.pt/dr/detalhe/contrato-publico/26155-938138794"
  },
  {
    "numero_procedimento": "N/A",
    "entidade": "AnÃºncio de procedimento  n.Âº 26157/2025  -  DiÃ¡rio da RepÃºblica n.Âº 192/2025, SÃ©rie II de 2025-10-06",
    "link": "https://diariodarepublica.pt/dr/detalhe/contrato-publico/26157-938138795"
  },
  {
    "numero_procedimento": "N/A",
    "entidade": "AnÃºncio de procedimento  n.Âº 26160/2025  -  DiÃ¡rio da RepÃºblica n.Âº 192/2025, SÃ©rie II de 2025-10-06",
    "link": "https://diariodarepublica.pt/dr/detalhe/contrato-publico/26160-938138797"
  },
  {
    "numero_procedimento": "N/A",
    "entidade": "AnÃºncio de procedimento  n.Âº 26161/2025  -  DiÃ¡rio da RepÃºblica n.Âº 192/2025, SÃ©rie II de 2025-10-06",
    "link": "https://diariodarepublica.pt/dr/detalhe/contrato-publico/26161-938138798"
  },
  {
    "numero_procedimento": "N/A",
    "entidade": "AnÃºncio de procedimento  n.Âº 26162/2025  -  DiÃ¡rio da RepÃºblica n.Âº 192/2025, SÃ©rie II de 2025-10-06",
    "link": "https://diariodarepublica.pt/dr/detalhe/contrato-publico/26162-938138799"
  },
  {
    "numero_procedimento": "N/A",
    "entidade": "AnÃºncio de procedimento  n.Âº 26165/2025  -  DiÃ¡rio da RepÃºblica n.Âº 192/2025, SÃ©rie II de 2025-10-06",
    "link": "https://diariodarepublica.pt/dr/detalhe/contrato-publico/26165-938138800"
  },
  {
    "numero_procedimento": "N/A",
    "entidade": "Ordem dos Advogados",
    "link": "https://diariodarepublica.pt/dr/detalhe/contrato-publico/26166-938138801",
    "detalhes_completos": "Alteração do Anúncio de procedimento n.º 23720/2025, de 2025-09-08, com o ID 419504171\n\n1 - IDENTIFICAÇÃO E CONTACTOS DA ENTIDADE ADJUDICANTE\nDesignação da entidade adjudicante: Ordem dos Advogados\nNIPC: 500965099\nEndereço: Lg.  S.Domingos Nr. 14 1º\nCódigo postal: 1050-000\nLocalidade: Lisboa\nPaís: Portugal\nNUT III: PT170\nDistrito: Lisboa\nConcelho: Lisboa\nFreguesia: Todas\nTelefone: 218823550\nFax: 218862403\nEndereço da Entidade (URL): https://portal.oa.pt/\nEndereço Eletrónico: cons.geral@cg.oa.pt\neDelivery Gateway (URL): https://community.vortal.biz/public/\nFunção da Organização: Adquirente\nNorma jurídica da Entidade Adjudicante: Autoridade da administração central\nÁrea de atividade da Autoridade Adjudicante: Serviços públicos das administrações públicas\n\n2 - JORNAL OFICIAL DA UNIÃO EUROPEIA\nO procedimento a que este anúncio diz respeito também é publicitado no Jornal Oficial da União Europeia? Sim\n\n3 - AVISO\nModelo de Anúncio: Concurso público\nData de Envio do Anúncio: 03-10-2025\n\n5 - PROCESSO\nTipo de Procedimento: Concurso público\nPreço base do procedimento: Sim\nValor do preço base do procedimento: 2.890.000,00 EUR\nProcedimento com lotes? Não\n\n6 - OBJETO DO CONTRATO\nNúmero de referência interna: CNI599/OA/2025_Seguro RC Profissional dos Avogados\nDesignação do contrato:  CNI599/OA/2025_Seguro de Grupo de Responsabilidade Civil Profissional para os Advogados com inscrição em vigor na Ordem dos Advogados\nDescrição:  CNI599/OA/2025_Seguro de Grupo de Responsabilidade Civil Profissional para os Advogados com inscrição em vigor na Ordem dos Advogados\nOpções: Não\nTipo de Contrato Principal: Aquisição de Serviços\nTipo de Contrato: Aquisição de Serviços\nClassificação CPV (Vocabulário Comum para os Contratos Públicos)\nObjeto principal\nVocabulário Principal: 66510000\nPreço base s/IVA: 2.890.000,00 EUR\n\n7 - INDICAÇÕES ADICIONAIS\nO contrato envolve aquisição conjunta (satisfação de várias entidades)? Não\nO contrato é adjudicado por uma central de compras? Não\n\n8 - TÉCNICAS\nO concurso destina-se à celebração de um acordo-quadro? Inexistência de acordo-quadro\nÉ utilizado um leilão eletrónico? Não\nÉ adotada uma fase de negociação? Não\nSistema de Aquisição Dinâmico: Inexistência de sistema de aquisição dinâmico\n\n9 - LOCAL DA EXECUÇÃO DO CONTRATO\nLOCAL DA EXECUÇÃO DO CONTRATO (PROCEDIMENTO)\nPaís: Portugal\nNUT III: PT170\nLocalidade: Lisboa\nDistrito: Lisboa\nConcelho: Lisboa\nFreguesia: Todas\n\n10 - PRAZO DE EXECUÇÃO DO CONTRATO\nPrazo de execução do contrato: 24 MESES\nPrevisão de renovações: Não\n\n11 - FUNDOS EU\nTêm fundos EU? Não\n\n12 - DOCUMENTOS DE HABILITAÇÃO\nHabilitação para o exercício da atividade profissional: Não\n\n13 - CONDIÇÕES DE APRESENTAÇÃO\nPlataforma eletrónica utilizada pela entidade adjudicante: VORTAL\nURL para Apresentação: https://community.vortal.biz/public/\nAdmissibilidade da apresentação de propostas variantes: Não autorizado\nPrazo para apresentação das propostas: 06-10-2025 23:59\nPrazo durante o qual os concorrentes são obrigados a manter as respetivas propostas: 66 dias a contar do termo do prazo para a apresentação das propostas\nApresentação de Catálogo Eletrónico: Não autorizado\nIndicação de Subcontratação na Proposta: Inexistência de indicação de subcontratação\n\n14 - PRESTAÇÃO DE CAUÇÃO\nPrestação de caução: Não\n\n15 - FORNECIMENTO DAS PEÇAS DO CONCURSO, APRESENTAÇÃO DE PEDIDOS DE PARTICIPAÇÃO E APRESENTAÇÃO DAS PROPOSTAS\nLink para acesso às peças do concurso (URL): https://community.vortal.biz/Public/public-tender-documents/d2F5bVhuU2doc1lBc3I4RTdjTVdEVHhwZXJhWUtVaXRNN09mZGFaak1KWHRadVRERi81VFovOEhnZzBFR3ZYbGFqZ0xWNk9vNE1qc0JLQTFMWnAvQ0E9PURlU1o4\n\n20 - OUTROS REQUISITOS\nInformação sobre contratos reservados. Aplica-se a contratos reservados (54º-A)? Não\n\n21 - CRITÉRIO DE ADJUDICAÇÃO\nMultifator: Não\nMonofator:\nNome: Preço\n\n24 - CONDIÇÕES DO CONTRATO\nFaturação Eletrónica: Permitido\nObrigação de Subcontratação:\nCódigo da Obrigação de Subcontratação: Não é aplicável nenhuma obrigação de subcontratação.\n\n25 - COMPRA PÚBLICA ESTRATÉGICA\nCompra Pública Estratégica: Inexistência de contratação pública estratégica\n\n26 - INFORMAÇÕES ADICIONAIS\nContrato adequado para PME: Sim\nCobertura ACP (Acordo dos Contratos Públicos da Organização Mundial do Comércio): Não\n\n27 - IDENTIFICAÇÃO E CONTACTOS DO ÓRGÃO DE RECURSOS ADMINISTRATIVOS\nDesignação: Bastonário da Ordem dos Advogados\nEndereço: Largo de S. Domingos\nCódigo postal: 1169-060\nLocalidade: Lisboa\nTelefone: +351 218823550\nFax: +351 218862403\nEndereço eletrónico: gab.bastonario@cg.oa.pt\n\n28 - IDENTIFICAÇÃO DO(S) AUTOR(ES) DE ANÚNCIO\nNome: Ana Rola\nCargo: Serviço de Compras Conselho Geral da Ordem dos Advogados\n\n29 - ALTERAÇÃO\nMotivo da Alteração: Correção pelo adquirente\nIdentificador da Versão do Anúncio a Alterar: 56e7ea4f-ba67-4422-90f8-d2a48cd052f8-01\nIdentificador das Secções Alteradas do Anúncio Anterior: Alteração\nAlteração dos Documentos do Concurso: Não\n419614323",
    "nipc": "500965099",
    "distrito": "Lisboa",
    "concelho": "Lisboa",
    "freguesia": "Todas",
    "site": "https://portal.oa.pt/",
    "email": "cons.geral@cg.oa.pt",
    "designacao_contrato": "CNI599/OA/2025_Seguro de Grupo de Responsabilidade Civil Profissional para os Advogados com inscrição em vigor na Ordem dos Advogados",
    "descricao": "CNI599/OA/2025_Seguro de Grupo de Responsabilidade Civil Profissional para os Advogados com inscrição em vigor na Ordem dos Advogados",
    "preco_base": "2.890.000,00 EUR",
    "prazo_execucao": "24 MESES",
    "prazo_apresentacao_propostas": "06-10-2025 23:59",
    "fundos_eu": "Não",
    "plataforma_eletronica": "VORTAL",
    "url_procedimento": "https://community.vortal.biz/public/",
    "autor_nome": "Ana Rola",
    "autor_cargo": "Serviço de Compras Conselho Geral da Ordem dos Advogados"
  },
  {
    "numero_procedimento": "N/A",
    "entidade": "AnÃºncio de procedimento  n.Âº 26167/2025  -  DiÃ¡rio da RepÃºblica n.Âº 192/2025, SÃ©rie II de 2025-10-06",
    "link": "https://diariodarepublica.pt/dr/detalhe/contrato-publico/26167-938138802"
  },
  {
    "numero_procedimento": "N/A",
    "entidade": "AnÃºncio de procedimento  n.Âº 26168/2025  -  DiÃ¡rio da RepÃºblica n.Âº 192/2025, SÃ©rie II de 2025-10-06",
    "link": "https://diariodarepublica.pt/dr/detalhe/contrato-publico/26168-938138803"
  },
  {
    "numero_procedimento": "N/A",
    "entidade": "AnÃºncio de procedimento  n.Âº 26169/2025  -  DiÃ¡rio da RepÃºblica n.Âº 192/2025, SÃ©rie II de 2025-10-06",
    "link": "https://diariodarepublica.pt/dr/detalhe/contrato-publico/26169-938138804"
  },
  {
    "numero_procedimento": "N/A",
    "entidade": "AnÃºncio de procedimento  n.Âº 26170/2025  -  DiÃ¡rio da RepÃºblica n.Âº 192/2025, SÃ©rie II de 2025-10-06",
    "link": "https://diariodarepublica.pt/dr/detalhe/contrato-publico/26170-938138805"
  },
  {
    "numero_procedimento": "N/A",
    "entidade": "AnÃºncio de procedimento  n.Âº 26142/2025  -  DiÃ¡rio da RepÃºblica n.Âº 192/2025, SÃ©rie II de 2025-10-06",
    "link": "https://diariodarepublica.pt/dr/detalhe/contrato-publico/26142-938169375"
  },
  {
    "numero_procedimento": "N/A",
    "entidade": "AnÃºncio de procedimento  n.Âº 26145/2025  -  DiÃ¡rio da RepÃºblica n.Âº 192/2025, SÃ©rie II de 2025-10-06",
    "link": "https://diariodarepublica.pt/dr/detalhe/contrato-publico/26145-938169376"
  },
  {
    "numero_procedimento": "N/A",
    "entidade": "AnÃºncio de procedimento  n.Âº 26147/2025  -  DiÃ¡rio da RepÃºblica n.Âº 192/2025, SÃ©rie II de 2025-10-06",
    "link": "https://diariodarepublica.pt/dr/detalhe/contrato-publico/26147-938169377"
  },
  {
    "numero_procedimento": "N/A",
    "entidade": "AnÃºncio de procedimento  n.Âº 26150/2025  -  DiÃ¡rio da RepÃºblica n.Âº 192/2025, SÃ©rie II de 2025-10-06",
    "link": "https://diariodarepublica.pt/dr/detalhe/contrato-publico/26150-938169378"
  },
  {
    "numero_procedimento": "N/A",
    "entidade": "AnÃºncio de procedimento  n.Âº 26153/2025  -  DiÃ¡rio da RepÃºblica n.Âº 192/2025, SÃ©rie II de 2025-10-06",
    "link": "https://diariodarepublica.pt/dr/detalhe/contrato-publico/26153-938169379"
  },
  {
    "numero_procedimento": "N/A",
    "entidade": "AnÃºncio de procedimento  n.Âº 26156/2025  -  DiÃ¡rio da RepÃºblica n.Âº 192/2025, SÃ©rie II de 2025-10-06",
    "link": "https://diariodarepublica.pt/dr/detalhe/contrato-publico/26156-938169380"
  },
  {
    "numero_procedimento": "N/A",
    "entidade": "AnÃºncio de procedimento  n.Âº 26158/2025  -  DiÃ¡rio da RepÃºblica n.Âº 192/2025, SÃ©rie II de 2025-10-06",
    "link": "https://diariodarepublica.pt/dr/detalhe/contrato-publico/26158-938169381"
  },
  {
    "numero_procedimento": "N/A",
    "entidade": "AnÃºncio de procedimento  n.Âº 26159/2025  -  DiÃ¡rio da RepÃºblica n.Âº 192/2025, SÃ©rie II de 2025-10-06",
    "link": "https://diariodarepublica.pt/dr/detalhe/contrato-publico/26159-938169382"
  },
  {
    "numero_procedimento": "N/A",
    "entidade": "AnÃºncio de procedimento  n.Âº 26163/2025  -  DiÃ¡rio da RepÃºblica n.Âº 192/2025, SÃ©rie II de 2025-10-06",
    "link": "https://diariodarepublica.pt/dr/detalhe/contrato-publico/26163-938169383"
  },
  {
    "numero_procedimento": "N/A",
    "entidade": "AnÃºncio de procedimento  n.Âº 26164/2025  -  DiÃ¡rio da RepÃºblica n.Âº 192/2025, SÃ©rie II de 2025-10-06",
    "link": "https://diariodarepublica.pt/dr/detalhe/contrato-publico/26164-938169384"
  },
  {
    "numero_procedimento": "N/A",
    "entidade": "AnÃºncio de procedimento  n.Âº 26171/2025  -  DiÃ¡rio da RepÃºblica n.Âº 192/2025, SÃ©rie II de 2025-10-06",
    "link": "https://diariodarepublica.pt/dr/detalhe/contrato-publico/26171-938169385"
  }
]