[
  {
    "numero_procedimento": "N/A",
    "entidade": "AnÃºncio de procedimento  n.Âº 21245/2025  -  DiÃ¡rio da RepÃºblica n.Âº 151/2025, SÃ©rie II de 2025-08-07",
    "link": "https://diariodarepublica.pt/dr/detalhe/contrato-publico/21245-928132162"
  },
  {
    "numero_procedimento": "N/A",
    "entidade": "AnÃºncio de procedimento  n.Âº 21246/2025  -  DiÃ¡rio da RepÃºblica n.Âº 151/2025, SÃ©rie II de 2025-08-07",
    "link": "https://diariodarepublica.pt/dr/detalhe/contrato-publico/21246-928132163"
  },
  {
    "numero_procedimento": "N/A",
    "entidade": "AnÃºncio de procedimento  n.Âº 21247/2025  -  DiÃ¡rio da RepÃºblica n.Âº 151/2025, SÃ©rie II de 2025-08-07",
    "link": "https://diariodarepublica.pt/dr/detalhe/contrato-publico/21247-928132164"
  },
  {
    "numero_procedimento": "N/A",
    "entidade": "AnÃºncio de procedimento  n.Âº 21248/2025  -  DiÃ¡rio da RepÃºblica n.Âº 151/2025, SÃ©rie II de 2025-08-07",
    "link": "https://diariodarepublica.pt/dr/detalhe/contrato-publico/21248-928132165"
  },
  {
    "numero_procedimento": "N/A",
    "entidade": "AnÃºncio de procedimento  n.Âº 21249/2025  -  DiÃ¡rio da RepÃºblica n.Âº 151/2025, SÃ©rie II de 2025-08-07",
    "link": "https://diariodarepublica.pt/dr/detalhe/contrato-publico/21249-928132166"
  },
  {
    "numero_procedimento": "N/A",
    "entidade": "AnÃºncio de procedimento  n.Âº 21250/2025  -  DiÃ¡rio da RepÃºblica n.Âº 151/2025, SÃ©rie II de 2025-08-07",
    "link": "https://diariodarepublica.pt/dr/detalhe/contrato-publico/21250-928132167"
  },
  {
    "numero_procedimento": "N/A",
    "entidade": "AnÃºncio de procedimento  n.Âº 21251/2025  -  DiÃ¡rio da RepÃºblica n.Âº 151/2025, SÃ©rie II de 2025-08-07",
    "link": "https://diariodarepublica.pt/dr/detalhe/contrato-publico/21251-928132168"
  },
  {
    "numero_procedimento": "N/A",
    "entidade": "AnÃºncio de procedimento  n.Âº 21242/2025  -  DiÃ¡rio da RepÃºblica n.Âº 151/2025, SÃ©rie II de 2025-08-07",
    "link": "https://diariodarepublica.pt/dr/detalhe/contrato-publico/21242-928163355"
  },
  {
    "numero_procedimento": "N/A",
    "entidade": "AnÃºncio de procedimento  n.Âº 21243/2025  -  DiÃ¡rio da RepÃºblica n.Âº 151/2025, SÃ©rie II de 2025-08-07",
    "link": "https://diariodarepublica.pt/dr/detalhe/contrato-publico/21243-928163356"
  },
  {
    "numero_procedimento": "N/A",
    "entidade": "AnÃºncio de procedimento  n.Âº 21244/2025  -  DiÃ¡rio da RepÃºblica n.Âº 151/2025, SÃ©rie II de 2025-08-07",
    "link": "https://diariodarepublica.pt/dr/detalhe/contrato-publico/21244-928163357"
  },
  {
    "numero_procedimento": "N/A",
    "entidade": "AnÃºncio de procedimento  n.Âº 21254/2025  -  DiÃ¡rio da RepÃºblica n.Âº 151/2025, SÃ©rie II de 2025-08-07",
    "link": "https://diariodarepublica.pt/dr/detalhe/contrato-publico/21254-928163360"
  },
  {
    "numero_procedimento": "N/A",
    "entidade": "AnÃºncio de procedimento  n.Âº 21257/2025  -  DiÃ¡rio da RepÃºblica n.Âº 151/2025, SÃ©rie II de 2025-08-07",
    "link": "https://diariodarepublica.pt/dr/detalhe/contrato-publico/21257-928163362"
  },
  {
    "numero_procedimento": "N/A",
    "entidade": "AnÃºncio de procedimento  n.Âº 21263/2025  -  DiÃ¡rio da RepÃºblica n.Âº 151/2025, SÃ©rie II de 2025-08-07",
    "link": "https://diariodarepublica.pt/dr/detalhe/contrato-publico/21263-928163363"
  },
  {
    "numero_procedimento": "N/A",
    "entidade": "AnÃºncio de procedimento  n.Âº 21252/2025  -  DiÃ¡rio da RepÃºblica n.Âº 151/2025, SÃ©rie II de 2025-08-07",
    "link": "https://diariodarepublica.pt/dr/detalhe/contrato-publico/21252-928188575"
  },
  {
    "numero_procedimento": "N/A",
    "entidade": "AnÃºncio de procedimento  n.Âº 21253/2025  -  DiÃ¡rio da RepÃºblica n.Âº 151/2025, SÃ©rie II de 2025-08-07",
    "link": "https://diariodarepublica.pt/dr/detalhe/contrato-publico/21253-928188576"
  },
  {
    "numero_procedimento": "N/A",
    "entidade": "AnÃºncio de procedimento  n.Âº 21255/2025  -  DiÃ¡rio da RepÃºblica n.Âº 151/2025, SÃ©rie II de 2025-08-07",
    "link": "https://diariodarepublica.pt/dr/detalhe/contrato-publico/21255-928188582"
  },
  {
    "numero_procedimento": "N/A",
    "entidade": "AnÃºncio de procedimento  n.Âº 21256/2025  -  DiÃ¡rio da RepÃºblica n.Âº 151/2025, SÃ©rie II de 2025-08-07",
    "link": "https://diariodarepublica.pt/dr/detalhe/contrato-publico/21256-928188583"
  },
  {
    "numero_procedimento": "N/A",
    "entidade": "Instituto Politécnico de Santarém",
    "link": "https://diariodarepublica.pt/dr/detalhe/contrato-publico/21258-928189639",
    "detalhes_completos": "1 - IDENTIFICAÇÃO E CONTACTOS DA ENTIDADE ADJUDICANTE\nDesignação da entidade adjudicante: Instituto Politécnico de Santarém\nNIPC: 501403906\nServiço/Órgão/Pessoa de contacto: geral@ipsantarem.pt\nEndereço: Complexo Andaluz - Moinho de Fau - Santarém\nCódigo postal: 2001-904\nLocalidade: Santarém\nPaís: Portugal\nNUT III: PT185\nDistrito: Santarém\nConcelho: Santarém\nFreguesia: União de Freguesias da Cidade de Santarém\nTelefone: 243309520\nFax: 243309539\nEndereço da Entidade (URL): www.ipsantarem.pt\nEndereço Eletrónico: geral@ipsantarem.pt\neDelivery Gateway (URL): https://www.acingov.pt\nFunção da Organização: Adquirente\nSubfunção da Organização: Organização cujo orçamento é utilizado para pagar o contrato; Organização que executa o pagamento; Organização que fornece informações adicionais sobre o processo de adjudicação; Organização que fornece mais informações sobre os prazos dos procedimentos de recurso; Organização responsável pelo tratamento das propostas; Organização que recebe as propostas; Organização que trata os pedidos de participação; Organização que recebe pedidos de participação; Organização que fornece mais informações sobre os procedimentos de recurso; Organização que assina o contrato\nNorma jurídica da Entidade Adjudicante: Organismo de direito público\nÁrea de atividade da Autoridade Adjudicante: Educação\n\n2 - JORNAL OFICIAL DA UNIÃO EUROPEIA\nO procedimento a que este anúncio diz respeito também é publicitado no Jornal Oficial da União Europeia? Não\n\n3 - AVISO\nModelo de Anúncio: Concurso público\nData de Envio do Anúncio: 06-08-2025\n\n5 - PROCESSO\nTipo de Procedimento: Concurso público\nPreço base do procedimento: Sim\nValor do preço base do procedimento: 100.464,00 EUR\nProcedimento com lotes? Sim\nNº Máx. de Lotes Autorizado: 5\nNúmero máximo de lotes que podem ser adjudicados a um concorrente: 5\n\n6 - OBJETO DO CONTRATO\nNúmero de referência interna: 063/CP/2025\nDesignação do contrato: 063/CP/2025 Aquisição de equipamento para laboratório da preservação de raças autóctones no âmbito do Projeto Santarém AgroHub\nDescrição: Aquisição de equipamento para laboratório da preservação de raças autóctones no âmbito do Projeto Santarém AgroHub \nTipo de Contrato Principal: Aquisição de Bens Móveis\nTipo de Contrato: Aquisição de Bens Móveis\nClassificação CPV (Vocabulário Comum para os Contratos Públicos)\nObjeto principal\nVocabulário Principal: 38000000\nPreço base s/IVA: 100.464,00 EUR\nLotes: \nNº: LOT-0001\nDescrição do Lote: lote 1\nPreço base s/IVA: 42.654,00 EUR\nClassificação CPV (Vocabulário Comum para os Contratos Públicos)\nObjeto principal\nVocabulário Principal: 38000000\nNº: LOT-0002\nDescrição do Lote: Lote 2\nPreço base s/IVA: 36.750,00 EUR\nClassificação CPV (Vocabulário Comum para os Contratos Públicos)\nObjeto principal\nVocabulário Principal: 38000000\nNº: LOT-0003\nDescrição do Lote: Lote 3\nPreço base s/IVA: 680,00 EUR\nClassificação CPV (Vocabulário Comum para os Contratos Públicos)\nObjeto principal\nVocabulário Principal: 38000000\nNº: LOT-0004\nDescrição do Lote: Lote 4\nPreço base s/IVA: 5.230,00 EUR\nClassificação CPV (Vocabulário Comum para os Contratos Públicos)\nObjeto principal\nVocabulário Principal: 38000000\nNº: LOT-0005\nDescrição do Lote: Lote 5\nPreço base s/IVA: 15.150,00 EUR\nClassificação CPV (Vocabulário Comum para os Contratos Públicos)\nObjeto principal\nVocabulário Principal: 38000000\n\n7 - INDICAÇÕES ADICIONAIS\nO contrato envolve aquisição conjunta (satisfação de várias entidades)? Não\nO contrato é adjudicado por uma central de compras? Não\n\n8 - TÉCNICAS\nO concurso destina-se à celebração de um acordo-quadro? Inexistência de acordo-quadro\nÉ utilizado um leilão eletrónico? Não\nÉ adotada uma fase de negociação? Não\nSistema de Aquisição Dinâmico: Inexistência de sistema de aquisição dinâmico\n\n9 - LOCAL DA EXECUÇÃO DO CONTRATO\nLOCAL DA EXECUÇÃO DO CONTRATO (PROCEDIMENTO)\nPaís: Portugal\nNUT III: PT185\nLocalidade: União de Freguesias da Cidade de Santarém\nDistrito: Santarém\nConcelho: Santarém\nFreguesia: União de Freguesias da Cidade de Santarém\nLOCAL DA EXECUÇÃO DO CONTRATO (LOTE)\nIdentificador do Lote: LOT-0001; LOT-0002; LOT-0003; LOT-0004; LOT-0005\nPaís: Portugal\nNUT III: PT185\nLocalidade: União de Freguesias da Cidade de Santarém\nDistrito: Santarém\nConcelho: Santarém\nFreguesia: União de Freguesias da Cidade de Santarém\n\n10 - PRAZO DE EXECUÇÃO DO CONTRATO\nIdentificador do Lote: LOT-0001; LOT-0002; LOT-0003; LOT-0004; LOT-0005\nData de Início: 15-08-2025\nData de Fim: 12-09-2025\nPrevisão de renovações: Não\n\n11 - FUNDOS EU\nIdentificador do Lote: LOT-0001; LOT-0002; LOT-0003; LOT-0004; LOT-0005\nTêm fundos EU? Sim\n\n12 - DOCUMENTOS DE HABILITAÇÃO\nHabilitação para o exercício da atividade profissional: Não\n\n13 - CONDIÇÕES DE APRESENTAÇÃO\nPlataforma eletrónica utilizada pela entidade adjudicante: ACIN\nURL para Apresentação: https://www.acingov.pt\nAdmissibilidade da apresentação de propostas variantes: Não autorizado\nPrazo para apresentação das propostas: 19-08-2025 23:59\nPrazo durante o qual os concorrentes são obrigados a manter as respetivas propostas: 66 dias a contar do termo do prazo para a apresentação das propostas\nIndicação de Subcontratação na Proposta: Inexistência de indicação de subcontratação\n\n14 - PRESTAÇÃO DE CAUÇÃO\nPrestação de caução: Não\n\n15 - FORNECIMENTO DAS PEÇAS DO CONCURSO, APRESENTAÇÃO DE PEDIDOS DE PARTICIPAÇÃO E APRESENTAÇÃO DAS PROPOSTAS\nLink para acesso às peças do concurso (URL): https://www.acingov.pt/acingovprod/2/zonaPublica/zona_publica_c/donwloadProcedurePiece/OTMwNjU1\n\n20 - OUTROS REQUISITOS\nIdentificador do Lote: LOT-0001; LOT-0002; LOT-0003; LOT-0004; LOT-0005\nInformação sobre contratos reservados. Aplica-se a contratos reservados (54º-A)? Não\n\n21 - CRITÉRIO DE ADJUDICAÇÃO\nO Critério de adjudicação é diferenciado por lote? Não\nMultifator: Não\nMonofator:\nNome: Preço\n\n24 - CONDIÇÕES DO CONTRATO\nIdentificador do Lote: LOT-0001; LOT-0002; LOT-0003; LOT-0004; LOT-0005\nFaturação Eletrónica: Permitido\nObrigação de Subcontratação:\nCódigo da Obrigação de Subcontratação: Não é aplicável nenhuma obrigação de subcontratação.\n\n25 - COMPRA PÚBLICA ESTRATÉGICA\nCompra Pública Estratégica: Aquisição inovadora\nCategorias da estratégia nacional: Outros\nOutra categoria (Descrição): N/A\nContratos Públicos Inovadores: As obras, fornecimentos ou serviços adjudicados envolvem atividades de investigação e desenvolvimento.; As obras, fornecimentos ou serviços adquiridos são inovadores ou significativamente melhorados em comparação com obras, fornecimentos ou serviços já existentes no mercado.\nCritério de Acessibilidade: Os critérios de acessibilidade para as pessoas com deficiência não estão incluídos porque o contrato não se destina a pessoas singulares\n\n26 - INFORMAÇÕES ADICIONAIS\nIdentificador do Lote: LOT-0001; LOT-0002; LOT-0003; LOT-0004; LOT-0005\nContrato adequado para PME: Sim\nCobertura ACP (Acordo dos Contratos Públicos da Organização Mundial do Comércio): Não\n\n27 - IDENTIFICAÇÃO E CONTACTOS DO ÓRGÃO DE RECURSOS ADMINISTRATIVOS\nDesignação: Presidente\nEndereço: Complexo Andaluz - Apartado 279\nCódigo postal: 2001-904\nLocalidade: Santarém, Portugal\nTelefone: 243309520\nFax: \nEndereço eletrónico: presidente@ipsantarem.pt\n\n28 - IDENTIFICAÇÃO DO(S) AUTOR(ES) DE ANÚNCIO\nNome: Sónia Catarina Rodrigues Fontes\nCargo: TS\n419404922",
    "nipc": "501403906",
    "distrito": "Santarém",
    "concelho": "Santarém",
    "freguesia": "União de Freguesias da Cidade de Santarém",
    "site": "www.ipsantarem.pt",
    "email": "geral@ipsantarem.pt",
    "designacao_contrato": "063/CP/2025 Aquisição de equipamento para laboratório da preservação de raças autóctones no âmbito do Projeto Santarém AgroHub",
    "descricao": "Aquisição de equipamento para laboratório da preservação de raças autóctones no âmbito do Projeto Santarém AgroHub",
    "preco_base": "100.464,00 EUR",
    "prazo_execucao": null,
    "prazo_apresentacao_propostas": "19-08-2025 23:59",
    "fundos_eu": "Sim",
    "plataforma_eletronica": "ACIN",
    "url_procedimento": "https://www.acingov.pt",
    "autor_nome": "Sónia Catarina Rodrigues Fontes",
    "autor_cargo": "TS"
  },
  {
    "numero_procedimento": "N/A",
    "entidade": "AnÃºncio de procedimento  n.Âº 21259/2025  -  DiÃ¡rio da RepÃºblica n.Âº 151/2025, SÃ©rie II de 2025-08-07",
    "link": "https://diariodarepublica.pt/dr/detalhe/contrato-publico/21259-928189640"
  },
  {
    "numero_procedimento": "N/A",
    "entidade": "AnÃºncio de procedimento  n.Âº 21260/2025  -  DiÃ¡rio da RepÃºblica n.Âº 151/2025, SÃ©rie II de 2025-08-07",
    "link": "https://diariodarepublica.pt/dr/detalhe/contrato-publico/21260-928189641"
  },
  {
    "numero_procedimento": "N/A",
    "entidade": "AnÃºncio de procedimento  n.Âº 21261/2025  -  DiÃ¡rio da RepÃºblica n.Âº 151/2025, SÃ©rie II de 2025-08-07",
    "link": "https://diariodarepublica.pt/dr/detalhe/contrato-publico/21261-928189642"
  },
  {
    "numero_procedimento": "N/A",
    "entidade": "AnÃºncio de procedimento  n.Âº 21262/2025  -  DiÃ¡rio da RepÃºblica n.Âº 151/2025, SÃ©rie II de 2025-08-07",
    "link": "https://diariodarepublica.pt/dr/detalhe/contrato-publico/21262-928189643"
  }
]