[
  {
    "numero_procedimento": "N/A",
    "entidade": "Secretaria-Geral do MAI",
    "link": "https://diariodarepublica.pt/dr/detalhe/contrato-publico/21354-928294603",
    "detalhes_completos": "1 - IDENTIFICAÇÃO E CONTACTOS DA ENTIDADE ADJUDICANTE\nDesignação da entidade adjudicante: Secretaria-Geral do MAI\nNIPC: 600014665\nEndereço: Rua São Mamede, 23\nCódigo postal: 1100-523\nLocalidade: Lisboa\nPaís: Portugal\nNUT III: PT170\nDistrito: Lisboa\nConcelho: Lisboa\nFreguesia: Freguesia de Santa Maria Maior - Lisboa\nTelefone: 213409000\nFax: 213409010\nEndereço da Entidade (URL): www.sg.mai.gov.pt/\nEndereço Eletrónico: gab.sec.geral@sg.mai.gov.pt\neDelivery Gateway (URL): https://community.vortal.biz/public/\nFunção da Organização: Adquirente\nNorma jurídica da Entidade Adjudicante: Autoridade da administração central\nÁrea de atividade da Autoridade Adjudicante: Serviços públicos das administrações públicas\n\n2 - JORNAL OFICIAL DA UNIÃO EUROPEIA\nO procedimento a que este anúncio diz respeito também é publicitado no Jornal Oficial da União Europeia? Sim\n\n3 - AVISO\nModelo de Anúncio: Concurso público\nData de Envio do Anúncio: 05-08-2025\n\n5 - PROCESSO\nTipo de Procedimento: Concurso público\nPreço base do procedimento: Sim\nValor do preço base do procedimento: 325.203,25 EUR\nProcedimento com lotes? Sim\nNº Máx. de Lotes Autorizado: 15\nNúmero máximo de lotes que podem ser adjudicados a um concorrente: 15\n\n6 - OBJETO DO CONTRATO\nNúmero de referência interna: Proc. 3/DPIE/2025\nDesignação do contrato: Proc.3/DPIE/2025  - Aquisição de vários equipamentos e aparelhos de saúde para os Centros Clínicos da GNR, para os anos de  2025 e 2026, no âmbito do DLPIEFSS\nDescrição: Proc.3/DPIE/2025  - Aquisição de vários equipamentos e aparelhos de saúde para os Centros Clínicos da GNR, para os anos de  2025 e 2026, no âmbito do DLPIEFSS\nOpções: Não\nTipo de Contrato Principal: Aquisição de Bens Móveis\nTipo de Contrato: Aquisição de Bens Móveis\nClassificação CPV (Vocabulário Comum para os Contratos Públicos)\nObjeto principal\nVocabulário Principal: 33100000\nPreço base s/IVA: 325.203,25 EUR\nLotes: \nNº: LOT-0001\nDescrição do Lote: Lote 1 - Cadeira de Medicina Dentária\nPreço base s/IVA: 13.821,14 EUR\nClassificação CPV (Vocabulário Comum para os Contratos Públicos)\nObjeto principal\nVocabulário Principal: 33100000\nNº: LOT-0002\nDescrição do Lote: Lote 2 - Piezotomo com motor e contra-ângulo\nPreço base s/IVA: 8.943,09 EUR\nClassificação CPV (Vocabulário Comum para os Contratos Públicos)\nObjeto principal\nVocabulário Principal: 33100000\nNº: LOT-0003\nDescrição do Lote: Lote 3 - Equipamento CBCT(Cone Beam Computed Tomography)\nPreço base s/IVA: 48.780,49 EUR\nClassificação CPV (Vocabulário Comum para os Contratos Públicos)\nObjeto principal\nVocabulário Principal: 33100000\nNº: LOT-0004\nDescrição do Lote: Lote 4 - Ecocardiografo c/ sondas e estação de trabalho\nPreço base s/IVA: 67.479,67 EUR\nClassificação CPV (Vocabulário Comum para os Contratos Públicos)\nObjeto principal\nVocabulário Principal: 33100000\nNº: LOT-0005\nDescrição do Lote: Lote 5 - Aparelho Monitor Desfibrilhador \nPreço base s/IVA: 24.390,24 EUR\nClassificação CPV (Vocabulário Comum para os Contratos Públicos)\nObjeto principal\nVocabulário Principal: 33100000\nNº: LOT-0006\nDescrição do Lote: Lote 6 - Impedanciometro/Audiómetro\nPreço base s/IVA: 5.691,06 EUR\nClassificação CPV (Vocabulário Comum para os Contratos Públicos)\nObjeto principal\nVocabulário Principal: 33100000\nNº: LOT-0007\nDescrição do Lote: Lote 7 - Aparelho de Kineo Multistation com acessórios, ou equivalente\nPreço base s/IVA: 30.081,30 EUR\nClassificação CPV (Vocabulário Comum para os Contratos Públicos)\nObjeto principal\nVocabulário Principal: 33100000\nNº: LOT-0008\nDescrição do Lote: Lote 8 - Aparelho de ondas de choque focais\nPreço base s/IVA: 48.780,48 EUR\nClassificação CPV (Vocabulário Comum para os Contratos Públicos)\nObjeto principal\nVocabulário Principal: 33100000\nNº: LOT-0009\nDescrição do Lote: Lote 9 - Aparelho Magnetoterapia de alta intensidade\nPreço base s/IVA: 16.260,16 EUR\nClassificação CPV (Vocabulário Comum para os Contratos Públicos)\nObjeto principal\nVocabulário Principal: 33100000\nNº: LOT-0010\nDescrição do Lote: Lote 10 - Aparelho de Tecarterapia\nPreço base s/IVA: 21.138,21 EUR\nClassificação CPV (Vocabulário Comum para os Contratos Públicos)\nObjeto principal\nVocabulário Principal: 33100000\nNº: LOT-0011\nDescrição do Lote: Lote 11 - Aparelho de Ultrassonoterapia\nPreço base s/IVA: 1.626,02 EUR\nClassificação CPV (Vocabulário Comum para os Contratos Públicos)\nObjeto principal\nVocabulário Principal: 33100000\nNº: LOT-0012\nDescrição do Lote: Lote 12 - Sonda Musculoesquelética\nPreço base s/IVA: 4.878,05 EUR\nClassificação CPV (Vocabulário Comum para os Contratos Públicos)\nObjeto principal\nVocabulário Principal: 33100000\nNº: LOT-0013\nDescrição do Lote: Lote 13 - Lâmpada de fenda com tonómetro de aplanação\nPreço base s/IVA: 12.195,12 EUR\nClassificação CPV (Vocabulário Comum para os Contratos Públicos)\nObjeto principal\nVocabulário Principal: 33100000\nNº: LOT-0014\nDescrição do Lote: Lote 14 - Unidade de ecografia para oftalmologia\nPreço base s/IVA: 14.634,15 EUR\nClassificação CPV (Vocabulário Comum para os Contratos Públicos)\nObjeto principal\nVocabulário Principal: 33100000\nNº: LOT-0015\nDescrição do Lote: Lote 15 - Histeroscópio\nPreço base s/IVA: 6.504,07 EUR\nClassificação CPV (Vocabulário Comum para os Contratos Públicos)\nObjeto principal\nVocabulário Principal: 33100000\n\n7 - INDICAÇÕES ADICIONAIS\nO contrato envolve aquisição conjunta (satisfação de várias entidades)? Não\nO contrato é adjudicado por uma central de compras? Não\n\n8 - TÉCNICAS\nO concurso destina-se à celebração de um acordo-quadro? Inexistência de acordo-quadro\nÉ utilizado um leilão eletrónico? Não\nÉ adotada uma fase de negociação? Não\nSistema de Aquisição Dinâmico: Inexistência de sistema de aquisição dinâmico\n\n9 - LOCAL DA EXECUÇÃO DO CONTRATO\nLOCAL DA EXECUÇÃO DO CONTRATO (PROCEDIMENTO)\nPaís: Portugal\nNUT III: PT170\nLocalidade: Lisboa\nDistrito: Lisboa\nConcelho: Lisboa\nFreguesia: Todas\nLOCAL DA EXECUÇÃO DO CONTRATO (LOTE)\nIdentificador do Lote: LOT-0001; LOT-0002; LOT-0003; LOT-0004; LOT-0005; LOT-0006; LOT-0007; LOT-0008; LOT-0009; LOT-0010; LOT-0011; LOT-0012; LOT-0013; LOT-0014; LOT-0015\nPaís: Portugal\nNUT III: PT170\nLocalidade: Lisboa\nDistrito: Lisboa\nConcelho: Lisboa\nFreguesia: Todas\n\n10 - PRAZO DE EXECUÇÃO DO CONTRATO\nIdentificador do Lote: LOT-0001; LOT-0002; LOT-0003; LOT-0004; LOT-0005; LOT-0006; LOT-0007; LOT-0008; LOT-0009; LOT-0010; LOT-0011; LOT-0012; LOT-0013; LOT-0014; LOT-0015\nPrazo de execução do contrato: 2 ANOS\nPrevisão de renovações: Não\n\n11 - FUNDOS EU\nIdentificador do Lote: LOT-0001; LOT-0002; LOT-0003; LOT-0004; LOT-0005; LOT-0006; LOT-0007; LOT-0008; LOT-0009; LOT-0010; LOT-0011; LOT-0012; LOT-0013; LOT-0014; LOT-0015\nTêm fundos EU? Não\n\n12 - DOCUMENTOS DE HABILITAÇÃO\nHabilitação para o exercício da atividade profissional: Não\n\n13 - CONDIÇÕES DE APRESENTAÇÃO\nPlataforma eletrónica utilizada pela entidade adjudicante: VORTAL\nURL para Apresentação: https://community.vortal.biz/public/\nAdmissibilidade da apresentação de propostas variantes: Não autorizado\nPrazo para apresentação das propostas: 22-09-2025 23:59\nPrazo durante o qual os concorrentes são obrigados a manter as respetivas propostas: 90 dias a contar do termo do prazo para a apresentação das propostas\nApresentação de Catálogo Eletrónico: Permitido\nIndicação de Subcontratação na Proposta: Inexistência de indicação de subcontratação\n\n14 - PRESTAÇÃO DE CAUÇÃO\nPrestação de caução: Não\n\n15 - FORNECIMENTO DAS PEÇAS DO CONCURSO, APRESENTAÇÃO DE PEDIDOS DE PARTICIPAÇÃO E APRESENTAÇÃO DAS PROPOSTAS\nLink para acesso às peças do concurso (URL): https://community.vortal.biz/Public/public-tender-documents/OUtOZlkwZERXSW5lZnR5WkUxYVluSVNySVBBd25mZUQ1ajBBaFcxK0FkN3NlWUM2eGFRNzlEbEpPRElXRFkzdnNKOHFsaTdzSmFESXV6dXNmQ3gxN3c9PUA4MlUo\n\n20 - OUTROS REQUISITOS\nIdentificador do Lote: LOT-0001; LOT-0002; LOT-0003; LOT-0004; LOT-0005; LOT-0006; LOT-0007; LOT-0008; LOT-0009; LOT-0010; LOT-0011; LOT-0012; LOT-0013; LOT-0014; LOT-0015\nInformação sobre contratos reservados. Aplica-se a contratos reservados (54º-A)? Não\n\n21 - CRITÉRIO DE ADJUDICAÇÃO\nO Critério de adjudicação é diferenciado por lote? Não\nMultifator: Sim\nFator: \nNome: Preço\nPonderação: 85%\nSubfatores: Não\nFator: \nNome: Qualidade\nPonderação: 15%\nSubfatores: Não\n\n24 - CONDIÇÕES DO CONTRATO\nIdentificador do Lote: LOT-0001; LOT-0002; LOT-0003; LOT-0004; LOT-0005; LOT-0006; LOT-0007; LOT-0008; LOT-0009; LOT-0010; LOT-0011; LOT-0012; LOT-0013; LOT-0014; LOT-0015\nFaturação Eletrónica: Permitido\nObrigação de Subcontratação:\nCódigo da Obrigação de Subcontratação: Não é aplicável nenhuma obrigação de subcontratação.\n\n25 - COMPRA PÚBLICA ESTRATÉGICA\nCompra Pública Estratégica: Inexistência de contratação pública estratégica\n\n26 - INFORMAÇÕES ADICIONAIS\nIdentificador do Lote: LOT-0001; LOT-0002; LOT-0003; LOT-0004; LOT-0005; LOT-0006; LOT-0007; LOT-0008; LOT-0009; LOT-0010; LOT-0011; LOT-0012; LOT-0013; LOT-0014; LOT-0015\nContrato adequado para PME: Sim\nCobertura ACP (Acordo dos Contratos Públicos da Organização Mundial do Comércio): Não\n\n27 - IDENTIFICAÇÃO E CONTACTOS DO ÓRGÃO DE RECURSOS ADMINISTRATIVOS\nDesignação: Ministério da Administração Interna\nEndereço: Praça do Comércio - Ala Oriental\nCódigo postal: 1149-015\nLocalidade: Lisboa\nTelefone: +351 213184621\nFax: +351 213184621\nEndereço eletrónico: dpie@sg.mai.gov.pt\n\n28 - IDENTIFICAÇÃO DO(S) AUTOR(ES) DE ANÚNCIO\nNome: Ricardo Carrilho\nCargo: Secretário-Geral do Ministério da Administração Interna\n419402808",
    "nipc": "600014665",
    "distrito": "Lisboa",
    "concelho": "Lisboa",
    "freguesia": "Freguesia de Santa Maria Maior - Lisboa",
    "site": "www.sg.mai.gov.pt/",
    "email": "gab.sec.geral@sg.mai.gov.pt",
    "designacao_contrato": "Proc.3/DPIE/2025 - Aquisição de vários equipamentos e aparelhos de saúde para os Centros Clínicos da GNR, para os anos de 2025 e 2026, no âmbito do DLPIEFSS",
    "descricao": "Proc.3/DPIE/2025 - Aquisição de vários equipamentos e aparelhos de saúde para os Centros Clínicos da GNR, para os anos de 2025 e 2026, no âmbito do DLPIEFSS",
    "preco_base": "325.203,25 EUR",
    "prazo_execucao": "2 ANOS",
    "prazo_apresentacao_propostas": "22-09-2025 23:59",
    "fundos_eu": "Não",
    "plataforma_eletronica": "VORTAL",
    "url_procedimento": "https://community.vortal.biz/public/",
    "autor_nome": "Ricardo Carrilho",
    "autor_cargo": "Secretário-Geral do Ministério da Administração Interna"
  },
  {
    "numero_procedimento": "N/A",
    "entidade": "Serviços de Acção Social do IPT",
    "link": "https://diariodarepublica.pt/dr/detalhe/contrato-publico/21355-928294604",
    "detalhes_completos": "1 - IDENTIFICAÇÃO E CONTACTOS DA ENTIDADE ADJUDICANTE\nDesignação da entidade adjudicante: Serviços de Acção Social do IPT\nNIPC: 600052338\nServiço/Órgão/Pessoa de contacto: Serviços de Aprovisionamento\nEndereço: Quinta do Contador-Estrada da Serra\nCódigo postal: 2300-313\nLocalidade: Tomar\nPaís: Portugal\nNUT III: PT16I\nDistrito: Santarém\nConcelho: Tomar\nFreguesia: União das Freguesias de Tomar (São João Baptista) e Santa Maria dos Olivais\nTelefone: 249328100\nFax: 249328100\nEndereço da Entidade (URL): https://www.ipt.pt/\nEndereço Eletrónico: aprovisionamento@ipt.pt\neDelivery Gateway (URL): https://www.acingov.pt\nFunção da Organização: Adquirente\nNorma jurídica da Entidade Adjudicante: Organismo de direito público\nÁrea de atividade da Autoridade Adjudicante: Serviços públicos das administrações públicas\n\n2 - JORNAL OFICIAL DA UNIÃO EUROPEIA\nO procedimento a que este anúncio diz respeito também é publicitado no Jornal Oficial da União Europeia? Não\n\n3 - AVISO\nModelo de Anúncio: Concurso público\nData de Envio do Anúncio: 07-08-2025\n\n5 - PROCESSO\nTipo de Procedimento: Concurso público\nPreço base do procedimento: Sim\nValor do preço base do procedimento: 177.471,00 EUR\nProcedimento com lotes? Não\n\n6 - OBJETO DO CONTRATO\nNúmero de referência interna: CP/01/SAS-IPT/2025\nDesignação do contrato: Concessão da Exploração do Snack-Bar/Cafetaria/Vending e Fornecimento de Refeições, nos Serviços de Acção Social Do Instituto Politécnico De Tomar/Escola Superior De Tecnologia De Abrantes\nDescrição: Concessão da Exploração do Snack-Bar/Cafetaria/Vending e Fornecimento de Refeições, nos Serviços de Acção Social Do\nInstituto Politécnico De Tomar/Escola Superior De Tecnologia De Abrantes\nTipo de Contrato Principal: Aquisição de Serviços\nTipo de Contrato: Aquisição de Bens Móveis; Aquisição de Serviços\nClassificação CPV (Vocabulário Comum para os Contratos Públicos)\nObjeto principal\nVocabulário Principal: 55130000\nPreço base s/IVA: 20.721,00 EUR\nObjeto Complementar\nVocabulário Principal: 15894210\nPreço base s/IVA: 156.750,00 EUR\n\n7 - INDICAÇÕES ADICIONAIS\nO contrato envolve aquisição conjunta (satisfação de várias entidades)? Não\nO contrato é adjudicado por uma central de compras? Não\n\n8 - TÉCNICAS\nO concurso destina-se à celebração de um acordo-quadro? Inexistência de acordo-quadro\nÉ utilizado um leilão eletrónico? Não\nÉ adotada uma fase de negociação? Não\nSistema de Aquisição Dinâmico: Inexistência de sistema de aquisição dinâmico\n\n9 - LOCAL DA EXECUÇÃO DO CONTRATO\nLOCAL DA EXECUÇÃO DO CONTRATO (PROCEDIMENTO)\nPaís: Portugal\nNUT III: PT16I\nLocalidade: União das Freguesias de Tomar (São João Baptista) e Santa Maria dos Olivais\nDistrito: Santarém\nConcelho: Tomar\nFreguesia: União das Freguesias de Tomar (São João Baptista) e Santa Maria dos Olivais\n\n10 - PRAZO DE EXECUÇÃO DO CONTRATO\nPrazo de execução do contrato: 12 MESES\nPrevisão de renovações: Sim\nIndicar número máximo de renovações: 2\nPrazo de renovações diferente do prazo inicial: Não\n\n11 - FUNDOS EU\nTêm fundos EU? Não\n\n12 - DOCUMENTOS DE HABILITAÇÃO\nHabilitação para o exercício da atividade profissional: Não\n\n13 - CONDIÇÕES DE APRESENTAÇÃO\nPlataforma eletrónica utilizada pela entidade adjudicante: ACIN\nURL para Apresentação: https://www.acingov.pt\nAdmissibilidade da apresentação de propostas variantes: Não autorizado\nPrazo para apresentação das propostas: 17-08-2025 23:59\nPrazo durante o qual os concorrentes são obrigados a manter as respetivas propostas: 66 dias a contar do termo do prazo para a apresentação das propostas\nIndicação de Subcontratação na Proposta: Inexistência de indicação de subcontratação\n\n14 - PRESTAÇÃO DE CAUÇÃO\nPrestação de caução: Não\n\n15 - FORNECIMENTO DAS PEÇAS DO CONCURSO, APRESENTAÇÃO DE PEDIDOS DE PARTICIPAÇÃO E APRESENTAÇÃO DAS PROPOSTAS\nLink para acesso às peças do concurso (URL): https://www.acingov.pt/acingovprod/2/zonaPublica/zona_publica_c/donwloadProcedurePiece/OTMyNDU2\n\n20 - OUTROS REQUISITOS\nInformação sobre contratos reservados. Aplica-se a contratos reservados (54º-A)? Não\n\n21 - CRITÉRIO DE ADJUDICAÇÃO\nMultifator: Sim\nFator: \nNome: Outros\nOutro Nome: Preço da refeição social\nPonderação: 60%\nSubfatores: Não\nFator: \nNome: Outros\nOutro Nome: Contrapartida financeira mensal pela concessão de exploração\nPonderação: 10%\nSubfatores: Não\nFator: \nNome: Outros\nOutro Nome: Adequabilidade do serviço a prestar\nPonderação: 20%\nSubfatores: Não\nFator: \nNome: Outros\nOutro Nome: Pessoal a afetar à exploração.\nPonderação: 10%\nSubfatores: Não\n\n24 - CONDIÇÕES DO CONTRATO\nFaturação Eletrónica: Permitido\nObrigação de Subcontratação:\nCódigo da Obrigação de Subcontratação: Não é aplicável nenhuma obrigação de subcontratação.\n\n25 - COMPRA PÚBLICA ESTRATÉGICA\nCompra Pública Estratégica: Inexistência de contratação pública estratégica\n\n26 - INFORMAÇÕES ADICIONAIS\nContrato adequado para PME: Não\nCobertura ACP (Acordo dos Contratos Públicos da Organização Mundial do Comércio): Não\n\n27 - IDENTIFICAÇÃO E CONTACTOS DO ÓRGÃO DE RECURSOS ADMINISTRATIVOS\nDesignação: Presidente do Instituto Politécnico de Tomar\nEndereço: Quinta do Contador-Estrada da Serra\nCódigo postal: 2300-313\nLocalidade: Tomar\nTelefone: 249328100\nFax: 249328100\nEndereço eletrónico: aprovisionamento@ipt.pt\nPrazo de interposição do recurso: 5 dias\n\n28 - IDENTIFICAÇÃO DO(S) AUTOR(ES) DE ANÚNCIO\nNome: Doutor João Paulo Pereira de Freitas Coroado\nCargo: Presidente do Instituto Politécnico de Tomar\n419413784",
    "nipc": "600052338",
    "distrito": "Santarém",
    "concelho": "Tomar",
    "freguesia": "União das Freguesias de Tomar (São João Baptista) e Santa Maria dos Olivais",
    "site": "https://www.ipt.pt/",
    "email": "aprovisionamento@ipt.pt",
    "designacao_contrato": "Concessão da Exploração do Snack-Bar/Cafetaria/Vending e Fornecimento de Refeições, nos Serviços de Acção Social Do Instituto Politécnico De Tomar/Escola Superior De Tecnologia De Abrantes",
    "descricao": "Concessão da Exploração do Snack-Bar/Cafetaria/Vending e Fornecimento de Refeições, nos Serviços de Acção Social Do",
    "preco_base": "20.721,00 EUR",
    "prazo_execucao": "12 MESES",
    "prazo_apresentacao_propostas": "17-08-2025 23:59",
    "fundos_eu": "Não",
    "plataforma_eletronica": "ACIN",
    "url_procedimento": "https://www.acingov.pt",
    "autor_nome": "Doutor João Paulo Pereira de Freitas Coroado",
    "autor_cargo": "Presidente do Instituto Politécnico de Tomar"
  },
  {
    "numero_procedimento": "N/A",
    "entidade": "Fundação INATEL",
    "link": "https://diariodarepublica.pt/dr/detalhe/contrato-publico/21358-928294651",
    "detalhes_completos": "1 - IDENTIFICAÇÃO E CONTACTOS DA ENTIDADE ADJUDICANTE\nDesignação da entidade adjudicante: Fundação INATEL\nNIPC: 500122237\nServiço/Órgão/Pessoa de contacto: Conselho de Administração\nEndereço: Calçada de Santana, nº 180\nCódigo postal: 1169-062\nLocalidade: Lisboa\nPaís: Portugal\nNUT III: PT170\nDistrito: Lisboa\nConcelho: Lisboa\nFreguesia: Freguesia de Arroios - Lisboa\nTelefone: 210027000\nFax: 210027000\nEndereço da Entidade (URL): https://www.inatel.pt\nEndereço Eletrónico: fundacao.inatel@inatel.pt\neDelivery Gateway (URL): https://www.acingov.pt\nFunção da Organização: Adquirente\nSubfunção da Organização: Organização cujo orçamento é utilizado para pagar o contrato; Organização que executa o pagamento; Organização que fornece informações adicionais sobre o processo de adjudicação; Organização que fornece mais informações sobre os prazos dos procedimentos de recurso; Organização que fornece acesso fora de linha aos documentos do concurso; Organização responsável pelo tratamento das propostas; Organização que recebe as propostas; Organização que trata os pedidos de participação; Organização que recebe pedidos de participação; Organização que fornece mais informações sobre os procedimentos de recurso; Organização que assina o contrato\nNorma jurídica da Entidade Adjudicante: Organismo de direito público\nÁrea de atividade da Autoridade Adjudicante: Atividades recreativas, culturais e religiosas\n\n2 - JORNAL OFICIAL DA UNIÃO EUROPEIA\nO procedimento a que este anúncio diz respeito também é publicitado no Jornal Oficial da União Europeia? Não\n\n3 - AVISO\nModelo de Anúncio: Concurso público\nData de Envio do Anúncio: 07-08-2025\n\n5 - PROCESSO\nTipo de Procedimento: Concurso público\nPreço base do procedimento: Sim\nValor do preço base do procedimento: 12.825,85 EUR\nProcedimento com lotes? Sim\nNº Máx. de Lotes Autorizado: 14\nNúmero máximo de lotes que podem ser adjudicados a um concorrente: 14\n\n6 - OBJETO DO CONTRATO\nNúmero de referência interna: P.25.136/NCP\nDesignação do contrato: Aquisição de ervas aromáticas, condimentos e especiarias para as UH e Restaurante de Sant´Ana da Fundação INATEL em Portugal Continental e na Região Autónoma da Madeira\nDescrição: Aquisição de ervas aromáticas, condimentos e especiarias para as UH e Restaurante de Sant´Ana da Fundação INATEL em Portugal Continental e na Região Autónoma da Madeira\nTipo de Contrato Principal: Aquisição de Bens Móveis\nTipo de Contrato: Aquisição de Bens Móveis\nClassificação CPV (Vocabulário Comum para os Contratos Públicos)\nObjeto principal\nVocabulário Principal: 15872000\nPreço base s/IVA: 12.825,85 EUR\nLotes: \nNº: LOT-0001\nDescrição do Lote: Unidade Hoteleira de Vila Nova de Cerveira\nPreço base s/IVA: 1.390,46 EUR\nClassificação CPV (Vocabulário Comum para os Contratos Públicos)\nObjeto principal\nVocabulário Principal: 15872000\nNº: LOT-0002\nDescrição do Lote: Unidade Hoteleira de Santa Maria da Feira\nPreço base s/IVA: 377,68 EUR\nClassificação CPV (Vocabulário Comum para os Contratos Públicos)\nObjeto principal\nVocabulário Principal: 15872000\nNº: LOT-0003\nDescrição do Lote: Unidade Hoteleira do Luso\nPreço base s/IVA: 295,09 EUR\nClassificação CPV (Vocabulário Comum para os Contratos Públicos)\nObjeto principal\nVocabulário Principal: 15872000\nNº: LOT-0004\nDescrição do Lote: Unidade Hoteleira de Vila Ruiva\nPreço base s/IVA: 921,04 EUR\nClassificação CPV (Vocabulário Comum para os Contratos Públicos)\nObjeto principal\nVocabulário Principal: 15872000\nNº: LOT-0005\nDescrição do Lote: Unidade Hoteleira de São Pedro do Sul\nPreço base s/IVA: 666,04 EUR\nClassificação CPV (Vocabulário Comum para os Contratos Públicos)\nObjeto principal\nVocabulário Principal: 15872000\nNº: LOT-0006\nDescrição do Lote: Unidade Hoteleira do Piódão\nPreço base s/IVA: 557,43 EUR\nClassificação CPV (Vocabulário Comum para os Contratos Públicos)\nObjeto principal\nVocabulário Principal: 15872000\nNº: LOT-0007\nDescrição do Lote: Unidade Hoteleira de Manteigas\nPreço base s/IVA: 479,62 EUR\nClassificação CPV (Vocabulário Comum para os Contratos Públicos)\nObjeto principal\nVocabulário Principal: 15872000\nNº: LOT-0008\nDescrição do Lote: Unidade Hoteleira da Foz do Arelho\nPreço base s/IVA: 1.222,71 EUR\nClassificação CPV (Vocabulário Comum para os Contratos Públicos)\nObjeto principal\nVocabulário Principal: 15872000\nNº: LOT-0009\nDescrição do Lote: Unidade Hoteleira de Castelo de Vide\nPreço base s/IVA: 418,17 EUR\nClassificação CPV (Vocabulário Comum para os Contratos Públicos)\nObjeto principal\nVocabulário Principal: 15872000\nNº: LOT-0010\nDescrição do Lote: Unidade Hoteleira de Oeiras\nPreço base s/IVA: 1.392,28 EUR\nClassificação CPV (Vocabulário Comum para os Contratos Públicos)\nObjeto principal\nVocabulário Principal: 15872000\nNº: LOT-0011\nDescrição do Lote: Sede/ Restaurante de Sant´Ana\nPreço base s/IVA: 736,40 EUR\nClassificação CPV (Vocabulário Comum para os Contratos Públicos)\nObjeto principal\nVocabulário Principal: 15872000\nNº: LOT-0012\nDescrição do Lote: Unidade Hoteleira da Costa da Caparica\nPreço base s/IVA: 1.247,34 EUR\nClassificação CPV (Vocabulário Comum para os Contratos Públicos)\nObjeto principal\nVocabulário Principal: 15872000\nNº: LOT-0013\nDescrição do Lote: Unidade Hoteleira de Albufeira\nPreço base s/IVA: 2.145,13 EUR\nClassificação CPV (Vocabulário Comum para os Contratos Públicos)\nObjeto principal\nVocabulário Principal: 15872000\nNº: LOT-0014\nDescrição do Lote: Unidade Hoteleira de Porto Santo/ Madeira\nPreço base s/IVA: 976,46 EUR\nClassificação CPV (Vocabulário Comum para os Contratos Públicos)\nObjeto principal\nVocabulário Principal: 15872000\n\n7 - INDICAÇÕES ADICIONAIS\nO contrato envolve aquisição conjunta (satisfação de várias entidades)? Não\nO contrato é adjudicado por uma central de compras? Não\n\n8 - TÉCNICAS\nO concurso destina-se à celebração de um acordo-quadro? Inexistência de acordo-quadro\nÉ utilizado um leilão eletrónico? Não\nÉ adotada uma fase de negociação? Não\nSistema de Aquisição Dinâmico: Inexistência de sistema de aquisição dinâmico\n\n9 - LOCAL DA EXECUÇÃO DO CONTRATO\nLOCAL DA EXECUÇÃO DO CONTRATO (PROCEDIMENTO)\nPaís: Portugal\nNUT III: PTZZZ\nLocalidade: Lisboa\nDistrito: Todos\nConcelho: Todos\nFreguesia: Todas\nLOCAL DA EXECUÇÃO DO CONTRATO (LOTE)\nIdentificador do Lote: LOT-0001; LOT-0002; LOT-0003; LOT-0004; LOT-0005; LOT-0006; LOT-0007; LOT-0008; LOT-0009; LOT-0010; LOT-0011; LOT-0012; LOT-0013; LOT-0014\nPaís: Portugal\nNUT III: PTZZZ\nLocalidade: Lisboa\nDistrito: Todos\nConcelho: Todos\nFreguesia: Todas\n\n10 - PRAZO DE EXECUÇÃO DO CONTRATO\nIdentificador do Lote: LOT-0001; LOT-0002; LOT-0003; LOT-0004; LOT-0005; LOT-0006; LOT-0007; LOT-0008; LOT-0009; LOT-0010; LOT-0011; LOT-0012; LOT-0013; LOT-0014\nPrazo de execução do contrato: 12 MESES\nPrevisão de renovações: Não\n\n11 - FUNDOS EU\nIdentificador do Lote: LOT-0001; LOT-0002; LOT-0003; LOT-0004; LOT-0005; LOT-0006; LOT-0007; LOT-0008; LOT-0009; LOT-0010; LOT-0011; LOT-0012; LOT-0013; LOT-0014\nTêm fundos EU? Não\n\n12 - DOCUMENTOS DE HABILITAÇÃO\nHabilitação para o exercício da atividade profissional: Não\n\n13 - CONDIÇÕES DE APRESENTAÇÃO\nPlataforma eletrónica utilizada pela entidade adjudicante: ACIN\nURL para Apresentação: https://www.acingov.pt\nAdmissibilidade da apresentação de propostas variantes: Não autorizado\nPrazo para apresentação das propostas: 13-08-2025 23:59\nPrazo durante o qual os concorrentes são obrigados a manter as respetivas propostas: 66 dias a contar do termo do prazo para a apresentação das propostas\nIndicação de Subcontratação na Proposta: Inexistência de indicação de subcontratação\n\n14 - PRESTAÇÃO DE CAUÇÃO\nPrestação de caução: Não\n\n15 - FORNECIMENTO DAS PEÇAS DO CONCURSO, APRESENTAÇÃO DE PEDIDOS DE PARTICIPAÇÃO E APRESENTAÇÃO DAS PROPOSTAS\nLink para acesso às peças do concurso (URL): https://www.acingov.pt/acingovprod/2/zonaPublica/zona_publica_c/donwloadProcedurePiece/OTMyNDQ1\n\n20 - OUTROS REQUISITOS\nIdentificador do Lote: LOT-0001; LOT-0002; LOT-0003; LOT-0004; LOT-0005; LOT-0006; LOT-0007; LOT-0008; LOT-0009; LOT-0010; LOT-0011; LOT-0012; LOT-0013; LOT-0014\nInformação sobre contratos reservados. Aplica-se a contratos reservados (54º-A)? Não\n\n21 - CRITÉRIO DE ADJUDICAÇÃO\nO Critério de adjudicação é diferenciado por lote? Não\nMultifator: Não\nMonofator:\nNome: Preço\n\n24 - CONDIÇÕES DO CONTRATO\nIdentificador do Lote: LOT-0001; LOT-0002; LOT-0003; LOT-0004; LOT-0005; LOT-0006; LOT-0007; LOT-0008; LOT-0009; LOT-0010; LOT-0011; LOT-0012; LOT-0013; LOT-0014\nFaturação Eletrónica: Permitido\nObrigação de Subcontratação:\nCódigo da Obrigação de Subcontratação: Não é aplicável nenhuma obrigação de subcontratação.\n\n25 - COMPRA PÚBLICA ESTRATÉGICA\nCompra Pública Estratégica: Inexistência de contratação pública estratégica\n\n26 - INFORMAÇÕES ADICIONAIS\nIdentificador do Lote: LOT-0001; LOT-0002; LOT-0003; LOT-0004; LOT-0005; LOT-0006; LOT-0007; LOT-0008; LOT-0009; LOT-0010; LOT-0011; LOT-0012; LOT-0013; LOT-0014\nContrato adequado para PME: Não\nCobertura ACP (Acordo dos Contratos Públicos da Organização Mundial do Comércio): Não\n\n27 - IDENTIFICAÇÃO E CONTACTOS DO ÓRGÃO DE RECURSOS ADMINISTRATIVOS\nDesignação: Conselho de Administração\nEndereço: Calçada de Santana, nº 180\nCódigo postal: 1169-062\nLocalidade: Lisboa\nTelefone: 210027000\nFax: 210027000\nEndereço eletrónico: NCP-Procedimentos@inatel.pt\nPrazo de interposição do recurso: 5 dias\n\n28 - IDENTIFICAÇÃO DO(S) AUTOR(ES) DE ANÚNCIO\nNome: Tiago Tenreiro Alves\nCargo: Técnico\n419414797",
    "nipc": "500122237",
    "distrito": "Lisboa",
    "concelho": "Lisboa",
    "freguesia": "Freguesia de Arroios - Lisboa",
    "site": "https://www.inatel.pt",
    "email": "fundacao.inatel@inatel.pt",
    "designacao_contrato": "Aquisição de ervas aromáticas, condimentos e especiarias para as UH e Restaurante de Sant´Ana da Fundação INATEL em Portugal Continental e na Região Autónoma da Madeira",
    "descricao": "Aquisição de ervas aromáticas, condimentos e especiarias para as UH e Restaurante de Sant´Ana da Fundação INATEL em Portugal Continental e na Região Autónoma da Madeira",
    "preco_base": "12.825,85 EUR",
    "prazo_execucao": "12 MESES",
    "prazo_apresentacao_propostas": "13-08-2025 23:59",
    "fundos_eu": "Não",
    "plataforma_eletronica": "ACIN",
    "url_procedimento": "https://www.acingov.pt",
    "autor_nome": "Tiago Tenreiro Alves",
    "autor_cargo": "Técnico"
  },
  {
    "numero_procedimento": "N/A",
    "entidade": "Instituto das Florestas e Conservação da Natureza, IP-RAM",
    "link": "https://diariodarepublica.pt/dr/detalhe/contrato-publico/21359-928294652",
    "detalhes_completos": "1 - IDENTIFICAÇÃO E CONTACTOS DA ENTIDADE ADJUDICANTE\nDesignação da entidade adjudicante: Instituto das Florestas e Conservação da Natureza, IP-RAM\nNIPC: 600086968\nServiço/Órgão/Pessoa de contacto: Conselho Diretivo\nEndereço: ifcn@madeira.gov.pt\nCódigo postal: 9054-505\nLocalidade: Funchal\nPaís: Portugal\nNUT III: PT300\nDistrito: Região Autónoma da Madeira\nConcelho: Todos\nFreguesia: Todas\nTelefone: 291145590\nEndereço da Entidade (URL): https://ifcn.madeira.gov.pt\nEndereço Eletrónico: ifcn@madeira.gov.pt\neDelivery Gateway (URL): https://www.acingov.pt\nFunção da Organização: Adquirente\nNorma jurídica da Entidade Adjudicante: Organismo de direito público\nÁrea de atividade da Autoridade Adjudicante: Serviços públicos das administrações públicas\n\n2 - JORNAL OFICIAL DA UNIÃO EUROPEIA\nO procedimento a que este anúncio diz respeito também é publicitado no Jornal Oficial da União Europeia? Não\n\n3 - AVISO\nModelo de Anúncio: Concurso público\nData de Envio do Anúncio: 07-08-2025\n\n5 - PROCESSO\nTipo de Procedimento: Concurso público\nPreço base do procedimento: Sim\nValor do preço base do procedimento: 66.625,49 EUR\nProcedimento com lotes? Não\n\n6 - OBJETO DO CONTRATO\nNúmero de referência interna: CP/8/2025\nDesignação do contrato: Aquisição de fardamento, artigos complementares e elementos de identificação para o Corpo de Polícia Florestal e Corpo de Vigilantes da Natureza da Região Autónoma da Madeira.\nDescrição: Aquisição de fardamento, artigos complementares e elementos de identificação para o Corpo de Polícia Florestal e Corpo de Vigilantes da Natureza da Região Autónoma da Madeira.\nTipo de Contrato Principal: Aquisição de Bens Móveis\nTipo de Contrato: Aquisição de Bens Móveis\nClassificação CPV (Vocabulário Comum para os Contratos Públicos)\nObjeto principal\nVocabulário Principal: 35811200\nPreço base s/IVA: 66.625,49 EUR\n\n7 - INDICAÇÕES ADICIONAIS\nO contrato envolve aquisição conjunta (satisfação de várias entidades)? Não\nO contrato é adjudicado por uma central de compras? Não\n\n8 - TÉCNICAS\nO concurso destina-se à celebração de um acordo-quadro? Inexistência de acordo-quadro\nÉ utilizado um leilão eletrónico? Não\nÉ adotada uma fase de negociação? Não\nSistema de Aquisição Dinâmico: Inexistência de sistema de aquisição dinâmico\n\n9 - LOCAL DA EXECUÇÃO DO CONTRATO\nLOCAL DA EXECUÇÃO DO CONTRATO (PROCEDIMENTO)\nPaís: Portugal\nNUT III: PT300\nLocalidade: Freguesia de Santa Luzia (Funchal)\nDistrito: Região Autónoma da Madeira\nConcelho: Funchal\nFreguesia: Freguesia de Santa Luzia (Funchal)\n\n10 - PRAZO DE EXECUÇÃO DO CONTRATO\nPrazo de execução do contrato: 90 DIAS\nPrevisão de renovações: Não\n\n11 - FUNDOS EU\nTêm fundos EU? Não\n\n12 - DOCUMENTOS DE HABILITAÇÃO\nHabilitação para o exercício da atividade profissional: Não\n\n13 - CONDIÇÕES DE APRESENTAÇÃO\nPlataforma eletrónica utilizada pela entidade adjudicante: ACIN\nURL para Apresentação: https://www.acingov.pt\nAdmissibilidade da apresentação de propostas variantes: Não autorizado\nPrazo para apresentação das propostas: 17-08-2025 23:59\nPrazo durante o qual os concorrentes são obrigados a manter as respetivas propostas: 66 dias a contar do termo do prazo para a apresentação das propostas\nIndicação de Subcontratação na Proposta: Inexistência de indicação de subcontratação\n\n14 - PRESTAÇÃO DE CAUÇÃO\nPrestação de caução: Não\n\n15 - FORNECIMENTO DAS PEÇAS DO CONCURSO, APRESENTAÇÃO DE PEDIDOS DE PARTICIPAÇÃO E APRESENTAÇÃO DAS PROPOSTAS\nLink para acesso às peças do concurso (URL): https://www.acingov.pt/acingovprod/2/zonaPublica/zona_publica_c/donwloadProcedurePiece/OTI5Mzkz\n\n20 - OUTROS REQUISITOS\nInformação sobre contratos reservados. Aplica-se a contratos reservados (54º-A)? Não\n\n21 - CRITÉRIO DE ADJUDICAÇÃO\nMultifator: Não\nMonofator:\nNome: Preço\n\n24 - CONDIÇÕES DO CONTRATO\nFaturação Eletrónica: Permitido\nObrigação de Subcontratação:\nCódigo da Obrigação de Subcontratação: Não é aplicável nenhuma obrigação de subcontratação.\n\n25 - COMPRA PÚBLICA ESTRATÉGICA\nCompra Pública Estratégica: Inexistência de contratação pública estratégica\n\n26 - INFORMAÇÕES ADICIONAIS\nContrato adequado para PME: Não\nCobertura ACP (Acordo dos Contratos Públicos da Organização Mundial do Comércio): Não\n\n27 - IDENTIFICAÇÃO E CONTACTOS DO ÓRGÃO DE RECURSOS ADMINISTRATIVOS\nDesignação: Secretaria Regional de Turismo, Ambiente e Cultura\nEndereço: Avenida Arriaga, nº 18\nCódigo postal: 9004-519\nLocalidade: Funchal\nTelefone: 291145300\nFax: \nEndereço eletrónico: gabinete.srtac@madeira.gov.pt\nPrazo de interposição do recurso: 5 dias\n\n28 - IDENTIFICAÇÃO DO(S) AUTOR(ES) DE ANÚNCIO\nNome: Duarte Filipe Silva Rodrigues\nCargo: Técnico Superior\n419412844",
    "nipc": "600086968",
    "distrito": "Região Autónoma da Madeira",
    "concelho": "Todos",
    "freguesia": "Todas",
    "site": "https://ifcn.madeira.gov.pt",
    "email": "ifcn@madeira.gov.pt",
    "designacao_contrato": "Aquisição de fardamento, artigos complementares e elementos de identificação para o Corpo de Polícia Florestal e Corpo de Vigilantes da Natureza da Região Autónoma da Madeira.",
    "descricao": "Aquisição de fardamento, artigos complementares e elementos de identificação para o Corpo de Polícia Florestal e Corpo de Vigilantes da Natureza da Região Autónoma da Madeira.",
    "preco_base": "66.625,49 EUR",
    "prazo_execucao": "90 DIAS",
    "prazo_apresentacao_propostas": "17-08-2025 23:59",
    "fundos_eu": "Não",
    "plataforma_eletronica": "ACIN",
    "url_procedimento": "https://www.acingov.pt",
    "autor_nome": "Duarte Filipe Silva Rodrigues",
    "autor_cargo": "Técnico Superior"
  },
  {
    "numero_procedimento": "N/A",
    "entidade": "Município de Serpa",
    "link": "https://diariodarepublica.pt/dr/detalhe/contrato-publico/21361-928294653",
    "detalhes_completos": "1 - IDENTIFICAÇÃO E CONTACTOS DA ENTIDADE ADJUDICANTE\nDesignação da entidade adjudicante: Município de Serpa\nNIPC: 501112049\nServiço/Órgão/Pessoa de contacto: Municipio de Serpa\nEndereço: Praça da República\nCódigo postal: 7830-389\nLocalidade: Serpa\nPaís: Portugal\nNUT III: PT184\nDistrito: Beja\nConcelho: Serpa\nFreguesia: Todas\nTelefone: 284540100\nEndereço da Entidade (URL): https://www.cm-serpa.p\nEndereço Eletrónico: geral@cm-serpa.pt\nFunção da Organização: Adquirente\nNorma jurídica da Entidade Adjudicante: Autoridade local\nÁrea de atividade da Autoridade Adjudicante: Serviços públicos das administrações públicas\n\n2 - JORNAL OFICIAL DA UNIÃO EUROPEIA\nO procedimento a que este anúncio diz respeito também é publicitado no Jornal Oficial da União Europeia? Não\n\n3 - AVISO\nModelo de Anúncio: Concurso público\nData de Envio do Anúncio: 07-08-2025\n\n5 - PROCESSO\nTipo de Procedimento: Concurso público\nPreço base do procedimento: Sim\nValor do preço base do procedimento: 109.400,00 EUR\nProcedimento com lotes? Não\n\n6 - OBJETO DO CONTRATO\nNúmero de referência interna: 139/2025\nDesignação do contrato: Reparação da Central de Asfalto\nDescrição: Reparação da Central de Asfalto\nTipo de Contrato Principal: Aquisição de Bens Móveis\nTipo de Contrato: Aquisição de Bens Móveis; Aquisição de Serviços\nClassificação CPV (Vocabulário Comum para os Contratos Públicos)\nObjeto principal\nVocabulário Principal: 44621200\nPreço base s/IVA: 109.400,00 EUR\n\n7 - INDICAÇÕES ADICIONAIS\nO contrato envolve aquisição conjunta (satisfação de várias entidades)? Não\nO contrato é adjudicado por uma central de compras? Não\n\n8 - TÉCNICAS\nO concurso destina-se à celebração de um acordo-quadro? Inexistência de acordo-quadro\nÉ utilizado um leilão eletrónico? Não\nÉ adotada uma fase de negociação? Não\nSistema de Aquisição Dinâmico: Inexistência de sistema de aquisição dinâmico\n\n9 - LOCAL DA EXECUÇÃO DO CONTRATO\nLOCAL DA EXECUÇÃO DO CONTRATO (PROCEDIMENTO)\nPaís: Portugal\nNUT III: PT184\nLocalidade: serpa\nDistrito: Beja\nConcelho: Serpa\nFreguesia: União das Freguesias de Serpa (Salvador e Santa Maria)\n\n10 - PRAZO DE EXECUÇÃO DO CONTRATO\nPrazo de execução do contrato: 90 DIAS\nPrevisão de renovações: Não\n\n11 - FUNDOS EU\nTêm fundos EU? Não\n\n12 - DOCUMENTOS DE HABILITAÇÃO\nHabilitação para o exercício da atividade profissional: Não\n\n13 - CONDIÇÕES DE APRESENTAÇÃO\nPlataforma eletrónica utilizada pela entidade adjudicante: VORTAL\nURL para Apresentação: https://community.vortal.biz\nAdmissibilidade da apresentação de propostas variantes: Não autorizado\nPrazo para apresentação das propostas: 25-08-2025 17:00\nPrazo durante o qual os concorrentes são obrigados a manter as respetivas propostas: 66 dias a contar do termo do prazo para a apresentação das propostas\nApresentação de Catálogo Eletrónico: Não autorizado\nIndicação de Subcontratação na Proposta: Inexistência de indicação de subcontratação\n\n14 - PRESTAÇÃO DE CAUÇÃO\nPrestação de caução: Não\n\n15 - FORNECIMENTO DAS PEÇAS DO CONCURSO, APRESENTAÇÃO DE PEDIDOS DE PARTICIPAÇÃO E APRESENTAÇÃO DAS PROPOSTAS\nLink para acesso às peças do concurso (URL): https://community.vortal.biz\n\n20 - OUTROS REQUISITOS\nInformação sobre contratos reservados. Aplica-se a contratos reservados (54º-A)? Não\n\n21 - CRITÉRIO DE ADJUDICAÇÃO\nMultifator: Não\nMonofator:\nNome: Preço\n\n24 - CONDIÇÕES DO CONTRATO\nFaturação Eletrónica: Permitido\nObrigação de Subcontratação:\nCódigo da Obrigação de Subcontratação: Não é aplicável nenhuma obrigação de subcontratação.\n\n25 - COMPRA PÚBLICA ESTRATÉGICA\nCompra Pública Estratégica: Inexistência de contratação pública estratégica\n\n26 - INFORMAÇÕES ADICIONAIS\nContrato adequado para PME: Sim\nCobertura ACP (Acordo dos Contratos Públicos da Organização Mundial do Comércio): Não\n\n27 - IDENTIFICAÇÃO E CONTACTOS DO ÓRGÃO DE RECURSOS ADMINISTRATIVOS\nDesignação: Municipio de Serpa\nEndereço: Praça da República\nCódigo postal: 7830-389\nLocalidade: Serpa\nEndereço eletrónico: geral@cm-serpa.pt\n\n28 - IDENTIFICAÇÃO DO(S) AUTOR(ES) DE ANÚNCIO\nNome: Odete Borralho\nCargo: Vice-Presidente\n419395398",
    "nipc": "501112049",
    "distrito": "Beja",
    "concelho": "Serpa",
    "freguesia": "Todas",
    "site": "https://www.cm-serpa.p",
    "email": "geral@cm-serpa.pt",
    "designacao_contrato": "Reparação da Central de Asfalto",
    "descricao": "Reparação da Central de Asfalto",
    "preco_base": "109.400,00 EUR",
    "prazo_execucao": "90 DIAS",
    "prazo_apresentacao_propostas": "25-08-2025 17:00",
    "fundos_eu": "Não",
    "plataforma_eletronica": "VORTAL",
    "url_procedimento": "https://community.vortal.biz",
    "autor_nome": "Odete Borralho",
    "autor_cargo": "Vice-Presidente"
  },
  {
    "numero_procedimento": "N/A",
    "entidade": "Município de Paços de Ferreira",
    "link": "https://diariodarepublica.pt/dr/detalhe/contrato-publico/21365-928294654",
    "detalhes_completos": "1 - IDENTIFICAÇÃO E CONTACTOS DA ENTIDADE ADJUDICANTE\nDesignação da entidade adjudicante: Município de Paços de Ferreira\nNIPC: 502173297\nServiço/Órgão/Pessoa de contacto: Departamento de Organização Administrativa\nEndereço: Praça da República, n.º 46\nCódigo postal: 4590-527\nLocalidade: Paços de Ferreira\nPaís: Portugal\nNUT III: PTZZZ\nDistrito: Todos\nConcelho: Todos\nFreguesia: Todas\nTelefone: 255860700\nFax: 255860734\nEndereço da Entidade (URL): http://www.cm-pacosdeferreira.pt\nEndereço Eletrónico: geral@cm-pacosdeferreira.pt\neDelivery Gateway (URL): https://www.acingov.pt\nFunção da Organização: Adquirente\nNorma jurídica da Entidade Adjudicante: Organismo de direito público\nÁrea de atividade da Autoridade Adjudicante: Serviços públicos das administrações públicas\n\n2 - JORNAL OFICIAL DA UNIÃO EUROPEIA\nO procedimento a que este anúncio diz respeito também é publicitado no Jornal Oficial da União Europeia? Não\n\n3 - AVISO\nModelo de Anúncio: Concurso público\nData de Envio do Anúncio: 07-08-2025\n\n5 - PROCESSO\nTipo de Procedimento: Concurso público\nPreço base do procedimento: Sim\nValor do preço base do procedimento: 96.600,00 EUR\nProcedimento com lotes? Não\n\n6 - OBJETO DO CONTRATO\nNúmero de referência interna: 129/F/2025\nDesignação do contrato: Aquisição de serviços de limpeza de contentores de lixo\nDescrição: Aquisição de serviços de limpeza de contentores de lixo\nTipo de Contrato Principal: Aquisição de Serviços\nTipo de Contrato: Aquisição de Serviços\nClassificação CPV (Vocabulário Comum para os Contratos Públicos)\nObjeto principal\nVocabulário Principal: 90918000\nPreço base s/IVA: 96.600,00 EUR\n\n7 - INDICAÇÕES ADICIONAIS\nO contrato envolve aquisição conjunta (satisfação de várias entidades)? Não\nO contrato é adjudicado por uma central de compras? Não\n\n8 - TÉCNICAS\nO concurso destina-se à celebração de um acordo-quadro? Inexistência de acordo-quadro\nÉ utilizado um leilão eletrónico? Não\nÉ adotada uma fase de negociação? Não\nSistema de Aquisição Dinâmico: Inexistência de sistema de aquisição dinâmico\n\n9 - LOCAL DA EXECUÇÃO DO CONTRATO\nLOCAL DA EXECUÇÃO DO CONTRATO (PROCEDIMENTO)\nPaís: Portugal\nNUT III: PT11C\nLocalidade: Todas\nDistrito: Porto\nConcelho: Paços de Ferreira\nFreguesia: Todas\n\n10 - PRAZO DE EXECUÇÃO DO CONTRATO\nPrazo de execução do contrato: 12 MESES\nPrevisão de renovações: Não\n\n11 - FUNDOS EU\nTêm fundos EU? Não\n\n12 - DOCUMENTOS DE HABILITAÇÃO\nHabilitação para o exercício da atividade profissional: Não\n\n13 - CONDIÇÕES DE APRESENTAÇÃO\nPlataforma eletrónica utilizada pela entidade adjudicante: ACIN\nURL para Apresentação: https://www.acingov.pt\nAdmissibilidade da apresentação de propostas variantes: Não autorizado\nPrazo para apresentação das propostas: 19-08-2025 23:59\nPrazo durante o qual os concorrentes são obrigados a manter as respetivas propostas: 66 dias a contar do termo do prazo para a apresentação das propostas\nIndicação de Subcontratação na Proposta: Inexistência de indicação de subcontratação\n\n14 - PRESTAÇÃO DE CAUÇÃO\nPrestação de caução: Não\n\n15 - FORNECIMENTO DAS PEÇAS DO CONCURSO, APRESENTAÇÃO DE PEDIDOS DE PARTICIPAÇÃO E APRESENTAÇÃO DAS PROPOSTAS\nLink para acesso às peças do concurso (URL): https://www.acingov.pt/acingovprod/2/zonaPublica/zona_publica_c/donwloadProcedurePiece/OTMwNjg4\n\n20 - OUTROS REQUISITOS\nInformação sobre contratos reservados. Aplica-se a contratos reservados (54º-A)? Não\n\n21 - CRITÉRIO DE ADJUDICAÇÃO\nMultifator: Não\nMonofator:\nNome: Preço\n\n24 - CONDIÇÕES DO CONTRATO\nFaturação Eletrónica: Permitido\nObrigação de Subcontratação:\nCódigo da Obrigação de Subcontratação: Não é aplicável nenhuma obrigação de subcontratação.\n\n25 - COMPRA PÚBLICA ESTRATÉGICA\nCompra Pública Estratégica: Inexistência de contratação pública estratégica\n\n26 - INFORMAÇÕES ADICIONAIS\nContrato adequado para PME: Sim\nCobertura ACP (Acordo dos Contratos Públicos da Organização Mundial do Comércio): Não\n\n27 - IDENTIFICAÇÃO E CONTACTOS DO ÓRGÃO DE RECURSOS ADMINISTRATIVOS\nDesignação: Departamento de Organização Administrativa\nEndereço: Praça da República, n.º 46\nCódigo postal: 4590-527\nLocalidade: Paços de Ferreira\nTelefone: 255860700\nFax: \nEndereço eletrónico: geral@cm-pacosdeferreira.pt\nPrazo de interposição do recurso: 5 dias\n\n28 - IDENTIFICAÇÃO DO(S) AUTOR(ES) DE ANÚNCIO\nNome: Paulo Jorge Rodrigues Ferreira\nCargo: Presidente da Câmara Municipal\n419411856",
    "nipc": "502173297",
    "distrito": "Todos",
    "concelho": "Todos",
    "freguesia": "Todas",
    "site": "http://www.cm-pacosdeferreira.pt",
    "email": "geral@cm-pacosdeferreira.pt",
    "designacao_contrato": "Aquisição de serviços de limpeza de contentores de lixo",
    "descricao": "Aquisição de serviços de limpeza de contentores de lixo",
    "preco_base": "96.600,00 EUR",
    "prazo_execucao": "12 MESES",
    "prazo_apresentacao_propostas": "19-08-2025 23:59",
    "fundos_eu": "Não",
    "plataforma_eletronica": "ACIN",
    "url_procedimento": "https://www.acingov.pt",
    "autor_nome": "Paulo Jorge Rodrigues Ferreira",
    "autor_cargo": "Presidente da Câmara Municipal"
  },
  {
    "numero_procedimento": "N/A",
    "entidade": "Municipio de Oliveira de Azeméis",
    "link": "https://diariodarepublica.pt/dr/detalhe/contrato-publico/21370-928294656",
    "detalhes_completos": "1 - IDENTIFICAÇÃO E CONTACTOS DA ENTIDADE ADJUDICANTE\nDesignação da entidade adjudicante: Municipio de Oliveira de Azeméis\nNIPC: 506302970\nServiço/Órgão/Pessoa de contacto: Gabinete de Contratação Pública\nEndereço: Largo da Républica\nCódigo postal: 3720-240\nLocalidade: Oliveira de Azeméis\nPaís: Portugal\nNUT III: PT11A\nDistrito: Aveiro\nConcelho: Oliveira de Azemeis\nFreguesia: União das Freguesias de Oliveira de Azeméis, Santiago de Riba-Ul, Ul, Macinhata da Seixa e Madail\nTelefone: 256600600\nFax: 256600626\nEndereço da Entidade (URL): www.cm-oaz.pt\nEndereço Eletrónico: geral@cm-oaz.pt\neDelivery Gateway (URL): https://www.acingov.pt\nFunção da Organização: Adquirente\nNorma jurídica da Entidade Adjudicante: Organismo de direito público\nÁrea de atividade da Autoridade Adjudicante: Serviços públicos das administrações públicas\n\n2 - JORNAL OFICIAL DA UNIÃO EUROPEIA\nO procedimento a que este anúncio diz respeito também é publicitado no Jornal Oficial da União Europeia? Sim\n\n3 - AVISO\nModelo de Anúncio: Concurso público\nData de Envio do Anúncio: 05-08-2025\n\n5 - PROCESSO\nTipo de Procedimento: Concurso público\nPreço base do procedimento: Sim\nValor do preço base do procedimento: 291.625,00 EUR\nProcedimento com lotes? Sim\nNº Máx. de Lotes Autorizado: 4\nNúmero máximo de lotes que podem ser adjudicados a um concorrente: 4\n\n6 - OBJETO DO CONTRATO\nNúmero de referência interna: CPI/6/2025 (Proc. n.º 29/25)\nDesignação do contrato: Aquisição de contentores com acesso condicionado, de baldes para biorresíduos e de compostores domésticos\nDescrição: Aquisição de contentores com acesso condicionado, de baldes para biorresíduos e de compostores domésticos\nOpções: Não\nTipo de Contrato Principal: Aquisição de Bens Móveis\nTipo de Contrato: Aquisição de Bens Móveis\nClassificação CPV (Vocabulário Comum para os Contratos Públicos)\nObjeto principal\nVocabulário Principal: 44613800\nPreço base s/IVA: 291.625,00 EUR\nLotes: \nNº: LOT-0001\nDescrição do Lote: fornecimento de contentores de superfície para a deposição controlada de biorresíduos, com acesso condicionado\nPreço base s/IVA: 224.500,00 EUR\nClassificação CPV (Vocabulário Comum para os Contratos Públicos)\nObjeto principal\nVocabulário Principal: 44613800\nNº: LOT-0002\nDescrição do Lote: fornecimento de baldes de biorresíduos domésticos de 7L de capacidade\nPreço base s/IVA: 40.000,00 EUR\nClassificação CPV (Vocabulário Comum para os Contratos Públicos)\nObjeto principal\nVocabulário Principal: 44613800\nNº: LOT-0003\nDescrição do Lote: fornecimento de contentores de biorresíduos domésticos de 35L a 50L de capacidade\nPreço base s/IVA: 625,00 EUR\nClassificação CPV (Vocabulário Comum para os Contratos Públicos)\nObjeto principal\nVocabulário Principal: 44613800\nNº: LOT-0004\nDescrição do Lote: fornecimento de compostores domésticos de 280L de capacidade\nPreço base s/IVA: 26.500,00 EUR\nClassificação CPV (Vocabulário Comum para os Contratos Públicos)\nObjeto principal\nVocabulário Principal: 44613800\n\n7 - INDICAÇÕES ADICIONAIS\nO contrato envolve aquisição conjunta (satisfação de várias entidades)? Não\nO contrato é adjudicado por uma central de compras? Não\n\n8 - TÉCNICAS\nO concurso destina-se à celebração de um acordo-quadro? Inexistência de acordo-quadro\nÉ utilizado um leilão eletrónico? Não\nÉ adotada uma fase de negociação? Não\nSistema de Aquisição Dinâmico: Inexistência de sistema de aquisição dinâmico\n\n9 - LOCAL DA EXECUÇÃO DO CONTRATO\nLOCAL DA EXECUÇÃO DO CONTRATO (PROCEDIMENTO)\nPaís: Portugal\nNUT III: PT11A\nLocalidade: Todas\nDistrito: Aveiro\nConcelho: Oliveira de Azemeis\nFreguesia: Todas\nLOCAL DA EXECUÇÃO DO CONTRATO (LOTE)\nIdentificador do Lote: LOT-0001; LOT-0002; LOT-0003; LOT-0004\nPaís: Portugal\nNUT III: PT11A\nLocalidade: Todas\nDistrito: Aveiro\nConcelho: Oliveira de Azemeis\nFreguesia: Todas\n\n10 - PRAZO DE EXECUÇÃO DO CONTRATO\nIdentificador do Lote: LOT-0001\nPrazo de execução do contrato: 24 MESES\nPrevisão de renovações: Não\nIdentificador do Lote: LOT-0002; LOT-0003\nPrazo de execução do contrato: 60 DIAS\nPrevisão de renovações: Não\nIdentificador do Lote: LOT-0004\nPrazo de execução do contrato: 30 DIAS\nPrevisão de renovações: Não\n\n11 - FUNDOS EU\nIdentificador do Lote: LOT-0001; LOT-0002; LOT-0003; LOT-0004\nTêm fundos EU? Não\n\n12 - DOCUMENTOS DE HABILITAÇÃO\nHabilitação para o exercício da atividade profissional: Não\n\n13 - CONDIÇÕES DE APRESENTAÇÃO\nPlataforma eletrónica utilizada pela entidade adjudicante: ACIN\nURL para Apresentação: https://www.acingov.pt\nAdmissibilidade da apresentação de propostas variantes: Não autorizado\nPrazo para apresentação das propostas: 04-09-2025 23:59\nPrazo durante o qual os concorrentes são obrigados a manter as respetivas propostas: 66 dias a contar do termo do prazo para a apresentação das propostas\nApresentação de Catálogo Eletrónico: Não autorizado\nIndicação de Subcontratação na Proposta: Inexistência de indicação de subcontratação\n\n14 - PRESTAÇÃO DE CAUÇÃO\nPrestação de caução: Não\n\n15 - FORNECIMENTO DAS PEÇAS DO CONCURSO, APRESENTAÇÃO DE PEDIDOS DE PARTICIPAÇÃO E APRESENTAÇÃO DAS PROPOSTAS\nLink para acesso às peças do concurso (URL): https://www.acingov.pt/acingovprod/2/zonaPublica/zona_publica_c/donwloadProcedurePiece/OTE5ODE5\n\n20 - OUTROS REQUISITOS\nIdentificador do Lote: LOT-0001; LOT-0002; LOT-0003; LOT-0004\nInformação sobre contratos reservados. Aplica-se a contratos reservados (54º-A)? Não\n\n21 - CRITÉRIO DE ADJUDICAÇÃO\nO Critério de adjudicação é diferenciado por lote? Não\nMultifator: Não\nMonofator:\nNome: Preço\n\n24 - CONDIÇÕES DO CONTRATO\nIdentificador do Lote: LOT-0001; LOT-0002; LOT-0003; LOT-0004\nFaturação Eletrónica: Permitido\nObrigação de Subcontratação:\nCódigo da Obrigação de Subcontratação: Não é aplicável nenhuma obrigação de subcontratação.\n\n25 - COMPRA PÚBLICA ESTRATÉGICA\nCompra Pública Estratégica: Inexistência de contratação pública estratégica\n\n26 - INFORMAÇÕES ADICIONAIS\nIdentificador do Lote: LOT-0001; LOT-0002; LOT-0003; LOT-0004\nContrato adequado para PME: Sim\nCobertura ACP (Acordo dos Contratos Públicos da Organização Mundial do Comércio): Não\n\n27 - IDENTIFICAÇÃO E CONTACTOS DO ÓRGÃO DE RECURSOS ADMINISTRATIVOS\nDesignação: Presidente da Câmara Municipal\nEndereço: Rua António Alegria, n.º 184\nCódigo postal: 3720-234\nLocalidade: Oliveira de Azemeis\nTelefone: 256600600\nFax: \nEndereço eletrónico: presidencia@cm-oaz.pt\n\n28 - IDENTIFICAÇÃO DO(S) AUTOR(ES) DE ANÚNCIO\nNome: Joaquim Jorge Ferreira\nCargo: Presidente da Câmara Municipal\n419403001",
    "nipc": "506302970",
    "distrito": "Aveiro",
    "concelho": "Oliveira de Azemeis",
    "freguesia": "União das Freguesias de Oliveira de Azeméis, Santiago de Riba-Ul, Ul, Macinhata da Seixa e Madail",
    "site": "www.cm-oaz.pt",
    "email": "geral@cm-oaz.pt",
    "designacao_contrato": "Aquisição de contentores com acesso condicionado, de baldes para biorresíduos e de compostores domésticos",
    "descricao": "Aquisição de contentores com acesso condicionado, de baldes para biorresíduos e de compostores domésticos",
    "preco_base": "291.625,00 EUR",
    "prazo_execucao": "24 MESES",
    "prazo_apresentacao_propostas": "04-09-2025 23:59",
    "fundos_eu": "Não",
    "plataforma_eletronica": "ACIN",
    "url_procedimento": "https://www.acingov.pt",
    "autor_nome": "Joaquim Jorge Ferreira",
    "autor_cargo": "Presidente da Câmara Municipal"
  },
  {
    "numero_procedimento": "N/A",
    "entidade": "Município de Ponte da Barca",
    "link": "https://diariodarepublica.pt/dr/detalhe/contrato-publico/21373-928294657",
    "detalhes_completos": "Alteração do Anúncio de procedimento n.º 19821/2025, de 2025-07-24, com o ID 419343898\n\n1 - IDENTIFICAÇÃO E CONTACTOS DA ENTIDADE ADJUDICANTE\nDesignação da entidade adjudicante: Município de Ponte da Barca\nNIPC: 505676770\nEndereço: Praça Dr. António Lacerda\nCódigo postal: 4980-626\nLocalidade: Ponte da Barca\nPaís: Portugal\nNUT III: PT111\nDistrito: Viana do Castelo\nConcelho: Ponte da Barca\nFreguesia: Todas\nTelefone: 258480180\nFax: 258480189\nEndereço da Entidade (URL): www.cmpb.pt\nEndereço Eletrónico: informatica@cmpb.pt\neDelivery Gateway (URL): https://community.vortal.biz/public/\nFunção da Organização: Adquirente\nNorma jurídica da Entidade Adjudicante: Autoridade local\nÁrea de atividade da Autoridade Adjudicante: Serviços públicos das administrações públicas\n\n2 - JORNAL OFICIAL DA UNIÃO EUROPEIA\nO procedimento a que este anúncio diz respeito também é publicitado no Jornal Oficial da União Europeia? Não\n\n3 - AVISO\nModelo de Anúncio: Concurso público\nData de Envio do Anúncio: 07-08-2025\n\n5 - PROCESSO\nTipo de Procedimento: Concurso público\nPreço base do procedimento: Sim\nValor do preço base do procedimento: 748.796,50 EUR\nProcedimento com lotes? Não\n\n6 - OBJETO DO CONTRATO\nNúmero de referência interna: E_18/2025\nDesignação do contrato: Construção de Edifício de Apoio à Praça da República\nDescrição: Construção de Edifício de Apoio à Praça da República\nTipo de Contrato Principal: Empreitada de Obras Públicas\nTipo de Contrato: Empreitada de Obras Públicas\nClassificação CPV (Vocabulário Comum para os Contratos Públicos)\nObjeto principal\nVocabulário Principal: 45210000\nPreço base s/IVA: 748.796,50 EUR\n\n7 - INDICAÇÕES ADICIONAIS\nO contrato envolve aquisição conjunta (satisfação de várias entidades)? Não\nO contrato é adjudicado por uma central de compras? Não\n\n8 - TÉCNICAS\nO concurso destina-se à celebração de um acordo-quadro? Inexistência de acordo-quadro\nÉ utilizado um leilão eletrónico? Não\nÉ adotada uma fase de negociação? Não\nSistema de Aquisição Dinâmico: Inexistência de sistema de aquisição dinâmico\n\n9 - LOCAL DA EXECUÇÃO DO CONTRATO\nLOCAL DA EXECUÇÃO DO CONTRATO (PROCEDIMENTO)\nPaís: Portugal\nNUT III: PTZZZ\nLocalidade: PORTUGAL\nDistrito: Todos\nConcelho: Todos\nFreguesia: Todas\n\n10 - PRAZO DE EXECUÇÃO DO CONTRATO\nPrazo de execução do contrato: 330 DIAS\nPrevisão de renovações: Não\n\n11 - FUNDOS EU\nTêm fundos EU? Não\n\n12 - DOCUMENTOS DE HABILITAÇÃO\nHabilitação para o exercício da atividade profissional: Não\n\n13 - CONDIÇÕES DE APRESENTAÇÃO\nPlataforma eletrónica utilizada pela entidade adjudicante: VORTAL\nURL para Apresentação: https://community.vortal.biz/public/\nAdmissibilidade da apresentação de propostas variantes: Não autorizado\nPrazo para apresentação das propostas: 14-08-2025 23:59\nPrazo durante o qual os concorrentes são obrigados a manter as respetivas propostas: 66 dias a contar do termo do prazo para a apresentação das propostas\nIndicação de Subcontratação na Proposta: Inexistência de indicação de subcontratação\n\n14 - PRESTAÇÃO DE CAUÇÃO\nPrestação de caução: Sim\nPercentagem: 10%\nDescrição da Garantia Exigida: Por depósito em dinheiro ou em títulos emitidos ou garantidos pelo Estado Português à ordem da entidade que for indicada pelo Município de Ponte da Barca ou mediante garantia bancária ou seguro-caução.\n\n15 - FORNECIMENTO DAS PEÇAS DO CONCURSO, APRESENTAÇÃO DE PEDIDOS DE PARTICIPAÇÃO E APRESENTAÇÃO DAS PROPOSTAS\nLink para acesso às peças do concurso (URL): https://community.vortal.biz/Public/public-tender-documents/TVkvSjZ4d0t3c1V4R3pCNGNvVUkrYk9SVkZrM3dwbmNtc3NucU15TEhuNkV2S3hNK0pIczc3eXJMUnE1UmlkZEtFaFlDTTQ3T3V4YWNMak5qUWdORFE9PUhxMmpm\n\n20 - OUTROS REQUISITOS\nInformação sobre contratos reservados. Aplica-se a contratos reservados (54º-A)? Não\n\n21 - CRITÉRIO DE ADJUDICAÇÃO\nMultifator: Sim\nFator: \nNome: Preço\nPonderação: 80%\nSubfatores: Não\nFator: \nNome: Qualidade\nPonderação: 20%\nSubfatores: SimSubfatores: \nNome: Número de anos acima do prazo legal, previsto na alínea a) do nº 2 do artigo 397º do CCP: Q1\nPonderação : 20%; \nNome: Número de anos acima do prazo legal, previsto na alínea b) do nº 2 do artigo 397º do CCP: Q2 \nPonderação : 40%; \nNome: Número de anos acima do prazo legal, previsto na alínea c) do nº 2 do artigo 397º do CCP: Q3\nPonderação : 40%; \n\n24 - CONDIÇÕES DO CONTRATO\nFaturação Eletrónica: Permitido\nObrigação de Subcontratação:\nCódigo da Obrigação de Subcontratação: Não é aplicável nenhuma obrigação de subcontratação.\n\n25 - COMPRA PÚBLICA ESTRATÉGICA\nCompra Pública Estratégica: Inexistência de contratação pública estratégica\n\n26 - INFORMAÇÕES ADICIONAIS\nContrato adequado para PME: Sim\nCobertura ACP (Acordo dos Contratos Públicos da Organização Mundial do Comércio): Não\n\n27 - IDENTIFICAÇÃO E CONTACTOS DO ÓRGÃO DE RECURSOS ADMINISTRATIVOS\nDesignação: Augusto Manuel dos Reis Marinho\nEndereço: Praça Dr. António Lacerda\nCódigo postal: 4980-626\nLocalidade: Ponte da Barca\nTelefone: +351 258480180\nFax: +351 258480189\nEndereço eletrónico: geral@cmpb.pt\n\n28 - IDENTIFICAÇÃO DO(S) AUTOR(ES) DE ANÚNCIO\nNome: Augusto Manuel dos Reis Marinho\nCargo: Presidente da Câmara Municipal\n\n29 - ALTERAÇÃO\nMotivo da Alteração: Anúncio cancelado\nIdentificador da Versão do Anúncio a Alterar: 35628947-accb-4dba-96a1-16e31fcfe733-01\nIdentificador das Secções Alteradas do Anúncio Anterior: Aviso\nDescrição das Alterações: Revogação da decisão de contratar, nos termos dos artigos 79.º e 80.º do Código dos Contratos Públicos, por razões de interesse público superveniente, nomeadamente na necessidade de proceder à correção de documentos essenciais ao procedimento.\nAlteração dos Documentos do Concurso: Não\n419414642",
    "nipc": "505676770",
    "distrito": "Viana do Castelo",
    "concelho": "Ponte da Barca",
    "freguesia": "Todas",
    "site": "www.cmpb.pt",
    "email": "informatica@cmpb.pt",
    "designacao_contrato": "Construção de Edifício de Apoio à Praça da República",
    "descricao": "Construção de Edifício de Apoio à Praça da República",
    "preco_base": "748.796,50 EUR",
    "prazo_execucao": "330 DIAS",
    "prazo_apresentacao_propostas": "14-08-2025 23:59",
    "fundos_eu": "Não",
    "plataforma_eletronica": "VORTAL",
    "url_procedimento": "https://community.vortal.biz/public/",
    "autor_nome": "Augusto Manuel dos Reis Marinho",
    "autor_cargo": "Presidente da Câmara Municipal"
  },
  {
    "numero_procedimento": "N/A",
    "entidade": "Serviços Municipalizados de Água e Saneamento do Município de Paredes - SMAS Paredes",
    "link": "https://diariodarepublica.pt/dr/detalhe/contrato-publico/21375-928294658",
    "detalhes_completos": "1 - IDENTIFICAÇÃO E CONTACTOS DA ENTIDADE ADJUDICANTE\nDesignação da entidade adjudicante: Serviços Municipalizados de Água e Saneamento do Município de Paredes - SMAS Paredes \nNIPC: 600087689\nEndereço: Rua de Timor, 27\nCódigo postal: 4580-015\nLocalidade:  Porto \nPaís: Portugal\nNUT III: PT11A\nDistrito: Porto\nConcelho: Paredes\nFreguesia: Freguesia de Paredes\nTelefone: 255788530\nFax: 255788530\nEndereço Eletrónico: contratacao@smas-paredes.pt\neDelivery Gateway (URL): https://community.vortal.biz/public/\nFunção da Organização: Adquirente\nNorma jurídica da Entidade Adjudicante: Organismo de direito público\nÁrea de atividade da Autoridade Adjudicante: Serviços públicos das administrações públicas\n\n2 - JORNAL OFICIAL DA UNIÃO EUROPEIA\nO procedimento a que este anúncio diz respeito também é publicitado no Jornal Oficial da União Europeia? Não\n\n3 - AVISO\nModelo de Anúncio: Concurso público\nData de Envio do Anúncio: 07-08-2025\n\n5 - PROCESSO\nTipo de Procedimento: Concurso público\nPreço base do procedimento: Sim\nValor do preço base do procedimento: 74.990,00 EUR\nProcedimento com lotes? Não\n\n6 - OBJETO DO CONTRATO\nNúmero de referência interna: PROCESSO Nº SMAS/181/CPN/B/25 – 2025\nDesignação do contrato: Fornecimento Contínuo de massas betuminosas a quente\nDescrição: Fornecimento Contínuo de massas betuminosas a quente\nTipo de Contrato Principal: Aquisição de Bens Móveis\nTipo de Contrato: Aquisição de Bens Móveis\nClassificação CPV (Vocabulário Comum para os Contratos Públicos)\nObjeto principal\nVocabulário Principal: 09241000\nPreço base s/IVA: 74.990,00 EUR\n\n7 - INDICAÇÕES ADICIONAIS\nO contrato envolve aquisição conjunta (satisfação de várias entidades)? Não\nO contrato é adjudicado por uma central de compras? Não\n\n8 - TÉCNICAS\nO concurso destina-se à celebração de um acordo-quadro? Inexistência de acordo-quadro\nÉ utilizado um leilão eletrónico? Não\nÉ adotada uma fase de negociação? Não\nSistema de Aquisição Dinâmico: Inexistência de sistema de aquisição dinâmico\n\n9 - LOCAL DA EXECUÇÃO DO CONTRATO\nLOCAL DA EXECUÇÃO DO CONTRATO (PROCEDIMENTO)\nPaís: Portugal\nNUT III: PT11A\nLocalidade: Porto\nDistrito: Porto\nConcelho: Paredes\nFreguesia: Freguesia de Paredes\n\n10 - PRAZO DE EXECUÇÃO DO CONTRATO\nPrazo de execução do contrato: 3 ANOS\nPrevisão de renovações: Não\n\n11 - FUNDOS EU\nTêm fundos EU? Não\n\n12 - DOCUMENTOS DE HABILITAÇÃO\nHabilitação para o exercício da atividade profissional: Não\n\n13 - CONDIÇÕES DE APRESENTAÇÃO\nPlataforma eletrónica utilizada pela entidade adjudicante: VORTAL\nURL para Apresentação: https://community.vortal.biz/public/\nAdmissibilidade da apresentação de propostas variantes: Não autorizado\nPrazo para apresentação das propostas: 13-08-2025 23:59\nPrazo durante o qual os concorrentes são obrigados a manter as respetivas propostas: 66 dias a contar do termo do prazo para a apresentação das propostas\nIndicação de Subcontratação na Proposta: Inexistência de indicação de subcontratação\n\n14 - PRESTAÇÃO DE CAUÇÃO\nPrestação de caução: Não\n\n15 - FORNECIMENTO DAS PEÇAS DO CONCURSO, APRESENTAÇÃO DE PEDIDOS DE PARTICIPAÇÃO E APRESENTAÇÃO DAS PROPOSTAS\nLink para acesso às peças do concurso (URL): https://community.vortal.biz/Public/public-tender-documents/cGxCb0gzekE0aGorNzVybk1JempmamFUVDFTeUZURW5TYnpHYTllb2szeUhUSmdRM0FsVTVkSFo3Mjc2QjVtaE41dkVCVkhhc3J1MklxWEw0dXM5Y1E9PTdjJlI4\n\n20 - OUTROS REQUISITOS\nInformação sobre contratos reservados. Aplica-se a contratos reservados (54º-A)? Não\n\n21 - CRITÉRIO DE ADJUDICAÇÃO\nMultifator: Não\nMonofator:\nNome: Outros\nOutro nome: Preço\n\n24 - CONDIÇÕES DO CONTRATO\nFaturação Eletrónica: Permitido\nObrigação de Subcontratação:\nCódigo da Obrigação de Subcontratação: Não é aplicável nenhuma obrigação de subcontratação.\n\n25 - COMPRA PÚBLICA ESTRATÉGICA\nCompra Pública Estratégica: Inexistência de contratação pública estratégica\n\n26 - INFORMAÇÕES ADICIONAIS\nContrato adequado para PME: Sim\nCobertura ACP (Acordo dos Contratos Públicos da Organização Mundial do Comércio): Não\n\n27 - IDENTIFICAÇÃO E CONTACTOS DO ÓRGÃO DE RECURSOS ADMINISTRATIVOS\nDesignação: Conselho de Administração\nEndereço: Rua de Timor nº27\nCódigo postal: 4580-015\nLocalidade: Paredes\nTelefone: +351 255788530\nFax: +351 255788530\nEndereço eletrónico: compras@smas-paredes.pt\n\n28 - IDENTIFICAÇÃO DO(S) AUTOR(ES) DE ANÚNCIO\nNome: José Alexandre da Silva Almeida\nCargo: Presidente do Conselho de Administração\n419415403",
    "nipc": "600087689",
    "distrito": "Porto",
    "concelho": "Paredes",
    "freguesia": "Freguesia de Paredes",
    "site": null,
    "email": "contratacao@smas-paredes.pt",
    "designacao_contrato": "Fornecimento Contínuo de massas betuminosas a quente",
    "descricao": "Fornecimento Contínuo de massas betuminosas a quente",
    "preco_base": "74.990,00 EUR",
    "prazo_execucao": "3 ANOS",
    "prazo_apresentacao_propostas": "13-08-2025 23:59",
    "fundos_eu": "Não",
    "plataforma_eletronica": "VORTAL",
    "url_procedimento": "https://community.vortal.biz/public/",
    "autor_nome": "José Alexandre da Silva Almeida",
    "autor_cargo": "Presidente do Conselho de Administração"
  },
  {
    "numero_procedimento": "N/A",
    "entidade": "Serviços de Acção Social da Universidade do Minho",
    "link": "https://diariodarepublica.pt/dr/detalhe/contrato-publico/21381-928294672",
    "detalhes_completos": "1 - IDENTIFICAÇÃO E CONTACTOS DA ENTIDADE ADJUDICANTE\nDesignação da entidade adjudicante: Serviços de Acção Social da Universidade do Minho\nNIPC: 680047360\nEndereço: Campus de Gualtar\nCódigo postal: 4710-057\nLocalidade: Braga\nPaís: Portugal\nNUT III: PT112\nDistrito: Braga\nConcelho: Braga\nFreguesia: Freguesia de Gualtar\nTelefone: 253601450\nFax: 253601451\nEndereço da Entidade (URL): www.sas.uminho.pt\nEndereço Eletrónico: sas@sas.uminho.pt\neDelivery Gateway (URL): https://www.acingov.pt\nFunção da Organização: Adquirente\nNorma jurídica da Entidade Adjudicante: Organismo de direito público\nÁrea de atividade da Autoridade Adjudicante: Serviços públicos das administrações públicas\n\n2 - JORNAL OFICIAL DA UNIÃO EUROPEIA\nO procedimento a que este anúncio diz respeito também é publicitado no Jornal Oficial da União Europeia? Não\n\n3 - AVISO\nModelo de Anúncio: Concurso público\nData de Envio do Anúncio: 08-08-2025\n\n5 - PROCESSO\nTipo de Procedimento: Concurso público\nPreço base do procedimento: Sim\nValor do preço base do procedimento: 107.795,50 EUR\nProcedimento com lotes? Sim\nNº Máx. de Lotes Autorizado: 23\nNúmero máximo de lotes que podem ser adjudicados a um concorrente: 23\n\n6 - OBJETO DO CONTRATO\nNúmero de referência interna: CP 030/2025\nDesignação do contrato: CP 030/2025- Aquisição de peixe congelado, por lotes\nDescrição: CP 030/2025- Aquisição de peixe congelado, por lotes\nTipo de Contrato Principal: Aquisição de Bens Móveis\nTipo de Contrato: Aquisição de Bens Móveis\nClassificação CPV (Vocabulário Comum para os Contratos Públicos)\nObjeto principal\nVocabulário Principal: 03311000\nPreço base s/IVA: 107.795,50 EUR\nLotes: \nNº: LOT-0001\nDescrição do Lote: Postas com gramagens entre 230 e 260gr\nPreço base s/IVA: 3.375,00 EUR\nClassificação CPV (Vocabulário Comum para os Contratos Públicos)\nObjeto principal\nVocabulário Principal: 03311000\nNº: LOT-0002\nDescrição do Lote: Peixe inteiro sem cabeça _ calibre n.º 4\nPreço base s/IVA: 1.936,00 EUR\nClassificação CPV (Vocabulário Comum para os Contratos Públicos)\nObjeto principal\nVocabulário Principal: 03311000\nNº: LOT-0003\nDescrição do Lote: Postas com gramagens entre 130 e 170gr\nPreço base s/IVA: 6.750,00 EUR\nClassificação CPV (Vocabulário Comum para os Contratos Públicos)\nObjeto principal\nVocabulário Principal: 03311000\nNº: LOT-0004\nDescrição do Lote: Tranches com gramagens entre 90 e 110gr\nPreço base s/IVA: 6.587,50 EUR\nClassificação CPV (Vocabulário Comum para os Contratos Públicos)\nObjeto principal\nVocabulário Principal: 03311000\nNº: LOT-0005\nDescrição do Lote: Postas com gramagens entre 230 e 260gr\nPreço base s/IVA: 2.100,00 EUR\nClassificação CPV (Vocabulário Comum para os Contratos Públicos)\nObjeto principal\nVocabulário Principal: 03311000\nNº: LOT-0006\nDescrição do Lote: Filetes com gramagens entre 150 e 180gr\nPreço base s/IVA: 6.050,00 EUR\nClassificação CPV (Vocabulário Comum para os Contratos Públicos)\nObjeto principal\nVocabulário Principal: 03311000\nNº: LOT-0007\nDescrição do Lote: Paloco desfiado\nPreço base s/IVA: 5.865,00 EUR\nClassificação CPV (Vocabulário Comum para os Contratos Públicos)\nObjeto principal\nVocabulário Principal: 03311000\nNº: LOT-0008\nDescrição do Lote: Postas com gramagens entre 150 e 200gr; e sem escama\nPreço base s/IVA: 7.125,00 EUR\nClassificação CPV (Vocabulário Comum para os Contratos Públicos)\nObjeto principal\nVocabulário Principal: 03311000\nNº: LOT-0009\nDescrição do Lote: Peixe inteiro sem cabeça com gramagens entre 1200 e 1500gr\nPreço base s/IVA: 1.540,00 EUR\nClassificação CPV (Vocabulário Comum para os Contratos Públicos)\nObjeto principal\nVocabulário Principal: 03311000\nNº: LOT-0010\nDescrição do Lote: Postas com gramagens entre 160 e 200gr\nPreço base s/IVA: 9.265,00 EUR\nClassificação CPV (Vocabulário Comum para os Contratos Públicos)\nObjeto principal\nVocabulário Principal: 03311000\nNº: LOT-0011\nDescrição do Lote: Postas com gramagens entre 100 e 130gr\nPreço base s/IVA: 1.334,00 EUR\nClassificação CPV (Vocabulário Comum para os Contratos Públicos)\nObjeto principal\nVocabulário Principal: 03311000\nNº: LOT-0012\nDescrição do Lote: Postas com gramagens entre 130 e 170gr\nPreço base s/IVA: 4.759,50 EUR\nClassificação CPV (Vocabulário Comum para os Contratos Públicos)\nObjeto principal\nVocabulário Principal: 03311000\nNº: LOT-0013\nDescrição do Lote: sardinhas tamanho médio, com 20 a 25 unidades por KG\nPreço base s/IVA: 155,50 EUR\nClassificação CPV (Vocabulário Comum para os Contratos Públicos)\nObjeto principal\nVocabulário Principal: 03311000\nNº: LOT-0014\nDescrição do Lote: peças com peso entre 190 gr e 250gr\nPreço base s/IVA: 6.804,00 EUR\nClassificação CPV (Vocabulário Comum para os Contratos Públicos)\nObjeto principal\nVocabulário Principal: 03311000\nNº: LOT-0015\nDescrição do Lote: peças com peso entre 250 gr e 300gr\nPreço base s/IVA: 4.128,50 EUR\nClassificação CPV (Vocabulário Comum para os Contratos Públicos)\nObjeto principal\nVocabulário Principal: 03311000\nNº: LOT-0016\nDescrição do Lote: Calibre 9/13\nPreço base s/IVA: 3.850,00 EUR\nClassificação CPV (Vocabulário Comum para os Contratos Públicos)\nObjeto principal\nVocabulário Principal: 03311000\nNº: LOT-0017\nDescrição do Lote: Migas de bacalhau desfiadas\nPreço base s/IVA: 12.040,00 EUR\nClassificação CPV (Vocabulário Comum para os Contratos Públicos)\nObjeto principal\nVocabulário Principal: 03311000\nNº: LOT-0018\nDescrição do Lote: tentáculos inteiros (com peso igual ou acima de 1KG)\nPreço base s/IVA: 9.504,00 EUR\nClassificação CPV (Vocabulário Comum para os Contratos Públicos)\nObjeto principal\nVocabulário Principal: 03311000\nNº: LOT-0019\nDescrição do Lote: Peixe inteiro com gramagens entre 200 e 300gr\nPreço base s/IVA: 3.420,00 EUR\nClassificação CPV (Vocabulário Comum para os Contratos Públicos)\nObjeto principal\nVocabulário Principal: 03311000\nNº: LOT-0020\nDescrição do Lote: Peixe inteiro com gramagens entre 200 e 300gr\nPreço base s/IVA: 2.494,00 EUR\nClassificação CPV (Vocabulário Comum para os Contratos Públicos)\nObjeto principal\nVocabulário Principal: 03311000\nNº: LOT-0021\nDescrição do Lote: Em filete com gramagens entre 170 e 220gr\nPreço base s/IVA: 4.425,00 EUR\nClassificação CPV (Vocabulário Comum para os Contratos Públicos)\nObjeto principal\nVocabulário Principal: 03311000\nNº: LOT-0022\nDescrição do Lote: Postas com gramagens entre 150 e 200 gr\nPreço base s/IVA: 2.587,50 EUR\nClassificação CPV (Vocabulário Comum para os Contratos Públicos)\nObjeto principal\nVocabulário Principal: 03311000\nNº: LOT-0023\nDescrição do Lote: unidade com gramagem entre 25 e 30 gr\nPreço base s/IVA: 1.700,00 EUR\nClassificação CPV (Vocabulário Comum para os Contratos Públicos)\nObjeto principal\nVocabulário Principal: 03311000\n\n7 - INDICAÇÕES ADICIONAIS\nO contrato envolve aquisição conjunta (satisfação de várias entidades)? Não\nO contrato é adjudicado por uma central de compras? Não\n\n8 - TÉCNICAS\nO concurso destina-se à celebração de um acordo-quadro? Inexistência de acordo-quadro\nÉ utilizado um leilão eletrónico? Não\nÉ adotada uma fase de negociação? Não\nSistema de Aquisição Dinâmico: Inexistência de sistema de aquisição dinâmico\n\n9 - LOCAL DA EXECUÇÃO DO CONTRATO\nLOCAL DA EXECUÇÃO DO CONTRATO (PROCEDIMENTO)\nPaís: Portugal\nNUT III: PT111\nLocalidade: Braga\nDistrito: Braga\nConcelho: Braga\nFreguesia: Todas\nLOCAL DA EXECUÇÃO DO CONTRATO (LOTE)\nIdentificador do Lote: LOT-0001; LOT-0002; LOT-0003; LOT-0004; LOT-0005; LOT-0006; LOT-0007; LOT-0008; LOT-0009; LOT-0010; LOT-0011; LOT-0012; LOT-0013; LOT-0014; LOT-0015; LOT-0016; LOT-0017; LOT-0018; LOT-0019; LOT-0020; LOT-0021; LOT-0022; LOT-0023\nPaís: Portugal\nNUT III: PT111\nLocalidade: Braga\nDistrito: Braga\nConcelho: Braga\nFreguesia: Todas\n\n10 - PRAZO DE EXECUÇÃO DO CONTRATO\nIdentificador do Lote: LOT-0001; LOT-0002; LOT-0003; LOT-0004; LOT-0005; LOT-0006; LOT-0007; LOT-0008; LOT-0009; LOT-0010; LOT-0011; LOT-0012; LOT-0013; LOT-0014; LOT-0015; LOT-0016; LOT-0017; LOT-0018; LOT-0019; LOT-0020; LOT-0021; LOT-0022; LOT-0023\nPrazo de execução do contrato: 6 MESES\nPrevisão de renovações: Não\n\n11 - FUNDOS EU\nIdentificador do Lote: LOT-0001; LOT-0002; LOT-0003; LOT-0004; LOT-0005; LOT-0006; LOT-0007; LOT-0008; LOT-0009; LOT-0010; LOT-0011; LOT-0012; LOT-0013; LOT-0014; LOT-0015; LOT-0016; LOT-0017; LOT-0018; LOT-0019; LOT-0020; LOT-0021; LOT-0022; LOT-0023\nTêm fundos EU? Não\n\n12 - DOCUMENTOS DE HABILITAÇÃO\nHabilitação para o exercício da atividade profissional: Não\n\n13 - CONDIÇÕES DE APRESENTAÇÃO\nPlataforma eletrónica utilizada pela entidade adjudicante: ACIN\nURL para Apresentação: https://www.acingov.pt\nAdmissibilidade da apresentação de propostas variantes: Não autorizado\nPrazo para apresentação das propostas: 31-08-2025 23:59\nPrazo durante o qual os concorrentes são obrigados a manter as respetivas propostas: 66 dias a contar do termo do prazo para a apresentação das propostas\nIndicação de Subcontratação na Proposta: Inexistência de indicação de subcontratação\n\n14 - PRESTAÇÃO DE CAUÇÃO\nPrestação de caução: Não\n\n15 - FORNECIMENTO DAS PEÇAS DO CONCURSO, APRESENTAÇÃO DE PEDIDOS DE PARTICIPAÇÃO E APRESENTAÇÃO DAS PROPOSTAS\nLink para acesso às peças do concurso (URL): https://www.acingov.pt/acingovprod/2/zonaPublica/zona_publica_c/donwloadProcedurePiece/OTMyNTI2\n\n20 - OUTROS REQUISITOS\nIdentificador do Lote: LOT-0001; LOT-0002; LOT-0003; LOT-0004; LOT-0005; LOT-0006; LOT-0007; LOT-0008; LOT-0009; LOT-0010; LOT-0011; LOT-0012; LOT-0013; LOT-0014; LOT-0015; LOT-0016; LOT-0017; LOT-0018; LOT-0019; LOT-0020; LOT-0021; LOT-0022; LOT-0023\nInformação sobre contratos reservados. Aplica-se a contratos reservados (54º-A)? Não\n\n21 - CRITÉRIO DE ADJUDICAÇÃO\nO Critério de adjudicação é diferenciado por lote? Não\nMultifator: Não\nMonofator:\nNome: Preço\n\n24 - CONDIÇÕES DO CONTRATO\nIdentificador do Lote: LOT-0001; LOT-0002; LOT-0003; LOT-0004; LOT-0005; LOT-0006; LOT-0007; LOT-0008; LOT-0009; LOT-0010; LOT-0011; LOT-0012; LOT-0013; LOT-0014; LOT-0015; LOT-0016; LOT-0017; LOT-0018; LOT-0019; LOT-0020; LOT-0021; LOT-0022; LOT-0023\nFaturação Eletrónica: Permitido\nObrigação de Subcontratação:\nCódigo da Obrigação de Subcontratação: Não é aplicável nenhuma obrigação de subcontratação.\n\n25 - COMPRA PÚBLICA ESTRATÉGICA\nCompra Pública Estratégica: Inexistência de contratação pública estratégica\n\n26 - INFORMAÇÕES ADICIONAIS\nIdentificador do Lote: LOT-0001; LOT-0002; LOT-0003; LOT-0004; LOT-0005; LOT-0006; LOT-0007; LOT-0008; LOT-0009; LOT-0010; LOT-0011; LOT-0012; LOT-0013; LOT-0014; LOT-0015; LOT-0016; LOT-0017; LOT-0018; LOT-0019; LOT-0020; LOT-0021; LOT-0022; LOT-0023\nContrato adequado para PME: Não\nCobertura ACP (Acordo dos Contratos Públicos da Organização Mundial do Comércio): Não\n\n27 - IDENTIFICAÇÃO E CONTACTOS DO ÓRGÃO DE RECURSOS ADMINISTRATIVOS\nDesignação: Reitor da Universidade do Minho\nEndereço: Gualtar Braga\nCódigo postal: 4710-057\nLocalidade: Braga\nTelefone: 253601450\nFax: \nEndereço eletrónico: sas@sas.uminho.pt\n\n28 - IDENTIFICAÇÃO DO(S) AUTOR(ES) DE ANÚNCIO\nNome: Paula Alexandra Seixas\nCargo: Administradora SASUM\n419412147",
    "nipc": "680047360",
    "distrito": "Braga",
    "concelho": "Braga",
    "freguesia": "Freguesia de Gualtar",
    "site": "www.sas.uminho.pt",
    "email": "sas@sas.uminho.pt",
    "designacao_contrato": "CP 030/2025- Aquisição de peixe congelado, por lotes",
    "descricao": "CP 030/2025- Aquisição de peixe congelado, por lotes",
    "preco_base": "107.795,50 EUR",
    "prazo_execucao": "6 MESES",
    "prazo_apresentacao_propostas": "31-08-2025 23:59",
    "fundos_eu": "Não",
    "plataforma_eletronica": "ACIN",
    "url_procedimento": "https://www.acingov.pt",
    "autor_nome": "Paula Alexandra Seixas",
    "autor_cargo": "Administradora SASUM"
  },
  {
    "numero_procedimento": "N/A",
    "entidade": "Instituto Nossa Senhora da Encarnação - Cooperativa de Ensino e Cultura, CRL.",
    "link": "https://diariodarepublica.pt/dr/detalhe/contrato-publico/21356-928299388",
    "detalhes_completos": "1 - IDENTIFICAÇÃO E CONTACTOS DA ENTIDADE ADJUDICANTE\nDesignação da entidade adjudicante: Instituto Nossa Senhora da Encarnação - Cooperativa de Ensino e Cultura, CRL.\nNIPC: 500139997\nServiço/Órgão/Pessoa de contacto: 262 925180\nEndereço: Rua do Externato Cooperativo\nCódigo postal: 2475-204\nLocalidade: Benedita\nPaís: Portugal\nNUT III: PT16B\nDistrito: Leiria\nConcelho: Alcobaça\nFreguesia: Freguesia de Benedita\nTelefone: 262925180\nFax: 262925185\nEndereço da Entidade (URL): https://ecbenedita.inse.pt/\nEndereço Eletrónico: ecb@inse.pt\nFunção da Organização: Adquirente\nNorma jurídica da Entidade Adjudicante: Organização que adjudica um contrato subvencionado por uma autoridade adjudicante\nÁrea de atividade da Autoridade Adjudicante: Assuntos económicos\n\n2 - JORNAL OFICIAL DA UNIÃO EUROPEIA\nO procedimento a que este anúncio diz respeito também é publicitado no Jornal Oficial da União Europeia? Não\n\n3 - AVISO\nModelo de Anúncio: Concurso público\nData de Envio do Anúncio: 07-08-2025\n\n5 - PROCESSO\nTipo de Procedimento: Concurso público\nPreço base do procedimento: Sim\nValor do preço base do procedimento: 121.467,06 EUR\nProcedimento com lotes? Não\n\n6 - OBJETO DO CONTRATO\nNúmero de referência interna: 03/2025\nDesignação do contrato: Confeção e Fornecimento de refeições escolares\nDescrição: Confeção e Fornecimento de refeições escolares no Instituto Nossa Senhora da Encarnação\nTipo de Contrato Principal: Aquisição de Serviços\nTipo de Contrato: Aquisição de Serviços\nClassificação CPV (Vocabulário Comum para os Contratos Públicos)\nObjeto principal\nVocabulário Principal: 55520000\nPreço base s/IVA: 121.467,06 EUR\n\n7 - INDICAÇÕES ADICIONAIS\nO contrato envolve aquisição conjunta (satisfação de várias entidades)? Não\nO contrato é adjudicado por uma central de compras? Não\n\n8 - TÉCNICAS\nO concurso destina-se à celebração de um acordo-quadro? Inexistência de acordo-quadro\nÉ utilizado um leilão eletrónico? Não\nÉ adotada uma fase de negociação? Não\nSistema de Aquisição Dinâmico: Inexistência de sistema de aquisição dinâmico\n\n9 - LOCAL DA EXECUÇÃO DO CONTRATO\nLOCAL DA EXECUÇÃO DO CONTRATO (PROCEDIMENTO)\nPaís: Portugal\nNUT III: PT16B\nLocalidade: Benedita\nDistrito: Leiria\nConcelho: Alcobaça\nFreguesia: Freguesia de Benedita\n\n10 - PRAZO DE EXECUÇÃO DO CONTRATO\nData de Início: 01-09-2025\nData de Fim: 31-07-2026\nPrevisão de renovações: Não\n\n11 - FUNDOS EU\nTêm fundos EU? Não\n\n12 - DOCUMENTOS DE HABILITAÇÃO\nHabilitação para o exercício da atividade profissional: Sim\nTipo: Alvará\nDescrição: Licenciamento para fabrico de pratos cozinhados e número veterinário, emitido pelo Ministério da Agricultura do Desenvolvimento Rural e das Pescas ( alínea d) do nº1 do ponto 24º do Programa do Procedimento\n\n13 - CONDIÇÕES DE APRESENTAÇÃO\nPlataforma eletrónica utilizada pela entidade adjudicante: ANOGOV\nURL para Apresentação: https://www.anogov.com/op-inse/faces/\nAdmissibilidade da apresentação de propostas variantes: Não autorizado\nPrazo para apresentação das propostas: 13-08-2025 23:59\nPrazo durante o qual os concorrentes são obrigados a manter as respetivas propostas: 180 dias a contar do termo do prazo para a apresentação das propostas\nApresentação de Catálogo Eletrónico: Permitido\nIndicação de Subcontratação na Proposta: Inexistência de indicação de subcontratação\n\n14 - PRESTAÇÃO DE CAUÇÃO\nPrestação de caução: Não\n\n15 - FORNECIMENTO DAS PEÇAS DO CONCURSO, APRESENTAÇÃO DE PEDIDOS DE PARTICIPAÇÃO E APRESENTAÇÃO DAS PROPOSTAS\nLink para acesso às peças do concurso (URL): https://www.anogov.com/op-inse/faces/app/acessoDocs.jsp?codigoAcesso=C9QmirvJ77hs5XFUPSk9Cer5ey7U6rH2kDYR3ovPEep0FQgcc4\n\n20 - OUTROS REQUISITOS\nInformação sobre contratos reservados. Aplica-se a contratos reservados (54º-A)? Não\n\n21 - CRITÉRIO DE ADJUDICAÇÃO\nMultifator: Sim\nFator: \nNome: Preço\nPonderação: 30%\nSubfatores: Não\nFator: \nNome: Qualidade\nPonderação: 70%\nSubfatores: Não\n\n24 - CONDIÇÕES DO CONTRATO\nFaturação Eletrónica: Permitido\nObrigação de Subcontratação:\nCódigo da Obrigação de Subcontratação: Não é aplicável nenhuma obrigação de subcontratação.\n\n25 - COMPRA PÚBLICA ESTRATÉGICA\nCompra Pública Estratégica: Inexistência de contratação pública estratégica\n\n26 - INFORMAÇÕES ADICIONAIS\nContrato adequado para PME: Não\nCobertura ACP (Acordo dos Contratos Públicos da Organização Mundial do Comércio): Não\n\n27 - IDENTIFICAÇÃO E CONTACTOS DO ÓRGÃO DE RECURSOS ADMINISTRATIVOS\nDesignação: Instituto Nossa Senhora da Encarnação - Externato Cooperativo da Benedita\nEndereço: Rua do Externato\nCódigo postal: 2475-204\nLocalidade: Benedita\nTelefone: 262925180\nFax: 262925185\nEndereço eletrónico: dbarreiro@inse.pt\n\n28 - IDENTIFICAÇÃO DO(S) AUTOR(ES) DE ANÚNCIO\nNome: Nuno Sardinha\nCargo: Presidente conselho de administração\n419414545",
    "nipc": "500139997",
    "distrito": "Leiria",
    "concelho": "Alcobaça",
    "freguesia": "Freguesia de Benedita",
    "site": "https://ecbenedita.inse.pt/",
    "email": "ecb@inse.pt",
    "designacao_contrato": "Confeção e Fornecimento de refeições escolares",
    "descricao": "Confeção e Fornecimento de refeições escolares no Instituto Nossa Senhora da Encarnação",
    "preco_base": "121.467,06 EUR",
    "prazo_execucao": null,
    "prazo_apresentacao_propostas": "13-08-2025 23:59",
    "fundos_eu": "Não",
    "plataforma_eletronica": "ANOGOV",
    "url_procedimento": "https://www.anogov.com/op-inse/faces/",
    "autor_nome": "Nuno Sardinha",
    "autor_cargo": "Presidente conselho de administração"
  },
  {
    "numero_procedimento": "N/A",
    "entidade": "Fundação INATEL",
    "link": "https://diariodarepublica.pt/dr/detalhe/contrato-publico/21357-928299389",
    "detalhes_completos": "1 - IDENTIFICAÇÃO E CONTACTOS DA ENTIDADE ADJUDICANTE\nDesignação da entidade adjudicante: Fundação INATEL\nNIPC: 500122237\nEndereço: Calçada de Santana, nº 180\nCódigo postal: 1169-062\nLocalidade: Lisboa\nPaís: Portugal\nNUT III: PT170\nDistrito: Lisboa\nConcelho: Lisboa\nFreguesia: Freguesia de Arroios - Lisboa\nTelefone: 210027000\nFax: 210027000\nEndereço da Entidade (URL): https://www.inatel.pt\nEndereço Eletrónico: fundacao.inatel@inatel.pt\neDelivery Gateway (URL): https://www.acingov.pt\nFunção da Organização: Adquirente\nSubfunção da Organização: Organização cujo orçamento é utilizado para pagar o contrato; Organização que executa o pagamento; Organização que fornece informações adicionais sobre o processo de adjudicação; Organização que fornece mais informações sobre os prazos dos procedimentos de recurso; Organização que fornece acesso fora de linha aos documentos do concurso; Organização responsável pelo tratamento das propostas; Organização que recebe as propostas; Organização que trata os pedidos de participação; Organização que recebe pedidos de participação; Organização que fornece mais informações sobre os procedimentos de recurso; Organização que assina o contrato\nNorma jurídica da Entidade Adjudicante: Organismo de direito público\nÁrea de atividade da Autoridade Adjudicante: Atividades recreativas, culturais e religiosas\n\n2 - JORNAL OFICIAL DA UNIÃO EUROPEIA\nO procedimento a que este anúncio diz respeito também é publicitado no Jornal Oficial da União Europeia? Não\n\n3 - AVISO\nModelo de Anúncio: Concurso público\nData de Envio do Anúncio: 07-08-2025\n\n5 - PROCESSO\nTipo de Procedimento: Concurso público\nPreço base do procedimento: Sim\nValor do preço base do procedimento: 170.000,00 EUR\nProcedimento com lotes? Não\n\n6 - OBJETO DO CONTRATO\nNúmero de referência interna: P.25.149/NCP\nDesignação do contrato: Aquisição de equipamentos e serviços para reestruturação da CLOUD privada da Fundação INATEL\nDescrição: Aquisição de equipamentos e serviços para reestruturação da CLOUD privada da Fundação INATEL\nTipo de Contrato Principal: Aquisição de Bens Móveis\nTipo de Contrato: Aquisição de Bens Móveis\nClassificação CPV (Vocabulário Comum para os Contratos Públicos)\nObjeto principal\nVocabulário Principal: 48822000\nPreço base s/IVA: 170.000,00 EUR\n\n7 - INDICAÇÕES ADICIONAIS\nO contrato envolve aquisição conjunta (satisfação de várias entidades)? Não\nO contrato é adjudicado por uma central de compras? Não\n\n8 - TÉCNICAS\nO concurso destina-se à celebração de um acordo-quadro? Inexistência de acordo-quadro\nÉ utilizado um leilão eletrónico? Não\nÉ adotada uma fase de negociação? Não\nSistema de Aquisição Dinâmico: Inexistência de sistema de aquisição dinâmico\n\n9 - LOCAL DA EXECUÇÃO DO CONTRATO\nLOCAL DA EXECUÇÃO DO CONTRATO (PROCEDIMENTO)\nPaís: Portugal\nNUT III: PT170\nLocalidade: Freguesia de Arroios - Lisboa\nDistrito: Lisboa\nConcelho: Lisboa\nFreguesia: Freguesia de Arroios - Lisboa\n\n10 - PRAZO DE EXECUÇÃO DO CONTRATO\nPrazo de execução do contrato: 12 MESES\nPrevisão de renovações: Não\n\n11 - FUNDOS EU\nTêm fundos EU? Não\n\n12 - DOCUMENTOS DE HABILITAÇÃO\nHabilitação para o exercício da atividade profissional: Não\n\n13 - CONDIÇÕES DE APRESENTAÇÃO\nPlataforma eletrónica utilizada pela entidade adjudicante: ACIN\nURL para Apresentação: https://www.acingov.pt\nAdmissibilidade da apresentação de propostas variantes: Não autorizado\nPrazo para apresentação das propostas: 19-08-2025 13:59\nPrazo durante o qual os concorrentes são obrigados a manter as respetivas propostas: 66 dias a contar do termo do prazo para a apresentação das propostas\nIndicação de Subcontratação na Proposta: Inexistência de indicação de subcontratação\n\n14 - PRESTAÇÃO DE CAUÇÃO\nPrestação de caução: Não\n\n15 - FORNECIMENTO DAS PEÇAS DO CONCURSO, APRESENTAÇÃO DE PEDIDOS DE PARTICIPAÇÃO E APRESENTAÇÃO DAS PROPOSTAS\nLink para acesso às peças do concurso (URL): https://www.acingov.pt/acingovprod/2/zonaPublica/zona_publica_c/donwloadProcedurePiece/OTMyNTc1\n\n20 - OUTROS REQUISITOS\nInformação sobre contratos reservados. Aplica-se a contratos reservados (54º-A)? Não\n\n21 - CRITÉRIO DE ADJUDICAÇÃO\nMultifator: Não\nMonofator:\nNome: Outros\nOutro nome: Fator Preço\n\n24 - CONDIÇÕES DO CONTRATO\nFaturação Eletrónica: Permitido\nObrigação de Subcontratação:\nCódigo da Obrigação de Subcontratação: Não é aplicável nenhuma obrigação de subcontratação.\n\n25 - COMPRA PÚBLICA ESTRATÉGICA\nCompra Pública Estratégica: Inexistência de contratação pública estratégica\n\n26 - INFORMAÇÕES ADICIONAIS\nContrato adequado para PME: Não\nCobertura ACP (Acordo dos Contratos Públicos da Organização Mundial do Comércio): Não\n\n27 - IDENTIFICAÇÃO E CONTACTOS DO ÓRGÃO DE RECURSOS ADMINISTRATIVOS\nDesignação: Conselho de Administração\nEndereço: Calçada de Sant'Ana, 180\nCódigo postal: 1169-062\nLocalidade: Lisboa\nTelefone: 210027000\nFax: 210027027\nEndereço eletrónico: ncp-procedimentos@inatel.pt\nPrazo de interposição do recurso: 5 dias\n\n28 - IDENTIFICAÇÃO DO(S) AUTOR(ES) DE ANÚNCIO\nNome: Rita Martins Marques Canas\nCargo: Técnico\n419413857",
    "nipc": "500122237",
    "distrito": "Lisboa",
    "concelho": "Lisboa",
    "freguesia": "Freguesia de Arroios - Lisboa",
    "site": "https://www.inatel.pt",
    "email": "fundacao.inatel@inatel.pt",
    "designacao_contrato": "Aquisição de equipamentos e serviços para reestruturação da CLOUD privada da Fundação INATEL",
    "descricao": "Aquisição de equipamentos e serviços para reestruturação da CLOUD privada da Fundação INATEL",
    "preco_base": "170.000,00 EUR",
    "prazo_execucao": "12 MESES",
    "prazo_apresentacao_propostas": "19-08-2025 13:59",
    "fundos_eu": "Não",
    "plataforma_eletronica": "ACIN",
    "url_procedimento": "https://www.acingov.pt",
    "autor_nome": "Rita Martins Marques Canas",
    "autor_cargo": "Técnico"
  },
  {
    "numero_procedimento": "N/A",
    "entidade": "Instituto Hidrográfico",
    "link": "https://diariodarepublica.pt/dr/detalhe/contrato-publico/21360-928299390",
    "detalhes_completos": "Alteração do Anúncio de procedimento n.º 20819/2025, de 2025-08-01, com o ID 419387865\n\n1 - IDENTIFICAÇÃO E CONTACTOS DA ENTIDADE ADJUDICANTE\nDesignação da entidade adjudicante: Instituto Hidrográfico\nNIPC: 501494170\nServiço/Órgão/Pessoa de contacto: CFR AN Paulo Martins Gonçalves\nEndereço: Rua das Trinas, n.º 49\nCódigo postal: 1249-093\nLocalidade: Lisboa\nPaís: Portugal\nNUT III: PT170\nDistrito: Lisboa\nConcelho: Lisboa\nFreguesia: Freguesia da Estrela\nTelefone: 210943270\nFax: 210943277\nEndereço da Entidade (URL): www.hidrografico.pt\nEndereço Eletrónico: administrativo@hidrografico.pt\neDelivery Gateway (URL): https://www.acingov.pt\nFunção da Organização: Adquirente\nNorma jurídica da Entidade Adjudicante: Organismo de direito público\nÁrea de atividade da Autoridade Adjudicante: Serviços públicos das administrações públicas\n\n2 - JORNAL OFICIAL DA UNIÃO EUROPEIA\nO procedimento a que este anúncio diz respeito também é publicitado no Jornal Oficial da União Europeia? Não\n\n3 - AVISO\nModelo de Anúncio: Concurso público\nData de Envio do Anúncio: 07-08-2025\n\n5 - PROCESSO\nTipo de Procedimento: Concurso público\nPreço base do procedimento: Sim\nValor do preço base do procedimento: 22.000,00 EUR\nProcedimento com lotes? Não\n\n6 - OBJETO DO CONTRATO\nNúmero de referência interna: 334/IT/2025\nDesignação do contrato: Aquisição de serviços de reparação da Grua 5T da Base Hidrográfica da Azinheira\nDescrição: Aquisição de serviços de reparação da Grua 5T da Base Hidrográfica da Azinheira\nTipo de Contrato Principal: Aquisição de Serviços\nTipo de Contrato: Aquisição de Serviços\nClassificação CPV (Vocabulário Comum para os Contratos Públicos)\nObjeto principal\nVocabulário Principal: 50800000\nPreço base s/IVA: 22.000,00 EUR\n\n7 - INDICAÇÕES ADICIONAIS\nO contrato envolve aquisição conjunta (satisfação de várias entidades)? Não\nO contrato é adjudicado por uma central de compras? Não\n\n8 - TÉCNICAS\nO concurso destina-se à celebração de um acordo-quadro? Inexistência de acordo-quadro\nÉ utilizado um leilão eletrónico? Não\nÉ adotada uma fase de negociação? Não\nSistema de Aquisição Dinâmico: Inexistência de sistema de aquisição dinâmico\n\n9 - LOCAL DA EXECUÇÃO DO CONTRATO\nLOCAL DA EXECUÇÃO DO CONTRATO (PROCEDIMENTO)\nPaís: Portugal\nNUT III: PT170\nLocalidade: Freguesia da Estrela\nDistrito: Lisboa\nConcelho: Lisboa\nFreguesia: Freguesia da Estrela\n\n10 - PRAZO DE EXECUÇÃO DO CONTRATO\nPrazo de execução do contrato: 90 DIAS\nPrevisão de renovações: Não\n\n11 - FUNDOS EU\nTêm fundos EU? Não\n\n12 - DOCUMENTOS DE HABILITAÇÃO\nHabilitação para o exercício da atividade profissional: Não\n\n13 - CONDIÇÕES DE APRESENTAÇÃO\nPlataforma eletrónica utilizada pela entidade adjudicante: ACIN\nURL para Apresentação: https://www.acingov.pt\nAdmissibilidade da apresentação de propostas variantes: Não autorizado\nPrazo para apresentação das propostas: 31-08-2025 23:59\nPrazo durante o qual os concorrentes são obrigados a manter as respetivas propostas: 66 dias a contar do termo do prazo para a apresentação das propostas\nIndicação de Subcontratação na Proposta: Inexistência de indicação de subcontratação\n\n14 - PRESTAÇÃO DE CAUÇÃO\nPrestação de caução: Não\n\n15 - FORNECIMENTO DAS PEÇAS DO CONCURSO, APRESENTAÇÃO DE PEDIDOS DE PARTICIPAÇÃO E APRESENTAÇÃO DAS PROPOSTAS\nLink para acesso às peças do concurso (URL): https://www.acingov.pt/acingovprod/2/zonaPublica/zona_publica_c/donwloadProcedurePiece/OTA0MTU2\n\n20 - OUTROS REQUISITOS\nInformação sobre contratos reservados. Aplica-se a contratos reservados (54º-A)? Não\n\n21 - CRITÉRIO DE ADJUDICAÇÃO\nMultifator: Não\nMonofator:\nNome: Preço\n\n24 - CONDIÇÕES DO CONTRATO\nFaturação Eletrónica: Necessário\nObrigação de Subcontratação:\nCódigo da Obrigação de Subcontratação: Não é aplicável nenhuma obrigação de subcontratação.\n\n25 - COMPRA PÚBLICA ESTRATÉGICA\nCompra Pública Estratégica: Inexistência de contratação pública estratégica\n\n26 - INFORMAÇÕES ADICIONAIS\nContrato adequado para PME: Não\nCobertura ACP (Acordo dos Contratos Públicos da Organização Mundial do Comércio): Não\n\n27 - IDENTIFICAÇÃO E CONTACTOS DO ÓRGÃO DE RECURSOS ADMINISTRATIVOS\nDesignação: Contra-Almirante João Paulo Ramalho Marreiros\nEndereço: Rua das Trinas, n.º 49\nCódigo postal: 1249-093\nLocalidade: Lisboa\nTelefone: 210943270\nFax: \nEndereço eletrónico: administrativo@hidrografico.pt\n\n28 - IDENTIFICAÇÃO DO(S) AUTOR(ES) DE ANÚNCIO\nNome: Paulo Martins Gonçalves\nCargo: Diretor Financeiro do Instituto Hidrográfico\n\n29 - ALTERAÇÃO\nMotivo da Alteração: Correção pelo adquirente\nIdentificador da Versão do Anúncio a Alterar: efccc90b-53da-4330-a56c-aeacaafc7520-01\nIdentificador das Secções Alteradas do Anúncio Anterior: Condições de Apresentação\nDescrição das Alterações: Modificação do prazo para a apresentação de propostas\nAlteração dos Documentos do Concurso: Não\n419414901",
    "nipc": "501494170",
    "distrito": "Lisboa",
    "concelho": "Lisboa",
    "freguesia": "Freguesia da Estrela",
    "site": "www.hidrografico.pt",
    "email": "administrativo@hidrografico.pt",
    "designacao_contrato": "Aquisição de serviços de reparação da Grua 5T da Base Hidrográfica da Azinheira",
    "descricao": "Aquisição de serviços de reparação da Grua 5T da Base Hidrográfica da Azinheira",
    "preco_base": "22.000,00 EUR",
    "prazo_execucao": "90 DIAS",
    "prazo_apresentacao_propostas": "31-08-2025 23:59",
    "fundos_eu": "Não",
    "plataforma_eletronica": "ACIN",
    "url_procedimento": "https://www.acingov.pt",
    "autor_nome": "Paulo Martins Gonçalves",
    "autor_cargo": "Diretor Financeiro do Instituto Hidrográfico"
  },
  {
    "numero_procedimento": "N/A",
    "entidade": "AML - Area Metropolitana de Lisboa",
    "link": "https://diariodarepublica.pt/dr/detalhe/contrato-publico/21362-928299391",
    "detalhes_completos": "1 - IDENTIFICAÇÃO E CONTACTOS DA ENTIDADE ADJUDICANTE\nDesignação da entidade adjudicante: AML - Area Metropolitana de Lisboa\nNIPC: 502826126\nEndereço: Rua da Cruz de Santa Apolónia\nCódigo postal: 1100-187\nLocalidade: Lisboa\nPaís: Portugal\nNUT III: PT170\nDistrito: Lisboa\nConcelho: Lisboa\nFreguesia: Todas\nTelefone: 218428570\nEndereço da Entidade (URL): https://www.aml.pt/municipios/\nEndereço Eletrónico: amlgeral@aml.pt\neDelivery Gateway (URL): https://community.vortal.biz/public/\nFunção da Organização: Adquirente\nNorma jurídica da Entidade Adjudicante: Organismo de direito público\nÁrea de atividade da Autoridade Adjudicante: Serviços públicos das administrações públicas\n\n2 - JORNAL OFICIAL DA UNIÃO EUROPEIA\nO procedimento a que este anúncio diz respeito também é publicitado no Jornal Oficial da União Europeia? Não\n\n3 - AVISO\nModelo de Anúncio: Concurso público\nData de Envio do Anúncio: 07-08-2025\n\n5 - PROCESSO\nTipo de Procedimento: Concurso público\nPreço base do procedimento: Sim\nValor do preço base do procedimento: 220.977,00 EUR\nProcedimento com lotes? Não\n\n6 - OBJETO DO CONTRATO\nNúmero de referência interna: 01CPN2025\nDesignação do contrato: Aquisição de serviços de Assistência técnica e Manutenção (preventiva e corretiva) e atualização do “Sistema Integrado de Videovigilância e Deteção de Incêndios Rurais na AML”\nDescrição: Aquisição de serviços de Assistência técnica e Manutenção (preventiva e corretiva) e atualização do “Sistema Integrado de Videovigilância e Deteção de Incêndios Rurais na AML”\nTipo de Contrato Principal: Aquisição de Bens Móveis\nTipo de Contrato: Aquisição de Bens Móveis\nClassificação CPV (Vocabulário Comum para os Contratos Públicos)\nObjeto principal\nVocabulário Principal: 32323500\nPreço base s/IVA: 220.977,00 EUR\n\n7 - INDICAÇÕES ADICIONAIS\nO contrato envolve aquisição conjunta (satisfação de várias entidades)? Não\nO contrato é adjudicado por uma central de compras? Não\n\n8 - TÉCNICAS\nO concurso destina-se à celebração de um acordo-quadro? Inexistência de acordo-quadro\nÉ utilizado um leilão eletrónico? Não\nÉ adotada uma fase de negociação? Não\nSistema de Aquisição Dinâmico: Inexistência de sistema de aquisição dinâmico\n\n9 - LOCAL DA EXECUÇÃO DO CONTRATO\nLOCAL DA EXECUÇÃO DO CONTRATO (PROCEDIMENTO)\nPaís: Portugal\nNUT III: PT170\nLocalidade: Lisboa\nDistrito: Lisboa\nConcelho: Lisboa\nFreguesia: Freguesia de São Vicente\n\n10 - PRAZO DE EXECUÇÃO DO CONTRATO\nPrazo de execução do contrato: 66 DIAS\nPrevisão de renovações: Não\n\n11 - FUNDOS EU\nTêm fundos EU? Sim\n\n12 - DOCUMENTOS DE HABILITAÇÃO\nHabilitação para o exercício da atividade profissional: Não\n\n13 - CONDIÇÕES DE APRESENTAÇÃO\nPlataforma eletrónica utilizada pela entidade adjudicante: VORTAL\nURL para Apresentação: https://community.vortal.biz/public/\nAdmissibilidade da apresentação de propostas variantes: Não autorizado\nPrazo para apresentação das propostas: 19-08-2025 23:59\nPrazo durante o qual os concorrentes são obrigados a manter as respetivas propostas: 66 dias a contar do termo do prazo para a apresentação das propostas\nIndicação de Subcontratação na Proposta: Inexistência de indicação de subcontratação\n\n14 - PRESTAÇÃO DE CAUÇÃO\nPrestação de caução: Não\n\n15 - FORNECIMENTO DAS PEÇAS DO CONCURSO, APRESENTAÇÃO DE PEDIDOS DE PARTICIPAÇÃO E APRESENTAÇÃO DAS PROPOSTAS\nLink para acesso às peças do concurso (URL): https://community.vortal.biz/Public/public-tender-documents/VG1jK0lKQXFmTW11ZWhra1hleFNOTUFnQzBmSjJzaVZ5N1R4L1dsOHpNS0c3TEZ4bDE3U212RzZjYk8rQUN2WTdnY2tpWHBGelpTMzl5WVVabVd0VXc9PXRSSWd0\n\n20 - OUTROS REQUISITOS\nInformação sobre contratos reservados. Aplica-se a contratos reservados (54º-A)? Não\n\n21 - CRITÉRIO DE ADJUDICAÇÃO\nMultifator: Sim\nFator: \nNome: Preço\nPonderação: 75%\nSubfatores: Não\nFator: \nNome: Outros\nOutro Nome: Média da pontuação individual obtida no critério “Experiência prévia comprovada dos membros da equipa técnica (que as concorrentes propõem afetar á execução do Contrato) na prestação de serviços subordinados à implementação, manutenção e assistência técnica de Sistemas de Videovigilância de Prevençã\nPonderação: 20%\nSubfatores: Não\nFator: \nNome: Outros\nOutro Nome: Média da pontuação individual obtida no critério “Formações  relevantes frequentadas pelos membros da equipa técnica (que as concorrentes propõem afetar á execução do Contrato) nas 2 (duas) áreas temáticas exigidas” (“F”)\nPonderação: 5%\nSubfatores: Não\n\n24 - CONDIÇÕES DO CONTRATO\nFaturação Eletrónica: Permitido\nObrigação de Subcontratação:\nCódigo da Obrigação de Subcontratação: Não é aplicável nenhuma obrigação de subcontratação.\n\n25 - COMPRA PÚBLICA ESTRATÉGICA\nCompra Pública Estratégica: Inexistência de contratação pública estratégica\n\n26 - INFORMAÇÕES ADICIONAIS\nContrato adequado para PME: Sim\nCobertura ACP (Acordo dos Contratos Públicos da Organização Mundial do Comércio): Não\n\n27 - IDENTIFICAÇÃO E CONTACTOS DO ÓRGÃO DE RECURSOS ADMINISTRATIVOS\nDesignação: Área Metropolitana de Lisboa\nEndereço: Rua Cruz de Santa Apolónia 23, 25 e 25A\nCódigo postal: 1100-187\nLocalidade: Lisboa\nTelefone: +351 218428570\nFax: +351 218428577\nEndereço eletrónico: amlcorreio@aml.pt\n\n28 - IDENTIFICAÇÃO DO(S) AUTOR(ES) DE ANÚNCIO\nNome: Carlos Humberto Palácios Pinheiro de Carvalho\nCargo:  Técnico Superior\n419414278",
    "nipc": "502826126",
    "distrito": "Lisboa",
    "concelho": "Lisboa",
    "freguesia": "Todas",
    "site": "https://www.aml.pt/municipios/",
    "email": "amlgeral@aml.pt",
    "designacao_contrato": "Aquisição de serviços de Assistência técnica e Manutenção (preventiva e corretiva) e atualização do “Sistema Integrado de Videovigilância e Deteção de Incêndios Rurais na AML”",
    "descricao": "Aquisição de serviços de Assistência técnica e Manutenção (preventiva e corretiva) e atualização do “Sistema Integrado de Videovigilância e Deteção de Incêndios Rurais na AML”",
    "preco_base": "220.977,00 EUR",
    "prazo_execucao": "66 DIAS",
    "prazo_apresentacao_propostas": "19-08-2025 23:59",
    "fundos_eu": "Sim",
    "plataforma_eletronica": "VORTAL",
    "url_procedimento": "https://community.vortal.biz/public/",
    "autor_nome": "Carlos Humberto Palácios Pinheiro de Carvalho",
    "autor_cargo": "Técnico Superior"
  },
  {
    "numero_procedimento": "N/A",
    "entidade": "Secretaria-Geral da Presidência da República",
    "link": "https://diariodarepublica.pt/dr/detalhe/contrato-publico/21363-928299392",
    "detalhes_completos": "1 - IDENTIFICAÇÃO E CONTACTOS DA ENTIDADE ADJUDICANTE\nDesignação da entidade adjudicante: Secretaria-Geral da Presidência da República\nNIPC: 600000869\nEndereço: Palácio de Belém, Calçada da Ajuda\nCódigo postal: 1349-022\nLocalidade: Lisboa\nPaís: Portugal\nNUT III: PT170\nDistrito: Lisboa\nConcelho: Lisboa\nFreguesia: Freguesia de Belém\nTelefone: 213614600\nFax: 213625700\nEndereço da Entidade (URL): http://www.presidencia.pt\nEndereço Eletrónico: procedimentos.ccp@presidencia.pt\nFunção da Organização: Adquirente\nNorma jurídica da Entidade Adjudicante: Autoridade da administração central\nÁrea de atividade da Autoridade Adjudicante: Serviços públicos das administrações públicas\n\n2 - JORNAL OFICIAL DA UNIÃO EUROPEIA\nO procedimento a que este anúncio diz respeito também é publicitado no Jornal Oficial da União Europeia? Sim\n\n3 - AVISO\nModelo de Anúncio: Concurso público\nData de Envio do Anúncio: 05-08-2025\n\n5 - PROCESSO\nTipo de Procedimento: Concurso público\nPreço base do procedimento: Sim\nValor do preço base do procedimento: 60.000,00 EUR\nProcedimento com lotes? Não\n\n6 - OBJETO DO CONTRATO\nNúmero de referência interna: CPI.05.DGFP-CP.2025\nDesignação do contrato: Locação de 1 (um) veículo novo, em regime de aluguer operacional de veículos (AOV) e dos respetivos serviços associados, em todo território nacional.\nDescrição: Locação de 1 (um) veículo novo, em regime de aluguer operacional de veículos (AOV)\nOpções: Não\nTipo de Contrato Principal: Aquisição de Bens Móveis\nTipo de Contrato: Aquisição de Bens Móveis\nClassificação CPV (Vocabulário Comum para os Contratos Públicos)\nObjeto principal\nVocabulário Principal: 34110000\nPreço base s/IVA: 60.000,00 EUR\n\n7 - INDICAÇÕES ADICIONAIS\nO contrato envolve aquisição conjunta (satisfação de várias entidades)? Não\nO contrato é adjudicado por uma central de compras? Não\n\n8 - TÉCNICAS\nO concurso destina-se à celebração de um acordo-quadro? Inexistência de acordo-quadro\nÉ utilizado um leilão eletrónico? Não\nÉ adotada uma fase de negociação? Não\nSistema de Aquisição Dinâmico: Inexistência de sistema de aquisição dinâmico\n\n9 - LOCAL DA EXECUÇÃO DO CONTRATO\nLOCAL DA EXECUÇÃO DO CONTRATO (PROCEDIMENTO)\nPaís: Portugal\nNUT III: PT170\nLocalidade: LISBOA\nDistrito: Lisboa\nConcelho: Lisboa\nFreguesia: Freguesia de Belém\n\n10 - PRAZO DE EXECUÇÃO DO CONTRATO\nPrazo de execução do contrato: 1095 DIAS\nPrevisão de renovações: Não\n\n11 - FUNDOS EU\nTêm fundos EU? Não\n\n12 - DOCUMENTOS DE HABILITAÇÃO\nHabilitação para o exercício da atividade profissional: Não\n\n13 - CONDIÇÕES DE APRESENTAÇÃO\nPlataforma eletrónica utilizada pela entidade adjudicante: ANOGOV\nURL para Apresentação: https://www.anogov.com/os-sgpr/faces/\nAdmissibilidade da apresentação de propostas variantes: Não autorizado\nPrazo para apresentação das propostas: 03-09-2025 23:59\nPrazo durante o qual os concorrentes são obrigados a manter as respetivas propostas: 66 dias a contar do termo do prazo para a apresentação das propostas\nApresentação de Catálogo Eletrónico: Permitido\nIndicação de Subcontratação na Proposta: Inexistência de indicação de subcontratação\n\n14 - PRESTAÇÃO DE CAUÇÃO\nPrestação de caução: Sim\nPercentagem: 5%\nDescrição da Garantia Exigida: SEGURO-CAUÇÃO\n\n15 - FORNECIMENTO DAS PEÇAS DO CONCURSO, APRESENTAÇÃO DE PEDIDOS DE PARTICIPAÇÃO E APRESENTAÇÃO DAS PROPOSTAS\nLink para acesso às peças do concurso (URL): https://www.anogov.com/os-sgpr/faces/app/acessoDocs.jsp?codigoAcesso=Kuyk1f78vEIIEEhIsyAJX23yFAn3hwPiZ6gPcxO3af2SRtvs5e\n\n20 - OUTROS REQUISITOS\nInformação sobre contratos reservados. Aplica-se a contratos reservados (54º-A)? Não\n\n21 - CRITÉRIO DE ADJUDICAÇÃO\nMultifator: Não\nMonofator:\nNome: Preço\n\n24 - CONDIÇÕES DO CONTRATO\nFaturação Eletrónica: Permitido\nObrigação de Subcontratação:\nCódigo da Obrigação de Subcontratação: Não é aplicável nenhuma obrigação de subcontratação.\n\n25 - COMPRA PÚBLICA ESTRATÉGICA\nCompra Pública Estratégica: Inexistência de contratação pública estratégica\n\n26 - INFORMAÇÕES ADICIONAIS\nContrato adequado para PME: Não\nCobertura ACP (Acordo dos Contratos Públicos da Organização Mundial do Comércio): Não\n\n27 - IDENTIFICAÇÃO E CONTACTOS DO ÓRGÃO DE RECURSOS ADMINISTRATIVOS\nDesignação: CONSELHO ADMINISTRATIVO\nEndereço: CALÇADA DA AJUDA\nCódigo postal: 1349-022\nLocalidade: LISBOA\nTelefone: +351219614600\nFax: \nEndereço eletrónico: sg@presidencia.pt\nPrazo de interposição do recurso: 5 dias\n\n28 - IDENTIFICAÇÃO DO(S) AUTOR(ES) DE ANÚNCIO\nNome: Tânia Julião\nCargo: Chefe de Divisão de Gestão Financeira e Património\n419403683",
    "nipc": "600000869",
    "distrito": "Lisboa",
    "concelho": "Lisboa",
    "freguesia": "Freguesia de Belém",
    "site": "http://www.presidencia.pt",
    "email": "procedimentos.ccp@presidencia.pt",
    "designacao_contrato": "Locação de 1 (um) veículo novo, em regime de aluguer operacional de veículos (AOV) e dos respetivos serviços associados, em todo território nacional.",
    "descricao": "Locação de 1 (um) veículo novo, em regime de aluguer operacional de veículos (AOV)",
    "preco_base": "60.000,00 EUR",
    "prazo_execucao": "1095 DIAS",
    "prazo_apresentacao_propostas": "03-09-2025 23:59",
    "fundos_eu": "Não",
    "plataforma_eletronica": "ANOGOV",
    "url_procedimento": "https://www.anogov.com/os-sgpr/faces/",
    "autor_nome": "Tânia Julião",
    "autor_cargo": "Chefe de Divisão de Gestão Financeira e Património"
  },
  {
    "numero_procedimento": "N/A",
    "entidade": "Secretaria-Geral da Presidência da República",
    "link": "https://diariodarepublica.pt/dr/detalhe/contrato-publico/21364-928299393",
    "detalhes_completos": "1 - IDENTIFICAÇÃO E CONTACTOS DA ENTIDADE ADJUDICANTE\nDesignação da entidade adjudicante: Secretaria-Geral da Presidência da República\nNIPC: 600000869\nEndereço: Palácio de Belém, Calçada da Ajuda\nCódigo postal: 1349-022\nLocalidade: Lisboa\nPaís: Portugal\nNUT III: PT170\nDistrito: Lisboa\nConcelho: Lisboa\nFreguesia: Freguesia de Belém\nTelefone: 213614600\nFax: 213625700\nEndereço da Entidade (URL): http://www.presidencia.pt\nEndereço Eletrónico: procedimentos.ccp@presidencia.pt\nFunção da Organização: Adquirente\nNorma jurídica da Entidade Adjudicante: Autoridade da administração central\nÁrea de atividade da Autoridade Adjudicante: Serviços públicos das administrações públicas\n\n2 - JORNAL OFICIAL DA UNIÃO EUROPEIA\nO procedimento a que este anúncio diz respeito também é publicitado no Jornal Oficial da União Europeia? Sim\n\n3 - AVISO\nModelo de Anúncio: Concurso público\nData de Envio do Anúncio: 05-08-2025\n\n5 - PROCESSO\nTipo de Procedimento: Concurso público\nPreço base do procedimento: Sim\nValor do preço base do procedimento: 170.000,00 EUR\nProcedimento com lotes? Sim\nNº Máx. de Lotes Autorizado: 3\nNúmero máximo de lotes que podem ser adjudicados a um concorrente: 3\n\n6 - OBJETO DO CONTRATO\nNúmero de referência interna: CPI.04.DGFP-CP.2025\nDesignação do contrato: Substituição de 4 (quatro) veículos automóveis em fim de contrato por novos, da mesma tipologia, em regime de Aluguer Operacional de Veículos (AOV) e dos respetivos serviços associados, em todo o território nacional, sem aumento de frota\nDescrição: Substituição de 4 (quatro) veículos automóveis em fim de contrato por novos\nOpções: Não\nTipo de Contrato Principal: Aquisição de Bens Móveis\nTipo de Contrato: Aquisição de Bens Móveis\nClassificação CPV (Vocabulário Comum para os Contratos Públicos)\nObjeto principal\nVocabulário Principal: 34110000\nPreço base s/IVA: 170.000,00 EUR\nLotes: \nNº: LOT-0001\nDescrição do Lote: Lote 1 - 1 (um) veículos Superior Híbrido Plug-In\nPreço base s/IVA: 60.000,00 EUR\nClassificação CPV (Vocabulário Comum para os Contratos Públicos)\nObjeto principal\nVocabulário Principal: 34110000\nNº: LOT-0002\nDescrição do Lote: Lote 2 - 2 (dois) veículo Médio Híbrido Plug-In\nPreço base s/IVA: 75.000,00 EUR\nClassificação CPV (Vocabulário Comum para os Contratos Públicos)\nObjeto principal\nVocabulário Principal: 34110000\nNº: LOT-0003\nDescrição do Lote: Lote 3 - 1 (um) veículo Inferior Híbrido Plug-In\nPreço base s/IVA: 35.000,00 EUR\nClassificação CPV (Vocabulário Comum para os Contratos Públicos)\nObjeto principal\nVocabulário Principal: 34110000\n\n7 - INDICAÇÕES ADICIONAIS\nO contrato envolve aquisição conjunta (satisfação de várias entidades)? Não\nO contrato é adjudicado por uma central de compras? Não\n\n8 - TÉCNICAS\nO concurso destina-se à celebração de um acordo-quadro? Inexistência de acordo-quadro\nÉ utilizado um leilão eletrónico? Não\nÉ adotada uma fase de negociação? Não\nSistema de Aquisição Dinâmico: Inexistência de sistema de aquisição dinâmico\n\n9 - LOCAL DA EXECUÇÃO DO CONTRATO\nLOCAL DA EXECUÇÃO DO CONTRATO (PROCEDIMENTO)\nLOCAL DA EXECUÇÃO DO CONTRATO (LOTE)\nIdentificador do Lote: LOT-0001\nPaís: Portugal\nNUT III: PT170\nLocalidade: Lisboa\nDistrito: Lisboa\nConcelho: Lisboa\nFreguesia: Freguesia de Belém\nIdentificador do Lote: LOT-0002\nPaís: Portugal\nNUT III: PT170\nLocalidade: Lisboa\nDistrito: Lisboa\nConcelho: Lisboa\nFreguesia: Freguesia de Belém\nIdentificador do Lote: LOT-0003\nPaís: Portugal\nNUT III: PT170\nLocalidade: Lisboa\nDistrito: Lisboa\nConcelho: Lisboa\nFreguesia: Freguesia de Belém\n\n10 - PRAZO DE EXECUÇÃO DO CONTRATO\nIdentificador do Lote: LOT-0001\nPrazo de execução do contrato: 1095 DIAS\nPrevisão de renovações: Não\nIdentificador do Lote: LOT-0002\nPrazo de execução do contrato: 1095 DIAS\nPrevisão de renovações: Não\nIdentificador do Lote: LOT-0003\nPrazo de execução do contrato: 1095 DIAS\nPrevisão de renovações: Não\n\n11 - FUNDOS EU\nIdentificador do Lote: LOT-0001; LOT-0002; LOT-0003\nTêm fundos EU? Não\n\n12 - DOCUMENTOS DE HABILITAÇÃO\nHabilitação para o exercício da atividade profissional: Não\n\n13 - CONDIÇÕES DE APRESENTAÇÃO\nPlataforma eletrónica utilizada pela entidade adjudicante: ANOGOV\nURL para Apresentação: https://www.anogov.com/os-sgpr/faces/\nAdmissibilidade da apresentação de propostas variantes: Não autorizado\nPrazo para apresentação das propostas: 03-09-2025 23:59\nPrazo durante o qual os concorrentes são obrigados a manter as respetivas propostas: 66 dias a contar do termo do prazo para a apresentação das propostas\nApresentação de Catálogo Eletrónico: Permitido\nIndicação de Subcontratação na Proposta: Inexistência de indicação de subcontratação\n\n14 - PRESTAÇÃO DE CAUÇÃO\nPrestação de caução: Sim\nPercentagem: 5%\nDescrição da Garantia Exigida: Seguro-caução\n\n15 - FORNECIMENTO DAS PEÇAS DO CONCURSO, APRESENTAÇÃO DE PEDIDOS DE PARTICIPAÇÃO E APRESENTAÇÃO DAS PROPOSTAS\nLink para acesso às peças do concurso (URL): https://www.anogov.com/os-sgpr/faces/app/acessoDocs.jsp?codigoAcesso=bxS4KhsB3RWIIAOy7ufh1tMX0lxV4QTLiEIf53W8wYjz0EpnxI\n\n20 - OUTROS REQUISITOS\nIdentificador do Lote: LOT-0001; LOT-0002; LOT-0003\nInformação sobre contratos reservados. Aplica-se a contratos reservados (54º-A)? Não\n\n21 - CRITÉRIO DE ADJUDICAÇÃO\nO Critério de adjudicação é diferenciado por lote? Não\nMultifator: Não\nMonofator:\nNome: Preço\n\n24 - CONDIÇÕES DO CONTRATO\nIdentificador do Lote: LOT-0001; LOT-0002; LOT-0003\nFaturação Eletrónica: Permitido\nObrigação de Subcontratação:\nCódigo da Obrigação de Subcontratação: Não é aplicável nenhuma obrigação de subcontratação.\n\n25 - COMPRA PÚBLICA ESTRATÉGICA\nCompra Pública Estratégica: Inexistência de contratação pública estratégica\n\n26 - INFORMAÇÕES ADICIONAIS\nIdentificador do Lote: LOT-0001\nContrato adequado para PME: Sim\nCobertura ACP (Acordo dos Contratos Públicos da Organização Mundial do Comércio): Não\nIdentificador do Lote: LOT-0002\nContrato adequado para PME: Sim\nCobertura ACP (Acordo dos Contratos Públicos da Organização Mundial do Comércio): Não\nIdentificador do Lote: LOT-0003\nContrato adequado para PME: Sim\nCobertura ACP (Acordo dos Contratos Públicos da Organização Mundial do Comércio): Não\n\n27 - IDENTIFICAÇÃO E CONTACTOS DO ÓRGÃO DE RECURSOS ADMINISTRATIVOS\nDesignação: Conselho Administrativo\nEndereço: Calçada da Ajuda\nCódigo postal: 1349-022\nLocalidade: Lisboa\nTelefone: 219614600\nFax: \nEndereço eletrónico: sg@presidencia.pt\nPrazo de interposição do recurso: 5 dias\n\n28 - IDENTIFICAÇÃO DO(S) AUTOR(ES) DE ANÚNCIO\nNome: Tânia Julião\nCargo: Chefe de Divisão de Gestão Financeira e Património\n419403391",
    "nipc": "600000869",
    "distrito": "Lisboa",
    "concelho": "Lisboa",
    "freguesia": "Freguesia de Belém",
    "site": "http://www.presidencia.pt",
    "email": "procedimentos.ccp@presidencia.pt",
    "designacao_contrato": "Substituição de 4 (quatro) veículos automóveis em fim de contrato por novos, da mesma tipologia, em regime de Aluguer Operacional de Veículos (AOV) e dos respetivos serviços associados, em todo o território nacional, sem aumento de frota",
    "descricao": "Substituição de 4 (quatro) veículos automóveis em fim de contrato por novos",
    "preco_base": "170.000,00 EUR",
    "prazo_execucao": "1095 DIAS",
    "prazo_apresentacao_propostas": "03-09-2025 23:59",
    "fundos_eu": "Não",
    "plataforma_eletronica": "ANOGOV",
    "url_procedimento": "https://www.anogov.com/os-sgpr/faces/",
    "autor_nome": "Tânia Julião",
    "autor_cargo": "Chefe de Divisão de Gestão Financeira e Património"
  },
  {
    "numero_procedimento": "N/A",
    "entidade": "Câmara Municipal de Matosinhos",
    "link": "https://diariodarepublica.pt/dr/detalhe/contrato-publico/21366-928299394",
    "detalhes_completos": "1 - IDENTIFICAÇÃO E CONTACTOS DA ENTIDADE ADJUDICANTE\nDesignação da entidade adjudicante: Câmara Municipal de Matosinhos\nNIPC: 501305912\nServiço/Órgão/Pessoa de contacto: Exmo Senhor Vereador\nEndereço: Av. D. Afonso Henriques\nCódigo postal: 4454-510\nLocalidade: Matosinhos\nPaís: Portugal\nNUT III: PT11A\nDistrito: Porto\nConcelho: Matosinhos\nFreguesia: Todas\nTelefone: 229390900\nFax: 229351645\nEndereço da Entidade (URL): http://www.cm-matosinhos.pt\nEndereço Eletrónico: contratacaopublica@cm-matosinhos.pt\neDelivery Gateway (URL): https://www.acingov.pt\nFunção da Organização: Adquirente\nSubfunção da Organização: Organização que recebe as propostas\nNorma jurídica da Entidade Adjudicante: Organismo de direito público\nÁrea de atividade da Autoridade Adjudicante: Serviços públicos das administrações públicas\n\n2 - JORNAL OFICIAL DA UNIÃO EUROPEIA\nO procedimento a que este anúncio diz respeito também é publicitado no Jornal Oficial da União Europeia? Não\n\n3 - AVISO\nModelo de Anúncio: Concurso público\nData de Envio do Anúncio: 07-08-2025\n\n5 - PROCESSO\nTipo de Procedimento: Concurso público\nPreço base do procedimento: Sim\nValor do preço base do procedimento: 90.000,00 EUR\nProcedimento com lotes? Não\n\n6 - OBJETO DO CONTRATO\nNúmero de referência interna: CP/55/2025/12575*1\nDesignação do contrato: PRESTAÇÃO DE SERVIÇOS PARA LAVAGEM E LIMPEZA DE VIATURAS, SEM ÁGUA, DA FROTA AUTOMÓVEL DO MUNICÍPIO 2025/2028\nDescrição: PRESTAÇÃO DE SERVIÇOS PARA LAVAGEM E LIMPEZA DE VIATURAS, SEM ÁGUA, DA FROTA AUTOMÓVEL DO MUNICÍPIO 2025/2028\nTipo de Contrato Principal: Aquisição de Serviços\nTipo de Contrato: Aquisição de Serviços\nClassificação CPV (Vocabulário Comum para os Contratos Públicos)\nObjeto principal\nVocabulário Principal: 50110000\nPreço base s/IVA: 90.000,00 EUR\n\n7 - INDICAÇÕES ADICIONAIS\nO contrato envolve aquisição conjunta (satisfação de várias entidades)? Não\nO contrato é adjudicado por uma central de compras? Não\n\n8 - TÉCNICAS\nO concurso destina-se à celebração de um acordo-quadro? Inexistência de acordo-quadro\nÉ utilizado um leilão eletrónico? Não\nÉ adotada uma fase de negociação? Não\nSistema de Aquisição Dinâmico: Inexistência de sistema de aquisição dinâmico\n\n9 - LOCAL DA EXECUÇÃO DO CONTRATO\nLOCAL DA EXECUÇÃO DO CONTRATO (PROCEDIMENTO)\nPaís: Portugal\nNUT III: PT11A\nLocalidade: Matosinhos\nDistrito: Porto\nConcelho: Matosinhos\nFreguesia: Todas\n\n10 - PRAZO DE EXECUÇÃO DO CONTRATO\nPrazo de execução do contrato: 36 MESES\nPrevisão de renovações: Não\n\n11 - FUNDOS EU\nTêm fundos EU? Não\n\n12 - DOCUMENTOS DE HABILITAÇÃO\nHabilitação para o exercício da atividade profissional: Não\n\n13 - CONDIÇÕES DE APRESENTAÇÃO\nPlataforma eletrónica utilizada pela entidade adjudicante: ACIN\nURL para Apresentação: https://www.acingov.pt\nAdmissibilidade da apresentação de propostas variantes: Não autorizado\nPrazo para apresentação das propostas: 16-08-2025 23:59\nPrazo durante o qual os concorrentes são obrigados a manter as respetivas propostas: 66 dias a contar do termo do prazo para a apresentação das propostas\nIndicação de Subcontratação na Proposta: Inexistência de indicação de subcontratação\n\n14 - PRESTAÇÃO DE CAUÇÃO\nPrestação de caução: Não\n\n15 - FORNECIMENTO DAS PEÇAS DO CONCURSO, APRESENTAÇÃO DE PEDIDOS DE PARTICIPAÇÃO E APRESENTAÇÃO DAS PROPOSTAS\nLink para acesso às peças do concurso (URL): https://www.acingov.pt/acingovprod/2/zonaPublica/zona_publica_c/donwloadProcedurePiece/OTI5NDA3\n\n20 - OUTROS REQUISITOS\nInformação sobre contratos reservados. Aplica-se a contratos reservados (54º-A)? Não\n\n21 - CRITÉRIO DE ADJUDICAÇÃO\nMultifator: Não\nMonofator:\nNome: Outros\nOutro nome: Fator Preço\n\n24 - CONDIÇÕES DO CONTRATO\nFaturação Eletrónica: Não autorizado\nObrigação de Subcontratação:\nCódigo da Obrigação de Subcontratação: Não é aplicável nenhuma obrigação de subcontratação.\n\n25 - COMPRA PÚBLICA ESTRATÉGICA\nCompra Pública Estratégica: Inexistência de contratação pública estratégica\n\n26 - INFORMAÇÕES ADICIONAIS\nContrato adequado para PME: Não\nCobertura ACP (Acordo dos Contratos Públicos da Organização Mundial do Comércio): Não\n\n27 - IDENTIFICAÇÃO E CONTACTOS DO ÓRGÃO DE RECURSOS ADMINISTRATIVOS\nDesignação: Câmara Municipal de Matosinhos\nEndereço: Edifício dos Paços do Concelho de Matosinhos\nCódigo postal: 4454-510\nLocalidade: Matosinhos\nTelefone: 2293909900\nFax: \nEndereço eletrónico: contratacaopublica@cm-matosinhos.pt\nPrazo de interposição do recurso: 5 dias\n\n28 - IDENTIFICAÇÃO DO(S) AUTOR(ES) DE ANÚNCIO\nNome: Luísa Maria Neves Salgueiro\nCargo: Presidente da Câmara\n419406064",
    "nipc": "501305912",
    "distrito": "Porto",
    "concelho": "Matosinhos",
    "freguesia": "Todas",
    "site": "http://www.cm-matosinhos.pt",
    "email": "contratacaopublica@cm-matosinhos.pt",
    "designacao_contrato": "PRESTAÇÃO DE SERVIÇOS PARA LAVAGEM E LIMPEZA DE VIATURAS, SEM ÁGUA, DA FROTA AUTOMÓVEL DO MUNICÍPIO 2025/2028",
    "descricao": "PRESTAÇÃO DE SERVIÇOS PARA LAVAGEM E LIMPEZA DE VIATURAS, SEM ÁGUA, DA FROTA AUTOMÓVEL DO MUNICÍPIO 2025/2028",
    "preco_base": "90.000,00 EUR",
    "prazo_execucao": "36 MESES",
    "prazo_apresentacao_propostas": "16-08-2025 23:59",
    "fundos_eu": "Não",
    "plataforma_eletronica": "ACIN",
    "url_procedimento": "https://www.acingov.pt",
    "autor_nome": "Luísa Maria Neves Salgueiro",
    "autor_cargo": "Presidente da Câmara"
  },
  {
    "numero_procedimento": "N/A",
    "entidade": "Agrupamento de Escolas João de Barros, Seixal",
    "link": "https://diariodarepublica.pt/dr/detalhe/contrato-publico/21367-928299395",
    "detalhes_completos": "Alteração do Anúncio de procedimento n.º 19768/2025, de 2025-07-23, com o ID 419334971\n\n1 - IDENTIFICAÇÃO E CONTACTOS DA ENTIDADE ADJUDICANTE\nDesignação da entidade adjudicante: Agrupamento de Escolas João de Barros, Seixal\nNIPC: 600079422\nEndereço: Rua Mário Castrim, Quinta da Mata\nCódigo postal: 2855-713\nLocalidade: Setúbal\nPaís: Portugal\nNUT III: PT170\nDistrito: Setúbal\nConcelho: Seixal\nFreguesia: Freguesia de Corroios\nTelefone: 212559800\nEndereço da Entidade (URL): https://www.aejoaodebarros.pt/\nEndereço Eletrónico: esb3.joaobarros@escolas.min-edu.pt\neDelivery Gateway (URL): https://community.vortal.biz/public/\nFunção da Organização: Adquirente\nNorma jurídica da Entidade Adjudicante: Organismo de direito público\nÁrea de atividade da Autoridade Adjudicante: Educação\n\n2 - JORNAL OFICIAL DA UNIÃO EUROPEIA\nO procedimento a que este anúncio diz respeito também é publicitado no Jornal Oficial da União Europeia? Sim\n\n3 - AVISO\nModelo de Anúncio: Concurso público\nData de Envio do Anúncio: 05-08-2025\n\n5 - PROCESSO\nTipo de Procedimento: Concurso público\nPreço base do procedimento: Sim\nValor do preço base do procedimento: 1.061.594,59 EUR\nProcedimento com lotes? Sim\nNº Máx. de Lotes Autorizado: 7\nNúmero máximo de lotes que podem ser adjudicados a um concorrente: 7\n\n6 - OBJETO DO CONTRATO\nNúmero de referência interna: CPI01/AEJB/2025\nDesignação do contrato: CPI01/AEJB/2025\nDescrição: Aquisição de Equipamento e Mobiliário no âmbito do Centro Tecnológico Especializado\nOpções: Não\nTipo de Contrato Principal: Aquisição de Bens Móveis\nTipo de Contrato: Aquisição de Bens Móveis\nClassificação CPV (Vocabulário Comum para os Contratos Públicos)\nObjeto principal\nVocabulário Principal: 39150000\nPreço base s/IVA: 1.061.594,59 EUR\nLotes: \nNº: LOT-0001\nDescrição do Lote: Lote 1 - R/V + Gamificação + IA + Softwares diversos\nPreço base s/IVA: 236.999,11 EUR\nClassificação CPV (Vocabulário Comum para os Contratos Públicos)\nObjeto principal\nVocabulário Principal: 39150000\nNº: LOT-0002\nDescrição do Lote: Lote 2 - Drones\nPreço base s/IVA: 103.650,00 EUR\nClassificação CPV (Vocabulário Comum para os Contratos Públicos)\nObjeto principal\nVocabulário Principal: 39150000\nNº: LOT-0003\nDescrição do Lote: Lote 3 - Robótica+ Programação\nPreço base s/IVA: 112.902,47 EUR\nClassificação CPV (Vocabulário Comum para os Contratos Públicos)\nObjeto principal\nVocabulário Principal: 39150000\nNº: LOT-0004\nDescrição do Lote: Lote 4 - Mobiliário\nPreço base s/IVA: 81.436,86 EUR\nClassificação CPV (Vocabulário Comum para os Contratos Públicos)\nObjeto principal\nVocabulário Principal: 39150000\nNº: LOT-0005\nDescrição do Lote: Lote 5 - Ferramentas + Kits eletrónica\nPreço base s/IVA: 362.026,40 EUR\nClassificação CPV (Vocabulário Comum para os Contratos Públicos)\nObjeto principal\nVocabulário Principal: 39150000\nNº: LOT-0006\nDescrição do Lote: Lote 6 - Rede e Sistemas\nPreço base s/IVA: 31.781,96 EUR\nClassificação CPV (Vocabulário Comum para os Contratos Públicos)\nObjeto principal\nVocabulário Principal: 39150000\nNº: LOT-0007\nDescrição do Lote: Lote 7 - Computadores\nPreço base s/IVA: 132.797,79 EUR\nClassificação CPV (Vocabulário Comum para os Contratos Públicos)\nObjeto principal\nVocabulário Principal: 39150000\n\n7 - INDICAÇÕES ADICIONAIS\nO contrato envolve aquisição conjunta (satisfação de várias entidades)? Não\nO contrato é adjudicado por uma central de compras? Não\n\n8 - TÉCNICAS\nO concurso destina-se à celebração de um acordo-quadro? Inexistência de acordo-quadro\nÉ utilizado um leilão eletrónico? Não\nÉ adotada uma fase de negociação? Não\nSistema de Aquisição Dinâmico: Inexistência de sistema de aquisição dinâmico\n\n9 - LOCAL DA EXECUÇÃO DO CONTRATO\nLOCAL DA EXECUÇÃO DO CONTRATO (PROCEDIMENTO)\nPaís: Portugal\nNUT III: PT170\nLocalidade: Setúbal\nDistrito: Setúbal\nConcelho: Seixal\nFreguesia: Todas\nLOCAL DA EXECUÇÃO DO CONTRATO (LOTE)\nIdentificador do Lote: LOT-0001; LOT-0002; LOT-0003; LOT-0004; LOT-0005; LOT-0006; LOT-0007\nPaís: Portugal\nNUT III: PT170\nLocalidade: Setúbal\nDistrito: Setúbal\nConcelho: Seixal\nFreguesia: Todas\n\n10 - PRAZO DE EXECUÇÃO DO CONTRATO\nIdentificador do Lote: LOT-0001; LOT-0002; LOT-0003; LOT-0004; LOT-0005; LOT-0006; LOT-0007\nPrazo de execução do contrato: 5 MESES\nPrevisão de renovações: Não\n\n11 - FUNDOS EU\nIdentificador do Lote: LOT-0001; LOT-0002; LOT-0003; LOT-0004; LOT-0005; LOT-0006; LOT-0007\nTêm fundos EU? Sim\n\n12 - DOCUMENTOS DE HABILITAÇÃO\nHabilitação para o exercício da atividade profissional: Não\n\n13 - CONDIÇÕES DE APRESENTAÇÃO\nPlataforma eletrónica utilizada pela entidade adjudicante: VORTAL\nURL para Apresentação: https://community.vortal.biz/public/\nAdmissibilidade da apresentação de propostas variantes: Não autorizado\nPrazo para apresentação das propostas: 05-09-2025 23:59\nPrazo durante o qual os concorrentes são obrigados a manter as respetivas propostas: 90 dias a contar do termo do prazo para a apresentação das propostas\nApresentação de Catálogo Eletrónico: Permitido\nIndicação de Subcontratação na Proposta: Inexistência de indicação de subcontratação\n\n14 - PRESTAÇÃO DE CAUÇÃO\nPrestação de caução: Sim\nPercentagem: 5%\nDescrição da Garantia Exigida: Garantia Bancária (preferencial)\n\n15 - FORNECIMENTO DAS PEÇAS DO CONCURSO, APRESENTAÇÃO DE PEDIDOS DE PARTICIPAÇÃO E APRESENTAÇÃO DAS PROPOSTAS\nLink para acesso às peças do concurso (URL): https://community.vortal.biz/Public/public-tender-documents/a1dZcEtuZksyZzQzZ2t0c2JmL0dIa1N4WUR5bXliUGgxcHAvNnFwTlpJNmZnSXpuSzUzR1ExUy9Rc1dDN09JWmQrVmljcGR3dzJwa2J6OXJ2ai9mN2c9PTJXVU5F\n\n20 - OUTROS REQUISITOS\nIdentificador do Lote: LOT-0001; LOT-0002; LOT-0003; LOT-0004; LOT-0005; LOT-0006; LOT-0007\nInformação sobre contratos reservados. Aplica-se a contratos reservados (54º-A)? Não\n\n21 - CRITÉRIO DE ADJUDICAÇÃO\nO Critério de adjudicação é diferenciado por lote? Sim\nIdentificador do lote: LOT-0001\nMultifator: Sim\nFator: \nNome: Preço\nPonderação: 60%\nSubfatores: Não\nFator: \nNome: Qualidade\nPonderação: 40%\nSubfatores: Não\nO Critério de adjudicação é diferenciado por lote? Sim\nIdentificador do lote: LOT-0002\nMultifator: Sim\nFator: \nNome: Preço\nPonderação: 60%\nSubfatores: Não\nFator: \nNome: Qualidade\nPonderação: 40%\nSubfatores: Não\nO Critério de adjudicação é diferenciado por lote? Sim\nIdentificador do lote: LOT-0003\nMultifator: Sim\nFator: \nNome: Preço\nPonderação: 60%\nSubfatores: Não\nFator: \nNome: Qualidade\nPonderação: 40%\nSubfatores: Não\nO Critério de adjudicação é diferenciado por lote? Sim\nIdentificador do lote: LOT-0004\nMultifator: Não\nMonofator:\nNome: Preço\nO Critério de adjudicação é diferenciado por lote? Sim\nIdentificador do lote: LOT-0005\nMultifator: Não\nMonofator:\nNome: Preço\nO Critério de adjudicação é diferenciado por lote? Sim\nIdentificador do lote: LOT-0006\nMultifator: Não\nMonofator:\nNome: Preço\nO Critério de adjudicação é diferenciado por lote? Sim\nIdentificador do lote: LOT-0007\nMultifator: Não\nMonofator:\nNome: Preço\n\n24 - CONDIÇÕES DO CONTRATO\nIdentificador do Lote: LOT-0001; LOT-0002; LOT-0003; LOT-0004; LOT-0005; LOT-0006; LOT-0007\nFaturação Eletrónica: Permitido\nObrigação de Subcontratação:\nCódigo da Obrigação de Subcontratação: Não é aplicável nenhuma obrigação de subcontratação.\n\n25 - COMPRA PÚBLICA ESTRATÉGICA\nCompra Pública Estratégica: Inexistência de contratação pública estratégica\n\n26 - INFORMAÇÕES ADICIONAIS\nIdentificador do Lote: LOT-0001; LOT-0002; LOT-0003; LOT-0004; LOT-0005; LOT-0006; LOT-0007\nContrato adequado para PME: Sim\nCobertura ACP (Acordo dos Contratos Públicos da Organização Mundial do Comércio): Não\n\n27 - IDENTIFICAÇÃO E CONTACTOS DO ÓRGÃO DE RECURSOS ADMINISTRATIVOS\nDesignação: Conselho Administrativo\nEndereço: Rua Mário Castrim, Quinta da Mata\nCódigo postal: 2855-713\nLocalidade: Seixal\nTelefone: +351 212559800\nFax: +351 212559800\nEndereço eletrónico: direcao@aejoaodebarros.pt\n\n28 - IDENTIFICAÇÃO DO(S) AUTOR(ES) DE ANÚNCIO\nNome: António Manuel de Almeida Carvalho\nCargo: Diretor\n\n29 - ALTERAÇÃO\nMotivo da Alteração: Correção pelo adquirente\nIdentificador da Versão do Anúncio a Alterar: 7333a80f-1518-4133-8811-ef7694e3b0ee-01\nIdentificador das Secções Alteradas do Anúncio Anterior: Alteração\nDescrição das Alterações: Melhoria das descrições técnicas, juntamente com prorrogação do prazo de apresentação de propostas até 05/09/2025 23h59\nAlteração dos Documentos do Concurso: Sim\nData de alteração dos documentos do concurso: 05-08-2025\n419404622",
    "nipc": "600079422",
    "distrito": "Setúbal",
    "concelho": "Seixal",
    "freguesia": "Freguesia de Corroios",
    "site": "https://www.aejoaodebarros.pt/",
    "email": "esb3.joaobarros@escolas.min-edu.pt",
    "designacao_contrato": "CPI01/AEJB/2025",
    "descricao": "Aquisição de Equipamento e Mobiliário no âmbito do Centro Tecnológico Especializado",
    "preco_base": "1.061.594,59 EUR",
    "prazo_execucao": "5 MESES",
    "prazo_apresentacao_propostas": "05-09-2025 23:59",
    "fundos_eu": "Sim",
    "plataforma_eletronica": "VORTAL",
    "url_procedimento": "https://community.vortal.biz/public/",
    "autor_nome": "António Manuel de Almeida Carvalho",
    "autor_cargo": "Diretor"
  },
  {
    "numero_procedimento": "N/A",
    "entidade": "Município das Lajes do Pico",
    "link": "https://diariodarepublica.pt/dr/detalhe/contrato-publico/21368-928299396",
    "detalhes_completos": "1 - IDENTIFICAÇÃO E CONTACTOS DA ENTIDADE ADJUDICANTE\nDesignação da entidade adjudicante: Município das Lajes do Pico\nNIPC: 512074143\nServiço/Órgão/Pessoa de contacto: Setor de Aprovisionamento/Contratação Pública\nEndereço: Rua de São Francisco\nCódigo postal: 9930-135\nLocalidade: Lajes do Pico\nPaís: Portugal\nNUT III: PT200\nDistrito: Região Autónoma dos Açores\nConcelho: Lajes do Pico\nFreguesia: Freguesia de Lajes do Pico\nTelefone: 292679700\nEndereço da Entidade (URL): http://cm-lajesdopico.pt/\nEndereço Eletrónico: aprovisionamento.cmlp@gmail.com\neDelivery Gateway (URL): https://www.acingov.pt\nFunção da Organização: Adquirente\nNorma jurídica da Entidade Adjudicante: Organismo de direito público\nÁrea de atividade da Autoridade Adjudicante: Serviços públicos das administrações públicas\n\n2 - JORNAL OFICIAL DA UNIÃO EUROPEIA\nO procedimento a que este anúncio diz respeito também é publicitado no Jornal Oficial da União Europeia? Não\n\n3 - AVISO\nModelo de Anúncio: Concurso público\nData de Envio do Anúncio: 07-08-2025\n\n5 - PROCESSO\nTipo de Procedimento: Concurso público\nPreço base do procedimento: Sim\nValor do preço base do procedimento: 81.600,00 EUR\nProcedimento com lotes? Sim\nNº Máx. de Lotes Autorizado: 2\nNúmero máximo de lotes que podem ser adjudicados a um concorrente: 2\n\n6 - OBJETO DO CONTRATO\nNúmero de referência interna: CP/16/CMLP/2025\nDesignação do contrato: Contratação de Aluguer Operacional de Duas Viaturas Ligeiras de Mercadoria para a Câmara Municipal das Lajes do Pico\nDescrição: Contratação de Aluguer Operacional de Duas Viaturas Ligeiras de Mercadoria para a Câmara Municipal das Lajes do Pico\nTipo de Contrato Principal: Locação de Bens Móveis\nTipo de Contrato: Locação de Bens Móveis\nClassificação CPV (Vocabulário Comum para os Contratos Públicos)\nObjeto principal\nVocabulário Principal: 34130000\nPreço base s/IVA: 81.600,00 EUR\nLotes: \nNº: LOT-0001\nDescrição do Lote: Viatura Comercial de 3 lugares com cabine fechada\nPreço base s/IVA: 31.200,00 EUR\nClassificação CPV (Vocabulário Comum para os Contratos Públicos)\nObjeto principal\nVocabulário Principal: 34130000\nNº: LOT-0002\nDescrição do Lote: Viatura 4x4 de 5 pessoas com caixa aberta de madeira\nPreço base s/IVA: 50.400,00 EUR\nClassificação CPV (Vocabulário Comum para os Contratos Públicos)\nObjeto principal\nVocabulário Principal: 34130000\n\n7 - INDICAÇÕES ADICIONAIS\nO contrato envolve aquisição conjunta (satisfação de várias entidades)? Não\nO contrato é adjudicado por uma central de compras? Não\n\n8 - TÉCNICAS\nO concurso destina-se à celebração de um acordo-quadro? Inexistência de acordo-quadro\nÉ utilizado um leilão eletrónico? Não\nÉ adotada uma fase de negociação? Não\nSistema de Aquisição Dinâmico: Inexistência de sistema de aquisição dinâmico\n\n9 - LOCAL DA EXECUÇÃO DO CONTRATO\nLOCAL DA EXECUÇÃO DO CONTRATO (PROCEDIMENTO)\nPaís: Portugal\nNUT III: PT200\nLocalidade: Freguesia de Lajes do Pico\nDistrito: Região Autónoma dos Açores\nConcelho: Lajes do Pico\nFreguesia: Freguesia de Lajes do Pico\nLOCAL DA EXECUÇÃO DO CONTRATO (LOTE)\nIdentificador do Lote: LOT-0001; LOT-0002\nPaís: Portugal\nNUT III: PT200\nLocalidade: Freguesia de Lajes do Pico\nDistrito: Região Autónoma dos Açores\nConcelho: Lajes do Pico\nFreguesia: Freguesia de Lajes do Pico\n\n10 - PRAZO DE EXECUÇÃO DO CONTRATO\nIdentificador do Lote: LOT-0001; LOT-0002\nPrazo de execução do contrato: 48 MESES\nPrevisão de renovações: Não\n\n11 - FUNDOS EU\nIdentificador do Lote: LOT-0001; LOT-0002\nTêm fundos EU? Não\n\n12 - DOCUMENTOS DE HABILITAÇÃO\nHabilitação para o exercício da atividade profissional: Não\n\n13 - CONDIÇÕES DE APRESENTAÇÃO\nPlataforma eletrónica utilizada pela entidade adjudicante: ACIN\nURL para Apresentação: https://www.acingov.pt\nAdmissibilidade da apresentação de propostas variantes: Não autorizado\nPrazo para apresentação das propostas: 22-08-2025 23:59\nPrazo durante o qual os concorrentes são obrigados a manter as respetivas propostas: 66 dias a contar do termo do prazo para a apresentação das propostas\nIndicação de Subcontratação na Proposta: Inexistência de indicação de subcontratação\n\n14 - PRESTAÇÃO DE CAUÇÃO\nPrestação de caução: Não\n\n15 - FORNECIMENTO DAS PEÇAS DO CONCURSO, APRESENTAÇÃO DE PEDIDOS DE PARTICIPAÇÃO E APRESENTAÇÃO DAS PROPOSTAS\nLink para acesso às peças do concurso (URL): https://www.acingov.pt/acingovprod/2/zonaPublica/zona_publica_c/donwloadProcedurePiece/OTMyNTU0\n\n20 - OUTROS REQUISITOS\nIdentificador do Lote: LOT-0001; LOT-0002\nInformação sobre contratos reservados. Aplica-se a contratos reservados (54º-A)? Não\n\n21 - CRITÉRIO DE ADJUDICAÇÃO\nO Critério de adjudicação é diferenciado por lote? Não\nMultifator: Não\nMonofator:\nNome: Preço\n\n24 - CONDIÇÕES DO CONTRATO\nIdentificador do Lote: LOT-0001; LOT-0002\nFaturação Eletrónica: Permitido\nObrigação de Subcontratação:\nCódigo da Obrigação de Subcontratação: Não é aplicável nenhuma obrigação de subcontratação.\n\n25 - COMPRA PÚBLICA ESTRATÉGICA\nCompra Pública Estratégica: Inexistência de contratação pública estratégica\n\n26 - INFORMAÇÕES ADICIONAIS\nIdentificador do Lote: LOT-0001; LOT-0002\nContrato adequado para PME: Não\nCobertura ACP (Acordo dos Contratos Públicos da Organização Mundial do Comércio): Não\n\n27 - IDENTIFICAÇÃO E CONTACTOS DO ÓRGÃO DE RECURSOS ADMINISTRATIVOS\nDesignação: Câmara Municipal das Lajes do Pico\nEndereço: Rua de São Francisco\nCódigo postal: 9930-135\nLocalidade: Lajes do Pico\nTelefone: 292679700\nFax: \nEndereço eletrónico: geral@cm-lajesdopico.pt\nPrazo de interposição do recurso: 5 dias\n\n28 - IDENTIFICAÇÃO DO(S) AUTOR(ES) DE ANÚNCIO\nNome: Amílcar Sérgio Oliveira Goulart\nCargo: Vereador da Câmara Municipal das Lajes do Pico\n419412682",
    "nipc": "512074143",
    "distrito": "Região Autónoma dos Açores",
    "concelho": "Lajes do Pico",
    "freguesia": "Freguesia de Lajes do Pico",
    "site": "http://cm-lajesdopico.pt/",
    "email": "aprovisionamento.cmlp@gmail.com",
    "designacao_contrato": "Contratação de Aluguer Operacional de Duas Viaturas Ligeiras de Mercadoria para a Câmara Municipal das Lajes do Pico",
    "descricao": "Contratação de Aluguer Operacional de Duas Viaturas Ligeiras de Mercadoria para a Câmara Municipal das Lajes do Pico",
    "preco_base": "81.600,00 EUR",
    "prazo_execucao": "48 MESES",
    "prazo_apresentacao_propostas": "22-08-2025 23:59",
    "fundos_eu": "Não",
    "plataforma_eletronica": "ACIN",
    "url_procedimento": "https://www.acingov.pt",
    "autor_nome": "Amílcar Sérgio Oliveira Goulart",
    "autor_cargo": "Vereador da Câmara Municipal das Lajes do Pico"
  },
  {
    "numero_procedimento": "N/A",
    "entidade": "Município de Santo Tirso",
    "link": "https://diariodarepublica.pt/dr/detalhe/contrato-publico/21369-928299397",
    "detalhes_completos": "1 - IDENTIFICAÇÃO E CONTACTOS DA ENTIDADE ADJUDICANTE\nDesignação da entidade adjudicante: Município de Santo Tirso\nNIPC: 501306870\nEndereço: Praça 25 de Abril\nCódigo postal: 4780-373\nLocalidade: Área Metropolitana do Porto\nPaís: Portugal\nNUT III: PT11A\nDistrito: Porto\nConcelho: Santo Tirso\nFreguesia: União das Freguesias de Santo Tirso, Couto (Santa Cristina e São Miguel) e Burgães\nTelefone: 252830400\nFax: 252856534\nEndereço da Entidade (URL): www.cm-stirso.pt\nEndereço Eletrónico: santotirso@cm-stirso.pt\neDelivery Gateway (URL): https://community.vortal.biz/public/\nFunção da Organização: Adquirente\nNorma jurídica da Entidade Adjudicante: Autoridade local\nÁrea de atividade da Autoridade Adjudicante: Serviços públicos das administrações públicas\n\n2 - JORNAL OFICIAL DA UNIÃO EUROPEIA\nO procedimento a que este anúncio diz respeito também é publicitado no Jornal Oficial da União Europeia? Não\n\n3 - AVISO\nModelo de Anúncio: Concurso público\nData de Envio do Anúncio: 07-08-2025\n\n5 - PROCESSO\nTipo de Procedimento: Concurso público\nPreço base do procedimento: Sim\nValor do preço base do procedimento: 117.770,94 EUR\nProcedimento com lotes? Não\n\n6 - OBJETO DO CONTRATO\nNúmero de referência interna: DPE55/25\nDesignação do contrato: OPJ 2020 - espaço de jogo e recreio acessível e inclusivo - Quinchães - Monte Córdova\nDescrição: OPJ 2020 - espaço de jogo e recreio acessível e inclusivo - Quinchães - Monte Córdova\nTipo de Contrato Principal: Empreitada de Obras Públicas\nTipo de Contrato: Empreitada de Obras Públicas\nClassificação CPV (Vocabulário Comum para os Contratos Públicos)\nObjeto principal\nVocabulário Principal: 45212120\nPreço base s/IVA: 117.770,94 EUR\n\n7 - INDICAÇÕES ADICIONAIS\nO contrato envolve aquisição conjunta (satisfação de várias entidades)? Não\nO contrato é adjudicado por uma central de compras? Não\n\n8 - TÉCNICAS\nO concurso destina-se à celebração de um acordo-quadro? Inexistência de acordo-quadro\nÉ utilizado um leilão eletrónico? Não\nÉ adotada uma fase de negociação? Não\nSistema de Aquisição Dinâmico: Inexistência de sistema de aquisição dinâmico\n\n9 - LOCAL DA EXECUÇÃO DO CONTRATO\nLOCAL DA EXECUÇÃO DO CONTRATO (PROCEDIMENTO)\nPaís: Portugal\nNUT III: PT11A\nLocalidade: Área Metropolitana do Porto\nDistrito: Porto\nConcelho: Santo Tirso\nFreguesia: União das Freguesias de Santo Tirso, Couto (Santa Cristina e São Miguel) e Burgães\n\n10 - PRAZO DE EXECUÇÃO DO CONTRATO\nPrazo de execução do contrato: 150 DIAS\nPrevisão de renovações: Não\n\n11 - FUNDOS EU\nTêm fundos EU? Não\n\n12 - DOCUMENTOS DE HABILITAÇÃO\nHabilitação para o exercício da atividade profissional: Sim\nTipo: Alvará\nDescrição: Alvará de empreiteiro de obras públicas, emitido pelo IMPIC (...) contendo as seguintes habilitações necessárias à execução da obra a realizar: \na.1 - 1ª Subcategoria da 2ª categoria a qual tem de ser de classe que cubra o valor global da proposta;\na.2 – As 6ª, 8ª, 9ª e 10ª subcategorias da 2ª categoria, a 1ª subcategoria da 4ª categoria e as 1ª e 2ª\nsubcategorias da 5ª categoria, (...)\n\n13 - CONDIÇÕES DE APRESENTAÇÃO\nPlataforma eletrónica utilizada pela entidade adjudicante: VORTAL\nURL para Apresentação: https://community.vortal.biz/public/\nAdmissibilidade da apresentação de propostas variantes: Não autorizado\nPrazo para apresentação das propostas: 01-09-2025 17:00\nPrazo durante o qual os concorrentes são obrigados a manter as respetivas propostas: 66 dias a contar do termo do prazo para a apresentação das propostas\nIndicação de Subcontratação na Proposta: Inexistência de indicação de subcontratação\n\n14 - PRESTAÇÃO DE CAUÇÃO\nPrestação de caução: Sim\nPercentagem: 5%\nDescrição da Garantia Exigida: A caução é prestada por depósito em dinheiro ou em títulos emitido ou garantidos pelo Estado, ou mediante garantia bancária ou seguro – caução, conforme modelos em anexo.\n\n15 - FORNECIMENTO DAS PEÇAS DO CONCURSO, APRESENTAÇÃO DE PEDIDOS DE PARTICIPAÇÃO E APRESENTAÇÃO DAS PROPOSTAS\nLink para acesso às peças do concurso (URL): https://community.vortal.biz/Public/public-tender-documents/VGtOVExYUGo5U0tER095amtYNnhHYXFMUTFOTnBjUmNFRTdmYWhMOTMvRXRUZk9NMUx2WUl3OXcxZERESjQ5VHphU201cG4vRHVDRnI0ZVRCS1NzZ1E9PWcwbmMh\n\n20 - OUTROS REQUISITOS\nInformação sobre contratos reservados. Aplica-se a contratos reservados (54º-A)? Não\n\n21 - CRITÉRIO DE ADJUDICAÇÃO\nMultifator: Não\nMonofator:\nNome: Outros\nOutro nome: Preço\n\n24 - CONDIÇÕES DO CONTRATO\nFaturação Eletrónica: Permitido\nObrigação de Subcontratação:\nCódigo da Obrigação de Subcontratação: Não é aplicável nenhuma obrigação de subcontratação.\n\n25 - COMPRA PÚBLICA ESTRATÉGICA\nCompra Pública Estratégica: Inexistência de contratação pública estratégica\n\n26 - INFORMAÇÕES ADICIONAIS\nContrato adequado para PME: Sim\nCobertura ACP (Acordo dos Contratos Públicos da Organização Mundial do Comércio): Não\n\n27 - IDENTIFICAÇÃO E CONTACTOS DO ÓRGÃO DE RECURSOS ADMINISTRATIVOS\nDesignação: Município de Santo Tirso\nEndereço: Praça 25 de Abril\nCódigo postal: 4780-373\nLocalidade: Santo Tirso\nTelefone: +351 252830400\nFax: +351 252856534\nEndereço eletrónico: santotirso@cm-stirso.pt\n\n28 - IDENTIFICAÇÃO DO(S) AUTOR(ES) DE ANÚNCIO\nNome: Alberto Manuel Martins da Costa\nCargo: Presidente da Câmara Municipal\n419410381",
    "nipc": "501306870",
    "distrito": "Porto",
    "concelho": "Santo Tirso",
    "freguesia": "União das Freguesias de Santo Tirso, Couto (Santa Cristina e São Miguel) e Burgães",
    "site": "www.cm-stirso.pt",
    "email": "santotirso@cm-stirso.pt",
    "designacao_contrato": "OPJ 2020 - espaço de jogo e recreio acessível e inclusivo - Quinchães - Monte Córdova",
    "descricao": "OPJ 2020 - espaço de jogo e recreio acessível e inclusivo - Quinchães - Monte Córdova",
    "preco_base": "117.770,94 EUR",
    "prazo_execucao": "150 DIAS",
    "prazo_apresentacao_propostas": "01-09-2025 17:00",
    "fundos_eu": "Não",
    "plataforma_eletronica": "VORTAL",
    "url_procedimento": "https://community.vortal.biz/public/",
    "autor_nome": "Alberto Manuel Martins da Costa",
    "autor_cargo": "Presidente da Câmara Municipal"
  },
  {
    "numero_procedimento": "N/A",
    "entidade": "MUNICÍPIO DE LOULÉ",
    "link": "https://diariodarepublica.pt/dr/detalhe/contrato-publico/21371-928299398",
    "detalhes_completos": "1 - IDENTIFICAÇÃO E CONTACTOS DA ENTIDADE ADJUDICANTE\nDesignação da entidade adjudicante: MUNICÍPIO DE LOULÉ\nNIPC: 502098139\nEndereço: Praça da República\nCódigo postal: 8104-001\nLocalidade: Faro\nPaís: Portugal\nNUT III: PT150\nDistrito: Faro\nConcelho: Loulé\nFreguesia: Todas\nTelefone: 289400834\nFax: 289415557\nEndereço da Entidade (URL): www.cm-loule.pt\nEndereço Eletrónico: aprovisionamento@cm-loule.pt\neDelivery Gateway (URL): https://community.vortal.biz/public/\nFunção da Organização: Adquirente\nNorma jurídica da Entidade Adjudicante: Organismo de direito público\nÁrea de atividade da Autoridade Adjudicante: Serviços públicos das administrações públicas\n\n2 - JORNAL OFICIAL DA UNIÃO EUROPEIA\nO procedimento a que este anúncio diz respeito também é publicitado no Jornal Oficial da União Europeia? Sim\n\n3 - AVISO\nModelo de Anúncio: Concurso público\nData de Envio do Anúncio: 05-08-2025\n\n5 - PROCESSO\nTipo de Procedimento: Concurso público\nPreço base do procedimento: Sim\nValor do preço base do procedimento: 219.000,00 EUR\nProcedimento com lotes? Sim\nNº Máx. de Lotes Autorizado: 2\nNúmero máximo de lotes que podem ser adjudicados a um concorrente: 2\n\n6 - OBJETO DO CONTRATO\nNúmero de referência interna: FM-2025-318 DACP\nDesignação do contrato: CONTRATAÇÃO DO FORNECIMENTO DE CONTENTORES DE SUPERFÍCIE PARA RECOLHA SELETIVA DE RESÍDUOS URBANOS PARA O CONCELHO DE LOULÉ\nDescrição: CONTRATAÇÃO DO FORNECIMENTO DE CONTENTORES DE SUPERFÍCIE PARA RECOLHA SELETIVA DE RESÍDUOS URBANOS PARA O CONCELHO DE LOULÉ\nOpções: Não\nTipo de Contrato Principal: Aquisição de Bens Móveis\nTipo de Contrato: Aquisição de Bens Móveis\nClassificação CPV (Vocabulário Comum para os Contratos Públicos)\nObjeto principal\nVocabulário Principal: 44610000\nPreço base s/IVA: 219.000,00 EUR\nLotes: \nNº: LOT-0001\nDescrição do Lote: LOTE 1 \nPreço base s/IVA: 165.000,00 EUR\nClassificação CPV (Vocabulário Comum para os Contratos Públicos)\nObjeto principal\nVocabulário Principal: 44610000\nNº: LOT-0002\nDescrição do Lote: LOTE 2 \nPreço base s/IVA: 54.000,00 EUR\nClassificação CPV (Vocabulário Comum para os Contratos Públicos)\nObjeto principal\nVocabulário Principal: 44610000\n\n7 - INDICAÇÕES ADICIONAIS\nO contrato envolve aquisição conjunta (satisfação de várias entidades)? Não\nO contrato é adjudicado por uma central de compras? Não\n\n8 - TÉCNICAS\nO concurso destina-se à celebração de um acordo-quadro? Inexistência de acordo-quadro\nÉ utilizado um leilão eletrónico? Não\nÉ adotada uma fase de negociação? Não\nSistema de Aquisição Dinâmico: Inexistência de sistema de aquisição dinâmico\n\n9 - LOCAL DA EXECUÇÃO DO CONTRATO\nLOCAL DA EXECUÇÃO DO CONTRATO (PROCEDIMENTO)\nPaís: Portugal\nNUT III: PT150\nLocalidade: Loulé\nDistrito: Faro\nConcelho: Loulé\nFreguesia: Todas\nLOCAL DA EXECUÇÃO DO CONTRATO (LOTE)\nIdentificador do Lote: LOT-0001; LOT-0002\nPaís: Portugal\nNUT III: PT150\nLocalidade: Loulé\nDistrito: Faro\nConcelho: Loulé\nFreguesia: Todas\n\n10 - PRAZO DE EXECUÇÃO DO CONTRATO\nIdentificador do Lote: LOT-0001; LOT-0002\nPrazo de execução do contrato: 120 DIAS\nPrevisão de renovações: Não\n\n11 - FUNDOS EU\nIdentificador do Lote: LOT-0001; LOT-0002\nTêm fundos EU? Não\n\n12 - DOCUMENTOS DE HABILITAÇÃO\nHabilitação para o exercício da atividade profissional: Não\n\n13 - CONDIÇÕES DE APRESENTAÇÃO\nPlataforma eletrónica utilizada pela entidade adjudicante: VORTAL\nURL para Apresentação: https://community.vortal.biz/public/\nAdmissibilidade da apresentação de propostas variantes: Não autorizado\nPrazo para apresentação das propostas: 10-09-2025 18:00\nPrazo durante o qual os concorrentes são obrigados a manter as respetivas propostas: 90 dias a contar do termo do prazo para a apresentação das propostas\nApresentação de Catálogo Eletrónico: Não autorizado\nIndicação de Subcontratação na Proposta: Inexistência de indicação de subcontratação\n\n14 - PRESTAÇÃO DE CAUÇÃO\nPrestação de caução: Não\n\n15 - FORNECIMENTO DAS PEÇAS DO CONCURSO, APRESENTAÇÃO DE PEDIDOS DE PARTICIPAÇÃO E APRESENTAÇÃO DAS PROPOSTAS\nLink para acesso às peças do concurso (URL): https://community.vortal.biz/Public/public-tender-documents/cENkbVJDVCtESHIxNGZlNjlZZTZSWTJMckE4RWppcHNYYkFJOVBPbDlVZldjcWt1dUYzMitQRzJwaDEydndYTDNEbTVFaWRHSjJidlVGMFJua1NZb1E9PXF3Xml4\n\n20 - OUTROS REQUISITOS\nIdentificador do Lote: LOT-0001; LOT-0002\nInformação sobre contratos reservados. Aplica-se a contratos reservados (54º-A)? Não\n\n21 - CRITÉRIO DE ADJUDICAÇÃO\nO Critério de adjudicação é diferenciado por lote? Não\nMultifator: Não\nMonofator:\nNome: Preço\n\n24 - CONDIÇÕES DO CONTRATO\nIdentificador do Lote: LOT-0001; LOT-0002\nFaturação Eletrónica: Permitido\nObrigação de Subcontratação:\nCódigo da Obrigação de Subcontratação: Não é aplicável nenhuma obrigação de subcontratação.\n\n25 - COMPRA PÚBLICA ESTRATÉGICA\nCompra Pública Estratégica: Inexistência de contratação pública estratégica\n\n26 - INFORMAÇÕES ADICIONAIS\nIdentificador do Lote: LOT-0001; LOT-0002\nContrato adequado para PME: Sim\nCobertura ACP (Acordo dos Contratos Públicos da Organização Mundial do Comércio): Não\n\n27 - IDENTIFICAÇÃO E CONTACTOS DO ÓRGÃO DE RECURSOS ADMINISTRATIVOS\nDesignação: Câmara Municipal de Loulé\nEndereço: Praça da República\nCódigo postal: 8104-001\nLocalidade: Loulé\nTelefone: +351 289400600\nFax: +351 289415557\nEndereço eletrónico: geral@cm-loule.pt\n\n28 - IDENTIFICAÇÃO DO(S) AUTOR(ES) DE ANÚNCIO\nNome: Vítor Manuel Gonçalves Aleixo\nCargo: Presidente da Câmara\n419395957",
    "nipc": "502098139",
    "distrito": "Faro",
    "concelho": "Loulé",
    "freguesia": "Todas",
    "site": "www.cm-loule.pt",
    "email": "aprovisionamento@cm-loule.pt",
    "designacao_contrato": "CONTRATAÇÃO DO FORNECIMENTO DE CONTENTORES DE SUPERFÍCIE PARA RECOLHA SELETIVA DE RESÍDUOS URBANOS PARA O CONCELHO DE LOULÉ",
    "descricao": "CONTRATAÇÃO DO FORNECIMENTO DE CONTENTORES DE SUPERFÍCIE PARA RECOLHA SELETIVA DE RESÍDUOS URBANOS PARA O CONCELHO DE LOULÉ",
    "preco_base": "219.000,00 EUR",
    "prazo_execucao": "120 DIAS",
    "prazo_apresentacao_propostas": "10-09-2025 18:00",
    "fundos_eu": "Não",
    "plataforma_eletronica": "VORTAL",
    "url_procedimento": "https://community.vortal.biz/public/",
    "autor_nome": "Vítor Manuel Gonçalves Aleixo",
    "autor_cargo": "Presidente da Câmara"
  },
  {
    "numero_procedimento": "N/A",
    "entidade": "Municipio de Oliveira de Azeméis",
    "link": "https://diariodarepublica.pt/dr/detalhe/contrato-publico/21372-928299399",
    "detalhes_completos": "1 - IDENTIFICAÇÃO E CONTACTOS DA ENTIDADE ADJUDICANTE\nDesignação da entidade adjudicante: Municipio de Oliveira de Azeméis\nNIPC: 506302970\nEndereço: Largo da Républica\nCódigo postal: 3720-240\nLocalidade: Oliveira de Azeméis\nPaís: Portugal\nNUT III: PT11A\nDistrito: Aveiro\nConcelho: Oliveira de Azemeis\nFreguesia: União das Freguesias de Oliveira de Azeméis, Santiago de Riba-Ul, Ul, Macinhata da Seixa e Madail\nTelefone: 256600600\nFax: 256600626\nEndereço da Entidade (URL): www.cm-oaz.pt\nEndereço Eletrónico: geral@cm-oaz.pt\neDelivery Gateway (URL): https://www.acingov.pt\nFunção da Organização: Adquirente\nNorma jurídica da Entidade Adjudicante: Organismo de direito público\nÁrea de atividade da Autoridade Adjudicante: Serviços públicos das administrações públicas\n\n2 - JORNAL OFICIAL DA UNIÃO EUROPEIA\nO procedimento a que este anúncio diz respeito também é publicitado no Jornal Oficial da União Europeia? Não\n\n3 - AVISO\nModelo de Anúncio: Concurso público\nData de Envio do Anúncio: 07-08-2025\n\n5 - PROCESSO\nTipo de Procedimento: Concurso público\nPreço base do procedimento: Sim\nValor do preço base do procedimento: 98.430,00 EUR\nProcedimento com lotes? Sim\nNº Máx. de Lotes Autorizado: 2\nNúmero máximo de lotes que podem ser adjudicados a um concorrente: 2\n\n6 - OBJETO DO CONTRATO\nNúmero de referência interna: CP/26/2025 (Proc. 101/25)\nDesignação do contrato: Aquisição de ginásio aquático completo e elevador aquático portátil\nDescrição: Aquisição de ginásio aquático completo e elevador aquático portátil\nTipo de Contrato Principal: Aquisição de Bens Móveis\nTipo de Contrato: Aquisição de Bens Móveis\nClassificação CPV (Vocabulário Comum para os Contratos Públicos)\nObjeto principal\nVocabulário Principal: 37420000\nPreço base s/IVA: 98.430,00 EUR\nLotes: \nNº: LOT-0001\nDescrição do Lote: Ginásio Aquático Completo\nPreço base s/IVA: 90.000,00 EUR\nClassificação CPV (Vocabulário Comum para os Contratos Públicos)\nObjeto principal\nVocabulário Principal: 37420000\nNº: LOT-0002\nDescrição do Lote: Elevador Aquático Portátil\nPreço base s/IVA: 8.430,00 EUR\nClassificação CPV (Vocabulário Comum para os Contratos Públicos)\nObjeto principal\nVocabulário Principal: 37420000\n\n7 - INDICAÇÕES ADICIONAIS\nO contrato envolve aquisição conjunta (satisfação de várias entidades)? Não\nO contrato é adjudicado por uma central de compras? Não\n\n8 - TÉCNICAS\nO concurso destina-se à celebração de um acordo-quadro? Inexistência de acordo-quadro\nÉ utilizado um leilão eletrónico? Não\nÉ adotada uma fase de negociação? Não\nSistema de Aquisição Dinâmico: Inexistência de sistema de aquisição dinâmico\n\n9 - LOCAL DA EXECUÇÃO DO CONTRATO\nLOCAL DA EXECUÇÃO DO CONTRATO (PROCEDIMENTO)\nPaís: Portugal\nNUT III: PT11A\nLocalidade: Oliveira de Azeméis\nDistrito: Aveiro\nConcelho: Oliveira de Azemeis\nFreguesia: União das Freguesias de Oliveira de Azeméis, Santiago de Riba-Ul, Ul, Macinhata da Seixa e Madail\nLOCAL DA EXECUÇÃO DO CONTRATO (LOTE)\nIdentificador do Lote: LOT-0001; LOT-0002\nPaís: Portugal\nNUT III: PT11A\nLocalidade: Oliveira de Azeméis\nDistrito: Aveiro\nConcelho: Oliveira de Azemeis\nFreguesia: União das Freguesias de Oliveira de Azeméis, Santiago de Riba-Ul, Ul, Macinhata da Seixa e Madail\n\n10 - PRAZO DE EXECUÇÃO DO CONTRATO\nIdentificador do Lote: LOT-0001; LOT-0002\nPrazo de execução do contrato: 90 DIAS\nPrevisão de renovações: Não\n\n11 - FUNDOS EU\nIdentificador do Lote: LOT-0001; LOT-0002\nTêm fundos EU? Sim\n\n12 - DOCUMENTOS DE HABILITAÇÃO\nHabilitação para o exercício da atividade profissional: Não\n\n13 - CONDIÇÕES DE APRESENTAÇÃO\nPlataforma eletrónica utilizada pela entidade adjudicante: ACIN\nURL para Apresentação: https://www.acingov.pt\nAdmissibilidade da apresentação de propostas variantes: Não autorizado\nPrazo para apresentação das propostas: 16-08-2025 23:59\nPrazo durante o qual os concorrentes são obrigados a manter as respetivas propostas: 66 dias a contar do termo do prazo para a apresentação das propostas\nIndicação de Subcontratação na Proposta: Inexistência de indicação de subcontratação\n\n14 - PRESTAÇÃO DE CAUÇÃO\nPrestação de caução: Não\n\n15 - FORNECIMENTO DAS PEÇAS DO CONCURSO, APRESENTAÇÃO DE PEDIDOS DE PARTICIPAÇÃO E APRESENTAÇÃO DAS PROPOSTAS\nLink para acesso às peças do concurso (URL): https://www.acingov.pt/acingovprod/2/zonaPublica/zona_publica_c/donwloadProcedurePiece/OTMyMDg5\n\n20 - OUTROS REQUISITOS\nIdentificador do Lote: LOT-0001; LOT-0002\nInformação sobre contratos reservados. Aplica-se a contratos reservados (54º-A)? Não\n\n21 - CRITÉRIO DE ADJUDICAÇÃO\nO Critério de adjudicação é diferenciado por lote? Não\nMultifator: Não\nMonofator:\nNome: Preço\n\n24 - CONDIÇÕES DO CONTRATO\nIdentificador do Lote: LOT-0001; LOT-0002\nFaturação Eletrónica: Permitido\nObrigação de Subcontratação:\nCódigo da Obrigação de Subcontratação: Não é aplicável nenhuma obrigação de subcontratação.\n\n25 - COMPRA PÚBLICA ESTRATÉGICA\nCompra Pública Estratégica: Inexistência de contratação pública estratégica\n\n26 - INFORMAÇÕES ADICIONAIS\nIdentificador do Lote: LOT-0001; LOT-0002\nContrato adequado para PME: Sim\nCobertura ACP (Acordo dos Contratos Públicos da Organização Mundial do Comércio): Não\n\n27 - IDENTIFICAÇÃO E CONTACTOS DO ÓRGÃO DE RECURSOS ADMINISTRATIVOS\nDesignação: Presidente da Câmara Municipal\nEndereço: Largo da República\nCódigo postal: 3720-240\nLocalidade: Oliveira de Azeméis\nTelefone: 256600600\nFax: 256674694\nEndereço eletrónico: presidencia@cm-oaz.pt\n\n28 - IDENTIFICAÇÃO DO(S) AUTOR(ES) DE ANÚNCIO\nNome: Joaquim Jorge Ferreira\nCargo: Joaquim Jorge Ferreira\n419411978",
    "nipc": "506302970",
    "distrito": "Aveiro",
    "concelho": "Oliveira de Azemeis",
    "freguesia": "União das Freguesias de Oliveira de Azeméis, Santiago de Riba-Ul, Ul, Macinhata da Seixa e Madail",
    "site": "www.cm-oaz.pt",
    "email": "geral@cm-oaz.pt",
    "designacao_contrato": "Aquisição de ginásio aquático completo e elevador aquático portátil",
    "descricao": "Aquisição de ginásio aquático completo e elevador aquático portátil",
    "preco_base": "98.430,00 EUR",
    "prazo_execucao": "90 DIAS",
    "prazo_apresentacao_propostas": "16-08-2025 23:59",
    "fundos_eu": "Sim",
    "plataforma_eletronica": "ACIN",
    "url_procedimento": "https://www.acingov.pt",
    "autor_nome": "Joaquim Jorge Ferreira",
    "autor_cargo": "Joaquim Jorge Ferreira"
  },
  {
    "numero_procedimento": "N/A",
    "entidade": "Águas do Alto Minho, S. A.",
    "link": "https://diariodarepublica.pt/dr/detalhe/contrato-publico/21374-928299400",
    "detalhes_completos": "1 - IDENTIFICAÇÃO E CONTACTOS DA ENTIDADE ADJUDICANTE\nDesignação da entidade adjudicante: Águas do Alto Minho, S. A.\nNIPC: 515486159\nServiço/Órgão/Pessoa de contacto: Dept. Compras e Logística\nEndereço: Rua Frei Bartolomeu dos Mártires, 156\nCódigo postal: 4904-878\nLocalidade: Viana do Castelo\nPaís: Portugal\nNUT III: PT111\nDistrito: Viana do Castelo\nConcelho: Todos\nFreguesia: Todas\nTelefone: 258806900\nFax: 258806990\nEndereço da Entidade (URL): www.adp.pt\nEndereço Eletrónico: geral.adam@adp.pt\neDelivery Gateway (URL): https://www.acingov.pt\nFunção da Organização: Adquirente\nNorma jurídica da Entidade Adjudicante: Organismo de direito público\nÁrea de atividade da Autoridade Adjudicante: Serviços públicos das administrações públicas\n\n2 - JORNAL OFICIAL DA UNIÃO EUROPEIA\nO procedimento a que este anúncio diz respeito também é publicitado no Jornal Oficial da União Europeia? Não\n\n3 - AVISO\nModelo de Anúncio: Concurso público\nData de Envio do Anúncio: 07-08-2025\n\n5 - PROCESSO\nTipo de Procedimento: Concurso público\nPreço base do procedimento: Sim\nValor do preço base do procedimento: 182.372,40 EUR\nProcedimento com lotes? Não\n\n6 - OBJETO DO CONTRATO\nNúmero de referência interna: PRC 110/2025\nDesignação do contrato: Prestação de Serviços de Higiene e Limpeza nas Instalações da Águas do Alto Minho S.A.\nDescrição: Prestação de Serviços de Higiene e Limpeza nas Instalações da Águas do Alto Minho S.A.\nTipo de Contrato Principal: Aquisição de Serviços\nTipo de Contrato: Aquisição de Serviços\nClassificação CPV (Vocabulário Comum para os Contratos Públicos)\nObjeto principal\nVocabulário Principal: 90911200\nPreço base s/IVA: 182.372,40 EUR\n\n7 - INDICAÇÕES ADICIONAIS\nO contrato envolve aquisição conjunta (satisfação de várias entidades)? Não\nO contrato é adjudicado por uma central de compras? Não\n\n8 - TÉCNICAS\nO concurso destina-se à celebração de um acordo-quadro? Inexistência de acordo-quadro\nÉ utilizado um leilão eletrónico? Não\nÉ adotada uma fase de negociação? Não\nSistema de Aquisição Dinâmico: Inexistência de sistema de aquisição dinâmico\n\n9 - LOCAL DA EXECUÇÃO DO CONTRATO\nLOCAL DA EXECUÇÃO DO CONTRATO (PROCEDIMENTO)\nPaís: Portugal\nNUT III: PT111\nLocalidade: Todas\nDistrito: Viana do Castelo\nConcelho: Arcos de Valdevez\nFreguesia: Todas\nPaís: Portugal\nNUT III: PT111\nLocalidade: Todas\nDistrito: Viana do Castelo\nConcelho: Caminha\nFreguesia: Todas\nPaís: Portugal\nNUT III: PT111\nLocalidade: Todas\nDistrito: Viana do Castelo\nConcelho: Paredes de Coura\nFreguesia: Todas\nPaís: Portugal\nNUT III: PT111\nLocalidade: Todas\nDistrito: Viana do Castelo\nConcelho: Ponte de Lima\nFreguesia: Todas\nPaís: Portugal\nNUT III: PT111\nLocalidade: Todas\nDistrito: Viana do Castelo\nConcelho: Valença\nFreguesia: Todas\nPaís: Portugal\nNUT III: PT111\nLocalidade: Todas\nDistrito: Viana do Castelo\nConcelho: Viana do Castelo\nFreguesia: Todas\nPaís: Portugal\nNUT III: PT111\nLocalidade: Todas\nDistrito: Viana do Castelo\nConcelho: Vila Nova de Cerveira\nFreguesia: Todas\n\n10 - PRAZO DE EXECUÇÃO DO CONTRATO\nPrazo de execução do contrato: 24 MESES\nPrevisão de renovações: Não\n\n11 - FUNDOS EU\nTêm fundos EU? Não\n\n12 - DOCUMENTOS DE HABILITAÇÃO\nHabilitação para o exercício da atividade profissional: Não\n\n13 - CONDIÇÕES DE APRESENTAÇÃO\nPlataforma eletrónica utilizada pela entidade adjudicante: ACIN\nURL para Apresentação: https://www.acingov.pt\nAdmissibilidade da apresentação de propostas variantes: Não autorizado\nPrazo para apresentação das propostas: 19-08-2025 23:59\nPrazo durante o qual os concorrentes são obrigados a manter as respetivas propostas: 90 dias a contar do termo do prazo para a apresentação das propostas\nIndicação de Subcontratação na Proposta: Inexistência de indicação de subcontratação\n\n14 - PRESTAÇÃO DE CAUÇÃO\nPrestação de caução: Não\n\n15 - FORNECIMENTO DAS PEÇAS DO CONCURSO, APRESENTAÇÃO DE PEDIDOS DE PARTICIPAÇÃO E APRESENTAÇÃO DAS PROPOSTAS\nLink para acesso às peças do concurso (URL): https://www.acingov.pt/acingovprod/2/zonaPublica/zona_publica_c/donwloadProcedurePiece/OTMyNjEz\n\n20 - OUTROS REQUISITOS\nInformação sobre contratos reservados. Aplica-se a contratos reservados (54º-A)? Não\n\n21 - CRITÉRIO DE ADJUDICAÇÃO\nMultifator: Sim\nFator: \nNome: Preço\nPonderação: 70%\nSubfatores: Não\nFator: \nNome: Outros\nOutro Nome: Sistemas de Certificação\nPonderação: 30%\nSubfatores: Não\n\n24 - CONDIÇÕES DO CONTRATO\nFaturação Eletrónica: Permitido\nObrigação de Subcontratação:\nCódigo da Obrigação de Subcontratação: Não é aplicável nenhuma obrigação de subcontratação.\n\n25 - COMPRA PÚBLICA ESTRATÉGICA\nCompra Pública Estratégica: Redução dos impactos ambientais\nDescrição do Processo de Adjudicação Estratégico: Mencionados no C.E.\nCritérios de contratos Públicos Ecológicos: Critérios de contratação pública ecológica nacional\nCategorias da estratégia nacional: Outros\nOutra categoria (Descrição): N/A\nDiretiva Veículos Não Poluentes: Não\nCritério de Acessibilidade: Os critérios de acessibilidade para as pessoas com deficiência não estão incluídos porque o contrato não se destina a pessoas singulares\n\n26 - INFORMAÇÕES ADICIONAIS\nContrato adequado para PME: Sim\nCobertura ACP (Acordo dos Contratos Públicos da Organização Mundial do Comércio): Não\n\n27 - IDENTIFICAÇÃO E CONTACTOS DO ÓRGÃO DE RECURSOS ADMINISTRATIVOS\nDesignação: Conselho de Administração da Águas do Alto Minho, S.A.\nEndereço: Rua Frei Bartolomeu dos Mártires, 156\nCódigo postal: 4904-878\nLocalidade: Viana do Castelo\nTelefone: 258806900\nFax: 258806990\nEndereço eletrónico: geral.adam@adp.pt\nPrazo de interposição do recurso: 30 dias\n\n28 - IDENTIFICAÇÃO DO(S) AUTOR(ES) DE ANÚNCIO\nNome: Fernanda Machado\nCargo: Vice Presidente do CA\n419415047",
    "nipc": "515486159",
    "distrito": "Viana do Castelo",
    "concelho": "Todos",
    "freguesia": "Todas",
    "site": "www.adp.pt",
    "email": "geral.adam@adp.pt",
    "designacao_contrato": "Prestação de Serviços de Higiene e Limpeza nas Instalações da Águas do Alto Minho S.A.",
    "descricao": "Prestação de Serviços de Higiene e Limpeza nas Instalações da Águas do Alto Minho S.A.",
    "preco_base": "182.372,40 EUR",
    "prazo_execucao": "24 MESES",
    "prazo_apresentacao_propostas": "19-08-2025 23:59",
    "fundos_eu": "Não",
    "plataforma_eletronica": "ACIN",
    "url_procedimento": "https://www.acingov.pt",
    "autor_nome": "Fernanda Machado",
    "autor_cargo": "Vice Presidente do CA"
  },
  {
    "numero_procedimento": "N/A",
    "entidade": "Portos dos Açores, SA",
    "link": "https://diariodarepublica.pt/dr/detalhe/contrato-publico/21376-928299401",
    "detalhes_completos": "1 - IDENTIFICAÇÃO E CONTACTOS DA ENTIDADE ADJUDICANTE\nDesignação da entidade adjudicante: Portos dos Açores, SA\nNIPC: 512077843\nServiço/Órgão/Pessoa de contacto: Portos dos Açores, SA\nEndereço: Avenida Gago Coutinho e Sacadura Cabral, nº 7\nCódigo postal: 9900-062\nLocalidade: Horta\nPaís: Portugal\nNUT III: PT200\nDistrito: Região Autónoma dos Açores\nConcelho: Todos\nFreguesia: Todas\nTelefone: 292208300\nFax: 292208315\nEndereço da Entidade (URL): www.portosdosacores.pt\nEndereço Eletrónico: geral@portosodosacores.pt\neDelivery Gateway (URL): https://www.acingov.pt\nFunção da Organização: Adquirente\nNorma jurídica da Entidade Adjudicante: Organismo de direito público\nÁrea de atividade da Autoridade Adjudicante: Serviços públicos das administrações públicas\n\n2 - JORNAL OFICIAL DA UNIÃO EUROPEIA\nO procedimento a que este anúncio diz respeito também é publicitado no Jornal Oficial da União Europeia? Sim\n\n3 - AVISO\nModelo de Anúncio: Concurso público\nData de Envio do Anúncio: 05-08-2025\n\n5 - PROCESSO\nTipo de Procedimento: Concurso público\nPreço base do procedimento: Sim\nValor do preço base do procedimento: 2.000.000,00 EUR\nProcedimento com lotes? Não\n\n6 - OBJETO DO CONTRATO\nNúmero de referência interna: CPI/3/2025/PA, SA\nDesignação do contrato: AQUISIÇÃO DE DOIS GUINDASTES MÓVEIS ELÉTRICOS TIPO PELICAN PARA EMBARCAÇÕES, COM CAPACIDADE ATÉ SETENTA TONELADAS PARA O PORTO DE PONTA DELGADA E PARA O PORTO DA HORTA\nDescrição: AQUISIÇÃO DE DOIS GUINDASTES MÓVEIS ELÉTRICOS TIPO PELICAN PARA EMBARCAÇÕES, COM CAPACIDADE ATÉ SETENTA TONELADAS PARA O PORTO DE PONTA DELGADA E PARA O PORTO DA HORTA\nOpções: Não\nTipo de Contrato Principal: Aquisição de Bens Móveis\nTipo de Contrato: Aquisição de Bens Móveis\nClassificação CPV (Vocabulário Comum para os Contratos Públicos)\nObjeto principal\nVocabulário Principal: 42416300\nPreço base s/IVA: 2.000.000,00 EUR\n\n7 - INDICAÇÕES ADICIONAIS\nO contrato envolve aquisição conjunta (satisfação de várias entidades)? Não\nO contrato é adjudicado por uma central de compras? Não\n\n8 - TÉCNICAS\nO concurso destina-se à celebração de um acordo-quadro? Inexistência de acordo-quadro\nÉ utilizado um leilão eletrónico? Não\nÉ adotada uma fase de negociação? Não\nSistema de Aquisição Dinâmico: Inexistência de sistema de aquisição dinâmico\n\n9 - LOCAL DA EXECUÇÃO DO CONTRATO\nLOCAL DA EXECUÇÃO DO CONTRATO (PROCEDIMENTO)\nPaís: Portugal\nNUT III: PT200\nLocalidade: Horta\nDistrito: Região Autónoma dos Açores\nConcelho: Horta\nFreguesia: Todas\n\n10 - PRAZO DE EXECUÇÃO DO CONTRATO\nPrazo de execução do contrato: 6 MESES\nPrevisão de renovações: Não\n\n11 - FUNDOS EU\nTêm fundos EU? Não\n\n12 - DOCUMENTOS DE HABILITAÇÃO\nHabilitação para o exercício da atividade profissional: Sim\nTipo: Outros\nDescrição - Outros: Conforme Peças do Procedimento\nDescrição: Documentos de Habilitação\n\n13 - CONDIÇÕES DE APRESENTAÇÃO\nPlataforma eletrónica utilizada pela entidade adjudicante: ACIN\nURL para Apresentação: https://www.acingov.pt\nAdmissibilidade da apresentação de propostas variantes: Não autorizado\nPrazo para apresentação das propostas: 04-09-2025 23:59\nPrazo durante o qual os concorrentes são obrigados a manter as respetivas propostas: 70 dias a contar do termo do prazo para a apresentação das propostas\nApresentação de Catálogo Eletrónico: Permitido\nIndicação de Subcontratação na Proposta: Inexistência de indicação de subcontratação\n\n14 - PRESTAÇÃO DE CAUÇÃO\nPrestação de caução: Sim\nPercentagem: 2%\nDescrição da Garantia Exigida: O valor da caução é de 2.00% do preço contratual.\n\n15 - FORNECIMENTO DAS PEÇAS DO CONCURSO, APRESENTAÇÃO DE PEDIDOS DE PARTICIPAÇÃO E APRESENTAÇÃO DAS PROPOSTAS\nLink para acesso às peças do concurso (URL): https://www.acingov.pt/acingovprod/2/zonaPublica/zona_publica_c/donwloadProcedurePiece/OTMxNjAx\n\n20 - OUTROS REQUISITOS\nInformação sobre contratos reservados. Aplica-se a contratos reservados (54º-A)? Não\n\n21 - CRITÉRIO DE ADJUDICAÇÃO\nMultifator: Não\nMonofator:\nNome: Preço\n\n24 - CONDIÇÕES DO CONTRATO\nFaturação Eletrónica: Permitido\nObrigação de Subcontratação:\nCódigo da Obrigação de Subcontratação: Não é aplicável nenhuma obrigação de subcontratação.\n\n25 - COMPRA PÚBLICA ESTRATÉGICA\nCompra Pública Estratégica: Inexistência de contratação pública estratégica\n\n26 - INFORMAÇÕES ADICIONAIS\nContrato adequado para PME: Não\nCobertura ACP (Acordo dos Contratos Públicos da Organização Mundial do Comércio): Não\n\n27 - IDENTIFICAÇÃO E CONTACTOS DO ÓRGÃO DE RECURSOS ADMINISTRATIVOS\nDesignação: Conselho de Administração\nEndereço: Avenida Gago Coutinho e Sacadura Cabral, nº 7\nCódigo postal: 9900-062\nLocalidade: Horta\nTelefone: 292208300\nFax: \nEndereço eletrónico: geral@portosdosacores.pt\n\n28 - IDENTIFICAÇÃO DO(S) AUTOR(ES) DE ANÚNCIO\nNome: Renata Maria Freitas Lima\nCargo: Técnica Administrativa\n419404963",
    "nipc": "512077843",
    "distrito": "Região Autónoma dos Açores",
    "concelho": "Todos",
    "freguesia": "Todas",
    "site": "www.portosdosacores.pt",
    "email": "geral@portosodosacores.pt",
    "designacao_contrato": "AQUISIÇÃO DE DOIS GUINDASTES MÓVEIS ELÉTRICOS TIPO PELICAN PARA EMBARCAÇÕES, COM CAPACIDADE ATÉ SETENTA TONELADAS PARA O PORTO DE PONTA DELGADA E PARA O PORTO DA HORTA",
    "descricao": "AQUISIÇÃO DE DOIS GUINDASTES MÓVEIS ELÉTRICOS TIPO PELICAN PARA EMBARCAÇÕES, COM CAPACIDADE ATÉ SETENTA TONELADAS PARA O PORTO DE PONTA DELGADA E PARA O PORTO DA HORTA",
    "preco_base": "2.000.000,00 EUR",
    "prazo_execucao": "6 MESES",
    "prazo_apresentacao_propostas": "04-09-2025 23:59",
    "fundos_eu": "Não",
    "plataforma_eletronica": "ACIN",
    "url_procedimento": "https://www.acingov.pt",
    "autor_nome": "Renata Maria Freitas Lima",
    "autor_cargo": "Técnica Administrativa"
  },
  {
    "numero_procedimento": "N/A",
    "entidade": "Autoridade da Concorrência (AdC)",
    "link": "https://diariodarepublica.pt/dr/detalhe/contrato-publico/21377-928299402",
    "detalhes_completos": "1 - IDENTIFICAÇÃO E CONTACTOS DA ENTIDADE ADJUDICANTE\nDesignação da entidade adjudicante: Autoridade da Concorrência (AdC)\nNIPC: 506557057\nServiço/Órgão/Pessoa de contacto: Unidade de Recursos Financeiros e Patrimoniais\nEndereço: Avenida de Berna, n.º 19\nCódigo postal: 1050-037\nLocalidade: Lisboa\nPaís: Portugal\nNUT III: PT170\nDistrito: Lisboa\nConcelho: Lisboa\nFreguesia: Freguesia de Avenidas Novas\nTelefone: 217902000\nFax: 217902099\nEndereço da Entidade (URL): www.concorrencia.pt\nEndereço Eletrónico: adc@concorrencia.pt\neDelivery Gateway (URL): https://www.acingov.pt\nFunção da Organização: Adquirente\nNorma jurídica da Entidade Adjudicante: Organismo de direito público\nÁrea de atividade da Autoridade Adjudicante: Serviços públicos das administrações públicas\n\n2 - JORNAL OFICIAL DA UNIÃO EUROPEIA\nO procedimento a que este anúncio diz respeito também é publicitado no Jornal Oficial da União Europeia? Não\n\n3 - AVISO\nModelo de Anúncio: Concurso público\nData de Envio do Anúncio: 07-08-2025\n\n5 - PROCESSO\nTipo de Procedimento: Concurso público\nPreço base do procedimento: Sim\nValor do preço base do procedimento: 160.000,00 EUR\nProcedimento com lotes? Não\n\n6 - OBJETO DO CONTRATO\nNúmero de referência interna: 119/URF/2025\nDesignação do contrato: Aquisição e instalação de mobiliário de postos de trabalho para colaboradores da AdC\nDescrição: Aquisição e instalação de mobiliário para a sede da Autoridade da Concorrência\nTipo de Contrato Principal: Aquisição de Bens Móveis\nTipo de Contrato: Aquisição de Bens Móveis\nClassificação CPV (Vocabulário Comum para os Contratos Públicos)\nObjeto principal\nVocabulário Principal: 39130000\nPreço base s/IVA: 160.000,00 EUR\n\n7 - INDICAÇÕES ADICIONAIS\nO contrato envolve aquisição conjunta (satisfação de várias entidades)? Não\nO contrato é adjudicado por uma central de compras? Não\n\n8 - TÉCNICAS\nO concurso destina-se à celebração de um acordo-quadro? Inexistência de acordo-quadro\nÉ utilizado um leilão eletrónico? Não\nÉ adotada uma fase de negociação? Não\nSistema de Aquisição Dinâmico: Inexistência de sistema de aquisição dinâmico\n\n9 - LOCAL DA EXECUÇÃO DO CONTRATO\nLOCAL DA EXECUÇÃO DO CONTRATO (PROCEDIMENTO)\nPaís: Portugal\nNUT III: PT170\nLocalidade: Freguesia de Campolide\nDistrito: Lisboa\nConcelho: Lisboa\nFreguesia: Freguesia de Campolide\n\n10 - PRAZO DE EXECUÇÃO DO CONTRATO\nPrazo de execução do contrato: 75 DIAS\nPrevisão de renovações: Não\n\n11 - FUNDOS EU\nTêm fundos EU? Não\n\n12 - DOCUMENTOS DE HABILITAÇÃO\nHabilitação para o exercício da atividade profissional: Não\n\n13 - CONDIÇÕES DE APRESENTAÇÃO\nPlataforma eletrónica utilizada pela entidade adjudicante: ACIN\nURL para Apresentação: https://www.acingov.pt\nAdmissibilidade da apresentação de propostas variantes: Não autorizado\nPrazo para apresentação das propostas: 19-09-2025 23:59\nPrazo durante o qual os concorrentes são obrigados a manter as respetivas propostas: 66 dias a contar do termo do prazo para a apresentação das propostas\nIndicação de Subcontratação na Proposta: Inexistência de indicação de subcontratação\n\n14 - PRESTAÇÃO DE CAUÇÃO\nPrestação de caução: Não\n\n15 - FORNECIMENTO DAS PEÇAS DO CONCURSO, APRESENTAÇÃO DE PEDIDOS DE PARTICIPAÇÃO E APRESENTAÇÃO DAS PROPOSTAS\nLink para acesso às peças do concurso (URL): https://www.acingov.pt/acingovprod/2/zonaPublica/zona_publica_c/donwloadProcedurePiece/OTMyNTg4\n\n20 - OUTROS REQUISITOS\nInformação sobre contratos reservados. Aplica-se a contratos reservados (54º-A)? Não\n\n21 - CRITÉRIO DE ADJUDICAÇÃO\nMultifator: Sim\nFator: \nNome: Outros\nOutro Nome: Prazo de Entrega e Montagem\nPonderação: 20%\nSubfatores: Não\nFator: \nNome: Outros\nOutro Nome: Prazo de Garantia\nPonderação: 5%\nSubfatores: Não\nFator: \nNome: Preço\nPonderação: 75%\nSubfatores: Não\n\n24 - CONDIÇÕES DO CONTRATO\nFaturação Eletrónica: Permitido\nObrigação de Subcontratação:\nCódigo da Obrigação de Subcontratação: Não é aplicável nenhuma obrigação de subcontratação.\n\n25 - COMPRA PÚBLICA ESTRATÉGICA\nCompra Pública Estratégica: Redução dos impactos ambientais\nDescrição do Processo de Adjudicação Estratégico: a) Componentes e/ou materiais recicláveis na composição dos bens; b) A madeira constante nos bens a fornecer deve ser obtida a partir de florestas com certificação de gestão sustentável, como por exemplo PEFC (Programme for the Endorsement of Forest Certification) e FSC (Forest Stewardship Council) ou o Rótulo Ecológico da EU.\nCritérios de contratos Públicos Ecológicos: Sem critérios de contratação pública ecológica\nCategorias da estratégia nacional: Outros\nOutra categoria (Descrição): Não aplicável\nContratos Públicos Ecológicos: A prevenção e o controlo da poluição\nDiretiva Veículos Não Poluentes: Não\nCritério de Acessibilidade: Os critérios de acessibilidade para as pessoas com deficiência não estão incluídos porque o contrato não se destina a pessoas singulares\n\n26 - INFORMAÇÕES ADICIONAIS\nContrato adequado para PME: Não\nCobertura ACP (Acordo dos Contratos Públicos da Organização Mundial do Comércio): Não\n\n27 - IDENTIFICAÇÃO E CONTACTOS DO ÓRGÃO DE RECURSOS ADMINISTRATIVOS\nDesignação: Conselho de Administração da Autoridade da Concorrência\nEndereço: Avenida de Berna, n.º 19\nCódigo postal: 1050-037\nLocalidade: Lisboa\nTelefone: 217902000\nFax: \nEndereço eletrónico: adc@concorrencia.pt\n\n28 - IDENTIFICAÇÃO DO(S) AUTOR(ES) DE ANÚNCIO\nNome: Maria Cristina Chora Fernandes\nCargo: Chefe de Unidade\n419415363",
    "nipc": "506557057",
    "distrito": "Lisboa",
    "concelho": "Lisboa",
    "freguesia": "Freguesia de Avenidas Novas",
    "site": "www.concorrencia.pt",
    "email": "adc@concorrencia.pt",
    "designacao_contrato": "Aquisição e instalação de mobiliário de postos de trabalho para colaboradores da AdC",
    "descricao": "Aquisição e instalação de mobiliário para a sede da Autoridade da Concorrência",
    "preco_base": "160.000,00 EUR",
    "prazo_execucao": "75 DIAS",
    "prazo_apresentacao_propostas": "19-09-2025 23:59",
    "fundos_eu": "Não",
    "plataforma_eletronica": "ACIN",
    "url_procedimento": "https://www.acingov.pt",
    "autor_nome": "Maria Cristina Chora Fernandes",
    "autor_cargo": "Chefe de Unidade"
  },
  {
    "numero_procedimento": "N/A",
    "entidade": "Portos dos Açores, SA",
    "link": "https://diariodarepublica.pt/dr/detalhe/contrato-publico/21378-928299403",
    "detalhes_completos": "1 - IDENTIFICAÇÃO E CONTACTOS DA ENTIDADE ADJUDICANTE\nDesignação da entidade adjudicante: Portos dos Açores, SA\nNIPC: 512077843\nServiço/Órgão/Pessoa de contacto: Portos dos Açores, SA\nEndereço: Avenida Gago Coutinho e Sacadura Cabral, nº 7\nCódigo postal: 9900-062\nLocalidade: Horta\nPaís: Portugal\nNUT III: PT200\nDistrito: Região Autónoma dos Açores\nConcelho: Todos\nFreguesia: Todas\nTelefone: 292208300\nFax: 292208315\nEndereço da Entidade (URL): www.portosdosacores.pt\nEndereço Eletrónico: geral@portosodosacores.pt\neDelivery Gateway (URL): https://www.acingov.pt\nFunção da Organização: Adquirente\nNorma jurídica da Entidade Adjudicante: Organismo de direito público\nÁrea de atividade da Autoridade Adjudicante: Serviços públicos das administrações públicas\n\n2 - JORNAL OFICIAL DA UNIÃO EUROPEIA\nO procedimento a que este anúncio diz respeito também é publicitado no Jornal Oficial da União Europeia? Sim\n\n3 - AVISO\nModelo de Anúncio: Concurso público\nData de Envio do Anúncio: 05-08-2025\n\n5 - PROCESSO\nTipo de Procedimento: Concurso público\nPreço base do procedimento: Sim\nValor do preço base do procedimento: 1.200.000,00 EUR\nProcedimento com lotes? Não\n\n6 - OBJETO DO CONTRATO\nNúmero de referência interna: CPI/4/2025/PA, SA\nDesignação do contrato: CONCURSO PÚBLICO PARA AQUISIÇÃO DE TRÊS ATRELADOS SLIPWAY TRAILER PARA EMBARCAÇÕES COM CAPACIDADE MÍNIMA DE OITENTA TONELADAS, PARA OS PORTOS DA HORTA, ANGRA DO HEROÍSMO E PONTA DELGADA - PORTOS DOS AÇORES, S.A\nDescrição: AQUISIÇÃO DE TRÊS ATRELADOS SLIPWAY TRAILER PARA EMBARCAÇÕES COM CAPACIDADE MÍNIMA DE OITENTA TONELADAS, PARA OS PORTOS DA HORTA, ANGRA DO HEROÍSMO E PONTA DELGADA - PORTOS DOS AÇORES, S.A\nOpções: Não\nTipo de Contrato Principal: Aquisição de Bens Móveis\nTipo de Contrato: Aquisição de Bens Móveis\nClassificação CPV (Vocabulário Comum para os Contratos Públicos)\nObjeto principal\nVocabulário Principal: 34223300\nPreço base s/IVA: 1.200.000,00 EUR\n\n7 - INDICAÇÕES ADICIONAIS\nO contrato envolve aquisição conjunta (satisfação de várias entidades)? Não\nO contrato é adjudicado por uma central de compras? Não\n\n8 - TÉCNICAS\nO concurso destina-se à celebração de um acordo-quadro? Inexistência de acordo-quadro\nÉ utilizado um leilão eletrónico? Não\nÉ adotada uma fase de negociação? Não\nSistema de Aquisição Dinâmico: Inexistência de sistema de aquisição dinâmico\n\n9 - LOCAL DA EXECUÇÃO DO CONTRATO\nLOCAL DA EXECUÇÃO DO CONTRATO (PROCEDIMENTO)\nPaís: Portugal\nNUT III: PT200\nLocalidade: Angra do Heroísmo\nDistrito: Região Autónoma dos Açores\nConcelho: Angra do Heroismo\nFreguesia: Todas\nPaís: Portugal\nNUT III: PT200\nLocalidade: Horta\nDistrito: Região Autónoma dos Açores\nConcelho: Horta\nFreguesia: Todas\nPaís: Portugal\nNUT III: PT200\nLocalidade: Ponta Delgada\nDistrito: Região Autónoma dos Açores\nConcelho: Ponta Delgada\nFreguesia: Todas\n\n10 - PRAZO DE EXECUÇÃO DO CONTRATO\nPrazo de execução do contrato: 6 MESES\nPrevisão de renovações: Não\n\n11 - FUNDOS EU\nTêm fundos EU? Não\n\n12 - DOCUMENTOS DE HABILITAÇÃO\nHabilitação para o exercício da atividade profissional: Sim\nTipo: Outros\nDescrição - Outros: Conforme Peças do Procedimento\nDescrição: Documentos de Habilitação\n\n13 - CONDIÇÕES DE APRESENTAÇÃO\nPlataforma eletrónica utilizada pela entidade adjudicante: ACIN\nURL para Apresentação: https://www.acingov.pt\nAdmissibilidade da apresentação de propostas variantes: Não autorizado\nPrazo para apresentação das propostas: 04-09-2025 23:59\nPrazo durante o qual os concorrentes são obrigados a manter as respetivas propostas: 70 dias a contar do termo do prazo para a apresentação das propostas\nApresentação de Catálogo Eletrónico: Permitido\nIndicação de Subcontratação na Proposta: Inexistência de indicação de subcontratação\n\n14 - PRESTAÇÃO DE CAUÇÃO\nPrestação de caução: Sim\nPercentagem: 2%\nDescrição da Garantia Exigida: O valor da caução é de 2.00% do preço contratual.\n\n15 - FORNECIMENTO DAS PEÇAS DO CONCURSO, APRESENTAÇÃO DE PEDIDOS DE PARTICIPAÇÃO E APRESENTAÇÃO DAS PROPOSTAS\nLink para acesso às peças do concurso (URL): https://www.acingov.pt/acingovprod/2/zonaPublica/zona_publica_c/donwloadProcedurePiece/OTMxNzc2\n\n20 - OUTROS REQUISITOS\nInformação sobre contratos reservados. Aplica-se a contratos reservados (54º-A)? Não\n\n21 - CRITÉRIO DE ADJUDICAÇÃO\nMultifator: Sim\nFator: \nNome: Preço\nPonderação: 50%\nSubfatores: Não\nFator: \nNome: Serviço e assistência técnica pós-venda e condições de entrega\nPonderação: 5%\nSubfatores: Não\nFator: \nNome: Qualidade\nPonderação: 45%\nSubfatores: Não\n\n24 - CONDIÇÕES DO CONTRATO\nFaturação Eletrónica: Permitido\nObrigação de Subcontratação:\nCódigo da Obrigação de Subcontratação: Não é aplicável nenhuma obrigação de subcontratação.\n\n25 - COMPRA PÚBLICA ESTRATÉGICA\nCompra Pública Estratégica: Inexistência de contratação pública estratégica\n\n26 - INFORMAÇÕES ADICIONAIS\nContrato adequado para PME: Não\nCobertura ACP (Acordo dos Contratos Públicos da Organização Mundial do Comércio): Não\n\n27 - IDENTIFICAÇÃO E CONTACTOS DO ÓRGÃO DE RECURSOS ADMINISTRATIVOS\nDesignação: Conselho de Administração\nEndereço: Avenida Gago Coutinho e Sacadura Cabral, nº 7\nCódigo postal: 9900-062\nLocalidade: Horta\nTelefone: 292208300\nFax: \nEndereço eletrónico: geral@portosdosacores.pt\n\n28 - IDENTIFICAÇÃO DO(S) AUTOR(ES) DE ANÚNCIO\nNome: Renata Maria Freitas Lima\nCargo: Técnica Administrativa\n419405205",
    "nipc": "512077843",
    "distrito": "Região Autónoma dos Açores",
    "concelho": "Todos",
    "freguesia": "Todas",
    "site": "www.portosdosacores.pt",
    "email": "geral@portosodosacores.pt",
    "designacao_contrato": "CONCURSO PÚBLICO PARA AQUISIÇÃO DE TRÊS ATRELADOS SLIPWAY TRAILER PARA EMBARCAÇÕES COM CAPACIDADE MÍNIMA DE OITENTA TONELADAS, PARA OS PORTOS DA HORTA, ANGRA DO HEROÍSMO E PONTA DELGADA - PORTOS DOS AÇORES, S.A",
    "descricao": "AQUISIÇÃO DE TRÊS ATRELADOS SLIPWAY TRAILER PARA EMBARCAÇÕES COM CAPACIDADE MÍNIMA DE OITENTA TONELADAS, PARA OS PORTOS DA HORTA, ANGRA DO HEROÍSMO E PONTA DELGADA - PORTOS DOS AÇORES, S.A",
    "preco_base": "1.200.000,00 EUR",
    "prazo_execucao": "6 MESES",
    "prazo_apresentacao_propostas": "04-09-2025 23:59",
    "fundos_eu": "Não",
    "plataforma_eletronica": "ACIN",
    "url_procedimento": "https://www.acingov.pt",
    "autor_nome": "Renata Maria Freitas Lima",
    "autor_cargo": "Técnica Administrativa"
  },
  {
    "numero_procedimento": "N/A",
    "entidade": "Serviços de Acção Social da Universidade do Minho",
    "link": "https://diariodarepublica.pt/dr/detalhe/contrato-publico/21379-928299411",
    "detalhes_completos": "1 - IDENTIFICAÇÃO E CONTACTOS DA ENTIDADE ADJUDICANTE\nDesignação da entidade adjudicante: Serviços de Acção Social da Universidade do Minho\nNIPC: 680047360\nServiço/Órgão/Pessoa de contacto: Serviços de Acção Social da Universidade do Minho\nEndereço: Campus de Gualtar\nCódigo postal: 4710-057\nLocalidade: Braga\nPaís: Portugal\nNUT III: PT112\nDistrito: Braga\nConcelho: Braga\nFreguesia: Freguesia de Gualtar\nTelefone: 253601450\nFax: 253601451\nEndereço da Entidade (URL): www.sas.uminho.pt\nEndereço Eletrónico: sas@sas.uminho.pt\neDelivery Gateway (URL): https://www.acingov.pt\nFunção da Organização: Adquirente\nNorma jurídica da Entidade Adjudicante: Organismo de direito público\nÁrea de atividade da Autoridade Adjudicante: Serviços públicos das administrações públicas\n\n2 - JORNAL OFICIAL DA UNIÃO EUROPEIA\nO procedimento a que este anúncio diz respeito também é publicitado no Jornal Oficial da União Europeia? Não\n\n3 - AVISO\nModelo de Anúncio: Concurso público\nData de Envio do Anúncio: 08-08-2025\n\n5 - PROCESSO\nTipo de Procedimento: Concurso público\nPreço base do procedimento: Sim\nValor do preço base do procedimento: 73.040,88 EUR\nProcedimento com lotes? Sim\nNº Máx. de Lotes Autorizado: 9\nNúmero máximo de lotes que podem ser adjudicados a um concorrente: 9\n\n6 - OBJETO DO CONTRATO\nNúmero de referência interna: CP 029/2025\nDesignação do contrato: CP 029/2025- Aquisição de refrigerantes e sumos de fruta, por lotes\nDescrição: CP 029/2025- Aquisição de refrigerantes e sumos de fruta, por lotes\nTipo de Contrato Principal: Aquisição de Bens Móveis\nTipo de Contrato: Aquisição de Bens Móveis\nClassificação CPV (Vocabulário Comum para os Contratos Públicos)\nObjeto principal\nVocabulário Principal: 15321000\nPreço base s/IVA: 38.274,60 EUR\nObjeto Complementar\nVocabulário Principal: 15982000\nPreço base s/IVA: 34.766,28 EUR\nLotes: \nNº: LOT-0001\nDescrição do Lote: NECTAR DE FRUTA CARTÃO LITRO - COMPAL VARIOS SABORES DO TIPO OU EQUIVALENTE\nPreço base s/IVA: 2.213,40 EUR\nClassificação CPV (Vocabulário Comum para os Contratos Públicos)\nObjeto principal\nVocabulário Principal: 15321000\nNº: LOT-0002\nDescrição do Lote: NECTAR DE FRUTA FRASCO VIDRO 20CL - COMPAL DO TIPO OU EQUIVALENTE DIVERSOS SABORES\nPreço base s/IVA: 36.061,20 EUR\nClassificação CPV (Vocabulário Comum para os Contratos Públicos)\nObjeto principal\nVocabulário Principal: 15321000\nNº: LOT-0003\nDescrição do Lote: REFR. CARTÃO TETRAPAK 33 CL - SANTAL DO TIPO OU EQUIVALENTE - DIVERSOS SABORES\nPreço base s/IVA: 1.984,32 EUR\nClassificação CPV (Vocabulário Comum para os Contratos Públicos)\nObjeto principal\nVocabulário Principal: 15982000\nNº: LOT-0004\nDescrição do Lote: REFR.LATA 33CL - COCA-COLA DO TIPO OU EQUIVALENTE\nPreço base s/IVA: 14.698,12 EUR\nClassificação CPV (Vocabulário Comum para os Contratos Públicos)\nObjeto principal\nVocabulário Principal: 15982000\nNº: LOT-0005\nDescrição do Lote: REFR.LATA 33CL - FANTA DO TIPO OU EQUIVALENTE DIVERSOS SABORES\nPreço base s/IVA: 4.003,20 EUR\nClassificação CPV (Vocabulário Comum para os Contratos Públicos)\nObjeto principal\nVocabulário Principal: 15982000\nNº: LOT-0006\nDescrição do Lote: REFR.LATA 33CL - GUARANÁ ANTÁRCTICA DO TIPO OU EQUIVALENTE\nPreço base s/IVA: 1.440,00 EUR\nClassificação CPV (Vocabulário Comum para os Contratos Públicos)\nObjeto principal\nVocabulário Principal: 15982000\nNº: LOT-0007\nDescrição do Lote: REFR.LATA 33CL - SEVEN-UP DO TIPO OU EQUIVALENTE\nPreço base s/IVA: 1.872,00 EUR\nClassificação CPV (Vocabulário Comum para os Contratos Públicos)\nObjeto principal\nVocabulário Principal: 15982000\nNº: LOT-0008\nDescrição do Lote: REFR.LATA 33CL - ICE TEA LIPTON DO TIPO OU EQUIVALENTE\nPreço base s/IVA: 9.824,64 EUR\nClassificação CPV (Vocabulário Comum para os Contratos Públicos)\nObjeto principal\nVocabulário Principal: 15982000\nNº: LOT-0009\nDescrição do Lote: REFR. GARRAFA 1,5L S/GÁS- JOI LARANJA VARIOS SABORES DO TIPO OU EQUIVALENTE\nPreço base s/IVA: 944,00 EUR\nClassificação CPV (Vocabulário Comum para os Contratos Públicos)\nObjeto principal\nVocabulário Principal: 15982000\n\n7 - INDICAÇÕES ADICIONAIS\nO contrato envolve aquisição conjunta (satisfação de várias entidades)? Não\nO contrato é adjudicado por uma central de compras? Não\n\n8 - TÉCNICAS\nO concurso destina-se à celebração de um acordo-quadro? Inexistência de acordo-quadro\nÉ utilizado um leilão eletrónico? Não\nÉ adotada uma fase de negociação? Não\nSistema de Aquisição Dinâmico: Inexistência de sistema de aquisição dinâmico\n\n9 - LOCAL DA EXECUÇÃO DO CONTRATO\nLOCAL DA EXECUÇÃO DO CONTRATO (PROCEDIMENTO)\nPaís: Portugal\nNUT III: PT111\nLocalidade: Braga\nDistrito: Braga\nConcelho: Braga\nFreguesia: Todas\nLOCAL DA EXECUÇÃO DO CONTRATO (LOTE)\nIdentificador do Lote: LOT-0001; LOT-0002; LOT-0003; LOT-0004; LOT-0005; LOT-0006; LOT-0007; LOT-0008; LOT-0009\nPaís: Portugal\nNUT III: PT111\nLocalidade: Braga\nDistrito: Braga\nConcelho: Braga\nFreguesia: Todas\n\n10 - PRAZO DE EXECUÇÃO DO CONTRATO\nIdentificador do Lote: LOT-0001; LOT-0002; LOT-0003; LOT-0004; LOT-0005; LOT-0006; LOT-0007; LOT-0008; LOT-0009\nPrazo de execução do contrato: 11 MESES\nPrevisão de renovações: Não\n\n11 - FUNDOS EU\nIdentificador do Lote: LOT-0001; LOT-0002; LOT-0003; LOT-0004; LOT-0005; LOT-0006; LOT-0007; LOT-0008; LOT-0009\nTêm fundos EU? Não\n\n12 - DOCUMENTOS DE HABILITAÇÃO\nHabilitação para o exercício da atividade profissional: Não\n\n13 - CONDIÇÕES DE APRESENTAÇÃO\nPlataforma eletrónica utilizada pela entidade adjudicante: ACIN\nURL para Apresentação: https://www.acingov.pt\nAdmissibilidade da apresentação de propostas variantes: Não autorizado\nPrazo para apresentação das propostas: 31-08-2025 23:59\nPrazo durante o qual os concorrentes são obrigados a manter as respetivas propostas: 66 dias a contar do termo do prazo para a apresentação das propostas\nIndicação de Subcontratação na Proposta: Inexistência de indicação de subcontratação\n\n14 - PRESTAÇÃO DE CAUÇÃO\nPrestação de caução: Não\n\n15 - FORNECIMENTO DAS PEÇAS DO CONCURSO, APRESENTAÇÃO DE PEDIDOS DE PARTICIPAÇÃO E APRESENTAÇÃO DAS PROPOSTAS\nLink para acesso às peças do concurso (URL): https://www.acingov.pt/acingovprod/2/zonaPublica/zona_publica_c/donwloadProcedurePiece/OTMyNDk2\n\n20 - OUTROS REQUISITOS\nIdentificador do Lote: LOT-0001; LOT-0002; LOT-0003; LOT-0004; LOT-0005; LOT-0006; LOT-0007; LOT-0008; LOT-0009\nInformação sobre contratos reservados. Aplica-se a contratos reservados (54º-A)? Não\n\n21 - CRITÉRIO DE ADJUDICAÇÃO\nO Critério de adjudicação é diferenciado por lote? Não\nMultifator: Sim\nFator: \nNome: Preço\nPonderação: 40%\nSubfatores: Não\nFator: \nNome: Qualidade\nPonderação: 60%\nSubfatores: Não\n\n24 - CONDIÇÕES DO CONTRATO\nIdentificador do Lote: LOT-0001; LOT-0002; LOT-0003; LOT-0004; LOT-0005; LOT-0006; LOT-0007; LOT-0008; LOT-0009\nFaturação Eletrónica: Permitido\nObrigação de Subcontratação:\nCódigo da Obrigação de Subcontratação: Não é aplicável nenhuma obrigação de subcontratação.\n\n25 - COMPRA PÚBLICA ESTRATÉGICA\nCompra Pública Estratégica: Inexistência de contratação pública estratégica\n\n26 - INFORMAÇÕES ADICIONAIS\nIdentificador do Lote: LOT-0001; LOT-0002; LOT-0003; LOT-0004; LOT-0005; LOT-0006; LOT-0007; LOT-0008; LOT-0009\nContrato adequado para PME: Não\nCobertura ACP (Acordo dos Contratos Públicos da Organização Mundial do Comércio): Não\n\n27 - IDENTIFICAÇÃO E CONTACTOS DO ÓRGÃO DE RECURSOS ADMINISTRATIVOS\nDesignação: Reitor da Universidade do Minho\nEndereço: campus de Gualtar\nCódigo postal: 4710-057\nLocalidade: GUALTAR\nTelefone: 253601450\nFax: \nEndereço eletrónico: sas@sas.uminho.pt\n\n28 - IDENTIFICAÇÃO DO(S) AUTOR(ES) DE ANÚNCIO\nNome: Paula Alexandra Seixas\nCargo: Administradora SASUM\n419412122",
    "nipc": "680047360",
    "distrito": "Braga",
    "concelho": "Braga",
    "freguesia": "Freguesia de Gualtar",
    "site": "www.sas.uminho.pt",
    "email": "sas@sas.uminho.pt",
    "designacao_contrato": "CP 029/2025- Aquisição de refrigerantes e sumos de fruta, por lotes",
    "descricao": "CP 029/2025- Aquisição de refrigerantes e sumos de fruta, por lotes",
    "preco_base": "38.274,60 EUR",
    "prazo_execucao": "11 MESES",
    "prazo_apresentacao_propostas": "31-08-2025 23:59",
    "fundos_eu": "Não",
    "plataforma_eletronica": "ACIN",
    "url_procedimento": "https://www.acingov.pt",
    "autor_nome": "Paula Alexandra Seixas",
    "autor_cargo": "Administradora SASUM"
  },
  {
    "numero_procedimento": "N/A",
    "entidade": "Serviços de Acção Social da Universidade do Minho",
    "link": "https://diariodarepublica.pt/dr/detalhe/contrato-publico/21380-928299412",
    "detalhes_completos": "1 - IDENTIFICAÇÃO E CONTACTOS DA ENTIDADE ADJUDICANTE\nDesignação da entidade adjudicante: Serviços de Acção Social da Universidade do Minho\nNIPC: 680047360\nServiço/Órgão/Pessoa de contacto: Serviços de Acção Social da Universidade do Minho\nEndereço: Campus de Gualtar\nCódigo postal: 4710-057\nLocalidade: Braga\nPaís: Portugal\nNUT III: PT112\nDistrito: Braga\nConcelho: Braga\nFreguesia: Freguesia de Gualtar\nTelefone: 253601450\nFax: 253601451\nEndereço da Entidade (URL): www.sas.uminho.pt\nEndereço Eletrónico: sas@sas.uminho.pt\neDelivery Gateway (URL): https://www.acingov.pt\nFunção da Organização: Adquirente\nNorma jurídica da Entidade Adjudicante: Organismo de direito público\nÁrea de atividade da Autoridade Adjudicante: Serviços públicos das administrações públicas\n\n2 - JORNAL OFICIAL DA UNIÃO EUROPEIA\nO procedimento a que este anúncio diz respeito também é publicitado no Jornal Oficial da União Europeia? Não\n\n3 - AVISO\nModelo de Anúncio: Concurso público\nData de Envio do Anúncio: 08-08-2025\n\n5 - PROCESSO\nTipo de Procedimento: Concurso público\nPreço base do procedimento: Sim\nValor do preço base do procedimento: 136.150,00 EUR\nProcedimento com lotes? Não\n\n6 - OBJETO DO CONTRATO\nNúmero de referência interna: CP 028/2025\nDesignação do contrato: CP 028/2025 - prestação de serviços desportivos na área de musculação, fitness e natação\nDescrição: CP 028/2025 - prestação de serviços desportivos na área de musculação, fitness e natação\nTipo de Contrato Principal: Aquisição de Serviços\nTipo de Contrato: Aquisição de Serviços\nClassificação CPV (Vocabulário Comum para os Contratos Públicos)\nObjeto principal\nVocabulário Principal: 92622000\nPreço base s/IVA: 136.150,00 EUR\n\n7 - INDICAÇÕES ADICIONAIS\nO contrato envolve aquisição conjunta (satisfação de várias entidades)? Não\nO contrato é adjudicado por uma central de compras? Não\n\n8 - TÉCNICAS\nO concurso destina-se à celebração de um acordo-quadro? Inexistência de acordo-quadro\nÉ utilizado um leilão eletrónico? Não\nÉ adotada uma fase de negociação? Não\nSistema de Aquisição Dinâmico: Inexistência de sistema de aquisição dinâmico\n\n9 - LOCAL DA EXECUÇÃO DO CONTRATO\nLOCAL DA EXECUÇÃO DO CONTRATO (PROCEDIMENTO)\nPaís: Portugal\nNUT III: PT111\nLocalidade: Braga\nDistrito: Braga\nConcelho: Braga\nFreguesia: Todas\n\n10 - PRAZO DE EXECUÇÃO DO CONTRATO\nPrazo de execução do contrato: 2 ANOS\nPrevisão de renovações: Não\n\n11 - FUNDOS EU\nTêm fundos EU? Não\n\n12 - DOCUMENTOS DE HABILITAÇÃO\nHabilitação para o exercício da atividade profissional: Não\n\n13 - CONDIÇÕES DE APRESENTAÇÃO\nPlataforma eletrónica utilizada pela entidade adjudicante: ACIN\nURL para Apresentação: https://www.acingov.pt\nAdmissibilidade da apresentação de propostas variantes: Não autorizado\nPrazo para apresentação das propostas: 25-08-2025 23:59\nPrazo durante o qual os concorrentes são obrigados a manter as respetivas propostas: 66 dias a contar do termo do prazo para a apresentação das propostas\nIndicação de Subcontratação na Proposta: Inexistência de indicação de subcontratação\n\n14 - PRESTAÇÃO DE CAUÇÃO\nPrestação de caução: Não\n\n15 - FORNECIMENTO DAS PEÇAS DO CONCURSO, APRESENTAÇÃO DE PEDIDOS DE PARTICIPAÇÃO E APRESENTAÇÃO DAS PROPOSTAS\nLink para acesso às peças do concurso (URL): https://www.acingov.pt/acingovprod/2/zonaPublica/zona_publica_c/donwloadProcedurePiece/OTMyNjQx\n\n20 - OUTROS REQUISITOS\nInformação sobre contratos reservados. Aplica-se a contratos reservados (54º-A)? Não\n\n21 - CRITÉRIO DE ADJUDICAÇÃO\nMultifator: Não\nMonofator:\nNome: Outros\nOutro nome: Fator Preço\n\n24 - CONDIÇÕES DO CONTRATO\nFaturação Eletrónica: Permitido\nObrigação de Subcontratação:\nCódigo da Obrigação de Subcontratação: Não é aplicável nenhuma obrigação de subcontratação.\n\n25 - COMPRA PÚBLICA ESTRATÉGICA\nCompra Pública Estratégica: Inexistência de contratação pública estratégica\n\n26 - INFORMAÇÕES ADICIONAIS\nContrato adequado para PME: Não\nCobertura ACP (Acordo dos Contratos Públicos da Organização Mundial do Comércio): Não\n\n27 - IDENTIFICAÇÃO E CONTACTOS DO ÓRGÃO DE RECURSOS ADMINISTRATIVOS\nDesignação: Não definido\nEndereço: Campus de Gualtar\nCódigo postal: 4710-057\nLocalidade: GUALTAR\nTelefone: 253601450\nFax: \nEndereço eletrónico: sas@sas.uminho.pt\n\n28 - IDENTIFICAÇÃO DO(S) AUTOR(ES) DE ANÚNCIO\nNome: Paula Alexandra Seixas\nCargo: Administradora SASUM\n419415136",
    "nipc": "680047360",
    "distrito": "Braga",
    "concelho": "Braga",
    "freguesia": "Freguesia de Gualtar",
    "site": "www.sas.uminho.pt",
    "email": "sas@sas.uminho.pt",
    "designacao_contrato": "CP 028/2025 - prestação de serviços desportivos na área de musculação, fitness e natação",
    "descricao": "CP 028/2025 - prestação de serviços desportivos na área de musculação, fitness e natação",
    "preco_base": "136.150,00 EUR",
    "prazo_execucao": "2 ANOS",
    "prazo_apresentacao_propostas": "25-08-2025 23:59",
    "fundos_eu": "Não",
    "plataforma_eletronica": "ACIN",
    "url_procedimento": "https://www.acingov.pt",
    "autor_nome": "Paula Alexandra Seixas",
    "autor_cargo": "Administradora SASUM"
  }
]