[
  {
    "numero_procedimento": "N/A",
    "entidade": "AnÃºncio de procedimento  n.Âº 23696/2025  -  DiÃ¡rio da RepÃºblica n.Âº 172/2025, SÃ©rie II de 2025-09-08",
    "link": "https://diariodarepublica.pt/dr/detalhe/contrato-publico/23696-934420437"
  },
  {
    "numero_procedimento": "N/A",
    "entidade": "AnÃºncio de procedimento  n.Âº 23702/2025  -  DiÃ¡rio da RepÃºblica n.Âº 172/2025, SÃ©rie II de 2025-09-08",
    "link": "https://diariodarepublica.pt/dr/detalhe/contrato-publico/23702-934420438"
  },
  {
    "numero_procedimento": "N/A",
    "entidade": "AnÃºncio de procedimento  n.Âº 23703/2025  -  DiÃ¡rio da RepÃºblica n.Âº 172/2025, SÃ©rie II de 2025-09-08",
    "link": "https://diariodarepublica.pt/dr/detalhe/contrato-publico/23703-934420439"
  },
  {
    "numero_procedimento": "N/A",
    "entidade": "AnÃºncio de procedimento  n.Âº 23695/2025  -  DiÃ¡rio da RepÃºblica n.Âº 172/2025, SÃ©rie II de 2025-09-08",
    "link": "https://diariodarepublica.pt/dr/detalhe/contrato-publico/23695-934422143"
  },
  {
    "numero_procedimento": "N/A",
    "entidade": "AnÃºncio de procedimento  n.Âº 23697/2025  -  DiÃ¡rio da RepÃºblica n.Âº 172/2025, SÃ©rie II de 2025-09-08",
    "link": "https://diariodarepublica.pt/dr/detalhe/contrato-publico/23697-934422144"
  },
  {
    "numero_procedimento": "N/A",
    "entidade": "AnÃºncio de procedimento  n.Âº 23698/2025  -  DiÃ¡rio da RepÃºblica n.Âº 172/2025, SÃ©rie II de 2025-09-08",
    "link": "https://diariodarepublica.pt/dr/detalhe/contrato-publico/23698-934422145"
  },
  {
    "numero_procedimento": "N/A",
    "entidade": "AnÃºncio de procedimento  n.Âº 23699/2025  -  DiÃ¡rio da RepÃºblica n.Âº 172/2025, SÃ©rie II de 2025-09-08",
    "link": "https://diariodarepublica.pt/dr/detalhe/contrato-publico/23699-934454761"
  },
  {
    "numero_procedimento": "N/A",
    "entidade": "AnÃºncio de procedimento  n.Âº 23700/2025  -  DiÃ¡rio da RepÃºblica n.Âº 172/2025, SÃ©rie II de 2025-09-08",
    "link": "https://diariodarepublica.pt/dr/detalhe/contrato-publico/23700-934454762"
  },
  {
    "numero_procedimento": "N/A",
    "entidade": "AnÃºncio de procedimento  n.Âº 23701/2025  -  DiÃ¡rio da RepÃºblica n.Âº 172/2025, SÃ©rie II de 2025-09-08",
    "link": "https://diariodarepublica.pt/dr/detalhe/contrato-publico/23701-934454763"
  },
  {
    "numero_procedimento": "N/A",
    "entidade": "AnÃºncio de procedimento  n.Âº 23704/2025  -  DiÃ¡rio da RepÃºblica n.Âº 172/2025, SÃ©rie II de 2025-09-08",
    "link": "https://diariodarepublica.pt/dr/detalhe/contrato-publico/23704-934454764"
  },
  {
    "numero_procedimento": "N/A",
    "entidade": "AnÃºncio de procedimento  n.Âº 23706/2025  -  DiÃ¡rio da RepÃºblica n.Âº 172/2025, SÃ©rie II de 2025-09-08",
    "link": "https://diariodarepublica.pt/dr/detalhe/contrato-publico/23706-934454765"
  },
  {
    "numero_procedimento": "N/A",
    "entidade": "AnÃºncio de procedimento  n.Âº 23707/2025  -  DiÃ¡rio da RepÃºblica n.Âº 172/2025, SÃ©rie II de 2025-09-08",
    "link": "https://diariodarepublica.pt/dr/detalhe/contrato-publico/23707-934454766"
  },
  {
    "numero_procedimento": "N/A",
    "entidade": "AnÃºncio de procedimento  n.Âº 23708/2025  -  DiÃ¡rio da RepÃºblica n.Âº 172/2025, SÃ©rie II de 2025-09-08",
    "link": "https://diariodarepublica.pt/dr/detalhe/contrato-publico/23708-934454767"
  },
  {
    "numero_procedimento": "N/A",
    "entidade": "AnÃºncio de procedimento  n.Âº 23710/2025  -  DiÃ¡rio da RepÃºblica n.Âº 172/2025, SÃ©rie II de 2025-09-08",
    "link": "https://diariodarepublica.pt/dr/detalhe/contrato-publico/23710-934454768"
  },
  {
    "numero_procedimento": "N/A",
    "entidade": "AnÃºncio de procedimento  n.Âº 23715/2025  -  DiÃ¡rio da RepÃºblica n.Âº 172/2025, SÃ©rie II de 2025-09-08",
    "link": "https://diariodarepublica.pt/dr/detalhe/contrato-publico/23715-934454769"
  },
  {
    "numero_procedimento": "N/A",
    "entidade": "AnÃºncio de procedimento  n.Âº 23717/2025  -  DiÃ¡rio da RepÃºblica n.Âº 172/2025, SÃ©rie II de 2025-09-08",
    "link": "https://diariodarepublica.pt/dr/detalhe/contrato-publico/23717-934454770"
  },
  {
    "numero_procedimento": "N/A",
    "entidade": "AnÃºncio de procedimento  n.Âº 23719/2025  -  DiÃ¡rio da RepÃºblica n.Âº 172/2025, SÃ©rie II de 2025-09-08",
    "link": "https://diariodarepublica.pt/dr/detalhe/contrato-publico/23719-934454771"
  },
  {
    "numero_procedimento": "N/A",
    "entidade": "AnÃºncio de procedimento  n.Âº 23721/2025  -  DiÃ¡rio da RepÃºblica n.Âº 172/2025, SÃ©rie II de 2025-09-08",
    "link": "https://diariodarepublica.pt/dr/detalhe/contrato-publico/23721-934454772"
  },
  {
    "numero_procedimento": "N/A",
    "entidade": "AnÃºncio de procedimento  n.Âº 23722/2025  -  DiÃ¡rio da RepÃºblica n.Âº 172/2025, SÃ©rie II de 2025-09-08",
    "link": "https://diariodarepublica.pt/dr/detalhe/contrato-publico/23722-934454773"
  },
  {
    "numero_procedimento": "N/A",
    "entidade": "AnÃºncio de procedimento  n.Âº 23723/2025  -  DiÃ¡rio da RepÃºblica n.Âº 172/2025, SÃ©rie II de 2025-09-08",
    "link": "https://diariodarepublica.pt/dr/detalhe/contrato-publico/23723-934454774"
  },
  {
    "numero_procedimento": "N/A",
    "entidade": "AnÃºncio de procedimento  n.Âº 23705/2025  -  DiÃ¡rio da RepÃºblica n.Âº 172/2025, SÃ©rie II de 2025-09-08",
    "link": "https://diariodarepublica.pt/dr/detalhe/contrato-publico/23705-934464551"
  },
  {
    "numero_procedimento": "N/A",
    "entidade": "Unidade Local de Saúde de Coimbra, E. P. E.",
    "link": "https://diariodarepublica.pt/dr/detalhe/contrato-publico/23709-934464552",
    "detalhes_completos": "1 - IDENTIFICAÇÃO E CONTACTOS DA ENTIDADE ADJUDICANTE\nDesignação da entidade adjudicante: Unidade Local de Saúde de Coimbra, E. P. E.\nNIPC: 510103448\nEndereço: Praceta Prof. Mota Pinto\nCódigo postal: 3004-561\nLocalidade: Coimbra\nPaís: Portugal\nNUT III: PT16E\nDistrito: Coimbra\nConcelho: Coimbra\nFreguesia: Todas\nTelefone: 239400605\nFax: 239400605\nEndereço da Entidade (URL): https://www.chuc.min-saude.pt\nEndereço Eletrónico: ana.rosete@ulscoimbra.min-saude.pt\neDelivery Gateway (URL): https://community.vortal.biz/public/\nFunção da Organização: Adquirente\nNorma jurídica da Entidade Adjudicante: Organismo de direito público\nÁrea de atividade da Autoridade Adjudicante: Saúde\n\n2 - JORNAL OFICIAL DA UNIÃO EUROPEIA\nO procedimento a que este anúncio diz respeito também é publicitado no Jornal Oficial da União Europeia? Sim\n\n3 - AVISO\nModelo de Anúncio: Concurso público\nData de Envio do Anúncio: 04-09-2025\n\n5 - PROCESSO\nTipo de Procedimento: Concurso público\nPreço base do procedimento: Sim\nValor do preço base do procedimento: 285.000,00 EUR\nProcedimento com lotes? Não\n\n6 - OBJETO DO CONTRATO\nNúmero de referência interna: 010200582025\nDesignação do contrato: Sistemas de Assistência Ventricular Implantável de Longa Duração\nDescrição: Sistemas de Assistência Ventricular Implantável de Longa Duração\nOpções: Não\nTipo de Contrato Principal: Aquisição de Bens Móveis\nTipo de Contrato: Aquisição de Bens Móveis\nClassificação CPV (Vocabulário Comum para os Contratos Públicos)\nObjeto principal\nVocabulário Principal: 33100000\nPreço base s/IVA: 285.000,00 EUR\n\n7 - INDICAÇÕES ADICIONAIS\nO contrato envolve aquisição conjunta (satisfação de várias entidades)? Não\nO contrato é adjudicado por uma central de compras? Não\n\n8 - TÉCNICAS\nO concurso destina-se à celebração de um acordo-quadro? Inexistência de acordo-quadro\nÉ utilizado um leilão eletrónico? Não\nÉ adotada uma fase de negociação? Não\nSistema de Aquisição Dinâmico: Inexistência de sistema de aquisição dinâmico\n\n9 - LOCAL DA EXECUÇÃO DO CONTRATO\nLOCAL DA EXECUÇÃO DO CONTRATO (PROCEDIMENTO)\nPaís: Portugal\nNUT III: PT16E\nLocalidade: Coimbra\nDistrito: Coimbra\nConcelho: Coimbra\nFreguesia: Freguesia de Santo António dos Olivais\n\n10 - PRAZO DE EXECUÇÃO DO CONTRATO\nPrazo de execução do contrato: 3 MESES\nPrevisão de renovações: Não\n\n11 - FUNDOS EU\nTêm fundos EU? Não\n\n12 - DOCUMENTOS DE HABILITAÇÃO\nHabilitação para o exercício da atividade profissional: Não\n\n13 - CONDIÇÕES DE APRESENTAÇÃO\nPlataforma eletrónica utilizada pela entidade adjudicante: VORTAL\nURL para Apresentação: https://community.vortal.biz/public/\nAdmissibilidade da apresentação de propostas variantes: Não autorizado\nPrazo para apresentação das propostas: 07-10-2025 23:59\nPrazo durante o qual os concorrentes são obrigados a manter as respetivas propostas: 90 dias a contar do termo do prazo para a apresentação das propostas\nApresentação de Catálogo Eletrónico: Não autorizado\nIndicação de Subcontratação na Proposta: Inexistência de indicação de subcontratação\n\n14 - PRESTAÇÃO DE CAUÇÃO\nPrestação de caução: Não\n\n15 - FORNECIMENTO DAS PEÇAS DO CONCURSO, APRESENTAÇÃO DE PEDIDOS DE PARTICIPAÇÃO E APRESENTAÇÃO DAS PROPOSTAS\nLink para acesso às peças do concurso (URL): https://community.vortal.biz/Public/public-tender-documents/MmR2N1Vhdy83UG5nd3pRajcraHN0cElNQmlRd2p6dFc2THk3S0RjNzFTeHp2dE5tNFB0emYvYkF3WjVhVlNPVU81d1dKZk5Ob1hubEdCSG80cHJqRGc9PTBBIzAj\n\n20 - OUTROS REQUISITOS\nInformação sobre contratos reservados. Aplica-se a contratos reservados (54º-A)? Não\n\n21 - CRITÉRIO DE ADJUDICAÇÃO\nMultifator: Não\nMonofator:\nNome: Outros\nOutro nome: Preço\n\n24 - CONDIÇÕES DO CONTRATO\nFaturação Eletrónica: Permitido\nObrigação de Subcontratação:\nCódigo da Obrigação de Subcontratação: Não é aplicável nenhuma obrigação de subcontratação.\n\n25 - COMPRA PÚBLICA ESTRATÉGICA\nCompra Pública Estratégica: Inexistência de contratação pública estratégica\n\n26 - INFORMAÇÕES ADICIONAIS\nContrato adequado para PME: Sim\nCobertura ACP (Acordo dos Contratos Públicos da Organização Mundial do Comércio): Não\n\n27 - IDENTIFICAÇÃO E CONTACTOS DO ÓRGÃO DE RECURSOS ADMINISTRATIVOS\nDesignação: Conselho de Administração da ULS Coimbra\nEndereço: Praceta Professor Mota Pinto\nCódigo postal: 3004-561\nLocalidade: Coimbra\nTelefone: +351 239400407\nFax: +351 239822291\nEndereço eletrónico: casec@ulscoimbra.min-saude.pt\n\n28 - IDENTIFICAÇÃO DO(S) AUTOR(ES) DE ANÚNCIO\nNome: Célia Cravo\nCargo: Administradora Hospitalar\n419500915",
    "nipc": "510103448",
    "distrito": "Coimbra",
    "concelho": "Coimbra",
    "freguesia": "Todas",
    "site": "https://www.chuc.min-saude.pt",
    "email": "ana.rosete@ulscoimbra.min-saude.pt",
    "designacao_contrato": "Sistemas de Assistência Ventricular Implantável de Longa Duração",
    "descricao": "Sistemas de Assistência Ventricular Implantável de Longa Duração",
    "preco_base": "285.000,00 EUR",
    "prazo_execucao": "3 MESES",
    "prazo_apresentacao_propostas": "07-10-2025 23:59",
    "fundos_eu": "Não",
    "plataforma_eletronica": "VORTAL",
    "url_procedimento": "https://community.vortal.biz/public/",
    "autor_nome": "Célia Cravo",
    "autor_cargo": "Administradora Hospitalar"
  },
  {
    "numero_procedimento": "N/A",
    "entidade": "AnÃºncio de procedimento  n.Âº 23711/2025  -  DiÃ¡rio da RepÃºblica n.Âº 172/2025, SÃ©rie II de 2025-09-08",
    "link": "https://diariodarepublica.pt/dr/detalhe/contrato-publico/23711-934464553"
  },
  {
    "numero_procedimento": "N/A",
    "entidade": "AnÃºncio de procedimento  n.Âº 23712/2025  -  DiÃ¡rio da RepÃºblica n.Âº 172/2025, SÃ©rie II de 2025-09-08",
    "link": "https://diariodarepublica.pt/dr/detalhe/contrato-publico/23712-934464554"
  },
  {
    "numero_procedimento": "N/A",
    "entidade": "AnÃºncio de procedimento  n.Âº 23713/2025  -  DiÃ¡rio da RepÃºblica n.Âº 172/2025, SÃ©rie II de 2025-09-08",
    "link": "https://diariodarepublica.pt/dr/detalhe/contrato-publico/23713-934464555"
  },
  {
    "numero_procedimento": "N/A",
    "entidade": "AnÃºncio de procedimento  n.Âº 23714/2025  -  DiÃ¡rio da RepÃºblica n.Âº 172/2025, SÃ©rie II de 2025-09-08",
    "link": "https://diariodarepublica.pt/dr/detalhe/contrato-publico/23714-934464556"
  },
  {
    "numero_procedimento": "N/A",
    "entidade": "AnÃºncio de procedimento  n.Âº 23716/2025  -  DiÃ¡rio da RepÃºblica n.Âº 172/2025, SÃ©rie II de 2025-09-08",
    "link": "https://diariodarepublica.pt/dr/detalhe/contrato-publico/23716-934464557"
  },
  {
    "numero_procedimento": "N/A",
    "entidade": "AnÃºncio de procedimento  n.Âº 23718/2025  -  DiÃ¡rio da RepÃºblica n.Âº 172/2025, SÃ©rie II de 2025-09-08",
    "link": "https://diariodarepublica.pt/dr/detalhe/contrato-publico/23718-934464558"
  },
  {
    "numero_procedimento": "N/A",
    "entidade": "AnÃºncio de procedimento  n.Âº 23720/2025  -  DiÃ¡rio da RepÃºblica n.Âº 172/2025, SÃ©rie II de 2025-09-08",
    "link": "https://diariodarepublica.pt/dr/detalhe/contrato-publico/23720-934464559"
  },
  {
    "numero_procedimento": "N/A",
    "entidade": "AnÃºncio de procedimento  n.Âº 23724/2025  -  DiÃ¡rio da RepÃºblica n.Âº 172/2025, SÃ©rie II de 2025-09-08",
    "link": "https://diariodarepublica.pt/dr/detalhe/contrato-publico/23724-934464560"
  },
  {
    "numero_procedimento": "N/A",
    "entidade": "AnÃºncio de procedimento  n.Âº 23725/2025  -  DiÃ¡rio da RepÃºblica n.Âº 172/2025, SÃ©rie II de 2025-09-08",
    "link": "https://diariodarepublica.pt/dr/detalhe/contrato-publico/23725-934464561"
  },
  {
    "numero_procedimento": "N/A",
    "entidade": "AnÃºncio de procedimento  n.Âº 23727/2025  -  DiÃ¡rio da RepÃºblica n.Âº 172/2025, SÃ©rie II de 2025-09-08",
    "link": "https://diariodarepublica.pt/dr/detalhe/contrato-publico/23727-934464562"
  },
  {
    "numero_procedimento": "N/A",
    "entidade": "AnÃºncio de procedimento  n.Âº 23732/2025  -  DiÃ¡rio da RepÃºblica n.Âº 172/2025, SÃ©rie II de 2025-09-08",
    "link": "https://diariodarepublica.pt/dr/detalhe/contrato-publico/23732-934464563"
  },
  {
    "numero_procedimento": "N/A",
    "entidade": "AnÃºncio de procedimento  n.Âº 23733/2025  -  DiÃ¡rio da RepÃºblica n.Âº 172/2025, SÃ©rie II de 2025-09-08",
    "link": "https://diariodarepublica.pt/dr/detalhe/contrato-publico/23733-934464564"
  },
  {
    "numero_procedimento": "N/A",
    "entidade": "AnÃºncio de procedimento  n.Âº 23734/2025  -  DiÃ¡rio da RepÃºblica n.Âº 172/2025, SÃ©rie II de 2025-09-08",
    "link": "https://diariodarepublica.pt/dr/detalhe/contrato-publico/23734-934464565"
  },
  {
    "numero_procedimento": "N/A",
    "entidade": "AnÃºncio de procedimento  n.Âº 23735/2025  -  DiÃ¡rio da RepÃºblica n.Âº 172/2025, SÃ©rie II de 2025-09-08",
    "link": "https://diariodarepublica.pt/dr/detalhe/contrato-publico/23735-934464566"
  },
  {
    "numero_procedimento": "N/A",
    "entidade": "AnÃºncio de procedimento  n.Âº 23742/2025  -  DiÃ¡rio da RepÃºblica n.Âº 172/2025, SÃ©rie II de 2025-09-08",
    "link": "https://diariodarepublica.pt/dr/detalhe/contrato-publico/23742-934464567"
  },
  {
    "numero_procedimento": "N/A",
    "entidade": "AnÃºncio de procedimento  n.Âº 23744/2025  -  DiÃ¡rio da RepÃºblica n.Âº 172/2025, SÃ©rie II de 2025-09-08",
    "link": "https://diariodarepublica.pt/dr/detalhe/contrato-publico/23744-934464568"
  },
  {
    "numero_procedimento": "N/A",
    "entidade": "AnÃºncio de procedimento  n.Âº 23745/2025  -  DiÃ¡rio da RepÃºblica n.Âº 172/2025, SÃ©rie II de 2025-09-08",
    "link": "https://diariodarepublica.pt/dr/detalhe/contrato-publico/23745-934464569"
  },
  {
    "numero_procedimento": "N/A",
    "entidade": "AnÃºncio de procedimento  n.Âº 23746/2025  -  DiÃ¡rio da RepÃºblica n.Âº 172/2025, SÃ©rie II de 2025-09-08",
    "link": "https://diariodarepublica.pt/dr/detalhe/contrato-publico/23746-934464570"
  },
  {
    "numero_procedimento": "N/A",
    "entidade": "AnÃºncio de procedimento  n.Âº 23747/2025  -  DiÃ¡rio da RepÃºblica n.Âº 172/2025, SÃ©rie II de 2025-09-08",
    "link": "https://diariodarepublica.pt/dr/detalhe/contrato-publico/23747-934464571"
  },
  {
    "numero_procedimento": "N/A",
    "entidade": "AnÃºncio de procedimento  n.Âº 23748/2025  -  DiÃ¡rio da RepÃºblica n.Âº 172/2025, SÃ©rie II de 2025-09-08",
    "link": "https://diariodarepublica.pt/dr/detalhe/contrato-publico/23748-934464572"
  },
  {
    "numero_procedimento": "N/A",
    "entidade": "AnÃºncio de procedimento  n.Âº 23749/2025  -  DiÃ¡rio da RepÃºblica n.Âº 172/2025, SÃ©rie II de 2025-09-08",
    "link": "https://diariodarepublica.pt/dr/detalhe/contrato-publico/23749-934464573"
  },
  {
    "numero_procedimento": "N/A",
    "entidade": "AnÃºncio de procedimento  n.Âº 23726/2025  -  DiÃ¡rio da RepÃºblica n.Âº 172/2025, SÃ©rie II de 2025-09-08",
    "link": "https://diariodarepublica.pt/dr/detalhe/contrato-publico/23726-934465375"
  },
  {
    "numero_procedimento": "N/A",
    "entidade": "Secretaria-Geral do MAI",
    "link": "https://diariodarepublica.pt/dr/detalhe/contrato-publico/23728-934465376",
    "detalhes_completos": "1 - IDENTIFICAÇÃO E CONTACTOS DA ENTIDADE ADJUDICANTE\nDesignação da entidade adjudicante: Secretaria-Geral do MAI\nNIPC: 600014665\nEndereço: Rua São Mamede, 23\nCódigo postal: 1100-523\nLocalidade: Lisboa\nPaís: Portugal\nNUT III: PT170\nDistrito: Lisboa\nConcelho: Lisboa\nFreguesia: Freguesia de Santa Maria Maior - Lisboa\nTelefone: 213409000\nFax: 213409010\nEndereço da Entidade (URL): www.sg.mai.gov.pt/\nEndereço Eletrónico: gab.sec.geral@sg.mai.gov.pt\neDelivery Gateway (URL): https://community.vortal.biz/public/\nFunção da Organização: Adquirente\nNorma jurídica da Entidade Adjudicante: Autoridade da administração central\nÁrea de atividade da Autoridade Adjudicante: Serviços públicos das administrações públicas\n\n2 - JORNAL OFICIAL DA UNIÃO EUROPEIA\nO procedimento a que este anúncio diz respeito também é publicitado no Jornal Oficial da União Europeia? Sim\n\n3 - AVISO\nModelo de Anúncio: Concurso público\nData de Envio do Anúncio: 05-09-2025\n\n5 - PROCESSO\nTipo de Procedimento: Concurso público\nPreço base do procedimento: Sim\nValor do preço base do procedimento: 962.635,36 EUR\nProcedimento com lotes? Sim\nNº Máx. de Lotes Autorizado: 5\nNúmero máximo de lotes que podem ser adjudicados a um concorrente: 5\n\n6 - OBJETO DO CONTRATO\nNúmero de referência interna: Proc. 06/DPIE/2025 \nDesignação do contrato: Proc. 06_DPIE_2025 - Aquisição de alcoolímetros e analisadores de droga para a GNR e PSP, no âmbito do DLPIEFSS. \nDescrição: Proc. 06_DPIE_2025 - Aquisição de alcoolímetros e analisadores, para a GNR e PSP, no âmbito do DLPIEFSS.\nOpções: Não\nTipo de Contrato Principal: Aquisição de Bens Móveis\nTipo de Contrato: Aquisição de Bens Móveis\nClassificação CPV (Vocabulário Comum para os Contratos Públicos)\nObjeto principal\nVocabulário Principal: 35200000\nPreço base s/IVA: 962.635,36 EUR\nLotes: \nNº: LOT-0001\nDescrição do Lote: Lote 1 - Alcoolímetro qualitativo portátil, para a GNR\nPreço base s/IVA: 323.400,00 EUR\nClassificação CPV (Vocabulário Comum para os Contratos Públicos)\nObjeto principal\nVocabulário Principal: 35200000\nNº: LOT-0002\nDescrição do Lote: Lote 2 - Analisadores de droga, para a GNR\nPreço base s/IVA: 72.000,00 EUR\nClassificação CPV (Vocabulário Comum para os Contratos Públicos)\nObjeto principal\nVocabulário Principal: 35200000\nNº: LOT-0003\nDescrição do Lote: Lote 3 - Alcoolímetro quantitativo portátil, para a PSP\nPreço base s/IVA: 463.878,80 EUR\nClassificação CPV (Vocabulário Comum para os Contratos Públicos)\nObjeto principal\nVocabulário Principal: 35200000\nNº: LOT-0004\nDescrição do Lote: Lote 4 - Alcoolímetro qualitativo, para a PSP\nPreço base s/IVA: 32.956,56 EUR\nClassificação CPV (Vocabulário Comum para os Contratos Públicos)\nObjeto principal\nVocabulário Principal: 35200000\nNº: LOT-0005\nDescrição do Lote: Lote 5 - Equipamento para rastreamento de estupefacientes para PSP\nPreço base s/IVA: 70.400,00 EUR\nClassificação CPV (Vocabulário Comum para os Contratos Públicos)\nObjeto principal\nVocabulário Principal: 35200000\n\n7 - INDICAÇÕES ADICIONAIS\nO contrato envolve aquisição conjunta (satisfação de várias entidades)? Não\nO contrato é adjudicado por uma central de compras? Não\n\n8 - TÉCNICAS\nO concurso destina-se à celebração de um acordo-quadro? Inexistência de acordo-quadro\nÉ utilizado um leilão eletrónico? Não\nÉ adotada uma fase de negociação? Não\nSistema de Aquisição Dinâmico: Inexistência de sistema de aquisição dinâmico\n\n9 - LOCAL DA EXECUÇÃO DO CONTRATO\nLOCAL DA EXECUÇÃO DO CONTRATO (PROCEDIMENTO)\nPaís: Portugal\nNUT III: PT170\nLocalidade: Lisboa\nDistrito: Lisboa\nConcelho: Lisboa\nFreguesia: Todas\nLOCAL DA EXECUÇÃO DO CONTRATO (LOTE)\nIdentificador do Lote: LOT-0001; LOT-0002; LOT-0003; LOT-0004; LOT-0005\nPaís: Portugal\nNUT III: PT170\nLocalidade: Lisboa\nDistrito: Lisboa\nConcelho: Lisboa\nFreguesia: Todas\n\n10 - PRAZO DE EXECUÇÃO DO CONTRATO\nIdentificador do Lote: LOT-0001; LOT-0002; LOT-0003; LOT-0004; LOT-0005\nPrazo de execução do contrato: 484 DIAS\nPrevisão de renovações: Não\n\n11 - FUNDOS EU\nIdentificador do Lote: LOT-0001; LOT-0002; LOT-0003; LOT-0004; LOT-0005\nTêm fundos EU? Não\n\n12 - DOCUMENTOS DE HABILITAÇÃO\nHabilitação para o exercício da atividade profissional: Não\n\n13 - CONDIÇÕES DE APRESENTAÇÃO\nPlataforma eletrónica utilizada pela entidade adjudicante: VORTAL\nURL para Apresentação: https://community.vortal.biz/public/\nAdmissibilidade da apresentação de propostas variantes: Não autorizado\nPrazo para apresentação das propostas: 08-10-2025 23:59\nPrazo durante o qual os concorrentes são obrigados a manter as respetivas propostas: 99 dias a contar do termo do prazo para a apresentação das propostas\nApresentação de Catálogo Eletrónico: Permitido\nIndicação de Subcontratação na Proposta: Inexistência de indicação de subcontratação\n\n14 - PRESTAÇÃO DE CAUÇÃO\nPrestação de caução: Sim\nPercentagem: 2%\nDescrição da Garantia Exigida: De acordo com o artigo 19º do programa do procedimento\n\n15 - FORNECIMENTO DAS PEÇAS DO CONCURSO, APRESENTAÇÃO DE PEDIDOS DE PARTICIPAÇÃO E APRESENTAÇÃO DAS PROPOSTAS\nLink para acesso às peças do concurso (URL): https://community.vortal.biz/Public/public-tender-documents/cjZyVWNzQ0VUUDF0NnI0czE0dms5dHVBNmZyeVp2VUl6VGJ2QURKbzJ0dmxPdTRsamorZjI4OENqaE5ZTlZlNi9zY1dLdEV5RDloVU9ERzU1dkFIZ2c9PW9KKUh3\n\n20 - OUTROS REQUISITOS\nIdentificador do Lote: LOT-0001; LOT-0002; LOT-0003; LOT-0004; LOT-0005\nInformação sobre contratos reservados. Aplica-se a contratos reservados (54º-A)? Não\n\n21 - CRITÉRIO DE ADJUDICAÇÃO\nO Critério de adjudicação é diferenciado por lote? Sim\nIdentificador do lote: LOT-0001\nMultifator: Sim\nFator: \nNome: Qualidade\nPonderação: 60%\nSubfatores: Não\nFator: \nNome: Preço\nPonderação: 40%\nSubfatores: Não\nO Critério de adjudicação é diferenciado por lote? Sim\nIdentificador do lote: LOT-0002\nMultifator: Não\nMonofator:\nNome: Preço\nO Critério de adjudicação é diferenciado por lote? Sim\nIdentificador do lote: LOT-0003\nMultifator: Sim\nFator: \nNome: Qualidade\nPonderação: 60%\nSubfatores: Não\nFator: \nNome: Preço\nPonderação: 40%\nSubfatores: Não\nO Critério de adjudicação é diferenciado por lote? Sim\nIdentificador do lote: LOT-0004\nMultifator: Sim\nFator: \nNome: Qualidade\nPonderação: 60%\nSubfatores: Não\nFator: \nNome: Preço\nPonderação: 40%\nSubfatores: Não\nO Critério de adjudicação é diferenciado por lote? Sim\nIdentificador do lote: LOT-0005\nMultifator: Não\nMonofator:\nNome: Preço\n\n24 - CONDIÇÕES DO CONTRATO\nIdentificador do Lote: LOT-0001; LOT-0002; LOT-0003; LOT-0004; LOT-0005\nFaturação Eletrónica: Permitido\nObrigação de Subcontratação:\nCódigo da Obrigação de Subcontratação: Não é aplicável nenhuma obrigação de subcontratação.\n\n25 - COMPRA PÚBLICA ESTRATÉGICA\nCompra Pública Estratégica: Inexistência de contratação pública estratégica\n\n26 - INFORMAÇÕES ADICIONAIS\nIdentificador do Lote: LOT-0001; LOT-0002; LOT-0003; LOT-0004; LOT-0005\nContrato adequado para PME: Sim\nCobertura ACP (Acordo dos Contratos Públicos da Organização Mundial do Comércio): Não\n\n27 - IDENTIFICAÇÃO E CONTACTOS DO ÓRGÃO DE RECURSOS ADMINISTRATIVOS\nDesignação: Ministério da Administração Interna\nEndereço: Praça do Comércio, Ala Oriental\nCódigo postal: 1149-015\nLocalidade: Lisboa\nTelefone: +351 213409081\nFax: +351 213409043\nEndereço eletrónico: dpie@sg.mai.gov.pt\n\n28 - IDENTIFICAÇÃO DO(S) AUTOR(ES) DE ANÚNCIO\nNome: Ricardo Carrilho\nCargo: Secretário geral do SGMAI\n419507485",
    "nipc": "600014665",
    "distrito": "Lisboa",
    "concelho": "Lisboa",
    "freguesia": "Freguesia de Santa Maria Maior - Lisboa",
    "site": "www.sg.mai.gov.pt/",
    "email": "gab.sec.geral@sg.mai.gov.pt",
    "designacao_contrato": "Proc. 06_DPIE_2025 - Aquisição de alcoolímetros e analisadores de droga para a GNR e PSP, no âmbito do DLPIEFSS.",
    "descricao": "Proc. 06_DPIE_2025 - Aquisição de alcoolímetros e analisadores, para a GNR e PSP, no âmbito do DLPIEFSS.",
    "preco_base": "962.635,36 EUR",
    "prazo_execucao": "484 DIAS",
    "prazo_apresentacao_propostas": "08-10-2025 23:59",
    "fundos_eu": "Não",
    "plataforma_eletronica": "VORTAL",
    "url_procedimento": "https://community.vortal.biz/public/",
    "autor_nome": "Ricardo Carrilho",
    "autor_cargo": "Secretário geral do SGMAI"
  },
  {
    "numero_procedimento": "N/A",
    "entidade": "AnÃºncio de procedimento  n.Âº 23729/2025  -  DiÃ¡rio da RepÃºblica n.Âº 172/2025, SÃ©rie II de 2025-09-08",
    "link": "https://diariodarepublica.pt/dr/detalhe/contrato-publico/23729-934465377"
  },
  {
    "numero_procedimento": "N/A",
    "entidade": "AnÃºncio de procedimento  n.Âº 23730/2025  -  DiÃ¡rio da RepÃºblica n.Âº 172/2025, SÃ©rie II de 2025-09-08",
    "link": "https://diariodarepublica.pt/dr/detalhe/contrato-publico/23730-934465378"
  },
  {
    "numero_procedimento": "N/A",
    "entidade": "AnÃºncio de procedimento  n.Âº 23731/2025  -  DiÃ¡rio da RepÃºblica n.Âº 172/2025, SÃ©rie II de 2025-09-08",
    "link": "https://diariodarepublica.pt/dr/detalhe/contrato-publico/23731-934465379"
  },
  {
    "numero_procedimento": "N/A",
    "entidade": "AnÃºncio de procedimento  n.Âº 23736/2025  -  DiÃ¡rio da RepÃºblica n.Âº 172/2025, SÃ©rie II de 2025-09-08",
    "link": "https://diariodarepublica.pt/dr/detalhe/contrato-publico/23736-934465380"
  },
  {
    "numero_procedimento": "N/A",
    "entidade": "AnÃºncio de procedimento  n.Âº 23737/2025  -  DiÃ¡rio da RepÃºblica n.Âº 172/2025, SÃ©rie II de 2025-09-08",
    "link": "https://diariodarepublica.pt/dr/detalhe/contrato-publico/23737-934465381"
  },
  {
    "numero_procedimento": "N/A",
    "entidade": "AnÃºncio de procedimento  n.Âº 23738/2025  -  DiÃ¡rio da RepÃºblica n.Âº 172/2025, SÃ©rie II de 2025-09-08",
    "link": "https://diariodarepublica.pt/dr/detalhe/contrato-publico/23738-934465382"
  },
  {
    "numero_procedimento": "N/A",
    "entidade": "AnÃºncio de procedimento  n.Âº 23739/2025  -  DiÃ¡rio da RepÃºblica n.Âº 172/2025, SÃ©rie II de 2025-09-08",
    "link": "https://diariodarepublica.pt/dr/detalhe/contrato-publico/23739-934465383"
  },
  {
    "numero_procedimento": "N/A",
    "entidade": "AnÃºncio de procedimento  n.Âº 23740/2025  -  DiÃ¡rio da RepÃºblica n.Âº 172/2025, SÃ©rie II de 2025-09-08",
    "link": "https://diariodarepublica.pt/dr/detalhe/contrato-publico/23740-934465384"
  },
  {
    "numero_procedimento": "N/A",
    "entidade": "AnÃºncio de procedimento  n.Âº 23741/2025  -  DiÃ¡rio da RepÃºblica n.Âº 172/2025, SÃ©rie II de 2025-09-08",
    "link": "https://diariodarepublica.pt/dr/detalhe/contrato-publico/23741-934465385"
  },
  {
    "numero_procedimento": "N/A",
    "entidade": "AnÃºncio de procedimento  n.Âº 23743/2025  -  DiÃ¡rio da RepÃºblica n.Âº 172/2025, SÃ©rie II de 2025-09-08",
    "link": "https://diariodarepublica.pt/dr/detalhe/contrato-publico/23743-934465386"
  }
]