[
  {
    "numero_procedimento": "N/A",
    "entidade": "AnÃºncio de procedimento  n.Âº 26356/2025  -  DiÃ¡rio da RepÃºblica n.Âº 194/2025, SÃ©rie II de 2025-10-08",
    "link": "https://diariodarepublica.pt/dr/detalhe/contrato-publico/26356-938630854"
  },
  {
    "numero_procedimento": "N/A",
    "entidade": "AnÃºncio de procedimento  n.Âº 26357/2025  -  DiÃ¡rio da RepÃºblica n.Âº 194/2025, SÃ©rie II de 2025-10-08",
    "link": "https://diariodarepublica.pt/dr/detalhe/contrato-publico/26357-938630855"
  },
  {
    "numero_procedimento": "N/A",
    "entidade": "Município de Oeiras",
    "link": "https://diariodarepublica.pt/dr/detalhe/contrato-publico/26358-938630865",
    "detalhes_completos": "1 - IDENTIFICAÇÃO E CONTACTOS DA ENTIDADE ADJUDICANTE\nDesignação da entidade adjudicante: Município de Oeiras\nNIPC: 500745943\nEndereço: Largo Marquês de Pombal\nCódigo postal: 2784-501\nLocalidade: Lisboa\nPaís: Portugal\nNUT III: PT170\nDistrito: Lisboa\nConcelho: Oeiras\nFreguesia: União das Freguesias de Oeiras e São Julião da Barra, Paço de Arcos e Caxias\nTelefone: 214408300\nFax: 214408712\nEndereço da Entidade (URL): www.cm-oeiras.pt\nEndereço Eletrónico: divisao.contratacaopublica@cm-oeiras.pt\neDelivery Gateway (URL): https://community.vortal.biz/public/\nFunção da Organização: Adquirente\nNorma jurídica da Entidade Adjudicante: Autoridade local\nÁrea de atividade da Autoridade Adjudicante: Serviços públicos das administrações públicas\n\n2 - JORNAL OFICIAL DA UNIÃO EUROPEIA\nO procedimento a que este anúncio diz respeito também é publicitado no Jornal Oficial da União Europeia? Não\n\n3 - AVISO\nModelo de Anúncio: Concurso público\nData de Envio do Anúncio: 07-10-2025\n\n5 - PROCESSO\nTipo de Procedimento: Concurso público\nPreço base do procedimento: Sim\nValor do preço base do procedimento: 160.000,00 EUR\nProcedimento com lotes? Não\n\n6 - OBJETO DO CONTRATO\nNúmero de referência interna: 10/DRU/2025\nDesignação do contrato: 10/DRU/2025 - Obras de recuperação do centro de dia do Bairro 25 de Abril\nDescrição: 10/DRU/2025 - Obras de recuperação do centro de dia do Bairro 25 de Abril\nTipo de Contrato Principal: Empreitada de Obras Públicas\nTipo de Contrato: Empreitada de Obras Públicas\nClassificação CPV (Vocabulário Comum para os Contratos Públicos)\nObjeto principal\nVocabulário Principal: 45453100\nPreço base s/IVA: 160.000,00 EUR\n\n7 - INDICAÇÕES ADICIONAIS\nO contrato envolve aquisição conjunta (satisfação de várias entidades)? Não\nO contrato é adjudicado por uma central de compras? Não\n\n8 - TÉCNICAS\nO concurso destina-se à celebração de um acordo-quadro? Inexistência de acordo-quadro\nÉ utilizado um leilão eletrónico? Não\nÉ adotada uma fase de negociação? Não\nSistema de Aquisição Dinâmico: Inexistência de sistema de aquisição dinâmico\n\n9 - LOCAL DA EXECUÇÃO DO CONTRATO\nLOCAL DA EXECUÇÃO DO CONTRATO (PROCEDIMENTO)\nPaís: Portugal\nNUT III: PT170\nLocalidade: Lisboa\nDistrito: Lisboa\nConcelho: Oeiras\nFreguesia: União das Freguesias de Algés, Linda-a-Velha e Cruz Quebrada-Dafundo\n\n10 - PRAZO DE EXECUÇÃO DO CONTRATO\nPrazo de execução do contrato: 90 DIAS\nPrevisão de renovações: Não\n\n11 - FUNDOS EU\nTêm fundos EU? Não\n\n12 - DOCUMENTOS DE HABILITAÇÃO\nHabilitação para o exercício da atividade profissional: Sim\nTipo: Alvará\nDescrição: Alvará de Empreiteiro ou certificado emitido pelo Instituto dos Mercados Públicos, do Imobiliário e da Construção (IMPIC), nos termos do Programa de Procedimento \n\n13 - CONDIÇÕES DE APRESENTAÇÃO\nPlataforma eletrónica utilizada pela entidade adjudicante: VORTAL\nURL para Apresentação: https://community.vortal.biz/public/\nAdmissibilidade da apresentação de propostas variantes: Não autorizado\nPrazo para apresentação das propostas: 06-11-2025 17:00\nPrazo durante o qual os concorrentes são obrigados a manter as respetivas propostas: 150 dias a contar do termo do prazo para a apresentação das propostas\nIndicação de Subcontratação na Proposta: Inexistência de indicação de subcontratação\n\n14 - PRESTAÇÃO DE CAUÇÃO\nPrestação de caução: Sim\nPercentagem: 5%\nDescrição da Garantia Exigida: Remete-se para programa procedimento\n\n15 - FORNECIMENTO DAS PEÇAS DO CONCURSO, APRESENTAÇÃO DE PEDIDOS DE PARTICIPAÇÃO E APRESENTAÇÃO DAS PROPOSTAS\nLink para acesso às peças do concurso (URL): https://community.vortal.biz/Public/public-tender-documents/TDdzb1dGQi8zOU9CUkEyV0dkSXVBN3dBYWZvM1BkZGhGQjNtVzJFRk44STZwUCtxekM3QjhIWXRQNUx2MG8wWEFvSzJiQytoZG91V1YrdU1EM1ZGOGc9PVJ0KGYh\n\n20 - OUTROS REQUISITOS\nInformação sobre contratos reservados. Aplica-se a contratos reservados (54º-A)? Não\n\n21 - CRITÉRIO DE ADJUDICAÇÃO\nMultifator: Sim\nFator: \nNome: Preço\nPonderação: 60%\nSubfatores: Não\nFator: \nNome: Qualidade\nPonderação: 40%\nSubfatores: Sim\nSubfatores: \nNome: Memória Descritiva e Justificativa\nPonderação : 20%; \nNome: Faseamento da Execução\nPonderação : 25%; \nNome: Meios Humanos e Equipamentos afetos à obra\nPonderação : 35%; \nNome: Organização do Estaleiro\nPonderação : 20%; \n\n24 - CONDIÇÕES DO CONTRATO\nFaturação Eletrónica: Permitido\nObrigação de Subcontratação:\nCódigo da Obrigação de Subcontratação: Não é aplicável nenhuma obrigação de subcontratação.\n\n25 - COMPRA PÚBLICA ESTRATÉGICA\nCompra Pública Estratégica: Inexistência de contratação pública estratégica\n\n26 - INFORMAÇÕES ADICIONAIS\nContrato adequado para PME: Sim\nCobertura ACP (Acordo dos Contratos Públicos da Organização Mundial do Comércio): Não\n\n27 - IDENTIFICAÇÃO E CONTACTOS DO ÓRGÃO DE RECURSOS ADMINISTRATIVOS\nDesignação: Câmara Municipal de Oeiras\nEndereço: Largo Marques de Pombal\nCódigo postal: 2784-501\nLocalidade: Oeiras\nTelefone: +351 214408300\nFax: +351 214408712\nEndereço eletrónico: geral@oeiras.pt\n\n28 - IDENTIFICAÇÃO DO(S) AUTOR(ES) DE ANÚNCIO\nNome: Isaltino Morais\nCargo: O Presidente da Câmara Municipal de Oeiras\n419625453",
    "nipc": "500745943",
    "distrito": "Lisboa",
    "concelho": "Oeiras",
    "freguesia": "União das Freguesias de Oeiras e São Julião da Barra, Paço de Arcos e Caxias",
    "site": "www.cm-oeiras.pt",
    "email": "divisao.contratacaopublica@cm-oeiras.pt",
    "designacao_contrato": "10/DRU/2025 - Obras de recuperação do centro de dia do Bairro 25 de Abril",
    "descricao": "10/DRU/2025 - Obras de recuperação do centro de dia do Bairro 25 de Abril",
    "preco_base": "160.000,00 EUR",
    "prazo_execucao": "90 DIAS",
    "prazo_apresentacao_propostas": "06-11-2025 17:00",
    "fundos_eu": "Não",
    "plataforma_eletronica": "VORTAL",
    "url_procedimento": "https://community.vortal.biz/public/",
    "autor_nome": "Isaltino Morais",
    "autor_cargo": "O Presidente da Câmara Municipal de Oeiras"
  },
  {
    "numero_procedimento": "N/A",
    "entidade": "AnÃºncio de procedimento  n.Âº 26359/2025  -  DiÃ¡rio da RepÃºblica n.Âº 194/2025, SÃ©rie II de 2025-10-08",
    "link": "https://diariodarepublica.pt/dr/detalhe/contrato-publico/26359-938630866"
  },
  {
    "numero_procedimento": "N/A",
    "entidade": "AnÃºncio de procedimento  n.Âº 26360/2025  -  DiÃ¡rio da RepÃºblica n.Âº 194/2025, SÃ©rie II de 2025-10-08",
    "link": "https://diariodarepublica.pt/dr/detalhe/contrato-publico/26360-938630867"
  },
  {
    "numero_procedimento": "N/A",
    "entidade": "AnÃºncio de procedimento  n.Âº 26361/2025  -  DiÃ¡rio da RepÃºblica n.Âº 194/2025, SÃ©rie II de 2025-10-08",
    "link": "https://diariodarepublica.pt/dr/detalhe/contrato-publico/26361-938630868"
  },
  {
    "numero_procedimento": "N/A",
    "entidade": "Município do Fundão",
    "link": "https://diariodarepublica.pt/dr/detalhe/contrato-publico/26362-938630869",
    "detalhes_completos": "1 - IDENTIFICAÇÃO E CONTACTOS DA ENTIDADE ADJUDICANTE\nDesignação da entidade adjudicante: Município do Fundão\nNIPC: 506215695\nEndereço: Pç. Município\nCódigo postal: 6230-338\nLocalidade: Castelo Branco\nPaís: Portugal\nNUT III: PT16J\nDistrito: Castelo Branco\nConcelho: Fundão\nFreguesia: União das Freguesias de Fundão, Valverde, Donas, Aldeia de Joanes e Aldeia Nova do Cabo\nTelefone: 275779060\nFax: 275779079\nEndereço da Entidade (URL): www.cm-fundao.pt\nEndereço Eletrónico: geral@cm-fundao.pt\neDelivery Gateway (URL): https://community.vortal.biz/public/\nFunção da Organização: Adquirente\nNorma jurídica da Entidade Adjudicante: Organismo de direito público\nÁrea de atividade da Autoridade Adjudicante: Serviços públicos das administrações públicas\n\n2 - JORNAL OFICIAL DA UNIÃO EUROPEIA\nO procedimento a que este anúncio diz respeito também é publicitado no Jornal Oficial da União Europeia? Não\n\n3 - AVISO\nModelo de Anúncio: Concurso público\nData de Envio do Anúncio: 07-10-2025\n\n5 - PROCESSO\nTipo de Procedimento: Concurso público\nPreço base do procedimento: Sim\nValor do preço base do procedimento: 110.758,89 EUR\nProcedimento com lotes? Não\n\n6 - OBJETO DO CONTRATO\nNúmero de referência interna: 2025/68\nDesignação do contrato: Requalificação do Edifício da Escola Primária - Janeiro de Cima \nDescrição: Requalificação do Edifício da Escola Primária - Janeiro de Cima \nTipo de Contrato Principal: Empreitada de Obras Públicas\nTipo de Contrato: Empreitada de Obras Públicas\nClassificação CPV (Vocabulário Comum para os Contratos Públicos)\nObjeto principal\nVocabulário Principal: 45200000\nPreço base s/IVA: 110.758,89 EUR\n\n7 - INDICAÇÕES ADICIONAIS\nO contrato envolve aquisição conjunta (satisfação de várias entidades)? Não\nO contrato é adjudicado por uma central de compras? Não\n\n8 - TÉCNICAS\nO concurso destina-se à celebração de um acordo-quadro? Inexistência de acordo-quadro\nÉ utilizado um leilão eletrónico? Não\nÉ adotada uma fase de negociação? Não\nSistema de Aquisição Dinâmico: Inexistência de sistema de aquisição dinâmico\n\n9 - LOCAL DA EXECUÇÃO DO CONTRATO\nLOCAL DA EXECUÇÃO DO CONTRATO (PROCEDIMENTO)\nPaís: Portugal\nNUT III: PT16J\nLocalidade: Castelo Branco\nDistrito: Castelo Branco\nConcelho: Fundão\nFreguesia: União das Freguesias de Fundão, Valverde, Donas, Aldeia de Joanes e Aldeia Nova do Cabo\n\n10 - PRAZO DE EXECUÇÃO DO CONTRATO\nPrazo de execução do contrato: 60 DIAS\nPrevisão de renovações: Não\n\n11 - FUNDOS EU\nTêm fundos EU? Não\n\n12 - DOCUMENTOS DE HABILITAÇÃO\nHabilitação para o exercício da atividade profissional: Sim\nTipo: Alvará\nDescrição: Alvará emitido pelo impic \n\n13 - CONDIÇÕES DE APRESENTAÇÃO\nPlataforma eletrónica utilizada pela entidade adjudicante: VORTAL\nURL para Apresentação: https://community.vortal.biz/public/\nAdmissibilidade da apresentação de propostas variantes: Não autorizado\nPrazo para apresentação das propostas: 22-10-2025 17:00\nPrazo durante o qual os concorrentes são obrigados a manter as respetivas propostas: 66 dias a contar do termo do prazo para a apresentação das propostas\nIndicação de Subcontratação na Proposta: Inexistência de indicação de subcontratação\n\n14 - PRESTAÇÃO DE CAUÇÃO\nPrestação de caução: Sim\nPercentagem: 5%\nDescrição da Garantia Exigida: nos termos do programa de concurso \n\n15 - FORNECIMENTO DAS PEÇAS DO CONCURSO, APRESENTAÇÃO DE PEDIDOS DE PARTICIPAÇÃO E APRESENTAÇÃO DAS PROPOSTAS\nLink para acesso às peças do concurso (URL): https://community.vortal.biz/Public/public-tender-documents/NU5EeExielZoNHRXaGYrdUlTdEFzcWFqNnRDampMWHZIeFZEWkkwNEtYVmk5WFA3V2pTYVBndEgxSmMvY0VFeGlVNUppRDM2bTBsQVBnOFZReU1OUFE9PXJZNkxw\n\n20 - OUTROS REQUISITOS\nInformação sobre contratos reservados. Aplica-se a contratos reservados (54º-A)? Não\n\n21 - CRITÉRIO DE ADJUDICAÇÃO\nMultifator: Não\nMonofator:\nNome: Preço\n\n24 - CONDIÇÕES DO CONTRATO\nFaturação Eletrónica: Permitido\nObrigação de Subcontratação:\nCódigo da Obrigação de Subcontratação: Não é aplicável nenhuma obrigação de subcontratação.\n\n25 - COMPRA PÚBLICA ESTRATÉGICA\nCompra Pública Estratégica: Inexistência de contratação pública estratégica\n\n26 - INFORMAÇÕES ADICIONAIS\nContrato adequado para PME: Sim\nCobertura ACP (Acordo dos Contratos Públicos da Organização Mundial do Comércio): Não\n\n27 - IDENTIFICAÇÃO E CONTACTOS DO ÓRGÃO DE RECURSOS ADMINISTRATIVOS\nDesignação: Município do Fundão\nEndereço: Praça do Município\nCódigo postal: 2230-338\nLocalidade: Fundão\nTelefone: +351 275779060\nFax: +351 275779079\nEndereço eletrónico: obraspublicas@cm-fundao.pt\n\n28 - IDENTIFICAÇÃO DO(S) AUTOR(ES) DE ANÚNCIO\nNome: Paulo Alexandre Bernardo Fernandes \nCargo: Presidente da Câmara Municipal do Fundão \n419621946",
    "nipc": "506215695",
    "distrito": "Castelo Branco",
    "concelho": "Fundão",
    "freguesia": "União das Freguesias de Fundão, Valverde, Donas, Aldeia de Joanes e Aldeia Nova do Cabo",
    "site": "www.cm-fundao.pt",
    "email": "geral@cm-fundao.pt",
    "designacao_contrato": "Requalificação do Edifício da Escola Primária - Janeiro de Cima",
    "descricao": "Requalificação do Edifício da Escola Primária - Janeiro de Cima",
    "preco_base": "110.758,89 EUR",
    "prazo_execucao": "60 DIAS",
    "prazo_apresentacao_propostas": "22-10-2025 17:00",
    "fundos_eu": "Não",
    "plataforma_eletronica": "VORTAL",
    "url_procedimento": "https://community.vortal.biz/public/",
    "autor_nome": "Paulo Alexandre Bernardo Fernandes",
    "autor_cargo": "Presidente da Câmara Municipal do Fundão"
  },
  {
    "numero_procedimento": "N/A",
    "entidade": "AnÃºncio de procedimento  n.Âº 26363/2025  -  DiÃ¡rio da RepÃºblica n.Âº 194/2025, SÃ©rie II de 2025-10-08",
    "link": "https://diariodarepublica.pt/dr/detalhe/contrato-publico/26363-938630870"
  },
  {
    "numero_procedimento": "N/A",
    "entidade": "AnÃºncio de procedimento  n.Âº 26364/2025  -  DiÃ¡rio da RepÃºblica n.Âº 194/2025, SÃ©rie II de 2025-10-08",
    "link": "https://diariodarepublica.pt/dr/detalhe/contrato-publico/26364-938630871"
  },
  {
    "numero_procedimento": "N/A",
    "entidade": "Universidade da Beira Interior",
    "link": "https://diariodarepublica.pt/dr/detalhe/contrato-publico/26365-938630872",
    "detalhes_completos": "1 - IDENTIFICAÇÃO E CONTACTOS DA ENTIDADE ADJUDICANTE\nDesignação da entidade adjudicante: Universidade da Beira Interior\nNIPC: 502083514\nServiço/Órgão/Pessoa de contacto: Reitora\nEndereço: Convento de Santo António\nCódigo postal: 6201-001\nLocalidade: Covilhã\nPaís: Portugal\nNUT III: PT16J\nDistrito: Castelo Branco\nConcelho: Covilhã\nFreguesia: União das Freguesias de Covilhã e Canhoso\nTelefone: 275329140\nEndereço da Entidade (URL): www.ubi.pt\nEndereço Eletrónico: div.economato@ubi.pt\neDelivery Gateway (URL): https://www.acingov.pt\nFunção da Organização: Adquirente\nNorma jurídica da Entidade Adjudicante: Organismo de direito público\nÁrea de atividade da Autoridade Adjudicante: Educação\n\n2 - JORNAL OFICIAL DA UNIÃO EUROPEIA\nO procedimento a que este anúncio diz respeito também é publicitado no Jornal Oficial da União Europeia? Não\n\n3 - AVISO\nModelo de Anúncio: Concurso público\nData de Envio do Anúncio: 07-10-2025\n\n5 - PROCESSO\nTipo de Procedimento: Concurso público\nPreço base do procedimento: Sim\nValor do preço base do procedimento: 58.000,00 EUR\nProcedimento com lotes? Não\n\n6 - OBJETO DO CONTRATO\nNúmero de referência interna: CP 35/2025\nDesignação do contrato: Aquisição de um Robô Humanóide para o Departamento de Informática da Beira Interior, do programa UBI Impulso Jovens STEAM - Plano de Recuperação e Resiliência para 2021-2026\nDescrição: Aquisição de um Robô Humanóide para o Departamento de Informática da Beira Interior\nTipo de Contrato Principal: Aquisição de Bens Móveis\nTipo de Contrato: Aquisição de Bens Móveis\nClassificação CPV (Vocabulário Comum para os Contratos Públicos)\nObjeto principal\nVocabulário Principal: 30230000\nPreço base s/IVA: 58.000,00 EUR\n\n7 - INDICAÇÕES ADICIONAIS\nO contrato envolve aquisição conjunta (satisfação de várias entidades)? Não\nO contrato é adjudicado por uma central de compras? Não\n\n8 - TÉCNICAS\nO concurso destina-se à celebração de um acordo-quadro? Inexistência de acordo-quadro\nÉ utilizado um leilão eletrónico? Não\nÉ adotada uma fase de negociação? Não\nSistema de Aquisição Dinâmico: Inexistência de sistema de aquisição dinâmico\n\n9 - LOCAL DA EXECUÇÃO DO CONTRATO\nLOCAL DA EXECUÇÃO DO CONTRATO (PROCEDIMENTO)\nPaís: Portugal\nNUT III: PT16J\nLocalidade: Covilhã\nDistrito: Castelo Branco\nConcelho: Covilhã\nFreguesia: Todas\n\n10 - PRAZO DE EXECUÇÃO DO CONTRATO\nPrazo de execução do contrato: 60 DIAS\nPrevisão de renovações: Não\n\n11 - FUNDOS EU\nTêm fundos EU? Sim\n\n12 - DOCUMENTOS DE HABILITAÇÃO\nHabilitação para o exercício da atividade profissional: Não\n\n13 - CONDIÇÕES DE APRESENTAÇÃO\nPlataforma eletrónica utilizada pela entidade adjudicante: ACIN\nURL para Apresentação: https://www.acingov.pt\nAdmissibilidade da apresentação de propostas variantes: Não autorizado\nPrazo para apresentação das propostas: 17-10-2025 23:59\nPrazo durante o qual os concorrentes são obrigados a manter as respetivas propostas: 90 dias a contar do termo do prazo para a apresentação das propostas\nIndicação de Subcontratação na Proposta: Inexistência de indicação de subcontratação\n\n14 - PRESTAÇÃO DE CAUÇÃO\nPrestação de caução: Não\n\n15 - FORNECIMENTO DAS PEÇAS DO CONCURSO, APRESENTAÇÃO DE PEDIDOS DE PARTICIPAÇÃO E APRESENTAÇÃO DAS PROPOSTAS\nLink para acesso às peças do concurso (URL): https://www.acingov.pt/acingovprod/2/zonaPublica/zona_publica_c/donwloadProcedurePiece/OTgyNDY1\n\n20 - OUTROS REQUISITOS\nInformação sobre contratos reservados. Aplica-se a contratos reservados (54º-A)? Não\n\n21 - CRITÉRIO DE ADJUDICAÇÃO\nMultifator: Não\nMonofator:\nNome: Preço\n\n24 - CONDIÇÕES DO CONTRATO\nFaturação Eletrónica: Permitido\nObrigação de Subcontratação:\nCódigo da Obrigação de Subcontratação: Não é aplicável nenhuma obrigação de subcontratação.\n\n25 - COMPRA PÚBLICA ESTRATÉGICA\nCompra Pública Estratégica: Inexistência de contratação pública estratégica\n\n26 - INFORMAÇÕES ADICIONAIS\nContrato adequado para PME: Não\nCobertura ACP (Acordo dos Contratos Públicos da Organização Mundial do Comércio): Não\n\n27 - IDENTIFICAÇÃO E CONTACTOS DO ÓRGÃO DE RECURSOS ADMINISTRATIVOS\nDesignação: Reitora\nEndereço: Convento de Santo António\nCódigo postal: 6201-001\nLocalidade: Covilhã\nTelefone: 275319700\nFax: \nEndereço eletrónico: reitor@ubi.pt\nPrazo de interposição do recurso: 5 dias\n\n28 - IDENTIFICAÇÃO DO(S) AUTOR(ES) DE ANÚNCIO\nNome: Ana Paula Coelho Duarte\nCargo: Reitora\n419621702",
    "nipc": "502083514",
    "distrito": "Castelo Branco",
    "concelho": "Covilhã",
    "freguesia": "União das Freguesias de Covilhã e Canhoso",
    "site": "www.ubi.pt",
    "email": "div.economato@ubi.pt",
    "designacao_contrato": "Aquisição de um Robô Humanóide para o Departamento de Informática da Beira Interior, do programa UBI Impulso Jovens STEAM - Plano de Recuperação e Resiliência para 2021-2026",
    "descricao": "Aquisição de um Robô Humanóide para o Departamento de Informática da Beira Interior",
    "preco_base": "58.000,00 EUR",
    "prazo_execucao": "60 DIAS",
    "prazo_apresentacao_propostas": "17-10-2025 23:59",
    "fundos_eu": "Sim",
    "plataforma_eletronica": "ACIN",
    "url_procedimento": "https://www.acingov.pt",
    "autor_nome": "Ana Paula Coelho Duarte",
    "autor_cargo": "Reitora"
  },
  {
    "numero_procedimento": "N/A",
    "entidade": "AnÃºncio de procedimento  n.Âº 26367/2025  -  DiÃ¡rio da RepÃºblica n.Âº 194/2025, SÃ©rie II de 2025-10-08",
    "link": "https://diariodarepublica.pt/dr/detalhe/contrato-publico/26367-938630873"
  },
  {
    "numero_procedimento": "N/A",
    "entidade": "AnÃºncio de procedimento  n.Âº 26369/2025  -  DiÃ¡rio da RepÃºblica n.Âº 194/2025, SÃ©rie II de 2025-10-08",
    "link": "https://diariodarepublica.pt/dr/detalhe/contrato-publico/26369-938630874"
  },
  {
    "numero_procedimento": "N/A",
    "entidade": "AnÃºncio de procedimento  n.Âº 26355/2025  -  DiÃ¡rio da RepÃºblica n.Âº 194/2025, SÃ©rie II de 2025-10-08",
    "link": "https://diariodarepublica.pt/dr/detalhe/contrato-publico/26355-938632012"
  },
  {
    "numero_procedimento": "N/A",
    "entidade": "Academia Profissional Professor Albino de Matos - Associação",
    "link": "https://diariodarepublica.pt/dr/detalhe/contrato-publico/26366-938668112",
    "detalhes_completos": "1 - IDENTIFICAÇÃO E CONTACTOS DA ENTIDADE ADJUDICANTE\nDesignação da entidade adjudicante: Academia Profissional Professor Albino de Matos - Associação\nNIPC: 504616129\nEndereço:  Av. Dr. Nicolau Carneiro, nº 196\nCódigo postal: 4590-512\nLocalidade: Porto\nPaís: Portugal\nNUT III: PT11C\nDistrito: Porto\nConcelho: Paços de Ferreira\nFreguesia: Freguesia de Paços de Ferreira\nTelefone: 255964143\nFax: 255964144\nEndereço da Entidade (URL): https://profisousa.pt/\nEndereço Eletrónico: profisousa@profisousa.pt\neDelivery Gateway (URL): https://community.vortal.biz/public/\nFunção da Organização: Adquirente\nNorma jurídica da Entidade Adjudicante: Empresa pública\nÁrea de atividade da Entidade Adjudicante: Serviços postais\n\n2 - JORNAL OFICIAL DA UNIÃO EUROPEIA\nO procedimento a que este anúncio diz respeito também é publicitado no Jornal Oficial da União Europeia? Não\n\n3 - AVISO\nModelo de Anúncio: Concurso público\nData de Envio do Anúncio: 07-10-2025\n\n5 - PROCESSO\nTipo de Procedimento: Concurso público\nPreço base do procedimento: Sim\nValor do preço base do procedimento: 32.180,00 EUR\nProcedimento com lotes? Sim\nNº Máx. de Lotes Autorizado: 4\nNúmero máximo de lotes que podem ser adjudicados a um concorrente: 4\n\n6 - OBJETO DO CONTRATO\nNúmero de referência interna: CP 01/2025\nDesignação do contrato: Prestação de Serviços de Seguros, por lotes\nDescrição: Prestação de Serviços de Seguros, por lotes\nTipo de Contrato Principal: Aquisição de Serviços\nTipo de Contrato: Aquisição de Serviços\nClassificação CPV (Vocabulário Comum para os Contratos Públicos)\nObjeto principal\nVocabulário Principal: 66510000\nPreço base s/IVA: 32.180,00 EUR\nLotes: \nNº: LOT-0001\nDescrição do Lote: Lote 1 – Ramo de Acidentes Pessoais\nPreço base s/IVA: 10.800,00 EUR\nClassificação CPV (Vocabulário Comum para os Contratos Públicos)\nObjeto principal\nVocabulário Principal: 66510000\nNº: LOT-0002\nDescrição do Lote: Lote 2 – Ramo Automóvel\nPreço base s/IVA: 580,00 EUR\nClassificação CPV (Vocabulário Comum para os Contratos Públicos)\nObjeto principal\nVocabulário Principal: 66510000\nNº: LOT-0003\nDescrição do Lote: Lote 3 – Ramo Multirriscos\nPreço base s/IVA: 8.600,00 EUR\nClassificação CPV (Vocabulário Comum para os Contratos Públicos)\nObjeto principal\nVocabulário Principal: 66510000\nNº: LOT-0004\nDescrição do Lote: Lote 4 – Ramo de Acidentes de Trabalho\nPreço base s/IVA: 12.200,00 EUR\nClassificação CPV (Vocabulário Comum para os Contratos Públicos)\nObjeto principal\nVocabulário Principal: 66510000\n\n7 - INDICAÇÕES ADICIONAIS\nO contrato envolve aquisição conjunta (satisfação de várias entidades)? Não\nO contrato é adjudicado por uma central de compras? Não\n\n8 - TÉCNICAS\nO concurso destina-se à celebração de um acordo-quadro? Inexistência de acordo-quadro\nÉ utilizado um leilão eletrónico? Não\nÉ adotada uma fase de negociação? Não\nSistema de Aquisição Dinâmico: Inexistência de sistema de aquisição dinâmico\n\n9 - LOCAL DA EXECUÇÃO DO CONTRATO\nLOCAL DA EXECUÇÃO DO CONTRATO (PROCEDIMENTO)\nPaís: Portugal\nNUT III: PT11C\nLocalidade: Porto\nDistrito: Porto\nConcelho: Paços de Ferreira\nFreguesia: Freguesia de Paços de Ferreira\nLOCAL DA EXECUÇÃO DO CONTRATO (LOTE)\nIdentificador do Lote: LOT-0001; LOT-0002; LOT-0003; LOT-0004\nPaís: Portugal\nNUT III: PT11C\nLocalidade: Porto\nDistrito: Porto\nConcelho: Paços de Ferreira\nFreguesia: Freguesia de Paços de Ferreira\n\n10 - PRAZO DE EXECUÇÃO DO CONTRATO\nIdentificador do Lote: LOT-0001; LOT-0002; LOT-0003; LOT-0004\nPrazo de execução do contrato: 12 MESES\nPrevisão de renovações: Sim\nIndicar número máximo de renovações: 1\nPrazo de renovações diferente do prazo inicial: Não\n\n11 - FUNDOS EU\nIdentificador do Lote: LOT-0001; LOT-0002; LOT-0003; LOT-0004\nTêm fundos EU? Não\n\n12 - DOCUMENTOS DE HABILITAÇÃO\nHabilitação para o exercício da atividade profissional: Não\n\n13 - CONDIÇÕES DE APRESENTAÇÃO\nPlataforma eletrónica utilizada pela entidade adjudicante: VORTAL\nURL para Apresentação: https://community.vortal.biz/public/\nAdmissibilidade da apresentação de propostas variantes: Não autorizado\nPrazo para apresentação das propostas: 13-10-2025 17:00\nPrazo durante o qual os concorrentes são obrigados a manter as respetivas propostas: 66 dias a contar do termo do prazo para a apresentação das propostas\nIndicação de Subcontratação na Proposta: Inexistência de indicação de subcontratação\n\n14 - PRESTAÇÃO DE CAUÇÃO\nPrestação de caução: Não\n\n15 - FORNECIMENTO DAS PEÇAS DO CONCURSO, APRESENTAÇÃO DE PEDIDOS DE PARTICIPAÇÃO E APRESENTAÇÃO DAS PROPOSTAS\nLink para acesso às peças do concurso (URL): https://community.vortal.biz/Public/public-tender-documents/ZzBlOE9HWkMweDBtSytRT01RR1BzRFhoNHVHaVpkOTZ1SjZtOVozUFZ5WEZQWlJMWHNVZnU3WXJreXhPQWVhOWFIRlF4UUdhZ1YybFlyYjBXSGNyaEE9PTVDMHE0\n\n20 - OUTROS REQUISITOS\nIdentificador do Lote: LOT-0001; LOT-0002; LOT-0003; LOT-0004\nInformação sobre contratos reservados. Aplica-se a contratos reservados (54º-A)? Não\n\n21 - CRITÉRIO DE ADJUDICAÇÃO\nO Critério de adjudicação é diferenciado por lote? Não\nMultifator: Não\nMonofator:\nNome: Preço\n\n24 - CONDIÇÕES DO CONTRATO\nIdentificador do Lote: LOT-0001; LOT-0002; LOT-0003; LOT-0004\nFaturação Eletrónica: Permitido\nObrigação de Subcontratação:\nCódigo da Obrigação de Subcontratação: Não é aplicável nenhuma obrigação de subcontratação.\n\n25 - COMPRA PÚBLICA ESTRATÉGICA\nCompra Pública Estratégica: Inexistência de contratação pública estratégica\n\n26 - INFORMAÇÕES ADICIONAIS\nIdentificador do Lote: LOT-0001; LOT-0002; LOT-0003; LOT-0004\nContrato adequado para PME: Sim\nCobertura ACP (Acordo dos Contratos Públicos da Organização Mundial do Comércio): Não\n\n27 - IDENTIFICAÇÃO E CONTACTOS DO ÓRGÃO DE RECURSOS ADMINISTRATIVOS\nDesignação: Conselho de Administração\nEndereço: Av. Dr. Jaime Barros\nCódigo postal: 4590-892\nLocalidade: Paços de Ferreira\nTelefone: +351 255962071\nFax: +351 255962071\nEndereço eletrónico: academia@academiaprofissional.pt\nPrazo de interposição do recurso: 10 dias\n\n28 - IDENTIFICAÇÃO DO(S) AUTOR(ES) DE ANÚNCIO\nNome: Sílvia Azevedo\nCargo: Presidente do Conselho de Administração\n419627243",
    "nipc": "504616129",
    "distrito": "Porto",
    "concelho": "Paços de Ferreira",
    "freguesia": "Freguesia de Paços de Ferreira",
    "site": "https://profisousa.pt/",
    "email": "profisousa@profisousa.pt",
    "designacao_contrato": "Prestação de Serviços de Seguros, por lotes",
    "descricao": "Prestação de Serviços de Seguros, por lotes",
    "preco_base": "32.180,00 EUR",
    "prazo_execucao": "12 MESES",
    "prazo_apresentacao_propostas": "13-10-2025 17:00",
    "fundos_eu": "Não",
    "plataforma_eletronica": "VORTAL",
    "url_procedimento": "https://community.vortal.biz/public/",
    "autor_nome": "Sílvia Azevedo",
    "autor_cargo": "Presidente do Conselho de Administração"
  },
  {
    "numero_procedimento": "N/A",
    "entidade": "AnÃºncio de procedimento  n.Âº 26368/2025  -  DiÃ¡rio da RepÃºblica n.Âº 194/2025, SÃ©rie II de 2025-10-08",
    "link": "https://diariodarepublica.pt/dr/detalhe/contrato-publico/26368-938668113"
  }
]