[
  {
    "numero_procedimento": "N/A",
    "entidade": "Instituto de Gestão Financeira da Educação, I.P.",
    "link": "https://diariodarepublica.pt/dr/detalhe/contrato-publico/23816-934502541",
    "detalhes_completos": "Alteração do Anúncio de procedimento n.º 21534/2025, de 2025-08-11, com o ID 419412552\n\n1 - IDENTIFICAÇÃO E CONTACTOS DA ENTIDADE ADJUDICANTE\nDesignação da entidade adjudicante: Instituto de Gestão Financeira da Educação, I.P.\nNIPC: 600086631\nServiço/Órgão/Pessoa de contacto: Diogo Freitas - NCP da DAG do IGeFE, I.P.\nEndereço: Av. 24 de julho, 134, 5.º andar\nCódigo postal: 1399-029\nLocalidade: Lisboa\nPaís: Portugal\nNUT III: PT170\nDistrito: Lisboa\nConcelho: Lisboa\nFreguesia: Freguesia da Estrela\nTelefone: 213949200\nFax: 213907003\nEndereço da Entidade (URL): https://www.igefe.mec.pt/\nEndereço Eletrónico: geral@igefe.medu.pt\neDelivery Gateway (URL): https://www.acingov.pt\nFunção da Organização: Adquirente\nNorma jurídica da Entidade Adjudicante: Organismo de direito público\nÁrea de atividade da Autoridade Adjudicante: Educação\n\n2 - JORNAL OFICIAL DA UNIÃO EUROPEIA\nO procedimento a que este anúncio diz respeito também é publicitado no Jornal Oficial da União Europeia? Sim\n\n3 - AVISO\nModelo de Anúncio: Concurso público\nData de Envio do Anúncio: 06-09-2025\n\n5 - PROCESSO\nTipo de Procedimento: Concurso público\nPreço base do procedimento: Sim\nValor do preço base do procedimento: 15.787.810,56 EUR\nProcedimento com lotes? Sim\nNº Máx. de Lotes Autorizado: 7\nNúmero máximo de lotes que podem ser adjudicados a um concorrente: 4\n\n6 - OBJETO DO CONTRATO\nNúmero de referência interna: 35/2025/IGeFE-CPI\nDesignação do contrato: Aquisição de serviços de interligação entre redes lógicas e de comunicações de dados para as escolas do 1.º, 2.º e 3.º ciclos do Ensino Básico, Ensino Secundário das Escolas Públicas, Organismos Centrais, Regionais e Tutelados do Ministério da Educação, Ciência e Inovação (MECI), para aquisição de funcionalidades de Ponto Focal e monitorização/gestão (3 anos)\nDescrição: Aquisição de serviços de interligação entre redes lógicas e de comunicações de dados para as escolas do 1.º, 2.º e 3.º ciclos do Ensino Básico, Ensino Secundário das Escolas Públicas, Organismos Centrais, Regionais e Tutelados do Ministério da Educação, Ciência e Inovação (MECI), para aquisição de funcionalidades de Ponto Focal e monitorização/gestão (3 anos)\nOpções: Não\nTipo de Contrato Principal: Aquisição de Serviços\nTipo de Contrato: Aquisição de Serviços\nClassificação CPV (Vocabulário Comum para os Contratos Públicos)\nObjeto principal\nVocabulário Principal: 72720000\nPreço base s/IVA: 15.787.810,56 EUR\nLotes: \nNº: LOT-0001\nDescrição do Lote: Aquisição dos SERVIÇOS de comunicações de dados entre Redes Lógicas das ESCOLAS do 1.º, 2.º e 3.º ciclos do ensino básico público e das ESCOLAS secundárias do ensino público, que correspondem a circunscrições geográficas distintas e a CIRCUITOS (principal e secundário) distintos.\nPreço base s/IVA: 3.570.981,02 EUR\nClassificação CPV (Vocabulário Comum para os Contratos Públicos)\nObjeto principal\nVocabulário Principal: 72720000\nNº: LOT-0002\nDescrição do Lote: Aquisição dos SERVIÇOS de comunicações de dados entre Redes Lógicas das ESCOLAS do 1.º, 2.º e 3.º ciclos do ensino básico público e das ESCOLAS secundárias do ensino público, que correspondem a circunscrições geográficas distintas e a CIRCUITOS (principal e secundário) distintos.\nPreço base s/IVA: 3.109.737,50 EUR\nClassificação CPV (Vocabulário Comum para os Contratos Públicos)\nObjeto principal\nVocabulário Principal: 72720000\nNº: LOT-0003\nDescrição do Lote: Aquisição dos SERVIÇOS de comunicações de dados entre Redes Lógicas das ESCOLAS do 1.º, 2.º e 3.º ciclos do ensino básico público e das ESCOLAS secundárias do ensino público, que correspondem a circunscrições geográficas distintas e a CIRCUITOS (principal e secundário) distintos.\nPreço base s/IVA: 3.256.010,54 EUR\nClassificação CPV (Vocabulário Comum para os Contratos Públicos)\nObjeto principal\nVocabulário Principal: 72720000\nNº: LOT-0004\nDescrição do Lote: Aquisição dos SERVIÇOS de comunicações de dados entre Redes Lógicas das ESCOLAS do 1.º, 2.º e 3.º ciclos do ensino básico público e das ESCOLAS secundárias do ensino público, que correspondem a circunscrições geográficas distintas e a CIRCUITOS (principal e secundário) distintos.\nPreço base s/IVA: 1.881.367,71 EUR\nClassificação CPV (Vocabulário Comum para os Contratos Públicos)\nObjeto principal\nVocabulário Principal: 72720000\nNº: LOT-0005\nDescrição do Lote: Aquisição dos SERVIÇOS de comunicações de dados entre Redes Lógicas das ESCOLAS do 1.º, 2.º e 3.º ciclos do ensino básico público e das ESCOLAS secundárias do ensino público, que correspondem a circunscrições geográficas distintas e a CIRCUITOS (principal e secundário) distintos.\nPreço base s/IVA: 1.579.624,93 EUR\nClassificação CPV (Vocabulário Comum para os Contratos Públicos)\nObjeto principal\nVocabulário Principal: 72720000\nNº: LOT-0006\nDescrição do Lote: Aquisição dos SERVIÇOS de comunicações de dados entre Redes Lógicas das ESCOLAS do 1.º, 2.º e 3.º ciclos do ensino básico público e das ESCOLAS secundárias do ensino público, que correspondem a circunscrições geográficas distintas e a CIRCUITOS (principal e secundário) distintos.\nPreço base s/IVA: 1.814.532,52 EUR\nClassificação CPV (Vocabulário Comum para os Contratos Públicos)\nObjeto principal\nVocabulário Principal: 72720000\nNº: LOT-0007\nDescrição do Lote: Aquisição dos SERVIÇOS de comunicações de dados entre Redes Lógicas dos ORGANISMOS\nPreço base s/IVA: 575.556,34 EUR\nClassificação CPV (Vocabulário Comum para os Contratos Públicos)\nObjeto principal\nVocabulário Principal: 72720000\n\n7 - INDICAÇÕES ADICIONAIS\nO contrato envolve aquisição conjunta (satisfação de várias entidades)? Não\nO contrato é adjudicado por uma central de compras? Não\n\n8 - TÉCNICAS\nO concurso destina-se à celebração de um acordo-quadro? Inexistência de acordo-quadro\nÉ utilizado um leilão eletrónico? Não\nÉ adotada uma fase de negociação? Não\nSistema de Aquisição Dinâmico: Inexistência de sistema de aquisição dinâmico\n\n9 - LOCAL DA EXECUÇÃO DO CONTRATO\nLOCAL DA EXECUÇÃO DO CONTRATO (PROCEDIMENTO)\nPaís: Portugal\nNUT III: PT170\nLocalidade: Todas\nDistrito: Lisboa\nConcelho: Todos\nFreguesia: Todas\nLOCAL DA EXECUÇÃO DO CONTRATO (LOTE)\nIdentificador do Lote: LOT-0001; LOT-0002; LOT-0003; LOT-0004; LOT-0005; LOT-0006; LOT-0007\nPaís: Portugal\nNUT III: PT170\nLocalidade: Todas\nDistrito: Lisboa\nConcelho: Todos\nFreguesia: Todas\n\n10 - PRAZO DE EXECUÇÃO DO CONTRATO\nIdentificador do Lote: LOT-0001; LOT-0002; LOT-0003; LOT-0004; LOT-0005; LOT-0006; LOT-0007\nPrazo de execução do contrato: 36 MESES\nPrevisão de renovações: Não\n\n11 - FUNDOS EU\nIdentificador do Lote: LOT-0001; LOT-0002; LOT-0003; LOT-0004; LOT-0005; LOT-0006; LOT-0007\nTêm fundos EU? Não\n\n12 - DOCUMENTOS DE HABILITAÇÃO\nHabilitação para o exercício da atividade profissional: Não\n\n13 - CONDIÇÕES DE APRESENTAÇÃO\nPlataforma eletrónica utilizada pela entidade adjudicante: ACIN\nURL para Apresentação: https://www.acingov.pt\nAdmissibilidade da apresentação de propostas variantes: Não autorizado\nPrazo para apresentação das propostas: 07-10-2025 17:00\nPrazo durante o qual os concorrentes são obrigados a manter as respetivas propostas: 120 dias a contar do termo do prazo para a apresentação das propostas\nApresentação de Catálogo Eletrónico: Não autorizado\nIndicação de Subcontratação na Proposta: Inexistência de indicação de subcontratação\n\n14 - PRESTAÇÃO DE CAUÇÃO\nPrestação de caução: Sim\nPercentagem: 5%\nDescrição da Garantia Exigida: O valor da caução é de 5.00% do preço contratual.\n\n15 - FORNECIMENTO DAS PEÇAS DO CONCURSO, APRESENTAÇÃO DE PEDIDOS DE PARTICIPAÇÃO E APRESENTAÇÃO DAS PROPOSTAS\nLink para acesso às peças do concurso (URL): https://www.acingov.pt/acingovprod/2/zonaPublica/zona_publica_c/donwloadProcedurePiece/OTI3OTA0\n\n20 - OUTROS REQUISITOS\nIdentificador do Lote: LOT-0001; LOT-0002; LOT-0003; LOT-0004; LOT-0005; LOT-0006; LOT-0007\nInformação sobre contratos reservados. Aplica-se a contratos reservados (54º-A)? Não\n\n21 - CRITÉRIO DE ADJUDICAÇÃO\nO Critério de adjudicação é diferenciado por lote? Não\nMultifator: Sim\nFator: \nNome: Outros\nOutro Nome: De acordo com o Anexo XI do Programa do Procedimento.\nPonderação: 100%\nSubfatores: Não\n\n24 - CONDIÇÕES DO CONTRATO\nIdentificador do Lote: LOT-0001; LOT-0002; LOT-0003; LOT-0004; LOT-0005; LOT-0006; LOT-0007\nFaturação Eletrónica: Necessário\nObrigação de Subcontratação:\nCódigo da Obrigação de Subcontratação: Não é aplicável nenhuma obrigação de subcontratação.\n\n25 - COMPRA PÚBLICA ESTRATÉGICA\nCompra Pública Estratégica: Realização dos objetivos sociais\nCategorias da estratégia nacional: Outros\nOutra categoria (Descrição): N/A\nContratos Públicos Sociais: Condições de trabalho justas\nCritério de Acessibilidade: Os critérios de acessibilidade para as pessoas com deficiência não estão incluídos porque o contrato não se destina a pessoas singulares\n\n26 - INFORMAÇÕES ADICIONAIS\nIdentificador do Lote: LOT-0001; LOT-0002; LOT-0003; LOT-0004; LOT-0005; LOT-0006; LOT-0007\nContrato adequado para PME: Sim\nCobertura ACP (Acordo dos Contratos Públicos da Organização Mundial do Comércio): Não\n\n27 - IDENTIFICAÇÃO E CONTACTOS DO ÓRGÃO DE RECURSOS ADMINISTRATIVOS\nDesignação: Conselho Diretivo do IGeFE, I.P.\nEndereço: Avenida 24 de julho, 134, 5.º andar\nCódigo postal: 1399-029\nLocalidade: Lisboa\nTelefone: 213949200\nFax: 213907003\nEndereço eletrónico: compras@igefe.medu.pt\nPrazo de interposição do recurso: 5 dias\n\n28 - IDENTIFICAÇÃO DO(S) AUTOR(ES) DE ANÚNCIO\nNome: Marlene Vieira\nCargo: Técnica Superior\n\n29 - ALTERAÇÃO\nMotivo da Alteração: Informações atualizadas\nIdentificador da Versão do Anúncio a Alterar: 1f1fc251-f252-46b6-8e37-5d9e64947e28-01\nIdentificador das Secções Alteradas do Anúncio Anterior: Condições de Apresentação; Identificação do(s) autor(es) do anúncio\nDescrição das Alterações: Modificação do prazo para a apresentação de propostas Atualização do(s) autor(es) do anúncio\nAlteração dos Documentos do Concurso: Não\n419509656",
    "nipc": "600086631",
    "distrito": "Lisboa",
    "concelho": "Lisboa",
    "freguesia": "Freguesia da Estrela",
    "site": "https://www.igefe.mec.pt/",
    "email": "geral@igefe.medu.pt",
    "designacao_contrato": "Aquisição de serviços de interligação entre redes lógicas e de comunicações de dados para as escolas do 1.º, 2.º e 3.º ciclos do Ensino Básico, Ensino Secundário das Escolas Públicas, Organismos Centrais, Regionais e Tutelados do Ministério da Educação, Ciência e Inovação (MECI), para aquisição de funcionalidades de Ponto Focal e monitorização/gestão (3 anos)",
    "descricao": "Aquisição de serviços de interligação entre redes lógicas e de comunicações de dados para as escolas do 1.º, 2.º e 3.º ciclos do Ensino Básico, Ensino Secundário das Escolas Públicas, Organismos Centrais, Regionais e Tutelados do Ministério da Educação, Ciência e Inovação (MECI), para aquisição de funcionalidades de Ponto Focal e monitorização/gestão (3 anos)",
    "preco_base": "15.787.810,56 EUR",
    "prazo_execucao": "36 MESES",
    "prazo_apresentacao_propostas": "07-10-2025 17:00",
    "fundos_eu": "Não",
    "plataforma_eletronica": "ACIN",
    "url_procedimento": "https://www.acingov.pt",
    "autor_nome": "Marlene Vieira",
    "autor_cargo": "Técnica Superior"
  },
  {
    "numero_procedimento": "N/A",
    "entidade": "Cooptécnica Gustave Eiffel, Cooperativa de Ensino e Formação Técnico Profissional, CRL",
    "link": "https://diariodarepublica.pt/dr/detalhe/contrato-publico/23817-934502542",
    "detalhes_completos": "Alteração do Anúncio de procedimento n.º 23389/2025, de 2025-09-03, com o ID 419497596\n\n1 - IDENTIFICAÇÃO E CONTACTOS DA ENTIDADE ADJUDICANTE\nDesignação da entidade adjudicante: Cooptécnica Gustave Eiffel, Cooperativa de Ensino e Formação Técnico Profissional, CRL\nNIPC: 502327669\nEndereço: Rua Elias Garcia, nº 29, Amadora\nCódigo postal: 2700-312\nLocalidade: Lisboa\nPaís: Portugal\nNUT III: PT170\nDistrito: Lisboa\nConcelho: Amadora\nFreguesia: Freguesia de Falagueira-Venda Nova\nTelefone: 214996440\nFax: 214966449\nEndereço da Entidade (URL): www.cooptecnica.pt\nEndereço Eletrónico: contratacao.publica@gustaveeiffel.pt\neDelivery Gateway (URL): https://community.vortal.biz/public/\nFunção da Organização: Adquirente\nNorma jurídica da Entidade Adjudicante: Organismo de direito público\nÁrea de atividade da Autoridade Adjudicante: Educação\n\n2 - JORNAL OFICIAL DA UNIÃO EUROPEIA\nO procedimento a que este anúncio diz respeito também é publicitado no Jornal Oficial da União Europeia? Não\n\n3 - AVISO\nModelo de Anúncio: Concurso público\nData de Envio do Anúncio: 08-09-2025\n\n5 - PROCESSO\nTipo de Procedimento: Concurso público\nPreço base do procedimento: Sim\nValor do preço base do procedimento: 150.225,00 EUR\nProcedimento com lotes? Não\n\n6 - OBJETO DO CONTRATO\nNúmero de referência interna: CP 008 CCP 2025\nDesignação do contrato: Locação de máquinas de cópia e impressão multifunções e aquisição de serviços de cópia e impressão, assistência técnica, revisão e reparação\nDescrição: Locação de máquinas de cópia e impressão multifunções e aquisição de serviços de cópia e impressão, assistência técnica, revisão e reparação\nTipo de Contrato Principal: Locação de Bens Móveis\nTipo de Contrato: Locação de Bens Móveis\nClassificação CPV (Vocabulário Comum para os Contratos Públicos)\nObjeto principal\nVocabulário Principal: 30121100\nPreço base s/IVA: 150.225,00 EUR\n\n7 - INDICAÇÕES ADICIONAIS\nO contrato envolve aquisição conjunta (satisfação de várias entidades)? Não\nO contrato é adjudicado por uma central de compras? Não\n\n8 - TÉCNICAS\nO concurso destina-se à celebração de um acordo-quadro? Inexistência de acordo-quadro\nÉ utilizado um leilão eletrónico? Não\nÉ adotada uma fase de negociação? Não\nSistema de Aquisição Dinâmico: Inexistência de sistema de aquisição dinâmico\n\n9 - LOCAL DA EXECUÇÃO DO CONTRATO\nLOCAL DA EXECUÇÃO DO CONTRATO (PROCEDIMENTO)\nPaís: Portugal\nNUT III: PT170\nLocalidade: Lisboa\nDistrito: Lisboa\nConcelho: Amadora\nFreguesia: Freguesia de Alfragide\n\n10 - PRAZO DE EXECUÇÃO DO CONTRATO\nPrazo de execução do contrato: 36 MESES\nPrevisão de renovações: Não\n\n11 - FUNDOS EU\nTêm fundos EU? Não\n\n12 - DOCUMENTOS DE HABILITAÇÃO\nHabilitação para o exercício da atividade profissional: Não\n\n13 - CONDIÇÕES DE APRESENTAÇÃO\nPlataforma eletrónica utilizada pela entidade adjudicante: VORTAL\nURL para Apresentação: https://community.vortal.biz/public/\nAdmissibilidade da apresentação de propostas variantes: Não autorizado\nPrazo para apresentação das propostas: 12-09-2025 23:59\nPrazo durante o qual os concorrentes são obrigados a manter as respetivas propostas: 66 dias a contar do termo do prazo para a apresentação das propostas\nApresentação de Catálogo Eletrónico: Permitido\nIndicação de Subcontratação na Proposta: Inexistência de indicação de subcontratação\n\n14 - PRESTAÇÃO DE CAUÇÃO\nPrestação de caução: Não\n\n15 - FORNECIMENTO DAS PEÇAS DO CONCURSO, APRESENTAÇÃO DE PEDIDOS DE PARTICIPAÇÃO E APRESENTAÇÃO DAS PROPOSTAS\nLink para acesso às peças do concurso (URL): https://community.vortal.biz/Public/public-tender-documents/Vkk3b0RWQzhRVlRnQk1Lc0I4WjBtMHZtQkZSYjNvTzBNV3dOV1pxcWNHa094OVF1anJlL1dEZnVyKzNYTjJyUktNL1Rnay95Sy9kWjNJWUFQZUU0OGc9PTMqOSh6\n\n20 - OUTROS REQUISITOS\nInformação sobre contratos reservados. Aplica-se a contratos reservados (54º-A)? Não\n\n21 - CRITÉRIO DE ADJUDICAÇÃO\nMultifator: Sim\nFator: \nNome: Preço\nPonderação: 50%\nSubfatores: Não\nFator: \nNome: Outros\nOutro Nome: Hardware\nPonderação: 10%\nSubfatores: Não\nFator: \nNome: Outros\nOutro Nome: Software\nPonderação: 10%\nSubfatores: Não\nFator: \nNome: Outros\nOutro Nome: Serviço\nPonderação: 20%\nSubfatores: Não\nFator: \nNome: Outros\nOutro Nome: Ecológico\nPonderação: 10%\nSubfatores: Não\n\n24 - CONDIÇÕES DO CONTRATO\nFaturação Eletrónica: Permitido\nObrigação de Subcontratação:\nCódigo da Obrigação de Subcontratação: Não é aplicável nenhuma obrigação de subcontratação.\n\n25 - COMPRA PÚBLICA ESTRATÉGICA\nCompra Pública Estratégica: Inexistência de contratação pública estratégica\n\n26 - INFORMAÇÕES ADICIONAIS\nContrato adequado para PME: Sim\nCobertura ACP (Acordo dos Contratos Públicos da Organização Mundial do Comércio): Não\n\n27 - IDENTIFICAÇÃO E CONTACTOS DO ÓRGÃO DE RECURSOS ADMINISTRATIVOS\nDesignação: Susana Fernandes\nEndereço: Rua Elias Garcia, nº 29, Amadora\nCódigo postal: 2700-312\nLocalidade: Amadora\nTelefone: +351 912355271\nFax: +351 214996449\nEndereço eletrónico: coontratacaopublica@gustaveeiffel.pt\n\n28 - IDENTIFICAÇÃO DO(S) AUTOR(ES) DE ANÚNCIO\nNome: Susana Fernandes\nCargo: Técnico \n\n29 - ALTERAÇÃO\nMotivo da Alteração: Correção pelo adquirente\nIdentificador da Versão do Anúncio a Alterar: f92b70c9-d07d-4354-b497-8804effc5494-01\nIdentificador das Secções Alteradas do Anúncio Anterior: Aviso\nAlteração dos Documentos do Concurso: Não\n419512888",
    "nipc": "502327669",
    "distrito": "Lisboa",
    "concelho": "Amadora",
    "freguesia": "Freguesia de Falagueira-Venda Nova",
    "site": "www.cooptecnica.pt",
    "email": "contratacao.publica@gustaveeiffel.pt",
    "designacao_contrato": "Locação de máquinas de cópia e impressão multifunções e aquisição de serviços de cópia e impressão, assistência técnica, revisão e reparação",
    "descricao": "Locação de máquinas de cópia e impressão multifunções e aquisição de serviços de cópia e impressão, assistência técnica, revisão e reparação",
    "preco_base": "150.225,00 EUR",
    "prazo_execucao": "36 MESES",
    "prazo_apresentacao_propostas": "12-09-2025 23:59",
    "fundos_eu": "Não",
    "plataforma_eletronica": "VORTAL",
    "url_procedimento": "https://community.vortal.biz/public/",
    "autor_nome": "Susana Fernandes",
    "autor_cargo": "Técnico"
  },
  {
    "numero_procedimento": "N/A",
    "entidade": "Câmara Municipal do Seixal",
    "link": "https://diariodarepublica.pt/dr/detalhe/contrato-publico/23818-934502545",
    "detalhes_completos": "1 - IDENTIFICAÇÃO E CONTACTOS DA ENTIDADE ADJUDICANTE\nDesignação da entidade adjudicante: Câmara Municipal do Seixal\nNIPC: 506173968\nServiço/Órgão/Pessoa de contacto: Divisão de Compras e Aprovisionamento\nEndereço: Rua Lino de Carvalho n.º 1\nCódigo postal: 2840-748\nLocalidade: Aldeia de Paio Pires\nPaís: Portugal\nNUT III: PT170\nDistrito: Setúbal\nConcelho: Seixal\nFreguesia: Todas\nTelefone: 212276700\nFax: 00\nEndereço da Entidade (URL): www.cm-seixal.pt\nEndereço Eletrónico: gestao.concursos@cm-seixal.pt\neDelivery Gateway (URL): https://www.acingov.pt\nFunção da Organização: Adquirente\nNorma jurídica da Entidade Adjudicante: Organismo de direito público\nÁrea de atividade da Autoridade Adjudicante: Serviços públicos das administrações públicas\n\n2 - JORNAL OFICIAL DA UNIÃO EUROPEIA\nO procedimento a que este anúncio diz respeito também é publicitado no Jornal Oficial da União Europeia? Não\n\n3 - AVISO\nModelo de Anúncio: Concurso público\nData de Envio do Anúncio: 08-09-2025\n\n5 - PROCESSO\nTipo de Procedimento: Concurso público\nPreço base do procedimento: Sim\nValor do preço base do procedimento: 208.135,00 EUR\nProcedimento com lotes? Sim\nNº Máx. de Lotes Autorizado: 3\nNúmero máximo de lotes que podem ser adjudicados a um concorrente: 3\n\n6 - OBJETO DO CONTRATO\nNúmero de referência interna: CP 1269/DCA/2025\nDesignação do contrato: Aquisição de serviços de transporte escolar de alunos com necessidades educativas especificas - Ano letivo 2025/2026 por Lotes\nDescrição: Aquisição de serviços de transporte escolar de alunos com necessidades educativas especificas - Ano letivo 2025/2026 por Lotes\nTipo de Contrato Principal: Aquisição de Serviços\nTipo de Contrato: Aquisição de Serviços\nClassificação CPV (Vocabulário Comum para os Contratos Públicos)\nObjeto principal\nVocabulário Principal: 60130000\nPreço base s/IVA: 208.135,00 EUR\nLotes: \nNº: LOT-0001\nDescrição do Lote: Rota Seixal - Almada - Seixal\nPreço base s/IVA: 126.480,00 EUR\nClassificação CPV (Vocabulário Comum para os Contratos Públicos)\nObjeto principal\nVocabulário Principal: 60130000\nNº: LOT-0002\nDescrição do Lote: Rota Seixal - Sesimbra - Seixal (com necessidade de vigilante)\nPreço base s/IVA: 32.015,00 EUR\nClassificação CPV (Vocabulário Comum para os Contratos Públicos)\nObjeto principal\nVocabulário Principal: 60130000\nNº: LOT-0003\nDescrição do Lote: Rota Seixal - Lisboa - Seixal\nPreço base s/IVA: 49.640,00 EUR\nClassificação CPV (Vocabulário Comum para os Contratos Públicos)\nObjeto principal\nVocabulário Principal: 60130000\n\n7 - INDICAÇÕES ADICIONAIS\nO contrato envolve aquisição conjunta (satisfação de várias entidades)? Não\nO contrato é adjudicado por uma central de compras? Não\n\n8 - TÉCNICAS\nO concurso destina-se à celebração de um acordo-quadro? Inexistência de acordo-quadro\nÉ utilizado um leilão eletrónico? Não\nÉ adotada uma fase de negociação? Não\nSistema de Aquisição Dinâmico: Inexistência de sistema de aquisição dinâmico\n\n9 - LOCAL DA EXECUÇÃO DO CONTRATO\nLOCAL DA EXECUÇÃO DO CONTRATO (PROCEDIMENTO)\nPaís: Portugal\nNUT III: PT170\nLocalidade: União das Freguesias do Seixal, Arrentela e Aldeia de Paio Pires\nDistrito: Setúbal\nConcelho: Seixal\nFreguesia: União das Freguesias do Seixal, Arrentela e Aldeia de Paio Pires\nLOCAL DA EXECUÇÃO DO CONTRATO (LOTE)\nIdentificador do Lote: LOT-0001; LOT-0002; LOT-0003\nPaís: Portugal\nNUT III: PT170\nLocalidade: União das Freguesias do Seixal, Arrentela e Aldeia de Paio Pires\nDistrito: Setúbal\nConcelho: Seixal\nFreguesia: União das Freguesias do Seixal, Arrentela e Aldeia de Paio Pires\n\n10 - PRAZO DE EXECUÇÃO DO CONTRATO\nIdentificador do Lote: LOT-0001; LOT-0002; LOT-0003\nPrazo de execução do contrato: 293 DIAS\nPrevisão de renovações: Não\n\n11 - FUNDOS EU\nIdentificador do Lote: LOT-0001; LOT-0002; LOT-0003\nTêm fundos EU? Não\n\n12 - DOCUMENTOS DE HABILITAÇÃO\nHabilitação para o exercício da atividade profissional: Não\n\n13 - CONDIÇÕES DE APRESENTAÇÃO\nPlataforma eletrónica utilizada pela entidade adjudicante: ACIN\nURL para Apresentação: https://www.acingov.pt\nAdmissibilidade da apresentação de propostas variantes: Não autorizado\nPrazo para apresentação das propostas: 18-09-2025 23:59\nPrazo durante o qual os concorrentes são obrigados a manter as respetivas propostas: 66 dias a contar do termo do prazo para a apresentação das propostas\nIndicação de Subcontratação na Proposta: Inexistência de indicação de subcontratação\n\n14 - PRESTAÇÃO DE CAUÇÃO\nPrestação de caução: Não\n\n15 - FORNECIMENTO DAS PEÇAS DO CONCURSO, APRESENTAÇÃO DE PEDIDOS DE PARTICIPAÇÃO E APRESENTAÇÃO DAS PROPOSTAS\nLink para acesso às peças do concurso (URL): https://www.acingov.pt/acingovprod/2/zonaPublica/zona_publica_c/donwloadProcedurePiece/OTc2MTY0\n\n20 - OUTROS REQUISITOS\nIdentificador do Lote: LOT-0001; LOT-0002; LOT-0003\nInformação sobre contratos reservados. Aplica-se a contratos reservados (54º-A)? Não\n\n21 - CRITÉRIO DE ADJUDICAÇÃO\nO Critério de adjudicação é diferenciado por lote? Não\nMultifator: Não\nMonofator:\nNome: Preço\n\n24 - CONDIÇÕES DO CONTRATO\nIdentificador do Lote: LOT-0001; LOT-0002; LOT-0003\nFaturação Eletrónica: Permitido\nObrigação de Subcontratação:\nCódigo da Obrigação de Subcontratação: Não é aplicável nenhuma obrigação de subcontratação.\n\n25 - COMPRA PÚBLICA ESTRATÉGICA\nCompra Pública Estratégica: Inexistência de contratação pública estratégica\n\n26 - INFORMAÇÕES ADICIONAIS\nIdentificador do Lote: LOT-0001; LOT-0002; LOT-0003\nContrato adequado para PME: Sim\nCobertura ACP (Acordo dos Contratos Públicos da Organização Mundial do Comércio): Não\n\n27 - IDENTIFICAÇÃO E CONTACTOS DO ÓRGÃO DE RECURSOS ADMINISTRATIVOS\nDesignação: Câmara Municipal do Seixal\nEndereço: Alameda dos Bombeiros Voluntários, 45\nCódigo postal: 2844-001\nLocalidade: Seixal\nTelefone: 212276700\nFax: \nEndereço eletrónico: gestao.concursos@cm-seixal.pt\n\n28 - IDENTIFICAÇÃO DO(S) AUTOR(ES) DE ANÚNCIO\nNome: Paulo Alexandre da Conceição Silva\nCargo: Presidente da Câmara Municipal do Seixal\n419513405",
    "nipc": "506173968",
    "distrito": "Setúbal",
    "concelho": "Seixal",
    "freguesia": "Todas",
    "site": "www.cm-seixal.pt",
    "email": "gestao.concursos@cm-seixal.pt",
    "designacao_contrato": "Aquisição de serviços de transporte escolar de alunos com necessidades educativas especificas - Ano letivo 2025/2026 por Lotes",
    "descricao": "Aquisição de serviços de transporte escolar de alunos com necessidades educativas especificas - Ano letivo 2025/2026 por Lotes",
    "preco_base": "208.135,00 EUR",
    "prazo_execucao": "293 DIAS",
    "prazo_apresentacao_propostas": "18-09-2025 23:59",
    "fundos_eu": "Não",
    "plataforma_eletronica": "ACIN",
    "url_procedimento": "https://www.acingov.pt",
    "autor_nome": "Paulo Alexandre da Conceição Silva",
    "autor_cargo": "Presidente da Câmara Municipal do Seixal"
  },
  {
    "numero_procedimento": "N/A",
    "entidade": "MUNICÍPIO DE VILA DO BISPO",
    "link": "https://diariodarepublica.pt/dr/detalhe/contrato-publico/23819-934502546",
    "detalhes_completos": "1 - IDENTIFICAÇÃO E CONTACTOS DA ENTIDADE ADJUDICANTE\nDesignação da entidade adjudicante: MUNICÍPIO DE VILA DO BISPO\nNIPC: 506730573\nEndereço: Pç. Município\nCódigo postal: 8650-407\nLocalidade: Faro\nPaís: Portugal\nNUT III: PT150\nDistrito: Faro\nConcelho: Vila do Bispo\nFreguesia: Todas\nTelefone: 282630600\nFax: 282639208\nEndereço da Entidade (URL): http://www.cm-viladobispo.pt\nEndereço Eletrónico: geral@cm-viladobispo.pt\neDelivery Gateway (URL): https://community.vortal.biz/public/\nFunção da Organização: Adquirente\nNorma jurídica da Entidade Adjudicante: Organismo de direito público\nÁrea de atividade da Autoridade Adjudicante: Serviços públicos das administrações públicas\n\n2 - JORNAL OFICIAL DA UNIÃO EUROPEIA\nO procedimento a que este anúncio diz respeito também é publicitado no Jornal Oficial da União Europeia? Não\n\n3 - AVISO\nModelo de Anúncio: Concurso público\nData de Envio do Anúncio: 08-09-2025\n\n5 - PROCESSO\nTipo de Procedimento: Concurso público\nPreço base do procedimento: Sim\nValor do preço base do procedimento: 116.000,00 EUR\nProcedimento com lotes? Não\n\n6 - OBJETO DO CONTRATO\nNúmero de referência interna: DGM 76/2025 Viatura pesada de recolha de resíduos\nDesignação do contrato: Concurso Público para aquisição de viatura pesada de recolha de resíduos com grua\nDescrição: Aquisição de viatura pesada de recolha de resíduos com grua\nTipo de Contrato Principal: Aquisição de Bens Móveis\nTipo de Contrato: Aquisição de Bens Móveis\nClassificação CPV (Vocabulário Comum para os Contratos Públicos)\nObjeto principal\nVocabulário Principal: 34144511\nPreço base s/IVA: 116.000,00 EUR\n\n7 - INDICAÇÕES ADICIONAIS\nO contrato envolve aquisição conjunta (satisfação de várias entidades)? Não\nO contrato é adjudicado por uma central de compras? Não\n\n8 - TÉCNICAS\nO concurso destina-se à celebração de um acordo-quadro? Inexistência de acordo-quadro\nÉ utilizado um leilão eletrónico? Não\nÉ adotada uma fase de negociação? Não\nSistema de Aquisição Dinâmico: Inexistência de sistema de aquisição dinâmico\n\n9 - LOCAL DA EXECUÇÃO DO CONTRATO\nLOCAL DA EXECUÇÃO DO CONTRATO (PROCEDIMENTO)\nPaís: Portugal\nNUT III: PT150\nLocalidade: Faro\nDistrito: Faro\nConcelho: Vila do Bispo\nFreguesia: Freguesia de Vila do Bispo e Raposeira\n\n10 - PRAZO DE EXECUÇÃO DO CONTRATO\nPrazo de execução do contrato: 90 DIAS\nPrevisão de renovações: Não\n\n11 - FUNDOS EU\nTêm fundos EU? Não\n\n12 - DOCUMENTOS DE HABILITAÇÃO\nHabilitação para o exercício da atividade profissional: Não\n\n13 - CONDIÇÕES DE APRESENTAÇÃO\nPlataforma eletrónica utilizada pela entidade adjudicante: VORTAL\nURL para Apresentação: https://community.vortal.biz/public/\nAdmissibilidade da apresentação de propostas variantes: Não autorizado\nPrazo para apresentação das propostas: 23-09-2025 15:00\nPrazo durante o qual os concorrentes são obrigados a manter as respetivas propostas: 66 dias a contar do termo do prazo para a apresentação das propostas\nIndicação de Subcontratação na Proposta: Inexistência de indicação de subcontratação\n\n14 - PRESTAÇÃO DE CAUÇÃO\nPrestação de caução: Não\n\n15 - FORNECIMENTO DAS PEÇAS DO CONCURSO, APRESENTAÇÃO DE PEDIDOS DE PARTICIPAÇÃO E APRESENTAÇÃO DAS PROPOSTAS\nLink para acesso às peças do concurso (URL): https://community.vortal.biz/Public/public-tender-documents/Nk1QVUw1Ym0ybythTldPUEsrVlhxKzZFRTJvTTFvV2wwc3VvWGtMQ1lDa1R2a3FMNHNGZmFPZTdIV0Q2WlhOVStKVmZxS1crbzR4Q2d1QW80Z2wzUEE9PVUzXjIl\n\n20 - OUTROS REQUISITOS\nInformação sobre contratos reservados. Aplica-se a contratos reservados (54º-A)? Não\n\n21 - CRITÉRIO DE ADJUDICAÇÃO\nMultifator: Não\nMonofator:\nNome: Preço\n\n24 - CONDIÇÕES DO CONTRATO\nFaturação Eletrónica: Permitido\nObrigação de Subcontratação:\nCódigo da Obrigação de Subcontratação: Não é aplicável nenhuma obrigação de subcontratação.\n\n25 - COMPRA PÚBLICA ESTRATÉGICA\nCompra Pública Estratégica: Inexistência de contratação pública estratégica\n\n26 - INFORMAÇÕES ADICIONAIS\nContrato adequado para PME: Sim\nCobertura ACP (Acordo dos Contratos Públicos da Organização Mundial do Comércio): Não\n\n27 - IDENTIFICAÇÃO E CONTACTOS DO ÓRGÃO DE RECURSOS ADMINISTRATIVOS\nDesignação: Presidente da Câmara Municipal\nEndereço: Pç. Município\nCódigo postal: 8650-407\nLocalidade: Vila do Bispo\nTelefone: +351 282630600\nFax: +351 282639208\nEndereço eletrónico: geral@cm-viladobispo.pt\n\n28 - IDENTIFICAÇÃO DO(S) AUTOR(ES) DE ANÚNCIO\nNome: Rute Maria Dias Maia Nunes da Silva\nCargo: Presidente da Câmara Municipal\n419510465",
    "nipc": "506730573",
    "distrito": "Faro",
    "concelho": "Vila do Bispo",
    "freguesia": "Todas",
    "site": "http://www.cm-viladobispo.pt",
    "email": "geral@cm-viladobispo.pt",
    "designacao_contrato": "Concurso Público para aquisição de viatura pesada de recolha de resíduos com grua",
    "descricao": "Aquisição de viatura pesada de recolha de resíduos com grua",
    "preco_base": "116.000,00 EUR",
    "prazo_execucao": "90 DIAS",
    "prazo_apresentacao_propostas": "23-09-2025 15:00",
    "fundos_eu": "Não",
    "plataforma_eletronica": "VORTAL",
    "url_procedimento": "https://community.vortal.biz/public/",
    "autor_nome": "Rute Maria Dias Maia Nunes da Silva",
    "autor_cargo": "Presidente da Câmara Municipal"
  },
  {
    "numero_procedimento": "N/A",
    "entidade": "Município de Monção",
    "link": "https://diariodarepublica.pt/dr/detalhe/contrato-publico/23820-934502547",
    "detalhes_completos": "Alteração do Anúncio de procedimento n.º 23586/2025, de 2025-09-05, com o ID 419503612\n\n1 - IDENTIFICAÇÃO E CONTACTOS DA ENTIDADE ADJUDICANTE\nDesignação da entidade adjudicante: Município de Monção\nNIPC: 501937471\nEndereço: Edifício Loreto\nCódigo postal: 4950-480\nLocalidade: Viana do Castelo\nPaís: Portugal\nNUT III: PT111\nDistrito: Viana do Castelo\nConcelho: Monção\nFreguesia: Todas\nTelefone: 251649000\nFax: 251649010\nEndereço da Entidade (URL): www.cm-moncao.pt\nEndereço Eletrónico: gap@cm-moncao.pt\neDelivery Gateway (URL): https://community.vortal.biz/public/\nFunção da Organização: Adquirente\nNorma jurídica da Entidade Adjudicante: Autoridade local\nÁrea de atividade da Autoridade Adjudicante: Serviços públicos das administrações públicas\n\n2 - JORNAL OFICIAL DA UNIÃO EUROPEIA\nO procedimento a que este anúncio diz respeito também é publicitado no Jornal Oficial da União Europeia? Não\n\n3 - AVISO\nModelo de Anúncio: Concurso público\nData de Envio do Anúncio: 08-09-2025\n\n5 - PROCESSO\nTipo de Procedimento: Concurso público\nPreço base do procedimento: Sim\nValor do preço base do procedimento: 205.285,00 EUR\nProcedimento com lotes? Não\n\n6 - OBJETO DO CONTRATO\nNúmero de referência interna: 17_578_5_DPOP\nDesignação do contrato: Aquisição de serviços para aluguer de instalações provisórias para o Centro de Saúde de Monção\nDescrição: Aquisição de serviços para aluguer de instalações provisórias para o Centro de Saúde de Monção\nTipo de Contrato Principal: Aquisição de Serviços\nTipo de Contrato: Aquisição de Serviços\nClassificação CPV (Vocabulário Comum para os Contratos Públicos)\nObjeto principal\nVocabulário Principal: 55250000\nPreço base s/IVA: 205.285,00 EUR\n\n7 - INDICAÇÕES ADICIONAIS\nO contrato envolve aquisição conjunta (satisfação de várias entidades)? Não\nO contrato é adjudicado por uma central de compras? Não\n\n8 - TÉCNICAS\nO concurso destina-se à celebração de um acordo-quadro? Inexistência de acordo-quadro\nÉ utilizado um leilão eletrónico? Não\nÉ adotada uma fase de negociação? Não\nSistema de Aquisição Dinâmico: Inexistência de sistema de aquisição dinâmico\n\n9 - LOCAL DA EXECUÇÃO DO CONTRATO\nLOCAL DA EXECUÇÃO DO CONTRATO (PROCEDIMENTO)\nPaís: Portugal\nNUT III: PT111\nLocalidade: Viana do Castelo\nDistrito: Viana do Castelo\nConcelho: Monção\nFreguesia: União das Freguesias de Monção e Troviscoso\n\n10 - PRAZO DE EXECUÇÃO DO CONTRATO\nPrazo de execução do contrato: 480 DIAS\nPrevisão de renovações: Não\n\n11 - FUNDOS EU\nTêm fundos EU? Não\n\n12 - DOCUMENTOS DE HABILITAÇÃO\nHabilitação para o exercício da atividade profissional: Não\n\n13 - CONDIÇÕES DE APRESENTAÇÃO\nPlataforma eletrónica utilizada pela entidade adjudicante: VORTAL\nURL para Apresentação: https://community.vortal.biz/public/\nAdmissibilidade da apresentação de propostas variantes: Não autorizado\nPrazo para apresentação das propostas: 12-09-2025 16:15\nPrazo durante o qual os concorrentes são obrigados a manter as respetivas propostas: 66 dias a contar do termo do prazo para a apresentação das propostas\nApresentação de Catálogo Eletrónico: Permitido\nIndicação de Subcontratação na Proposta: Inexistência de indicação de subcontratação\n\n14 - PRESTAÇÃO DE CAUÇÃO\nPrestação de caução: Não\n\n15 - FORNECIMENTO DAS PEÇAS DO CONCURSO, APRESENTAÇÃO DE PEDIDOS DE PARTICIPAÇÃO E APRESENTAÇÃO DAS PROPOSTAS\nLink para acesso às peças do concurso (URL): https://community.vortal.biz/Public/public-tender-documents/NCtPZUhwQzcxYnNXR3FvSnpFQ2d0V2paeGF6dVl4Y1R6ZW5aSnN3UFpyUnUrdldHaHVFUDBjT1ZZZnpCRnV0eXFlRDNaVEpvckZiUmZEREd1TjJQT0E9PSQ4dHRa\n\n20 - OUTROS REQUISITOS\nInformação sobre contratos reservados. Aplica-se a contratos reservados (54º-A)? Não\n\n21 - CRITÉRIO DE ADJUDICAÇÃO\nMultifator: Não\nMonofator:\nNome: Preço\n\n24 - CONDIÇÕES DO CONTRATO\nFaturação Eletrónica: Permitido\nObrigação de Subcontratação:\nCódigo da Obrigação de Subcontratação: Não é aplicável nenhuma obrigação de subcontratação.\n\n25 - COMPRA PÚBLICA ESTRATÉGICA\nCompra Pública Estratégica: Inexistência de contratação pública estratégica\n\n26 - INFORMAÇÕES ADICIONAIS\nContrato adequado para PME: Sim\nCobertura ACP (Acordo dos Contratos Públicos da Organização Mundial do Comércio): Não\n\n27 - IDENTIFICAÇÃO E CONTACTOS DO ÓRGÃO DE RECURSOS ADMINISTRATIVOS\nDesignação: Câmara Municipal de Monção\nEndereço: Largo do Loreto n. 60\nCódigo postal: 4950-480\nLocalidade: Monção\nTelefone: +351 251649000\nFax: +351 251649000\nEndereço eletrónico: gap@cm-moncao.pt\n\n28 - IDENTIFICAÇÃO DO(S) AUTOR(ES) DE ANÚNCIO\nNome: António José Fernandes Barbosa\nCargo: Presidente da Câmara Municipal\n\n29 - ALTERAÇÃO\nMotivo da Alteração: Informações atualizadas\nIdentificador da Versão do Anúncio a Alterar: a69d3886-afcd-4c95-9845-4d2928ed896f-01\nIdentificador das Secções Alteradas do Anúncio Anterior: Condições de Apresentação\nDescrição das Alterações: prorrogação de prazo para apresentação de propostas\nAlteração dos Documentos do Concurso: Não\n419513519",
    "nipc": "501937471",
    "distrito": "Viana do Castelo",
    "concelho": "Monção",
    "freguesia": "Todas",
    "site": "www.cm-moncao.pt",
    "email": "gap@cm-moncao.pt",
    "designacao_contrato": "Aquisição de serviços para aluguer de instalações provisórias para o Centro de Saúde de Monção",
    "descricao": "Aquisição de serviços para aluguer de instalações provisórias para o Centro de Saúde de Monção",
    "preco_base": "205.285,00 EUR",
    "prazo_execucao": "480 DIAS",
    "prazo_apresentacao_propostas": "12-09-2025 16:15",
    "fundos_eu": "Não",
    "plataforma_eletronica": "VORTAL",
    "url_procedimento": "https://community.vortal.biz/public/",
    "autor_nome": "António José Fernandes Barbosa",
    "autor_cargo": "Presidente da Câmara Municipal"
  },
  {
    "numero_procedimento": "N/A",
    "entidade": "Universidade do Minho",
    "link": "https://diariodarepublica.pt/dr/detalhe/contrato-publico/23823-934502548",
    "detalhes_completos": "1 - IDENTIFICAÇÃO E CONTACTOS DA ENTIDADE ADJUDICANTE\nDesignação da entidade adjudicante: Universidade do Minho\nNIPC: 502011378\nServiço/Órgão/Pessoa de contacto: Ana Paula Esteves\nEndereço: Largo do Paço\nCódigo postal: 4704-553\nLocalidade: Braga\nPaís: Portugal\nNUT III: PT112\nDistrito: Braga\nConcelho: Braga\nFreguesia: Freguesia de Gualtar\nTelefone: 253601045\nFax: 253601045\nEndereço da Entidade (URL): www.uminho.pt\nEndereço Eletrónico: sec-adm@reitoria.uminho.pt\neDelivery Gateway (URL): https://www.acingov.pt\nFunção da Organização: Adquirente\nSubfunção da Organização: Organização cujo orçamento é utilizado para pagar o contrato; Organização que executa o pagamento; Líder do grupo; Organização que fornece informações adicionais sobre o processo de adjudicação; Organização que fornece mais informações sobre os prazos dos procedimentos de recurso; Organização que fornece acesso fora de linha aos documentos do concurso; Organização responsável pelo tratamento das propostas; Organização que recebe as propostas; Organização que trata os pedidos de participação; Organização que recebe pedidos de participação; Organização que fornece mais informações sobre os procedimentos de recurso; Organização que assina o contrato\nNorma jurídica da Entidade Adjudicante: Organismo de direito público\nÁrea de atividade da Autoridade Adjudicante: Educação\n\n2 - JORNAL OFICIAL DA UNIÃO EUROPEIA\nO procedimento a que este anúncio diz respeito também é publicitado no Jornal Oficial da União Europeia? Não\n\n3 - AVISO\nModelo de Anúncio: Concurso público\nData de Envio do Anúncio: 08-09-2025\n\n5 - PROCESSO\nTipo de Procedimento: Concurso público\nPreço base do procedimento: Sim\nValor do preço base do procedimento: 24.814,77 EUR\nProcedimento com lotes? Sim\nNº Máx. de Lotes Autorizado: 218\nNúmero máximo de lotes que podem ser adjudicados a um concorrente: 218\n\n6 - OBJETO DO CONTRATO\nNúmero de referência interna: CP USDB-03/2025\nDesignação do contrato: AQUISIÇÃO DE RECURSOS BIBLIOGRÁFICOS, POR LOTES.\nDescrição: AQUISIÇÃO DE RECURSOS BIBLIOGRÁFICOS, POR LOTES.\nTipo de Contrato Principal: Aquisição de Bens Móveis\nTipo de Contrato: Aquisição de Bens Móveis\nClassificação CPV (Vocabulário Comum para os Contratos Públicos)\nObjeto principal\nVocabulário Principal: 22113000\nPreço base s/IVA: 24.814,77 EUR\nLotes: \nNº: LOT-0001\nDescrição do Lote: Klaus Evertz, Ludwig Janus & Rupert Linder. Handbook of prenatal and perinatal psychology. Springer Cham\nPreço base s/IVA: 239,47 EUR\nClassificação CPV (Vocabulário Comum para os Contratos Públicos)\nObjeto principal\nVocabulário Principal: 22113000\nNº: LOT-0002\nDescrição do Lote: Downes, Paul;  Li, Guofang; Van Praag, Lore;  Lamb, Stephen. The Routledge International Handbook of Equity and Inclusion in Education. Routlege\nPreço base s/IVA: 311,41 EUR\nClassificação CPV (Vocabulário Comum para os Contratos Públicos)\nObjeto principal\nVocabulário Principal: 22113000\nNº: LOT-0003\nDescrição do Lote: Van Weele & Rozemeijer (2022) Procurement and Supply Chain Management, 8th Edition. Cengage\nPreço base s/IVA: 51,81 EUR\nClassificação CPV (Vocabulário Comum para os Contratos Públicos)\nObjeto principal\nVocabulário Principal: 22113000\nNº: LOT-0004\nDescrição do Lote: Craig, L. A.; Dixon, L.; Gannon, T. A.The Wiley Handbook of What Works in Correctional Rehabilitation: An Evidence-Based Approach to Theory, Assessment and Treatment, 2nd Edition\nPreço base s/IVA: 67,51 EUR\nClassificação CPV (Vocabulário Comum para os Contratos Públicos)\nObjeto principal\nVocabulário Principal: 22113000\nNº: LOT-0005\nDescrição do Lote: Wyatt R. Evans, Robyn D. Walser, Kent D. Drescher. The Moral Injury Workbook: Acceptance and Commitment Therapy Skills for Moving Beyond Shame, Anger, and Trauma to Reclaim Your Values Paperback\nPreço base s/IVA: 16,17 EUR\nClassificação CPV (Vocabulário Comum para os Contratos Públicos)\nObjeto principal\nVocabulário Principal: 22113000\nNº: LOT-0006\nDescrição do Lote: Tetrick, L.E.; Fisher, G.G.; Ford, M.T.; Campbell, J. (2023). Handbook of Occupational Health Psychology (3rd ed.)\nPreço base s/IVA: 99,22 EUR\nClassificação CPV (Vocabulário Comum para os Contratos Públicos)\nObjeto principal\nVocabulário Principal: 22113000\nNº: LOT-0007\nDescrição do Lote: Cooper, C. L.; Quick, J. C. (2017) The handbook of stress and health: A Guide to Research and Practice\nPreço base s/IVA: 221,19 EUR\nClassificação CPV (Vocabulário Comum para os Contratos Públicos)\nObjeto principal\nVocabulário Principal: 22113000\nNº: LOT-0008\nDescrição do Lote: AGMacedo, M. Pereira, M. Oliveira and J. Passos. Women, the Arts and Dictatorship in the Portuguese Speaking Context. De Gruyter, 2024\nPreço base s/IVA: 115,85 EUR\nClassificação CPV (Vocabulário Comum para os Contratos Públicos)\nObjeto principal\nVocabulário Principal: 22113000\nNº: LOT-0009\nDescrição do Lote: Winters, A. (2021). Omni-Channel Retailing: An Analysis of Channel Interdependencies, Integration Services and Specific Marketing Instruments. Springer Gabler.\nPreço base s/IVA: 90,17 EUR\nClassificação CPV (Vocabulário Comum para os Contratos Públicos)\nObjeto principal\nVocabulário Principal: 22113000\nNº: LOT-0010\nDescrição do Lote: Dirsehan, T. (2020). Managing Customer Experiences in an Omnichannel World: Melody of Online and Offline Environments in the Customer Journey\nPreço base s/IVA: 96,76 EUR\nClassificação CPV (Vocabulário Comum para os Contratos Públicos)\nObjeto principal\nVocabulário Principal: 22113000\nNº: LOT-0011\nDescrição do Lote: Keeley, K. L. (Ed.). (2025) AI Applications and Strategies in Teacher Education. IGI Global\nPreço base s/IVA: 202,65 EUR\nClassificação CPV (Vocabulário Comum para os Contratos Públicos)\nObjeto principal\nVocabulário Principal: 22113000\nNº: LOT-0012\nDescrição do Lote: Sharma, R. C. & Bozkurt, A. (Eds.). (2024) Transforming Education With Generative AI: Prompt Engineering and Synthetic Content Creation. IGI Global\nPreço base s/IVA: 198,52 EUR\nClassificação CPV (Vocabulário Comum para os Contratos Públicos)\nObjeto principal\nVocabulário Principal: 22113000\nNº: LOT-0013\nDescrição do Lote: Pan, F. (Ed.). (2024) AI in Language Teaching, Learning, and Assessment. IGI Global\nPreço base s/IVA: 190,27 EUR\nClassificação CPV (Vocabulário Comum para os Contratos Públicos)\nObjeto principal\nVocabulário Principal: 22113000\nNº: LOT-0014\nDescrição do Lote: eBo. Innovative Teaching Strategies and New Learning Paradigms in Computer Programming. IGI Global\nPreço base s/IVA: 161,35 EUR\nClassificação CPV (Vocabulário Comum para os Contratos Públicos)\nObjeto principal\nVocabulário Principal: 22113000\nNº: LOT-0015\nDescrição do Lote: Bers, M. (Ed.). (2021)Teaching Computational Thinking and Coding to Young Children. IGI Global\nPreço base s/IVA: 177,84 EUR\nClassificação CPV (Vocabulário Comum para os Contratos Públicos)\nObjeto principal\nVocabulário Principal: 22113000\nNº: LOT-0016\nDescrição do Lote: Kert, S. B. (Ed.). (2025) Effective Computer Science Education in K-12 Classrooms. IGI Global\nPreço base s/IVA: 194,38 EUR\nClassificação CPV (Vocabulário Comum para os Contratos Públicos)\nObjeto principal\nVocabulário Principal: 22113000\nNº: LOT-0017\nDescrição do Lote: Meletiadou, E. (Ed.). (2023) Handbook of Research on Redesigning Teaching, Learning, and Assessment in the Digital Era. IGI Global\nPreço base s/IVA: 223,33 EUR\nClassificação CPV (Vocabulário Comum para os Contratos Públicos)\nObjeto principal\nVocabulário Principal: 22113000\nNº: LOT-0018\nDescrição do Lote: Karen Hammerness, Raisa Ahtiainen, Pasi Sahlberg (2017) Empowered Educators in Finland How High-Performing Systems Shape Teaching Quality. Jossey-Bass\nPreço base s/IVA: 24,81 EUR\nClassificação CPV (Vocabulário Comum para os Contratos Públicos)\nObjeto principal\nVocabulário Principal: 22113000\nNº: LOT-0019\nDescrição do Lote: Bob Bain, Arthur Chapman, Alison Kitson. History Education and Historical Inquiry (International Review of History Education). Information Age Publishing\nPreço base s/IVA: 70,31 EUR\nClassificação CPV (Vocabulário Comum para os Contratos Públicos)\nObjeto principal\nVocabulário Principal: 22113000\nNº: LOT-0020\nDescrição do Lote: Dupourqué, Etienne; Planchet, Frédéric; Sator, Néfissa (Editors) (2019), Actuarial Aspects of Long Term Care, Springer (Springer Actuarial Book Series).\nPreço base s/IVA: 123,24 EUR\nClassificação CPV (Vocabulário Comum para os Contratos Públicos)\nObjeto principal\nVocabulário Principal: 22113000\nNº: LOT-0021\nDescrição do Lote: Burrell, Barbara (ed.) A Companion to the Archaeology of the Roman Empire. John Wiley & Sons, 2024\nPreço base s/IVA: 410,24 EUR\nClassificação CPV (Vocabulário Comum para os Contratos Públicos)\nObjeto principal\nVocabulário Principal: 22113000\nNº: LOT-0022\nDescrição do Lote: Jonathan Michael Bowman. Nonverbal Communication - an applied approach. Sage\nPreço base s/IVA: 74,12 EUR\nClassificação CPV (Vocabulário Comum para os Contratos Públicos)\nObjeto principal\nVocabulário Principal: 22113000\nNº: LOT-0023\nDescrição do Lote: Rubén Camilo Lois-González. Geographies of Mediterranean Europe. Springer\nPreço base s/IVA: 132,34 EUR\nClassificação CPV (Vocabulário Comum para os Contratos Públicos)\nObjeto principal\nVocabulário Principal: 22113000\nNº: LOT-0024\nDescrição do Lote: Edited by Tanya Bondarouk et al. (2024). Research Handbook on Human Resource Management and Disruptive Technologies. Edward Elgar.\nPreço base s/IVA: 219,20 EUR\nClassificação CPV (Vocabulário Comum para os Contratos Públicos)\nObjeto principal\nVocabulário Principal: 22113000\nNº: LOT-0025\nDescrição do Lote: Almond, Gabriel A. e Sidney Verba. 1963. The Civic Culture: Political Attitudes and Democracy in Five Nations. Boston, MA: Little, Brown and Company.\nPreço base s/IVA: 98,43 EUR\nClassificação CPV (Vocabulário Comum para os Contratos Públicos)\nObjeto principal\nVocabulário Principal: 22113000\nNº: LOT-0026\nDescrição do Lote: Piketty, T. (2014). Capital in the 21st century. Harvard University Press.\nPreço base s/IVA: 33,91 EUR\nClassificação CPV (Vocabulário Comum para os Contratos Públicos)\nObjeto principal\nVocabulário Principal: 22113000\nNº: LOT-0027\nDescrição do Lote: Dahl, Robert, Democracy and its critics, Yale: Yale University Press, 1992\nPreço base s/IVA: 23,15 EUR\nClassificação CPV (Vocabulário Comum para os Contratos Públicos)\nObjeto principal\nVocabulário Principal: 22113000\nNº: LOT-0028\nDescrição do Lote: Coulon, Edouard. L´évasion fiscale Essai de construction d'une catégorie juridique - Prix de thèse de l'Université Paris-Panthéon-Assas. Dalloz\nPreço base s/IVA: 82,00 EUR\nClassificação CPV (Vocabulário Comum para os Contratos Públicos)\nObjeto principal\nVocabulário Principal: 22113000\nNº: LOT-0029\nDescrição do Lote: Linda D. Urden, Kathleen M. Stacy, & Mary E. Lough. Critical care nursing: diagnosis and management (9th ed.). Elsevier\nPreço base s/IVA: 123,61 EUR\nClassificação CPV (Vocabulário Comum para os Contratos Públicos)\nObjeto principal\nVocabulário Principal: 22113000\nNº: LOT-0030\nDescrição do Lote: Donna D. Ignatavicius & M. Linda Workman & Cherie R. Rebar & Nicole M. Heimgartner. Medical-surgical nursing. Elsevier\nPreço base s/IVA: 166,68 EUR\nClassificação CPV (Vocabulário Comum para os Contratos Públicos)\nObjeto principal\nVocabulário Principal: 22113000\nNº: LOT-0031\nDescrição do Lote: Manuela Frederico & Fernando Sousa. Gerir com qualidade em saúde. Lidel\nPreço base s/IVA: 22,80 EUR\nClassificação CPV (Vocabulário Comum para os Contratos Públicos)\nObjeto principal\nVocabulário Principal: 22113000\nNº: LOT-0032\nDescrição do Lote: Edited by Colette Henry et al. (2023). Women's Entrepreneurship Policy. Edward Elgar.\nPreço base s/IVA: 115,96 EUR\nClassificação CPV (Vocabulário Comum para os Contratos Públicos)\nObjeto principal\nVocabulário Principal: 22113000\nNº: LOT-0033\nDescrição do Lote: José Carlos Santos & John R. Cutcliffe. European psychiatric/mental health nursing In the 21st century. Springer International Publishing AG\nPreço base s/IVA: 78,85 EUR\nClassificação CPV (Vocabulário Comum para os Contratos Públicos)\nObjeto principal\nVocabulário Principal: 22113000\nNº: LOT-0034\nDescrição do Lote: Sérgio Deodato. Direito da saúde. Almedina\nPreço base s/IVA: 24,10 EUR\nClassificação CPV (Vocabulário Comum para os Contratos Públicos)\nObjeto principal\nVocabulário Principal: 22113000\nNº: LOT-0035\nDescrição do Lote: Edited by Cynthia Forson et al. (2024) Research Handbook on Inequalities and Work.Edward Elger.\nPreço base s/IVA: 289,11 EUR\nClassificação CPV (Vocabulário Comum para os Contratos Públicos)\nObjeto principal\nVocabulário Principal: 22113000\nNº: LOT-0036\nDescrição do Lote: Margarida Ferreira & Carlos M. Ferreira. Intervenções e procedimentos em enfermagem. Lidel\nPreço base s/IVA: 25,36 EUR\nClassificação CPV (Vocabulário Comum para os Contratos Públicos)\nObjeto principal\nVocabulário Principal: 22113000\nNº: LOT-0037\nDescrição do Lote: Lisa Feldman Barrett. How emotions are made - The secret life of the brain. Pan MacMillan\nPreço base s/IVA: 14,57 EUR\nClassificação CPV (Vocabulário Comum para os Contratos Públicos)\nObjeto principal\nVocabulário Principal: 22113000\nNº: LOT-0038\nDescrição do Lote: Arulkumaran, S., Ledger, W. & Denny,L. Oxford textbook of obstetrics and gynaecology. Oxford University Press\nPreço base s/IVA: 44,32 EUR\nClassificação CPV (Vocabulário Comum para os Contratos Públicos)\nObjeto principal\nVocabulário Principal: 22113000\nNº: LOT-0039\nDescrição do Lote: Roger P. Smith. Netter's obstetrics and gynecology. Elsevier\nPreço base s/IVA: 90,33 EUR\nClassificação CPV (Vocabulário Comum para os Contratos Públicos)\nObjeto principal\nVocabulário Principal: 22113000\nNº: LOT-0040\nDescrição do Lote: Barbara L. Hoffman, John O. Schorge, Joseph I. Schaffer, Lisa M. Halvorson & Karen D. Bradshaw. Ginecologia de Williams. McGraw-Hill Education\nPreço base s/IVA: 189,25 EUR\nClassificação CPV (Vocabulário Comum para os Contratos Públicos)\nObjeto principal\nVocabulário Principal: 22113000\nNº: LOT-0041\nDescrição do Lote: Albina Sequeira, Olga Pousa & Catarina Freitas Amaral. Procedimentos de enfermagem em saúde materna e obstétrica. Lidel\nPreço base s/IVA: 38,85 EUR\nClassificação CPV (Vocabulário Comum para os Contratos Públicos)\nObjeto principal\nVocabulário Principal: 22113000\nNº: LOT-0042\nDescrição do Lote: F. Gary Cunningham, Kenneth J. Leveno, Jodi S. Dashe, Barbara L. Hoffman, Catherine Y. Spong, & Brian M. Casey. Williams obstetrics. McGraw Hill\nPreço base s/IVA: 201,10 EUR\nClassificação CPV (Vocabulário Comum para os Contratos Públicos)\nObjeto principal\nVocabulário Principal: 22113000\nNº: LOT-0043\nDescrição do Lote: Sharon Smith Murray, Emily Slone McKinney, Karen Holub & Renee Jones & Kristin L. Scheffer. Foundations of maternal-newborn and women's health nursing. Elsevier\nPreço base s/IVA: 106,91 EUR\nClassificação CPV (Vocabulário Comum para os Contratos Públicos)\nObjeto principal\nVocabulário Principal: 22113000\nNº: LOT-0044\nDescrição do Lote: Henriqueta Figueiredo. Enfermagem de saúde familiar. Lidel\nPreço base s/IVA: 44,54 EUR\nClassificação CPV (Vocabulário Comum para os Contratos Públicos)\nObjeto principal\nVocabulário Principal: 22113000\nNº: LOT-0045\nDescrição do Lote: Lopes dos Reis, R. & Delgado, M. Uma nova gestão em serviços de saúde. Sílabo\nPreço base s/IVA: 24,82 EUR\nClassificação CPV (Vocabulário Comum para os Contratos Públicos)\nObjeto principal\nVocabulário Principal: 22113000\nNº: LOT-0046\nDescrição do Lote: Crane, A. & Matten, D. (2016). Business Ethics: Managing Corporate Citizenship and Sustainability in the Age of Globalisation (4th Edition). Oxford: Oxford University Press. \nPreço base s/IVA: 69,51 EUR\nClassificação CPV (Vocabulário Comum para os Contratos Públicos)\nObjeto principal\nVocabulário Principal: 22113000\nNº: LOT-0047\nDescrição do Lote: Rochat, Shekina. Mapping Career Counseling Interventions A Guide for Career Practitioners. Routlege\nPreço base s/IVA: 44,48 EUR\nClassificação CPV (Vocabulário Comum para os Contratos Públicos)\nObjeto principal\nVocabulário Principal: 22113000\nNº: LOT-0048\nDescrição do Lote: João Lopes. Conceptualização, avaliação e intervenção nas dificuldade de aprendizagem: a sofisticada arquitectura de um equívoco\nPreço base s/IVA: 18,62 EUR\nClassificação CPV (Vocabulário Comum para os Contratos Públicos)\nObjeto principal\nVocabulário Principal: 22113000\nNº: LOT-0049\nDescrição do Lote: Ingmar H.A. Franken, Reinout Wiers, Katie Witkiewitz . The Sage Handbook of Addiction Psychology\nPreço base s/IVA: 151,02 EUR\nClassificação CPV (Vocabulário Comum para os Contratos Públicos)\nObjeto principal\nVocabulário Principal: 22113000\nNº: LOT-0050\nDescrição do Lote: Boswell, J. F. & Constantino, M. J. Deliberate Practice in Cognitive Behavioral Therapy\nPreço base s/IVA: 47,60 EUR\nClassificação CPV (Vocabulário Comum para os Contratos Públicos)\nObjeto principal\nVocabulário Principal: 22113000\nNº: LOT-0051\nDescrição do Lote: Cooper, T., Maguire, G., & Stahl, S. (Eds.). Case Studies: Stahl s Essential Psychopharmacology. Cambridge: Cambridge University Press. \nPreço base s/IVA: 67,25 EUR\nClassificação CPV (Vocabulário Comum para os Contratos Públicos)\nObjeto principal\nVocabulário Principal: 22113000\nNº: LOT-0052\nDescrição do Lote: Marlene Matos. Vítimas de Crimes e Violência. Práticas de intervenção\nPreço base s/IVA: 25,70 EUR\nClassificação CPV (Vocabulário Comum para os Contratos Públicos)\nObjeto principal\nVocabulário Principal: 22113000\nNº: LOT-0053\nDescrição do Lote: Carolyn B. Allard. Transform Your Guilt and Shame. Evidence-Based Strategies to Heal From Trauma and Adversity\nPreço base s/IVA: 25,59 EUR\nClassificação CPV (Vocabulário Comum para os Contratos Públicos)\nObjeto principal\nVocabulário Principal: 22113000\nNº: LOT-0054\nDescrição do Lote: Wirtz, J. and Lovelock, C. (2021). Services Marketing: People, Technology, Strategy (Ninth Edition). London: World Scientific Publishing.\nPreço base s/IVA: 127,90 EUR\nClassificação CPV (Vocabulário Comum para os Contratos Públicos)\nObjeto principal\nVocabulário Principal: 22113000\nNº: LOT-0055\nDescrição do Lote: Schultz, D.; Schultz, S. E. (2016) Psychology and work today: An introduction to industrial and organizational psychology (10th Ed.).\nPreço base s/IVA: 170,45 EUR\nClassificação CPV (Vocabulário Comum para os Contratos Públicos)\nObjeto principal\nVocabulário Principal: 22113000\nNº: LOT-0056\nDescrição do Lote: Melo, P.N.; Machado, C. (Coords.) (2023). Gestor de Recursos Humanos Guia de Sobrevivência Profissional\nPreço base s/IVA: 23,78 EUR\nClassificação CPV (Vocabulário Comum para os Contratos Públicos)\nObjeto principal\nVocabulário Principal: 22113000\nNº: LOT-0057\nDescrição do Lote: Boxall, P. F. & Purcell, J. (2011), Strategy and Human Resource Management, (3rd edition) Basingstoke and New York: Palgrave MacMillan.\nPreço base s/IVA: 64,93 EUR\nClassificação CPV (Vocabulário Comum para os Contratos Públicos)\nObjeto principal\nVocabulário Principal: 22113000\nNº: LOT-0058\nDescrição do Lote: Melo, P. N.; Machado, C. F. (2020). O Livro de Ouro da Gestão de Recursos Humanos nas Pequenas e Médias Empresas\nPreço base s/IVA: 17,83 EUR\nClassificação CPV (Vocabulário Comum para os Contratos Públicos)\nObjeto principal\nVocabulário Principal: 22113000\nNº: LOT-0059\nDescrição do Lote: Matthias Dehmer, Salissou Moutari, Frank Emmert-Streib. Elements of Data Science, Machine Learning, and Artificial Intelligence Using R. Springer\nPreço base s/IVA: 63,16 EUR\nClassificação CPV (Vocabulário Comum para os Contratos Públicos)\nObjeto principal\nVocabulário Principal: 22113000\nNº: LOT-0060\nDescrição do Lote: Hollensen (2021) Global marketing\nPreço base s/IVA: 67,23 EUR\nClassificação CPV (Vocabulário Comum para os Contratos Públicos)\nObjeto principal\nVocabulário Principal: 22113000\nNº: LOT-0061\nDescrição do Lote: Bodie, Z., Kane, A., & Marcus, A. (2024). Investments. 13th ed., Mac Graw Hill.\nPreço base s/IVA: 68,79 EUR\nClassificação CPV (Vocabulário Comum para os Contratos Públicos)\nObjeto principal\nVocabulário Principal: 22113000\nNº: LOT-0062\nDescrição do Lote: Rhodes, R. A. W., T Hart, Paul (eds.) (2014) The Oxford Handbook of Political Leadership. Oxford: Oxford University Press.\nPreço base s/IVA: 111,05 EUR\nClassificação CPV (Vocabulário Comum para os Contratos Públicos)\nObjeto principal\nVocabulário Principal: 22113000\nNº: LOT-0063\nDescrição do Lote: Lamb, C., Hair, J. & McDaniel, C. (2024). MKTG, Principles of Marketing (14th Edition). New York: Cengage Learning.\nPreço base s/IVA: 62,80 EUR\nClassificação CPV (Vocabulário Comum para os Contratos Públicos)\nObjeto principal\nVocabulário Principal: 22113000\nNº: LOT-0064\nDescrição do Lote: Palmatier, R. W., Sivadas, E., Stern, L. W., & El-Ansary, A. I. (2019). Marketing Channel Strategy: An Omni-Channel Approach. Routledge, 9th ediion.\nPreço base s/IVA: 83,66 EUR\nClassificação CPV (Vocabulário Comum para os Contratos Públicos)\nObjeto principal\nVocabulário Principal: 22113000\nNº: LOT-0065\nDescrição do Lote: Ziliani, C., & Ieva, M. (2019). Loyalty management: from loyalty programs to omnichannel customer experiences. Routledge.\nPreço base s/IVA: 45,64 EUR\nClassificação CPV (Vocabulário Comum para os Contratos Públicos)\nObjeto principal\nVocabulário Principal: 22113000\nNº: LOT-0066\nDescrição do Lote: Kumar, R. (2014). Research Methodology: A step-by-step guide for beginners. Sage Publications.\nPreço base s/IVA: 60,37 EUR\nClassificação CPV (Vocabulário Comum para os Contratos Públicos)\nObjeto principal\nVocabulário Principal: 22113000\nNº: LOT-0067\nDescrição do Lote: Gunther, R.; Montero, J. R. e Linz, J. (2002). Political Parties: Old concepts and New challenges. Oxford: Oxford University Press\nPreço base s/IVA: 129,72 EUR\nClassificação CPV (Vocabulário Comum para os Contratos Públicos)\nObjeto principal\nVocabulário Principal: 22113000\nNº: LOT-0068\nDescrição do Lote: Katz, R. e Mair, P. (1994). How parties organize. Change and Adaptation in Party Organizations in Western Democracies. Londres: SAGE Publications.\nPreço base s/IVA: 74,11 EUR\nClassificação CPV (Vocabulário Comum para os Contratos Públicos)\nObjeto principal\nVocabulário Principal: 22113000\nNº: LOT-0069\nDescrição do Lote: Nunan D., Birks, D. & Malhotra, N. K. (2020). Marketing Research: Applied Insight (6th Edition). Harlow: Pearson Education.\nPreço base s/IVA: 85,38 EUR\nClassificação CPV (Vocabulário Comum para os Contratos Públicos)\nObjeto principal\nVocabulário Principal: 22113000\nNº: LOT-0070\nDescrição do Lote: Bouchery, Y., Corbett, C. J., Fransoo, J. C., & Tan, T. (Eds.). (2016). Sustainable supply chains: A research-based textbook on operations and strategy (Vol. 4). Springer.\nPreço base s/IVA: 98,99 EUR\nClassificação CPV (Vocabulário Comum para os Contratos Públicos)\nObjeto principal\nVocabulário Principal: 22113000\nNº: LOT-0071\nDescrição do Lote: Haveman, (2022). The Power of Organizations: A New Approach to Organizational Theory.Princeton University\nPreço base s/IVA: 35,50 EUR\nClassificação CPV (Vocabulário Comum para os Contratos Públicos)\nObjeto principal\nVocabulário Principal: 22113000\nNº: LOT-0072\nDescrição do Lote: \"2023 Program Curriculum Level I Box Set\", Wiley, 1st Edition\nPreço base s/IVA: 213,12 EUR\nClassificação CPV (Vocabulário Comum para os Contratos Públicos)\nObjeto principal\nVocabulário Principal: 22113000\nNº: LOT-0073\nDescrição do Lote: Pherson, R. H., Donner, O., & Gnad, O. (2024). Clear thinking: Structured analytic techniques and strategic foresight analysis for decisionmakers. Springer.\nPreço base s/IVA: 83,82 EUR\nClassificação CPV (Vocabulário Comum para os Contratos Públicos)\nObjeto principal\nVocabulário Principal: 22113000\nNº: LOT-0074\nDescrição do Lote: William Pinar, Daniel Tröhler and Nelli Piattoeva (2022) World Yearbook of Education 2022: Education, Schooling and the Global Universalization of Nationalism. Routledge\nPreço base s/IVA: 47,98 EUR\nClassificação CPV (Vocabulário Comum para os Contratos Públicos)\nObjeto principal\nVocabulário Principal: 22113000\nNº: LOT-0075\nDescrição do Lote: David Hopkins (2007) Every School a Great School: Realizing the Potential of System Leadership. Open University Press\nPreço base s/IVA: 36,34 EUR\nClassificação CPV (Vocabulário Comum para os Contratos Públicos)\nObjeto principal\nVocabulário Principal: 22113000\nNº: LOT-0076\nDescrição do Lote: David Hopkins (2001) School Improvement for Real. Routledge\nPreço base s/IVA: 51,48 EUR\nClassificação CPV (Vocabulário Comum para os Contratos Públicos)\nObjeto principal\nVocabulário Principal: 22113000\nNº: LOT-0077\nDescrição do Lote: Pasi Sahlberg (2018) FinnishED Leadership: Four Big, Inexpensive Ideas to Transform Education. Corwin\nPreço base s/IVA: 21,59 EUR\nClassificação CPV (Vocabulário Comum para os Contratos Públicos)\nObjeto principal\nVocabulário Principal: 22113000\nNº: LOT-0078\nDescrição do Lote: Pasi Sahlberg, Jonathan Hasak, Vanessa Rodriguez (2016) Hard Questions on Global Educational Change Policies, Practices, and the Future of Education. Teachers College Press\nPreço base s/IVA: 31,90 EUR\nClassificação CPV (Vocabulário Comum para os Contratos Públicos)\nObjeto principal\nVocabulário Principal: 22113000\nNº: LOT-0079\nDescrição do Lote: Pasi Sahlberg and William Doyle (2019) Let the Children Play Why More Play Will Save Our Schools and Help Children Thrive. Oxford University Press\nPreço base s/IVA: 50,87 EUR\nClassificação CPV (Vocabulário Comum para os Contratos Públicos)\nObjeto principal\nVocabulário Principal: 22113000\nNº: LOT-0080\nDescrição do Lote: Baldwin, Patrice (2024). 40+ Drama Strategies to Deepen Whole Class Learning. Routledge\nPreço base s/IVA: 26,98 EUR\nClassificação CPV (Vocabulário Comum para os Contratos Públicos)\nObjeto principal\nVocabulário Principal: 22113000\nNº: LOT-0081\nDescrição do Lote: Smith, Johanna (2019). Puppetry in Theatre and Arts Education: Head, Hands and Heart, by Johanna Smith. Methuen Drama\nPreço base s/IVA: 30,60 EUR\nClassificação CPV (Vocabulário Comum para os Contratos Públicos)\nObjeto principal\nVocabulário Principal: 22113000\nNº: LOT-0082\nDescrição do Lote: Michèle Petit. Ler o Mundo. Kalandraka\nPreço base s/IVA: 14,34 EUR\nClassificação CPV (Vocabulário Comum para os Contratos Públicos)\nObjeto principal\nVocabulário Principal: 22113000\nNº: LOT-0083\nDescrição do Lote: Pikler, E. e Tardos, A. (2022) Crescer Autónomo. APEI\nPreço base s/IVA: 33,00 EUR\nClassificação CPV (Vocabulário Comum para os Contratos Públicos)\nObjeto principal\nVocabulário Principal: 22113000\nNº: LOT-0084\nDescrição do Lote: Folque, M. A. (2014).O aprender a aprender no pré-escolar: O Modelo pedagógico do Movimento da Escola Moderna (2ªed.). Fundação Calouste Gulbenkian\nPreço base s/IVA: 17,92 EUR\nClassificação CPV (Vocabulário Comum para os Contratos Públicos)\nObjeto principal\nVocabulário Principal: 22113000\nNº: LOT-0085\nDescrição do Lote: Gloria Quiñones, G. Li, L & Avis Ridgway, A. (2023).Pedagogia e afetividade na educação de crianças com menos de três anos. APEI\nPreço base s/IVA: 31,13 EUR\nClassificação CPV (Vocabulário Comum para os Contratos Públicos)\nObjeto principal\nVocabulário Principal: 22113000\nNº: LOT-0086\nDescrição do Lote: Jorn Rusen. Teoria da História - Uma teoria da história como ciência. Editora UFPR\nPreço base s/IVA: 31,08 EUR\nClassificação CPV (Vocabulário Comum para os Contratos Públicos)\nObjeto principal\nVocabulário Principal: 22113000\nNº: LOT-0087\nDescrição do Lote: Jason Stanley. Erasing History - How fascists rewrite the past to control the future. Atria/One Signal Publishers\nPreço base s/IVA: 21,44 EUR\nClassificação CPV (Vocabulário Comum para os Contratos Públicos)\nObjeto principal\nVocabulário Principal: 22113000\nNº: LOT-0088\nDescrição do Lote: Marian Small. Eyes on Math, A Visual Approach to Teaching Math Concepts, Second Edition. NCTM\nPreço base s/IVA: 39,80 EUR\nClassificação CPV (Vocabulário Comum para os Contratos Públicos)\nObjeto principal\nVocabulário Principal: 22113000\nNº: LOT-0089\nDescrição do Lote: Jean S. Lee and Enrique Galindo. Project-Based Learning in Elementary Classrooms: Making Mathematics Come Alive. NCTM\nPreço base s/IVA: 48,10 EUR\nClassificação CPV (Vocabulário Comum para os Contratos Públicos)\nObjeto principal\nVocabulário Principal: 22113000\nNº: LOT-0090\nDescrição do Lote: Paul Zananaziani. Historical Consciousness and Practical Life. University of Toronto Press (February 1, 2025)\nPreço base s/IVA: 57,95 EUR\nClassificação CPV (Vocabulário Comum para os Contratos Públicos)\nObjeto principal\nVocabulário Principal: 22113000\nNº: LOT-0091\nDescrição do Lote: William. Dylan; Leahy, Siobhán. Integrar la evaluación formativa en la ensñanza. Técnicas para usar a lo largo de toda a trayectoria escolar. Graó\nPreço base s/IVA: 28,52 EUR\nClassificação CPV (Vocabulário Comum para os Contratos Públicos)\nObjeto principal\nVocabulário Principal: 22113000\nNº: LOT-0092\nDescrição do Lote: Rico de Santiago, Bélen Sáenz; Rayón Rumayor, Laura. Retos y desafios de la formación pedagógica en las sociedades actuales. La figura del docente. Graó\nPreço base s/IVA: 32,33 EUR\nClassificação CPV (Vocabulário Comum para os Contratos Públicos)\nObjeto principal\nVocabulário Principal: 22113000\nNº: LOT-0093\nDescrição do Lote: Wahlen, J., Baginski, S., & Bradshaw, M. (2022) Financial Reporting, Financial Statement Analysis and Valuation, 10th edition, Cengage\nPreço base s/IVA: 329,33 EUR\nClassificação CPV (Vocabulário Comum para os Contratos Públicos)\nObjeto principal\nVocabulário Principal: 22113000\nNº: LOT-0094\nDescrição do Lote: Fidson, M. & Alvarez, F. (2022). Financial Statement Analysis: A Practitioner's Guide, 5th edition, Wiley\nPreço base s/IVA: 72,40 EUR\nClassificação CPV (Vocabulário Comum para os Contratos Públicos)\nObjeto principal\nVocabulário Principal: 22113000\nNº: LOT-0095\nDescrição do Lote: Simon, Carl and Blume, Lawrence (2010), Mathematics for Economists, W.W. Norton&Company;, New York\nPreço base s/IVA: 88,15 EUR\nClassificação CPV (Vocabulário Comum para os Contratos Públicos)\nObjeto principal\nVocabulário Principal: 22113000\nNº: LOT-0096\nDescrição do Lote: Carnegie, G. D., & Napier, C. J. (2023). Handbook of Accounting, Accountability and Governance. Edward Elgar Publishing\nPreço base s/IVA: 254,29 EUR\nClassificação CPV (Vocabulário Comum para os Contratos Públicos)\nObjeto principal\nVocabulário Principal: 22113000\nNº: LOT-0097\nDescrição do Lote: Hedetoft, Ulf, Hjort, M. (eds.) 2002. The Postnational Self, Belonging and identity. Minneapolis, London: University of Minnesota Press.\nPreço base s/IVA: 26,41 EUR\nClassificação CPV (Vocabulário Comum para os Contratos Públicos)\nObjeto principal\nVocabulário Principal: 22113000\nNº: LOT-0098\nDescrição do Lote: Joan Pedro-Carañana, Rodrigo Gómez, Thomas F. Corrigan, Francisco Sierra Caballero. Political Economy of Media and Communication - Methodological Approaches. Routledge\nPreço base s/IVA: 42,55 EUR\nClassificação CPV (Vocabulário Comum para os Contratos Públicos)\nObjeto principal\nVocabulário Principal: 22113000\nNº: LOT-0099\nDescrição do Lote: Karen Fowler-Watt, Julian McDougall.  The Palgrave Handbook of Media Misinformation. palgrave macmillan\nPreço base s/IVA: 225,66 EUR\nClassificação CPV (Vocabulário Comum para os Contratos Públicos)\nObjeto principal\nVocabulário Principal: 22113000\nNº: LOT-0100\nDescrição do Lote: Chris Couch. Urban Planning: An Introduction\nPreço base s/IVA: 44,48 EUR\nClassificação CPV (Vocabulário Comum para os Contratos Públicos)\nObjeto principal\nVocabulário Principal: 22113000\nNº: LOT-0101\nDescrição do Lote: Le Corbusier. Planejamento urbano\nPreço base s/IVA: 25,05 EUR\nClassificação CPV (Vocabulário Comum para os Contratos Públicos)\nObjeto principal\nVocabulário Principal: 22113000\nNº: LOT-0102\nDescrição do Lote: Albert Postma, Stefan Hartman and Ian Yeoman. CENARIO PLANNING AND TOURISM FUTURES. Theory Building, Methodologies and Case Studies. Channel View Publications Ltd / Multilingual Matters\nPreço base s/IVA: 42,05 EUR\nClassificação CPV (Vocabulário Comum para os Contratos Públicos)\nObjeto principal\nVocabulário Principal: 22113000\nNº: LOT-0103\nDescrição do Lote: Cardina, Miguel. O Atrito da Memória. Colonialismo, Guerra e Descolonização no Portugal Contemporâneo. Tinta da China\nPreço base s/IVA: 16,05 EUR\nClassificação CPV (Vocabulário Comum para os Contratos Públicos)\nObjeto principal\nVocabulário Principal: 22113000\nNº: LOT-0104\nDescrição do Lote: João Camargo, Paulo Pimenta de Castro. Portugal em Chamas - Como Resgatar as Florestas. Bertrand Editora\nPreço base s/IVA: 13,16 EUR\nClassificação CPV (Vocabulário Comum para os Contratos Públicos)\nObjeto principal\nVocabulário Principal: 22113000\nNº: LOT-0105\nDescrição do Lote: Andrew Goudie. Encyclopedia of Geomorphology. Routledge\nPreço base s/IVA: 104,05 EUR\nClassificação CPV (Vocabulário Comum para os Contratos Públicos)\nObjeto principal\nVocabulário Principal: 22113000\nNº: LOT-0106\nDescrição do Lote: A. Vieira, A.Bento-Gonçalves. Wildland Fires: A Worldwide Reality. Nova Science Publishers\nPreço base s/IVA: 281,25 EUR\nClassificação CPV (Vocabulário Comum para os Contratos Públicos)\nObjeto principal\nVocabulário Principal: 22113000\nNº: LOT-0107\nDescrição do Lote: Alves, Fátima (coord.) Saúde, medicina e sociedade: uma visão sociológica. Pactor\nPreço base s/IVA: 16,45 EUR\nClassificação CPV (Vocabulário Comum para os Contratos Públicos)\nObjeto principal\nVocabulário Principal: 22113000\nNº: LOT-0108\nDescrição do Lote: Betty Friedan. The Feminine Mystique. Penguin Books\nPreço base s/IVA: 13,43 EUR\nClassificação CPV (Vocabulário Comum para os Contratos Públicos)\nObjeto principal\nVocabulário Principal: 22113000\nNº: LOT-0109\nDescrição do Lote: Pierre Rosanvallon. The Society of Equals. Harvard University Press\nPreço base s/IVA: 42,15 EUR\nClassificação CPV (Vocabulário Comum para os Contratos Públicos)\nObjeto principal\nVocabulário Principal: 22113000\nNº: LOT-0110\nDescrição do Lote: Joëlle Rollo-Koster et al. The Cambridge History of the Papacy. 3 vols. Cambridge University Press\nPreço base s/IVA: 354,47 EUR\nClassificação CPV (Vocabulário Comum para os Contratos Públicos)\nObjeto principal\nVocabulário Principal: 22113000\nNº: LOT-0111\nDescrição do Lote: Philippe Genequand. Officiers et Gouvernement de l Église sous Clément VII d Avignon (1378-1394). Garnier\nPreço base s/IVA: 50,46 EUR\nClassificação CPV (Vocabulário Comum para os Contratos Públicos)\nObjeto principal\nVocabulário Principal: 22113000\nNº: LOT-0112\nDescrição do Lote: Flexor, Maria Helena Ochi. Abreviaturas: Manuscritos e Documentos Luso-Brasileiros (séculos XVI ao XX). Editora CRV, 2019\nPreço base s/IVA: 90,95 EUR\nClassificação CPV (Vocabulário Comum para os Contratos Públicos)\nObjeto principal\nVocabulário Principal: 22113000\nNº: LOT-0113\nDescrição do Lote: Irene Bueno, Vincenzo Lavenia, Riccardo Parmeggiani. Current Trends in the Historiography of Inquisitions\nPreço base s/IVA: 46,68 EUR\nClassificação CPV (Vocabulário Comum para os Contratos Públicos)\nObjeto principal\nVocabulário Principal: 22113000\nNº: LOT-0114\nDescrição do Lote: Boucheron, P. Trace and Aura. The Recurring Lives of St. Ambrose of Milan\nPreço base s/IVA: 45,34 EUR\nClassificação CPV (Vocabulário Comum para os Contratos Públicos)\nObjeto principal\nVocabulário Principal: 22113000\nNº: LOT-0115\nDescrição do Lote: Riello, Giorgio; Hayward, Maria; Rublack, Ulinka. A Revolution in Colour: Natural Dyes and Dress in Europe, c. 1400-1800. Bloomsbury\nPreço base s/IVA: 100,47 EUR\nClassificação CPV (Vocabulário Comum para os Contratos Públicos)\nObjeto principal\nVocabulário Principal: 22113000\nNº: LOT-0116\nDescrição do Lote: Aaron Cohen (2020). Counterproductive work behaviors. Routledge\nPreço base s/IVA: 49,14 EUR\nClassificação CPV (Vocabulário Comum para os Contratos Públicos)\nObjeto principal\nVocabulário Principal: 22113000\nNº: LOT-0117\nDescrição do Lote: Rachel Weber, Randall Crane. The Oxford Handbook of Urban Planning\nPreço base s/IVA: 106,82 EUR\nClassificação CPV (Vocabulário Comum para os Contratos Públicos)\nObjeto principal\nVocabulário Principal: 22113000\nNº: LOT-0118\nDescrição do Lote: Maria José Roxo. Desertificação em Portugal. FFMS\nPreço base s/IVA: 4,49 EUR\nClassificação CPV (Vocabulário Comum para os Contratos Públicos)\nObjeto principal\nVocabulário Principal: 22113000\nNº: LOT-0119\nDescrição do Lote: Francisco Díaz-Fierros Viqueira. Eucaliptos en España - Razones y pasiones. Univ. Santiago Compostela\nPreço base s/IVA: 17,36 EUR\nClassificação CPV (Vocabulário Comum para os Contratos Públicos)\nObjeto principal\nVocabulário Principal: 22113000\nNº: LOT-0120\nDescrição do Lote: A. Vieira, A.Bento-Gonçalves. Soil Conservation: Strategies, Management and Challenges. Nova Science Publishers\nPreço base s/IVA: 164,51 EUR\nClassificação CPV (Vocabulário Comum para os Contratos Públicos)\nObjeto principal\nVocabulário Principal: 22113000\nNº: LOT-0121\nDescrição do Lote: A Bento-Gonçalves, A Vieira, M Costa, J Aranha. Wildfires: Perspectives, Issues and Challenges of the 21st Century. Nova Science Publishers\nPreço base s/IVA: 281,25 EUR\nClassificação CPV (Vocabulário Comum para os Contratos Públicos)\nObjeto principal\nVocabulário Principal: 22113000\nNº: LOT-0122\nDescrição do Lote: Barry, A. & Yuill, C. Understanding the Sociology of Health: an introduction. SAGE\nPreço base s/IVA: 39,81 EUR\nClassificação CPV (Vocabulário Comum para os Contratos Públicos)\nObjeto principal\nVocabulário Principal: 22113000\nNº: LOT-0123\nDescrição do Lote: Joseph Bergin. The Seventeenth Century: Europe 1598-1715. Oxford University Press\nPreço base s/IVA: 39,18 EUR\nClassificação CPV (Vocabulário Comum para os Contratos Públicos)\nObjeto principal\nVocabulário Principal: 22113000\nNº: LOT-0124\nDescrição do Lote: Beat Kümin (ed.) The European World 1500 1800. Routledge\nPreço base s/IVA: 42,50 EUR\nClassificação CPV (Vocabulário Comum para os Contratos Públicos)\nObjeto principal\nVocabulário Principal: 22113000\nNº: LOT-0125\nDescrição do Lote: Frans van Liere. An Introduction to the Medieval Bible. Cambridge University Press\nPreço base s/IVA: 35,49 EUR\nClassificação CPV (Vocabulário Comum para os Contratos Públicos)\nObjeto principal\nVocabulário Principal: 22113000\nNº: LOT-0126\nDescrição do Lote: Reinhold Kaiser. Le Monde méditerranéen et l Europeau Bas-Empire et au haut Moyen Âge (ive-xie siècle) Garnier\nPreço base s/IVA: 60,48 EUR\nClassificação CPV (Vocabulário Comum para os Contratos Públicos)\nObjeto principal\nVocabulário Principal: 22113000\nNº: LOT-0127\nDescrição do Lote: Denis Gabriel. La « Maison des pauvres maîtres » de Robert de SorbonLes débuts de la Sorbonne (1254-1274) Garnier\nPreço base s/IVA: 40,43 EUR\nClassificação CPV (Vocabulário Comum para os Contratos Públicos)\nObjeto principal\nVocabulário Principal: 22113000\nNº: LOT-0128\nDescrição do Lote: Thomas Deswarte. Une Chrétienté romaine sans papeL Espagne et Rome (586-1085) Garnier\nPreço base s/IVA: 47,46 EUR\nClassificação CPV (Vocabulário Comum para os Contratos Públicos)\nObjeto principal\nVocabulário Principal: 22113000\nNº: LOT-0129\nDescrição do Lote: Robert E. Bjork. The Oxford Dictionary of the Middle Ages. Oxford University Press\nPreço base s/IVA: 611,12 EUR\nClassificação CPV (Vocabulário Comum para os Contratos Públicos)\nObjeto principal\nVocabulário Principal: 22113000\nNº: LOT-0130\nDescrição do Lote: Pascale Bermon. La Fondation de l'Université de Paris. Les Belles Lettres\nPreço base s/IVA: 40,43 EUR\nClassificação CPV (Vocabulário Comum para os Contratos Públicos)\nObjeto principal\nVocabulário Principal: 22113000\nNº: LOT-0131\nDescrição do Lote: John Willinsky. The Intellectual Properties of Learning. University of Chicago Press\nPreço base s/IVA: 40,55 EUR\nClassificação CPV (Vocabulário Comum para os Contratos Públicos)\nObjeto principal\nVocabulário Principal: 22113000\nNº: LOT-0132\nDescrição do Lote: John Rury et al. The Oxford Handbook of the History of Education. Oxford University Press\nPreço base s/IVA: 159,37 EUR\nClassificação CPV (Vocabulário Comum para os Contratos Públicos)\nObjeto principal\nVocabulário Principal: 22113000\nNº: LOT-0133\nDescrição do Lote: Edwad Muir; Guido Ruggiero. Sex and gender in historical perspective, Baltimore: Johns Hopkins University Press\nPreço base s/IVA: 32,21 EUR\nClassificação CPV (Vocabulário Comum para os Contratos Públicos)\nObjeto principal\nVocabulário Principal: 22113000\nNº: LOT-0134\nDescrição do Lote: Renato Barahon. Sex crimes, honour, and the law in Early Modern Spain. Toronto: University of Toronto Press, 2003,\nPreço base s/IVA: 75,10 EUR\nClassificação CPV (Vocabulário Comum para os Contratos Públicos)\nObjeto principal\nVocabulário Principal: 22113000\nNº: LOT-0135\nDescrição do Lote: Edited by Ioanna Constantiou et al. (2024). Research Handbook on Artificial Intelligence and Decision Making in Organizations. Edward Elger.\nPreço base s/IVA: 195,37 EUR\nClassificação CPV (Vocabulário Comum para os Contratos Públicos)\nObjeto principal\nVocabulário Principal: 22113000\nNº: LOT-0136\nDescrição do Lote: Encyclopedia of Medieval Philosophy: Philosophy Between 500 and 1500, ed. Henrik Lagerlund, Springer, 2010.\nPreço base s/IVA: 766,65 EUR\nClassificação CPV (Vocabulário Comum para os Contratos Públicos)\nObjeto principal\nVocabulário Principal: 22113000\nNº: LOT-0137\nDescrição do Lote: Philip J. Kitchen, Marwa E. Tourky (2022) Integrated Marketing Communications - A Global Brand Driven Approach, Springer\nPreço base s/IVA: 57,98 EUR\nClassificação CPV (Vocabulário Comum para os Contratos Públicos)\nObjeto principal\nVocabulário Principal: 22113000\nNº: LOT-0138\nDescrição do Lote: Moreira, J.A. (2020). Contabilidade- Da preparação à interpretação da informação financeira, 2ª edição, Lisboa: Edições Sílabo.\nPreço base s/IVA: 29,49 EUR\nClassificação CPV (Vocabulário Comum para os Contratos Públicos)\nObjeto principal\nVocabulário Principal: 22113000\nNº: LOT-0139\nDescrição do Lote: Sadie, S. (Ed.) (2000) The New Grove of Music and Musicians. London: MacMillan.\nPreço base s/IVA: 1.341,06 EUR\nClassificação CPV (Vocabulário Comum para os Contratos Públicos)\nObjeto principal\nVocabulário Principal: 22113000\nNº: LOT-0140\nDescrição do Lote: Lopes, C.R.; Oliveira, D.; Pires, J.R.; Malaquias, R.; Covane, S.; Rabaça, B. (2020). Manual de Contabilidade Teoria e Casos Práticos. 2ª Edição. Escolar Editora\nPreço base s/IVA: 36,48 EUR\nClassificação CPV (Vocabulário Comum para os Contratos Públicos)\nObjeto principal\nVocabulário Principal: 22113000\nNº: LOT-0141\nDescrição do Lote: Giugni, M e Grasso, M. (2022) The oxford hanbook of political participation. Oxford university press\nPreço base s/IVA: 182,26 EUR\nClassificação CPV (Vocabulário Comum para os Contratos Públicos)\nObjeto principal\nVocabulário Principal: 22113000\nNº: LOT-0142\nDescrição do Lote: Lane, Jan-Erik e Svante O. Ersson. 2005. Culture and Politics: A Comparative Approach. London: Ashgate.\nPreço base s/IVA: 121,19 EUR\nClassificação CPV (Vocabulário Comum para os Contratos Públicos)\nObjeto principal\nVocabulário Principal: 22113000\nNº: LOT-0143\nDescrição do Lote: Guinsberg, Jacob (2001) Stanislaviski, Meierhold & Cia. São Paulo: Perspectiva.\nPreço base s/IVA: 39,05 EUR\nClassificação CPV (Vocabulário Comum para os Contratos Públicos)\nObjeto principal\nVocabulário Principal: 22113000\nNº: LOT-0144\nDescrição do Lote: Almada Negreiros, José de (1993) Deseja-se Mulher. Obras Completas Teatro, Vol VII. Imprensa Nacional Casa da Moeda.\nPreço base s/IVA: 14,32 EUR\nClassificação CPV (Vocabulário Comum para os Contratos Públicos)\nObjeto principal\nVocabulário Principal: 22113000\nNº: LOT-0145\nDescrição do Lote: Parisotti, A. (2000). Arie Antiche Volume II & III. Milano: Ricordi.\nPreço base s/IVA: 41,75 EUR\nClassificação CPV (Vocabulário Comum para os Contratos Públicos)\nObjeto principal\nVocabulário Principal: 22113000\nNº: LOT-0146\nDescrição do Lote: BRITO, Manuel Carlos de, CYMBRON, Luísa (1992), História da Música Portuguesa. Lisboa: Universidade Aberta\nPreço base s/IVA: 26,85 EUR\nClassificação CPV (Vocabulário Comum para os Contratos Públicos)\nObjeto principal\nVocabulário Principal: 22113000\nNº: LOT-0147\nDescrição do Lote: Biezen, J. Van ( 2016). Rythm, meter and tempo in gregorian chant. Usa: Lancelot Andrwes Press.\nPreço base s/IVA: 25,92 EUR\nClassificação CPV (Vocabulário Comum para os Contratos Públicos)\nObjeto principal\nVocabulário Principal: 22113000\nNº: LOT-0148\nDescrição do Lote: ALVARENGA, João Pedro d' (coord.) (1993), João Domingos Bomtempo 1775-1842. Lisboa: Instituto da Biblioteca Nacional e do Livro\nPreço base s/IVA: 9,54 EUR\nClassificação CPV (Vocabulário Comum para os Contratos Públicos)\nObjeto principal\nVocabulário Principal: 22113000\nNº: LOT-0149\nDescrição do Lote: Vieira de Carvalho. Mário (2006). Pensar a música, mudar o mundo: Fernando Lopes-Graça, Porto, Campo das Letras.\nPreço base s/IVA: 12,48 EUR\nClassificação CPV (Vocabulário Comum para os Contratos Públicos)\nObjeto principal\nVocabulário Principal: 22113000\nNº: LOT-0150\nDescrição do Lote: ABREU, Jorge Manuel Coutinho de. Código das Sociedades Comerciais em Comentário - Volume IV (Artigos 246º a 270º-G)-3.ª ed. 2025. Almedina\nPreço base s/IVA: 62,64 EUR\nClassificação CPV (Vocabulário Comum para os Contratos Públicos)\nObjeto principal\nVocabulário Principal: 22113000\nNº: LOT-0151\nDescrição do Lote: OLIVEIRA, Madalena Perestrelo. Tutela do Investidor Perante o Emitente no Mercado de Capitais: Um Modelo Dinâmico de Proteção. Almedina\nPreço base s/IVA: 73,13 EUR\nClassificação CPV (Vocabulário Comum para os Contratos Públicos)\nObjeto principal\nVocabulário Principal: 22113000\nNº: LOT-0152\nDescrição do Lote: FESTAS, David de Oliveira. Das Inibições de Voto dos Sócios por Conflito de Interesses com a Sociedade nas Sociedades Anónimas e por Quotas. Almedina\nPreço base s/IVA: 120,89 EUR\nClassificação CPV (Vocabulário Comum para os Contratos Públicos)\nObjeto principal\nVocabulário Principal: 22113000\nNº: LOT-0153\nDescrição do Lote: Lionel Bently, Brad Sherman, Dev Gangjee, and Phillip Johnson. Intellectual Property Law. Oxford University Press\nPreço base s/IVA: 61,50 EUR\nClassificação CPV (Vocabulário Comum para os Contratos Públicos)\nObjeto principal\nVocabulário Principal: 22113000\nNº: LOT-0154\nDescrição do Lote: Tato Plaza, Anxo. Actas de Derecho Industrial y Derecho de Autor. Marcial Pons\nPreço base s/IVA: 91,35 EUR\nClassificação CPV (Vocabulário Comum para os Contratos Públicos)\nObjeto principal\nVocabulário Principal: 22113000\nNº: LOT-0155\nDescrição do Lote: Tato Plaza, Anxo. Actas de Derecho Industrial y Derecho de Autor. Marcial Pons\nPreço base s/IVA: 82,27 EUR\nClassificação CPV (Vocabulário Comum para os Contratos Públicos)\nObjeto principal\nVocabulário Principal: 22113000\nNº: LOT-0156\nDescrição do Lote: GARCÍA Pérez, Rafael. El Derecho de Marcas de la UE en la Jurisprudencia del Tribunal de Justicia. Marcial Pons\nPreço base s/IVA: 220,00 EUR\nClassificação CPV (Vocabulário Comum para os Contratos Públicos)\nObjeto principal\nVocabulário Principal: 22113000\nNº: LOT-0157\nDescrição do Lote: ZOI, Krokida. Internet service provider liability for copyright and trade mark infringement towards an EU co-regulatory framework. Hart Publishing\nPreço base s/IVA: 91,96 EUR\nClassificação CPV (Vocabulário Comum para os Contratos Públicos)\nObjeto principal\nVocabulário Principal: 22113000\nNº: LOT-0158\nDescrição do Lote: GARCÍA Pérez, Rafael. El derecho de marcas y de la competencia ante las tecnologías de vanguardia. Editorial Tirant lo Blanch\nPreço base s/IVA: 60,60 EUR\nClassificação CPV (Vocabulário Comum para os Contratos Públicos)\nObjeto principal\nVocabulário Principal: 22113000\nNº: LOT-0159\nDescrição do Lote: Theodore H. Wilson, Raymond Paternoster, Ronet D. Bachman. Statistics for Criminology and Criminal Justice. Sage\nPreço base s/IVA: 185,61 EUR\nClassificação CPV (Vocabulário Comum para os Contratos Públicos)\nObjeto principal\nVocabulário Principal: 22113000\nNº: LOT-0160\nDescrição do Lote: Stephanie Kewley, Charlotte Barlow. Preventing Sexual Violence: Problems and Possibilities. Bristol University Press\nPreço base s/IVA: 99,76 EUR\nClassificação CPV (Vocabulário Comum para os Contratos Públicos)\nObjeto principal\nVocabulário Principal: 22113000\nNº: LOT-0161\nDescrição do Lote: Marie Keenan, Estelle Zinsstag. Sexual Violence and Restorative Justice. Oxford University Press\nPreço base s/IVA: 93,56 EUR\nClassificação CPV (Vocabulário Comum para os Contratos Públicos)\nObjeto principal\nVocabulário Principal: 22113000\nNº: LOT-0162\nDescrição do Lote: Cabral, L. (2017). Introduction to Industrial Organization (2nd ed.). MIT Press. \nPreço base s/IVA: 106,12 EUR\nClassificação CPV (Vocabulário Comum para os Contratos Públicos)\nObjeto principal\nVocabulário Principal: 22113000\nNº: LOT-0163\nDescrição do Lote: Hillman, A. L. (2019). Public Finance and Public Policy: A Political Economy Perspective on the Responsibilities and Limitations of Government (3rd ed.). Cambridge: Cambridge University Press.\nPreço base s/IVA: 57,14 EUR\nClassificação CPV (Vocabulário Comum para os Contratos Públicos)\nObjeto principal\nVocabulário Principal: 22113000\nNº: LOT-0164\nDescrição do Lote: Miguel Teixeira de Sousa. Manual de Processo Civil. AAFDL\nPreço base s/IVA: 114,53 EUR\nClassificação CPV (Vocabulário Comum para os Contratos Públicos)\nObjeto principal\nVocabulário Principal: 22113000\nNº: LOT-0165\nDescrição do Lote: Goetz, Klaus H. (ed.), The Oxford Handbook of Time and Politics (online edn, Oxford Academic, 4 Apr. 2019), https://doi.org/10.1093/oxfordhb/9780190862084.001.0001\nPreço base s/IVA: 135,46 EUR\nClassificação CPV (Vocabulário Comum para os Contratos Públicos)\nObjeto principal\nVocabulário Principal: 22113000\nNº: LOT-0166\nDescrição do Lote: International Macroeconomics: A Modern Approach\nPreço base s/IVA: 94,10 EUR\nClassificação CPV (Vocabulário Comum para os Contratos Públicos)\nObjeto principal\nVocabulário Principal: 22113000\nNº: LOT-0167\nDescrição do Lote: Auteri; Floridia; Mangini; Olivieri; Ricolfi, Romano; Sironi; Spada. Diritto Industriale Proprietà Intellettuale e Concorrenza, 7ª ed., Giappichelli Editore, Torino, 2023.\nPreço base s/IVA: 60,72 EUR\nClassificação CPV (Vocabulário Comum para os Contratos Públicos)\nObjeto principal\nVocabulário Principal: 22113000\nNº: LOT-0168\nDescrição do Lote: BENKARD, Georg. Patentgesetz, 12.ª ed., C.H. Beck, München, 2023\nPreço base s/IVA: 294,00 EUR\nClassificação CPV (Vocabulário Comum para os Contratos Públicos)\nObjeto principal\nVocabulário Principal: 22113000\nNº: LOT-0169\nDescrição do Lote: Ingerl; Rohnke; Nordemann. Markengesetz, 4.ª ed, C.H. Beck, München, 2023.\nPreço base s/IVA: 272,00 EUR\nClassificação CPV (Vocabulário Comum para os Contratos Públicos)\nObjeto principal\nVocabulário Principal: 22113000\nNº: LOT-0170\nDescrição do Lote: Gabriele Cirener, Henning Radtke, Ruth Rissing-van Saan, Thomas Rönnau and Wilhelm Schluckebier. Strafgesetzbuch. Leipziger Kommentar, 13th rev. Ed. De Gruyter, 2019-2024. (20 volumes)\nPreço base s/IVA: 204,13 EUR\nClassificação CPV (Vocabulário Comum para os Contratos Públicos)\nObjeto principal\nVocabulário Principal: 22113000\nNº: LOT-0171\nDescrição do Lote: CARDOSO, Raquel. As Funções do Direito Penal Europeu e a Legitimidade da Criminalização - Entre o Harm Principle e a Protecção de Bens Jurídicos. Coimbra: Almedina, 2023\nPreço base s/IVA: 72,06 EUR\nClassificação CPV (Vocabulário Comum para os Contratos Públicos)\nObjeto principal\nVocabulário Principal: 22113000\nNº: LOT-0172\nDescrição do Lote: COSTA, J.M. Nogueira da. Regime Jurídico do Mandado de Detenção Europeu. Coimbra: Almedina, 2024\nPreço base s/IVA: 67,12 EUR\nClassificação CPV (Vocabulário Comum para os Contratos Públicos)\nObjeto principal\nVocabulário Principal: 22113000\nNº: LOT-0173\nDescrição do Lote: MACHADO, Pedro Sá. Teoria da Conduta na Realização Jurisdicional do Direito Penal - Pressupostos e Fundamentos do Comportamento Ilícito-típico. Coimbra: Almedina, 2023;\nPreço base s/IVA: 78,33 EUR\nClassificação CPV (Vocabulário Comum para os Contratos Públicos)\nObjeto principal\nVocabulário Principal: 22113000\nNº: LOT-0174\nDescrição do Lote: ROXIN, Claus, Täterschaft und Tatherrschaft. Berlin, Boston: De Guyter, 2023;\nPreço base s/IVA: 102,81 EUR\nClassificação CPV (Vocabulário Comum para os Contratos Públicos)\nObjeto principal\nVocabulário Principal: 22113000\nNº: LOT-0175\nDescrição do Lote: FIANDACA, Giovanni e MUSCO, Enzo, Diritto penale. Parte generale. 9.ª edizione. Zanichelli: 2024\nPreço base s/IVA: 83,80 EUR\nClassificação CPV (Vocabulário Comum para os Contratos Públicos)\nObjeto principal\nVocabulário Principal: 22113000\nNº: LOT-0176\nDescrição do Lote: FIORE, Carlo e FIORE, Stefano, Diritto penale. Parte generale. 7.ª edizione. Utet Giuridica, 2023;\nPreço base s/IVA: 98,42 EUR\nClassificação CPV (Vocabulário Comum para os Contratos Públicos)\nObjeto principal\nVocabulário Principal: 22113000\nNº: LOT-0177\nDescrição do Lote: Lattanzi, Giorgio, Codice Penale: Annotato con la Giurisprudenza. Giuffrè, 2024;\nPreço base s/IVA: 95,00 EUR\nClassificação CPV (Vocabulário Comum para os Contratos Públicos)\nObjeto principal\nVocabulário Principal: 22113000\nNº: LOT-0178\nDescrição do Lote: MANTOVANI, Ferrando e FLORA, Giovanni, Diritto Penale: Parte Generale. 12.ª edizione. CEDAM, 2023;\nPreço base s/IVA: 64,74 EUR\nClassificação CPV (Vocabulário Comum para os Contratos Públicos)\nObjeto principal\nVocabulário Principal: 22113000\nNº: LOT-0179\nDescrição do Lote: RODRIGUES, Benjamim Silva, Crime de Violência Doméstica. Rei dos Livors, 2024;\nPreço base s/IVA: 118,86 EUR\nClassificação CPV (Vocabulário Comum para os Contratos Públicos)\nObjeto principal\nVocabulário Principal: 22113000\nNº: LOT-0180\nDescrição do Lote: RODRIGUEZ, Carlos Suárez-Mira, Manual de Derecho Penal: Parte General, Tomo I. 9.º edición. Editorial Aranzadi, 2023;\nPreço base s/IVA: 64,94 EUR\nClassificação CPV (Vocabulário Comum para os Contratos Públicos)\nObjeto principal\nVocabulário Principal: 22113000\nNº: LOT-0181\nDescrição do Lote: RODRIGUEZ, Carlos Suárez-Mira, Manual de Derecho Penal: Parte Especial, Tomo II. 9.º edición. Editorial Aranzadi, 2023;\nPreço base s/IVA: 64,78 EUR\nClassificação CPV (Vocabulário Comum para os Contratos Públicos)\nObjeto principal\nVocabulário Principal: 22113000\nNº: LOT-0182\nDescrição do Lote: VV.AA., Código Penal. Comentado com Jurisprudencia Sistematizada y Concordancias. 11.ª edición. Lefebvre, 2024;\nPreço base s/IVA: 124,55 EUR\nClassificação CPV (Vocabulário Comum para os Contratos Públicos)\nObjeto principal\nVocabulário Principal: 22113000\nNº: LOT-0183\nDescrição do Lote: VV.AA., Código Penal Comentado: Tomo I e Tomo II. Colex, 2024;\nPreço base s/IVA: 78,11 EUR\nClassificação CPV (Vocabulário Comum para os Contratos Públicos)\nObjeto principal\nVocabulário Principal: 22113000\nNº: LOT-0184\nDescrição do Lote: Juarez Tavares, Teoria do Injusto Penal, 4ª edição. São Paulo: Tirant lo Blanch, 2019.\nPreço base s/IVA: 131,35 EUR\nClassificação CPV (Vocabulário Comum para os Contratos Públicos)\nObjeto principal\nVocabulário Principal: 22113000\nNº: LOT-0185\nDescrição do Lote: Juarez Tavares, Fundamentos de Teoria do Delito. São Paulo: Tirant lo Blanch, 2018.\nPreço base s/IVA: 110,26 EUR\nClassificação CPV (Vocabulário Comum para os Contratos Públicos)\nObjeto principal\nVocabulário Principal: 22113000\nNº: LOT-0186\nDescrição do Lote: Juarez Tavares, Teoria do Crime Culposo, 5ª edição. Florianópolis: Empório do Direito, 2018.\nPreço base s/IVA: 131,35 EUR\nClassificação CPV (Vocabulário Comum para os Contratos Públicos)\nObjeto principal\nVocabulário Principal: 22113000\nNº: LOT-0187\nDescrição do Lote: Russo, Teresa; Oriolo, Anna; Dalia, Gaspare. Solidarity and Rule of Law: The New Dimension of EU Security. Springer\nPreço base s/IVA: 163,65 EUR\nClassificação CPV (Vocabulário Comum para os Contratos Públicos)\nObjeto principal\nVocabulário Principal: 22113000\nNº: LOT-0188\nDescrição do Lote: Schmeer, Laura. The European Public Prosecutor's Office: From Souvereignty to Supranationalism. Palgrave Macmillan Cham\nPreço base s/IVA: 130,98 EUR\nClassificação CPV (Vocabulário Comum para os Contratos Públicos)\nObjeto principal\nVocabulário Principal: 22113000\nNº: LOT-0189\nDescrição do Lote: Mitsliegas, Valsamis; Bergstrom, Maria; Quintel, Teresa. Research Handbook on EU Criminal Law. Elgar\nPreço base s/IVA: 289,25 EUR\nClassificação CPV (Vocabulário Comum para os Contratos Públicos)\nObjeto principal\nVocabulário Principal: 22113000\nNº: LOT-0190\nDescrição do Lote: Vesna Lazi, Peter Mankowski. The Brussels I-bis Regulation. Edward Elgar publishing\nPreço base s/IVA: 236,77 EUR\nClassificação CPV (Vocabulário Comum para os Contratos Públicos)\nObjeto principal\nVocabulário Principal: 22113000\nNº: LOT-0191\nDescrição do Lote: Franco Ferrari, Friedrich Rosenfeld, Charles T. Kotuby. Recognition and Enforcement of Foreign Arbitral Awards. Edward Elgar publishing\nPreço base s/IVA: 97,48 EUR\nClassificação CPV (Vocabulário Comum para os Contratos Públicos)\nObjeto principal\nVocabulário Principal: 22113000\nNº: LOT-0192\nDescrição do Lote: Cristina Gonzalez Beilfuss, Laura Carpaneto, Thalia Kruger, Ilaria Pretelli, Mirela upan. Jurisdiction, Recognition and Enforcement in Matrimonial and Parental Responsibility Matters. Edward Elgar publishing\nPreço base s/IVA: 301,43 EUR\nClassificação CPV (Vocabulário Comum para os Contratos Públicos)\nObjeto principal\nVocabulário Principal: 22113000\nNº: LOT-0193\nDescrição do Lote: Guillermo Palao. The Singapore Convention on Mediation. Edward Elgar publishing\nPreço base s/IVA: 192,69 EUR\nClassificação CPV (Vocabulário Comum para os Contratos Públicos)\nObjeto principal\nVocabulário Principal: 22113000\nNº: LOT-0194\nDescrição do Lote: Marta Requejo Isidro. Brussels I Bis. Edward Elgar publishing\nPreço base s/IVA: 330,51 EUR\nClassificação CPV (Vocabulário Comum para os Contratos Públicos)\nObjeto principal\nVocabulário Principal: 22113000\nNº: LOT-0195\nDescrição do Lote: Ilaria Viarengo, Pietro Franzina. The EU Regulations on the Property Regimes of International Couples. Edward Elgar publishing\nPreço base s/IVA: 244,36 EUR\nClassificação CPV (Vocabulário Comum para os Contratos Públicos)\nObjeto principal\nVocabulário Principal: 22113000\nNº: LOT-0196\nDescrição do Lote: Handbook of Philosophy of Management\nPreço base s/IVA: 326,98 EUR\nClassificação CPV (Vocabulário Comum para os Contratos Públicos)\nObjeto principal\nVocabulário Principal: 22113000\nNº: LOT-0197\nDescrição do Lote: Peter Mankowski. Research Handbook on the Brussels Ibis Regulation. Edward Elgar publishing\nPreço base s/IVA: 206,98 EUR\nClassificação CPV (Vocabulário Comum para os Contratos Públicos)\nObjeto principal\nVocabulário Principal: 22113000\nNº: LOT-0198\nDescrição do Lote: Michael Hellner, Nigel Lowe, Costanza Honorati. Cross-border Marriage Dissolution, Parental Responsibility Disputes and Child Abduction in the EU. Intersentia\nPreço base s/IVA: 121,25 EUR\nClassificação CPV (Vocabulário Comum para os Contratos Públicos)\nObjeto principal\nVocabulário Principal: 22113000\nNº: LOT-0199\nDescrição do Lote: Xandra Kramer e Laura Carballo Piñeiro. Research Methods in Private International Law: A Handbook on Regulation, Research and Teaching (Handbooks of Research Methods in Law series). Edward Elgar Publishing\nPreço base s/IVA: 195,37 EUR\nClassificação CPV (Vocabulário Comum para os Contratos Públicos)\nObjeto principal\nVocabulário Principal: 22113000\nNº: LOT-0200\nDescrição do Lote: Louise Merrett. Employment Contracts and Private International Law, 2nd edition. Oxford University Press\nPreço base s/IVA: 196,56 EUR\nClassificação CPV (Vocabulário Comum para os Contratos Públicos)\nObjeto principal\nVocabulário Principal: 22113000\nNº: LOT-0201\nDescrição do Lote: Kazin Michael, The Populist Persuasion: An American History, Ithaca and London: Cornel University Press, 2017.      \nPreço base s/IVA: 24,10 EUR\nClassificação CPV (Vocabulário Comum para os Contratos Públicos)\nObjeto principal\nVocabulário Principal: 22113000\nNº: LOT-0202\nDescrição do Lote: Diamond L e Morlino L, Assessing the Quality of Democracy, Baltimore, John Hopkins, 2005\nPreço base s/IVA: 30,41 EUR\nClassificação CPV (Vocabulário Comum para os Contratos Públicos)\nObjeto principal\nVocabulário Principal: 22113000\nNº: LOT-0203\nDescrição do Lote: F. Bechenback, W. Kahlenborn (eds). New Perspectives for Environmental Policies Through Behavioral Economics\nPreço base s/IVA: 98,98 EUR\nClassificação CPV (Vocabulário Comum para os Contratos Públicos)\nObjeto principal\nVocabulário Principal: 22113000\nNº: LOT-0204\nDescrição do Lote: Barbara Pozzo. Property and Environment: Old and New Remedies to Protect Natural Resources in the European Context\nPreço base s/IVA: 83,12 EUR\nClassificação CPV (Vocabulário Comum para os Contratos Públicos)\nObjeto principal\nVocabulário Principal: 22113000\nNº: LOT-0205\nDescrição do Lote: Cass R. Sunstein, Lucia Reisch. Research Handbook on Nudges and Society\nPreço base s/IVA: 184,60 EUR\nClassificação CPV (Vocabulário Comum para os Contratos Públicos)\nObjeto principal\nVocabulário Principal: 22113000\nNº: LOT-0206\nDescrição do Lote: Karen Yeung, Sofia Ranchordás. An Introduction to Law and Regulation: Text and Materials\nPreço base s/IVA: 142,65 EUR\nClassificação CPV (Vocabulário Comum para os Contratos Públicos)\nObjeto principal\nVocabulário Principal: 22113000\nNº: LOT-0207\nDescrição do Lote: Lucia A. Reisch, John Thøgersen (eds) Handbook of Research on Sustainable Consumption\nPreço base s/IVA: 209,29 EUR\nClassificação CPV (Vocabulário Comum para os Contratos Públicos)\nObjeto principal\nVocabulário Principal: 22113000\nNº: LOT-0208\nDescrição do Lote: Sabrina Lanni. Greening the Civil Codes: Comparative Private Law and Environmental protection\nPreço base s/IVA: 105,86 EUR\nClassificação CPV (Vocabulário Comum para os Contratos Públicos)\nObjeto principal\nVocabulário Principal: 22113000\nNº: LOT-0209\nDescrição do Lote: Hillier, D., Ross, S., Westerfield, R., Jaffe, J. and Jordan, B. (2021), Corporate Finance, 4th European Edition, MacGraw-Hill.\nPreço base s/IVA: 71,58 EUR\nClassificação CPV (Vocabulário Comum para os Contratos Públicos)\nObjeto principal\nVocabulário Principal: 22113000\nNº: LOT-0210\nDescrição do Lote: Hans-W. Micklitz, Anne-Lise Sibony, and Fabrizio Esposito. Research methods in Consumer Law: A Handbook\nPreço base s/IVA: 224,06 EUR\nClassificação CPV (Vocabulário Comum para os Contratos Públicos)\nObjeto principal\nVocabulário Principal: 22113000\nNº: LOT-0211\nDescrição do Lote: Hans-W. Micklitz and Giuseppe Vettori. The future of the person\nPreço base s/IVA: 127,89 EUR\nClassificação CPV (Vocabulário Comum para os Contratos Públicos)\nObjeto principal\nVocabulário Principal: 22113000\nNº: LOT-0212\nDescrição do Lote: Correia, S. & Martins, A. (2018). Preços de Transferência, Litigância e Arbitragem Fiscal. Petrony Editores\nPreço base s/IVA: 16,05 EUR\nClassificação CPV (Vocabulário Comum para os Contratos Públicos)\nObjeto principal\nVocabulário Principal: 22113000\nNº: LOT-0213\nDescrição do Lote: Stefan Grundmann, Mateusz Grochowski. European Contract Law and the creation of norms\nPreço base s/IVA: 110,49 EUR\nClassificação CPV (Vocabulário Comum para os Contratos Públicos)\nObjeto principal\nVocabulário Principal: 22113000\nNº: LOT-0214\nDescrição do Lote: Stefan Grundmann, Philip Hacker. Theories of Choice: The social science and the law of decision making\nPreço base s/IVA: 118,35 EUR\nClassificação CPV (Vocabulário Comum para os Contratos Públicos)\nObjeto principal\nVocabulário Principal: 22113000\nNº: LOT-0215\nDescrição do Lote: Arno Lodder, Andrew D. Murray. EU Regulation of E-Commerce\nPreço base s/IVA: 226,38 EUR\nClassificação CPV (Vocabulário Comum para os Contratos Públicos)\nObjeto principal\nVocabulário Principal: 22113000\nNº: LOT-0216\nDescrição do Lote: Guilherme Dray et alt. Código do Trabalho Anotado. Almedina\nPreço base s/IVA: 98,49 EUR\nClassificação CPV (Vocabulário Comum para os Contratos Públicos)\nObjeto principal\nVocabulário Principal: 22113000\nNº: LOT-0217\nDescrição do Lote: Neumark, Fritz. Principios de la imposición. Ediciones Jurídicas Olejnik\nPreço base s/IVA: 62,66 EUR\nClassificação CPV (Vocabulário Comum para os Contratos Públicos)\nObjeto principal\nVocabulário Principal: 22113000\nNº: LOT-0218\nDescrição do Lote: Kokott, Juliane. EU tax law. Beck/Hart/Nomos\nPreço base s/IVA: 322,07 EUR\nClassificação CPV (Vocabulário Comum para os Contratos Públicos)\nObjeto principal\nVocabulário Principal: 22113000\n\n7 - INDICAÇÕES ADICIONAIS\nO contrato envolve aquisição conjunta (satisfação de várias entidades)? Não\nO contrato é adjudicado por uma central de compras? Não\n\n8 - TÉCNICAS\nO concurso destina-se à celebração de um acordo-quadro? Inexistência de acordo-quadro\nÉ utilizado um leilão eletrónico? Não\nÉ adotada uma fase de negociação? Não\nSistema de Aquisição Dinâmico: Inexistência de sistema de aquisição dinâmico\n\n9 - LOCAL DA EXECUÇÃO DO CONTRATO\nLOCAL DA EXECUÇÃO DO CONTRATO (PROCEDIMENTO)\nPaís: Portugal\nNUT III: PT112\nLocalidade: Freguesia de Gualtar\nDistrito: Braga\nConcelho: Braga\nFreguesia: Freguesia de Gualtar\nLOCAL DA EXECUÇÃO DO CONTRATO (LOTE)\nIdentificador do Lote: LOT-0001; LOT-0002; LOT-0003; LOT-0004; LOT-0005; LOT-0006; LOT-0007; LOT-0008; LOT-0009; LOT-0010; LOT-0011; LOT-0012; LOT-0013; LOT-0014; LOT-0015; LOT-0016; LOT-0017; LOT-0018; LOT-0019; LOT-0020; LOT-0021; LOT-0022; LOT-0023; LOT-0024; LOT-0025; LOT-0026; LOT-0027; LOT-0028; LOT-0029; LOT-0030; LOT-0031; LOT-0032; LOT-0033; LOT-0034; LOT-0035; LOT-0036; LOT-0037; LOT-0038; LOT-0039; LOT-0040; LOT-0041; LOT-0042; LOT-0043; LOT-0044; LOT-0045; LOT-0046; LOT-0047; LOT-0048; LOT-0049; LOT-0050; LOT-0051; LOT-0052; LOT-0053; LOT-0054; LOT-0055; LOT-0056; LOT-0057; LOT-0058; LOT-0059; LOT-0060; LOT-0061; LOT-0062; LOT-0063; LOT-0064; LOT-0065; LOT-0066; LOT-0067; LOT-0068; LOT-0069; LOT-0070; LOT-0071; LOT-0072; LOT-0073; LOT-0074; LOT-0075; LOT-0076; LOT-0077; LOT-0078; LOT-0079; LOT-0080; LOT-0081; LOT-0082; LOT-0083; LOT-0084; LOT-0085; LOT-0086; LOT-0087; LOT-0088; LOT-0089; LOT-0090; LOT-0091; LOT-0092; LOT-0093; LOT-0094; LOT-0095; LOT-0096; LOT-0097; LOT-0098; LOT-0099; LOT-0100; LOT-0101; LOT-0102; LOT-0103; LOT-0104; LOT-0105; LOT-0106; LOT-0107; LOT-0108; LOT-0109; LOT-0110; LOT-0111; LOT-0112; LOT-0113; LOT-0114; LOT-0115; LOT-0116; LOT-0117; LOT-0118; LOT-0119; LOT-0120; LOT-0121; LOT-0122; LOT-0123; LOT-0124; LOT-0125; LOT-0126; LOT-0127; LOT-0128; LOT-0129; LOT-0130; LOT-0131; LOT-0132; LOT-0133; LOT-0134; LOT-0135; LOT-0136; LOT-0137; LOT-0138; LOT-0139; LOT-0140; LOT-0141; LOT-0142; LOT-0143; LOT-0144; LOT-0145; LOT-0146; LOT-0147; LOT-0148; LOT-0149; LOT-0150; LOT-0151; LOT-0152; LOT-0153; LOT-0154; LOT-0155; LOT-0156; LOT-0157; LOT-0158; LOT-0159; LOT-0160; LOT-0161; LOT-0162; LOT-0163; LOT-0164; LOT-0165; LOT-0166; LOT-0167; LOT-0168; LOT-0169; LOT-0170; LOT-0171; LOT-0172; LOT-0173; LOT-0174; LOT-0175; LOT-0176; LOT-0177; LOT-0178; LOT-0179; LOT-0180; LOT-0181; LOT-0182; LOT-0183; LOT-0184; LOT-0185; LOT-0186; LOT-0187; LOT-0188; LOT-0189; LOT-0190; LOT-0191; LOT-0192; LOT-0193; LOT-0194; LOT-0195; LOT-0196; LOT-0197; LOT-0198; LOT-0199; LOT-0200; LOT-0201; LOT-0202; LOT-0203; LOT-0204; LOT-0205; LOT-0206; LOT-0207; LOT-0208; LOT-0209; LOT-0210; LOT-0211; LOT-0212; LOT-0213; LOT-0214; LOT-0215; LOT-0216; LOT-0217; LOT-0218\nPaís: Portugal\nNUT III: PT112\nLocalidade: Gualtar\nDistrito: Braga\nConcelho: Braga\nFreguesia: Todas\n\n10 - PRAZO DE EXECUÇÃO DO CONTRATO\nIdentificador do Lote: LOT-0001; LOT-0002; LOT-0003; LOT-0004; LOT-0005; LOT-0006; LOT-0007; LOT-0008; LOT-0009; LOT-0010; LOT-0011; LOT-0012; LOT-0013; LOT-0014; LOT-0015; LOT-0016; LOT-0017; LOT-0018; LOT-0019; LOT-0020; LOT-0021; LOT-0022; LOT-0023; LOT-0024; LOT-0025; LOT-0026; LOT-0027; LOT-0028; LOT-0029; LOT-0030; LOT-0031; LOT-0032; LOT-0033; LOT-0034; LOT-0035; LOT-0036; LOT-0037; LOT-0038; LOT-0039; LOT-0040; LOT-0041; LOT-0042; LOT-0043; LOT-0044; LOT-0045; LOT-0046; LOT-0047; LOT-0048; LOT-0049; LOT-0050; LOT-0051; LOT-0052; LOT-0053; LOT-0054; LOT-0055; LOT-0056; LOT-0057; LOT-0058; LOT-0059; LOT-0060; LOT-0061; LOT-0062; LOT-0063; LOT-0064; LOT-0065; LOT-0066; LOT-0067; LOT-0068; LOT-0069; LOT-0070; LOT-0071; LOT-0072; LOT-0073; LOT-0074; LOT-0075; LOT-0076; LOT-0077; LOT-0078; LOT-0079; LOT-0080; LOT-0081; LOT-0082; LOT-0083; LOT-0084; LOT-0085; LOT-0086; LOT-0087; LOT-0088; LOT-0089; LOT-0090; LOT-0091; LOT-0092; LOT-0093; LOT-0094; LOT-0095; LOT-0096; LOT-0097; LOT-0098; LOT-0099; LOT-0100; LOT-0101; LOT-0102; LOT-0103; LOT-0104; LOT-0105; LOT-0106; LOT-0107; LOT-0108; LOT-0109; LOT-0110; LOT-0111; LOT-0112; LOT-0113; LOT-0114; LOT-0115; LOT-0116; LOT-0117; LOT-0118; LOT-0119; LOT-0120; LOT-0121; LOT-0122; LOT-0123; LOT-0124; LOT-0125; LOT-0126; LOT-0127; LOT-0128; LOT-0129; LOT-0130; LOT-0131; LOT-0132; LOT-0133; LOT-0134; LOT-0135; LOT-0136; LOT-0137; LOT-0138; LOT-0139; LOT-0140; LOT-0141; LOT-0142; LOT-0143; LOT-0144; LOT-0145; LOT-0146; LOT-0147; LOT-0148; LOT-0149; LOT-0150; LOT-0151; LOT-0152; LOT-0153; LOT-0154; LOT-0155; LOT-0156; LOT-0157; LOT-0158; LOT-0159; LOT-0160; LOT-0161; LOT-0162; LOT-0163; LOT-0164; LOT-0165; LOT-0166; LOT-0167; LOT-0168; LOT-0169; LOT-0170; LOT-0171; LOT-0172; LOT-0173; LOT-0174; LOT-0175; LOT-0176; LOT-0177; LOT-0178; LOT-0179; LOT-0180; LOT-0181; LOT-0182; LOT-0183; LOT-0184; LOT-0185; LOT-0186; LOT-0187; LOT-0188; LOT-0189; LOT-0190; LOT-0191; LOT-0192; LOT-0193; LOT-0194; LOT-0195; LOT-0196; LOT-0197; LOT-0198; LOT-0199; LOT-0200; LOT-0201; LOT-0202; LOT-0203; LOT-0204; LOT-0205; LOT-0206; LOT-0207; LOT-0208; LOT-0209; LOT-0210; LOT-0211; LOT-0212; LOT-0213; LOT-0214; LOT-0215; LOT-0216; LOT-0217; LOT-0218\nPrazo de execução do contrato: 117 DIAS\nPrevisão de renovações: Não\n\n11 - FUNDOS EU\nIdentificador do Lote: LOT-0001; LOT-0002; LOT-0003; LOT-0004; LOT-0005; LOT-0006; LOT-0007; LOT-0008; LOT-0009; LOT-0010; LOT-0011; LOT-0012; LOT-0013; LOT-0014; LOT-0015; LOT-0016; LOT-0017; LOT-0018; LOT-0019; LOT-0020; LOT-0021; LOT-0022; LOT-0023; LOT-0024; LOT-0025; LOT-0026; LOT-0027; LOT-0028; LOT-0029; LOT-0030; LOT-0031; LOT-0032; LOT-0033; LOT-0034; LOT-0035; LOT-0036; LOT-0037; LOT-0038; LOT-0039; LOT-0040; LOT-0041; LOT-0042; LOT-0043; LOT-0044; LOT-0045; LOT-0046; LOT-0047; LOT-0048; LOT-0049; LOT-0050; LOT-0051; LOT-0052; LOT-0053; LOT-0054; LOT-0055; LOT-0056; LOT-0057; LOT-0058; LOT-0059; LOT-0060; LOT-0061; LOT-0062; LOT-0063; LOT-0064; LOT-0065; LOT-0066; LOT-0067; LOT-0068; LOT-0069; LOT-0070; LOT-0071; LOT-0072; LOT-0073; LOT-0074; LOT-0075; LOT-0076; LOT-0077; LOT-0078; LOT-0079; LOT-0080; LOT-0081; LOT-0082; LOT-0083; LOT-0084; LOT-0085; LOT-0086; LOT-0087; LOT-0088; LOT-0089; LOT-0090; LOT-0091; LOT-0092; LOT-0093; LOT-0094; LOT-0095; LOT-0096; LOT-0097; LOT-0098; LOT-0099; LOT-0100; LOT-0101; LOT-0102; LOT-0103; LOT-0104; LOT-0105; LOT-0106; LOT-0107; LOT-0108; LOT-0109; LOT-0110; LOT-0111; LOT-0112; LOT-0113; LOT-0114; LOT-0115; LOT-0116; LOT-0117; LOT-0118; LOT-0119; LOT-0120; LOT-0121; LOT-0122; LOT-0123; LOT-0124; LOT-0125; LOT-0126; LOT-0127; LOT-0128; LOT-0129; LOT-0130; LOT-0131; LOT-0132; LOT-0133; LOT-0134; LOT-0135; LOT-0136; LOT-0137; LOT-0138; LOT-0139; LOT-0140; LOT-0141; LOT-0142; LOT-0143; LOT-0144; LOT-0145; LOT-0146; LOT-0147; LOT-0148; LOT-0149; LOT-0150; LOT-0151; LOT-0152; LOT-0153; LOT-0154; LOT-0155; LOT-0156; LOT-0157; LOT-0158; LOT-0159; LOT-0160; LOT-0161; LOT-0162; LOT-0163; LOT-0164; LOT-0165; LOT-0166; LOT-0167; LOT-0168; LOT-0169; LOT-0170; LOT-0171; LOT-0172; LOT-0173; LOT-0174; LOT-0175; LOT-0176; LOT-0177; LOT-0178; LOT-0179; LOT-0180; LOT-0181; LOT-0182; LOT-0183; LOT-0184; LOT-0185; LOT-0186; LOT-0187; LOT-0188; LOT-0189; LOT-0190; LOT-0191; LOT-0192; LOT-0193; LOT-0194; LOT-0195; LOT-0196; LOT-0197; LOT-0198; LOT-0199; LOT-0200; LOT-0201; LOT-0202; LOT-0203; LOT-0204; LOT-0205; LOT-0206; LOT-0207; LOT-0208; LOT-0209; LOT-0210; LOT-0211; LOT-0212; LOT-0213; LOT-0214; LOT-0215; LOT-0216; LOT-0217; LOT-0218\nTêm fundos EU? Não\n\n12 - DOCUMENTOS DE HABILITAÇÃO\nHabilitação para o exercício da atividade profissional: Não\n\n13 - CONDIÇÕES DE APRESENTAÇÃO\nPlataforma eletrónica utilizada pela entidade adjudicante: ACIN\nURL para Apresentação: https://www.acingov.pt\nAdmissibilidade da apresentação de propostas variantes: Não autorizado\nPrazo para apresentação das propostas: 19-09-2025 23:59\nPrazo durante o qual os concorrentes são obrigados a manter as respetivas propostas: 120 dias a contar do termo do prazo para a apresentação das propostas\nIndicação de Subcontratação na Proposta: Inexistência de indicação de subcontratação\n\n14 - PRESTAÇÃO DE CAUÇÃO\nPrestação de caução: Não\n\n15 - FORNECIMENTO DAS PEÇAS DO CONCURSO, APRESENTAÇÃO DE PEDIDOS DE PARTICIPAÇÃO E APRESENTAÇÃO DAS PROPOSTAS\nLink para acesso às peças do concurso (URL): https://www.acingov.pt/acingovprod/2/zonaPublica/zona_publica_c/donwloadProcedurePiece/OTc1OTU1\n\n20 - OUTROS REQUISITOS\nIdentificador do Lote: LOT-0001; LOT-0002; LOT-0003; LOT-0004; LOT-0005; LOT-0006; LOT-0007; LOT-0008; LOT-0009; LOT-0010; LOT-0011; LOT-0012; LOT-0013; LOT-0014; LOT-0015; LOT-0016; LOT-0017; LOT-0018; LOT-0019; LOT-0020; LOT-0021; LOT-0022; LOT-0023; LOT-0024; LOT-0025; LOT-0026; LOT-0027; LOT-0028; LOT-0029; LOT-0030; LOT-0031; LOT-0032; LOT-0033; LOT-0034; LOT-0035; LOT-0036; LOT-0037; LOT-0038; LOT-0039; LOT-0040; LOT-0041; LOT-0042; LOT-0043; LOT-0044; LOT-0045; LOT-0046; LOT-0047; LOT-0048; LOT-0049; LOT-0050; LOT-0051; LOT-0052; LOT-0053; LOT-0054; LOT-0055; LOT-0056; LOT-0057; LOT-0058; LOT-0059; LOT-0060; LOT-0061; LOT-0062; LOT-0063; LOT-0064; LOT-0065; LOT-0066; LOT-0067; LOT-0068; LOT-0069; LOT-0070; LOT-0071; LOT-0072; LOT-0073; LOT-0074; LOT-0075; LOT-0076; LOT-0077; LOT-0078; LOT-0079; LOT-0080; LOT-0081; LOT-0082; LOT-0083; LOT-0084; LOT-0085; LOT-0086; LOT-0087; LOT-0088; LOT-0089; LOT-0090; LOT-0091; LOT-0092; LOT-0093; LOT-0094; LOT-0095; LOT-0096; LOT-0097; LOT-0098; LOT-0099; LOT-0100; LOT-0101; LOT-0102; LOT-0103; LOT-0104; LOT-0105; LOT-0106; LOT-0107; LOT-0108; LOT-0109; LOT-0110; LOT-0111; LOT-0112; LOT-0113; LOT-0114; LOT-0115; LOT-0116; LOT-0117; LOT-0118; LOT-0119; LOT-0120; LOT-0121; LOT-0122; LOT-0123; LOT-0124; LOT-0125; LOT-0126; LOT-0127; LOT-0128; LOT-0129; LOT-0130; LOT-0131; LOT-0132; LOT-0133; LOT-0134; LOT-0135; LOT-0136; LOT-0137; LOT-0138; LOT-0139; LOT-0140; LOT-0141; LOT-0142; LOT-0143; LOT-0144; LOT-0145; LOT-0146; LOT-0147; LOT-0148; LOT-0149; LOT-0150; LOT-0151; LOT-0152; LOT-0153; LOT-0154; LOT-0155; LOT-0156; LOT-0157; LOT-0158; LOT-0159; LOT-0160; LOT-0161; LOT-0162; LOT-0163; LOT-0164; LOT-0165; LOT-0166; LOT-0167; LOT-0168; LOT-0169; LOT-0170; LOT-0171; LOT-0172; LOT-0173; LOT-0174; LOT-0175; LOT-0176; LOT-0177; LOT-0178; LOT-0179; LOT-0180; LOT-0181; LOT-0182; LOT-0183; LOT-0184; LOT-0185; LOT-0186; LOT-0187; LOT-0188; LOT-0189; LOT-0190; LOT-0191; LOT-0192; LOT-0193; LOT-0194; LOT-0195; LOT-0196; LOT-0197; LOT-0198; LOT-0199; LOT-0200; LOT-0201; LOT-0202; LOT-0203; LOT-0204; LOT-0205; LOT-0206; LOT-0207; LOT-0208; LOT-0209; LOT-0210; LOT-0211; LOT-0212; LOT-0213; LOT-0214; LOT-0215; LOT-0216; LOT-0217; LOT-0218\nInformação sobre contratos reservados. Aplica-se a contratos reservados (54º-A)? Não\n\n21 - CRITÉRIO DE ADJUDICAÇÃO\nO Critério de adjudicação é diferenciado por lote? Não\nMultifator: Não\nMonofator:\nNome: Preço\n\n24 - CONDIÇÕES DO CONTRATO\nIdentificador do Lote: LOT-0001; LOT-0002; LOT-0003; LOT-0004; LOT-0005; LOT-0006; LOT-0007; LOT-0008; LOT-0009; LOT-0010; LOT-0011; LOT-0012; LOT-0013; LOT-0014; LOT-0015; LOT-0016; LOT-0017; LOT-0018; LOT-0019; LOT-0020; LOT-0021; LOT-0022; LOT-0023; LOT-0024; LOT-0025; LOT-0026; LOT-0027; LOT-0028; LOT-0029; LOT-0030; LOT-0031; LOT-0032; LOT-0033; LOT-0034; LOT-0035; LOT-0036; LOT-0037; LOT-0038; LOT-0039; LOT-0040; LOT-0041; LOT-0042; LOT-0043; LOT-0044; LOT-0045; LOT-0046; LOT-0047; LOT-0048; LOT-0049; LOT-0050; LOT-0051; LOT-0052; LOT-0053; LOT-0054; LOT-0055; LOT-0056; LOT-0057; LOT-0058; LOT-0059; LOT-0060; LOT-0061; LOT-0062; LOT-0063; LOT-0064; LOT-0065; LOT-0066; LOT-0067; LOT-0068; LOT-0069; LOT-0070; LOT-0071; LOT-0072; LOT-0073; LOT-0074; LOT-0075; LOT-0076; LOT-0077; LOT-0078; LOT-0079; LOT-0080; LOT-0081; LOT-0082; LOT-0083; LOT-0084; LOT-0085; LOT-0086; LOT-0087; LOT-0088; LOT-0089; LOT-0090; LOT-0091; LOT-0092; LOT-0093; LOT-0094; LOT-0095; LOT-0096; LOT-0097; LOT-0098; LOT-0099; LOT-0100; LOT-0101; LOT-0102; LOT-0103; LOT-0104; LOT-0105; LOT-0106; LOT-0107; LOT-0108; LOT-0109; LOT-0110; LOT-0111; LOT-0112; LOT-0113; LOT-0114; LOT-0115; LOT-0116; LOT-0117; LOT-0118; LOT-0119; LOT-0120; LOT-0121; LOT-0122; LOT-0123; LOT-0124; LOT-0125; LOT-0126; LOT-0127; LOT-0128; LOT-0129; LOT-0130; LOT-0131; LOT-0132; LOT-0133; LOT-0134; LOT-0135; LOT-0136; LOT-0137; LOT-0138; LOT-0139; LOT-0140; LOT-0141; LOT-0142; LOT-0143; LOT-0144; LOT-0145; LOT-0146; LOT-0147; LOT-0148; LOT-0149; LOT-0150; LOT-0151; LOT-0152; LOT-0153; LOT-0154; LOT-0155; LOT-0156; LOT-0157; LOT-0158; LOT-0159; LOT-0160; LOT-0161; LOT-0162; LOT-0163; LOT-0164; LOT-0165; LOT-0166; LOT-0167; LOT-0168; LOT-0169; LOT-0170; LOT-0171; LOT-0172; LOT-0173; LOT-0174; LOT-0175; LOT-0176; LOT-0177; LOT-0178; LOT-0179; LOT-0180; LOT-0181; LOT-0182; LOT-0183; LOT-0184; LOT-0185; LOT-0186; LOT-0187; LOT-0188; LOT-0189; LOT-0190; LOT-0191; LOT-0192; LOT-0193; LOT-0194; LOT-0195; LOT-0196; LOT-0197; LOT-0198; LOT-0199; LOT-0200; LOT-0201; LOT-0202; LOT-0203; LOT-0204; LOT-0205; LOT-0206; LOT-0207; LOT-0208; LOT-0209; LOT-0210; LOT-0211; LOT-0212; LOT-0213; LOT-0214; LOT-0215; LOT-0216; LOT-0217; LOT-0218\nFaturação Eletrónica: Permitido\nObrigação de Subcontratação:\nCódigo da Obrigação de Subcontratação: Não é aplicável nenhuma obrigação de subcontratação.\n\n25 - COMPRA PÚBLICA ESTRATÉGICA\nCompra Pública Estratégica: Inexistência de contratação pública estratégica\n\n26 - INFORMAÇÕES ADICIONAIS\nIdentificador do Lote: LOT-0001; LOT-0002; LOT-0003; LOT-0004; LOT-0005; LOT-0006; LOT-0007; LOT-0008; LOT-0009; LOT-0010; LOT-0011; LOT-0012; LOT-0013; LOT-0014; LOT-0015; LOT-0016; LOT-0017; LOT-0018; LOT-0019; LOT-0020; LOT-0021; LOT-0022; LOT-0023; LOT-0024; LOT-0025; LOT-0026; LOT-0027; LOT-0028; LOT-0029; LOT-0030; LOT-0031; LOT-0032; LOT-0033; LOT-0034; LOT-0035; LOT-0036; LOT-0037; LOT-0038; LOT-0039; LOT-0040; LOT-0041; LOT-0042; LOT-0043; LOT-0044; LOT-0045; LOT-0046; LOT-0047; LOT-0048; LOT-0049; LOT-0050; LOT-0051; LOT-0052; LOT-0053; LOT-0054; LOT-0055; LOT-0056; LOT-0057; LOT-0058; LOT-0059; LOT-0060; LOT-0061; LOT-0062; LOT-0063; LOT-0064; LOT-0065; LOT-0066; LOT-0067; LOT-0068; LOT-0069; LOT-0070; LOT-0071; LOT-0072; LOT-0073; LOT-0074; LOT-0075; LOT-0076; LOT-0077; LOT-0078; LOT-0079; LOT-0080; LOT-0081; LOT-0082; LOT-0083; LOT-0084; LOT-0085; LOT-0086; LOT-0087; LOT-0088; LOT-0089; LOT-0090; LOT-0091; LOT-0092; LOT-0093; LOT-0094; LOT-0095; LOT-0096; LOT-0097; LOT-0098; LOT-0099; LOT-0100; LOT-0101; LOT-0102; LOT-0103; LOT-0104; LOT-0105; LOT-0106; LOT-0107; LOT-0108; LOT-0109; LOT-0110; LOT-0111; LOT-0112; LOT-0113; LOT-0114; LOT-0115; LOT-0116; LOT-0117; LOT-0118; LOT-0119; LOT-0120; LOT-0121; LOT-0122; LOT-0123; LOT-0124; LOT-0125; LOT-0126; LOT-0127; LOT-0128; LOT-0129; LOT-0130; LOT-0131; LOT-0132; LOT-0133; LOT-0134; LOT-0135; LOT-0136; LOT-0137; LOT-0138; LOT-0139; LOT-0140; LOT-0141; LOT-0142; LOT-0143; LOT-0144; LOT-0145; LOT-0146; LOT-0147; LOT-0148; LOT-0149; LOT-0150; LOT-0151; LOT-0152; LOT-0153; LOT-0154; LOT-0155; LOT-0156; LOT-0157; LOT-0158; LOT-0159; LOT-0160; LOT-0161; LOT-0162; LOT-0163; LOT-0164; LOT-0165; LOT-0166; LOT-0167; LOT-0168; LOT-0169; LOT-0170; LOT-0171; LOT-0172; LOT-0173; LOT-0174; LOT-0175; LOT-0176; LOT-0177; LOT-0178; LOT-0179; LOT-0180; LOT-0181; LOT-0182; LOT-0183; LOT-0184; LOT-0185; LOT-0186; LOT-0187; LOT-0188; LOT-0189; LOT-0190; LOT-0191; LOT-0192; LOT-0193; LOT-0194; LOT-0195; LOT-0196; LOT-0197; LOT-0198; LOT-0199; LOT-0200; LOT-0201; LOT-0202; LOT-0203; LOT-0204; LOT-0205; LOT-0206; LOT-0207; LOT-0208; LOT-0209; LOT-0210; LOT-0211; LOT-0212; LOT-0213; LOT-0214; LOT-0215; LOT-0216; LOT-0217; LOT-0218\nContrato adequado para PME: Não\nCobertura ACP (Acordo dos Contratos Públicos da Organização Mundial do Comércio): Não\n\n27 - IDENTIFICAÇÃO E CONTACTOS DO ÓRGÃO DE RECURSOS ADMINISTRATIVOS\nDesignação: Sr. Reitor da Universidade do Minho\nEndereço: Largo do Paço\nCódigo postal: 4704-553\nLocalidade: Braga\nTelefone: 253601045\nFax: 253601045\nEndereço eletrónico: sec-adm@reitoria.uminho.pt\n\n28 - IDENTIFICAÇÃO DO(S) AUTOR(ES) DE ANÚNCIO\nNome: Elói António Santos Cordeiro Rodrigues\nCargo: -Diretor da Unidade de Serviços de Documentação e Bibliotecas (USDB)\n419513665",
    "nipc": "502011378",
    "distrito": "Braga",
    "concelho": "Braga",
    "freguesia": "Freguesia de Gualtar",
    "site": "www.uminho.pt",
    "email": "sec-adm@reitoria.uminho.pt",
    "designacao_contrato": "AQUISIÇÃO DE RECURSOS BIBLIOGRÁFICOS, POR LOTES.",
    "descricao": "AQUISIÇÃO DE RECURSOS BIBLIOGRÁFICOS, POR LOTES.",
    "preco_base": "24.814,77 EUR",
    "prazo_execucao": "117 DIAS",
    "prazo_apresentacao_propostas": "19-09-2025 23:59",
    "fundos_eu": "Não",
    "plataforma_eletronica": "ACIN",
    "url_procedimento": "https://www.acingov.pt",
    "autor_nome": "Elói António Santos Cordeiro Rodrigues",
    "autor_cargo": "-Diretor da Unidade de Serviços de Documentação e Bibliotecas (USDB)"
  },
  {
    "numero_procedimento": "N/A",
    "entidade": "Estado-Maior do Exército",
    "link": "https://diariodarepublica.pt/dr/detalhe/contrato-publico/23826-934502549",
    "detalhes_completos": "Alteração do Anúncio de procedimento n.º 23420/2025, de 2025-09-03, com o ID 419497936\n\n1 - IDENTIFICAÇÃO E CONTACTOS DA ENTIDADE ADJUDICANTE\nDesignação da entidade adjudicante: Estado-Maior do Exército\nNIPC: 600021610\nEndereço: Av. Infante Santo nº 49, 2º Piso\nCódigo postal: 1399-056\nLocalidade: Lisboa\nPaís: Portugal\nNUT III: PT170\nDistrito: Lisboa\nConcelho: Lisboa\nFreguesia: Freguesia da Estrela\nTelefone: 213912000\nFax: 213912009\nEndereço da Entidade (URL): https://www.exercito.pt/\nEndereço Eletrónico: cmdlog.da@exercito.pt\neDelivery Gateway (URL): https://www.acingov.pt\nFunção da Organização: Adquirente\nSubfunção da Organização: Organização cujo orçamento é utilizado para pagar o contrato; Organização que executa o pagamento; Organização que fornece mais informações sobre os prazos dos procedimentos de recurso; Organização responsável pelo tratamento das propostas; Organização que recebe as propostas; Organização que trata os pedidos de participação; Organização que recebe pedidos de participação; Organização que assina o contrato\nNorma jurídica da Entidade Adjudicante: Organismo de direito público\nÁrea de atividade da Autoridade Adjudicante: Defesa\n\n2 - JORNAL OFICIAL DA UNIÃO EUROPEIA\nO procedimento a que este anúncio diz respeito também é publicitado no Jornal Oficial da União Europeia? Não\n\n3 - AVISO\nModelo de Anúncio: Concurso público\nData de Envio do Anúncio: 08-09-2025\n\n5 - PROCESSO\nTipo de Procedimento: Concurso público\nPreço base do procedimento: Sim\nValor do preço base do procedimento: 142.998,50 EUR\nProcedimento com lotes? Sim\nNº Máx. de Lotes Autorizado: 4\nNúmero máximo de lotes que podem ser adjudicados a um concorrente: 4\n\n6 - OBJETO DO CONTRATO\nNúmero de referência interna: A0092A/2025\nDesignação do contrato: 4025020254/DA/A0092A/2025-A0092A/2025-Aquisição de distintivos posto, por lotes\nDescrição: 4025020254/DA/A0092A/2025-A0092A/2025-Aquisição de distintivos posto, por lotes\nTipo de Contrato Principal: Aquisição de Bens Móveis\nTipo de Contrato: Aquisição de Bens Móveis\nClassificação CPV (Vocabulário Comum para os Contratos Públicos)\nObjeto principal\nVocabulário Principal: 35811300\nPreço base s/IVA: 142.998,50 EUR\nLotes: \nNº: LOT-0001\nDescrição do Lote: Distintivo Manga Unif. 1\nPreço base s/IVA: 43.000,00 EUR\nClassificação CPV (Vocabulário Comum para os Contratos Públicos)\nObjeto principal\nVocabulário Principal: 35811300\nNº: LOT-0002\nDescrição do Lote: Distintivo Platina Unif. 1/2\nPreço base s/IVA: 68.035,00 EUR\nClassificação CPV (Vocabulário Comum para os Contratos Públicos)\nObjeto principal\nVocabulário Principal: 35811300\nNº: LOT-0003\nDescrição do Lote: Distintivo Posto T-Shirt NFE\nPreço base s/IVA: 17.527,50 EUR\nClassificação CPV (Vocabulário Comum para os Contratos Públicos)\nObjeto principal\nVocabulário Principal: 35811300\nNº: LOT-0004\nDescrição do Lote: Distintivo Posto Unif. 3\nPreço base s/IVA: 14.436,00 EUR\nClassificação CPV (Vocabulário Comum para os Contratos Públicos)\nObjeto principal\nVocabulário Principal: 35811300\n\n7 - INDICAÇÕES ADICIONAIS\nO contrato envolve aquisição conjunta (satisfação de várias entidades)? Não\nO contrato é adjudicado por uma central de compras? Não\n\n8 - TÉCNICAS\nO concurso destina-se à celebração de um acordo-quadro? Inexistência de acordo-quadro\nÉ utilizado um leilão eletrónico? Não\nÉ adotada uma fase de negociação? Não\nSistema de Aquisição Dinâmico: Inexistência de sistema de aquisição dinâmico\n\n9 - LOCAL DA EXECUÇÃO DO CONTRATO\nLOCAL DA EXECUÇÃO DO CONTRATO (PROCEDIMENTO)\nPaís: Portugal\nNUT III: PT185\nLocalidade: Freguesia de Benavente\nDistrito: Santarém\nConcelho: Benavente\nFreguesia: Freguesia de Benavente\nLOCAL DA EXECUÇÃO DO CONTRATO (LOTE)\nIdentificador do Lote: LOT-0001; LOT-0002; LOT-0003; LOT-0004\nPaís: Portugal\nNUT III: PT185\nLocalidade: Freguesia de Benavente\nDistrito: Santarém\nConcelho: Benavente\nFreguesia: Freguesia de Benavente\n\n10 - PRAZO DE EXECUÇÃO DO CONTRATO\nIdentificador do Lote: LOT-0001; LOT-0002; LOT-0003; LOT-0004\nPrazo de execução do contrato: 60 DIAS\nPrevisão de renovações: Não\n\n11 - FUNDOS EU\nIdentificador do Lote: LOT-0001; LOT-0002; LOT-0003; LOT-0004\nTêm fundos EU? Não\n\n12 - DOCUMENTOS DE HABILITAÇÃO\nHabilitação para o exercício da atividade profissional: Não\n\n13 - CONDIÇÕES DE APRESENTAÇÃO\nPlataforma eletrónica utilizada pela entidade adjudicante: ACIN\nURL para Apresentação: https://www.acingov.pt\nAdmissibilidade da apresentação de propostas variantes: Não autorizado\nPrazo para apresentação das propostas: 12-09-2025 23:59\nPrazo durante o qual os concorrentes são obrigados a manter as respetivas propostas: 120 dias a contar do termo do prazo para a apresentação das propostas\nIndicação de Subcontratação na Proposta: Inexistência de indicação de subcontratação\n\n14 - PRESTAÇÃO DE CAUÇÃO\nPrestação de caução: Não\n\n15 - FORNECIMENTO DAS PEÇAS DO CONCURSO, APRESENTAÇÃO DE PEDIDOS DE PARTICIPAÇÃO E APRESENTAÇÃO DAS PROPOSTAS\nLink para acesso às peças do concurso (URL): https://www.acingov.pt/acingovprod/2/zonaPublica/zona_publica_c/donwloadProcedurePiece/OTczMDIw\n\n20 - OUTROS REQUISITOS\nIdentificador do Lote: LOT-0001; LOT-0002; LOT-0003; LOT-0004\nInformação sobre contratos reservados. Aplica-se a contratos reservados (54º-A)? Não\n\n21 - CRITÉRIO DE ADJUDICAÇÃO\nO Critério de adjudicação é diferenciado por lote? Não\nMultifator: Não\nMonofator:\nNome: Preço\n\n24 - CONDIÇÕES DO CONTRATO\nIdentificador do Lote: LOT-0001; LOT-0002; LOT-0003; LOT-0004\nFaturação Eletrónica: Permitido\nObrigação de Subcontratação:\nCódigo da Obrigação de Subcontratação: Não é aplicável nenhuma obrigação de subcontratação.\n\n25 - COMPRA PÚBLICA ESTRATÉGICA\nCompra Pública Estratégica: Inexistência de contratação pública estratégica\n\n26 - INFORMAÇÕES ADICIONAIS\nIdentificador do Lote: LOT-0001; LOT-0002; LOT-0003; LOT-0004\nContrato adequado para PME: Não\nCobertura ACP (Acordo dos Contratos Públicos da Organização Mundial do Comércio): Não\n\n27 - IDENTIFICAÇÃO E CONTACTOS DO ÓRGÃO DE RECURSOS ADMINISTRATIVOS\nDesignação: Conforme Direito Contencioso Administrativo\nEndereço: Comando da Logística do Exército - Avenida Infante Santo, nº 49\nCódigo postal: 1399-056\nLocalidade: Lisboa\nTelefone: 213912000\nFax: \nEndereço eletrónico: cmdlog.da@exercito.pt\nPrazo de interposição do recurso: 10 dias\n\n28 - IDENTIFICAÇÃO DO(S) AUTOR(ES) DE ANÚNCIO\nNome: Brigadeiro - General Albino Marques Lameiras\nCargo: Diretor de Aquisições\n\n29 - ALTERAÇÃO\nMotivo da Alteração: Correção pelo adquirente\nIdentificador da Versão do Anúncio a Alterar: 8061fc56-7f01-4a88-b298-381498d62140-01\nIdentificador das Secções Alteradas do Anúncio Anterior: Condições de Apresentação\nDescrição das Alterações: Modificação do prazo para a apresentação de propostas\nAlteração dos Documentos do Concurso: Não\n419514312",
    "nipc": "600021610",
    "distrito": "Lisboa",
    "concelho": "Lisboa",
    "freguesia": "Freguesia da Estrela",
    "site": "https://www.exercito.pt/",
    "email": "cmdlog.da@exercito.pt",
    "designacao_contrato": "4025020254/DA/A0092A/2025-A0092A/2025-Aquisição de distintivos posto, por lotes",
    "descricao": "4025020254/DA/A0092A/2025-A0092A/2025-Aquisição de distintivos posto, por lotes",
    "preco_base": "142.998,50 EUR",
    "prazo_execucao": "60 DIAS",
    "prazo_apresentacao_propostas": "12-09-2025 23:59",
    "fundos_eu": "Não",
    "plataforma_eletronica": "ACIN",
    "url_procedimento": "https://www.acingov.pt",
    "autor_nome": "Brigadeiro - General Albino Marques Lameiras",
    "autor_cargo": "Diretor de Aquisições"
  },
  {
    "numero_procedimento": "N/A",
    "entidade": "BIKiNNOV - BIKE VALUE INNOVATION CENTER - ASSOCIATION",
    "link": "https://diariodarepublica.pt/dr/detalhe/contrato-publico/23827-934502556",
    "detalhes_completos": "1 - IDENTIFICAÇÃO E CONTACTOS DA ENTIDADE ADJUDICANTE\nDesignação da entidade adjudicante: BIKiNNOV - BIKE VALUE INNOVATION CENTER - ASSOCIATION\nNIPC: 516839268\nServiço/Órgão/Pessoa de contacto: BIKiNNOV\nEndereço: Rua Ramiro Soares de Miranda, 133\nCódigo postal: 3750-866\nLocalidade: Borralha\nPaís: Portugal\nNUT III: PT16D\nDistrito: Aveiro\nConcelho: Águeda\nFreguesia: Freguesia de Valongo do Vouga\nTelefone: 234248960\nFax: 000000000\nEndereço da Entidade (URL): www.bikinnov.pt\nEndereço Eletrónico: geral@bikinnov.pt\neDelivery Gateway (URL): https://www.acingov.pt\nFunção da Organização: Adquirente\nNorma jurídica da Entidade Adjudicante: Organismo de direito público\nÁrea de atividade da Autoridade Adjudicante: Serviços públicos das administrações públicas\n\n2 - JORNAL OFICIAL DA UNIÃO EUROPEIA\nO procedimento a que este anúncio diz respeito também é publicitado no Jornal Oficial da União Europeia? Não\n\n3 - AVISO\nModelo de Anúncio: Concurso público\nData de Envio do Anúncio: 08-09-2025\n\n5 - PROCESSO\nTipo de Procedimento: Concurso público\nPreço base do procedimento: Sim\nValor do preço base do procedimento: 2.485.021,31 EUR\nProcedimento com lotes? Não\n\n6 - OBJETO DO CONTRATO\nNúmero de referência interna: 57-111-CTI-25\nDesignação do contrato: Empreitada de Adaptação de Armazém para Centro de Tecnologia e Inovação (Nave Norte)\nDescrição: Empreitada de Adaptação de Armazém para Centro de Tecnologia e Inovação (Nave Norte)\nTipo de Contrato Principal: Empreitada de Obras Públicas\nTipo de Contrato: Empreitada de Obras Públicas\nClassificação CPV (Vocabulário Comum para os Contratos Públicos)\nObjeto principal\nVocabulário Principal: 45453100\nPreço base s/IVA: 2.485.021,31 EUR\n\n7 - INDICAÇÕES ADICIONAIS\nO contrato envolve aquisição conjunta (satisfação de várias entidades)? Não\nO contrato é adjudicado por uma central de compras? Não\n\n8 - TÉCNICAS\nO concurso destina-se à celebração de um acordo-quadro? Inexistência de acordo-quadro\nÉ utilizado um leilão eletrónico? Não\nÉ adotada uma fase de negociação? Não\nSistema de Aquisição Dinâmico: Inexistência de sistema de aquisição dinâmico\n\n9 - LOCAL DA EXECUÇÃO DO CONTRATO\nLOCAL DA EXECUÇÃO DO CONTRATO (PROCEDIMENTO)\nPaís: Portugal\nNUT III: PT16D\nLocalidade: Freguesia de Valongo do Vouga\nDistrito: Aveiro\nConcelho: Águeda\nFreguesia: Freguesia de Valongo do Vouga\n\n10 - PRAZO DE EXECUÇÃO DO CONTRATO\nPrazo de execução do contrato: 6 MESES\nPrevisão de renovações: Não\n\n11 - FUNDOS EU\nTêm fundos EU? Sim\n\n12 - DOCUMENTOS DE HABILITAÇÃO\nHabilitação para o exercício da atividade profissional: Sim\nTipo: Alvará\nDescrição: Alvará de empreiteiro emitido pelo IMPIC adequado à tipologia de obra, cuja comprovação será verificada pela entidade adjudicante, na página eletrónica deste organismo\n\n13 - CONDIÇÕES DE APRESENTAÇÃO\nPlataforma eletrónica utilizada pela entidade adjudicante: ACIN\nURL para Apresentação: https://www.acingov.pt\nAdmissibilidade da apresentação de propostas variantes: Não autorizado\nPrazo para apresentação das propostas: 28-09-2025 17:00\nPrazo durante o qual os concorrentes são obrigados a manter as respetivas propostas: 66 dias a contar do termo do prazo para a apresentação das propostas\nIndicação de Subcontratação na Proposta: Inexistência de indicação de subcontratação\n\n14 - PRESTAÇÃO DE CAUÇÃO\nPrestação de caução: Sim\nPercentagem: 5%\nDescrição da Garantia Exigida: O valor da caução é de 5.00% do preço contratual.\n\n15 - FORNECIMENTO DAS PEÇAS DO CONCURSO, APRESENTAÇÃO DE PEDIDOS DE PARTICIPAÇÃO E APRESENTAÇÃO DAS PROPOSTAS\nLink para acesso às peças do concurso (URL): https://www.acingov.pt/acingovprod/2/zonaPublica/zona_publica_c/donwloadProcedurePiece/OTczMDAz\n\n20 - OUTROS REQUISITOS\nInformação sobre contratos reservados. Aplica-se a contratos reservados (54º-A)? Não\n\n21 - CRITÉRIO DE ADJUDICAÇÃO\nMultifator: Não\nMonofator:\nNome: Preço\n\n24 - CONDIÇÕES DO CONTRATO\nFaturação Eletrónica: Permitido\nObrigação de Subcontratação:\nCódigo da Obrigação de Subcontratação: O contratante tem de indicar qualquer mudança de subcontratantes durante a execução do contrato.\n\n25 - COMPRA PÚBLICA ESTRATÉGICA\nCompra Pública Estratégica: Inexistência de contratação pública estratégica\n\n26 - INFORMAÇÕES ADICIONAIS\nContrato adequado para PME: Sim\nCobertura ACP (Acordo dos Contratos Públicos da Organização Mundial do Comércio): Não\n\n27 - IDENTIFICAÇÃO E CONTACTOS DO ÓRGÃO DE RECURSOS ADMINISTRATIVOS\nDesignação: BIKiNNOV\nEndereço: Rua Ramiro Soares de Miranda, 133\nCódigo postal: 3750-866\nLocalidade: Borralha\nTelefone: 234248960\nFax: \nEndereço eletrónico: geral@bikinnov.pt\n\n28 - IDENTIFICAÇÃO DO(S) AUTOR(ES) DE ANÚNCIO\nNome: Inês Tavares\nCargo: Gestora Financeira de Projetos\n419514483",
    "nipc": "516839268",
    "distrito": "Aveiro",
    "concelho": "Águeda",
    "freguesia": "Freguesia de Valongo do Vouga",
    "site": "www.bikinnov.pt",
    "email": "geral@bikinnov.pt",
    "designacao_contrato": "Empreitada de Adaptação de Armazém para Centro de Tecnologia e Inovação (Nave Norte)",
    "descricao": "Empreitada de Adaptação de Armazém para Centro de Tecnologia e Inovação (Nave Norte)",
    "preco_base": "2.485.021,31 EUR",
    "prazo_execucao": "6 MESES",
    "prazo_apresentacao_propostas": "28-09-2025 17:00",
    "fundos_eu": "Sim",
    "plataforma_eletronica": "ACIN",
    "url_procedimento": "https://www.acingov.pt",
    "autor_nome": "Inês Tavares",
    "autor_cargo": "Gestora Financeira de Projetos"
  },
  {
    "numero_procedimento": "N/A",
    "entidade": "Unidade Local de Saúde da Lezíria, E. P. E.",
    "link": "https://diariodarepublica.pt/dr/detalhe/contrato-publico/23828-934502563",
    "detalhes_completos": "1 - IDENTIFICAÇÃO E CONTACTOS DA ENTIDADE ADJUDICANTE\nDesignação da entidade adjudicante: Unidade Local de Saúde da Lezíria, E. P. E.\nNIPC: 506361462\nEndereço: Av. Bernardo Santareno S/N\nCódigo postal: 2005-177\nLocalidade: Santarém\nPaís: Portugal\nNUT III: PT185\nDistrito: Santarém\nConcelho: Santarém\nFreguesia: União de Freguesias da Cidade de Santarém\nTelefone: 243300200\nFax: 243370220\nEndereço da Entidade (URL): www.hds.min-saude.pt\nEndereço Eletrónico: hdsca@hds.min-saude.pt\neDelivery Gateway (URL): https://community.vortal.biz/public/\nFunção da Organização: Adquirente\nNorma jurídica da Entidade Adjudicante: Organismo de direito público\nÁrea de atividade da Autoridade Adjudicante: Saúde\n\n2 - JORNAL OFICIAL DA UNIÃO EUROPEIA\nO procedimento a que este anúncio diz respeito também é publicitado no Jornal Oficial da União Europeia? Não\n\n3 - AVISO\nModelo de Anúncio: Concurso público\nData de Envio do Anúncio: 08-09-2025\n\n5 - PROCESSO\nTipo de Procedimento: Concurso público\nPreço base do procedimento: Sim\nValor do preço base do procedimento: 88.735,00 EUR\nProcedimento com lotes? Não\n\n6 - OBJETO DO CONTRATO\nNúmero de referência interna: 180011/2025\nDesignação do contrato: Aquisição de serviços para fiscalização da empreitada para alargamento e melhoria das instalações do departamento de psiquiatria e saúde mental (DPSM) da ULS Lezíria, E.P.E\nDescrição: Aquisição de serviços para fiscalização da empreitada para alargamento e melhoria das instalações do departamento de psiquiatria e saúde mental (DPSM) da ULS Lezíria, E.P.E\nTipo de Contrato Principal: Aquisição de Serviços\nTipo de Contrato: Aquisição de Serviços\nClassificação CPV (Vocabulário Comum para os Contratos Públicos)\nObjeto principal\nVocabulário Principal: 79419000\nPreço base s/IVA: 88.735,00 EUR\n\n7 - INDICAÇÕES ADICIONAIS\nO contrato envolve aquisição conjunta (satisfação de várias entidades)? Não\nO contrato é adjudicado por uma central de compras? Não\n\n8 - TÉCNICAS\nO concurso destina-se à celebração de um acordo-quadro? Inexistência de acordo-quadro\nÉ utilizado um leilão eletrónico? Não\nÉ adotada uma fase de negociação? Não\nSistema de Aquisição Dinâmico: Inexistência de sistema de aquisição dinâmico\n\n9 - LOCAL DA EXECUÇÃO DO CONTRATO\nLOCAL DA EXECUÇÃO DO CONTRATO (PROCEDIMENTO)\nPaís: Portugal\nNUT III: PT185\nLocalidade: Santarém\nDistrito: Santarém\nConcelho: Santarém\nFreguesia: União de Freguesias da Cidade de Santarém\n\n10 - PRAZO DE EXECUÇÃO DO CONTRATO\nPrazo de execução do contrato: 220 DIAS\nPrevisão de renovações: Não\n\n11 - FUNDOS EU\nTêm fundos EU? Não\n\n12 - DOCUMENTOS DE HABILITAÇÃO\nHabilitação para o exercício da atividade profissional: Não\n\n13 - CONDIÇÕES DE APRESENTAÇÃO\nPlataforma eletrónica utilizada pela entidade adjudicante: VORTAL\nURL para Apresentação: https://community.vortal.biz/public/\nAdmissibilidade da apresentação de propostas variantes: Não autorizado\nPrazo para apresentação das propostas: 22-09-2025 23:59\nPrazo durante o qual os concorrentes são obrigados a manter as respetivas propostas: 66 dias a contar do termo do prazo para a apresentação das propostas\nIndicação de Subcontratação na Proposta: Inexistência de indicação de subcontratação\n\n14 - PRESTAÇÃO DE CAUÇÃO\nPrestação de caução: Não\n\n15 - FORNECIMENTO DAS PEÇAS DO CONCURSO, APRESENTAÇÃO DE PEDIDOS DE PARTICIPAÇÃO E APRESENTAÇÃO DAS PROPOSTAS\nLink para acesso às peças do concurso (URL): https://community.vortal.biz/Public/public-tender-documents/ckFDQ0p3U01FVnNnVkp3bndpMURZaGtNVUF1K2lLY0hiSFBIejhWVG1TYjVGcFFtaENmL2hsZWdQVDd4SVc3Y1M4MkVoQzEzUFdGN0NpMEF5RUNMeFE9PSZxckk2\n\n20 - OUTROS REQUISITOS\nInformação sobre contratos reservados. Aplica-se a contratos reservados (54º-A)? Não\n\n21 - CRITÉRIO DE ADJUDICAÇÃO\nMultifator: Não\nMonofator:\nNome: Preço\n\n24 - CONDIÇÕES DO CONTRATO\nFaturação Eletrónica: Permitido\nObrigação de Subcontratação:\nCódigo da Obrigação de Subcontratação: Não é aplicável nenhuma obrigação de subcontratação.\n\n25 - COMPRA PÚBLICA ESTRATÉGICA\nCompra Pública Estratégica: Inexistência de contratação pública estratégica\n\n26 - INFORMAÇÕES ADICIONAIS\nContrato adequado para PME: Sim\nCobertura ACP (Acordo dos Contratos Públicos da Organização Mundial do Comércio): Não\n\n27 - IDENTIFICAÇÃO E CONTACTOS DO ÓRGÃO DE RECURSOS ADMINISTRATIVOS\nDesignação: Conselho de Administração\nEndereço: Av. Bernardo Santareno\nCódigo postal: 2005-177\nLocalidade: Santarém\nTelefone: +351 243300200\nFax: +351 243370220\nEndereço eletrónico: ca@ulsleziria.min-saude.pt\n\n28 - IDENTIFICAÇÃO DO(S) AUTOR(ES) DE ANÚNCIO\nNome: Dr. Pedro Manuel Dias de Figueiredo Pereira Marques \nCargo: Presidente do Conselho de Administração \n419512117",
    "nipc": "506361462",
    "distrito": "Santarém",
    "concelho": "Santarém",
    "freguesia": "União de Freguesias da Cidade de Santarém",
    "site": "www.hds.min-saude.pt",
    "email": "hdsca@hds.min-saude.pt",
    "designacao_contrato": "Aquisição de serviços para fiscalização da empreitada para alargamento e melhoria das instalações do departamento de psiquiatria e saúde mental (DPSM) da ULS Lezíria, E.P.E",
    "descricao": "Aquisição de serviços para fiscalização da empreitada para alargamento e melhoria das instalações do departamento de psiquiatria e saúde mental (DPSM) da ULS Lezíria, E.P.E",
    "preco_base": "88.735,00 EUR",
    "prazo_execucao": "220 DIAS",
    "prazo_apresentacao_propostas": "22-09-2025 23:59",
    "fundos_eu": "Não",
    "plataforma_eletronica": "VORTAL",
    "url_procedimento": "https://community.vortal.biz/public/",
    "autor_nome": "Dr. Pedro Manuel Dias de Figueiredo Pereira Marques",
    "autor_cargo": "Presidente do Conselho de Administração"
  },
  {
    "numero_procedimento": "N/A",
    "entidade": "Unidade Local de Saúde do Alentejo Central, E.P.E",
    "link": "https://diariodarepublica.pt/dr/detalhe/contrato-publico/23821-934587707",
    "detalhes_completos": "1 - IDENTIFICAÇÃO E CONTACTOS DA ENTIDADE ADJUDICANTE\nDesignação da entidade adjudicante: Unidade Local de Saúde do Alentejo Central, E.P.E\nNIPC: 508085888\nEndereço: Largo Sr. da Pobreza\nCódigo postal: 7000-811\nLocalidade: Évora\nPaís: Portugal\nNUT III: PT187\nDistrito: Évora\nConcelho: Évora\nFreguesia: Todas\nTelefone: 266740111\nFax: 266744212\nEndereço da Entidade (URL): www.hevora.min-saude.pt\nEndereço Eletrónico: concursos.aprov@ulsac.min-saude.pt\neDelivery Gateway (URL): https://community.vortal.biz/public/\nFunção da Organização: Adquirente\nNorma jurídica da Entidade Adjudicante: Organismo de direito público\nÁrea de atividade da Autoridade Adjudicante: Saúde\n\n2 - JORNAL OFICIAL DA UNIÃO EUROPEIA\nO procedimento a que este anúncio diz respeito também é publicitado no Jornal Oficial da União Europeia? Não\n\n3 - AVISO\nModelo de Anúncio: Concurso público\nData de Envio do Anúncio: 08-09-2025\n\n5 - PROCESSO\nTipo de Procedimento: Concurso público\nPreço base do procedimento: Sim\nValor do preço base do procedimento: 97.920,00 EUR\nProcedimento com lotes? Não\n\n6 - OBJETO DO CONTRATO\nNúmero de referência interna: 120013/26\nDesignação do contrato: Aquisição de Fibras Laser, com colocação contra consumo de equipamentos\nDescrição: Aquisição de Fibras Laser, com colocação contra consumo de equipamentos\nTipo de Contrato Principal: Aquisição de Bens Móveis\nTipo de Contrato: Aquisição de Bens Móveis\nClassificação CPV (Vocabulário Comum para os Contratos Públicos)\nObjeto principal\nVocabulário Principal: 33140000\nPreço base s/IVA: 97.920,00 EUR\n\n7 - INDICAÇÕES ADICIONAIS\nO contrato envolve aquisição conjunta (satisfação de várias entidades)? Não\nO contrato é adjudicado por uma central de compras? Não\n\n8 - TÉCNICAS\nO concurso destina-se à celebração de um acordo-quadro? Inexistência de acordo-quadro\nÉ utilizado um leilão eletrónico? Não\nÉ adotada uma fase de negociação? Não\nSistema de Aquisição Dinâmico: Inexistência de sistema de aquisição dinâmico\n\n9 - LOCAL DA EXECUÇÃO DO CONTRATO\nLOCAL DA EXECUÇÃO DO CONTRATO (PROCEDIMENTO)\nPaís: Portugal\nNUT III: PT187\nLocalidade: Évora\nDistrito: Évora\nConcelho: Évora\nFreguesia: União das Freguesias de Évora (São Mamede, Sé, São Pedro e Santo Antão)\n\n10 - PRAZO DE EXECUÇÃO DO CONTRATO\nPrazo de execução do contrato: 36 MESES\nPrevisão de renovações: Sim\nIndicar número máximo de renovações: 2\nPrazo de renovações diferente do prazo inicial: Não\n\n11 - FUNDOS EU\nTêm fundos EU? Não\n\n12 - DOCUMENTOS DE HABILITAÇÃO\nHabilitação para o exercício da atividade profissional: Não\n\n13 - CONDIÇÕES DE APRESENTAÇÃO\nPlataforma eletrónica utilizada pela entidade adjudicante: VORTAL\nURL para Apresentação: https://community.vortal.biz/public/\nAdmissibilidade da apresentação de propostas variantes: Não autorizado\nPrazo para apresentação das propostas: 23-09-2025 18:00\nPrazo durante o qual os concorrentes são obrigados a manter as respetivas propostas: 120 dias a contar do termo do prazo para a apresentação das propostas\nIndicação de Subcontratação na Proposta: Inexistência de indicação de subcontratação\n\n14 - PRESTAÇÃO DE CAUÇÃO\nPrestação de caução: Não\n\n15 - FORNECIMENTO DAS PEÇAS DO CONCURSO, APRESENTAÇÃO DE PEDIDOS DE PARTICIPAÇÃO E APRESENTAÇÃO DAS PROPOSTAS\nLink para acesso às peças do concurso (URL): https://community.vortal.biz/Public/public-tender-documents/U1FKQXBGNEVmbmtsd1l5YmFjRnlHbzVYT3VzWTMxV1BleldBcDM0d3pZOXBnS0JYa1Y0U3lSWFFDNXQ3SkpwNUV5ZHVTNGJxNmI5TXZaZG93K3BLM1E9PUhaOXFn\n\n20 - OUTROS REQUISITOS\nInformação sobre contratos reservados. Aplica-se a contratos reservados (54º-A)? Não\n\n21 - CRITÉRIO DE ADJUDICAÇÃO\nMultifator: Não\nMonofator:\nNome: Preço\n\n24 - CONDIÇÕES DO CONTRATO\nFaturação Eletrónica: Permitido\nObrigação de Subcontratação:\nCódigo da Obrigação de Subcontratação: Não é aplicável nenhuma obrigação de subcontratação.\n\n25 - COMPRA PÚBLICA ESTRATÉGICA\nCompra Pública Estratégica: Inexistência de contratação pública estratégica\n\n26 - INFORMAÇÕES ADICIONAIS\nContrato adequado para PME: Sim\nCobertura ACP (Acordo dos Contratos Públicos da Organização Mundial do Comércio): Não\n\n27 - IDENTIFICAÇÃO E CONTACTOS DO ÓRGÃO DE RECURSOS ADMINISTRATIVOS\nDesignação: Unidade Local de Saúde do Alentejo Central, E.P.E.\nEndereço: Largo da Pobreza\nCódigo postal: 7005-594\nLocalidade: Évora\nTelefone: +351 266740111\nFax: +351 266744212\nEndereço eletrónico: concursos.aprov@ulsac.min-saude.pt\n\n28 - IDENTIFICAÇÃO DO(S) AUTOR(ES) DE ANÚNCIO\nNome: Vítor Rui Gomes Fialho\nCargo: Presidente do Conselho de Administração\n419512774",
    "nipc": "508085888",
    "distrito": "Évora",
    "concelho": "Évora",
    "freguesia": "Todas",
    "site": "www.hevora.min-saude.pt",
    "email": "concursos.aprov@ulsac.min-saude.pt",
    "designacao_contrato": "Aquisição de Fibras Laser, com colocação contra consumo de equipamentos",
    "descricao": "Aquisição de Fibras Laser, com colocação contra consumo de equipamentos",
    "preco_base": "97.920,00 EUR",
    "prazo_execucao": "36 MESES",
    "prazo_apresentacao_propostas": "23-09-2025 18:00",
    "fundos_eu": "Não",
    "plataforma_eletronica": "VORTAL",
    "url_procedimento": "https://community.vortal.biz/public/",
    "autor_nome": "Vítor Rui Gomes Fialho",
    "autor_cargo": "Presidente do Conselho de Administração"
  },
  {
    "numero_procedimento": "N/A",
    "entidade": "Câmara Municipal de Matosinhos",
    "link": "https://diariodarepublica.pt/dr/detalhe/contrato-publico/23822-934587708",
    "detalhes_completos": "Alteração do Anúncio de procedimento n.º 23028/2025, de 2025-08-29, com o ID 419476916\n\n1 - IDENTIFICAÇÃO E CONTACTOS DA ENTIDADE ADJUDICANTE\nDesignação da entidade adjudicante: Câmara Municipal de Matosinhos\nNIPC: 501305912\nServiço/Órgão/Pessoa de contacto: Departamento de Ambiente\nEndereço: Av. D. Afonso Henriques\nCódigo postal: 4454-510\nLocalidade: Matosinhos\nPaís: Portugal\nNUT III: PT11A\nDistrito: Porto\nConcelho: Matosinhos\nFreguesia: Todas\nTelefone: 229390900\nFax: 229351645\nEndereço da Entidade (URL): http://www.cm-matosinhos.pt\nEndereço Eletrónico: contratacaopublica@cm-matosinhos.pt\neDelivery Gateway (URL): https://www.acingov.pt\nFunção da Organização: Adquirente\nNorma jurídica da Entidade Adjudicante: Organismo de direito público\nÁrea de atividade da Autoridade Adjudicante: Serviços públicos das administrações públicas\n\n2 - JORNAL OFICIAL DA UNIÃO EUROPEIA\nO procedimento a que este anúncio diz respeito também é publicitado no Jornal Oficial da União Europeia? Não\n\n3 - AVISO\nModelo de Anúncio: Concurso público\nData de Envio do Anúncio: 08-09-2025\n\n5 - PROCESSO\nTipo de Procedimento: Concurso público\nPreço base do procedimento: Sim\nValor do preço base do procedimento: 124.501,00 EUR\nProcedimento com lotes? Não\n\n6 - OBJETO DO CONTRATO\nNúmero de referência interna: 2025/27072\nDesignação do contrato: PODAS E ABATES DE ÁRVORES EM ESPAÇO PUBLICO DO CONCELHO DE MATOSINHOS\nDescrição: PODAS E ABATES DE ÁRVORES EM ESPAÇO PUBLICO DO CONCELHO DE MATOSINHOS\nTipo de Contrato Principal: Aquisição de Serviços\nTipo de Contrato: Aquisição de Serviços\nClassificação CPV (Vocabulário Comum para os Contratos Públicos)\nObjeto principal\nVocabulário Principal: 77340000\nPreço base s/IVA: 124.501,00 EUR\n\n7 - INDICAÇÕES ADICIONAIS\nO contrato envolve aquisição conjunta (satisfação de várias entidades)? Não\nO contrato é adjudicado por uma central de compras? Não\n\n8 - TÉCNICAS\nO concurso destina-se à celebração de um acordo-quadro? Inexistência de acordo-quadro\nÉ utilizado um leilão eletrónico? Não\nÉ adotada uma fase de negociação? Não\nSistema de Aquisição Dinâmico: Inexistência de sistema de aquisição dinâmico\n\n9 - LOCAL DA EXECUÇÃO DO CONTRATO\nLOCAL DA EXECUÇÃO DO CONTRATO (PROCEDIMENTO)\nPaís: Portugal\nNUT III: PT11A\nLocalidade: Matosinhos\nDistrito: Porto\nConcelho: Matosinhos\nFreguesia: Todas\n\n10 - PRAZO DE EXECUÇÃO DO CONTRATO\nPrazo de execução do contrato: 36 MESES\nPrevisão de renovações: Não\n\n11 - FUNDOS EU\nTêm fundos EU? Não\n\n12 - DOCUMENTOS DE HABILITAÇÃO\nHabilitação para o exercício da atividade profissional: Não\n\n13 - CONDIÇÕES DE APRESENTAÇÃO\nPlataforma eletrónica utilizada pela entidade adjudicante: ACIN\nURL para Apresentação: https://www.acingov.pt\nAdmissibilidade da apresentação de propostas variantes: Não autorizado\nPrazo para apresentação das propostas: 17-09-2025 23:59\nPrazo durante o qual os concorrentes são obrigados a manter as respetivas propostas: 66 dias a contar do termo do prazo para a apresentação das propostas\nIndicação de Subcontratação na Proposta: Inexistência de indicação de subcontratação\n\n14 - PRESTAÇÃO DE CAUÇÃO\nPrestação de caução: Não\n\n15 - FORNECIMENTO DAS PEÇAS DO CONCURSO, APRESENTAÇÃO DE PEDIDOS DE PARTICIPAÇÃO E APRESENTAÇÃO DAS PROPOSTAS\nLink para acesso às peças do concurso (URL): https://www.acingov.pt/acingovprod/2/zonaPublica/zona_publica_c/donwloadProcedurePiece/OTcyNDY0\n\n20 - OUTROS REQUISITOS\nInformação sobre contratos reservados. Aplica-se a contratos reservados (54º-A)? Não\n\n21 - CRITÉRIO DE ADJUDICAÇÃO\nMultifator: Sim\nFator: \nNome: Outros\nOutro Nome: Multifator\nPonderação: 100%\nSubfatores: Não\n\n24 - CONDIÇÕES DO CONTRATO\nFaturação Eletrónica: Não autorizado\nObrigação de Subcontratação:\nCódigo da Obrigação de Subcontratação: Não é aplicável nenhuma obrigação de subcontratação.\n\n25 - COMPRA PÚBLICA ESTRATÉGICA\nCompra Pública Estratégica: Inexistência de contratação pública estratégica\n\n26 - INFORMAÇÕES ADICIONAIS\nContrato adequado para PME: Não\nCobertura ACP (Acordo dos Contratos Públicos da Organização Mundial do Comércio): Não\n\n27 - IDENTIFICAÇÃO E CONTACTOS DO ÓRGÃO DE RECURSOS ADMINISTRATIVOS\nDesignação: Município de Matosinhos\nEndereço: Av. D. Afonso Henriques\nCódigo postal: 4454-510\nLocalidade: Matosinhos\nTelefone: 229390900\nFax: 229351645\nEndereço eletrónico: contratacaopublica@cm-matosinhos.pt\nPrazo de interposição do recurso: 5 dias\n\n28 - IDENTIFICAÇÃO DO(S) AUTOR(ES) DE ANÚNCIO\nNome: Luísa Maria Neves Salgueiro\nCargo: Presidente da Câmara\n\n29 - ALTERAÇÃO\nMotivo da Alteração: Informações atualizadas\nIdentificador da Versão do Anúncio a Alterar: 8c9bedd9-568a-4387-94a8-c5c81d3ff090-01\nIdentificador das Secções Alteradas do Anúncio Anterior: Outros Requisitos\nDescrição das Alterações: Alteração ao programa de concurso e caderno de encargos\nAlteração dos Documentos do Concurso: Não\n419507322",
    "nipc": "501305912",
    "distrito": "Porto",
    "concelho": "Matosinhos",
    "freguesia": "Todas",
    "site": "http://www.cm-matosinhos.pt",
    "email": "contratacaopublica@cm-matosinhos.pt",
    "designacao_contrato": "PODAS E ABATES DE ÁRVORES EM ESPAÇO PUBLICO DO CONCELHO DE MATOSINHOS",
    "descricao": "PODAS E ABATES DE ÁRVORES EM ESPAÇO PUBLICO DO CONCELHO DE MATOSINHOS",
    "preco_base": "124.501,00 EUR",
    "prazo_execucao": "36 MESES",
    "prazo_apresentacao_propostas": "17-09-2025 23:59",
    "fundos_eu": "Não",
    "plataforma_eletronica": "ACIN",
    "url_procedimento": "https://www.acingov.pt",
    "autor_nome": "Luísa Maria Neves Salgueiro",
    "autor_cargo": "Presidente da Câmara"
  },
  {
    "numero_procedimento": "N/A",
    "entidade": "Município de Matosinhos",
    "link": "https://diariodarepublica.pt/dr/detalhe/contrato-publico/23824-934587709",
    "detalhes_completos": "1 - IDENTIFICAÇÃO E CONTACTOS DA ENTIDADE ADJUDICANTE\nDesignação da entidade adjudicante: Município de Matosinhos\nNIPC: 501305912\nServiço/Órgão/Pessoa de contacto: Divisão de Contratação Publica\nEndereço: Matosinhos\nCódigo postal: 4454-510\nLocalidade: Matosinhos\nPaís: Portugal\nNUT III: PT11A\nDistrito: Porto\nConcelho: Matosinhos\nFreguesia: Todas\nTelefone: 229390900\nFax: 229351645\nEndereço da Entidade (URL): http://www.cm-matosinhos.pt\nEndereço Eletrónico: contratacaopublica@cm-matosinhos.pt\neDelivery Gateway (URL): https://www.acingov.pt\nFunção da Organização: Adquirente\nSubfunção da Organização: Organização que recebe as propostas\nNorma jurídica da Entidade Adjudicante: Organismo de direito público\nÁrea de atividade da Autoridade Adjudicante: Serviços públicos das administrações públicas\n\n2 - JORNAL OFICIAL DA UNIÃO EUROPEIA\nO procedimento a que este anúncio diz respeito também é publicitado no Jornal Oficial da União Europeia? Não\n\n3 - AVISO\nModelo de Anúncio: Concurso público\nData de Envio do Anúncio: 08-09-2025\n\n5 - PROCESSO\nTipo de Procedimento: Concurso público\nPreço base do procedimento: Sim\nValor do preço base do procedimento: 396.001,00 EUR\nProcedimento com lotes? Não\n\n6 - OBJETO DO CONTRATO\nNúmero de referência interna: 2025/26258\nDesignação do contrato: MANUTENÇÃO DOS PASSADIÇOS DA ORLA COSTEIRA DE MATOSINHOS\nDescrição: MANUTENÇÃO DOS PASSADIÇOS DA ORLA COSTEIRA DE MATOSINHOS \nTipo de Contrato Principal: Empreitada de Obras Públicas\nTipo de Contrato: Empreitada de Obras Públicas\nClassificação CPV (Vocabulário Comum para os Contratos Públicos)\nObjeto principal\nVocabulário Principal: 45240000\nPreço base s/IVA: 396.001,00 EUR\n\n7 - INDICAÇÕES ADICIONAIS\nO contrato envolve aquisição conjunta (satisfação de várias entidades)? Não\nO contrato é adjudicado por uma central de compras? Não\n\n8 - TÉCNICAS\nO concurso destina-se à celebração de um acordo-quadro? Inexistência de acordo-quadro\nÉ utilizado um leilão eletrónico? Não\nÉ adotada uma fase de negociação? Não\nSistema de Aquisição Dinâmico: Inexistência de sistema de aquisição dinâmico\n\n9 - LOCAL DA EXECUÇÃO DO CONTRATO\nLOCAL DA EXECUÇÃO DO CONTRATO (PROCEDIMENTO)\nPaís: Portugal\nNUT III: PT11A\nLocalidade: Matosinhos\nDistrito: Porto\nConcelho: Matosinhos\nFreguesia: Todas\n\n10 - PRAZO DE EXECUÇÃO DO CONTRATO\nPrazo de execução do contrato: 18 MESES\nPrevisão de renovações: Não\n\n11 - FUNDOS EU\nTêm fundos EU? Não\n\n12 - DOCUMENTOS DE HABILITAÇÃO\nHabilitação para o exercício da atividade profissional: Não\n\n13 - CONDIÇÕES DE APRESENTAÇÃO\nPlataforma eletrónica utilizada pela entidade adjudicante: ACIN\nURL para Apresentação: https://www.acingov.pt\nAdmissibilidade da apresentação de propostas variantes: Não autorizado\nPrazo para apresentação das propostas: 24-09-2025 23:59\nPrazo durante o qual os concorrentes são obrigados a manter as respetivas propostas: 66 dias a contar do termo do prazo para a apresentação das propostas\nIndicação de Subcontratação na Proposta: Inexistência de indicação de subcontratação\n\n14 - PRESTAÇÃO DE CAUÇÃO\nPrestação de caução: Não\n\n15 - FORNECIMENTO DAS PEÇAS DO CONCURSO, APRESENTAÇÃO DE PEDIDOS DE PARTICIPAÇÃO E APRESENTAÇÃO DAS PROPOSTAS\nLink para acesso às peças do concurso (URL): https://www.acingov.pt/acingovprod/2/zonaPublica/zona_publica_c/donwloadProcedurePiece/OTc1Njgz\n\n20 - OUTROS REQUISITOS\nInformação sobre contratos reservados. Aplica-se a contratos reservados (54º-A)? Não\n\n21 - CRITÉRIO DE ADJUDICAÇÃO\nMultifator: Não\nMonofator:\nNome: Preço\n\n24 - CONDIÇÕES DO CONTRATO\nFaturação Eletrónica: Permitido\nObrigação de Subcontratação:\nCódigo da Obrigação de Subcontratação: Não é aplicável nenhuma obrigação de subcontratação.\n\n25 - COMPRA PÚBLICA ESTRATÉGICA\nCompra Pública Estratégica: Inexistência de contratação pública estratégica\n\n26 - INFORMAÇÕES ADICIONAIS\nContrato adequado para PME: Não\nCobertura ACP (Acordo dos Contratos Públicos da Organização Mundial do Comércio): Não\n\n27 - IDENTIFICAÇÃO E CONTACTOS DO ÓRGÃO DE RECURSOS ADMINISTRATIVOS\nDesignação: Município de Matosinhos\nEndereço: Matosinhos\nCódigo postal: 4454-510\nLocalidade: Matosinhos\nTelefone: 229390900\nFax: \nEndereço eletrónico: contratacaopublica@cm-matosinhos.pt\nPrazo de interposição do recurso: 5 dias\n\n28 - IDENTIFICAÇÃO DO(S) AUTOR(ES) DE ANÚNCIO\nNome: Luisa Maria Neves Salgueiro\nCargo: Presidente da Câmara\n419507477",
    "nipc": "501305912",
    "distrito": "Porto",
    "concelho": "Matosinhos",
    "freguesia": "Todas",
    "site": "http://www.cm-matosinhos.pt",
    "email": "contratacaopublica@cm-matosinhos.pt",
    "designacao_contrato": "MANUTENÇÃO DOS PASSADIÇOS DA ORLA COSTEIRA DE MATOSINHOS",
    "descricao": "MANUTENÇÃO DOS PASSADIÇOS DA ORLA COSTEIRA DE MATOSINHOS",
    "preco_base": "396.001,00 EUR",
    "prazo_execucao": "18 MESES",
    "prazo_apresentacao_propostas": "24-09-2025 23:59",
    "fundos_eu": "Não",
    "plataforma_eletronica": "ACIN",
    "url_procedimento": "https://www.acingov.pt",
    "autor_nome": "Luisa Maria Neves Salgueiro",
    "autor_cargo": "Presidente da Câmara"
  },
  {
    "numero_procedimento": "N/A",
    "entidade": "Lardouro  Lar de idosos e Centro de Dia, Lda",
    "link": "https://diariodarepublica.pt/dr/detalhe/contrato-publico/23825-934587710",
    "detalhes_completos": "1 - IDENTIFICAÇÃO E CONTACTOS DA ENTIDADE ADJUDICANTE\nDesignação da entidade adjudicante: Lardouro  Lar de idosos e Centro de Dia, Lda\nNIPC: 507474031\nServiço/Órgão/Pessoa de contacto: Direção\nEndereço: Rua de Recarei, nºs 698 e 714\nCódigo postal: 4465-730\nLocalidade: Leça do Balio, Matosinhos\nPaís: Portugal\nNUT III: PT11A\nDistrito: Porto\nConcelho: Matosinhos\nFreguesia: União das Freguesias de Matosinhos e Leça da Palmeira\nTelefone: 229537785\nFax: 229537785\nEndereço da Entidade (URL): www.lardouro.pt\nEndereço Eletrónico: geral@lardouro.pt\neDelivery Gateway (URL): https://www.acingov.pt\nFunção da Organização: Adquirente\nSubfunção da Organização: Organização que recebe as propostas\nNorma jurídica da Entidade Adjudicante: Organismo de direito público\nÁrea de atividade da Autoridade Adjudicante: Serviços públicos das administrações públicas\n\n2 - JORNAL OFICIAL DA UNIÃO EUROPEIA\nO procedimento a que este anúncio diz respeito também é publicitado no Jornal Oficial da União Europeia? Não\n\n3 - AVISO\nModelo de Anúncio: Concurso público\nData de Envio do Anúncio: 08-09-2025\n\n5 - PROCESSO\nTipo de Procedimento: Concurso público\nPreço base do procedimento: Sim\nValor do preço base do procedimento: 218.500,00 EUR\nProcedimento com lotes? Não\n\n6 - OBJETO DO CONTRATO\nNúmero de referência interna: CP 01/2025\nDesignação do contrato: Aquisição de serviços de Fiscalização e Coordenação de Segurança e Saúde\nDescrição: Aquisição de serviços de Fiscalização e Coordenação de Segurança e Saúde\nTipo de Contrato Principal: Aquisição de Serviços\nTipo de Contrato: Aquisição de Serviços\nClassificação CPV (Vocabulário Comum para os Contratos Públicos)\nObjeto principal\nVocabulário Principal: 71520000\nPreço base s/IVA: 218.500,00 EUR\n\n7 - INDICAÇÕES ADICIONAIS\nO contrato envolve aquisição conjunta (satisfação de várias entidades)? Não\nO contrato é adjudicado por uma central de compras? Não\n\n8 - TÉCNICAS\nO concurso destina-se à celebração de um acordo-quadro? Inexistência de acordo-quadro\nÉ utilizado um leilão eletrónico? Não\nÉ adotada uma fase de negociação? Não\nSistema de Aquisição Dinâmico: Inexistência de sistema de aquisição dinâmico\n\n9 - LOCAL DA EXECUÇÃO DO CONTRATO\nLOCAL DA EXECUÇÃO DO CONTRATO (PROCEDIMENTO)\nPaís: Portugal\nNUT III: PT11A\nLocalidade: União das Freguesias de Matosinhos e Leça da Palmeira\nDistrito: Porto\nConcelho: Matosinhos\nFreguesia: União das Freguesias de Matosinhos e Leça da Palmeira\n\n10 - PRAZO DE EXECUÇÃO DO CONTRATO\nPrazo de execução do contrato: 19 MESES\nPrevisão de renovações: Não\n\n11 - FUNDOS EU\nTêm fundos EU? Não\n\n12 - DOCUMENTOS DE HABILITAÇÃO\nHabilitação para o exercício da atividade profissional: Não\n\n13 - CONDIÇÕES DE APRESENTAÇÃO\nPlataforma eletrónica utilizada pela entidade adjudicante: ACIN\nURL para Apresentação: https://www.acingov.pt\nAdmissibilidade da apresentação de propostas variantes: Não autorizado\nPrazo para apresentação das propostas: 14-09-2025 17:00\nPrazo durante o qual os concorrentes são obrigados a manter as respetivas propostas: 66 dias a contar do termo do prazo para a apresentação das propostas\nIndicação de Subcontratação na Proposta: Inexistência de indicação de subcontratação\n\n14 - PRESTAÇÃO DE CAUÇÃO\nPrestação de caução: Não\n\n15 - FORNECIMENTO DAS PEÇAS DO CONCURSO, APRESENTAÇÃO DE PEDIDOS DE PARTICIPAÇÃO E APRESENTAÇÃO DAS PROPOSTAS\nLink para acesso às peças do concurso (URL): https://www.acingov.pt/acingovprod/2/zonaPublica/zona_publica_c/donwloadProcedurePiece/OTc1OTc1\n\n20 - OUTROS REQUISITOS\nInformação sobre contratos reservados. Aplica-se a contratos reservados (54º-A)? Não\n\n21 - CRITÉRIO DE ADJUDICAÇÃO\nMultifator: Sim\nFator: \nNome: Preço\nPonderação: 60%\nSubfatores: Não\nFator: \nNome: Outros\nOutro Nome: valia técnica\nPonderação: 20%\nSubfatores: Não\nFator: \nNome: Outros\nOutro Nome: Equipa técnica\nPonderação: 20%\nSubfatores: Não\n\n24 - CONDIÇÕES DO CONTRATO\nFaturação Eletrónica: Não autorizado\nObrigação de Subcontratação:\nCódigo da Obrigação de Subcontratação: Não é aplicável nenhuma obrigação de subcontratação.\n\n25 - COMPRA PÚBLICA ESTRATÉGICA\nCompra Pública Estratégica: Inexistência de contratação pública estratégica\n\n26 - INFORMAÇÕES ADICIONAIS\nContrato adequado para PME: Sim\nCobertura ACP (Acordo dos Contratos Públicos da Organização Mundial do Comércio): Não\n\n27 - IDENTIFICAÇÃO E CONTACTOS DO ÓRGÃO DE RECURSOS ADMINISTRATIVOS\nDesignação: Direção do Lardouro  Lar de idosos e Centro de Dia, Lda.\nEndereço: Rua de Recarei, nºs 698 e 714\nCódigo postal: 4465-730\nLocalidade: Leça do Balio, Matosinhos\nTelefone: 229537785\nFax: 229537785\nEndereço eletrónico: geral@lardouro.pt\nPrazo de interposição do recurso: 10 dias\n\n28 - IDENTIFICAÇÃO DO(S) AUTOR(ES) DE ANÚNCIO\nNome: Manuel Carlos Miranda Borges\nCargo: gerente\n419514248",
    "nipc": "507474031",
    "distrito": "Porto",
    "concelho": "Matosinhos",
    "freguesia": "União das Freguesias de Matosinhos e Leça da Palmeira",
    "site": "www.lardouro.pt",
    "email": "geral@lardouro.pt",
    "designacao_contrato": "Aquisição de serviços de Fiscalização e Coordenação de Segurança e Saúde",
    "descricao": "Aquisição de serviços de Fiscalização e Coordenação de Segurança e Saúde",
    "preco_base": "218.500,00 EUR",
    "prazo_execucao": "19 MESES",
    "prazo_apresentacao_propostas": "14-09-2025 17:00",
    "fundos_eu": "Não",
    "plataforma_eletronica": "ACIN",
    "url_procedimento": "https://www.acingov.pt",
    "autor_nome": "Manuel Carlos Miranda Borges",
    "autor_cargo": "gerente"
  },
  {
    "numero_procedimento": "N/A",
    "entidade": "ESTADO-MAIOR-GENERAL DAS FORÇAS ARMADAS",
    "link": "https://diariodarepublica.pt/dr/detalhe/contrato-publico/23829-934587719",
    "detalhes_completos": "1 - IDENTIFICAÇÃO E CONTACTOS DA ENTIDADE ADJUDICANTE\nDesignação da entidade adjudicante: ESTADO-MAIOR-GENERAL DAS FORÇAS ARMADAS\nNIPC: 600010180\nServiço/Órgão/Pessoa de contacto: DepComp/DF/HFAR\nEndereço: AVENIDA ILHA DA MADEIRA\nCódigo postal: 1449-004\nLocalidade: Lisboa\nPaís: Portugal\nNUT III: PT170\nDistrito: Lisboa\nConcelho: Lisboa\nFreguesia: Freguesia de Lumiar\nTelefone: 2130100001\nEndereço da Entidade (URL): www.emgfa.pt\nEndereço Eletrónico: DIRFIN_Contratos@emgfa.pt\neDelivery Gateway (URL): https://www.acingov.pt\nFunção da Organização: Adquirente\nNorma jurídica da Entidade Adjudicante: Organismo de direito público\nÁrea de atividade da Autoridade Adjudicante: Serviços públicos das administrações públicas\n\n2 - JORNAL OFICIAL DA UNIÃO EUROPEIA\nO procedimento a que este anúncio diz respeito também é publicitado no Jornal Oficial da União Europeia? Não\n\n3 - AVISO\nModelo de Anúncio: Concurso público\nData de Envio do Anúncio: 09-09-2025\n\n5 - PROCESSO\nTipo de Procedimento: Concurso público\nPreço base do procedimento: Sim\nValor do preço base do procedimento: 89.600,00 EUR\nProcedimento com lotes? Sim\nNº Máx. de Lotes Autorizado: 3\nNúmero máximo de lotes que podem ser adjudicados a um concorrente: 3\n\n6 - OBJETO DO CONTRATO\nNúmero de referência interna: HFAR-PL 2025006757\nDesignação do contrato: 2025006757/HFAR-Fardamento para o Hospital das Forças Armadas\nDescrição: 2025006757/HFAR-Fardamento para o Hospital das Forças Armadas\nTipo de Contrato Principal: Aquisição de Bens Móveis\nTipo de Contrato: Aquisição de Bens Móveis\nClassificação CPV (Vocabulário Comum para os Contratos Públicos)\nObjeto principal\nVocabulário Principal: 35811300\nPreço base s/IVA: 89.600,00 EUR\nLotes: \nNº: LOT-0001\nDescrição do Lote: BATAS HOSPITALAR\nPreço base s/IVA: 14.356,00 EUR\nClassificação CPV (Vocabulário Comum para os Contratos Públicos)\nObjeto principal\nVocabulário Principal: 35811300\nNº: LOT-0002\nDescrição do Lote: ROUPA HOSPITALAR\nPreço base s/IVA: 60.624,00 EUR\nClassificação CPV (Vocabulário Comum para os Contratos Públicos)\nObjeto principal\nVocabulário Principal: 35811300\nNº: LOT-0003\nDescrição do Lote: PIJAMA E BATA UTENTE\nPreço base s/IVA: 14.620,00 EUR\nClassificação CPV (Vocabulário Comum para os Contratos Públicos)\nObjeto principal\nVocabulário Principal: 35811300\n\n7 - INDICAÇÕES ADICIONAIS\nO contrato envolve aquisição conjunta (satisfação de várias entidades)? Não\nO contrato é adjudicado por uma central de compras? Não\n\n8 - TÉCNICAS\nO concurso destina-se à celebração de um acordo-quadro? Inexistência de acordo-quadro\nÉ utilizado um leilão eletrónico? Não\nÉ adotada uma fase de negociação? Não\nSistema de Aquisição Dinâmico: Inexistência de sistema de aquisição dinâmico\n\n9 - LOCAL DA EXECUÇÃO DO CONTRATO\nLOCAL DA EXECUÇÃO DO CONTRATO (PROCEDIMENTO)\nPaís: Portugal\nNUT III: PT170\nLocalidade: Freguesia de Lumiar\nDistrito: Lisboa\nConcelho: Lisboa\nFreguesia: Freguesia de Lumiar\nLOCAL DA EXECUÇÃO DO CONTRATO (LOTE)\nIdentificador do Lote: LOT-0001; LOT-0002; LOT-0003\nPaís: Portugal\nNUT III: PT170\nLocalidade: Lumiar\nDistrito: Lisboa\nConcelho: Lisboa\nFreguesia: Todas\n\n10 - PRAZO DE EXECUÇÃO DO CONTRATO\nIdentificador do Lote: LOT-0001; LOT-0002; LOT-0003\nPrazo de execução do contrato: 120 DIAS\nPrevisão de renovações: Não\n\n11 - FUNDOS EU\nIdentificador do Lote: LOT-0001; LOT-0002; LOT-0003\nTêm fundos EU? Não\n\n12 - DOCUMENTOS DE HABILITAÇÃO\nHabilitação para o exercício da atividade profissional: Não\n\n13 - CONDIÇÕES DE APRESENTAÇÃO\nPlataforma eletrónica utilizada pela entidade adjudicante: ACIN\nURL para Apresentação: https://www.acingov.pt\nAdmissibilidade da apresentação de propostas variantes: Não autorizado\nPrazo para apresentação das propostas: 22-09-2025 23:59\nPrazo durante o qual os concorrentes são obrigados a manter as respetivas propostas: 66 dias a contar do termo do prazo para a apresentação das propostas\nIndicação de Subcontratação na Proposta: Inexistência de indicação de subcontratação\n\n14 - PRESTAÇÃO DE CAUÇÃO\nPrestação de caução: Não\n\n15 - FORNECIMENTO DAS PEÇAS DO CONCURSO, APRESENTAÇÃO DE PEDIDOS DE PARTICIPAÇÃO E APRESENTAÇÃO DAS PROPOSTAS\nLink para acesso às peças do concurso (URL): https://www.acingov.pt/acingovprod/2/zonaPublica/zona_publica_c/donwloadProcedurePiece/OTc1Njk5\n\n20 - OUTROS REQUISITOS\nIdentificador do Lote: LOT-0001; LOT-0002; LOT-0003\nInformação sobre contratos reservados. Aplica-se a contratos reservados (54º-A)? Não\n\n21 - CRITÉRIO DE ADJUDICAÇÃO\nO Critério de adjudicação é diferenciado por lote? Não\nMultifator: Não\nMonofator:\nNome: Preço\n\n24 - CONDIÇÕES DO CONTRATO\nIdentificador do Lote: LOT-0001; LOT-0002; LOT-0003\nFaturação Eletrónica: Permitido\nObrigação de Subcontratação:\nCódigo da Obrigação de Subcontratação: Não é aplicável nenhuma obrigação de subcontratação.\n\n25 - COMPRA PÚBLICA ESTRATÉGICA\nCompra Pública Estratégica: Inexistência de contratação pública estratégica\n\n26 - INFORMAÇÕES ADICIONAIS\nIdentificador do Lote: LOT-0001; LOT-0002; LOT-0003\nContrato adequado para PME: Sim\nCobertura ACP (Acordo dos Contratos Públicos da Organização Mundial do Comércio): Não\n\n27 - IDENTIFICAÇÃO E CONTACTOS DO ÓRGÃO DE RECURSOS ADMINISTRATIVOS\nDesignação: EMGMFA\nEndereço: Av. Ilha da Madeira N.º 1\nCódigo postal: 1449-004\nLocalidade: LISBOA\nTelefone: 213043000\nFax: \nEndereço eletrónico: emgfa@emgfa.pt\n\n28 - IDENTIFICAÇÃO DO(S) AUTOR(ES) DE ANÚNCIO\nNome: José Carlos Candeias Pinheiro Monge\nCargo: DIRETOR DO HFAR\n419513365",
    "nipc": "600010180",
    "distrito": "Lisboa",
    "concelho": "Lisboa",
    "freguesia": "Freguesia de Lumiar",
    "site": "www.emgfa.pt",
    "email": "DIRFIN_Contratos@emgfa.pt",
    "designacao_contrato": "2025006757/HFAR-Fardamento para o Hospital das Forças Armadas",
    "descricao": "2025006757/HFAR-Fardamento para o Hospital das Forças Armadas",
    "preco_base": "89.600,00 EUR",
    "prazo_execucao": "120 DIAS",
    "prazo_apresentacao_propostas": "22-09-2025 23:59",
    "fundos_eu": "Não",
    "plataforma_eletronica": "ACIN",
    "url_procedimento": "https://www.acingov.pt",
    "autor_nome": "José Carlos Candeias Pinheiro Monge",
    "autor_cargo": "DIRETOR DO HFAR"
  }
]