[
  {
    "numero_procedimento": "N/A",
    "entidade": "Município de Aveiro",
    "link": "https://diariodarepublica.pt/dr/detalhe/contrato-publico/26475-938846169",
    "detalhes_completos": "1 - IDENTIFICAÇÃO E CONTACTOS DA ENTIDADE ADJUDICANTE\nDesignação da entidade adjudicante: Município de Aveiro\nNIPC: 505931192\nServiço/Órgão/Pessoa de contacto: Divisão Compras e Património\nEndereço: Cais da Fonte Nova\nCódigo postal: 3810-200\nLocalidade: Aveiro\nPaís: Portugal\nNUT III: PT16D\nDistrito: Aveiro\nConcelho: Aveiro\nFreguesia: União das Freguesias de Glória e Vera Cruz\nTelefone: 234406496\nFax: 234406301\nEndereço da Entidade (URL): www.cm-aveiro.pt\nEndereço Eletrónico: geral@cm-aveiro.pt\neDelivery Gateway (URL): https://www.acingov.pt\nFunção da Organização: Adquirente\nNorma jurídica da Entidade Adjudicante: Organismo de direito público\nÁrea de atividade da Autoridade Adjudicante: Serviços públicos das administrações públicas\n\n2 - JORNAL OFICIAL DA UNIÃO EUROPEIA\nO procedimento a que este anúncio diz respeito também é publicitado no Jornal Oficial da União Europeia? Não\n\n3 - AVISO\nModelo de Anúncio: Concurso público\nData de Envio do Anúncio: 08-10-2025\n\n5 - PROCESSO\nTipo de Procedimento: Concurso público\nPreço base do procedimento: Sim\nValor do preço base do procedimento: 200.000,00 EUR\nProcedimento com lotes? Não\n\n6 - OBJETO DO CONTRATO\nNúmero de referência interna: 28/2025\nDesignação do contrato: AQUISIÇÃO DE TRAPICHES PARA OS CAIS 15 E 16 NO CANAL DAS PIRÂMIDES - AVEIRO\nDescrição: AQUISIÇÃO DE TRAPICHES PARA OS CAIS 15 E 16 NO CANAL DAS PIRÂMIDES - AVEIRO\nTipo de Contrato Principal: Aquisição de Bens Móveis\nTipo de Contrato: Aquisição de Bens Móveis\nClassificação CPV (Vocabulário Comum para os Contratos Públicos)\nObjeto principal\nVocabulário Principal: 34515000\nPreço base s/IVA: 200.000,00 EUR\n\n7 - INDICAÇÕES ADICIONAIS\nO contrato envolve aquisição conjunta (satisfação de várias entidades)? Não\nO contrato é adjudicado por uma central de compras? Não\n\n8 - TÉCNICAS\nO concurso destina-se à celebração de um acordo-quadro? Inexistência de acordo-quadro\nÉ utilizado um leilão eletrónico? Não\nÉ adotada uma fase de negociação? Não\nSistema de Aquisição Dinâmico: Inexistência de sistema de aquisição dinâmico\n\n9 - LOCAL DA EXECUÇÃO DO CONTRATO\nLOCAL DA EXECUÇÃO DO CONTRATO (PROCEDIMENTO)\nPaís: Portugal\nNUT III: PT16D\nLocalidade: União das Freguesias de Glória e Vera Cruz\nDistrito: Aveiro\nConcelho: Aveiro\nFreguesia: União das Freguesias de Glória e Vera Cruz\n\n10 - PRAZO DE EXECUÇÃO DO CONTRATO\nPrazo de execução do contrato: 120 DIAS\nPrevisão de renovações: Não\n\n11 - FUNDOS EU\nTêm fundos EU? Não\n\n12 - DOCUMENTOS DE HABILITAÇÃO\nHabilitação para o exercício da atividade profissional: Não\n\n13 - CONDIÇÕES DE APRESENTAÇÃO\nPlataforma eletrónica utilizada pela entidade adjudicante: ACIN\nURL para Apresentação: https://www.acingov.pt\nAdmissibilidade da apresentação de propostas variantes: Não autorizado\nPrazo para apresentação das propostas: 24-10-2025 17:00\nPrazo durante o qual os concorrentes são obrigados a manter as respetivas propostas: 120 dias a contar do termo do prazo para a apresentação das propostas\nIndicação de Subcontratação na Proposta: Inexistência de indicação de subcontratação\n\n14 - PRESTAÇÃO DE CAUÇÃO\nPrestação de caução: Não\n\n15 - FORNECIMENTO DAS PEÇAS DO CONCURSO, APRESENTAÇÃO DE PEDIDOS DE PARTICIPAÇÃO E APRESENTAÇÃO DAS PROPOSTAS\nLink para acesso às peças do concurso (URL): https://www.acingov.pt/acingovprod/2/zonaPublica/zona_publica_c/donwloadProcedurePiece/OTg0MTU4\n\n20 - OUTROS REQUISITOS\nInformação sobre contratos reservados. Aplica-se a contratos reservados (54º-A)? Não\n\n21 - CRITÉRIO DE ADJUDICAÇÃO\nMultifator: Não\nMonofator:\nNome: Preço\n\n24 - CONDIÇÕES DO CONTRATO\nFaturação Eletrónica: Permitido\nObrigação de Subcontratação:\nCódigo da Obrigação de Subcontratação: Não é aplicável nenhuma obrigação de subcontratação.\n\n25 - COMPRA PÚBLICA ESTRATÉGICA\nCompra Pública Estratégica: Inexistência de contratação pública estratégica\n\n26 - INFORMAÇÕES ADICIONAIS\nContrato adequado para PME: Sim\nCobertura ACP (Acordo dos Contratos Públicos da Organização Mundial do Comércio): Não\n\n27 - IDENTIFICAÇÃO E CONTACTOS DO ÓRGÃO DE RECURSOS ADMINISTRATIVOS\nDesignação: Câmara Municipal de Aveiro\nEndereço: Praça da República\nCódigo postal: 3800-200\nLocalidade: Aveiro\nTelefone: 234406300\nFax: \nEndereço eletrónico: geral@cm-aveiro.pt\nPrazo de interposição do recurso: 5 dias\n\n28 - IDENTIFICAÇÃO DO(S) AUTOR(ES) DE ANÚNCIO\nNome: José Agostinho Ribau Esteves\nCargo: Presidente\n419623436",
    "nipc": "505931192",
    "distrito": "Aveiro",
    "concelho": "Aveiro",
    "freguesia": "União das Freguesias de Glória e Vera Cruz",
    "site": "www.cm-aveiro.pt",
    "email": "geral@cm-aveiro.pt",
    "designacao_contrato": "AQUISIÇÃO DE TRAPICHES PARA OS CAIS 15 E 16 NO CANAL DAS PIRÂMIDES - AVEIRO",
    "descricao": "AQUISIÇÃO DE TRAPICHES PARA OS CAIS 15 E 16 NO CANAL DAS PIRÂMIDES - AVEIRO",
    "preco_base": "200.000,00 EUR",
    "prazo_execucao": "120 DIAS",
    "prazo_apresentacao_propostas": "24-10-2025 17:00",
    "fundos_eu": "Não",
    "plataforma_eletronica": "ACIN",
    "url_procedimento": "https://www.acingov.pt",
    "autor_nome": "José Agostinho Ribau Esteves",
    "autor_cargo": "Presidente"
  },
  {
    "numero_procedimento": "N/A",
    "entidade": "Maiambiente, E. M.",
    "link": "https://diariodarepublica.pt/dr/detalhe/contrato-publico/26477-938846170",
    "detalhes_completos": "1 - IDENTIFICAÇÃO E CONTACTOS DA ENTIDADE ADJUDICANTE\nDesignação da entidade adjudicante: Maiambiente, E. M.\nNIPC: 505060868\nServiço/Órgão/Pessoa de contacto: Unidade de Compras e Aprovisionamento\nEndereço: Rua 5 de Outubro, 359\nCódigo postal: 4475-302\nLocalidade: Maia\nPaís: Portugal\nNUT III: PT11A\nDistrito: Porto\nConcelho: Maia\nFreguesia: Freguesia de Milheirós\nTelefone: 229478130\nFax: 229478139\nEndereço da Entidade (URL): www.maiambiente.pt\nEndereço Eletrónico: daf@maiambiente.pt\neDelivery Gateway (URL): https://www.acingov.pt\nFunção da Organização: Adquirente\nSubfunção da Organização: Organização que recebe as propostas\nNorma jurídica da Entidade Adjudicante: Organismo de direito público\nÁrea de atividade da Autoridade Adjudicante: Serviços públicos das administrações públicas\n\n2 - JORNAL OFICIAL DA UNIÃO EUROPEIA\nO procedimento a que este anúncio diz respeito também é publicitado no Jornal Oficial da União Europeia? Não\n\n3 - AVISO\nModelo de Anúncio: Concurso público\nData de Envio do Anúncio: 08-10-2025\n\n5 - PROCESSO\nTipo de Procedimento: Concurso público\nPreço base do procedimento: Sim\nValor do preço base do procedimento: 510.000,00 EUR\nProcedimento com lotes? Não\n\n6 - OBJETO DO CONTRATO\nNúmero de referência interna: 35/2025\nDesignação do contrato: RENOVAÇÃO/REABILITAÇÃO E ADAPTAÇÃO DO ECOCENTRO DE ÁGUAS SANTAS  ECOCENTRO INTELIGENTE\nDescrição: RENOVAÇÃO/REABILITAÇÃO E ADAPTAÇÃO DO ECOCENTRO DE ÁGUAS SANTAS  ECOCENTRO INTELIGENTE\nTipo de Contrato Principal: Empreitada de Obras Públicas\nTipo de Contrato: Empreitada de Obras Públicas\nClassificação CPV (Vocabulário Comum para os Contratos Públicos)\nObjeto principal\nVocabulário Principal: 45453100\nPreço base s/IVA: 510.000,00 EUR\n\n7 - INDICAÇÕES ADICIONAIS\nO contrato envolve aquisição conjunta (satisfação de várias entidades)? Não\nO contrato é adjudicado por uma central de compras? Não\n\n8 - TÉCNICAS\nO concurso destina-se à celebração de um acordo-quadro? Inexistência de acordo-quadro\nÉ utilizado um leilão eletrónico? Não\nÉ adotada uma fase de negociação? Não\nSistema de Aquisição Dinâmico: Inexistência de sistema de aquisição dinâmico\n\n9 - LOCAL DA EXECUÇÃO DO CONTRATO\nLOCAL DA EXECUÇÃO DO CONTRATO (PROCEDIMENTO)\nPaís: Portugal\nNUT III: PT11A\nLocalidade: Freguesia de Águas Santas - Maia\nDistrito: Porto\nConcelho: Maia\nFreguesia: Freguesia de Águas Santas - Maia\n\n10 - PRAZO DE EXECUÇÃO DO CONTRATO\nPrazo de execução do contrato: 210 DIAS\nPrevisão de renovações: Não\n\n11 - FUNDOS EU\nTêm fundos EU? Sim\n\n12 - DOCUMENTOS DE HABILITAÇÃO\nHabilitação para o exercício da atividade profissional: Não\n\n13 - CONDIÇÕES DE APRESENTAÇÃO\nPlataforma eletrónica utilizada pela entidade adjudicante: ACIN\nURL para Apresentação: https://www.acingov.pt\nAdmissibilidade da apresentação de propostas variantes: Não autorizado\nPrazo para apresentação das propostas: 07-11-2025 18:00\nPrazo durante o qual os concorrentes são obrigados a manter as respetivas propostas: 66 dias a contar do termo do prazo para a apresentação das propostas\nIndicação de Subcontratação na Proposta: Inexistência de indicação de subcontratação\n\n14 - PRESTAÇÃO DE CAUÇÃO\nPrestação de caução: Sim\nPercentagem: 5%\nDescrição da Garantia Exigida: O valor da caução é de 5.00% do preço contratual.\n\n15 - FORNECIMENTO DAS PEÇAS DO CONCURSO, APRESENTAÇÃO DE PEDIDOS DE PARTICIPAÇÃO E APRESENTAÇÃO DAS PROPOSTAS\nLink para acesso às peças do concurso (URL): https://www.acingov.pt/acingovprod/2/zonaPublica/zona_publica_c/donwloadProcedurePiece/OTgzMTcx\n\n20 - OUTROS REQUISITOS\nInformação sobre contratos reservados. Aplica-se a contratos reservados (54º-A)? Não\n\n21 - CRITÉRIO DE ADJUDICAÇÃO\nMultifator: Sim\nFator: \nNome: Outros\nOutro Nome: PG PP- Pontuação Global do Preço Proposto\nPonderação: 50%\nSubfatores: Não\nFator: \nNome: Outros\nOutro Nome: PG IMRR - Pontuação Global do fator de Incorporação de Materiais Recuperados ou Reciclados (IMRR)\nPonderação: 5%\nSubfatores: Não\nFator: \nNome: Outros\nOutro Nome: PG PCO - Pontuação Global do fator do Prazo de Conclusão da Obra\nPonderação: 45%\nSubfatores: Não\n\n24 - CONDIÇÕES DO CONTRATO\nFaturação Eletrónica: Permitido\nObrigação de Subcontratação:\nCódigo da Obrigação de Subcontratação: Não é aplicável nenhuma obrigação de subcontratação.\n\n25 - COMPRA PÚBLICA ESTRATÉGICA\nCompra Pública Estratégica: Inexistência de contratação pública estratégica\n\n26 - INFORMAÇÕES ADICIONAIS\nContrato adequado para PME: Não\nCobertura ACP (Acordo dos Contratos Públicos da Organização Mundial do Comércio): Não\n\n27 - IDENTIFICAÇÃO E CONTACTOS DO ÓRGÃO DE RECURSOS ADMINISTRATIVOS\nDesignação: Conselho de Administração\nEndereço: Rua 5 de Outubro, 359\nCódigo postal: 4475-302\nLocalidade: Maia\nTelefone: 229478130\nFax: 229478139\nEndereço eletrónico: daf@maiambiente.pt\n\n28 - IDENTIFICAÇÃO DO(S) AUTOR(ES) DE ANÚNCIO\nNome: Marta Moreira de Sá Peneda\nCargo: Presidente do Conselho de Administração\n419629674",
    "nipc": "505060868",
    "distrito": "Porto",
    "concelho": "Maia",
    "freguesia": "Freguesia de Milheirós",
    "site": "www.maiambiente.pt",
    "email": "daf@maiambiente.pt",
    "designacao_contrato": "RENOVAÇÃO/REABILITAÇÃO E ADAPTAÇÃO DO ECOCENTRO DE ÁGUAS SANTAS  ECOCENTRO INTELIGENTE",
    "descricao": "RENOVAÇÃO/REABILITAÇÃO E ADAPTAÇÃO DO ECOCENTRO DE ÁGUAS SANTAS  ECOCENTRO INTELIGENTE",
    "preco_base": "510.000,00 EUR",
    "prazo_execucao": "210 DIAS",
    "prazo_apresentacao_propostas": "07-11-2025 18:00",
    "fundos_eu": "Sim",
    "plataforma_eletronica": "ACIN",
    "url_procedimento": "https://www.acingov.pt",
    "autor_nome": "Marta Moreira de Sá Peneda",
    "autor_cargo": "Presidente do Conselho de Administração"
  },
  {
    "numero_procedimento": "N/A",
    "entidade": "LM - Laboratório Nacional do Medicamento",
    "link": "https://diariodarepublica.pt/dr/detalhe/contrato-publico/26479-938846171",
    "detalhes_completos": "1 - IDENTIFICAÇÃO E CONTACTOS DA ENTIDADE ADJUDICANTE\nDesignação da entidade adjudicante: LM - Laboratório Nacional do Medicamento\nNIPC: 600087581\nServiço/Órgão/Pessoa de contacto: Divisão de Compras e Contratação\nEndereço: Avenida Dr. Alfredo Bensaúde\nCódigo postal: 1849-012\nLocalidade: Freguesia de Olivais\nPaís: Portugal\nNUT III: PT170\nDistrito: Lisboa\nConcelho: Lisboa\nFreguesia: Freguesia de Olivais\nTelefone: 218541178\nFax: 218541159\nEndereço da Entidade (URL): https://lm.exercito.pt/\nEndereço Eletrónico: lm.contratacao@exercito.pt\neDelivery Gateway (URL): https://www.acingov.pt\nFunção da Organização: Adquirente\nNorma jurídica da Entidade Adjudicante: Organismo de direito público\nÁrea de atividade da Autoridade Adjudicante: Serviços públicos das administrações públicas\n\n2 - JORNAL OFICIAL DA UNIÃO EUROPEIA\nO procedimento a que este anúncio diz respeito também é publicitado no Jornal Oficial da União Europeia? Não\n\n3 - AVISO\nModelo de Anúncio: Concurso público\nData de Envio do Anúncio: 08-10-2025\n\n5 - PROCESSO\nTipo de Procedimento: Concurso público\nPreço base do procedimento: Sim\nValor do preço base do procedimento: 51.940,00 EUR\nProcedimento com lotes? Sim\nNº Máx. de Lotes Autorizado: 5\nNúmero máximo de lotes que podem ser adjudicados a um concorrente: 5\n\n6 - OBJETO DO CONTRATO\nNúmero de referência interna: LM 249/2025\nDesignação do contrato: LM 249/2025 - Aquisição de produtos de apoio, destinados a satisfazer as necessidades dos Deficientes das Forças Armadas (DFA) da Madeira\nDescrição: LM 249/2025 - Aquisição de produtos de apoio, destinados a satisfazer as necessidades dos Deficientes das Forças Armadas (DFA) da Madeira\nTipo de Contrato Principal: Aquisição de Bens Móveis\nTipo de Contrato: Aquisição de Bens Móveis\nClassificação CPV (Vocabulário Comum para os Contratos Públicos)\nObjeto principal\nVocabulário Principal: 33183200\nPreço base s/IVA: 51.940,00 EUR\nLotes: \nNº: LOT-0001\nDescrição do Lote: 3466 / 142.2024\nPreço base s/IVA: 9.000,00 EUR\nClassificação CPV (Vocabulário Comum para os Contratos Públicos)\nObjeto principal\nVocabulário Principal: 33183200\nNº: LOT-0002\nDescrição do Lote: 3468 / 144.2024\nPreço base s/IVA: 3.000,00 EUR\nClassificação CPV (Vocabulário Comum para os Contratos Públicos)\nObjeto principal\nVocabulário Principal: 33183200\nNº: LOT-0003\nDescrição do Lote: 3469 / 145.2024\nPreço base s/IVA: 4.400,00 EUR\nClassificação CPV (Vocabulário Comum para os Contratos Públicos)\nObjeto principal\nVocabulário Principal: 33183200\nNº: LOT-0004\nDescrição do Lote: 3600 / 205.2024\nPreço base s/IVA: 5.040,00 EUR\nClassificação CPV (Vocabulário Comum para os Contratos Públicos)\nObjeto principal\nVocabulário Principal: 33183200\nNº: LOT-0005\nDescrição do Lote: 3932 / 154.2025\nPreço base s/IVA: 30.500,00 EUR\nClassificação CPV (Vocabulário Comum para os Contratos Públicos)\nObjeto principal\nVocabulário Principal: 33183200\n\n7 - INDICAÇÕES ADICIONAIS\nO contrato envolve aquisição conjunta (satisfação de várias entidades)? Não\nO contrato é adjudicado por uma central de compras? Não\n\n8 - TÉCNICAS\nO concurso destina-se à celebração de um acordo-quadro? Inexistência de acordo-quadro\nÉ utilizado um leilão eletrónico? Não\nÉ adotada uma fase de negociação? Não\nSistema de Aquisição Dinâmico: Inexistência de sistema de aquisição dinâmico\n\n9 - LOCAL DA EXECUÇÃO DO CONTRATO\nLOCAL DA EXECUÇÃO DO CONTRATO (PROCEDIMENTO)\nPaís: Portugal\nNUT III: PT300\nLocalidade: Região Autónoma da Madeira\nDistrito: Região Autónoma da Madeira\nConcelho: Todos\nFreguesia: Todas\nLOCAL DA EXECUÇÃO DO CONTRATO (LOTE)\nIdentificador do Lote: LOT-0001; LOT-0002\nPaís: Portugal\nNUT III: PT300\nLocalidade: 9200-406 Paraíso\nDistrito: Região Autónoma da Madeira\nConcelho: Todos\nFreguesia: Todas\nIdentificador do Lote: LOT-0003\nPaís: Portugal\nNUT III: PT300\nLocalidade: 9020-266 Funchal\nDistrito: Região Autónoma da Madeira\nConcelho: Todos\nFreguesia: Todas\nIdentificador do Lote: LOT-0004; LOT-0005\nPaís: Portugal\nNUT III: PT300\nLocalidade: 9050-205 Funchal\nDistrito: Região Autónoma da Madeira\nConcelho: Todos\nFreguesia: Todas\n\n10 - PRAZO DE EXECUÇÃO DO CONTRATO\nIdentificador do Lote: LOT-0001; LOT-0002; LOT-0003; LOT-0004; LOT-0005\nPrazo de execução do contrato: 13 MESES\nPrevisão de renovações: Não\n\n11 - FUNDOS EU\nIdentificador do Lote: LOT-0001; LOT-0002; LOT-0003; LOT-0004; LOT-0005\nTêm fundos EU? Não\n\n12 - DOCUMENTOS DE HABILITAÇÃO\nHabilitação para o exercício da atividade profissional: Não\n\n13 - CONDIÇÕES DE APRESENTAÇÃO\nPlataforma eletrónica utilizada pela entidade adjudicante: ACIN\nURL para Apresentação: https://www.acingov.pt\nAdmissibilidade da apresentação de propostas variantes: Não autorizado\nPrazo para apresentação das propostas: 14-10-2025 23:59\nPrazo durante o qual os concorrentes são obrigados a manter as respetivas propostas: 90 dias a contar do termo do prazo para a apresentação das propostas\nIndicação de Subcontratação na Proposta: Inexistência de indicação de subcontratação\n\n14 - PRESTAÇÃO DE CAUÇÃO\nPrestação de caução: Não\n\n15 - FORNECIMENTO DAS PEÇAS DO CONCURSO, APRESENTAÇÃO DE PEDIDOS DE PARTICIPAÇÃO E APRESENTAÇÃO DAS PROPOSTAS\nLink para acesso às peças do concurso (URL): https://www.acingov.pt/acingovprod/2/zonaPublica/zona_publica_c/donwloadProcedurePiece/OTg0Mzcz\n\n20 - OUTROS REQUISITOS\nIdentificador do Lote: LOT-0001; LOT-0002; LOT-0003; LOT-0004; LOT-0005\nInformação sobre contratos reservados. Aplica-se a contratos reservados (54º-A)? Não\n\n21 - CRITÉRIO DE ADJUDICAÇÃO\nO Critério de adjudicação é diferenciado por lote? Não\nMultifator: Não\nMonofator:\nNome: Preço\n\n24 - CONDIÇÕES DO CONTRATO\nIdentificador do Lote: LOT-0001; LOT-0002; LOT-0003; LOT-0004; LOT-0005\nFaturação Eletrónica: Permitido\nObrigação de Subcontratação:\nCódigo da Obrigação de Subcontratação: Não é aplicável nenhuma obrigação de subcontratação.\n\n25 - COMPRA PÚBLICA ESTRATÉGICA\nCompra Pública Estratégica: Inexistência de contratação pública estratégica\n\n26 - INFORMAÇÕES ADICIONAIS\nIdentificador do Lote: LOT-0001; LOT-0002; LOT-0003; LOT-0004; LOT-0005\nContrato adequado para PME: Não\nCobertura ACP (Acordo dos Contratos Públicos da Organização Mundial do Comércio): Não\n\n27 - IDENTIFICAÇÃO E CONTACTOS DO ÓRGÃO DE RECURSOS ADMINISTRATIVOS\nDesignação: Laboratório Nacional do Medicamento\nEndereço: Avenida Dr. Alfredo Bensaúde\nCódigo postal: 1849-012\nLocalidade: Freguesia de Olivais\nTelefone: 218541178\nFax: 218541159\nEndereço eletrónico: lm.contratacao@exercito.pt\n\n28 - IDENTIFICAÇÃO DO(S) AUTOR(ES) DE ANÚNCIO\nNome: Eduardo Esperança de Carvalho\nCargo: Diretor da Logística Farmacêutica\n419632735",
    "nipc": "600087581",
    "distrito": "Lisboa",
    "concelho": "Lisboa",
    "freguesia": "Freguesia de Olivais",
    "site": "https://lm.exercito.pt/",
    "email": "lm.contratacao@exercito.pt",
    "designacao_contrato": "LM 249/2025 - Aquisição de produtos de apoio, destinados a satisfazer as necessidades dos Deficientes das Forças Armadas (DFA) da Madeira",
    "descricao": "LM 249/2025 - Aquisição de produtos de apoio, destinados a satisfazer as necessidades dos Deficientes das Forças Armadas (DFA) da Madeira",
    "preco_base": "51.940,00 EUR",
    "prazo_execucao": "13 MESES",
    "prazo_apresentacao_propostas": "14-10-2025 23:59",
    "fundos_eu": "Não",
    "plataforma_eletronica": "ACIN",
    "url_procedimento": "https://www.acingov.pt",
    "autor_nome": "Eduardo Esperança de Carvalho",
    "autor_cargo": "Diretor da Logística Farmacêutica"
  },
  {
    "numero_procedimento": "N/A",
    "entidade": "Município de Albufeira",
    "link": "https://diariodarepublica.pt/dr/detalhe/contrato-publico/26480-938846172",
    "detalhes_completos": "1 - IDENTIFICAÇÃO E CONTACTOS DA ENTIDADE ADJUDICANTE\nDesignação da entidade adjudicante: Município de Albufeira\nNIPC: 503539473\nEndereço: R. Município\nCódigo postal: 8201-863\nLocalidade: Faro\nPaís: Portugal\nNUT III: PT150\nDistrito: Faro\nConcelho: Albufeira\nFreguesia: Freguesia de Albufeira e Olhos de Água\nTelefone: 289 599 500\nEndereço da Entidade (URL): www.cm-albufeira.pt\nEndereço Eletrónico: geral@cm-albufeira.pt\neDelivery Gateway (URL): https://community.vortal.biz/public/\nFunção da Organização: Adquirente\nNorma jurídica da Entidade Adjudicante: Organismo de direito público\nÁrea de atividade da Autoridade Adjudicante: Serviços públicos das administrações públicas\n\n2 - JORNAL OFICIAL DA UNIÃO EUROPEIA\nO procedimento a que este anúncio diz respeito também é publicitado no Jornal Oficial da União Europeia? Sim\n\n3 - AVISO\nModelo de Anúncio: Concurso público\nData de Envio do Anúncio: 06-10-2025\n\n5 - PROCESSO\nTipo de Procedimento: Concurso público\nPreço base do procedimento: Sim\nValor do preço base do procedimento: 230.200,00 EUR\nProcedimento com lotes? Não\n\n6 - OBJETO DO CONTRATO\nNúmero de referência interna: DISU/DAVEGF/2025/463\nDesignação do contrato: Concurso público com publicação no JOUE para aluguer de máquinas e viaturas com operador ou condutor\nDescrição: Aluguer de máquinas e viaturas com operador ou condutor\nOpções: Não\nTipo de Contrato Principal: Aquisição de Serviços\nTipo de Contrato: Aquisição de Serviços\nClassificação CPV (Vocabulário Comum para os Contratos Públicos)\nObjeto principal\nVocabulário Principal: 60182000\nPreço base s/IVA: 230.200,00 EUR\n\n7 - INDICAÇÕES ADICIONAIS\nO contrato envolve aquisição conjunta (satisfação de várias entidades)? Não\nO contrato é adjudicado por uma central de compras? Não\n\n8 - TÉCNICAS\nO concurso destina-se à celebração de um acordo-quadro? Inexistência de acordo-quadro\nÉ utilizado um leilão eletrónico? Não\nÉ adotada uma fase de negociação? Não\nSistema de Aquisição Dinâmico: Inexistência de sistema de aquisição dinâmico\n\n9 - LOCAL DA EXECUÇÃO DO CONTRATO\nLOCAL DA EXECUÇÃO DO CONTRATO (PROCEDIMENTO)\nPaís: Portugal\nNUT III: PT150\nLocalidade: Faro\nDistrito: Faro\nConcelho: Albufeira\nFreguesia: Freguesia de Albufeira e Olhos de Água\n\n10 - PRAZO DE EXECUÇÃO DO CONTRATO\nPrazo de execução do contrato: 2 ANOS\nPrevisão de renovações: Não\n\n11 - FUNDOS EU\nTêm fundos EU? Não\n\n12 - DOCUMENTOS DE HABILITAÇÃO\nHabilitação para o exercício da atividade profissional: Não\n\n13 - CONDIÇÕES DE APRESENTAÇÃO\nPlataforma eletrónica utilizada pela entidade adjudicante: VORTAL\nURL para Apresentação: https://community.vortal.biz/public/\nAdmissibilidade da apresentação de propostas variantes: Não autorizado\nPrazo para apresentação das propostas: 05-11-2025 23:59\nPrazo durante o qual os concorrentes são obrigados a manter as respetivas propostas: 66 dias a contar do termo do prazo para a apresentação das propostas\nApresentação de Catálogo Eletrónico: Não autorizado\nIndicação de Subcontratação na Proposta: Inexistência de indicação de subcontratação\n\n14 - PRESTAÇÃO DE CAUÇÃO\nPrestação de caução: Sim\nPercentagem: 5%\nDescrição da Garantia Exigida: De acordo com a cláusula 14ª do caderno de encargos e artigo 16º do programa de concurso \n\n15 - FORNECIMENTO DAS PEÇAS DO CONCURSO, APRESENTAÇÃO DE PEDIDOS DE PARTICIPAÇÃO E APRESENTAÇÃO DAS PROPOSTAS\nLink para acesso às peças do concurso (URL): https://community.vortal.biz/Public/public-tender-documents/bGIxSlVtcE9FWnRUY2ZOdFZsb0p1OTNCOTVzM21WNjEreDdJZGE2NmgrUlp6UUhWVmtwN0JoR2FycHltNmFIWGhGeUtLVzBXRjNYTnZHeG1Sa0ttQWc9PSllbUwm\n\n20 - OUTROS REQUISITOS\nInformação sobre contratos reservados. Aplica-se a contratos reservados (54º-A)? Não\n\n21 - CRITÉRIO DE ADJUDICAÇÃO\nMultifator: Não\nMonofator:\nNome: Preço\n\n24 - CONDIÇÕES DO CONTRATO\nFaturação Eletrónica: Permitido\nObrigação de Subcontratação:\nCódigo da Obrigação de Subcontratação: Não é aplicável nenhuma obrigação de subcontratação.\n\n25 - COMPRA PÚBLICA ESTRATÉGICA\nCompra Pública Estratégica: Inexistência de contratação pública estratégica\n\n26 - INFORMAÇÕES ADICIONAIS\nContrato adequado para PME: Sim\nCobertura ACP (Acordo dos Contratos Públicos da Organização Mundial do Comércio): Não\n\n27 - IDENTIFICAÇÃO E CONTACTOS DO ÓRGÃO DE RECURSOS ADMINISTRATIVOS\nDesignação: José Carlos Martins Rolo\nEndereço: Rua do Município\nCódigo postal: 8201-863\nLocalidade: Albufeira\nTelefone: +351 289599500\nFax: +351 289599511\nEndereço eletrónico: geral@cm-albufeira.pt\n\n28 - IDENTIFICAÇÃO DO(S) AUTOR(ES) DE ANÚNCIO\nNome: José Carlos Martins Rolo\nCargo: Presidente da Câmara Municipal\n419615685",
    "nipc": "503539473",
    "distrito": "Faro",
    "concelho": "Albufeira",
    "freguesia": "Freguesia de Albufeira e Olhos de Água",
    "site": "www.cm-albufeira.pt",
    "email": "geral@cm-albufeira.pt",
    "designacao_contrato": "Concurso público com publicação no JOUE para aluguer de máquinas e viaturas com operador ou condutor",
    "descricao": "Aluguer de máquinas e viaturas com operador ou condutor",
    "preco_base": "230.200,00 EUR",
    "prazo_execucao": "2 ANOS",
    "prazo_apresentacao_propostas": "05-11-2025 23:59",
    "fundos_eu": "Não",
    "plataforma_eletronica": "VORTAL",
    "url_procedimento": "https://community.vortal.biz/public/",
    "autor_nome": "José Carlos Martins Rolo",
    "autor_cargo": "Presidente da Câmara Municipal"
  },
  {
    "numero_procedimento": "N/A",
    "entidade": "Município de Albufeira",
    "link": "https://diariodarepublica.pt/dr/detalhe/contrato-publico/26481-938846173",
    "detalhes_completos": "1 - IDENTIFICAÇÃO E CONTACTOS DA ENTIDADE ADJUDICANTE\nDesignação da entidade adjudicante: Município de Albufeira\nNIPC: 503539473\nEndereço: R. Município\nCódigo postal: 8201-863\nLocalidade: Faro\nPaís: Portugal\nNUT III: PT150\nDistrito: Faro\nConcelho: Albufeira\nFreguesia: Freguesia de Albufeira e Olhos de Água\nTelefone: 289 599 500\nEndereço da Entidade (URL): www.cm-albufeira.pt\nEndereço Eletrónico: geral@cm-albufeira.pt\neDelivery Gateway (URL): https://community.vortal.biz/public/\nFunção da Organização: Adquirente\nNorma jurídica da Entidade Adjudicante: Organismo de direito público\nÁrea de atividade da Autoridade Adjudicante: Serviços públicos das administrações públicas\n\n2 - JORNAL OFICIAL DA UNIÃO EUROPEIA\nO procedimento a que este anúncio diz respeito também é publicitado no Jornal Oficial da União Europeia? Sim\n\n3 - AVISO\nModelo de Anúncio: Concurso público\nData de Envio do Anúncio: 06-10-2025\n\n5 - PROCESSO\nTipo de Procedimento: Concurso público\nPreço base do procedimento: Sim\nValor do preço base do procedimento: 450.515,00 EUR\nProcedimento com lotes? Não\n\n6 - OBJETO DO CONTRATO\nNúmero de referência interna: DISU/DAVEGF/2025/465\nDesignação do contrato: CONCURSO PÚBLICO PARA PRESTAÇÃO DE SERVIÇOS DE PINTURA NO PAVIMENTO NO MUNICÍPIO DE ALBUFEIRA\nDescrição: PRESTAÇÃO DE SERVIÇOS DE PINTURA NO PAVIMENTO NO MUNICÍPIO DE ALBUFEIRA\nOpções: Não\nTipo de Contrato Principal: Aquisição de Serviços\nTipo de Contrato: Aquisição de Serviços\nClassificação CPV (Vocabulário Comum para os Contratos Públicos)\nObjeto principal\nVocabulário Principal: 50200000\nPreço base s/IVA: 450.515,00 EUR\n\n7 - INDICAÇÕES ADICIONAIS\nO contrato envolve aquisição conjunta (satisfação de várias entidades)? Não\nO contrato é adjudicado por uma central de compras? Não\n\n8 - TÉCNICAS\nO concurso destina-se à celebração de um acordo-quadro? Inexistência de acordo-quadro\nÉ utilizado um leilão eletrónico? Não\nÉ adotada uma fase de negociação? Não\nSistema de Aquisição Dinâmico: Inexistência de sistema de aquisição dinâmico\n\n9 - LOCAL DA EXECUÇÃO DO CONTRATO\nLOCAL DA EXECUÇÃO DO CONTRATO (PROCEDIMENTO)\nPaís: Portugal\nNUT III: PT150\nLocalidade: Faro\nDistrito: Faro\nConcelho: Albufeira\nFreguesia: Freguesia de Albufeira e Olhos de Água\n\n10 - PRAZO DE EXECUÇÃO DO CONTRATO\nPrazo de execução do contrato: 3 ANOS\nPrevisão de renovações: Não\n\n11 - FUNDOS EU\nTêm fundos EU? Não\n\n12 - DOCUMENTOS DE HABILITAÇÃO\nHabilitação para o exercício da atividade profissional: Não\n\n13 - CONDIÇÕES DE APRESENTAÇÃO\nPlataforma eletrónica utilizada pela entidade adjudicante: VORTAL\nURL para Apresentação: https://community.vortal.biz/public/\nAdmissibilidade da apresentação de propostas variantes: Não autorizado\nPrazo para apresentação das propostas: 05-11-2025 23:59\nPrazo durante o qual os concorrentes são obrigados a manter as respetivas propostas: 66 dias a contar do termo do prazo para a apresentação das propostas\nApresentação de Catálogo Eletrónico: Não autorizado\nIndicação de Subcontratação na Proposta: Inexistência de indicação de subcontratação\n\n14 - PRESTAÇÃO DE CAUÇÃO\nPrestação de caução: Não\n\n15 - FORNECIMENTO DAS PEÇAS DO CONCURSO, APRESENTAÇÃO DE PEDIDOS DE PARTICIPAÇÃO E APRESENTAÇÃO DAS PROPOSTAS\nLink para acesso às peças do concurso (URL): https://community.vortal.biz/Public/public-tender-documents/VzBsSzRCM3lFUGN2bjQ3ZnNIb2U4bExPOGFVNFlQdHIvOEVBQUVKR0dUcWQ1ZFY0RFQ1V3Q4YWRRQXZEVG41aDBFSDV0RWNaT0RNTk02MlkxMy9GcEE9PTZASzFs\n\n20 - OUTROS REQUISITOS\nInformação sobre contratos reservados. Aplica-se a contratos reservados (54º-A)? Não\n\n21 - CRITÉRIO DE ADJUDICAÇÃO\nMultifator: Não\nMonofator:\nNome: Preço\n\n24 - CONDIÇÕES DO CONTRATO\nFaturação Eletrónica: Permitido\nObrigação de Subcontratação:\nCódigo da Obrigação de Subcontratação: Não é aplicável nenhuma obrigação de subcontratação.\n\n25 - COMPRA PÚBLICA ESTRATÉGICA\nCompra Pública Estratégica: Inexistência de contratação pública estratégica\n\n26 - INFORMAÇÕES ADICIONAIS\nContrato adequado para PME: Sim\nCobertura ACP (Acordo dos Contratos Públicos da Organização Mundial do Comércio): Não\n\n27 - IDENTIFICAÇÃO E CONTACTOS DO ÓRGÃO DE RECURSOS ADMINISTRATIVOS\nDesignação: José Carlos Martins Rolo\nEndereço: R. do Município.\nCódigo postal: 8201-863\nLocalidade: Albufeira\nTelefone: +351 289599500\nFax: +351 289589558\nEndereço eletrónico: geral@cm-albufeira.pt\n\n28 - IDENTIFICAÇÃO DO(S) AUTOR(ES) DE ANÚNCIO\nNome: José Carlos Martins Rolo\nCargo: Presidente da Câmara Municipal de Albufeira\n419615441",
    "nipc": "503539473",
    "distrito": "Faro",
    "concelho": "Albufeira",
    "freguesia": "Freguesia de Albufeira e Olhos de Água",
    "site": "www.cm-albufeira.pt",
    "email": "geral@cm-albufeira.pt",
    "designacao_contrato": "CONCURSO PÚBLICO PARA PRESTAÇÃO DE SERVIÇOS DE PINTURA NO PAVIMENTO NO MUNICÍPIO DE ALBUFEIRA",
    "descricao": "PRESTAÇÃO DE SERVIÇOS DE PINTURA NO PAVIMENTO NO MUNICÍPIO DE ALBUFEIRA",
    "preco_base": "450.515,00 EUR",
    "prazo_execucao": "3 ANOS",
    "prazo_apresentacao_propostas": "05-11-2025 23:59",
    "fundos_eu": "Não",
    "plataforma_eletronica": "VORTAL",
    "url_procedimento": "https://community.vortal.biz/public/",
    "autor_nome": "José Carlos Martins Rolo",
    "autor_cargo": "Presidente da Câmara Municipal de Albufeira"
  },
  {
    "numero_procedimento": "N/A",
    "entidade": "Município de Aveiro",
    "link": "https://diariodarepublica.pt/dr/detalhe/contrato-publico/26482-938846174",
    "detalhes_completos": "1 - IDENTIFICAÇÃO E CONTACTOS DA ENTIDADE ADJUDICANTE\nDesignação da entidade adjudicante: Município de Aveiro\nNIPC: 505931192\nServiço/Órgão/Pessoa de contacto: obrasmunicipais@cm-aveiro.pt\nEndereço: Praça da Republica\nCódigo postal: 3810-156\nLocalidade: Aveiro\nPaís: Portugal\nNUT III: PT16D\nDistrito: Aveiro\nConcelho: Aveiro\nFreguesia: União das Freguesias de Glória e Vera Cruz\nTelefone: 230406300\nFax: 234406301\nEndereço da Entidade (URL): www.cm-aveiro.pt\nEndereço Eletrónico: geral@cm-aveiro.pt\neDelivery Gateway (URL): https://www.acingov.pt\nFunção da Organização: Adquirente\nNorma jurídica da Entidade Adjudicante: Organismo de direito público\nÁrea de atividade da Autoridade Adjudicante: Serviços públicos das administrações públicas\n\n2 - JORNAL OFICIAL DA UNIÃO EUROPEIA\nO procedimento a que este anúncio diz respeito também é publicitado no Jornal Oficial da União Europeia? Sim\n\n3 - AVISO\nModelo de Anúncio: Concurso público\nData de Envio do Anúncio: 06-10-2025\n\n5 - PROCESSO\nTipo de Procedimento: Concurso público\nPreço base do procedimento: Sim\nValor do preço base do procedimento: 6.503.630,39 EUR\nProcedimento com lotes? Não\n\n6 - OBJETO DO CONTRATO\nNúmero de referência interna: OM/CP/41/25\nDesignação do contrato: Reabilitação do Conservatório de Música de Aveiro Calouste Gulbenkian\nDescrição: Reabilitação do Conservatório de Música de Aveiro Calouste Gulbenkian\nOpções: Não\nTipo de Contrato Principal: Empreitada de Obras Públicas\nTipo de Contrato: Empreitada de Obras Públicas\nClassificação CPV (Vocabulário Comum para os Contratos Públicos)\nObjeto principal\nVocabulário Principal: 45453100\nPreço base s/IVA: 6.503.630,39 EUR\n\n7 - INDICAÇÕES ADICIONAIS\nO contrato envolve aquisição conjunta (satisfação de várias entidades)? Não\nO contrato é adjudicado por uma central de compras? Não\n\n8 - TÉCNICAS\nO concurso destina-se à celebração de um acordo-quadro? Inexistência de acordo-quadro\nÉ utilizado um leilão eletrónico? Não\nÉ adotada uma fase de negociação? Não\nSistema de Aquisição Dinâmico: Inexistência de sistema de aquisição dinâmico\n\n9 - LOCAL DA EXECUÇÃO DO CONTRATO\nLOCAL DA EXECUÇÃO DO CONTRATO (PROCEDIMENTO)\nPaís: Portugal\nNUT III: PT16D\nLocalidade: União das Freguesias de Glória e Vera Cruz\nDistrito: Aveiro\nConcelho: Aveiro\nFreguesia: União das Freguesias de Glória e Vera Cruz\n\n10 - PRAZO DE EXECUÇÃO DO CONTRATO\nPrazo de execução do contrato: 660 DIAS\nPrevisão de renovações: Não\n\n11 - FUNDOS EU\nTêm fundos EU? Não\n\n12 - DOCUMENTOS DE HABILITAÇÃO\nHabilitação para o exercício da atividade profissional: Sim\nTipo: Alvará\nDescrição: 1.ª Subcategoria da 1.ª Categoria, de classe correspondente ao valor global da proposta;\n2.ª, 4.ª , 5ª, 6ª e 8.ª Subcategorias da 1.ª Categoria, de classe correspondente ao valor parcial da proposta;\n1.ª, 9.ª e 10.ª  e 12º Subcategorias da 4.ª Categoria, de classe correspondente ao valor parcial da proposta;\n1.ª, 2.ª, 11.ª e 12.ª Subcategorias da 5.ª Categoria, de classe correspondente ao valor parcial da proposta;\n\n13 - CONDIÇÕES DE APRESENTAÇÃO\nPlataforma eletrónica utilizada pela entidade adjudicante: ACIN\nURL para Apresentação: https://www.acingov.pt\nAdmissibilidade da apresentação de propostas variantes: Não autorizado\nPrazo para apresentação das propostas: 08-11-2025 17:00\nPrazo durante o qual os concorrentes são obrigados a manter as respetivas propostas: 120 dias a contar do termo do prazo para a apresentação das propostas\nApresentação de Catálogo Eletrónico: Permitido\nIndicação de Subcontratação na Proposta: Inexistência de indicação de subcontratação\n\n14 - PRESTAÇÃO DE CAUÇÃO\nPrestação de caução: Sim\nPercentagem: 5%\nDescrição da Garantia Exigida: O valor da caução é de 5.00% do preço contratual.\n\n15 - FORNECIMENTO DAS PEÇAS DO CONCURSO, APRESENTAÇÃO DE PEDIDOS DE PARTICIPAÇÃO E APRESENTAÇÃO DAS PROPOSTAS\nLink para acesso às peças do concurso (URL): https://www.acingov.pt/acingovprod/2/zonaPublica/zona_publica_c/donwloadProcedurePiece/OTgyNDMx\n\n20 - OUTROS REQUISITOS\nInformação sobre contratos reservados. Aplica-se a contratos reservados (54º-A)? Não\n\n21 - CRITÉRIO DE ADJUDICAÇÃO\nMultifator: Não\nMonofator:\nNome: Preço\n\n24 - CONDIÇÕES DO CONTRATO\nFaturação Eletrónica: Necessário\nObrigação de Subcontratação:\nCódigo da Obrigação de Subcontratação: Não é aplicável nenhuma obrigação de subcontratação.\n\n25 - COMPRA PÚBLICA ESTRATÉGICA\nCompra Pública Estratégica: Inexistência de contratação pública estratégica\n\n26 - INFORMAÇÕES ADICIONAIS\nContrato adequado para PME: Sim\nCobertura ACP (Acordo dos Contratos Públicos da Organização Mundial do Comércio): Não\n\n27 - IDENTIFICAÇÃO E CONTACTOS DO ÓRGÃO DE RECURSOS ADMINISTRATIVOS\nDesignação: Câmara Municipal de Aveiro\nEndereço: Praça da República\nCódigo postal: 3810-156\nLocalidade: Aveiro\nTelefone: 351234406300\nFax: \nEndereço eletrónico: geral@cm-aveiro.pt\nPrazo de interposição do recurso: 5 dias\n\n28 - IDENTIFICAÇÃO DO(S) AUTOR(ES) DE ANÚNCIO\nNome: José Agostinho Ribau Esteves\nCargo: Presidente\n419609001",
    "nipc": "505931192",
    "distrito": "Aveiro",
    "concelho": "Aveiro",
    "freguesia": "União das Freguesias de Glória e Vera Cruz",
    "site": "www.cm-aveiro.pt",
    "email": "geral@cm-aveiro.pt",
    "designacao_contrato": "Reabilitação do Conservatório de Música de Aveiro Calouste Gulbenkian",
    "descricao": "Reabilitação do Conservatório de Música de Aveiro Calouste Gulbenkian",
    "preco_base": "6.503.630,39 EUR",
    "prazo_execucao": "660 DIAS",
    "prazo_apresentacao_propostas": "08-11-2025 17:00",
    "fundos_eu": "Não",
    "plataforma_eletronica": "ACIN",
    "url_procedimento": "https://www.acingov.pt",
    "autor_nome": "José Agostinho Ribau Esteves",
    "autor_cargo": "Presidente"
  },
  {
    "numero_procedimento": "N/A",
    "entidade": "Município do Montijo",
    "link": "https://diariodarepublica.pt/dr/detalhe/contrato-publico/26476-938853433",
    "detalhes_completos": "1 - IDENTIFICAÇÃO E CONTACTOS DA ENTIDADE ADJUDICANTE\nDesignação da entidade adjudicante: Município do Montijo\nNIPC: 502834846\nEndereço: Rua Manuel Neves Nunes de Almeida\nCódigo postal: 2870-352\nLocalidade: Setúbal\nPaís: Portugal\nNUT III: PT170\nDistrito: Setúbal\nConcelho: Montijo\nFreguesia: Todas\nTelefone: 212327600\nFax: 212327600\nEndereço da Entidade (URL): www.mun-montijo.pt\nEndereço Eletrónico: geral@mun-montijo.pt\neDelivery Gateway (URL): https://community.vortal.biz/public/\nFunção da Organização: Adquirente\nNorma jurídica da Entidade Adjudicante: Autoridade local\nÁrea de atividade da Autoridade Adjudicante: Serviços públicos das administrações públicas\n\n2 - JORNAL OFICIAL DA UNIÃO EUROPEIA\nO procedimento a que este anúncio diz respeito também é publicitado no Jornal Oficial da União Europeia? Sim\n\n3 - AVISO\nModelo de Anúncio: Concurso público\nData de Envio do Anúncio: 06-10-2025\n\n5 - PROCESSO\nTipo de Procedimento: Concurso público\nPreço base do procedimento: Sim\nValor do preço base do procedimento: 99.000,00 EUR\nProcedimento com lotes? Não\n\n6 - OBJETO DO CONTRATO\nNúmero de referência interna: 248/2025\nDesignação do contrato: Aquisição de serviços para a \"Gestão, fiscalização e coordenação de segurança da empreitada de construção do Centro Escolar de Pegões\"\nDescrição: Aquisição de serviços para a \"Gestão, fiscalização e coordenação de segurança da empreitada de construção do Centro Escolar de Pegões\"\nOpções: Não\nTipo de Contrato Principal: Aquisição de Serviços\nTipo de Contrato: Aquisição de Serviços\nClassificação CPV (Vocabulário Comum para os Contratos Públicos)\nObjeto principal\nVocabulário Principal: 71520000\nPreço base s/IVA: 99.000,00 EUR\n\n7 - INDICAÇÕES ADICIONAIS\nO contrato envolve aquisição conjunta (satisfação de várias entidades)? Não\nO contrato é adjudicado por uma central de compras? Não\n\n8 - TÉCNICAS\nO concurso destina-se à celebração de um acordo-quadro? Inexistência de acordo-quadro\nÉ utilizado um leilão eletrónico? Não\nÉ adotada uma fase de negociação? Não\nSistema de Aquisição Dinâmico: Inexistência de sistema de aquisição dinâmico\n\n9 - LOCAL DA EXECUÇÃO DO CONTRATO\nLOCAL DA EXECUÇÃO DO CONTRATO (PROCEDIMENTO)\nPaís: Portugal\nNUT III: PT170\nLocalidade: Setúbal\nDistrito: Setúbal\nConcelho: Montijo\nFreguesia: União das Freguesias de Montijo e Afonsoeiro\n\n10 - PRAZO DE EXECUÇÃO DO CONTRATO\nPrazo de execução do contrato: 570 DIAS\nPrevisão de renovações: Não\n\n11 - FUNDOS EU\nTêm fundos EU? Não\n\n12 - DOCUMENTOS DE HABILITAÇÃO\nHabilitação para o exercício da atividade profissional: Não\n\n13 - CONDIÇÕES DE APRESENTAÇÃO\nPlataforma eletrónica utilizada pela entidade adjudicante: VORTAL\nURL para Apresentação: https://community.vortal.biz/public/\nAdmissibilidade da apresentação de propostas variantes: Não autorizado\nPrazo para apresentação das propostas: 05-11-2025 18:00\nPrazo durante o qual os concorrentes são obrigados a manter as respetivas propostas: 120 dias a contar do termo do prazo para a apresentação das propostas\nApresentação de Catálogo Eletrónico: Não autorizado\nIndicação de Subcontratação na Proposta: Inexistência de indicação de subcontratação\n\n14 - PRESTAÇÃO DE CAUÇÃO\nPrestação de caução: Não\n\n15 - FORNECIMENTO DAS PEÇAS DO CONCURSO, APRESENTAÇÃO DE PEDIDOS DE PARTICIPAÇÃO E APRESENTAÇÃO DAS PROPOSTAS\nLink para acesso às peças do concurso (URL): https://community.vortal.biz/Public/public-tender-documents/RE5VQTRIS3dvNkI0NzBMVXN1dWhZaS94cWJzV2ZGSnpMaTBSc1B0S0pMRldvV2NNMlQycG9YRC9PbENDU1R6b0s1UkZER09vbi9DdWNOckora2l1bGc9PTJaKVNu\n\n20 - OUTROS REQUISITOS\nInformação sobre contratos reservados. Aplica-se a contratos reservados (54º-A)? Não\n\n21 - CRITÉRIO DE ADJUDICAÇÃO\nMultifator: Não\nMonofator:\nNome: Preço\n\n24 - CONDIÇÕES DO CONTRATO\nFaturação Eletrónica: Permitido\nObrigação de Subcontratação:\nCódigo da Obrigação de Subcontratação: Não é aplicável nenhuma obrigação de subcontratação.\n\n25 - COMPRA PÚBLICA ESTRATÉGICA\nCompra Pública Estratégica: Inexistência de contratação pública estratégica\n\n26 - INFORMAÇÕES ADICIONAIS\nContrato adequado para PME: Sim\nCobertura ACP (Acordo dos Contratos Públicos da Organização Mundial do Comércio): Não\n\n27 - IDENTIFICAÇÃO E CONTACTOS DO ÓRGÃO DE RECURSOS ADMINISTRATIVOS\nDesignação: Município de Montijo\nEndereço: Rua Manuel Neves Nunes de Almeida - P.Concelho\nCódigo postal: 2870-352\nLocalidade: Montijo\nTelefone: +351 212327600\nFax: +351 000000000\nEndereço eletrónico: dgfp.contratacaopublica@mun-montijo.pt\n\n28 - IDENTIFICAÇÃO DO(S) AUTOR(ES) DE ANÚNCIO\nNome: Maria Clara de Oliveira da Silva\nCargo: Presidente da Câmara Municipal de Montijo\n419605632",
    "nipc": "502834846",
    "distrito": "Setúbal",
    "concelho": "Montijo",
    "freguesia": "Todas",
    "site": "www.mun-montijo.pt",
    "email": "geral@mun-montijo.pt",
    "designacao_contrato": "Aquisição de serviços para a \"Gestão, fiscalização e coordenação de segurança da empreitada de construção do Centro Escolar de Pegões\"",
    "descricao": "Aquisição de serviços para a \"Gestão, fiscalização e coordenação de segurança da empreitada de construção do Centro Escolar de Pegões\"",
    "preco_base": "99.000,00 EUR",
    "prazo_execucao": "570 DIAS",
    "prazo_apresentacao_propostas": "05-11-2025 18:00",
    "fundos_eu": "Não",
    "plataforma_eletronica": "VORTAL",
    "url_procedimento": "https://community.vortal.biz/public/",
    "autor_nome": "Maria Clara de Oliveira da Silva",
    "autor_cargo": "Presidente da Câmara Municipal de Montijo"
  },
  {
    "numero_procedimento": "N/A",
    "entidade": "EMAC - Empresa Municipal de Ambiente de Cascais, E. M., S. A.",
    "link": "https://diariodarepublica.pt/dr/detalhe/contrato-publico/26478-938853434",
    "detalhes_completos": "1 - IDENTIFICAÇÃO E CONTACTOS DA ENTIDADE ADJUDICANTE\nDesignação da entidade adjudicante: EMAC - Empresa Municipal de Ambiente de Cascais, E. M., S. A.\nNIPC: 507396081\nServiço/Órgão/Pessoa de contacto: Departamento Financeiro\nEndereço: Complexo Multiserviços, Estrada de Manique, nº 1830, Alcoitão,\nCódigo postal: 2645-138\nLocalidade: Alcabideche\nPaís: Portugal\nNUT III: PT170\nDistrito: Lisboa\nConcelho: Cascais\nFreguesia: Todas\nTelefone: +351214604249\nFax: +351214604249\nEndereço da Entidade (URL): https://ambiente.cascais.pt\nEndereço Eletrónico: geral@cascaisambiente.pt\neDelivery Gateway (URL): https://www.acingov.pt\nFunção da Organização: Adquirente\nNorma jurídica da Entidade Adjudicante: Empresa pública, controlada por uma autoridade local\nÁrea de atividade da Autoridade Adjudicante: Serviços públicos das administrações públicas\n\n2 - JORNAL OFICIAL DA UNIÃO EUROPEIA\nO procedimento a que este anúncio diz respeito também é publicitado no Jornal Oficial da União Europeia? Sim\n\n3 - AVISO\nModelo de Anúncio: Concurso público\nData de Envio do Anúncio: 06-10-2025\n\n5 - PROCESSO\nTipo de Procedimento: Concurso público\nPreço base do procedimento: Sim\nValor do preço base do procedimento: 380.000,00 EUR\nProcedimento com lotes? Não\n\n6 - OBJETO DO CONTRATO\nNúmero de referência interna: CPUB011DTEDGA2025\nDesignação do contrato: CPUB011DTEDGA2025 - Aquisição de peças e componentes e manutenção de equipamentos\nDescrição: CPUB011DTEDGA2025 - Aquisição de peças e componentes e manutenção de equipamentos\nOpções: Não\nTipo de Contrato Principal: Aquisição de Bens Móveis\nTipo de Contrato: Aquisição de Bens Móveis; Aquisição de Serviços\nClassificação CPV (Vocabulário Comum para os Contratos Públicos)\nObjeto principal\nVocabulário Principal: 42670000\nPreço base s/IVA: 152.000,00 EUR\nObjeto Complementar\nVocabulário Principal: 50100000\nPreço base s/IVA: 95.000,00 EUR\nObjeto Complementar\nVocabulário Principal: 34300000\nPreço base s/IVA: 95.000,00 EUR\nObjeto Complementar\nVocabulário Principal: 34913000\nPreço base s/IVA: 19.000,00 EUR\nObjeto Complementar\nVocabulário Principal: 42600000\nPreço base s/IVA: 19.000,00 EUR\n\n7 - INDICAÇÕES ADICIONAIS\nO contrato envolve aquisição conjunta (satisfação de várias entidades)? Não\nO contrato é adjudicado por uma central de compras? Não\n\n8 - TÉCNICAS\nO concurso destina-se à celebração de um acordo-quadro? Inexistência de acordo-quadro\nÉ utilizado um leilão eletrónico? Não\nÉ adotada uma fase de negociação? Não\nSistema de Aquisição Dinâmico: Inexistência de sistema de aquisição dinâmico\n\n9 - LOCAL DA EXECUÇÃO DO CONTRATO\nLOCAL DA EXECUÇÃO DO CONTRATO (PROCEDIMENTO)\nPaís: Portugal\nNUT III: PT170\nLocalidade: Cascais\nDistrito: Lisboa\nConcelho: Cascais\nFreguesia: Todas\n\n10 - PRAZO DE EXECUÇÃO DO CONTRATO\nPrazo de execução do contrato: 12 MESES\nPrevisão de renovações: Sim\nIndicar número máximo de renovações: 2\nPrazo de renovações diferente do prazo inicial: Não\n\n11 - FUNDOS EU\nTêm fundos EU? Não\n\n12 - DOCUMENTOS DE HABILITAÇÃO\nHabilitação para o exercício da atividade profissional: Não\n\n13 - CONDIÇÕES DE APRESENTAÇÃO\nPlataforma eletrónica utilizada pela entidade adjudicante: ACIN\nURL para Apresentação: https://www.acingov.pt\nAdmissibilidade da apresentação de propostas variantes: Não autorizado\nPrazo para apresentação das propostas: 05-11-2025 23:59\nPrazo durante o qual os concorrentes são obrigados a manter as respetivas propostas: 120 dias a contar do termo do prazo para a apresentação das propostas\nApresentação de Catálogo Eletrónico: Não autorizado\nIndicação de Subcontratação na Proposta: Inexistência de indicação de subcontratação\n\n14 - PRESTAÇÃO DE CAUÇÃO\nPrestação de caução: Não\n\n15 - FORNECIMENTO DAS PEÇAS DO CONCURSO, APRESENTAÇÃO DE PEDIDOS DE PARTICIPAÇÃO E APRESENTAÇÃO DAS PROPOSTAS\nLink para acesso às peças do concurso (URL): https://www.acingov.pt/acingovprod/2/zonaPublica/zona_publica_c/donwloadProcedurePiece/OTgyOTc4\n\n20 - OUTROS REQUISITOS\nInformação sobre contratos reservados. Aplica-se a contratos reservados (54º-A)? Não\n\n21 - CRITÉRIO DE ADJUDICAÇÃO\nMultifator: Sim\nFator: \nNome: Outros\nOutro Nome: MO - O preço da mão-de-obra / hora\nPonderação: 30%\nSubfatores: Não\nFator: \nNome: Outros\nOutro Nome: FC - Fornecimento de Componentes Diversos\nPonderação: 50%\nSubfatores: Não\nFator: \nNome: Outros\nOutro Nome: GR - Garantia das reparações incluindo as peças e acessórios\nPonderação: 5%\nSubfatores: Não\nFator: \nNome: Outros\nOutro Nome: DRO  Distância Rodoviária à Oficina\nPonderação: 5%\nSubfatores: Não\nFator: \nNome: Outros\nOutro Nome: DM  Desconto médio sobre a tabela de preços das peças (novas, multimarca/linha branca e de origem)\nPonderação: 10%\nSubfatores: Não\n\n24 - CONDIÇÕES DO CONTRATO\nFaturação Eletrónica: Necessário\nObrigação de Subcontratação:\nCódigo da Obrigação de Subcontratação: Não é aplicável nenhuma obrigação de subcontratação.\n\n25 - COMPRA PÚBLICA ESTRATÉGICA\nCompra Pública Estratégica: Inexistência de contratação pública estratégica\n\n26 - INFORMAÇÕES ADICIONAIS\nContrato adequado para PME: Sim\nCobertura ACP (Acordo dos Contratos Públicos da Organização Mundial do Comércio): Não\n\n27 - IDENTIFICAÇÃO E CONTACTOS DO ÓRGÃO DE RECURSOS ADMINISTRATIVOS\nDesignação: EMAC - Empresa Municipal de Ambiente de Cascais, EM, SA\nEndereço: Complexo Multiserviços, Estrada de Manique, nº 1830, Alcoitão,\nCódigo postal: 2645-138\nLocalidade: Alcabideche\nTelefone: 351214604249\nFax: 351214604249\nEndereço eletrónico: geral@cascaisambiente.pt\nPrazo de interposição do recurso: 30 dias\n\n28 - IDENTIFICAÇÃO DO(S) AUTOR(ES) DE ANÚNCIO\nNome: Ana Maria de Bessa e Meneses Machado\nCargo: Unidade de Compras e Contratação\n419618147",
    "nipc": "507396081",
    "distrito": "Lisboa",
    "concelho": "Cascais",
    "freguesia": "Todas",
    "site": "https://ambiente.cascais.pt",
    "email": "geral@cascaisambiente.pt",
    "designacao_contrato": "CPUB011DTEDGA2025 - Aquisição de peças e componentes e manutenção de equipamentos",
    "descricao": "CPUB011DTEDGA2025 - Aquisição de peças e componentes e manutenção de equipamentos",
    "preco_base": "152.000,00 EUR",
    "prazo_execucao": "12 MESES",
    "prazo_apresentacao_propostas": "05-11-2025 23:59",
    "fundos_eu": "Não",
    "plataforma_eletronica": "ACIN",
    "url_procedimento": "https://www.acingov.pt",
    "autor_nome": "Ana Maria de Bessa e Meneses Machado",
    "autor_cargo": "Unidade de Compras e Contratação"
  },
  {
    "numero_procedimento": "N/A",
    "entidade": "Unidade Local de Saúde de Santo António, E. P. E.",
    "link": "https://diariodarepublica.pt/dr/detalhe/contrato-publico/26489-938853436",
    "detalhes_completos": "1 - IDENTIFICAÇÃO E CONTACTOS DA ENTIDADE ADJUDICANTE\nDesignação da entidade adjudicante: Unidade Local de Saúde de Santo António, E. P. E.\nNIPC: 517392259\nEndereço: Largo Prof. Abel Salazar\nCódigo postal: 4099-001\nLocalidade: Área Metropolitana do Porto\nPaís: Portugal\nNUT III: PT11A\nDistrito: Porto\nConcelho: Porto\nFreguesia: Todas\nTelefone: 222077500\nFax: 223320318\nEndereço da Entidade (URL): www.hgsa.pt\nEndereço Eletrónico: helpdesk.b-on@hgsa.min-saude.pt\neDelivery Gateway (URL): https://community.vortal.biz/public/\nFunção da Organização: Adquirente\nNorma jurídica da Entidade Adjudicante: Empresa pública\nÁrea de atividade da Autoridade Adjudicante: Saúde\n\n2 - JORNAL OFICIAL DA UNIÃO EUROPEIA\nO procedimento a que este anúncio diz respeito também é publicitado no Jornal Oficial da União Europeia? Sim\n\n3 - AVISO\nModelo de Anúncio: Concurso público\nData de Envio do Anúncio: 06-10-2025\n\n5 - PROCESSO\nTipo de Procedimento: Concurso público\nPreço base do procedimento: Sim\nValor do preço base do procedimento: 646.140,00 EUR\nProcedimento com lotes? Não\n\n6 - OBJETO DO CONTRATO\nNúmero de referência interna: CI/1253/2025\nDesignação do contrato: Serviços de internamento hospitalar externo de doentes de medicina interna com doença aguda ou agudização de doença crónica\nDescrição: Concurso Público Internacional n.º 1253/2025: contratação de serviços de internamento hospitalar externo de doentes de medicina interna com doença aguda ou agudização de doença crónica\nOpções: Não\nTipo de Contrato Principal: Aquisição de Serviços\nTipo de Contrato: Aquisição de Serviços\nClassificação CPV (Vocabulário Comum para os Contratos Públicos)\nObjeto principal\nVocabulário Principal: 85144000\nPreço base s/IVA: 646.140,00 EUR\n\n7 - INDICAÇÕES ADICIONAIS\nO contrato envolve aquisição conjunta (satisfação de várias entidades)? Não\nO contrato é adjudicado por uma central de compras? Não\n\n8 - TÉCNICAS\nO concurso destina-se à celebração de um acordo-quadro? Inexistência de acordo-quadro\nÉ utilizado um leilão eletrónico? Não\nÉ adotada uma fase de negociação? Não\nSistema de Aquisição Dinâmico: Inexistência de sistema de aquisição dinâmico\n\n9 - LOCAL DA EXECUÇÃO DO CONTRATO\nLOCAL DA EXECUÇÃO DO CONTRATO (PROCEDIMENTO)\nPaís: Portugal\nNUT III: PT11A\nLocalidade: Área Metropolitana do Porto\nDistrito: Porto\nConcelho: Porto\nFreguesia: Todas\n\n10 - PRAZO DE EXECUÇÃO DO CONTRATO\nPrazo de execução do contrato: 7 MESES\nPrevisão de renovações: Não\n\n11 - FUNDOS EU\nTêm fundos EU? Não\n\n12 - DOCUMENTOS DE HABILITAÇÃO\nHabilitação para o exercício da atividade profissional: Não\n\n13 - CONDIÇÕES DE APRESENTAÇÃO\nPlataforma eletrónica utilizada pela entidade adjudicante: VORTAL\nURL para Apresentação: https://community.vortal.biz/public/\nAdmissibilidade da apresentação de propostas variantes: Não autorizado\nPrazo para apresentação das propostas: 06-11-2025 23:59\nPrazo durante o qual os concorrentes são obrigados a manter as respetivas propostas: 120 dias a contar do termo do prazo para a apresentação das propostas\nApresentação de Catálogo Eletrónico: Não autorizado\nIndicação de Subcontratação na Proposta: Inexistência de indicação de subcontratação\n\n14 - PRESTAÇÃO DE CAUÇÃO\nPrestação de caução: Sim\nPercentagem: 5%\nDescrição da Garantia Exigida: Garantia bancaria ou seguro caução\n\n15 - FORNECIMENTO DAS PEÇAS DO CONCURSO, APRESENTAÇÃO DE PEDIDOS DE PARTICIPAÇÃO E APRESENTAÇÃO DAS PROPOSTAS\nLink para acesso às peças do concurso (URL): https://community.vortal.biz/Public/public-tender-documents/WUxHSWxXejhDTS8xanA1aEpCYzd2UWx1eUFwRzU3TEUwUmlPNHl6WTZldWo2WXFrZmIvcWVyR2dQOUFrbFN1Wm92S3VUUEJrT2k1QVRCUU10UzVXakE9PU1Ga1lh\n\n20 - OUTROS REQUISITOS\nInformação sobre contratos reservados. Aplica-se a contratos reservados (54º-A)? Não\n\n21 - CRITÉRIO DE ADJUDICAÇÃO\nMultifator: Sim\nFator: \nNome: Preço\nPonderação: 50%\nSubfatores: Não\nFator: \nNome: Outros\nOutro Nome: Valor da diária prolongada \nPonderação: 10%\nSubfatores: Não\nFator: \nNome: Qualidade\nPonderação: 20%\nSubfatores: Não\nFator: \nNome: Qualidade\nPonderação: 10%\nSubfatores: Não\nFator: \nNome: Qualidade\nPonderação: 10%\nSubfatores: Não\n\n24 - CONDIÇÕES DO CONTRATO\nFaturação Eletrónica: Permitido\nObrigação de Subcontratação:\nCódigo da Obrigação de Subcontratação: Não é aplicável nenhuma obrigação de subcontratação.\n\n25 - COMPRA PÚBLICA ESTRATÉGICA\nCompra Pública Estratégica: Inexistência de contratação pública estratégica\n\n26 - INFORMAÇÕES ADICIONAIS\nContrato adequado para PME: Sim\nCobertura ACP (Acordo dos Contratos Públicos da Organização Mundial do Comércio): Não\n\n27 - IDENTIFICAÇÃO E CONTACTOS DO ÓRGÃO DE RECURSOS ADMINISTRATIVOS\nDesignação: Conselho de Administração\nEndereço: Largo Professor Abel salazar\nCódigo postal: 4099-001\nLocalidade: Porto\nTelefone: +351 222077500\nFax: +351 223320318\nEndereço eletrónico: secretariado.aprov@chporto.min-saude.pt\n\n28 - IDENTIFICAÇÃO DO(S) AUTOR(ES) DE ANÚNCIO\nNome: Caroline Silva\nCargo: Técnica Superior\n419611561",
    "nipc": "517392259",
    "distrito": "Porto",
    "concelho": "Porto",
    "freguesia": "Todas",
    "site": "www.hgsa.pt",
    "email": "helpdesk.b-on@hgsa.min-saude.pt",
    "designacao_contrato": "Serviços de internamento hospitalar externo de doentes de medicina interna com doença aguda ou agudização de doença crónica",
    "descricao": "Concurso Público Internacional n.º 1253/2025: contratação de serviços de internamento hospitalar externo de doentes de medicina interna com doença aguda ou agudização de doença crónica",
    "preco_base": "646.140,00 EUR",
    "prazo_execucao": "7 MESES",
    "prazo_apresentacao_propostas": "06-11-2025 23:59",
    "fundos_eu": "Não",
    "plataforma_eletronica": "VORTAL",
    "url_procedimento": "https://community.vortal.biz/public/",
    "autor_nome": "Caroline Silva",
    "autor_cargo": "Técnica Superior"
  },
  {
    "numero_procedimento": "N/A",
    "entidade": "Faculdade de Direito da Universidade de Lisboa",
    "link": "https://diariodarepublica.pt/dr/detalhe/contrato-publico/26483-938923375",
    "detalhes_completos": "1 - IDENTIFICAÇÃO E CONTACTOS DA ENTIDADE ADJUDICANTE\nDesignação da entidade adjudicante: Faculdade de Direito da Universidade de Lisboa\nNIPC: 502736208\nServiço/Órgão/Pessoa de contacto: Ana Ramos\nEndereço: Alameda da Universidade\nCódigo postal: 1649-014\nLocalidade: Lisboa\nPaís: Portugal\nNUT III: PT170\nDistrito: Lisboa\nConcelho: Lisboa\nFreguesia: Freguesia de Alvalade - Lisboa\nTelefone: 217984600\nFax: 217984600\nEndereço da Entidade (URL): www.fd.ulisboa.pt\nEndereço Eletrónico: contratacaopublica@fd.ulisboa.pt\neDelivery Gateway (URL): https://www.acingov.pt\nFunção da Organização: Adquirente\nNorma jurídica da Entidade Adjudicante: Organismo de direito público\nÁrea de atividade da Autoridade Adjudicante: Educação\n\n2 - JORNAL OFICIAL DA UNIÃO EUROPEIA\nO procedimento a que este anúncio diz respeito também é publicitado no Jornal Oficial da União Europeia? Não\n\n3 - AVISO\nModelo de Anúncio: Concurso público\nData de Envio do Anúncio: 08-10-2025\n\n5 - PROCESSO\nTipo de Procedimento: Concurso público\nPreço base do procedimento: Sim\nValor do preço base do procedimento: 86.000,00 EUR\nProcedimento com lotes? Não\n\n6 - OBJETO DO CONTRATO\nNúmero de referência interna: CP/5/2025\nDesignação do contrato: Aquisição e instalação de equipamentos audiovisuais nas instalações da Faculdade de Direito da Universidade de Lisboa\nDescrição: Aquisição e instalação de equipamentos audiovisuais nas instalações da Faculdade de Direito da Universidade de Lisboa\nTipo de Contrato Principal: Aquisição de Bens Móveis\nTipo de Contrato: Aquisição de Bens Móveis\nClassificação CPV (Vocabulário Comum para os Contratos Públicos)\nObjeto principal\nVocabulário Principal: 32321200\nPreço base s/IVA: 86.000,00 EUR\n\n7 - INDICAÇÕES ADICIONAIS\nO contrato envolve aquisição conjunta (satisfação de várias entidades)? Não\nO contrato é adjudicado por uma central de compras? Não\n\n8 - TÉCNICAS\nO concurso destina-se à celebração de um acordo-quadro? Inexistência de acordo-quadro\nÉ utilizado um leilão eletrónico? Não\nÉ adotada uma fase de negociação? Não\nSistema de Aquisição Dinâmico: Inexistência de sistema de aquisição dinâmico\n\n9 - LOCAL DA EXECUÇÃO DO CONTRATO\nLOCAL DA EXECUÇÃO DO CONTRATO (PROCEDIMENTO)\nPaís: Portugal\nNUT III: PT170\nLocalidade: Freguesia de Alvalade - Lisboa\nDistrito: Lisboa\nConcelho: Lisboa\nFreguesia: Freguesia de Alvalade - Lisboa\n\n10 - PRAZO DE EXECUÇÃO DO CONTRATO\nPrazo de execução do contrato: 212 DIAS\nPrevisão de renovações: Não\n\n11 - FUNDOS EU\nTêm fundos EU? Sim\n\n12 - DOCUMENTOS DE HABILITAÇÃO\nHabilitação para o exercício da atividade profissional: Não\n\n13 - CONDIÇÕES DE APRESENTAÇÃO\nPlataforma eletrónica utilizada pela entidade adjudicante: ACIN\nURL para Apresentação: https://www.acingov.pt\nAdmissibilidade da apresentação de propostas variantes: Não autorizado\nPrazo para apresentação das propostas: 23-10-2025 23:59\nPrazo durante o qual os concorrentes são obrigados a manter as respetivas propostas: 66 dias a contar do termo do prazo para a apresentação das propostas\nIndicação de Subcontratação na Proposta: Inexistência de indicação de subcontratação\n\n14 - PRESTAÇÃO DE CAUÇÃO\nPrestação de caução: Não\n\n15 - FORNECIMENTO DAS PEÇAS DO CONCURSO, APRESENTAÇÃO DE PEDIDOS DE PARTICIPAÇÃO E APRESENTAÇÃO DAS PROPOSTAS\nLink para acesso às peças do concurso (URL): https://www.acingov.pt/acingovprod/2/zonaPublica/zona_publica_c/donwloadProcedurePiece/OTgyNjgw\n\n20 - OUTROS REQUISITOS\nInformação sobre contratos reservados. Aplica-se a contratos reservados (54º-A)? Não\n\n21 - CRITÉRIO DE ADJUDICAÇÃO\nMultifator: Não\nMonofator:\nNome: Preço\n\n24 - CONDIÇÕES DO CONTRATO\nFaturação Eletrónica: Permitido\nObrigação de Subcontratação:\nCódigo da Obrigação de Subcontratação: Não é aplicável nenhuma obrigação de subcontratação.\n\n25 - COMPRA PÚBLICA ESTRATÉGICA\nCompra Pública Estratégica: Inexistência de contratação pública estratégica\n\n26 - INFORMAÇÕES ADICIONAIS\nContrato adequado para PME: Sim\nCobertura ACP (Acordo dos Contratos Públicos da Organização Mundial do Comércio): Não\n\n27 - IDENTIFICAÇÃO E CONTACTOS DO ÓRGÃO DE RECURSOS ADMINISTRATIVOS\nDesignação: Diretor\nEndereço: Alameda da Universidade\nCódigo postal: 1649-014\nLocalidade: Lisboa\nTelefone: 217984600\nFax: \nEndereço eletrónico: secretariadodir@fd.ulisboa.pt\nPrazo de interposição do recurso: 5 dias\n\n28 - IDENTIFICAÇÃO DO(S) AUTOR(ES) DE ANÚNCIO\nNome: Ana Sofia Ramos\nCargo: Coordenadora Área Financeira\n419627657",
    "nipc": "502736208",
    "distrito": "Lisboa",
    "concelho": "Lisboa",
    "freguesia": "Freguesia de Alvalade - Lisboa",
    "site": "www.fd.ulisboa.pt",
    "email": "contratacaopublica@fd.ulisboa.pt",
    "designacao_contrato": "Aquisição e instalação de equipamentos audiovisuais nas instalações da Faculdade de Direito da Universidade de Lisboa",
    "descricao": "Aquisição e instalação de equipamentos audiovisuais nas instalações da Faculdade de Direito da Universidade de Lisboa",
    "preco_base": "86.000,00 EUR",
    "prazo_execucao": "212 DIAS",
    "prazo_apresentacao_propostas": "23-10-2025 23:59",
    "fundos_eu": "Sim",
    "plataforma_eletronica": "ACIN",
    "url_procedimento": "https://www.acingov.pt",
    "autor_nome": "Ana Sofia Ramos",
    "autor_cargo": "Coordenadora Área Financeira"
  },
  {
    "numero_procedimento": "N/A",
    "entidade": "Município de Guimarães",
    "link": "https://diariodarepublica.pt/dr/detalhe/contrato-publico/26484-938923376",
    "detalhes_completos": "Alteração do Anúncio de procedimento n.º 24690/2025, de 2025-09-18, com o ID 419548058\n\n1 - IDENTIFICAÇÃO E CONTACTOS DA ENTIDADE ADJUDICANTE\nDesignação da entidade adjudicante: Município de Guimarães\nNIPC: 505948605\nServiço/Órgão/Pessoa de contacto: Divisão de Empreitadas\nEndereço: Largo Cónego José Maria Gomes\nCódigo postal: 4804-534\nLocalidade: Guimarães\nPaís: Portugal\nNUT III: PT119\nDistrito: Braga\nConcelho: Guimarães\nFreguesia: Freguesia de Candoso (São Martinho)\nTelefone: 253421200\nFax: 253515134\nEndereço da Entidade (URL): http://www.cm-guimaraes.pt\nEndereço Eletrónico: geral@cm-guimaraes.pt\neDelivery Gateway (URL): https://www.acingov.pt\nFunção da Organização: Adquirente\nSubfunção da Organização: Organização que recebe as propostas\nNorma jurídica da Entidade Adjudicante: Organismo de direito público\nÁrea de atividade da Autoridade Adjudicante: Serviços públicos das administrações públicas\n\n2 - JORNAL OFICIAL DA UNIÃO EUROPEIA\nO procedimento a que este anúncio diz respeito também é publicitado no Jornal Oficial da União Europeia? Não\n\n3 - AVISO\nModelo de Anúncio: Concurso público\nData de Envio do Anúncio: 08-10-2025\n\n5 - PROCESSO\nTipo de Procedimento: Concurso público\nPreço base do procedimento: Sim\nValor do preço base do procedimento: 2.982.335,16 EUR\nProcedimento com lotes? Não\n\n6 - OBJETO DO CONTRATO\nNúmero de referência interna: 129/25\nDesignação do contrato: Via Ciclável do Lugar do Reboto à Vila de Pevidém - Candoso S. Martinho\nDescrição: Via Ciclável do Lugar do Reboto à Vila de Pevidém - Candoso S. Martinho\nTipo de Contrato Principal: Empreitada de Obras Públicas\nTipo de Contrato: Empreitada de Obras Públicas\nClassificação CPV (Vocabulário Comum para os Contratos Públicos)\nObjeto principal\nVocabulário Principal: 45233162\nPreço base s/IVA: 2.982.335,16 EUR\n\n7 - INDICAÇÕES ADICIONAIS\nO contrato envolve aquisição conjunta (satisfação de várias entidades)? Não\nO contrato é adjudicado por uma central de compras? Não\n\n8 - TÉCNICAS\nO concurso destina-se à celebração de um acordo-quadro? Inexistência de acordo-quadro\nÉ utilizado um leilão eletrónico? Não\nÉ adotada uma fase de negociação? Não\nSistema de Aquisição Dinâmico: Inexistência de sistema de aquisição dinâmico\n\n9 - LOCAL DA EXECUÇÃO DO CONTRATO\nLOCAL DA EXECUÇÃO DO CONTRATO (PROCEDIMENTO)\nPaís: Portugal\nNUT III: PT119\nLocalidade: Freguesia de Candoso (São Martinho)\nDistrito: Braga\nConcelho: Guimarães\nFreguesia: Freguesia de Candoso (São Martinho)\n\n10 - PRAZO DE EXECUÇÃO DO CONTRATO\nPrazo de execução do contrato: 545 DIAS\nPrevisão de renovações: Não\n\n11 - FUNDOS EU\nTêm fundos EU? Não\n\n12 - DOCUMENTOS DE HABILITAÇÃO\nHabilitação para o exercício da atividade profissional: Sim\nTipo: Alvará\nDescrição: A 3ª subcategoria da 1ª categoria, em classe que cubra o valor global da proposta;\nA(s) 1ª, 4ª, 7ª subcategorias da 1ª categoria; 6ª, 8ª, 9ª subcategorias da 2ª categoria; 4ª, 18ª subcategorias da 4ª categoria; 1ª, 2ª, 4ª, 6ª, 13ª subcategorias da 5ª categoria em classe correspondente, cada uma, ao valor dos trabalhos a que lhes respeitem.\n\n13 - CONDIÇÕES DE APRESENTAÇÃO\nPlataforma eletrónica utilizada pela entidade adjudicante: ACIN\nURL para Apresentação: https://www.acingov.pt\nAdmissibilidade da apresentação de propostas variantes: Não autorizado\nPrazo para apresentação das propostas: 15-10-2025 00:00\nPrazo durante o qual os concorrentes são obrigados a manter as respetivas propostas: 120 dias a contar do termo do prazo para a apresentação das propostas\nIndicação de Subcontratação na Proposta: Inexistência de indicação de subcontratação\n\n14 - PRESTAÇÃO DE CAUÇÃO\nPrestação de caução: Sim\nPercentagem: 5%\nDescrição da Garantia Exigida: O valor da caução é de 5.00% do preço contratual.\n\n15 - FORNECIMENTO DAS PEÇAS DO CONCURSO, APRESENTAÇÃO DE PEDIDOS DE PARTICIPAÇÃO E APRESENTAÇÃO DAS PROPOSTAS\nLink para acesso às peças do concurso (URL): https://www.acingov.pt/acingovprod/2/zonaPublica/zona_publica_c/donwloadProcedurePiece/OTc1OTk4\n\n20 - OUTROS REQUISITOS\nInformação sobre contratos reservados. Aplica-se a contratos reservados (54º-A)? Não\n\n21 - CRITÉRIO DE ADJUDICAÇÃO\nMultifator: Sim\nFator: \nNome: Preço\nPonderação: 60%\nSubfatores: Não\nFator: \nNome: Outros\nOutro Nome: Memória descritiva e Justificativo\nPonderação: 20%\nSubfatores: Não\nFator: \nNome: Outros\nOutro Nome: Plano de Trabalhos\nPonderação: 14%\nSubfatores: Não\nFator: \nNome: Outros\nOutro Nome: Sistema de Gestão e Controlo de Qualidade\nPonderação: 2%\nSubfatores: Não\nFator: \nNome: Outros\nOutro Nome: Sistema de Gestão de Segurança\nPonderação: 2%\nSubfatores: Não\nFator: \nNome: Outros\nOutro Nome: Sistema de Acompanhamento Ambiental\nPonderação: 2%\nSubfatores: Não\n\n24 - CONDIÇÕES DO CONTRATO\nFaturação Eletrónica: Permitido\nObrigação de Subcontratação:\nCódigo da Obrigação de Subcontratação: Não é aplicável nenhuma obrigação de subcontratação.\n\n25 - COMPRA PÚBLICA ESTRATÉGICA\nCompra Pública Estratégica: Inexistência de contratação pública estratégica\n\n26 - INFORMAÇÕES ADICIONAIS\nContrato adequado para PME: Não\nCobertura ACP (Acordo dos Contratos Públicos da Organização Mundial do Comércio): Não\n\n27 - IDENTIFICAÇÃO E CONTACTOS DO ÓRGÃO DE RECURSOS ADMINISTRATIVOS\nDesignação: Municipio de Guimarães\nEndereço: Largo Cónego José Maria Gomes\nCódigo postal: 4804-534\nLocalidade: Guimarães\nTelefone: 253421200\nFax: 253515134\nEndereço eletrónico: geral@cm-guimaraes.pt\nPrazo de interposição do recurso: 5 dias\n\n28 - IDENTIFICAÇÃO DO(S) AUTOR(ES) DE ANÚNCIO\nNome: Dr. Domingos Bragança\nCargo: Presidente da Câmara\n\n29 - ALTERAÇÃO\nMotivo da Alteração: Informações agora disponíveis\nIdentificador da Versão do Anúncio a Alterar: 7cd2d3de-4fae-40ce-9ec3-0a5c81dbe367-01\nIdentificador das Secções Alteradas do Anúncio Anterior: Condições de Apresentação\nDescrição das Alterações: Modificação do prazo para a apresentação de propostas\nAlteração dos Documentos do Concurso: Não\n419631877",
    "nipc": "505948605",
    "distrito": "Braga",
    "concelho": "Guimarães",
    "freguesia": "Freguesia de Candoso (São Martinho)",
    "site": "http://www.cm-guimaraes.pt",
    "email": "geral@cm-guimaraes.pt",
    "designacao_contrato": "Via Ciclável do Lugar do Reboto à Vila de Pevidém - Candoso S. Martinho",
    "descricao": "Via Ciclável do Lugar do Reboto à Vila de Pevidém - Candoso S. Martinho",
    "preco_base": "2.982.335,16 EUR",
    "prazo_execucao": "545 DIAS",
    "prazo_apresentacao_propostas": "15-10-2025 00:00",
    "fundos_eu": "Não",
    "plataforma_eletronica": "ACIN",
    "url_procedimento": "https://www.acingov.pt",
    "autor_nome": "Dr. Domingos Bragança",
    "autor_cargo": "Presidente da Câmara"
  },
  {
    "numero_procedimento": "N/A",
    "entidade": "Unidade Local de Saúde de Santo António, E. P. E.",
    "link": "https://diariodarepublica.pt/dr/detalhe/contrato-publico/26485-938923377",
    "detalhes_completos": "1 - IDENTIFICAÇÃO E CONTACTOS DA ENTIDADE ADJUDICANTE\nDesignação da entidade adjudicante: Unidade Local de Saúde de Santo António, E. P. E.\nNIPC: 517392259\nEndereço: Largo Prof. Abel Salazar\nCódigo postal: 4099-001\nLocalidade: Área Metropolitana do Porto\nPaís: Portugal\nNUT III: PT11A\nDistrito: Porto\nConcelho: Porto\nFreguesia: Todas\nTelefone: 222077500\nFax: 223320318\nEndereço da Entidade (URL): www.hgsa.pt\nEndereço Eletrónico: helpdesk.b-on@hgsa.min-saude.pt\neDelivery Gateway (URL): https://community.vortal.biz/public/\nFunção da Organização: Adquirente\nNorma jurídica da Entidade Adjudicante: Empresa pública\nÁrea de atividade da Autoridade Adjudicante: Saúde\n\n2 - JORNAL OFICIAL DA UNIÃO EUROPEIA\nO procedimento a que este anúncio diz respeito também é publicitado no Jornal Oficial da União Europeia? Sim\n\n3 - AVISO\nModelo de Anúncio: Concurso público\nData de Envio do Anúncio: 06-10-2025\n\n5 - PROCESSO\nTipo de Procedimento: Concurso público\nPreço base do procedimento: Sim\nValor do preço base do procedimento: 599.604,00 EUR\nProcedimento com lotes? Sim\nNº Máx. de Lotes Autorizado: 8\nNúmero máximo de lotes que podem ser adjudicados a um concorrente: 8\n\n6 - OBJETO DO CONTRATO\nNúmero de referência interna: CI/1273/2025\nDesignação do contrato: Aquisição de serviços de diálise peritoneal domiciliária para doentes da ULSSA\nDescrição: Concurso Público Internacional n.º 1273/2025: Aquisição de serviços de diálise peritoneal domiciliária para doentes da Unidade Local de Saúde de Santo António, E.P.E.\nOpções: Não\nTipo de Contrato Principal: Aquisição de Serviços\nTipo de Contrato: Aquisição de Serviços\nClassificação CPV (Vocabulário Comum para os Contratos Públicos)\nObjeto principal\nVocabulário Principal: 85144000\nPreço base s/IVA: 599.604,00 EUR\nLotes: \nNº: LOT-0001\nDescrição do Lote: Lote 1\nPreço base s/IVA: 194.545,00 EUR\nClassificação CPV (Vocabulário Comum para os Contratos Públicos)\nObjeto principal\nVocabulário Principal: 85144000\nNº: LOT-0002\nDescrição do Lote: Lote 2\nPreço base s/IVA: 98.368,00 EUR\nClassificação CPV (Vocabulário Comum para os Contratos Públicos)\nObjeto principal\nVocabulário Principal: 85144000\nNº: LOT-0003\nDescrição do Lote: Lote 3\nPreço base s/IVA: 42.705,00 EUR\nClassificação CPV (Vocabulário Comum para os Contratos Públicos)\nObjeto principal\nVocabulário Principal: 85144000\nNº: LOT-0004\nDescrição do Lote: Lote 4\nPreço base s/IVA: 5.475,00 EUR\nClassificação CPV (Vocabulário Comum para os Contratos Públicos)\nObjeto principal\nVocabulário Principal: 85144000\nNº: LOT-0005\nDescrição do Lote: Lote 5\nPreço base s/IVA: 171.094,00 EUR\nClassificação CPV (Vocabulário Comum para os Contratos Públicos)\nObjeto principal\nVocabulário Principal: 85144000\nNº: LOT-0006\nDescrição do Lote: Lote 6\nPreço base s/IVA: 61.274,00 EUR\nClassificação CPV (Vocabulário Comum para os Contratos Públicos)\nObjeto principal\nVocabulário Principal: 85144000\nNº: LOT-0007\nDescrição do Lote: Lote 7\nPreço base s/IVA: 17.246,00 EUR\nClassificação CPV (Vocabulário Comum para os Contratos Públicos)\nObjeto principal\nVocabulário Principal: 85144000\nNº: LOT-0008\nDescrição do Lote: Lote 8\nPreço base s/IVA: 8.897,00 EUR\nClassificação CPV (Vocabulário Comum para os Contratos Públicos)\nObjeto principal\nVocabulário Principal: 85144000\n\n7 - INDICAÇÕES ADICIONAIS\nO contrato envolve aquisição conjunta (satisfação de várias entidades)? Não\nO contrato é adjudicado por uma central de compras? Não\n\n8 - TÉCNICAS\nO concurso destina-se à celebração de um acordo-quadro? Inexistência de acordo-quadro\nÉ utilizado um leilão eletrónico? Não\nÉ adotada uma fase de negociação? Não\nSistema de Aquisição Dinâmico: Inexistência de sistema de aquisição dinâmico\n\n9 - LOCAL DA EXECUÇÃO DO CONTRATO\nLOCAL DA EXECUÇÃO DO CONTRATO (PROCEDIMENTO)\nPaís: Portugal\nNUT III: PT11A\nLocalidade: Área Metropolitana do Porto\nDistrito: Porto\nConcelho: Porto\nFreguesia: Todas\nLOCAL DA EXECUÇÃO DO CONTRATO (LOTE)\nIdentificador do Lote: LOT-0001; LOT-0002; LOT-0003; LOT-0004; LOT-0005; LOT-0006; LOT-0007; LOT-0008\nPaís: Portugal\nNUT III: PT11A\nLocalidade: Área Metropolitana do Porto\nDistrito: Porto\nConcelho: Porto\nFreguesia: Todas\n\n10 - PRAZO DE EXECUÇÃO DO CONTRATO\nIdentificador do Lote: LOT-0001; LOT-0002; LOT-0003; LOT-0004; LOT-0005; LOT-0006; LOT-0007; LOT-0008\nPrazo de execução do contrato: 6 MESES\nPrevisão de renovações: Não\n\n11 - FUNDOS EU\nIdentificador do Lote: LOT-0001; LOT-0002; LOT-0003; LOT-0004; LOT-0005; LOT-0006; LOT-0007; LOT-0008\nTêm fundos EU? Não\n\n12 - DOCUMENTOS DE HABILITAÇÃO\nHabilitação para o exercício da atividade profissional: Não\n\n13 - CONDIÇÕES DE APRESENTAÇÃO\nPlataforma eletrónica utilizada pela entidade adjudicante: VORTAL\nURL para Apresentação: https://community.vortal.biz/public/\nAdmissibilidade da apresentação de propostas variantes: Não autorizado\nPrazo para apresentação das propostas: 06-11-2025 23:59\nPrazo durante o qual os concorrentes são obrigados a manter as respetivas propostas: 120 dias a contar do termo do prazo para a apresentação das propostas\nApresentação de Catálogo Eletrónico: Não autorizado\nIndicação de Subcontratação na Proposta: Inexistência de indicação de subcontratação\n\n14 - PRESTAÇÃO DE CAUÇÃO\nPrestação de caução: Sim\nPercentagem: 5%\nDescrição da Garantia Exigida: Garantia bancária, seguro caução\n\n15 - FORNECIMENTO DAS PEÇAS DO CONCURSO, APRESENTAÇÃO DE PEDIDOS DE PARTICIPAÇÃO E APRESENTAÇÃO DAS PROPOSTAS\nLink para acesso às peças do concurso (URL): https://community.vortal.biz/Public/public-tender-documents/S2NEZ0R3cEFKVUhsU1ZQYkRyY1pPR252Y0J6UlVvdkZBQ3ZGaHlycXRtbVZkUHkrOGRPdmprU2YzM0JsSm1HbHlJemVFdC9zQ0FjQTNiY1V0K1JKUnc9PW9POXlf\n\n20 - OUTROS REQUISITOS\nIdentificador do Lote: LOT-0001; LOT-0002; LOT-0003; LOT-0004; LOT-0005; LOT-0006; LOT-0007; LOT-0008\nInformação sobre contratos reservados. Aplica-se a contratos reservados (54º-A)? Não\n\n21 - CRITÉRIO DE ADJUDICAÇÃO\nO Critério de adjudicação é diferenciado por lote? Não\nMultifator: Sim\nFator: \nNome: Preço\nPonderação: 70%\nSubfatores: Não\nFator: \nNome: Qualidade\nPonderação: 30%\nSubfatores: Não\n\n24 - CONDIÇÕES DO CONTRATO\nIdentificador do Lote: LOT-0001; LOT-0002; LOT-0003; LOT-0004; LOT-0005; LOT-0006; LOT-0007; LOT-0008\nFaturação Eletrónica: Permitido\nObrigação de Subcontratação:\nCódigo da Obrigação de Subcontratação: Não é aplicável nenhuma obrigação de subcontratação.\n\n25 - COMPRA PÚBLICA ESTRATÉGICA\nCompra Pública Estratégica: Inexistência de contratação pública estratégica\n\n26 - INFORMAÇÕES ADICIONAIS\nIdentificador do Lote: LOT-0001; LOT-0002; LOT-0003; LOT-0004; LOT-0005; LOT-0006; LOT-0007; LOT-0008\nContrato adequado para PME: Sim\nCobertura ACP (Acordo dos Contratos Públicos da Organização Mundial do Comércio): Não\n\n27 - IDENTIFICAÇÃO E CONTACTOS DO ÓRGÃO DE RECURSOS ADMINISTRATIVOS\nDesignação: Conselho de Administração\nEndereço: Largo Professor Abel Salazar\nCódigo postal: 4099-001\nLocalidade: Porto\nTelefone: +351 222077500\nFax: +351 223320318\nEndereço eletrónico: secretariado.aprov@chporto.min-saude.pt\n\n28 - IDENTIFICAÇÃO DO(S) AUTOR(ES) DE ANÚNCIO\nNome: Caroline Silva\nCargo: Técnica Superior\n419612663",
    "nipc": "517392259",
    "distrito": "Porto",
    "concelho": "Porto",
    "freguesia": "Todas",
    "site": "www.hgsa.pt",
    "email": "helpdesk.b-on@hgsa.min-saude.pt",
    "designacao_contrato": "Aquisição de serviços de diálise peritoneal domiciliária para doentes da ULSSA",
    "descricao": "Concurso Público Internacional n.º 1273/2025: Aquisição de serviços de diálise peritoneal domiciliária para doentes da Unidade Local de Saúde de Santo António, E.P.E.",
    "preco_base": "599.604,00 EUR",
    "prazo_execucao": "6 MESES",
    "prazo_apresentacao_propostas": "06-11-2025 23:59",
    "fundos_eu": "Não",
    "plataforma_eletronica": "VORTAL",
    "url_procedimento": "https://community.vortal.biz/public/",
    "autor_nome": "Caroline Silva",
    "autor_cargo": "Técnica Superior"
  },
  {
    "numero_procedimento": "N/A",
    "entidade": "Ministério da Defesa Nacional - Marinha",
    "link": "https://diariodarepublica.pt/dr/detalhe/contrato-publico/26486-938923378",
    "detalhes_completos": "1 - IDENTIFICAÇÃO E CONTACTOS DA ENTIDADE ADJUDICANTE\nDesignação da entidade adjudicante: Ministério da Defesa Nacional - Marinha\nNIPC: 600012662\nEndereço: Praça do Comércio\nCódigo postal: 1100-148\nLocalidade: Lisboa\nPaís: Portugal\nNUT III: PTZZZ\nDistrito: Todos\nConcelho: Todos\nFreguesia: Todas\nTelefone: 210984022\nFax: 213217651\nEndereço da Entidade (URL): www.amn.pt\nEndereço Eletrónico: dgam.dafl@marinha.pt\neDelivery Gateway (URL): https://www.acingov.pt\nFunção da Organização: Adquirente\nNorma jurídica da Entidade Adjudicante: Organismo de direito público\nÁrea de atividade da Autoridade Adjudicante: Serviços públicos das administrações públicas\n\n2 - JORNAL OFICIAL DA UNIÃO EUROPEIA\nO procedimento a que este anúncio diz respeito também é publicitado no Jornal Oficial da União Europeia? Não\n\n3 - AVISO\nModelo de Anúncio: Concurso público\nData de Envio do Anúncio: 08-10-2025\n\n5 - PROCESSO\nTipo de Procedimento: Concurso público\nPreço base do procedimento: Sim\nValor do preço base do procedimento: 62.000,00 EUR\nProcedimento com lotes? Sim\nNº Máx. de Lotes Autorizado: 6\nNúmero máximo de lotes que podem ser adjudicados a um concorrente: 6\n\n6 - OBJETO DO CONTRATO\nNúmero de referência interna: 3025010303\nDesignação do contrato: 3025010303 - AMN - Aquisição de serviços de manutenção corretiva de embarcações\nDescrição: 3025010303 - AMN -  Aquisição de serviços de manutenção corretiva de embarcações\nTipo de Contrato Principal: Aquisição de Serviços\nTipo de Contrato: Aquisição de Serviços\nClassificação CPV (Vocabulário Comum para os Contratos Públicos)\nObjeto principal\nVocabulário Principal: 50241100\nPreço base s/IVA: 62.000,00 EUR\nLotes: \nNº: LOT-0001\nDescrição do Lote: FLUTUADOR ISN-SR37\nPreço base s/IVA: 10.000,00 EUR\nClassificação CPV (Vocabulário Comum para os Contratos Públicos)\nObjeto principal\nVocabulário Principal: 50112100\nNº: LOT-0002\nDescrição do Lote: ISN-SR21 e AMN-49-SM GILÃO\nPreço base s/IVA: 10.500,00 EUR\nClassificação CPV (Vocabulário Comum para os Contratos Públicos)\nObjeto principal\nVocabulário Principal: 50112100\nNº: LOT-0003\nDescrição do Lote: AMN-13-SG EAV OURA, ISN-SR17, AMN-05-B BOTE, AMN-06-B BOTE, AMN-26-R ARNILHA e AMN-27-R VEJA\nPreço base s/IVA: 20.000,00 EUR\nClassificação CPV (Vocabulário Comum para os Contratos Públicos)\nObjeto principal\nVocabulário Principal: 50112100\nNº: LOT-0004\nDescrição do Lote: AMN-22-SG TRITÃO\nPreço base s/IVA: 8.500,00 EUR\nClassificação CPV (Vocabulário Comum para os Contratos Públicos)\nObjeto principal\nVocabulário Principal: 50112100\nNº: LOT-0005\nDescrição do Lote: ISN-SR37\nPreço base s/IVA: 6.000,00 EUR\nClassificação CPV (Vocabulário Comum para os Contratos Públicos)\nObjeto principal\nVocabulário Principal: 50112100\nNº: LOT-0006\nDescrição do Lote: AMN-04-SG FARO (Conforme CAD)\nPreço base s/IVA: 7.000,00 EUR\nClassificação CPV (Vocabulário Comum para os Contratos Públicos)\nObjeto principal\nVocabulário Principal: 50112100\n\n7 - INDICAÇÕES ADICIONAIS\nO contrato envolve aquisição conjunta (satisfação de várias entidades)? Não\nO contrato é adjudicado por uma central de compras? Não\n\n8 - TÉCNICAS\nO concurso destina-se à celebração de um acordo-quadro? Inexistência de acordo-quadro\nÉ utilizado um leilão eletrónico? Não\nÉ adotada uma fase de negociação? Não\nSistema de Aquisição Dinâmico: Inexistência de sistema de aquisição dinâmico\n\n9 - LOCAL DA EXECUÇÃO DO CONTRATO\nLOCAL DA EXECUÇÃO DO CONTRATO (PROCEDIMENTO)\nPaís: Portugal\nNUT III: PT150\nLocalidade: União das Freguesias de Conceição e Estoi\nDistrito: Faro\nConcelho: Faro\nFreguesia: União das Freguesias de Conceição e Estoi\nLOCAL DA EXECUÇÃO DO CONTRATO (LOTE)\nIdentificador do Lote: LOT-0001; LOT-0002; LOT-0003; LOT-0004; LOT-0005; LOT-0006\nPaís: Portugal\nNUT III: PT150\nLocalidade: União das Freguesias de Conceição e Estoi\nDistrito: Faro\nConcelho: Faro\nFreguesia: União das Freguesias de Conceição e Estoi\n\n10 - PRAZO DE EXECUÇÃO DO CONTRATO\nIdentificador do Lote: LOT-0001; LOT-0002; LOT-0003; LOT-0004; LOT-0005; LOT-0006\nPrazo de execução do contrato: 90 DIAS\nPrevisão de renovações: Não\n\n11 - FUNDOS EU\nIdentificador do Lote: LOT-0001; LOT-0002; LOT-0003; LOT-0004; LOT-0005; LOT-0006\nTêm fundos EU? Não\n\n12 - DOCUMENTOS DE HABILITAÇÃO\nHabilitação para o exercício da atividade profissional: Não\n\n13 - CONDIÇÕES DE APRESENTAÇÃO\nPlataforma eletrónica utilizada pela entidade adjudicante: ACIN\nURL para Apresentação: https://www.acingov.pt\nAdmissibilidade da apresentação de propostas variantes: Não autorizado\nPrazo para apresentação das propostas: 23-10-2025 23:59\nPrazo durante o qual os concorrentes são obrigados a manter as respetivas propostas: 66 dias a contar do termo do prazo para a apresentação das propostas\nIndicação de Subcontratação na Proposta: Inexistência de indicação de subcontratação\n\n14 - PRESTAÇÃO DE CAUÇÃO\nPrestação de caução: Não\n\n15 - FORNECIMENTO DAS PEÇAS DO CONCURSO, APRESENTAÇÃO DE PEDIDOS DE PARTICIPAÇÃO E APRESENTAÇÃO DAS PROPOSTAS\nLink para acesso às peças do concurso (URL): https://www.acingov.pt/acingovprod/2/zonaPublica/zona_publica_c/donwloadProcedurePiece/OTg0ODU3\n\n20 - OUTROS REQUISITOS\nIdentificador do Lote: LOT-0001; LOT-0002; LOT-0003; LOT-0004; LOT-0005; LOT-0006\nInformação sobre contratos reservados. Aplica-se a contratos reservados (54º-A)? Não\n\n21 - CRITÉRIO DE ADJUDICAÇÃO\nO Critério de adjudicação é diferenciado por lote? Não\nMultifator: Não\nMonofator:\nNome: Preço\n\n24 - CONDIÇÕES DO CONTRATO\nIdentificador do Lote: LOT-0001; LOT-0002; LOT-0003; LOT-0004; LOT-0005; LOT-0006\nFaturação Eletrónica: Permitido\nObrigação de Subcontratação:\nCódigo da Obrigação de Subcontratação: Não é aplicável nenhuma obrigação de subcontratação.\n\n25 - COMPRA PÚBLICA ESTRATÉGICA\nCompra Pública Estratégica: Inexistência de contratação pública estratégica\n\n26 - INFORMAÇÕES ADICIONAIS\nIdentificador do Lote: LOT-0001; LOT-0002; LOT-0003; LOT-0004; LOT-0005; LOT-0006\nContrato adequado para PME: Não\nCobertura ACP (Acordo dos Contratos Públicos da Organização Mundial do Comércio): Não\n\n27 - IDENTIFICAÇÃO E CONTACTOS DO ÓRGÃO DE RECURSOS ADMINISTRATIVOS\nDesignação: Direção Geral Autoridade Marítima\nEndereço: Praça do Comércio\nCódigo postal: 1100-148\nLocalidade: Lisboa\nTelefone: 210984022\nFax: 213217651\nEndereço eletrónico: dgam.dafl@marinha.pt\n\n28 - IDENTIFICAÇÃO DO(S) AUTOR(ES) DE ANÚNCIO\nNome: Nuno Chaves Ferreira\nCargo: vice-almirante\n419631999",
    "nipc": "600012662",
    "distrito": "Todos",
    "concelho": "Todos",
    "freguesia": "Todas",
    "site": "www.amn.pt",
    "email": "dgam.dafl@marinha.pt",
    "designacao_contrato": "3025010303 - AMN - Aquisição de serviços de manutenção corretiva de embarcações",
    "descricao": "3025010303 - AMN - Aquisição de serviços de manutenção corretiva de embarcações",
    "preco_base": "62.000,00 EUR",
    "prazo_execucao": "90 DIAS",
    "prazo_apresentacao_propostas": "23-10-2025 23:59",
    "fundos_eu": "Não",
    "plataforma_eletronica": "ACIN",
    "url_procedimento": "https://www.acingov.pt",
    "autor_nome": "Nuno Chaves Ferreira",
    "autor_cargo": "vice-almirante"
  },
  {
    "numero_procedimento": "N/A",
    "entidade": "Município de Ourém",
    "link": "https://diariodarepublica.pt/dr/detalhe/contrato-publico/26487-938923379",
    "detalhes_completos": "1 - IDENTIFICAÇÃO E CONTACTOS DA ENTIDADE ADJUDICANTE\nDesignação da entidade adjudicante: Município de Ourém\nNIPC: 501280740\nServiço/Órgão/Pessoa de contacto: Serviço de Contratação Pública - Divisão de Gestão Financeira\nEndereço: Praça D. Maria II, N.º 1\nCódigo postal: 2490-499\nLocalidade: Ourém\nPaís: Portugal\nNUT III: PT16I\nDistrito: Santarém\nConcelho: Ourém\nFreguesia: Freguesia de Nossa Senhora da Piedade\nTelefone: +351 249540900\nFax: +351 249540908\nEndereço da Entidade (URL): https://www.ourem.pt\nEndereço Eletrónico: geral@mail.cm-ourem.pt\neDelivery Gateway (URL): https://www.acingov.pt\nFunção da Organização: Adquirente\nNorma jurídica da Entidade Adjudicante: Autoridade local\nÁrea de atividade da Autoridade Adjudicante: Serviços públicos das administrações públicas\n\n2 - JORNAL OFICIAL DA UNIÃO EUROPEIA\nO procedimento a que este anúncio diz respeito também é publicitado no Jornal Oficial da União Europeia? Sim\n\n3 - AVISO\nModelo de Anúncio: Concurso público\nData de Envio do Anúncio: 06-10-2025\n\n5 - PROCESSO\nTipo de Procedimento: Concurso público\nPreço base do procedimento: Sim\nValor do preço base do procedimento: 2.700.000,00 EUR\nProcedimento com lotes? Não\n\n6 - OBJETO DO CONTRATO\nNúmero de referência interna: P222/2025\nDesignação do contrato: P222/2025 - Prestação de Serviços de Limpeza Urbana no Município de Ourém - 2026-2029 (MGD: 71887/2025)\nDescrição: P222/2025 - Prestação de Serviços de Limpeza Urbana no Município de Ourém - 2026-2029 (MGD: 71887/2025)\nOpções: Não\nTipo de Contrato Principal: Aquisição de Serviços\nTipo de Contrato: Aquisição de Serviços\nClassificação CPV (Vocabulário Comum para os Contratos Públicos)\nObjeto principal\nVocabulário Principal: 90610000\nPreço base s/IVA: 2.700.000,00 EUR\n\n7 - INDICAÇÕES ADICIONAIS\nO contrato envolve aquisição conjunta (satisfação de várias entidades)? Não\nO contrato é adjudicado por uma central de compras? Não\n\n8 - TÉCNICAS\nO concurso destina-se à celebração de um acordo-quadro? Inexistência de acordo-quadro\nÉ utilizado um leilão eletrónico? Não\nÉ adotada uma fase de negociação? Não\nSistema de Aquisição Dinâmico: Inexistência de sistema de aquisição dinâmico\n\n9 - LOCAL DA EXECUÇÃO DO CONTRATO\nLOCAL DA EXECUÇÃO DO CONTRATO (PROCEDIMENTO)\nPaís: Portugal\nNUT III: PT16I\nLocalidade: Vários locais\nDistrito: Santarém\nConcelho: Ourém\nFreguesia: Todas\n\n10 - PRAZO DE EXECUÇÃO DO CONTRATO\nPrazo de execução do contrato: 36 MESES\nPrevisão de renovações: Não\n\n11 - FUNDOS EU\nTêm fundos EU? Não\n\n12 - DOCUMENTOS DE HABILITAÇÃO\nHabilitação para o exercício da atividade profissional: Sim\nTipo: Outros\nDescrição - Outros: Documentos de Habilitação\nDescrição: Os referidos no Ponto 6 do Programa de Procedimento.\n\n13 - CONDIÇÕES DE APRESENTAÇÃO\nPlataforma eletrónica utilizada pela entidade adjudicante: ACIN\nURL para Apresentação: https://www.acingov.pt\nAdmissibilidade da apresentação de propostas variantes: Não autorizado\nPrazo para apresentação das propostas: 13-11-2025 23:59\nPrazo durante o qual os concorrentes são obrigados a manter as respetivas propostas: 66 dias a contar do termo do prazo para a apresentação das propostas\nApresentação de Catálogo Eletrónico: Não autorizado\nIndicação de Subcontratação na Proposta: Inexistência de indicação de subcontratação\n\n14 - PRESTAÇÃO DE CAUÇÃO\nPrestação de caução: Sim\nPercentagem: 5%\nDescrição da Garantia Exigida: O valor da caução é de 5.00% do preço contratual.\n\n15 - FORNECIMENTO DAS PEÇAS DO CONCURSO, APRESENTAÇÃO DE PEDIDOS DE PARTICIPAÇÃO E APRESENTAÇÃO DAS PROPOSTAS\nLink para acesso às peças do concurso (URL): https://www.acingov.pt/acingovprod/2/zonaPublica/zona_publica_c/donwloadProcedurePiece/OTgzNjYw\n\n20 - OUTROS REQUISITOS\nInformação sobre contratos reservados. Aplica-se a contratos reservados (54º-A)? Não\n\n21 - CRITÉRIO DE ADJUDICAÇÃO\nMultifator: Não\nMonofator:\nNome: Preço\n\n24 - CONDIÇÕES DO CONTRATO\nFaturação Eletrónica: Permitido\nObrigação de Subcontratação:\nCódigo da Obrigação de Subcontratação: Não é aplicável nenhuma obrigação de subcontratação.\n\n25 - COMPRA PÚBLICA ESTRATÉGICA\nCompra Pública Estratégica: Inexistência de contratação pública estratégica\n\n26 - INFORMAÇÕES ADICIONAIS\nContrato adequado para PME: Sim\nCobertura ACP (Acordo dos Contratos Públicos da Organização Mundial do Comércio): Não\n\n27 - IDENTIFICAÇÃO E CONTACTOS DO ÓRGÃO DE RECURSOS ADMINISTRATIVOS\nDesignação: Câmara Municipal de Ourém\nEndereço: Praça D. Maria II, n.º 1\nCódigo postal: 2490-499\nLocalidade: Ourém\nTelefone: 351249540900\nFax: 351249540908\nEndereço eletrónico: geral@mail.cm-ourem.pt\nPrazo de interposição do recurso: 5 dias\n\n28 - IDENTIFICAÇÃO DO(S) AUTOR(ES) DE ANÚNCIO\nNome: Luís Miguel Albuquerque\nCargo: Presidente de Câmara\n419615855",
    "nipc": "501280740",
    "distrito": "Santarém",
    "concelho": "Ourém",
    "freguesia": "Freguesia de Nossa Senhora da Piedade",
    "site": "https://www.ourem.pt",
    "email": "geral@mail.cm-ourem.pt",
    "designacao_contrato": "P222/2025 - Prestação de Serviços de Limpeza Urbana no Município de Ourém - 2026-2029 (MGD: 71887/2025)",
    "descricao": "P222/2025 - Prestação de Serviços de Limpeza Urbana no Município de Ourém - 2026-2029 (MGD: 71887/2025)",
    "preco_base": "2.700.000,00 EUR",
    "prazo_execucao": "36 MESES",
    "prazo_apresentacao_propostas": "13-11-2025 23:59",
    "fundos_eu": "Não",
    "plataforma_eletronica": "ACIN",
    "url_procedimento": "https://www.acingov.pt",
    "autor_nome": "Luís Miguel Albuquerque",
    "autor_cargo": "Presidente de Câmara"
  },
  {
    "numero_procedimento": "N/A",
    "entidade": "Município de Vila do Bispo",
    "link": "https://diariodarepublica.pt/dr/detalhe/contrato-publico/26488-938923380",
    "detalhes_completos": "1 - IDENTIFICAÇÃO E CONTACTOS DA ENTIDADE ADJUDICANTE\nDesignação da entidade adjudicante: Município de Vila do Bispo\nNIPC: 506730573\nEndereço: Pç. Município\nCódigo postal: 8650-407\nLocalidade: Faro\nPaís: Portugal\nNUT III: PT150\nDistrito: Faro\nConcelho: Vila do Bispo\nFreguesia: Todas\nTelefone: 282630600\nFax: 282639208\nEndereço da Entidade (URL): http://www.cm-viladobispo.pt\nEndereço Eletrónico: geral@cm-viladobispo.pt\neDelivery Gateway (URL): https://community.vortal.biz/public/\nFunção da Organização: Adquirente\nNorma jurídica da Entidade Adjudicante: Organismo de direito público\nÁrea de atividade da Autoridade Adjudicante: Serviços públicos das administrações públicas\n\n2 - JORNAL OFICIAL DA UNIÃO EUROPEIA\nO procedimento a que este anúncio diz respeito também é publicitado no Jornal Oficial da União Europeia? Sim\n\n3 - AVISO\nModelo de Anúncio: Concurso público\nData de Envio do Anúncio: 06-10-2025\n\n5 - PROCESSO\nTipo de Procedimento: Concurso público\nPreço base do procedimento: Sim\nValor do preço base do procedimento: 703.100,00 EUR\nProcedimento com lotes? Não\n\n6 - OBJETO DO CONTRATO\nNúmero de referência interna: DGM 88/2025 Sistema de telegestão\nDesignação do contrato: Concurso público para aquisição, instalação e colocação em serviço do sistema de telegestão nos sistemas de abastecimento de água e drenagem de águas residuais no Município de Vila do Bispo\nDescrição: Aquisição, instalação e colocação em serviço do sistema de telegestão nos sistemas de abastecimento de água e drenagem de águas residuais no Município de Vila do Bispo\nOpções: Não\nTipo de Contrato Principal: Aquisição de Serviços\nTipo de Contrato: Aquisição de Serviços\nClassificação CPV (Vocabulário Comum para os Contratos Públicos)\nObjeto principal\nVocabulário Principal: 71356000\nPreço base s/IVA: 703.100,00 EUR\n\n7 - INDICAÇÕES ADICIONAIS\nO contrato envolve aquisição conjunta (satisfação de várias entidades)? Não\nO contrato é adjudicado por uma central de compras? Não\n\n8 - TÉCNICAS\nO concurso destina-se à celebração de um acordo-quadro? Inexistência de acordo-quadro\nÉ utilizado um leilão eletrónico? Não\nÉ adotada uma fase de negociação? Não\nSistema de Aquisição Dinâmico: Inexistência de sistema de aquisição dinâmico\n\n9 - LOCAL DA EXECUÇÃO DO CONTRATO\nLOCAL DA EXECUÇÃO DO CONTRATO (PROCEDIMENTO)\nPaís: Portugal\nNUT III: PT150\nLocalidade: Faro\nDistrito: Faro\nConcelho: Vila do Bispo\nFreguesia: Freguesia de Vila do Bispo e Raposeira\n\n10 - PRAZO DE EXECUÇÃO DO CONTRATO\nPrazo de execução do contrato: 120 DIAS\nPrevisão de renovações: Não\n\n11 - FUNDOS EU\nTêm fundos EU? Não\n\n12 - DOCUMENTOS DE HABILITAÇÃO\nHabilitação para o exercício da atividade profissional: Não\n\n13 - CONDIÇÕES DE APRESENTAÇÃO\nPlataforma eletrónica utilizada pela entidade adjudicante: VORTAL\nURL para Apresentação: https://community.vortal.biz/public/\nAdmissibilidade da apresentação de propostas variantes: Não autorizado\nPrazo para apresentação das propostas: 08-11-2025 15:00\nPrazo durante o qual os concorrentes são obrigados a manter as respetivas propostas: 66 dias a contar do termo do prazo para a apresentação das propostas\nApresentação de Catálogo Eletrónico: Permitido\nIndicação de Subcontratação na Proposta: Inexistência de indicação de subcontratação\n\n14 - PRESTAÇÃO DE CAUÇÃO\nPrestação de caução: Não\n\n15 - FORNECIMENTO DAS PEÇAS DO CONCURSO, APRESENTAÇÃO DE PEDIDOS DE PARTICIPAÇÃO E APRESENTAÇÃO DAS PROPOSTAS\nLink para acesso às peças do concurso (URL): https://community.vortal.biz/Public/public-tender-documents/MFhMWnRxVVJRNSs0cU1kYjM2WUJRdkpkU1ZOZjVQNXdOV1U3WjhjWGVzNHlpUjFZdHVkazNLZitwaUQ4a0sxMmMrSDJtU2F5Y012UC8vY2htYUc4V0E9PSpuJCRp\n\n20 - OUTROS REQUISITOS\nInformação sobre contratos reservados. Aplica-se a contratos reservados (54º-A)? Não\n\n21 - CRITÉRIO DE ADJUDICAÇÃO\nMultifator: Não\nMonofator:\nNome: Preço\n\n24 - CONDIÇÕES DO CONTRATO\nFaturação Eletrónica: Permitido\nObrigação de Subcontratação:\nCódigo da Obrigação de Subcontratação: Não é aplicável nenhuma obrigação de subcontratação.\n\n25 - COMPRA PÚBLICA ESTRATÉGICA\nCompra Pública Estratégica: Inexistência de contratação pública estratégica\n\n26 - INFORMAÇÕES ADICIONAIS\nContrato adequado para PME: Sim\nCobertura ACP (Acordo dos Contratos Públicos da Organização Mundial do Comércio): Não\n\n27 - IDENTIFICAÇÃO E CONTACTOS DO ÓRGÃO DE RECURSOS ADMINISTRATIVOS\nDesignação: Câmara Municipal\nEndereço: Pç. Município\nCódigo postal: 8650-407\nLocalidade: Vila do Bispo\nTelefone: +351 282630600\nFax: +351 282639208\nEndereço eletrónico: geral@cm-viladobispo.pt\n\n28 - IDENTIFICAÇÃO DO(S) AUTOR(ES) DE ANÚNCIO\nNome: Dora Isabel da Silva Rosado Guerreiro\nCargo: Vice-Presidente da Câmara Municipal\n419618463",
    "nipc": "506730573",
    "distrito": "Faro",
    "concelho": "Vila do Bispo",
    "freguesia": "Todas",
    "site": "http://www.cm-viladobispo.pt",
    "email": "geral@cm-viladobispo.pt",
    "designacao_contrato": "Concurso público para aquisição, instalação e colocação em serviço do sistema de telegestão nos sistemas de abastecimento de água e drenagem de águas residuais no Município de Vila do Bispo",
    "descricao": "Aquisição, instalação e colocação em serviço do sistema de telegestão nos sistemas de abastecimento de água e drenagem de águas residuais no Município de Vila do Bispo",
    "preco_base": "703.100,00 EUR",
    "prazo_execucao": "120 DIAS",
    "prazo_apresentacao_propostas": "08-11-2025 15:00",
    "fundos_eu": "Não",
    "plataforma_eletronica": "VORTAL",
    "url_procedimento": "https://community.vortal.biz/public/",
    "autor_nome": "Dora Isabel da Silva Rosado Guerreiro",
    "autor_cargo": "Vice-Presidente da Câmara Municipal"
  },
  {
    "numero_procedimento": "N/A",
    "entidade": "Faculdade de Medicina Veterinária",
    "link": "https://diariodarepublica.pt/dr/detalhe/contrato-publico/26490-938923384",
    "detalhes_completos": "1 - IDENTIFICAÇÃO E CONTACTOS DA ENTIDADE ADJUDICANTE\nDesignação da entidade adjudicante: Faculdade de Medicina Veterinária\nNIPC: 502286326\nServiço/Órgão/Pessoa de contacto: Gabinete de Aprovisionamento e Património da FMV\nEndereço: Av.ª da Universidade Técnica\nCódigo postal: 1300-477\nLocalidade: Lisboa\nPaís: Portugal\nNUT III: PT170\nDistrito: Lisboa\nConcelho: Lisboa\nFreguesia: Freguesia de Ajuda\nTelefone: 213652800\nFax: 213652800\nEndereço da Entidade (URL): https://www.fmv.ulisboa.pt/\nEndereço Eletrónico: cg@fmv.ulisboa.pt\neDelivery Gateway (URL): https://www.acingov.pt\nFunção da Organização: Adquirente\nNorma jurídica da Entidade Adjudicante: Organismo de direito público\nÁrea de atividade da Autoridade Adjudicante: Serviços públicos das administrações públicas\n\n2 - JORNAL OFICIAL DA UNIÃO EUROPEIA\nO procedimento a que este anúncio diz respeito também é publicitado no Jornal Oficial da União Europeia? Não\n\n3 - AVISO\nModelo de Anúncio: Concurso público\nData de Envio do Anúncio: 08-10-2025\n\n5 - PROCESSO\nTipo de Procedimento: Concurso público\nPreço base do procedimento: Sim\nValor do preço base do procedimento: 115.560,00 EUR\nProcedimento com lotes? Sim\nNº Máx. de Lotes Autorizado: 5\nNúmero máximo de lotes que podem ser adjudicados a um concorrente: 5\n\n6 - OBJETO DO CONTRATO\nNúmero de referência interna: Concurso Público 11/FMV/2025\nDesignação do contrato: Concurso Público 11/FMV/2025 - AQUISIÇÃO DE EQUIPAMENTOS E MATERIAL PARA BIOSSEGURANÇA DA FMV\nDescrição: Concurso Público 11/FMV/2025 - AQUISIÇÃO DE EQUIPAMENTOS E MATERIAL PARA BIOSSEGURANÇA DA FMV\nTipo de Contrato Principal: Aquisição de Bens Móveis\nTipo de Contrato: Aquisição de Bens Móveis\nClassificação CPV (Vocabulário Comum para os Contratos Públicos)\nObjeto principal\nVocabulário Principal: 35113400\nPreço base s/IVA: 29.780,00 EUR\nObjeto Complementar\nVocabulário Principal: 33933100\nPreço base s/IVA: 18.390,00 EUR\nObjeto Complementar\nVocabulário Principal: 39150000\nPreço base s/IVA: 34.695,00 EUR\nObjeto Complementar\nVocabulário Principal: 42995000\nPreço base s/IVA: 32.695,00 EUR\nLotes: \nNº: LOT-0001\nDescrição do Lote: Lava botas automático, lava aventais, lava-mãos 3 bicas, cabides de aventais, suporte para botas de parede, lava botas manual, pedilúvio, estantes inox, carro roupa limpa inox\nPreço base s/IVA: 32.695,00 EUR\nClassificação CPV (Vocabulário Comum para os Contratos Públicos)\nObjeto principal\nVocabulário Principal: 42995000\nNº: LOT-0002\nDescrição do Lote: Banco corrido tampo madeira 2m, cacifos 3x3, cacifos 3x4, cacifos 3x2, 5x3, cabides de parede, bancos corridos, armários portas de abrir\nPreço base s/IVA: 34.695,00 EUR\nClassificação CPV (Vocabulário Comum para os Contratos Públicos)\nObjeto principal\nVocabulário Principal: 39150000\nNº: LOT-0003\nDescrição do Lote: Material lavável: Botas, galochas, aventais de trabalho, jardineiras, manguitos (mangas)\nPreço base s/IVA: 7.890,00 EUR\nClassificação CPV (Vocabulário Comum para os Contratos Públicos)\nObjeto principal\nVocabulário Principal: 35113400\nNº: LOT-0004\nDescrição do Lote: Batas brancas, pijamas cirúrgicos\nPreço base s/IVA: 21.890,00 EUR\nClassificação CPV (Vocabulário Comum para os Contratos Públicos)\nObjeto principal\nVocabulário Principal: 35113400\nNº: LOT-0005\nDescrição do Lote: Mesas de autópsia com pia\nPreço base s/IVA: 18.390,00 EUR\nClassificação CPV (Vocabulário Comum para os Contratos Públicos)\nObjeto principal\nVocabulário Principal: 33933100\n\n7 - INDICAÇÕES ADICIONAIS\nO contrato envolve aquisição conjunta (satisfação de várias entidades)? Não\nO contrato é adjudicado por uma central de compras? Não\n\n8 - TÉCNICAS\nO concurso destina-se à celebração de um acordo-quadro? Inexistência de acordo-quadro\nÉ utilizado um leilão eletrónico? Não\nÉ adotada uma fase de negociação? Não\nSistema de Aquisição Dinâmico: Inexistência de sistema de aquisição dinâmico\n\n9 - LOCAL DA EXECUÇÃO DO CONTRATO\nLOCAL DA EXECUÇÃO DO CONTRATO (PROCEDIMENTO)\nPaís: Portugal\nNUT III: PT170\nLocalidade: Freguesia de Ajuda\nDistrito: Lisboa\nConcelho: Lisboa\nFreguesia: Freguesia de Ajuda\nLOCAL DA EXECUÇÃO DO CONTRATO (LOTE)\nIdentificador do Lote: LOT-0001; LOT-0002; LOT-0003; LOT-0004; LOT-0005\nPaís: Portugal\nNUT III: PT170\nLocalidade: Freguesia de Ajuda\nDistrito: Lisboa\nConcelho: Lisboa\nFreguesia: Freguesia de Ajuda\n\n10 - PRAZO DE EXECUÇÃO DO CONTRATO\nIdentificador do Lote: LOT-0001; LOT-0002; LOT-0003; LOT-0004; LOT-0005\nPrazo de execução do contrato: 30 DIAS\nPrevisão de renovações: Não\n\n11 - FUNDOS EU\nIdentificador do Lote: LOT-0001; LOT-0002; LOT-0003; LOT-0004; LOT-0005\nTêm fundos EU? Não\n\n12 - DOCUMENTOS DE HABILITAÇÃO\nHabilitação para o exercício da atividade profissional: Não\n\n13 - CONDIÇÕES DE APRESENTAÇÃO\nPlataforma eletrónica utilizada pela entidade adjudicante: ACIN\nURL para Apresentação: https://www.acingov.pt\nAdmissibilidade da apresentação de propostas variantes: Não autorizado\nPrazo para apresentação das propostas: 23-10-2025 23:59\nPrazo durante o qual os concorrentes são obrigados a manter as respetivas propostas: 66 dias a contar do termo do prazo para a apresentação das propostas\nIndicação de Subcontratação na Proposta: Inexistência de indicação de subcontratação\n\n14 - PRESTAÇÃO DE CAUÇÃO\nPrestação de caução: Não\n\n15 - FORNECIMENTO DAS PEÇAS DO CONCURSO, APRESENTAÇÃO DE PEDIDOS DE PARTICIPAÇÃO E APRESENTAÇÃO DAS PROPOSTAS\nLink para acesso às peças do concurso (URL): https://www.acingov.pt/acingovprod/2/zonaPublica/zona_publica_c/donwloadProcedurePiece/OTg0OTYy\n\n20 - OUTROS REQUISITOS\nIdentificador do Lote: LOT-0001; LOT-0002; LOT-0003; LOT-0004; LOT-0005\nInformação sobre contratos reservados. Aplica-se a contratos reservados (54º-A)? Não\n\n21 - CRITÉRIO DE ADJUDICAÇÃO\nO Critério de adjudicação é diferenciado por lote? Não\nMultifator: Não\nMonofator:\nNome: Preço\n\n24 - CONDIÇÕES DO CONTRATO\nIdentificador do Lote: LOT-0001; LOT-0002; LOT-0003; LOT-0004; LOT-0005\nFaturação Eletrónica: Permitido\nObrigação de Subcontratação:\nCódigo da Obrigação de Subcontratação: Não é aplicável nenhuma obrigação de subcontratação.\n\n25 - COMPRA PÚBLICA ESTRATÉGICA\nCompra Pública Estratégica: Inexistência de contratação pública estratégica\n\n26 - INFORMAÇÕES ADICIONAIS\nIdentificador do Lote: LOT-0001; LOT-0002; LOT-0003; LOT-0004; LOT-0005\nContrato adequado para PME: Não\nCobertura ACP (Acordo dos Contratos Públicos da Organização Mundial do Comércio): Não\n\n27 - IDENTIFICAÇÃO E CONTACTOS DO ÓRGÃO DE RECURSOS ADMINISTRATIVOS\nDesignação: Faculdade de Medicina Veterinária - ULisboa\nEndereço: Av.ª da Universidade Técnica\nCódigo postal: 1300-477\nLocalidade: Lisboa\nTelefone: 213652800\nFax: 213652800\nEndereço eletrónico: cg@fmv.ulisboa.pt\nPrazo de interposição do recurso: 10 dias\n\n28 - IDENTIFICAÇÃO DO(S) AUTOR(ES) DE ANÚNCIO\nNome: Fábio Jorge Carvalho Costa\nCargo: tÉCNICO sUPERIOR\n419633059",
    "nipc": "502286326",
    "distrito": "Lisboa",
    "concelho": "Lisboa",
    "freguesia": "Freguesia de Ajuda",
    "site": "https://www.fmv.ulisboa.pt/",
    "email": "cg@fmv.ulisboa.pt",
    "designacao_contrato": "Concurso Público 11/FMV/2025 - AQUISIÇÃO DE EQUIPAMENTOS E MATERIAL PARA BIOSSEGURANÇA DA FMV",
    "descricao": "Concurso Público 11/FMV/2025 - AQUISIÇÃO DE EQUIPAMENTOS E MATERIAL PARA BIOSSEGURANÇA DA FMV",
    "preco_base": "29.780,00 EUR",
    "prazo_execucao": "30 DIAS",
    "prazo_apresentacao_propostas": "23-10-2025 23:59",
    "fundos_eu": "Não",
    "plataforma_eletronica": "ACIN",
    "url_procedimento": "https://www.acingov.pt",
    "autor_nome": "Fábio Jorge Carvalho Costa",
    "autor_cargo": "tÉCNICO sUPERIOR"
  },
  {
    "numero_procedimento": "N/A",
    "entidade": "Instituto Superior de Engenharia de Lisboa",
    "link": "https://diariodarepublica.pt/dr/detalhe/contrato-publico/26496-938923386",
    "detalhes_completos": "1 - IDENTIFICAÇÃO E CONTACTOS DA ENTIDADE ADJUDICANTE\nDesignação da entidade adjudicante: Instituto Superior de Engenharia de Lisboa\nNIPC: 600016234\nServiço/Órgão/Pessoa de contacto: Núcleo de Aprovisionamento e Património do ISEL\nEndereço: Rua Conselheiro Emídio Navarro n.º 1\nCódigo postal: 1959-007\nLocalidade: Lisboa\nPaís: Portugal\nNUT III: PT170\nDistrito: Lisboa\nConcelho: Lisboa\nFreguesia: Freguesia de Marvila - Lisboa\nTelefone: 218317240\nFax: 218317240\nEndereço da Entidade (URL): www.isel.pt\nEndereço Eletrónico: procedimentos.nap@isel.pt\nFunção da Organização: Adquirente\nNorma jurídica da Entidade Adjudicante: Autoridade da administração central\nÁrea de atividade da Autoridade Adjudicante: Educação\n\n2 - JORNAL OFICIAL DA UNIÃO EUROPEIA\nO procedimento a que este anúncio diz respeito também é publicitado no Jornal Oficial da União Europeia? Não\n\n3 - AVISO\nModelo de Anúncio: Concurso público\nData de Envio do Anúncio: 08-10-2025\n\n5 - PROCESSO\nTipo de Procedimento: Concurso público\nPreço base do procedimento: Sim\nValor do preço base do procedimento: 55.899,20 EUR\nProcedimento com lotes? Não\n\n6 - OBJETO DO CONTRATO\nNúmero de referência interna: 49/ISEL/2025\nDesignação do contrato: Concurso Público para Aquisição de Serviços Técnicos Especializados de Informática\nDescrição: Aquisição de Serviços Técnicos Especializados de Informática\nTipo de Contrato Principal: Aquisição de Serviços\nTipo de Contrato: Aquisição de Serviços\nClassificação CPV (Vocabulário Comum para os Contratos Públicos)\nObjeto principal\nVocabulário Principal: 72500000\nPreço base s/IVA: 55.899,20 EUR\n\n7 - INDICAÇÕES ADICIONAIS\nO contrato envolve aquisição conjunta (satisfação de várias entidades)? Não\nO contrato é adjudicado por uma central de compras? Não\n\n8 - TÉCNICAS\nO concurso destina-se à celebração de um acordo-quadro? Inexistência de acordo-quadro\nÉ utilizado um leilão eletrónico? Não\nÉ adotada uma fase de negociação? Não\nSistema de Aquisição Dinâmico: Inexistência de sistema de aquisição dinâmico\n\n9 - LOCAL DA EXECUÇÃO DO CONTRATO\nLOCAL DA EXECUÇÃO DO CONTRATO (PROCEDIMENTO)\nPaís: Portugal\nNUT III: PT170\nLocalidade: Lisboa\nDistrito: Lisboa\nConcelho: Lisboa\nFreguesia: Freguesia de Marvila - Lisboa\n\n10 - PRAZO DE EXECUÇÃO DO CONTRATO\nPrazo de execução do contrato: 12 MESES\nPrevisão de renovações: Não\n\n11 - FUNDOS EU\nTêm fundos EU? Não\n\n12 - DOCUMENTOS DE HABILITAÇÃO\nHabilitação para o exercício da atividade profissional: Não\n\n13 - CONDIÇÕES DE APRESENTAÇÃO\nPlataforma eletrónica utilizada pela entidade adjudicante: COMPRASPT\nURL para Apresentação: https://www.compraspt.com/cpt-isel/faces/\nAdmissibilidade da apresentação de propostas variantes: Não autorizado\nPrazo para apresentação das propostas: 14-10-2025 23:59\nPrazo durante o qual os concorrentes são obrigados a manter as respetivas propostas: 66 dias a contar do termo do prazo para a apresentação das propostas\nApresentação de Catálogo Eletrónico: Necessário\nIndicação de Subcontratação na Proposta: O(s) subcontratante(s) proposto(s) necessário(s) para cumprir a obrigação de subcontratar uma percentagem mínima do contrato\n\n14 - PRESTAÇÃO DE CAUÇÃO\nPrestação de caução: Não\n\n15 - FORNECIMENTO DAS PEÇAS DO CONCURSO, APRESENTAÇÃO DE PEDIDOS DE PARTICIPAÇÃO E APRESENTAÇÃO DAS PROPOSTAS\nLink para acesso às peças do concurso (URL): https://www.compraspt.com/cpt-isel/faces/app/acessoDocs.jsp?codigoAcesso=QmFGfSkDKRrbgkt8ORW4gvalYncHPsmEjXWB82GlTQ0BKLEWwx\n\n20 - OUTROS REQUISITOS\nInformação sobre contratos reservados. Aplica-se a contratos reservados (54º-A)? Não\n\n21 - CRITÉRIO DE ADJUDICAÇÃO\nMultifator: Não\nMonofator:\nNome: Preço\n\n24 - CONDIÇÕES DO CONTRATO\nFaturação Eletrónica: Permitido\nObrigação de Subcontratação:\nCódigo da Obrigação de Subcontratação: Não é aplicável nenhuma obrigação de subcontratação.\n\n25 - COMPRA PÚBLICA ESTRATÉGICA\nCompra Pública Estratégica: Inexistência de contratação pública estratégica\n\n26 - INFORMAÇÕES ADICIONAIS\nContrato adequado para PME: Sim\nCobertura ACP (Acordo dos Contratos Públicos da Organização Mundial do Comércio): Não\n\n27 - IDENTIFICAÇÃO E CONTACTOS DO ÓRGÃO DE RECURSOS ADMINISTRATIVOS\nDesignação: Presidente do ISEL\nEndereço: presidente@isel.pt\nCódigo postal: 1959-007\nLocalidade: Lisboa\nEndereço eletrónico: procedimentos.nap@isel.pt\nPrazo de interposição do recurso: 5 dias\n\n28 - IDENTIFICAÇÃO DO(S) AUTOR(ES) DE ANÚNCIO\nNome: José M. P. do Nascimento\nCargo: Presidente do ISEL\n419630191",
    "nipc": "600016234",
    "distrito": "Lisboa",
    "concelho": "Lisboa",
    "freguesia": "Freguesia de Marvila - Lisboa",
    "site": "www.isel.pt",
    "email": "procedimentos.nap@isel.pt",
    "designacao_contrato": "Concurso Público para Aquisição de Serviços Técnicos Especializados de Informática",
    "descricao": "Aquisição de Serviços Técnicos Especializados de Informática",
    "preco_base": "55.899,20 EUR",
    "prazo_execucao": "12 MESES",
    "prazo_apresentacao_propostas": "14-10-2025 23:59",
    "fundos_eu": "Não",
    "plataforma_eletronica": "COMPRASPT",
    "url_procedimento": "https://www.compraspt.com/cpt-isel/faces/",
    "autor_nome": "José M. P. do Nascimento",
    "autor_cargo": "Presidente do ISEL"
  },
  {
    "numero_procedimento": "N/A",
    "entidade": "AdRA - Águas da Região de Aveiro, S. A.",
    "link": "https://diariodarepublica.pt/dr/detalhe/contrato-publico/26501-938923409",
    "detalhes_completos": "1 - IDENTIFICAÇÃO E CONTACTOS DA ENTIDADE ADJUDICANTE\nDesignação da entidade adjudicante: AdRA - Águas da Região de Aveiro, S. A.\nNIPC: 509107630\nServiço/Órgão/Pessoa de contacto: AdRA - Águas da Região de Aveiro, S.A\nEndereço: travessa da Rua da Paz, n.º 4,\nCódigo postal: 3800-587\nLocalidade: Cacia - Aveiro\nPaís: Portugal\nNUT III: PT16D\nDistrito: Aveiro\nConcelho: Aveiro\nFreguesia: Freguesia de Cacia\nTelefone: 234910200\nFax: 234910299\nEndereço da Entidade (URL): http://www.adra.pt.\nEndereço Eletrónico: adra@adp.pt\neDelivery Gateway (URL): https://www.acingov.pt\nFunção da Organização: Adquirente\nSubfunção da Organização: Organização cujo orçamento é utilizado para pagar o contrato; Organização que executa o pagamento; Organização responsável pelo tratamento das propostas; Organização que recebe as propostas; Organização que trata os pedidos de participação; Organização que recebe pedidos de participação; Organização que assina o contrato\nNorma jurídica da Entidade Adjudicante: Organismo de direito público\nÁrea de atividade da Entidade Adjudicante: Atividades relacionadas com a água\n\n2 - JORNAL OFICIAL DA UNIÃO EUROPEIA\nO procedimento a que este anúncio diz respeito também é publicitado no Jornal Oficial da União Europeia? Não\n\n3 - AVISO\nModelo de Anúncio: Concurso público\nData de Envio do Anúncio: 08-10-2025\n\n5 - PROCESSO\nTipo de Procedimento: Concurso público\nPreço base do procedimento: Sim\nValor do preço base do procedimento: 50.000,00 EUR\nProcedimento com lotes? Não\n\n6 - OBJETO DO CONTRATO\nNúmero de referência interna: CP/2025/39_DEGA\nDesignação do contrato: Renovação da Rede de AA na Rua do Sobral de Baixo - Sever do Vouga\nDescrição: Renovação da Rede de AA na Rua do Sobral de Baixo - Sever do Vouga\nTipo de Contrato Principal: Empreitada de Obras Públicas\nTipo de Contrato: Empreitada de Obras Públicas\nClassificação CPV (Vocabulário Comum para os Contratos Públicos)\nObjeto principal\nVocabulário Principal: 45232151\nPreço base s/IVA: 50.000,00 EUR\n\n7 - INDICAÇÕES ADICIONAIS\nO contrato envolve aquisição conjunta (satisfação de várias entidades)? Não\nO contrato é adjudicado por uma central de compras? Não\n\n8 - TÉCNICAS\nO concurso destina-se à celebração de um acordo-quadro? Inexistência de acordo-quadro\nÉ utilizado um leilão eletrónico? Não\nÉ adotada uma fase de negociação? Não\nSistema de Aquisição Dinâmico: Inexistência de sistema de aquisição dinâmico\n\n9 - LOCAL DA EXECUÇÃO DO CONTRATO\nLOCAL DA EXECUÇÃO DO CONTRATO (PROCEDIMENTO)\nPaís: Portugal\nNUT III: PT16D\nLocalidade: Freguesia de Sever do Vouga\nDistrito: Aveiro\nConcelho: Sever do Vouga\nFreguesia: Freguesia de Sever do Vouga\n\n10 - PRAZO DE EXECUÇÃO DO CONTRATO\nPrazo de execução do contrato: 90 DIAS\nPrevisão de renovações: Não\n\n11 - FUNDOS EU\nTêm fundos EU? Não\n\n12 - DOCUMENTOS DE HABILITAÇÃO\nHabilitação para o exercício da atividade profissional: Sim\nTipo: Alvará\nDescrição: Definidas no programa do procedimento\n\n13 - CONDIÇÕES DE APRESENTAÇÃO\nPlataforma eletrónica utilizada pela entidade adjudicante: ACIN\nURL para Apresentação: https://www.acingov.pt\nAdmissibilidade da apresentação de propostas variantes: Não autorizado\nPrazo para apresentação das propostas: 07-11-2025 18:00\nPrazo durante o qual os concorrentes são obrigados a manter as respetivas propostas: 66 dias a contar do termo do prazo para a apresentação das propostas\nIndicação de Subcontratação na Proposta: Inexistência de indicação de subcontratação\n\n14 - PRESTAÇÃO DE CAUÇÃO\nPrestação de caução: Não\n\n15 - FORNECIMENTO DAS PEÇAS DO CONCURSO, APRESENTAÇÃO DE PEDIDOS DE PARTICIPAÇÃO E APRESENTAÇÃO DAS PROPOSTAS\nLink para acesso às peças do concurso (URL): https://www.acingov.pt/acingovprod/2/zonaPublica/zona_publica_c/donwloadProcedurePiece/OTg0ODkw\n\n20 - OUTROS REQUISITOS\nInformação sobre contratos reservados. Aplica-se a contratos reservados (54º-A)? Não\n\n21 - CRITÉRIO DE ADJUDICAÇÃO\nMultifator: Não\nMonofator:\nNome: Preço\n\n24 - CONDIÇÕES DO CONTRATO\nFaturação Eletrónica: Necessário\nObrigação de Subcontratação:\nCódigo da Obrigação de Subcontratação: Não é aplicável nenhuma obrigação de subcontratação.\n\n25 - COMPRA PÚBLICA ESTRATÉGICA\nCompra Pública Estratégica: Redução dos impactos ambientais; Realização dos objetivos sociais\nDescrição do Processo de Adjudicação Estratégico: Nos termos assinalados na declaração de subscrição dos valores e compromissos nas vertentes de qualidade, ambiente, higiene, segurança e saúde no trabalho (HSST) e responsabilidade social da entidade adjudicante, definidos na Política de Gestão e no Código de Conduta a Fornecedores\nCritérios de contratos Públicos Ecológicos: Critérios de contratação pública ecológica nacional\nCategorias da estratégia nacional: Infraestruturas de tratamento de águas residuais\nContratos Públicos Ecológicos: Outros; A prevenção e o controlo da poluição\nDiretiva Veículos Não Poluentes: Não\nContratos Públicos Sociais: Condições de trabalho justas; Igualdade de género; Igualdade étnica; Outros\nCritério de Acessibilidade: Os critérios de acessibilidade para as pessoas com deficiência não estão incluídos porque o contrato não se destina a pessoas singulares\n\n26 - INFORMAÇÕES ADICIONAIS\nContrato adequado para PME: Sim\nCobertura ACP (Acordo dos Contratos Públicos da Organização Mundial do Comércio): Não\n\n27 - IDENTIFICAÇÃO E CONTACTOS DO ÓRGÃO DE RECURSOS ADMINISTRATIVOS\nDesignação: Tribunal Administrativo e Fiscal do Porto\nEndereço: Rua Duque da Terceira, 333\nCódigo postal: 4000-537\nLocalidade: Porto\nTelefone: 225198400\nFax: 225198499\nEndereço eletrónico: porto.taf@tribunais.org.pt\n\n28 - IDENTIFICAÇÃO DO(S) AUTOR(ES) DE ANÚNCIO\nNome: Susana Goretti Silva\nCargo: Gestora de Procedimentos\n419630572",
    "nipc": "509107630",
    "distrito": "Aveiro",
    "concelho": "Aveiro",
    "freguesia": "Freguesia de Cacia",
    "site": "http://www.adra.pt.",
    "email": "adra@adp.pt",
    "designacao_contrato": "Renovação da Rede de AA na Rua do Sobral de Baixo - Sever do Vouga",
    "descricao": "Renovação da Rede de AA na Rua do Sobral de Baixo - Sever do Vouga",
    "preco_base": "50.000,00 EUR",
    "prazo_execucao": "90 DIAS",
    "prazo_apresentacao_propostas": "07-11-2025 18:00",
    "fundos_eu": "Não",
    "plataforma_eletronica": "ACIN",
    "url_procedimento": "https://www.acingov.pt",
    "autor_nome": "Susana Goretti Silva",
    "autor_cargo": "Gestora de Procedimentos"
  },
  {
    "numero_procedimento": "N/A",
    "entidade": "Águas do Norte, S. A.",
    "link": "https://diariodarepublica.pt/dr/detalhe/contrato-publico/26502-938923410",
    "detalhes_completos": "1 - IDENTIFICAÇÃO E CONTACTOS DA ENTIDADE ADJUDICANTE\nDesignação da entidade adjudicante: Águas do Norte, S. A.\nNIPC: 513606084\nServiço/Órgão/Pessoa de contacto: Compras e Logística\nEndereço: Rua Dom Pedro de Castro, N.º 1A\nCódigo postal: 5000-669\nLocalidade: Vila Real\nPaís: Portugal\nNUT III: PT11D\nDistrito: Vila Real\nConcelho: Vila Real\nFreguesia: Freguesia de Vila Real\nTelefone: 259309370\nFax: 259309371\nEndereço da Entidade (URL): www.adnorte.pt\nEndereço Eletrónico: geral.adnorte@adp.pt\neDelivery Gateway (URL): https://www.acingov.pt\nFunção da Organização: Adquirente\nNorma jurídica da Entidade Adjudicante: Organismo de direito público\nÁrea de atividade da Autoridade Adjudicante: Serviços públicos das administrações públicas\n\n2 - JORNAL OFICIAL DA UNIÃO EUROPEIA\nO procedimento a que este anúncio diz respeito também é publicitado no Jornal Oficial da União Europeia? Não\n\n3 - AVISO\nModelo de Anúncio: Concurso público\nData de Envio do Anúncio: 09-10-2025\n\n5 - PROCESSO\nTipo de Procedimento: Concurso público\nPreço base do procedimento: Sim\nValor do preço base do procedimento: 26.100,00 EUR\nProcedimento com lotes? Não\n\n6 - OBJETO DO CONTRATO\nNúmero de referência interna: PRC_0327/2025_DEX\nDesignação do contrato: PRC_0327/2025_DEX - Aquisição de contentores multibenne para a Águas do Norte, S.A.\nDescrição: PRC_0327/2025_DEX - Aquisição de contentores multibenne para a Águas do Norte, S.A.\nTipo de Contrato Principal: Aquisição de Bens Móveis\nTipo de Contrato: Aquisição de Bens Móveis\nClassificação CPV (Vocabulário Comum para os Contratos Públicos)\nObjeto principal\nVocabulário Principal: 44613800\nPreço base s/IVA: 26.100,00 EUR\n\n7 - INDICAÇÕES ADICIONAIS\nO contrato envolve aquisição conjunta (satisfação de várias entidades)? Não\nO contrato é adjudicado por uma central de compras? Não\n\n8 - TÉCNICAS\nO concurso destina-se à celebração de um acordo-quadro? Inexistência de acordo-quadro\nÉ utilizado um leilão eletrónico? Não\nÉ adotada uma fase de negociação? Não\nSistema de Aquisição Dinâmico: Inexistência de sistema de aquisição dinâmico\n\n9 - LOCAL DA EXECUÇÃO DO CONTRATO\nLOCAL DA EXECUÇÃO DO CONTRATO (PROCEDIMENTO)\nPaís: Portugal\nNUT III: PT119\nLocalidade: Freguesia de Lordelo - Guimarães\nDistrito: Braga\nConcelho: Guimarães\nFreguesia: Freguesia de Lordelo - Guimarães\nPaís: Portugal\nNUT III: PT119\nLocalidade: Freguesia de Serzedelo - Guimarães\nDistrito: Braga\nConcelho: Guimarães\nFreguesia: Freguesia de Serzedelo - Guimarães\nPaís: Portugal\nNUT III: PT119\nLocalidade: Freguesia de Fradelos - Vila Nova de Famalicão\nDistrito: Braga\nConcelho: Vila Nova de Famalicão\nFreguesia: Freguesia de Fradelos - Vila Nova de Famalicão\nPaís: Portugal\nNUT III: PT11A\nLocalidade: Todas\nDistrito: Porto\nConcelho: Santo Tirso\nFreguesia: Todas\n\n10 - PRAZO DE EXECUÇÃO DO CONTRATO\nPrazo de execução do contrato: 150 DIAS\nPrevisão de renovações: Não\n\n11 - FUNDOS EU\nTêm fundos EU? Não\n\n12 - DOCUMENTOS DE HABILITAÇÃO\nHabilitação para o exercício da atividade profissional: Não\n\n13 - CONDIÇÕES DE APRESENTAÇÃO\nPlataforma eletrónica utilizada pela entidade adjudicante: ACIN\nURL para Apresentação: https://www.acingov.pt\nAdmissibilidade da apresentação de propostas variantes: Não autorizado\nPrazo para apresentação das propostas: 15-10-2025 17:00\nPrazo durante o qual os concorrentes são obrigados a manter as respetivas propostas: 90 dias a contar do termo do prazo para a apresentação das propostas\nIndicação de Subcontratação na Proposta: Inexistência de indicação de subcontratação\n\n14 - PRESTAÇÃO DE CAUÇÃO\nPrestação de caução: Não\n\n15 - FORNECIMENTO DAS PEÇAS DO CONCURSO, APRESENTAÇÃO DE PEDIDOS DE PARTICIPAÇÃO E APRESENTAÇÃO DAS PROPOSTAS\nLink para acesso às peças do concurso (URL): https://www.acingov.pt/acingovprod/2/zonaPublica/zona_publica_c/donwloadProcedurePiece/OTg0NzEw\n\n20 - OUTROS REQUISITOS\nInformação sobre contratos reservados. Aplica-se a contratos reservados (54º-A)? Não\n\n21 - CRITÉRIO DE ADJUDICAÇÃO\nMultifator: Não\nMonofator:\nNome: Preço\n\n24 - CONDIÇÕES DO CONTRATO\nFaturação Eletrónica: Permitido\nObrigação de Subcontratação:\nCódigo da Obrigação de Subcontratação: Não é aplicável nenhuma obrigação de subcontratação.\n\n25 - COMPRA PÚBLICA ESTRATÉGICA\nCompra Pública Estratégica: Inexistência de contratação pública estratégica\n\n26 - INFORMAÇÕES ADICIONAIS\nContrato adequado para PME: Sim\nCobertura ACP (Acordo dos Contratos Públicos da Organização Mundial do Comércio): Não\n\n27 - IDENTIFICAÇÃO E CONTACTOS DO ÓRGÃO DE RECURSOS ADMINISTRATIVOS\nDesignação: Conselho de Administração da Águas do Norte, S.A.\nEndereço: Rua Dom Pedro de Castro, N.º 1A\nCódigo postal: 5000-669\nLocalidade: Vila Real\nTelefone: 259309370\nFax: 259309371\nEndereço eletrónico: geral.adnorte@adp.pt\n\n28 - IDENTIFICAÇÃO DO(S) AUTOR(ES) DE ANÚNCIO\nNome: Alice Maria Carvalho Alves\nCargo: Técnica Superior de Compras e Logística\n419627584",
    "nipc": "513606084",
    "distrito": "Vila Real",
    "concelho": "Vila Real",
    "freguesia": "Freguesia de Vila Real",
    "site": "www.adnorte.pt",
    "email": "geral.adnorte@adp.pt",
    "designacao_contrato": "PRC_0327/2025_DEX - Aquisição de contentores multibenne para a Águas do Norte, S.A.",
    "descricao": "PRC_0327/2025_DEX - Aquisição de contentores multibenne para a Águas do Norte, S.A.",
    "preco_base": "26.100,00 EUR",
    "prazo_execucao": "150 DIAS",
    "prazo_apresentacao_propostas": "15-10-2025 17:00",
    "fundos_eu": "Não",
    "plataforma_eletronica": "ACIN",
    "url_procedimento": "https://www.acingov.pt",
    "autor_nome": "Alice Maria Carvalho Alves",
    "autor_cargo": "Técnica Superior de Compras e Logística"
  },
  {
    "numero_procedimento": "N/A",
    "entidade": "AnÃºncio de procedimento  n.Âº 26504/2025  -  DiÃ¡rio da RepÃºblica n.Âº 195/2025, SÃ©rie II de 2025-10-09",
    "link": "https://diariodarepublica.pt/dr/detalhe/contrato-publico/26504-938923411"
  },
  {
    "numero_procedimento": "N/A",
    "entidade": "Unidade Local de Saúde do Alto Minho, E. P. E.",
    "link": "https://diariodarepublica.pt/dr/detalhe/contrato-publico/26491-938924585",
    "detalhes_completos": "1 - IDENTIFICAÇÃO E CONTACTOS DA ENTIDADE ADJUDICANTE\nDesignação da entidade adjudicante: Unidade Local de Saúde do Alto Minho, E. P. E.\nNIPC: 508786193\nServiço/Órgão/Pessoa de contacto: Serviço de Aprovisionamento - Sourcing\nEndereço: Estrada de Santa Luzia, Viana do Castelo\nCódigo postal: 4904-858\nLocalidade: Viana do Castelo\nPaís: Portugal\nNUT III: PT111\nDistrito: Viana do Castelo\nConcelho: Viana do Castelo\nFreguesia: União das Freguesias de Viana do Castelo (Santa Maria Maior e Monserrate) e Meadela\nTelefone: 258802381\nFax: 258802389\nEndereço da Entidade (URL): https://www.ulsam.min-saude.pt\nEndereço Eletrónico: sourcing@ulsam.min-saude.pt\neDelivery Gateway (URL): https://community.vortal.biz/public/\nFunção da Organização: Adquirente\nNorma jurídica da Entidade Adjudicante: Organismo de direito público\nÁrea de atividade da Autoridade Adjudicante: Saúde\n\n2 - JORNAL OFICIAL DA UNIÃO EUROPEIA\nO procedimento a que este anúncio diz respeito também é publicitado no Jornal Oficial da União Europeia? Não\n\n3 - AVISO\nModelo de Anúncio: Concurso público\nData de Envio do Anúncio: 08-10-2025\n\n5 - PROCESSO\nTipo de Procedimento: Concurso público\nPreço base do procedimento: Sim\nValor do preço base do procedimento: 105.993,00 EUR\nProcedimento com lotes? Não\n\n6 - OBJETO DO CONTRATO\nNúmero de referência interna: CS-8515-CP-M-250923-A\nDesignação do contrato: Lote de MCDT’s para realização de Estudos Urodinâmicos na ULSAM, EPE\nDescrição: Lote de MCDT’s para realização de Estudos Urodinâmicos na ULSAM, EPE\nTipo de Contrato Principal: Aquisição de Serviços\nTipo de Contrato: Aquisição de Serviços\nClassificação CPV (Vocabulário Comum para os Contratos Públicos)\nObjeto principal\nVocabulário Principal: 85150000\nPreço base s/IVA: 105.993,00 EUR\n\n7 - INDICAÇÕES ADICIONAIS\nO contrato envolve aquisição conjunta (satisfação de várias entidades)? Não\nO contrato é adjudicado por uma central de compras? Não\n\n8 - TÉCNICAS\nO concurso destina-se à celebração de um acordo-quadro? Inexistência de acordo-quadro\nÉ utilizado um leilão eletrónico? Não\nÉ adotada uma fase de negociação? Não\nSistema de Aquisição Dinâmico: Inexistência de sistema de aquisição dinâmico\n\n9 - LOCAL DA EXECUÇÃO DO CONTRATO\nLOCAL DA EXECUÇÃO DO CONTRATO (PROCEDIMENTO)\nPaís: Portugal\nNUT III: PT111\nLocalidade: Viana do Castelo\nDistrito: Viana do Castelo\nConcelho: Viana do Castelo\nFreguesia: União das Freguesias de Viana do Castelo (Santa Maria Maior e Monserrate) e Meadela\n\n10 - PRAZO DE EXECUÇÃO DO CONTRATO\nPrazo de execução do contrato: 2 ANOS\nPrevisão de renovações: Não\n\n11 - FUNDOS EU\nTêm fundos EU? Não\n\n12 - DOCUMENTOS DE HABILITAÇÃO\nHabilitação para o exercício da atividade profissional: Não\n\n13 - CONDIÇÕES DE APRESENTAÇÃO\nPlataforma eletrónica utilizada pela entidade adjudicante: VORTAL\nURL para Apresentação: https://community.vortal.biz/public/\nAdmissibilidade da apresentação de propostas variantes: Não autorizado\nPrazo para apresentação das propostas: 20-10-2025 18:00\nPrazo durante o qual os concorrentes são obrigados a manter as respetivas propostas: 120 dias a contar do termo do prazo para a apresentação das propostas\nIndicação de Subcontratação na Proposta: Inexistência de indicação de subcontratação\n\n14 - PRESTAÇÃO DE CAUÇÃO\nPrestação de caução: Não\n\n15 - FORNECIMENTO DAS PEÇAS DO CONCURSO, APRESENTAÇÃO DE PEDIDOS DE PARTICIPAÇÃO E APRESENTAÇÃO DAS PROPOSTAS\nLink para acesso às peças do concurso (URL): https://community.vortal.biz/Public/public-tender-documents/UnFoZmZrclBWSFVzenBFWFhONjJUVytDODlUL2x4NnBXRkszTUlHaFZpeldXVThlVEtlR2g2blJLK242V1Y3ancvSUNqbDYwbEhwd3d4Zmp4TEZvNVE9PTgkWSQk\n\n20 - OUTROS REQUISITOS\nInformação sobre contratos reservados. Aplica-se a contratos reservados (54º-A)? Não\n\n21 - CRITÉRIO DE ADJUDICAÇÃO\nMultifator: Sim\nFator: \nNome: Preço\nPonderação: 50%\nSubfatores: Não\nFator: \nNome: Qualidade\nPonderação: 50%\nSubfatores: Não\n\n24 - CONDIÇÕES DO CONTRATO\nFaturação Eletrónica: Permitido\nObrigação de Subcontratação:\nCódigo da Obrigação de Subcontratação: Não é aplicável nenhuma obrigação de subcontratação.\n\n25 - COMPRA PÚBLICA ESTRATÉGICA\nCompra Pública Estratégica: Inexistência de contratação pública estratégica\n\n26 - INFORMAÇÕES ADICIONAIS\nContrato adequado para PME: Sim\nCobertura ACP (Acordo dos Contratos Públicos da Organização Mundial do Comércio): Não\n\n27 - IDENTIFICAÇÃO E CONTACTOS DO ÓRGÃO DE RECURSOS ADMINISTRATIVOS\nDesignação: Conselho de Administração da Unidade Local de Saúde do Alto Minho, E.P.E.\nEndereço: Estrada de Santa Luzia\nCódigo postal: 4904-858\nLocalidade: Viana do Castelo\nTelefone: +351 258802511\nFax: +351 258802511\nEndereço eletrónico: administracao@ulsam.min-saude.pt\n\n28 - IDENTIFICAÇÃO DO(S) AUTOR(ES) DE ANÚNCIO\nNome: Ana Filipa Monteiro\nCargo:  As Técnica (Gestão de Compras)\n419632257",
    "nipc": "508786193",
    "distrito": "Viana do Castelo",
    "concelho": "Viana do Castelo",
    "freguesia": "União das Freguesias de Viana do Castelo (Santa Maria Maior e Monserrate) e Meadela",
    "site": "https://www.ulsam.min-saude.pt",
    "email": "sourcing@ulsam.min-saude.pt",
    "designacao_contrato": "Lote de MCDT’s para realização de Estudos Urodinâmicos na ULSAM, EPE",
    "descricao": "Lote de MCDT’s para realização de Estudos Urodinâmicos na ULSAM, EPE",
    "preco_base": "105.993,00 EUR",
    "prazo_execucao": "2 ANOS",
    "prazo_apresentacao_propostas": "20-10-2025 18:00",
    "fundos_eu": "Não",
    "plataforma_eletronica": "VORTAL",
    "url_procedimento": "https://community.vortal.biz/public/",
    "autor_nome": "Ana Filipa Monteiro",
    "autor_cargo": "As Técnica (Gestão de Compras)"
  },
  {
    "numero_procedimento": "N/A",
    "entidade": "Município do Fundão",
    "link": "https://diariodarepublica.pt/dr/detalhe/contrato-publico/26492-938924586",
    "detalhes_completos": "1 - IDENTIFICAÇÃO E CONTACTOS DA ENTIDADE ADJUDICANTE\nDesignação da entidade adjudicante: Município do Fundão\nNIPC: 506215695\nEndereço: Pç. Município\nCódigo postal: 6230-338\nLocalidade: Castelo Branco\nPaís: Portugal\nNUT III: PT16J\nDistrito: Castelo Branco\nConcelho: Fundão\nFreguesia: União das Freguesias de Fundão, Valverde, Donas, Aldeia de Joanes e Aldeia Nova do Cabo\nTelefone: 275779060\nFax: 275779079\nEndereço da Entidade (URL): www.cm-fundao.pt\nEndereço Eletrónico: geral@cm-fundao.pt\neDelivery Gateway (URL): https://community.vortal.biz/public/\nFunção da Organização: Adquirente\nNorma jurídica da Entidade Adjudicante: Organismo de direito público\nÁrea de atividade da Autoridade Adjudicante: Serviços públicos das administrações públicas\n\n2 - JORNAL OFICIAL DA UNIÃO EUROPEIA\nO procedimento a que este anúncio diz respeito também é publicitado no Jornal Oficial da União Europeia? Não\n\n3 - AVISO\nModelo de Anúncio: Concurso público\nData de Envio do Anúncio: 08-10-2025\n\n5 - PROCESSO\nTipo de Procedimento: Concurso público\nPreço base do procedimento: Sim\nValor do preço base do procedimento: 61.729,98 EUR\nProcedimento com lotes? Não\n\n6 - OBJETO DO CONTRATO\nNúmero de referência interna: 2025/69\nDesignação do contrato: Projecto de Alteração do Restaurante Centro de Negócios do Fundão\nDescrição: Projecto de Alteração do Restaurante Centro de Negócios do Fundão\nTipo de Contrato Principal: Empreitada de Obras Públicas\nTipo de Contrato: Empreitada de Obras Públicas\nClassificação CPV (Vocabulário Comum para os Contratos Públicos)\nObjeto principal\nVocabulário Principal: 45200000\nPreço base s/IVA: 61.729,98 EUR\n\n7 - INDICAÇÕES ADICIONAIS\nO contrato envolve aquisição conjunta (satisfação de várias entidades)? Não\nO contrato é adjudicado por uma central de compras? Não\n\n8 - TÉCNICAS\nO concurso destina-se à celebração de um acordo-quadro? Inexistência de acordo-quadro\nÉ utilizado um leilão eletrónico? Não\nÉ adotada uma fase de negociação? Não\nSistema de Aquisição Dinâmico: Inexistência de sistema de aquisição dinâmico\n\n9 - LOCAL DA EXECUÇÃO DO CONTRATO\nLOCAL DA EXECUÇÃO DO CONTRATO (PROCEDIMENTO)\nPaís: Portugal\nNUT III: PT16J\nLocalidade: Castelo Branco\nDistrito: Castelo Branco\nConcelho: Fundão\nFreguesia: União das Freguesias de Fundão, Valverde, Donas, Aldeia de Joanes e Aldeia Nova do Cabo\n\n10 - PRAZO DE EXECUÇÃO DO CONTRATO\nPrazo de execução do contrato: 90 DIAS\nPrevisão de renovações: Não\n\n11 - FUNDOS EU\nTêm fundos EU? Não\n\n12 - DOCUMENTOS DE HABILITAÇÃO\nHabilitação para o exercício da atividade profissional: Sim\nTipo: Alvará\nDescrição: Alvará emitido pelo IMPIC \n\n13 - CONDIÇÕES DE APRESENTAÇÃO\nPlataforma eletrónica utilizada pela entidade adjudicante: VORTAL\nURL para Apresentação: https://community.vortal.biz/public/\nAdmissibilidade da apresentação de propostas variantes: Não autorizado\nPrazo para apresentação das propostas: 24-10-2025 17:00\nPrazo durante o qual os concorrentes são obrigados a manter as respetivas propostas: 66 dias a contar do termo do prazo para a apresentação das propostas\nIndicação de Subcontratação na Proposta: Inexistência de indicação de subcontratação\n\n14 - PRESTAÇÃO DE CAUÇÃO\nPrestação de caução: Sim\nPercentagem: 5%\nDescrição da Garantia Exigida: nos termos do programa de concurso \n\n15 - FORNECIMENTO DAS PEÇAS DO CONCURSO, APRESENTAÇÃO DE PEDIDOS DE PARTICIPAÇÃO E APRESENTAÇÃO DAS PROPOSTAS\nLink para acesso às peças do concurso (URL): https://community.vortal.biz/Public/public-tender-documents/KzVtWTZBeTFJMGZ6M0NmREFnZ0g3dWxLVFhjSFZYdFh2Tm5FdTBCUkYxUUZiZU1PYktnbm02UHhqRUoyTEhBNmprSy9uS09PdXNYQ0tvb3ptemY5dlE9PXNrITdG\n\n20 - OUTROS REQUISITOS\nInformação sobre contratos reservados. Aplica-se a contratos reservados (54º-A)? Não\n\n21 - CRITÉRIO DE ADJUDICAÇÃO\nMultifator: Não\nMonofator:\nNome: Preço\n\n24 - CONDIÇÕES DO CONTRATO\nFaturação Eletrónica: Permitido\nObrigação de Subcontratação:\nCódigo da Obrigação de Subcontratação: Não é aplicável nenhuma obrigação de subcontratação.\n\n25 - COMPRA PÚBLICA ESTRATÉGICA\nCompra Pública Estratégica: Inexistência de contratação pública estratégica\n\n26 - INFORMAÇÕES ADICIONAIS\nContrato adequado para PME: Sim\nCobertura ACP (Acordo dos Contratos Públicos da Organização Mundial do Comércio): Não\n\n27 - IDENTIFICAÇÃO E CONTACTOS DO ÓRGÃO DE RECURSOS ADMINISTRATIVOS\nDesignação: Munucípio do Fundão\nEndereço: Praça do Município\nCódigo postal: 2230-338\nLocalidade: Fundão\nTelefone: +351 2745779060\nFax: +351 275779079\nEndereço eletrónico: obraspublicas@cm-fundao.pt\n\n28 - IDENTIFICAÇÃO DO(S) AUTOR(ES) DE ANÚNCIO\nNome: Paulo Alexandre Bernardo Fernandes \nCargo: Presidente da Câmara Municipal  do Fundão \n419629236",
    "nipc": "506215695",
    "distrito": "Castelo Branco",
    "concelho": "Fundão",
    "freguesia": "União das Freguesias de Fundão, Valverde, Donas, Aldeia de Joanes e Aldeia Nova do Cabo",
    "site": "www.cm-fundao.pt",
    "email": "geral@cm-fundao.pt",
    "designacao_contrato": "Projecto de Alteração do Restaurante Centro de Negócios do Fundão",
    "descricao": "Projecto de Alteração do Restaurante Centro de Negócios do Fundão",
    "preco_base": "61.729,98 EUR",
    "prazo_execucao": "90 DIAS",
    "prazo_apresentacao_propostas": "24-10-2025 17:00",
    "fundos_eu": "Não",
    "plataforma_eletronica": "VORTAL",
    "url_procedimento": "https://community.vortal.biz/public/",
    "autor_nome": "Paulo Alexandre Bernardo Fernandes",
    "autor_cargo": "Presidente da Câmara Municipal do Fundão"
  },
  {
    "numero_procedimento": "N/A",
    "entidade": "Instituto da Habitação e da Reabilitação Urbana, I. P.",
    "link": "https://diariodarepublica.pt/dr/detalhe/contrato-publico/26493-938924587",
    "detalhes_completos": "1 - IDENTIFICAÇÃO E CONTACTOS DA ENTIDADE ADJUDICANTE\nDesignação da entidade adjudicante: Instituto da Habitação e da Reabilitação Urbana, I. P.\nNIPC: 501460888\nEndereço: Av. Columbano Bordalo Pinheiro, 5\nCódigo postal: 1099-019\nLocalidade: Lisboa\nPaís: Portugal\nNUT III: PT170\nDistrito: Lisboa\nConcelho: Lisboa\nFreguesia: Freguesia de Campolide\nTelefone: 217231500\nFax: 217231500\nEndereço da Entidade (URL): http://www.portalhabitacao.pt/\nEndereço Eletrónico: contratacao@ihru.pt\nFunção da Organização: Adquirente\nNorma jurídica da Entidade Adjudicante: Organismo de direito público, controlado por uma autoridade da administração central\nÁrea de atividade da Autoridade Adjudicante: Habitação e equipamentos coletivos\n\n2 - JORNAL OFICIAL DA UNIÃO EUROPEIA\nO procedimento a que este anúncio diz respeito também é publicitado no Jornal Oficial da União Europeia? Sim\n\n3 - AVISO\nModelo de Anúncio: Concurso público\nData de Envio do Anúncio: 06-10-2025\n\n5 - PROCESSO\nTipo de Procedimento: Concurso público\nPreço base do procedimento: Sim\nValor do preço base do procedimento: 8.625.840,00 EUR\nProcedimento com lotes? Sim\nNº Máx. de Lotes Autorizado: 3\nNúmero máximo de lotes que podem ser adjudicados a um concorrente: 3\n\n6 - OBJETO DO CONTRATO\nNúmero de referência interna: PA.160.2025.0000101\nDesignação do contrato: PA.160.2025.0000101 - Reabilitação das partes comuns de 36 blocos do Bairro do Zambujal (3ª fase) em Amadora\nDescrição: PA.160.2025.0000101 - Reabilitação das partes comuns de 36 blocos do Bairro do Zambujal (3ª fase) em Amadora\nOpções: Não\nTipo de Contrato Principal: Empreitada de Obras Públicas\nTipo de Contrato: Empreitada de Obras Públicas\nClassificação CPV (Vocabulário Comum para os Contratos Públicos)\nObjeto principal\nVocabulário Principal: 45453000\nPreço base s/IVA: 8.625.840,00 EUR\nLotes: \nNº: LOT-0001\nDescrição do Lote: Lote 1 - PC.160.2025.0000128 - Reabilitação das partes comuns de 8 edifícios\nPreço base s/IVA: 2.394.073,00 EUR\nClassificação CPV (Vocabulário Comum para os Contratos Públicos)\nObjeto principal\nVocabulário Principal: 45453000\nNº: LOT-0002\nDescrição do Lote: Lote 2 - PC.160.2025.0000129 -  Reabilitação das partes comuns de 11 edifícios\nPreço base s/IVA: 3.214.899,00 EUR\nClassificação CPV (Vocabulário Comum para os Contratos Públicos)\nObjeto principal\nVocabulário Principal: 45453000\nNº: LOT-0003\nDescrição do Lote: Lote 3 - PC.160.2025.0000130 - Reabilitação das partes comuns de 13 edifícios\nPreço base s/IVA: 3.016.868,00 EUR\nClassificação CPV (Vocabulário Comum para os Contratos Públicos)\nObjeto principal\nVocabulário Principal: 45453000\n\n7 - INDICAÇÕES ADICIONAIS\nO contrato envolve aquisição conjunta (satisfação de várias entidades)? Não\nO contrato é adjudicado por uma central de compras? Não\n\n8 - TÉCNICAS\nO concurso destina-se à celebração de um acordo-quadro? Inexistência de acordo-quadro\nÉ utilizado um leilão eletrónico? Não\nÉ adotada uma fase de negociação? Não\nSistema de Aquisição Dinâmico: Inexistência de sistema de aquisição dinâmico\n\n9 - LOCAL DA EXECUÇÃO DO CONTRATO\nLOCAL DA EXECUÇÃO DO CONTRATO (PROCEDIMENTO)\nLOCAL DA EXECUÇÃO DO CONTRATO (LOTE)\nIdentificador do Lote: LOT-0001\nPaís: Portugal\nNUT III: PT170\nLocalidade: Amadora\nDistrito: Lisboa\nConcelho: Amadora\nFreguesia: Freguesia de Alfragide\nIdentificador do Lote: LOT-0002\nPaís: Portugal\nNUT III: PT170\nLocalidade: Amadora\nDistrito: Lisboa\nConcelho: Amadora\nFreguesia: Freguesia de Alfragide\nIdentificador do Lote: LOT-0003\nPaís: Portugal\nNUT III: PT170\nLocalidade: Amadora\nDistrito: Lisboa\nConcelho: Amadora\nFreguesia: Freguesia de Alfragide\n\n10 - PRAZO DE EXECUÇÃO DO CONTRATO\nIdentificador do Lote: LOT-0001\nPrazo de execução do contrato: 730 DIAS\nPrevisão de renovações: Não\nIdentificador do Lote: LOT-0002\nPrazo de execução do contrato: 730 DIAS\nPrevisão de renovações: Não\nIdentificador do Lote: LOT-0003\nPrazo de execução do contrato: 730 DIAS\nPrevisão de renovações: Não\n\n11 - FUNDOS EU\nIdentificador do Lote: LOT-0001; LOT-0002; LOT-0003\nTêm fundos EU? Não\n\n12 - DOCUMENTOS DE HABILITAÇÃO\nHabilitação para o exercício da atividade profissional: Sim\nTipo: Alvará\nDescrição: - 5ª subcategoria, da 1ª categoria, em classe que cubra o valor da proposta, das 6ª, 7ª e 8ª subcategorias, da 1ª categoria, 1ª, 9ª e 14ª subcategorias da 4ª categoria e 1ª, 5ª, 11ª e 12ª subcategorias da 5ª categoria, nas classes correspondentes às partes dos trabalhos a que respeitam.\n\n13 - CONDIÇÕES DE APRESENTAÇÃO\nPlataforma eletrónica utilizada pela entidade adjudicante: ANOGOV\nURL para Apresentação: https://www.anogov.com/ip-ihru/faces/\nAdmissibilidade da apresentação de propostas variantes: Não autorizado\nPrazo para apresentação das propostas: 05-11-2025 23:59\nPrazo durante o qual os concorrentes são obrigados a manter as respetivas propostas: 66 dias a contar do termo do prazo para a apresentação das propostas\nApresentação de Catálogo Eletrónico: Não autorizado\nIndicação de Subcontratação na Proposta: Inexistência de indicação de subcontratação\n\n14 - PRESTAÇÃO DE CAUÇÃO\nPrestação de caução: Sim\nPercentagem: 5%\nDescrição da Garantia Exigida: a) Por depósito em dinheiro; b) Por títulos emitidos ou garantidos pelo Estado Português; c) Mediante garantia bancária; d) Mediante seguro-caução\n\n15 - FORNECIMENTO DAS PEÇAS DO CONCURSO, APRESENTAÇÃO DE PEDIDOS DE PARTICIPAÇÃO E APRESENTAÇÃO DAS PROPOSTAS\nLink para acesso às peças do concurso (URL): https://www.anogov.com/ip-ihru/faces/app/acessoDocs.jsp?codigoAcesso=5QEFeSyAnxo4M9Jm33I4ZP42clpNOVtOIudjjun15U8RzyrhSL\n\n20 - OUTROS REQUISITOS\nIdentificador do Lote: LOT-0001; LOT-0002; LOT-0003\nInformação sobre contratos reservados. Aplica-se a contratos reservados (54º-A)? Não\n\n21 - CRITÉRIO DE ADJUDICAÇÃO\nO Critério de adjudicação é diferenciado por lote? Não\nMultifator: Não\nMonofator:\nNome: Preço\n\n24 - CONDIÇÕES DO CONTRATO\nIdentificador do Lote: LOT-0001; LOT-0002; LOT-0003\nFaturação Eletrónica: Necessário\nObrigação de Subcontratação:\nCódigo da Obrigação de Subcontratação: Não é aplicável nenhuma obrigação de subcontratação.\n\n25 - COMPRA PÚBLICA ESTRATÉGICA\nCompra Pública Estratégica: Inexistência de contratação pública estratégica\n\n26 - INFORMAÇÕES ADICIONAIS\nIdentificador do Lote: LOT-0001\nContrato adequado para PME: Sim\nCobertura ACP (Acordo dos Contratos Públicos da Organização Mundial do Comércio): Não\nIdentificador do Lote: LOT-0002\nContrato adequado para PME: Sim\nCobertura ACP (Acordo dos Contratos Públicos da Organização Mundial do Comércio): Não\nIdentificador do Lote: LOT-0003\nContrato adequado para PME: Sim\nCobertura ACP (Acordo dos Contratos Públicos da Organização Mundial do Comércio): Não\n\n27 - IDENTIFICAÇÃO E CONTACTOS DO ÓRGÃO DE RECURSOS ADMINISTRATIVOS\nDesignação: Conselho Diretivo do IHRU, I.P.\nEndereço: Av. Columbano Bordalo Pinheiro, 5\nCódigo postal: 1099-019\nLocalidade: Lisboa\nEndereço eletrónico: cd@ihru.pt\nPrazo de interposição do recurso: 5 dias\n\n28 - IDENTIFICAÇÃO DO(S) AUTOR(ES) DE ANÚNCIO\nNome: António Benjamim da Costa Pereira\nCargo: Presidente do Conselho Diretivo do IHRU, I.P\n419619946",
    "nipc": "501460888",
    "distrito": "Lisboa",
    "concelho": "Lisboa",
    "freguesia": "Freguesia de Campolide",
    "site": "http://www.portalhabitacao.pt/",
    "email": "contratacao@ihru.pt",
    "designacao_contrato": "PA.160.2025.0000101 - Reabilitação das partes comuns de 36 blocos do Bairro do Zambujal (3ª fase) em Amadora",
    "descricao": "PA.160.2025.0000101 - Reabilitação das partes comuns de 36 blocos do Bairro do Zambujal (3ª fase) em Amadora",
    "preco_base": "8.625.840,00 EUR",
    "prazo_execucao": "730 DIAS",
    "prazo_apresentacao_propostas": "05-11-2025 23:59",
    "fundos_eu": "Não",
    "plataforma_eletronica": "ANOGOV",
    "url_procedimento": "https://www.anogov.com/ip-ihru/faces/",
    "autor_nome": "António Benjamim da Costa Pereira",
    "autor_cargo": "Presidente do Conselho Diretivo do IHRU, I.P"
  },
  {
    "numero_procedimento": "N/A",
    "entidade": "Comissão de Coordenação e Desenvolvimento Regional do Alentejo, I. P.",
    "link": "https://diariodarepublica.pt/dr/detalhe/contrato-publico/26494-938924588",
    "detalhes_completos": "1 - IDENTIFICAÇÃO E CONTACTOS DA ENTIDADE ADJUDICANTE\nDesignação da entidade adjudicante: Comissão de Coordenação e Desenvolvimento Regional do Alentejo, I. P.\nNIPC: 517699044\nServiço/Órgão/Pessoa de contacto: Comissão de Coordenação e Desenvolvimento Regional do Alentejo, I.P. Gabinete de Projetos e Compras Públicas, \nEndereço: Avenida Engenheiro Arantes e Oliveira, 193\nCódigo postal: 7004-514\nLocalidade: Évora\nPaís: Portugal\nNUT III: Alentejo Central\nDistrito: Évora\nConcelho: Évora\nFreguesia: União das Freguesias de Malagueira e Horta das Figueiras\nTelefone: 266740300\nEndereço da Entidade (URL): https://www.ccdr-a.gov.pt/\nEndereço Eletrónico: aprovisionamento@ccdr-a.gov.pt\nFunção da Organização: \nNorma jurídica da Entidade Adjudicante: Organismo de direito público\nÁrea de atividade da Entidade Adjudicante: Atividades relacionadas com a água\n\n2 - AVISO\nData de Envio do Anúncio: 08-10-2025\n\n3 - PROCESSO\nModelo de Anúncio: Hasta pública de alienação de bens móveis\nPreço de licitação base do procedimento: Sim\nValor da licitação base do procedimento: 98.500,00 EUR\nContratação por Lotes? Sim\n\n4 - OBJETO DO CONTRATO\nNúmero de referência interna: 2025/GPCP/HP001\nDesignação do procedimento de alienação de bens móveis: Venda de azeitona na árvore nos centros de experimentação do Baixo Alentejo e dos Lameirões.\nTipo de bens: Azeitona na árvore\nLegislação aplicável: DL n.º 18/2008 de 29 janeiro\nAvaliação do bem: 98.500,00 EUR\nClassificação CPV (Vocabulário Comum para os Contratos Públicos)\nObjeto: Objeto principal\nVocabulário Principal: Serviços relacionados com produção agrícola\nLotes: \nNº: LOT-0001\nDescrição do Lote: Centro de Experimentação do Baixo Alentejo - Olival da Herdade da Abobada\nPreço base s/IVA: 62.500,00 EUR\nClassificação CPV (Vocabulário Comum para os Contratos Públicos)\nObjeto: Objeto principal\nVocabulário Principal: Serviços relacionados com produção agrícola\nNº: LOT-0002\nDescrição do Lote: Centro de Experimentação do Baixo Alentejo - Olival da Herdade do Monte Novo\nPreço base s/IVA: 20.000,00 EUR\nClassificação CPV (Vocabulário Comum para os Contratos Públicos)\nObjeto: Objeto principal\nVocabulário Principal: Serviços relacionados com produção agrícola\nNº: LOT-0003\nDescrição do Lote: Centro de Experimentação dos Lameirões - Olival da Herdade dos Lameirões e da Herdade do Metum\nPreço base s/IVA: 16.000,00 EUR\nClassificação CPV (Vocabulário Comum para os Contratos Públicos)\nObjeto: Objeto principal\nVocabulário Principal: Serviços relacionados com produção agrícola\n\n5 - DESTINATÁRIOS\nDestinatários: Todos os interessados\n\n6 - INDICAÇÕES ADICIONAIS\nReferência do Portal dos Contratos Públicos:Não\nA entidade adjudicante atua como compradora no procedimento? Não\nÉ utilizado um leilão eletrónico?  Não\nÉ adotada uma fase de negociação?  Sim\n\n7 - CONSULTA DAS PEÇAS E OBTENÇÃO DE CÓPIAS\nLink para acesso às peças do concurso (URL):https://www.ccdr-a.gov.pt/contratacao-publica/\n\n8 -  PEDIDOS DE ESCLARECIMENTO SOBRE AS PEÇAS DO PROCEDIMENTO\nPedidos de esclarecimento sobre as peças do procedimento: aprovisionamento@ccdr-a.gov.pt\n\n9 -  DOCUMENTOS DE HABILITAÇÃO\nDocumentos de habilitação: Programa do procedimento\n\n10 -  CONDIÇÕES DE PARTICIPAÇÃO\nCondições de participação: Estão expressas no programa do procedimento\n\n11 - DATA, LOCAL E REGRAS ATO PÚBLICO\nData, Local e Regras do Ato Publico: Dia 30 de outubro de 2025, pelas 10h30, na Herdade da Abóbada 7830-908 Vila Nova de São Bento\n\n12- CONDIÇÕES DE APRESENTAÇÃO\nModo de apresentação das propostas: E-mail\nLocal de apresentação das propostas:  aprovisionamento@ccdr-a.gov.pt\nPrazo para apresentação das propostas: 19-10-2025\nPrazo durante o qual os concorrentes são obrigados a manter as respetivas propostas: 66 dias a contar do termo do prazo para a apresentação das propostas\n\n13- CRITÉRIO DE SELEÇÃO\nApenas o valor licitado? Sim\nFator de avaliação: \nPonderação: 0\n\n14 - PRESTAÇÃO DE CAUÇÃO\nPrestação de caução: Sim\nPercentagem: 10%\n\n15 - IDENTIFICAÇÃO DO(S) AUTOR(ES) DE ANÚNCIO\nNome: Maria Manuel Bengala Pôla Romão\nCargo: Técnica Superior\n419629536",
    "nipc": "517699044",
    "distrito": "Évora",
    "concelho": "Évora",
    "freguesia": "União das Freguesias de Malagueira e Horta das Figueiras",
    "site": "https://www.ccdr-a.gov.pt/",
    "email": "aprovisionamento@ccdr-a.gov.pt",
    "designacao_contrato": null,
    "descricao": null,
    "preco_base": "62.500,00 EUR",
    "prazo_execucao": null,
    "prazo_apresentacao_propostas": "19-10-2025",
    "fundos_eu": null,
    "plataforma_eletronica": null,
    "url_procedimento": null,
    "autor_nome": null,
    "autor_cargo": "Técnica Superior"
  },
  {
    "numero_procedimento": "N/A",
    "entidade": "Instituto Superior de Engenharia de Lisboa",
    "link": "https://diariodarepublica.pt/dr/detalhe/contrato-publico/26495-938924589",
    "detalhes_completos": "1 - IDENTIFICAÇÃO E CONTACTOS DA ENTIDADE ADJUDICANTE\nDesignação da entidade adjudicante: Instituto Superior de Engenharia de Lisboa\nNIPC: 600016234\nServiço/Órgão/Pessoa de contacto: Núcleo de Aprovisionamento e Património do ISEL\nEndereço: Rua Conselheiro Emídio Navarro n.º 1\nCódigo postal: 1959-007\nLocalidade: Lisboa\nPaís: Portugal\nNUT III: PT170\nDistrito: Lisboa\nConcelho: Lisboa\nFreguesia: Freguesia de Marvila - Lisboa\nTelefone: 218317240\nFax: 218317240\nEndereço da Entidade (URL): www.isel.pt\nEndereço Eletrónico: procedimentos.nap@isel.pt\nFunção da Organização: Adquirente\nNorma jurídica da Entidade Adjudicante: Autoridade da administração central\nÁrea de atividade da Autoridade Adjudicante: Educação\n\n2 - JORNAL OFICIAL DA UNIÃO EUROPEIA\nO procedimento a que este anúncio diz respeito também é publicitado no Jornal Oficial da União Europeia? Não\n\n3 - AVISO\nModelo de Anúncio: Concurso público\nData de Envio do Anúncio: 08-10-2025\n\n5 - PROCESSO\nTipo de Procedimento: Concurso público\nPreço base do procedimento: Sim\nValor do preço base do procedimento: 97.000,00 EUR\nProcedimento com lotes? Não\n\n6 - OBJETO DO CONTRATO\nNúmero de referência interna: 53/ISEL/2025\nDesignação do contrato: Concurso Público para Reabilitação do Laboratório de Desenvolvimento de Novos Processos\nDescrição: Empreitada para Reabilitação do Laboratório de Desenvolvimento de Novos Processos\nTipo de Contrato Principal: Empreitada de Obras Públicas\nTipo de Contrato: Empreitada de Obras Públicas\nClassificação CPV (Vocabulário Comum para os Contratos Públicos)\nObjeto principal\nVocabulário Principal: 45453000\nPreço base s/IVA: 97.000,00 EUR\n\n7 - INDICAÇÕES ADICIONAIS\nO contrato envolve aquisição conjunta (satisfação de várias entidades)? Não\nO contrato é adjudicado por uma central de compras? Não\n\n8 - TÉCNICAS\nO concurso destina-se à celebração de um acordo-quadro? Inexistência de acordo-quadro\nÉ utilizado um leilão eletrónico? Não\nÉ adotada uma fase de negociação? Não\nSistema de Aquisição Dinâmico: Inexistência de sistema de aquisição dinâmico\n\n9 - LOCAL DA EXECUÇÃO DO CONTRATO\nLOCAL DA EXECUÇÃO DO CONTRATO (PROCEDIMENTO)\nPaís: Portugal\nNUT III: PT170\nLocalidade: Lisboa\nDistrito: Lisboa\nConcelho: Lisboa\nFreguesia: Freguesia de Marvila - Lisboa\n\n10 - PRAZO DE EXECUÇÃO DO CONTRATO\nPrazo de execução do contrato: 120 DIAS\nPrevisão de renovações: Não\n\n11 - FUNDOS EU\nTêm fundos EU? Sim\n\n12 - DOCUMENTOS DE HABILITAÇÃO\nHabilitação para o exercício da atividade profissional: Não\n\n13 - CONDIÇÕES DE APRESENTAÇÃO\nPlataforma eletrónica utilizada pela entidade adjudicante: COMPRASPT\nURL para Apresentação: https://www.compraspt.com/cpt-isel/faces/\nAdmissibilidade da apresentação de propostas variantes: Não autorizado\nPrazo para apresentação das propostas: 23-10-2025 23:59\nPrazo durante o qual os concorrentes são obrigados a manter as respetivas propostas: 66 dias a contar do termo do prazo para a apresentação das propostas\nApresentação de Catálogo Eletrónico: Permitido\nIndicação de Subcontratação na Proposta: O(s) subcontratante(s) proposto(s) necessário(s) para cumprir a obrigação de subcontratar uma percentagem mínima do contrato\n\n14 - PRESTAÇÃO DE CAUÇÃO\nPrestação de caução: Sim\nPercentagem: 5%\nDescrição da Garantia Exigida: de acordo com o previsto no artigo 21 do programa\n\n15 - FORNECIMENTO DAS PEÇAS DO CONCURSO, APRESENTAÇÃO DE PEDIDOS DE PARTICIPAÇÃO E APRESENTAÇÃO DAS PROPOSTAS\nLink para acesso às peças do concurso (URL): https://www.compraspt.com/cpt-isel/faces/app/acessoDocs.jsp?codigoAcesso=wnUav4Wrq8KZjioX4ijP0YpCG5mu32D6yvXCLIWZW4MFehQKBZ\n\n20 - OUTROS REQUISITOS\nInformação sobre contratos reservados. Aplica-se a contratos reservados (54º-A)? Não\n\n21 - CRITÉRIO DE ADJUDICAÇÃO\nMultifator: Sim\nFator: \nNome: Preço\nPonderação: 75%\nSubfatores: Não\nFator: \nNome: Outros\nOutro Nome: Prazo de execução\nPonderação: 25%\nSubfatores: Não\n\n24 - CONDIÇÕES DO CONTRATO\nFaturação Eletrónica: Permitido\nObrigação de Subcontratação:\nCódigo da Obrigação de Subcontratação: Não é aplicável nenhuma obrigação de subcontratação.\n\n25 - COMPRA PÚBLICA ESTRATÉGICA\nCompra Pública Estratégica: Inexistência de contratação pública estratégica\n\n26 - INFORMAÇÕES ADICIONAIS\nContrato adequado para PME: Sim\nCobertura ACP (Acordo dos Contratos Públicos da Organização Mundial do Comércio): Não\n\n27 - IDENTIFICAÇÃO E CONTACTOS DO ÓRGÃO DE RECURSOS ADMINISTRATIVOS\nDesignação: Presidente do ISEL\nEndereço: presidente@isel.pt\nCódigo postal: 1959-007\nLocalidade: Lisboa\nEndereço eletrónico: procedimentos.nap@isel.pt\nPrazo de interposição do recurso: 5 dias\n\n28 - IDENTIFICAÇÃO DO(S) AUTOR(ES) DE ANÚNCIO\nNome: José M. P. do Nascimento\nCargo: Presidente do ISEL\n419629577",
    "nipc": "600016234",
    "distrito": "Lisboa",
    "concelho": "Lisboa",
    "freguesia": "Freguesia de Marvila - Lisboa",
    "site": "www.isel.pt",
    "email": "procedimentos.nap@isel.pt",
    "designacao_contrato": "Concurso Público para Reabilitação do Laboratório de Desenvolvimento de Novos Processos",
    "descricao": "Empreitada para Reabilitação do Laboratório de Desenvolvimento de Novos Processos",
    "preco_base": "97.000,00 EUR",
    "prazo_execucao": "120 DIAS",
    "prazo_apresentacao_propostas": "23-10-2025 23:59",
    "fundos_eu": "Sim",
    "plataforma_eletronica": "COMPRASPT",
    "url_procedimento": "https://www.compraspt.com/cpt-isel/faces/",
    "autor_nome": "José M. P. do Nascimento",
    "autor_cargo": "Presidente do ISEL"
  },
  {
    "numero_procedimento": "N/A",
    "entidade": "Ensiprof - Ensino e Formação Profissional, L.da",
    "link": "https://diariodarepublica.pt/dr/detalhe/contrato-publico/26497-938924590",
    "detalhes_completos": "1 - IDENTIFICAÇÃO E CONTACTOS DA ENTIDADE ADJUDICANTE\nDesignação da entidade adjudicante: Ensiprof - Ensino e Formação Profissional, L.da\nNIPC: 504769642\nServiço/Órgão/Pessoa de contacto: Departamento Contratação Pública\nEndereço: Largo de Mompilher, 22\nCódigo postal: 4050-392\nLocalidade: Porto\nPaís: Portugal\nNUT III: PT11A\nDistrito: Porto\nConcelho: Porto\nFreguesia: União das Freguesias de Cedofeita, Santo Ildefonso, Sé, Miragaia, São Nicolau e Vitória\nTelefone: 222063000\nEndereço da Entidade (URL): https://www.profitecla.pt/\nEndereço Eletrónico: contratacao.publica@profitecla.pt\neDelivery Gateway (URL): https://www.acingov.pt\nFunção da Organização: Adquirente\nNorma jurídica da Entidade Adjudicante: Organismo de direito público\nÁrea de atividade da Autoridade Adjudicante: Serviços públicos das administrações públicas\n\n2 - JORNAL OFICIAL DA UNIÃO EUROPEIA\nO procedimento a que este anúncio diz respeito também é publicitado no Jornal Oficial da União Europeia? Sim\n\n3 - AVISO\nModelo de Anúncio: Concurso público\nData de Envio do Anúncio: 06-10-2025\n\n5 - PROCESSO\nTipo de Procedimento: Concurso público\nPreço base do procedimento: Sim\nValor do preço base do procedimento: 508.371,83 EUR\nProcedimento com lotes? Sim\nNº Máx. de Lotes Autorizado: 3\nNúmero máximo de lotes que podem ser adjudicados a um concorrente: 3\n\n6 - OBJETO DO CONTRATO\nNúmero de referência interna: CPI 3/2025\nDesignação do contrato: CPI 3/2025 - Centro Tecnológico Especializado Digital\nDescrição: CPI 3/2025 - Centro Tecnológico Especializado Digital \nOpções: Não\nTipo de Contrato Principal: Aquisição de Bens Móveis\nTipo de Contrato: Aquisição de Bens Móveis\nClassificação CPV (Vocabulário Comum para os Contratos Públicos)\nObjeto principal\nVocabulário Principal: 38652000\nPreço base s/IVA: 266.213,83 EUR\nObjeto Complementar\nVocabulário Principal: 30233141\nPreço base s/IVA: 177.350,00 EUR\nObjeto Complementar\nVocabulário Principal: 30213100\nPreço base s/IVA: 64.808,00 EUR\nLotes: \nNº: LOT-0001\nDescrição do Lote: Lote 1 - Multimédia e informático\nPreço base s/IVA: 266.213,83 EUR\nClassificação CPV (Vocabulário Comum para os Contratos Públicos)\nObjeto principal\nVocabulário Principal: 38652000\nNº: LOT-0002\nDescrição do Lote: Lote 2 - Solução de Edição Colaborativa\nPreço base s/IVA: 177.350,00 EUR\nClassificação CPV (Vocabulário Comum para os Contratos Públicos)\nObjeto principal\nVocabulário Principal: 30233141\nNº: LOT-0003\nDescrição do Lote: Lote 3 - Portáteis\nPreço base s/IVA: 64.808,00 EUR\nClassificação CPV (Vocabulário Comum para os Contratos Públicos)\nObjeto principal\nVocabulário Principal: 30213100\n\n7 - INDICAÇÕES ADICIONAIS\nO contrato envolve aquisição conjunta (satisfação de várias entidades)? Não\nO contrato é adjudicado por uma central de compras? Não\n\n8 - TÉCNICAS\nO concurso destina-se à celebração de um acordo-quadro? Inexistência de acordo-quadro\nÉ utilizado um leilão eletrónico? Não\nÉ adotada uma fase de negociação? Não\nSistema de Aquisição Dinâmico: Inexistência de sistema de aquisição dinâmico\n\n9 - LOCAL DA EXECUÇÃO DO CONTRATO\nLOCAL DA EXECUÇÃO DO CONTRATO (PROCEDIMENTO)\nPaís: Portugal\nNUT III: PT11A\nLocalidade: União das Freguesias de Cedofeita, Santo Ildefonso, Sé, Miragaia, São Nicolau e Vitória\nDistrito: Porto\nConcelho: Porto\nFreguesia: União das Freguesias de Cedofeita, Santo Ildefonso, Sé, Miragaia, São Nicolau e Vitória\nLOCAL DA EXECUÇÃO DO CONTRATO (LOTE)\nIdentificador do Lote: LOT-0001; LOT-0002; LOT-0003\nPaís: Portugal\nNUT III: PT11A\nLocalidade: União das Freguesias de Cedofeita, Santo Ildefonso, Sé, Miragaia, São Nicolau e Vitória\nDistrito: Porto\nConcelho: Porto\nFreguesia: União das Freguesias de Cedofeita, Santo Ildefonso, Sé, Miragaia, São Nicolau e Vitória\n\n10 - PRAZO DE EXECUÇÃO DO CONTRATO\nIdentificador do Lote: LOT-0001; LOT-0002; LOT-0003\nData de Início: 01-11-2025\nData de Fim: 31-12-2025\nPrevisão de renovações: Não\n\n11 - FUNDOS EU\nIdentificador do Lote: LOT-0001; LOT-0002; LOT-0003\nTêm fundos EU? Sim\n\n12 - DOCUMENTOS DE HABILITAÇÃO\nHabilitação para o exercício da atividade profissional: Não\n\n13 - CONDIÇÕES DE APRESENTAÇÃO\nPlataforma eletrónica utilizada pela entidade adjudicante: ACIN\nURL para Apresentação: https://www.acingov.pt\nAdmissibilidade da apresentação de propostas variantes: Não autorizado\nPrazo para apresentação das propostas: 21-10-2025 23:59\nPrazo durante o qual os concorrentes são obrigados a manter as respetivas propostas: 66 dias a contar do termo do prazo para a apresentação das propostas\nApresentação de Catálogo Eletrónico: Não autorizado\nIndicação de Subcontratação na Proposta: Inexistência de indicação de subcontratação\n\n14 - PRESTAÇÃO DE CAUÇÃO\nPrestação de caução: Sim\nPercentagem: 5%\nDescrição da Garantia Exigida: Será exigida ao Adjudicatário, nos termos do n.º 1 e n.º 2, alínea a) ambos do artigo 88.º do CCP, a prestação de uma caução destinada a garantir a celebração do contrato, bem como o exato e pontual cumprimento de todas as obrigações legais e contratuais que assume com essa celebração, se o preço contratual for igual ou superior a 500.000 (quinhentos mil euros).\n\n15 - FORNECIMENTO DAS PEÇAS DO CONCURSO, APRESENTAÇÃO DE PEDIDOS DE PARTICIPAÇÃO E APRESENTAÇÃO DAS PROPOSTAS\nLink para acesso às peças do concurso (URL): https://www.acingov.pt/acingovprod/2/zonaPublica/zona_publica_c/donwloadProcedurePiece/OTgzODQ3\n\n20 - OUTROS REQUISITOS\nIdentificador do Lote: LOT-0001; LOT-0002; LOT-0003\nInformação sobre contratos reservados. Aplica-se a contratos reservados (54º-A)? Não\n\n21 - CRITÉRIO DE ADJUDICAÇÃO\nO Critério de adjudicação é diferenciado por lote? Sim\nIdentificador do lote: LOT-0001\nMultifator: Sim\nFator: \nNome: Preço\nPonderação: 90%\nSubfatores: Não\nFator: \nNome: Outros\nOutro Nome: Adequação técnico-funcional (Prazo de Entrega)\nPonderação: 10%\nSubfatores: Não\nO Critério de adjudicação é diferenciado por lote? Sim\nIdentificador do lote: LOT-0002\nMultifator: Sim\nFator: \nNome: Preço\nPonderação: 60%\nSubfatores: Não\nFator: \nNome: Outros\nOutro Nome: Adequação técnico-funcional\nPonderação: 40%\nSubfatores: Não\nO Critério de adjudicação é diferenciado por lote? Sim\nIdentificador do lote: LOT-0003\nMultifator: Sim\nFator: \nNome: Preço\nPonderação: 60%\nSubfatores: Não\nFator: \nNome: Outros\nOutro Nome: Adequação técnico-funcional\nPonderação: 40%\nSubfatores: Não\n\n24 - CONDIÇÕES DO CONTRATO\nIdentificador do Lote: LOT-0001; LOT-0002; LOT-0003\nFaturação Eletrónica: Permitido\nObrigação de Subcontratação:\nCódigo da Obrigação de Subcontratação: Não é aplicável nenhuma obrigação de subcontratação.\n\n25 - COMPRA PÚBLICA ESTRATÉGICA\nCompra Pública Estratégica: Inexistência de contratação pública estratégica\n\n26 - INFORMAÇÕES ADICIONAIS\nIdentificador do Lote: LOT-0001; LOT-0002; LOT-0003\nContrato adequado para PME: Não\nCobertura ACP (Acordo dos Contratos Públicos da Organização Mundial do Comércio): Não\n\n27 - IDENTIFICAÇÃO E CONTACTOS DO ÓRGÃO DE RECURSOS ADMINISTRATIVOS\nDesignação: Gerência\nEndereço: Largo de Mompilher, 22\nCódigo postal: 4050-392\nLocalidade: Porto\nTelefone: 222063000\nFax: \nEndereço eletrónico: contratacao.publica@profitecla.pt\nPrazo de interposição do recurso: 5 dias\n\n28 - IDENTIFICAÇÃO DO(S) AUTOR(ES) DE ANÚNCIO\nNome: Marta Cristovão\nCargo: Jurista\n419620293",
    "nipc": "504769642",
    "distrito": "Porto",
    "concelho": "Porto",
    "freguesia": "União das Freguesias de Cedofeita, Santo Ildefonso, Sé, Miragaia, São Nicolau e Vitória",
    "site": "https://www.profitecla.pt/",
    "email": "contratacao.publica@profitecla.pt",
    "designacao_contrato": "CPI 3/2025 - Centro Tecnológico Especializado Digital",
    "descricao": "CPI 3/2025 - Centro Tecnológico Especializado Digital",
    "preco_base": "266.213,83 EUR",
    "prazo_execucao": null,
    "prazo_apresentacao_propostas": "21-10-2025 23:59",
    "fundos_eu": "Sim",
    "plataforma_eletronica": "ACIN",
    "url_procedimento": "https://www.acingov.pt",
    "autor_nome": "Marta Cristovão",
    "autor_cargo": "Jurista"
  },
  {
    "numero_procedimento": "N/A",
    "entidade": "Freguesia de Estorãos",
    "link": "https://diariodarepublica.pt/dr/detalhe/contrato-publico/26498-938924591",
    "detalhes_completos": "1 - IDENTIFICAÇÃO E CONTACTOS DA ENTIDADE ADJUDICANTE\nDesignação da entidade adjudicante: Freguesia de Estorãos\nNIPC: 506964019\nServiço/Órgão/Pessoa de contacto: Executivo\nEndereço: Rua da Igreja, nº 380, 4820-594 Estorãos-Fafe\nCódigo postal: 4820-594\nLocalidade: Fafe\nPaís: Portugal\nNUT III: PT119\nDistrito: Braga\nConcelho: Fafe\nFreguesia: Freguesia de Passos - Fafe\nTelefone: 253503880\nFax: 253503880\nEndereço da Entidade (URL): https://www.freguesiadeestoraos.pt/\nEndereço Eletrónico: geral@estoraos-fafe.pt\neDelivery Gateway (URL): https://www.acingov.pt\nFunção da Organização: Adquirente\nSubfunção da Organização: Organização que recebe as propostas\nNorma jurídica da Entidade Adjudicante: Organismo de direito público\nÁrea de atividade da Autoridade Adjudicante: Serviços públicos das administrações públicas\n\n2 - JORNAL OFICIAL DA UNIÃO EUROPEIA\nO procedimento a que este anúncio diz respeito também é publicitado no Jornal Oficial da União Europeia? Não\n\n3 - AVISO\nModelo de Anúncio: Concurso público\nData de Envio do Anúncio: 08-10-2025\n\n5 - PROCESSO\nTipo de Procedimento: Concurso público\nPreço base do procedimento: Sim\nValor do preço base do procedimento: 249.900,00 EUR\nProcedimento com lotes? Não\n\n6 - OBJETO DO CONTRATO\nNúmero de referência interna: CP 02/2025\nDesignação do contrato: Empreitada para construção de um salão\nDescrição: Empreitada para a construção de um salão\nTipo de Contrato Principal: Empreitada de Obras Públicas\nTipo de Contrato: Empreitada de Obras Públicas\nClassificação CPV (Vocabulário Comum para os Contratos Públicos)\nObjeto principal\nVocabulário Principal: 45211350\nPreço base s/IVA: 249.900,00 EUR\n\n7 - INDICAÇÕES ADICIONAIS\nO contrato envolve aquisição conjunta (satisfação de várias entidades)? Não\nO contrato é adjudicado por uma central de compras? Não\n\n8 - TÉCNICAS\nO concurso destina-se à celebração de um acordo-quadro? Inexistência de acordo-quadro\nÉ utilizado um leilão eletrónico? Não\nÉ adotada uma fase de negociação? Não\nSistema de Aquisição Dinâmico: Inexistência de sistema de aquisição dinâmico\n\n9 - LOCAL DA EXECUÇÃO DO CONTRATO\nLOCAL DA EXECUÇÃO DO CONTRATO (PROCEDIMENTO)\nPaís: Portugal\nNUT III: PT111\nLocalidade: Freguesia de Estorãos\nDistrito: Braga\nConcelho: Fafe\nFreguesia: Freguesia de Estorãos\n\n10 - PRAZO DE EXECUÇÃO DO CONTRATO\nPrazo de execução do contrato: 365 DIAS\nPrevisão de renovações: Não\n\n11 - FUNDOS EU\nTêm fundos EU? Não\n\n12 - DOCUMENTOS DE HABILITAÇÃO\nHabilitação para o exercício da atividade profissional: Não\n\n13 - CONDIÇÕES DE APRESENTAÇÃO\nPlataforma eletrónica utilizada pela entidade adjudicante: ACIN\nURL para Apresentação: https://www.acingov.pt\nAdmissibilidade da apresentação de propostas variantes: Não autorizado\nPrazo para apresentação das propostas: 23-10-2025 17:00\nPrazo durante o qual os concorrentes são obrigados a manter as respetivas propostas: 66 dias a contar do termo do prazo para a apresentação das propostas\nIndicação de Subcontratação na Proposta: Inexistência de indicação de subcontratação\n\n14 - PRESTAÇÃO DE CAUÇÃO\nPrestação de caução: Não\n\n15 - FORNECIMENTO DAS PEÇAS DO CONCURSO, APRESENTAÇÃO DE PEDIDOS DE PARTICIPAÇÃO E APRESENTAÇÃO DAS PROPOSTAS\nLink para acesso às peças do concurso (URL): https://www.acingov.pt/acingovprod/2/zonaPublica/zona_publica_c/donwloadProcedurePiece/OTg0Nzk3\n\n20 - OUTROS REQUISITOS\nInformação sobre contratos reservados. Aplica-se a contratos reservados (54º-A)? Não\n\n21 - CRITÉRIO DE ADJUDICAÇÃO\nMultifator: Não\nMonofator:\nNome: Outros\nOutro nome: Fator Preço\n\n24 - CONDIÇÕES DO CONTRATO\nFaturação Eletrónica: Não autorizado\nObrigação de Subcontratação:\nCódigo da Obrigação de Subcontratação: Não é aplicável nenhuma obrigação de subcontratação.\n\n25 - COMPRA PÚBLICA ESTRATÉGICA\nCompra Pública Estratégica: Inexistência de contratação pública estratégica\n\n26 - INFORMAÇÕES ADICIONAIS\nContrato adequado para PME: Não\nCobertura ACP (Acordo dos Contratos Públicos da Organização Mundial do Comércio): Não\n\n27 - IDENTIFICAÇÃO E CONTACTOS DO ÓRGÃO DE RECURSOS ADMINISTRATIVOS\nDesignação: Executivo\nEndereço: RUA DA IGREJA N.º 380\nCódigo postal: 4820-594\nLocalidade: FAFE\nTelefone: 253503880\nFax: 253503880\nEndereço eletrónico: geral@estoraos-fafe.pt\nPrazo de interposição do recurso: 10 dias\n\n28 - IDENTIFICAÇÃO DO(S) AUTOR(ES) DE ANÚNCIO\nNome: Ernesto Oliveira\nCargo: Presidente\n419629585",
    "nipc": "506964019",
    "distrito": "Braga",
    "concelho": "Fafe",
    "freguesia": "Freguesia de Passos - Fafe",
    "site": "https://www.freguesiadeestoraos.pt/",
    "email": "geral@estoraos-fafe.pt",
    "designacao_contrato": "Empreitada para construção de um salão",
    "descricao": "Empreitada para a construção de um salão",
    "preco_base": "249.900,00 EUR",
    "prazo_execucao": "365 DIAS",
    "prazo_apresentacao_propostas": "23-10-2025 17:00",
    "fundos_eu": "Não",
    "plataforma_eletronica": "ACIN",
    "url_procedimento": "https://www.acingov.pt",
    "autor_nome": "Ernesto Oliveira",
    "autor_cargo": "Presidente"
  },
  {
    "numero_procedimento": "N/A",
    "entidade": "Centro de Formação Profissional da Industria Metalúrgica e Metalomecânica (CENFIM)",
    "link": "https://diariodarepublica.pt/dr/detalhe/contrato-publico/26499-938924592",
    "detalhes_completos": "1 - IDENTIFICAÇÃO E CONTACTOS DA ENTIDADE ADJUDICANTE\nDesignação da entidade adjudicante: Centro de Formação Profissional da Industria Metalúrgica e Metalomecânica (CENFIM)\nNIPC: 502077352\nEndereço: Rua do Açucar, n.º 88\nCódigo postal: 1950-010\nLocalidade: Lisboa\nPaís: Portugal\nNUT III: PT170\nDistrito: Lisboa\nConcelho: Lisboa\nFreguesia: Todas\nTelefone: 226103901\nFax: 226189596\nEndereço da Entidade (URL): www.cenfim.pt\nEndereço Eletrónico: dgaf@cenfim.pt\neDelivery Gateway (URL): https://community.vortal.biz/public/\nFunção da Organização: Adquirente\nNorma jurídica da Entidade Adjudicante: Organismo de direito público\nÁrea de atividade da Autoridade Adjudicante: Educação\n\n2 - JORNAL OFICIAL DA UNIÃO EUROPEIA\nO procedimento a que este anúncio diz respeito também é publicitado no Jornal Oficial da União Europeia? Não\n\n3 - AVISO\nModelo de Anúncio: Concurso público\nData de Envio do Anúncio: 08-10-2025\n\n5 - PROCESSO\nTipo de Procedimento: Concurso público\nPreço base do procedimento: Sim\nValor do preço base do procedimento: 97.160,00 EUR\nProcedimento com lotes? Sim\nNº Máx. de Lotes Autorizado: 5\nNúmero máximo de lotes que podem ser adjudicados a um concorrente: 5\n\n6 - OBJETO DO CONTRATO\nNúmero de referência interna: Concurso Público n.º 0016 P 25 FN\nDesignação do contrato: Aquisição, por LOTES, de Equipamentos Informáticos\nDescrição: Aquisição, por LOTES, de Equipamentos Informáticos\nTipo de Contrato Principal: Aquisição de Bens Móveis\nTipo de Contrato: Aquisição de Bens Móveis\nClassificação CPV (Vocabulário Comum para os Contratos Públicos)\nObjeto principal\nVocabulário Principal: 30230000\nPreço base s/IVA: 97.160,00 EUR\nLotes: \nNº: LOT-0001\nDescrição do Lote: Portátil versão 1 - PRT 01\nPreço base s/IVA: 17.080,00 EUR\nClassificação CPV (Vocabulário Comum para os Contratos Públicos)\nObjeto principal\nVocabulário Principal: 30230000\nNº: LOT-0002\nDescrição do Lote: Portátil versão 2 - PRT 02\nPreço base s/IVA: 35.650,00 EUR\nClassificação CPV (Vocabulário Comum para os Contratos Públicos)\nObjeto principal\nVocabulário Principal: 30230000\nNº: LOT-0003\nDescrição do Lote: Desktop Técnico v.1 DSK1\nPreço base s/IVA: 2.930,00 EUR\nClassificação CPV (Vocabulário Comum para os Contratos Públicos)\nObjeto principal\nVocabulário Principal: 30230000\nNº: LOT-0004\nDescrição do Lote: Desktop Técnico v.2 DSK2\nPreço base s/IVA: 28.675,00 EUR\nClassificação CPV (Vocabulário Comum para os Contratos Públicos)\nObjeto principal\nVocabulário Principal: 30230000\nNº: LOT-0005\nDescrição do Lote: Tablet - TABL\nPreço base s/IVA: 12.825,00 EUR\nClassificação CPV (Vocabulário Comum para os Contratos Públicos)\nObjeto principal\nVocabulário Principal: 30230000\n\n7 - INDICAÇÕES ADICIONAIS\nO contrato envolve aquisição conjunta (satisfação de várias entidades)? Não\nO contrato é adjudicado por uma central de compras? Não\n\n8 - TÉCNICAS\nO concurso destina-se à celebração de um acordo-quadro? Inexistência de acordo-quadro\nÉ utilizado um leilão eletrónico? Não\nÉ adotada uma fase de negociação? Não\nSistema de Aquisição Dinâmico: Inexistência de sistema de aquisição dinâmico\n\n9 - LOCAL DA EXECUÇÃO DO CONTRATO\nLOCAL DA EXECUÇÃO DO CONTRATO (PROCEDIMENTO)\nPaís: Portugal\nNUT III: PT170\nLocalidade: Lisboa\nDistrito: Lisboa\nConcelho: Lisboa\nFreguesia: Todas\nLOCAL DA EXECUÇÃO DO CONTRATO (LOTE)\nIdentificador do Lote: LOT-0001; LOT-0002; LOT-0003; LOT-0004; LOT-0005\nPaís: Portugal\nNUT III: PT170\nLocalidade: Lisboa\nDistrito: Lisboa\nConcelho: Lisboa\nFreguesia: Todas\nIdentificador do Lote: LOT-0001; LOT-0002; LOT-0003; LOT-0004; LOT-0005\nPaís: Portugal\nNUT III: PT11A\nLocalidade: Área Metropolitana do Porto\nDistrito: Porto\nConcelho: Valongo\nFreguesia: Freguesia de Ermesinde\nIdentificador do Lote: LOT-0001; LOT-0002; LOT-0003; LOT-0004; LOT-0005\nPaís: Portugal\nNUT III: PT11C\nLocalidade: Porto\nDistrito: Porto\nConcelho: Amarante\nFreguesia: Todas\nIdentificador do Lote: LOT-0001; LOT-0002; LOT-0003; LOT-0004; LOT-0005\nPaís: Portugal\nNUT III: PT16B\nLocalidade: Leiria\nDistrito: Leiria\nConcelho: Caldas da Rainha\nFreguesia: Todas\nIdentificador do Lote: LOT-0001; LOT-0002; LOT-0003; LOT-0004; LOT-0005\nPaís: Portugal\nNUT III: PT181\nLocalidade: Setúbal\nDistrito: Setúbal\nConcelho: Grandola\nFreguesia: Todas\nIdentificador do Lote: LOT-0001; LOT-0002; LOT-0003; LOT-0004; LOT-0005\nPaís: Portugal\nNUT III: PT181\nLocalidade: Setúbal\nDistrito: Setúbal\nConcelho: Sines\nFreguesia: Freguesia de Sines\nIdentificador do Lote: LOT-0001; LOT-0002; LOT-0003; LOT-0004; LOT-0005\nPaís: Portugal\nNUT III: PT16F\nLocalidade: Leiria\nDistrito: Leiria\nConcelho: Marinha Grande\nFreguesia: Todas\n\n10 - PRAZO DE EXECUÇÃO DO CONTRATO\nIdentificador do Lote: LOT-0001; LOT-0002; LOT-0003; LOT-0004; LOT-0005\nPrazo de execução do contrato: 60 DIAS\nPrevisão de renovações: Não\n\n11 - FUNDOS EU\nIdentificador do Lote: LOT-0001; LOT-0002; LOT-0003; LOT-0004; LOT-0005\nTêm fundos EU? Sim\n\n12 - DOCUMENTOS DE HABILITAÇÃO\nHabilitação para o exercício da atividade profissional: Não\n\n13 - CONDIÇÕES DE APRESENTAÇÃO\nPlataforma eletrónica utilizada pela entidade adjudicante: VORTAL\nURL para Apresentação: https://community.vortal.biz/public/\nAdmissibilidade da apresentação de propostas variantes: Não autorizado\nPrazo para apresentação das propostas: 23-10-2025 23:59\nPrazo durante o qual os concorrentes são obrigados a manter as respetivas propostas: 66 dias a contar do termo do prazo para a apresentação das propostas\nIndicação de Subcontratação na Proposta: Inexistência de indicação de subcontratação\n\n14 - PRESTAÇÃO DE CAUÇÃO\nPrestação de caução: Não\n\n15 - FORNECIMENTO DAS PEÇAS DO CONCURSO, APRESENTAÇÃO DE PEDIDOS DE PARTICIPAÇÃO E APRESENTAÇÃO DAS PROPOSTAS\nLink para acesso às peças do concurso (URL): https://community.vortal.biz/Public/public-tender-documents/YzBaQy9IY3g1NzExekJJd2ZRNW9sM3hyOStmNGE0RkROR2NDMnpLaUpFUjJha3BXZTljN2tja2o4OVVMUUNlRWxucHpEaHVabnVsK2dEelBBVjdFemc9PVY1WmIm\n\n20 - OUTROS REQUISITOS\nIdentificador do Lote: LOT-0001; LOT-0002; LOT-0003; LOT-0004; LOT-0005\nInformação sobre contratos reservados. Aplica-se a contratos reservados (54º-A)? Não\n\n21 - CRITÉRIO DE ADJUDICAÇÃO\nO Critério de adjudicação é diferenciado por lote? Não\nMultifator: Não\nMonofator:\nNome: Preço\n\n24 - CONDIÇÕES DO CONTRATO\nIdentificador do Lote: LOT-0001; LOT-0002; LOT-0003; LOT-0004; LOT-0005\nFaturação Eletrónica: Permitido\nObrigação de Subcontratação:\nCódigo da Obrigação de Subcontratação: Não é aplicável nenhuma obrigação de subcontratação.\n\n25 - COMPRA PÚBLICA ESTRATÉGICA\nCompra Pública Estratégica: Inexistência de contratação pública estratégica\n\n26 - INFORMAÇÕES ADICIONAIS\nIdentificador do Lote: LOT-0001; LOT-0002; LOT-0003; LOT-0004; LOT-0005\nContrato adequado para PME: Sim\nCobertura ACP (Acordo dos Contratos Públicos da Organização Mundial do Comércio): Não\n\n27 - IDENTIFICAÇÃO E CONTACTOS DO ÓRGÃO DE RECURSOS ADMINISTRATIVOS\nDesignação: Conselho de Administração\nEndereço: Rua do Açúcar, N.º 88, 1950-010 LISBOA\nCódigo postal: 1950-010\nLocalidade: Lisboa\nTelefone: +351 226182164\nFax: +351 226182164\nEndereço eletrónico: dgaf@cenfim.pt\n\n28 - IDENTIFICAÇÃO DO(S) AUTOR(ES) DE ANÚNCIO\nNome: CENFIM - Centro de Formação Profissional da Indústria Metalúrgica e Metalomecânica\nCargo: Diretor do Departamento de Gestão Administrativa e Financeira\n419633797",
    "nipc": "502077352",
    "distrito": "Lisboa",
    "concelho": "Lisboa",
    "freguesia": "Todas",
    "site": "www.cenfim.pt",
    "email": "dgaf@cenfim.pt",
    "designacao_contrato": "Aquisição, por LOTES, de Equipamentos Informáticos",
    "descricao": "Aquisição, por LOTES, de Equipamentos Informáticos",
    "preco_base": "97.160,00 EUR",
    "prazo_execucao": "60 DIAS",
    "prazo_apresentacao_propostas": "23-10-2025 23:59",
    "fundos_eu": "Sim",
    "plataforma_eletronica": "VORTAL",
    "url_procedimento": "https://community.vortal.biz/public/",
    "autor_nome": "CENFIM - Centro de Formação Profissional da Indústria Metalúrgica e Metalomecânica",
    "autor_cargo": "Diretor do Departamento de Gestão Administrativa e Financeira"
  },
  {
    "numero_procedimento": "N/A",
    "entidade": "Ordem dos Médicos Dentistas",
    "link": "https://diariodarepublica.pt/dr/detalhe/contrato-publico/26500-938924614",
    "detalhes_completos": "1 - IDENTIFICAÇÃO E CONTACTOS DA ENTIDADE ADJUDICANTE\nDesignação da entidade adjudicante: Ordem dos Médicos Dentistas\nNIPC: 502840579\nEndereço: Avenida Dr. Antunes Guimarães, 463\nCódigo postal: 4100-080\nLocalidade: Porto\nPaís: Portugal\nNUT III: PTZZZ\nDistrito: Todos\nConcelho: Todos\nFreguesia: Todas\nTelefone: 226197690\nFax: 226197699\nEndereço da Entidade (URL): www.omd.pt\nEndereço Eletrónico: geral@omd.pt\neDelivery Gateway (URL): https://www.acingov.pt\nFunção da Organização: Adquirente\nNorma jurídica da Entidade Adjudicante: Organismo de direito público\nÁrea de atividade da Autoridade Adjudicante: Serviços públicos das administrações públicas\n\n2 - JORNAL OFICIAL DA UNIÃO EUROPEIA\nO procedimento a que este anúncio diz respeito também é publicitado no Jornal Oficial da União Europeia? Não\n\n3 - AVISO\nModelo de Anúncio: Concurso público\nData de Envio do Anúncio: 08-10-2025\n\n5 - PROCESSO\nTipo de Procedimento: Concurso público\nPreço base do procedimento: Sim\nValor do preço base do procedimento: 110.000,00 EUR\nProcedimento com lotes? Não\n\n6 - OBJETO DO CONTRATO\nNúmero de referência interna: CP/2/2025\nDesignação do contrato: Serviços de seguros, na modalidade de Seguro de Responsabilidade Civil Profissional\nDescrição: Serviços de seguros, na modalidade de Seguro de Responsabilidade Civil Profissional \nTipo de Contrato Principal: Aquisição de Serviços\nTipo de Contrato: Aquisição de Serviços\nClassificação CPV (Vocabulário Comum para os Contratos Públicos)\nObjeto principal\nVocabulário Principal: 66516000\nPreço base s/IVA: 110.000,00 EUR\n\n7 - INDICAÇÕES ADICIONAIS\nO contrato envolve aquisição conjunta (satisfação de várias entidades)? Não\nO contrato é adjudicado por uma central de compras? Não\n\n8 - TÉCNICAS\nO concurso destina-se à celebração de um acordo-quadro? Inexistência de acordo-quadro\nÉ utilizado um leilão eletrónico? Não\nÉ adotada uma fase de negociação? Não\nSistema de Aquisição Dinâmico: Inexistência de sistema de aquisição dinâmico\n\n9 - LOCAL DA EXECUÇÃO DO CONTRATO\nLOCAL DA EXECUÇÃO DO CONTRATO (PROCEDIMENTO)\nPaís: Portugal\nNUT III: PT11A\nLocalidade: Todas\nDistrito: Porto\nConcelho: Todos\nFreguesia: Todas\n\n10 - PRAZO DE EXECUÇÃO DO CONTRATO\nPrazo de execução do contrato: 12 MESES\nPrevisão de renovações: Não\n\n11 - FUNDOS EU\nTêm fundos EU? Não\n\n12 - DOCUMENTOS DE HABILITAÇÃO\nHabilitação para o exercício da atividade profissional: Não\n\n13 - CONDIÇÕES DE APRESENTAÇÃO\nPlataforma eletrónica utilizada pela entidade adjudicante: ACIN\nURL para Apresentação: https://www.acingov.pt\nAdmissibilidade da apresentação de propostas variantes: Não autorizado\nPrazo para apresentação das propostas: 28-10-2025 23:59\nPrazo durante o qual os concorrentes são obrigados a manter as respetivas propostas: 66 dias a contar do termo do prazo para a apresentação das propostas\nIndicação de Subcontratação na Proposta: Inexistência de indicação de subcontratação\n\n14 - PRESTAÇÃO DE CAUÇÃO\nPrestação de caução: Não\n\n15 - FORNECIMENTO DAS PEÇAS DO CONCURSO, APRESENTAÇÃO DE PEDIDOS DE PARTICIPAÇÃO E APRESENTAÇÃO DAS PROPOSTAS\nLink para acesso às peças do concurso (URL): https://www.acingov.pt/acingovprod/2/zonaPublica/zona_publica_c/donwloadProcedurePiece/OTgzNDAy\n\n20 - OUTROS REQUISITOS\nInformação sobre contratos reservados. Aplica-se a contratos reservados (54º-A)? Não\n\n21 - CRITÉRIO DE ADJUDICAÇÃO\nMultifator: Não\nMonofator:\nNome: Preço\n\n24 - CONDIÇÕES DO CONTRATO\nFaturação Eletrónica: Permitido\nObrigação de Subcontratação:\nCódigo da Obrigação de Subcontratação: Não é aplicável nenhuma obrigação de subcontratação.\n\n25 - COMPRA PÚBLICA ESTRATÉGICA\nCompra Pública Estratégica: Inexistência de contratação pública estratégica\n\n26 - INFORMAÇÕES ADICIONAIS\nContrato adequado para PME: Não\nCobertura ACP (Acordo dos Contratos Públicos da Organização Mundial do Comércio): Não\n\n27 - IDENTIFICAÇÃO E CONTACTOS DO ÓRGÃO DE RECURSOS ADMINISTRATIVOS\nDesignação: Conselho Deontológico e de Disciplina da OMD\nEndereço: Avenida Dr. Antunes Guimarães, 463\nCódigo postal: 4100-080\nLocalidade: Porto\nTelefone: 226197690\nFax: 226197699\nEndereço eletrónico: cdd@omd.pt\n\n28 - IDENTIFICAÇÃO DO(S) AUTOR(ES) DE ANÚNCIO\nNome: Daniel Bulas Cruz\nCargo: colaborador\n419629074",
    "nipc": "502840579",
    "distrito": "Todos",
    "concelho": "Todos",
    "freguesia": "Todas",
    "site": "www.omd.pt",
    "email": "geral@omd.pt",
    "designacao_contrato": "Serviços de seguros, na modalidade de Seguro de Responsabilidade Civil Profissional",
    "descricao": "Serviços de seguros, na modalidade de Seguro de Responsabilidade Civil Profissional",
    "preco_base": "110.000,00 EUR",
    "prazo_execucao": "12 MESES",
    "prazo_apresentacao_propostas": "28-10-2025 23:59",
    "fundos_eu": "Não",
    "plataforma_eletronica": "ACIN",
    "url_procedimento": "https://www.acingov.pt",
    "autor_nome": "Daniel Bulas Cruz",
    "autor_cargo": "colaborador"
  },
  {
    "numero_procedimento": "N/A",
    "entidade": "Águas do Norte, S. A.",
    "link": "https://diariodarepublica.pt/dr/detalhe/contrato-publico/26503-938924615",
    "detalhes_completos": "1 - IDENTIFICAÇÃO E CONTACTOS DA ENTIDADE ADJUDICANTE\nDesignação da entidade adjudicante: Águas do Norte, S. A.\nNIPC: 513606084\nEndereço: Rua Dom Pedro de Castro, N.º 1A\nCódigo postal: 5000-669\nLocalidade: Vila Real\nPaís: Portugal\nNUT III: PT11D\nDistrito: Vila Real\nConcelho: Vila Real\nFreguesia: Freguesia de Vila Real\nTelefone: 259309370\nFax: 259309371\nEndereço da Entidade (URL): www.adnorte.pt\nEndereço Eletrónico: geral.adnorte@adp.pt\neDelivery Gateway (URL): https://www.acingov.pt\nFunção da Organização: Adquirente\nNorma jurídica da Entidade Adjudicante: Organismo de direito público\nÁrea de atividade da Autoridade Adjudicante: Serviços públicos das administrações públicas\n\n2 - JORNAL OFICIAL DA UNIÃO EUROPEIA\nO procedimento a que este anúncio diz respeito também é publicitado no Jornal Oficial da União Europeia? Sim\n\n3 - AVISO\nModelo de Anúncio: Concurso público\nData de Envio do Anúncio: 07-10-2025\n\n5 - PROCESSO\nTipo de Procedimento: Concurso público\nPreço base do procedimento: Sim\nValor do preço base do procedimento: 4.500.000,00 EUR\nProcedimento com lotes? Não\n\n6 - OBJETO DO CONTRATO\nNúmero de referência interna: PRC_0335/2025_GAE-EB1273\nDesignação do contrato: PRC_0335/2025_GAE-EB1273 - Empreitada de saneamento na União de Freguesias de Santo Tirso, Couto (S. Cristina e S. Miguel) e Burgães (Santo Tirso)\nDescrição: PRC_0335/2025_GAE-EB1273 - Empreitada de saneamento na União de Freguesias de Santo Tirso, Couto (S. Cristina e S. Miguel) e Burgães (Santo Tirso)\n\nOpções: Não\nTipo de Contrato Principal: Empreitada de Obras Públicas\nTipo de Contrato: Empreitada de Obras Públicas\nClassificação CPV (Vocabulário Comum para os Contratos Públicos)\nObjeto principal\nVocabulário Principal: 45231300\nPreço base s/IVA: 4.500.000,00 EUR\n\n7 - INDICAÇÕES ADICIONAIS\nO contrato envolve aquisição conjunta (satisfação de várias entidades)? Não\nO contrato é adjudicado por uma central de compras? Não\n\n8 - TÉCNICAS\nO concurso destina-se à celebração de um acordo-quadro? Inexistência de acordo-quadro\nÉ utilizado um leilão eletrónico? Não\nÉ adotada uma fase de negociação? Não\nSistema de Aquisição Dinâmico: Inexistência de sistema de aquisição dinâmico\n\n9 - LOCAL DA EXECUÇÃO DO CONTRATO\nLOCAL DA EXECUÇÃO DO CONTRATO (PROCEDIMENTO)\nPaís: Portugal\nNUT III: PT11A\nLocalidade: União das Freguesias de Santo Tirso, Couto (Santa Cristina e São Miguel) e Burgães\nDistrito: Porto\nConcelho: Santo Tirso\nFreguesia: União das Freguesias de Santo Tirso, Couto (Santa Cristina e São Miguel) e Burgães\n\n10 - PRAZO DE EXECUÇÃO DO CONTRATO\nPrazo de execução do contrato: 476 DIAS\nPrevisão de renovações: Não\n\n11 - FUNDOS EU\nTêm fundos EU? Não\n\n12 - DOCUMENTOS DE HABILITAÇÃO\nHabilitação para o exercício da atividade profissional: Sim\nTipo: Alvará\nDescrição: Documentos de Habilitação\n\n13 - CONDIÇÕES DE APRESENTAÇÃO\nPlataforma eletrónica utilizada pela entidade adjudicante: ACIN\nURL para Apresentação: https://www.acingov.pt\nAdmissibilidade da apresentação de propostas variantes: Não autorizado\nPrazo para apresentação das propostas: 10-11-2025 18:00\nPrazo durante o qual os concorrentes são obrigados a manter as respetivas propostas: 90 dias a contar do termo do prazo para a apresentação das propostas\nApresentação de Catálogo Eletrónico: Não autorizado\nIndicação de Subcontratação na Proposta: Inexistência de indicação de subcontratação\n\n14 - PRESTAÇÃO DE CAUÇÃO\nPrestação de caução: Sim\nPercentagem: 5%\nDescrição da Garantia Exigida: O valor da caução é de 5.00% do preço contratual.\n\n15 - FORNECIMENTO DAS PEÇAS DO CONCURSO, APRESENTAÇÃO DE PEDIDOS DE PARTICIPAÇÃO E APRESENTAÇÃO DAS PROPOSTAS\nLink para acesso às peças do concurso (URL): https://www.acingov.pt/acingovprod/2/zonaPublica/zona_publica_c/donwloadProcedurePiece/OTgzMzIx\n\n20 - OUTROS REQUISITOS\nInformação sobre contratos reservados. Aplica-se a contratos reservados (54º-A)? Não\n\n21 - CRITÉRIO DE ADJUDICAÇÃO\nMultifator: Não\nMonofator:\nNome: Preço\n\n24 - CONDIÇÕES DO CONTRATO\nFaturação Eletrónica: Permitido\nObrigação de Subcontratação:\nCódigo da Obrigação de Subcontratação: Não é aplicável nenhuma obrigação de subcontratação.\n\n25 - COMPRA PÚBLICA ESTRATÉGICA\nCompra Pública Estratégica: Inexistência de contratação pública estratégica\n\n26 - INFORMAÇÕES ADICIONAIS\nContrato adequado para PME: Não\nCobertura ACP (Acordo dos Contratos Públicos da Organização Mundial do Comércio): Não\n\n27 - IDENTIFICAÇÃO E CONTACTOS DO ÓRGÃO DE RECURSOS ADMINISTRATIVOS\nDesignação: Conselho de Administração da Águas do Norte, S.A.\nEndereço: Rua Dom Pedro de Castro, N.º 1A\nCódigo postal: 5000-669\nLocalidade: Vila Real\nTelefone: 259309370\nFax: 259309371\nEndereço eletrónico: geral.adnorte@adp.pt\nPrazo de interposição do recurso: 5 dias\n\n28 - IDENTIFICAÇÃO DO(S) AUTOR(ES) DE ANÚNCIO\nNome: Alexandra Bezelga\nCargo: Técnica Superior de Gestão de Ativos e Engenharia\n419616268",
    "nipc": "513606084",
    "distrito": "Vila Real",
    "concelho": "Vila Real",
    "freguesia": "Freguesia de Vila Real",
    "site": "www.adnorte.pt",
    "email": "geral.adnorte@adp.pt",
    "designacao_contrato": "PRC_0335/2025_GAE-EB1273 - Empreitada de saneamento na União de Freguesias de Santo Tirso, Couto (S. Cristina e S. Miguel) e Burgães (Santo Tirso)",
    "descricao": "PRC_0335/2025_GAE-EB1273 - Empreitada de saneamento na União de Freguesias de Santo Tirso, Couto (S. Cristina e S. Miguel) e Burgães (Santo Tirso)",
    "preco_base": "4.500.000,00 EUR",
    "prazo_execucao": "476 DIAS",
    "prazo_apresentacao_propostas": "10-11-2025 18:00",
    "fundos_eu": "Não",
    "plataforma_eletronica": "ACIN",
    "url_procedimento": "https://www.acingov.pt",
    "autor_nome": "Alexandra Bezelga",
    "autor_cargo": "Técnica Superior de Gestão de Ativos e Engenharia"
  }
]