[
  {
    "numero_procedimento": "N/A",
    "entidade": "Município de Belmonte",
    "link": "https://diariodarepublica.pt/dr/detalhe/contrato-publico/23911-934744986",
    "detalhes_completos": "Alteração do Anúncio de procedimento n.º 22908/2025, de 2025-08-28, com o ID 419475303\n\n1 - IDENTIFICAÇÃO E CONTACTOS DA ENTIDADE ADJUDICANTE\nDesignação da entidade adjudicante: Município de Belmonte\nNIPC: 506695956\nServiço/Órgão/Pessoa de contacto: Câmara Municipal de Belmonte\nEndereço: Rua Pedro Álvares Cabral, 135\nCódigo postal: 6250-088\nLocalidade: Belmonte\nPaís: Portugal\nNUT III: PT16J\nDistrito: Castelo Branco\nConcelho: Belmonte\nFreguesia: União das Freguesias de Belmonte e Colmeal da Torre\nTelefone: 275910010\nFax: 275910019\nEndereço da Entidade (URL): https://cm-belmonte.pt\nEndereço Eletrónico: geral@cm-belmonte.pt\nFunção da Organização: Adquirente\nNorma jurídica da Entidade Adjudicante: Autoridade local\nÁrea de atividade da Autoridade Adjudicante: Serviços públicos das administrações públicas\n\n2 - JORNAL OFICIAL DA UNIÃO EUROPEIA\nO procedimento a que este anúncio diz respeito também é publicitado no Jornal Oficial da União Europeia? Não\n\n3 - AVISO\nModelo de Anúncio: Concurso público\nData de Envio do Anúncio: 09-09-2025\n\n5 - PROCESSO\nTipo de Procedimento: Concurso público\nPreço base do procedimento: Sim\nValor do preço base do procedimento: 4.513.836,09 EUR\nProcedimento com lotes? Não\n\n6 - OBJETO DO CONTRATO\nNúmero de referência interna: 04/CP-EMP/2025\nDesignação do contrato: EMPREITADA DE CONSTRUÇÃO DE 30 HABITAÇÕES NO ÂMBITO DO PROGRAMA DE HABITAÇÃO A CUSTOS ACESSÍVEIS DA BEIRA E SERRA DA ESTRELA\nDescrição: Trata-se da construção de 30 habitações no âmbito do programa de habitação a Custos Acessíveis da Beira e Serra da Estrela\nTipo de Contrato Principal: Empreitada de Obras Públicas\nTipo de Contrato: Empreitada de Obras Públicas\nClassificação CPV (Vocabulário Comum para os Contratos Públicos)\nObjeto principal\nVocabulário Principal: 45000000\nPreço base s/IVA: 4.513.836,09 EUR\n\n7 - INDICAÇÕES ADICIONAIS\nO contrato envolve aquisição conjunta (satisfação de várias entidades)? Não\nO contrato é adjudicado por uma central de compras? Não\n\n8 - TÉCNICAS\nO concurso destina-se à celebração de um acordo-quadro? Inexistência de acordo-quadro\nÉ utilizado um leilão eletrónico? Não\nÉ adotada uma fase de negociação? Não\nSistema de Aquisição Dinâmico: Inexistência de sistema de aquisição dinâmico\n\n9 - LOCAL DA EXECUÇÃO DO CONTRATO\nLOCAL DA EXECUÇÃO DO CONTRATO (PROCEDIMENTO)\nPaís: Portugal\nNUT III: PT16J\nLocalidade: Belmonte\nDistrito: Castelo Branco\nConcelho: Belmonte\nFreguesia: União das Freguesias de Belmonte e Colmeal da Torre\n\n10 - PRAZO DE EXECUÇÃO DO CONTRATO\nPrazo de execução do contrato: 9 MESES\nPrevisão de renovações: Não\n\n11 - FUNDOS EU\nTêm fundos EU? Sim\n\n12 - DOCUMENTOS DE HABILITAÇÃO\nHabilitação para o exercício da atividade profissional: Sim\nTipo: Alvará\nDescrição: alvará empreiteiro de obras públicas com a classe máxima que cubra o valor da proposta e que tenha também a 1.ª, 4.ª e 5.ª subcategorias da 1.ª categoria, na classe correspondente ao valor dos trabalhos especializados que lhes respeitam\n\n13 - CONDIÇÕES DE APRESENTAÇÃO\nPlataforma eletrónica utilizada pela entidade adjudicante: ANOGOV\nURL para Apresentação: https://www.anogov.com/cm-belmonte/faces/\nAdmissibilidade da apresentação de propostas variantes: Não autorizado\nPrazo para apresentação das propostas: 16-09-2025 23:59\nPrazo durante o qual os concorrentes são obrigados a manter as respetivas propostas: 66 dias a contar do termo do prazo para a apresentação das propostas\nApresentação de Catálogo Eletrónico: Necessário\nIndicação de Subcontratação na Proposta: A parte do contrato que o proponente tenciona subcontratar\n\n14 - PRESTAÇÃO DE CAUÇÃO\nPrestação de caução: Sim\nPercentagem: 5%\nDescrição da Garantia Exigida: Para garantir a celebração do contrato, bem como o exato e pontual cumprimento de todas as obrigações legais e contratuais que assume com a celebração do mesmo\n\n15 - FORNECIMENTO DAS PEÇAS DO CONCURSO, APRESENTAÇÃO DE PEDIDOS DE PARTICIPAÇÃO E APRESENTAÇÃO DAS PROPOSTAS\nLink para acesso às peças do concurso (URL): https://www.anogov.com/cm-belmonte/faces/app/acessoDocs.jsp?codigoAcesso=df8I5KEAjffQvN9hk61T11zklAQdp65BtMyrY75akx2yjYiQ8d\n\n20 - OUTROS REQUISITOS\nInformação sobre contratos reservados. Aplica-se a contratos reservados (54º-A)? Não\n\n21 - CRITÉRIO DE ADJUDICAÇÃO\nMultifator: Sim\nFator: \nNome: Qualidade\nPonderação: 50%\nSubfatores: Não\nFator: \nNome: Preço\nPonderação: 50%\nSubfatores: Não\n\n24 - CONDIÇÕES DO CONTRATO\nFaturação Eletrónica: Permitido\nObrigação de Subcontratação:\nCódigo da Obrigação de Subcontratação: Não é aplicável nenhuma obrigação de subcontratação.\n\n25 - COMPRA PÚBLICA ESTRATÉGICA\nCompra Pública Estratégica: Inexistência de contratação pública estratégica\n\n26 - INFORMAÇÕES ADICIONAIS\nContrato adequado para PME: Não\nCobertura ACP (Acordo dos Contratos Públicos da Organização Mundial do Comércio): Não\n\n27 - IDENTIFICAÇÃO E CONTACTOS DO ÓRGÃO DE RECURSOS ADMINISTRATIVOS\nDesignação: Câmara Municipal de Belmonte\nEndereço: Rua Pedro Álvares Cabral, 135\nCódigo postal: 6250-088\nLocalidade: Belmonte\nEndereço eletrónico: geral@cm-belmonte.pt\nPrazo de interposição do recurso: 5 dias\n\n28 - IDENTIFICAÇÃO DO(S) AUTOR(ES) DE ANÚNCIO\nNome: António Pinto Dias Rocha\nCargo: Presidente do Município\n\n29 - ALTERAÇÃO\nMotivo da Alteração: Informações atualizadas\nIdentificador da Versão do Anúncio a Alterar: 59b4c98b-f5ca-4ffd-ac54-5295913539df-01\nIdentificador das Secções Alteradas do Anúncio Anterior: Acesso às peças do concurso, pedidos de participação e apresentação das propostas\nDescrição das Alterações: Prorrogação do prazo para entrega das propostas, em resultado do atraso na prestação dos esclarecimentos e erros e omissões.\nAlteração dos Documentos do Concurso: Sim\nData de alteração dos documentos do concurso: 09-09-2025\n419518339",
    "nipc": "506695956",
    "distrito": "Castelo Branco",
    "concelho": "Belmonte",
    "freguesia": "União das Freguesias de Belmonte e Colmeal da Torre",
    "site": "https://cm-belmonte.pt",
    "email": "geral@cm-belmonte.pt",
    "designacao_contrato": "EMPREITADA DE CONSTRUÇÃO DE 30 HABITAÇÕES NO ÂMBITO DO PROGRAMA DE HABITAÇÃO A CUSTOS ACESSÍVEIS DA BEIRA E SERRA DA ESTRELA",
    "descricao": "Trata-se da construção de 30 habitações no âmbito do programa de habitação a Custos Acessíveis da Beira e Serra da Estrela",
    "preco_base": "4.513.836,09 EUR",
    "prazo_execucao": "9 MESES",
    "prazo_apresentacao_propostas": "16-09-2025 23:59",
    "fundos_eu": "Sim",
    "plataforma_eletronica": "ANOGOV",
    "url_procedimento": "https://www.anogov.com/cm-belmonte/faces/",
    "autor_nome": "António Pinto Dias Rocha",
    "autor_cargo": "Presidente do Município"
  },
  {
    "numero_procedimento": "N/A",
    "entidade": "Unidade Local de Saúde de Coimbra, E. P. E.",
    "link": "https://diariodarepublica.pt/dr/detalhe/contrato-publico/23912-934744987",
    "detalhes_completos": "1 - IDENTIFICAÇÃO E CONTACTOS DA ENTIDADE ADJUDICANTE\nDesignação da entidade adjudicante: Unidade Local de Saúde de Coimbra, E. P. E.\nNIPC: 510103448\nEndereço: Praceta Prof. Mota Pinto\nCódigo postal: 3004-561\nLocalidade: Coimbra\nPaís: Portugal\nNUT III: PT16E\nDistrito: Coimbra\nConcelho: Coimbra\nFreguesia: Todas\nTelefone: 239400605\nFax: 239400605\nEndereço da Entidade (URL): https://www.chuc.min-saude.pt\nEndereço Eletrónico: ana.rosete@ulscoimbra.min-saude.pt\neDelivery Gateway (URL): https://community.vortal.biz/public/\nFunção da Organização: Adquirente\nNorma jurídica da Entidade Adjudicante: Organismo de direito público\nÁrea de atividade da Autoridade Adjudicante: Saúde\n\n2 - JORNAL OFICIAL DA UNIÃO EUROPEIA\nO procedimento a que este anúncio diz respeito também é publicitado no Jornal Oficial da União Europeia? Não\n\n3 - AVISO\nModelo de Anúncio: Concurso público\nData de Envio do Anúncio: 09-09-2025\n\n5 - PROCESSO\nTipo de Procedimento: Concurso público\nPreço base do procedimento: Sim\nValor do preço base do procedimento: 235.177,41 EUR\nProcedimento com lotes? Não\n\n6 - OBJETO DO CONTRATO\nNúmero de referência interna: 010900602025\nDesignação do contrato: Empreitada  de Remodelação do Serviço de Rouparia do polo HUC da Unidade Local de Saúde de Coimbra, E.P.E. \nDescrição: Empreitada  de Remodelação do Serviço de Rouparia do polo HUC da Unidade Local de Saúde de Coimbra, E.P.E. \nTipo de Contrato Principal: Empreitada de Obras Públicas\nTipo de Contrato: Empreitada de Obras Públicas\nClassificação CPV (Vocabulário Comum para os Contratos Públicos)\nObjeto principal\nVocabulário Principal: 45450000\nPreço base s/IVA: 235.177,41 EUR\n\n7 - INDICAÇÕES ADICIONAIS\nO contrato envolve aquisição conjunta (satisfação de várias entidades)? Não\nO contrato é adjudicado por uma central de compras? Não\n\n8 - TÉCNICAS\nO concurso destina-se à celebração de um acordo-quadro? Inexistência de acordo-quadro\nÉ utilizado um leilão eletrónico? Não\nÉ adotada uma fase de negociação? Não\nSistema de Aquisição Dinâmico: Inexistência de sistema de aquisição dinâmico\n\n9 - LOCAL DA EXECUÇÃO DO CONTRATO\nLOCAL DA EXECUÇÃO DO CONTRATO (PROCEDIMENTO)\nPaís: Portugal\nNUT III: PT16E\nLocalidade: Coimbra\nDistrito: Coimbra\nConcelho: Coimbra\nFreguesia: Freguesia de Santo António dos Olivais\n\n10 - PRAZO DE EXECUÇÃO DO CONTRATO\nPrazo de execução do contrato: 90 DIAS\nPrevisão de renovações: Não\n\n11 - FUNDOS EU\nTêm fundos EU? Não\n\n12 - DOCUMENTOS DE HABILITAÇÃO\nHabilitação para o exercício da atividade profissional: Não\n\n13 - CONDIÇÕES DE APRESENTAÇÃO\nPlataforma eletrónica utilizada pela entidade adjudicante: VORTAL\nURL para Apresentação: https://community.vortal.biz/public/\nAdmissibilidade da apresentação de propostas variantes: Não autorizado\nPrazo para apresentação das propostas: 30-09-2025 23:59\nPrazo durante o qual os concorrentes são obrigados a manter as respetivas propostas: 90 dias a contar do termo do prazo para a apresentação das propostas\nIndicação de Subcontratação na Proposta: Inexistência de indicação de subcontratação\n\n14 - PRESTAÇÃO DE CAUÇÃO\nPrestação de caução: Não\n\n15 - FORNECIMENTO DAS PEÇAS DO CONCURSO, APRESENTAÇÃO DE PEDIDOS DE PARTICIPAÇÃO E APRESENTAÇÃO DAS PROPOSTAS\nLink para acesso às peças do concurso (URL): https://community.vortal.biz/Public/public-tender-documents/VExmaEtUY3J4WUswc0RUMVZkSEQzVVQvQVhWSEN6cUdIdGgvQmxJR1R0Y2FTSWdydnh4MzhzK0ZjeER6aE5IaEFrYTZYUXVEeWxMYU1Cd0FHMTJiSFE9PWx2eEY3\n\n20 - OUTROS REQUISITOS\nInformação sobre contratos reservados. Aplica-se a contratos reservados (54º-A)? Não\n\n21 - CRITÉRIO DE ADJUDICAÇÃO\nMultifator: Não\nMonofator:\nNome: Preço\n\n24 - CONDIÇÕES DO CONTRATO\nFaturação Eletrónica: Permitido\nObrigação de Subcontratação:\nCódigo da Obrigação de Subcontratação: Não é aplicável nenhuma obrigação de subcontratação.\n\n25 - COMPRA PÚBLICA ESTRATÉGICA\nCompra Pública Estratégica: Inexistência de contratação pública estratégica\n\n26 - INFORMAÇÕES ADICIONAIS\nContrato adequado para PME: Sim\nCobertura ACP (Acordo dos Contratos Públicos da Organização Mundial do Comércio): Não\n\n27 - IDENTIFICAÇÃO E CONTACTOS DO ÓRGÃO DE RECURSOS ADMINISTRATIVOS\nDesignação: Conselho de Administração da Unidade Local de Saúde de Coimbra, E.P.E.\nEndereço: Praceta Prof. Mota Pinto\nCódigo postal: 3004-561\nLocalidade: Coimbra\nTelefone: +351 239400605\nFax: +351 239400400\nEndereço eletrónico: casec@ulscoimbra.min-saude.pt\n\n28 - IDENTIFICAÇÃO DO(S) AUTOR(ES) DE ANÚNCIO\nNome: Teresa Roseiro\nCargo: Assistente Técnico\n419517229",
    "nipc": "510103448",
    "distrito": "Coimbra",
    "concelho": "Coimbra",
    "freguesia": "Todas",
    "site": "https://www.chuc.min-saude.pt",
    "email": "ana.rosete@ulscoimbra.min-saude.pt",
    "designacao_contrato": "Empreitada de Remodelação do Serviço de Rouparia do polo HUC da Unidade Local de Saúde de Coimbra, E.P.E.",
    "descricao": "Empreitada de Remodelação do Serviço de Rouparia do polo HUC da Unidade Local de Saúde de Coimbra, E.P.E.",
    "preco_base": "235.177,41 EUR",
    "prazo_execucao": "90 DIAS",
    "prazo_apresentacao_propostas": "30-09-2025 23:59",
    "fundos_eu": "Não",
    "plataforma_eletronica": "VORTAL",
    "url_procedimento": "https://community.vortal.biz/public/",
    "autor_nome": "Teresa Roseiro",
    "autor_cargo": "Assistente Técnico"
  },
  {
    "numero_procedimento": "N/A",
    "entidade": "CRUZ VERMELHA PORTUGUESA (CVP)",
    "link": "https://diariodarepublica.pt/dr/detalhe/contrato-publico/23913-934778175",
    "detalhes_completos": "1 - IDENTIFICAÇÃO E CONTACTOS DA ENTIDADE ADJUDICANTE\nDesignação da entidade adjudicante: CRUZ VERMELHA PORTUGUESA (CVP)\nNIPC: 500745749\nEndereço: Jardim 9 de Abril, n.ºs 1 a 5\nCódigo postal: 1249-083\nLocalidade: Lisboa\nPaís: Portugal\nNUT III: PT170\nDistrito: Lisboa\nConcelho: Lisboa\nFreguesia: Freguesia da Estrela\nTelefone: 213939768\nFax: 213913993\nEndereço da Entidade (URL): http://www.cruzvermelha.org.pt\nEndereço Eletrónico: manuela.pontes@cruzvermelha.org.pt\neDelivery Gateway (URL): https://community.vortal.biz/public/\nFunção da Organização: Adquirente\nNorma jurídica da Entidade Adjudicante: Organismo de direito público\nÁrea de atividade da Autoridade Adjudicante: Saúde\n\n2 - JORNAL OFICIAL DA UNIÃO EUROPEIA\nO procedimento a que este anúncio diz respeito também é publicitado no Jornal Oficial da União Europeia? Não\n\n3 - AVISO\nModelo de Anúncio: Concurso público\nData de Envio do Anúncio: 09-09-2025\n\n5 - PROCESSO\nTipo de Procedimento: Concurso público\nPreço base do procedimento: Sim\nValor do preço base do procedimento: 84.400,00 EUR\nProcedimento com lotes? Não\n\n6 - OBJETO DO CONTRATO\nNúmero de referência interna: CP002/ESSLISBOA/2025\nDesignação do contrato: Aquisição do simulador de alta fidelidade obstétrico com recém-nascido \nDescrição: Aquisição do Simulador de Alta Fidelidade Obstétrico com Recém-Nascido para a Escola Superior de Saúde da Cruz Vermelha Portuguesa de Lisboa\nTipo de Contrato Principal: Aquisição de Bens Móveis\nTipo de Contrato: Aquisição de Bens Móveis\nClassificação CPV (Vocabulário Comum para os Contratos Públicos)\nObjeto principal\nVocabulário Principal: 34150000\nPreço base s/IVA: 84.400,00 EUR\n\n7 - INDICAÇÕES ADICIONAIS\nO contrato envolve aquisição conjunta (satisfação de várias entidades)? Não\nO contrato é adjudicado por uma central de compras? Não\n\n8 - TÉCNICAS\nO concurso destina-se à celebração de um acordo-quadro? Inexistência de acordo-quadro\nÉ utilizado um leilão eletrónico? Não\nÉ adotada uma fase de negociação? Não\nSistema de Aquisição Dinâmico: Inexistência de sistema de aquisição dinâmico\n\n9 - LOCAL DA EXECUÇÃO DO CONTRATO\nLOCAL DA EXECUÇÃO DO CONTRATO (PROCEDIMENTO)\nPaís: Portugal\nNUT III: PT170\nLocalidade: Lisboa\nDistrito: Lisboa\nConcelho: Lisboa\nFreguesia: Freguesia da Estrela\n\n10 - PRAZO DE EXECUÇÃO DO CONTRATO\nPrazo de execução do contrato: 45 DIAS\nPrevisão de renovações: Não\n\n11 - FUNDOS EU\nTêm fundos EU? Sim\n\n12 - DOCUMENTOS DE HABILITAÇÃO\nHabilitação para o exercício da atividade profissional: Não\n\n13 - CONDIÇÕES DE APRESENTAÇÃO\nPlataforma eletrónica utilizada pela entidade adjudicante: VORTAL\nURL para Apresentação: https://community.vortal.biz/public/\nAdmissibilidade da apresentação de propostas variantes: Não autorizado\nPrazo para apresentação das propostas: 15-09-2025 23:59\nPrazo durante o qual os concorrentes são obrigados a manter as respetivas propostas: 66 dias a contar do termo do prazo para a apresentação das propostas\nIndicação de Subcontratação na Proposta: Inexistência de indicação de subcontratação\n\n14 - PRESTAÇÃO DE CAUÇÃO\nPrestação de caução: Não\n\n15 - FORNECIMENTO DAS PEÇAS DO CONCURSO, APRESENTAÇÃO DE PEDIDOS DE PARTICIPAÇÃO E APRESENTAÇÃO DAS PROPOSTAS\nLink para acesso às peças do concurso (URL): https://community.vortal.biz/Public/public-tender-documents/a2p3NmhBd2NIK3JUNkt2Q1hvZjU2WmpEazQ0TU1FUi83aWNpRkxtZmxVeUxSUkdCakFnWnhrTlFJbTZ5dUxMeHFybVhrZmVjTjk4Q0tyTWd3dzB4d1E9PTNQcDQz\n\n20 - OUTROS REQUISITOS\nInformação sobre contratos reservados. Aplica-se a contratos reservados (54º-A)? Não\n\n21 - CRITÉRIO DE ADJUDICAÇÃO\nMultifator: Não\nMonofator:\nNome: Outros\nOutro nome: Preço\n\n24 - CONDIÇÕES DO CONTRATO\nFaturação Eletrónica: Permitido\nObrigação de Subcontratação:\nCódigo da Obrigação de Subcontratação: Não é aplicável nenhuma obrigação de subcontratação.\n\n25 - COMPRA PÚBLICA ESTRATÉGICA\nCompra Pública Estratégica: Inexistência de contratação pública estratégica\n\n26 - INFORMAÇÕES ADICIONAIS\nContrato adequado para PME: Sim\nCobertura ACP (Acordo dos Contratos Públicos da Organização Mundial do Comércio): Não\n\n27 - IDENTIFICAÇÃO E CONTACTOS DO ÓRGÃO DE RECURSOS ADMINISTRATIVOS\nDesignação: Presidente Nacional da Cruz Vermelha Portuguesa\nEndereço: Jardim 9 de Abril 1 a 5\nCódigo postal: 1249-083\nLocalidade: Lisboa\nTelefone: +351 213939768\nFax: +351 213939768\nEndereço eletrónico: presidente@cruzvermelha.org.pt\n\n28 - IDENTIFICAÇÃO DO(S) AUTOR(ES) DE ANÚNCIO\nNome: Manuela Pontes\nCargo: Coordenadora\n419516273",
    "nipc": "500745749",
    "distrito": "Lisboa",
    "concelho": "Lisboa",
    "freguesia": "Freguesia da Estrela",
    "site": "http://www.cruzvermelha.org.pt",
    "email": "manuela.pontes@cruzvermelha.org.pt",
    "designacao_contrato": "Aquisição do simulador de alta fidelidade obstétrico com recém-nascido",
    "descricao": "Aquisição do Simulador de Alta Fidelidade Obstétrico com Recém-Nascido para a Escola Superior de Saúde da Cruz Vermelha Portuguesa de Lisboa",
    "preco_base": "84.400,00 EUR",
    "prazo_execucao": "45 DIAS",
    "prazo_apresentacao_propostas": "15-09-2025 23:59",
    "fundos_eu": "Sim",
    "plataforma_eletronica": "VORTAL",
    "url_procedimento": "https://community.vortal.biz/public/",
    "autor_nome": "Manuela Pontes",
    "autor_cargo": "Coordenadora"
  },
  {
    "numero_procedimento": "N/A",
    "entidade": "Serviços Municipalizados de Alcobaça",
    "link": "https://diariodarepublica.pt/dr/detalhe/contrato-publico/23917-934778177",
    "detalhes_completos": "1 - IDENTIFICAÇÃO E CONTACTOS DA ENTIDADE ADJUDICANTE\nDesignação da entidade adjudicante: Serviços Municipalizados de Alcobaça\nNIPC: 680014942\nServiço/Órgão/Pessoa de contacto: Divisão Jurídica e de Contratação Pública\nEndereço: Rua da Liberdade, 9\nCódigo postal: 2460-060\nLocalidade: Alcobaça\nPaís: Portugal\nNUT III: PT16B\nDistrito: Leiria\nConcelho: Alcobaça\nFreguesia: Todas\nTelefone: 262580910\nFax: 262580905\nEndereço da Entidade (URL): www.smalcobaca.pt\nEndereço Eletrónico: geral@sm-alcobaca.pt\neDelivery Gateway (URL): https://www.acingov.pt\nFunção da Organização: Adquirente\nNorma jurídica da Entidade Adjudicante: Organismo de direito público\nÁrea de atividade da Entidade Adjudicante: Atividades relacionadas com a água\n\n2 - JORNAL OFICIAL DA UNIÃO EUROPEIA\nO procedimento a que este anúncio diz respeito também é publicitado no Jornal Oficial da União Europeia? Não\n\n3 - AVISO\nModelo de Anúncio: Concurso público\nData de Envio do Anúncio: 09-09-2025\n\n5 - PROCESSO\nTipo de Procedimento: Concurso público\nPreço base do procedimento: Sim\nValor do preço base do procedimento: 75.000,00 EUR\nProcedimento com lotes? Não\n\n6 - OBJETO DO CONTRATO\nNúmero de referência interna: 46/25/CP\nDesignação do contrato: Procedimento n.º 46/25/CP - Aquisição de Serviços para elaboração de Projeto- Intercetor de Drenagem do Casal da Areia\nDescrição: Aquisição de Serviços para elaboração de Projeto- Intercetor de Drenagem do Casal da Areia\nTipo de Contrato Principal: Aquisição de Serviços\nTipo de Contrato: Aquisição de Serviços\nClassificação CPV (Vocabulário Comum para os Contratos Públicos)\nObjeto principal\nVocabulário Principal: 71242000\nPreço base s/IVA: 75.000,00 EUR\n\n7 - INDICAÇÕES ADICIONAIS\nO contrato envolve aquisição conjunta (satisfação de várias entidades)? Não\nO contrato é adjudicado por uma central de compras? Não\n\n8 - TÉCNICAS\nO concurso destina-se à celebração de um acordo-quadro? Inexistência de acordo-quadro\nÉ utilizado um leilão eletrónico? Não\nÉ adotada uma fase de negociação? Não\nSistema de Aquisição Dinâmico: Inexistência de sistema de aquisição dinâmico\n\n9 - LOCAL DA EXECUÇÃO DO CONTRATO\nLOCAL DA EXECUÇÃO DO CONTRATO (PROCEDIMENTO)\nPaís: Portugal\nNUT III: PT16B\nLocalidade: Freguesia de Maiorga\nDistrito: Leiria\nConcelho: Alcobaça\nFreguesia: Freguesia de Maiorga\n\n10 - PRAZO DE EXECUÇÃO DO CONTRATO\nPrazo de execução do contrato: 6 MESES\nPrevisão de renovações: Não\n\n11 - FUNDOS EU\nTêm fundos EU? Não\n\n12 - DOCUMENTOS DE HABILITAÇÃO\nHabilitação para o exercício da atividade profissional: Não\n\n13 - CONDIÇÕES DE APRESENTAÇÃO\nPlataforma eletrónica utilizada pela entidade adjudicante: ACIN\nURL para Apresentação: https://www.acingov.pt\nAdmissibilidade da apresentação de propostas variantes: Não autorizado\nPrazo para apresentação das propostas: 15-09-2025 23:59\nPrazo durante o qual os concorrentes são obrigados a manter as respetivas propostas: 66 dias a contar do termo do prazo para a apresentação das propostas\nIndicação de Subcontratação na Proposta: Inexistência de indicação de subcontratação\n\n14 - PRESTAÇÃO DE CAUÇÃO\nPrestação de caução: Não\n\n15 - FORNECIMENTO DAS PEÇAS DO CONCURSO, APRESENTAÇÃO DE PEDIDOS DE PARTICIPAÇÃO E APRESENTAÇÃO DAS PROPOSTAS\nLink para acesso às peças do concurso (URL): https://www.acingov.pt/acingovprod/2/zonaPublica/zona_publica_c/donwloadProcedurePiece/OTc2NDkz\n\n20 - OUTROS REQUISITOS\nInformação sobre contratos reservados. Aplica-se a contratos reservados (54º-A)? Não\n\n21 - CRITÉRIO DE ADJUDICAÇÃO\nMultifator: Não\nMonofator:\nNome: Outros\nOutro nome: Fator Preço\n\n24 - CONDIÇÕES DO CONTRATO\nFaturação Eletrónica: Permitido\nObrigação de Subcontratação:\nCódigo da Obrigação de Subcontratação: Não é aplicável nenhuma obrigação de subcontratação.\n\n25 - COMPRA PÚBLICA ESTRATÉGICA\nCompra Pública Estratégica: Inexistência de contratação pública estratégica\n\n26 - INFORMAÇÕES ADICIONAIS\nContrato adequado para PME: Sim\nCobertura ACP (Acordo dos Contratos Públicos da Organização Mundial do Comércio): Não\n\n27 - IDENTIFICAÇÃO E CONTACTOS DO ÓRGÃO DE RECURSOS ADMINISTRATIVOS\nDesignação: Conselho de Administração\nEndereço: Rua da Liberdade, 9\nCódigo postal: 2460-060\nLocalidade: Alcobaça\nTelefone: 262580910\nFax: \nEndereço eletrónico: geral@sm-alcobaca.pt\n\n28 - IDENTIFICAÇÃO DO(S) AUTOR(ES) DE ANÚNCIO\nNome: Paula Maria Marques Evangelista Emidio\nCargo: Coordenadora\n419517837",
    "nipc": "680014942",
    "distrito": "Leiria",
    "concelho": "Alcobaça",
    "freguesia": "Todas",
    "site": "www.smalcobaca.pt",
    "email": "geral@sm-alcobaca.pt",
    "designacao_contrato": "Procedimento n.º 46/25/CP - Aquisição de Serviços para elaboração de Projeto- Intercetor de Drenagem do Casal da Areia",
    "descricao": "Aquisição de Serviços para elaboração de Projeto- Intercetor de Drenagem do Casal da Areia",
    "preco_base": "75.000,00 EUR",
    "prazo_execucao": "6 MESES",
    "prazo_apresentacao_propostas": "15-09-2025 23:59",
    "fundos_eu": "Não",
    "plataforma_eletronica": "ACIN",
    "url_procedimento": "https://www.acingov.pt",
    "autor_nome": "Paula Maria Marques Evangelista Emidio",
    "autor_cargo": "Coordenadora"
  },
  {
    "numero_procedimento": "N/A",
    "entidade": "BIKiNNOV - BIKE VALUE INNOVATION CENTER - ASSOCIATION",
    "link": "https://diariodarepublica.pt/dr/detalhe/contrato-publico/23922-934778182",
    "detalhes_completos": "1 - IDENTIFICAÇÃO E CONTACTOS DA ENTIDADE ADJUDICANTE\nDesignação da entidade adjudicante: BIKiNNOV - BIKE VALUE INNOVATION CENTER - ASSOCIATION\nNIPC: 516839268\nServiço/Órgão/Pessoa de contacto: BIKiNNOV\nEndereço: Rua da Indústria, 369, Covão, 3750-792 Águeda\nCódigo postal: 3750-792\nLocalidade: Águeda\nPaís: Portugal\nNUT III: PT16D\nDistrito: Aveiro\nConcelho: Águeda\nFreguesia: Freguesia de Valongo do Vouga\nTelefone: 234248960\nEndereço da Entidade (URL): www.bikinnov.pt\nEndereço Eletrónico: geral@bikinnov.pt\neDelivery Gateway (URL): https://www.acingov.pt\nFunção da Organização: Adquirente\nNorma jurídica da Entidade Adjudicante: Organismo de direito público\nÁrea de atividade da Autoridade Adjudicante: Serviços públicos das administrações públicas\n\n2 - JORNAL OFICIAL DA UNIÃO EUROPEIA\nO procedimento a que este anúncio diz respeito também é publicitado no Jornal Oficial da União Europeia? Não\n\n3 - AVISO\nModelo de Anúncio: Concurso público\nData de Envio do Anúncio: 09-09-2025\n\n5 - PROCESSO\nTipo de Procedimento: Concurso público\nPreço base do procedimento: Sim\nValor do preço base do procedimento: 76.000,00 EUR\nProcedimento com lotes? Não\n\n6 - OBJETO DO CONTRATO\nNúmero de referência interna: 47-004-ANI-25\nDesignação do contrato: Logística e Apoio à organização e disseminação de resultados de Eventos Colaborativos da Linha de Ação 1  Cidades Inteligentes do Futuro\nDescrição: Logística e Apoio à organização e disseminação de resultados de Eventos Colaborativos da Linha de Ação 1  Cidades Inteligentes do Futuro\nTipo de Contrato Principal: Aquisição de Serviços\nTipo de Contrato: Aquisição de Serviços\nClassificação CPV (Vocabulário Comum para os Contratos Públicos)\nObjeto principal\nVocabulário Principal: 79952000\nPreço base s/IVA: 76.000,00 EUR\n\n7 - INDICAÇÕES ADICIONAIS\nO contrato envolve aquisição conjunta (satisfação de várias entidades)? Não\nO contrato é adjudicado por uma central de compras? Não\n\n8 - TÉCNICAS\nO concurso destina-se à celebração de um acordo-quadro? Inexistência de acordo-quadro\nÉ utilizado um leilão eletrónico? Não\nÉ adotada uma fase de negociação? Não\nSistema de Aquisição Dinâmico: Inexistência de sistema de aquisição dinâmico\n\n9 - LOCAL DA EXECUÇÃO DO CONTRATO\nLOCAL DA EXECUÇÃO DO CONTRATO (PROCEDIMENTO)\nPaís: Portugal\nNUT III: PT16D\nLocalidade: Freguesia de Valongo do Vouga\nDistrito: Aveiro\nConcelho: Águeda\nFreguesia: Freguesia de Valongo do Vouga\n\n10 - PRAZO DE EXECUÇÃO DO CONTRATO\nData de Início: 09-10-2025\nData de Fim: 30-03-2026\nPrevisão de renovações: Não\n\n11 - FUNDOS EU\nTêm fundos EU? Sim\n\n12 - DOCUMENTOS DE HABILITAÇÃO\nHabilitação para o exercício da atividade profissional: Não\n\n13 - CONDIÇÕES DE APRESENTAÇÃO\nPlataforma eletrónica utilizada pela entidade adjudicante: ACIN\nURL para Apresentação: https://www.acingov.pt\nAdmissibilidade da apresentação de propostas variantes: Não autorizado\nPrazo para apresentação das propostas: 16-09-2025 17:00\nPrazo durante o qual os concorrentes são obrigados a manter as respetivas propostas: 66 dias a contar do termo do prazo para a apresentação das propostas\nIndicação de Subcontratação na Proposta: Inexistência de indicação de subcontratação\n\n14 - PRESTAÇÃO DE CAUÇÃO\nPrestação de caução: Não\n\n15 - FORNECIMENTO DAS PEÇAS DO CONCURSO, APRESENTAÇÃO DE PEDIDOS DE PARTICIPAÇÃO E APRESENTAÇÃO DAS PROPOSTAS\nLink para acesso às peças do concurso (URL): https://www.acingov.pt/acingovprod/2/zonaPublica/zona_publica_c/donwloadProcedurePiece/OTc2NDU4\n\n20 - OUTROS REQUISITOS\nInformação sobre contratos reservados. Aplica-se a contratos reservados (54º-A)? Não\n\n21 - CRITÉRIO DE ADJUDICAÇÃO\nMultifator: Sim\nFator: \nNome: Outros\nOutro Nome: Preço global da proposta (P1)\nPonderação: 40%\nSubfatores: Não\nFator: \nNome: Outros\nOutro Nome: Qualidade técnica da proposta (P2)\nPonderação: 60%\nSubfatores: Sim\nSubfatores: \nNome: Cenarização e proposta visual (A)\nPonderação : 40%; \nNome: Exequibilidade e clareza da proposta (B)\nPonderação : 20%; \nNome: Inovação e criatividade (C)\nPonderação : 20%; \nNome: Sustentabilidade e eficiência dos recursos (D)\nPonderação : 20%; \n\n24 - CONDIÇÕES DO CONTRATO\nFaturação Eletrónica: Permitido\nObrigação de Subcontratação:\nCódigo da Obrigação de Subcontratação: Não é aplicável nenhuma obrigação de subcontratação.\n\n25 - COMPRA PÚBLICA ESTRATÉGICA\nCompra Pública Estratégica: Inexistência de contratação pública estratégica\n\n26 - INFORMAÇÕES ADICIONAIS\nContrato adequado para PME: Sim\nCobertura ACP (Acordo dos Contratos Públicos da Organização Mundial do Comércio): Não\n\n27 - IDENTIFICAÇÃO E CONTACTOS DO ÓRGÃO DE RECURSOS ADMINISTRATIVOS\nDesignação: BIKiNNOV\nEndereço: Rua da Indústria, 369, Covão, 3750-792 Águeda\nCódigo postal: 3750-792\nLocalidade: Águeda\nTelefone: 234248960\nFax: \nEndereço eletrónico: geral@bikinnov.pt\nPrazo de interposição do recurso: 10 dias\n\n28 - IDENTIFICAÇÃO DO(S) AUTOR(ES) DE ANÚNCIO\nNome: Inês Tavares\nCargo: Gestora Financeira de Projetos\n419517001",
    "nipc": "516839268",
    "distrito": "Aveiro",
    "concelho": "Águeda",
    "freguesia": "Freguesia de Valongo do Vouga",
    "site": "www.bikinnov.pt",
    "email": "geral@bikinnov.pt",
    "designacao_contrato": "Logística e Apoio à organização e disseminação de resultados de Eventos Colaborativos da Linha de Ação 1  Cidades Inteligentes do Futuro",
    "descricao": "Logística e Apoio à organização e disseminação de resultados de Eventos Colaborativos da Linha de Ação 1  Cidades Inteligentes do Futuro",
    "preco_base": "76.000,00 EUR",
    "prazo_execucao": null,
    "prazo_apresentacao_propostas": "16-09-2025 17:00",
    "fundos_eu": "Sim",
    "plataforma_eletronica": "ACIN",
    "url_procedimento": "https://www.acingov.pt",
    "autor_nome": "Inês Tavares",
    "autor_cargo": "Gestora Financeira de Projetos"
  },
  {
    "numero_procedimento": "N/A",
    "entidade": "Procuradoria-Geral da República",
    "link": "https://diariodarepublica.pt/dr/detalhe/contrato-publico/23923-934778183",
    "detalhes_completos": "1 - IDENTIFICAÇÃO E CONTACTOS DA ENTIDADE ADJUDICANTE\nDesignação da entidade adjudicante: Procuradoria-Geral da República\nNIPC: 600020339\nEndereço: Rua da Escola Politécnica,140\nCódigo postal: 1269-269\nLocalidade: Lisboa\nPaís: Portugal\nNUT III: PT170\nDistrito: Lisboa\nConcelho: Lisboa\nFreguesia: Todas\nTelefone: 213921900\nFax: 213921900\nEndereço da Entidade (URL): www.ministeriopublico.pt\nEndereço Eletrónico: contratacaopublica@pgr.pt\neDelivery Gateway (URL): https://community.vortal.biz/public/\nFunção da Organização: Adquirente\nNorma jurídica da Entidade Adjudicante: Organismo de direito público\nÁrea de atividade da Autoridade Adjudicante: Serviços públicos das administrações públicas\n\n2 - JORNAL OFICIAL DA UNIÃO EUROPEIA\nO procedimento a que este anúncio diz respeito também é publicitado no Jornal Oficial da União Europeia? Não\n\n3 - AVISO\nModelo de Anúncio: Concurso público\nData de Envio do Anúncio: 09-09-2025\n\n5 - PROCESSO\nTipo de Procedimento: Concurso público\nPreço base do procedimento: Sim\nValor do preço base do procedimento: 35.000,00 EUR\nProcedimento com lotes? Não\n\n6 - OBJETO DO CONTRATO\nNúmero de referência interna: DA 21505/25 \nDesignação do contrato: Fornecimento, instalação e configuração de equipamento audiovisual digital, no âmbito do Plano de Recuperação e Resiliência (PRR) - TD C18-i01.10\nDescrição: Fornecimento, instalação e configuração de equipamento audiovisual digital, no âmbito do Plano de Recuperação e Resiliência (PRR) - TD C18-i01.10\nTipo de Contrato Principal: Aquisição de Bens Móveis\nTipo de Contrato: Aquisição de Bens Móveis\nClassificação CPV (Vocabulário Comum para os Contratos Públicos)\nObjeto principal\nVocabulário Principal: 32321200\nPreço base s/IVA: 35.000,00 EUR\n\n7 - INDICAÇÕES ADICIONAIS\nO contrato envolve aquisição conjunta (satisfação de várias entidades)? Não\nO contrato é adjudicado por uma central de compras? Não\n\n8 - TÉCNICAS\nO concurso destina-se à celebração de um acordo-quadro? Inexistência de acordo-quadro\nÉ utilizado um leilão eletrónico? Não\nÉ adotada uma fase de negociação? Não\nSistema de Aquisição Dinâmico: Inexistência de sistema de aquisição dinâmico\n\n9 - LOCAL DA EXECUÇÃO DO CONTRATO\nLOCAL DA EXECUÇÃO DO CONTRATO (PROCEDIMENTO)\nPaís: Portugal\nNUT III: PT170\nLocalidade: Lisboa\nDistrito: Lisboa\nConcelho: Lisboa\nFreguesia: Todas\n\n10 - PRAZO DE EXECUÇÃO DO CONTRATO\nPrazo de execução do contrato: 15 DIAS\nPrevisão de renovações: Não\n\n11 - FUNDOS EU\nTêm fundos EU? Sim\n\n12 - DOCUMENTOS DE HABILITAÇÃO\nHabilitação para o exercício da atividade profissional: Não\n\n13 - CONDIÇÕES DE APRESENTAÇÃO\nPlataforma eletrónica utilizada pela entidade adjudicante: VORTAL\nURL para Apresentação: https://community.vortal.biz/public/\nAdmissibilidade da apresentação de propostas variantes: Não autorizado\nPrazo para apresentação das propostas: 18-09-2025 23:59\nPrazo durante o qual os concorrentes são obrigados a manter as respetivas propostas: 90 dias a contar do termo do prazo para a apresentação das propostas\nIndicação de Subcontratação na Proposta: Inexistência de indicação de subcontratação\n\n14 - PRESTAÇÃO DE CAUÇÃO\nPrestação de caução: Não\n\n15 - FORNECIMENTO DAS PEÇAS DO CONCURSO, APRESENTAÇÃO DE PEDIDOS DE PARTICIPAÇÃO E APRESENTAÇÃO DAS PROPOSTAS\nLink para acesso às peças do concurso (URL): https://community.vortal.biz/Public/public-tender-documents/NHpvMmFEOFV6SjVrTGNmR1ZLODZCRUFFY2hSS2RmTlZrNlNsb29TR3dUeXhjc3RGWXhXV0o1Rk1DNXVVdVRzaWd2RS9XcEtCRW9VTi9Tek1mbkJheUE9PVU4WGpp\n\n20 - OUTROS REQUISITOS\nInformação sobre contratos reservados. Aplica-se a contratos reservados (54º-A)? Não\n\n21 - CRITÉRIO DE ADJUDICAÇÃO\nMultifator: Sim\nFator: \nNome: Preço\nPonderação: 60%\nSubfatores: Não\nFator: \nNome: Qualidade\nPonderação: 40%\nSubfatores: Não\n\n24 - CONDIÇÕES DO CONTRATO\nFaturação Eletrónica: Permitido\nObrigação de Subcontratação:\nCódigo da Obrigação de Subcontratação: Não é aplicável nenhuma obrigação de subcontratação.\n\n25 - COMPRA PÚBLICA ESTRATÉGICA\nCompra Pública Estratégica: Inexistência de contratação pública estratégica\n\n26 - INFORMAÇÕES ADICIONAIS\nContrato adequado para PME: Sim\nCobertura ACP (Acordo dos Contratos Públicos da Organização Mundial do Comércio): Não\n\n27 - IDENTIFICAÇÃO E CONTACTOS DO ÓRGÃO DE RECURSOS ADMINISTRATIVOS\nDesignação: Secretária Geral da Procuradoria Geral da República\nEndereço: Rua da Escola Politécnica, 140\nCódigo postal: 1269-269\nLocalidade: Lisboa\nTelefone: +351 213921900\nFax: +351 213975255\nEndereço eletrónico: correiopgr@pgr.pt\n\n28 - IDENTIFICAÇÃO DO(S) AUTOR(ES) DE ANÚNCIO\nNome: Carla Botelho\nCargo: Secretária Geral da Procuradoria Geral da República\n419517497",
    "nipc": "600020339",
    "distrito": "Lisboa",
    "concelho": "Lisboa",
    "freguesia": "Todas",
    "site": "www.ministeriopublico.pt",
    "email": "contratacaopublica@pgr.pt",
    "designacao_contrato": "Fornecimento, instalação e configuração de equipamento audiovisual digital, no âmbito do Plano de Recuperação e Resiliência (PRR) - TD C18-i01.10",
    "descricao": "Fornecimento, instalação e configuração de equipamento audiovisual digital, no âmbito do Plano de Recuperação e Resiliência (PRR) - TD C18-i01.10",
    "preco_base": "35.000,00 EUR",
    "prazo_execucao": "15 DIAS",
    "prazo_apresentacao_propostas": "18-09-2025 23:59",
    "fundos_eu": "Sim",
    "plataforma_eletronica": "VORTAL",
    "url_procedimento": "https://community.vortal.biz/public/",
    "autor_nome": "Carla Botelho",
    "autor_cargo": "Secretária Geral da Procuradoria Geral da República"
  },
  {
    "numero_procedimento": "N/A",
    "entidade": "Infraestruturas de Portugal",
    "link": "https://diariodarepublica.pt/dr/detalhe/contrato-publico/23914-934778875",
    "detalhes_completos": "1 - IDENTIFICAÇÃO E CONTACTOS DA ENTIDADE ADJUDICANTE\nDesignação da entidade adjudicante: Infraestruturas de Portugal\nNIPC: 503933813\nServiço/Órgão/Pessoa de contacto: Direção de Compras e Logística - Departamento de Compras - Edifício 2\nEndereço: Praça da Portagem\nCódigo postal: 2809-013\nLocalidade: Almada\nPaís: Portugal\nNUT III: PT170\nDistrito: Setúbal\nConcelho: Almada\nFreguesia: União das Freguesias de Almada, Cova da Piedade, Pragal e Cacilhas\nTelefone:  212 879 300 \nFax: 21 287 90 00\nEndereço da Entidade (URL): www.infraestruturasdeportugal.pt\nEndereço Eletrónico: dcl@infraestruturasdeportugal.pt\nFunção da Organização: Adquirente\nNorma jurídica da Entidade Adjudicante: Organismo de direito público\nÁrea de atividade da Entidade Adjudicante: Serviços ferroviários\n\n2 - JORNAL OFICIAL DA UNIÃO EUROPEIA\nO procedimento a que este anúncio diz respeito também é publicitado no Jornal Oficial da União Europeia? Não\n\n3 - AVISO\nModelo de Anúncio: Concurso público\nData de Envio do Anúncio: 09-09-2025\n\n5 - PROCESSO\nTipo de Procedimento: Concurso público\nPreço base do procedimento: Sim\nValor do preço base do procedimento: 600.000,00 EUR\nProcedimento com lotes? Não\n\n6 - OBJETO DO CONTRATO\nNúmero de referência interna: 10021147\nDesignação do contrato: Empreitada L. SUL - ESTAÇÃO DE FUNCHEIRA - REABILITAÇÃO INTERIOR DO EP\nDescrição: Empreitada L. SUL - ESTAÇÃO DE FUNCHEIRA - REABILITAÇÃO INTERIOR DO EP\nTipo de Contrato Principal: Empreitada de Obras Públicas\nTipo de Contrato: Empreitada de Obras Públicas\nClassificação CPV (Vocabulário Comum para os Contratos Públicos)\nObjeto principal\nVocabulário Principal: 45259000\nPreço base s/IVA: 600.000,00 EUR\n\n7 - INDICAÇÕES ADICIONAIS\nO contrato envolve aquisição conjunta (satisfação de várias entidades)? Não\nO contrato é adjudicado por uma central de compras? Não\n\n8 - TÉCNICAS\nO concurso destina-se à celebração de um acordo-quadro? Inexistência de acordo-quadro\nÉ utilizado um leilão eletrónico? Não\nÉ adotada uma fase de negociação? Não\nSistema de Aquisição Dinâmico: Inexistência de sistema de aquisição dinâmico\n\n9 - LOCAL DA EXECUÇÃO DO CONTRATO\nLOCAL DA EXECUÇÃO DO CONTRATO (PROCEDIMENTO)\nPaís: Portugal\nNUT III: PT184\nLocalidade: Ourique\nDistrito: Beja\nConcelho: Ourique\nFreguesia: União das Freguesias de Garvão e Santa Luzia\n\n10 - PRAZO DE EXECUÇÃO DO CONTRATO\nPrazo de execução do contrato: 210 DIAS\nPrevisão de renovações: Não\n\n11 - FUNDOS EU\nTêm fundos EU? Não\n\n12 - DOCUMENTOS DE HABILITAÇÃO\nHabilitação para o exercício da atividade profissional: Sim\nTipo: Alvará\nDescrição: 4ª Subcategoria da 1ª Categoria e da classe que cubra o valor global da proposta; 1ª Subcategoria da 4ª Categoria correspondente ao valor dos trabalhos especializados que lhe respeita\n\n13 - CONDIÇÕES DE APRESENTAÇÃO\nPlataforma eletrónica utilizada pela entidade adjudicante: ANOGOV\nURL para Apresentação: https://www.anogov.com/infraestruturasdeportugal-ip/faces/\nAdmissibilidade da apresentação de propostas variantes: Não autorizado\nPrazo para apresentação das propostas: 09-10-2025 17:00\nPrazo durante o qual os concorrentes são obrigados a manter as respetivas propostas: 120 dias a contar do termo do prazo para a apresentação das propostas\nApresentação de Catálogo Eletrónico: Não autorizado\nIndicação de Subcontratação na Proposta: Inexistência de indicação de subcontratação\n\n14 - PRESTAÇÃO DE CAUÇÃO\nPrestação de caução: Sim\nPercentagem: 5%\nDescrição da Garantia Exigida: 5% do preço contratual\n\n15 - FORNECIMENTO DAS PEÇAS DO CONCURSO, APRESENTAÇÃO DE PEDIDOS DE PARTICIPAÇÃO E APRESENTAÇÃO DAS PROPOSTAS\nLink para acesso às peças do concurso (URL): https://www.anogov.com/infraestruturasdeportugal-ip/faces/app/acessoDocs.jsp?codigoAcesso=HyA8XhXoosgUw4y18r1g9d8A6g6wkiXumUGQd9B21WCIXD6xVi\n\n20 - OUTROS REQUISITOS\nInformação sobre contratos reservados. Aplica-se a contratos reservados (54º-A)? Não\n\n21 - CRITÉRIO DE ADJUDICAÇÃO\nMultifator: Não\nMonofator:\nNome: Preço\n\n24 - CONDIÇÕES DO CONTRATO\nFaturação Eletrónica: Permitido\nObrigação de Subcontratação:\nCódigo da Obrigação de Subcontratação: Não é aplicável nenhuma obrigação de subcontratação.\n\n25 - COMPRA PÚBLICA ESTRATÉGICA\nCompra Pública Estratégica: Realização dos objetivos sociais\nContratos Públicos Sociais: Acessibilidade para todos\nCritério de Acessibilidade: Os critérios de acessibilidade para as pessoas com deficiência estão incluídos\n\n26 - INFORMAÇÕES ADICIONAIS\nContrato adequado para PME: Sim\nCobertura ACP (Acordo dos Contratos Públicos da Organização Mundial do Comércio): Não\n\n27 - IDENTIFICAÇÃO E CONTACTOS DO ÓRGÃO DE RECURSOS ADMINISTRATIVOS\nDesignação: Conselho de Administração da Infraestruturas de Portugal, S.A.\nEndereço: Praça da Portagem\nCódigo postal: 2809-013\nLocalidade: Almada\nEndereço eletrónico: contratos@infraestruturasdeportugal.pt\n\n28 - IDENTIFICAÇÃO DO(S) AUTOR(ES) DE ANÚNCIO\nNome: Clara Lourenço\nCargo: Diretora de Compras e Logística\n419514904",
    "nipc": "503933813",
    "distrito": "Setúbal",
    "concelho": "Almada",
    "freguesia": "União das Freguesias de Almada, Cova da Piedade, Pragal e Cacilhas",
    "site": "www.infraestruturasdeportugal.pt",
    "email": "dcl@infraestruturasdeportugal.pt",
    "designacao_contrato": "Empreitada L. SUL - ESTAÇÃO DE FUNCHEIRA - REABILITAÇÃO INTERIOR DO EP",
    "descricao": "Empreitada L. SUL - ESTAÇÃO DE FUNCHEIRA - REABILITAÇÃO INTERIOR DO EP",
    "preco_base": "600.000,00 EUR",
    "prazo_execucao": "210 DIAS",
    "prazo_apresentacao_propostas": "09-10-2025 17:00",
    "fundos_eu": "Não",
    "plataforma_eletronica": "ANOGOV",
    "url_procedimento": "https://www.anogov.com/infraestruturasdeportugal-ip/faces/",
    "autor_nome": "Clara Lourenço",
    "autor_cargo": "Diretora de Compras e Logística"
  },
  {
    "numero_procedimento": "N/A",
    "entidade": "Município de Ourém",
    "link": "https://diariodarepublica.pt/dr/detalhe/contrato-publico/23915-934778876",
    "detalhes_completos": "1 - IDENTIFICAÇÃO E CONTACTOS DA ENTIDADE ADJUDICANTE\nDesignação da entidade adjudicante: Município de Ourém\nNIPC: 501280740\nServiço/Órgão/Pessoa de contacto: Serviço de Contratação Pública - Divisão de Gestão Financeira\nEndereço: Praça D. Maria II, n.º1\nCódigo postal: 2490-499\nLocalidade: Ourém\nPaís: Portugal\nNUT III: PT16I\nDistrito: Santarém\nConcelho: Ourém\nFreguesia: Freguesia de Nossa Senhora da Piedade\nTelefone: 249540900\nFax: 249540908\nEndereço da Entidade (URL): www.ourem.pt\nEndereço Eletrónico: geral@mail.cm-ourem.pt\neDelivery Gateway (URL): https://www.acingov.pt\nFunção da Organização: Adquirente\nNorma jurídica da Entidade Adjudicante: Autoridade local\nÁrea de atividade da Autoridade Adjudicante: Serviços públicos das administrações públicas\n\n2 - JORNAL OFICIAL DA UNIÃO EUROPEIA\nO procedimento a que este anúncio diz respeito também é publicitado no Jornal Oficial da União Europeia? Não\n\n3 - AVISO\nModelo de Anúncio: Concurso público\nData de Envio do Anúncio: 09-09-2025\n\n5 - PROCESSO\nTipo de Procedimento: Concurso público\nPreço base do procedimento: Sim\nValor do preço base do procedimento: 139.390,80 EUR\nProcedimento com lotes? Não\n\n6 - OBJETO DO CONTRATO\nNúmero de referência interna: P220/2025\nDesignação do contrato: P220/2025 - Reparação e Reabilitação da Ponte 068, Botelha, Formigais e Pelmá, Município de Ourém e Município de Alvaiázere (108552/2025)\nDescrição: P220/2025 - Reparação e Reabilitação da Ponte 068, Botelha, Formigais e Pelmá, Município de Ourém e Município de Alvaiázere (108552/2025)\nTipo de Contrato Principal: Empreitada de Obras Públicas\nTipo de Contrato: Empreitada de Obras Públicas\nClassificação CPV (Vocabulário Comum para os Contratos Públicos)\nObjeto principal\nVocabulário Principal: 45221119\nPreço base s/IVA: 139.390,80 EUR\n\n7 - INDICAÇÕES ADICIONAIS\nO contrato envolve aquisição conjunta (satisfação de várias entidades)? Não\nO contrato é adjudicado por uma central de compras? Não\n\n8 - TÉCNICAS\nO concurso destina-se à celebração de um acordo-quadro? Inexistência de acordo-quadro\nÉ utilizado um leilão eletrónico? Não\nÉ adotada uma fase de negociação? Não\nSistema de Aquisição Dinâmico: Inexistência de sistema de aquisição dinâmico\n\n9 - LOCAL DA EXECUÇÃO DO CONTRATO\nLOCAL DA EXECUÇÃO DO CONTRATO (PROCEDIMENTO)\nPaís: Portugal\nNUT III: PT16I\nLocalidade: Freguesia de Pelmá\nDistrito: Leiria\nConcelho: Alvaiázere\nFreguesia: Freguesia de Pelmá\nPaís: Portugal\nNUT III: PT16I\nLocalidade: União das Freguesias de Freixianda, Ribeira do Fárrio e Formigais\nDistrito: Santarém\nConcelho: Ourém\nFreguesia: União das Freguesias de Freixianda, Ribeira do Fárrio e Formigais\n\n10 - PRAZO DE EXECUÇÃO DO CONTRATO\nPrazo de execução do contrato: 180 DIAS\nPrevisão de renovações: Não\n\n11 - FUNDOS EU\nTêm fundos EU? Não\n\n12 - DOCUMENTOS DE HABILITAÇÃO\nHabilitação para o exercício da atividade profissional: Sim\nTipo: Outros\nDescrição - Outros: Documentos de Habilitação\nDescrição: Os referidos no Ponto 6 do Programa de Procedimento\n\n13 - CONDIÇÕES DE APRESENTAÇÃO\nPlataforma eletrónica utilizada pela entidade adjudicante: ACIN\nURL para Apresentação: https://www.acingov.pt\nAdmissibilidade da apresentação de propostas variantes: Não autorizado\nPrazo para apresentação das propostas: 03-10-2025 23:59\nPrazo durante o qual os concorrentes são obrigados a manter as respetivas propostas: 150 dias a contar do termo do prazo para a apresentação das propostas\nIndicação de Subcontratação na Proposta: Inexistência de indicação de subcontratação\n\n14 - PRESTAÇÃO DE CAUÇÃO\nPrestação de caução: Sim\nPercentagem: 5%\nDescrição da Garantia Exigida: O valor da caução é de 5.00% do preço contratual.\n\n15 - FORNECIMENTO DAS PEÇAS DO CONCURSO, APRESENTAÇÃO DE PEDIDOS DE PARTICIPAÇÃO E APRESENTAÇÃO DAS PROPOSTAS\nLink para acesso às peças do concurso (URL): https://www.acingov.pt/acingovprod/2/zonaPublica/zona_publica_c/donwloadProcedurePiece/OTc1NTA3\n\n20 - OUTROS REQUISITOS\nInformação sobre contratos reservados. Aplica-se a contratos reservados (54º-A)? Não\n\n21 - CRITÉRIO DE ADJUDICAÇÃO\nMultifator: Não\nMonofator:\nNome: Preço\n\n24 - CONDIÇÕES DO CONTRATO\nFaturação Eletrónica: Permitido\nObrigação de Subcontratação:\nCódigo da Obrigação de Subcontratação: Não é aplicável nenhuma obrigação de subcontratação.\n\n25 - COMPRA PÚBLICA ESTRATÉGICA\nCompra Pública Estratégica: Inexistência de contratação pública estratégica\n\n26 - INFORMAÇÕES ADICIONAIS\nContrato adequado para PME: Sim\nCobertura ACP (Acordo dos Contratos Públicos da Organização Mundial do Comércio): Não\n\n27 - IDENTIFICAÇÃO E CONTACTOS DO ÓRGÃO DE RECURSOS ADMINISTRATIVOS\nDesignação: Câmara Municipal de Ourém\nEndereço: Praça D. Maria II, n.º1\nCódigo postal: 2490-499\nLocalidade: Ourém\nTelefone: 249540900\nFax: 249540908\nEndereço eletrónico: geral@mail.cm-ourem.pt\nPrazo de interposição do recurso: 5 dias\n\n28 - IDENTIFICAÇÃO DO(S) AUTOR(ES) DE ANÚNCIO\nNome: Luís Miguel Albuquerque\nCargo: Presidente de Câmara\n419515099",
    "nipc": "501280740",
    "distrito": "Santarém",
    "concelho": "Ourém",
    "freguesia": "Freguesia de Nossa Senhora da Piedade",
    "site": "www.ourem.pt",
    "email": "geral@mail.cm-ourem.pt",
    "designacao_contrato": "P220/2025 - Reparação e Reabilitação da Ponte 068, Botelha, Formigais e Pelmá, Município de Ourém e Município de Alvaiázere (108552/2025)",
    "descricao": "P220/2025 - Reparação e Reabilitação da Ponte 068, Botelha, Formigais e Pelmá, Município de Ourém e Município de Alvaiázere (108552/2025)",
    "preco_base": "139.390,80 EUR",
    "prazo_execucao": "180 DIAS",
    "prazo_apresentacao_propostas": "03-10-2025 23:59",
    "fundos_eu": "Não",
    "plataforma_eletronica": "ACIN",
    "url_procedimento": "https://www.acingov.pt",
    "autor_nome": "Luís Miguel Albuquerque",
    "autor_cargo": "Presidente de Câmara"
  },
  {
    "numero_procedimento": "N/A",
    "entidade": "Infraestruturas de Portugal",
    "link": "https://diariodarepublica.pt/dr/detalhe/contrato-publico/23916-934778877",
    "detalhes_completos": "1 - IDENTIFICAÇÃO E CONTACTOS DA ENTIDADE ADJUDICANTE\nDesignação da entidade adjudicante: Infraestruturas de Portugal\nNIPC: 503933813\nServiço/Órgão/Pessoa de contacto: Direção de Compras e Logística - Departamento de Compras - Edifício 2\nEndereço: Praça da Portagem\nCódigo postal: 2809-013\nLocalidade: Almada\nPaís: Portugal\nNUT III: PT170\nDistrito: Setúbal\nConcelho: Almada\nFreguesia: União das Freguesias de Almada, Cova da Piedade, Pragal e Cacilhas\nTelefone:  212 879 300 \nFax: 21 287 90 00\nEndereço da Entidade (URL): www.infraestruturasdeportugal.pt\nEndereço Eletrónico: dcl@infraestruturasdeportugal.pt\nFunção da Organização: Adquirente\nNorma jurídica da Entidade Adjudicante: Organismo de direito público\nÁrea de atividade da Entidade Adjudicante: Serviços ferroviários\n\n2 - JORNAL OFICIAL DA UNIÃO EUROPEIA\nO procedimento a que este anúncio diz respeito também é publicitado no Jornal Oficial da União Europeia? Não\n\n3 - AVISO\nModelo de Anúncio: Concurso público\nData de Envio do Anúncio: 09-09-2025\n\n5 - PROCESSO\nTipo de Procedimento: Concurso público\nPreço base do procedimento: Sim\nValor do preço base do procedimento: 100.000,00 EUR\nProcedimento com lotes? Não\n\n6 - OBJETO DO CONTRATO\nNúmero de referência interna: 10020272\nDesignação do contrato: L. GUIMARÃES - VIDEOMONITORIZAÇÃO  NAS ESTAÇÕES DA LINHA DE GUIMARÃES\nDescrição: L. GUIMARÃES - VIDEOMONITORIZAÇÃO  NAS ESTAÇÕES DA LINHA DE GUIMARÃES\nTipo de Contrato Principal: Aquisição de Bens Móveis\nTipo de Contrato: Aquisição de Bens Móveis\nClassificação CPV (Vocabulário Comum para os Contratos Públicos)\nObjeto principal\nVocabulário Principal: 32323500\nPreço base s/IVA: 100.000,00 EUR\n\n7 - INDICAÇÕES ADICIONAIS\nO contrato envolve aquisição conjunta (satisfação de várias entidades)? Não\nO contrato é adjudicado por uma central de compras? Não\n\n8 - TÉCNICAS\nO concurso destina-se à celebração de um acordo-quadro? Inexistência de acordo-quadro\nÉ utilizado um leilão eletrónico? Não\nÉ adotada uma fase de negociação? Não\nSistema de Aquisição Dinâmico: Inexistência de sistema de aquisição dinâmico\n\n9 - LOCAL DA EXECUÇÃO DO CONTRATO\nLOCAL DA EXECUÇÃO DO CONTRATO (PROCEDIMENTO)\nPaís: Portugal\nNUT III: PT11A\nLocalidade: Guimarães\nDistrito: Braga\nConcelho: Guimarães\nFreguesia: Todas\n\n10 - PRAZO DE EXECUÇÃO DO CONTRATO\nPrazo de execução do contrato: 232 DIAS\nPrevisão de renovações: Não\n\n11 - FUNDOS EU\nTêm fundos EU? Não\n\n12 - DOCUMENTOS DE HABILITAÇÃO\nHabilitação para o exercício da atividade profissional: Não\n\n13 - CONDIÇÕES DE APRESENTAÇÃO\nPlataforma eletrónica utilizada pela entidade adjudicante: ANOGOV\nURL para Apresentação: https://www.anogov.com/infraestruturasdeportugal-ip/faces/\nAdmissibilidade da apresentação de propostas variantes: Não autorizado\nPrazo para apresentação das propostas: 24-09-2025 17:00\nPrazo durante o qual os concorrentes são obrigados a manter as respetivas propostas: 120 dias a contar do termo do prazo para a apresentação das propostas\nApresentação de Catálogo Eletrónico: Não autorizado\nIndicação de Subcontratação na Proposta: Inexistência de indicação de subcontratação\n\n14 - PRESTAÇÃO DE CAUÇÃO\nPrestação de caução: Não\n\n15 - FORNECIMENTO DAS PEÇAS DO CONCURSO, APRESENTAÇÃO DE PEDIDOS DE PARTICIPAÇÃO E APRESENTAÇÃO DAS PROPOSTAS\nLink para acesso às peças do concurso (URL): https://www.anogov.com/infraestruturasdeportugal-ip/faces/app/acessoDocs.jsp?codigoAcesso=NokHuVYMmkcdf2RoJtwAFX6LtFy41OfEq2rn74Ev0D0uaJkghz\n\n20 - OUTROS REQUISITOS\nInformação sobre contratos reservados. Aplica-se a contratos reservados (54º-A)? Não\n\n21 - CRITÉRIO DE ADJUDICAÇÃO\nMultifator: Não\nMonofator:\nNome: Preço\n\n24 - CONDIÇÕES DO CONTRATO\nFaturação Eletrónica: Permitido\nObrigação de Subcontratação:\nCódigo da Obrigação de Subcontratação: Não é aplicável nenhuma obrigação de subcontratação.\n\n25 - COMPRA PÚBLICA ESTRATÉGICA\nCompra Pública Estratégica: Inexistência de contratação pública estratégica\n\n26 - INFORMAÇÕES ADICIONAIS\nContrato adequado para PME: Não\nCobertura ACP (Acordo dos Contratos Públicos da Organização Mundial do Comércio): Não\n\n27 - IDENTIFICAÇÃO E CONTACTOS DO ÓRGÃO DE RECURSOS ADMINISTRATIVOS\nDesignação: Infraestruturas de Portugal, S.A.\nEndereço: Praça da Portagem\nCódigo postal: 2809-013\nLocalidade: Almada\nEndereço eletrónico: contratos@infraestruturasdeportugal.pt\n\n28 - IDENTIFICAÇÃO DO(S) AUTOR(ES) DE ANÚNCIO\nNome: Clara Lourenço\nCargo: Diretora da Direção de Compras e Logística\n419515106",
    "nipc": "503933813",
    "distrito": "Setúbal",
    "concelho": "Almada",
    "freguesia": "União das Freguesias de Almada, Cova da Piedade, Pragal e Cacilhas",
    "site": "www.infraestruturasdeportugal.pt",
    "email": "dcl@infraestruturasdeportugal.pt",
    "designacao_contrato": "L. GUIMARÃES - VIDEOMONITORIZAÇÃO NAS ESTAÇÕES DA LINHA DE GUIMARÃES",
    "descricao": "L. GUIMARÃES - VIDEOMONITORIZAÇÃO NAS ESTAÇÕES DA LINHA DE GUIMARÃES",
    "preco_base": "100.000,00 EUR",
    "prazo_execucao": "232 DIAS",
    "prazo_apresentacao_propostas": "24-09-2025 17:00",
    "fundos_eu": "Não",
    "plataforma_eletronica": "ANOGOV",
    "url_procedimento": "https://www.anogov.com/infraestruturasdeportugal-ip/faces/",
    "autor_nome": "Clara Lourenço",
    "autor_cargo": "Diretora da Direção de Compras e Logística"
  },
  {
    "numero_procedimento": "N/A",
    "entidade": "Universidade de Lisboa",
    "link": "https://diariodarepublica.pt/dr/detalhe/contrato-publico/23918-934778881",
    "detalhes_completos": "1 - IDENTIFICAÇÃO E CONTACTOS DA ENTIDADE ADJUDICANTE\nDesignação da entidade adjudicante: Universidade de Lisboa\nNIPC: 510739024\nServiço/Órgão/Pessoa de contacto: Reitor\nEndereço: Alameda da Universidade, Cidade Universitária\nCódigo postal: 1649-004\nLocalidade: Lisboa\nPaís: Portugal\nNUT III: PT170\nDistrito: Lisboa\nConcelho: Lisboa\nFreguesia: Freguesia de Alvalade - Lisboa\nTelefone: 210113400\nFax: 210113402\nEndereço da Entidade (URL): www.ulisboa.pt\nEndereço Eletrónico: geral.aca@reitoria.ulisboa.pt\neDelivery Gateway (URL): https://www.acingov.pt\nFunção da Organização: Adquirente\nSubfunção da Organização: Organização cujo orçamento é utilizado para pagar o contrato; Organização que executa o pagamento; Organização que fornece informações adicionais sobre o processo de adjudicação; Organização responsável pelo tratamento das propostas; Organização que recebe as propostas; Organização que recebe pedidos de participação; Organização que assina o contrato\nNorma jurídica da Entidade Adjudicante: Organismo de direito público\nÁrea de atividade da Autoridade Adjudicante: Educação\n\n2 - JORNAL OFICIAL DA UNIÃO EUROPEIA\nO procedimento a que este anúncio diz respeito também é publicitado no Jornal Oficial da União Europeia? Não\n\n3 - AVISO\nModelo de Anúncio: Concurso público\nData de Envio do Anúncio: 09-09-2025\n\n5 - PROCESSO\nTipo de Procedimento: Concurso público\nPreço base do procedimento: Sim\nValor do preço base do procedimento: 75.000,00 EUR\nProcedimento com lotes? Não\n\n6 - OBJETO DO CONTRATO\nNúmero de referência interna: 2500000623_CF_50DI2025\nDesignação do contrato: Serviços de cibersegurança de SOC (Security Operations Center) + SIEM (Security Information and Event Management) e respetivo licenciamento\nDescrição: Serviços de cibersegurança de SOC (Security Operations Center) + SIEM (Security Information and Event Management) e respetivo licenciamento\nTipo de Contrato Principal: Aquisição de Serviços\nTipo de Contrato: Aquisição de Serviços\nClassificação CPV (Vocabulário Comum para os Contratos Públicos)\nObjeto principal\nVocabulário Principal: 72910000\nPreço base s/IVA: 75.000,00 EUR\n\n7 - INDICAÇÕES ADICIONAIS\nO contrato envolve aquisição conjunta (satisfação de várias entidades)? Não\nO contrato é adjudicado por uma central de compras? Não\n\n8 - TÉCNICAS\nO concurso destina-se à celebração de um acordo-quadro? Inexistência de acordo-quadro\nÉ utilizado um leilão eletrónico? Não\nÉ adotada uma fase de negociação? Não\nSistema de Aquisição Dinâmico: Inexistência de sistema de aquisição dinâmico\n\n9 - LOCAL DA EXECUÇÃO DO CONTRATO\nLOCAL DA EXECUÇÃO DO CONTRATO (PROCEDIMENTO)\nPaís: Portugal\nNUT III: PT170\nLocalidade: Freguesia de Alvalade - Lisboa\nDistrito: Lisboa\nConcelho: Lisboa\nFreguesia: Freguesia de Alvalade - Lisboa\n\n10 - PRAZO DE EXECUÇÃO DO CONTRATO\nPrazo de execução do contrato: 12 MESES\nPrevisão de renovações: Não\n\n11 - FUNDOS EU\nTêm fundos EU? Não\n\n12 - DOCUMENTOS DE HABILITAÇÃO\nHabilitação para o exercício da atividade profissional: Não\n\n13 - CONDIÇÕES DE APRESENTAÇÃO\nPlataforma eletrónica utilizada pela entidade adjudicante: ACIN\nURL para Apresentação: https://www.acingov.pt\nAdmissibilidade da apresentação de propostas variantes: Não autorizado\nPrazo para apresentação das propostas: 16-09-2025 23:59\nPrazo durante o qual os concorrentes são obrigados a manter as respetivas propostas: 66 dias a contar do termo do prazo para a apresentação das propostas\nIndicação de Subcontratação na Proposta: Inexistência de indicação de subcontratação\n\n14 - PRESTAÇÃO DE CAUÇÃO\nPrestação de caução: Não\n\n15 - FORNECIMENTO DAS PEÇAS DO CONCURSO, APRESENTAÇÃO DE PEDIDOS DE PARTICIPAÇÃO E APRESENTAÇÃO DAS PROPOSTAS\nLink para acesso às peças do concurso (URL): https://www.acingov.pt/acingovprod/2/zonaPublica/zona_publica_c/donwloadProcedurePiece/OTc2MzMz\n\n20 - OUTROS REQUISITOS\nInformação sobre contratos reservados. Aplica-se a contratos reservados (54º-A)? Não\n\n21 - CRITÉRIO DE ADJUDICAÇÃO\nMultifator: Não\nMonofator:\nNome: Preço\n\n24 - CONDIÇÕES DO CONTRATO\nFaturação Eletrónica: Necessário\nObrigação de Subcontratação:\nCódigo da Obrigação de Subcontratação: Não é aplicável nenhuma obrigação de subcontratação.\n\n25 - COMPRA PÚBLICA ESTRATÉGICA\nCompra Pública Estratégica: Inexistência de contratação pública estratégica\n\n26 - INFORMAÇÕES ADICIONAIS\nContrato adequado para PME: Sim\nCobertura ACP (Acordo dos Contratos Públicos da Organização Mundial do Comércio): Não\n\n27 - IDENTIFICAÇÃO E CONTACTOS DO ÓRGÃO DE RECURSOS ADMINISTRATIVOS\nDesignação: Vice-Reitor Professor Doutor Luís Manuel Soares dos Santos Castro\nEndereço: Alameda da Universidade, Cidade Universitária\nCódigo postal: 1649-004\nLocalidade: Lisboa\nTelefone: 210113400\nFax: 210113402\nEndereço eletrónico: geral.aca@reitoria.ulisboa.pt\nPrazo de interposição do recurso: 5 dias\n\n28 - IDENTIFICAÇÃO DO(S) AUTOR(ES) DE ANÚNCIO\nNome: Catarina Faquinéu\nCargo: Técnica Superior\n419517918",
    "nipc": "510739024",
    "distrito": "Lisboa",
    "concelho": "Lisboa",
    "freguesia": "Freguesia de Alvalade - Lisboa",
    "site": "www.ulisboa.pt",
    "email": "geral.aca@reitoria.ulisboa.pt",
    "designacao_contrato": "Serviços de cibersegurança de SOC (Security Operations Center) + SIEM (Security Information and Event Management) e respetivo licenciamento",
    "descricao": "Serviços de cibersegurança de SOC (Security Operations Center) + SIEM (Security Information and Event Management) e respetivo licenciamento",
    "preco_base": "75.000,00 EUR",
    "prazo_execucao": "12 MESES",
    "prazo_apresentacao_propostas": "16-09-2025 23:59",
    "fundos_eu": "Não",
    "plataforma_eletronica": "ACIN",
    "url_procedimento": "https://www.acingov.pt",
    "autor_nome": "Catarina Faquinéu",
    "autor_cargo": "Técnica Superior"
  },
  {
    "numero_procedimento": "N/A",
    "entidade": "Agência de Gestão da Tesouraria e da Dívida Pública - IGCP, E.P.E.",
    "link": "https://diariodarepublica.pt/dr/detalhe/contrato-publico/23919-934778882",
    "detalhes_completos": "1 - IDENTIFICAÇÃO E CONTACTOS DA ENTIDADE ADJUDICANTE\nDesignação da entidade adjudicante: Agência de Gestão da Tesouraria e da Dívida Pública - IGCP, E.P.E.\nNIPC: 503756237\nEndereço: Av. da República n.º 57, 1º\nCódigo postal: 1050-189\nLocalidade: Lisboa\nPaís: Portugal\nNUT III: PT170\nDistrito: Lisboa\nConcelho: Lisboa\nFreguesia: Todas\nTelefone: 217923300\nFax: 217993795\nEndereço da Entidade (URL): www.igcp.pt\nEndereço Eletrónico: info@igcp.pt\neDelivery Gateway (URL): https://community.vortal.biz/public/\nFunção da Organização: Adquirente\nNorma jurídica da Entidade Adjudicante: Autoridade da administração central\nÁrea de atividade da Autoridade Adjudicante: Assuntos económicos\n\n2 - JORNAL OFICIAL DA UNIÃO EUROPEIA\nO procedimento a que este anúncio diz respeito também é publicitado no Jornal Oficial da União Europeia? Não\n\n3 - AVISO\nModelo de Anúncio: Concurso público\nData de Envio do Anúncio: 09-09-2025\n\n5 - PROCESSO\nTipo de Procedimento: Concurso público\nPreço base do procedimento: Sim\nValor do preço base do procedimento: 130.000,00 EUR\nProcedimento com lotes? Não\n\n6 - OBJETO DO CONTRATO\nNúmero de referência interna: CP/SDR/2025-003\nDesignação do contrato: Prestação de serviços de impressão, envelopagem e entrega para expedição dos extratos das Contas Aforro\nDescrição: Prestação de serviços de impressão, envelopagem e entrega para expedição dos extratos das Contas Aforro\nTipo de Contrato Principal: Aquisição de Bens Móveis\nTipo de Contrato: Aquisição de Bens Móveis\nClassificação CPV (Vocabulário Comum para os Contratos Públicos)\nObjeto principal\nVocabulário Principal: 22900000\nPreço base s/IVA: 130.000,00 EUR\n\n7 - INDICAÇÕES ADICIONAIS\nO contrato envolve aquisição conjunta (satisfação de várias entidades)? Não\nO contrato é adjudicado por uma central de compras? Não\n\n8 - TÉCNICAS\nO concurso destina-se à celebração de um acordo-quadro? Inexistência de acordo-quadro\nÉ utilizado um leilão eletrónico? Não\nÉ adotada uma fase de negociação? Não\nSistema de Aquisição Dinâmico: Inexistência de sistema de aquisição dinâmico\n\n9 - LOCAL DA EXECUÇÃO DO CONTRATO\nLOCAL DA EXECUÇÃO DO CONTRATO (PROCEDIMENTO)\nPaís: Portugal\nNUT III: PT170\nLocalidade: Lisboa\nDistrito: Lisboa\nConcelho: Lisboa\nFreguesia: Todas\n\n10 - PRAZO DE EXECUÇÃO DO CONTRATO\nPrazo de execução do contrato: 36 MESES\nPrevisão de renovações: Não\n\n11 - FUNDOS EU\nTêm fundos EU? Não\n\n12 - DOCUMENTOS DE HABILITAÇÃO\nHabilitação para o exercício da atividade profissional: Não\n\n13 - CONDIÇÕES DE APRESENTAÇÃO\nPlataforma eletrónica utilizada pela entidade adjudicante: VORTAL\nURL para Apresentação: https://community.vortal.biz/public/\nAdmissibilidade da apresentação de propostas variantes: Não autorizado\nPrazo para apresentação das propostas: 21-09-2025 17:00\nPrazo durante o qual os concorrentes são obrigados a manter as respetivas propostas: 90 dias a contar do termo do prazo para a apresentação das propostas\nIndicação de Subcontratação na Proposta: Inexistência de indicação de subcontratação\n\n14 - PRESTAÇÃO DE CAUÇÃO\nPrestação de caução: Não\n\n15 - FORNECIMENTO DAS PEÇAS DO CONCURSO, APRESENTAÇÃO DE PEDIDOS DE PARTICIPAÇÃO E APRESENTAÇÃO DAS PROPOSTAS\nLink para acesso às peças do concurso (URL): https://community.vortal.biz/Public/public-tender-documents/UW5ucmpCOXVweXFCMjFyR1c3T1ZOWmh2VHNHMko3ZUt5N1c3N2JOaWZhQVBUeWJMd3RBdi80SDNtdUd0OXBYWVFDalA5Mm9GdmJsUEVya05ub0NhNGc9PWRLNm42\n\n20 - OUTROS REQUISITOS\nInformação sobre contratos reservados. Aplica-se a contratos reservados (54º-A)? Não\n\n21 - CRITÉRIO DE ADJUDICAÇÃO\nMultifator: Não\nMonofator:\nNome: Outros\nOutro nome: Preço\n\n24 - CONDIÇÕES DO CONTRATO\nFaturação Eletrónica: Permitido\nObrigação de Subcontratação:\nCódigo da Obrigação de Subcontratação: Não é aplicável nenhuma obrigação de subcontratação.\n\n25 - COMPRA PÚBLICA ESTRATÉGICA\nCompra Pública Estratégica: Redução dos impactos ambientais\nDescrição do Processo de Adjudicação Estratégico: Conforme as peças do procedimento\nCritérios de contratos Públicos Ecológicos: Critérios de contratação pública ecológica nacional\nCategorias da estratégia nacional: Outros\nOutra categoria (Descrição): Não Aplicável\nDiretiva Veículos Não Poluentes: Não\nCritério de Acessibilidade: Os critérios de acessibilidade para as pessoas com deficiência não estão incluídos porque o contrato não se destina a pessoas singulares\n\n26 - INFORMAÇÕES ADICIONAIS\nContrato adequado para PME: Sim\nCobertura ACP (Acordo dos Contratos Públicos da Organização Mundial do Comércio): Não\n\n27 - IDENTIFICAÇÃO E CONTACTOS DO ÓRGÃO DE RECURSOS ADMINISTRATIVOS\nDesignação: IGCP - Agência de Gestão da Tesouraria e da Dívida Pública\nEndereço: Avª da República, 57 - 1º\nCódigo postal: 1050-189\nLocalidade: Lisboa\nTelefone: +351 217923300\nFax: +351 217993795\nEndereço eletrónico: info@igcp.pt\n\n28 - IDENTIFICAÇÃO DO(S) AUTOR(ES) DE ANÚNCIO\nNome: pedro.santos@igcp.pt\nCargo: Técnico\n419517489",
    "nipc": "503756237",
    "distrito": "Lisboa",
    "concelho": "Lisboa",
    "freguesia": "Todas",
    "site": "www.igcp.pt",
    "email": "info@igcp.pt",
    "designacao_contrato": "Prestação de serviços de impressão, envelopagem e entrega para expedição dos extratos das Contas Aforro",
    "descricao": "Prestação de serviços de impressão, envelopagem e entrega para expedição dos extratos das Contas Aforro",
    "preco_base": "130.000,00 EUR",
    "prazo_execucao": "36 MESES",
    "prazo_apresentacao_propostas": "21-09-2025 17:00",
    "fundos_eu": "Não",
    "plataforma_eletronica": "VORTAL",
    "url_procedimento": "https://community.vortal.biz/public/",
    "autor_nome": "pedro.santos@igcp.pt",
    "autor_cargo": "Técnico"
  },
  {
    "numero_procedimento": "N/A",
    "entidade": "Instituto Politécnico de Bragança",
    "link": "https://diariodarepublica.pt/dr/detalhe/contrato-publico/23920-934778883",
    "detalhes_completos": "Alteração do Anúncio de procedimento n.º 23032/2025, de 2025-08-29, com o ID 419479476\n\n1 - IDENTIFICAÇÃO E CONTACTOS DA ENTIDADE ADJUDICANTE\nDesignação da entidade adjudicante: Instituto Politécnico de Bragança\nNIPC: 600013758\nServiço/Órgão/Pessoa de contacto: Vice-Presidente do IPB, Prof. Doutor Albano Agostinho Gomes Alves\nEndereço: Campus de Santa Apolónia\nCódigo postal: 5300-253\nLocalidade: Bragança\nPaís: Portugal\nNUT III: PT11E\nDistrito: Braganca\nConcelho: Bragança\nFreguesia: União das Freguesias de Sé, Santa Maria e Meixedo\nTelefone: 273303200\nFax: 273325405\nEndereço da Entidade (URL): www.ipb.pt\nEndereço Eletrónico: ipb@ipb.pt\neDelivery Gateway (URL): https://www.acingov.pt\nFunção da Organização: Adquirente\nNorma jurídica da Entidade Adjudicante: Organismo de direito público\nÁrea de atividade da Autoridade Adjudicante: Educação\n\n2 - JORNAL OFICIAL DA UNIÃO EUROPEIA\nO procedimento a que este anúncio diz respeito também é publicitado no Jornal Oficial da União Europeia? Não\n\n3 - AVISO\nModelo de Anúncio: Concurso público\nData de Envio do Anúncio: 09-09-2025\n\n5 - PROCESSO\nTipo de Procedimento: Concurso público\nPreço base do procedimento: Sim\nValor do preço base do procedimento: 600.000,00 EUR\nProcedimento com lotes? Sim\nNº Máx. de Lotes Autorizado: 2\nNúmero máximo de lotes que podem ser adjudicados a um concorrente: 2\n\n6 - OBJETO DO CONTRATO\nNúmero de referência interna: 63/CPNE/2025\nDesignação do contrato: Empreitada para a Requalificação de coberturas de edifícios do Instituto Politécnico de Bragança\nDescrição: Empreitada para a Requalificação de coberturas de edifícios do Instituto Politécnico de Bragança\nTipo de Contrato Principal: Empreitada de Obras Públicas\nTipo de Contrato: Empreitada de Obras Públicas\nClassificação CPV (Vocabulário Comum para os Contratos Públicos)\nObjeto principal\nVocabulário Principal: 45220000\nPreço base s/IVA: 600.000,00 EUR\nLotes: \nNº: LOT-0001\nDescrição do Lote: Substituição da tela asfáltica na cobertura da ESTIG, incluindo claraboias e demais trabalhos necessários à estanquicidade.\nPreço base s/IVA: 490.000,00 EUR\nClassificação CPV (Vocabulário Comum para os Contratos Públicos)\nObjeto principal\nVocabulário Principal: 45220000\nNº: LOT-0002\nDescrição do Lote: Remoção das coberturas de fibrocimento e a sua substituição por painel do tipo sandwich nos edifícios do Hangar e Manjedoura da Escola Superior Agrária\nPreço base s/IVA: 110.000,00 EUR\nClassificação CPV (Vocabulário Comum para os Contratos Públicos)\nObjeto principal\nVocabulário Principal: 45220000\n\n7 - INDICAÇÕES ADICIONAIS\nO contrato envolve aquisição conjunta (satisfação de várias entidades)? Não\nO contrato é adjudicado por uma central de compras? Não\n\n8 - TÉCNICAS\nO concurso destina-se à celebração de um acordo-quadro? Inexistência de acordo-quadro\nÉ utilizado um leilão eletrónico? Não\nÉ adotada uma fase de negociação? Não\nSistema de Aquisição Dinâmico: Inexistência de sistema de aquisição dinâmico\n\n9 - LOCAL DA EXECUÇÃO DO CONTRATO\nLOCAL DA EXECUÇÃO DO CONTRATO (PROCEDIMENTO)\nPaís: Portugal\nNUT III: PT11E\nLocalidade: União das Freguesias de Sé, Santa Maria e Meixedo\nDistrito: Braganca\nConcelho: Bragança\nFreguesia: União das Freguesias de Sé, Santa Maria e Meixedo\nLOCAL DA EXECUÇÃO DO CONTRATO (LOTE)\nIdentificador do Lote: LOT-0001; LOT-0002\nPaís: Portugal\nNUT III: PT11E\nLocalidade: União das Freguesias de Sé, Santa Maria e Meixedo\nDistrito: Braganca\nConcelho: Bragança\nFreguesia: União das Freguesias de Sé, Santa Maria e Meixedo\n\n10 - PRAZO DE EXECUÇÃO DO CONTRATO\nIdentificador do Lote: LOT-0001; LOT-0002\nPrazo de execução do contrato: 90 DIAS\nPrevisão de renovações: Não\n\n11 - FUNDOS EU\nIdentificador do Lote: LOT-0001; LOT-0002\nTêm fundos EU? Não\n\n12 - DOCUMENTOS DE HABILITAÇÃO\nHabilitação para o exercício da atividade profissional: Sim\nTipo: Alvará\nDescrição: Alvará de empreiteiro de obras públicas\n- Lote 1: classe 3 das categorias 1ª e 5ª;\n- Lote 2: classe 1 das categorias 1ª;\n\n13 - CONDIÇÕES DE APRESENTAÇÃO\nPlataforma eletrónica utilizada pela entidade adjudicante: ACIN\nURL para Apresentação: https://www.acingov.pt\nAdmissibilidade da apresentação de propostas variantes: Não autorizado\nPrazo para apresentação das propostas: 15-09-2025 20:00\nPrazo durante o qual os concorrentes são obrigados a manter as respetivas propostas: 90 dias a contar do termo do prazo para a apresentação das propostas\nIndicação de Subcontratação na Proposta: Inexistência de indicação de subcontratação\n\n14 - PRESTAÇÃO DE CAUÇÃO\nPrestação de caução: Não\n\n15 - FORNECIMENTO DAS PEÇAS DO CONCURSO, APRESENTAÇÃO DE PEDIDOS DE PARTICIPAÇÃO E APRESENTAÇÃO DAS PROPOSTAS\nLink para acesso às peças do concurso (URL): https://www.acingov.pt/acingovprod/2/zonaPublica/zona_publica_c/donwloadProcedurePiece/OTcyODgy\n\n20 - OUTROS REQUISITOS\nIdentificador do Lote: LOT-0001; LOT-0002\nInformação sobre contratos reservados. Aplica-se a contratos reservados (54º-A)? Não\n\n21 - CRITÉRIO DE ADJUDICAÇÃO\nO Critério de adjudicação é diferenciado por lote? Não\nMultifator: Não\nMonofator:\nNome: Preço\n\n24 - CONDIÇÕES DO CONTRATO\nIdentificador do Lote: LOT-0001; LOT-0002\nFaturação Eletrónica: Necessário\nObrigação de Subcontratação:\nCódigo da Obrigação de Subcontratação: Não é aplicável nenhuma obrigação de subcontratação.\n\n25 - COMPRA PÚBLICA ESTRATÉGICA\nCompra Pública Estratégica: Inexistência de contratação pública estratégica\n\n26 - INFORMAÇÕES ADICIONAIS\nIdentificador do Lote: LOT-0001; LOT-0002\nContrato adequado para PME: Sim\nCobertura ACP (Acordo dos Contratos Públicos da Organização Mundial do Comércio): Não\n\n27 - IDENTIFICAÇÃO E CONTACTOS DO ÓRGÃO DE RECURSOS ADMINISTRATIVOS\nDesignação: Presidente do IPB\nEndereço: Campus de Santa Apolónia, s/n\nCódigo postal: 5300-253\nLocalidade: Bragança\nTelefone: 273303200\nFax: 273325405\nEndereço eletrónico: ipb@ipb.pt\nPrazo de interposição do recurso: 5 dias\n\n28 - IDENTIFICAÇÃO DO(S) AUTOR(ES) DE ANÚNCIO\nNome: Albano Agostinho Gomes Alves\nCargo: Vice-Presidente\n\n29 - ALTERAÇÃO\nMotivo da Alteração: Informações atualizadas\nIdentificador da Versão do Anúncio a Alterar: ba4227b1-369f-429f-a774-d72fcc78505f-01\nIdentificador das Secções Alteradas do Anúncio Anterior: Condições de Apresentação\nDescrição das Alterações: Modificação do prazo para a apresentação de propostas\nAlteração dos Documentos do Concurso: Não\n419518947",
    "nipc": "600013758",
    "distrito": "Braganca",
    "concelho": "Bragança",
    "freguesia": "União das Freguesias de Sé, Santa Maria e Meixedo",
    "site": "www.ipb.pt",
    "email": "ipb@ipb.pt",
    "designacao_contrato": "Empreitada para a Requalificação de coberturas de edifícios do Instituto Politécnico de Bragança",
    "descricao": "Empreitada para a Requalificação de coberturas de edifícios do Instituto Politécnico de Bragança",
    "preco_base": "600.000,00 EUR",
    "prazo_execucao": "90 DIAS",
    "prazo_apresentacao_propostas": "15-09-2025 20:00",
    "fundos_eu": "Não",
    "plataforma_eletronica": "ACIN",
    "url_procedimento": "https://www.acingov.pt",
    "autor_nome": "Albano Agostinho Gomes Alves",
    "autor_cargo": "Vice-Presidente"
  },
  {
    "numero_procedimento": "N/A",
    "entidade": "MUNICÍPIO DE LOULÉ",
    "link": "https://diariodarepublica.pt/dr/detalhe/contrato-publico/23921-934778884",
    "detalhes_completos": "1 - IDENTIFICAÇÃO E CONTACTOS DA ENTIDADE ADJUDICANTE\nDesignação da entidade adjudicante: MUNICÍPIO DE LOULÉ\nNIPC: 502098139\nEndereço: Praça da República\nCódigo postal: 8104-001\nLocalidade: Faro\nPaís: Portugal\nNUT III: PT150\nDistrito: Faro\nConcelho: Loulé\nFreguesia: Todas\nTelefone: 289400834\nFax: 289415557\nEndereço da Entidade (URL): www.cm-loule.pt\nEndereço Eletrónico: aprovisionamento@cm-loule.pt\neDelivery Gateway (URL): https://community.vortal.biz/public/\nFunção da Organização: Adquirente\nNorma jurídica da Entidade Adjudicante: Autoridade local\nÁrea de atividade da Autoridade Adjudicante: Serviços públicos das administrações públicas\n\n2 - JORNAL OFICIAL DA UNIÃO EUROPEIA\nO procedimento a que este anúncio diz respeito também é publicitado no Jornal Oficial da União Europeia? Não\n\n3 - AVISO\nModelo de Anúncio: Concurso público\nData de Envio do Anúncio: 09-09-2025\n\n5 - PROCESSO\nTipo de Procedimento: Concurso público\nPreço base do procedimento: Sim\nValor do preço base do procedimento: 80.000,00 EUR\nProcedimento com lotes? Não\n\n6 - OBJETO DO CONTRATO\nNúmero de referência interna: FM-2025-401 DACP\nDesignação do contrato: CONTRATAÇÃO DE LOCAÇÃO DE STAND PROMOCIONAL DESTINADO À PARTICIPAÇÃO DO MUNICÍPIO DE LOULÉ NA BTL– BOLSA DE TURISMO DE LISBOA 2026\nDescrição: CONTRATAÇÃO DE LOCAÇÃO DE STAND PROMOCIONAL DESTINADO À PARTICIPAÇÃO DO MUNICÍPIO DE LOULÉ NA BTL– BOLSA DE TURISMO DE LISBOA 2026\nTipo de Contrato Principal: Locação de Bens Móveis\nTipo de Contrato: Locação de Bens Móveis\nClassificação CPV (Vocabulário Comum para os Contratos Públicos)\nObjeto principal\nVocabulário Principal: 39154000\nPreço base s/IVA: 80.000,00 EUR\n\n7 - INDICAÇÕES ADICIONAIS\nO contrato envolve aquisição conjunta (satisfação de várias entidades)? Não\nO contrato é adjudicado por uma central de compras? Não\n\n8 - TÉCNICAS\nO concurso destina-se à celebração de um acordo-quadro? Inexistência de acordo-quadro\nÉ utilizado um leilão eletrónico? Não\nÉ adotada uma fase de negociação? Não\nSistema de Aquisição Dinâmico: Inexistência de sistema de aquisição dinâmico\n\n9 - LOCAL DA EXECUÇÃO DO CONTRATO\nLOCAL DA EXECUÇÃO DO CONTRATO (PROCEDIMENTO)\nPaís: Portugal\nNUT III: PT150\nLocalidade: Faro\nDistrito: Faro\nConcelho: Loulé\nFreguesia: Todas\n\n10 - PRAZO DE EXECUÇÃO DO CONTRATO\nPrazo de execução do contrato: 6 MESES\nPrevisão de renovações: Não\n\n11 - FUNDOS EU\nTêm fundos EU? Não\n\n12 - DOCUMENTOS DE HABILITAÇÃO\nHabilitação para o exercício da atividade profissional: Não\n\n13 - CONDIÇÕES DE APRESENTAÇÃO\nPlataforma eletrónica utilizada pela entidade adjudicante: VORTAL\nURL para Apresentação: https://community.vortal.biz/public/\nAdmissibilidade da apresentação de propostas variantes: Não autorizado\nPrazo para apresentação das propostas: 30-09-2025 18:00\nPrazo durante o qual os concorrentes são obrigados a manter as respetivas propostas: 90 dias a contar do termo do prazo para a apresentação das propostas\nIndicação de Subcontratação na Proposta: Inexistência de indicação de subcontratação\n\n14 - PRESTAÇÃO DE CAUÇÃO\nPrestação de caução: Não\n\n15 - FORNECIMENTO DAS PEÇAS DO CONCURSO, APRESENTAÇÃO DE PEDIDOS DE PARTICIPAÇÃO E APRESENTAÇÃO DAS PROPOSTAS\nLink para acesso às peças do concurso (URL): https://community.vortal.biz/Public/public-tender-documents/WDExakc1UXhZaVNpdDBCSzNGd0hqVE9PeDVJRVpiaGFmL1Z0d2xqL2hqVktTeExBU1doNTdOcjVmK3ZoYXpDYnBEVy9RN0FZME5KbzRrQjdGUTZYQ2c9PWk0b19I\n\n20 - OUTROS REQUISITOS\nInformação sobre contratos reservados. Aplica-se a contratos reservados (54º-A)? Não\n\n21 - CRITÉRIO DE ADJUDICAÇÃO\nMultifator: Sim\nFator: \nNome: Preço\nPonderação: 40%\nSubfatores: Não\nFator: \nNome: Qualidade\nPonderação: 60%\nSubfatores: Sim\nSubfatores: \nNome: Características estéticas e layout\nPonderação : 40%; \nNome: Características tecnológicas e inovadoras\nPonderação : 30%; \nNome: Características de funcionalidade\nPonderação : 20%; \nNome: Características de sustentabilidade\nPonderação : 10%; \n\n24 - CONDIÇÕES DO CONTRATO\nFaturação Eletrónica: Permitido\nObrigação de Subcontratação:\nCódigo da Obrigação de Subcontratação: Não é aplicável nenhuma obrigação de subcontratação.\n\n25 - COMPRA PÚBLICA ESTRATÉGICA\nCompra Pública Estratégica: Inexistência de contratação pública estratégica\n\n26 - INFORMAÇÕES ADICIONAIS\nContrato adequado para PME: Sim\nCobertura ACP (Acordo dos Contratos Públicos da Organização Mundial do Comércio): Não\n\n27 - IDENTIFICAÇÃO E CONTACTOS DO ÓRGÃO DE RECURSOS ADMINISTRATIVOS\nDesignação: Câmara Municipal de Loulé\nEndereço: Praça da República\nCódigo postal: 8104-001\nLocalidade: Loulé\nTelefone: +351 289400600\nFax: +351 289415557\nEndereço eletrónico: geral@cm-loule.pt\n\n28 - IDENTIFICAÇÃO DO(S) AUTOR(ES) DE ANÚNCIO\nNome: Vìtor Manuel Gonçalves Aleixo\nCargo: Presidente da Câmara Municipal \n419513924",
    "nipc": "502098139",
    "distrito": "Faro",
    "concelho": "Loulé",
    "freguesia": "Todas",
    "site": "www.cm-loule.pt",
    "email": "aprovisionamento@cm-loule.pt",
    "designacao_contrato": "CONTRATAÇÃO DE LOCAÇÃO DE STAND PROMOCIONAL DESTINADO À PARTICIPAÇÃO DO MUNICÍPIO DE LOULÉ NA BTL– BOLSA DE TURISMO DE LISBOA 2026",
    "descricao": "CONTRATAÇÃO DE LOCAÇÃO DE STAND PROMOCIONAL DESTINADO À PARTICIPAÇÃO DO MUNICÍPIO DE LOULÉ NA BTL– BOLSA DE TURISMO DE LISBOA 2026",
    "preco_base": "80.000,00 EUR",
    "prazo_execucao": "6 MESES",
    "prazo_apresentacao_propostas": "30-09-2025 18:00",
    "fundos_eu": "Não",
    "plataforma_eletronica": "VORTAL",
    "url_procedimento": "https://community.vortal.biz/public/",
    "autor_nome": "Vìtor Manuel Gonçalves Aleixo",
    "autor_cargo": "Presidente da Câmara Municipal"
  },
  {
    "numero_procedimento": "N/A",
    "entidade": "Serviços Municipalizados de Água e Saneamento de Viseu",
    "link": "https://diariodarepublica.pt/dr/detalhe/contrato-publico/23924-934783473",
    "detalhes_completos": "1 - IDENTIFICAÇÃO E CONTACTOS DA ENTIDADE ADJUDICANTE\nDesignação da entidade adjudicante: Serviços Municipalizados de Água e Saneamento de Viseu\nNIPC: 680020063\nServiço/Órgão/Pessoa de contacto: Serviços Municipalizados de Água e Saneamento de Viseu\nEndereço: Rua Conselheiro Afonso de Melo\nCódigo postal: 3510-024\nLocalidade: Viseu\nPaís: Portugal\nNUT III: PT16G\nDistrito: Viseu\nConcelho: Viseu\nFreguesia: Freguesia de Viseu\nTelefone: 232470670\nFax: 232424080\nEndereço da Entidade (URL): www.smasviseu.pt\nEndereço Eletrónico: geral@smasviseu.pt\neDelivery Gateway (URL): https://www.acingov.pt\nFunção da Organização: Adquirente\nNorma jurídica da Entidade Adjudicante: Autoridade local\nÁrea de atividade da Autoridade Adjudicante: Serviços públicos das administrações públicas\n\n2 - JORNAL OFICIAL DA UNIÃO EUROPEIA\nO procedimento a que este anúncio diz respeito também é publicitado no Jornal Oficial da União Europeia? Não\n\n3 - AVISO\nModelo de Anúncio: Concurso público\nData de Envio do Anúncio: 10-09-2025\n\n5 - PROCESSO\nTipo de Procedimento: Concurso público\nPreço base do procedimento: Sim\nValor do preço base do procedimento: 529.897,87 EUR\nProcedimento com lotes? Não\n\n6 - OBJETO DO CONTRATO\nNúmero de referência interna: E1205\nDesignação do contrato: Remodelação das Redes de Água e Esgoto e Rede de Águas Pluviais no Bairro Moinho de Vento em Viseu\nDescrição: Remodelação das Redes de Água e Esgoto e Rede de Águas Pluviais no Bairro Moinho de Vento em Viseu\nTipo de Contrato Principal: Empreitada de Obras Públicas\nTipo de Contrato: Empreitada de Obras Públicas\nClassificação CPV (Vocabulário Comum para os Contratos Públicos)\nObjeto principal\nVocabulário Principal: 45232460\nPreço base s/IVA: 529.897,87 EUR\n\n7 - INDICAÇÕES ADICIONAIS\nO contrato envolve aquisição conjunta (satisfação de várias entidades)? Não\nO contrato é adjudicado por uma central de compras? Não\n\n8 - TÉCNICAS\nO concurso destina-se à celebração de um acordo-quadro? Inexistência de acordo-quadro\nÉ utilizado um leilão eletrónico? Não\nÉ adotada uma fase de negociação? Não\nSistema de Aquisição Dinâmico: Inexistência de sistema de aquisição dinâmico\n\n9 - LOCAL DA EXECUÇÃO DO CONTRATO\nLOCAL DA EXECUÇÃO DO CONTRATO (PROCEDIMENTO)\nPaís: Portugal\nNUT III: PT16G\nLocalidade: Freguesia de Viseu\nDistrito: Viseu\nConcelho: Viseu\nFreguesia: Freguesia de Viseu\n\n10 - PRAZO DE EXECUÇÃO DO CONTRATO\nPrazo de execução do contrato: 340 DIAS\nPrevisão de renovações: Não\n\n11 - FUNDOS EU\nTêm fundos EU? Não\n\n12 - DOCUMENTOS DE HABILITAÇÃO\nHabilitação para o exercício da atividade profissional: Sim\nTipo: Alvará\nDescrição: A 6ª subcategoria da 2ª categoria, sendo que a classe da 6ª subcategoria da 2ª categoria tem de ser de classe que cubra o valor global da proposta e integrar-se na categoria em que o tipo da obra se enquadra.\n\n13 - CONDIÇÕES DE APRESENTAÇÃO\nPlataforma eletrónica utilizada pela entidade adjudicante: ACIN\nURL para Apresentação: https://www.acingov.pt\nAdmissibilidade da apresentação de propostas variantes: Não autorizado\nPrazo para apresentação das propostas: 01-10-2025 23:59\nPrazo durante o qual os concorrentes são obrigados a manter as respetivas propostas: 120 dias a contar do termo do prazo para a apresentação das propostas\nIndicação de Subcontratação na Proposta: Inexistência de indicação de subcontratação\n\n14 - PRESTAÇÃO DE CAUÇÃO\nPrestação de caução: Sim\nPercentagem: 5%\nDescrição da Garantia Exigida: O valor da caução é de 5.00% do preço contratual.\n\n15 - FORNECIMENTO DAS PEÇAS DO CONCURSO, APRESENTAÇÃO DE PEDIDOS DE PARTICIPAÇÃO E APRESENTAÇÃO DAS PROPOSTAS\nLink para acesso às peças do concurso (URL): https://www.acingov.pt/acingovprod/2/zonaPublica/zona_publica_c/donwloadProcedurePiece/OTc1ODE0\n\n20 - OUTROS REQUISITOS\nInformação sobre contratos reservados. Aplica-se a contratos reservados (54º-A)? Não\n\n21 - CRITÉRIO DE ADJUDICAÇÃO\nMultifator: Não\nMonofator:\nNome: Preço\n\n24 - CONDIÇÕES DO CONTRATO\nFaturação Eletrónica: Permitido\nObrigação de Subcontratação:\nCódigo da Obrigação de Subcontratação: Não é aplicável nenhuma obrigação de subcontratação.\n\n25 - COMPRA PÚBLICA ESTRATÉGICA\nCompra Pública Estratégica: Inexistência de contratação pública estratégica\n\n26 - INFORMAÇÕES ADICIONAIS\nContrato adequado para PME: Sim\nCobertura ACP (Acordo dos Contratos Públicos da Organização Mundial do Comércio): Não\n\n27 - IDENTIFICAÇÃO E CONTACTOS DO ÓRGÃO DE RECURSOS ADMINISTRATIVOS\nDesignação: Município de Viseu\nEndereço: Praça da República S/N\nCódigo postal: 3514-501\nLocalidade: Viseu\nTelefone: 00351232427427\nFax: 00351232423112\nEndereço eletrónico: geral@cmviseu.pt\nPrazo de interposição do recurso: 5 dias\n\n28 - IDENTIFICAÇÃO DO(S) AUTOR(ES) DE ANÚNCIO\nNome: João Paulo Lopes Gouveia\nCargo: Vogal do Conselho de Administração\n419509712",
    "nipc": "680020063",
    "distrito": "Viseu",
    "concelho": "Viseu",
    "freguesia": "Freguesia de Viseu",
    "site": "www.smasviseu.pt",
    "email": "geral@smasviseu.pt",
    "designacao_contrato": "Remodelação das Redes de Água e Esgoto e Rede de Águas Pluviais no Bairro Moinho de Vento em Viseu",
    "descricao": "Remodelação das Redes de Água e Esgoto e Rede de Águas Pluviais no Bairro Moinho de Vento em Viseu",
    "preco_base": "529.897,87 EUR",
    "prazo_execucao": "340 DIAS",
    "prazo_apresentacao_propostas": "01-10-2025 23:59",
    "fundos_eu": "Não",
    "plataforma_eletronica": "ACIN",
    "url_procedimento": "https://www.acingov.pt",
    "autor_nome": "João Paulo Lopes Gouveia",
    "autor_cargo": "Vogal do Conselho de Administração"
  },
  {
    "numero_procedimento": "N/A",
    "entidade": "Instituto Português de Oncologia de Lisboa FG, E.P.E.",
    "link": "https://diariodarepublica.pt/dr/detalhe/contrato-publico/23926-934783474",
    "detalhes_completos": "1 - IDENTIFICAÇÃO E CONTACTOS DA ENTIDADE ADJUDICANTE\nDesignação da entidade adjudicante: Instituto Português de Oncologia de Lisboa FG, E.P.E.\nNIPC: 506361616\nEndereço: Rua Profº Lima Basto\nCódigo postal: 1099-023\nLocalidade: Lisboa\nPaís: Portugal\nNUT III: PT170\nDistrito: Lisboa\nConcelho: Lisboa\nFreguesia: Todas\nTelefone: 217229800\nFax: 217229880\nEndereço da Entidade (URL): www.ipolisboa.min-saude.pt/\nEndereço Eletrónico: ipofg@ipolisboa.min-saude.pt\neDelivery Gateway (URL): https://community.vortal.biz/public/\nFunção da Organização: Adquirente\nNorma jurídica da Entidade Adjudicante: Organismo de direito público\nÁrea de atividade da Autoridade Adjudicante: Saúde\n\n2 - JORNAL OFICIAL DA UNIÃO EUROPEIA\nO procedimento a que este anúncio diz respeito também é publicitado no Jornal Oficial da União Europeia? Não\n\n3 - AVISO\nModelo de Anúncio: Concurso público\nData de Envio do Anúncio: 10-09-2025\n\n5 - PROCESSO\nTipo de Procedimento: Concurso público\nPreço base do procedimento: Sim\nValor do preço base do procedimento: 50.000,00 EUR\nProcedimento com lotes? Não\n\n6 - OBJETO DO CONTRATO\nNúmero de referência interna: PN/2595/2025\nDesignação do contrato: Aquisição de Torre completa de videolaringoscopia \nDescrição: Aquisição de Torre completa de videolaringoscopia \nTipo de Contrato Principal: Aquisição de Bens Móveis\nTipo de Contrato: Aquisição de Bens Móveis\nClassificação CPV (Vocabulário Comum para os Contratos Públicos)\nObjeto principal\nVocabulário Principal: 33100000\nPreço base s/IVA: 50.000,00 EUR\n\n7 - INDICAÇÕES ADICIONAIS\nO contrato envolve aquisição conjunta (satisfação de várias entidades)? Não\nO contrato é adjudicado por uma central de compras? Não\n\n8 - TÉCNICAS\nO concurso destina-se à celebração de um acordo-quadro? Inexistência de acordo-quadro\nÉ utilizado um leilão eletrónico? Não\nÉ adotada uma fase de negociação? Não\nSistema de Aquisição Dinâmico: Inexistência de sistema de aquisição dinâmico\n\n9 - LOCAL DA EXECUÇÃO DO CONTRATO\nLOCAL DA EXECUÇÃO DO CONTRATO (PROCEDIMENTO)\nPaís: Portugal\nNUT III: PT170\nLocalidade: Lisboa\nDistrito: Lisboa\nConcelho: Lisboa\nFreguesia: Freguesia de São Domingos de Benfica\n\n10 - PRAZO DE EXECUÇÃO DO CONTRATO\nPrazo de execução do contrato: 30 DIAS\nPrevisão de renovações: Não\n\n11 - FUNDOS EU\nTêm fundos EU? Sim\n\n12 - DOCUMENTOS DE HABILITAÇÃO\nHabilitação para o exercício da atividade profissional: Não\n\n13 - CONDIÇÕES DE APRESENTAÇÃO\nPlataforma eletrónica utilizada pela entidade adjudicante: VORTAL\nURL para Apresentação: https://community.vortal.biz/public/\nAdmissibilidade da apresentação de propostas variantes: Não autorizado\nPrazo para apresentação das propostas: 19-09-2025 17:59\nPrazo durante o qual os concorrentes são obrigados a manter as respetivas propostas: 90 dias a contar do termo do prazo para a apresentação das propostas\nIndicação de Subcontratação na Proposta: Inexistência de indicação de subcontratação\n\n14 - PRESTAÇÃO DE CAUÇÃO\nPrestação de caução: Não\n\n15 - FORNECIMENTO DAS PEÇAS DO CONCURSO, APRESENTAÇÃO DE PEDIDOS DE PARTICIPAÇÃO E APRESENTAÇÃO DAS PROPOSTAS\nLink para acesso às peças do concurso (URL): https://community.vortal.biz/Public/public-tender-documents/U2c5aGtkSkVEWmNjUUo4UFFCOHhxNWtJUm9VNmcxM2QzNXZRbjlRa2FFY3dpb1UzZnk0d2VTZnVLSkhCYUxlU01MeDJ5dWZlNFFXRDJwOUJZSW14cHc9PV9LWkp0\n\n20 - OUTROS REQUISITOS\nInformação sobre contratos reservados. Aplica-se a contratos reservados (54º-A)? Não\n\n21 - CRITÉRIO DE ADJUDICAÇÃO\nMultifator: Não\nMonofator:\nNome: Preço\n\n24 - CONDIÇÕES DO CONTRATO\nFaturação Eletrónica: Permitido\nObrigação de Subcontratação:\nCódigo da Obrigação de Subcontratação: Não é aplicável nenhuma obrigação de subcontratação.\n\n25 - COMPRA PÚBLICA ESTRATÉGICA\nCompra Pública Estratégica: Inexistência de contratação pública estratégica\n\n26 - INFORMAÇÕES ADICIONAIS\nContrato adequado para PME: Sim\nCobertura ACP (Acordo dos Contratos Públicos da Organização Mundial do Comércio): Não\n\n27 - IDENTIFICAÇÃO E CONTACTOS DO ÓRGÃO DE RECURSOS ADMINISTRATIVOS\nDesignação: Conselho de Administração\nEndereço: Rua Profesor Lima Basto\nCódigo postal: 1099-023\nLocalidade: Lisboa\nTelefone: +351 217229800\nFax: +351 217229880\nEndereço eletrónico: ipofg@ipolisboa.min-saude.pt\n\n28 - IDENTIFICAÇÃO DO(S) AUTOR(ES) DE ANÚNCIO\nNome: Ricardo Costa\nCargo: Técnico Superior\n419518014",
    "nipc": "506361616",
    "distrito": "Lisboa",
    "concelho": "Lisboa",
    "freguesia": "Todas",
    "site": "www.ipolisboa.min-saude.pt/",
    "email": "ipofg@ipolisboa.min-saude.pt",
    "designacao_contrato": "Aquisição de Torre completa de videolaringoscopia",
    "descricao": "Aquisição de Torre completa de videolaringoscopia",
    "preco_base": "50.000,00 EUR",
    "prazo_execucao": "30 DIAS",
    "prazo_apresentacao_propostas": "19-09-2025 17:59",
    "fundos_eu": "Sim",
    "plataforma_eletronica": "VORTAL",
    "url_procedimento": "https://community.vortal.biz/public/",
    "autor_nome": "Ricardo Costa",
    "autor_cargo": "Técnico Superior"
  },
  {
    "numero_procedimento": "N/A",
    "entidade": "Serviços Municipalizados de Água e Saneamento de Viseu",
    "link": "https://diariodarepublica.pt/dr/detalhe/contrato-publico/23925-934784778",
    "detalhes_completos": "1 - IDENTIFICAÇÃO E CONTACTOS DA ENTIDADE ADJUDICANTE\nDesignação da entidade adjudicante: Serviços Municipalizados de Água e Saneamento de Viseu\nNIPC: 680020063\nEndereço: Rua Conselheiro Afonso de Melo\nCódigo postal: 3510-024\nLocalidade: Viseu\nPaís: Portugal\nNUT III: PT16G\nDistrito: Viseu\nConcelho: Viseu\nFreguesia: Freguesia de Viseu\nTelefone: 232470670\nFax: 232424080\nEndereço da Entidade (URL): www.smasviseu.pt\nEndereço Eletrónico: geral@smasviseu.pt\neDelivery Gateway (URL): https://www.acingov.pt\nFunção da Organização: Adquirente\nNorma jurídica da Entidade Adjudicante: Autoridade local\nÁrea de atividade da Autoridade Adjudicante: Serviços públicos das administrações públicas\n\n2 - JORNAL OFICIAL DA UNIÃO EUROPEIA\nO procedimento a que este anúncio diz respeito também é publicitado no Jornal Oficial da União Europeia? Não\n\n3 - AVISO\nModelo de Anúncio: Concurso público\nData de Envio do Anúncio: 10-09-2025\n\n5 - PROCESSO\nTipo de Procedimento: Concurso público\nPreço base do procedimento: Sim\nValor do preço base do procedimento: 17.000,00 EUR\nProcedimento com lotes? Não\n\n6 - OBJETO DO CONTRATO\nNúmero de referência interna: ABS2025-075\nDesignação do contrato: Aquisição de Ácido Cítrico Monohidratado para a ETAR Viseu Sul - 2025\nDescrição: Aquisição de Ácido Cítrico Monohidratado para a ETAR Viseu Sul - 2025\nTipo de Contrato Principal: Aquisição de Bens Móveis\nTipo de Contrato: Aquisição de Bens Móveis\nClassificação CPV (Vocabulário Comum para os Contratos Públicos)\nObjeto principal\nVocabulário Principal: 24323200\nPreço base s/IVA: 17.000,00 EUR\n\n7 - INDICAÇÕES ADICIONAIS\nO contrato envolve aquisição conjunta (satisfação de várias entidades)? Não\nO contrato é adjudicado por uma central de compras? Não\n\n8 - TÉCNICAS\nO concurso destina-se à celebração de um acordo-quadro? Inexistência de acordo-quadro\nÉ utilizado um leilão eletrónico? Não\nÉ adotada uma fase de negociação? Não\nSistema de Aquisição Dinâmico: Inexistência de sistema de aquisição dinâmico\n\n9 - LOCAL DA EXECUÇÃO DO CONTRATO\nLOCAL DA EXECUÇÃO DO CONTRATO (PROCEDIMENTO)\nPaís: Portugal\nNUT III: PT16G\nLocalidade: União das Freguesias de Faíl e Vila Chã de Sá\nDistrito: Viseu\nConcelho: Viseu\nFreguesia: União das Freguesias de Faíl e Vila Chã de Sá\n\n10 - PRAZO DE EXECUÇÃO DO CONTRATO\nPrazo de execução do contrato: 365 DIAS\nPrevisão de renovações: Não\n\n11 - FUNDOS EU\nTêm fundos EU? Não\n\n12 - DOCUMENTOS DE HABILITAÇÃO\nHabilitação para o exercício da atividade profissional: Não\n\n13 - CONDIÇÕES DE APRESENTAÇÃO\nPlataforma eletrónica utilizada pela entidade adjudicante: ACIN\nURL para Apresentação: https://www.acingov.pt\nAdmissibilidade da apresentação de propostas variantes: Não autorizado\nPrazo para apresentação das propostas: 25-09-2025 23:59\nPrazo durante o qual os concorrentes são obrigados a manter as respetivas propostas: 66 dias a contar do termo do prazo para a apresentação das propostas\nIndicação de Subcontratação na Proposta: Inexistência de indicação de subcontratação\n\n14 - PRESTAÇÃO DE CAUÇÃO\nPrestação de caução: Não\n\n15 - FORNECIMENTO DAS PEÇAS DO CONCURSO, APRESENTAÇÃO DE PEDIDOS DE PARTICIPAÇÃO E APRESENTAÇÃO DAS PROPOSTAS\nLink para acesso às peças do concurso (URL): https://www.acingov.pt/acingovprod/2/zonaPublica/zona_publica_c/donwloadProcedurePiece/OTc1ODY5\n\n20 - OUTROS REQUISITOS\nInformação sobre contratos reservados. Aplica-se a contratos reservados (54º-A)? Não\n\n21 - CRITÉRIO DE ADJUDICAÇÃO\nMultifator: Não\nMonofator:\nNome: Preço\n\n24 - CONDIÇÕES DO CONTRATO\nFaturação Eletrónica: Permitido\nObrigação de Subcontratação:\nCódigo da Obrigação de Subcontratação: Não é aplicável nenhuma obrigação de subcontratação.\n\n25 - COMPRA PÚBLICA ESTRATÉGICA\nCompra Pública Estratégica: Inexistência de contratação pública estratégica\n\n26 - INFORMAÇÕES ADICIONAIS\nContrato adequado para PME: Sim\nCobertura ACP (Acordo dos Contratos Públicos da Organização Mundial do Comércio): Não\n\n27 - IDENTIFICAÇÃO E CONTACTOS DO ÓRGÃO DE RECURSOS ADMINISTRATIVOS\nDesignação: Serviços Municipalizados de Viseu\nEndereço: Rua Conselheiro Afonso de Melo\nCódigo postal: 3510-024\nLocalidade: Viseu\nTelefone: 00351232470670\nFax: 00351232424080\nEndereço eletrónico: geral@smasviseu.pt\nPrazo de interposição do recurso: 5 dias\n\n28 - IDENTIFICAÇÃO DO(S) AUTOR(ES) DE ANÚNCIO\nNome: João Paulo Lopes Gouveia\nCargo: Vogal do Conselho de Administração\n419509923",
    "nipc": "680020063",
    "distrito": "Viseu",
    "concelho": "Viseu",
    "freguesia": "Freguesia de Viseu",
    "site": "www.smasviseu.pt",
    "email": "geral@smasviseu.pt",
    "designacao_contrato": "Aquisição de Ácido Cítrico Monohidratado para a ETAR Viseu Sul - 2025",
    "descricao": "Aquisição de Ácido Cítrico Monohidratado para a ETAR Viseu Sul - 2025",
    "preco_base": "17.000,00 EUR",
    "prazo_execucao": "365 DIAS",
    "prazo_apresentacao_propostas": "25-09-2025 23:59",
    "fundos_eu": "Não",
    "plataforma_eletronica": "ACIN",
    "url_procedimento": "https://www.acingov.pt",
    "autor_nome": "João Paulo Lopes Gouveia",
    "autor_cargo": "Vogal do Conselho de Administração"
  },
  {
    "numero_procedimento": "N/A",
    "entidade": "Universidade de Évora",
    "link": "https://diariodarepublica.pt/dr/detalhe/contrato-publico/23927-934784779",
    "detalhes_completos": "1 - IDENTIFICAÇÃO E CONTACTOS DA ENTIDADE ADJUDICANTE\nDesignação da entidade adjudicante: Universidade de Évora\nNIPC: 501201920\nServiço/Órgão/Pessoa de contacto: Sra. Reitora\nEndereço: Largo Sra. da Natividade, Antiga Cadeia\nCódigo postal: 7000-810\nLocalidade: Évora\nPaís: Portugal\nNUT III: PT187\nDistrito: Évora\nConcelho: Évora\nFreguesia: Todas\nTelefone: 266740800\nFax: 266760970\nEndereço da Entidade (URL): www.uevora.pt\nEndereço Eletrónico: compras@uevora.pt\neDelivery Gateway (URL): https://www.acingov.pt\nFunção da Organização: Adquirente\nNorma jurídica da Entidade Adjudicante: Organismo de direito público\nÁrea de atividade da Autoridade Adjudicante: Serviços públicos das administrações públicas\n\n2 - JORNAL OFICIAL DA UNIÃO EUROPEIA\nO procedimento a que este anúncio diz respeito também é publicitado no Jornal Oficial da União Europeia? Não\n\n3 - AVISO\nModelo de Anúncio: Concurso público\nData de Envio do Anúncio: 10-09-2025\n\n5 - PROCESSO\nTipo de Procedimento: Concurso público\nPreço base do procedimento: Sim\nValor do preço base do procedimento: 1.250.000,00 EUR\nProcedimento com lotes? Não\n\n6 - OBJETO DO CONTRATO\nNúmero de referência interna: 102/DCP-GCE/UE/2025\nDesignação do contrato: Procedimento n.º 102/DCP-GCE/UE/2025\nDescrição: Obra de Melhoria de Eficiência Energética do Colégio Luís António Verney \nTipo de Contrato Principal: Empreitada de Obras Públicas\nTipo de Contrato: Empreitada de Obras Públicas\nClassificação CPV (Vocabulário Comum para os Contratos Públicos)\nObjeto principal\nVocabulário Principal: 45453000\nPreço base s/IVA: 1.250.000,00 EUR\n\n7 - INDICAÇÕES ADICIONAIS\nO contrato envolve aquisição conjunta (satisfação de várias entidades)? Não\nO contrato é adjudicado por uma central de compras? Não\n\n8 - TÉCNICAS\nO concurso destina-se à celebração de um acordo-quadro? Inexistência de acordo-quadro\nÉ utilizado um leilão eletrónico? Não\nÉ adotada uma fase de negociação? Não\nSistema de Aquisição Dinâmico: Inexistência de sistema de aquisição dinâmico\n\n9 - LOCAL DA EXECUÇÃO DO CONTRATO\nLOCAL DA EXECUÇÃO DO CONTRATO (PROCEDIMENTO)\nPaís: Portugal\nNUT III: PT187\nLocalidade: Évora\nDistrito: Évora\nConcelho: Évora\nFreguesia: Todas\n\n10 - PRAZO DE EXECUÇÃO DO CONTRATO\nPrazo de execução do contrato: 270 DIAS\nPrevisão de renovações: Não\n\n11 - FUNDOS EU\nTêm fundos EU? Sim\n\n12 - DOCUMENTOS DE HABILITAÇÃO\nHabilitação para o exercício da atividade profissional: Não\n\n13 - CONDIÇÕES DE APRESENTAÇÃO\nPlataforma eletrónica utilizada pela entidade adjudicante: ACIN\nURL para Apresentação: https://www.acingov.pt\nAdmissibilidade da apresentação de propostas variantes: Não autorizado\nPrazo para apresentação das propostas: 10-10-2025 23:59\nPrazo durante o qual os concorrentes são obrigados a manter as respetivas propostas: 90 dias a contar do termo do prazo para a apresentação das propostas\nIndicação de Subcontratação na Proposta: Inexistência de indicação de subcontratação\n\n14 - PRESTAÇÃO DE CAUÇÃO\nPrestação de caução: Sim\nPercentagem: 5%\nDescrição da Garantia Exigida: O valor da caução é de 5.00% do preço contratual.\n\n15 - FORNECIMENTO DAS PEÇAS DO CONCURSO, APRESENTAÇÃO DE PEDIDOS DE PARTICIPAÇÃO E APRESENTAÇÃO DAS PROPOSTAS\nLink para acesso às peças do concurso (URL): https://www.acingov.pt/acingovprod/2/zonaPublica/zona_publica_c/donwloadProcedurePiece/OTc0ODI5\n\n20 - OUTROS REQUISITOS\nInformação sobre contratos reservados. Aplica-se a contratos reservados (54º-A)? Não\n\n21 - CRITÉRIO DE ADJUDICAÇÃO\nMultifator: Não\nMonofator:\nNome: Outros\nOutro nome: Fator Preço\n\n24 - CONDIÇÕES DO CONTRATO\nFaturação Eletrónica: Permitido\nObrigação de Subcontratação:\nCódigo da Obrigação de Subcontratação: Não é aplicável nenhuma obrigação de subcontratação.\n\n25 - COMPRA PÚBLICA ESTRATÉGICA\nCompra Pública Estratégica: Inexistência de contratação pública estratégica\n\n26 - INFORMAÇÕES ADICIONAIS\nContrato adequado para PME: Sim\nCobertura ACP (Acordo dos Contratos Públicos da Organização Mundial do Comércio): Não\n\n27 - IDENTIFICAÇÃO E CONTACTOS DO ÓRGÃO DE RECURSOS ADMINISTRATIVOS\nDesignação: Sra. Reitora\nEndereço: Largo Sra. da Natividade, Antiga Cadeia\nCódigo postal: 7000-810\nLocalidade: Évora\nTelefone: 266740800\nFax: 266760970\nEndereço eletrónico: compras@uevora.pt\nPrazo de interposição do recurso: 10 dias\n\n28 - IDENTIFICAÇÃO DO(S) AUTOR(ES) DE ANÚNCIO\nNome: Maria da Graça Fusco Talhinhas\nCargo: Assistente Técnico\n419518152",
    "nipc": "501201920",
    "distrito": "Évora",
    "concelho": "Évora",
    "freguesia": "Todas",
    "site": "www.uevora.pt",
    "email": "compras@uevora.pt",
    "designacao_contrato": "Procedimento n.º 102/DCP-GCE/UE/2025",
    "descricao": "Obra de Melhoria de Eficiência Energética do Colégio Luís António Verney",
    "preco_base": "1.250.000,00 EUR",
    "prazo_execucao": "270 DIAS",
    "prazo_apresentacao_propostas": "10-10-2025 23:59",
    "fundos_eu": "Sim",
    "plataforma_eletronica": "ACIN",
    "url_procedimento": "https://www.acingov.pt",
    "autor_nome": "Maria da Graça Fusco Talhinhas",
    "autor_cargo": "Assistente Técnico"
  }
]