[
  {
    "numero_procedimento": "N/A",
    "entidade": "AnÃºncio de procedimento  n.Âº 21496/2025  -  DiÃ¡rio da RepÃºblica n.Âº 153/2025, SÃ©rie II de 2025-08-11",
    "link": "https://diariodarepublica.pt/dr/detalhe/contrato-publico/21496-928332650"
  },
  {
    "numero_procedimento": "N/A",
    "entidade": "AnÃºncio de procedimento  n.Âº 21497/2025  -  DiÃ¡rio da RepÃºblica n.Âº 153/2025, SÃ©rie II de 2025-08-11",
    "link": "https://diariodarepublica.pt/dr/detalhe/contrato-publico/21497-928332651"
  },
  {
    "numero_procedimento": "N/A",
    "entidade": "AnÃºncio de procedimento  n.Âº 21499/2025  -  DiÃ¡rio da RepÃºblica n.Âº 153/2025, SÃ©rie II de 2025-08-11",
    "link": "https://diariodarepublica.pt/dr/detalhe/contrato-publico/21499-928332652"
  },
  {
    "numero_procedimento": "N/A",
    "entidade": "AnÃºncio de procedimento  n.Âº 21501/2025  -  DiÃ¡rio da RepÃºblica n.Âº 153/2025, SÃ©rie II de 2025-08-11",
    "link": "https://diariodarepublica.pt/dr/detalhe/contrato-publico/21501-928332656"
  },
  {
    "numero_procedimento": "N/A",
    "entidade": "AnÃºncio de procedimento  n.Âº 21503/2025  -  DiÃ¡rio da RepÃºblica n.Âº 153/2025, SÃ©rie II de 2025-08-11",
    "link": "https://diariodarepublica.pt/dr/detalhe/contrato-publico/21503-928332657"
  },
  {
    "numero_procedimento": "N/A",
    "entidade": "AnÃºncio de procedimento  n.Âº 21504/2025  -  DiÃ¡rio da RepÃºblica n.Âº 153/2025, SÃ©rie II de 2025-08-11",
    "link": "https://diariodarepublica.pt/dr/detalhe/contrato-publico/21504-928332658"
  },
  {
    "numero_procedimento": "N/A",
    "entidade": "AnÃºncio de procedimento  n.Âº 21508/2025  -  DiÃ¡rio da RepÃºblica n.Âº 153/2025, SÃ©rie II de 2025-08-11",
    "link": "https://diariodarepublica.pt/dr/detalhe/contrato-publico/21508-928332659"
  },
  {
    "numero_procedimento": "N/A",
    "entidade": "AnÃºncio de procedimento  n.Âº 21509/2025  -  DiÃ¡rio da RepÃºblica n.Âº 153/2025, SÃ©rie II de 2025-08-11",
    "link": "https://diariodarepublica.pt/dr/detalhe/contrato-publico/21509-928332660"
  },
  {
    "numero_procedimento": "N/A",
    "entidade": "AnÃºncio de procedimento  n.Âº 21492/2025  -  DiÃ¡rio da RepÃºblica n.Âº 153/2025, SÃ©rie II de 2025-08-11",
    "link": "https://diariodarepublica.pt/dr/detalhe/contrato-publico/21492-928460664"
  },
  {
    "numero_procedimento": "N/A",
    "entidade": "AnÃºncio de procedimento  n.Âº 21493/2025  -  DiÃ¡rio da RepÃºblica n.Âº 153/2025, SÃ©rie II de 2025-08-11",
    "link": "https://diariodarepublica.pt/dr/detalhe/contrato-publico/21493-928460665"
  },
  {
    "numero_procedimento": "N/A",
    "entidade": "AnÃºncio de procedimento  n.Âº 21494/2025  -  DiÃ¡rio da RepÃºblica n.Âº 153/2025, SÃ©rie II de 2025-08-11",
    "link": "https://diariodarepublica.pt/dr/detalhe/contrato-publico/21494-928460666"
  },
  {
    "numero_procedimento": "N/A",
    "entidade": "AnÃºncio de procedimento  n.Âº 21495/2025  -  DiÃ¡rio da RepÃºblica n.Âº 153/2025, SÃ©rie II de 2025-08-11",
    "link": "https://diariodarepublica.pt/dr/detalhe/contrato-publico/21495-928460667"
  },
  {
    "numero_procedimento": "N/A",
    "entidade": "AnÃºncio de procedimento  n.Âº 21498/2025  -  DiÃ¡rio da RepÃºblica n.Âº 153/2025, SÃ©rie II de 2025-08-11",
    "link": "https://diariodarepublica.pt/dr/detalhe/contrato-publico/21498-928478138"
  },
  {
    "numero_procedimento": "N/A",
    "entidade": "AnÃºncio de procedimento  n.Âº 21500/2025  -  DiÃ¡rio da RepÃºblica n.Âº 153/2025, SÃ©rie II de 2025-08-11",
    "link": "https://diariodarepublica.pt/dr/detalhe/contrato-publico/21500-928478139"
  },
  {
    "numero_procedimento": "N/A",
    "entidade": "AnÃºncio de procedimento  n.Âº 21502/2025  -  DiÃ¡rio da RepÃºblica n.Âº 153/2025, SÃ©rie II de 2025-08-11",
    "link": "https://diariodarepublica.pt/dr/detalhe/contrato-publico/21502-928478140"
  },
  {
    "numero_procedimento": "N/A",
    "entidade": "AnÃºncio de procedimento  n.Âº 21505/2025  -  DiÃ¡rio da RepÃºblica n.Âº 153/2025, SÃ©rie II de 2025-08-11",
    "link": "https://diariodarepublica.pt/dr/detalhe/contrato-publico/21505-928478141"
  },
  {
    "numero_procedimento": "N/A",
    "entidade": "AnÃºncio de procedimento  n.Âº 21506/2025  -  DiÃ¡rio da RepÃºblica n.Âº 153/2025, SÃ©rie II de 2025-08-11",
    "link": "https://diariodarepublica.pt/dr/detalhe/contrato-publico/21506-928478142"
  },
  {
    "numero_procedimento": "N/A",
    "entidade": "AnÃºncio de procedimento  n.Âº 21507/2025  -  DiÃ¡rio da RepÃºblica n.Âº 153/2025, SÃ©rie II de 2025-08-11",
    "link": "https://diariodarepublica.pt/dr/detalhe/contrato-publico/21507-928478143"
  },
  {
    "numero_procedimento": "N/A",
    "entidade": "AnÃºncio de procedimento  n.Âº 21510/2025  -  DiÃ¡rio da RepÃºblica n.Âº 153/2025, SÃ©rie II de 2025-08-11",
    "link": "https://diariodarepublica.pt/dr/detalhe/contrato-publico/21510-928478145"
  },
  {
    "numero_procedimento": "N/A",
    "entidade": "AnÃºncio de procedimento  n.Âº 21511/2025  -  DiÃ¡rio da RepÃºblica n.Âº 153/2025, SÃ©rie II de 2025-08-11",
    "link": "https://diariodarepublica.pt/dr/detalhe/contrato-publico/21511-928478146"
  },
  {
    "numero_procedimento": "N/A",
    "entidade": "AnÃºncio de procedimento  n.Âº 21514/2025  -  DiÃ¡rio da RepÃºblica n.Âº 153/2025, SÃ©rie II de 2025-08-11",
    "link": "https://diariodarepublica.pt/dr/detalhe/contrato-publico/21514-928478150"
  },
  {
    "numero_procedimento": "N/A",
    "entidade": "AnÃºncio de procedimento  n.Âº 21515/2025  -  DiÃ¡rio da RepÃºblica n.Âº 153/2025, SÃ©rie II de 2025-08-11",
    "link": "https://diariodarepublica.pt/dr/detalhe/contrato-publico/21515-928478151"
  },
  {
    "numero_procedimento": "N/A",
    "entidade": "AnÃºncio de procedimento  n.Âº 21518/2025  -  DiÃ¡rio da RepÃºblica n.Âº 153/2025, SÃ©rie II de 2025-08-11",
    "link": "https://diariodarepublica.pt/dr/detalhe/contrato-publico/21518-928478152"
  },
  {
    "numero_procedimento": "N/A",
    "entidade": "AnÃºncio de procedimento  n.Âº 21520/2025  -  DiÃ¡rio da RepÃºblica n.Âº 153/2025, SÃ©rie II de 2025-08-11",
    "link": "https://diariodarepublica.pt/dr/detalhe/contrato-publico/21520-928478153"
  },
  {
    "numero_procedimento": "N/A",
    "entidade": "AnÃºncio de procedimento  n.Âº 21522/2025  -  DiÃ¡rio da RepÃºblica n.Âº 153/2025, SÃ©rie II de 2025-08-11",
    "link": "https://diariodarepublica.pt/dr/detalhe/contrato-publico/21522-928478154"
  },
  {
    "numero_procedimento": "N/A",
    "entidade": "AnÃºncio de procedimento  n.Âº 21524/2025  -  DiÃ¡rio da RepÃºblica n.Âº 153/2025, SÃ©rie II de 2025-08-11",
    "link": "https://diariodarepublica.pt/dr/detalhe/contrato-publico/21524-928478155"
  },
  {
    "numero_procedimento": "N/A",
    "entidade": "AnÃºncio de procedimento  n.Âº 21525/2025  -  DiÃ¡rio da RepÃºblica n.Âº 153/2025, SÃ©rie II de 2025-08-11",
    "link": "https://diariodarepublica.pt/dr/detalhe/contrato-publico/21525-928478156"
  },
  {
    "numero_procedimento": "N/A",
    "entidade": "AnÃºncio de procedimento  n.Âº 21527/2025  -  DiÃ¡rio da RepÃºblica n.Âº 153/2025, SÃ©rie II de 2025-08-11",
    "link": "https://diariodarepublica.pt/dr/detalhe/contrato-publico/21527-928478157"
  },
  {
    "numero_procedimento": "N/A",
    "entidade": "AnÃºncio de procedimento  n.Âº 21528/2025  -  DiÃ¡rio da RepÃºblica n.Âº 153/2025, SÃ©rie II de 2025-08-11",
    "link": "https://diariodarepublica.pt/dr/detalhe/contrato-publico/21528-928478158"
  },
  {
    "numero_procedimento": "N/A",
    "entidade": "AnÃºncio de procedimento  n.Âº 21530/2025  -  DiÃ¡rio da RepÃºblica n.Âº 153/2025, SÃ©rie II de 2025-08-11",
    "link": "https://diariodarepublica.pt/dr/detalhe/contrato-publico/21530-928478159"
  },
  {
    "numero_procedimento": "N/A",
    "entidade": "AnÃºncio de procedimento  n.Âº 21531/2025  -  DiÃ¡rio da RepÃºblica n.Âº 153/2025, SÃ©rie II de 2025-08-11",
    "link": "https://diariodarepublica.pt/dr/detalhe/contrato-publico/21531-928478160"
  },
  {
    "numero_procedimento": "N/A",
    "entidade": "AnÃºncio de procedimento  n.Âº 21533/2025  -  DiÃ¡rio da RepÃºblica n.Âº 153/2025, SÃ©rie II de 2025-08-11",
    "link": "https://diariodarepublica.pt/dr/detalhe/contrato-publico/21533-928478161"
  },
  {
    "numero_procedimento": "N/A",
    "entidade": "AnÃºncio de procedimento  n.Âº 21535/2025  -  DiÃ¡rio da RepÃºblica n.Âº 153/2025, SÃ©rie II de 2025-08-11",
    "link": "https://diariodarepublica.pt/dr/detalhe/contrato-publico/21535-928478162"
  },
  {
    "numero_procedimento": "N/A",
    "entidade": "Agrupamento de Escolas de Barcelos",
    "link": "https://diariodarepublica.pt/dr/detalhe/contrato-publico/21536-928478163",
    "detalhes_completos": "1 - IDENTIFICAÇÃO E CONTACTOS DA ENTIDADE ADJUDICANTE\nDesignação da entidade adjudicante: Agrupamento de Escolas de Barcelos\nNIPC: 600085198\nEndereço: Avenida João Paulo II-Apart. 166\nCódigo postal: 4750-304\nLocalidade: Braga\nPaís: Portugal\nNUT III: PT112\nDistrito: Braga\nConcelho: Barcelos\nFreguesia: Todas\nTelefone: 253809360\nFax: 253809368\nEndereço da Entidade (URL): https://aebarcelos.pt/\nEndereço Eletrónico: esb3.barcelos@escolas.min-edu.pt\neDelivery Gateway (URL): https://community.vortal.biz/public/\nFunção da Organização: Adquirente\nNorma jurídica da Entidade Adjudicante: Organismo de direito público\nÁrea de atividade da Autoridade Adjudicante: Educação\n\n2 - JORNAL OFICIAL DA UNIÃO EUROPEIA\nO procedimento a que este anúncio diz respeito também é publicitado no Jornal Oficial da União Europeia? Sim\n\n3 - AVISO\nModelo de Anúncio: Concurso público\nData de Envio do Anúncio: 07-08-2025\n\n5 - PROCESSO\nTipo de Procedimento: Concurso público\nPreço base do procedimento: Sim\nValor do preço base do procedimento: 802.946,14 EUR\nProcedimento com lotes? Sim\nNº Máx. de Lotes Autorizado: 5\nNúmero máximo de lotes que podem ser adjudicados a um concorrente: 5\n\n6 - OBJETO DO CONTRATO\nNúmero de referência interna: CPI 03/2025\nDesignação do contrato: Aquisição de equipamento para equipar o Centro Tecnológico Especializado - Informática, por lotes\nDescrição: Aquisição de equipamento para equipar o Centro Tecnológico Especializado - Informática, por lotes\nOpções: Não\nTipo de Contrato Principal: Aquisição de Bens Móveis\nTipo de Contrato: Aquisição de Bens Móveis\nClassificação CPV (Vocabulário Comum para os Contratos Públicos)\nObjeto principal\nVocabulário Principal: 30200000\nPreço base s/IVA: 802.946,14 EUR\nLotes: \nNº: LOT-0001\nDescrição do Lote: Lote 1\nPreço base s/IVA: 322.067,86 EUR\nClassificação CPV (Vocabulário Comum para os Contratos Públicos)\nObjeto principal\nVocabulário Principal: 30200000\nNº: LOT-0002\nDescrição do Lote: Lote 2\nPreço base s/IVA: 41.999,20 EUR\nClassificação CPV (Vocabulário Comum para os Contratos Públicos)\nObjeto principal\nVocabulário Principal: 30200000\nNº: LOT-0003\nDescrição do Lote: Lote 3\nPreço base s/IVA: 177.027,70 EUR\nClassificação CPV (Vocabulário Comum para os Contratos Públicos)\nObjeto principal\nVocabulário Principal: 30200000\nNº: LOT-0004\nDescrição do Lote: Lote 4\nPreço base s/IVA: 16.077,20 EUR\nClassificação CPV (Vocabulário Comum para os Contratos Públicos)\nObjeto principal\nVocabulário Principal: 30200000\nNº: LOT-0005\nDescrição do Lote: Lote 5\nPreço base s/IVA: 245.774,18 EUR\nClassificação CPV (Vocabulário Comum para os Contratos Públicos)\nObjeto principal\nVocabulário Principal: 30200000\n\n7 - INDICAÇÕES ADICIONAIS\nO contrato envolve aquisição conjunta (satisfação de várias entidades)? Não\nO contrato é adjudicado por uma central de compras? Não\n\n8 - TÉCNICAS\nO concurso destina-se à celebração de um acordo-quadro? Inexistência de acordo-quadro\nÉ utilizado um leilão eletrónico? Não\nÉ adotada uma fase de negociação? Não\nSistema de Aquisição Dinâmico: Inexistência de sistema de aquisição dinâmico\n\n9 - LOCAL DA EXECUÇÃO DO CONTRATO\nLOCAL DA EXECUÇÃO DO CONTRATO (PROCEDIMENTO)\nPaís: Portugal\nNUT III: PT112\nLocalidade: Braga\nDistrito: Braga\nConcelho: Barcelos\nFreguesia: Todas\nLOCAL DA EXECUÇÃO DO CONTRATO (LOTE)\nIdentificador do Lote: LOT-0001; LOT-0002; LOT-0003; LOT-0004; LOT-0005\nPaís: Portugal\nNUT III: PT112\nLocalidade: Braga\nDistrito: Braga\nConcelho: Barcelos\nFreguesia: Todas\n\n10 - PRAZO DE EXECUÇÃO DO CONTRATO\nIdentificador do Lote: LOT-0001; LOT-0002; LOT-0003; LOT-0004; LOT-0005\nPrazo de execução do contrato: 60 DIAS\nPrevisão de renovações: Não\n\n11 - FUNDOS EU\nIdentificador do Lote: LOT-0001; LOT-0002; LOT-0003; LOT-0004; LOT-0005\nTêm fundos EU? Sim\n\n12 - DOCUMENTOS DE HABILITAÇÃO\nHabilitação para o exercício da atividade profissional: Não\n\n13 - CONDIÇÕES DE APRESENTAÇÃO\nPlataforma eletrónica utilizada pela entidade adjudicante: VORTAL\nURL para Apresentação: https://community.vortal.biz/public/\nAdmissibilidade da apresentação de propostas variantes: Não autorizado\nPrazo para apresentação das propostas: 06-09-2025 17:00\nPrazo durante o qual os concorrentes são obrigados a manter as respetivas propostas: 66 dias a contar do termo do prazo para a apresentação das propostas\nApresentação de Catálogo Eletrónico: Não autorizado\nIndicação de Subcontratação na Proposta: Inexistência de indicação de subcontratação\n\n14 - PRESTAÇÃO DE CAUÇÃO\nPrestação de caução: Sim\nPercentagem: 5%\nDescrição da Garantia Exigida: Garantia bancária\n\n15 - FORNECIMENTO DAS PEÇAS DO CONCURSO, APRESENTAÇÃO DE PEDIDOS DE PARTICIPAÇÃO E APRESENTAÇÃO DAS PROPOSTAS\nLink para acesso às peças do concurso (URL): https://community.vortal.biz/Public/public-tender-documents/T1k0b0VmeFprTTFCbWtyY0RCbUw2YmZac2syNys5L3EyeXBOMDg5TzY4blh2QlZUQjdKT09pelF2WC9QM29MckdabkxEbk9iOUN5QlNrQmI5Y084R0E9PSMlIXZ6\n\n20 - OUTROS REQUISITOS\nIdentificador do Lote: LOT-0001; LOT-0002; LOT-0003; LOT-0004; LOT-0005\nInformação sobre contratos reservados. Aplica-se a contratos reservados (54º-A)? Não\n\n21 - CRITÉRIO DE ADJUDICAÇÃO\nO Critério de adjudicação é diferenciado por lote? Não\nMultifator: Não\nMonofator:\nNome: Preço\n\n24 - CONDIÇÕES DO CONTRATO\nIdentificador do Lote: LOT-0001; LOT-0002; LOT-0003; LOT-0004; LOT-0005\nFaturação Eletrónica: Permitido\nObrigação de Subcontratação:\nCódigo da Obrigação de Subcontratação: Não é aplicável nenhuma obrigação de subcontratação.\n\n25 - COMPRA PÚBLICA ESTRATÉGICA\nCompra Pública Estratégica: Redução dos impactos ambientais\nDescrição do Processo de Adjudicação Estratégico: Conforme as peças do procedimento\nCritérios de contratos Públicos Ecológicos: Critérios de contratação pública ecológica nacional\nCategorias da estratégia nacional: Outros\nOutra categoria (Descrição): De acordo com as peças do procedimento\nDiretiva Veículos Não Poluentes: Não\nCritério de Acessibilidade: Os critérios de acessibilidade para as pessoas com deficiência não estão incluídos porque o contrato não se destina a pessoas singulares\n\n26 - INFORMAÇÕES ADICIONAIS\nIdentificador do Lote: LOT-0001; LOT-0002; LOT-0003; LOT-0004; LOT-0005\nContrato adequado para PME: Sim\nCobertura ACP (Acordo dos Contratos Públicos da Organização Mundial do Comércio): Não\n\n27 - IDENTIFICAÇÃO E CONTACTOS DO ÓRGÃO DE RECURSOS ADMINISTRATIVOS\nDesignação: Conselho Administrativo\nEndereço: Avenida João Paulo II\nCódigo postal: 4750-304\nLocalidade: Barcelos\nTelefone: +351 253809360\nFax: +351 000000000\nEndereço eletrónico: aeb@aebarcelos.pt\nPrazo de interposição do recurso: 10 dias\n\n28 - IDENTIFICAÇÃO DO(S) AUTOR(ES) DE ANÚNCIO\nNome: Jorge Saleiro\nCargo: Diretor\n419413695",
    "nipc": "600085198",
    "distrito": "Braga",
    "concelho": "Barcelos",
    "freguesia": "Todas",
    "site": "https://aebarcelos.pt/",
    "email": "esb3.barcelos@escolas.min-edu.pt",
    "designacao_contrato": "Aquisição de equipamento para equipar o Centro Tecnológico Especializado - Informática, por lotes",
    "descricao": "Aquisição de equipamento para equipar o Centro Tecnológico Especializado - Informática, por lotes",
    "preco_base": "802.946,14 EUR",
    "prazo_execucao": "60 DIAS",
    "prazo_apresentacao_propostas": "06-09-2025 17:00",
    "fundos_eu": "Sim",
    "plataforma_eletronica": "VORTAL",
    "url_procedimento": "https://community.vortal.biz/public/",
    "autor_nome": "Jorge Saleiro",
    "autor_cargo": "Diretor"
  },
  {
    "numero_procedimento": "N/A",
    "entidade": "AnÃºncio de procedimento  n.Âº 21545/2025  -  DiÃ¡rio da RepÃºblica n.Âº 153/2025, SÃ©rie II de 2025-08-11",
    "link": "https://diariodarepublica.pt/dr/detalhe/contrato-publico/21545-928478164"
  },
  {
    "numero_procedimento": "N/A",
    "entidade": "AnÃºncio de procedimento  n.Âº 21546/2025  -  DiÃ¡rio da RepÃºblica n.Âº 153/2025, SÃ©rie II de 2025-08-11",
    "link": "https://diariodarepublica.pt/dr/detalhe/contrato-publico/21546-928478165"
  },
  {
    "numero_procedimento": "N/A",
    "entidade": "AnÃºncio de procedimento  n.Âº 21547/2025  -  DiÃ¡rio da RepÃºblica n.Âº 153/2025, SÃ©rie II de 2025-08-11",
    "link": "https://diariodarepublica.pt/dr/detalhe/contrato-publico/21547-928478166"
  },
  {
    "numero_procedimento": "N/A",
    "entidade": "AnÃºncio de procedimento  n.Âº 21550/2025  -  DiÃ¡rio da RepÃºblica n.Âº 153/2025, SÃ©rie II de 2025-08-11",
    "link": "https://diariodarepublica.pt/dr/detalhe/contrato-publico/21550-928478167"
  },
  {
    "numero_procedimento": "N/A",
    "entidade": "AnÃºncio de procedimento  n.Âº 21553/2025  -  DiÃ¡rio da RepÃºblica n.Âº 153/2025, SÃ©rie II de 2025-08-11",
    "link": "https://diariodarepublica.pt/dr/detalhe/contrato-publico/21553-928478168"
  },
  {
    "numero_procedimento": "N/A",
    "entidade": "AnÃºncio de procedimento  n.Âº 21555/2025  -  DiÃ¡rio da RepÃºblica n.Âº 153/2025, SÃ©rie II de 2025-08-11",
    "link": "https://diariodarepublica.pt/dr/detalhe/contrato-publico/21555-928478169"
  },
  {
    "numero_procedimento": "N/A",
    "entidade": "AnÃºncio de procedimento  n.Âº 21561/2025  -  DiÃ¡rio da RepÃºblica n.Âº 153/2025, SÃ©rie II de 2025-08-11",
    "link": "https://diariodarepublica.pt/dr/detalhe/contrato-publico/21561-928478170"
  },
  {
    "numero_procedimento": "N/A",
    "entidade": "AnÃºncio de procedimento  n.Âº 21563/2025  -  DiÃ¡rio da RepÃºblica n.Âº 153/2025, SÃ©rie II de 2025-08-11",
    "link": "https://diariodarepublica.pt/dr/detalhe/contrato-publico/21563-928478171"
  },
  {
    "numero_procedimento": "N/A",
    "entidade": "AnÃºncio de procedimento  n.Âº 21566/2025  -  DiÃ¡rio da RepÃºblica n.Âº 153/2025, SÃ©rie II de 2025-08-11",
    "link": "https://diariodarepublica.pt/dr/detalhe/contrato-publico/21566-928478172"
  },
  {
    "numero_procedimento": "N/A",
    "entidade": "AnÃºncio de procedimento  n.Âº 21574/2025  -  DiÃ¡rio da RepÃºblica n.Âº 153/2025, SÃ©rie II de 2025-08-11",
    "link": "https://diariodarepublica.pt/dr/detalhe/contrato-publico/21574-928478173"
  },
  {
    "numero_procedimento": "N/A",
    "entidade": "AnÃºncio de procedimento  n.Âº 21575/2025  -  DiÃ¡rio da RepÃºblica n.Âº 153/2025, SÃ©rie II de 2025-08-11",
    "link": "https://diariodarepublica.pt/dr/detalhe/contrato-publico/21575-928478174"
  },
  {
    "numero_procedimento": "N/A",
    "entidade": "AnÃºncio de procedimento  n.Âº 21512/2025  -  DiÃ¡rio da RepÃºblica n.Âº 153/2025, SÃ©rie II de 2025-08-11",
    "link": "https://diariodarepublica.pt/dr/detalhe/contrato-publico/21512-928480330"
  },
  {
    "numero_procedimento": "N/A",
    "entidade": "AnÃºncio de procedimento  n.Âº 21513/2025  -  DiÃ¡rio da RepÃºblica n.Âº 153/2025, SÃ©rie II de 2025-08-11",
    "link": "https://diariodarepublica.pt/dr/detalhe/contrato-publico/21513-928480335"
  },
  {
    "numero_procedimento": "N/A",
    "entidade": "AnÃºncio de procedimento  n.Âº 21516/2025  -  DiÃ¡rio da RepÃºblica n.Âº 153/2025, SÃ©rie II de 2025-08-11",
    "link": "https://diariodarepublica.pt/dr/detalhe/contrato-publico/21516-928480336"
  },
  {
    "numero_procedimento": "N/A",
    "entidade": "AnÃºncio de procedimento  n.Âº 21517/2025  -  DiÃ¡rio da RepÃºblica n.Âº 153/2025, SÃ©rie II de 2025-08-11",
    "link": "https://diariodarepublica.pt/dr/detalhe/contrato-publico/21517-928480337"
  },
  {
    "numero_procedimento": "N/A",
    "entidade": "AnÃºncio de procedimento  n.Âº 21519/2025  -  DiÃ¡rio da RepÃºblica n.Âº 153/2025, SÃ©rie II de 2025-08-11",
    "link": "https://diariodarepublica.pt/dr/detalhe/contrato-publico/21519-928480338"
  },
  {
    "numero_procedimento": "N/A",
    "entidade": "AnÃºncio de procedimento  n.Âº 21521/2025  -  DiÃ¡rio da RepÃºblica n.Âº 153/2025, SÃ©rie II de 2025-08-11",
    "link": "https://diariodarepublica.pt/dr/detalhe/contrato-publico/21521-928480339"
  },
  {
    "numero_procedimento": "N/A",
    "entidade": "AnÃºncio de procedimento  n.Âº 21523/2025  -  DiÃ¡rio da RepÃºblica n.Âº 153/2025, SÃ©rie II de 2025-08-11",
    "link": "https://diariodarepublica.pt/dr/detalhe/contrato-publico/21523-928480340"
  },
  {
    "numero_procedimento": "N/A",
    "entidade": "AnÃºncio de procedimento  n.Âº 21526/2025  -  DiÃ¡rio da RepÃºblica n.Âº 153/2025, SÃ©rie II de 2025-08-11",
    "link": "https://diariodarepublica.pt/dr/detalhe/contrato-publico/21526-928480341"
  },
  {
    "numero_procedimento": "N/A",
    "entidade": "AnÃºncio de procedimento  n.Âº 21529/2025  -  DiÃ¡rio da RepÃºblica n.Âº 153/2025, SÃ©rie II de 2025-08-11",
    "link": "https://diariodarepublica.pt/dr/detalhe/contrato-publico/21529-928480342"
  },
  {
    "numero_procedimento": "N/A",
    "entidade": "AnÃºncio de procedimento  n.Âº 21532/2025  -  DiÃ¡rio da RepÃºblica n.Âº 153/2025, SÃ©rie II de 2025-08-11",
    "link": "https://diariodarepublica.pt/dr/detalhe/contrato-publico/21532-928480343"
  },
  {
    "numero_procedimento": "N/A",
    "entidade": "AnÃºncio de procedimento  n.Âº 21534/2025  -  DiÃ¡rio da RepÃºblica n.Âº 153/2025, SÃ©rie II de 2025-08-11",
    "link": "https://diariodarepublica.pt/dr/detalhe/contrato-publico/21534-928480344"
  },
  {
    "numero_procedimento": "N/A",
    "entidade": "AnÃºncio de procedimento  n.Âº 21537/2025  -  DiÃ¡rio da RepÃºblica n.Âº 153/2025, SÃ©rie II de 2025-08-11",
    "link": "https://diariodarepublica.pt/dr/detalhe/contrato-publico/21537-928480345"
  },
  {
    "numero_procedimento": "N/A",
    "entidade": "AnÃºncio de procedimento  n.Âº 21538/2025  -  DiÃ¡rio da RepÃºblica n.Âº 153/2025, SÃ©rie II de 2025-08-11",
    "link": "https://diariodarepublica.pt/dr/detalhe/contrato-publico/21538-928480346"
  },
  {
    "numero_procedimento": "N/A",
    "entidade": "AnÃºncio de procedimento  n.Âº 21539/2025  -  DiÃ¡rio da RepÃºblica n.Âº 153/2025, SÃ©rie II de 2025-08-11",
    "link": "https://diariodarepublica.pt/dr/detalhe/contrato-publico/21539-928480347"
  },
  {
    "numero_procedimento": "N/A",
    "entidade": "AnÃºncio de procedimento  n.Âº 21540/2025  -  DiÃ¡rio da RepÃºblica n.Âº 153/2025, SÃ©rie II de 2025-08-11",
    "link": "https://diariodarepublica.pt/dr/detalhe/contrato-publico/21540-928480348"
  },
  {
    "numero_procedimento": "N/A",
    "entidade": "AnÃºncio de procedimento  n.Âº 21541/2025  -  DiÃ¡rio da RepÃºblica n.Âº 153/2025, SÃ©rie II de 2025-08-11",
    "link": "https://diariodarepublica.pt/dr/detalhe/contrato-publico/21541-928480349"
  },
  {
    "numero_procedimento": "N/A",
    "entidade": "AnÃºncio de procedimento  n.Âº 21542/2025  -  DiÃ¡rio da RepÃºblica n.Âº 153/2025, SÃ©rie II de 2025-08-11",
    "link": "https://diariodarepublica.pt/dr/detalhe/contrato-publico/21542-928480350"
  },
  {
    "numero_procedimento": "N/A",
    "entidade": "AnÃºncio de procedimento  n.Âº 21543/2025  -  DiÃ¡rio da RepÃºblica n.Âº 153/2025, SÃ©rie II de 2025-08-11",
    "link": "https://diariodarepublica.pt/dr/detalhe/contrato-publico/21543-928480351"
  },
  {
    "numero_procedimento": "N/A",
    "entidade": "AnÃºncio de procedimento  n.Âº 21544/2025  -  DiÃ¡rio da RepÃºblica n.Âº 153/2025, SÃ©rie II de 2025-08-11",
    "link": "https://diariodarepublica.pt/dr/detalhe/contrato-publico/21544-928480352"
  },
  {
    "numero_procedimento": "N/A",
    "entidade": "AnÃºncio de procedimento  n.Âº 21548/2025  -  DiÃ¡rio da RepÃºblica n.Âº 153/2025, SÃ©rie II de 2025-08-11",
    "link": "https://diariodarepublica.pt/dr/detalhe/contrato-publico/21548-928480353"
  },
  {
    "numero_procedimento": "N/A",
    "entidade": "AnÃºncio de procedimento  n.Âº 21549/2025  -  DiÃ¡rio da RepÃºblica n.Âº 153/2025, SÃ©rie II de 2025-08-11",
    "link": "https://diariodarepublica.pt/dr/detalhe/contrato-publico/21549-928480354"
  },
  {
    "numero_procedimento": "N/A",
    "entidade": "AnÃºncio de procedimento  n.Âº 21551/2025  -  DiÃ¡rio da RepÃºblica n.Âº 153/2025, SÃ©rie II de 2025-08-11",
    "link": "https://diariodarepublica.pt/dr/detalhe/contrato-publico/21551-928480355"
  },
  {
    "numero_procedimento": "N/A",
    "entidade": "AnÃºncio de procedimento  n.Âº 21552/2025  -  DiÃ¡rio da RepÃºblica n.Âº 153/2025, SÃ©rie II de 2025-08-11",
    "link": "https://diariodarepublica.pt/dr/detalhe/contrato-publico/21552-928480356"
  },
  {
    "numero_procedimento": "N/A",
    "entidade": "AnÃºncio de procedimento  n.Âº 21554/2025  -  DiÃ¡rio da RepÃºblica n.Âº 153/2025, SÃ©rie II de 2025-08-11",
    "link": "https://diariodarepublica.pt/dr/detalhe/contrato-publico/21554-928480357"
  },
  {
    "numero_procedimento": "N/A",
    "entidade": "AnÃºncio de procedimento  n.Âº 21556/2025  -  DiÃ¡rio da RepÃºblica n.Âº 153/2025, SÃ©rie II de 2025-08-11",
    "link": "https://diariodarepublica.pt/dr/detalhe/contrato-publico/21556-928480358"
  },
  {
    "numero_procedimento": "N/A",
    "entidade": "AnÃºncio de procedimento  n.Âº 21557/2025  -  DiÃ¡rio da RepÃºblica n.Âº 153/2025, SÃ©rie II de 2025-08-11",
    "link": "https://diariodarepublica.pt/dr/detalhe/contrato-publico/21557-928480359"
  },
  {
    "numero_procedimento": "N/A",
    "entidade": "AnÃºncio de procedimento  n.Âº 21558/2025  -  DiÃ¡rio da RepÃºblica n.Âº 153/2025, SÃ©rie II de 2025-08-11",
    "link": "https://diariodarepublica.pt/dr/detalhe/contrato-publico/21558-928480360"
  },
  {
    "numero_procedimento": "N/A",
    "entidade": "AnÃºncio de procedimento  n.Âº 21559/2025  -  DiÃ¡rio da RepÃºblica n.Âº 153/2025, SÃ©rie II de 2025-08-11",
    "link": "https://diariodarepublica.pt/dr/detalhe/contrato-publico/21559-928480361"
  },
  {
    "numero_procedimento": "N/A",
    "entidade": "AnÃºncio de procedimento  n.Âº 21560/2025  -  DiÃ¡rio da RepÃºblica n.Âº 153/2025, SÃ©rie II de 2025-08-11",
    "link": "https://diariodarepublica.pt/dr/detalhe/contrato-publico/21560-928480362"
  },
  {
    "numero_procedimento": "N/A",
    "entidade": "AnÃºncio de procedimento  n.Âº 21562/2025  -  DiÃ¡rio da RepÃºblica n.Âº 153/2025, SÃ©rie II de 2025-08-11",
    "link": "https://diariodarepublica.pt/dr/detalhe/contrato-publico/21562-928480363"
  },
  {
    "numero_procedimento": "N/A",
    "entidade": "AnÃºncio de procedimento  n.Âº 21564/2025  -  DiÃ¡rio da RepÃºblica n.Âº 153/2025, SÃ©rie II de 2025-08-11",
    "link": "https://diariodarepublica.pt/dr/detalhe/contrato-publico/21564-928480364"
  },
  {
    "numero_procedimento": "N/A",
    "entidade": "AnÃºncio de procedimento  n.Âº 21565/2025  -  DiÃ¡rio da RepÃºblica n.Âº 153/2025, SÃ©rie II de 2025-08-11",
    "link": "https://diariodarepublica.pt/dr/detalhe/contrato-publico/21565-928480365"
  },
  {
    "numero_procedimento": "N/A",
    "entidade": "AnÃºncio de procedimento  n.Âº 21567/2025  -  DiÃ¡rio da RepÃºblica n.Âº 153/2025, SÃ©rie II de 2025-08-11",
    "link": "https://diariodarepublica.pt/dr/detalhe/contrato-publico/21567-928480366"
  },
  {
    "numero_procedimento": "N/A",
    "entidade": "AnÃºncio de procedimento  n.Âº 21568/2025  -  DiÃ¡rio da RepÃºblica n.Âº 153/2025, SÃ©rie II de 2025-08-11",
    "link": "https://diariodarepublica.pt/dr/detalhe/contrato-publico/21568-928480367"
  },
  {
    "numero_procedimento": "N/A",
    "entidade": "AnÃºncio de procedimento  n.Âº 21569/2025  -  DiÃ¡rio da RepÃºblica n.Âº 153/2025, SÃ©rie II de 2025-08-11",
    "link": "https://diariodarepublica.pt/dr/detalhe/contrato-publico/21569-928480368"
  },
  {
    "numero_procedimento": "N/A",
    "entidade": "AnÃºncio de procedimento  n.Âº 21570/2025  -  DiÃ¡rio da RepÃºblica n.Âº 153/2025, SÃ©rie II de 2025-08-11",
    "link": "https://diariodarepublica.pt/dr/detalhe/contrato-publico/21570-928480369"
  },
  {
    "numero_procedimento": "N/A",
    "entidade": "AnÃºncio de procedimento  n.Âº 21571/2025  -  DiÃ¡rio da RepÃºblica n.Âº 153/2025, SÃ©rie II de 2025-08-11",
    "link": "https://diariodarepublica.pt/dr/detalhe/contrato-publico/21571-928480370"
  },
  {
    "numero_procedimento": "N/A",
    "entidade": "AnÃºncio de procedimento  n.Âº 21572/2025  -  DiÃ¡rio da RepÃºblica n.Âº 153/2025, SÃ©rie II de 2025-08-11",
    "link": "https://diariodarepublica.pt/dr/detalhe/contrato-publico/21572-928480371"
  },
  {
    "numero_procedimento": "N/A",
    "entidade": "AnÃºncio de procedimento  n.Âº 21573/2025  -  DiÃ¡rio da RepÃºblica n.Âº 153/2025, SÃ©rie II de 2025-08-11",
    "link": "https://diariodarepublica.pt/dr/detalhe/contrato-publico/21573-928480372"
  },
  {
    "numero_procedimento": "N/A",
    "entidade": "AnÃºncio de procedimento  n.Âº 21578/2025  -  DiÃ¡rio da RepÃºblica n.Âº 153/2025, SÃ©rie II de 2025-08-11",
    "link": "https://diariodarepublica.pt/dr/detalhe/contrato-publico/21578-928480373"
  },
  {
    "numero_procedimento": "N/A",
    "entidade": "AnÃºncio de procedimento  n.Âº 21580/2025  -  DiÃ¡rio da RepÃºblica n.Âº 153/2025, SÃ©rie II de 2025-08-11",
    "link": "https://diariodarepublica.pt/dr/detalhe/contrato-publico/21580-928480374"
  },
  {
    "numero_procedimento": "N/A",
    "entidade": "AnÃºncio de procedimento  n.Âº 21576/2025  -  DiÃ¡rio da RepÃºblica n.Âº 153/2025, SÃ©rie II de 2025-08-11",
    "link": "https://diariodarepublica.pt/dr/detalhe/contrato-publico/21576-928506175"
  },
  {
    "numero_procedimento": "N/A",
    "entidade": "AnÃºncio de procedimento  n.Âº 21577/2025  -  DiÃ¡rio da RepÃºblica n.Âº 153/2025, SÃ©rie II de 2025-08-11",
    "link": "https://diariodarepublica.pt/dr/detalhe/contrato-publico/21577-928506176"
  },
  {
    "numero_procedimento": "N/A",
    "entidade": "AnÃºncio de procedimento  n.Âº 21579/2025  -  DiÃ¡rio da RepÃºblica n.Âº 153/2025, SÃ©rie II de 2025-08-11",
    "link": "https://diariodarepublica.pt/dr/detalhe/contrato-publico/21579-928506177"
  },
  {
    "numero_procedimento": "N/A",
    "entidade": "AnÃºncio de procedimento  n.Âº 21581/2025  -  DiÃ¡rio da RepÃºblica n.Âº 153/2025, SÃ©rie II de 2025-08-11",
    "link": "https://diariodarepublica.pt/dr/detalhe/contrato-publico/21581-928506275"
  },
  {
    "numero_procedimento": "N/A",
    "entidade": "AnÃºncio de procedimento  n.Âº 21582/2025  -  DiÃ¡rio da RepÃºblica n.Âº 153/2025, SÃ©rie II de 2025-08-11",
    "link": "https://diariodarepublica.pt/dr/detalhe/contrato-publico/21582-928506276"
  }
]