[
  {
    "numero_procedimento": "N/A",
    "entidade": "AnÃºncio de procedimento  n.Âº 24121/2025  -  DiÃ¡rio da RepÃºblica n.Âº 176/2025, SÃ©rie II de 2025-09-12",
    "link": "https://diariodarepublica.pt/dr/detalhe/contrato-publico/24121-935096720"
  },
  {
    "numero_procedimento": "N/A",
    "entidade": "AnÃºncio de procedimento  n.Âº 24122/2025  -  DiÃ¡rio da RepÃºblica n.Âº 176/2025, SÃ©rie II de 2025-09-12",
    "link": "https://diariodarepublica.pt/dr/detalhe/contrato-publico/24122-935096721"
  },
  {
    "numero_procedimento": "N/A",
    "entidade": "AnÃºncio de procedimento  n.Âº 24123/2025  -  DiÃ¡rio da RepÃºblica n.Âº 176/2025, SÃ©rie II de 2025-09-12",
    "link": "https://diariodarepublica.pt/dr/detalhe/contrato-publico/24123-935096722"
  },
  {
    "numero_procedimento": "N/A",
    "entidade": "AnÃºncio de procedimento  n.Âº 24126/2025  -  DiÃ¡rio da RepÃºblica n.Âº 176/2025, SÃ©rie II de 2025-09-12",
    "link": "https://diariodarepublica.pt/dr/detalhe/contrato-publico/24126-935096723"
  },
  {
    "numero_procedimento": "N/A",
    "entidade": "AnÃºncio de procedimento  n.Âº 24129/2025  -  DiÃ¡rio da RepÃºblica n.Âº 176/2025, SÃ©rie II de 2025-09-12",
    "link": "https://diariodarepublica.pt/dr/detalhe/contrato-publico/24129-935096724"
  },
  {
    "numero_procedimento": "N/A",
    "entidade": "AnÃºncio de procedimento  n.Âº 24133/2025  -  DiÃ¡rio da RepÃºblica n.Âº 176/2025, SÃ©rie II de 2025-09-12",
    "link": "https://diariodarepublica.pt/dr/detalhe/contrato-publico/24133-935096725"
  },
  {
    "numero_procedimento": "N/A",
    "entidade": "AnÃºncio de procedimento  n.Âº 24134/2025  -  DiÃ¡rio da RepÃºblica n.Âº 176/2025, SÃ©rie II de 2025-09-12",
    "link": "https://diariodarepublica.pt/dr/detalhe/contrato-publico/24134-935096726"
  },
  {
    "numero_procedimento": "N/A",
    "entidade": "AnÃºncio de procedimento  n.Âº 24135/2025  -  DiÃ¡rio da RepÃºblica n.Âº 176/2025, SÃ©rie II de 2025-09-12",
    "link": "https://diariodarepublica.pt/dr/detalhe/contrato-publico/24135-935096727"
  },
  {
    "numero_procedimento": "N/A",
    "entidade": "AnÃºncio de procedimento  n.Âº 24138/2025  -  DiÃ¡rio da RepÃºblica n.Âº 176/2025, SÃ©rie II de 2025-09-12",
    "link": "https://diariodarepublica.pt/dr/detalhe/contrato-publico/24138-935096728"
  },
  {
    "numero_procedimento": "N/A",
    "entidade": "AnÃºncio de procedimento  n.Âº 24141/2025  -  DiÃ¡rio da RepÃºblica n.Âº 176/2025, SÃ©rie II de 2025-09-12",
    "link": "https://diariodarepublica.pt/dr/detalhe/contrato-publico/24141-935096735"
  },
  {
    "numero_procedimento": "N/A",
    "entidade": "AnÃºncio de procedimento  n.Âº 24143/2025  -  DiÃ¡rio da RepÃºblica n.Âº 176/2025, SÃ©rie II de 2025-09-12",
    "link": "https://diariodarepublica.pt/dr/detalhe/contrato-publico/24143-935096736"
  },
  {
    "numero_procedimento": "N/A",
    "entidade": "Instituto Português de Oncologia de Lisboa FG, E.P.E.",
    "link": "https://diariodarepublica.pt/dr/detalhe/contrato-publico/24144-935096737",
    "detalhes_completos": "1 - IDENTIFICAÇÃO E CONTACTOS DA ENTIDADE ADJUDICANTE\nDesignação da entidade adjudicante: Instituto Português de Oncologia de Lisboa FG, E.P.E.\nNIPC: 506361616\nEndereço: Rua Profº Lima Basto\nCódigo postal: 1099-023\nLocalidade: Lisboa\nPaís: Portugal\nNUT III: PT170\nDistrito: Lisboa\nConcelho: Lisboa\nFreguesia: Todas\nTelefone: 217229800\nFax: 217229880\nEndereço da Entidade (URL): www.ipolisboa.min-saude.pt/\nEndereço Eletrónico: ipofg@ipolisboa.min-saude.pt\neDelivery Gateway (URL): https://community.vortal.biz/public/\nFunção da Organização: Adquirente\nNorma jurídica da Entidade Adjudicante: Organismo de direito público\nÁrea de atividade da Autoridade Adjudicante: Saúde\n\n2 - JORNAL OFICIAL DA UNIÃO EUROPEIA\nO procedimento a que este anúncio diz respeito também é publicitado no Jornal Oficial da União Europeia? Não\n\n3 - AVISO\nModelo de Anúncio: Concurso público\nData de Envio do Anúncio: 12-09-2025\n\n5 - PROCESSO\nTipo de Procedimento: Concurso público\nPreço base do procedimento: Sim\nValor do preço base do procedimento: 4.900,00 EUR\nProcedimento com lotes? Não\n\n6 - OBJETO DO CONTRATO\nNúmero de referência interna: PN/2587/2025\nDesignação do contrato: FILTRO ANTI BACTERIANO P/ TORNEIRA P/ 93 DIAS\nDescrição: FILTRO ANTI BACTERIANO P/ TORNEIRA P/ 93 DIAS\nTipo de Contrato Principal: Aquisição de Bens Móveis\nTipo de Contrato: Aquisição de Bens Móveis; Locação de Bens Móveis\nClassificação CPV (Vocabulário Comum para os Contratos Públicos)\nObjeto principal\nVocabulário Principal: 42132200\nPreço base s/IVA: 4.900,00 EUR\n\n7 - INDICAÇÕES ADICIONAIS\nO contrato envolve aquisição conjunta (satisfação de várias entidades)? Não\nO contrato é adjudicado por uma central de compras? Não\n\n8 - TÉCNICAS\nO concurso destina-se à celebração de um acordo-quadro? Inexistência de acordo-quadro\nÉ utilizado um leilão eletrónico? Não\nÉ adotada uma fase de negociação? Não\nSistema de Aquisição Dinâmico: Inexistência de sistema de aquisição dinâmico\n\n9 - LOCAL DA EXECUÇÃO DO CONTRATO\nLOCAL DA EXECUÇÃO DO CONTRATO (PROCEDIMENTO)\nPaís: Portugal\nNUT III: PT170\nLocalidade: Lisboa\nDistrito: Lisboa\nConcelho: Lisboa\nFreguesia: Freguesia de São Domingos de Benfica\n\n10 - PRAZO DE EXECUÇÃO DO CONTRATO\nPrazo de execução do contrato: 3 MESES\nPrevisão de renovações: Não\n\n11 - FUNDOS EU\nTêm fundos EU? Não\n\n12 - DOCUMENTOS DE HABILITAÇÃO\nHabilitação para o exercício da atividade profissional: Não\n\n13 - CONDIÇÕES DE APRESENTAÇÃO\nPlataforma eletrónica utilizada pela entidade adjudicante: VORTAL\nURL para Apresentação: https://community.vortal.biz/public/\nAdmissibilidade da apresentação de propostas variantes: Não autorizado\nPrazo para apresentação das propostas: 22-09-2025 17:59\nPrazo durante o qual os concorrentes são obrigados a manter as respetivas propostas: 90 dias a contar do termo do prazo para a apresentação das propostas\nIndicação de Subcontratação na Proposta: Inexistência de indicação de subcontratação\n\n14 - PRESTAÇÃO DE CAUÇÃO\nPrestação de caução: Não\n\n15 - FORNECIMENTO DAS PEÇAS DO CONCURSO, APRESENTAÇÃO DE PEDIDOS DE PARTICIPAÇÃO E APRESENTAÇÃO DAS PROPOSTAS\nLink para acesso às peças do concurso (URL): https://community.vortal.biz/Public/public-tender-documents/elF4dkNFa2JQcXUyRmlMMFNpMlJUeVhRLzVaM2xVckpZK0EzK0RSazh4S1RCTjRra2NLTVF0d0Nvbms1NjBHYmNUOXErZ3dWWkVSc05WdXdGaGF0U3c9PW1Ac3dP\n\n20 - OUTROS REQUISITOS\nInformação sobre contratos reservados. Aplica-se a contratos reservados (54º-A)? Não\n\n21 - CRITÉRIO DE ADJUDICAÇÃO\nMultifator: Não\nMonofator:\nNome: Preço\n\n24 - CONDIÇÕES DO CONTRATO\nFaturação Eletrónica: Permitido\nObrigação de Subcontratação:\nCódigo da Obrigação de Subcontratação: Não é aplicável nenhuma obrigação de subcontratação.\n\n25 - COMPRA PÚBLICA ESTRATÉGICA\nCompra Pública Estratégica: Inexistência de contratação pública estratégica\n\n26 - INFORMAÇÕES ADICIONAIS\nContrato adequado para PME: Sim\nCobertura ACP (Acordo dos Contratos Públicos da Organização Mundial do Comércio): Não\n\n27 - IDENTIFICAÇÃO E CONTACTOS DO ÓRGÃO DE RECURSOS ADMINISTRATIVOS\nDesignação: Conselho de Administração\nEndereço: Rua Profesor Lima Basto\nCódigo postal: 1099-023\nLocalidade: Lisboa\nTelefone: +351 217229800\nFax: +351 217229833\nEndereço eletrónico: ipofg@ipolisboa.min-saude.pt\n\n28 - IDENTIFICAÇÃO DO(S) AUTOR(ES) DE ANÚNCIO\nNome: Raquel Graça Fernandes\nCargo: Assistente Técnico\n419527476",
    "nipc": "506361616",
    "distrito": "Lisboa",
    "concelho": "Lisboa",
    "freguesia": "Todas",
    "site": "www.ipolisboa.min-saude.pt/",
    "email": "ipofg@ipolisboa.min-saude.pt",
    "designacao_contrato": "FILTRO ANTI BACTERIANO P/ TORNEIRA P/ 93 DIAS",
    "descricao": "FILTRO ANTI BACTERIANO P/ TORNEIRA P/ 93 DIAS",
    "preco_base": "4.900,00 EUR",
    "prazo_execucao": "3 MESES",
    "prazo_apresentacao_propostas": "22-09-2025 17:59",
    "fundos_eu": "Não",
    "plataforma_eletronica": "VORTAL",
    "url_procedimento": "https://community.vortal.biz/public/",
    "autor_nome": "Raquel Graça Fernandes",
    "autor_cargo": "Assistente Técnico"
  },
  {
    "numero_procedimento": "N/A",
    "entidade": "AnÃºncio de procedimento  n.Âº 24124/2025  -  DiÃ¡rio da RepÃºblica n.Âº 176/2025, SÃ©rie II de 2025-09-12",
    "link": "https://diariodarepublica.pt/dr/detalhe/contrato-publico/24124-935098460"
  },
  {
    "numero_procedimento": "N/A",
    "entidade": "AnÃºncio de procedimento  n.Âº 24125/2025  -  DiÃ¡rio da RepÃºblica n.Âº 176/2025, SÃ©rie II de 2025-09-12",
    "link": "https://diariodarepublica.pt/dr/detalhe/contrato-publico/24125-935098461"
  },
  {
    "numero_procedimento": "N/A",
    "entidade": "AnÃºncio de procedimento  n.Âº 24127/2025  -  DiÃ¡rio da RepÃºblica n.Âº 176/2025, SÃ©rie II de 2025-09-12",
    "link": "https://diariodarepublica.pt/dr/detalhe/contrato-publico/24127-935098462"
  },
  {
    "numero_procedimento": "N/A",
    "entidade": "AnÃºncio de procedimento  n.Âº 24128/2025  -  DiÃ¡rio da RepÃºblica n.Âº 176/2025, SÃ©rie II de 2025-09-12",
    "link": "https://diariodarepublica.pt/dr/detalhe/contrato-publico/24128-935098463"
  },
  {
    "numero_procedimento": "N/A",
    "entidade": "AnÃºncio de procedimento  n.Âº 24130/2025  -  DiÃ¡rio da RepÃºblica n.Âº 176/2025, SÃ©rie II de 2025-09-12",
    "link": "https://diariodarepublica.pt/dr/detalhe/contrato-publico/24130-935098464"
  },
  {
    "numero_procedimento": "N/A",
    "entidade": "AnÃºncio de procedimento  n.Âº 24131/2025  -  DiÃ¡rio da RepÃºblica n.Âº 176/2025, SÃ©rie II de 2025-09-12",
    "link": "https://diariodarepublica.pt/dr/detalhe/contrato-publico/24131-935098465"
  },
  {
    "numero_procedimento": "N/A",
    "entidade": "AnÃºncio de procedimento  n.Âº 24132/2025  -  DiÃ¡rio da RepÃºblica n.Âº 176/2025, SÃ©rie II de 2025-09-12",
    "link": "https://diariodarepublica.pt/dr/detalhe/contrato-publico/24132-935098466"
  },
  {
    "numero_procedimento": "N/A",
    "entidade": "AnÃºncio de procedimento  n.Âº 24136/2025  -  DiÃ¡rio da RepÃºblica n.Âº 176/2025, SÃ©rie II de 2025-09-12",
    "link": "https://diariodarepublica.pt/dr/detalhe/contrato-publico/24136-935098467"
  },
  {
    "numero_procedimento": "N/A",
    "entidade": "MUNICÍPIO DE LOULÉ",
    "link": "https://diariodarepublica.pt/dr/detalhe/contrato-publico/24137-935098468",
    "detalhes_completos": "1 - IDENTIFICAÇÃO E CONTACTOS DA ENTIDADE ADJUDICANTE\nDesignação da entidade adjudicante: MUNICÍPIO DE LOULÉ\nNIPC: 502098139\nEndereço: Praça da República\nCódigo postal: 8104-001\nLocalidade: Faro\nPaís: Portugal\nNUT III: PT150\nDistrito: Faro\nConcelho: Loulé\nFreguesia: Todas\nTelefone: 289400834\nFax: 289415557\nEndereço da Entidade (URL): www.cm-loule.pt\nEndereço Eletrónico: aprovisionamento@cm-loule.pt\neDelivery Gateway (URL): https://community.vortal.biz/public/\nFunção da Organização: Adquirente\nNorma jurídica da Entidade Adjudicante: Organismo de direito público\nÁrea de atividade da Autoridade Adjudicante: Serviços públicos das administrações públicas\n\n2 - JORNAL OFICIAL DA UNIÃO EUROPEIA\nO procedimento a que este anúncio diz respeito também é publicitado no Jornal Oficial da União Europeia? Sim\n\n3 - AVISO\nModelo de Anúncio: Concurso público\nData de Envio do Anúncio: 09-09-2025\n\n5 - PROCESSO\nTipo de Procedimento: Concurso público\nPreço base do procedimento: Sim\nValor do preço base do procedimento: 149.000,00 EUR\nProcedimento com lotes? Sim\nNº Máx. de Lotes Autorizado: 3\nNúmero máximo de lotes que podem ser adjudicados a um concorrente: 3\n\n6 - OBJETO DO CONTRATO\nNúmero de referência interna: FM-2025-411 DACP\nDesignação do contrato: CONTRATAÇÃO DA AQUISIÇÃO DE CADERNOS DE ATIVIDADES – ANO LETIVO 2025/2026 (2.º, 6.º e 11.º ANO)\nDescrição: CONTRATAÇÃO DA AQUISIÇÃO DE CADERNOS DE ATIVIDADES – ANO LETIVO 2025/2026 (2.º, 6.º e 11.º ANO)\nOpções: Não\nTipo de Contrato Principal: Aquisição de Bens Móveis\nTipo de Contrato: Aquisição de Bens Móveis\nClassificação CPV (Vocabulário Comum para os Contratos Públicos)\nObjeto principal\nVocabulário Principal: 22110000\nPreço base s/IVA: 149.000,00 EUR\nLotes: \nNº: LOT-0001\nDescrição do Lote: LOTE 1 \nPreço base s/IVA: 45.600,00 EUR\nClassificação CPV (Vocabulário Comum para os Contratos Públicos)\nObjeto principal\nVocabulário Principal: 22110000\nNº: LOT-0002\nDescrição do Lote: LOTE 2 \nPreço base s/IVA: 77.700,00 EUR\nClassificação CPV (Vocabulário Comum para os Contratos Públicos)\nObjeto principal\nVocabulário Principal: 22110000\nNº: LOT-0003\nDescrição do Lote: LOTE 3 \nPreço base s/IVA: 25.700,00 EUR\nClassificação CPV (Vocabulário Comum para os Contratos Públicos)\nObjeto principal\nVocabulário Principal: 22110000\n\n7 - INDICAÇÕES ADICIONAIS\nO contrato envolve aquisição conjunta (satisfação de várias entidades)? Não\nO contrato é adjudicado por uma central de compras? Não\n\n8 - TÉCNICAS\nO concurso destina-se à celebração de um acordo-quadro? Inexistência de acordo-quadro\nÉ utilizado um leilão eletrónico? Não\nÉ adotada uma fase de negociação? Não\nSistema de Aquisição Dinâmico: Inexistência de sistema de aquisição dinâmico\n\n9 - LOCAL DA EXECUÇÃO DO CONTRATO\nLOCAL DA EXECUÇÃO DO CONTRATO (PROCEDIMENTO)\nPaís: Portugal\nNUT III: PT150\nLocalidade: Loulé\nDistrito: Faro\nConcelho: Loulé\nFreguesia: Todas\nLOCAL DA EXECUÇÃO DO CONTRATO (LOTE)\nIdentificador do Lote: LOT-0001; LOT-0002; LOT-0003\nPaís: Portugal\nNUT III: PT150\nLocalidade: Faro\nDistrito: Faro\nConcelho: Loulé\nFreguesia: Todas\n\n10 - PRAZO DE EXECUÇÃO DO CONTRATO\nIdentificador do Lote: LOT-0001; LOT-0002; LOT-0003\nPrazo de execução do contrato: 10 DIAS\nPrevisão de renovações: Não\n\n11 - FUNDOS EU\nIdentificador do Lote: LOT-0001; LOT-0002; LOT-0003\nTêm fundos EU? Não\n\n12 - DOCUMENTOS DE HABILITAÇÃO\nHabilitação para o exercício da atividade profissional: Não\n\n13 - CONDIÇÕES DE APRESENTAÇÃO\nPlataforma eletrónica utilizada pela entidade adjudicante: VORTAL\nURL para Apresentação: https://community.vortal.biz/public/\nAdmissibilidade da apresentação de propostas variantes: Não autorizado\nPrazo para apresentação das propostas: 29-09-2025 18:00\nPrazo durante o qual os concorrentes são obrigados a manter as respetivas propostas: 90 dias a contar do termo do prazo para a apresentação das propostas\nApresentação de Catálogo Eletrónico: Não autorizado\nIndicação de Subcontratação na Proposta: Inexistência de indicação de subcontratação\n\n14 - PRESTAÇÃO DE CAUÇÃO\nPrestação de caução: Não\n\n15 - FORNECIMENTO DAS PEÇAS DO CONCURSO, APRESENTAÇÃO DE PEDIDOS DE PARTICIPAÇÃO E APRESENTAÇÃO DAS PROPOSTAS\nLink para acesso às peças do concurso (URL): https://community.vortal.biz/Public/public-tender-documents/RXZzU2plR2RGQS9RcWFnZ3h6aHJGTldxblQwMHVXVDZIeXQ4WU5pRVZ2RjdpZGRtZkg0WGQ1SElYZXcvRGEwVnJrTk1UZmFyZDVIK0sxQVEvekVTTkE9PSl5IXpA\n\n20 - OUTROS REQUISITOS\nIdentificador do Lote: LOT-0001; LOT-0002; LOT-0003\nInformação sobre contratos reservados. Aplica-se a contratos reservados (54º-A)? Não\n\n21 - CRITÉRIO DE ADJUDICAÇÃO\nO Critério de adjudicação é diferenciado por lote? Não\nMultifator: Não\nMonofator:\nNome: Preço\n\n24 - CONDIÇÕES DO CONTRATO\nIdentificador do Lote: LOT-0001; LOT-0002; LOT-0003\nFaturação Eletrónica: Permitido\nObrigação de Subcontratação:\nCódigo da Obrigação de Subcontratação: Não é aplicável nenhuma obrigação de subcontratação.\n\n25 - COMPRA PÚBLICA ESTRATÉGICA\nCompra Pública Estratégica: Inexistência de contratação pública estratégica\n\n26 - INFORMAÇÕES ADICIONAIS\nIdentificador do Lote: LOT-0001; LOT-0002; LOT-0003\nContrato adequado para PME: Sim\nCobertura ACP (Acordo dos Contratos Públicos da Organização Mundial do Comércio): Não\n\n27 - IDENTIFICAÇÃO E CONTACTOS DO ÓRGÃO DE RECURSOS ADMINISTRATIVOS\nDesignação: Câmara Municipal de Loulé\nEndereço: Praça da República\nCódigo postal: 8104-001\nLocalidade: Loulé\nTelefone: +351 289400600\nFax: +351 289415557\nEndereço eletrónico: geral@cm-loule.pt\n\n28 - IDENTIFICAÇÃO DO(S) AUTOR(ES) DE ANÚNCIO\nNome: Vítor Manuel Gonçalves Aleixo\nCargo: Presidente da Câmara Municipal\n419517131",
    "nipc": "502098139",
    "distrito": "Faro",
    "concelho": "Loulé",
    "freguesia": "Todas",
    "site": "www.cm-loule.pt",
    "email": "aprovisionamento@cm-loule.pt",
    "designacao_contrato": "CONTRATAÇÃO DA AQUISIÇÃO DE CADERNOS DE ATIVIDADES – ANO LETIVO 2025/2026 (2.º, 6.º e 11.º ANO)",
    "descricao": "CONTRATAÇÃO DA AQUISIÇÃO DE CADERNOS DE ATIVIDADES – ANO LETIVO 2025/2026 (2.º, 6.º e 11.º ANO)",
    "preco_base": "149.000,00 EUR",
    "prazo_execucao": "10 DIAS",
    "prazo_apresentacao_propostas": "29-09-2025 18:00",
    "fundos_eu": "Não",
    "plataforma_eletronica": "VORTAL",
    "url_procedimento": "https://community.vortal.biz/public/",
    "autor_nome": "Vítor Manuel Gonçalves Aleixo",
    "autor_cargo": "Presidente da Câmara Municipal"
  },
  {
    "numero_procedimento": "N/A",
    "entidade": "AnÃºncio de procedimento  n.Âº 24139/2025  -  DiÃ¡rio da RepÃºblica n.Âº 176/2025, SÃ©rie II de 2025-09-12",
    "link": "https://diariodarepublica.pt/dr/detalhe/contrato-publico/24139-935098469"
  },
  {
    "numero_procedimento": "N/A",
    "entidade": "AnÃºncio de procedimento  n.Âº 24140/2025  -  DiÃ¡rio da RepÃºblica n.Âº 176/2025, SÃ©rie II de 2025-09-12",
    "link": "https://diariodarepublica.pt/dr/detalhe/contrato-publico/24140-935098470"
  },
  {
    "numero_procedimento": "N/A",
    "entidade": "AnÃºncio de procedimento  n.Âº 24142/2025  -  DiÃ¡rio da RepÃºblica n.Âº 176/2025, SÃ©rie II de 2025-09-12",
    "link": "https://diariodarepublica.pt/dr/detalhe/contrato-publico/24142-935098471"
  }
]