[
  {
    "numero_procedimento": "N/A",
    "entidade": "Município de Santo Tirso",
    "link": "https://diariodarepublica.pt/dr/detalhe/contrato-publico/21746-928803707",
    "detalhes_completos": "Alteração do Anúncio de procedimento n.º 20389/2025, de 2025-07-30, com o ID 419369697\n\n1 - IDENTIFICAÇÃO E CONTACTOS DA ENTIDADE ADJUDICANTE\nDesignação da entidade adjudicante: Município de Santo Tirso\nNIPC: 501306870\nServiço/Órgão/Pessoa de contacto: Serviço de Compras\nEndereço: Praça 25 de Abril\nCódigo postal: 4780-373\nLocalidade: Área Metropolitana do Porto\nPaís: Portugal\nNUT III: PT11A\nDistrito: Porto\nConcelho: Santo Tirso\nFreguesia: União das Freguesias de Santo Tirso, Couto (Santa Cristina e São Miguel) e Burgães\nTelefone: 252830400\nFax: 252856534\nEndereço da Entidade (URL): www.cm-stirso.pt\nEndereço Eletrónico: santotirso@cm-stirso.pt\neDelivery Gateway (URL): https://community.vortal.biz/public/\nFunção da Organização: Adquirente\nNorma jurídica da Entidade Adjudicante: Autoridade local\nÁrea de atividade da Autoridade Adjudicante: Serviços públicos das administrações públicas\n\n2 - JORNAL OFICIAL DA UNIÃO EUROPEIA\nO procedimento a que este anúncio diz respeito também é publicitado no Jornal Oficial da União Europeia? Não\n\n3 - AVISO\nModelo de Anúncio: Concurso público\nData de Envio do Anúncio: 12-08-2025\n\n5 - PROCESSO\nTipo de Procedimento: Concurso público\nPreço base do procedimento: Sim\nValor do preço base do procedimento: 47.000,00 EUR\nProcedimento com lotes? Não\n\n6 - OBJETO DO CONTRATO\nNúmero de referência interna: 697/CPN/S/2025\nDesignação do contrato: Aquisição de serviços para a Elaboração dos Projetos de Especialidades para a Requalificação da Rua Silva Araújo – 2.ª Fase – Vila das Aves\nDescrição: Aquisição de serviços para a Elaboração dos Projetos de Especialidades para a requalificação da Rua Silva Araújo – 2.ª Fase – Vila das Aves\nTipo de Contrato Principal: Aquisição de Serviços\nTipo de Contrato: Aquisição de Serviços\nClassificação CPV (Vocabulário Comum para os Contratos Públicos)\nObjeto principal\nVocabulário Principal: 71330000\nPreço base s/IVA: 47.000,00 EUR\n\n7 - INDICAÇÕES ADICIONAIS\nO contrato envolve aquisição conjunta (satisfação de várias entidades)? Não\nO contrato é adjudicado por uma central de compras? Não\n\n8 - TÉCNICAS\nO concurso destina-se à celebração de um acordo-quadro? Inexistência de acordo-quadro\nÉ utilizado um leilão eletrónico? Não\nÉ adotada uma fase de negociação? Não\nSistema de Aquisição Dinâmico: Inexistência de sistema de aquisição dinâmico\n\n9 - LOCAL DA EXECUÇÃO DO CONTRATO\nLOCAL DA EXECUÇÃO DO CONTRATO (PROCEDIMENTO)\nPaís: Portugal\nNUT III: PT11A\nLocalidade: Área Metropolitana do Porto\nDistrito: Porto\nConcelho: Santo Tirso\nFreguesia: União das Freguesias de Santo Tirso, Couto (Santa Cristina e São Miguel) e Burgães\n\n10 - PRAZO DE EXECUÇÃO DO CONTRATO\nPrazo de execução do contrato: 100 DIAS\nPrevisão de renovações: Não\n\n11 - FUNDOS EU\nTêm fundos EU? Não\n\n12 - DOCUMENTOS DE HABILITAÇÃO\nHabilitação para o exercício da atividade profissional: Não\n\n13 - CONDIÇÕES DE APRESENTAÇÃO\nPlataforma eletrónica utilizada pela entidade adjudicante: VORTAL\nURL para Apresentação: https://community.vortal.biz/public/\nAdmissibilidade da apresentação de propostas variantes: Não autorizado\nPrazo para apresentação das propostas: 18-08-2025 17:30\nPrazo durante o qual os concorrentes são obrigados a manter as respetivas propostas: 120 dias a contar do termo do prazo para a apresentação das propostas\nApresentação de Catálogo Eletrónico: Permitido\nIndicação de Subcontratação na Proposta: Inexistência de indicação de subcontratação\n\n14 - PRESTAÇÃO DE CAUÇÃO\nPrestação de caução: Não\n\n15 - FORNECIMENTO DAS PEÇAS DO CONCURSO, APRESENTAÇÃO DE PEDIDOS DE PARTICIPAÇÃO E APRESENTAÇÃO DAS PROPOSTAS\nLink para acesso às peças do concurso (URL): https://community.vortal.biz/Public/public-tender-documents/V2NLdUlXZGVRL2szYU9IVmFqRDNpbVBTOFloUXAvWjROdDZBU3FHbnp6bW5HZ0N5b25UU3BkdG80N3ZuQmpxVFhUakJta25yZ0JPVWRrck9TVjM1UkE9PUImbjB5\n\n20 - OUTROS REQUISITOS\nInformação sobre contratos reservados. Aplica-se a contratos reservados (54º-A)? Não\n\n21 - CRITÉRIO DE ADJUDICAÇÃO\nMultifator: Não\nMonofator:\nNome: Preço\n\n24 - CONDIÇÕES DO CONTRATO\nFaturação Eletrónica: Permitido\nObrigação de Subcontratação:\nCódigo da Obrigação de Subcontratação: Não é aplicável nenhuma obrigação de subcontratação.\n\n25 - COMPRA PÚBLICA ESTRATÉGICA\nCompra Pública Estratégica: Inexistência de contratação pública estratégica\n\n26 - INFORMAÇÕES ADICIONAIS\nContrato adequado para PME: Sim\nCobertura ACP (Acordo dos Contratos Públicos da Organização Mundial do Comércio): Não\n\n27 - IDENTIFICAÇÃO E CONTACTOS DO ÓRGÃO DE RECURSOS ADMINISTRATIVOS\nDesignação: Município de Santo Tirso\nEndereço: Praça 25 de Abril\nCódigo postal: 4780-373\nLocalidade: Santo Tirso\nTelefone: +351 252830400\nFax: +351 252856534\nEndereço eletrónico: santotirso@cm-stirso.pt\n\n28 - IDENTIFICAÇÃO DO(S) AUTOR(ES) DE ANÚNCIO\nNome: Alberto Costa\nCargo: Presidente da Câmara Municipal\n\n29 - ALTERAÇÃO\nMotivo da Alteração: Correção pelo adquirente\nIdentificador da Versão do Anúncio a Alterar: 7a18c916-0330-4b78-a753-893940b4e302-01\nIdentificador das Secções Alteradas do Anúncio Anterior: Acesso às peças do concurso, pedidos de participação e apresentação das propostas\nDescrição das Alterações: prorrogação prazo de entrega de propostas\nAlteração dos Documentos do Concurso: Não\n419429247",
    "nipc": "501306870",
    "distrito": "Porto",
    "concelho": "Santo Tirso",
    "freguesia": "União das Freguesias de Santo Tirso, Couto (Santa Cristina e São Miguel) e Burgães",
    "site": "www.cm-stirso.pt",
    "email": "santotirso@cm-stirso.pt",
    "designacao_contrato": "Aquisição de serviços para a Elaboração dos Projetos de Especialidades para a Requalificação da Rua Silva Araújo – 2.ª Fase – Vila das Aves",
    "descricao": "Aquisição de serviços para a Elaboração dos Projetos de Especialidades para a requalificação da Rua Silva Araújo – 2.ª Fase – Vila das Aves",
    "preco_base": "47.000,00 EUR",
    "prazo_execucao": "100 DIAS",
    "prazo_apresentacao_propostas": "18-08-2025 17:30",
    "fundos_eu": "Não",
    "plataforma_eletronica": "VORTAL",
    "url_procedimento": "https://community.vortal.biz/public/",
    "autor_nome": "Alberto Costa",
    "autor_cargo": "Presidente da Câmara Municipal"
  },
  {
    "numero_procedimento": "N/A",
    "entidade": "Património Cultural, IP",
    "link": "https://diariodarepublica.pt/dr/detalhe/contrato-publico/21748-928803708",
    "detalhes_completos": "Alteração do Anúncio de procedimento n.º 20664/2025, de 2025-08-01, com o ID 419384308\n\n1 - IDENTIFICAÇÃO E CONTACTOS DA ENTIDADE ADJUDICANTE\nDesignação da entidade adjudicante: Património Cultural, IP\nNIPC: 517842920\nServiço/Órgão/Pessoa de contacto: Departamento de Projetos e Obras\nEndereço: Palacete Vilar de Allen, Rua António Cardoso, 175\nCódigo postal: 4150-081\nLocalidade: Porto\nPaís: Portugal\nNUT III: PT11A\nDistrito: Porto\nConcelho: Porto\nFreguesia: Todas\nTelefone: 213614200\nFax: 213614200\nEndereço da Entidade (URL): www.patrimoniocultural.gov.pt\nEndereço Eletrónico: dpo@patrimoniocultural.gov.pt\neDelivery Gateway (URL): https://www.acingov.pt\nFunção da Organização: Adquirente\nNorma jurídica da Entidade Adjudicante: Organismo de direito público\nÁrea de atividade da Autoridade Adjudicante: Serviços públicos das administrações públicas\n\n2 - JORNAL OFICIAL DA UNIÃO EUROPEIA\nO procedimento a que este anúncio diz respeito também é publicitado no Jornal Oficial da União Europeia? Não\n\n3 - AVISO\nModelo de Anúncio: Concurso público\nData de Envio do Anúncio: 12-08-2025\n\n5 - PROCESSO\nTipo de Procedimento: Concurso público\nPreço base do procedimento: Sim\nValor do preço base do procedimento: 1.049.500,00 EUR\nProcedimento com lotes? Não\n\n6 - OBJETO DO CONTRATO\nNúmero de referência interna: CP/29/2025\nDesignação do contrato: ID 6925 PRR - Forte de Sacavém -Recuperação geral das instalações técnicas\nDescrição: ID 6925 PRR - Forte de Sacavém -Recuperação geral das instalações técnicas\n\nTipo de Contrato Principal: Empreitada de Obras Públicas\nTipo de Contrato: Empreitada de Obras Públicas\nClassificação CPV (Vocabulário Comum para os Contratos Públicos)\nObjeto principal\nVocabulário Principal: 45331000\nPreço base s/IVA: 1.049.500,00 EUR\n\n7 - INDICAÇÕES ADICIONAIS\nO contrato envolve aquisição conjunta (satisfação de várias entidades)? Não\nO contrato é adjudicado por uma central de compras? Não\n\n8 - TÉCNICAS\nO concurso destina-se à celebração de um acordo-quadro? Inexistência de acordo-quadro\nÉ utilizado um leilão eletrónico? Não\nÉ adotada uma fase de negociação? Não\nSistema de Aquisição Dinâmico: Inexistência de sistema de aquisição dinâmico\n\n9 - LOCAL DA EXECUÇÃO DO CONTRATO\nLOCAL DA EXECUÇÃO DO CONTRATO (PROCEDIMENTO)\nPaís: Portugal\nNUT III: PT170\nLocalidade: União das Freguesias de Sacavém e Prior Velho\nDistrito: Lisboa\nConcelho: Loures\nFreguesia: União das Freguesias de Sacavém e Prior Velho\n\n10 - PRAZO DE EXECUÇÃO DO CONTRATO\nPrazo de execução do contrato: 270 DIAS\nPrevisão de renovações: Não\n\n11 - FUNDOS EU\nTêm fundos EU? Sim\n\n12 - DOCUMENTOS DE HABILITAÇÃO\nHabilitação para o exercício da atividade profissional: Sim\nTipo: Alvará\nDescrição: - 1.ª Subcategoria (Instalações elétricas de utilização de baixa tensão com potência até 50 kVA) da 4ª categoria (instalações elétricas e mecânicas), em classe correspondente ao valor da parte dos trabalhos a que respeita (instalações elétricas);\n- 9.ª subcategoria (Infraestruturas de telecomunicações) da 4ª categoria (instalações elétricas e mecânicas), em classe correspondente ao valor da parte dos trabalhos a que respeita (instalações de telecomunicações);\n- 12.ª subcategoria (Aquecimento, ventilação, ar condicionado e refrigeração) da 4ª categoria (instalações elétricas e mecânicas), em classe correspondente ao valor da parte dos trabalhos a que respeita (instalações de ar condicionado).\n\n13 - CONDIÇÕES DE APRESENTAÇÃO\nPlataforma eletrónica utilizada pela entidade adjudicante: ACIN\nURL para Apresentação: https://www.acingov.pt\nAdmissibilidade da apresentação de propostas variantes: Não autorizado\nPrazo para apresentação das propostas: 22-08-2025 23:59\nPrazo durante o qual os concorrentes são obrigados a manter as respetivas propostas: 180 dias a contar do termo do prazo para a apresentação das propostas\nIndicação de Subcontratação na Proposta: Inexistência de indicação de subcontratação\n\n14 - PRESTAÇÃO DE CAUÇÃO\nPrestação de caução: Sim\nPercentagem: 5%\nDescrição da Garantia Exigida: O valor da caução é de 5.00% do preço contratual.\n\n15 - FORNECIMENTO DAS PEÇAS DO CONCURSO, APRESENTAÇÃO DE PEDIDOS DE PARTICIPAÇÃO E APRESENTAÇÃO DAS PROPOSTAS\nLink para acesso às peças do concurso (URL): https://www.acingov.pt/acingovprod/2/zonaPublica/zona_publica_c/donwloadProcedurePiece/OTMwNTM4\n\n20 - OUTROS REQUISITOS\nInformação sobre contratos reservados. Aplica-se a contratos reservados (54º-A)? Não\n\n21 - CRITÉRIO DE ADJUDICAÇÃO\nMultifator: Não\nMonofator:\nNome: Preço\n\n24 - CONDIÇÕES DO CONTRATO\nFaturação Eletrónica: Permitido\nObrigação de Subcontratação:\nCódigo da Obrigação de Subcontratação: Não é aplicável nenhuma obrigação de subcontratação.\n\n25 - COMPRA PÚBLICA ESTRATÉGICA\nCompra Pública Estratégica: Inexistência de contratação pública estratégica\n\n26 - INFORMAÇÕES ADICIONAIS\nContrato adequado para PME: Sim\nCobertura ACP (Acordo dos Contratos Públicos da Organização Mundial do Comércio): Não\n\n27 - IDENTIFICAÇÃO E CONTACTOS DO ÓRGÃO DE RECURSOS ADMINISTRATIVOS\nDesignação: Presidente do Concelho Diretivo\nEndereço: Palácio Nacional da Ajuda, Ala Norte\nCódigo postal: 1349-021\nLocalidade: Lisboa\nTelefone: 213614200\nFax: \nEndereço eletrónico: joao.soalheiro@patrimoniocultural.gov.pt\n\n28 - IDENTIFICAÇÃO DO(S) AUTOR(ES) DE ANÚNCIO\nNome: Raquel Barroso\nCargo: Assistente Técnico\n\n29 - ALTERAÇÃO\nMotivo da Alteração: Informações atualizadas\nIdentificador da Versão do Anúncio a Alterar: 7d19362c-2544-498e-be22-910d3d7df1d4-01\nIdentificador das Secções Alteradas do Anúncio Anterior: Condições de Apresentação\nDescrição das Alterações: Prorrogação de prazo até 22-08-2025\nAlteração dos Documentos do Concurso: Não\n419430348",
    "nipc": "517842920",
    "distrito": "Porto",
    "concelho": "Porto",
    "freguesia": "Todas",
    "site": "www.patrimoniocultural.gov.pt",
    "email": "dpo@patrimoniocultural.gov.pt",
    "designacao_contrato": "ID 6925 PRR - Forte de Sacavém -Recuperação geral das instalações técnicas",
    "descricao": "ID 6925 PRR - Forte de Sacavém -Recuperação geral das instalações técnicas",
    "preco_base": "1.049.500,00 EUR",
    "prazo_execucao": "270 DIAS",
    "prazo_apresentacao_propostas": "22-08-2025 23:59",
    "fundos_eu": "Sim",
    "plataforma_eletronica": "ACIN",
    "url_procedimento": "https://www.acingov.pt",
    "autor_nome": "Raquel Barroso",
    "autor_cargo": "Assistente Técnico"
  },
  {
    "numero_procedimento": "N/A",
    "entidade": "Câmara Municipal de Matosinhos",
    "link": "https://diariodarepublica.pt/dr/detalhe/contrato-publico/21749-928803709",
    "detalhes_completos": "1 - IDENTIFICAÇÃO E CONTACTOS DA ENTIDADE ADJUDICANTE\nDesignação da entidade adjudicante: Câmara Municipal de Matosinhos\nNIPC: 501305912\nServiço/Órgão/Pessoa de contacto: Divisão Contratação Pública\nEndereço: Av. D. Afonso Henriques\nCódigo postal: 4454-510\nLocalidade: Matosinhos\nPaís: Portugal\nNUT III: PT11A\nDistrito: Porto\nConcelho: Matosinhos\nFreguesia: Todas\nTelefone: 229390900\nFax: 229351645\nEndereço da Entidade (URL): http://www.cm-matosinhos.pt\nEndereço Eletrónico: contratacaopublica@cm-matosinhos.pt\neDelivery Gateway (URL): https://www.acingov.pt\nFunção da Organização: Adquirente\nSubfunção da Organização: Organização que recebe as propostas\nNorma jurídica da Entidade Adjudicante: Organismo de direito público\nÁrea de atividade da Autoridade Adjudicante: Serviços públicos das administrações públicas\n\n2 - JORNAL OFICIAL DA UNIÃO EUROPEIA\nO procedimento a que este anúncio diz respeito também é publicitado no Jornal Oficial da União Europeia? Não\n\n3 - AVISO\nModelo de Anúncio: Concurso público\nData de Envio do Anúncio: 12-08-2025\n\n5 - PROCESSO\nTipo de Procedimento: Concurso público\nPreço base do procedimento: Sim\nValor do preço base do procedimento: 91.166,00 EUR\nProcedimento com lotes? Não\n\n6 - OBJETO DO CONTRATO\nNúmero de referência interna: CP/2025/24843\nDesignação do contrato: DESPORTO NA CIDADE - CONSTRUÇÃO DE CAMPO DE ANDEBOL DE PRAIA - PARQUE FLORBELA ESPANCA\nDescrição: DESPORTO NA CIDADE - CONSTRUÇÃO DE CAMPO DE ANDEBOL DE PRAIA - PARQUE FLORBELA ESPANCA\nTipo de Contrato Principal: Empreitada de Obras Públicas\nTipo de Contrato: Empreitada de Obras Públicas\nClassificação CPV (Vocabulário Comum para os Contratos Públicos)\nObjeto principal\nVocabulário Principal: 45212221\nPreço base s/IVA: 91.166,00 EUR\n\n7 - INDICAÇÕES ADICIONAIS\nO contrato envolve aquisição conjunta (satisfação de várias entidades)? Não\nO contrato é adjudicado por uma central de compras? Não\n\n8 - TÉCNICAS\nO concurso destina-se à celebração de um acordo-quadro? Inexistência de acordo-quadro\nÉ utilizado um leilão eletrónico? Não\nÉ adotada uma fase de negociação? Não\nSistema de Aquisição Dinâmico: Inexistência de sistema de aquisição dinâmico\n\n9 - LOCAL DA EXECUÇÃO DO CONTRATO\nLOCAL DA EXECUÇÃO DO CONTRATO (PROCEDIMENTO)\nPaís: Portugal\nNUT III: PT11A\nLocalidade: Matosinhos\nDistrito: Porto\nConcelho: Matosinhos\nFreguesia: Todas\n\n10 - PRAZO DE EXECUÇÃO DO CONTRATO\nPrazo de execução do contrato: 2 MESES\nPrevisão de renovações: Não\n\n11 - FUNDOS EU\nTêm fundos EU? Não\n\n12 - DOCUMENTOS DE HABILITAÇÃO\nHabilitação para o exercício da atividade profissional: Sim\nTipo: Alvará\nDescrição: - Categoria: 2ª Vias de comunicação, obras de urbanização e outras infraestruturas.   \n- Subcategoria: 1ª Vias de circulação rodoviária e aeródromos. \n\n13 - CONDIÇÕES DE APRESENTAÇÃO\nPlataforma eletrónica utilizada pela entidade adjudicante: ACIN\nURL para Apresentação: https://www.acingov.pt\nAdmissibilidade da apresentação de propostas variantes: Não autorizado\nPrazo para apresentação das propostas: 25-08-2025 23:59\nPrazo durante o qual os concorrentes são obrigados a manter as respetivas propostas: 66 dias a contar do termo do prazo para a apresentação das propostas\nIndicação de Subcontratação na Proposta: Inexistência de indicação de subcontratação\n\n14 - PRESTAÇÃO DE CAUÇÃO\nPrestação de caução: Não\n\n15 - FORNECIMENTO DAS PEÇAS DO CONCURSO, APRESENTAÇÃO DE PEDIDOS DE PARTICIPAÇÃO E APRESENTAÇÃO DAS PROPOSTAS\nLink para acesso às peças do concurso (URL): https://www.acingov.pt/acingovprod/2/zonaPublica/zona_publica_c/donwloadProcedurePiece/OTMyMzIy\n\n20 - OUTROS REQUISITOS\nInformação sobre contratos reservados. Aplica-se a contratos reservados (54º-A)? Não\n\n21 - CRITÉRIO DE ADJUDICAÇÃO\nMultifator: Não\nMonofator:\nNome: Preço\n\n24 - CONDIÇÕES DO CONTRATO\nFaturação Eletrónica: Permitido\nObrigação de Subcontratação:\nCódigo da Obrigação de Subcontratação: Não é aplicável nenhuma obrigação de subcontratação.\n\n25 - COMPRA PÚBLICA ESTRATÉGICA\nCompra Pública Estratégica: Inexistência de contratação pública estratégica\n\n26 - INFORMAÇÕES ADICIONAIS\nContrato adequado para PME: Não\nCobertura ACP (Acordo dos Contratos Públicos da Organização Mundial do Comércio): Não\n\n27 - IDENTIFICAÇÃO E CONTACTOS DO ÓRGÃO DE RECURSOS ADMINISTRATIVOS\nDesignação: Câmara Municipal\nEndereço: Av. D. Afonso Henriques\nCódigo postal: 4454-510\nLocalidade: Matosinhos\nTelefone: 229390900\nFax: \nEndereço eletrónico: contratacaopublica@cm-matosinhos.pt\nPrazo de interposição do recurso: 5 dias\n\n28 - IDENTIFICAÇÃO DO(S) AUTOR(ES) DE ANÚNCIO\nNome: Dra Luísa Salgueiro\nCargo: Presidente da Câmara\n419422159",
    "nipc": "501305912",
    "distrito": "Porto",
    "concelho": "Matosinhos",
    "freguesia": "Todas",
    "site": "http://www.cm-matosinhos.pt",
    "email": "contratacaopublica@cm-matosinhos.pt",
    "designacao_contrato": "DESPORTO NA CIDADE - CONSTRUÇÃO DE CAMPO DE ANDEBOL DE PRAIA - PARQUE FLORBELA ESPANCA",
    "descricao": "DESPORTO NA CIDADE - CONSTRUÇÃO DE CAMPO DE ANDEBOL DE PRAIA - PARQUE FLORBELA ESPANCA",
    "preco_base": "91.166,00 EUR",
    "prazo_execucao": "2 MESES",
    "prazo_apresentacao_propostas": "25-08-2025 23:59",
    "fundos_eu": "Não",
    "plataforma_eletronica": "ACIN",
    "url_procedimento": "https://www.acingov.pt",
    "autor_nome": "Dra Luísa Salgueiro",
    "autor_cargo": "Presidente da Câmara"
  },
  {
    "numero_procedimento": "N/A",
    "entidade": "Município do Porto",
    "link": "https://diariodarepublica.pt/dr/detalhe/contrato-publico/21750-928803710",
    "detalhes_completos": "Alteração do Anúncio de procedimento n.º 20288/2025, de 2025-07-29, com o ID 419366123\n\n1 - IDENTIFICAÇÃO E CONTACTOS DA ENTIDADE ADJUDICANTE\nDesignação da entidade adjudicante: Município do Porto\nNIPC: 501306099\nServiço/Órgão/Pessoa de contacto: Divisão Municipal de Compras Gerais\nEndereço: Rua do Bolhão, 162, 6.º piso\nCódigo postal: 4000-111\nLocalidade: Porto\nPaís: Portugal\nNUT III: PT11A\nDistrito: Porto\nConcelho: Porto\nFreguesia: União das Freguesias de Cedofeita, Santo Ildefonso, Sé, Miragaia, São Nicolau e Vitória\nTelefone: 222097216\nFax: 222097296\nEndereço da Entidade (URL): http://www.cm-porto.pt\nEndereço Eletrónico: suportepce@cm-porto.pt\neDelivery Gateway (URL): https://www.acingov.pt\nFunção da Organização: Adquirente\nNorma jurídica da Entidade Adjudicante: Autoridade local\nÁrea de atividade da Autoridade Adjudicante: Serviços públicos das administrações públicas\n\n2 - JORNAL OFICIAL DA UNIÃO EUROPEIA\nO procedimento a que este anúncio diz respeito também é publicitado no Jornal Oficial da União Europeia? Não\n\n3 - AVISO\nModelo de Anúncio: Concurso público\nData de Envio do Anúncio: 12-08-2025\n\n5 - PROCESSO\nTipo de Procedimento: Concurso público\nPreço base do procedimento: Sim\nValor do preço base do procedimento: 437.532,50 EUR\nProcedimento com lotes? Não\n\n6 - OBJETO DO CONTRATO\nNúmero de referência interna: CPAQ/2/2025/DMCG\nDesignação do contrato: Reparação de pavimentos a saibro e/ou gravilha em Parques Urbanos e Jardins\nDescrição: Reparação de pavimentos a saibro e/ou gravilha em parques urbanos e jardins\nTipo de Contrato Principal: Empreitada de Obras Públicas\nTipo de Contrato: Empreitada de Obras Públicas\nClassificação CPV (Vocabulário Comum para os Contratos Públicos)\nObjeto principal\nVocabulário Principal: 45233200\nPreço base s/IVA: 437.532,50 EUR\n\n7 - INDICAÇÕES ADICIONAIS\nO contrato envolve aquisição conjunta (satisfação de várias entidades)? Não\nO contrato é adjudicado por uma central de compras? Não\n\n8 - TÉCNICAS\nO concurso destina-se à celebração de um acordo-quadro? Acordo-quadro, sem reabertura de concurso\nModalidade: Com uma entidade\nPrazo de vigência: 24 meses\nValor estimado: Sim\nPara Acordo-Quadro — valor total máximo estimado para toda a duração do Acordo-Quadro: 437.532,50 EUR\nÉ utilizado um leilão eletrónico? Não\nÉ adotada uma fase de negociação? Não\nSistema de Aquisição Dinâmico: Inexistência de sistema de aquisição dinâmico\n\n9 - LOCAL DA EXECUÇÃO DO CONTRATO\nLOCAL DA EXECUÇÃO DO CONTRATO (PROCEDIMENTO)\nPaís: Portugal\nNUT III: PT11A\nLocalidade: Porto\nDistrito: Porto\nConcelho: Porto\nFreguesia: Todas\n\n10 - PRAZO DE EXECUÇÃO DO CONTRATO\nPrazo de execução do contrato: 24 MESES\nPrevisão de renovações: Não\n\n11 - FUNDOS EU\nTêm fundos EU? Não\n\n12 - DOCUMENTOS DE HABILITAÇÃO\nHabilitação para o exercício da atividade profissional: Sim\nTipo: Alvará\nDescrição: 9.a subcategoria da 2.a categoria\n\n13 - CONDIÇÕES DE APRESENTAÇÃO\nPlataforma eletrónica utilizada pela entidade adjudicante: ACIN\nURL para Apresentação: https://www.acingov.pt\nAdmissibilidade da apresentação de propostas variantes: Não autorizado\nPrazo para apresentação das propostas: 27-08-2025 17:00\nPrazo durante o qual os concorrentes são obrigados a manter as respetivas propostas: 90 dias a contar do termo do prazo para a apresentação das propostas\nIndicação de Subcontratação na Proposta: Inexistência de indicação de subcontratação\n\n14 - PRESTAÇÃO DE CAUÇÃO\nPrestação de caução: Não\n\n15 - FORNECIMENTO DAS PEÇAS DO CONCURSO, APRESENTAÇÃO DE PEDIDOS DE PARTICIPAÇÃO E APRESENTAÇÃO DAS PROPOSTAS\nLink para acesso às peças do concurso (URL): https://www.acingov.pt/acingovprod/2/zonaPublica/zona_publica_c/donwloadProcedurePiece/ODkyNzAx\n\n20 - OUTROS REQUISITOS\nInformação sobre contratos reservados. Aplica-se a contratos reservados (54º-A)? Não\n\n21 - CRITÉRIO DE ADJUDICAÇÃO\nMultifator: Não\nMonofator:\nNome: Preço\n\n24 - CONDIÇÕES DO CONTRATO\nFaturação Eletrónica: Necessário\nObrigação de Subcontratação:\nCódigo da Obrigação de Subcontratação: Não é aplicável nenhuma obrigação de subcontratação.\n\n25 - COMPRA PÚBLICA ESTRATÉGICA\nCompra Pública Estratégica: Redução dos impactos ambientais\nDescrição do Processo de Adjudicação Estratégico: Recurso a materiais de elevada durabilidade - diminuição da utilização de novos recursos para reparar os elementos em operação.\nCritérios de contratos Públicos Ecológicos: Critérios de contratação pública ecológica nacional\nCategorias da estratégia nacional: Outros\nOutra categoria (Descrição): Recurso a materiais de elevada durabilidade - diminuição da utilização de novos recursos para reparar os elementos em operação.\nDiretiva Veículos Não Poluentes: Não\nCritério de Acessibilidade: Os critérios de acessibilidade para as pessoas com deficiência não estão incluídos porque o contrato não se destina a pessoas singulares\n\n26 - INFORMAÇÕES ADICIONAIS\nContrato adequado para PME: Sim\nCobertura ACP (Acordo dos Contratos Públicos da Organização Mundial do Comércio): Não\n\n27 - IDENTIFICAÇÃO E CONTACTOS DO ÓRGÃO DE RECURSOS ADMINISTRATIVOS\nDesignação: Divisão Municipal de Compras Gerais\nEndereço: Rua do Bolhão, 162, 6.º piso\nCódigo postal: 4000-111\nLocalidade: Porto\nTelefone: 222097216\nFax: 222097296\nEndereço eletrónico: dmcompras@cm-porto.pt\n\n28 - IDENTIFICAÇÃO DO(S) AUTOR(ES) DE ANÚNCIO\nNome: Vera Sampaio\nCargo: Chefe Divisão Compras Gerais\n\n29 - ALTERAÇÃO\nMotivo da Alteração: Informações atualizadas\nIdentificador da Versão do Anúncio a Alterar: f3ae1734-6a03-48bd-9512-3601df7094e9-01\nIdentificador das Secções Alteradas do Anúncio Anterior: Informações adicionais; Identificação do(s) autor(es) do anúncio\nDescrição das Alterações: Modificação do prazo para a apresentação de propostas Atualização do(s) autor(es) do anúncio\nAlteração dos Documentos do Concurso: Sim\nData de alteração dos documentos do concurso: 12-08-2025\n419429603",
    "nipc": "501306099",
    "distrito": "Porto",
    "concelho": "Porto",
    "freguesia": "União das Freguesias de Cedofeita, Santo Ildefonso, Sé, Miragaia, São Nicolau e Vitória",
    "site": "http://www.cm-porto.pt",
    "email": "suportepce@cm-porto.pt",
    "designacao_contrato": "Reparação de pavimentos a saibro e/ou gravilha em Parques Urbanos e Jardins",
    "descricao": "Reparação de pavimentos a saibro e/ou gravilha em parques urbanos e jardins",
    "preco_base": "437.532,50 EUR",
    "prazo_execucao": "24 MESES",
    "prazo_apresentacao_propostas": "27-08-2025 17:00",
    "fundos_eu": "Não",
    "plataforma_eletronica": "ACIN",
    "url_procedimento": "https://www.acingov.pt",
    "autor_nome": "Vera Sampaio",
    "autor_cargo": "Chefe Divisão Compras Gerais"
  },
  {
    "numero_procedimento": "N/A",
    "entidade": "Município de Loures",
    "link": "https://diariodarepublica.pt/dr/detalhe/contrato-publico/21751-928803711",
    "detalhes_completos": "1 - IDENTIFICAÇÃO E CONTACTOS DA ENTIDADE ADJUDICANTE\nDesignação da entidade adjudicante: Município de Loures\nNIPC: 501294996\nServiço/Órgão/Pessoa de contacto: DOM/DCAD\nEndereço: Praça da Liberdade\nCódigo postal: 2674-501\nLocalidade: Lisboa\nPaís: Portugal\nNUT III: PT170\nDistrito: Lisboa\nConcelho: Loures\nFreguesia: Freguesia de Loures\nTelefone: 211150100\nFax: 211151704\nEndereço da Entidade (URL): www.cm-loures.pt\nEndereço Eletrónico: geral@cm-loures.pt\neDelivery Gateway (URL): https://community.vortal.biz/public/\nFunção da Organização: Adquirente\nNorma jurídica da Entidade Adjudicante: Autoridade local\nÁrea de atividade da Autoridade Adjudicante: Serviços públicos das administrações públicas\n\n2 - JORNAL OFICIAL DA UNIÃO EUROPEIA\nO procedimento a que este anúncio diz respeito também é publicitado no Jornal Oficial da União Europeia? Não\n\n3 - AVISO\nModelo de Anúncio: Concurso público\nData de Envio do Anúncio: 12-08-2025\n\n5 - PROCESSO\nTipo de Procedimento: Concurso público\nPreço base do procedimento: Sim\nValor do preço base do procedimento: 349.900,00 EUR\nProcedimento com lotes? Não\n\n6 - OBJETO DO CONTRATO\nNúmero de referência interna: 1953/DOM\nDesignação do contrato: Requalificação de Arruamentos no Concelho\nDescrição: Requalificação de Arruamentos no Concelho\nTipo de Contrato Principal: Empreitada de Obras Públicas\nTipo de Contrato: Empreitada de Obras Públicas\nClassificação CPV (Vocabulário Comum para os Contratos Públicos)\nObjeto principal\nVocabulário Principal: 45233200\nPreço base s/IVA: 349.900,00 EUR\n\n7 - INDICAÇÕES ADICIONAIS\nO contrato envolve aquisição conjunta (satisfação de várias entidades)? Não\nO contrato é adjudicado por uma central de compras? Não\n\n8 - TÉCNICAS\nO concurso destina-se à celebração de um acordo-quadro? Inexistência de acordo-quadro\nÉ utilizado um leilão eletrónico? Não\nÉ adotada uma fase de negociação? Não\nSistema de Aquisição Dinâmico: Inexistência de sistema de aquisição dinâmico\n\n9 - LOCAL DA EXECUÇÃO DO CONTRATO\nLOCAL DA EXECUÇÃO DO CONTRATO (PROCEDIMENTO)\nPaís: Portugal\nNUT III: PT170\nLocalidade: Lisboa\nDistrito: Lisboa\nConcelho: Loures\nFreguesia: Todas\n\n10 - PRAZO DE EXECUÇÃO DO CONTRATO\nPrazo de execução do contrato: 90 DIAS\nPrevisão de renovações: Não\n\n11 - FUNDOS EU\nTêm fundos EU? Não\n\n12 - DOCUMENTOS DE HABILITAÇÃO\nHabilitação para o exercício da atividade profissional: Sim\nTipo: Alvará\nDescrição: Alvará; 1ª subcategoria da 2ª categoria,  classe que cubra o valor global da proposta\n\n13 - CONDIÇÕES DE APRESENTAÇÃO\nPlataforma eletrónica utilizada pela entidade adjudicante: VORTAL\nURL para Apresentação: https://community.vortal.biz/public/\nAdmissibilidade da apresentação de propostas variantes: Não autorizado\nPrazo para apresentação das propostas: 28-08-2025 23:59\nPrazo durante o qual os concorrentes são obrigados a manter as respetivas propostas: 66 dias a contar do termo do prazo para a apresentação das propostas\nIndicação de Subcontratação na Proposta: Inexistência de indicação de subcontratação\n\n14 - PRESTAÇÃO DE CAUÇÃO\nPrestação de caução: Não\n\n15 - FORNECIMENTO DAS PEÇAS DO CONCURSO, APRESENTAÇÃO DE PEDIDOS DE PARTICIPAÇÃO E APRESENTAÇÃO DAS PROPOSTAS\nLink para acesso às peças do concurso (URL): https://community.vortal.biz/Public/public-tender-documents/TG9YOUF5TVZQTndwVU1BMkxFdFRxUGdTNy9UTHF6SUtCKzFQSklveUh1cDA0SjlVZ1dVcUZQQXp5M0pyZjJRS0tlM2FMeElHVmVCWHJXQkhlVFBaMFE9PTJ2I0xZ\n\n20 - OUTROS REQUISITOS\nInformação sobre contratos reservados. Aplica-se a contratos reservados (54º-A)? Não\n\n21 - CRITÉRIO DE ADJUDICAÇÃO\nMultifator: Não\nMonofator:\nNome: Preço\n\n24 - CONDIÇÕES DO CONTRATO\nFaturação Eletrónica: Permitido\nObrigação de Subcontratação:\nCódigo da Obrigação de Subcontratação: Não é aplicável nenhuma obrigação de subcontratação.\n\n25 - COMPRA PÚBLICA ESTRATÉGICA\nCompra Pública Estratégica: Redução dos impactos ambientais\nDescrição do Processo de Adjudicação Estratégico: Este processo tem como base a Estratégia de Compras Publicas Sustentáveis, adotada pelo Município de Loures em 20 de setembro de 2023, publicada no site do Município.\nCritérios de contratos Públicos Ecológicos: Critérios de contratação pública ecológica nacional\nCategorias da estratégia nacional: Outros\nOutra categoria (Descrição): De acordo com Código de Conduta de empreitadas, PPGRCD e PSS\nDiretiva Veículos Não Poluentes: Não\nCritério de Acessibilidade: Os critérios de acessibilidade para as pessoas com deficiência não estão incluídos porque o contrato não se destina a pessoas singulares\n\n26 - INFORMAÇÕES ADICIONAIS\nContrato adequado para PME: Sim\nCobertura ACP (Acordo dos Contratos Públicos da Organização Mundial do Comércio): Não\n\n27 - IDENTIFICAÇÃO E CONTACTOS DO ÓRGÃO DE RECURSOS ADMINISTRATIVOS\nDesignação: Câmara Municipal de Loures\nEndereço: Praça da Liberdade\nCódigo postal: 2674-501\nLocalidade: Loures\nTelefone: +351 211150100\nFax: +351 211151709\nEndereço eletrónico: geral@cm-loures.pt\nPrazo de interposição do recurso: 5 dias\n\n28 - IDENTIFICAÇÃO DO(S) AUTOR(ES) DE ANÚNCIO\nNome: Ricardo Leão\nCargo: Presidente\n419426103",
    "nipc": "501294996",
    "distrito": "Lisboa",
    "concelho": "Loures",
    "freguesia": "Freguesia de Loures",
    "site": "www.cm-loures.pt",
    "email": "geral@cm-loures.pt",
    "designacao_contrato": "Requalificação de Arruamentos no Concelho",
    "descricao": "Requalificação de Arruamentos no Concelho",
    "preco_base": "349.900,00 EUR",
    "prazo_execucao": "90 DIAS",
    "prazo_apresentacao_propostas": "28-08-2025 23:59",
    "fundos_eu": "Não",
    "plataforma_eletronica": "VORTAL",
    "url_procedimento": "https://community.vortal.biz/public/",
    "autor_nome": "Ricardo Leão",
    "autor_cargo": "Presidente"
  },
  {
    "numero_procedimento": "N/A",
    "entidade": "Município de Loures",
    "link": "https://diariodarepublica.pt/dr/detalhe/contrato-publico/21752-928803712",
    "detalhes_completos": "1 - IDENTIFICAÇÃO E CONTACTOS DA ENTIDADE ADJUDICANTE\nDesignação da entidade adjudicante: Município de Loures\nNIPC: 501294996\nServiço/Órgão/Pessoa de contacto: DOM/DIEP\nEndereço: Praça da Liberdade\nCódigo postal: 2674-501\nLocalidade: Lisboa\nPaís: Portugal\nNUT III: PT170\nDistrito: Lisboa\nConcelho: Loures\nFreguesia: Freguesia de Loures\nTelefone: 211150100\nFax: 211151704\nEndereço da Entidade (URL): www.cm-loures.pt\nEndereço Eletrónico: geral@cm-loures.pt\neDelivery Gateway (URL): https://community.vortal.biz/public/\nFunção da Organização: Adquirente\nNorma jurídica da Entidade Adjudicante: Autoridade local\nÁrea de atividade da Autoridade Adjudicante: Serviços públicos das administrações públicas\n\n2 - JORNAL OFICIAL DA UNIÃO EUROPEIA\nO procedimento a que este anúncio diz respeito também é publicitado no Jornal Oficial da União Europeia? Não\n\n3 - AVISO\nModelo de Anúncio: Concurso público\nData de Envio do Anúncio: 12-08-2025\n\n5 - PROCESSO\nTipo de Procedimento: Concurso público\nPreço base do procedimento: Sim\nValor do preço base do procedimento: 198.865,00 EUR\nProcedimento com lotes? Não\n\n6 - OBJETO DO CONTRATO\nNúmero de referência interna: 1915/DOM\nDesignação do contrato: Melhoria das Acessibilidades na Urbanização do Covão e zonas envolventes na freguesia de Loures \nDescrição: Melhoria das Acessibilidades na Urbanização do Covão e zonas envolventes na freguesia de Loures \nTipo de Contrato Principal: Empreitada de Obras Públicas\nTipo de Contrato: Empreitada de Obras Públicas\nClassificação CPV (Vocabulário Comum para os Contratos Públicos)\nObjeto principal\nVocabulário Principal: 45233160\nPreço base s/IVA: 198.865,00 EUR\n\n7 - INDICAÇÕES ADICIONAIS\nO contrato envolve aquisição conjunta (satisfação de várias entidades)? Não\nO contrato é adjudicado por uma central de compras? Não\n\n8 - TÉCNICAS\nO concurso destina-se à celebração de um acordo-quadro? Inexistência de acordo-quadro\nÉ utilizado um leilão eletrónico? Não\nÉ adotada uma fase de negociação? Não\nSistema de Aquisição Dinâmico: Inexistência de sistema de aquisição dinâmico\n\n9 - LOCAL DA EXECUÇÃO DO CONTRATO\nLOCAL DA EXECUÇÃO DO CONTRATO (PROCEDIMENTO)\nPaís: Portugal\nNUT III: PT170\nLocalidade: Lisboa\nDistrito: Lisboa\nConcelho: Loures\nFreguesia: Freguesia de Loures\n\n10 - PRAZO DE EXECUÇÃO DO CONTRATO\nPrazo de execução do contrato: 120 DIAS\nPrevisão de renovações: Não\n\n11 - FUNDOS EU\nTêm fundos EU? Não\n\n12 - DOCUMENTOS DE HABILITAÇÃO\nHabilitação para o exercício da atividade profissional: Sim\nTipo: Alvará\nDescrição: 1.ª subcategoria da 2.ª categoria de alvará, a qual tem de ser de classe que cubra o valor global da proposta\n\n13 - CONDIÇÕES DE APRESENTAÇÃO\nPlataforma eletrónica utilizada pela entidade adjudicante: VORTAL\nURL para Apresentação: https://community.vortal.biz/public/\nAdmissibilidade da apresentação de propostas variantes: Não autorizado\nPrazo para apresentação das propostas: 12-09-2025 17:00\nPrazo durante o qual os concorrentes são obrigados a manter as respetivas propostas: 66 dias a contar do termo do prazo para a apresentação das propostas\nIndicação de Subcontratação na Proposta: Inexistência de indicação de subcontratação\n\n14 - PRESTAÇÃO DE CAUÇÃO\nPrestação de caução: Não\n\n15 - FORNECIMENTO DAS PEÇAS DO CONCURSO, APRESENTAÇÃO DE PEDIDOS DE PARTICIPAÇÃO E APRESENTAÇÃO DAS PROPOSTAS\nLink para acesso às peças do concurso (URL): https://community.vortal.biz/Public/public-tender-documents/STVxVFRZRTArK3FIaW4vWE0zWFdqQmpKWHpZanZhUTZQK3JGTW5XKzAzaEp2NzFOaXZSeElmdEx6ak1hWWlDSVIwZ1AxcU9TdUgySEc4NTV6VEE3c1E9PW1jM2NJ\n\n20 - OUTROS REQUISITOS\nInformação sobre contratos reservados. Aplica-se a contratos reservados (54º-A)? Não\n\n21 - CRITÉRIO DE ADJUDICAÇÃO\nMultifator: Não\nMonofator:\nNome: Preço\n\n24 - CONDIÇÕES DO CONTRATO\nFaturação Eletrónica: Permitido\nObrigação de Subcontratação:\nCódigo da Obrigação de Subcontratação: Não é aplicável nenhuma obrigação de subcontratação.\n\n25 - COMPRA PÚBLICA ESTRATÉGICA\nCompra Pública Estratégica: Redução dos impactos ambientais\nDescrição do Processo de Adjudicação Estratégico: Este processo tem como base a Estratégia de Compras Publicas Sustentáveis, adotada pelo Município de Loures em 20 de setembro de 2023, publicada no site do Município.\nCritérios de contratos Públicos Ecológicos: Critérios de contratação pública ecológica nacional\nCategorias da estratégia nacional: Outros\nOutra categoria (Descrição): Critérios ambientais identificados e quantificados no PPGRCD, FPSS e Código de Conduta.\nDiretiva Veículos Não Poluentes: Não\nCritério de Acessibilidade: Os critérios de acessibilidade para as pessoas com deficiência estão incluídos\n\n26 - INFORMAÇÕES ADICIONAIS\nContrato adequado para PME: Sim\nCobertura ACP (Acordo dos Contratos Públicos da Organização Mundial do Comércio): Não\n\n27 - IDENTIFICAÇÃO E CONTACTOS DO ÓRGÃO DE RECURSOS ADMINISTRATIVOS\nDesignação: Câmara Municipal de Loures\nEndereço: Praça da Liberdade\nCódigo postal: 2674-501\nLocalidade: Loures\nTelefone: +351 211150100\nFax: +351 211151709\nEndereço eletrónico: geral@cm-loures.pt\nPrazo de interposição do recurso: 5 dias\n\n28 - IDENTIFICAÇÃO DO(S) AUTOR(ES) DE ANÚNCIO\nNome: Ricardo Leão\nCargo: Presidente\n419425578",
    "nipc": "501294996",
    "distrito": "Lisboa",
    "concelho": "Loures",
    "freguesia": "Freguesia de Loures",
    "site": "www.cm-loures.pt",
    "email": "geral@cm-loures.pt",
    "designacao_contrato": "Melhoria das Acessibilidades na Urbanização do Covão e zonas envolventes na freguesia de Loures",
    "descricao": "Melhoria das Acessibilidades na Urbanização do Covão e zonas envolventes na freguesia de Loures",
    "preco_base": "198.865,00 EUR",
    "prazo_execucao": "120 DIAS",
    "prazo_apresentacao_propostas": "12-09-2025 17:00",
    "fundos_eu": "Não",
    "plataforma_eletronica": "VORTAL",
    "url_procedimento": "https://community.vortal.biz/public/",
    "autor_nome": "Ricardo Leão",
    "autor_cargo": "Presidente"
  },
  {
    "numero_procedimento": "N/A",
    "entidade": "Município de Ponte de Lima",
    "link": "https://diariodarepublica.pt/dr/detalhe/contrato-publico/21747-928804796",
    "detalhes_completos": "1 - IDENTIFICAÇÃO E CONTACTOS DA ENTIDADE ADJUDICANTE\nDesignação da entidade adjudicante: Município de Ponte de Lima\nNIPC: 506811913\nServiço/Órgão/Pessoa de contacto: Divisão Financeira e Patrimonial\nEndereço: Praça da Rainha, 20\nCódigo postal: 4990-062\nLocalidade: Ponte de Lima\nPaís: Portugal\nNUT III: PT111\nDistrito: Viana do Castelo\nConcelho: Ponte de Lima\nFreguesia: Todas\nTelefone: 258900400\nFax: 258900410\nEndereço da Entidade (URL): www.cm-pontedelima.pt\nEndereço Eletrónico: geral@cm-pontedelima.pt\neDelivery Gateway (URL): https://www.acingov.pt\nFunção da Organização: Adquirente\nSubfunção da Organização: Organização que recebe as propostas\nNorma jurídica da Entidade Adjudicante: Organismo de direito público\nÁrea de atividade da Autoridade Adjudicante: Serviços públicos das administrações públicas\n\n2 - JORNAL OFICIAL DA UNIÃO EUROPEIA\nO procedimento a que este anúncio diz respeito também é publicitado no Jornal Oficial da União Europeia? Não\n\n3 - AVISO\nModelo de Anúncio: Concurso público\nData de Envio do Anúncio: 12-08-2025\n\n5 - PROCESSO\nTipo de Procedimento: Concurso público\nPreço base do procedimento: Sim\nValor do preço base do procedimento: 103.250,00 EUR\nProcedimento com lotes? Não\n\n6 - OBJETO DO CONTRATO\nNúmero de referência interna: CP/10/2025\nDesignação do contrato: Aquisição de duas viaturas elétricas para DAEV e Educação\nDescrição: Aquisição de duas viaturas elétricas para DAEV e Educação\nTipo de Contrato Principal: Aquisição de Bens Móveis\nTipo de Contrato: Aquisição de Bens Móveis\nClassificação CPV (Vocabulário Comum para os Contratos Públicos)\nObjeto principal\nVocabulário Principal: 34110000\nPreço base s/IVA: 103.250,00 EUR\n\n7 - INDICAÇÕES ADICIONAIS\nO contrato envolve aquisição conjunta (satisfação de várias entidades)? Não\nO contrato é adjudicado por uma central de compras? Não\n\n8 - TÉCNICAS\nO concurso destina-se à celebração de um acordo-quadro? Inexistência de acordo-quadro\nÉ utilizado um leilão eletrónico? Não\nÉ adotada uma fase de negociação? Não\nSistema de Aquisição Dinâmico: Inexistência de sistema de aquisição dinâmico\n\n9 - LOCAL DA EXECUÇÃO DO CONTRATO\nLOCAL DA EXECUÇÃO DO CONTRATO (PROCEDIMENTO)\nPaís: Portugal\nNUT III: PT111\nLocalidade: Ponte de Lima\nDistrito: Viana do Castelo\nConcelho: Ponte de Lima\nFreguesia: Todas\n\n10 - PRAZO DE EXECUÇÃO DO CONTRATO\nPrazo de execução do contrato: 120 DIAS\nPrevisão de renovações: Não\n\n11 - FUNDOS EU\nTêm fundos EU? Não\n\n12 - DOCUMENTOS DE HABILITAÇÃO\nHabilitação para o exercício da atividade profissional: Não\n\n13 - CONDIÇÕES DE APRESENTAÇÃO\nPlataforma eletrónica utilizada pela entidade adjudicante: ACIN\nURL para Apresentação: https://www.acingov.pt\nAdmissibilidade da apresentação de propostas variantes: Não autorizado\nPrazo para apresentação das propostas: 14-08-2025 23:59\nPrazo durante o qual os concorrentes são obrigados a manter as respetivas propostas: 120 dias a contar do termo do prazo para a apresentação das propostas\nIndicação de Subcontratação na Proposta: Inexistência de indicação de subcontratação\n\n14 - PRESTAÇÃO DE CAUÇÃO\nPrestação de caução: Não\n\n15 - FORNECIMENTO DAS PEÇAS DO CONCURSO, APRESENTAÇÃO DE PEDIDOS DE PARTICIPAÇÃO E APRESENTAÇÃO DAS PROPOSTAS\nLink para acesso às peças do concurso (URL): https://www.acingov.pt/acingovprod/2/zonaPublica/zona_publica_c/donwloadProcedurePiece/OTMzMDkw\n\n20 - OUTROS REQUISITOS\nInformação sobre contratos reservados. Aplica-se a contratos reservados (54º-A)? Não\n\n21 - CRITÉRIO DE ADJUDICAÇÃO\nMultifator: Não\nMonofator:\nNome: Preço\n\n24 - CONDIÇÕES DO CONTRATO\nFaturação Eletrónica: Permitido\nObrigação de Subcontratação:\nCódigo da Obrigação de Subcontratação: Não é aplicável nenhuma obrigação de subcontratação.\n\n25 - COMPRA PÚBLICA ESTRATÉGICA\nCompra Pública Estratégica: Inexistência de contratação pública estratégica\n\n26 - INFORMAÇÕES ADICIONAIS\nContrato adequado para PME: Não\nCobertura ACP (Acordo dos Contratos Públicos da Organização Mundial do Comércio): Não\n\n27 - IDENTIFICAÇÃO E CONTACTOS DO ÓRGÃO DE RECURSOS ADMINISTRATIVOS\nDesignação: Presidente da Câmara Municipal\nEndereço: Praça da República\nCódigo postal: 4990-062\nLocalidade: Ponte de Lima\nTelefone: 258900400\nFax: \nEndereço eletrónico: geral@cm-pontedelima.pt\n\n28 - IDENTIFICAÇÃO DO(S) AUTOR(ES) DE ANÚNCIO\nNome: Vasco Nuno Magalhães Velho de Almeida Ferraz\nCargo: Presidente da Câmara Municipal\n419420596",
    "nipc": "506811913",
    "distrito": "Viana do Castelo",
    "concelho": "Ponte de Lima",
    "freguesia": "Todas",
    "site": "www.cm-pontedelima.pt",
    "email": "geral@cm-pontedelima.pt",
    "designacao_contrato": "Aquisição de duas viaturas elétricas para DAEV e Educação",
    "descricao": "Aquisição de duas viaturas elétricas para DAEV e Educação",
    "preco_base": "103.250,00 EUR",
    "prazo_execucao": "120 DIAS",
    "prazo_apresentacao_propostas": "14-08-2025 23:59",
    "fundos_eu": "Não",
    "plataforma_eletronica": "ACIN",
    "url_procedimento": "https://www.acingov.pt",
    "autor_nome": "Vasco Nuno Magalhães Velho de Almeida Ferraz",
    "autor_cargo": "Presidente da Câmara Municipal"
  },
  {
    "numero_procedimento": "N/A",
    "entidade": "Instituto Nacional de Saúde Doutor Ricardo Jorge, IP",
    "link": "https://diariodarepublica.pt/dr/detalhe/contrato-publico/21756-928804799",
    "detalhes_completos": "1 - IDENTIFICAÇÃO E CONTACTOS DA ENTIDADE ADJUDICANTE\nDesignação da entidade adjudicante: Instituto Nacional de Saúde Doutor Ricardo Jorge, IP\nNIPC: 501427511\nEndereço: Avenida Padre Cruz\nCódigo postal: 1649-016\nLocalidade: LISBOA\nPaís: Portugal\nNUT III: PTZZZ\nDistrito: Todos\nConcelho: Todos\nFreguesia: Todas\nTelefone: 217319200\nEndereço da Entidade (URL): https://www.insa.pt/\nEndereço Eletrónico: drf.aprov@insa.min-saude.pt\neDelivery Gateway (URL): https://www.acingov.pt\nFunção da Organização: Adquirente\nNorma jurídica da Entidade Adjudicante: Organismo de direito público\nÁrea de atividade da Autoridade Adjudicante: Serviços públicos das administrações públicas\n\n2 - JORNAL OFICIAL DA UNIÃO EUROPEIA\nO procedimento a que este anúncio diz respeito também é publicitado no Jornal Oficial da União Europeia? Não\n\n3 - AVISO\nModelo de Anúncio: Concurso público\nData de Envio do Anúncio: 12-08-2025\n\n5 - PROCESSO\nTipo de Procedimento: Concurso público\nPreço base do procedimento: Sim\nValor do preço base do procedimento: 194.936,16 EUR\nProcedimento com lotes? Sim\nNº Máx. de Lotes Autorizado: 43\nNúmero máximo de lotes que podem ser adjudicados a um concorrente: 43\n\n6 - OBJETO DO CONTRATO\nNúmero de referência interna: CP 33-2025\nDesignação do contrato: CP 33-2025 Aquisição de Material de Filtração, Esterilização e Outro material\nDescrição: CP 33-2025 Aquisição de Material de Filtração, Esterilização e Outro material \nTipo de Contrato Principal: Aquisição de Bens Móveis\nTipo de Contrato: Aquisição de Bens Móveis\nClassificação CPV (Vocabulário Comum para os Contratos Públicos)\nObjeto principal\nVocabulário Principal: 33140000\nPreço base s/IVA: 194.936,16 EUR\nLotes: \nNº: LOT-0001\nDescrição do Lote: Aquisição de Material de Filtração, Esterilização e Outro material\nPreço base s/IVA: 250,00 EUR\nClassificação CPV (Vocabulário Comum para os Contratos Públicos)\nObjeto principal\nVocabulário Principal: 33140000\nNº: LOT-0002\nDescrição do Lote: Material de Filtração, Esterilização e Outro\nPreço base s/IVA: 670,00 EUR\nClassificação CPV (Vocabulário Comum para os Contratos Públicos)\nObjeto principal\nVocabulário Principal: 33140000\nNº: LOT-0003\nDescrição do Lote: Material de Filtração, Esterilização e Outro\nPreço base s/IVA: 1.000,00 EUR\nClassificação CPV (Vocabulário Comum para os Contratos Públicos)\nObjeto principal\nVocabulário Principal: 33140000\nNº: LOT-0004\nDescrição do Lote: Material de Filtração, Esterilização e Outro\nPreço base s/IVA: 600,00 EUR\nClassificação CPV (Vocabulário Comum para os Contratos Públicos)\nObjeto principal\nVocabulário Principal: 33140000\nNº: LOT-0005\nDescrição do Lote: Material de Filtração, Esterilização e Outro\nPreço base s/IVA: 360,00 EUR\nClassificação CPV (Vocabulário Comum para os Contratos Públicos)\nObjeto principal\nVocabulário Principal: 33140000\nNº: LOT-0006\nDescrição do Lote: Material de Filtração, Esterilização e Outro\nPreço base s/IVA: 3.573,40 EUR\nClassificação CPV (Vocabulário Comum para os Contratos Públicos)\nObjeto principal\nVocabulário Principal: 33140000\nNº: LOT-0007\nDescrição do Lote: Material de Filtração, Esterilização e Outro\nPreço base s/IVA: 18.395,60 EUR\nClassificação CPV (Vocabulário Comum para os Contratos Públicos)\nObjeto principal\nVocabulário Principal: 33140000\nNº: LOT-0008\nDescrição do Lote: Material de Filtração, Esterilização e Outro\nPreço base s/IVA: 144,98 EUR\nClassificação CPV (Vocabulário Comum para os Contratos Públicos)\nObjeto principal\nVocabulário Principal: 33140000\nNº: LOT-0009\nDescrição do Lote: Material de Filtração, Esterilização e Outro\nPreço base s/IVA: 5.289,38 EUR\nClassificação CPV (Vocabulário Comum para os Contratos Públicos)\nObjeto principal\nVocabulário Principal: 33140000\nNº: LOT-0010\nDescrição do Lote: Material de Filtração, Esterilização e Outro\nPreço base s/IVA: 2.997,00 EUR\nClassificação CPV (Vocabulário Comum para os Contratos Públicos)\nObjeto principal\nVocabulário Principal: 33140000\nNº: LOT-0011\nDescrição do Lote: Material de Filtração, Esterilização e Outro\nPreço base s/IVA: 914,00 EUR\nClassificação CPV (Vocabulário Comum para os Contratos Públicos)\nObjeto principal\nVocabulário Principal: 33140000\nNº: LOT-0012\nDescrição do Lote: Material de Filtração, Esterilização e Outro\nPreço base s/IVA: 465,00 EUR\nClassificação CPV (Vocabulário Comum para os Contratos Públicos)\nObjeto principal\nVocabulário Principal: 33140000\nNº: LOT-0013\nDescrição do Lote: Material de Filtração, Esterilização e Outro\nPreço base s/IVA: 4.860,00 EUR\nClassificação CPV (Vocabulário Comum para os Contratos Públicos)\nObjeto principal\nVocabulário Principal: 33140000\nNº: LOT-0014\nDescrição do Lote: Material de Filtração, Esterilização e Outro\nPreço base s/IVA: 4.815,00 EUR\nClassificação CPV (Vocabulário Comum para os Contratos Públicos)\nObjeto principal\nVocabulário Principal: 33140000\nNº: LOT-0015\nDescrição do Lote: Material de Filtração, Esterilização e Outro\nPreço base s/IVA: 585,00 EUR\nClassificação CPV (Vocabulário Comum para os Contratos Públicos)\nObjeto principal\nVocabulário Principal: 33140000\nNº: LOT-0016\nDescrição do Lote: Material de Filtração, Esterilização e Outro\nPreço base s/IVA: 180,00 EUR\nClassificação CPV (Vocabulário Comum para os Contratos Públicos)\nObjeto principal\nVocabulário Principal: 33140000\nNº: LOT-0017\nDescrição do Lote: Material de Filtração, Esterilização e Outro\nPreço base s/IVA: 7.050,00 EUR\nClassificação CPV (Vocabulário Comum para os Contratos Públicos)\nObjeto principal\nVocabulário Principal: 33140000\nNº: LOT-0018\nDescrição do Lote: Material de Filtração, Esterilização e Outro\nPreço base s/IVA: 5.286,00 EUR\nClassificação CPV (Vocabulário Comum para os Contratos Públicos)\nObjeto principal\nVocabulário Principal: 33140000\nNº: LOT-0019\nDescrição do Lote: Material de Filtração, Esterilização e Outro\nPreço base s/IVA: 464,00 EUR\nClassificação CPV (Vocabulário Comum para os Contratos Públicos)\nObjeto principal\nVocabulário Principal: 33140000\nNº: LOT-0020\nDescrição do Lote: Material de Filtração, Esterilização e Outro\nPreço base s/IVA: 1.241,01 EUR\nClassificação CPV (Vocabulário Comum para os Contratos Públicos)\nObjeto principal\nVocabulário Principal: 33140000\nNº: LOT-0021\nDescrição do Lote: Material de Filtração, Esterilização e Outro\nPreço base s/IVA: 140,00 EUR\nClassificação CPV (Vocabulário Comum para os Contratos Públicos)\nObjeto principal\nVocabulário Principal: 33140000\nNº: LOT-0022\nDescrição do Lote: Material de Filtração, Esterilização e Outro\nPreço base s/IVA: 24,70 EUR\nClassificação CPV (Vocabulário Comum para os Contratos Públicos)\nObjeto principal\nVocabulário Principal: 33140000\nNº: LOT-0023\nDescrição do Lote: Material de Filtração, Esterilização e Outro\nPreço base s/IVA: 10.804,34 EUR\nClassificação CPV (Vocabulário Comum para os Contratos Públicos)\nObjeto principal\nVocabulário Principal: 33140000\nNº: LOT-0024\nDescrição do Lote: Material de Filtração, Esterilização e Outro\nPreço base s/IVA: 108,00 EUR\nClassificação CPV (Vocabulário Comum para os Contratos Públicos)\nObjeto principal\nVocabulário Principal: 33140000\nNº: LOT-0025\nDescrição do Lote: Material de Filtração, Esterilização e Outro\nPreço base s/IVA: 56,00 EUR\nClassificação CPV (Vocabulário Comum para os Contratos Públicos)\nObjeto principal\nVocabulário Principal: 33140000\nNº: LOT-0026\nDescrição do Lote: Material de Filtração, Esterilização e Outro\nPreço base s/IVA: 1.235,20 EUR\nClassificação CPV (Vocabulário Comum para os Contratos Públicos)\nObjeto principal\nVocabulário Principal: 33140000\nNº: LOT-0027\nDescrição do Lote: Material de Filtração, Esterilização e Outro\nPreço base s/IVA: 4.150,00 EUR\nClassificação CPV (Vocabulário Comum para os Contratos Públicos)\nObjeto principal\nVocabulário Principal: 33140000\nNº: LOT-0028\nDescrição do Lote: Material de Filtração, Esterilização e Outro\nPreço base s/IVA: 1.350,00 EUR\nClassificação CPV (Vocabulário Comum para os Contratos Públicos)\nObjeto principal\nVocabulário Principal: 33140000\nNº: LOT-0029\nDescrição do Lote: Material de Filtração, Esterilização e Outro\nPreço base s/IVA: 86,00 EUR\nClassificação CPV (Vocabulário Comum para os Contratos Públicos)\nObjeto principal\nVocabulário Principal: 33140000\nNº: LOT-0030\nDescrição do Lote: Material de Filtração, Esterilização e Outro\nPreço base s/IVA: 378,50 EUR\nClassificação CPV (Vocabulário Comum para os Contratos Públicos)\nObjeto principal\nVocabulário Principal: 33140000\nNº: LOT-0031\nDescrição do Lote: Material de Filtração, Esterilização e Outro\nPreço base s/IVA: 1.000,00 EUR\nClassificação CPV (Vocabulário Comum para os Contratos Públicos)\nObjeto principal\nVocabulário Principal: 33140000\nNº: LOT-0032\nDescrição do Lote: Material de Filtração, Esterilização e Outro\nPreço base s/IVA: 2.315,48 EUR\nClassificação CPV (Vocabulário Comum para os Contratos Públicos)\nObjeto principal\nVocabulário Principal: 33140000\nNº: LOT-0033\nDescrição do Lote: Material de Filtração, Esterilização e Outro\nPreço base s/IVA: 28.979,80 EUR\nClassificação CPV (Vocabulário Comum para os Contratos Públicos)\nObjeto principal\nVocabulário Principal: 33140000\nNº: LOT-0034\nDescrição do Lote: Material de Filtração, Esterilização e Outro\nPreço base s/IVA: 14.726,20 EUR\nClassificação CPV (Vocabulário Comum para os Contratos Públicos)\nObjeto principal\nVocabulário Principal: 33140000\nNº: LOT-0035\nDescrição do Lote: Material de Filtração, Esterilização e Outro\nPreço base s/IVA: 3.242,80 EUR\nClassificação CPV (Vocabulário Comum para os Contratos Públicos)\nObjeto principal\nVocabulário Principal: 33140000\nNº: LOT-0036\nDescrição do Lote: Material de Filtração, Esterilização e Outro\nPreço base s/IVA: 7.760,00 EUR\nClassificação CPV (Vocabulário Comum para os Contratos Públicos)\nObjeto principal\nVocabulário Principal: 33140000\nNº: LOT-0037\nDescrição do Lote: Material de Filtração, Esterilização e Outro\nPreço base s/IVA: 32.044,87 EUR\nClassificação CPV (Vocabulário Comum para os Contratos Públicos)\nObjeto principal\nVocabulário Principal: 33140000\nNº: LOT-0038\nDescrição do Lote: Material de Filtração, Esterilização e Outro\nPreço base s/IVA: 1.253,70 EUR\nClassificação CPV (Vocabulário Comum para os Contratos Públicos)\nObjeto principal\nVocabulário Principal: 33140000\nNº: LOT-0039\nDescrição do Lote: Material de Filtração, Esterilização e Outro\nPreço base s/IVA: 2.563,62 EUR\nClassificação CPV (Vocabulário Comum para os Contratos Públicos)\nObjeto principal\nVocabulário Principal: 33140000\nNº: LOT-0040\nDescrição do Lote: Material de Filtração, Esterilização e Outro\nPreço base s/IVA: 21.346,58 EUR\nClassificação CPV (Vocabulário Comum para os Contratos Públicos)\nObjeto principal\nVocabulário Principal: 33140000\nNº: LOT-0041\nDescrição do Lote: Material de Filtração, Esterilização e Outro\nPreço base s/IVA: 1.349,50 EUR\nClassificação CPV (Vocabulário Comum para os Contratos Públicos)\nObjeto principal\nVocabulário Principal: 33140000\nNº: LOT-0042\nDescrição do Lote: Material de Filtração, Esterilização e Outro\nPreço base s/IVA: 790,50 EUR\nClassificação CPV (Vocabulário Comum para os Contratos Públicos)\nObjeto principal\nVocabulário Principal: 33140000\nNº: LOT-0043\nDescrição do Lote: Material de Filtração, Esterilização e Outro\nPreço base s/IVA: 90,00 EUR\nClassificação CPV (Vocabulário Comum para os Contratos Públicos)\nObjeto principal\nVocabulário Principal: 33140000\n\n7 - INDICAÇÕES ADICIONAIS\nO contrato envolve aquisição conjunta (satisfação de várias entidades)? Não\nO contrato é adjudicado por uma central de compras? Não\n\n8 - TÉCNICAS\nO concurso destina-se à celebração de um acordo-quadro? Inexistência de acordo-quadro\nÉ utilizado um leilão eletrónico? Não\nÉ adotada uma fase de negociação? Não\nSistema de Aquisição Dinâmico: Inexistência de sistema de aquisição dinâmico\n\n9 - LOCAL DA EXECUÇÃO DO CONTRATO\nLOCAL DA EXECUÇÃO DO CONTRATO (PROCEDIMENTO)\nPaís: Portugal\nNUT III: PT11A\nLocalidade: Freguesia de Lumiar\nDistrito: Lisboa\nConcelho: Lisboa\nFreguesia: Freguesia de Lumiar\nPaís: Portugal\nNUT III: PT170\nLocalidade: União das Freguesias de Cedofeita, Santo Ildefonso, Sé, Miragaia, São Nicolau e Vitória\nDistrito: Porto\nConcelho: Porto\nFreguesia: União das Freguesias de Cedofeita, Santo Ildefonso, Sé, Miragaia, São Nicolau e Vitória\nLOCAL DA EXECUÇÃO DO CONTRATO (LOTE)\nIdentificador do Lote: LOT-0001; LOT-0002; LOT-0003; LOT-0004; LOT-0005; LOT-0006; LOT-0007; LOT-0008; LOT-0009; LOT-0010; LOT-0011; LOT-0012; LOT-0013; LOT-0014; LOT-0015; LOT-0016; LOT-0017; LOT-0018; LOT-0019; LOT-0020; LOT-0021; LOT-0022; LOT-0023; LOT-0024; LOT-0025; LOT-0026; LOT-0027; LOT-0028; LOT-0029; LOT-0030; LOT-0031; LOT-0032; LOT-0033; LOT-0034; LOT-0035; LOT-0036; LOT-0037; LOT-0038; LOT-0039; LOT-0040; LOT-0041; LOT-0042; LOT-0043\nPaís: Portugal\nNUT III: PT11A\nLocalidade: Freguesia de Lumiar\nDistrito: Lisboa\nConcelho: Lisboa\nFreguesia: Freguesia de Lumiar\nIdentificador do Lote: LOT-0001; LOT-0002; LOT-0003; LOT-0004; LOT-0005; LOT-0006; LOT-0007; LOT-0008; LOT-0009; LOT-0010; LOT-0011; LOT-0012; LOT-0013; LOT-0014; LOT-0015; LOT-0016; LOT-0017; LOT-0018; LOT-0019; LOT-0020; LOT-0021; LOT-0022; LOT-0023; LOT-0024; LOT-0025; LOT-0026; LOT-0027; LOT-0028; LOT-0029; LOT-0030; LOT-0031; LOT-0032; LOT-0033; LOT-0034; LOT-0035; LOT-0036; LOT-0037; LOT-0038; LOT-0039; LOT-0040; LOT-0041; LOT-0042; LOT-0043\nPaís: Portugal\nNUT III: PT170\nLocalidade: União das Freguesias de Cedofeita, Santo Ildefonso, Sé, Miragaia, São Nicolau e Vitória\nDistrito: Porto\nConcelho: Porto\nFreguesia: União das Freguesias de Cedofeita, Santo Ildefonso, Sé, Miragaia, São Nicolau e Vitória\n\n10 - PRAZO DE EXECUÇÃO DO CONTRATO\nIdentificador do Lote: LOT-0001; LOT-0002; LOT-0003; LOT-0004; LOT-0005; LOT-0006; LOT-0007; LOT-0008; LOT-0009; LOT-0010; LOT-0011; LOT-0012; LOT-0013; LOT-0014; LOT-0015; LOT-0016; LOT-0017; LOT-0018; LOT-0019; LOT-0020; LOT-0021; LOT-0022; LOT-0023; LOT-0024; LOT-0025; LOT-0026; LOT-0027; LOT-0028; LOT-0029; LOT-0030; LOT-0031; LOT-0032; LOT-0033; LOT-0034; LOT-0035; LOT-0036; LOT-0037; LOT-0038; LOT-0039; LOT-0040; LOT-0041; LOT-0042; LOT-0043\nPrazo de execução do contrato: 134 DIAS\nPrevisão de renovações: Não\n\n11 - FUNDOS EU\nIdentificador do Lote: LOT-0001; LOT-0002; LOT-0003; LOT-0004; LOT-0005; LOT-0006; LOT-0007; LOT-0008; LOT-0009; LOT-0010; LOT-0011; LOT-0012; LOT-0013; LOT-0014; LOT-0015; LOT-0016; LOT-0017; LOT-0018; LOT-0019; LOT-0020; LOT-0021; LOT-0022; LOT-0023; LOT-0024; LOT-0025; LOT-0026; LOT-0027; LOT-0028; LOT-0029; LOT-0030; LOT-0031; LOT-0032; LOT-0033; LOT-0034; LOT-0035; LOT-0036; LOT-0037; LOT-0038; LOT-0039; LOT-0040; LOT-0041; LOT-0042; LOT-0043\nTêm fundos EU? Não\n\n12 - DOCUMENTOS DE HABILITAÇÃO\nHabilitação para o exercício da atividade profissional: Não\n\n13 - CONDIÇÕES DE APRESENTAÇÃO\nPlataforma eletrónica utilizada pela entidade adjudicante: ACIN\nURL para Apresentação: https://www.acingov.pt\nAdmissibilidade da apresentação de propostas variantes: Não autorizado\nPrazo para apresentação das propostas: 24-08-2025 23:59\nPrazo durante o qual os concorrentes são obrigados a manter as respetivas propostas: 66 dias a contar do termo do prazo para a apresentação das propostas\nIndicação de Subcontratação na Proposta: Inexistência de indicação de subcontratação\n\n14 - PRESTAÇÃO DE CAUÇÃO\nPrestação de caução: Não\n\n15 - FORNECIMENTO DAS PEÇAS DO CONCURSO, APRESENTAÇÃO DE PEDIDOS DE PARTICIPAÇÃO E APRESENTAÇÃO DAS PROPOSTAS\nLink para acesso às peças do concurso (URL): https://www.acingov.pt/acingovprod/2/zonaPublica/zona_publica_c/donwloadProcedurePiece/OTMxMTcz\n\n20 - OUTROS REQUISITOS\nIdentificador do Lote: LOT-0001; LOT-0002; LOT-0003; LOT-0004; LOT-0005; LOT-0006; LOT-0007; LOT-0008; LOT-0009; LOT-0010; LOT-0011; LOT-0012; LOT-0013; LOT-0014; LOT-0015; LOT-0016; LOT-0017; LOT-0018; LOT-0019; LOT-0020; LOT-0021; LOT-0022; LOT-0023; LOT-0024; LOT-0025; LOT-0026; LOT-0027; LOT-0028; LOT-0029; LOT-0030; LOT-0031; LOT-0032; LOT-0033; LOT-0034; LOT-0035; LOT-0036; LOT-0037; LOT-0038; LOT-0039; LOT-0040; LOT-0041; LOT-0042; LOT-0043\nInformação sobre contratos reservados. Aplica-se a contratos reservados (54º-A)? Não\n\n21 - CRITÉRIO DE ADJUDICAÇÃO\nO Critério de adjudicação é diferenciado por lote? Não\nMultifator: Não\nMonofator:\nNome: Preço\n\n24 - CONDIÇÕES DO CONTRATO\nIdentificador do Lote: LOT-0001; LOT-0002; LOT-0003; LOT-0004; LOT-0005; LOT-0006; LOT-0007; LOT-0008; LOT-0009; LOT-0010; LOT-0011; LOT-0012; LOT-0013; LOT-0014; LOT-0015; LOT-0016; LOT-0017; LOT-0018; LOT-0019; LOT-0020; LOT-0021; LOT-0022; LOT-0023; LOT-0024; LOT-0025; LOT-0026; LOT-0027; LOT-0028; LOT-0029; LOT-0030; LOT-0031; LOT-0032; LOT-0033; LOT-0034; LOT-0035; LOT-0036; LOT-0037; LOT-0038; LOT-0039; LOT-0040; LOT-0041; LOT-0042; LOT-0043\nFaturação Eletrónica: Permitido\nObrigação de Subcontratação:\nCódigo da Obrigação de Subcontratação: Não é aplicável nenhuma obrigação de subcontratação.\n\n25 - COMPRA PÚBLICA ESTRATÉGICA\nCompra Pública Estratégica: Inexistência de contratação pública estratégica\n\n26 - INFORMAÇÕES ADICIONAIS\nIdentificador do Lote: LOT-0001; LOT-0002; LOT-0003; LOT-0004; LOT-0005; LOT-0006; LOT-0007; LOT-0008; LOT-0009; LOT-0010; LOT-0011; LOT-0012; LOT-0013; LOT-0014; LOT-0015; LOT-0016; LOT-0017; LOT-0018; LOT-0019; LOT-0020; LOT-0021; LOT-0022; LOT-0023; LOT-0024; LOT-0025; LOT-0026; LOT-0027; LOT-0028; LOT-0029; LOT-0030; LOT-0031; LOT-0032; LOT-0033; LOT-0034; LOT-0035; LOT-0036; LOT-0037; LOT-0038; LOT-0039; LOT-0040; LOT-0041; LOT-0042; LOT-0043\nContrato adequado para PME: Não\nCobertura ACP (Acordo dos Contratos Públicos da Organização Mundial do Comércio): Não\n\n27 - IDENTIFICAÇÃO E CONTACTOS DO ÓRGÃO DE RECURSOS ADMINISTRATIVOS\nDesignação: Presidente do Conselho Diretivo\nEndereço: Avenida Padre Cruz s /n 1649-016 Lisboa\nCódigo postal: 1649-016\nLocalidade: Lisboa\nTelefone: 217519363\nFax: 217519390\nEndereço eletrónico: drf.aprov@insa.min-saude.pt\nPrazo de interposição do recurso: 5 dias\n\n28 - IDENTIFICAÇÃO DO(S) AUTOR(ES) DE ANÚNCIO\nNome: Fernando de Almeida\nCargo: Presidente do Conselho Diretivo\n419430623",
    "nipc": "501427511",
    "distrito": "Todos",
    "concelho": "Todos",
    "freguesia": "Todas",
    "site": "https://www.insa.pt/",
    "email": "drf.aprov@insa.min-saude.pt",
    "designacao_contrato": "CP 33-2025 Aquisição de Material de Filtração, Esterilização e Outro material",
    "descricao": "CP 33-2025 Aquisição de Material de Filtração, Esterilização e Outro material",
    "preco_base": "194.936,16 EUR",
    "prazo_execucao": "134 DIAS",
    "prazo_apresentacao_propostas": "24-08-2025 23:59",
    "fundos_eu": "Não",
    "plataforma_eletronica": "ACIN",
    "url_procedimento": "https://www.acingov.pt",
    "autor_nome": "Fernando de Almeida",
    "autor_cargo": "Presidente do Conselho Diretivo"
  },
  {
    "numero_procedimento": "N/A",
    "entidade": "União das Freguesias de Massamá e Monte Abraão",
    "link": "https://diariodarepublica.pt/dr/detalhe/contrato-publico/21758-928804800",
    "detalhes_completos": "1 - IDENTIFICAÇÃO E CONTACTOS DA ENTIDADE ADJUDICANTE\nDesignação da entidade adjudicante: União das Freguesias de Massamá e Monte Abraão\nNIPC: 510837808\nServiço/Órgão/Pessoa de contacto: Executivo\nEndereço: Rua Dr. Francisco Ribeiro de Spínola - s/n - vivenda - Massamá\nCódigo postal: 2745-872\nLocalidade: Sintra\nPaís: Portugal\nNUT III: PT170\nDistrito: Lisboa\nConcelho: Sintra\nFreguesia: União das Freguesias de Massamá e Monte Abraão\nTelefone: 214392331\nFax: 214389170\nEndereço da Entidade (URL): www.uf-massamamabraao.pt\nEndereço Eletrónico: geral@uf-massamamabraao.pt\neDelivery Gateway (URL): https://www.acingov.pt\nFunção da Organização: Adquirente\nNorma jurídica da Entidade Adjudicante: Organismo de direito público\nÁrea de atividade da Autoridade Adjudicante: Serviços públicos das administrações públicas\n\n2 - JORNAL OFICIAL DA UNIÃO EUROPEIA\nO procedimento a que este anúncio diz respeito também é publicitado no Jornal Oficial da União Europeia? Não\n\n3 - AVISO\nModelo de Anúncio: Concurso público\nData de Envio do Anúncio: 12-08-2025\n\n5 - PROCESSO\nTipo de Procedimento: Concurso público\nPreço base do procedimento: Sim\nValor do preço base do procedimento: 65.000,00 EUR\nProcedimento com lotes? Não\n\n6 - OBJETO DO CONTRATO\nNúmero de referência interna: 20/CP/PS/25\nDesignação do contrato: Aquisição de serviços de telecomunicações, internet e televisão para a União de Freguesias de Massamá e Monte Abraão\nDescrição: Aquisição de serviços de telecomunicações, internet e televisão para a União de Freguesias de Massamá e Monte Abraão\nTipo de Contrato Principal: Aquisição de Serviços\nTipo de Contrato: Aquisição de Serviços\nClassificação CPV (Vocabulário Comum para os Contratos Públicos)\nObjeto principal\nVocabulário Principal: 64200000\nPreço base s/IVA: 65.000,00 EUR\n\n7 - INDICAÇÕES ADICIONAIS\nO contrato envolve aquisição conjunta (satisfação de várias entidades)? Não\nO contrato é adjudicado por uma central de compras? Não\n\n8 - TÉCNICAS\nO concurso destina-se à celebração de um acordo-quadro? Inexistência de acordo-quadro\nÉ utilizado um leilão eletrónico? Não\nÉ adotada uma fase de negociação? Não\nSistema de Aquisição Dinâmico: Inexistência de sistema de aquisição dinâmico\n\n9 - LOCAL DA EXECUÇÃO DO CONTRATO\nLOCAL DA EXECUÇÃO DO CONTRATO (PROCEDIMENTO)\nPaís: Portugal\nNUT III: PT170\nLocalidade: União das Freguesias de Massamá e Monte Abraão\nDistrito: Lisboa\nConcelho: Sintra\nFreguesia: União das Freguesias de Massamá e Monte Abraão\n\n10 - PRAZO DE EXECUÇÃO DO CONTRATO\nPrazo de execução do contrato: 12 MESES\nPrevisão de renovações: Sim\nIndicar número máximo de renovações: 2\nPrazo de renovações diferente do prazo inicial: Não\n\n11 - FUNDOS EU\nTêm fundos EU? Não\n\n12 - DOCUMENTOS DE HABILITAÇÃO\nHabilitação para o exercício da atividade profissional: Não\n\n13 - CONDIÇÕES DE APRESENTAÇÃO\nPlataforma eletrónica utilizada pela entidade adjudicante: ACIN\nURL para Apresentação: https://www.acingov.pt\nAdmissibilidade da apresentação de propostas variantes: Não autorizado\nPrazo para apresentação das propostas: 25-08-2025 23:59\nPrazo durante o qual os concorrentes são obrigados a manter as respetivas propostas: 120 dias a contar do termo do prazo para a apresentação das propostas\nIndicação de Subcontratação na Proposta: Inexistência de indicação de subcontratação\n\n14 - PRESTAÇÃO DE CAUÇÃO\nPrestação de caução: Não\n\n15 - FORNECIMENTO DAS PEÇAS DO CONCURSO, APRESENTAÇÃO DE PEDIDOS DE PARTICIPAÇÃO E APRESENTAÇÃO DAS PROPOSTAS\nLink para acesso às peças do concurso (URL): https://www.acingov.pt/acingovprod/2/zonaPublica/zona_publica_c/donwloadProcedurePiece/OTMxNTg1\n\n20 - OUTROS REQUISITOS\nInformação sobre contratos reservados. Aplica-se a contratos reservados (54º-A)? Não\n\n21 - CRITÉRIO DE ADJUDICAÇÃO\nMultifator: Sim\nFator: \nNome: Preço\nPonderação: 60%\nSubfatores: Não\nFator: \nNome: Outros\nOutro Nome: Valor em equipamentos\nPonderação: 40%\nSubfatores: Não\n\n24 - CONDIÇÕES DO CONTRATO\nFaturação Eletrónica: Permitido\nObrigação de Subcontratação:\nCódigo da Obrigação de Subcontratação: Não é aplicável nenhuma obrigação de subcontratação.\n\n25 - COMPRA PÚBLICA ESTRATÉGICA\nCompra Pública Estratégica: Inexistência de contratação pública estratégica\n\n26 - INFORMAÇÕES ADICIONAIS\nContrato adequado para PME: Sim\nCobertura ACP (Acordo dos Contratos Públicos da Organização Mundial do Comércio): Não\n\n27 - IDENTIFICAÇÃO E CONTACTOS DO ÓRGÃO DE RECURSOS ADMINISTRATIVOS\nDesignação: Executivo\nEndereço: Rua Dr. Francisco Spínola, s/n Massamá, Queluz\nCódigo postal: 2745-872\nLocalidade: Lisboa\nTelefone: 210133550\nFax: \nEndereço eletrónico: geral@uf-massamamabraao.pt\n\n28 - IDENTIFICAÇÃO DO(S) AUTOR(ES) DE ANÚNCIO\nNome: Sara Lopes\nCargo: Técnica Superior\n419425448",
    "nipc": "510837808",
    "distrito": "Lisboa",
    "concelho": "Sintra",
    "freguesia": "União das Freguesias de Massamá e Monte Abraão",
    "site": "www.uf-massamamabraao.pt",
    "email": "geral@uf-massamamabraao.pt",
    "designacao_contrato": "Aquisição de serviços de telecomunicações, internet e televisão para a União de Freguesias de Massamá e Monte Abraão",
    "descricao": "Aquisição de serviços de telecomunicações, internet e televisão para a União de Freguesias de Massamá e Monte Abraão",
    "preco_base": "65.000,00 EUR",
    "prazo_execucao": "12 MESES",
    "prazo_apresentacao_propostas": "25-08-2025 23:59",
    "fundos_eu": "Não",
    "plataforma_eletronica": "ACIN",
    "url_procedimento": "https://www.acingov.pt",
    "autor_nome": "Sara Lopes",
    "autor_cargo": "Técnica Superior"
  },
  {
    "numero_procedimento": "N/A",
    "entidade": "GEBALIS - Gestão do Arrendamento da Habitação Municipal de Lisboa, E.M., S.A.",
    "link": "https://diariodarepublica.pt/dr/detalhe/contrato-publico/21759-928804801",
    "detalhes_completos": "1 - IDENTIFICAÇÃO E CONTACTOS DA ENTIDADE ADJUDICANTE\nDesignação da entidade adjudicante: GEBALIS - Gestão do Arrendamento da Habitação Municipal de Lisboa, E.M., S.A.\nNIPC: 503541567\nServiço/Órgão/Pessoa de contacto: Joana Pereira\nEndereço: Rua Laura Alves, n.º 12, 7º Piso\nCódigo postal: 1050-138\nLocalidade: Lisboa\nPaís: Portugal\nNUT III: PT170\nDistrito: Lisboa\nConcelho: Lisboa\nFreguesia: Freguesia de Avenidas Novas\nTelefone: 217511000\nFax: 217511000\nEndereço da Entidade (URL): www.gebalis.pt\nEndereço Eletrónico: contratacao.publica@gebalis.pt\nFunção da Organização: Adquirente\nNorma jurídica da Entidade Adjudicante: Empresa pública, controlada por uma autoridade local\nÁrea de atividade da Autoridade Adjudicante: Habitação e equipamentos coletivos\n\n2 - JORNAL OFICIAL DA UNIÃO EUROPEIA\nO procedimento a que este anúncio diz respeito também é publicitado no Jornal Oficial da União Europeia? Não\n\n3 - AVISO\nModelo de Anúncio: Concurso público\nData de Envio do Anúncio: 13-08-2025\n\n5 - PROCESSO\nTipo de Procedimento: Concurso público\nPreço base do procedimento: Sim\nValor do preço base do procedimento: 91.694,60 EUR\nProcedimento com lotes? Não\n\n6 - OBJETO DO CONTRATO\nNúmero de referência interna: Empreitada 56/GEBALIS/2025\nDesignação do contrato: Empreitada 56/GEBALIS/2025 - Manutenção e Reparação de Fogos e Zonas Comuns no Património Disperso\nDescrição: Empreitada 56/GEBALIS/2025 - Manutenção e Reparação de Fogos e Zonas Comuns no Património Disperso\nTipo de Contrato Principal: Empreitada de Obras Públicas\nTipo de Contrato: Empreitada de Obras Públicas\nClassificação CPV (Vocabulário Comum para os Contratos Públicos)\nObjeto principal\nVocabulário Principal: 45453100\nPreço base s/IVA: 91.694,60 EUR\n\n7 - INDICAÇÕES ADICIONAIS\nO contrato envolve aquisição conjunta (satisfação de várias entidades)? Não\nO contrato é adjudicado por uma central de compras? Não\n\n8 - TÉCNICAS\nO concurso destina-se à celebração de um acordo-quadro? Inexistência de acordo-quadro\nÉ utilizado um leilão eletrónico? Não\nÉ adotada uma fase de negociação? Não\nSistema de Aquisição Dinâmico: Inexistência de sistema de aquisição dinâmico\n\n9 - LOCAL DA EXECUÇÃO DO CONTRATO\nLOCAL DA EXECUÇÃO DO CONTRATO (PROCEDIMENTO)\nPaís: Portugal\nNUT III: PT170\nLocalidade: Lisboa\nDistrito: Lisboa\nConcelho: Lisboa\nFreguesia: Todas\n\n10 - PRAZO DE EXECUÇÃO DO CONTRATO\nPrazo de execução do contrato: 540 DIAS\nPrevisão de renovações: Não\n\n11 - FUNDOS EU\nTêm fundos EU? Não\n\n12 - DOCUMENTOS DE HABILITAÇÃO\nHabilitação para o exercício da atividade profissional: Sim\nTipo: Alvará\nDescrição: Alvará Obras Públicas\n\n13 - CONDIÇÕES DE APRESENTAÇÃO\nPlataforma eletrónica utilizada pela entidade adjudicante: ANOGOV\nURL para Apresentação: https://www.anogov.com/em-gebalis/faces/\nAdmissibilidade da apresentação de propostas variantes: Não autorizado\nPrazo para apresentação das propostas: 28-08-2025 23:59\nPrazo durante o qual os concorrentes são obrigados a manter as respetivas propostas: 180 dias a contar do termo do prazo para a apresentação das propostas\nApresentação de Catálogo Eletrónico: Permitido\nIndicação de Subcontratação na Proposta: Inexistência de indicação de subcontratação\n\n14 - PRESTAÇÃO DE CAUÇÃO\nPrestação de caução: Não\n\n15 - FORNECIMENTO DAS PEÇAS DO CONCURSO, APRESENTAÇÃO DE PEDIDOS DE PARTICIPAÇÃO E APRESENTAÇÃO DAS PROPOSTAS\nLink para acesso às peças do concurso (URL): https://www.anogov.com/em-gebalis/faces/app/acessoDocs.jsp?codigoAcesso=1fEHjkKCPJZCYLMTPiUd4yFL1XBWmrgzlg2qvz2DtrXAZxzz2y\n\n20 - OUTROS REQUISITOS\nInformação sobre contratos reservados. Aplica-se a contratos reservados (54º-A)? Não\n\n21 - CRITÉRIO DE ADJUDICAÇÃO\nMultifator: Não\nMonofator:\nNome: Preço\n\n24 - CONDIÇÕES DO CONTRATO\nFaturação Eletrónica: Permitido\nObrigação de Subcontratação:\nCódigo da Obrigação de Subcontratação: Não é aplicável nenhuma obrigação de subcontratação.\n\n25 - COMPRA PÚBLICA ESTRATÉGICA\nCompra Pública Estratégica: Inexistência de contratação pública estratégica\n\n26 - INFORMAÇÕES ADICIONAIS\nContrato adequado para PME: Sim\nCobertura ACP (Acordo dos Contratos Públicos da Organização Mundial do Comércio): Não\n\n27 - IDENTIFICAÇÃO E CONTACTOS DO ÓRGÃO DE RECURSOS ADMINISTRATIVOS\nDesignação: Conselho de Administração\nEndereço: Rua Laura Alves, n.º 12, 7.º piso\nCódigo postal: 1050-138\nLocalidade: Lisboa\nEndereço eletrónico: contratacao.publica@gebalis.pt\n\n28 - IDENTIFICAÇÃO DO(S) AUTOR(ES) DE ANÚNCIO\nNome: Miguel Fernando Costa da Silva Pereira\nCargo: Vogal do Conselho de Administração\n419427521",
    "nipc": "503541567",
    "distrito": "Lisboa",
    "concelho": "Lisboa",
    "freguesia": "Freguesia de Avenidas Novas",
    "site": "www.gebalis.pt",
    "email": "contratacao.publica@gebalis.pt",
    "designacao_contrato": "Empreitada 56/GEBALIS/2025 - Manutenção e Reparação de Fogos e Zonas Comuns no Património Disperso",
    "descricao": "Empreitada 56/GEBALIS/2025 - Manutenção e Reparação de Fogos e Zonas Comuns no Património Disperso",
    "preco_base": "91.694,60 EUR",
    "prazo_execucao": "540 DIAS",
    "prazo_apresentacao_propostas": "28-08-2025 23:59",
    "fundos_eu": "Não",
    "plataforma_eletronica": "ANOGOV",
    "url_procedimento": "https://www.anogov.com/em-gebalis/faces/",
    "autor_nome": "Miguel Fernando Costa da Silva Pereira",
    "autor_cargo": "Vogal do Conselho de Administração"
  },
  {
    "numero_procedimento": "N/A",
    "entidade": "Município de Silves",
    "link": "https://diariodarepublica.pt/dr/detalhe/contrato-publico/21761-928804802",
    "detalhes_completos": "1 - IDENTIFICAÇÃO E CONTACTOS DA ENTIDADE ADJUDICANTE\nDesignação da entidade adjudicante: Município de Silves\nNIPC: 506818837\nServiço/Órgão/Pessoa de contacto: Divisão de Obras Municipais e Trânsito\nEndereço: Rua da Sé, 6 - 1º\nCódigo postal: 8300-175\nLocalidade: Silves\nPaís: Portugal\nNUT III: PT150\nDistrito: Faro\nConcelho: Silves\nFreguesia: Freguesia de Silves\nTelefone: 282440800\nFax: 282440850\nEndereço da Entidade (URL): www.cm-silves.pt\nEndereço Eletrónico: obras.municipais@cm-silves.pt\neDelivery Gateway (URL): https://www.acingov.pt\nFunção da Organização: Adquirente\nNorma jurídica da Entidade Adjudicante: Organismo de direito público\nÁrea de atividade da Autoridade Adjudicante: Serviços públicos das administrações públicas\n\n2 - JORNAL OFICIAL DA UNIÃO EUROPEIA\nO procedimento a que este anúncio diz respeito também é publicitado no Jornal Oficial da União Europeia? Não\n\n3 - AVISO\nModelo de Anúncio: Concurso público\nData de Envio do Anúncio: 13-08-2025\n\n5 - PROCESSO\nTipo de Procedimento: Concurso público\nPreço base do procedimento: Sim\nValor do preço base do procedimento: 1.500.000,00 EUR\nProcedimento com lotes? Não\n\n6 - OBJETO DO CONTRATO\nNúmero de referência interna: 1353/DOMT\nDesignação do contrato: Sé de Silves  Recuperação de Coberturas e Fachadas\nDescrição: Sé de Silves  Recuperação de Coberturas e Fachadas\nTipo de Contrato Principal: Empreitada de Obras Públicas\nTipo de Contrato: Empreitada de Obras Públicas\nClassificação CPV (Vocabulário Comum para os Contratos Públicos)\nObjeto principal\nVocabulário Principal: 45212350\nPreço base s/IVA: 1.500.000,00 EUR\n\n7 - INDICAÇÕES ADICIONAIS\nO contrato envolve aquisição conjunta (satisfação de várias entidades)? Não\nO contrato é adjudicado por uma central de compras? Não\n\n8 - TÉCNICAS\nO concurso destina-se à celebração de um acordo-quadro? Inexistência de acordo-quadro\nÉ utilizado um leilão eletrónico? Não\nÉ adotada uma fase de negociação? Não\nSistema de Aquisição Dinâmico: Inexistência de sistema de aquisição dinâmico\n\n9 - LOCAL DA EXECUÇÃO DO CONTRATO\nLOCAL DA EXECUÇÃO DO CONTRATO (PROCEDIMENTO)\nPaís: Portugal\nNUT III: PT150\nLocalidade: Freguesia de Silves\nDistrito: Faro\nConcelho: Silves\nFreguesia: Freguesia de Silves\n\n10 - PRAZO DE EXECUÇÃO DO CONTRATO\nPrazo de execução do contrato: 240 DIAS\nPrevisão de renovações: Não\n\n11 - FUNDOS EU\nTêm fundos EU? Não\n\n12 - DOCUMENTOS DE HABILITAÇÃO\nHabilitação para o exercício da atividade profissional: Sim\nTipo: Alvará\nDescrição: 10.ª subcategoria da 1.ª categoria, em classe que cubra o valor global da proposta\n\n13 - CONDIÇÕES DE APRESENTAÇÃO\nPlataforma eletrónica utilizada pela entidade adjudicante: ACIN\nURL para Apresentação: https://www.acingov.pt\nAdmissibilidade da apresentação de propostas variantes: Não autorizado\nPrazo para apresentação das propostas: 12-09-2025 23:59\nPrazo durante o qual os concorrentes são obrigados a manter as respetivas propostas: 120 dias a contar do termo do prazo para a apresentação das propostas\nIndicação de Subcontratação na Proposta: Inexistência de indicação de subcontratação\n\n14 - PRESTAÇÃO DE CAUÇÃO\nPrestação de caução: Sim\nPercentagem: 5%\nDescrição da Garantia Exigida: O valor da caução é de 5.00% do preço contratual.\n\n15 - FORNECIMENTO DAS PEÇAS DO CONCURSO, APRESENTAÇÃO DE PEDIDOS DE PARTICIPAÇÃO E APRESENTAÇÃO DAS PROPOSTAS\nLink para acesso às peças do concurso (URL): https://www.acingov.pt/acingovprod/2/zonaPublica/zona_publica_c/donwloadProcedurePiece/OTMyNjQ0\n\n20 - OUTROS REQUISITOS\nInformação sobre contratos reservados. Aplica-se a contratos reservados (54º-A)? Não\n\n21 - CRITÉRIO DE ADJUDICAÇÃO\nMultifator: Não\nMonofator:\nNome: Preço\n\n24 - CONDIÇÕES DO CONTRATO\nFaturação Eletrónica: Permitido\nObrigação de Subcontratação:\nCódigo da Obrigação de Subcontratação: Não é aplicável nenhuma obrigação de subcontratação.\n\n25 - COMPRA PÚBLICA ESTRATÉGICA\nCompra Pública Estratégica: Inexistência de contratação pública estratégica\n\n26 - INFORMAÇÕES ADICIONAIS\nContrato adequado para PME: Sim\nCobertura ACP (Acordo dos Contratos Públicos da Organização Mundial do Comércio): Não\n\n27 - IDENTIFICAÇÃO E CONTACTOS DO ÓRGÃO DE RECURSOS ADMINISTRATIVOS\nDesignação: Município de Silves\nEndereço: Largo do Município\nCódigo postal: 8300-117\nLocalidade: Silves\nTelefone: 282440800\nFax: 282440850\nEndereço eletrónico: gabinete.presidente@cm-silves.pt\nPrazo de interposição do recurso: 5 dias\n\n28 - IDENTIFICAÇÃO DO(S) AUTOR(ES) DE ANÚNCIO\nNome: Rosa Cristina Gonçalves da Palma\nCargo: Presidente da Câmara\n419419405",
    "nipc": "506818837",
    "distrito": "Faro",
    "concelho": "Silves",
    "freguesia": "Freguesia de Silves",
    "site": "www.cm-silves.pt",
    "email": "obras.municipais@cm-silves.pt",
    "designacao_contrato": "Sé de Silves  Recuperação de Coberturas e Fachadas",
    "descricao": "Sé de Silves  Recuperação de Coberturas e Fachadas",
    "preco_base": "1.500.000,00 EUR",
    "prazo_execucao": "240 DIAS",
    "prazo_apresentacao_propostas": "12-09-2025 23:59",
    "fundos_eu": "Não",
    "plataforma_eletronica": "ACIN",
    "url_procedimento": "https://www.acingov.pt",
    "autor_nome": "Rosa Cristina Gonçalves da Palma",
    "autor_cargo": "Presidente da Câmara"
  },
  {
    "numero_procedimento": "N/A",
    "entidade": "ASSOCIAÇÃO DE BOMBEIROS VOLUNTÁRIOS DE PORTALEGRE",
    "link": "https://diariodarepublica.pt/dr/detalhe/contrato-publico/21753-928808409",
    "detalhes_completos": "Alteração do Anúncio de procedimento n.º 21013/2025, de 2025-08-05, com o ID 419394506\n\n1 - IDENTIFICAÇÃO E CONTACTOS DA ENTIDADE ADJUDICANTE\nDesignação da entidade adjudicante: ASSOCIAÇÃO DE BOMBEIROS VOLUNTÁRIOS DE PORTALEGRE\nNIPC: 501177922\nEndereço: AVENIDA DA EXTREMADURA ESPANHOLA Nº 23\nCódigo postal: 7300-051\nLocalidade: Portalegre\nPaís: Portugal\nNUT III: PT186\nDistrito: Portalegre\nConcelho: Portalegre\nFreguesia: União das Freguesias da Sé e São Lourenço\nTelefone: 245307000\nEndereço Eletrónico: secretaria@bvportalegre.pt\neDelivery Gateway (URL): https://community.vortal.biz/public/\nFunção da Organização: Adquirente\nNorma jurídica da Entidade Adjudicante: Autoridade da administração central\nÁrea de atividade da Autoridade Adjudicante: Proteção ambiental\n\n2 - JORNAL OFICIAL DA UNIÃO EUROPEIA\nO procedimento a que este anúncio diz respeito também é publicitado no Jornal Oficial da União Europeia? Não\n\n3 - AVISO\nModelo de Anúncio: Concurso público\nData de Envio do Anúncio: 12-08-2025\n\n5 - PROCESSO\nTipo de Procedimento: Concurso público\nPreço base do procedimento: Sim\nValor do preço base do procedimento: 39.945,00 EUR\nProcedimento com lotes? Não\n\n6 - OBJETO DO CONTRATO\nNúmero de referência interna: 1./2025\nDesignação do contrato: Melhoria da Eficiência Energética do edifício da Associação Humanitária de Bombeiros Voluntários de Portalegre \nDescrição: Melhoria da Eficiência Energética do edifício da Associação Humanitária de Bombeiros Voluntários de Portalegre\nTipo de Contrato Principal: Aquisição de Bens Móveis\nTipo de Contrato: Aquisição de Bens Móveis\nClassificação CPV (Vocabulário Comum para os Contratos Públicos)\nObjeto principal\nVocabulário Principal: 09330000\nPreço base s/IVA: 39.945,00 EUR\n\n7 - INDICAÇÕES ADICIONAIS\nO contrato envolve aquisição conjunta (satisfação de várias entidades)? Não\nO contrato é adjudicado por uma central de compras? Não\n\n8 - TÉCNICAS\nO concurso destina-se à celebração de um acordo-quadro? Inexistência de acordo-quadro\nÉ utilizado um leilão eletrónico? Não\nÉ adotada uma fase de negociação? Não\nSistema de Aquisição Dinâmico: Inexistência de sistema de aquisição dinâmico\n\n9 - LOCAL DA EXECUÇÃO DO CONTRATO\nLOCAL DA EXECUÇÃO DO CONTRATO (PROCEDIMENTO)\nPaís: Portugal\nNUT III: PT186\nLocalidade: Portalegre\nDistrito: Portalegre\nConcelho: Portalegre\nFreguesia: União das Freguesias da Sé e São Lourenço\n\n10 - PRAZO DE EXECUÇÃO DO CONTRATO\nPrazo de execução do contrato: 120 DIAS\nPrevisão de renovações: Não\n\n11 - FUNDOS EU\nTêm fundos EU? Sim\n\n12 - DOCUMENTOS DE HABILITAÇÃO\nHabilitação para o exercício da atividade profissional: Não\n\n13 - CONDIÇÕES DE APRESENTAÇÃO\nPlataforma eletrónica utilizada pela entidade adjudicante: VORTAL\nURL para Apresentação: https://community.vortal.biz/public/\nAdmissibilidade da apresentação de propostas variantes: Não autorizado\nPrazo para apresentação das propostas: 22-08-2025 23:59\nPrazo durante o qual os concorrentes são obrigados a manter as respetivas propostas: 66 dias a contar do termo do prazo para a apresentação das propostas\nApresentação de Catálogo Eletrónico: Permitido\nIndicação de Subcontratação na Proposta: Inexistência de indicação de subcontratação\n\n14 - PRESTAÇÃO DE CAUÇÃO\nPrestação de caução: Não\n\n15 - FORNECIMENTO DAS PEÇAS DO CONCURSO, APRESENTAÇÃO DE PEDIDOS DE PARTICIPAÇÃO E APRESENTAÇÃO DAS PROPOSTAS\nLink para acesso às peças do concurso (URL): https://community.vortal.biz/Public/public-tender-documents/ZWRoZFRTdWRnbVJLMmM2QlhxcGVLekRCNk5jNHdYUmJPQnRMb29uTkU3QThRYUdVUWtPQm5kcjZMb01BRTBpdytVZEovSFBWZ1hJc2dSM0F1MVBaZ1E9PXkkQGlA\n\n20 - OUTROS REQUISITOS\nInformação sobre contratos reservados. Aplica-se a contratos reservados (54º-A)? Não\n\n21 - CRITÉRIO DE ADJUDICAÇÃO\nMultifator: Não\nMonofator:\nNome: Outros\nOutro nome: Preço\n\n24 - CONDIÇÕES DO CONTRATO\nFaturação Eletrónica: Permitido\nObrigação de Subcontratação:\nCódigo da Obrigação de Subcontratação: Não é aplicável nenhuma obrigação de subcontratação.\n\n25 - COMPRA PÚBLICA ESTRATÉGICA\nCompra Pública Estratégica: Inexistência de contratação pública estratégica\n\n26 - INFORMAÇÕES ADICIONAIS\nContrato adequado para PME: Sim\nCobertura ACP (Acordo dos Contratos Públicos da Organização Mundial do Comércio): Não\n\n27 - IDENTIFICAÇÃO E CONTACTOS DO ÓRGÃO DE RECURSOS ADMINISTRATIVOS\nDesignação: Associação Humanitária de  Bombeiros Voluntários de Portalegre\nEndereço: Av. Estremadura Espanhola, 23\nCódigo postal: 7300-051\nLocalidade: Portalegre\nTelefone: +351 245307005\nFax: +351 245307005\nEndereço eletrónico: direcao@bvportalegre.pt\n\n28 - IDENTIFICAÇÃO DO(S) AUTOR(ES) DE ANÚNCIO\nNome: João António Mota Lourenço\nCargo: Presidente da Direção\n\n29 - ALTERAÇÃO\nMotivo da Alteração: Informações atualizadas\nIdentificador da Versão do Anúncio a Alterar: 8e249414-b94b-4960-9eaa-78aa0271c0cf-01\nIdentificador das Secções Alteradas do Anúncio Anterior: Alteração\nAlteração dos Documentos do Concurso: Sim\nData de alteração dos documentos do concurso: 11-08-2025\n419430364",
    "nipc": "501177922",
    "distrito": "Portalegre",
    "concelho": "Portalegre",
    "freguesia": "União das Freguesias da Sé e São Lourenço",
    "site": null,
    "email": "secretaria@bvportalegre.pt",
    "designacao_contrato": "Melhoria da Eficiência Energética do edifício da Associação Humanitária de Bombeiros Voluntários de Portalegre",
    "descricao": "Melhoria da Eficiência Energética do edifício da Associação Humanitária de Bombeiros Voluntários de Portalegre",
    "preco_base": "39.945,00 EUR",
    "prazo_execucao": "120 DIAS",
    "prazo_apresentacao_propostas": "22-08-2025 23:59",
    "fundos_eu": "Sim",
    "plataforma_eletronica": "VORTAL",
    "url_procedimento": "https://community.vortal.biz/public/",
    "autor_nome": "João António Mota Lourenço",
    "autor_cargo": "Presidente da Direção"
  },
  {
    "numero_procedimento": "N/A",
    "entidade": "Associação Para a Recuperação de Cidadãos Inadaptados da Lousã - ARCIL",
    "link": "https://diariodarepublica.pt/dr/detalhe/contrato-publico/21754-928808462",
    "detalhes_completos": "1 - IDENTIFICAÇÃO E CONTACTOS DA ENTIDADE ADJUDICANTE\nDesignação da entidade adjudicante: Associação Para a Recuperação de Cidadãos Inadaptados da Lousã - ARCIL\nNIPC: 501227083\nServiço/Órgão/Pessoa de contacto: Júri\nEndereço: R. Francisco Lopes Fernandes, 6 Cabo do Soito\nCódigo postal: 3200-065\nLocalidade: Lousã\nPaís: Portugal\nNUT III: PT16E\nDistrito: Coimbra\nConcelho: Lousã\nFreguesia: União das Freguesias de Lousã e Vilarinho\nTelefone: 239990300\nFax: 239991989\nEndereço da Entidade (URL): https://arcil.org.pt/\nEndereço Eletrónico: arcil@arcil.org\neDelivery Gateway (URL): https://www.acingov.pt\nFunção da Organização: Adquirente\nNorma jurídica da Entidade Adjudicante: Organismo de direito público\nÁrea de atividade da Autoridade Adjudicante: Serviços públicos das administrações públicas\n\n2 - JORNAL OFICIAL DA UNIÃO EUROPEIA\nO procedimento a que este anúncio diz respeito também é publicitado no Jornal Oficial da União Europeia? Não\n\n3 - AVISO\nModelo de Anúncio: Concurso público\nData de Envio do Anúncio: 12-08-2025\n\n5 - PROCESSO\nTipo de Procedimento: Concurso público\nPreço base do procedimento: Sim\nValor do preço base do procedimento: 46.595,00 EUR\nProcedimento com lotes? Não\n\n6 - OBJETO DO CONTRATO\nNúmero de referência interna: CP/11/2025\nDesignação do contrato: Aquisição de veículo elétrico novo com transformação no âmbito do programa PRR - N.º 12/C03-i01/2024 RE-C03-i01.m04  Mobilidade Verde Social\nDescrição: Aquisição de veículo elétrico novo com transformação no âmbito do programa PRR - N.º 12/C03-i01/2024 RE-C03-i01.m04  Mobilidade Verde Social\nTipo de Contrato Principal: Aquisição de Bens Móveis\nTipo de Contrato: Aquisição de Bens Móveis\nClassificação CPV (Vocabulário Comum para os Contratos Públicos)\nObjeto principal\nVocabulário Principal: 34100000\nPreço base s/IVA: 46.595,00 EUR\n\n7 - INDICAÇÕES ADICIONAIS\nO contrato envolve aquisição conjunta (satisfação de várias entidades)? Não\nO contrato é adjudicado por uma central de compras? Não\n\n8 - TÉCNICAS\nO concurso destina-se à celebração de um acordo-quadro? Inexistência de acordo-quadro\nÉ utilizado um leilão eletrónico? Não\nÉ adotada uma fase de negociação? Não\nSistema de Aquisição Dinâmico: Inexistência de sistema de aquisição dinâmico\n\n9 - LOCAL DA EXECUÇÃO DO CONTRATO\nLOCAL DA EXECUÇÃO DO CONTRATO (PROCEDIMENTO)\nPaís: Portugal\nNUT III: PT16E\nLocalidade: União das Freguesias de Lousã e Vilarinho\nDistrito: Coimbra\nConcelho: Lousã\nFreguesia: União das Freguesias de Lousã e Vilarinho\n\n10 - PRAZO DE EXECUÇÃO DO CONTRATO\nPrazo de execução do contrato: 120 DIAS\nPrevisão de renovações: Não\n\n11 - FUNDOS EU\nTêm fundos EU? Não\n\n12 - DOCUMENTOS DE HABILITAÇÃO\nHabilitação para o exercício da atividade profissional: Não\n\n13 - CONDIÇÕES DE APRESENTAÇÃO\nPlataforma eletrónica utilizada pela entidade adjudicante: ACIN\nURL para Apresentação: https://www.acingov.pt\nAdmissibilidade da apresentação de propostas variantes: Não autorizado\nPrazo para apresentação das propostas: 27-08-2025 18:00\nPrazo durante o qual os concorrentes são obrigados a manter as respetivas propostas: 66 dias a contar do termo do prazo para a apresentação das propostas\nIndicação de Subcontratação na Proposta: Inexistência de indicação de subcontratação\n\n14 - PRESTAÇÃO DE CAUÇÃO\nPrestação de caução: Não\n\n15 - FORNECIMENTO DAS PEÇAS DO CONCURSO, APRESENTAÇÃO DE PEDIDOS DE PARTICIPAÇÃO E APRESENTAÇÃO DAS PROPOSTAS\nLink para acesso às peças do concurso (URL): https://www.acingov.pt/acingovprod/2/zonaPublica/zona_publica_c/donwloadProcedurePiece/OTMzNDg0\n\n20 - OUTROS REQUISITOS\nInformação sobre contratos reservados. Aplica-se a contratos reservados (54º-A)? Não\n\n21 - CRITÉRIO DE ADJUDICAÇÃO\nMultifator: Não\nMonofator:\nNome: Preço\n\n24 - CONDIÇÕES DO CONTRATO\nFaturação Eletrónica: Permitido\nObrigação de Subcontratação:\nCódigo da Obrigação de Subcontratação: Não é aplicável nenhuma obrigação de subcontratação.\n\n25 - COMPRA PÚBLICA ESTRATÉGICA\nCompra Pública Estratégica: Inexistência de contratação pública estratégica\n\n26 - INFORMAÇÕES ADICIONAIS\nContrato adequado para PME: Não\nCobertura ACP (Acordo dos Contratos Públicos da Organização Mundial do Comércio): Não\n\n27 - IDENTIFICAÇÃO E CONTACTOS DO ÓRGÃO DE RECURSOS ADMINISTRATIVOS\nDesignação: Direção da A.R.C.I.L.\nEndereço: Rua Francisco Fernandes | 6\nCódigo postal: 3200-065\nLocalidade: Lousã\nTelefone: 239990300\nFax: \nEndereço eletrónico: arcil@arcil.org\nPrazo de interposição do recurso: 30 dias\n\n28 - IDENTIFICAÇÃO DO(S) AUTOR(ES) DE ANÚNCIO\nNome: Tiago Duarte Simões\nCargo: Chefe de Serviços Gerais\n419426582",
    "nipc": "501227083",
    "distrito": "Coimbra",
    "concelho": "Lousã",
    "freguesia": "União das Freguesias de Lousã e Vilarinho",
    "site": "https://arcil.org.pt/",
    "email": "arcil@arcil.org",
    "designacao_contrato": "Aquisição de veículo elétrico novo com transformação no âmbito do programa PRR - N.º 12/C03-i01/2024 RE-C03-i01.m04  Mobilidade Verde Social",
    "descricao": "Aquisição de veículo elétrico novo com transformação no âmbito do programa PRR - N.º 12/C03-i01/2024 RE-C03-i01.m04  Mobilidade Verde Social",
    "preco_base": "46.595,00 EUR",
    "prazo_execucao": "120 DIAS",
    "prazo_apresentacao_propostas": "27-08-2025 18:00",
    "fundos_eu": "Não",
    "plataforma_eletronica": "ACIN",
    "url_procedimento": "https://www.acingov.pt",
    "autor_nome": "Tiago Duarte Simões",
    "autor_cargo": "Chefe de Serviços Gerais"
  },
  {
    "numero_procedimento": "N/A",
    "entidade": "Direção-Geral da Administração Escolar",
    "link": "https://diariodarepublica.pt/dr/detalhe/contrato-publico/21755-928825107",
    "detalhes_completos": "1 - IDENTIFICAÇÃO E CONTACTOS DA ENTIDADE ADJUDICANTE\nDesignação da entidade adjudicante: Direção-Geral da Administração Escolar\nNIPC: 600084817\nServiço/Órgão/Pessoa de contacto: Direção-Geral da Administração Escolar, Serviço der Património, com sede na Avenida 24 de Julho, n.º 142, 1399-024 Lisboa, com o\nEndereço: Av. 24 de Julho, nº 142\nCódigo postal: 1399-024\nLocalidade: Lisboa\nPaís: Portugal\nNUT III: PT170\nDistrito: Lisboa\nConcelho: Lisboa\nFreguesia: Freguesia da Estrela\nTelefone: 213938600\nFax: 213943491\nEndereço da Entidade (URL): http://www.dgae.mec.pt/_main/\nEndereço Eletrónico: contratacao@dgae.medu.pt\neDelivery Gateway (URL): https://www.acingov.pt\nFunção da Organização: Adquirente\nSubfunção da Organização: Organização cujo orçamento é utilizado para pagar o contrato; Organização que executa o pagamento; Líder do grupo; Organização que fornece informações adicionais sobre o processo de adjudicação; Organização que fornece mais informações sobre os prazos dos procedimentos de recurso; Organização que fornece acesso fora de linha aos documentos do concurso; Organização responsável pelo tratamento das propostas; Organização que recebe as propostas; Organização que trata os pedidos de participação; Organização que recebe pedidos de participação; Organização que fornece mais informações sobre os procedimentos de recurso; Organização que assina o contrato\nNorma jurídica da Entidade Adjudicante: Organismo de direito público\nÁrea de atividade da Autoridade Adjudicante: Educação\n\n2 - JORNAL OFICIAL DA UNIÃO EUROPEIA\nO procedimento a que este anúncio diz respeito também é publicitado no Jornal Oficial da União Europeia? Não\n\n3 - AVISO\nModelo de Anúncio: Concurso público\nData de Envio do Anúncio: 12-08-2025\n\n5 - PROCESSO\nTipo de Procedimento: Concurso público\nPreço base do procedimento: Sim\nValor do preço base do procedimento: 98.982,00 EUR\nProcedimento com lotes? Sim\nNº Máx. de Lotes Autorizado: 2\nNúmero máximo de lotes que podem ser adjudicados a um concorrente: 2\n\n6 - OBJETO DO CONTRATO\nNúmero de referência interna: CPN/003/DGAE/2025\nDesignação do contrato: AQUISIÇÃO DE SERVIÇOS DE MÉDICOS PARA REALIZAÇÃO DE JUNTAS MÉDICAS/2025-2026\nDescrição: AQUISIÇÃO DE SERVIÇOS DE MÉDICOS PARA REALIZAÇÃO DE JUNTAS MÉDICAS/2025-2026\nTipo de Contrato Principal: Aquisição de Serviços\nTipo de Contrato: Aquisição de Serviços\nClassificação CPV (Vocabulário Comum para os Contratos Públicos)\nObjeto principal\nVocabulário Principal: 85100000\nPreço base s/IVA: 98.982,00 EUR\nLotes: \nNº: LOT-0001\nDescrição do Lote: Serviço de Junta Médica - Norte/Centro\nPreço base s/IVA: 66.549,60 EUR\nClassificação CPV (Vocabulário Comum para os Contratos Públicos)\nObjeto principal\nVocabulário Principal: 85100000\nNº: LOT-0002\nDescrição do Lote: Serviço de Junta Médica - Lisboa e Vale do Tejo/Alentejo/Algarve\nPreço base s/IVA: 32.432,40 EUR\nClassificação CPV (Vocabulário Comum para os Contratos Públicos)\nObjeto principal\nVocabulário Principal: 85100000\n\n7 - INDICAÇÕES ADICIONAIS\nO contrato envolve aquisição conjunta (satisfação de várias entidades)? Não\nO contrato é adjudicado por uma central de compras? Não\n\n8 - TÉCNICAS\nO concurso destina-se à celebração de um acordo-quadro? Inexistência de acordo-quadro\nÉ utilizado um leilão eletrónico? Não\nÉ adotada uma fase de negociação? Não\nSistema de Aquisição Dinâmico: Inexistência de sistema de aquisição dinâmico\n\n9 - LOCAL DA EXECUÇÃO DO CONTRATO\nLOCAL DA EXECUÇÃO DO CONTRATO (PROCEDIMENTO)\nPaís: Portugal\nNUT III: PT170\nLocalidade: Freguesia da Estrela\nDistrito: Lisboa\nConcelho: Lisboa\nFreguesia: Freguesia da Estrela\nLOCAL DA EXECUÇÃO DO CONTRATO (LOTE)\nIdentificador do Lote: LOT-0001; LOT-0002\nPaís: Portugal\nNUT III: PT170\nLocalidade: Freguesia da Estrela\nDistrito: Lisboa\nConcelho: Lisboa\nFreguesia: Freguesia da Estrela\n\n10 - PRAZO DE EXECUÇÃO DO CONTRATO\nIdentificador do Lote: LOT-0001; LOT-0002\nPrazo de execução do contrato: 10 MESES\nPrevisão de renovações: Não\n\n11 - FUNDOS EU\nIdentificador do Lote: LOT-0001; LOT-0002\nTêm fundos EU? Não\n\n12 - DOCUMENTOS DE HABILITAÇÃO\nHabilitação para o exercício da atividade profissional: Não\n\n13 - CONDIÇÕES DE APRESENTAÇÃO\nPlataforma eletrónica utilizada pela entidade adjudicante: ACIN\nURL para Apresentação: https://www.acingov.pt\nAdmissibilidade da apresentação de propostas variantes: Não autorizado\nPrazo para apresentação das propostas: 18-08-2025 23:59\nPrazo durante o qual os concorrentes são obrigados a manter as respetivas propostas: 66 dias a contar do termo do prazo para a apresentação das propostas\nIndicação de Subcontratação na Proposta: Inexistência de indicação de subcontratação\n\n14 - PRESTAÇÃO DE CAUÇÃO\nPrestação de caução: Não\n\n15 - FORNECIMENTO DAS PEÇAS DO CONCURSO, APRESENTAÇÃO DE PEDIDOS DE PARTICIPAÇÃO E APRESENTAÇÃO DAS PROPOSTAS\nLink para acesso às peças do concurso (URL): https://www.acingov.pt/acingovprod/2/zonaPublica/zona_publica_c/donwloadProcedurePiece/OTMzMzkw\n\n20 - OUTROS REQUISITOS\nIdentificador do Lote: LOT-0001; LOT-0002\nInformação sobre contratos reservados. Aplica-se a contratos reservados (54º-A)? Não\n\n21 - CRITÉRIO DE ADJUDICAÇÃO\nO Critério de adjudicação é diferenciado por lote? Não\nMultifator: Não\nMonofator:\nNome: Preço\n\n24 - CONDIÇÕES DO CONTRATO\nIdentificador do Lote: LOT-0001; LOT-0002\nFaturação Eletrónica: Permitido\nObrigação de Subcontratação:\nCódigo da Obrigação de Subcontratação: Não é aplicável nenhuma obrigação de subcontratação.\n\n25 - COMPRA PÚBLICA ESTRATÉGICA\nCompra Pública Estratégica: Inexistência de contratação pública estratégica\n\n26 - INFORMAÇÕES ADICIONAIS\nIdentificador do Lote: LOT-0001; LOT-0002\nContrato adequado para PME: Não\nCobertura ACP (Acordo dos Contratos Públicos da Organização Mundial do Comércio): Não\n\n27 - IDENTIFICAÇÃO E CONTACTOS DO ÓRGÃO DE RECURSOS ADMINISTRATIVOS\nDesignação: Tribunal Administrativo do Circulo de Lisboa\nEndereço: Av D. João II, Bloco G, piso 6-8, nº 1.08.01\nCódigo postal: 1990-097\nLocalidade: Lisboa\nTelefone: 218367100\nFax: \nEndereço eletrónico: lisboa.tacl@tribunais.org.pt\n\n28 - IDENTIFICAÇÃO DO(S) AUTOR(ES) DE ANÚNCIO\nNome: Maria Inês Ângelo Borges Monteiro Soares\nCargo: Diretora de Serviços de Gestão e Planeamento\n419428291",
    "nipc": "600084817",
    "distrito": "Lisboa",
    "concelho": "Lisboa",
    "freguesia": "Freguesia da Estrela",
    "site": "http://www.dgae.mec.pt/_main/",
    "email": "contratacao@dgae.medu.pt",
    "designacao_contrato": "AQUISIÇÃO DE SERVIÇOS DE MÉDICOS PARA REALIZAÇÃO DE JUNTAS MÉDICAS/2025-2026",
    "descricao": "AQUISIÇÃO DE SERVIÇOS DE MÉDICOS PARA REALIZAÇÃO DE JUNTAS MÉDICAS/2025-2026",
    "preco_base": "98.982,00 EUR",
    "prazo_execucao": "10 MESES",
    "prazo_apresentacao_propostas": "18-08-2025 23:59",
    "fundos_eu": "Não",
    "plataforma_eletronica": "ACIN",
    "url_procedimento": "https://www.acingov.pt",
    "autor_nome": "Maria Inês Ângelo Borges Monteiro Soares",
    "autor_cargo": "Diretora de Serviços de Gestão e Planeamento"
  },
  {
    "numero_procedimento": "N/A",
    "entidade": "Instituto Nacional de Saúde Doutor Ricardo Jorge, IP",
    "link": "https://diariodarepublica.pt/dr/detalhe/contrato-publico/21757-928825108",
    "detalhes_completos": "1 - IDENTIFICAÇÃO E CONTACTOS DA ENTIDADE ADJUDICANTE\nDesignação da entidade adjudicante: Instituto Nacional de Saúde Doutor Ricardo Jorge, IP\nNIPC: 501427511\nEndereço: Avenida Padre Cruz\nCódigo postal: 1649-016\nLocalidade: LISBOA\nPaís: Portugal\nNUT III: PTZZZ\nDistrito: Todos\nConcelho: Todos\nFreguesia: Todas\nTelefone: 217319200\nEndereço da Entidade (URL): https://www.insa.pt/\nEndereço Eletrónico: drf.aprov@insa.min-saude.pt\neDelivery Gateway (URL): https://www.acingov.pt\nFunção da Organização: Adquirente\nNorma jurídica da Entidade Adjudicante: Organismo de direito público\nÁrea de atividade da Autoridade Adjudicante: Serviços públicos das administrações públicas\n\n2 - JORNAL OFICIAL DA UNIÃO EUROPEIA\nO procedimento a que este anúncio diz respeito também é publicitado no Jornal Oficial da União Europeia? Não\n\n3 - AVISO\nModelo de Anúncio: Concurso público\nData de Envio do Anúncio: 12-08-2025\n\n5 - PROCESSO\nTipo de Procedimento: Concurso público\nPreço base do procedimento: Sim\nValor do preço base do procedimento: 170.736,00 EUR\nProcedimento com lotes? Sim\nNº Máx. de Lotes Autorizado: 4\nNúmero máximo de lotes que podem ser adjudicados a um concorrente: 4\n\n6 - OBJETO DO CONTRATO\nNúmero de referência interna: CP 36-2025\nDesignação do contrato: CP 36-2025 Aquisição de reagentes para sequenciação de nova geração\nDescrição: CP 36-2025 Aquisição de reagentes para sequenciação de nova geração \nTipo de Contrato Principal: Aquisição de Bens Móveis\nTipo de Contrato: Aquisição de Bens Móveis\nClassificação CPV (Vocabulário Comum para os Contratos Públicos)\nObjeto principal\nVocabulário Principal: 33696500\nPreço base s/IVA: 170.736,00 EUR\nLotes: \nNº: LOT-0001\nDescrição do Lote: reagentes para sequenciação de nova geração\nPreço base s/IVA: 101.520,00 EUR\nClassificação CPV (Vocabulário Comum para os Contratos Públicos)\nObjeto principal\nVocabulário Principal: 33696500\nNº: LOT-0002\nDescrição do Lote: reagentes para sequenciação de nova geração\nPreço base s/IVA: 1.416,00 EUR\nClassificação CPV (Vocabulário Comum para os Contratos Públicos)\nObjeto principal\nVocabulário Principal: 33696500\nNº: LOT-0003\nDescrição do Lote: reagentes para sequenciação de nova geração\nPreço base s/IVA: 7.800,00 EUR\nClassificação CPV (Vocabulário Comum para os Contratos Públicos)\nObjeto principal\nVocabulário Principal: 33696500\nNº: LOT-0004\nDescrição do Lote: reagentes para sequenciação de nova geração\nPreço base s/IVA: 60.000,00 EUR\nClassificação CPV (Vocabulário Comum para os Contratos Públicos)\nObjeto principal\nVocabulário Principal: 33696500\n\n7 - INDICAÇÕES ADICIONAIS\nO contrato envolve aquisição conjunta (satisfação de várias entidades)? Não\nO contrato é adjudicado por uma central de compras? Não\n\n8 - TÉCNICAS\nO concurso destina-se à celebração de um acordo-quadro? Inexistência de acordo-quadro\nÉ utilizado um leilão eletrónico? Não\nÉ adotada uma fase de negociação? Não\nSistema de Aquisição Dinâmico: Inexistência de sistema de aquisição dinâmico\n\n9 - LOCAL DA EXECUÇÃO DO CONTRATO\nLOCAL DA EXECUÇÃO DO CONTRATO (PROCEDIMENTO)\nPaís: Portugal\nNUT III: PT170\nLocalidade: Freguesia de Lumiar\nDistrito: Lisboa\nConcelho: Lisboa\nFreguesia: Freguesia de Lumiar\nPaís: Portugal\nNUT III: PT11A\nLocalidade: União das Freguesias de Cedofeita, Santo Ildefonso, Sé, Miragaia, São Nicolau e Vitória\nDistrito: Porto\nConcelho: Porto\nFreguesia: União das Freguesias de Cedofeita, Santo Ildefonso, Sé, Miragaia, São Nicolau e Vitória\nPaís: Portugal\nNUT III: PT170\nLocalidade: União das Freguesias de Poceirão e Marateca\nDistrito: Setúbal\nConcelho: Palmela\nFreguesia: União das Freguesias de Poceirão e Marateca\nLOCAL DA EXECUÇÃO DO CONTRATO (LOTE)\nIdentificador do Lote: LOT-0001; LOT-0002; LOT-0003; LOT-0004\nPaís: Portugal\nNUT III: PT170\nLocalidade: Freguesia de Lumiar\nDistrito: Lisboa\nConcelho: Lisboa\nFreguesia: Freguesia de Lumiar\nIdentificador do Lote: LOT-0001; LOT-0002; LOT-0003; LOT-0004\nPaís: Portugal\nNUT III: PT170\nLocalidade: União das Freguesias de Poceirão e Marateca\nDistrito: Setúbal\nConcelho: Palmela\nFreguesia: União das Freguesias de Poceirão e Marateca\nIdentificador do Lote: LOT-0001; LOT-0002; LOT-0003; LOT-0004\nPaís: Portugal\nNUT III: PT11A\nLocalidade: União das Freguesias de Cedofeita, Santo Ildefonso, Sé, Miragaia, São Nicolau e Vitória\nDistrito: Porto\nConcelho: Porto\nFreguesia: União das Freguesias de Cedofeita, Santo Ildefonso, Sé, Miragaia, São Nicolau e Vitória\n\n10 - PRAZO DE EXECUÇÃO DO CONTRATO\nIdentificador do Lote: LOT-0001; LOT-0002; LOT-0003; LOT-0004\nPrazo de execução do contrato: 163 DIAS\nPrevisão de renovações: Não\n\n11 - FUNDOS EU\nIdentificador do Lote: LOT-0001; LOT-0002; LOT-0003; LOT-0004\nTêm fundos EU? Não\n\n12 - DOCUMENTOS DE HABILITAÇÃO\nHabilitação para o exercício da atividade profissional: Não\n\n13 - CONDIÇÕES DE APRESENTAÇÃO\nPlataforma eletrónica utilizada pela entidade adjudicante: ACIN\nURL para Apresentação: https://www.acingov.pt\nAdmissibilidade da apresentação de propostas variantes: Não autorizado\nPrazo para apresentação das propostas: 20-08-2025 23:59\nPrazo durante o qual os concorrentes são obrigados a manter as respetivas propostas: 66 dias a contar do termo do prazo para a apresentação das propostas\nIndicação de Subcontratação na Proposta: Inexistência de indicação de subcontratação\n\n14 - PRESTAÇÃO DE CAUÇÃO\nPrestação de caução: Não\n\n15 - FORNECIMENTO DAS PEÇAS DO CONCURSO, APRESENTAÇÃO DE PEDIDOS DE PARTICIPAÇÃO E APRESENTAÇÃO DAS PROPOSTAS\nLink para acesso às peças do concurso (URL): https://www.acingov.pt/acingovprod/2/zonaPublica/zona_publica_c/donwloadProcedurePiece/OTE2OTcy\n\n20 - OUTROS REQUISITOS\nIdentificador do Lote: LOT-0001; LOT-0002; LOT-0003; LOT-0004\nInformação sobre contratos reservados. Aplica-se a contratos reservados (54º-A)? Não\n\n21 - CRITÉRIO DE ADJUDICAÇÃO\nO Critério de adjudicação é diferenciado por lote? Não\nMultifator: Não\nMonofator:\nNome: Preço\n\n24 - CONDIÇÕES DO CONTRATO\nIdentificador do Lote: LOT-0001; LOT-0002; LOT-0003; LOT-0004\nFaturação Eletrónica: Permitido\nObrigação de Subcontratação:\nCódigo da Obrigação de Subcontratação: Não é aplicável nenhuma obrigação de subcontratação.\n\n25 - COMPRA PÚBLICA ESTRATÉGICA\nCompra Pública Estratégica: Inexistência de contratação pública estratégica\n\n26 - INFORMAÇÕES ADICIONAIS\nIdentificador do Lote: LOT-0001; LOT-0002; LOT-0003; LOT-0004\nContrato adequado para PME: Não\nCobertura ACP (Acordo dos Contratos Públicos da Organização Mundial do Comércio): Não\n\n27 - IDENTIFICAÇÃO E CONTACTOS DO ÓRGÃO DE RECURSOS ADMINISTRATIVOS\nDesignação: O Presidente do Conselho Diretivo\nEndereço: Av. Padre Cruz\nCódigo postal: 1649-016\nLocalidade: Lisboa\nTelefone: 217519200\nFax: 917519390\nEndereço eletrónico: drf.aprov@insa.min-saude.pt\nPrazo de interposição do recurso: 5 dias\n\n28 - IDENTIFICAÇÃO DO(S) AUTOR(ES) DE ANÚNCIO\nNome: Fernando de Almeida\nCargo: Presidente do Conselho Diretivo\n419430712",
    "nipc": "501427511",
    "distrito": "Todos",
    "concelho": "Todos",
    "freguesia": "Todas",
    "site": "https://www.insa.pt/",
    "email": "drf.aprov@insa.min-saude.pt",
    "designacao_contrato": "CP 36-2025 Aquisição de reagentes para sequenciação de nova geração",
    "descricao": "CP 36-2025 Aquisição de reagentes para sequenciação de nova geração",
    "preco_base": "170.736,00 EUR",
    "prazo_execucao": "163 DIAS",
    "prazo_apresentacao_propostas": "20-08-2025 23:59",
    "fundos_eu": "Não",
    "plataforma_eletronica": "ACIN",
    "url_procedimento": "https://www.acingov.pt",
    "autor_nome": "Fernando de Almeida",
    "autor_cargo": "Presidente do Conselho Diretivo"
  },
  {
    "numero_procedimento": "N/A",
    "entidade": "Município de Silves",
    "link": "https://diariodarepublica.pt/dr/detalhe/contrato-publico/21760-928825109",
    "detalhes_completos": "1 - IDENTIFICAÇÃO E CONTACTOS DA ENTIDADE ADJUDICANTE\nDesignação da entidade adjudicante: Município de Silves\nNIPC: 506818837\nServiço/Órgão/Pessoa de contacto: Divisão de Obras Municipais e Trânsito\nEndereço: Rua da Sé, 6 - 1º\nCódigo postal: 8300-175\nLocalidade: Silves\nPaís: Portugal\nNUT III: PT150\nDistrito: Faro\nConcelho: Silves\nFreguesia: União das Freguesias de Alcantarilha e Pêra\nTelefone: 282440800\nFax: 282440850\nEndereço da Entidade (URL): www.cm-silves.pt\nEndereço Eletrónico: obras.municipais@cm-silves.pt\neDelivery Gateway (URL): https://www.acingov.pt\nFunção da Organização: Adquirente\nNorma jurídica da Entidade Adjudicante: Organismo de direito público\nÁrea de atividade da Autoridade Adjudicante: Serviços públicos das administrações públicas\n\n2 - JORNAL OFICIAL DA UNIÃO EUROPEIA\nO procedimento a que este anúncio diz respeito também é publicitado no Jornal Oficial da União Europeia? Não\n\n3 - AVISO\nModelo de Anúncio: Concurso público\nData de Envio do Anúncio: 13-08-2025\n\n5 - PROCESSO\nTipo de Procedimento: Concurso público\nPreço base do procedimento: Sim\nValor do preço base do procedimento: 359.578,90 EUR\nProcedimento com lotes? Não\n\n6 - OBJETO DO CONTRATO\nNúmero de referência interna: 1346/DOMT\nDesignação do contrato: AMPLIAÇÃO DA EB1 DE ALCANTARILHA\nDescrição: AMPLIAÇÃO DA EB1 DE ALCANTARILHA\nTipo de Contrato Principal: Empreitada de Obras Públicas\nTipo de Contrato: Empreitada de Obras Públicas\nClassificação CPV (Vocabulário Comum para os Contratos Públicos)\nObjeto principal\nVocabulário Principal: 45214210\nPreço base s/IVA: 359.578,90 EUR\n\n7 - INDICAÇÕES ADICIONAIS\nO contrato envolve aquisição conjunta (satisfação de várias entidades)? Não\nO contrato é adjudicado por uma central de compras? Não\n\n8 - TÉCNICAS\nO concurso destina-se à celebração de um acordo-quadro? Inexistência de acordo-quadro\nÉ utilizado um leilão eletrónico? Não\nÉ adotada uma fase de negociação? Não\nSistema de Aquisição Dinâmico: Inexistência de sistema de aquisição dinâmico\n\n9 - LOCAL DA EXECUÇÃO DO CONTRATO\nLOCAL DA EXECUÇÃO DO CONTRATO (PROCEDIMENTO)\nPaís: Portugal\nNUT III: PT150\nLocalidade: União das Freguesias de Alcantarilha e Pêra\nDistrito: Faro\nConcelho: Silves\nFreguesia: União das Freguesias de Alcantarilha e Pêra\n\n10 - PRAZO DE EXECUÇÃO DO CONTRATO\nPrazo de execução do contrato: 240 DIAS\nPrevisão de renovações: Não\n\n11 - FUNDOS EU\nTêm fundos EU? Não\n\n12 - DOCUMENTOS DE HABILITAÇÃO\nHabilitação para o exercício da atividade profissional: Sim\nTipo: Alvará\nDescrição: 2.ª subcategoria da 1.ª categoria, em classe que cubra o valor global da proposta, e\n1.ª, 4.ª, 5.ª e 8.ª subcategorias da 1.ª categoria, 1.ª e 12.ª subcategoria da 4.ª categoria e 11.ª subcategoria da 5.ª categoria, tudo em classe que cubra o valor dos respetivos trabalhos na proposta.\n\n13 - CONDIÇÕES DE APRESENTAÇÃO\nPlataforma eletrónica utilizada pela entidade adjudicante: ACIN\nURL para Apresentação: https://www.acingov.pt\nAdmissibilidade da apresentação de propostas variantes: Não autorizado\nPrazo para apresentação das propostas: 12-09-2025 23:59\nPrazo durante o qual os concorrentes são obrigados a manter as respetivas propostas: 120 dias a contar do termo do prazo para a apresentação das propostas\nIndicação de Subcontratação na Proposta: Inexistência de indicação de subcontratação\n\n14 - PRESTAÇÃO DE CAUÇÃO\nPrestação de caução: Sim\nPercentagem: 5%\nDescrição da Garantia Exigida: O valor da caução é de 5.00% do preço contratual.\n\n15 - FORNECIMENTO DAS PEÇAS DO CONCURSO, APRESENTAÇÃO DE PEDIDOS DE PARTICIPAÇÃO E APRESENTAÇÃO DAS PROPOSTAS\nLink para acesso às peças do concurso (URL): https://www.acingov.pt/acingovprod/2/zonaPublica/zona_publica_c/donwloadProcedurePiece/OTMyMjEx\n\n20 - OUTROS REQUISITOS\nInformação sobre contratos reservados. Aplica-se a contratos reservados (54º-A)? Não\n\n21 - CRITÉRIO DE ADJUDICAÇÃO\nMultifator: Não\nMonofator:\nNome: Preço\n\n24 - CONDIÇÕES DO CONTRATO\nFaturação Eletrónica: Permitido\nObrigação de Subcontratação:\nCódigo da Obrigação de Subcontratação: Não é aplicável nenhuma obrigação de subcontratação.\n\n25 - COMPRA PÚBLICA ESTRATÉGICA\nCompra Pública Estratégica: Inexistência de contratação pública estratégica\n\n26 - INFORMAÇÕES ADICIONAIS\nContrato adequado para PME: Sim\nCobertura ACP (Acordo dos Contratos Públicos da Organização Mundial do Comércio): Não\n\n27 - IDENTIFICAÇÃO E CONTACTOS DO ÓRGÃO DE RECURSOS ADMINISTRATIVOS\nDesignação: Município de Silves\nEndereço: Largo do Município\nCódigo postal: 8300-117\nLocalidade: Silves\nTelefone: 282440800\nFax: 282440850\nEndereço eletrónico: gabinete.presidente@cm-silves.pt\nPrazo de interposição do recurso: 5 dias\n\n28 - IDENTIFICAÇÃO DO(S) AUTOR(ES) DE ANÚNCIO\nNome: Rosa Cristina Gonçalves da Palma\nCargo: Presidente da Câmara\n419417818",
    "nipc": "506818837",
    "distrito": "Faro",
    "concelho": "Silves",
    "freguesia": "União das Freguesias de Alcantarilha e Pêra",
    "site": "www.cm-silves.pt",
    "email": "obras.municipais@cm-silves.pt",
    "designacao_contrato": "AMPLIAÇÃO DA EB1 DE ALCANTARILHA",
    "descricao": "AMPLIAÇÃO DA EB1 DE ALCANTARILHA",
    "preco_base": "359.578,90 EUR",
    "prazo_execucao": "240 DIAS",
    "prazo_apresentacao_propostas": "12-09-2025 23:59",
    "fundos_eu": "Não",
    "plataforma_eletronica": "ACIN",
    "url_procedimento": "https://www.acingov.pt",
    "autor_nome": "Rosa Cristina Gonçalves da Palma",
    "autor_cargo": "Presidente da Câmara"
  },
  {
    "numero_procedimento": "N/A",
    "entidade": "Município de Sintra",
    "link": "https://diariodarepublica.pt/dr/detalhe/contrato-publico/21762-928825110",
    "detalhes_completos": "1 - IDENTIFICAÇÃO E CONTACTOS DA ENTIDADE ADJUDICANTE\nDesignação da entidade adjudicante: Município de Sintra\nNIPC: 500051062\nEndereço: Largo Doutor Virgílio Horta\nCódigo postal: 2710-501\nLocalidade: Lisboa\nPaís: Portugal\nNUT III: PT170\nDistrito: Lisboa\nConcelho: Sintra\nFreguesia: União das Freguesias de Sintra (Santa Maria e São Miguel, São Martinho e São Pedro de Penaferrim)\nTelefone: 219238749\nFax: 219238790\nEndereço da Entidade (URL): www.cm-sintra.pt\nEndereço Eletrónico: dcp@cm-sintra.pt\neDelivery Gateway (URL): https://community.vortal.biz/public/\nFunção da Organização: Adquirente\nNorma jurídica da Entidade Adjudicante: Autoridade local\nÁrea de atividade da Autoridade Adjudicante: Serviços públicos das administrações públicas\n\n2 - JORNAL OFICIAL DA UNIÃO EUROPEIA\nO procedimento a que este anúncio diz respeito também é publicitado no Jornal Oficial da União Europeia? Não\n\n3 - AVISO\nModelo de Anúncio: Concurso público\nData de Envio do Anúncio: 13-08-2025\n\n5 - PROCESSO\nTipo de Procedimento: Concurso público\nPreço base do procedimento: Sim\nValor do preço base do procedimento: 15.000,00 EUR\nProcedimento com lotes? Não\n\n6 - OBJETO DO CONTRATO\nNúmero de referência interna: CT-25/00995\nDesignação do contrato: Limpeza e desinfestação dos fogos e edifícios do Parque Habitacional Municipal, em RFC, por 12 meses\nDescrição: Limpeza e desinfestação dos fogos e edifícios do Parque Habitacional Municipal, em RFC, por 12 meses\nTipo de Contrato Principal: Aquisição de Serviços\nTipo de Contrato: Aquisição de Serviços\nClassificação CPV (Vocabulário Comum para os Contratos Públicos)\nObjeto principal\nVocabulário Principal: 90910000\nPreço base s/IVA: 15.000,00 EUR\n\n7 - INDICAÇÕES ADICIONAIS\nO contrato envolve aquisição conjunta (satisfação de várias entidades)? Não\nO contrato é adjudicado por uma central de compras? Não\n\n8 - TÉCNICAS\nO concurso destina-se à celebração de um acordo-quadro? Inexistência de acordo-quadro\nÉ utilizado um leilão eletrónico? Não\nÉ adotada uma fase de negociação? Não\nSistema de Aquisição Dinâmico: Inexistência de sistema de aquisição dinâmico\n\n9 - LOCAL DA EXECUÇÃO DO CONTRATO\nLOCAL DA EXECUÇÃO DO CONTRATO (PROCEDIMENTO)\nPaís: Portugal\nNUT III: PT170\nLocalidade: Lisboa\nDistrito: Lisboa\nConcelho: Sintra\nFreguesia: União das Freguesias de Sintra (Santa Maria e São Miguel, São Martinho e São Pedro de Penaferrim)\n\n10 - PRAZO DE EXECUÇÃO DO CONTRATO\nPrazo de execução do contrato: 12 MESES\nPrevisão de renovações: Não\n\n11 - FUNDOS EU\nTêm fundos EU? Não\n\n12 - DOCUMENTOS DE HABILITAÇÃO\nHabilitação para o exercício da atividade profissional: Não\n\n13 - CONDIÇÕES DE APRESENTAÇÃO\nPlataforma eletrónica utilizada pela entidade adjudicante: VORTAL\nURL para Apresentação: https://community.vortal.biz/public/\nAdmissibilidade da apresentação de propostas variantes: Não autorizado\nPrazo para apresentação das propostas: 28-08-2025 18:00\nPrazo durante o qual os concorrentes são obrigados a manter as respetivas propostas: 66 dias a contar do termo do prazo para a apresentação das propostas\nIndicação de Subcontratação na Proposta: Inexistência de indicação de subcontratação\n\n14 - PRESTAÇÃO DE CAUÇÃO\nPrestação de caução: Sim\nPercentagem: 5%\nDescrição da Garantia Exigida: Conforme Programa de Concurso e Caderno de Encargos.\n\n15 - FORNECIMENTO DAS PEÇAS DO CONCURSO, APRESENTAÇÃO DE PEDIDOS DE PARTICIPAÇÃO E APRESENTAÇÃO DAS PROPOSTAS\nLink para acesso às peças do concurso (URL): https://community.vortal.biz/Public/public-tender-documents/Nzk1bHpsYWE2c3JlRHdnRzZRRnh4dlpqTkl2d1VJYWc3UGpXT0xoNjMwaVJRK0xjbmlZNFhxQVl2aENrcTRaZ0VVODRHTDJSc0o2NGJVS21wN0I0RHc9PWtuUW41\n\n20 - OUTROS REQUISITOS\nInformação sobre contratos reservados. Aplica-se a contratos reservados (54º-A)? Não\n\n21 - CRITÉRIO DE ADJUDICAÇÃO\nMultifator: Não\nMonofator:\nNome: Preço\n\n24 - CONDIÇÕES DO CONTRATO\nFaturação Eletrónica: Permitido\nObrigação de Subcontratação:\nCódigo da Obrigação de Subcontratação: Não é aplicável nenhuma obrigação de subcontratação.\n\n25 - COMPRA PÚBLICA ESTRATÉGICA\nCompra Pública Estratégica: Inexistência de contratação pública estratégica\n\n26 - INFORMAÇÕES ADICIONAIS\nContrato adequado para PME: Sim\nCobertura ACP (Acordo dos Contratos Públicos da Organização Mundial do Comércio): Não\n\n27 - IDENTIFICAÇÃO E CONTACTOS DO ÓRGÃO DE RECURSOS ADMINISTRATIVOS\nDesignação: Presidente da Câmara Municipal de Sintra\nEndereço: Largo Dr. Virgílio Horta\nCódigo postal: 2714-501\nLocalidade: Sintra\nTelefone: +351 219238744\nFax: +351 219238790\nEndereço eletrónico: dcp@cm-sintra.pt\n\n28 - IDENTIFICAÇÃO DO(S) AUTOR(ES) DE ANÚNCIO\nNome: Basílio Horta\nCargo: Presidente da Câmara Municipal de Sintra\n419426988",
    "nipc": "500051062",
    "distrito": "Lisboa",
    "concelho": "Sintra",
    "freguesia": "União das Freguesias de Sintra (Santa Maria e São Miguel, São Martinho e São Pedro de Penaferrim)",
    "site": "www.cm-sintra.pt",
    "email": "dcp@cm-sintra.pt",
    "designacao_contrato": "Limpeza e desinfestação dos fogos e edifícios do Parque Habitacional Municipal, em RFC, por 12 meses",
    "descricao": "Limpeza e desinfestação dos fogos e edifícios do Parque Habitacional Municipal, em RFC, por 12 meses",
    "preco_base": "15.000,00 EUR",
    "prazo_execucao": "12 MESES",
    "prazo_apresentacao_propostas": "28-08-2025 18:00",
    "fundos_eu": "Não",
    "plataforma_eletronica": "VORTAL",
    "url_procedimento": "https://community.vortal.biz/public/",
    "autor_nome": "Basílio Horta",
    "autor_cargo": "Presidente da Câmara Municipal de Sintra"
  }
]