[
  {
    "numero_procedimento": "N/A",
    "entidade": "AnÃºncio de procedimento  n.Âº 21865/2025  -  DiÃ¡rio da RepÃºblica n.Âº 156/2025, SÃ©rie II de 2025-08-14",
    "link": "https://diariodarepublica.pt/dr/detalhe/contrato-publico/21865-928937289"
  },
  {
    "numero_procedimento": "N/A",
    "entidade": "AnÃºncio de procedimento  n.Âº 21866/2025  -  DiÃ¡rio da RepÃºblica n.Âº 156/2025, SÃ©rie II de 2025-08-14",
    "link": "https://diariodarepublica.pt/dr/detalhe/contrato-publico/21866-928937290"
  },
  {
    "numero_procedimento": "N/A",
    "entidade": "AnÃºncio de procedimento  n.Âº 21867/2025  -  DiÃ¡rio da RepÃºblica n.Âº 156/2025, SÃ©rie II de 2025-08-14",
    "link": "https://diariodarepublica.pt/dr/detalhe/contrato-publico/21867-928937291"
  },
  {
    "numero_procedimento": "N/A",
    "entidade": "AnÃºncio de procedimento  n.Âº 21868/2025  -  DiÃ¡rio da RepÃºblica n.Âº 156/2025, SÃ©rie II de 2025-08-14",
    "link": "https://diariodarepublica.pt/dr/detalhe/contrato-publico/21868-928937292"
  },
  {
    "numero_procedimento": "N/A",
    "entidade": "AnÃºncio de procedimento  n.Âº 21869/2025  -  DiÃ¡rio da RepÃºblica n.Âº 156/2025, SÃ©rie II de 2025-08-14",
    "link": "https://diariodarepublica.pt/dr/detalhe/contrato-publico/21869-928937293"
  },
  {
    "numero_procedimento": "N/A",
    "entidade": "AnÃºncio de procedimento  n.Âº 21875/2025  -  DiÃ¡rio da RepÃºblica n.Âº 156/2025, SÃ©rie II de 2025-08-14",
    "link": "https://diariodarepublica.pt/dr/detalhe/contrato-publico/21875-928937294"
  },
  {
    "numero_procedimento": "N/A",
    "entidade": "AnÃºncio de procedimento  n.Âº 21881/2025  -  DiÃ¡rio da RepÃºblica n.Âº 156/2025, SÃ©rie II de 2025-08-14",
    "link": "https://diariodarepublica.pt/dr/detalhe/contrato-publico/21881-928937295"
  },
  {
    "numero_procedimento": "N/A",
    "entidade": "AnÃºncio de procedimento  n.Âº 21882/2025  -  DiÃ¡rio da RepÃºblica n.Âº 156/2025, SÃ©rie II de 2025-08-14",
    "link": "https://diariodarepublica.pt/dr/detalhe/contrato-publico/21882-928937296"
  },
  {
    "numero_procedimento": "N/A",
    "entidade": "AnÃºncio de procedimento  n.Âº 21883/2025  -  DiÃ¡rio da RepÃºblica n.Âº 156/2025, SÃ©rie II de 2025-08-14",
    "link": "https://diariodarepublica.pt/dr/detalhe/contrato-publico/21883-928937297"
  },
  {
    "numero_procedimento": "N/A",
    "entidade": "AnÃºncio de procedimento  n.Âº 21884/2025  -  DiÃ¡rio da RepÃºblica n.Âº 156/2025, SÃ©rie II de 2025-08-14",
    "link": "https://diariodarepublica.pt/dr/detalhe/contrato-publico/21884-928937298"
  },
  {
    "numero_procedimento": "N/A",
    "entidade": "AnÃºncio de procedimento  n.Âº 21886/2025  -  DiÃ¡rio da RepÃºblica n.Âº 156/2025, SÃ©rie II de 2025-08-14",
    "link": "https://diariodarepublica.pt/dr/detalhe/contrato-publico/21886-928937310"
  },
  {
    "numero_procedimento": "N/A",
    "entidade": "AnÃºncio de procedimento  n.Âº 21888/2025  -  DiÃ¡rio da RepÃºblica n.Âº 156/2025, SÃ©rie II de 2025-08-14",
    "link": "https://diariodarepublica.pt/dr/detalhe/contrato-publico/21888-928937311"
  },
  {
    "numero_procedimento": "N/A",
    "entidade": "AnÃºncio de procedimento  n.Âº 21889/2025  -  DiÃ¡rio da RepÃºblica n.Âº 156/2025, SÃ©rie II de 2025-08-14",
    "link": "https://diariodarepublica.pt/dr/detalhe/contrato-publico/21889-928937312"
  },
  {
    "numero_procedimento": "N/A",
    "entidade": "AnÃºncio de procedimento  n.Âº 21891/2025  -  DiÃ¡rio da RepÃºblica n.Âº 156/2025, SÃ©rie II de 2025-08-14",
    "link": "https://diariodarepublica.pt/dr/detalhe/contrato-publico/21891-928937313"
  },
  {
    "numero_procedimento": "N/A",
    "entidade": "AnÃºncio de procedimento  n.Âº 21892/2025  -  DiÃ¡rio da RepÃºblica n.Âº 156/2025, SÃ©rie II de 2025-08-14",
    "link": "https://diariodarepublica.pt/dr/detalhe/contrato-publico/21892-928937314"
  },
  {
    "numero_procedimento": "N/A",
    "entidade": "AnÃºncio de procedimento  n.Âº 21893/2025  -  DiÃ¡rio da RepÃºblica n.Âº 156/2025, SÃ©rie II de 2025-08-14",
    "link": "https://diariodarepublica.pt/dr/detalhe/contrato-publico/21893-928937315"
  },
  {
    "numero_procedimento": "N/A",
    "entidade": "AnÃºncio de procedimento  n.Âº 21863/2025  -  DiÃ¡rio da RepÃºblica n.Âº 156/2025, SÃ©rie II de 2025-08-14",
    "link": "https://diariodarepublica.pt/dr/detalhe/contrato-publico/21863-928939480"
  },
  {
    "numero_procedimento": "N/A",
    "entidade": "AnÃºncio de procedimento  n.Âº 21864/2025  -  DiÃ¡rio da RepÃºblica n.Âº 156/2025, SÃ©rie II de 2025-08-14",
    "link": "https://diariodarepublica.pt/dr/detalhe/contrato-publico/21864-928939481"
  },
  {
    "numero_procedimento": "N/A",
    "entidade": "MUNICÍPIO DE LOULÉ",
    "link": "https://diariodarepublica.pt/dr/detalhe/contrato-publico/21870-928939483",
    "detalhes_completos": "1 - IDENTIFICAÇÃO E CONTACTOS DA ENTIDADE ADJUDICANTE\nDesignação da entidade adjudicante: MUNICÍPIO DE LOULÉ\nNIPC: 502098139\nEndereço: Praça da República\nCódigo postal: 8104-001\nLocalidade: Faro\nPaís: Portugal\nNUT III: PT150\nDistrito: Faro\nConcelho: Loulé\nFreguesia: Todas\nTelefone: 289400834\nFax: 289415557\nEndereço da Entidade (URL): www.cm-loule.pt\nEndereço Eletrónico: aprovisionamento@cm-loule.pt\neDelivery Gateway (URL): https://community.vortal.biz/public/\nFunção da Organização: Adquirente\nNorma jurídica da Entidade Adjudicante: Organismo de direito público\nÁrea de atividade da Autoridade Adjudicante: Serviços públicos das administrações públicas\n\n2 - JORNAL OFICIAL DA UNIÃO EUROPEIA\nO procedimento a que este anúncio diz respeito também é publicitado no Jornal Oficial da União Europeia? Sim\n\n3 - AVISO\nModelo de Anúncio: Concurso público\nData de Envio do Anúncio: 11-08-2025\n\n5 - PROCESSO\nTipo de Procedimento: Concurso público\nPreço base do procedimento: Sim\nValor do preço base do procedimento: 134.825,00 EUR\nProcedimento com lotes? Não\n\n6 - OBJETO DO CONTRATO\nNúmero de referência interna: FM-2025-361 DACP\nDesignação do contrato: CONTRATAÇÃO DO FORNECIMENTO DE APOIO ALIMENTAR A 2500 FAMÍLIAS SOCIALMENTE VULNERÁVEIS\nDescrição: CONTRATAÇÃO DO FORNECIMENTO DE APOIO ALIMENTAR A 2500 FAMÍLIAS SOCIALMENTE VULNERÁVEIS\nOpções: Não\nTipo de Contrato Principal: Aquisição de Bens Móveis\nTipo de Contrato: Aquisição de Bens Móveis\nClassificação CPV (Vocabulário Comum para os Contratos Públicos)\nObjeto principal\nVocabulário Principal: 03310000\nPreço base s/IVA: 134.825,00 EUR\n\n7 - INDICAÇÕES ADICIONAIS\nO contrato envolve aquisição conjunta (satisfação de várias entidades)? Não\nO contrato é adjudicado por uma central de compras? Não\n\n8 - TÉCNICAS\nO concurso destina-se à celebração de um acordo-quadro? Inexistência de acordo-quadro\nÉ utilizado um leilão eletrónico? Não\nÉ adotada uma fase de negociação? Não\nSistema de Aquisição Dinâmico: Inexistência de sistema de aquisição dinâmico\n\n9 - LOCAL DA EXECUÇÃO DO CONTRATO\nLOCAL DA EXECUÇÃO DO CONTRATO (PROCEDIMENTO)\nPaís: Portugal\nNUT III: PT150\nLocalidade: Faro\nDistrito: Faro\nConcelho: Loulé\nFreguesia: Todas\n\n10 - PRAZO DE EXECUÇÃO DO CONTRATO\nPrazo de execução do contrato: 3 MESES\nPrevisão de renovações: Não\n\n11 - FUNDOS EU\nTêm fundos EU? Não\n\n12 - DOCUMENTOS DE HABILITAÇÃO\nHabilitação para o exercício da atividade profissional: Não\n\n13 - CONDIÇÕES DE APRESENTAÇÃO\nPlataforma eletrónica utilizada pela entidade adjudicante: VORTAL\nURL para Apresentação: https://community.vortal.biz/public/\nAdmissibilidade da apresentação de propostas variantes: Não autorizado\nPrazo para apresentação das propostas: 17-09-2025 18:00\nPrazo durante o qual os concorrentes são obrigados a manter as respetivas propostas: 90 dias a contar do termo do prazo para a apresentação das propostas\nApresentação de Catálogo Eletrónico: Não autorizado\nIndicação de Subcontratação na Proposta: Inexistência de indicação de subcontratação\n\n14 - PRESTAÇÃO DE CAUÇÃO\nPrestação de caução: Não\n\n15 - FORNECIMENTO DAS PEÇAS DO CONCURSO, APRESENTAÇÃO DE PEDIDOS DE PARTICIPAÇÃO E APRESENTAÇÃO DAS PROPOSTAS\nLink para acesso às peças do concurso (URL): https://community.vortal.biz/Public/public-tender-documents/QU5wVSs3SFlJaW4wOGtIQzkvZUZpbE5UbXFSa25UbU5aWk5FZUhWcURFWHNGSVl4eE5VTHRWWkhYcGU1MnEzUUdvVDRQLzEyQ04xaE5CSVVxVm93Tmc9PU9YWHVC\n\n20 - OUTROS REQUISITOS\nInformação sobre contratos reservados. Aplica-se a contratos reservados (54º-A)? Não\n\n21 - CRITÉRIO DE ADJUDICAÇÃO\nMultifator: Não\nMonofator:\nNome: Preço\n\n24 - CONDIÇÕES DO CONTRATO\nFaturação Eletrónica: Permitido\nObrigação de Subcontratação:\nCódigo da Obrigação de Subcontratação: Não é aplicável nenhuma obrigação de subcontratação.\n\n25 - COMPRA PÚBLICA ESTRATÉGICA\nCompra Pública Estratégica: Inexistência de contratação pública estratégica\n\n26 - INFORMAÇÕES ADICIONAIS\nContrato adequado para PME: Sim\nCobertura ACP (Acordo dos Contratos Públicos da Organização Mundial do Comércio): Não\n\n27 - IDENTIFICAÇÃO E CONTACTOS DO ÓRGÃO DE RECURSOS ADMINISTRATIVOS\nDesignação: Câmara Municipal de Loulé\nEndereço: Praça da Republica\nCódigo postal: 8104-001\nLocalidade: Loulé\nTelefone: +351 289400600\nFax: +351 289415557\nEndereço eletrónico: geral@cm-loule.pt\n\n28 - IDENTIFICAÇÃO DO(S) AUTOR(ES) DE ANÚNCIO\nNome: Vítor Manuel Gonçalves Aleixo\nCargo: Presidente da Câmara Municipal \n419423544",
    "nipc": "502098139",
    "distrito": "Faro",
    "concelho": "Loulé",
    "freguesia": "Todas",
    "site": "www.cm-loule.pt",
    "email": "aprovisionamento@cm-loule.pt",
    "designacao_contrato": "CONTRATAÇÃO DO FORNECIMENTO DE APOIO ALIMENTAR A 2500 FAMÍLIAS SOCIALMENTE VULNERÁVEIS",
    "descricao": "CONTRATAÇÃO DO FORNECIMENTO DE APOIO ALIMENTAR A 2500 FAMÍLIAS SOCIALMENTE VULNERÁVEIS",
    "preco_base": "134.825,00 EUR",
    "prazo_execucao": "3 MESES",
    "prazo_apresentacao_propostas": "17-09-2025 18:00",
    "fundos_eu": "Não",
    "plataforma_eletronica": "VORTAL",
    "url_procedimento": "https://community.vortal.biz/public/",
    "autor_nome": "Vítor Manuel Gonçalves Aleixo",
    "autor_cargo": "Presidente da Câmara Municipal"
  },
  {
    "numero_procedimento": "N/A",
    "entidade": "AnÃºncio de procedimento  n.Âº 21871/2025  -  DiÃ¡rio da RepÃºblica n.Âº 156/2025, SÃ©rie II de 2025-08-14",
    "link": "https://diariodarepublica.pt/dr/detalhe/contrato-publico/21871-928939484"
  },
  {
    "numero_procedimento": "N/A",
    "entidade": "AnÃºncio de procedimento  n.Âº 21872/2025  -  DiÃ¡rio da RepÃºblica n.Âº 156/2025, SÃ©rie II de 2025-08-14",
    "link": "https://diariodarepublica.pt/dr/detalhe/contrato-publico/21872-928939485"
  },
  {
    "numero_procedimento": "N/A",
    "entidade": "AnÃºncio de procedimento  n.Âº 21873/2025  -  DiÃ¡rio da RepÃºblica n.Âº 156/2025, SÃ©rie II de 2025-08-14",
    "link": "https://diariodarepublica.pt/dr/detalhe/contrato-publico/21873-928939486"
  },
  {
    "numero_procedimento": "N/A",
    "entidade": "AnÃºncio de procedimento  n.Âº 21874/2025  -  DiÃ¡rio da RepÃºblica n.Âº 156/2025, SÃ©rie II de 2025-08-14",
    "link": "https://diariodarepublica.pt/dr/detalhe/contrato-publico/21874-928939487"
  },
  {
    "numero_procedimento": "N/A",
    "entidade": "AnÃºncio de procedimento  n.Âº 21876/2025  -  DiÃ¡rio da RepÃºblica n.Âº 156/2025, SÃ©rie II de 2025-08-14",
    "link": "https://diariodarepublica.pt/dr/detalhe/contrato-publico/21876-928939488"
  },
  {
    "numero_procedimento": "N/A",
    "entidade": "AnÃºncio de procedimento  n.Âº 21877/2025  -  DiÃ¡rio da RepÃºblica n.Âº 156/2025, SÃ©rie II de 2025-08-14",
    "link": "https://diariodarepublica.pt/dr/detalhe/contrato-publico/21877-928939501"
  },
  {
    "numero_procedimento": "N/A",
    "entidade": "AnÃºncio de procedimento  n.Âº 21878/2025  -  DiÃ¡rio da RepÃºblica n.Âº 156/2025, SÃ©rie II de 2025-08-14",
    "link": "https://diariodarepublica.pt/dr/detalhe/contrato-publico/21878-928939502"
  },
  {
    "numero_procedimento": "N/A",
    "entidade": "AnÃºncio de procedimento  n.Âº 21879/2025  -  DiÃ¡rio da RepÃºblica n.Âº 156/2025, SÃ©rie II de 2025-08-14",
    "link": "https://diariodarepublica.pt/dr/detalhe/contrato-publico/21879-928939503"
  },
  {
    "numero_procedimento": "N/A",
    "entidade": "AnÃºncio de procedimento  n.Âº 21880/2025  -  DiÃ¡rio da RepÃºblica n.Âº 156/2025, SÃ©rie II de 2025-08-14",
    "link": "https://diariodarepublica.pt/dr/detalhe/contrato-publico/21880-928939504"
  },
  {
    "numero_procedimento": "N/A",
    "entidade": "AnÃºncio de procedimento  n.Âº 21885/2025  -  DiÃ¡rio da RepÃºblica n.Âº 156/2025, SÃ©rie II de 2025-08-14",
    "link": "https://diariodarepublica.pt/dr/detalhe/contrato-publico/21885-928939505"
  },
  {
    "numero_procedimento": "N/A",
    "entidade": "AnÃºncio de procedimento  n.Âº 21887/2025  -  DiÃ¡rio da RepÃºblica n.Âº 156/2025, SÃ©rie II de 2025-08-14",
    "link": "https://diariodarepublica.pt/dr/detalhe/contrato-publico/21887-928939506"
  },
  {
    "numero_procedimento": "N/A",
    "entidade": "AnÃºncio de procedimento  n.Âº 21890/2025  -  DiÃ¡rio da RepÃºblica n.Âº 156/2025, SÃ©rie II de 2025-08-14",
    "link": "https://diariodarepublica.pt/dr/detalhe/contrato-publico/21890-928939511"
  },
  {
    "numero_procedimento": "N/A",
    "entidade": "AnÃºncio de procedimento  n.Âº 21894/2025  -  DiÃ¡rio da RepÃºblica n.Âº 156/2025, SÃ©rie II de 2025-08-14",
    "link": "https://diariodarepublica.pt/dr/detalhe/contrato-publico/21894-928939512"
  },
  {
    "numero_procedimento": "N/A",
    "entidade": "AnÃºncio de procedimento  n.Âº 21895/2025  -  DiÃ¡rio da RepÃºblica n.Âº 156/2025, SÃ©rie II de 2025-08-14",
    "link": "https://diariodarepublica.pt/dr/detalhe/contrato-publico/21895-928939513"
  },
  {
    "numero_procedimento": "N/A",
    "entidade": "AnÃºncio de procedimento  n.Âº 21896/2025  -  DiÃ¡rio da RepÃºblica n.Âº 156/2025, SÃ©rie II de 2025-08-14",
    "link": "https://diariodarepublica.pt/dr/detalhe/contrato-publico/21896-928939514"
  },
  {
    "numero_procedimento": "N/A",
    "entidade": "AnÃºncio de procedimento  n.Âº 21898/2025  -  DiÃ¡rio da RepÃºblica n.Âº 156/2025, SÃ©rie II de 2025-08-14",
    "link": "https://diariodarepublica.pt/dr/detalhe/contrato-publico/21898-928939521"
  },
  {
    "numero_procedimento": "N/A",
    "entidade": "AnÃºncio de procedimento  n.Âº 21899/2025  -  DiÃ¡rio da RepÃºblica n.Âº 156/2025, SÃ©rie II de 2025-08-14",
    "link": "https://diariodarepublica.pt/dr/detalhe/contrato-publico/21899-928939522"
  },
  {
    "numero_procedimento": "N/A",
    "entidade": "AnÃºncio de procedimento  n.Âº 21901/2025  -  DiÃ¡rio da RepÃºblica n.Âº 156/2025, SÃ©rie II de 2025-08-14",
    "link": "https://diariodarepublica.pt/dr/detalhe/contrato-publico/21901-928939523"
  },
  {
    "numero_procedimento": "N/A",
    "entidade": "AnÃºncio de procedimento  n.Âº 21903/2025  -  DiÃ¡rio da RepÃºblica n.Âº 156/2025, SÃ©rie II de 2025-08-14",
    "link": "https://diariodarepublica.pt/dr/detalhe/contrato-publico/21903-928939524"
  },
  {
    "numero_procedimento": "N/A",
    "entidade": "AnÃºncio de procedimento  n.Âº 21910/2025  -  DiÃ¡rio da RepÃºblica n.Âº 156/2025, SÃ©rie II de 2025-08-14",
    "link": "https://diariodarepublica.pt/dr/detalhe/contrato-publico/21910-928939525"
  },
  {
    "numero_procedimento": "N/A",
    "entidade": "AnÃºncio de procedimento  n.Âº 21911/2025  -  DiÃ¡rio da RepÃºblica n.Âº 156/2025, SÃ©rie II de 2025-08-14",
    "link": "https://diariodarepublica.pt/dr/detalhe/contrato-publico/21911-928939526"
  },
  {
    "numero_procedimento": "N/A",
    "entidade": "AnÃºncio de procedimento  n.Âº 21914/2025  -  DiÃ¡rio da RepÃºblica n.Âº 156/2025, SÃ©rie II de 2025-08-14",
    "link": "https://diariodarepublica.pt/dr/detalhe/contrato-publico/21914-928939527"
  },
  {
    "numero_procedimento": "N/A",
    "entidade": "AnÃºncio de procedimento  n.Âº 21918/2025  -  DiÃ¡rio da RepÃºblica n.Âº 156/2025, SÃ©rie II de 2025-08-14",
    "link": "https://diariodarepublica.pt/dr/detalhe/contrato-publico/21918-928939528"
  },
  {
    "numero_procedimento": "N/A",
    "entidade": "AnÃºncio de procedimento  n.Âº 21919/2025  -  DiÃ¡rio da RepÃºblica n.Âº 156/2025, SÃ©rie II de 2025-08-14",
    "link": "https://diariodarepublica.pt/dr/detalhe/contrato-publico/21919-928939529"
  },
  {
    "numero_procedimento": "N/A",
    "entidade": "AnÃºncio de procedimento  n.Âº 21920/2025  -  DiÃ¡rio da RepÃºblica n.Âº 156/2025, SÃ©rie II de 2025-08-14",
    "link": "https://diariodarepublica.pt/dr/detalhe/contrato-publico/21920-928939531"
  },
  {
    "numero_procedimento": "N/A",
    "entidade": "AnÃºncio de procedimento  n.Âº 21922/2025  -  DiÃ¡rio da RepÃºblica n.Âº 156/2025, SÃ©rie II de 2025-08-14",
    "link": "https://diariodarepublica.pt/dr/detalhe/contrato-publico/21922-928939532"
  },
  {
    "numero_procedimento": "N/A",
    "entidade": "AnÃºncio de procedimento  n.Âº 21927/2025  -  DiÃ¡rio da RepÃºblica n.Âº 156/2025, SÃ©rie II de 2025-08-14",
    "link": "https://diariodarepublica.pt/dr/detalhe/contrato-publico/21927-928939534"
  },
  {
    "numero_procedimento": "N/A",
    "entidade": "AnÃºncio de procedimento  n.Âº 21930/2025  -  DiÃ¡rio da RepÃºblica n.Âº 156/2025, SÃ©rie II de 2025-08-14",
    "link": "https://diariodarepublica.pt/dr/detalhe/contrato-publico/21930-928939535"
  },
  {
    "numero_procedimento": "N/A",
    "entidade": "AnÃºncio de procedimento  n.Âº 21932/2025  -  DiÃ¡rio da RepÃºblica n.Âº 156/2025, SÃ©rie II de 2025-08-14",
    "link": "https://diariodarepublica.pt/dr/detalhe/contrato-publico/21932-928939543"
  },
  {
    "numero_procedimento": "N/A",
    "entidade": "AnÃºncio de procedimento  n.Âº 21934/2025  -  DiÃ¡rio da RepÃºblica n.Âº 156/2025, SÃ©rie II de 2025-08-14",
    "link": "https://diariodarepublica.pt/dr/detalhe/contrato-publico/21934-928939544"
  },
  {
    "numero_procedimento": "N/A",
    "entidade": "AnÃºncio de procedimento  n.Âº 21937/2025  -  DiÃ¡rio da RepÃºblica n.Âº 156/2025, SÃ©rie II de 2025-08-14",
    "link": "https://diariodarepublica.pt/dr/detalhe/contrato-publico/21937-928939545"
  },
  {
    "numero_procedimento": "N/A",
    "entidade": "AnÃºncio de procedimento  n.Âº 21940/2025  -  DiÃ¡rio da RepÃºblica n.Âº 156/2025, SÃ©rie II de 2025-08-14",
    "link": "https://diariodarepublica.pt/dr/detalhe/contrato-publico/21940-928939546"
  },
  {
    "numero_procedimento": "N/A",
    "entidade": "AnÃºncio de procedimento  n.Âº 21941/2025  -  DiÃ¡rio da RepÃºblica n.Âº 156/2025, SÃ©rie II de 2025-08-14",
    "link": "https://diariodarepublica.pt/dr/detalhe/contrato-publico/21941-928939547"
  },
  {
    "numero_procedimento": "N/A",
    "entidade": "AnÃºncio de procedimento  n.Âº 21948/2025  -  DiÃ¡rio da RepÃºblica n.Âº 156/2025, SÃ©rie II de 2025-08-14",
    "link": "https://diariodarepublica.pt/dr/detalhe/contrato-publico/21948-928939548"
  },
  {
    "numero_procedimento": "N/A",
    "entidade": "AnÃºncio de procedimento  n.Âº 21950/2025  -  DiÃ¡rio da RepÃºblica n.Âº 156/2025, SÃ©rie II de 2025-08-14",
    "link": "https://diariodarepublica.pt/dr/detalhe/contrato-publico/21950-928939549"
  },
  {
    "numero_procedimento": "N/A",
    "entidade": "AnÃºncio de procedimento  n.Âº 21952/2025  -  DiÃ¡rio da RepÃºblica n.Âº 156/2025, SÃ©rie II de 2025-08-14",
    "link": "https://diariodarepublica.pt/dr/detalhe/contrato-publico/21952-928939550"
  },
  {
    "numero_procedimento": "N/A",
    "entidade": "AnÃºncio de procedimento  n.Âº 21953/2025  -  DiÃ¡rio da RepÃºblica n.Âº 156/2025, SÃ©rie II de 2025-08-14",
    "link": "https://diariodarepublica.pt/dr/detalhe/contrato-publico/21953-928939551"
  },
  {
    "numero_procedimento": "N/A",
    "entidade": "AnÃºncio de procedimento  n.Âº 21959/2025  -  DiÃ¡rio da RepÃºblica n.Âº 156/2025, SÃ©rie II de 2025-08-14",
    "link": "https://diariodarepublica.pt/dr/detalhe/contrato-publico/21959-928939552"
  },
  {
    "numero_procedimento": "N/A",
    "entidade": "AnÃºncio de procedimento  n.Âº 21961/2025  -  DiÃ¡rio da RepÃºblica n.Âº 156/2025, SÃ©rie II de 2025-08-14",
    "link": "https://diariodarepublica.pt/dr/detalhe/contrato-publico/21961-928939553"
  },
  {
    "numero_procedimento": "N/A",
    "entidade": "AnÃºncio de procedimento  n.Âº 21965/2025  -  DiÃ¡rio da RepÃºblica n.Âº 156/2025, SÃ©rie II de 2025-08-14",
    "link": "https://diariodarepublica.pt/dr/detalhe/contrato-publico/21965-928939554"
  },
  {
    "numero_procedimento": "N/A",
    "entidade": "AnÃºncio de procedimento  n.Âº 21966/2025  -  DiÃ¡rio da RepÃºblica n.Âº 156/2025, SÃ©rie II de 2025-08-14",
    "link": "https://diariodarepublica.pt/dr/detalhe/contrato-publico/21966-928939555"
  },
  {
    "numero_procedimento": "N/A",
    "entidade": "AnÃºncio de procedimento  n.Âº 21967/2025  -  DiÃ¡rio da RepÃºblica n.Âº 156/2025, SÃ©rie II de 2025-08-14",
    "link": "https://diariodarepublica.pt/dr/detalhe/contrato-publico/21967-928939556"
  },
  {
    "numero_procedimento": "N/A",
    "entidade": "AnÃºncio de procedimento  n.Âº 21968/2025  -  DiÃ¡rio da RepÃºblica n.Âº 156/2025, SÃ©rie II de 2025-08-14",
    "link": "https://diariodarepublica.pt/dr/detalhe/contrato-publico/21968-928939557"
  },
  {
    "numero_procedimento": "N/A",
    "entidade": "AnÃºncio de procedimento  n.Âº 21973/2025  -  DiÃ¡rio da RepÃºblica n.Âº 156/2025, SÃ©rie II de 2025-08-14",
    "link": "https://diariodarepublica.pt/dr/detalhe/contrato-publico/21973-928939558"
  },
  {
    "numero_procedimento": "N/A",
    "entidade": "Unidade Local de Saúde de Lisboa Ocidental, E. P. E.",
    "link": "https://diariodarepublica.pt/dr/detalhe/contrato-publico/21978-928939560",
    "detalhes_completos": "1 - IDENTIFICAÇÃO E CONTACTOS DA ENTIDADE ADJUDICANTE\nDesignação da entidade adjudicante: Unidade Local de Saúde de Lisboa Ocidental, E. P. E.\nNIPC: 507618319\nEndereço: Santa Maria de Belém  Estrada do Forte do Alto do Duque\nCódigo postal: 1449-005\nLocalidade: Lisboa\nPaís: Portugal\nNUT III: PT170\nDistrito: Lisboa\nConcelho: Lisboa\nFreguesia: Todas\nTelefone: 210431000\nFax: 210431642\nEndereço da Entidade (URL): www.chlo.min-saude.pt/\nEndereço Eletrónico: comprasgeral@ulslo.min-saude.pt\neDelivery Gateway (URL): https://community.vortal.biz/public/\nFunção da Organização: Adquirente\nNorma jurídica da Entidade Adjudicante: Organismo de direito público\nÁrea de atividade da Autoridade Adjudicante: Saúde\n\n2 - JORNAL OFICIAL DA UNIÃO EUROPEIA\nO procedimento a que este anúncio diz respeito também é publicitado no Jornal Oficial da União Europeia? Não\n\n3 - AVISO\nModelo de Anúncio: Concurso público\nData de Envio do Anúncio: 14-08-2025\n\n5 - PROCESSO\nTipo de Procedimento: Concurso público\nPreço base do procedimento: Sim\nValor do preço base do procedimento: 169.575,00 EUR\nProcedimento com lotes? Sim\nNº Máx. de Lotes Autorizado: 3\nNúmero máximo de lotes que podem ser adjudicados a um concorrente: 3\n\n6 - OBJETO DO CONTRATO\nNúmero de referência interna: 142006925 STENTS INTRACRANIANOS\nDesignação do contrato: 142006925  AQUISIÇÃO DE STENTS INTRACRANIANOS DIVERSORES DE FLUXO 2025\nDescrição: 142006925 AQUISIÇÃO DE STENTS INTRACRANIANOS DIVERSORES DE FLUXO 2025\nTipo de Contrato Principal: Aquisição de Bens Móveis\nTipo de Contrato: Aquisição de Bens Móveis\nClassificação CPV (Vocabulário Comum para os Contratos Públicos)\nObjeto principal\nVocabulário Principal: 33140000\nPreço base s/IVA: 169.575,00 EUR\nLotes: \nNº: LOT-0001\nDescrição do Lote: Lote 1\nPreço base s/IVA: 33.450,00 EUR\nClassificação CPV (Vocabulário Comum para os Contratos Públicos)\nObjeto principal\nVocabulário Principal: 33140000\nNº: LOT-0002\nDescrição do Lote: Lote 2\nPreço base s/IVA: 102.675,00 EUR\nClassificação CPV (Vocabulário Comum para os Contratos Públicos)\nObjeto principal\nVocabulário Principal: 33140000\nNº: LOT-0003\nDescrição do Lote: Lote 3\nPreço base s/IVA: 33.450,00 EUR\nClassificação CPV (Vocabulário Comum para os Contratos Públicos)\nObjeto principal\nVocabulário Principal: 33140000\n\n7 - INDICAÇÕES ADICIONAIS\nO contrato envolve aquisição conjunta (satisfação de várias entidades)? Não\nO contrato é adjudicado por uma central de compras? Não\n\n8 - TÉCNICAS\nO concurso destina-se à celebração de um acordo-quadro? Inexistência de acordo-quadro\nÉ utilizado um leilão eletrónico? Não\nÉ adotada uma fase de negociação? Não\nSistema de Aquisição Dinâmico: Inexistência de sistema de aquisição dinâmico\n\n9 - LOCAL DA EXECUÇÃO DO CONTRATO\nLOCAL DA EXECUÇÃO DO CONTRATO (PROCEDIMENTO)\nPaís: Portugal\nNUT III: PT170\nLocalidade: Lisboa\nDistrito: Lisboa\nConcelho: Lisboa\nFreguesia: Todas\nLOCAL DA EXECUÇÃO DO CONTRATO (LOTE)\nIdentificador do Lote: LOT-0001; LOT-0002; LOT-0003\nPaís: Portugal\nNUT III: PT170\nLocalidade: Lisboa\nDistrito: Lisboa\nConcelho: Lisboa\nFreguesia: Todas\n\n10 - PRAZO DE EXECUÇÃO DO CONTRATO\nIdentificador do Lote: LOT-0001; LOT-0002; LOT-0003\nPrazo de execução do contrato: 150 DIAS\nPrevisão de renovações: Não\n\n11 - FUNDOS EU\nIdentificador do Lote: LOT-0001; LOT-0002; LOT-0003\nTêm fundos EU? Não\n\n12 - DOCUMENTOS DE HABILITAÇÃO\nHabilitação para o exercício da atividade profissional: Não\n\n13 - CONDIÇÕES DE APRESENTAÇÃO\nPlataforma eletrónica utilizada pela entidade adjudicante: VORTAL\nURL para Apresentação: https://community.vortal.biz/public/\nAdmissibilidade da apresentação de propostas variantes: Não autorizado\nPrazo para apresentação das propostas: 29-08-2025 23:59\nPrazo durante o qual os concorrentes são obrigados a manter as respetivas propostas: 66 dias a contar do termo do prazo para a apresentação das propostas\nIndicação de Subcontratação na Proposta: Inexistência de indicação de subcontratação\n\n14 - PRESTAÇÃO DE CAUÇÃO\nPrestação de caução: Não\n\n15 - FORNECIMENTO DAS PEÇAS DO CONCURSO, APRESENTAÇÃO DE PEDIDOS DE PARTICIPAÇÃO E APRESENTAÇÃO DAS PROPOSTAS\nLink para acesso às peças do concurso (URL): https://community.vortal.biz/Public/public-tender-documents/c2NhYXdUK1IrU3RnWTU4WFpEOEdBd05IVmZwdE9pbGRIbWNzcGw3NE1memc4dm1hMnVPblJZK1RhZ1ZtMmQ5QktHTlZoUm5sYThBamttUzNTeEFOUUE9PSpxUU9t\n\n20 - OUTROS REQUISITOS\nIdentificador do Lote: LOT-0001; LOT-0002; LOT-0003\nInformação sobre contratos reservados. Aplica-se a contratos reservados (54º-A)? Não\n\n21 - CRITÉRIO DE ADJUDICAÇÃO\nO Critério de adjudicação é diferenciado por lote? Não\nMultifator: Sim\nFator: \nNome: Preço\nPonderação: 50%\nSubfatores: Não\nFator: \nNome: Qualidade\nPonderação: 50%\nSubfatores: Não\n\n24 - CONDIÇÕES DO CONTRATO\nIdentificador do Lote: LOT-0001; LOT-0002; LOT-0003\nFaturação Eletrónica: Permitido\nObrigação de Subcontratação:\nCódigo da Obrigação de Subcontratação: Não é aplicável nenhuma obrigação de subcontratação.\n\n25 - COMPRA PÚBLICA ESTRATÉGICA\nCompra Pública Estratégica: Inexistência de contratação pública estratégica\n\n26 - INFORMAÇÕES ADICIONAIS\nIdentificador do Lote: LOT-0001; LOT-0002; LOT-0003\nContrato adequado para PME: Sim\nCobertura ACP (Acordo dos Contratos Públicos da Organização Mundial do Comércio): Não\n\n27 - IDENTIFICAÇÃO E CONTACTOS DO ÓRGÃO DE RECURSOS ADMINISTRATIVOS\nDesignação: Serviço Gestão Compras\nEndereço: Estrada do Forte do Alto do Duque\nCódigo postal: 1449-005\nLocalidade: Lisboa\nTelefone: +351 210431000\nFax: +351 210431642\nEndereço eletrónico: comprascclinico@ulslo.min-saude.pt\n\n28 - IDENTIFICAÇÃO DO(S) AUTOR(ES) DE ANÚNCIO\nNome: Andrea Malta\nCargo: Diretora Serviço Gestão Compras\n419433531",
    "nipc": "507618319",
    "distrito": "Lisboa",
    "concelho": "Lisboa",
    "freguesia": "Todas",
    "site": "www.chlo.min-saude.pt/",
    "email": "comprasgeral@ulslo.min-saude.pt",
    "designacao_contrato": "142006925 AQUISIÇÃO DE STENTS INTRACRANIANOS DIVERSORES DE FLUXO 2025",
    "descricao": "142006925 AQUISIÇÃO DE STENTS INTRACRANIANOS DIVERSORES DE FLUXO 2025",
    "preco_base": "169.575,00 EUR",
    "prazo_execucao": "150 DIAS",
    "prazo_apresentacao_propostas": "29-08-2025 23:59",
    "fundos_eu": "Não",
    "plataforma_eletronica": "VORTAL",
    "url_procedimento": "https://community.vortal.biz/public/",
    "autor_nome": "Andrea Malta",
    "autor_cargo": "Diretora Serviço Gestão Compras"
  },
  {
    "numero_procedimento": "N/A",
    "entidade": "AnÃºncio de procedimento  n.Âº 21979/2025  -  DiÃ¡rio da RepÃºblica n.Âº 156/2025, SÃ©rie II de 2025-08-14",
    "link": "https://diariodarepublica.pt/dr/detalhe/contrato-publico/21979-928939561"
  },
  {
    "numero_procedimento": "N/A",
    "entidade": "AnÃºncio de procedimento  n.Âº 21982/2025  -  DiÃ¡rio da RepÃºblica n.Âº 156/2025, SÃ©rie II de 2025-08-14",
    "link": "https://diariodarepublica.pt/dr/detalhe/contrato-publico/21982-928939562"
  },
  {
    "numero_procedimento": "N/A",
    "entidade": "AnÃºncio de procedimento  n.Âº 21983/2025  -  DiÃ¡rio da RepÃºblica n.Âº 156/2025, SÃ©rie II de 2025-08-14",
    "link": "https://diariodarepublica.pt/dr/detalhe/contrato-publico/21983-928939563"
  },
  {
    "numero_procedimento": "N/A",
    "entidade": "AnÃºncio de procedimento  n.Âº 21985/2025  -  DiÃ¡rio da RepÃºblica n.Âº 156/2025, SÃ©rie II de 2025-08-14",
    "link": "https://diariodarepublica.pt/dr/detalhe/contrato-publico/21985-928939564"
  },
  {
    "numero_procedimento": "N/A",
    "entidade": "AnÃºncio de procedimento  n.Âº 21897/2025  -  DiÃ¡rio da RepÃºblica n.Âº 156/2025, SÃ©rie II de 2025-08-14",
    "link": "https://diariodarepublica.pt/dr/detalhe/contrato-publico/21897-929017719"
  },
  {
    "numero_procedimento": "N/A",
    "entidade": "AnÃºncio de procedimento  n.Âº 21900/2025  -  DiÃ¡rio da RepÃºblica n.Âº 156/2025, SÃ©rie II de 2025-08-14",
    "link": "https://diariodarepublica.pt/dr/detalhe/contrato-publico/21900-929017720"
  },
  {
    "numero_procedimento": "N/A",
    "entidade": "AnÃºncio de procedimento  n.Âº 21902/2025  -  DiÃ¡rio da RepÃºblica n.Âº 156/2025, SÃ©rie II de 2025-08-14",
    "link": "https://diariodarepublica.pt/dr/detalhe/contrato-publico/21902-929017721"
  },
  {
    "numero_procedimento": "N/A",
    "entidade": "AnÃºncio de procedimento  n.Âº 21904/2025  -  DiÃ¡rio da RepÃºblica n.Âº 156/2025, SÃ©rie II de 2025-08-14",
    "link": "https://diariodarepublica.pt/dr/detalhe/contrato-publico/21904-929017722"
  },
  {
    "numero_procedimento": "N/A",
    "entidade": "AnÃºncio de procedimento  n.Âº 21905/2025  -  DiÃ¡rio da RepÃºblica n.Âº 156/2025, SÃ©rie II de 2025-08-14",
    "link": "https://diariodarepublica.pt/dr/detalhe/contrato-publico/21905-929017723"
  },
  {
    "numero_procedimento": "N/A",
    "entidade": "AnÃºncio de procedimento  n.Âº 21906/2025  -  DiÃ¡rio da RepÃºblica n.Âº 156/2025, SÃ©rie II de 2025-08-14",
    "link": "https://diariodarepublica.pt/dr/detalhe/contrato-publico/21906-929017724"
  },
  {
    "numero_procedimento": "N/A",
    "entidade": "AnÃºncio de procedimento  n.Âº 21907/2025  -  DiÃ¡rio da RepÃºblica n.Âº 156/2025, SÃ©rie II de 2025-08-14",
    "link": "https://diariodarepublica.pt/dr/detalhe/contrato-publico/21907-929017725"
  },
  {
    "numero_procedimento": "N/A",
    "entidade": "AnÃºncio de procedimento  n.Âº 21908/2025  -  DiÃ¡rio da RepÃºblica n.Âº 156/2025, SÃ©rie II de 2025-08-14",
    "link": "https://diariodarepublica.pt/dr/detalhe/contrato-publico/21908-929017726"
  },
  {
    "numero_procedimento": "N/A",
    "entidade": "AnÃºncio de procedimento  n.Âº 21909/2025  -  DiÃ¡rio da RepÃºblica n.Âº 156/2025, SÃ©rie II de 2025-08-14",
    "link": "https://diariodarepublica.pt/dr/detalhe/contrato-publico/21909-929017727"
  },
  {
    "numero_procedimento": "N/A",
    "entidade": "AnÃºncio de procedimento  n.Âº 21912/2025  -  DiÃ¡rio da RepÃºblica n.Âº 156/2025, SÃ©rie II de 2025-08-14",
    "link": "https://diariodarepublica.pt/dr/detalhe/contrato-publico/21912-929044289"
  },
  {
    "numero_procedimento": "N/A",
    "entidade": "AnÃºncio de procedimento  n.Âº 21913/2025  -  DiÃ¡rio da RepÃºblica n.Âº 156/2025, SÃ©rie II de 2025-08-14",
    "link": "https://diariodarepublica.pt/dr/detalhe/contrato-publico/21913-929044290"
  },
  {
    "numero_procedimento": "N/A",
    "entidade": "AnÃºncio de procedimento  n.Âº 21915/2025  -  DiÃ¡rio da RepÃºblica n.Âº 156/2025, SÃ©rie II de 2025-08-14",
    "link": "https://diariodarepublica.pt/dr/detalhe/contrato-publico/21915-929044291"
  },
  {
    "numero_procedimento": "N/A",
    "entidade": "AnÃºncio de procedimento  n.Âº 21916/2025  -  DiÃ¡rio da RepÃºblica n.Âº 156/2025, SÃ©rie II de 2025-08-14",
    "link": "https://diariodarepublica.pt/dr/detalhe/contrato-publico/21916-929044292"
  },
  {
    "numero_procedimento": "N/A",
    "entidade": "AnÃºncio de procedimento  n.Âº 21917/2025  -  DiÃ¡rio da RepÃºblica n.Âº 156/2025, SÃ©rie II de 2025-08-14",
    "link": "https://diariodarepublica.pt/dr/detalhe/contrato-publico/21917-929044293"
  },
  {
    "numero_procedimento": "N/A",
    "entidade": "AnÃºncio de procedimento  n.Âº 21921/2025  -  DiÃ¡rio da RepÃºblica n.Âº 156/2025, SÃ©rie II de 2025-08-14",
    "link": "https://diariodarepublica.pt/dr/detalhe/contrato-publico/21921-929044294"
  },
  {
    "numero_procedimento": "N/A",
    "entidade": "AnÃºncio de procedimento  n.Âº 21923/2025  -  DiÃ¡rio da RepÃºblica n.Âº 156/2025, SÃ©rie II de 2025-08-14",
    "link": "https://diariodarepublica.pt/dr/detalhe/contrato-publico/21923-929044295"
  },
  {
    "numero_procedimento": "N/A",
    "entidade": "AnÃºncio de procedimento  n.Âº 21924/2025  -  DiÃ¡rio da RepÃºblica n.Âº 156/2025, SÃ©rie II de 2025-08-14",
    "link": "https://diariodarepublica.pt/dr/detalhe/contrato-publico/21924-929044296"
  },
  {
    "numero_procedimento": "N/A",
    "entidade": "AnÃºncio de procedimento  n.Âº 21925/2025  -  DiÃ¡rio da RepÃºblica n.Âº 156/2025, SÃ©rie II de 2025-08-14",
    "link": "https://diariodarepublica.pt/dr/detalhe/contrato-publico/21925-929044297"
  },
  {
    "numero_procedimento": "N/A",
    "entidade": "AnÃºncio de procedimento  n.Âº 21926/2025  -  DiÃ¡rio da RepÃºblica n.Âº 156/2025, SÃ©rie II de 2025-08-14",
    "link": "https://diariodarepublica.pt/dr/detalhe/contrato-publico/21926-929044298"
  },
  {
    "numero_procedimento": "N/A",
    "entidade": "AnÃºncio de procedimento  n.Âº 21928/2025  -  DiÃ¡rio da RepÃºblica n.Âº 156/2025, SÃ©rie II de 2025-08-14",
    "link": "https://diariodarepublica.pt/dr/detalhe/contrato-publico/21928-929044299"
  },
  {
    "numero_procedimento": "N/A",
    "entidade": "AnÃºncio de procedimento  n.Âº 21929/2025  -  DiÃ¡rio da RepÃºblica n.Âº 156/2025, SÃ©rie II de 2025-08-14",
    "link": "https://diariodarepublica.pt/dr/detalhe/contrato-publico/21929-929044300"
  },
  {
    "numero_procedimento": "N/A",
    "entidade": "AnÃºncio de procedimento  n.Âº 21931/2025  -  DiÃ¡rio da RepÃºblica n.Âº 156/2025, SÃ©rie II de 2025-08-14",
    "link": "https://diariodarepublica.pt/dr/detalhe/contrato-publico/21931-929044301"
  },
  {
    "numero_procedimento": "N/A",
    "entidade": "Unidade Local de Saúde do Alto Ave, E.P.E",
    "link": "https://diariodarepublica.pt/dr/detalhe/contrato-publico/21933-929044302",
    "detalhes_completos": "1 - IDENTIFICAÇÃO E CONTACTOS DA ENTIDADE ADJUDICANTE\nDesignação da entidade adjudicante:  Unidade Local de Saúde do Alto Ave, E.P.E\nNIPC: 508080827\nServiço/Órgão/Pessoa de contacto: Unidade Local e Saúde do Alto Ave ,EPE\nEndereço: Rua dos Cutileiros, Creixomil\nCódigo postal: 4835-044\nLocalidade: Guimarães\nPaís: Portugal\nNUT III: PT119\nDistrito: Braga\nConcelho: Guimarães\nFreguesia: Todas\nTelefone: 253540330\nFax: 253513592\nEndereço da Entidade (URL): http://www.hospitaldeguimaraes.min-saude.pt/\nEndereço Eletrónico: aprovisionamento@hospitaldeguimaraes.min-saude.pt\neDelivery Gateway (URL): https://community.vortal.biz/public/\nFunção da Organização: Adquirente\nNorma jurídica da Entidade Adjudicante: Organismo de direito público\nÁrea de atividade da Autoridade Adjudicante: Saúde\n\n2 - JORNAL OFICIAL DA UNIÃO EUROPEIA\nO procedimento a que este anúncio diz respeito também é publicitado no Jornal Oficial da União Europeia? Não\n\n3 - AVISO\nModelo de Anúncio: Concurso público\nData de Envio do Anúncio: 14-08-2025\n\n5 - PROCESSO\nTipo de Procedimento: Concurso público\nPreço base do procedimento: Sim\nValor do preço base do procedimento: 69.000,00 EUR\nProcedimento com lotes? Sim\nNº Máx. de Lotes Autorizado: 2\nNúmero máximo de lotes que podem ser adjudicados a um concorrente: 2\n\n6 - OBJETO DO CONTRATO\nNúmero de referência interna: CP/0549/2025\nDesignação do contrato: Prestação de Serviços de manutenção de espacos verdes\nDescrição: Prestação de Serviços de manutenção de espacos verdes\nTipo de Contrato Principal: Aquisição de Serviços\nTipo de Contrato: Aquisição de Serviços\nClassificação CPV (Vocabulário Comum para os Contratos Públicos)\nObjeto principal\nVocabulário Principal: 71421000\nPreço base s/IVA: 69.000,00 EUR\nLotes: \nNº: LOT-0001\nDescrição do Lote: Lote 1\nPreço base s/IVA: 49.800,00 EUR\nClassificação CPV (Vocabulário Comum para os Contratos Públicos)\nObjeto principal\nVocabulário Principal: 71421000\nNº: LOT-0002\nDescrição do Lote: Lote 2\nPreço base s/IVA: 19.200,00 EUR\nClassificação CPV (Vocabulário Comum para os Contratos Públicos)\nObjeto principal\nVocabulário Principal: 71421000\n\n7 - INDICAÇÕES ADICIONAIS\nO contrato envolve aquisição conjunta (satisfação de várias entidades)? Não\nO contrato é adjudicado por uma central de compras? Não\n\n8 - TÉCNICAS\nO concurso destina-se à celebração de um acordo-quadro? Inexistência de acordo-quadro\nÉ utilizado um leilão eletrónico? Não\nÉ adotada uma fase de negociação? Não\nSistema de Aquisição Dinâmico: Inexistência de sistema de aquisição dinâmico\n\n9 - LOCAL DA EXECUÇÃO DO CONTRATO\nLOCAL DA EXECUÇÃO DO CONTRATO (PROCEDIMENTO)\nPaís: Portugal\nNUT III: PT119\nLocalidade: Braga\nDistrito: Braga\nConcelho: Guimarães\nFreguesia: Freguesia de Creixomil - Guimarães\nLOCAL DA EXECUÇÃO DO CONTRATO (LOTE)\nIdentificador do Lote: LOT-0001; LOT-0002\nPaís: Portugal\nNUT III: PT119\nLocalidade: Braga\nDistrito: Braga\nConcelho: Guimarães\nFreguesia: Freguesia de Creixomil - Guimarães\n\n10 - PRAZO DE EXECUÇÃO DO CONTRATO\nIdentificador do Lote: LOT-0001; LOT-0002\nPrazo de execução do contrato: 36 MESES\nPrevisão de renovações: Não\n\n11 - FUNDOS EU\nIdentificador do Lote: LOT-0001; LOT-0002\nTêm fundos EU? Não\n\n12 - DOCUMENTOS DE HABILITAÇÃO\nHabilitação para o exercício da atividade profissional: Não\n\n13 - CONDIÇÕES DE APRESENTAÇÃO\nPlataforma eletrónica utilizada pela entidade adjudicante: VORTAL\nURL para Apresentação: https://community.vortal.biz/public/\nAdmissibilidade da apresentação de propostas variantes: Não autorizado\nPrazo para apresentação das propostas: 25-08-2025 17:00\nPrazo durante o qual os concorrentes são obrigados a manter as respetivas propostas: 180 dias a contar do termo do prazo para a apresentação das propostas\nIndicação de Subcontratação na Proposta: Inexistência de indicação de subcontratação\n\n14 - PRESTAÇÃO DE CAUÇÃO\nPrestação de caução: Não\n\n15 - FORNECIMENTO DAS PEÇAS DO CONCURSO, APRESENTAÇÃO DE PEDIDOS DE PARTICIPAÇÃO E APRESENTAÇÃO DAS PROPOSTAS\nLink para acesso às peças do concurso (URL): https://community.vortal.biz/Public/public-tender-documents/TVNJS2NrdUxYOUUyN2ZMSUFMZlZmejBZLzFLWkdVenp4NjdvYlBKUWRVVE5JV015RExqYk5BLzJwQXErelF4WEtSejhLWWtpcy80ZmlMMkJzeDZlWVE9PUtWXlVU\n\n20 - OUTROS REQUISITOS\nIdentificador do Lote: LOT-0001; LOT-0002\nInformação sobre contratos reservados. Aplica-se a contratos reservados (54º-A)? Não\n\n21 - CRITÉRIO DE ADJUDICAÇÃO\nO Critério de adjudicação é diferenciado por lote? Não\nMultifator: Não\nMonofator:\nNome: Preço\n\n24 - CONDIÇÕES DO CONTRATO\nIdentificador do Lote: LOT-0001; LOT-0002\nFaturação Eletrónica: Permitido\nObrigação de Subcontratação:\nCódigo da Obrigação de Subcontratação: Não é aplicável nenhuma obrigação de subcontratação.\n\n25 - COMPRA PÚBLICA ESTRATÉGICA\nCompra Pública Estratégica: Inexistência de contratação pública estratégica\n\n26 - INFORMAÇÕES ADICIONAIS\nIdentificador do Lote: LOT-0001; LOT-0002\nContrato adequado para PME: Sim\nCobertura ACP (Acordo dos Contratos Públicos da Organização Mundial do Comércio): Não\n\n27 - IDENTIFICAÇÃO E CONTACTOS DO ÓRGÃO DE RECURSOS ADMINISTRATIVOS\nDesignação: Unidade Local de Saúde do Alto Ave , EPE\nEndereço: Rua dos Cutileiros, Creixomil\nCódigo postal: 4835-044\nLocalidade: Guimarães\nTelefone: +351 253540330\nFax: +351 253540330\nEndereço eletrónico: compras@ulsaave.min-saude.pt\n\n28 - IDENTIFICAÇÃO DO(S) AUTOR(ES) DE ANÚNCIO\nNome: Eng. Arlindo Soares \nCargo: Diretor do SCL\n419433556",
    "nipc": "508080827",
    "distrito": "Braga",
    "concelho": "Guimarães",
    "freguesia": "Todas",
    "site": "http://www.hospitaldeguimaraes.min-saude.pt/",
    "email": "aprovisionamento@hospitaldeguimaraes.min-saude.pt",
    "designacao_contrato": "Prestação de Serviços de manutenção de espacos verdes",
    "descricao": "Prestação de Serviços de manutenção de espacos verdes",
    "preco_base": "69.000,00 EUR",
    "prazo_execucao": "36 MESES",
    "prazo_apresentacao_propostas": "25-08-2025 17:00",
    "fundos_eu": "Não",
    "plataforma_eletronica": "VORTAL",
    "url_procedimento": "https://community.vortal.biz/public/",
    "autor_nome": "Eng. Arlindo Soares",
    "autor_cargo": "Diretor do SCL"
  },
  {
    "numero_procedimento": "N/A",
    "entidade": "AnÃºncio de procedimento  n.Âº 21935/2025  -  DiÃ¡rio da RepÃºblica n.Âº 156/2025, SÃ©rie II de 2025-08-14",
    "link": "https://diariodarepublica.pt/dr/detalhe/contrato-publico/21935-929044303"
  },
  {
    "numero_procedimento": "N/A",
    "entidade": "AnÃºncio de procedimento  n.Âº 21936/2025  -  DiÃ¡rio da RepÃºblica n.Âº 156/2025, SÃ©rie II de 2025-08-14",
    "link": "https://diariodarepublica.pt/dr/detalhe/contrato-publico/21936-929044304"
  },
  {
    "numero_procedimento": "N/A",
    "entidade": "AnÃºncio de procedimento  n.Âº 21938/2025  -  DiÃ¡rio da RepÃºblica n.Âº 156/2025, SÃ©rie II de 2025-08-14",
    "link": "https://diariodarepublica.pt/dr/detalhe/contrato-publico/21938-929044305"
  },
  {
    "numero_procedimento": "N/A",
    "entidade": "Unidade Local de Saúde de São José, E. P. E.",
    "link": "https://diariodarepublica.pt/dr/detalhe/contrato-publico/21939-929044306",
    "detalhes_completos": "1 - IDENTIFICAÇÃO E CONTACTOS DA ENTIDADE ADJUDICANTE\nDesignação da entidade adjudicante: Unidade Local de Saúde de São José, E. P. E.\nNIPC: 508080142\nEndereço: Rua José António Serrano\nCódigo postal: 1150-199\nLocalidade: Lisboa\nPaís: Portugal\nNUT III: PT170\nDistrito: Lisboa\nConcelho: Lisboa\nFreguesia: Freguesia de Arroios - Lisboa\nTelefone: 218841403\nFax: 218841025\nEndereço da Entidade (URL): www.chlc.min-saude.pt\nEndereço Eletrónico: geral@chlc.min-saude.pt\neDelivery Gateway (URL): https://community.vortal.biz/public/\nFunção da Organização: Adquirente\nNorma jurídica da Entidade Adjudicante: Organismo de direito público\nÁrea de atividade da Autoridade Adjudicante: Saúde\n\n2 - JORNAL OFICIAL DA UNIÃO EUROPEIA\nO procedimento a que este anúncio diz respeito também é publicitado no Jornal Oficial da União Europeia? Não\n\n3 - AVISO\nModelo de Anúncio: Concurso público\nData de Envio do Anúncio: 14-08-2025\n\n5 - PROCESSO\nTipo de Procedimento: Concurso público\nPreço base do procedimento: Sim\nValor do preço base do procedimento: 180.812,50 EUR\nProcedimento com lotes? Sim\nNº Máx. de Lotes Autorizado: 9\nNúmero máximo de lotes que podem ser adjudicados a um concorrente: 9\n\n6 - OBJETO DO CONTRATO\nNúmero de referência interna: 12023525\nDesignação do contrato: CONCURSO PÚBLICO TENDENTE AO FORNECIMENTO DE COLAS CIRÚRGICAS E SINTÉTICAS, DESTINADO UNIDADE LOCAL DE SAÚDE DE S. JOSÉ, E.P.E., PARA O ANO DE 2025\nDescrição: COLAS CIRÚRGICAS E SINTÉTICAS\nTipo de Contrato Principal: Aquisição de Bens Móveis\nTipo de Contrato: Aquisição de Bens Móveis\nClassificação CPV (Vocabulário Comum para os Contratos Públicos)\nObjeto principal\nVocabulário Principal: 33140000\nPreço base s/IVA: 180.812,50 EUR\nLotes: \nNº: LOT-0001\nDescrição do Lote: Lote 1\nPreço base s/IVA: 16.500,00 EUR\nClassificação CPV (Vocabulário Comum para os Contratos Públicos)\nObjeto principal\nVocabulário Principal: 33140000\nNº: LOT-0002\nDescrição do Lote: Lote 2\nPreço base s/IVA: 10.850,00 EUR\nClassificação CPV (Vocabulário Comum para os Contratos Públicos)\nObjeto principal\nVocabulário Principal: 33140000\nNº: LOT-0003\nDescrição do Lote: Lote 3\nPreço base s/IVA: 16.284,00 EUR\nClassificação CPV (Vocabulário Comum para os Contratos Públicos)\nObjeto principal\nVocabulário Principal: 33140000\nNº: LOT-0004\nDescrição do Lote: Lote 4\nPreço base s/IVA: 15.500,00 EUR\nClassificação CPV (Vocabulário Comum para os Contratos Públicos)\nObjeto principal\nVocabulário Principal: 33140000\nNº: LOT-0005\nDescrição do Lote: Lote 5\nPreço base s/IVA: 45.500,00 EUR\nClassificação CPV (Vocabulário Comum para os Contratos Públicos)\nObjeto principal\nVocabulário Principal: 33140000\nNº: LOT-0006\nDescrição do Lote: Lote 6\nPreço base s/IVA: 56.080,00 EUR\nClassificação CPV (Vocabulário Comum para os Contratos Públicos)\nObjeto principal\nVocabulário Principal: 33140000\nNº: LOT-0007\nDescrição do Lote: Lote 7\nPreço base s/IVA: 16.900,00 EUR\nClassificação CPV (Vocabulário Comum para os Contratos Públicos)\nObjeto principal\nVocabulário Principal: 33140000\nNº: LOT-0008\nDescrição do Lote: Lote 8\nPreço base s/IVA: 2.890,50 EUR\nClassificação CPV (Vocabulário Comum para os Contratos Públicos)\nObjeto principal\nVocabulário Principal: 33140000\nNº: LOT-0009\nDescrição do Lote: Lote 9\nPreço base s/IVA: 308,00 EUR\nClassificação CPV (Vocabulário Comum para os Contratos Públicos)\nObjeto principal\nVocabulário Principal: 33140000\n\n7 - INDICAÇÕES ADICIONAIS\nO contrato envolve aquisição conjunta (satisfação de várias entidades)? Não\nO contrato é adjudicado por uma central de compras? Não\n\n8 - TÉCNICAS\nO concurso destina-se à celebração de um acordo-quadro? Inexistência de acordo-quadro\nÉ utilizado um leilão eletrónico? Não\nÉ adotada uma fase de negociação? Não\nSistema de Aquisição Dinâmico: Inexistência de sistema de aquisição dinâmico\n\n9 - LOCAL DA EXECUÇÃO DO CONTRATO\nLOCAL DA EXECUÇÃO DO CONTRATO (PROCEDIMENTO)\nPaís: Portugal\nNUT III: PT170\nLocalidade: Lisboa\nDistrito: Lisboa\nConcelho: Lisboa\nFreguesia: Freguesia de Arroios - Lisboa\nLOCAL DA EXECUÇÃO DO CONTRATO (LOTE)\nIdentificador do Lote: LOT-0001; LOT-0002; LOT-0003; LOT-0004; LOT-0005; LOT-0006; LOT-0007; LOT-0008; LOT-0009\nPaís: Portugal\nNUT III: PT170\nLocalidade: Lisboa\nDistrito: Lisboa\nConcelho: Lisboa\nFreguesia: Freguesia de Arroios - Lisboa\n\n10 - PRAZO DE EXECUÇÃO DO CONTRATO\nIdentificador do Lote: LOT-0001; LOT-0002; LOT-0003; LOT-0004; LOT-0005; LOT-0006; LOT-0007; LOT-0008; LOT-0009\nPrazo de execução do contrato: 5 MESES\nPrevisão de renovações: Não\n\n11 - FUNDOS EU\nIdentificador do Lote: LOT-0001; LOT-0002; LOT-0003; LOT-0004; LOT-0005; LOT-0006; LOT-0007; LOT-0008; LOT-0009\nTêm fundos EU? Não\n\n12 - DOCUMENTOS DE HABILITAÇÃO\nHabilitação para o exercício da atividade profissional: Não\n\n13 - CONDIÇÕES DE APRESENTAÇÃO\nPlataforma eletrónica utilizada pela entidade adjudicante: VORTAL\nURL para Apresentação: https://community.vortal.biz/public/\nAdmissibilidade da apresentação de propostas variantes: Não autorizado\nPrazo para apresentação das propostas: 26-08-2025 23:59\nPrazo durante o qual os concorrentes são obrigados a manter as respetivas propostas: 120 dias a contar do termo do prazo para a apresentação das propostas\nIndicação de Subcontratação na Proposta: Inexistência de indicação de subcontratação\n\n14 - PRESTAÇÃO DE CAUÇÃO\nPrestação de caução: Não\n\n15 - FORNECIMENTO DAS PEÇAS DO CONCURSO, APRESENTAÇÃO DE PEDIDOS DE PARTICIPAÇÃO E APRESENTAÇÃO DAS PROPOSTAS\nLink para acesso às peças do concurso (URL): https://community.vortal.biz/Public/public-tender-documents/QU9qSjhRZFI3V0JBZmNJSzFJTm1EYXUxT21MTWs0dGo0WU43WnhkR0xvOHY3N1RFSzE1eWh1Nk1hNzNteEpPcnpxMkxQTms2VG5ZbjNjVzJ3T0VuNUE9PUwkdXJM\n\n20 - OUTROS REQUISITOS\nIdentificador do Lote: LOT-0001; LOT-0002; LOT-0003; LOT-0004; LOT-0005; LOT-0006; LOT-0007; LOT-0008; LOT-0009\nInformação sobre contratos reservados. Aplica-se a contratos reservados (54º-A)? Não\n\n21 - CRITÉRIO DE ADJUDICAÇÃO\nO Critério de adjudicação é diferenciado por lote? Não\nMultifator: Não\nMonofator:\nNome: Preço\n\n24 - CONDIÇÕES DO CONTRATO\nIdentificador do Lote: LOT-0001; LOT-0002; LOT-0003; LOT-0004; LOT-0005; LOT-0006; LOT-0007; LOT-0008; LOT-0009\nFaturação Eletrónica: Permitido\nObrigação de Subcontratação:\nCódigo da Obrigação de Subcontratação: Não é aplicável nenhuma obrigação de subcontratação.\n\n25 - COMPRA PÚBLICA ESTRATÉGICA\nCompra Pública Estratégica: Inexistência de contratação pública estratégica\n\n26 - INFORMAÇÕES ADICIONAIS\nIdentificador do Lote: LOT-0001; LOT-0002; LOT-0003; LOT-0004; LOT-0005; LOT-0006; LOT-0007; LOT-0008; LOT-0009\nContrato adequado para PME: Sim\nCobertura ACP (Acordo dos Contratos Públicos da Organização Mundial do Comércio): Não\n\n27 - IDENTIFICAÇÃO E CONTACTOS DO ÓRGÃO DE RECURSOS ADMINISTRATIVOS\nDesignação: Conselho de Administração\nEndereço: Rua José António Serrano s/n\nCódigo postal: 1150-199\nLocalidade: Lisboa\nTelefone: +351 218841403\nFax: +351 218841025\nEndereço eletrónico: sec.vca@ulssjose.min-saude.pt\n\n28 - IDENTIFICAÇÃO DO(S) AUTOR(ES) DE ANÚNCIO\nNome: Conselho de Administração\nCargo: Conselho de Administração\n419429741",
    "nipc": "508080142",
    "distrito": "Lisboa",
    "concelho": "Lisboa",
    "freguesia": "Freguesia de Arroios - Lisboa",
    "site": "www.chlc.min-saude.pt",
    "email": "geral@chlc.min-saude.pt",
    "designacao_contrato": "CONCURSO PÚBLICO TENDENTE AO FORNECIMENTO DE COLAS CIRÚRGICAS E SINTÉTICAS, DESTINADO UNIDADE LOCAL DE SAÚDE DE S. JOSÉ, E.P.E., PARA O ANO DE 2025",
    "descricao": "COLAS CIRÚRGICAS E SINTÉTICAS",
    "preco_base": "180.812,50 EUR",
    "prazo_execucao": "5 MESES",
    "prazo_apresentacao_propostas": "26-08-2025 23:59",
    "fundos_eu": "Não",
    "plataforma_eletronica": "VORTAL",
    "url_procedimento": "https://community.vortal.biz/public/",
    "autor_nome": "Conselho de Administração",
    "autor_cargo": "Conselho de Administração"
  },
  {
    "numero_procedimento": "N/A",
    "entidade": "AnÃºncio de procedimento  n.Âº 21942/2025  -  DiÃ¡rio da RepÃºblica n.Âº 156/2025, SÃ©rie II de 2025-08-14",
    "link": "https://diariodarepublica.pt/dr/detalhe/contrato-publico/21942-929044307"
  },
  {
    "numero_procedimento": "N/A",
    "entidade": "AnÃºncio de procedimento  n.Âº 21943/2025  -  DiÃ¡rio da RepÃºblica n.Âº 156/2025, SÃ©rie II de 2025-08-14",
    "link": "https://diariodarepublica.pt/dr/detalhe/contrato-publico/21943-929044308"
  },
  {
    "numero_procedimento": "N/A",
    "entidade": "Município de Aljezur",
    "link": "https://diariodarepublica.pt/dr/detalhe/contrato-publico/21944-929044309",
    "detalhes_completos": "1 - IDENTIFICAÇÃO E CONTACTOS DA ENTIDADE ADJUDICANTE\nDesignação da entidade adjudicante: Município de Aljezur\nNIPC: 505932512\nServiço/Órgão/Pessoa de contacto: Divisão Administrativa e de Recursos Humanos - Serviço de Contratação Pública\nEndereço: Rua Capitão Salgueiro Maia\nCódigo postal: 8670-005\nLocalidade: Aljezur\nPaís: Portugal\nNUT III: PT150\nDistrito: Faro\nConcelho: Aljezur\nFreguesia: Freguesia de Aljezur\nTelefone: 282990010\nFax: 282990011\nEndereço da Entidade (URL): www.cm-aljezur.pt\nEndereço Eletrónico: geral@cm-aljezur.pt\neDelivery Gateway (URL): https://www.acingov.pt\nFunção da Organização: Adquirente\nNorma jurídica da Entidade Adjudicante: Organismo de direito público\nÁrea de atividade da Autoridade Adjudicante: Serviços públicos das administrações públicas\n\n2 - JORNAL OFICIAL DA UNIÃO EUROPEIA\nO procedimento a que este anúncio diz respeito também é publicitado no Jornal Oficial da União Europeia? Não\n\n3 - AVISO\nModelo de Anúncio: Concurso público\nData de Envio do Anúncio: 14-08-2025\n\n5 - PROCESSO\nTipo de Procedimento: Concurso público\nPreço base do procedimento: Sim\nValor do preço base do procedimento: 210.540,00 EUR\nProcedimento com lotes? Não\n\n6 - OBJETO DO CONTRATO\nNúmero de referência interna: 2025/300.10.005/870\nDesignação do contrato: Serviço de aluguer de viaturas certificadas para transporte coletivo de crianças\nDescrição: Serviço de aluguer de viaturas certificadas para transporte coletivo de crianças \n\nTipo de Contrato Principal: Aquisição de Serviços\nTipo de Contrato: Aquisição de Serviços\nClassificação CPV (Vocabulário Comum para os Contratos Públicos)\nObjeto principal\nVocabulário Principal: 60170000\nPreço base s/IVA: 210.540,00 EUR\n\n7 - INDICAÇÕES ADICIONAIS\nO contrato envolve aquisição conjunta (satisfação de várias entidades)? Não\nO contrato é adjudicado por uma central de compras? Não\n\n8 - TÉCNICAS\nO concurso destina-se à celebração de um acordo-quadro? Inexistência de acordo-quadro\nÉ utilizado um leilão eletrónico? Não\nÉ adotada uma fase de negociação? Não\nSistema de Aquisição Dinâmico: Inexistência de sistema de aquisição dinâmico\n\n9 - LOCAL DA EXECUÇÃO DO CONTRATO\nLOCAL DA EXECUÇÃO DO CONTRATO (PROCEDIMENTO)\nPaís: Portugal\nNUT III: PT150\nLocalidade: Freguesia de Aljezur\nDistrito: Faro\nConcelho: Aljezur\nFreguesia: Freguesia de Aljezur\n\n10 - PRAZO DE EXECUÇÃO DO CONTRATO\nData de Início: 11-09-2025\nData de Fim: 30-06-2026\nPrevisão de renovações: Não\n\n11 - FUNDOS EU\nTêm fundos EU? Não\n\n12 - DOCUMENTOS DE HABILITAÇÃO\nHabilitação para o exercício da atividade profissional: Não\n\n13 - CONDIÇÕES DE APRESENTAÇÃO\nPlataforma eletrónica utilizada pela entidade adjudicante: ACIN\nURL para Apresentação: https://www.acingov.pt\nAdmissibilidade da apresentação de propostas variantes: Não autorizado\nPrazo para apresentação das propostas: 22-08-2025 23:59\nPrazo durante o qual os concorrentes são obrigados a manter as respetivas propostas: 66 dias a contar do termo do prazo para a apresentação das propostas\nIndicação de Subcontratação na Proposta: Inexistência de indicação de subcontratação\n\n14 - PRESTAÇÃO DE CAUÇÃO\nPrestação de caução: Não\n\n15 - FORNECIMENTO DAS PEÇAS DO CONCURSO, APRESENTAÇÃO DE PEDIDOS DE PARTICIPAÇÃO E APRESENTAÇÃO DAS PROPOSTAS\nLink para acesso às peças do concurso (URL): https://www.acingov.pt/acingovprod/2/zonaPublica/zona_publica_c/donwloadProcedurePiece/OTM0MjM3\n\n20 - OUTROS REQUISITOS\nInformação sobre contratos reservados. Aplica-se a contratos reservados (54º-A)? Não\n\n21 - CRITÉRIO DE ADJUDICAÇÃO\nMultifator: Não\nMonofator:\nNome: Preço\n\n24 - CONDIÇÕES DO CONTRATO\nFaturação Eletrónica: Permitido\nObrigação de Subcontratação:\nCódigo da Obrigação de Subcontratação: Não é aplicável nenhuma obrigação de subcontratação.\n\n25 - COMPRA PÚBLICA ESTRATÉGICA\nCompra Pública Estratégica: Inexistência de contratação pública estratégica\n\n26 - INFORMAÇÕES ADICIONAIS\nContrato adequado para PME: Sim\nCobertura ACP (Acordo dos Contratos Públicos da Organização Mundial do Comércio): Não\n\n27 - IDENTIFICAÇÃO E CONTACTOS DO ÓRGÃO DE RECURSOS ADMINISTRATIVOS\nDesignação: Câmara Municipal de Aljezur\nEndereço: Rua Capitão Salgueiro Maia\nCódigo postal: 8670-005\nLocalidade: Aljezur\nTelefone: 282990010\nFax: 282990011\nEndereço eletrónico: geral@cm-aljezur.pt\n\n28 - IDENTIFICAÇÃO DO(S) AUTOR(ES) DE ANÚNCIO\nNome: José Manuel Lucas Gonçalves\nCargo: Presidente da Câmara\n419437306",
    "nipc": "505932512",
    "distrito": "Faro",
    "concelho": "Aljezur",
    "freguesia": "Freguesia de Aljezur",
    "site": "www.cm-aljezur.pt",
    "email": "geral@cm-aljezur.pt",
    "designacao_contrato": "Serviço de aluguer de viaturas certificadas para transporte coletivo de crianças",
    "descricao": "Serviço de aluguer de viaturas certificadas para transporte coletivo de crianças",
    "preco_base": "210.540,00 EUR",
    "prazo_execucao": null,
    "prazo_apresentacao_propostas": "22-08-2025 23:59",
    "fundos_eu": "Não",
    "plataforma_eletronica": "ACIN",
    "url_procedimento": "https://www.acingov.pt",
    "autor_nome": "José Manuel Lucas Gonçalves",
    "autor_cargo": "Presidente da Câmara"
  },
  {
    "numero_procedimento": "N/A",
    "entidade": "AnÃºncio de procedimento  n.Âº 21945/2025  -  DiÃ¡rio da RepÃºblica n.Âº 156/2025, SÃ©rie II de 2025-08-14",
    "link": "https://diariodarepublica.pt/dr/detalhe/contrato-publico/21945-929044310"
  },
  {
    "numero_procedimento": "N/A",
    "entidade": "AnÃºncio de procedimento  n.Âº 21946/2025  -  DiÃ¡rio da RepÃºblica n.Âº 156/2025, SÃ©rie II de 2025-08-14",
    "link": "https://diariodarepublica.pt/dr/detalhe/contrato-publico/21946-929044311"
  },
  {
    "numero_procedimento": "N/A",
    "entidade": "AnÃºncio de procedimento  n.Âº 21947/2025  -  DiÃ¡rio da RepÃºblica n.Âº 156/2025, SÃ©rie II de 2025-08-14",
    "link": "https://diariodarepublica.pt/dr/detalhe/contrato-publico/21947-929044312"
  },
  {
    "numero_procedimento": "N/A",
    "entidade": "AnÃºncio de procedimento  n.Âº 21949/2025  -  DiÃ¡rio da RepÃºblica n.Âº 156/2025, SÃ©rie II de 2025-08-14",
    "link": "https://diariodarepublica.pt/dr/detalhe/contrato-publico/21949-929044313"
  },
  {
    "numero_procedimento": "N/A",
    "entidade": "AnÃºncio de procedimento  n.Âº 21951/2025  -  DiÃ¡rio da RepÃºblica n.Âº 156/2025, SÃ©rie II de 2025-08-14",
    "link": "https://diariodarepublica.pt/dr/detalhe/contrato-publico/21951-929044314"
  },
  {
    "numero_procedimento": "N/A",
    "entidade": "AnÃºncio de procedimento  n.Âº 21954/2025  -  DiÃ¡rio da RepÃºblica n.Âº 156/2025, SÃ©rie II de 2025-08-14",
    "link": "https://diariodarepublica.pt/dr/detalhe/contrato-publico/21954-929044315"
  },
  {
    "numero_procedimento": "N/A",
    "entidade": "AnÃºncio de procedimento  n.Âº 21955/2025  -  DiÃ¡rio da RepÃºblica n.Âº 156/2025, SÃ©rie II de 2025-08-14",
    "link": "https://diariodarepublica.pt/dr/detalhe/contrato-publico/21955-929044316"
  },
  {
    "numero_procedimento": "N/A",
    "entidade": "AnÃºncio de procedimento  n.Âº 21956/2025  -  DiÃ¡rio da RepÃºblica n.Âº 156/2025, SÃ©rie II de 2025-08-14",
    "link": "https://diariodarepublica.pt/dr/detalhe/contrato-publico/21956-929044317"
  },
  {
    "numero_procedimento": "N/A",
    "entidade": "AnÃºncio de procedimento  n.Âº 21957/2025  -  DiÃ¡rio da RepÃºblica n.Âº 156/2025, SÃ©rie II de 2025-08-14",
    "link": "https://diariodarepublica.pt/dr/detalhe/contrato-publico/21957-929044318"
  },
  {
    "numero_procedimento": "N/A",
    "entidade": "AnÃºncio de procedimento  n.Âº 21958/2025  -  DiÃ¡rio da RepÃºblica n.Âº 156/2025, SÃ©rie II de 2025-08-14",
    "link": "https://diariodarepublica.pt/dr/detalhe/contrato-publico/21958-929044319"
  },
  {
    "numero_procedimento": "N/A",
    "entidade": "AnÃºncio de procedimento  n.Âº 21960/2025  -  DiÃ¡rio da RepÃºblica n.Âº 156/2025, SÃ©rie II de 2025-08-14",
    "link": "https://diariodarepublica.pt/dr/detalhe/contrato-publico/21960-929044320"
  },
  {
    "numero_procedimento": "N/A",
    "entidade": "AnÃºncio de procedimento  n.Âº 21962/2025  -  DiÃ¡rio da RepÃºblica n.Âº 156/2025, SÃ©rie II de 2025-08-14",
    "link": "https://diariodarepublica.pt/dr/detalhe/contrato-publico/21962-929044321"
  },
  {
    "numero_procedimento": "N/A",
    "entidade": "Município de Vila Nova de Poiares",
    "link": "https://diariodarepublica.pt/dr/detalhe/contrato-publico/21963-929044322",
    "detalhes_completos": "1 - IDENTIFICAÇÃO E CONTACTOS DA ENTIDADE ADJUDICANTE\nDesignação da entidade adjudicante: Município de Vila Nova de Poiares\nNIPC: 505371600\nServiço/Órgão/Pessoa de contacto: Presidente da Câmara\nEndereço: Largo da República, n.º 1\nCódigo postal: 3350-156\nLocalidade: Vila Nova de Poiares\nPaís: Portugal\nNUT III: PT16E\nDistrito: Coimbra\nConcelho: Vila Nova de Poiares\nFreguesia: Todas\nTelefone: 239420850\nFax: 239421800\nEndereço da Entidade (URL): https://www.cm-vilanovadepoiares.pt/\nEndereço Eletrónico: geral@cm-vilanovadepoiares.pt\neDelivery Gateway (URL): https://www.acingov.pt\nFunção da Organização: Adquirente\nNorma jurídica da Entidade Adjudicante: Organismo de direito público\nÁrea de atividade da Autoridade Adjudicante: Serviços públicos das administrações públicas\n\n2 - JORNAL OFICIAL DA UNIÃO EUROPEIA\nO procedimento a que este anúncio diz respeito também é publicitado no Jornal Oficial da União Europeia? Não\n\n3 - AVISO\nModelo de Anúncio: Concurso público\nData de Envio do Anúncio: 14-08-2025\n\n5 - PROCESSO\nTipo de Procedimento: Concurso público\nPreço base do procedimento: Sim\nValor do preço base do procedimento: 39.649,60 EUR\nProcedimento com lotes? Não\n\n6 - OBJETO DO CONTRATO\nNúmero de referência interna: 78/2025\nDesignação do contrato: Aquisição de Plataforma de Gestão Municipal da Educação\nDescrição: Aquisição de Plataforma de Gestão Municipal da Educação\nTipo de Contrato Principal: Aquisição de Bens Móveis\nTipo de Contrato: Aquisição de Bens Móveis; Aquisição de Serviços\nClassificação CPV (Vocabulário Comum para os Contratos Públicos)\nObjeto principal\nVocabulário Principal: 48190000\nPreço base s/IVA: 28.569,60 EUR\nObjeto Complementar\nVocabulário Principal: 98300000\nPreço base s/IVA: 10.440,00 EUR\nObjeto Complementar\nVocabulário Principal: 35123400\nPreço base s/IVA: 640,00 EUR\n\n7 - INDICAÇÕES ADICIONAIS\nO contrato envolve aquisição conjunta (satisfação de várias entidades)? Não\nO contrato é adjudicado por uma central de compras? Não\n\n8 - TÉCNICAS\nO concurso destina-se à celebração de um acordo-quadro? Inexistência de acordo-quadro\nÉ utilizado um leilão eletrónico? Não\nÉ adotada uma fase de negociação? Não\nSistema de Aquisição Dinâmico: Inexistência de sistema de aquisição dinâmico\n\n9 - LOCAL DA EXECUÇÃO DO CONTRATO\nLOCAL DA EXECUÇÃO DO CONTRATO (PROCEDIMENTO)\nPaís: Portugal\nNUT III: PT16E\nLocalidade: Todas\nDistrito: Coimbra\nConcelho: Vila Nova de Poiares\nFreguesia: Todas\n\n10 - PRAZO DE EXECUÇÃO DO CONTRATO\nPrazo de execução do contrato: 36 MESES\nPrevisão de renovações: Não\n\n11 - FUNDOS EU\nTêm fundos EU? Não\n\n12 - DOCUMENTOS DE HABILITAÇÃO\nHabilitação para o exercício da atividade profissional: Não\n\n13 - CONDIÇÕES DE APRESENTAÇÃO\nPlataforma eletrónica utilizada pela entidade adjudicante: ACIN\nURL para Apresentação: https://www.acingov.pt\nAdmissibilidade da apresentação de propostas variantes: Não autorizado\nPrazo para apresentação das propostas: 20-08-2025 23:59\nPrazo durante o qual os concorrentes são obrigados a manter as respetivas propostas: 66 dias a contar do termo do prazo para a apresentação das propostas\nIndicação de Subcontratação na Proposta: Inexistência de indicação de subcontratação\n\n14 - PRESTAÇÃO DE CAUÇÃO\nPrestação de caução: Não\n\n15 - FORNECIMENTO DAS PEÇAS DO CONCURSO, APRESENTAÇÃO DE PEDIDOS DE PARTICIPAÇÃO E APRESENTAÇÃO DAS PROPOSTAS\nLink para acesso às peças do concurso (URL): https://www.acingov.pt/acingovprod/2/zonaPublica/zona_publica_c/donwloadProcedurePiece/OTMxNzEx\n\n20 - OUTROS REQUISITOS\nInformação sobre contratos reservados. Aplica-se a contratos reservados (54º-A)? Não\n\n21 - CRITÉRIO DE ADJUDICAÇÃO\nMultifator: Não\nMonofator:\nNome: Preço\n\n24 - CONDIÇÕES DO CONTRATO\nFaturação Eletrónica: Permitido\nObrigação de Subcontratação:\nCódigo da Obrigação de Subcontratação: Não é aplicável nenhuma obrigação de subcontratação.\n\n25 - COMPRA PÚBLICA ESTRATÉGICA\nCompra Pública Estratégica: Inexistência de contratação pública estratégica\n\n26 - INFORMAÇÕES ADICIONAIS\nContrato adequado para PME: Não\nCobertura ACP (Acordo dos Contratos Públicos da Organização Mundial do Comércio): Não\n\n27 - IDENTIFICAÇÃO E CONTACTOS DO ÓRGÃO DE RECURSOS ADMINISTRATIVOS\nDesignação: Presidente da Câmara\nEndereço: Largo da República, n.º 1\nCódigo postal: 3350-156\nLocalidade: Vila Nova de Poiares\nTelefone: 239420850\nFax: 239421800\nEndereço eletrónico: geral@cm-vilanovadepoiares.pt\nPrazo de interposição do recurso: 3 dias\n\n28 - IDENTIFICAÇÃO DO(S) AUTOR(ES) DE ANÚNCIO\nNome: João Miguel Sousa Henriques\nCargo: Presidente da Câmara Municipa\n419436504",
    "nipc": "505371600",
    "distrito": "Coimbra",
    "concelho": "Vila Nova de Poiares",
    "freguesia": "Todas",
    "site": "https://www.cm-vilanovadepoiares.pt/",
    "email": "geral@cm-vilanovadepoiares.pt",
    "designacao_contrato": "Aquisição de Plataforma de Gestão Municipal da Educação",
    "descricao": "Aquisição de Plataforma de Gestão Municipal da Educação",
    "preco_base": "28.569,60 EUR",
    "prazo_execucao": "36 MESES",
    "prazo_apresentacao_propostas": "20-08-2025 23:59",
    "fundos_eu": "Não",
    "plataforma_eletronica": "ACIN",
    "url_procedimento": "https://www.acingov.pt",
    "autor_nome": "João Miguel Sousa Henriques",
    "autor_cargo": "Presidente da Câmara Municipa"
  },
  {
    "numero_procedimento": "N/A",
    "entidade": "AnÃºncio de procedimento  n.Âº 21964/2025  -  DiÃ¡rio da RepÃºblica n.Âº 156/2025, SÃ©rie II de 2025-08-14",
    "link": "https://diariodarepublica.pt/dr/detalhe/contrato-publico/21964-929044323"
  },
  {
    "numero_procedimento": "N/A",
    "entidade": "AnÃºncio de procedimento  n.Âº 21969/2025  -  DiÃ¡rio da RepÃºblica n.Âº 156/2025, SÃ©rie II de 2025-08-14",
    "link": "https://diariodarepublica.pt/dr/detalhe/contrato-publico/21969-929044324"
  },
  {
    "numero_procedimento": "N/A",
    "entidade": "AnÃºncio de procedimento  n.Âº 21970/2025  -  DiÃ¡rio da RepÃºblica n.Âº 156/2025, SÃ©rie II de 2025-08-14",
    "link": "https://diariodarepublica.pt/dr/detalhe/contrato-publico/21970-929044325"
  },
  {
    "numero_procedimento": "N/A",
    "entidade": "AnÃºncio de procedimento  n.Âº 21971/2025  -  DiÃ¡rio da RepÃºblica n.Âº 156/2025, SÃ©rie II de 2025-08-14",
    "link": "https://diariodarepublica.pt/dr/detalhe/contrato-publico/21971-929044326"
  },
  {
    "numero_procedimento": "N/A",
    "entidade": "AnÃºncio de procedimento  n.Âº 21972/2025  -  DiÃ¡rio da RepÃºblica n.Âº 156/2025, SÃ©rie II de 2025-08-14",
    "link": "https://diariodarepublica.pt/dr/detalhe/contrato-publico/21972-929044327"
  },
  {
    "numero_procedimento": "N/A",
    "entidade": "AnÃºncio de procedimento  n.Âº 21974/2025  -  DiÃ¡rio da RepÃºblica n.Âº 156/2025, SÃ©rie II de 2025-08-14",
    "link": "https://diariodarepublica.pt/dr/detalhe/contrato-publico/21974-929044328"
  },
  {
    "numero_procedimento": "N/A",
    "entidade": "AnÃºncio de procedimento  n.Âº 21975/2025  -  DiÃ¡rio da RepÃºblica n.Âº 156/2025, SÃ©rie II de 2025-08-14",
    "link": "https://diariodarepublica.pt/dr/detalhe/contrato-publico/21975-929044329"
  },
  {
    "numero_procedimento": "N/A",
    "entidade": "AnÃºncio de procedimento  n.Âº 21976/2025  -  DiÃ¡rio da RepÃºblica n.Âº 156/2025, SÃ©rie II de 2025-08-14",
    "link": "https://diariodarepublica.pt/dr/detalhe/contrato-publico/21976-929044330"
  },
  {
    "numero_procedimento": "N/A",
    "entidade": "AnÃºncio de procedimento  n.Âº 21977/2025  -  DiÃ¡rio da RepÃºblica n.Âº 156/2025, SÃ©rie II de 2025-08-14",
    "link": "https://diariodarepublica.pt/dr/detalhe/contrato-publico/21977-929044331"
  },
  {
    "numero_procedimento": "N/A",
    "entidade": "AnÃºncio de procedimento  n.Âº 21980/2025  -  DiÃ¡rio da RepÃºblica n.Âº 156/2025, SÃ©rie II de 2025-08-14",
    "link": "https://diariodarepublica.pt/dr/detalhe/contrato-publico/21980-929044332"
  },
  {
    "numero_procedimento": "N/A",
    "entidade": "AnÃºncio de procedimento  n.Âº 21981/2025  -  DiÃ¡rio da RepÃºblica n.Âº 156/2025, SÃ©rie II de 2025-08-14",
    "link": "https://diariodarepublica.pt/dr/detalhe/contrato-publico/21981-929044342"
  },
  {
    "numero_procedimento": "N/A",
    "entidade": "AnÃºncio de procedimento  n.Âº 21984/2025  -  DiÃ¡rio da RepÃºblica n.Âº 156/2025, SÃ©rie II de 2025-08-14",
    "link": "https://diariodarepublica.pt/dr/detalhe/contrato-publico/21984-929044343"
  },
  {
    "numero_procedimento": "N/A",
    "entidade": "AnÃºncio de procedimento  n.Âº 21986/2025  -  DiÃ¡rio da RepÃºblica n.Âº 156/2025, SÃ©rie II de 2025-08-14",
    "link": "https://diariodarepublica.pt/dr/detalhe/contrato-publico/21986-929044344"
  },
  {
    "numero_procedimento": "N/A",
    "entidade": "AnÃºncio de procedimento  n.Âº 21987/2025  -  DiÃ¡rio da RepÃºblica n.Âº 156/2025, SÃ©rie II de 2025-08-14",
    "link": "https://diariodarepublica.pt/dr/detalhe/contrato-publico/21987-929044345"
  },
  {
    "numero_procedimento": "N/A",
    "entidade": "AnÃºncio de procedimento  n.Âº 21988/2025  -  DiÃ¡rio da RepÃºblica n.Âº 156/2025, SÃ©rie II de 2025-08-14",
    "link": "https://diariodarepublica.pt/dr/detalhe/contrato-publico/21988-929044346"
  },
  {
    "numero_procedimento": "N/A",
    "entidade": "AnÃºncio de procedimento  n.Âº 21989/2025  -  DiÃ¡rio da RepÃºblica n.Âº 156/2025, SÃ©rie II de 2025-08-14",
    "link": "https://diariodarepublica.pt/dr/detalhe/contrato-publico/21989-929044347"
  },
  {
    "numero_procedimento": "N/A",
    "entidade": "AnÃºncio de procedimento  n.Âº 21990/2025  -  DiÃ¡rio da RepÃºblica n.Âº 156/2025, SÃ©rie II de 2025-08-14",
    "link": "https://diariodarepublica.pt/dr/detalhe/contrato-publico/21990-929044352"
  }
]