[
  {
    "numero_procedimento": "N/A",
    "entidade": "Município de São João da Pesqueira",
    "link": "https://diariodarepublica.pt/dr/detalhe/contrato-publico/27261-940388174",
    "detalhes_completos": "Alteração do Anúncio de procedimento n.º 25621/2025, de 2025-09-29, com o ID 419588542\n\n1 - IDENTIFICAÇÃO E CONTACTOS DA ENTIDADE ADJUDICANTE\nDesignação da entidade adjudicante: Município de São João da Pesqueira\nNIPC: 506892646\nServiço/Órgão/Pessoa de contacto: DPOAU\nEndereço: AV MARQUES DE SOVERAL N 67\nCódigo postal: 5130-321\nLocalidade: São João da Pesqueira\nPaís: Portugal\nNUT III: PT11D\nDistrito: Viseu\nConcelho: São João da Pesqueira\nFreguesia: União das Freguesias de São João da Pesqueira e Várzea de Trevões\nTelefone: 254489999\nFax: 254489999\nEndereço da Entidade (URL): https://www.acingov.pt/acingovprod/2/\nEndereço Eletrónico: cmsjp@sjpesqueira.pt\neDelivery Gateway (URL): https://www.acingov.pt\nFunção da Organização: Adquirente\nNorma jurídica da Entidade Adjudicante: Organismo de direito público\nÁrea de atividade da Autoridade Adjudicante: Serviços públicos das administrações públicas\n\n2 - JORNAL OFICIAL DA UNIÃO EUROPEIA\nO procedimento a que este anúncio diz respeito também é publicitado no Jornal Oficial da União Europeia? Não\n\n3 - AVISO\nModelo de Anúncio: Concurso público\nData de Envio do Anúncio: 15-10-2025\n\n5 - PROCESSO\nTipo de Procedimento: Concurso público\nPreço base do procedimento: Sim\nValor do preço base do procedimento: 335.000,00 EUR\nProcedimento com lotes? Não\n\n6 - OBJETO DO CONTRATO\nNúmero de referência interna: CP/14/2025\nDesignação do contrato: Estaleiro, equipamentos e plano de higiene, segurança e saúde, gestão de resíduos em obra, demolições, movimentos de terras, estruturas metálicas, pavimentação e equipamentos de sinalização e segurança.\nDescrição: Requalificação da Escola Básica de São João da Pesqueira\nTipo de Contrato Principal: Empreitada de Obras Públicas\nTipo de Contrato: Empreitada de Obras Públicas\nClassificação CPV (Vocabulário Comum para os Contratos Públicos)\nObjeto principal\nVocabulário Principal: 45223110\nPreço base s/IVA: 335.000,00 EUR\n\n7 - INDICAÇÕES ADICIONAIS\nO contrato envolve aquisição conjunta (satisfação de várias entidades)? Não\nO contrato é adjudicado por uma central de compras? Não\n\n8 - TÉCNICAS\nO concurso destina-se à celebração de um acordo-quadro? Inexistência de acordo-quadro\nÉ utilizado um leilão eletrónico? Não\nÉ adotada uma fase de negociação? Não\nSistema de Aquisição Dinâmico: Inexistência de sistema de aquisição dinâmico\n\n9 - LOCAL DA EXECUÇÃO DO CONTRATO\nLOCAL DA EXECUÇÃO DO CONTRATO (PROCEDIMENTO)\nPaís: Portugal\nNUT III: PT11D\nLocalidade: União das Freguesias de São João da Pesqueira e Várzea de Trevões\nDistrito: Viseu\nConcelho: São João da Pesqueira\nFreguesia: União das Freguesias de São João da Pesqueira e Várzea de Trevões\n\n10 - PRAZO DE EXECUÇÃO DO CONTRATO\nPrazo de execução do contrato: 240 DIAS\nPrevisão de renovações: Não\n\n11 - FUNDOS EU\nTêm fundos EU? Sim\n\n12 - DOCUMENTOS DE HABILITAÇÃO\nHabilitação para o exercício da atividade profissional: Sim\nTipo: Alvará\nDescrição: Detenção de alvará de empreiteiro de obras públicas ou do título de registo emitido pelo IMPIC, I.P, na 1ª Categoria (Edifícios e Património Construído), com classe que cubra o valor global da proposta, e a 2.ª Subcategoria (Estruturas metálicas) da 1.ª Categoria, da classe corresponde ao valor dos trabalhos a que respeita, a proposta, e a 10.ª subcategoria (Infraestruturas de desporto e de lazer), da 2.ª Categoria (Vias de Comunicação, Obras de Urbanização e outras Infraestruturas), da classe corresponde ao valor dos trabalhos a que respeita, a proposta.\n\n13 - CONDIÇÕES DE APRESENTAÇÃO\nPlataforma eletrónica utilizada pela entidade adjudicante: ACIN\nURL para Apresentação: https://www.acingov.pt\nAdmissibilidade da apresentação de propostas variantes: Não autorizado\nPrazo para apresentação das propostas: 03-12-2025 00:00\nPrazo durante o qual os concorrentes são obrigados a manter as respetivas propostas: 120 dias a contar do termo do prazo para a apresentação das propostas\nIndicação de Subcontratação na Proposta: Inexistência de indicação de subcontratação\n\n14 - PRESTAÇÃO DE CAUÇÃO\nPrestação de caução: Não\n\n15 - FORNECIMENTO DAS PEÇAS DO CONCURSO, APRESENTAÇÃO DE PEDIDOS DE PARTICIPAÇÃO E APRESENTAÇÃO DAS PROPOSTAS\nLink para acesso às peças do concurso (URL): https://www.acingov.pt/acingovprod/2/zonaPublica/zona_publica_c/donwloadProcedurePiece/OTgyMDkz\n\n20 - OUTROS REQUISITOS\nInformação sobre contratos reservados. Aplica-se a contratos reservados (54º-A)? Não\n\n21 - CRITÉRIO DE ADJUDICAÇÃO\nMultifator: Não\nMonofator:\nNome: Preço\n\n24 - CONDIÇÕES DO CONTRATO\nFaturação Eletrónica: Permitido\nObrigação de Subcontratação:\nCódigo da Obrigação de Subcontratação: Não é aplicável nenhuma obrigação de subcontratação.\n\n25 - COMPRA PÚBLICA ESTRATÉGICA\nCompra Pública Estratégica: Inexistência de contratação pública estratégica\n\n26 - INFORMAÇÕES ADICIONAIS\nContrato adequado para PME: Sim\nCobertura ACP (Acordo dos Contratos Públicos da Organização Mundial do Comércio): Não\n\n27 - IDENTIFICAÇÃO E CONTACTOS DO ÓRGÃO DE RECURSOS ADMINISTRATIVOS\nDesignação: Câmara Municipal\nEndereço: Av. Marquês de Soveral\nCódigo postal: 5130-321\nLocalidade: São João da Pesqueira\nTelefone: 254489999\nFax: 254489999\nEndereço eletrónico: cmsjp@sjpesqueira.pt\nPrazo de interposição do recurso: 5 dias\n\n28 - IDENTIFICAÇÃO DO(S) AUTOR(ES) DE ANÚNCIO\nNome: Manuel António Natário Cordeiro\nCargo: Presidente\n\n29 - ALTERAÇÃO\nMotivo da Alteração: Correção pelo adquirente\nIdentificador da Versão do Anúncio a Alterar: 2e9179aa-8b08-4b64-950a-35d899aa8965-01\nIdentificador das Secções Alteradas do Anúncio Anterior: Condições de Apresentação\nDescrição das Alterações: Modificação do prazo para a apresentação de propostas\nAlteração dos Documentos do Concurso: Não\n419662098",
    "nipc": "506892646",
    "distrito": "Viseu",
    "concelho": "São João da Pesqueira",
    "freguesia": "União das Freguesias de São João da Pesqueira e Várzea de Trevões",
    "site": "https://www.acingov.pt/acingovprod/2/",
    "email": "cmsjp@sjpesqueira.pt",
    "designacao_contrato": "Estaleiro, equipamentos e plano de higiene, segurança e saúde, gestão de resíduos em obra, demolições, movimentos de terras, estruturas metálicas, pavimentação e equipamentos de sinalização e segurança.",
    "descricao": "Requalificação da Escola Básica de São João da Pesqueira",
    "preco_base": "335.000,00 EUR",
    "prazo_execucao": "240 DIAS",
    "prazo_apresentacao_propostas": "03-12-2025 00:00",
    "fundos_eu": "Sim",
    "plataforma_eletronica": "ACIN",
    "url_procedimento": "https://www.acingov.pt",
    "autor_nome": "Manuel António Natário Cordeiro",
    "autor_cargo": "Presidente"
  },
  {
    "numero_procedimento": "N/A",
    "entidade": "Associação de Promoção da Região Autónoma da Madeira",
    "link": "https://diariodarepublica.pt/dr/detalhe/contrato-publico/27257-940390076",
    "detalhes_completos": "1 - IDENTIFICAÇÃO E CONTACTOS DA ENTIDADE ADJUDICANTE\nDesignação da entidade adjudicante: Associação de Promoção da Região Autónoma da Madeira\nNIPC: 511236077\nServiço/Órgão/Pessoa de contacto: Direção da Associação de Promoção da Madeira\nEndereço: Rua dos Aranhas, n.º 24\nCódigo postal: 9000-044\nLocalidade: Funchal\nPaís: Portugal\nNUT III: PT300\nDistrito: Região Autónoma da Madeira\nConcelho: Funchal\nFreguesia: Freguesia de Sé (Funchal)\nTelefone: 291203420\nFax: 291222167\nEndereço da Entidade (URL): https://www.apmadeira.pt/pt/\nEndereço Eletrónico: geral@ap-madeira.pt\neDelivery Gateway (URL): https://www.acingov.pt\nFunção da Organização: Adquirente\nSubfunção da Organização: Organização cujo orçamento é utilizado para pagar o contrato; Organização que executa o pagamento; Organização responsável pelo tratamento das propostas; Organização que recebe as propostas; Organização que assina o contrato\nNorma jurídica da Entidade Adjudicante: Organismo de direito público\nÁrea de atividade da Autoridade Adjudicante: Serviços públicos das administrações públicas\n\n2 - JORNAL OFICIAL DA UNIÃO EUROPEIA\nO procedimento a que este anúncio diz respeito também é publicitado no Jornal Oficial da União Europeia? Não\n\n3 - AVISO\nModelo de Anúncio: Concurso limitado por prévia qualificação\nData de Envio do Anúncio: 15-10-2025\n\n5 - PROCESSO\nTipo de Procedimento: Concurso limitado por prévia qualificação\nPreço base do procedimento: Sim\nValor do preço base do procedimento: 170.000,00 EUR\nProcedimento com lotes? Não\n\n6 - OBJETO DO CONTRATO\nNúmero de referência interna: 5/2025\nDesignação do contrato: Aquisição de serviços de Relações Públicas e de assessoria de imprensa e comunicação, para mobilizar um target específico de cultura canadiana.\nDescrição: Aquisição de serviços de Relações Públicas e de assessoria de imprensa e comunicação, para mobilizar um target específico de cultura canadiana\nTipo de Contrato Principal: Aquisição de Serviços\nTipo de Contrato: Aquisição de Serviços\nClassificação CPV (Vocabulário Comum para os Contratos Públicos)\nObjeto principal\nVocabulário Principal: 79416000\nPreço base s/IVA: 170.000,00 EUR\n\n7 - INDICAÇÕES ADICIONAIS\nO contrato envolve aquisição conjunta (satisfação de várias entidades)? Não\nO contrato é adjudicado por uma central de compras? Não\n\n8 - TÉCNICAS\nO concurso destina-se à celebração de um acordo-quadro? Inexistência de acordo-quadro\nÉ utilizado um leilão eletrónico? Não\nSistema de Aquisição Dinâmico: Inexistência de sistema de aquisição dinâmico\n\n9 - LOCAL DA EXECUÇÃO DO CONTRATO\nLOCAL DA EXECUÇÃO DO CONTRATO (PROCEDIMENTO)\nPaís: Portugal\nLocalidade: Todas\nDistrito: Região Autónoma da Madeira\nConcelho: Todos\nFreguesia: Todas\nPaís: Canadá\nLocalidade: Toronto\n\n10 - PRAZO DE EXECUÇÃO DO CONTRATO\nPrazo de execução do contrato: 1 ANOS\nPrevisão de renovações: Sim\nIndicar número máximo de renovações: 2\nPrazo de renovações diferente do prazo inicial: Não\n\n11 - FUNDOS EU\nTêm fundos EU? Não\n\n12 - DOCUMENTOS DE HABILITAÇÃO\nHabilitação para o exercício da atividade profissional: Não\n\n13 - CONDIÇÕES DE APRESENTAÇÃO\nPlataforma eletrónica utilizada pela entidade adjudicante: ACIN\nURL para Apresentação: https://www.acingov.pt\nAdmissibilidade da apresentação de propostas variantes: Não autorizado\nPrazo para apresentação das candidaturas: 31-10-2025 18:00\nPrazo para a decisão de qualificação: 44 dias a contar do termo do prazo para a apresentação das candidaturas\nRequisitos mínimos \nRequisitos mínimos de capacidade técnica: a) Qualificação técnica e experiência curricular do candidato: i. Deter experiência a trabalhar com, pelo menos, 3 (três) destinos turísticos ou Convention Bureaux internacionais diferentes, bem como experiência a representar destinos de dimensão e com ofertas turísticas comparáveis às da Região Autónoma da Madeira e do destino Madeira, em press events sobre destinos turísticos, no Canadá;; b) Descrição geral sobre os recursos humanos do candidato, em especial a quantidade e funções dos membros da equipa do candidato a afetar à prestação de serviços: i. Dispor de, no mínimo, 2 (dois) recursos humanos  1 (um) Diretor e 1 (um) Gestor de Contas (Account Executive) , suficientes para apoiar eventos e atividades além das operações diárias, incluindo a gestão de projetos e iniciativas ad hoc;; c) Localização de instalações do candidato no Canadá: i. Ter, no mínimo, 1 (um) escritório físico, no Canadá, em uma das seguintes cidades: Toronto, Montreal e Vancouver. \nRequisitos mínimos de capacidade financeira: Requisitos Mínimos (Artigo 165º do CCP)\nPrazo durante o qual os concorrentes são obrigados a manter as respetivas propostas: 66 dias a contar do termo do prazo para a apresentação das propostas\nIndicação de Subcontratação na Proposta: Inexistência de indicação de subcontratação\n\n14 - PRESTAÇÃO DE CAUÇÃO\nPrestação de caução: Não\n\n15 - FORNECIMENTO DAS PEÇAS DO CONCURSO, APRESENTAÇÃO DE PEDIDOS DE PARTICIPAÇÃO E APRESENTAÇÃO DAS PROPOSTAS\nLink para acesso às peças do concurso (URL): https://www.acingov.pt/acingovprod/2/zonaPublica/zona_publica_c/donwloadProcedurePiece/OTg2NTI4\n\n20 - OUTROS REQUISITOS\nInformação sobre contratos reservados. Aplica-se a contratos reservados (54º-A)? Não\n\n21 - CRITÉRIO DE ADJUDICAÇÃO\nMultifator: Não\nMonofator:\nNome: Outros\nOutro nome: Fator Preço\n\n24 - CONDIÇÕES DO CONTRATO\nFaturação Eletrónica: Permitido\nObrigação de Subcontratação:\nCódigo da Obrigação de Subcontratação: Não é aplicável nenhuma obrigação de subcontratação.\n\n25 - COMPRA PÚBLICA ESTRATÉGICA\nCompra Pública Estratégica: Inexistência de contratação pública estratégica\n\n26 - INFORMAÇÕES ADICIONAIS\nContrato adequado para PME: Não\nCobertura ACP (Acordo dos Contratos Públicos da Organização Mundial do Comércio): Não\n\n27 - IDENTIFICAÇÃO E CONTACTOS DO ÓRGÃO DE RECURSOS ADMINISTRATIVOS\nDesignação: Direção da Associação de Promoção da Madeira\nEndereço: Rua dos Aranhas, n.º 24\nCódigo postal: 9000-044\nLocalidade: Funchal\nTelefone: 291203420\nFax: \nEndereço eletrónico: cp@ap-madeira.pt\nPrazo de interposição do recurso: 5 dias\n\n28 - IDENTIFICAÇÃO DO(S) AUTOR(ES) DE ANÚNCIO\nNome: António Eduardo de Freitas Jesus\nCargo: Presidente da Direção da Associação de Promoção da Madeira\n419661311",
    "nipc": "511236077",
    "distrito": "Região Autónoma da Madeira",
    "concelho": "Funchal",
    "freguesia": "Freguesia de Sé (Funchal)",
    "site": "https://www.apmadeira.pt/pt/",
    "email": "geral@ap-madeira.pt",
    "designacao_contrato": "Aquisição de serviços de Relações Públicas e de assessoria de imprensa e comunicação, para mobilizar um target específico de cultura canadiana.",
    "descricao": "Aquisição de serviços de Relações Públicas e de assessoria de imprensa e comunicação, para mobilizar um target específico de cultura canadiana",
    "preco_base": "170.000,00 EUR",
    "prazo_execucao": "1 ANOS",
    "prazo_apresentacao_propostas": null,
    "fundos_eu": "Não",
    "plataforma_eletronica": "ACIN",
    "url_procedimento": "https://www.acingov.pt",
    "autor_nome": "António Eduardo de Freitas Jesus",
    "autor_cargo": "Presidente da Direção da Associação de Promoção da Madeira"
  },
  {
    "numero_procedimento": "N/A",
    "entidade": "Unidade Local de Saúde de Lisboa Ocidental, E. P. E.",
    "link": "https://diariodarepublica.pt/dr/detalhe/contrato-publico/27258-940390077",
    "detalhes_completos": "1 - IDENTIFICAÇÃO E CONTACTOS DA ENTIDADE ADJUDICANTE\nDesignação da entidade adjudicante: Unidade Local de Saúde de Lisboa Ocidental, E. P. E.\nNIPC: 507618319\nEndereço: Santa Maria de Belém  Estrada do Forte do Alto do Duque\nCódigo postal: 1449-005\nLocalidade: Lisboa\nPaís: Portugal\nNUT III: PT170\nDistrito: Lisboa\nConcelho: Lisboa\nFreguesia: Todas\nTelefone: 210431000\nFax: 210431642\nEndereço da Entidade (URL): www.chlo.min-saude.pt/\nEndereço Eletrónico: comprasgeral@ulslo.min-saude.pt\neDelivery Gateway (URL): https://community.vortal.biz/public/\nFunção da Organização: Adquirente\nNorma jurídica da Entidade Adjudicante: Organismo de direito público\nÁrea de atividade da Autoridade Adjudicante: Saúde\n\n2 - JORNAL OFICIAL DA UNIÃO EUROPEIA\nO procedimento a que este anúncio diz respeito também é publicitado no Jornal Oficial da União Europeia? Não\n\n3 - AVISO\nModelo de Anúncio: Concurso público\nData de Envio do Anúncio: 15-10-2025\n\n5 - PROCESSO\nTipo de Procedimento: Concurso público\nPreço base do procedimento: Sim\nValor do preço base do procedimento: 211.035,00 EUR\nProcedimento com lotes? Sim\nNº Máx. de Lotes Autorizado: 4\nNúmero máximo de lotes que podem ser adjudicados a um concorrente: 4\n\n6 - OBJETO DO CONTRATO\nNúmero de referência interna: LG-142007325 PERFUSAO E CCT PARA A ULSLO\nDesignação do contrato: 142007325  AQUISICAO MATERIAL PERFUSAO E CCT PARA A ULSLO\nDescrição: 142007325 AQUISICAO MATERIAL PERFUSAO E CCT PARA A ULSLO\nTipo de Contrato Principal: Aquisição de Bens Móveis\nTipo de Contrato: Aquisição de Bens Móveis\nClassificação CPV (Vocabulário Comum para os Contratos Públicos)\nObjeto principal\nVocabulário Principal: 33140000\nPreço base s/IVA: 211.035,00 EUR\nLotes: \nNº: LOT-0001\nDescrição do Lote: 1\nPreço base s/IVA: 42.480,00 EUR\nClassificação CPV (Vocabulário Comum para os Contratos Públicos)\nObjeto principal\nVocabulário Principal: 33140000\nNº: LOT-0002\nDescrição do Lote: 2\nPreço base s/IVA: 57.375,00 EUR\nClassificação CPV (Vocabulário Comum para os Contratos Públicos)\nObjeto principal\nVocabulário Principal: 33140000\nNº: LOT-0003\nDescrição do Lote: 3\nPreço base s/IVA: 79.680,00 EUR\nClassificação CPV (Vocabulário Comum para os Contratos Públicos)\nObjeto principal\nVocabulário Principal: 33140000\nNº: LOT-0004\nDescrição do Lote: 4\nPreço base s/IVA: 31.500,00 EUR\nClassificação CPV (Vocabulário Comum para os Contratos Públicos)\nObjeto principal\nVocabulário Principal: 33140000\n\n7 - INDICAÇÕES ADICIONAIS\nO contrato envolve aquisição conjunta (satisfação de várias entidades)? Não\nO contrato é adjudicado por uma central de compras? Não\n\n8 - TÉCNICAS\nO concurso destina-se à celebração de um acordo-quadro? Inexistência de acordo-quadro\nÉ utilizado um leilão eletrónico? Não\nÉ adotada uma fase de negociação? Não\nSistema de Aquisição Dinâmico: Inexistência de sistema de aquisição dinâmico\n\n9 - LOCAL DA EXECUÇÃO DO CONTRATO\nLOCAL DA EXECUÇÃO DO CONTRATO (PROCEDIMENTO)\nPaís: Portugal\nNUT III: PT170\nLocalidade: Lisboa\nDistrito: Lisboa\nConcelho: Lisboa\nFreguesia: Todas\nLOCAL DA EXECUÇÃO DO CONTRATO (LOTE)\nIdentificador do Lote: LOT-0001; LOT-0002; LOT-0003; LOT-0004\nPaís: Portugal\nNUT III: PT170\nLocalidade: Lisboa\nDistrito: Lisboa\nConcelho: Lisboa\nFreguesia: Todas\n\n10 - PRAZO DE EXECUÇÃO DO CONTRATO\nIdentificador do Lote: LOT-0001; LOT-0002; LOT-0003; LOT-0004\nPrazo de execução do contrato: 4 MESES\nPrevisão de renovações: Não\n\n11 - FUNDOS EU\nIdentificador do Lote: LOT-0001; LOT-0002; LOT-0003; LOT-0004\nTêm fundos EU? Não\n\n12 - DOCUMENTOS DE HABILITAÇÃO\nHabilitação para o exercício da atividade profissional: Não\n\n13 - CONDIÇÕES DE APRESENTAÇÃO\nPlataforma eletrónica utilizada pela entidade adjudicante: VORTAL\nURL para Apresentação: https://community.vortal.biz/public/\nAdmissibilidade da apresentação de propostas variantes: Não autorizado\nPrazo para apresentação das propostas: 30-10-2025 23:59\nPrazo durante o qual os concorrentes são obrigados a manter as respetivas propostas: 66 dias a contar do termo do prazo para a apresentação das propostas\nIndicação de Subcontratação na Proposta: Inexistência de indicação de subcontratação\n\n14 - PRESTAÇÃO DE CAUÇÃO\nPrestação de caução: Não\n\n15 - FORNECIMENTO DAS PEÇAS DO CONCURSO, APRESENTAÇÃO DE PEDIDOS DE PARTICIPAÇÃO E APRESENTAÇÃO DAS PROPOSTAS\nLink para acesso às peças do concurso (URL): https://community.vortal.biz/Public/public-tender-documents/UjEvbGNNbTFHaVpkWEVaeUlKeXZnR2hYdEU3K2VUV0tWeGEwSzA2S1d3cHdZWmwwcFk0WGhvVVU4WUtScjBldmUxaEpsVFRndEY3Uk9YZU81YUEyU1E9PUByRyh3\n\n20 - OUTROS REQUISITOS\nIdentificador do Lote: LOT-0001; LOT-0002; LOT-0003; LOT-0004\nInformação sobre contratos reservados. Aplica-se a contratos reservados (54º-A)? Não\n\n21 - CRITÉRIO DE ADJUDICAÇÃO\nO Critério de adjudicação é diferenciado por lote? Não\nMultifator: Não\nMonofator:\nNome: Preço\n\n24 - CONDIÇÕES DO CONTRATO\nIdentificador do Lote: LOT-0001; LOT-0002; LOT-0003; LOT-0004\nFaturação Eletrónica: Permitido\nObrigação de Subcontratação:\nCódigo da Obrigação de Subcontratação: Não é aplicável nenhuma obrigação de subcontratação.\n\n25 - COMPRA PÚBLICA ESTRATÉGICA\nCompra Pública Estratégica: Inexistência de contratação pública estratégica\n\n26 - INFORMAÇÕES ADICIONAIS\nIdentificador do Lote: LOT-0001; LOT-0002; LOT-0003; LOT-0004\nContrato adequado para PME: Sim\nCobertura ACP (Acordo dos Contratos Públicos da Organização Mundial do Comércio): Não\n\n27 - IDENTIFICAÇÃO E CONTACTOS DO ÓRGÃO DE RECURSOS ADMINISTRATIVOS\nDesignação: Serviço Gestão de Compras\nEndereço: Estrada do Forte do Alto do Duque\nCódigo postal: 1449-005\nLocalidade: Lisboa\nTelefone: +351 210431000\nFax: +351 210431642\nEndereço eletrónico: comprascclinico@ulslo.min-saude.pt\n\n28 - IDENTIFICAÇÃO DO(S) AUTOR(ES) DE ANÚNCIO\nNome: Andrea Malta\nCargo: Diretora Serviço Gestão de Compras\n419657602",
    "nipc": "507618319",
    "distrito": "Lisboa",
    "concelho": "Lisboa",
    "freguesia": "Todas",
    "site": "www.chlo.min-saude.pt/",
    "email": "comprasgeral@ulslo.min-saude.pt",
    "designacao_contrato": "142007325 AQUISICAO MATERIAL PERFUSAO E CCT PARA A ULSLO",
    "descricao": "142007325 AQUISICAO MATERIAL PERFUSAO E CCT PARA A ULSLO",
    "preco_base": "211.035,00 EUR",
    "prazo_execucao": "4 MESES",
    "prazo_apresentacao_propostas": "30-10-2025 23:59",
    "fundos_eu": "Não",
    "plataforma_eletronica": "VORTAL",
    "url_procedimento": "https://community.vortal.biz/public/",
    "autor_nome": "Andrea Malta",
    "autor_cargo": "Diretora Serviço Gestão de Compras"
  },
  {
    "numero_procedimento": "N/A",
    "entidade": "Unidade Local de Saúde de Santo António, E. P. E.",
    "link": "https://diariodarepublica.pt/dr/detalhe/contrato-publico/27259-940390078",
    "detalhes_completos": "1 - IDENTIFICAÇÃO E CONTACTOS DA ENTIDADE ADJUDICANTE\nDesignação da entidade adjudicante: Unidade Local de Saúde de Santo António, E. P. E.\nNIPC: 517392259\nEndereço: Largo Prof. Abel Salazar\nCódigo postal: 4099-001\nLocalidade: Área Metropolitana do Porto\nPaís: Portugal\nNUT III: PT11A\nDistrito: Porto\nConcelho: Porto\nFreguesia: Todas\nTelefone: 222077500\nFax: 223320318\nEndereço da Entidade (URL): www.hgsa.pt\nEndereço Eletrónico: helpdesk.b-on@hgsa.min-saude.pt\neDelivery Gateway (URL): https://community.vortal.biz/public/\nFunção da Organização: Adquirente\nNorma jurídica da Entidade Adjudicante: Organismo de direito público\nÁrea de atividade da Autoridade Adjudicante: Saúde\n\n2 - JORNAL OFICIAL DA UNIÃO EUROPEIA\nO procedimento a que este anúncio diz respeito também é publicitado no Jornal Oficial da União Europeia? Sim\n\n3 - AVISO\nModelo de Anúncio: Concurso público\nData de Envio do Anúncio: 13-10-2025\n\n5 - PROCESSO\nTipo de Procedimento: Concurso público\nPreço base do procedimento: Sim\nValor do preço base do procedimento: 469.860,00 EUR\nProcedimento com lotes? Sim\nNº Máx. de Lotes Autorizado: 3\nNúmero máximo de lotes que podem ser adjudicados a um concorrente: 3\n\n6 - OBJETO DO CONTRATO\nNúmero de referência interna: CPI/899/2025\nDesignação do contrato: Concurso Público Internacional nº 899/2025 - Aquisição de Lentes fáquicas e fáquicas tóricas para um período de 36 meses \nDescrição: Concurso Público Internacional nº 899/2025 - Aquisição de Lentes fáquicas e fáquicas tóricas para um período de 36 meses \nOpções: Não\nTipo de Contrato Principal: Aquisição de Bens Móveis\nTipo de Contrato: Aquisição de Bens Móveis\nClassificação CPV (Vocabulário Comum para os Contratos Públicos)\nObjeto principal\nVocabulário Principal: 33731110\nPreço base s/IVA: 469.860,00 EUR\nLotes: \nNº: LOT-0001\nDescrição do Lote: Lote 1\nPreço base s/IVA: 301.020,00 EUR\nClassificação CPV (Vocabulário Comum para os Contratos Públicos)\nObjeto principal\nVocabulário Principal: 33731110\nNº: LOT-0002\nDescrição do Lote: Lote 2\nPreço base s/IVA: 124.320,00 EUR\nClassificação CPV (Vocabulário Comum para os Contratos Públicos)\nObjeto principal\nVocabulário Principal: 33731110\nNº: LOT-0003\nDescrição do Lote: Lote 3\nPreço base s/IVA: 44.520,00 EUR\nClassificação CPV (Vocabulário Comum para os Contratos Públicos)\nObjeto principal\nVocabulário Principal: 33731110\n\n7 - INDICAÇÕES ADICIONAIS\nO contrato envolve aquisição conjunta (satisfação de várias entidades)? Não\nO contrato é adjudicado por uma central de compras? Não\n\n8 - TÉCNICAS\nO concurso destina-se à celebração de um acordo-quadro? Inexistência de acordo-quadro\nÉ utilizado um leilão eletrónico? Não\nÉ adotada uma fase de negociação? Não\nSistema de Aquisição Dinâmico: Inexistência de sistema de aquisição dinâmico\n\n9 - LOCAL DA EXECUÇÃO DO CONTRATO\nLOCAL DA EXECUÇÃO DO CONTRATO (PROCEDIMENTO)\nPaís: Portugal\nNUT III: PT11A\nLocalidade: Área Metropolitana do Porto\nDistrito: Porto\nConcelho: Porto\nFreguesia: União das Freguesias de Cedofeita, Santo Ildefonso, Sé, Miragaia, São Nicolau e Vitória\nLOCAL DA EXECUÇÃO DO CONTRATO (LOTE)\nIdentificador do Lote: LOT-0001; LOT-0002; LOT-0003\nPaís: Portugal\nNUT III: PT11A\nLocalidade: Área Metropolitana do Porto\nDistrito: Porto\nConcelho: Porto\nFreguesia: União das Freguesias de Cedofeita, Santo Ildefonso, Sé, Miragaia, São Nicolau e Vitória\n\n10 - PRAZO DE EXECUÇÃO DO CONTRATO\nIdentificador do Lote: LOT-0001; LOT-0002; LOT-0003\nPrazo de execução do contrato: 36 MESES\nPrevisão de renovações: Não\n\n11 - FUNDOS EU\nIdentificador do Lote: LOT-0001; LOT-0002; LOT-0003\nTêm fundos EU? Não\n\n12 - DOCUMENTOS DE HABILITAÇÃO\nHabilitação para o exercício da atividade profissional: Não\n\n13 - CONDIÇÕES DE APRESENTAÇÃO\nPlataforma eletrónica utilizada pela entidade adjudicante: VORTAL\nURL para Apresentação: https://community.vortal.biz/public/\nAdmissibilidade da apresentação de propostas variantes: Não autorizado\nPrazo para apresentação das propostas: 13-11-2025 23:59\nPrazo durante o qual os concorrentes são obrigados a manter as respetivas propostas: 120 dias a contar do termo do prazo para a apresentação das propostas\nApresentação de Catálogo Eletrónico: Necessário\nIndicação de Subcontratação na Proposta: Inexistência de indicação de subcontratação\n\n14 - PRESTAÇÃO DE CAUÇÃO\nPrestação de caução: Não\n\n15 - FORNECIMENTO DAS PEÇAS DO CONCURSO, APRESENTAÇÃO DE PEDIDOS DE PARTICIPAÇÃO E APRESENTAÇÃO DAS PROPOSTAS\nLink para acesso às peças do concurso (URL): https://community.vortal.biz/Public/public-tender-documents/TUJwbk0wdFpUMmcxQzVmWkVPVFFkVTB5TmVKeHY4cU45am0vSFcwSXJQYllNdEIzb2tvejBOYkh5VDMrYnRKaTZyOHQ4UFVQUW9MQ0dXTGtGeERUZ1E9PTRKU0NF\n\n20 - OUTROS REQUISITOS\nIdentificador do Lote: LOT-0001; LOT-0002; LOT-0003\nInformação sobre contratos reservados. Aplica-se a contratos reservados (54º-A)? Não\n\n21 - CRITÉRIO DE ADJUDICAÇÃO\nO Critério de adjudicação é diferenciado por lote? Sim\nIdentificador do lote: LOT-0001\nMultifator: Sim\nFator: \nNome: Preço\nPonderação: 60%\nSubfatores: Não\nFator: \nNome: Qualidade\nPonderação: 40%\nSubfatores: Não\nO Critério de adjudicação é diferenciado por lote? Sim\nIdentificador do lote: LOT-0002\nMultifator: Sim\nFator: \nNome: Preço\nPonderação: 60%\nSubfatores: Não\nFator: \nNome: Qualidade\nPonderação: 40%\nSubfatores: Não\nO Critério de adjudicação é diferenciado por lote? Sim\nIdentificador do lote: LOT-0003\nMultifator: Sim\nFator: \nNome: Preço\nPonderação: 60%\nSubfatores: Não\nFator: \nNome: Qualidade\nPonderação: 40%\nSubfatores: Não\n\n24 - CONDIÇÕES DO CONTRATO\nIdentificador do Lote: LOT-0001; LOT-0002; LOT-0003\nFaturação Eletrónica: Permitido\nObrigação de Subcontratação:\nCódigo da Obrigação de Subcontratação: Não é aplicável nenhuma obrigação de subcontratação.\n\n25 - COMPRA PÚBLICA ESTRATÉGICA\nCompra Pública Estratégica: Inexistência de contratação pública estratégica\n\n26 - INFORMAÇÕES ADICIONAIS\nIdentificador do Lote: LOT-0001; LOT-0002; LOT-0003\nContrato adequado para PME: Sim\nCobertura ACP (Acordo dos Contratos Públicos da Organização Mundial do Comércio): Não\n\n27 - IDENTIFICAÇÃO E CONTACTOS DO ÓRGÃO DE RECURSOS ADMINISTRATIVOS\nDesignação: Conselho de Administração\nEndereço: Largo Professor Abel Salazar\nCódigo postal: 4099-001\nLocalidade: Porto\nTelefone: +351 222077500\nFax: +351 223320318\nEndereço eletrónico: susanateixeira.aprov@chporto.min-saude.pt\n\n28 - IDENTIFICAÇÃO DO(S) AUTOR(ES) DE ANÚNCIO\nNome: Susana Teixeira\nCargo: Técnica Superior\n419649616",
    "nipc": "517392259",
    "distrito": "Porto",
    "concelho": "Porto",
    "freguesia": "Todas",
    "site": "www.hgsa.pt",
    "email": "helpdesk.b-on@hgsa.min-saude.pt",
    "designacao_contrato": "Concurso Público Internacional nº 899/2025 - Aquisição de Lentes fáquicas e fáquicas tóricas para um período de 36 meses",
    "descricao": "Concurso Público Internacional nº 899/2025 - Aquisição de Lentes fáquicas e fáquicas tóricas para um período de 36 meses",
    "preco_base": "469.860,00 EUR",
    "prazo_execucao": "36 MESES",
    "prazo_apresentacao_propostas": "13-11-2025 23:59",
    "fundos_eu": "Não",
    "plataforma_eletronica": "VORTAL",
    "url_procedimento": "https://community.vortal.biz/public/",
    "autor_nome": "Susana Teixeira",
    "autor_cargo": "Técnica Superior"
  },
  {
    "numero_procedimento": "N/A",
    "entidade": "Unidade Local de Saúde de Santo António, E. P. E.",
    "link": "https://diariodarepublica.pt/dr/detalhe/contrato-publico/27260-940390079",
    "detalhes_completos": "1 - IDENTIFICAÇÃO E CONTACTOS DA ENTIDADE ADJUDICANTE\nDesignação da entidade adjudicante: Unidade Local de Saúde de Santo António, E. P. E.\nNIPC: 517392259\nEndereço: Largo Prof. Abel Salazar\nCódigo postal: 4099-001\nLocalidade: Área Metropolitana do Porto\nPaís: Portugal\nNUT III: PT11A\nDistrito: Porto\nConcelho: Porto\nFreguesia: Todas\nTelefone: 222077500\nFax: 223320318\nEndereço da Entidade (URL): www.hgsa.pt\nEndereço Eletrónico: helpdesk.b-on@hgsa.min-saude.pt\neDelivery Gateway (URL): https://community.vortal.biz/public/\nFunção da Organização: Adquirente\nNorma jurídica da Entidade Adjudicante: Organismo de direito público\nÁrea de atividade da Autoridade Adjudicante: Saúde\n\n2 - JORNAL OFICIAL DA UNIÃO EUROPEIA\nO procedimento a que este anúncio diz respeito também é publicitado no Jornal Oficial da União Europeia? Sim\n\n3 - AVISO\nModelo de Anúncio: Concurso público\nData de Envio do Anúncio: 13-10-2025\n\n5 - PROCESSO\nTipo de Procedimento: Concurso público\nPreço base do procedimento: Sim\nValor do preço base do procedimento: 433.500,00 EUR\nProcedimento com lotes? Não\n\n6 - OBJETO DO CONTRATO\nNúmero de referência interna: CPI/1248/2025\nDesignação do contrato: Concurso Público Internacional nº 1248/2025 - Aquisição de Lâminas prontas para leitura de Imunohistoquímica, com colocação de equipamento em regime de comodato para o Serviço de Anatomia Patológica p\nDescrição: Concurso Público Internacional nº 1248/2025 - Aquisição de Lâminas prontas para leitura de Imunohistoquímica, com colocação de equipamento em regime de comodato para o Serviço de Anatomia Patológica para um período de 36 meses\nOpções: Não\nTipo de Contrato Principal: Aquisição de Bens Móveis\nTipo de Contrato: Aquisição de Bens Móveis\nClassificação CPV (Vocabulário Comum para os Contratos Públicos)\nObjeto principal\nVocabulário Principal: 33696000\nPreço base s/IVA: 433.500,00 EUR\n\n7 - INDICAÇÕES ADICIONAIS\nO contrato envolve aquisição conjunta (satisfação de várias entidades)? Não\nO contrato é adjudicado por uma central de compras? Não\n\n8 - TÉCNICAS\nO concurso destina-se à celebração de um acordo-quadro? Inexistência de acordo-quadro\nÉ utilizado um leilão eletrónico? Não\nÉ adotada uma fase de negociação? Não\nSistema de Aquisição Dinâmico: Inexistência de sistema de aquisição dinâmico\n\n9 - LOCAL DA EXECUÇÃO DO CONTRATO\nLOCAL DA EXECUÇÃO DO CONTRATO (PROCEDIMENTO)\nPaís: Portugal\nNUT III: PT11A\nLocalidade: Área Metropolitana do Porto\nDistrito: Porto\nConcelho: Porto\nFreguesia: União das Freguesias de Cedofeita, Santo Ildefonso, Sé, Miragaia, São Nicolau e Vitória\n\n10 - PRAZO DE EXECUÇÃO DO CONTRATO\nPrazo de execução do contrato: 36 MESES\nPrevisão de renovações: Não\n\n11 - FUNDOS EU\nTêm fundos EU? Não\n\n12 - DOCUMENTOS DE HABILITAÇÃO\nHabilitação para o exercício da atividade profissional: Não\n\n13 - CONDIÇÕES DE APRESENTAÇÃO\nPlataforma eletrónica utilizada pela entidade adjudicante: VORTAL\nURL para Apresentação: https://community.vortal.biz/public/\nAdmissibilidade da apresentação de propostas variantes: Não autorizado\nPrazo para apresentação das propostas: 13-11-2025 23:59\nPrazo durante o qual os concorrentes são obrigados a manter as respetivas propostas: 120 dias a contar do termo do prazo para a apresentação das propostas\nApresentação de Catálogo Eletrónico: Necessário\nIndicação de Subcontratação na Proposta: Inexistência de indicação de subcontratação\n\n14 - PRESTAÇÃO DE CAUÇÃO\nPrestação de caução: Não\n\n15 - FORNECIMENTO DAS PEÇAS DO CONCURSO, APRESENTAÇÃO DE PEDIDOS DE PARTICIPAÇÃO E APRESENTAÇÃO DAS PROPOSTAS\nLink para acesso às peças do concurso (URL): https://community.vortal.biz/Public/public-tender-documents/cnZWUDJBMWU2ZFVWb1BWTUpNdjdkcHdxd0VIREFqWXFxT2t3V3A3U2ZhdUhFeE53NEdzZGYwNWhUQ1dTWUpkZnZoVjlMM3JQODJYMHZtUXd2SUxKSGc9PVJtQVNh\n\n20 - OUTROS REQUISITOS\nInformação sobre contratos reservados. Aplica-se a contratos reservados (54º-A)? Não\n\n21 - CRITÉRIO DE ADJUDICAÇÃO\nMultifator: Sim\nFator: \nNome: Preço\nPonderação: 50%\nSubfatores: Não\nFator: \nNome: Qualidade\nPonderação: 50%\nSubfatores: Não\n\n24 - CONDIÇÕES DO CONTRATO\nFaturação Eletrónica: Permitido\nObrigação de Subcontratação:\nCódigo da Obrigação de Subcontratação: Não é aplicável nenhuma obrigação de subcontratação.\n\n25 - COMPRA PÚBLICA ESTRATÉGICA\nCompra Pública Estratégica: Inexistência de contratação pública estratégica\n\n26 - INFORMAÇÕES ADICIONAIS\nContrato adequado para PME: Sim\nCobertura ACP (Acordo dos Contratos Públicos da Organização Mundial do Comércio): Não\n\n27 - IDENTIFICAÇÃO E CONTACTOS DO ÓRGÃO DE RECURSOS ADMINISTRATIVOS\nDesignação: Conselho de Administração\nEndereço: Largo Professor Abel Salazar\nCódigo postal: 4099-001\nLocalidade: Porto\nTelefone: +351 222077500\nFax: +351 223320318\nEndereço eletrónico: susanateixeira.aprov@chporto.min-saude.pt\n\n28 - IDENTIFICAÇÃO DO(S) AUTOR(ES) DE ANÚNCIO\nNome: Susana Teixeira\nCargo: Técnica Superior\n419650409",
    "nipc": "517392259",
    "distrito": "Porto",
    "concelho": "Porto",
    "freguesia": "Todas",
    "site": "www.hgsa.pt",
    "email": "helpdesk.b-on@hgsa.min-saude.pt",
    "designacao_contrato": "Concurso Público Internacional nº 1248/2025 - Aquisição de Lâminas prontas para leitura de Imunohistoquímica, com colocação de equipamento em regime de comodato para o Serviço de Anatomia Patológica p",
    "descricao": "Concurso Público Internacional nº 1248/2025 - Aquisição de Lâminas prontas para leitura de Imunohistoquímica, com colocação de equipamento em regime de comodato para o Serviço de Anatomia Patológica para um período de 36 meses",
    "preco_base": "433.500,00 EUR",
    "prazo_execucao": "36 MESES",
    "prazo_apresentacao_propostas": "13-11-2025 23:59",
    "fundos_eu": "Não",
    "plataforma_eletronica": "VORTAL",
    "url_procedimento": "https://community.vortal.biz/public/",
    "autor_nome": "Susana Teixeira",
    "autor_cargo": "Técnica Superior"
  },
  {
    "numero_procedimento": "N/A",
    "entidade": "Unidade Local de Saúde de Coimbra, E. P. E.",
    "link": "https://diariodarepublica.pt/dr/detalhe/contrato-publico/27262-940415575",
    "detalhes_completos": "1 - IDENTIFICAÇÃO E CONTACTOS DA ENTIDADE ADJUDICANTE\nDesignação da entidade adjudicante: Unidade Local de Saúde de Coimbra, E. P. E.\nNIPC: 510103448\nEndereço: Praceta Prof. Mota Pinto\nCódigo postal: 3004-561\nLocalidade: Coimbra\nPaís: Portugal\nNUT III: PT16E\nDistrito: Coimbra\nConcelho: Coimbra\nFreguesia: Todas\nTelefone: 239400605\nFax: 239400605\nEndereço da Entidade (URL): https://www.chuc.min-saude.pt\nEndereço Eletrónico: ana.rosete@ulscoimbra.min-saude.pt\neDelivery Gateway (URL): https://community.vortal.biz/public/\nFunção da Organização: Adquirente\nNorma jurídica da Entidade Adjudicante: Organismo de direito público\nÁrea de atividade da Autoridade Adjudicante: Saúde\n\n2 - JORNAL OFICIAL DA UNIÃO EUROPEIA\nO procedimento a que este anúncio diz respeito também é publicitado no Jornal Oficial da União Europeia? Não\n\n3 - AVISO\nModelo de Anúncio: Concurso público\nData de Envio do Anúncio: 15-10-2025\n\n5 - PROCESSO\nTipo de Procedimento: Concurso público\nPreço base do procedimento: Sim\nValor do preço base do procedimento: 201.279,50 EUR\nProcedimento com lotes? Não\n\n6 - OBJETO DO CONTRATO\nNúmero de referência interna: 010900642025\nDesignação do contrato: Empreitada  de transferência de Estruturas Modulares Pré-fabricadas (contentores) localizados no polo HUC da Unidade Local de Saúde de Coimbra, E.P.E. \nDescrição: Empreitada  de transferência de Estruturas Modulares Pré-fabricadas (contentores) localizados no polo HUC da Unidade Local de Saúde de Coimbra, E.P.E. \nTipo de Contrato Principal: Empreitada de Obras Públicas\nTipo de Contrato: Empreitada de Obras Públicas\nClassificação CPV (Vocabulário Comum para os Contratos Públicos)\nObjeto principal\nVocabulário Principal: 45223800\nPreço base s/IVA: 201.279,50 EUR\n\n7 - INDICAÇÕES ADICIONAIS\nO contrato envolve aquisição conjunta (satisfação de várias entidades)? Não\nO contrato é adjudicado por uma central de compras? Não\n\n8 - TÉCNICAS\nO concurso destina-se à celebração de um acordo-quadro? Inexistência de acordo-quadro\nÉ utilizado um leilão eletrónico? Não\nÉ adotada uma fase de negociação? Não\nSistema de Aquisição Dinâmico: Inexistência de sistema de aquisição dinâmico\n\n9 - LOCAL DA EXECUÇÃO DO CONTRATO\nLOCAL DA EXECUÇÃO DO CONTRATO (PROCEDIMENTO)\nPaís: Portugal\nNUT III: PT16E\nLocalidade: Coimbra\nDistrito: Coimbra\nConcelho: Coimbra\nFreguesia: Freguesia de Santo António dos Olivais\n\n10 - PRAZO DE EXECUÇÃO DO CONTRATO\nPrazo de execução do contrato: 30 DIAS\nPrevisão de renovações: Não\n\n11 - FUNDOS EU\nTêm fundos EU? Não\n\n12 - DOCUMENTOS DE HABILITAÇÃO\nHabilitação para o exercício da atividade profissional: Não\n\n13 - CONDIÇÕES DE APRESENTAÇÃO\nPlataforma eletrónica utilizada pela entidade adjudicante: VORTAL\nURL para Apresentação: https://community.vortal.biz/public/\nAdmissibilidade da apresentação de propostas variantes: Não autorizado\nPrazo para apresentação das propostas: 30-10-2025 23:59\nPrazo durante o qual os concorrentes são obrigados a manter as respetivas propostas: 90 dias a contar do termo do prazo para a apresentação das propostas\nIndicação de Subcontratação na Proposta: Inexistência de indicação de subcontratação\n\n14 - PRESTAÇÃO DE CAUÇÃO\nPrestação de caução: Não\n\n15 - FORNECIMENTO DAS PEÇAS DO CONCURSO, APRESENTAÇÃO DE PEDIDOS DE PARTICIPAÇÃO E APRESENTAÇÃO DAS PROPOSTAS\nLink para acesso às peças do concurso (URL): https://community.vortal.biz/Public/public-tender-documents/TFkyYmNEUERZR0pTNVRzR0I2WCtCc0M1VUJJUkJrNitzb1ZpWGVrNUM2MVZ3NUhGRXVCa0kyS1E0a1N5MFR5MEd2eUI3cHVONlVtcll2ZytGM2ZFakE9PUx0KGZw\n\n20 - OUTROS REQUISITOS\nInformação sobre contratos reservados. Aplica-se a contratos reservados (54º-A)? Não\n\n21 - CRITÉRIO DE ADJUDICAÇÃO\nMultifator: Não\nMonofator:\nNome: Preço\n\n24 - CONDIÇÕES DO CONTRATO\nFaturação Eletrónica: Permitido\nObrigação de Subcontratação:\nCódigo da Obrigação de Subcontratação: Não é aplicável nenhuma obrigação de subcontratação.\n\n25 - COMPRA PÚBLICA ESTRATÉGICA\nCompra Pública Estratégica: Inexistência de contratação pública estratégica\n\n26 - INFORMAÇÕES ADICIONAIS\nContrato adequado para PME: Sim\nCobertura ACP (Acordo dos Contratos Públicos da Organização Mundial do Comércio): Não\n\n27 - IDENTIFICAÇÃO E CONTACTOS DO ÓRGÃO DE RECURSOS ADMINISTRATIVOS\nDesignação: Conselho de Administração da ULS Coimbra; E.P.E.\nEndereço: Praceta Prof Mota Pinto\nCódigo postal: 3004-561\nLocalidade: Coimbra\nTelefone: +351 239400400\nFax: +351 239400400\nEndereço eletrónico: casec@ulscoimbra.min-saude.pt\n\n28 - IDENTIFICAÇÃO DO(S) AUTOR(ES) DE ANÚNCIO\nNome: Teresa Roseiro\nCargo: Assistente Tecnico\n419659109",
    "nipc": "510103448",
    "distrito": "Coimbra",
    "concelho": "Coimbra",
    "freguesia": "Todas",
    "site": "https://www.chuc.min-saude.pt",
    "email": "ana.rosete@ulscoimbra.min-saude.pt",
    "designacao_contrato": "Empreitada de transferência de Estruturas Modulares Pré-fabricadas (contentores) localizados no polo HUC da Unidade Local de Saúde de Coimbra, E.P.E.",
    "descricao": "Empreitada de transferência de Estruturas Modulares Pré-fabricadas (contentores) localizados no polo HUC da Unidade Local de Saúde de Coimbra, E.P.E.",
    "preco_base": "201.279,50 EUR",
    "prazo_execucao": "30 DIAS",
    "prazo_apresentacao_propostas": "30-10-2025 23:59",
    "fundos_eu": "Não",
    "plataforma_eletronica": "VORTAL",
    "url_procedimento": "https://community.vortal.biz/public/",
    "autor_nome": "Teresa Roseiro",
    "autor_cargo": "Assistente Tecnico"
  },
  {
    "numero_procedimento": "N/A",
    "entidade": "Município de São João da Pesqueira",
    "link": "https://diariodarepublica.pt/dr/detalhe/contrato-publico/27263-940415576",
    "detalhes_completos": "Alteração do Anúncio de procedimento n.º 25640/2025, de 2025-09-30, com o ID 419590072\n\n1 - IDENTIFICAÇÃO E CONTACTOS DA ENTIDADE ADJUDICANTE\nDesignação da entidade adjudicante: Município de São João da Pesqueira\nNIPC: 506892646\nServiço/Órgão/Pessoa de contacto: DPOAU\nEndereço: Avenida Marquês de Soveral, n.º 67\nCódigo postal: 5130-321\nLocalidade: S. João da Pesqueira\nPaís: Portugal\nNUT III: PT11D\nDistrito: Viseu\nConcelho: São João da Pesqueira\nFreguesia: União das Freguesias de São João da Pesqueira e Várzea de Trevões\nTelefone: 254489999\nFax: 254489999\nEndereço da Entidade (URL): https://www.acingov.pt/acingovprod/2/\nEndereço Eletrónico: cmsjp@sjpesqueira.pt\neDelivery Gateway (URL): https://www.acingov.pt\nFunção da Organização: Adquirente\nNorma jurídica da Entidade Adjudicante: Organismo de direito público\nÁrea de atividade da Autoridade Adjudicante: Serviços públicos das administrações públicas\n\n2 - JORNAL OFICIAL DA UNIÃO EUROPEIA\nO procedimento a que este anúncio diz respeito também é publicitado no Jornal Oficial da União Europeia? Não\n\n3 - AVISO\nModelo de Anúncio: Concurso público\nData de Envio do Anúncio: 15-10-2025\n\n5 - PROCESSO\nTipo de Procedimento: Concurso público\nPreço base do procedimento: Sim\nValor do preço base do procedimento: 943.603,67 EUR\nProcedimento com lotes? Não\n\n6 - OBJETO DO CONTRATO\nNúmero de referência interna: CP/15/2025\nDesignação do contrato: Remoção de pavimentos, rede de abastecimento de água, rede de drenagem de esgotos domésticos, rede de drenagem de águas pluviais, demolições, execução de pavimentos em cubo de granito, imobiliário urbano e plantações, infraestruturas elétricas, rede de telecomunicações, outros trabalhos e movimento de terras\nDescrição: Regeneração Urbana - Rua Dr. Paradela de Oliveira, Rua General Humberto Delgado, Rua da Cruz e Praça de Santa Maria, na Vila de São João da Pesqueira\n\nTipo de Contrato Principal: Empreitada de Obras Públicas\nTipo de Contrato: Empreitada de Obras Públicas\nClassificação CPV (Vocabulário Comum para os Contratos Públicos)\nObjeto principal\nVocabulário Principal: 45233252\nPreço base s/IVA: 943.603,67 EUR\n\n7 - INDICAÇÕES ADICIONAIS\nO contrato envolve aquisição conjunta (satisfação de várias entidades)? Não\nO contrato é adjudicado por uma central de compras? Não\n\n8 - TÉCNICAS\nO concurso destina-se à celebração de um acordo-quadro? Inexistência de acordo-quadro\nÉ utilizado um leilão eletrónico? Não\nÉ adotada uma fase de negociação? Não\nSistema de Aquisição Dinâmico: Inexistência de sistema de aquisição dinâmico\n\n9 - LOCAL DA EXECUÇÃO DO CONTRATO\nLOCAL DA EXECUÇÃO DO CONTRATO (PROCEDIMENTO)\nPaís: Portugal\nNUT III: PT11D\nLocalidade: União das Freguesias de São João da Pesqueira e Várzea de Trevões\nDistrito: Viseu\nConcelho: São João da Pesqueira\nFreguesia: União das Freguesias de São João da Pesqueira e Várzea de Trevões\n\n10 - PRAZO DE EXECUÇÃO DO CONTRATO\nPrazo de execução do contrato: 360 DIAS\nPrevisão de renovações: Não\n\n11 - FUNDOS EU\nTêm fundos EU? Sim\n\n12 - DOCUMENTOS DE HABILITAÇÃO\nHabilitação para o exercício da atividade profissional: Sim\nTipo: Alvará\nDescrição: IMPIC, I.P, na 2ª categoria (Vias de Comunicação, Obras de Urbanização e outras Infraestruturas), da qual deve ser da classe corresponde ao valor dos trabalhos a que respeita, a proposta; e a 6.ª subcategoria da 2.ª categoria (Saneamento básico), da qual deve ser da classe que cubra o valor global dos trabalhos; e a 8. ª subcategoria da 2.ª categoria (Calcetamentos), da qual deve ser da classe que cubra o valor global dos trabalhos; e a 9.ª subcategoria da 2.ª categoria (Ajardinamentos), da qual deve ser da classe que cubra o valor global dos trabalhos; e a 10.ª subcategoria da 2.ª categoria (Infraestruturas de desporto e de lazer), da qual deve ser da classe que cubra o valor global dos trabalhos; e a 4.ª categoria (Instalações Elétricas e Mecânica), da qual deve ser da classe que cubra o valor global dos trabalhos; e a 1.ª subcategoria da 4.ª categoria (Instalações elétricas de utilização de baixa tensão), da qual deve ser da classe que cubra o valor global dos trabalhos; e a 7.ª subcategoria da 4.ª categoria (Infraestruturas de telecomunicações), da qual deve ser da classe que cubra o valor global dos trabalhos, e a 5.ª categoria (Outros Trabalhos), da qual deve ser da classe que cubra o valor global dos trabalhos; e a 2.ª subcategoria da 5.ª categoria (Movimento de terras), da qual deve ser da classe que cubra o valor global dos trabalhos \n\n13 - CONDIÇÕES DE APRESENTAÇÃO\nPlataforma eletrónica utilizada pela entidade adjudicante: ACIN\nURL para Apresentação: https://www.acingov.pt\nAdmissibilidade da apresentação de propostas variantes: Não autorizado\nPrazo para apresentação das propostas: 03-12-2025 23:59\nPrazo durante o qual os concorrentes são obrigados a manter as respetivas propostas: 120 dias a contar do termo do prazo para a apresentação das propostas\nIndicação de Subcontratação na Proposta: Inexistência de indicação de subcontratação\n\n14 - PRESTAÇÃO DE CAUÇÃO\nPrestação de caução: Sim\nPercentagem: 5%\nDescrição da Garantia Exigida: O valor da caução é de 5.00% do preço contratual.\n\n15 - FORNECIMENTO DAS PEÇAS DO CONCURSO, APRESENTAÇÃO DE PEDIDOS DE PARTICIPAÇÃO E APRESENTAÇÃO DAS PROPOSTAS\nLink para acesso às peças do concurso (URL): https://www.acingov.pt/acingovprod/2/zonaPublica/zona_publica_c/donwloadProcedurePiece/OTgyMjQ2\n\n20 - OUTROS REQUISITOS\nInformação sobre contratos reservados. Aplica-se a contratos reservados (54º-A)? Não\n\n21 - CRITÉRIO DE ADJUDICAÇÃO\nMultifator: Não\nMonofator:\nNome: Preço\n\n24 - CONDIÇÕES DO CONTRATO\nFaturação Eletrónica: Permitido\nObrigação de Subcontratação:\nCódigo da Obrigação de Subcontratação: Não é aplicável nenhuma obrigação de subcontratação.\n\n25 - COMPRA PÚBLICA ESTRATÉGICA\nCompra Pública Estratégica: Inexistência de contratação pública estratégica\n\n26 - INFORMAÇÕES ADICIONAIS\nContrato adequado para PME: Sim\nCobertura ACP (Acordo dos Contratos Públicos da Organização Mundial do Comércio): Não\n\n27 - IDENTIFICAÇÃO E CONTACTOS DO ÓRGÃO DE RECURSOS ADMINISTRATIVOS\nDesignação: Câmara Municipal\nEndereço: Avenida Marquês de Soveral, n.º 67\nCódigo postal: 5130-321\nLocalidade: S. João da Pesqueira\nTelefone: 254489999\nFax: 254489999\nEndereço eletrónico: cmsjp@sjpesqueira.pt\nPrazo de interposição do recurso: 5 dias\n\n28 - IDENTIFICAÇÃO DO(S) AUTOR(ES) DE ANÚNCIO\nNome: Manuel António Natário Cordeiro\nCargo: Presidente\n\n29 - ALTERAÇÃO\nMotivo da Alteração: Correção pelo adquirente\nIdentificador da Versão do Anúncio a Alterar: d3f5d67c-f42c-4a1f-a21b-d3160e569fd1-01\nIdentificador das Secções Alteradas do Anúncio Anterior: Condições de Apresentação\nDescrição das Alterações: Modificação do prazo para a apresentação de propostas\nAlteração dos Documentos do Concurso: Não\n419662227",
    "nipc": "506892646",
    "distrito": "Viseu",
    "concelho": "São João da Pesqueira",
    "freguesia": "União das Freguesias de São João da Pesqueira e Várzea de Trevões",
    "site": "https://www.acingov.pt/acingovprod/2/",
    "email": "cmsjp@sjpesqueira.pt",
    "designacao_contrato": "Remoção de pavimentos, rede de abastecimento de água, rede de drenagem de esgotos domésticos, rede de drenagem de águas pluviais, demolições, execução de pavimentos em cubo de granito, imobiliário urbano e plantações, infraestruturas elétricas, rede de telecomunicações, outros trabalhos e movimento de terras",
    "descricao": "Regeneração Urbana - Rua Dr. Paradela de Oliveira, Rua General Humberto Delgado, Rua da Cruz e Praça de Santa Maria, na Vila de São João da Pesqueira",
    "preco_base": "943.603,67 EUR",
    "prazo_execucao": "360 DIAS",
    "prazo_apresentacao_propostas": "03-12-2025 23:59",
    "fundos_eu": "Sim",
    "plataforma_eletronica": "ACIN",
    "url_procedimento": "https://www.acingov.pt",
    "autor_nome": "Manuel António Natário Cordeiro",
    "autor_cargo": "Presidente"
  },
  {
    "numero_procedimento": "N/A",
    "entidade": "Unidade Local de Saúde de Lisboa Ocidental, E. P. E.",
    "link": "https://diariodarepublica.pt/dr/detalhe/contrato-publico/27264-940415577",
    "detalhes_completos": "1 - IDENTIFICAÇÃO E CONTACTOS DA ENTIDADE ADJUDICANTE\nDesignação da entidade adjudicante: Unidade Local de Saúde de Lisboa Ocidental, E. P. E.\nNIPC: 507618319\nEndereço: Santa Maria de Belém  Estrada do Forte do Alto do Duque\nCódigo postal: 1449-005\nLocalidade: Lisboa\nPaís: Portugal\nNUT III: PT170\nDistrito: Lisboa\nConcelho: Lisboa\nFreguesia: Todas\nTelefone: 210431000\nFax: 210431642\nEndereço da Entidade (URL): www.chlo.min-saude.pt/\nEndereço Eletrónico: comprasgeral@ulslo.min-saude.pt\neDelivery Gateway (URL): https://community.vortal.biz/public/\nFunção da Organização: Adquirente\nNorma jurídica da Entidade Adjudicante: Organismo de direito público\nÁrea de atividade da Autoridade Adjudicante: Saúde\n\n2 - JORNAL OFICIAL DA UNIÃO EUROPEIA\nO procedimento a que este anúncio diz respeito também é publicitado no Jornal Oficial da União Europeia? Não\n\n3 - AVISO\nModelo de Anúncio: Concurso público\nData de Envio do Anúncio: 15-10-2025\n\n5 - PROCESSO\nTipo de Procedimento: Concurso público\nPreço base do procedimento: Sim\nValor do preço base do procedimento: 199.500,00 EUR\nProcedimento com lotes? Não\n\n6 - OBJETO DO CONTRATO\nNúmero de referência interna: LG-142007425 Perneiras  p/ Compressão Pneumática\nDesignação do contrato:  142007425 Aquisição de Perneiras  p/ Compressão Pneumática\nDescrição:  142007425 Aquisição de Perneiras  p/ Compressão Pneumática\nTipo de Contrato Principal: Aquisição de Bens Móveis\nTipo de Contrato: Aquisição de Bens Móveis\nClassificação CPV (Vocabulário Comum para os Contratos Públicos)\nObjeto principal\nVocabulário Principal: 33140000\nPreço base s/IVA: 199.500,00 EUR\n\n7 - INDICAÇÕES ADICIONAIS\nO contrato envolve aquisição conjunta (satisfação de várias entidades)? Não\nO contrato é adjudicado por uma central de compras? Não\n\n8 - TÉCNICAS\nO concurso destina-se à celebração de um acordo-quadro? Inexistência de acordo-quadro\nÉ utilizado um leilão eletrónico? Não\nÉ adotada uma fase de negociação? Não\nSistema de Aquisição Dinâmico: Inexistência de sistema de aquisição dinâmico\n\n9 - LOCAL DA EXECUÇÃO DO CONTRATO\nLOCAL DA EXECUÇÃO DO CONTRATO (PROCEDIMENTO)\nPaís: Portugal\nNUT III: PT170\nLocalidade: Lisboa\nDistrito: Lisboa\nConcelho: Lisboa\nFreguesia: Todas\n\n10 - PRAZO DE EXECUÇÃO DO CONTRATO\nPrazo de execução do contrato: 18 MESES\nPrevisão de renovações: Não\n\n11 - FUNDOS EU\nTêm fundos EU? Não\n\n12 - DOCUMENTOS DE HABILITAÇÃO\nHabilitação para o exercício da atividade profissional: Não\n\n13 - CONDIÇÕES DE APRESENTAÇÃO\nPlataforma eletrónica utilizada pela entidade adjudicante: VORTAL\nURL para Apresentação: https://community.vortal.biz/public/\nAdmissibilidade da apresentação de propostas variantes: Não autorizado\nPrazo para apresentação das propostas: 30-10-2025 23:59\nPrazo durante o qual os concorrentes são obrigados a manter as respetivas propostas: 66 dias a contar do termo do prazo para a apresentação das propostas\nIndicação de Subcontratação na Proposta: Inexistência de indicação de subcontratação\n\n14 - PRESTAÇÃO DE CAUÇÃO\nPrestação de caução: Não\n\n15 - FORNECIMENTO DAS PEÇAS DO CONCURSO, APRESENTAÇÃO DE PEDIDOS DE PARTICIPAÇÃO E APRESENTAÇÃO DAS PROPOSTAS\nLink para acesso às peças do concurso (URL): https://community.vortal.biz/Public/public-tender-documents/Q09EZlRFRTNNdjRBWi9CRlZyT1pYSklnWUdoUXVTOFFxeHN2TEFwNmxyQThBbzdWN2ozQlZYalJ0VmdGemtxWUxsSVdhaG9rS29NQUNxWjRYTmpaTnc9PVhhMlo5\n\n20 - OUTROS REQUISITOS\nInformação sobre contratos reservados. Aplica-se a contratos reservados (54º-A)? Não\n\n21 - CRITÉRIO DE ADJUDICAÇÃO\nMultifator: Não\nMonofator:\nNome: Preço\n\n24 - CONDIÇÕES DO CONTRATO\nFaturação Eletrónica: Permitido\nObrigação de Subcontratação:\nCódigo da Obrigação de Subcontratação: Não é aplicável nenhuma obrigação de subcontratação.\n\n25 - COMPRA PÚBLICA ESTRATÉGICA\nCompra Pública Estratégica: Inexistência de contratação pública estratégica\n\n26 - INFORMAÇÕES ADICIONAIS\nContrato adequado para PME: Sim\nCobertura ACP (Acordo dos Contratos Públicos da Organização Mundial do Comércio): Não\n\n27 - IDENTIFICAÇÃO E CONTACTOS DO ÓRGÃO DE RECURSOS ADMINISTRATIVOS\nDesignação: Serviço Gestão de Compras\nEndereço: Estrada do Forte do Alto do Duque\nCódigo postal: 1449-005\nLocalidade: Lisboa\nTelefone: +351 210431000\nFax: +351 210431642\nEndereço eletrónico: comprascclinico@ulslo.min-saude.pt\n\n28 - IDENTIFICAÇÃO DO(S) AUTOR(ES) DE ANÚNCIO\nNome: Andrea Malta\nCargo: Diretora Serviço Gestão de Compras\n419657902",
    "nipc": "507618319",
    "distrito": "Lisboa",
    "concelho": "Lisboa",
    "freguesia": "Todas",
    "site": "www.chlo.min-saude.pt/",
    "email": "comprasgeral@ulslo.min-saude.pt",
    "designacao_contrato": "142007425 Aquisição de Perneiras p/ Compressão Pneumática",
    "descricao": "142007425 Aquisição de Perneiras p/ Compressão Pneumática",
    "preco_base": "199.500,00 EUR",
    "prazo_execucao": "18 MESES",
    "prazo_apresentacao_propostas": "30-10-2025 23:59",
    "fundos_eu": "Não",
    "plataforma_eletronica": "VORTAL",
    "url_procedimento": "https://community.vortal.biz/public/",
    "autor_nome": "Andrea Malta",
    "autor_cargo": "Diretora Serviço Gestão de Compras"
  },
  {
    "numero_procedimento": "N/A",
    "entidade": "Centro de Formação Profissional da Indústria de Fundição",
    "link": "https://diariodarepublica.pt/dr/detalhe/contrato-publico/27268-940415579",
    "detalhes_completos": "1 - IDENTIFICAÇÃO E CONTACTOS DA ENTIDADE ADJUDICANTE\nDesignação da entidade adjudicante: Centro de Formação Profissional da Indústria de Fundição\nNIPC: 501957910\nServiço/Órgão/Pessoa de contacto: Júri\nEndereço: Rua Delfim Ferreira, 800/840\nCódigo postal: 4100-199\nLocalidade: PORTO\nPaís: Portugal\nNUT III: PT11A\nDistrito: Porto\nConcelho: Porto\nFreguesia: Freguesia de Ramalde\nTelefone: 226175760\nFax: 226103160\nEndereço da Entidade (URL): www.cinfu.pt\nEndereço Eletrónico: fernando.barbosa@cinfu.pt\neDelivery Gateway (URL): https://www.acingov.pt\nFunção da Organização: Adquirente\nSubfunção da Organização: Organização cujo orçamento é utilizado para pagar o contrato; Organização que executa o pagamento; Organização que fornece informações adicionais sobre o processo de adjudicação; Organização que fornece mais informações sobre os prazos dos procedimentos de recurso; Organização responsável pelo tratamento das propostas; Organização que recebe as propostas; Organização que fornece mais informações sobre os procedimentos de recurso; Organização que assina o contrato\nNorma jurídica da Entidade Adjudicante: Organismo de direito público, controlado por uma autoridade da administração central\nÁrea de atividade da Autoridade Adjudicante: Serviços públicos das administrações públicas\n\n2 - JORNAL OFICIAL DA UNIÃO EUROPEIA\nO procedimento a que este anúncio diz respeito também é publicitado no Jornal Oficial da União Europeia? Não\n\n3 - AVISO\nModelo de Anúncio: Concurso público\nData de Envio do Anúncio: 15-10-2025\n\n5 - PROCESSO\nTipo de Procedimento: Concurso público\nPreço base do procedimento: Sim\nValor do preço base do procedimento: 3.200,00 EUR\nProcedimento com lotes? Não\n\n6 - OBJETO DO CONTRATO\nNúmero de referência interna: PRR 26/2025\nDesignação do contrato: Fornecimento de uma Máquina de impressão 3D com corte e gravação laser\nDescrição: Fornecimento de uma Máquina de impressão 3D com corte e gravação laser \nTipo de Contrato Principal: Aquisição de Bens Móveis\nTipo de Contrato: Aquisição de Bens Móveis\nClassificação CPV (Vocabulário Comum para os Contratos Públicos)\nObjeto principal\nVocabulário Principal: 42991200\nPreço base s/IVA: 3.200,00 EUR\n\n7 - INDICAÇÕES ADICIONAIS\nO contrato envolve aquisição conjunta (satisfação de várias entidades)? Não\nO contrato é adjudicado por uma central de compras? Não\n\n8 - TÉCNICAS\nO concurso destina-se à celebração de um acordo-quadro? Inexistência de acordo-quadro\nÉ utilizado um leilão eletrónico? Não\nÉ adotada uma fase de negociação? Não\nSistema de Aquisição Dinâmico: Inexistência de sistema de aquisição dinâmico\n\n9 - LOCAL DA EXECUÇÃO DO CONTRATO\nLOCAL DA EXECUÇÃO DO CONTRATO (PROCEDIMENTO)\nPaís: Portugal\nNUT III: PT11A\nLocalidade: Freguesia de Ramalde\nDistrito: Porto\nConcelho: Porto\nFreguesia: Freguesia de Ramalde\n\n10 - PRAZO DE EXECUÇÃO DO CONTRATO\nPrazo de execução do contrato: 35 DIAS\nPrevisão de renovações: Não\n\n11 - FUNDOS EU\nTêm fundos EU? Sim\n\n12 - DOCUMENTOS DE HABILITAÇÃO\nHabilitação para o exercício da atividade profissional: Não\n\n13 - CONDIÇÕES DE APRESENTAÇÃO\nPlataforma eletrónica utilizada pela entidade adjudicante: ACIN\nURL para Apresentação: https://www.acingov.pt\nAdmissibilidade da apresentação de propostas variantes: Não autorizado\nPrazo para apresentação das propostas: 27-10-2025 23:59\nPrazo durante o qual os concorrentes são obrigados a manter as respetivas propostas: 66 dias a contar do termo do prazo para a apresentação das propostas\nIndicação de Subcontratação na Proposta: Inexistência de indicação de subcontratação\n\n14 - PRESTAÇÃO DE CAUÇÃO\nPrestação de caução: Não\n\n15 - FORNECIMENTO DAS PEÇAS DO CONCURSO, APRESENTAÇÃO DE PEDIDOS DE PARTICIPAÇÃO E APRESENTAÇÃO DAS PROPOSTAS\nLink para acesso às peças do concurso (URL): https://www.acingov.pt/acingovprod/2/zonaPublica/zona_publica_c/donwloadProcedurePiece/OTg1OTE5\n\n20 - OUTROS REQUISITOS\nInformação sobre contratos reservados. Aplica-se a contratos reservados (54º-A)? Não\n\n21 - CRITÉRIO DE ADJUDICAÇÃO\nMultifator: Sim\nFator: \nNome: Preço\nPonderação: 40%\nSubfatores: Não\nFator: \nNome: Qualidade\nPonderação: 45%\nSubfatores: Sim\nSubfatores: \nNome: Valor técnico da impressora\nPonderação : 75%; \nNome: Inclusão de unidade de purificação de ar externa e anexo rotativo para gravação de cilindros\nPonderação : 25%; \nFator: \nNome: Outros\nOutro Nome: Assistência técnica\nPonderação: 10%\nSubfatores: Sim\nSubfatores: \nNome: Tempo de resposta em caso de avaria\nPonderação : 60%; \nNome: Prestada por técnicos qualificados do fornecedor e assegurada pelo fornecedor durante e após a validade da garantia\nPonderação : 20%; \nNome: Custos previstos para assistência técnica e resolução de avarias, durante e após a validade da garantia\nPonderação : 20%; \nFator: \nNome: Outros\nOutro Nome: Sustentabilidade Ambiental\nPonderação: 5%\nSubfatores: Sim\nSubfatores: \nNome: Certificação ambiental\nPonderação : 50%; \nNome: Materiais recicláveis\nPonderação : 50%; \n\n24 - CONDIÇÕES DO CONTRATO\nFaturação Eletrónica: Necessário\nObrigação de Subcontratação:\nCódigo da Obrigação de Subcontratação: Não é aplicável nenhuma obrigação de subcontratação.\n\n25 - COMPRA PÚBLICA ESTRATÉGICA\nCompra Pública Estratégica: Inexistência de contratação pública estratégica\n\n26 - INFORMAÇÕES ADICIONAIS\nContrato adequado para PME: Sim\nCobertura ACP (Acordo dos Contratos Públicos da Organização Mundial do Comércio): Não\n\n27 - IDENTIFICAÇÃO E CONTACTOS DO ÓRGÃO DE RECURSOS ADMINISTRATIVOS\nDesignação: Conselho de Administração\nEndereço: Rua Delfim Ferreira, 800/840\nCódigo postal: 4100-199\nLocalidade: PORTO\nTelefone: 226175760\nFax: \nEndereço eletrónico: helena.oliveira@cinfu.pt\nPrazo de interposição do recurso: 5 dias\n\n28 - IDENTIFICAÇÃO DO(S) AUTOR(ES) DE ANÚNCIO\nNome: Paula Alexandra Martins dos Santos de Macedo Teixeira\nCargo: Presidente do Conselho de Administração\n419661409",
    "nipc": "501957910",
    "distrito": "Porto",
    "concelho": "Porto",
    "freguesia": "Freguesia de Ramalde",
    "site": "www.cinfu.pt",
    "email": "fernando.barbosa@cinfu.pt",
    "designacao_contrato": "Fornecimento de uma Máquina de impressão 3D com corte e gravação laser",
    "descricao": "Fornecimento de uma Máquina de impressão 3D com corte e gravação laser",
    "preco_base": "3.200,00 EUR",
    "prazo_execucao": "35 DIAS",
    "prazo_apresentacao_propostas": "27-10-2025 23:59",
    "fundos_eu": "Sim",
    "plataforma_eletronica": "ACIN",
    "url_procedimento": "https://www.acingov.pt",
    "autor_nome": "Paula Alexandra Martins dos Santos de Macedo Teixeira",
    "autor_cargo": "Presidente do Conselho de Administração"
  },
  {
    "numero_procedimento": "N/A",
    "entidade": "Centro de Formação Profissional da Indústria de Fundição",
    "link": "https://diariodarepublica.pt/dr/detalhe/contrato-publico/27270-940415580",
    "detalhes_completos": "1 - IDENTIFICAÇÃO E CONTACTOS DA ENTIDADE ADJUDICANTE\nDesignação da entidade adjudicante: Centro de Formação Profissional da Indústria de Fundição\nNIPC: 501957910\nServiço/Órgão/Pessoa de contacto: Júri\nEndereço: Rua Delfim Ferreira, 800/840\nCódigo postal: 4100-199\nLocalidade: PORTO\nPaís: Portugal\nNUT III: PT11A\nDistrito: Porto\nConcelho: Porto\nFreguesia: Freguesia de Ramalde\nTelefone: 226175760\nFax: 226103160\nEndereço da Entidade (URL): www.cinfu.pt\nEndereço Eletrónico: fernando.barbosa@cinfu.pt\neDelivery Gateway (URL): https://www.acingov.pt\nFunção da Organização: Adquirente\nSubfunção da Organização: Organização cujo orçamento é utilizado para pagar o contrato; Organização que executa o pagamento; Organização que fornece informações adicionais sobre o processo de adjudicação; Organização que fornece mais informações sobre os prazos dos procedimentos de recurso; Organização responsável pelo tratamento das propostas; Organização que recebe as propostas; Organização que fornece mais informações sobre os procedimentos de recurso; Organização que assina o contrato\nNorma jurídica da Entidade Adjudicante: Organismo de direito público, controlado por uma autoridade da administração central\nÁrea de atividade da Autoridade Adjudicante: Serviços públicos das administrações públicas\n\n2 - JORNAL OFICIAL DA UNIÃO EUROPEIA\nO procedimento a que este anúncio diz respeito também é publicitado no Jornal Oficial da União Europeia? Não\n\n3 - AVISO\nModelo de Anúncio: Concurso público\nData de Envio do Anúncio: 15-10-2025\n\n5 - PROCESSO\nTipo de Procedimento: Concurso público\nPreço base do procedimento: Sim\nValor do preço base do procedimento: 75.000,00 EUR\nProcedimento com lotes? Não\n\n6 - OBJETO DO CONTRATO\nNúmero de referência interna: PRR 28/2025\nDesignação do contrato: Fornecimento de um Microscópio Metalográfico\nDescrição: Fornecimento de um Microscópio Metalográfico\nTipo de Contrato Principal: Aquisição de Bens Móveis\nTipo de Contrato: Aquisição de Bens Móveis\nClassificação CPV (Vocabulário Comum para os Contratos Públicos)\nObjeto principal\nVocabulário Principal: 38513200\nPreço base s/IVA: 75.000,00 EUR\n\n7 - INDICAÇÕES ADICIONAIS\nO contrato envolve aquisição conjunta (satisfação de várias entidades)? Não\nO contrato é adjudicado por uma central de compras? Não\n\n8 - TÉCNICAS\nO concurso destina-se à celebração de um acordo-quadro? Inexistência de acordo-quadro\nÉ utilizado um leilão eletrónico? Não\nÉ adotada uma fase de negociação? Não\nSistema de Aquisição Dinâmico: Inexistência de sistema de aquisição dinâmico\n\n9 - LOCAL DA EXECUÇÃO DO CONTRATO\nLOCAL DA EXECUÇÃO DO CONTRATO (PROCEDIMENTO)\nPaís: Portugal\nNUT III: PT11A\nLocalidade: Freguesia de Ramalde\nDistrito: Porto\nConcelho: Porto\nFreguesia: Freguesia de Ramalde\n\n10 - PRAZO DE EXECUÇÃO DO CONTRATO\nPrazo de execução do contrato: 28 DIAS\nPrevisão de renovações: Não\n\n11 - FUNDOS EU\nTêm fundos EU? Sim\n\n12 - DOCUMENTOS DE HABILITAÇÃO\nHabilitação para o exercício da atividade profissional: Não\n\n13 - CONDIÇÕES DE APRESENTAÇÃO\nPlataforma eletrónica utilizada pela entidade adjudicante: ACIN\nURL para Apresentação: https://www.acingov.pt\nAdmissibilidade da apresentação de propostas variantes: Não autorizado\nPrazo para apresentação das propostas: 30-10-2025 23:59\nPrazo durante o qual os concorrentes são obrigados a manter as respetivas propostas: 66 dias a contar do termo do prazo para a apresentação das propostas\nIndicação de Subcontratação na Proposta: Inexistência de indicação de subcontratação\n\n14 - PRESTAÇÃO DE CAUÇÃO\nPrestação de caução: Não\n\n15 - FORNECIMENTO DAS PEÇAS DO CONCURSO, APRESENTAÇÃO DE PEDIDOS DE PARTICIPAÇÃO E APRESENTAÇÃO DAS PROPOSTAS\nLink para acesso às peças do concurso (URL): https://www.acingov.pt/acingovprod/2/zonaPublica/zona_publica_c/donwloadProcedurePiece/OTg1OTg0\n\n20 - OUTROS REQUISITOS\nInformação sobre contratos reservados. Aplica-se a contratos reservados (54º-A)? Não\n\n21 - CRITÉRIO DE ADJUDICAÇÃO\nMultifator: Sim\nFator: \nNome: Preço\nPonderação: 40%\nSubfatores: Não\nFator: \nNome: Qualidade\nPonderação: 45%\nSubfatores: Sim\nSubfatores: \nNome: Valor técnico\nPonderação : 70%; \nNome: Características ergonómicas\nPonderação : 10%; \nNome: Características ergonómicas\nPonderação : 20%; \nFator: \nNome: Outros\nOutro Nome: Assistência técnica\nPonderação: 10%\nSubfatores: Sim\nSubfatores: \nNome: Custos estimados de manutenção\nPonderação : 50%; \nNome: Prestada por técnicos do fabricante e assegurada pelo fornecedor durante e após a validade da garantia\nPonderação : 20%; \nNome: Tempo de resposta\nPonderação : 30%; \nFator: \nNome: Outros\nOutro Nome: Sustentabilidade Ambiental e Circularidade\nPonderação: 5%\nSubfatores: Sim\nSubfatores: \nNome: Certificação ambiental/certificação ecológica do equipamento\nPonderação : 80%; \nNome: Consumo energético\nPonderação : 20%; \n\n24 - CONDIÇÕES DO CONTRATO\nFaturação Eletrónica: Necessário\nObrigação de Subcontratação:\nCódigo da Obrigação de Subcontratação: Não é aplicável nenhuma obrigação de subcontratação.\n\n25 - COMPRA PÚBLICA ESTRATÉGICA\nCompra Pública Estratégica: Inexistência de contratação pública estratégica\n\n26 - INFORMAÇÕES ADICIONAIS\nContrato adequado para PME: Sim\nCobertura ACP (Acordo dos Contratos Públicos da Organização Mundial do Comércio): Não\n\n27 - IDENTIFICAÇÃO E CONTACTOS DO ÓRGÃO DE RECURSOS ADMINISTRATIVOS\nDesignação: Conselho de Administração\nEndereço: Rua Delfim Ferreira, 800/840\nCódigo postal: 4100-199\nLocalidade: PORTO\nTelefone: 226175760\nFax: \nEndereço eletrónico: helena.oliveira@cinfu.pt\nPrazo de interposição do recurso: 5 dias\n\n28 - IDENTIFICAÇÃO DO(S) AUTOR(ES) DE ANÚNCIO\nNome: Paula Alexandra Martins dos Santos de Macedo Teixeira\nCargo: Presidente do Conselho de Administração\n419661911",
    "nipc": "501957910",
    "distrito": "Porto",
    "concelho": "Porto",
    "freguesia": "Freguesia de Ramalde",
    "site": "www.cinfu.pt",
    "email": "fernando.barbosa@cinfu.pt",
    "designacao_contrato": "Fornecimento de um Microscópio Metalográfico",
    "descricao": "Fornecimento de um Microscópio Metalográfico",
    "preco_base": "75.000,00 EUR",
    "prazo_execucao": "28 DIAS",
    "prazo_apresentacao_propostas": "30-10-2025 23:59",
    "fundos_eu": "Sim",
    "plataforma_eletronica": "ACIN",
    "url_procedimento": "https://www.acingov.pt",
    "autor_nome": "Paula Alexandra Martins dos Santos de Macedo Teixeira",
    "autor_cargo": "Presidente do Conselho de Administração"
  },
  {
    "numero_procedimento": "N/A",
    "entidade": "Centro de Formação Profissional da Indústria de Fundição",
    "link": "https://diariodarepublica.pt/dr/detalhe/contrato-publico/27271-940415581",
    "detalhes_completos": "1 - IDENTIFICAÇÃO E CONTACTOS DA ENTIDADE ADJUDICANTE\nDesignação da entidade adjudicante: Centro de Formação Profissional da Indústria de Fundição\nNIPC: 501957910\nServiço/Órgão/Pessoa de contacto: Júri\nEndereço: Rua Delfim Ferreira, 800/840\nCódigo postal: 4100-199\nLocalidade: PORTO\nPaís: Portugal\nNUT III: PT11A\nDistrito: Porto\nConcelho: Porto\nFreguesia: Freguesia de Ramalde\nTelefone: 226175760\nFax: 226103160\nEndereço da Entidade (URL): www.cinfu.pt\nEndereço Eletrónico: fernando.barbosa@cinfu.pt\neDelivery Gateway (URL): https://www.acingov.pt\nFunção da Organização: Adquirente\nSubfunção da Organização: Organização cujo orçamento é utilizado para pagar o contrato; Organização que executa o pagamento; Organização que fornece informações adicionais sobre o processo de adjudicação; Organização que fornece mais informações sobre os prazos dos procedimentos de recurso; Organização responsável pelo tratamento das propostas; Organização que recebe as propostas; Organização que fornece mais informações sobre os procedimentos de recurso; Organização que assina o contrato\nNorma jurídica da Entidade Adjudicante: Organismo de direito público, controlado por uma autoridade da administração central\nÁrea de atividade da Autoridade Adjudicante: Serviços públicos das administrações públicas\n\n2 - JORNAL OFICIAL DA UNIÃO EUROPEIA\nO procedimento a que este anúncio diz respeito também é publicitado no Jornal Oficial da União Europeia? Não\n\n3 - AVISO\nModelo de Anúncio: Concurso público\nData de Envio do Anúncio: 15-10-2025\n\n5 - PROCESSO\nTipo de Procedimento: Concurso público\nPreço base do procedimento: Sim\nValor do preço base do procedimento: 195.000,00 EUR\nProcedimento com lotes? Não\n\n6 - OBJETO DO CONTRATO\nNúmero de referência interna: PRR 24/2025\nDesignação do contrato: Fornecimento de um Torno horizontal CNC multieixos\nDescrição: Fornecimento de um Torno horizontal CNC multieixos\nTipo de Contrato Principal: Aquisição de Bens Móveis\nTipo de Contrato: Aquisição de Bens Móveis\nClassificação CPV (Vocabulário Comum para os Contratos Públicos)\nObjeto principal\nVocabulário Principal: 42612200\nPreço base s/IVA: 195.000,00 EUR\n\n7 - INDICAÇÕES ADICIONAIS\nO contrato envolve aquisição conjunta (satisfação de várias entidades)? Não\nO contrato é adjudicado por uma central de compras? Não\n\n8 - TÉCNICAS\nO concurso destina-se à celebração de um acordo-quadro? Inexistência de acordo-quadro\nÉ utilizado um leilão eletrónico? Não\nÉ adotada uma fase de negociação? Não\nSistema de Aquisição Dinâmico: Inexistência de sistema de aquisição dinâmico\n\n9 - LOCAL DA EXECUÇÃO DO CONTRATO\nLOCAL DA EXECUÇÃO DO CONTRATO (PROCEDIMENTO)\nPaís: Portugal\nNUT III: PT11A\nLocalidade: Freguesia de Ramalde\nDistrito: Porto\nConcelho: Porto\nFreguesia: Freguesia de Ramalde\n\n10 - PRAZO DE EXECUÇÃO DO CONTRATO\nPrazo de execução do contrato: 100 DIAS\nPrevisão de renovações: Não\n\n11 - FUNDOS EU\nTêm fundos EU? Sim\n\n12 - DOCUMENTOS DE HABILITAÇÃO\nHabilitação para o exercício da atividade profissional: Não\n\n13 - CONDIÇÕES DE APRESENTAÇÃO\nPlataforma eletrónica utilizada pela entidade adjudicante: ACIN\nURL para Apresentação: https://www.acingov.pt\nAdmissibilidade da apresentação de propostas variantes: Não autorizado\nPrazo para apresentação das propostas: 27-10-2025 23:59\nPrazo durante o qual os concorrentes são obrigados a manter as respetivas propostas: 66 dias a contar do termo do prazo para a apresentação das propostas\nIndicação de Subcontratação na Proposta: Inexistência de indicação de subcontratação\n\n14 - PRESTAÇÃO DE CAUÇÃO\nPrestação de caução: Não\n\n15 - FORNECIMENTO DAS PEÇAS DO CONCURSO, APRESENTAÇÃO DE PEDIDOS DE PARTICIPAÇÃO E APRESENTAÇÃO DAS PROPOSTAS\nLink para acesso às peças do concurso (URL): https://www.acingov.pt/acingovprod/2/zonaPublica/zona_publica_c/donwloadProcedurePiece/OTg2MTIz\n\n20 - OUTROS REQUISITOS\nInformação sobre contratos reservados. Aplica-se a contratos reservados (54º-A)? Não\n\n21 - CRITÉRIO DE ADJUDICAÇÃO\nMultifator: Sim\nFator: \nNome: Preço\nPonderação: 35%\nSubfatores: Não\nFator: \nNome: Qualidade\nPonderação: 40%\nSubfatores: Sim\nSubfatores: \nNome: Dimensões máximas do equipamento\nPonderação : 40%; \nNome: Torque máximo da árvore principal\nPonderação : 15%; \nNome: Torque máximo da árvore secundária\nPonderação : 15%; \nNome: Número de suportes de ferramentas exteriores simples\nPonderação : 10%; \nNome: Número de suportes duplos de ferramentas exteriores\nPonderação : 10%; \nNome: Número de suportes duplos para brocas\nPonderação : 10%; \nFator: \nNome: Outros\nOutro Nome: Assistência técnica\nPonderação: 15%\nSubfatores: Sim\nSubfatores: \nNome: Tempo de resposta contratual em caso de avaria\nPonderação : 50%; \nNome: Custo de reparação em caso de avaria (por hora)\nPonderação : 50%; \nFator: \nNome: Outros\nOutro Nome: Formação\nPonderação: 5%\nSubfatores: Não\nFator: \nNome: Outros\nOutro Nome: Sustentabilidade Ambiental\nPonderação: 5%\nSubfatores: Sim\nSubfatores: \nNome: Certificação ambiental\nPonderação : 100%; \n\n24 - CONDIÇÕES DO CONTRATO\nFaturação Eletrónica: Necessário\nObrigação de Subcontratação:\nCódigo da Obrigação de Subcontratação: Não é aplicável nenhuma obrigação de subcontratação.\n\n25 - COMPRA PÚBLICA ESTRATÉGICA\nCompra Pública Estratégica: Inexistência de contratação pública estratégica\n\n26 - INFORMAÇÕES ADICIONAIS\nContrato adequado para PME: Sim\nCobertura ACP (Acordo dos Contratos Públicos da Organização Mundial do Comércio): Não\n\n27 - IDENTIFICAÇÃO E CONTACTOS DO ÓRGÃO DE RECURSOS ADMINISTRATIVOS\nDesignação: Conselho de Administração\nEndereço: Rua Delfim Ferreira, 800/840\nCódigo postal: 4100-199\nLocalidade: PORTO\nTelefone: 226175760\nFax: \nEndereço eletrónico: helena.oliveira@cinfu.pt\nPrazo de interposição do recurso: 5 dias\n\n28 - IDENTIFICAÇÃO DO(S) AUTOR(ES) DE ANÚNCIO\nNome: Paula Alexandra Martins dos Santos de Macedo Teixeira\nCargo: Presidente do Conselho de Administração\n419662073",
    "nipc": "501957910",
    "distrito": "Porto",
    "concelho": "Porto",
    "freguesia": "Freguesia de Ramalde",
    "site": "www.cinfu.pt",
    "email": "fernando.barbosa@cinfu.pt",
    "designacao_contrato": "Fornecimento de um Torno horizontal CNC multieixos",
    "descricao": "Fornecimento de um Torno horizontal CNC multieixos",
    "preco_base": "195.000,00 EUR",
    "prazo_execucao": "100 DIAS",
    "prazo_apresentacao_propostas": "27-10-2025 23:59",
    "fundos_eu": "Sim",
    "plataforma_eletronica": "ACIN",
    "url_procedimento": "https://www.acingov.pt",
    "autor_nome": "Paula Alexandra Martins dos Santos de Macedo Teixeira",
    "autor_cargo": "Presidente do Conselho de Administração"
  },
  {
    "numero_procedimento": "N/A",
    "entidade": "Município de Loulé",
    "link": "https://diariodarepublica.pt/dr/detalhe/contrato-publico/27273-940415582",
    "detalhes_completos": "1 - IDENTIFICAÇÃO E CONTACTOS DA ENTIDADE ADJUDICANTE\nDesignação da entidade adjudicante: Município de Loulé\nNIPC: 502098139\nEndereço: Praça da República\nCódigo postal: 8104-001\nLocalidade: Faro\nPaís: Portugal\nNUT III: PT150\nDistrito: Faro\nConcelho: Loulé\nFreguesia: Todas\nTelefone: 289400834\nFax: 289415557\nEndereço da Entidade (URL): www.cm-loule.pt\nEndereço Eletrónico: aprovisionamento@cm-loule.pt\neDelivery Gateway (URL): https://community.vortal.biz/public/\nFunção da Organização: Adquirente\nNorma jurídica da Entidade Adjudicante: Organismo de direito público\nÁrea de atividade da Autoridade Adjudicante: Serviços públicos das administrações públicas\n\n2 - JORNAL OFICIAL DA UNIÃO EUROPEIA\nO procedimento a que este anúncio diz respeito também é publicitado no Jornal Oficial da União Europeia? Não\n\n3 - AVISO\nModelo de Anúncio: Concurso público\nData de Envio do Anúncio: 15-10-2025\n\n5 - PROCESSO\nTipo de Procedimento: Concurso público\nPreço base do procedimento: Sim\nValor do preço base do procedimento: 43.200,00 EUR\nProcedimento com lotes? Não\n\n6 - OBJETO DO CONTRATO\nNúmero de referência interna: FM-2025-481 DACP\nDesignação do contrato: CONTRATAÇÃO DO FORNECIMENTO CONTÍNUO DE BLOCOS DE SACOS BIODEGRADÁVEIS PARA DEJETOS CANINOS\nDescrição: CONTRATAÇÃO DO FORNECIMENTO CONTÍNUO DE BLOCOS DE SACOS BIODEGRADÁVEIS PARA DEJETOS CANINOS\nTipo de Contrato Principal: Aquisição de Bens Móveis\nTipo de Contrato: Aquisição de Bens Móveis\nClassificação CPV (Vocabulário Comum para os Contratos Públicos)\nObjeto principal\nVocabulário Principal: 19640000\nPreço base s/IVA: 43.200,00 EUR\n\n7 - INDICAÇÕES ADICIONAIS\nO contrato envolve aquisição conjunta (satisfação de várias entidades)? Não\nO contrato é adjudicado por uma central de compras? Não\n\n8 - TÉCNICAS\nO concurso destina-se à celebração de um acordo-quadro? Inexistência de acordo-quadro\nÉ utilizado um leilão eletrónico? Não\nÉ adotada uma fase de negociação? Não\nSistema de Aquisição Dinâmico: Inexistência de sistema de aquisição dinâmico\n\n9 - LOCAL DA EXECUÇÃO DO CONTRATO\nLOCAL DA EXECUÇÃO DO CONTRATO (PROCEDIMENTO)\nPaís: Portugal\nNUT III: PT150\nLocalidade: Faro\nDistrito: Faro\nConcelho: Loulé\nFreguesia: Freguesia de Loulé (São Clemente)\n\n10 - PRAZO DE EXECUÇÃO DO CONTRATO\nPrazo de execução do contrato: 6 MESES\nPrevisão de renovações: Não\n\n11 - FUNDOS EU\nTêm fundos EU? Não\n\n12 - DOCUMENTOS DE HABILITAÇÃO\nHabilitação para o exercício da atividade profissional: Não\n\n13 - CONDIÇÕES DE APRESENTAÇÃO\nPlataforma eletrónica utilizada pela entidade adjudicante: VORTAL\nURL para Apresentação: https://community.vortal.biz/public/\nAdmissibilidade da apresentação de propostas variantes: Não autorizado\nPrazo para apresentação das propostas: 27-10-2025 18:00\nPrazo durante o qual os concorrentes são obrigados a manter as respetivas propostas: 90 dias a contar do termo do prazo para a apresentação das propostas\nIndicação de Subcontratação na Proposta: Inexistência de indicação de subcontratação\n\n14 - PRESTAÇÃO DE CAUÇÃO\nPrestação de caução: Não\n\n15 - FORNECIMENTO DAS PEÇAS DO CONCURSO, APRESENTAÇÃO DE PEDIDOS DE PARTICIPAÇÃO E APRESENTAÇÃO DAS PROPOSTAS\nLink para acesso às peças do concurso (URL): https://community.vortal.biz/Public/public-tender-documents/UzlkWXF2MlVBMk9oZ1ZmYnd6eWdvdzI0ejlGWGhFeGhNNlpkVDI5SkZHQW83MTVXVVhOeVR1d1NWUE5YREFvdldaQTVTK3NObmVIeGN1M1BzWjZPSVE9PVdWT2Fv\n\n20 - OUTROS REQUISITOS\nInformação sobre contratos reservados. Aplica-se a contratos reservados (54º-A)? Não\n\n21 - CRITÉRIO DE ADJUDICAÇÃO\nMultifator: Não\nMonofator:\nNome: Preço\n\n24 - CONDIÇÕES DO CONTRATO\nFaturação Eletrónica: Permitido\nObrigação de Subcontratação:\nCódigo da Obrigação de Subcontratação: Não é aplicável nenhuma obrigação de subcontratação.\n\n25 - COMPRA PÚBLICA ESTRATÉGICA\nCompra Pública Estratégica: Inexistência de contratação pública estratégica\n\n26 - INFORMAÇÕES ADICIONAIS\nContrato adequado para PME: Sim\nCobertura ACP (Acordo dos Contratos Públicos da Organização Mundial do Comércio): Não\n\n27 - IDENTIFICAÇÃO E CONTACTOS DO ÓRGÃO DE RECURSOS ADMINISTRATIVOS\nDesignação: Câmara Municipal de Loulé\nEndereço: Praça da República\nCódigo postal: 8104-001\nLocalidade: Loulé\nTelefone: +351 289400600\nFax: +351 289415557\nEndereço eletrónico: geral@cm-loule.pt\n\n28 - IDENTIFICAÇÃO DO(S) AUTOR(ES) DE ANÚNCIO\nNome: Vítor Manuel Gonçalves Aleixo\nCargo: Presidente da Câmara\n419659117",
    "nipc": "502098139",
    "distrito": "Faro",
    "concelho": "Loulé",
    "freguesia": "Todas",
    "site": "www.cm-loule.pt",
    "email": "aprovisionamento@cm-loule.pt",
    "designacao_contrato": "CONTRATAÇÃO DO FORNECIMENTO CONTÍNUO DE BLOCOS DE SACOS BIODEGRADÁVEIS PARA DEJETOS CANINOS",
    "descricao": "CONTRATAÇÃO DO FORNECIMENTO CONTÍNUO DE BLOCOS DE SACOS BIODEGRADÁVEIS PARA DEJETOS CANINOS",
    "preco_base": "43.200,00 EUR",
    "prazo_execucao": "6 MESES",
    "prazo_apresentacao_propostas": "27-10-2025 18:00",
    "fundos_eu": "Não",
    "plataforma_eletronica": "VORTAL",
    "url_procedimento": "https://community.vortal.biz/public/",
    "autor_nome": "Vítor Manuel Gonçalves Aleixo",
    "autor_cargo": "Presidente da Câmara"
  },
  {
    "numero_procedimento": "N/A",
    "entidade": "Município de Loulé",
    "link": "https://diariodarepublica.pt/dr/detalhe/contrato-publico/27274-940415584",
    "detalhes_completos": "1 - IDENTIFICAÇÃO E CONTACTOS DA ENTIDADE ADJUDICANTE\nDesignação da entidade adjudicante: Município de Loulé\nNIPC: 502098139\nEndereço: Praça da República\nCódigo postal: 8104-001\nLocalidade: Faro\nPaís: Portugal\nNUT III: PT150\nDistrito: Faro\nConcelho: Loulé\nFreguesia: Todas\nTelefone: 289400834\nFax: 289415557\nEndereço da Entidade (URL): www.cm-loule.pt\nEndereço Eletrónico: aprovisionamento@cm-loule.pt\neDelivery Gateway (URL): https://community.vortal.biz/public/\nFunção da Organização: Adquirente\nNorma jurídica da Entidade Adjudicante: Organismo de direito público\nÁrea de atividade da Autoridade Adjudicante: Serviços públicos das administrações públicas\n\n2 - JORNAL OFICIAL DA UNIÃO EUROPEIA\nO procedimento a que este anúncio diz respeito também é publicitado no Jornal Oficial da União Europeia? Não\n\n3 - AVISO\nModelo de Anúncio: Concurso público\nData de Envio do Anúncio: 15-10-2025\n\n5 - PROCESSO\nTipo de Procedimento: Concurso público\nPreço base do procedimento: Sim\nValor do preço base do procedimento: 116.023,00 EUR\nProcedimento com lotes? Sim\nNº Máx. de Lotes Autorizado: 3\nNúmero máximo de lotes que podem ser adjudicados a um concorrente: 3\n\n6 - OBJETO DO CONTRATO\nNúmero de referência interna: FM-2025-464 DACP \nDesignação do contrato: CONTRATAÇÃO DO FORNECIMENTO DE MATERIAIS E PRODUTOS E SERVIÇOS DE MÃO DE OBRA PARA A MANUTENÇÃO, REPARAÇÃO E RECUPERAÇÃO DOS CAMPOS DE FUTEBOL E RUGBY DO CONCELHO DE LOULÉ\nDescrição: CONTRATAÇÃO DO FORNECIMENTO DE MATERIAIS E PRODUTOS E SERVIÇOS DE MÃO DE OBRA PARA A MANUTENÇÃO, REPARAÇÃO E RECUPERAÇÃO DOS CAMPOS DE FUTEBOL E RUGBY DO CONCELHO DE LOULÉ\nTipo de Contrato Principal: Aquisição de Serviços\nTipo de Contrato: Aquisição de Serviços\nClassificação CPV (Vocabulário Comum para os Contratos Públicos)\nObjeto principal\nVocabulário Principal: 77320000\nPreço base s/IVA: 116.023,00 EUR\nLotes: \nNº: LOT-0001\nDescrição do Lote: LOTE 1 \nPreço base s/IVA: 11.750,00 EUR\nClassificação CPV (Vocabulário Comum para os Contratos Públicos)\nObjeto principal\nVocabulário Principal: 77320000\nNº: LOT-0002\nDescrição do Lote: LOTE 2 \nPreço base s/IVA: 59.250,00 EUR\nClassificação CPV (Vocabulário Comum para os Contratos Públicos)\nObjeto principal\nVocabulário Principal: 77320000\nNº: LOT-0003\nDescrição do Lote: LOTE 3\nPreço base s/IVA: 45.023,00 EUR\nClassificação CPV (Vocabulário Comum para os Contratos Públicos)\nObjeto principal\nVocabulário Principal: 77320000\n\n7 - INDICAÇÕES ADICIONAIS\nO contrato envolve aquisição conjunta (satisfação de várias entidades)? Não\nO contrato é adjudicado por uma central de compras? Não\n\n8 - TÉCNICAS\nO concurso destina-se à celebração de um acordo-quadro? Inexistência de acordo-quadro\nÉ utilizado um leilão eletrónico? Não\nÉ adotada uma fase de negociação? Não\nSistema de Aquisição Dinâmico: Inexistência de sistema de aquisição dinâmico\n\n9 - LOCAL DA EXECUÇÃO DO CONTRATO\nLOCAL DA EXECUÇÃO DO CONTRATO (PROCEDIMENTO)\nPaís: Portugal\nNUT III: PT150\nLocalidade: Faro\nDistrito: Faro\nConcelho: Loulé\nFreguesia: Freguesia de Loulé (São Clemente)\nLOCAL DA EXECUÇÃO DO CONTRATO (LOTE)\nIdentificador do Lote: LOT-0001; LOT-0002; LOT-0003\nPaís: Portugal\nNUT III: PT150\nLocalidade: Faro\nDistrito: Faro\nConcelho: Loulé\nFreguesia: Freguesia de Loulé (São Clemente)\n\n10 - PRAZO DE EXECUÇÃO DO CONTRATO\nIdentificador do Lote: LOT-0001; LOT-0002; LOT-0003\nPrazo de execução do contrato: 10 MESES\nPrevisão de renovações: Não\n\n11 - FUNDOS EU\nIdentificador do Lote: LOT-0001; LOT-0002; LOT-0003\nTêm fundos EU? Não\n\n12 - DOCUMENTOS DE HABILITAÇÃO\nHabilitação para o exercício da atividade profissional: Não\n\n13 - CONDIÇÕES DE APRESENTAÇÃO\nPlataforma eletrónica utilizada pela entidade adjudicante: VORTAL\nURL para Apresentação: https://community.vortal.biz/public/\nAdmissibilidade da apresentação de propostas variantes: Não autorizado\nPrazo para apresentação das propostas: 17-11-2025 18:00\nPrazo durante o qual os concorrentes são obrigados a manter as respetivas propostas: 90 dias a contar do termo do prazo para a apresentação das propostas\nIndicação de Subcontratação na Proposta: Inexistência de indicação de subcontratação\n\n14 - PRESTAÇÃO DE CAUÇÃO\nPrestação de caução: Não\n\n15 - FORNECIMENTO DAS PEÇAS DO CONCURSO, APRESENTAÇÃO DE PEDIDOS DE PARTICIPAÇÃO E APRESENTAÇÃO DAS PROPOSTAS\nLink para acesso às peças do concurso (URL): https://community.vortal.biz/Public/public-tender-documents/WFQ0ZlpQNThRTVdXS0tLdnQvTTNqa1VBcDBqc0hQdGdVYmpmRWxRaDAyZjdKV3JYN2gxUnZBNjNieWNWYlVZaUFKNDFVZEF6YUNORk1uZDdjRGhXekE9PUViQ2NY\n\n20 - OUTROS REQUISITOS\nIdentificador do Lote: LOT-0001; LOT-0002; LOT-0003\nInformação sobre contratos reservados. Aplica-se a contratos reservados (54º-A)? Não\n\n21 - CRITÉRIO DE ADJUDICAÇÃO\nO Critério de adjudicação é diferenciado por lote? Não\nMultifator: Não\nMonofator:\nNome: Preço\n\n24 - CONDIÇÕES DO CONTRATO\nIdentificador do Lote: LOT-0001; LOT-0002; LOT-0003\nFaturação Eletrónica: Permitido\nObrigação de Subcontratação:\nCódigo da Obrigação de Subcontratação: Não é aplicável nenhuma obrigação de subcontratação.\n\n25 - COMPRA PÚBLICA ESTRATÉGICA\nCompra Pública Estratégica: Inexistência de contratação pública estratégica\n\n26 - INFORMAÇÕES ADICIONAIS\nIdentificador do Lote: LOT-0001; LOT-0002; LOT-0003\nContrato adequado para PME: Sim\nCobertura ACP (Acordo dos Contratos Públicos da Organização Mundial do Comércio): Não\n\n27 - IDENTIFICAÇÃO E CONTACTOS DO ÓRGÃO DE RECURSOS ADMINISTRATIVOS\nDesignação: Câmara Municipal de Loulé\nEndereço: Praça da República\nCódigo postal: 8104-001\nLocalidade: Loulé\nTelefone: +351 289400600\nFax: +351 289415557\nEndereço eletrónico: geral@cm-loule.pt\n\n28 - IDENTIFICAÇÃO DO(S) AUTOR(ES) DE ANÚNCIO\nNome: Vítor Manuel Gonçalves Aleixo\nCargo: Presidente da Câmara\n419659822",
    "nipc": "502098139",
    "distrito": "Faro",
    "concelho": "Loulé",
    "freguesia": "Todas",
    "site": "www.cm-loule.pt",
    "email": "aprovisionamento@cm-loule.pt",
    "designacao_contrato": "CONTRATAÇÃO DO FORNECIMENTO DE MATERIAIS E PRODUTOS E SERVIÇOS DE MÃO DE OBRA PARA A MANUTENÇÃO, REPARAÇÃO E RECUPERAÇÃO DOS CAMPOS DE FUTEBOL E RUGBY DO CONCELHO DE LOULÉ",
    "descricao": "CONTRATAÇÃO DO FORNECIMENTO DE MATERIAIS E PRODUTOS E SERVIÇOS DE MÃO DE OBRA PARA A MANUTENÇÃO, REPARAÇÃO E RECUPERAÇÃO DOS CAMPOS DE FUTEBOL E RUGBY DO CONCELHO DE LOULÉ",
    "preco_base": "116.023,00 EUR",
    "prazo_execucao": "10 MESES",
    "prazo_apresentacao_propostas": "17-11-2025 18:00",
    "fundos_eu": "Não",
    "plataforma_eletronica": "VORTAL",
    "url_procedimento": "https://community.vortal.biz/public/",
    "autor_nome": "Vítor Manuel Gonçalves Aleixo",
    "autor_cargo": "Presidente da Câmara"
  },
  {
    "numero_procedimento": "N/A",
    "entidade": "Município de Loulé",
    "link": "https://diariodarepublica.pt/dr/detalhe/contrato-publico/27275-940415585",
    "detalhes_completos": "1 - IDENTIFICAÇÃO E CONTACTOS DA ENTIDADE ADJUDICANTE\nDesignação da entidade adjudicante: Município de Loulé\nNIPC: 502098139\nEndereço: Praça da República\nCódigo postal: 8104-001\nLocalidade: Faro\nPaís: Portugal\nNUT III: PT150\nDistrito: Faro\nConcelho: Loulé\nFreguesia: Todas\nTelefone: 289400834\nFax: 289415557\nEndereço da Entidade (URL): www.cm-loule.pt\nEndereço Eletrónico: aprovisionamento@cm-loule.pt\neDelivery Gateway (URL): https://community.vortal.biz/public/\nFunção da Organização: Adquirente\nNorma jurídica da Entidade Adjudicante: Organismo de direito público\nÁrea de atividade da Autoridade Adjudicante: Serviços públicos das administrações públicas\n\n2 - JORNAL OFICIAL DA UNIÃO EUROPEIA\nO procedimento a que este anúncio diz respeito também é publicitado no Jornal Oficial da União Europeia? Não\n\n3 - AVISO\nModelo de Anúncio: Concurso público\nData de Envio do Anúncio: 15-10-2025\n\n5 - PROCESSO\nTipo de Procedimento: Concurso público\nPreço base do procedimento: Sim\nValor do preço base do procedimento: 31.668,00 EUR\nProcedimento com lotes? Não\n\n6 - OBJETO DO CONTRATO\nNúmero de referência interna: FM-2025-483 DACP\nDesignação do contrato: CONTRATAÇÃO DO FORNECIMENTO CONTÍNUO DE GARRAFAS DE ÁGUA MINERAL DE 0,33 LITROS\nDescrição: CONTRATAÇÃO DO FORNECIMENTO CONTÍNUO DE GARRAFAS DE ÁGUA MINERAL DE 0,33 LITROS\nTipo de Contrato Principal: Aquisição de Bens Móveis\nTipo de Contrato: Aquisição de Bens Móveis\nClassificação CPV (Vocabulário Comum para os Contratos Públicos)\nObjeto principal\nVocabulário Principal: 15980000\nPreço base s/IVA: 31.668,00 EUR\n\n7 - INDICAÇÕES ADICIONAIS\nO contrato envolve aquisição conjunta (satisfação de várias entidades)? Não\nO contrato é adjudicado por uma central de compras? Não\n\n8 - TÉCNICAS\nO concurso destina-se à celebração de um acordo-quadro? Inexistência de acordo-quadro\nÉ utilizado um leilão eletrónico? Não\nÉ adotada uma fase de negociação? Não\nSistema de Aquisição Dinâmico: Inexistência de sistema de aquisição dinâmico\n\n9 - LOCAL DA EXECUÇÃO DO CONTRATO\nLOCAL DA EXECUÇÃO DO CONTRATO (PROCEDIMENTO)\nPaís: Portugal\nNUT III: PT150\nLocalidade: Loulé\nDistrito: Faro\nConcelho: Loulé\nFreguesia: Freguesia de Loulé (São Clemente)\n\n10 - PRAZO DE EXECUÇÃO DO CONTRATO\nPrazo de execução do contrato: 14 MESES\nPrevisão de renovações: Não\n\n11 - FUNDOS EU\nTêm fundos EU? Não\n\n12 - DOCUMENTOS DE HABILITAÇÃO\nHabilitação para o exercício da atividade profissional: Não\n\n13 - CONDIÇÕES DE APRESENTAÇÃO\nPlataforma eletrónica utilizada pela entidade adjudicante: VORTAL\nURL para Apresentação: https://community.vortal.biz/public/\nAdmissibilidade da apresentação de propostas variantes: Não autorizado\nPrazo para apresentação das propostas: 31-10-2025 18:00\nPrazo durante o qual os concorrentes são obrigados a manter as respetivas propostas: 90 dias a contar do termo do prazo para a apresentação das propostas\nIndicação de Subcontratação na Proposta: Inexistência de indicação de subcontratação\n\n14 - PRESTAÇÃO DE CAUÇÃO\nPrestação de caução: Não\n\n15 - FORNECIMENTO DAS PEÇAS DO CONCURSO, APRESENTAÇÃO DE PEDIDOS DE PARTICIPAÇÃO E APRESENTAÇÃO DAS PROPOSTAS\nLink para acesso às peças do concurso (URL): https://community.vortal.biz/Public/public-tender-documents/Q2x4aW9TYXZidkwwdjN1R0xtVFdmak5oUmpqT0FoRVJQSjFWV0xyUHI5eklQY0lxbnFreVYvT2pVVUI0MmNmcElFVlBPWXR6empTNElHS05Td0cvNEE9PUU1T01K\n\n20 - OUTROS REQUISITOS\nInformação sobre contratos reservados. Aplica-se a contratos reservados (54º-A)? Não\n\n21 - CRITÉRIO DE ADJUDICAÇÃO\nMultifator: Não\nMonofator:\nNome: Preço\n\n24 - CONDIÇÕES DO CONTRATO\nFaturação Eletrónica: Permitido\nObrigação de Subcontratação:\nCódigo da Obrigação de Subcontratação: Não é aplicável nenhuma obrigação de subcontratação.\n\n25 - COMPRA PÚBLICA ESTRATÉGICA\nCompra Pública Estratégica: Inexistência de contratação pública estratégica\n\n26 - INFORMAÇÕES ADICIONAIS\nContrato adequado para PME: Sim\nCobertura ACP (Acordo dos Contratos Públicos da Organização Mundial do Comércio): Não\n\n27 - IDENTIFICAÇÃO E CONTACTOS DO ÓRGÃO DE RECURSOS ADMINISTRATIVOS\nDesignação: Câmara Municipal de Loulé\nEndereço: Praça da República\nCódigo postal: 8104-001\nLocalidade: Loulé\nTelefone: +351 289400600\nFax: +351 289415557\nEndereço eletrónico: geral@cm-loule.pt\n\n28 - IDENTIFICAÇÃO DO(S) AUTOR(ES) DE ANÚNCIO\nNome: Vítor Manuel Gonçalves Aleixo\nCargo: Presidente da Câmara Municipal\n419661199",
    "nipc": "502098139",
    "distrito": "Faro",
    "concelho": "Loulé",
    "freguesia": "Todas",
    "site": "www.cm-loule.pt",
    "email": "aprovisionamento@cm-loule.pt",
    "designacao_contrato": "CONTRATAÇÃO DO FORNECIMENTO CONTÍNUO DE GARRAFAS DE ÁGUA MINERAL DE 0,33 LITROS",
    "descricao": "CONTRATAÇÃO DO FORNECIMENTO CONTÍNUO DE GARRAFAS DE ÁGUA MINERAL DE 0,33 LITROS",
    "preco_base": "31.668,00 EUR",
    "prazo_execucao": "14 MESES",
    "prazo_apresentacao_propostas": "31-10-2025 18:00",
    "fundos_eu": "Não",
    "plataforma_eletronica": "VORTAL",
    "url_procedimento": "https://community.vortal.biz/public/",
    "autor_nome": "Vítor Manuel Gonçalves Aleixo",
    "autor_cargo": "Presidente da Câmara Municipal"
  },
  {
    "numero_procedimento": "N/A",
    "entidade": "AgdA - Águas Públicas do Alentejo, S. A.",
    "link": "https://diariodarepublica.pt/dr/detalhe/contrato-publico/27276-940415587",
    "detalhes_completos": "1 - IDENTIFICAÇÃO E CONTACTOS DA ENTIDADE ADJUDICANTE\nDesignação da entidade adjudicante: AgdA - Águas Públicas do Alentejo, S. A.\nNIPC: 509133843\nServiço/Órgão/Pessoa de contacto: Serviço de Compras e Logística\nEndereço: Rua Dr. Aresta Branco, nº.51\nCódigo postal: 7800-310\nLocalidade: Beja\nPaís: Portugal\nNUT III: PT184\nDistrito: Beja\nConcelho: Beja\nFreguesia: Todas\nTelefone: 284101100\nFax: 284101199\nEndereço da Entidade (URL): https://www.agda.pt\nEndereço Eletrónico: geral.agda@adp.pt\neDelivery Gateway (URL): https://www.acingov.pt\nFunção da Organização: Adquirente\nNorma jurídica da Entidade Adjudicante: Organismo de direito público\nÁrea de atividade da Autoridade Adjudicante: Serviços públicos das administrações públicas\n\n2 - JORNAL OFICIAL DA UNIÃO EUROPEIA\nO procedimento a que este anúncio diz respeito também é publicitado no Jornal Oficial da União Europeia? Não\n\n3 - AVISO\nModelo de Anúncio: Concurso público\nData de Envio do Anúncio: 15-10-2025\n\n5 - PROCESSO\nTipo de Procedimento: Concurso público\nPreço base do procedimento: Sim\nValor do preço base do procedimento: 1.778.400,00 EUR\nProcedimento com lotes? Não\n\n6 - OBJETO DO CONTRATO\nNúmero de referência interna: 89_006_25_CP_EO_B\nDesignação do contrato: Empreitada de Execução do Reforço da Fiabilidade de Adução a Aljustrel\nDescrição: Empreitada de Execução do Reforço da Fiabilidade de Adução a Aljustrel\nTipo de Contrato Principal: Empreitada de Obras Públicas\nTipo de Contrato: Empreitada de Obras Públicas\nClassificação CPV (Vocabulário Comum para os Contratos Públicos)\nObjeto principal\nVocabulário Principal: 45232150\nPreço base s/IVA: 1.778.400,00 EUR\n\n7 - INDICAÇÕES ADICIONAIS\nO contrato envolve aquisição conjunta (satisfação de várias entidades)? Não\nO contrato é adjudicado por uma central de compras? Não\n\n8 - TÉCNICAS\nO concurso destina-se à celebração de um acordo-quadro? Inexistência de acordo-quadro\nÉ utilizado um leilão eletrónico? Não\nÉ adotada uma fase de negociação? Não\nSistema de Aquisição Dinâmico: Inexistência de sistema de aquisição dinâmico\n\n9 - LOCAL DA EXECUÇÃO DO CONTRATO\nLOCAL DA EXECUÇÃO DO CONTRATO (PROCEDIMENTO)\nPaís: Portugal\nNUT III: PT184\nLocalidade: Aljustrel, São João de Negrilhos e Messejana\nDistrito: Beja\nConcelho: Aljustrel\nFreguesia: Todas\n\n10 - PRAZO DE EXECUÇÃO DO CONTRATO\nPrazo de execução do contrato: 365 DIAS\nPrevisão de renovações: Não\n\n11 - FUNDOS EU\nTêm fundos EU? Não\n\n12 - DOCUMENTOS DE HABILITAÇÃO\nHabilitação para o exercício da atividade profissional: Sim\nTipo: Alvará\nDescrição: Documento comprovativo da titularidade de alvará ou certificado de empreiteiro de obras públicas, contendo as seguintes habilitações:\ni) 6ª subcategoria da 2ª categoria e da classe correspondente ao valor global da proposta;\nii) 1ª, 2ª, 4ª, 5ª, e 7ª subcategorias da 1ª categoria, da classe correspondente ao valor dos trabalhos especializados que lhe respeite, consoante a parte que a esses trabalhos cabe na proposta;\niii) 1ª subcategoria da 2ª categoria, da classe correspondente ao valor dos trabalhos especializados que lhe respeite, consoante a parte que a esses trabalhos cabe na proposta;\niv) 1ª e 9 ª subcategorias da 4ª categoria, da classe correspondente ao valor dos trabalhos especializados que lhe respeite;\nv) 1ª, 2ª, 5ª,7ª, 8ª, 9ª, 10ª, 11ª e 12ª da 5ª categoria, da classe correspondente ao valor dos trabalhos especializados que lhe respeite\n\n13 - CONDIÇÕES DE APRESENTAÇÃO\nPlataforma eletrónica utilizada pela entidade adjudicante: ACIN\nURL para Apresentação: https://www.acingov.pt\nAdmissibilidade da apresentação de propostas variantes: Não autorizado\nPrazo para apresentação das propostas: 29-11-2025 18:00\nPrazo durante o qual os concorrentes são obrigados a manter as respetivas propostas: 180 dias a contar do termo do prazo para a apresentação das propostas\nIndicação de Subcontratação na Proposta: Inexistência de indicação de subcontratação\n\n14 - PRESTAÇÃO DE CAUÇÃO\nPrestação de caução: Sim\nPercentagem: 5%\nDescrição da Garantia Exigida: O valor da caução é de 5.00% do preço contratual.\n\n15 - FORNECIMENTO DAS PEÇAS DO CONCURSO, APRESENTAÇÃO DE PEDIDOS DE PARTICIPAÇÃO E APRESENTAÇÃO DAS PROPOSTAS\nLink para acesso às peças do concurso (URL): https://www.acingov.pt/acingovprod/2/zonaPublica/zona_publica_c/donwloadProcedurePiece/OTg1NzAw\n\n20 - OUTROS REQUISITOS\nInformação sobre contratos reservados. Aplica-se a contratos reservados (54º-A)? Não\n\n21 - CRITÉRIO DE ADJUDICAÇÃO\nMultifator: Sim\nFator: \nNome: Outros\nOutro Nome: Preço\nPonderação: 50%\nSubfatores: Não\nFator: \nNome: Outros\nOutro Nome: Valia Técnica\nPonderação: 50%\nSubfatores: Sim\nSubfatores: \nNome: Metodologia de execução da obra\nPonderação : 50%; \nNome: Detalhe e consistência do Plano de Trabalhos\nPonderação : 30%; \nNome: Caracterização dos equipamentos e materiais\nPonderação : 20%; \n\n24 - CONDIÇÕES DO CONTRATO\nFaturação Eletrónica: Necessário\nObrigação de Subcontratação:\nCódigo da Obrigação de Subcontratação: Não é aplicável nenhuma obrigação de subcontratação.\n\n25 - COMPRA PÚBLICA ESTRATÉGICA\nCompra Pública Estratégica: Inexistência de contratação pública estratégica\n\n26 - INFORMAÇÕES ADICIONAIS\nContrato adequado para PME: Não\nCobertura ACP (Acordo dos Contratos Públicos da Organização Mundial do Comércio): Não\n\n27 - IDENTIFICAÇÃO E CONTACTOS DO ÓRGÃO DE RECURSOS ADMINISTRATIVOS\nDesignação: AgdA-Águas Públicas do Alentejo, S.A.\nEndereço: Rua Dr. Aresta Branco, nº.51\nCódigo postal: 7800-310\nLocalidade: Beja\nTelefone: 284101100\nFax: \nEndereço eletrónico: agda.geral@adp.pt\nPrazo de interposição do recurso: 10 dias\n\n28 - IDENTIFICAÇÃO DO(S) AUTOR(ES) DE ANÚNCIO\nNome: Maria de Fátima Costa\nCargo: Técnica Superior de Compras e Logística\n419662868",
    "nipc": "509133843",
    "distrito": "Beja",
    "concelho": "Beja",
    "freguesia": "Todas",
    "site": "https://www.agda.pt",
    "email": "geral.agda@adp.pt",
    "designacao_contrato": "Empreitada de Execução do Reforço da Fiabilidade de Adução a Aljustrel",
    "descricao": "Empreitada de Execução do Reforço da Fiabilidade de Adução a Aljustrel",
    "preco_base": "1.778.400,00 EUR",
    "prazo_execucao": "365 DIAS",
    "prazo_apresentacao_propostas": "29-11-2025 18:00",
    "fundos_eu": "Não",
    "plataforma_eletronica": "ACIN",
    "url_procedimento": "https://www.acingov.pt",
    "autor_nome": "Maria de Fátima Costa",
    "autor_cargo": "Técnica Superior de Compras e Logística"
  },
  {
    "numero_procedimento": "N/A",
    "entidade": "Instituto Superior de Engenharia do Porto",
    "link": "https://diariodarepublica.pt/dr/detalhe/contrato-publico/27281-940415589",
    "detalhes_completos": "Alteração do Anúncio de procedimento n.º 25967/2025, de 2025-10-02, com o ID 419606897\n\n1 - IDENTIFICAÇÃO E CONTACTOS DA ENTIDADE ADJUDICANTE\nDesignação da entidade adjudicante: Instituto Superior de Engenharia do Porto\nNIPC: 501540709\nServiço/Órgão/Pessoa de contacto: Presidente\nEndereço: Rua Dr. António Bernardino de Almeida, 431\nCódigo postal: 4249-015\nLocalidade: Porto\nPaís: Portugal\nNUT III: PT11A\nDistrito: Porto\nConcelho: Porto\nFreguesia: Freguesia de Paranhos - Porto\nTelefone: 228340500\nFax: 228321159\nEndereço da Entidade (URL): www.isep.ipp.pt\nEndereço Eletrónico: info-sef@isep.ipp.pt\neDelivery Gateway (URL): https://www.acingov.pt\nFunção da Organização: Adquirente\nNorma jurídica da Entidade Adjudicante: Organismo de direito público\nÁrea de atividade da Autoridade Adjudicante: Educação\n\n2 - JORNAL OFICIAL DA UNIÃO EUROPEIA\nO procedimento a que este anúncio diz respeito também é publicitado no Jornal Oficial da União Europeia? Não\n\n3 - AVISO\nModelo de Anúncio: Concurso público\nData de Envio do Anúncio: 15-10-2025\n\n5 - PROCESSO\nTipo de Procedimento: Concurso público\nPreço base do procedimento: Sim\nValor do preço base do procedimento: 475.000,00 EUR\nProcedimento com lotes? Não\n\n6 - OBJETO DO CONTRATO\nNúmero de referência interna: 94/2025\nDesignação do contrato: Projeto de Conceção-Construção e Operação & Manutenção de Sistemas de Produção de Energia Fotovoltaica  Unidade de Produção em Autoconsumo (UPAC) para o ISEP  Instituto Superior de Engenharia do Porto\nDescrição: Projeto de Conceção-Construção e Operação & Manutenção de Sistemas de Produção de Energia Fotovoltaica  Unidade de Produção em Autoconsumo (UPAC) para o ISEP  Instituto Superior de Engenharia do Porto\nTipo de Contrato Principal: Empreitada de Obras Públicas\nTipo de Contrato: Empreitada de Obras Públicas\nClassificação CPV (Vocabulário Comum para os Contratos Públicos)\nObjeto principal\nVocabulário Principal: 45200000\nPreço base s/IVA: 475.000,00 EUR\n\n7 - INDICAÇÕES ADICIONAIS\nO contrato envolve aquisição conjunta (satisfação de várias entidades)? Não\nO contrato é adjudicado por uma central de compras? Não\n\n8 - TÉCNICAS\nO concurso destina-se à celebração de um acordo-quadro? Inexistência de acordo-quadro\nÉ utilizado um leilão eletrónico? Não\nÉ adotada uma fase de negociação? Não\nSistema de Aquisição Dinâmico: Inexistência de sistema de aquisição dinâmico\n\n9 - LOCAL DA EXECUÇÃO DO CONTRATO\nLOCAL DA EXECUÇÃO DO CONTRATO (PROCEDIMENTO)\nPaís: Portugal\nNUT III: PT11A\nLocalidade: Freguesia de Paranhos - Porto\nDistrito: Porto\nConcelho: Porto\nFreguesia: Freguesia de Paranhos - Porto\n\n10 - PRAZO DE EXECUÇÃO DO CONTRATO\nPrazo de execução do contrato: 3834 DIAS\nPrevisão de renovações: Não\n\n11 - FUNDOS EU\nTêm fundos EU? Sim\n\n12 - DOCUMENTOS DE HABILITAÇÃO\nHabilitação para o exercício da atividade profissional: Sim\nTipo: Alvará\nDescrição: 2ª e 7ª subcategorias da 1ª categoria e da 6ª subcategoria da 4ª categoria;\n\n13 - CONDIÇÕES DE APRESENTAÇÃO\nPlataforma eletrónica utilizada pela entidade adjudicante: ACIN\nURL para Apresentação: https://www.acingov.pt\nAdmissibilidade da apresentação de propostas variantes: Não autorizado\nPrazo para apresentação das propostas: 21-10-2025 17:00\nPrazo durante o qual os concorrentes são obrigados a manter as respetivas propostas: 90 dias a contar do termo do prazo para a apresentação das propostas\nIndicação de Subcontratação na Proposta: Inexistência de indicação de subcontratação\n\n14 - PRESTAÇÃO DE CAUÇÃO\nPrestação de caução: Sim\nPercentagem: 5%\nDescrição da Garantia Exigida: O valor da caução é de 5.00% do preço contratual.\n\n15 - FORNECIMENTO DAS PEÇAS DO CONCURSO, APRESENTAÇÃO DE PEDIDOS DE PARTICIPAÇÃO E APRESENTAÇÃO DAS PROPOSTAS\nLink para acesso às peças do concurso (URL): https://www.acingov.pt/acingovprod/2/zonaPublica/zona_publica_c/donwloadProcedurePiece/OTgyMjgy\n\n20 - OUTROS REQUISITOS\nInformação sobre contratos reservados. Aplica-se a contratos reservados (54º-A)? Não\n\n21 - CRITÉRIO DE ADJUDICAÇÃO\nMultifator: Sim\nFator: \nNome: Preço\nPonderação: 70%\nSubfatores: Não\nFator: \nNome: Outros\nOutro Nome: Performance Ratio\nPonderação: 20%\nSubfatores: Não\nFator: \nNome: Outros\nOutro Nome: Potência instalada\nPonderação: 10%\nSubfatores: Não\n\n24 - CONDIÇÕES DO CONTRATO\nFaturação Eletrónica: Permitido\nObrigação de Subcontratação:\nCódigo da Obrigação de Subcontratação: Não é aplicável nenhuma obrigação de subcontratação.\n\n25 - COMPRA PÚBLICA ESTRATÉGICA\nCompra Pública Estratégica: Redução dos impactos ambientais\nDescrição do Processo de Adjudicação Estratégico: Este procedimento é estratégico para a implementação da política de sustentabilidade da instituição.\nCritérios de contratos Públicos Ecológicos: Critérios de contratação pública ecológica nacional\nCategorias da estratégia nacional: Eletricidade\nContratos Públicos Ecológicos: Outros\nDiretiva Veículos Não Poluentes: Não\nCritério de Acessibilidade: Os critérios de acessibilidade para as pessoas com deficiência não estão incluídos porque o contrato não se destina a pessoas singulares\n\n26 - INFORMAÇÕES ADICIONAIS\nContrato adequado para PME: Sim\nCobertura ACP (Acordo dos Contratos Públicos da Organização Mundial do Comércio): Não\n\n27 - IDENTIFICAÇÃO E CONTACTOS DO ÓRGÃO DE RECURSOS ADMINISTRATIVOS\nDesignação: Presidente\nEndereço: Rua Dr. António Bernardino de Almeida, 431\nCódigo postal: 4249-015\nLocalidade: Porto\nTelefone: 228340500\nFax: 228321159\nEndereço eletrónico: info-sef@isep.ipp.pt\nPrazo de interposição do recurso: 5 dias\n\n28 - IDENTIFICAÇÃO DO(S) AUTOR(ES) DE ANÚNCIO\nNome: Carla Maria Oliveira Martins\nCargo: Assistente Técnico\n\n29 - ALTERAÇÃO\nMotivo da Alteração: Correção pelo adquirente\nIdentificador da Versão do Anúncio a Alterar: 95a3e42e-7a90-4faa-a51c-5fab757e3519-01\nIdentificador das Secções Alteradas do Anúncio Anterior: Condições de Apresentação\nDescrição das Alterações: Modificação do prazo para a apresentação de propostas\nAlteração dos Documentos do Concurso: Não\n419662827",
    "nipc": "501540709",
    "distrito": "Porto",
    "concelho": "Porto",
    "freguesia": "Freguesia de Paranhos - Porto",
    "site": "www.isep.ipp.pt",
    "email": "info-sef@isep.ipp.pt",
    "designacao_contrato": "Projeto de Conceção-Construção e Operação & Manutenção de Sistemas de Produção de Energia Fotovoltaica  Unidade de Produção em Autoconsumo (UPAC) para o ISEP  Instituto Superior de Engenharia do Porto",
    "descricao": "Projeto de Conceção-Construção e Operação & Manutenção de Sistemas de Produção de Energia Fotovoltaica  Unidade de Produção em Autoconsumo (UPAC) para o ISEP  Instituto Superior de Engenharia do Porto",
    "preco_base": "475.000,00 EUR",
    "prazo_execucao": "3834 DIAS",
    "prazo_apresentacao_propostas": "21-10-2025 17:00",
    "fundos_eu": "Sim",
    "plataforma_eletronica": "ACIN",
    "url_procedimento": "https://www.acingov.pt",
    "autor_nome": "Carla Maria Oliveira Martins",
    "autor_cargo": "Assistente Técnico"
  },
  {
    "numero_procedimento": "N/A",
    "entidade": "Unidade Local de Saúde de Lisboa Ocidental, E. P. E.",
    "link": "https://diariodarepublica.pt/dr/detalhe/contrato-publico/27282-940415590",
    "detalhes_completos": "1 - IDENTIFICAÇÃO E CONTACTOS DA ENTIDADE ADJUDICANTE\nDesignação da entidade adjudicante: Unidade Local de Saúde de Lisboa Ocidental, E. P. E.\nNIPC: 507618319\nEndereço: Santa Maria de Belém  Estrada do Forte do Alto do Duque\nCódigo postal: 1449-005\nLocalidade: Lisboa\nPaís: Portugal\nNUT III: PT170\nDistrito: Lisboa\nConcelho: Lisboa\nFreguesia: Todas\nTelefone: 210431000\nFax: 210431642\nEndereço da Entidade (URL): www.chlo.min-saude.pt/\nEndereço Eletrónico: comprasgeral@ulslo.min-saude.pt\neDelivery Gateway (URL): https://community.vortal.biz/public/\nFunção da Organização: Adquirente\nNorma jurídica da Entidade Adjudicante: Organismo de direito público\nÁrea de atividade da Autoridade Adjudicante: Saúde\n\n2 - JORNAL OFICIAL DA UNIÃO EUROPEIA\nO procedimento a que este anúncio diz respeito também é publicitado no Jornal Oficial da União Europeia? Sim\n\n3 - AVISO\nModelo de Anúncio: Concurso público\nData de Envio do Anúncio: 13-10-2025\n\n5 - PROCESSO\nTipo de Procedimento: Concurso público\nPreço base do procedimento: Sim\nValor do preço base do procedimento: 2.665.000,00 EUR\nProcedimento com lotes? Não\n\n6 - OBJETO DO CONTRATO\nNúmero de referência interna: 148003825\nDesignação do contrato: 148003825 para Aquisição de 1 Ressonância Magnética 3 Tesla para o Serviço de Radiologia do Hospital de São Francisco Xavier da Unidade Local de Saúde de Lisboa Ocidental E.P.E. no âmbito do PRR\nDescrição: 148003825 para Aquisição de 1 Ressonância Magnética 3 Tesla para o Serviço de Radiologia do Hospital de São Francisco Xavier da Unidade Local de Saúde de Lisboa Ocidental E.P.E. no âmbito do PRR/AC03/C01- i10/2025 projeto nº 17837\nOpções: Não\nTipo de Contrato Principal: Aquisição de Bens Móveis\nTipo de Contrato: Aquisição de Bens Móveis\nClassificação CPV (Vocabulário Comum para os Contratos Públicos)\nObjeto principal\nVocabulário Principal: 33100000\nPreço base s/IVA: 2.665.000,00 EUR\n\n7 - INDICAÇÕES ADICIONAIS\nO contrato envolve aquisição conjunta (satisfação de várias entidades)? Não\nO contrato é adjudicado por uma central de compras? Não\n\n8 - TÉCNICAS\nO concurso destina-se à celebração de um acordo-quadro? Inexistência de acordo-quadro\nÉ utilizado um leilão eletrónico? Não\nÉ adotada uma fase de negociação? Não\nSistema de Aquisição Dinâmico: Inexistência de sistema de aquisição dinâmico\n\n9 - LOCAL DA EXECUÇÃO DO CONTRATO\nLOCAL DA EXECUÇÃO DO CONTRATO (PROCEDIMENTO)\nPaís: Portugal\nNUT III: PT170\nLocalidade: Lisboa\nDistrito: Lisboa\nConcelho: Lisboa\nFreguesia: Todas\n\n10 - PRAZO DE EXECUÇÃO DO CONTRATO\nPrazo de execução do contrato: 8 MESES\nPrevisão de renovações: Não\n\n11 - FUNDOS EU\nTêm fundos EU? Não\n\n12 - DOCUMENTOS DE HABILITAÇÃO\nHabilitação para o exercício da atividade profissional: Não\n\n13 - CONDIÇÕES DE APRESENTAÇÃO\nPlataforma eletrónica utilizada pela entidade adjudicante: VORTAL\nURL para Apresentação: https://community.vortal.biz/public/\nAdmissibilidade da apresentação de propostas variantes: Não autorizado\nPrazo para apresentação das propostas: 14-11-2025 17:00\nPrazo durante o qual os concorrentes são obrigados a manter as respetivas propostas: 66 dias a contar do termo do prazo para a apresentação das propostas\nApresentação de Catálogo Eletrónico: Permitido\nIndicação de Subcontratação na Proposta: Inexistência de indicação de subcontratação\n\n14 - PRESTAÇÃO DE CAUÇÃO\nPrestação de caução: Não\n\n15 - FORNECIMENTO DAS PEÇAS DO CONCURSO, APRESENTAÇÃO DE PEDIDOS DE PARTICIPAÇÃO E APRESENTAÇÃO DAS PROPOSTAS\nLink para acesso às peças do concurso (URL): https://community.vortal.biz/Public/public-tender-documents/dkRMY2tKQmlYN0RxOEZtWjBSRUpHMnNOdDBoOTE3Wkw1N2Nib1ZGbGRQVHArc1dPSUx0d2pMaDg0VlJONWdYUVJjY0w5TFJrZEpnM2x4NnFGNzM4Snc9PUJtNGxY\n\n20 - OUTROS REQUISITOS\nInformação sobre contratos reservados. Aplica-se a contratos reservados (54º-A)? Não\n\n21 - CRITÉRIO DE ADJUDICAÇÃO\nMultifator: Sim\nFator: \nNome: Preço\nPonderação: 40%\nSubfatores: Não\nFator: \nNome: Qualidade\nPonderação: 50%\nSubfatores: Não\nFator: \nNome: Qualidade\nPonderação: 10%\nSubfatores: Não\n\n24 - CONDIÇÕES DO CONTRATO\nFaturação Eletrónica: Permitido\nObrigação de Subcontratação:\nCódigo da Obrigação de Subcontratação: Não é aplicável nenhuma obrigação de subcontratação.\n\n25 - COMPRA PÚBLICA ESTRATÉGICA\nCompra Pública Estratégica: Inexistência de contratação pública estratégica\n\n26 - INFORMAÇÕES ADICIONAIS\nContrato adequado para PME: Sim\nCobertura ACP (Acordo dos Contratos Públicos da Organização Mundial do Comércio): Não\n\n27 - IDENTIFICAÇÃO E CONTACTOS DO ÓRGÃO DE RECURSOS ADMINISTRATIVOS\nDesignação: Conselho de Administração\nEndereço: Estrada do Forte do Alto do Duque,\nCódigo postal: 1449-005\nLocalidade: Lisboa\nTelefone: +351 210431000\nFax: +351 210431639\nEndereço eletrónico: comprasgeral@ulslo.min-saude.pt\n\n28 - IDENTIFICAÇÃO DO(S) AUTOR(ES) DE ANÚNCIO\nNome: Ana Santos\nCargo: Assistente Técnica\n419650417",
    "nipc": "507618319",
    "distrito": "Lisboa",
    "concelho": "Lisboa",
    "freguesia": "Todas",
    "site": "www.chlo.min-saude.pt/",
    "email": "comprasgeral@ulslo.min-saude.pt",
    "designacao_contrato": "148003825 para Aquisição de 1 Ressonância Magnética 3 Tesla para o Serviço de Radiologia do Hospital de São Francisco Xavier da Unidade Local de Saúde de Lisboa Ocidental E.P.E. no âmbito do PRR",
    "descricao": "148003825 para Aquisição de 1 Ressonância Magnética 3 Tesla para o Serviço de Radiologia do Hospital de São Francisco Xavier da Unidade Local de Saúde de Lisboa Ocidental E.P.E. no âmbito do PRR/AC03/C01- i10/2025 projeto nº 17837",
    "preco_base": "2.665.000,00 EUR",
    "prazo_execucao": "8 MESES",
    "prazo_apresentacao_propostas": "14-11-2025 17:00",
    "fundos_eu": "Não",
    "plataforma_eletronica": "VORTAL",
    "url_procedimento": "https://community.vortal.biz/public/",
    "autor_nome": "Ana Santos",
    "autor_cargo": "Assistente Técnica"
  },
  {
    "numero_procedimento": "N/A",
    "entidade": "Centro de Bem Estar Social de Brasfemes - CEBES",
    "link": "https://diariodarepublica.pt/dr/detalhe/contrato-publico/27283-940415591",
    "detalhes_completos": "1 - IDENTIFICAÇÃO E CONTACTOS DA ENTIDADE ADJUDICANTE\nDesignação da entidade adjudicante: Centro de Bem Estar Social de Brasfemes - CEBES\nNIPC: 503867225\nServiço/Órgão/Pessoa de contacto: Paulo Jorge de Quadros Tenreiro\nEndereço: Rua dos Descobrimentos nº 53 3020-542 Brasfemes\nCódigo postal: 3020-542\nLocalidade: Brasfemes\nPaís: Portugal\nNUT III: PT16E\nDistrito: Coimbra\nConcelho: Coimbra\nFreguesia: Freguesia de Brasfemes\nTelefone: 239914800\nEndereço Eletrónico: cebesbrasfemes@gmail.com\neDelivery Gateway (URL): https://www.acingov.pt\nFunção da Organização: Adquirente\nSubfunção da Organização: Organização cujo orçamento é utilizado para pagar o contrato; Organização que executa o pagamento; Organização responsável pelo tratamento das propostas; Organização que recebe as propostas; Organização que assina o contrato\nNorma jurídica da Entidade Adjudicante: Organização que adjudica um contrato subvencionado por uma autoridade adjudicante\nÁrea de atividade da Autoridade Adjudicante: Proteção social\n\n2 - JORNAL OFICIAL DA UNIÃO EUROPEIA\nO procedimento a que este anúncio diz respeito também é publicitado no Jornal Oficial da União Europeia? Não\n\n3 - AVISO\nModelo de Anúncio: Concurso público\nData de Envio do Anúncio: 15-10-2025\n\n5 - PROCESSO\nTipo de Procedimento: Concurso público\nPreço base do procedimento: Sim\nValor do preço base do procedimento: 258.000,00 EUR\nProcedimento com lotes? Não\n\n6 - OBJETO DO CONTRATO\nNúmero de referência interna: CP/2/2025\nDesignação do contrato: EMPREITADA PARA REMODELAÇÃO E AMPLIAÇÃO DO EDIFÍCIO DO CENTRO DE DIA E APOIO DOMICILIÁRIO DO CENTRO DE BEM ESTAR SOCIAL DE BRASFEMES\nDescrição: O presente concurso tem como objetivo a adjudicação de uma proposta para a execução de uma empreitada para a remodelação e ampliação do edifício do Centro de Dia e apoio domiciliário do Centro de Bem estar de Brasfemes.A empreitada consiste na realização de trabalhos necessários à sua remodelação e ampliação de acordo com as características e especificações previstas no projeto e caderno de encargos.\nTipo de Contrato Principal: Empreitada de Obras Públicas\nTipo de Contrato: Empreitada de Obras Públicas\nClassificação CPV (Vocabulário Comum para os Contratos Públicos)\nObjeto principal\nVocabulário Principal: 45262800\nPreço base s/IVA: 258.000,00 EUR\n\n7 - INDICAÇÕES ADICIONAIS\nO contrato envolve aquisição conjunta (satisfação de várias entidades)? Não\nO contrato é adjudicado por uma central de compras? Não\n\n8 - TÉCNICAS\nO concurso destina-se à celebração de um acordo-quadro? Inexistência de acordo-quadro\nÉ utilizado um leilão eletrónico? Não\nÉ adotada uma fase de negociação? Não\nSistema de Aquisição Dinâmico: Inexistência de sistema de aquisição dinâmico\n\n9 - LOCAL DA EXECUÇÃO DO CONTRATO\nLOCAL DA EXECUÇÃO DO CONTRATO (PROCEDIMENTO)\nPaís: Portugal\nNUT III: PT16E\nLocalidade: Freguesia de Brasfemes\nDistrito: Coimbra\nConcelho: Coimbra\nFreguesia: Freguesia de Brasfemes\n\n10 - PRAZO DE EXECUÇÃO DO CONTRATO\nPrazo de execução do contrato: 180 DIAS\nPrevisão de renovações: Não\n\n11 - FUNDOS EU\nTêm fundos EU? Sim\n\n12 - DOCUMENTOS DE HABILITAÇÃO\nHabilitação para o exercício da atividade profissional: Sim\nTipo: Alvará\nDescrição: e) Alvará de empreiteiro de obras públicas ou o certificado de empreiteiro de obras públicas emitidos pelo Instituto dos Mercados Públicos do Imobiliário e da Construção, I.P. (IMPIC, I.P), contendo as seguintes habilitações adequadas e necessárias à execução da obra: \n -  1ª Subcategorias da 1ª Categoria e da classe correspondente ao valor da proposta; Na classe correspondente cada uma ao valor dos respetivos trabalhos especializados a que lhe respeitem: -  4.ª, 5.ª, 6.ª, 7.ª, 8.ª e 9.ª subcategorias da 1.ª categoria;\n\n13 - CONDIÇÕES DE APRESENTAÇÃO\nPlataforma eletrónica utilizada pela entidade adjudicante: ACIN\nURL para Apresentação: https://www.acingov.pt\nAdmissibilidade da apresentação de propostas variantes: Não autorizado\nPrazo para apresentação das propostas: 15-11-2025 23:59\nPrazo durante o qual os concorrentes são obrigados a manter as respetivas propostas: 66 dias a contar do termo do prazo para a apresentação das propostas\nIndicação de Subcontratação na Proposta: Inexistência de indicação de subcontratação\n\n14 - PRESTAÇÃO DE CAUÇÃO\nPrestação de caução: Sim\nPercentagem: 5%\nDescrição da Garantia Exigida: O valor da caução é de 5.00% do preço contratual.\n\n15 - FORNECIMENTO DAS PEÇAS DO CONCURSO, APRESENTAÇÃO DE PEDIDOS DE PARTICIPAÇÃO E APRESENTAÇÃO DAS PROPOSTAS\nLink para acesso às peças do concurso (URL): https://www.acingov.pt/acingovprod/2/zonaPublica/zona_publica_c/donwloadProcedurePiece/OTg3NzMw\n\n20 - OUTROS REQUISITOS\nInformação sobre contratos reservados. Aplica-se a contratos reservados (54º-A)? Não\n\n21 - CRITÉRIO DE ADJUDICAÇÃO\nMultifator: Sim\nFator: \nNome: Preço\nPonderação: 60%\nSubfatores: Não\nFator: \nNome: Outros\nOutro Nome: Valia Técnica da Proposta\nPonderação: 40%\nSubfatores: Sim\nSubfatores: \nNome: ) Memória e descritiva sumária do modo de execução da obra\nPonderação : 75%; \nNome: Plano de Trabalhos\nPonderação : 25%; \n\n24 - CONDIÇÕES DO CONTRATO\nFaturação Eletrónica: Permitido\nObrigação de Subcontratação:\nCódigo da Obrigação de Subcontratação: Não é aplicável nenhuma obrigação de subcontratação.\n\n25 - COMPRA PÚBLICA ESTRATÉGICA\nCompra Pública Estratégica: Inexistência de contratação pública estratégica\n\n26 - INFORMAÇÕES ADICIONAIS\nContrato adequado para PME: Sim\nCobertura ACP (Acordo dos Contratos Públicos da Organização Mundial do Comércio): Não\n\n27 - IDENTIFICAÇÃO E CONTACTOS DO ÓRGÃO DE RECURSOS ADMINISTRATIVOS\nDesignação: Direção\nEndereço: Rua dos Descobrimentos nº 53 3020-542 Brasfemes\nCódigo postal: 3020-542\nLocalidade: Brasfemes\nTelefone: 239914800\nFax: \nEndereço eletrónico: cebesbrasfemes@gmail.com\nPrazo de interposição do recurso: 5 dias\n\n28 - IDENTIFICAÇÃO DO(S) AUTOR(ES) DE ANÚNCIO\nNome: Paulo Jorge de Quadros Tenreiro\nCargo: Presidente\n419662754",
    "nipc": "503867225",
    "distrito": "Coimbra",
    "concelho": "Coimbra",
    "freguesia": "Freguesia de Brasfemes",
    "site": null,
    "email": "cebesbrasfemes@gmail.com",
    "designacao_contrato": "EMPREITADA PARA REMODELAÇÃO E AMPLIAÇÃO DO EDIFÍCIO DO CENTRO DE DIA E APOIO DOMICILIÁRIO DO CENTRO DE BEM ESTAR SOCIAL DE BRASFEMES",
    "descricao": "O presente concurso tem como objetivo a adjudicação de uma proposta para a execução de uma empreitada para a remodelação e ampliação do edifício do Centro de Dia e apoio domiciliário do Centro de Bem estar de Brasfemes.A empreitada consiste na realização de trabalhos necessários à sua remodelação e ampliação de acordo com as características e especificações previstas no projeto e caderno de encargos.",
    "preco_base": "258.000,00 EUR",
    "prazo_execucao": "180 DIAS",
    "prazo_apresentacao_propostas": "15-11-2025 23:59",
    "fundos_eu": "Sim",
    "plataforma_eletronica": "ACIN",
    "url_procedimento": "https://www.acingov.pt",
    "autor_nome": "Paulo Jorge de Quadros Tenreiro",
    "autor_cargo": "Presidente"
  },
  {
    "numero_procedimento": "N/A",
    "entidade": "Águas do Vale do Tejo, S. A.",
    "link": "https://diariodarepublica.pt/dr/detalhe/contrato-publico/27265-940416179",
    "detalhes_completos": "1 - IDENTIFICAÇÃO E CONTACTOS DA ENTIDADE ADJUDICANTE\nDesignação da entidade adjudicante: Águas do Vale do Tejo, S. A.\nNIPC: 513606130\nServiço/Órgão/Pessoa de contacto: Direção de Engenharia\nEndereço: Rua Dr. Francisco Pissarra de Matos, n.º 21, r/c\nCódigo postal: 6300-693\nLocalidade: Guarda\nPaís: Portugal\nNUT III: PT16J\nDistrito: Guarda\nConcelho: Guarda\nFreguesia: Freguesia de Arrifana - Guarda\nTelefone: 271225317\nFax: 271221955\nEndereço da Entidade (URL): http://www.advt.pt\nEndereço Eletrónico: ConcursosEngenharia.EPAL@ADP.pt\neDelivery Gateway (URL): https://www.acingov.pt\nFunção da Organização: Adquirente\nNorma jurídica da Entidade Adjudicante: Empresa pública\nÁrea de atividade da Entidade Adjudicante: Atividades relacionadas com a água\n\n2 - JORNAL OFICIAL DA UNIÃO EUROPEIA\nO procedimento a que este anúncio diz respeito também é publicitado no Jornal Oficial da União Europeia? Não\n\n3 - AVISO\nModelo de Anúncio: Concurso público\nData de Envio do Anúncio: 15-10-2025\n\n5 - PROCESSO\nTipo de Procedimento: Concurso público\nPreço base do procedimento: Sim\nValor do preço base do procedimento: 600.000,00 EUR\nProcedimento com lotes? Não\n\n6 - OBJETO DO CONTRATO\nNúmero de referência interna: ENG24034\nDesignação do contrato: Execução de melhorias de segurança nas barragens de Carvalhal do Eiró e Fumadinha\nDescrição: Execução de melhorias de segurança nas barragens de Carvalhal do Eiró e de Fumadinha\nTipo de Contrato Principal: Empreitada de Obras Públicas\nTipo de Contrato: Empreitada de Obras Públicas\nClassificação CPV (Vocabulário Comum para os Contratos Públicos)\nObjeto principal\nVocabulário Principal: 45247212\nPreço base s/IVA: 600.000,00 EUR\n\n7 - INDICAÇÕES ADICIONAIS\nO contrato envolve aquisição conjunta (satisfação de várias entidades)? Não\nO contrato é adjudicado por uma central de compras? Não\n\n8 - TÉCNICAS\nO concurso destina-se à celebração de um acordo-quadro? Inexistência de acordo-quadro\nÉ utilizado um leilão eletrónico? Não\nÉ adotada uma fase de negociação? Não\nSistema de Aquisição Dinâmico: Inexistência de sistema de aquisição dinâmico\n\n9 - LOCAL DA EXECUÇÃO DO CONTRATO\nLOCAL DA EXECUÇÃO DO CONTRATO (PROCEDIMENTO)\nPaís: Portugal\nNUT III: PT16J\nLocalidade: Carvalhal do Eiró e Fumadinha\nDistrito: Guarda\nConcelho: Aguiar da Beira\nFreguesia: Todas\n\n10 - PRAZO DE EXECUÇÃO DO CONTRATO\nPrazo de execução do contrato: 270 DIAS\nPrevisão de renovações: Não\n\n11 - FUNDOS EU\nTêm fundos EU? Não\n\n12 - DOCUMENTOS DE HABILITAÇÃO\nHabilitação para o exercício da atividade profissional: Sim\nTipo: Alvará\nDescrição: Alvarás, certificados ou declarações emitidos pelo Instituto dos Mercados Públicos, do Imobiliário e da Construção, I.P.\n(IMPIC), contendo as habilitações adequadas e necessárias à execução da obra a realizar, designadamente: \n- 1.ª Subcategoria (Obras fluviais e aproveitamentos hidráulicos) da 3.ª categoria (Obras hidráulicas), da classe correspondente ao valor global da proposta \n- 19.ª Subcategoria (Outras instalações mecânicas e eletromecânicas) da 4.ª categoria (Instalações elétricas e mecânicas), da classe correspondente à parte dos trabalhos a que respeita\n\n13 - CONDIÇÕES DE APRESENTAÇÃO\nPlataforma eletrónica utilizada pela entidade adjudicante: ACIN\nURL para Apresentação: https://www.acingov.pt\nAdmissibilidade da apresentação de propostas variantes: Não autorizado\nPrazo para apresentação das propostas: 02-12-2025 19:00\nPrazo durante o qual os concorrentes são obrigados a manter as respetivas propostas: 180 dias a contar do termo do prazo para a apresentação das propostas\nApresentação de Catálogo Eletrónico: Permitido\nIndicação de Subcontratação na Proposta: A parte do contrato que o proponente tenciona subcontratar\n\n14 - PRESTAÇÃO DE CAUÇÃO\nPrestação de caução: Sim\nPercentagem: 5%\nDescrição da Garantia Exigida: Depósito em dinheiro ou em títulos emitidos ou garantidos pelo Estado Português à ordem da AdVT, ou mediante garantia bancária ou seguro-caução, nos termos dos anexos ao programa do concurso\n\n15 - FORNECIMENTO DAS PEÇAS DO CONCURSO, APRESENTAÇÃO DE PEDIDOS DE PARTICIPAÇÃO E APRESENTAÇÃO DAS PROPOSTAS\nLink para acesso às peças do concurso (URL): https://www.acingov.pt/acingovprod/2/zonaPublica/zona_publica_c/donwloadProcedurePiece/OTg2NTEw\n\n20 - OUTROS REQUISITOS\nInformação sobre contratos reservados. Aplica-se a contratos reservados (54º-A)? Não\n\n21 - CRITÉRIO DE ADJUDICAÇÃO\nMultifator: Sim\nFator: \nNome: Preço\nPonderação: 50%\nSubfatores: Não\nFator: \nNome: Outros\nOutro Nome: Valia Técnica\nPonderação: 50%\nSubfatores: Sim\nSubfatores: \nNome: Metodologia de execução da obra\nPonderação : 60%; \nNome: Detalhe e Consistência do Plano de Trabalhos\nPonderação : 40%; \n\n24 - CONDIÇÕES DO CONTRATO\nFaturação Eletrónica: Permitido\nObrigação de Subcontratação:\nCódigo da Obrigação de Subcontratação: Não é aplicável nenhuma obrigação de subcontratação.\n\n25 - COMPRA PÚBLICA ESTRATÉGICA\nCompra Pública Estratégica: Inexistência de contratação pública estratégica\n\n26 - INFORMAÇÕES ADICIONAIS\nContrato adequado para PME: Sim\nCobertura ACP (Acordo dos Contratos Públicos da Organização Mundial do Comércio): Não\n\n27 - IDENTIFICAÇÃO E CONTACTOS DO ÓRGÃO DE RECURSOS ADMINISTRATIVOS\nDesignação: Conselho de Administração da EPAL, S.A.\nEndereço: Avenida da Liberdade, 24\nCódigo postal: 1250-144\nLocalidade: Lisboa\nTelefone: 213107900\nFax: \nEndereço eletrónico: geral.epal@adp.pt\n\n28 - IDENTIFICAÇÃO DO(S) AUTOR(ES) DE ANÚNCIO\nNome: José Manuel Sardinha\nCargo: Presidente do Conselho de Administração\n419656136",
    "nipc": "513606130",
    "distrito": "Guarda",
    "concelho": "Guarda",
    "freguesia": "Freguesia de Arrifana - Guarda",
    "site": "http://www.advt.pt",
    "email": "ConcursosEngenharia.EPAL@ADP.pt",
    "designacao_contrato": "Execução de melhorias de segurança nas barragens de Carvalhal do Eiró e Fumadinha",
    "descricao": "Execução de melhorias de segurança nas barragens de Carvalhal do Eiró e de Fumadinha",
    "preco_base": "600.000,00 EUR",
    "prazo_execucao": "270 DIAS",
    "prazo_apresentacao_propostas": "02-12-2025 19:00",
    "fundos_eu": "Não",
    "plataforma_eletronica": "ACIN",
    "url_procedimento": "https://www.acingov.pt",
    "autor_nome": "José Manuel Sardinha",
    "autor_cargo": "Presidente do Conselho de Administração"
  },
  {
    "numero_procedimento": "N/A",
    "entidade": "Secretaria Regional da Juventude, Habitação e Emprego",
    "link": "https://diariodarepublica.pt/dr/detalhe/contrato-publico/27266-940416180",
    "detalhes_completos": "1 - IDENTIFICAÇÃO E CONTACTOS DA ENTIDADE ADJUDICANTE\nDesignação da entidade adjudicante: Secretaria Regional da Juventude, Habitação e Emprego\nNIPC: 600087549\nServiço/Órgão/Pessoa de contacto: Direção Regional da Habitação\nEndereço: Rua Dr. Bruno Tavares Carreiro s/n\nCódigo postal: 9500-119\nLocalidade: Ponta Delgada\nPaís: Portugal\nNUT III: PT200\nDistrito: Região Autónoma dos Açores\nConcelho: Todos\nFreguesia: Todas\nTelefone: 296308000\nEndereço da Entidade (URL): https://portal.azores.gov.pt/web/srjhe\nEndereço Eletrónico: srjhe@azores.gov.pt\neDelivery Gateway (URL): https://www.acingov.pt\nFunção da Organização: Adquirente\nNorma jurídica da Entidade Adjudicante: Organismo de direito público\nÁrea de atividade da Autoridade Adjudicante: Serviços públicos das administrações públicas\n\n2 - JORNAL OFICIAL DA UNIÃO EUROPEIA\nO procedimento a que este anúncio diz respeito também é publicitado no Jornal Oficial da União Europeia? Não\n\n3 - AVISO\nModelo de Anúncio: Concurso público\nData de Envio do Anúncio: 15-10-2025\n\n5 - PROCESSO\nTipo de Procedimento: Concurso público\nPreço base do procedimento: Sim\nValor do preço base do procedimento: 230.000,00 EUR\nProcedimento com lotes? Não\n\n6 - OBJETO DO CONTRATO\nNúmero de referência interna: CCP/2025/20\nDesignação do contrato: EMPREITADA DE CONSTRUÇÃO DE MORADIA NA RUA FORMOSA, 6, FREGUESIA DE NOSSA SENHORA DO ROSÁRIO, CONCELHO DA LAGOA, ILHA DE SÃO MIGUEL\nDescrição: EMPREITADA DE CONSTRUÇÃO DE MORADIA NA RUA FORMOSA, 6, FREGUESIA DE NOSSA SENHORA DO ROSÁRIO, CONCELHO DA LAGOA, ILHA DE SÃO MIGUEL\nTipo de Contrato Principal: Empreitada de Obras Públicas\nTipo de Contrato: Empreitada de Obras Públicas\nClassificação CPV (Vocabulário Comum para os Contratos Públicos)\nObjeto principal\nVocabulário Principal: 45211300\nPreço base s/IVA: 230.000,00 EUR\n\n7 - INDICAÇÕES ADICIONAIS\nO contrato envolve aquisição conjunta (satisfação de várias entidades)? Não\nO contrato é adjudicado por uma central de compras? Não\n\n8 - TÉCNICAS\nO concurso destina-se à celebração de um acordo-quadro? Inexistência de acordo-quadro\nÉ utilizado um leilão eletrónico? Não\nÉ adotada uma fase de negociação? Não\nSistema de Aquisição Dinâmico: Inexistência de sistema de aquisição dinâmico\n\n9 - LOCAL DA EXECUÇÃO DO CONTRATO\nLOCAL DA EXECUÇÃO DO CONTRATO (PROCEDIMENTO)\nPaís: Portugal\nNUT III: PT111\nLocalidade: Freguesia de Lagoa (Nossa Senhora do Rosário)\nDistrito: Região Autónoma dos Açores\nConcelho: Lagoa\nFreguesia: Freguesia de Lagoa (Nossa Senhora do Rosário)\n\n10 - PRAZO DE EXECUÇÃO DO CONTRATO\nPrazo de execução do contrato: 270 DIAS\nPrevisão de renovações: Não\n\n11 - FUNDOS EU\nTêm fundos EU? Não\n\n12 - DOCUMENTOS DE HABILITAÇÃO\nHabilitação para o exercício da atividade profissional: Sim\nTipo: Alvará\nDescrição: Alvará contendo as habilitações adequadas e necessárias à execução da obra a realizar, designadamente:\ni.a 1ª Subcategoria (Estruturas e elementos de betão) da 1ª Categoria, a qual tem de ser de classe que cubra o valor global da proposta, e integrar-se na categoria em que o tipo de obra se enquadra;\nii.As seguintes subcategorias em classe correspondente ao valor destes trabalhos na sua proposta e integrar-se na categoria em que o tipo de obra se enquadra:\n1ª Categoria (Edifícios e Património Construído)\n4ª Subcategoria (Alvenarias, rebocos e assentamento de cantarias)\n5ª Subcategoria (Estuques, pinturas e outros revestimentos)\n6ª Subcategoria (Carpintarias)\n7ª Subcategoria (Trabalhos em perfis não estruturais)\n8ª Subcategoria (Canalizações e condutas em edifícios)\n4ª Categoria (Instalações Elétricas e Mecânicas)\n1ª Subcategoria (Instalações elétricas de utilização de baixa tensão com potência até 50 kVA)\n9ª Subcategoria (Infraestruturas de telecomunicações)\n14ª Subcategoria (Redes e ramais de distribuição de gás, instalações e aparelhos a gás)\n5ª Categoria (Outros Trabalhos)\n1ª Subcategoria (Demolições)\n11ª Subcategoria (Impermeabilizações e isolamentos)\n\n13 - CONDIÇÕES DE APRESENTAÇÃO\nPlataforma eletrónica utilizada pela entidade adjudicante: ACIN\nURL para Apresentação: https://www.acingov.pt\nAdmissibilidade da apresentação de propostas variantes: Não autorizado\nPrazo para apresentação das propostas: 14-11-2025 23:59\nPrazo durante o qual os concorrentes são obrigados a manter as respetivas propostas: 180 dias a contar do termo do prazo para a apresentação das propostas\nIndicação de Subcontratação na Proposta: A parte do contrato que o proponente tenciona subcontratar\n\n14 - PRESTAÇÃO DE CAUÇÃO\nPrestação de caução: Sim\nPercentagem: 2%\nDescrição da Garantia Exigida: O valor da caução é de 2.00% do preço contratual.\n\n15 - FORNECIMENTO DAS PEÇAS DO CONCURSO, APRESENTAÇÃO DE PEDIDOS DE PARTICIPAÇÃO E APRESENTAÇÃO DAS PROPOSTAS\nLink para acesso às peças do concurso (URL): https://www.acingov.pt/acingovprod/2/zonaPublica/zona_publica_c/donwloadProcedurePiece/OTg1NDU0\n\n20 - OUTROS REQUISITOS\nInformação sobre contratos reservados. Aplica-se a contratos reservados (54º-A)? Não\n\n21 - CRITÉRIO DE ADJUDICAÇÃO\nMultifator: Sim\nFator: \nNome: Outros\nOutro Nome: K1 - Preço - 60%\nPonderação: 60%\nSubfatores: Não\nFator: \nNome: Outros\nOutro Nome: K2-Qualidade Técnica da Proposta - 40%\nPonderação: 40%\nSubfatores: Não\n\n24 - CONDIÇÕES DO CONTRATO\nFaturação Eletrónica: Permitido\nObrigação de Subcontratação:\nCódigo da Obrigação de Subcontratação: Não é aplicável nenhuma obrigação de subcontratação.\n\n25 - COMPRA PÚBLICA ESTRATÉGICA\nCompra Pública Estratégica: Inexistência de contratação pública estratégica\n\n26 - INFORMAÇÕES ADICIONAIS\nContrato adequado para PME: Não\nCobertura ACP (Acordo dos Contratos Públicos da Organização Mundial do Comércio): Não\n\n27 - IDENTIFICAÇÃO E CONTACTOS DO ÓRGÃO DE RECURSOS ADMINISTRATIVOS\nDesignação: Secretaria Regional da Juventude, Habitação e Emprego\nEndereço: Rua Dr. Bruno Tavares Carreiro s/n\nCódigo postal: 9500-119\nLocalidade: Ponta Delgada\nTelefone: 296308000\nFax: \nEndereço eletrónico: srjhe@azores.gov.pt\nPrazo de interposição do recurso: 10 dias\n\n28 - IDENTIFICAÇÃO DO(S) AUTOR(ES) DE ANÚNCIO\nNome: Márcio Patricio Medeiros Almeida\nCargo: Técnico Superior\n419658801",
    "nipc": "600087549",
    "distrito": "Região Autónoma dos Açores",
    "concelho": "Todos",
    "freguesia": "Todas",
    "site": "https://portal.azores.gov.pt/web/srjhe",
    "email": "srjhe@azores.gov.pt",
    "designacao_contrato": "EMPREITADA DE CONSTRUÇÃO DE MORADIA NA RUA FORMOSA, 6, FREGUESIA DE NOSSA SENHORA DO ROSÁRIO, CONCELHO DA LAGOA, ILHA DE SÃO MIGUEL",
    "descricao": "EMPREITADA DE CONSTRUÇÃO DE MORADIA NA RUA FORMOSA, 6, FREGUESIA DE NOSSA SENHORA DO ROSÁRIO, CONCELHO DA LAGOA, ILHA DE SÃO MIGUEL",
    "preco_base": "230.000,00 EUR",
    "prazo_execucao": "270 DIAS",
    "prazo_apresentacao_propostas": "14-11-2025 23:59",
    "fundos_eu": "Não",
    "plataforma_eletronica": "ACIN",
    "url_procedimento": "https://www.acingov.pt",
    "autor_nome": "Márcio Patricio Medeiros Almeida",
    "autor_cargo": "Técnico Superior"
  },
  {
    "numero_procedimento": "N/A",
    "entidade": "Centro de Formação Profissional da Indústria de Fundição",
    "link": "https://diariodarepublica.pt/dr/detalhe/contrato-publico/27267-940416181",
    "detalhes_completos": "1 - IDENTIFICAÇÃO E CONTACTOS DA ENTIDADE ADJUDICANTE\nDesignação da entidade adjudicante: Centro de Formação Profissional da Indústria de Fundição\nNIPC: 501957910\nServiço/Órgão/Pessoa de contacto: Júri\nEndereço: Rua Delfim Ferreira, 800/840\nCódigo postal: 4100-199\nLocalidade: PORTO\nPaís: Portugal\nNUT III: PT11A\nDistrito: Porto\nConcelho: Porto\nFreguesia: Freguesia de Ramalde\nTelefone: 226175760\nFax: 226103160\nEndereço da Entidade (URL): www.cinfu.pt\nEndereço Eletrónico: fernando.barbosa@cinfu.pt\neDelivery Gateway (URL): https://www.acingov.pt\nFunção da Organização: Adquirente\nSubfunção da Organização: Organização cujo orçamento é utilizado para pagar o contrato; Organização que executa o pagamento; Organização que fornece informações adicionais sobre o processo de adjudicação; Organização que fornece mais informações sobre os prazos dos procedimentos de recurso; Organização responsável pelo tratamento das propostas; Organização que recebe as propostas; Organização que fornece mais informações sobre os procedimentos de recurso; Organização que assina o contrato\nNorma jurídica da Entidade Adjudicante: Organismo de direito público, controlado por uma autoridade da administração central\nÁrea de atividade da Autoridade Adjudicante: Serviços públicos das administrações públicas\n\n2 - JORNAL OFICIAL DA UNIÃO EUROPEIA\nO procedimento a que este anúncio diz respeito também é publicitado no Jornal Oficial da União Europeia? Não\n\n3 - AVISO\nModelo de Anúncio: Concurso público\nData de Envio do Anúncio: 15-10-2025\n\n5 - PROCESSO\nTipo de Procedimento: Concurso público\nPreço base do procedimento: Sim\nValor do preço base do procedimento: 75.000,00 EUR\nProcedimento com lotes? Não\n\n6 - OBJETO DO CONTRATO\nNúmero de referência interna: PRR 27/2025\nDesignação do contrato: Fornecimento e instalação de Computadores para Softwares de CAD/CAM e Indústria 4.0\nDescrição: Fornecimento e instalação de Computadores para Softwares de CAD/CAM e Indústria 4.0\nTipo de Contrato Principal: Aquisição de Bens Móveis\nTipo de Contrato: Aquisição de Bens Móveis\nClassificação CPV (Vocabulário Comum para os Contratos Públicos)\nObjeto principal\nVocabulário Principal: 30213300\nPreço base s/IVA: 75.000,00 EUR\n\n7 - INDICAÇÕES ADICIONAIS\nO contrato envolve aquisição conjunta (satisfação de várias entidades)? Não\nO contrato é adjudicado por uma central de compras? Não\n\n8 - TÉCNICAS\nO concurso destina-se à celebração de um acordo-quadro? Inexistência de acordo-quadro\nÉ utilizado um leilão eletrónico? Não\nÉ adotada uma fase de negociação? Não\nSistema de Aquisição Dinâmico: Inexistência de sistema de aquisição dinâmico\n\n9 - LOCAL DA EXECUÇÃO DO CONTRATO\nLOCAL DA EXECUÇÃO DO CONTRATO (PROCEDIMENTO)\nPaís: Portugal\nNUT III: PT11A\nLocalidade: Freguesia de Ramalde\nDistrito: Porto\nConcelho: Porto\nFreguesia: Freguesia de Ramalde\n\n10 - PRAZO DE EXECUÇÃO DO CONTRATO\nPrazo de execução do contrato: 28 DIAS\nPrevisão de renovações: Não\n\n11 - FUNDOS EU\nTêm fundos EU? Sim\n\n12 - DOCUMENTOS DE HABILITAÇÃO\nHabilitação para o exercício da atividade profissional: Não\n\n13 - CONDIÇÕES DE APRESENTAÇÃO\nPlataforma eletrónica utilizada pela entidade adjudicante: ACIN\nURL para Apresentação: https://www.acingov.pt\nAdmissibilidade da apresentação de propostas variantes: Não autorizado\nPrazo para apresentação das propostas: 30-10-2025 23:59\nPrazo durante o qual os concorrentes são obrigados a manter as respetivas propostas: 66 dias a contar do termo do prazo para a apresentação das propostas\nIndicação de Subcontratação na Proposta: Inexistência de indicação de subcontratação\n\n14 - PRESTAÇÃO DE CAUÇÃO\nPrestação de caução: Não\n\n15 - FORNECIMENTO DAS PEÇAS DO CONCURSO, APRESENTAÇÃO DE PEDIDOS DE PARTICIPAÇÃO E APRESENTAÇÃO DAS PROPOSTAS\nLink para acesso às peças do concurso (URL): https://www.acingov.pt/acingovprod/2/zonaPublica/zona_publica_c/donwloadProcedurePiece/OTg1OTY4\n\n20 - OUTROS REQUISITOS\nInformação sobre contratos reservados. Aplica-se a contratos reservados (54º-A)? Não\n\n21 - CRITÉRIO DE ADJUDICAÇÃO\nMultifator: Sim\nFator: \nNome: Preço\nPonderação: 45%\nSubfatores: Não\nFator: \nNome: Outros\nOutro Nome: Qualidade dos materiais e equipamentos\nPonderação: 35%\nSubfatores: Sim\nSubfatores: \nNome: Valor técnico\nPonderação : 100%; \nFator: \nNome: Outros\nOutro Nome: Assistência técnica\nPonderação: 10%\nSubfatores: Sim\nSubfatores: \nNome: Tempo de resposta em caso de avaria\nPonderação : 60%; \nNome: Prestada por técnicos qualificados do fornecedor e assegurada pelo fornecedor durante e após a validade da garantia.\nPonderação : 20%; \nNome: Custos previstos para assistência técnica e resolução de avarias, durante e após a validade da garantia\nPonderação : 20%; \nFator: \nNome: Outros\nOutro Nome: Sustentabilidade Ambiental\nPonderação: 10%\nSubfatores: Sim\nSubfatores: \nNome: Certificação ambiental\nPonderação : 25%; \nNome: Certificação dos equipamentos (Blue Angel, Nordic Swan, EPEAT, TCO certified, Rótulo Ecológico da EU, ou equivalente)\nPonderação : 25%; \nNome: Definição dos níveis máximos de consumo energético\nPonderação : 25%; \nNome: Plano de recolha, tratamento de reciclagem/reutilização de equipamentos em fim de vida\nPonderação : 25%; \n\n24 - CONDIÇÕES DO CONTRATO\nFaturação Eletrónica: Necessário\nObrigação de Subcontratação:\nCódigo da Obrigação de Subcontratação: Não é aplicável nenhuma obrigação de subcontratação.\n\n25 - COMPRA PÚBLICA ESTRATÉGICA\nCompra Pública Estratégica: Inexistência de contratação pública estratégica\n\n26 - INFORMAÇÕES ADICIONAIS\nContrato adequado para PME: Sim\nCobertura ACP (Acordo dos Contratos Públicos da Organização Mundial do Comércio): Não\n\n27 - IDENTIFICAÇÃO E CONTACTOS DO ÓRGÃO DE RECURSOS ADMINISTRATIVOS\nDesignação: Conselho de Administração\nEndereço: Rua Delfim Ferreira, 800/840\nCódigo postal: 4100-199\nLocalidade: PORTO\nTelefone: 226175760\nFax: \nEndereço eletrónico: helena.oliveira@cinfu.pt\nPrazo de interposição do recurso: 5 dias\n\n28 - IDENTIFICAÇÃO DO(S) AUTOR(ES) DE ANÚNCIO\nNome: Paula Alexandra Martins dos Santos de Macedo Teixeira\nCargo: Presidente do Conselho de Administração\n419661539",
    "nipc": "501957910",
    "distrito": "Porto",
    "concelho": "Porto",
    "freguesia": "Freguesia de Ramalde",
    "site": "www.cinfu.pt",
    "email": "fernando.barbosa@cinfu.pt",
    "designacao_contrato": "Fornecimento e instalação de Computadores para Softwares de CAD/CAM e Indústria 4.0",
    "descricao": "Fornecimento e instalação de Computadores para Softwares de CAD/CAM e Indústria 4.0",
    "preco_base": "75.000,00 EUR",
    "prazo_execucao": "28 DIAS",
    "prazo_apresentacao_propostas": "30-10-2025 23:59",
    "fundos_eu": "Sim",
    "plataforma_eletronica": "ACIN",
    "url_procedimento": "https://www.acingov.pt",
    "autor_nome": "Paula Alexandra Martins dos Santos de Macedo Teixeira",
    "autor_cargo": "Presidente do Conselho de Administração"
  },
  {
    "numero_procedimento": "N/A",
    "entidade": "Centro de Formação Profissional da Indústria de Fundição",
    "link": "https://diariodarepublica.pt/dr/detalhe/contrato-publico/27269-940416187",
    "detalhes_completos": "1 - IDENTIFICAÇÃO E CONTACTOS DA ENTIDADE ADJUDICANTE\nDesignação da entidade adjudicante: Centro de Formação Profissional da Indústria de Fundição\nNIPC: 501957910\nServiço/Órgão/Pessoa de contacto: Júri\nEndereço: Rua Delfim Ferreira, 800/840\nCódigo postal: 4100-199\nLocalidade: PORTO\nPaís: Portugal\nNUT III: PT11A\nDistrito: Porto\nConcelho: Porto\nFreguesia: Freguesia de Ramalde\nTelefone: 226175760\nFax: 226103160\nEndereço da Entidade (URL): www.cinfu.pt\nEndereço Eletrónico: fernando.barbosa@cinfu.pt\neDelivery Gateway (URL): https://www.acingov.pt\nFunção da Organização: Adquirente\nSubfunção da Organização: Organização cujo orçamento é utilizado para pagar o contrato; Organização que executa o pagamento; Organização que fornece informações adicionais sobre o processo de adjudicação; Organização que fornece mais informações sobre os prazos dos procedimentos de recurso; Organização responsável pelo tratamento das propostas; Organização que recebe as propostas; Organização que fornece mais informações sobre os procedimentos de recurso; Organização que assina o contrato\nNorma jurídica da Entidade Adjudicante: Organismo de direito público, controlado por uma autoridade da administração central\nÁrea de atividade da Autoridade Adjudicante: Serviços públicos das administrações públicas\n\n2 - JORNAL OFICIAL DA UNIÃO EUROPEIA\nO procedimento a que este anúncio diz respeito também é publicitado no Jornal Oficial da União Europeia? Não\n\n3 - AVISO\nModelo de Anúncio: Concurso público\nData de Envio do Anúncio: 15-10-2025\n\n5 - PROCESSO\nTipo de Procedimento: Concurso público\nPreço base do procedimento: Sim\nValor do preço base do procedimento: 20.000,00 EUR\nProcedimento com lotes? Não\n\n6 - OBJETO DO CONTRATO\nNúmero de referência interna: PRR 29/2025\nDesignação do contrato: Fornecimento de uma Máquina de medição e ajuste de ferramentas de corte\nDescrição: Fornecimento de uma Máquina de medição e ajuste de ferramentas de corte\nTipo de Contrato Principal: Aquisição de Bens Móveis\nTipo de Contrato: Aquisição de Bens Móveis\nClassificação CPV (Vocabulário Comum para os Contratos Públicos)\nObjeto principal\nVocabulário Principal: 38424000\nPreço base s/IVA: 20.000,00 EUR\n\n7 - INDICAÇÕES ADICIONAIS\nO contrato envolve aquisição conjunta (satisfação de várias entidades)? Não\nO contrato é adjudicado por uma central de compras? Não\n\n8 - TÉCNICAS\nO concurso destina-se à celebração de um acordo-quadro? Inexistência de acordo-quadro\nÉ utilizado um leilão eletrónico? Não\nÉ adotada uma fase de negociação? Não\nSistema de Aquisição Dinâmico: Inexistência de sistema de aquisição dinâmico\n\n9 - LOCAL DA EXECUÇÃO DO CONTRATO\nLOCAL DA EXECUÇÃO DO CONTRATO (PROCEDIMENTO)\nPaís: Portugal\nNUT III: PT11A\nLocalidade: Freguesia de Ramalde\nDistrito: Porto\nConcelho: Porto\nFreguesia: Freguesia de Ramalde\n\n10 - PRAZO DE EXECUÇÃO DO CONTRATO\nPrazo de execução do contrato: 35 DIAS\nPrevisão de renovações: Não\n\n11 - FUNDOS EU\nTêm fundos EU? Sim\n\n12 - DOCUMENTOS DE HABILITAÇÃO\nHabilitação para o exercício da atividade profissional: Não\n\n13 - CONDIÇÕES DE APRESENTAÇÃO\nPlataforma eletrónica utilizada pela entidade adjudicante: ACIN\nURL para Apresentação: https://www.acingov.pt\nAdmissibilidade da apresentação de propostas variantes: Não autorizado\nPrazo para apresentação das propostas: 27-10-2025 23:59\nPrazo durante o qual os concorrentes são obrigados a manter as respetivas propostas: 66 dias a contar do termo do prazo para a apresentação das propostas\nIndicação de Subcontratação na Proposta: Inexistência de indicação de subcontratação\n\n14 - PRESTAÇÃO DE CAUÇÃO\nPrestação de caução: Não\n\n15 - FORNECIMENTO DAS PEÇAS DO CONCURSO, APRESENTAÇÃO DE PEDIDOS DE PARTICIPAÇÃO E APRESENTAÇÃO DAS PROPOSTAS\nLink para acesso às peças do concurso (URL): https://www.acingov.pt/acingovprod/2/zonaPublica/zona_publica_c/donwloadProcedurePiece/OTg2MDA1\n\n20 - OUTROS REQUISITOS\nInformação sobre contratos reservados. Aplica-se a contratos reservados (54º-A)? Não\n\n21 - CRITÉRIO DE ADJUDICAÇÃO\nMultifator: Sim\nFator: \nNome: Preço\nPonderação: 35%\nSubfatores: Não\nFator: \nNome: Qualidade\nPonderação: 40%\nSubfatores: Sim\nSubfatores: \nNome: Campo de medição em Z(Altura)\nPonderação : 35%; \nNome: Campo de medição em X(Diâmetro)\nPonderação : 35%; \nNome: Prazo de entrega\nPonderação : 30%; \nFator: \nNome: Outros\nOutro Nome: Assistência técnica\nPonderação: 15%\nSubfatores: Sim\nSubfatores: \nNome: Tempo de resposta em caso de avaria\nPonderação : 50%; \nNome: Custo de reparação em caso de avaria (por hora)\nPonderação : 50%; \nFator: \nNome: Outros\nOutro Nome: Formação\nPonderação: 5%\nSubfatores: Não\nFator: \nNome: Outros\nOutro Nome: Sustentabilidade Ambiental\nPonderação: 5%\nSubfatores: Sim\nSubfatores: \nNome: Certificação ambiental\nPonderação : 100%; \n\n24 - CONDIÇÕES DO CONTRATO\nFaturação Eletrónica: Necessário\nObrigação de Subcontratação:\nCódigo da Obrigação de Subcontratação: Não é aplicável nenhuma obrigação de subcontratação.\n\n25 - COMPRA PÚBLICA ESTRATÉGICA\nCompra Pública Estratégica: Inexistência de contratação pública estratégica\n\n26 - INFORMAÇÕES ADICIONAIS\nContrato adequado para PME: Sim\nCobertura ACP (Acordo dos Contratos Públicos da Organização Mundial do Comércio): Não\n\n27 - IDENTIFICAÇÃO E CONTACTOS DO ÓRGÃO DE RECURSOS ADMINISTRATIVOS\nDesignação: Conselho de Administração\nEndereço: Rua Delfim Ferreira, 800/840\nCódigo postal: 4100-199\nLocalidade: PORTO\nTelefone: 226175760\nFax: \nEndereço eletrónico: helena.oliveira@cinfu.pt\nPrazo de interposição do recurso: 5 dias\n\n28 - IDENTIFICAÇÃO DO(S) AUTOR(ES) DE ANÚNCIO\nNome: Paula Alexandra Martins dos Santos de Macedo Teixeira\nCargo: Presidente do Conselho de Administração\n419661977",
    "nipc": "501957910",
    "distrito": "Porto",
    "concelho": "Porto",
    "freguesia": "Freguesia de Ramalde",
    "site": "www.cinfu.pt",
    "email": "fernando.barbosa@cinfu.pt",
    "designacao_contrato": "Fornecimento de uma Máquina de medição e ajuste de ferramentas de corte",
    "descricao": "Fornecimento de uma Máquina de medição e ajuste de ferramentas de corte",
    "preco_base": "20.000,00 EUR",
    "prazo_execucao": "35 DIAS",
    "prazo_apresentacao_propostas": "27-10-2025 23:59",
    "fundos_eu": "Sim",
    "plataforma_eletronica": "ACIN",
    "url_procedimento": "https://www.acingov.pt",
    "autor_nome": "Paula Alexandra Martins dos Santos de Macedo Teixeira",
    "autor_cargo": "Presidente do Conselho de Administração"
  },
  {
    "numero_procedimento": "N/A",
    "entidade": "Centro de Formação Profissional da Indústria de Fundição",
    "link": "https://diariodarepublica.pt/dr/detalhe/contrato-publico/27272-940416189",
    "detalhes_completos": "1 - IDENTIFICAÇÃO E CONTACTOS DA ENTIDADE ADJUDICANTE\nDesignação da entidade adjudicante: Centro de Formação Profissional da Indústria de Fundição\nNIPC: 501957910\nServiço/Órgão/Pessoa de contacto: Júri\nEndereço: Rua Delfim Ferreira, 800/840\nCódigo postal: 4100-199\nLocalidade: PORTO\nPaís: Portugal\nNUT III: PT11A\nDistrito: Porto\nConcelho: Porto\nFreguesia: Freguesia de Ramalde\nTelefone: 226175760\nFax: 226103160\nEndereço da Entidade (URL): www.cinfu.pt\nEndereço Eletrónico: fernando.barbosa@cinfu.pt\neDelivery Gateway (URL): https://www.acingov.pt\nFunção da Organização: Adquirente\nSubfunção da Organização: Organização cujo orçamento é utilizado para pagar o contrato; Organização que executa o pagamento; Organização que fornece informações adicionais sobre o processo de adjudicação; Organização que fornece mais informações sobre os prazos dos procedimentos de recurso; Organização responsável pelo tratamento das propostas; Organização que recebe as propostas; Organização que fornece mais informações sobre os procedimentos de recurso; Organização que assina o contrato\nNorma jurídica da Entidade Adjudicante: Organismo de direito público, controlado por uma autoridade da administração central\nÁrea de atividade da Autoridade Adjudicante: Serviços públicos das administrações públicas\n\n2 - JORNAL OFICIAL DA UNIÃO EUROPEIA\nO procedimento a que este anúncio diz respeito também é publicitado no Jornal Oficial da União Europeia? Não\n\n3 - AVISO\nModelo de Anúncio: Concurso público\nData de Envio do Anúncio: 15-10-2025\n\n5 - PROCESSO\nTipo de Procedimento: Concurso público\nPreço base do procedimento: Sim\nValor do preço base do procedimento: 35.000,00 EUR\nProcedimento com lotes? Não\n\n6 - OBJETO DO CONTRATO\nNúmero de referência interna: PRR 30/2025\nDesignação do contrato: Fornecimento de um Empilhador elétrico\nDescrição: Fornecimento de um Empilhador elétrico\nTipo de Contrato Principal: Aquisição de Bens Móveis\nTipo de Contrato: Aquisição de Bens Móveis\nClassificação CPV (Vocabulário Comum para os Contratos Públicos)\nObjeto principal\nVocabulário Principal: 42415110\nPreço base s/IVA: 35.000,00 EUR\n\n7 - INDICAÇÕES ADICIONAIS\nO contrato envolve aquisição conjunta (satisfação de várias entidades)? Não\nO contrato é adjudicado por uma central de compras? Não\n\n8 - TÉCNICAS\nO concurso destina-se à celebração de um acordo-quadro? Inexistência de acordo-quadro\nÉ utilizado um leilão eletrónico? Não\nÉ adotada uma fase de negociação? Não\nSistema de Aquisição Dinâmico: Inexistência de sistema de aquisição dinâmico\n\n9 - LOCAL DA EXECUÇÃO DO CONTRATO\nLOCAL DA EXECUÇÃO DO CONTRATO (PROCEDIMENTO)\nPaís: Portugal\nNUT III: PT11A\nLocalidade: Freguesia de Ramalde\nDistrito: Porto\nConcelho: Porto\nFreguesia: Freguesia de Ramalde\n\n10 - PRAZO DE EXECUÇÃO DO CONTRATO\nPrazo de execução do contrato: 35 DIAS\nPrevisão de renovações: Não\n\n11 - FUNDOS EU\nTêm fundos EU? Sim\n\n12 - DOCUMENTOS DE HABILITAÇÃO\nHabilitação para o exercício da atividade profissional: Não\n\n13 - CONDIÇÕES DE APRESENTAÇÃO\nPlataforma eletrónica utilizada pela entidade adjudicante: ACIN\nURL para Apresentação: https://www.acingov.pt\nAdmissibilidade da apresentação de propostas variantes: Não autorizado\nPrazo para apresentação das propostas: 27-10-2025 23:59\nPrazo durante o qual os concorrentes são obrigados a manter as respetivas propostas: 66 dias a contar do termo do prazo para a apresentação das propostas\nIndicação de Subcontratação na Proposta: Inexistência de indicação de subcontratação\n\n14 - PRESTAÇÃO DE CAUÇÃO\nPrestação de caução: Não\n\n15 - FORNECIMENTO DAS PEÇAS DO CONCURSO, APRESENTAÇÃO DE PEDIDOS DE PARTICIPAÇÃO E APRESENTAÇÃO DAS PROPOSTAS\nLink para acesso às peças do concurso (URL): https://www.acingov.pt/acingovprod/2/zonaPublica/zona_publica_c/donwloadProcedurePiece/OTg2MDE2\n\n20 - OUTROS REQUISITOS\nInformação sobre contratos reservados. Aplica-se a contratos reservados (54º-A)? Não\n\n21 - CRITÉRIO DE ADJUDICAÇÃO\nMultifator: Sim\nFator: \nNome: Preço\nPonderação: 40%\nSubfatores: Não\nFator: \nNome: Qualidade\nPonderação: 30%\nSubfatores: Sim\nSubfatores: \nNome: Capacidade da bateria\nPonderação : 30%; \nNome: Capacidade de carregador\nPonderação : 10%; \nNome: Capacidade de carga da bateria\nPonderação : 10%; \nNome: Autonomia\nPonderação : 10%; \nNome: Capacidade de elevação de carga\nPonderação : 10%; \nNome: Elevação livre\nPonderação : 20%; \nNome: Elevação máxima\nPonderação : 10%; \nFator: \nNome: Outros\nOutro Nome: Segurança\nPonderação: 15%\nSubfatores: Não\nFator: \nNome: Outros\nOutro Nome: Assistência técnica\nPonderação: 10%\nSubfatores: Sim\nSubfatores: \nNome: Periocidade de manutenção\nPonderação : 50%; \nNome: Tempo de resposta a avarias\nPonderação : 50%; \nFator: \nNome: Outros\nOutro Nome: Sustentabilidade Ambiental\nPonderação: 5%\nSubfatores: Sim\nSubfatores: \nNome: Certificação ambiental\nPonderação : 50%; \nNome: Eficiência energética\nPonderação : 50%; \n\n24 - CONDIÇÕES DO CONTRATO\nFaturação Eletrónica: Necessário\nObrigação de Subcontratação:\nCódigo da Obrigação de Subcontratação: Não é aplicável nenhuma obrigação de subcontratação.\n\n25 - COMPRA PÚBLICA ESTRATÉGICA\nCompra Pública Estratégica: Inexistência de contratação pública estratégica\n\n26 - INFORMAÇÕES ADICIONAIS\nContrato adequado para PME: Sim\nCobertura ACP (Acordo dos Contratos Públicos da Organização Mundial do Comércio): Não\n\n27 - IDENTIFICAÇÃO E CONTACTOS DO ÓRGÃO DE RECURSOS ADMINISTRATIVOS\nDesignação: Conselho de Administração\nEndereço: Rua Delfim Ferreira, 800/840\nCódigo postal: 4100-199\nLocalidade: PORTO\nTelefone: 226175760\nFax: \nEndereço eletrónico: helena.oliveira@cinfu.pt\nPrazo de interposição do recurso: 5 dias\n\n28 - IDENTIFICAÇÃO DO(S) AUTOR(ES) DE ANÚNCIO\nNome: Paula Alexandra Martins dos Santos de Macedo Teixeira\nCargo: Presidente do Conselho de Administração\n419662032",
    "nipc": "501957910",
    "distrito": "Porto",
    "concelho": "Porto",
    "freguesia": "Freguesia de Ramalde",
    "site": "www.cinfu.pt",
    "email": "fernando.barbosa@cinfu.pt",
    "designacao_contrato": "Fornecimento de um Empilhador elétrico",
    "descricao": "Fornecimento de um Empilhador elétrico",
    "preco_base": "35.000,00 EUR",
    "prazo_execucao": "35 DIAS",
    "prazo_apresentacao_propostas": "27-10-2025 23:59",
    "fundos_eu": "Sim",
    "plataforma_eletronica": "ACIN",
    "url_procedimento": "https://www.acingov.pt",
    "autor_nome": "Paula Alexandra Martins dos Santos de Macedo Teixeira",
    "autor_cargo": "Presidente do Conselho de Administração"
  },
  {
    "numero_procedimento": "N/A",
    "entidade": "Fundação Cultursintra, FP",
    "link": "https://diariodarepublica.pt/dr/detalhe/contrato-publico/27277-940416192",
    "detalhes_completos": "1 - IDENTIFICAÇÃO E CONTACTOS DA ENTIDADE ADJUDICANTE\nDesignação da entidade adjudicante: Fundação Cultursintra, FP\nNIPC: 503888729\nServiço/Órgão/Pessoa de contacto: Direção Administrativa e Financeira\nEndereço: Rua Barbosa du Bocage, 5 - Quinta da Regaleira\nCódigo postal: 2710-567\nLocalidade: Lisboa\nPaís: Portugal\nNUT III: PT170\nDistrito: Lisboa\nConcelho: Sintra\nFreguesia: União das Freguesias de Sintra (Santa Maria e São Miguel, São Martinho e São Pedro de Penaferrim)\nTelefone: 219106650\nFax: 219106659\nEndereço da Entidade (URL): www.cultursintra.pt\nEndereço Eletrónico: geral@cultursintra.pt\neDelivery Gateway (URL): https://community.vortal.biz/public/\nFunção da Organização: Adquirente\nNorma jurídica da Entidade Adjudicante: Organismo de direito público\nÁrea de atividade da Autoridade Adjudicante: Serviços públicos das administrações públicas\n\n2 - JORNAL OFICIAL DA UNIÃO EUROPEIA\nO procedimento a que este anúncio diz respeito também é publicitado no Jornal Oficial da União Europeia? Sim\n\n3 - AVISO\nModelo de Anúncio: Concurso público\nData de Envio do Anúncio: 13-10-2025\n\n5 - PROCESSO\nTipo de Procedimento: Concurso público\nPreço base do procedimento: Sim\nValor do preço base do procedimento: 406.000,00 EUR\nProcedimento com lotes? Não\n\n6 - OBJETO DO CONTRATO\nNúmero de referência interna: 2025-086 - Serviços de vigilância e segurança 2026\nDesignação do contrato: 2025-086 - Aquisição de serviços de vigilância e segurança das instalações da Fundação Cultursintra FP, para o ano de 2026\nDescrição: Aquisição de serviços de vigilância e segurança das instalações da Fundação Cultursintra FP, para o ano de 2026\nOpções: Não\nTipo de Contrato Principal: Aquisição de Serviços\nTipo de Contrato: Aquisição de Serviços\nClassificação CPV (Vocabulário Comum para os Contratos Públicos)\nObjeto principal\nVocabulário Principal: 79714000\nPreço base s/IVA: 406.000,00 EUR\n\n7 - INDICAÇÕES ADICIONAIS\nO contrato envolve aquisição conjunta (satisfação de várias entidades)? Não\nO contrato é adjudicado por uma central de compras? Não\n\n8 - TÉCNICAS\nO concurso destina-se à celebração de um acordo-quadro? Inexistência de acordo-quadro\nÉ utilizado um leilão eletrónico? Não\nÉ adotada uma fase de negociação? Não\nSistema de Aquisição Dinâmico: Inexistência de sistema de aquisição dinâmico\n\n9 - LOCAL DA EXECUÇÃO DO CONTRATO\nLOCAL DA EXECUÇÃO DO CONTRATO (PROCEDIMENTO)\nPaís: Portugal\nNUT III: PT170\nLocalidade: Lisboa\nDistrito: Lisboa\nConcelho: Sintra\nFreguesia: Todas\n\n10 - PRAZO DE EXECUÇÃO DO CONTRATO\nPrazo de execução do contrato: 12 MESES\nPrevisão de renovações: Não\n\n11 - FUNDOS EU\nTêm fundos EU? Não\n\n12 - DOCUMENTOS DE HABILITAÇÃO\nHabilitação para o exercício da atividade profissional: Sim\nTipo: Alvará\nDescrição: - Títulos (Alvarás) para os tipos A e C, emitidos pela entidade pública habilitada para o efeito no país de origem, conforme disposto no DL 34/2013, de 21 de fevereiro; \n- Registo na Autoridade Nacional de Emergência e Proteção Civil para atividades de comercialização ou manutenção de equipamentos e sistemas de segurança contra incêndios em edifícios (SCIE), constantes da Portaria n.º 773/2009, de 21 de julho, na sua redação em vigor.\n\n13 - CONDIÇÕES DE APRESENTAÇÃO\nPlataforma eletrónica utilizada pela entidade adjudicante: VORTAL\nURL para Apresentação: https://community.vortal.biz/public/\nAdmissibilidade da apresentação de propostas variantes: Não autorizado\nPrazo para apresentação das propostas: 12-11-2025 17:00\nPrazo durante o qual os concorrentes são obrigados a manter as respetivas propostas: 66 dias a contar do termo do prazo para a apresentação das propostas\nApresentação de Catálogo Eletrónico: Permitido\nIndicação de Subcontratação na Proposta: Inexistência de indicação de subcontratação\n\n14 - PRESTAÇÃO DE CAUÇÃO\nPrestação de caução: Não\n\n15 - FORNECIMENTO DAS PEÇAS DO CONCURSO, APRESENTAÇÃO DE PEDIDOS DE PARTICIPAÇÃO E APRESENTAÇÃO DAS PROPOSTAS\nLink para acesso às peças do concurso (URL): https://community.vortal.biz/Public/public-tender-documents/alZTWjVhRmFlaWNKWnZzSzNCRVlEN1N0TUQyTFp1L0ZMeEFOWnlMS2RnOUl0cm9tZ0lBRDhRdkhQSWFLejVSZEh3ZDI3QVAzQlE5Mk0yNmcxOGVVekE9PUskJXQj\n\n20 - OUTROS REQUISITOS\nInformação sobre contratos reservados. Aplica-se a contratos reservados (54º-A)? Não\n\n21 - CRITÉRIO DE ADJUDICAÇÃO\nMultifator: Não\nMonofator:\nNome: Preço\n\n24 - CONDIÇÕES DO CONTRATO\nFaturação Eletrónica: Permitido\nObrigação de Subcontratação:\nCódigo da Obrigação de Subcontratação: Não é aplicável nenhuma obrigação de subcontratação.\n\n25 - COMPRA PÚBLICA ESTRATÉGICA\nCompra Pública Estratégica: Inexistência de contratação pública estratégica\n\n26 - INFORMAÇÕES ADICIONAIS\nContrato adequado para PME: Sim\nCobertura ACP (Acordo dos Contratos Públicos da Organização Mundial do Comércio): Não\n\n27 - IDENTIFICAÇÃO E CONTACTOS DO ÓRGÃO DE RECURSOS ADMINISTRATIVOS\nDesignação: Presidente do Conselho Diretivo\nEndereço: Rua Barbosa du Bocage, 5\nCódigo postal: 2710-567\nLocalidade: Sintra\nTelefone: +351 219106650\nFax: +351 219106659\nEndereço eletrónico: geral@cultursintra.pt\n\n28 - IDENTIFICAÇÃO DO(S) AUTOR(ES) DE ANÚNCIO\nNome: Bruno Alexandre Nobre Parreira\nCargo: Presidente do Conselho Diretivo\n419650936",
    "nipc": "503888729",
    "distrito": "Lisboa",
    "concelho": "Sintra",
    "freguesia": "União das Freguesias de Sintra (Santa Maria e São Miguel, São Martinho e São Pedro de Penaferrim)",
    "site": "www.cultursintra.pt",
    "email": "geral@cultursintra.pt",
    "designacao_contrato": "2025-086 - Aquisição de serviços de vigilância e segurança das instalações da Fundação Cultursintra FP, para o ano de 2026",
    "descricao": "Aquisição de serviços de vigilância e segurança das instalações da Fundação Cultursintra FP, para o ano de 2026",
    "preco_base": "406.000,00 EUR",
    "prazo_execucao": "12 MESES",
    "prazo_apresentacao_propostas": "12-11-2025 17:00",
    "fundos_eu": "Não",
    "plataforma_eletronica": "VORTAL",
    "url_procedimento": "https://community.vortal.biz/public/",
    "autor_nome": "Bruno Alexandre Nobre Parreira",
    "autor_cargo": "Presidente do Conselho Diretivo"
  },
  {
    "numero_procedimento": "N/A",
    "entidade": "Unidade Local de Saúde de Braga, E. P. E.",
    "link": "https://diariodarepublica.pt/dr/detalhe/contrato-publico/27278-940416193",
    "detalhes_completos": "1 - IDENTIFICAÇÃO E CONTACTOS DA ENTIDADE ADJUDICANTE\nDesignação da entidade adjudicante: Unidade Local de Saúde de Braga, E. P. E.\nNIPC: 515545180\nEndereço: Sete Fontes – São Victor  \nCódigo postal: 4710-243\nLocalidade: Braga\nPaís: Portugal\nNUT III: PT112\nDistrito: Braga\nConcelho: Braga\nFreguesia: Todas\nTelefone: 220411150\nEndereço da Entidade (URL): https://www.hospitaldebraga.pt/\nEndereço Eletrónico: hospitaldebraga@arsnorte.min-saude.pt\neDelivery Gateway (URL): https://community.vortal.biz/public/\nFunção da Organização: Adquirente\nNorma jurídica da Entidade Adjudicante: Empresa pública\nÁrea de atividade da Autoridade Adjudicante: Saúde\n\n2 - JORNAL OFICIAL DA UNIÃO EUROPEIA\nO procedimento a que este anúncio diz respeito também é publicitado no Jornal Oficial da União Europeia? Não\n\n3 - AVISO\nModelo de Anúncio: Concurso público\nData de Envio do Anúncio: 15-10-2025\n\n5 - PROCESSO\nTipo de Procedimento: Concurso público\nPreço base do procedimento: Sim\nValor do preço base do procedimento: 152.640,00 EUR\nProcedimento com lotes? Não\n\n6 - OBJETO DO CONTRATO\nNúmero de referência interna: 5/04639/25\nDesignação do contrato: Aquisição de FUMARATO DIMETILO 240MG CAPS OR.\nDescrição: Aquisição de FUMARATO DIMETILO 240MG CAPS OR.\nTipo de Contrato Principal: Aquisição de Bens Móveis\nTipo de Contrato: Aquisição de Bens Móveis\nClassificação CPV (Vocabulário Comum para os Contratos Públicos)\nObjeto principal\nVocabulário Principal: 33600000\nPreço base s/IVA: 152.640,00 EUR\n\n7 - INDICAÇÕES ADICIONAIS\nO contrato envolve aquisição conjunta (satisfação de várias entidades)? Não\nO contrato é adjudicado por uma central de compras? Não\n\n8 - TÉCNICAS\nO concurso destina-se à celebração de um acordo-quadro? Inexistência de acordo-quadro\nÉ utilizado um leilão eletrónico? Não\nÉ adotada uma fase de negociação? Não\nSistema de Aquisição Dinâmico: Inexistência de sistema de aquisição dinâmico\n\n9 - LOCAL DA EXECUÇÃO DO CONTRATO\nLOCAL DA EXECUÇÃO DO CONTRATO (PROCEDIMENTO)\nPaís: Portugal\nNUT III: PT112\nLocalidade: Braga\nDistrito: Braga\nConcelho: Braga\nFreguesia: Todas\n\n10 - PRAZO DE EXECUÇÃO DO CONTRATO\nPrazo de execução do contrato: 3 MESES\nPrevisão de renovações: Não\n\n11 - FUNDOS EU\nTêm fundos EU? Não\n\n12 - DOCUMENTOS DE HABILITAÇÃO\nHabilitação para o exercício da atividade profissional: Não\n\n13 - CONDIÇÕES DE APRESENTAÇÃO\nPlataforma eletrónica utilizada pela entidade adjudicante: VORTAL\nURL para Apresentação: https://community.vortal.biz/public/\nAdmissibilidade da apresentação de propostas variantes: Não autorizado\nPrazo para apresentação das propostas: 26-10-2025 17:00\nPrazo durante o qual os concorrentes são obrigados a manter as respetivas propostas: 120 dias a contar do termo do prazo para a apresentação das propostas\nIndicação de Subcontratação na Proposta: Inexistência de indicação de subcontratação\n\n14 - PRESTAÇÃO DE CAUÇÃO\nPrestação de caução: Não\n\n15 - FORNECIMENTO DAS PEÇAS DO CONCURSO, APRESENTAÇÃO DE PEDIDOS DE PARTICIPAÇÃO E APRESENTAÇÃO DAS PROPOSTAS\nLink para acesso às peças do concurso (URL): https://community.vortal.biz/Public/public-tender-documents/YnFiTG1EcURwY3FvSDlzSW95YkRDKzN3TTNqL3gxUlVyRG40eFRhblZ6UGdFZVQ2THpYOXBxT2kxSkhnRHArMzJkNkY0anhYRzJ2cUY4WW5QUml3YXc9PVMxVzhL\n\n20 - OUTROS REQUISITOS\nInformação sobre contratos reservados. Aplica-se a contratos reservados (54º-A)? Não\n\n21 - CRITÉRIO DE ADJUDICAÇÃO\nMultifator: Não\nMonofator:\nNome: Preço\n\n24 - CONDIÇÕES DO CONTRATO\nFaturação Eletrónica: Permitido\nObrigação de Subcontratação:\nCódigo da Obrigação de Subcontratação: Não é aplicável nenhuma obrigação de subcontratação.\n\n25 - COMPRA PÚBLICA ESTRATÉGICA\nCompra Pública Estratégica: Inexistência de contratação pública estratégica\n\n26 - INFORMAÇÕES ADICIONAIS\nContrato adequado para PME: Sim\nCobertura ACP (Acordo dos Contratos Públicos da Organização Mundial do Comércio): Não\n\n27 - IDENTIFICAÇÃO E CONTACTOS DO ÓRGÃO DE RECURSOS ADMINISTRATIVOS\nDesignação: Unidade Local Saúde de Braga, E.P.E.\nEndereço: Sete Fontes- São Victor\nCódigo postal: 4710-243\nLocalidade: Braga\nTelefone: +351 253027000\nFax: +351 253027999\nEndereço eletrónico: hbraga@ulsb.min-saude.pt\n\n28 - IDENTIFICAÇÃO DO(S) AUTOR(ES) DE ANÚNCIO\nNome: Guilherme Alexandre\nCargo: Técnico Superior  Serviço de Gestão de Compras\n419655204",
    "nipc": "515545180",
    "distrito": "Braga",
    "concelho": "Braga",
    "freguesia": "Todas",
    "site": "https://www.hospitaldebraga.pt/",
    "email": "hospitaldebraga@arsnorte.min-saude.pt",
    "designacao_contrato": "Aquisição de FUMARATO DIMETILO 240MG CAPS OR.",
    "descricao": "Aquisição de FUMARATO DIMETILO 240MG CAPS OR.",
    "preco_base": "152.640,00 EUR",
    "prazo_execucao": "3 MESES",
    "prazo_apresentacao_propostas": "26-10-2025 17:00",
    "fundos_eu": "Não",
    "plataforma_eletronica": "VORTAL",
    "url_procedimento": "https://community.vortal.biz/public/",
    "autor_nome": "Guilherme Alexandre",
    "autor_cargo": "Técnico Superior Serviço de Gestão de Compras"
  },
  {
    "numero_procedimento": "N/A",
    "entidade": "Infraestruturas de Portugal, S. A.",
    "link": "https://diariodarepublica.pt/dr/detalhe/contrato-publico/27279-940416194",
    "detalhes_completos": "1 - IDENTIFICAÇÃO E CONTACTOS DA ENTIDADE ADJUDICANTE\nDesignação da entidade adjudicante: Infraestruturas de Portugal, S. A.\nNIPC: 503933813\nServiço/Órgão/Pessoa de contacto: Direção de Compras e Logística – Departamento de Gestão de Materiais – Unidade de Valorização de Materiais – Edifício 2\nEndereço: Praça da Portagem\nCódigo postal: 2809-013\nLocalidade: Almada\nPaís: Portugal\nNUT III: PT170\nDistrito: Setúbal\nConcelho: Almada\nFreguesia: União das Freguesias de Almada, Cova da Piedade, Pragal e Cacilhas\nTelefone: 212879000\nEndereço Eletrónico: vendas@infraestruturasdeportugal.pt\nFunção da Organização: Adquirente\nNorma jurídica da Entidade Adjudicante: Organismo de direito público\nÁrea de atividade da Entidade Adjudicante: Serviços ferroviários\n\n2 - JORNAL OFICIAL DA UNIÃO EUROPEIA\nO procedimento a que este anúncio diz respeito também é publicitado no Jornal Oficial da União Europeia? Não\n\n3 - AVISO\nModelo de Anúncio: Concurso público\nData de Envio do Anúncio: 15-10-2025\n\n5 - PROCESSO\nTipo de Procedimento: Concurso público\nPreço base do procedimento: Sim\nValor do preço base do procedimento: 31.850,00 EUR\nProcedimento com lotes? Não\n\n6 - OBJETO DO CONTRATO\nNúmero de referência interna: A162-25-VLM\nDesignação do contrato: Alienação de resíduos ferrosos\nDescrição: Os resíduos objeto da presente alienação encontram-se depositados em instalações no Complexo Logístico do Entroncamento, conforme descrito no número 2 do Caderno de Encargos - Parte II - Cláusulas Específicas\nTipo de Contrato Principal: Aquisição de Bens Móveis\nTipo de Contrato: Aquisição de Bens Móveis\nClassificação CPV (Vocabulário Comum para os Contratos Públicos)\nObjeto principal\nVocabulário Principal: 44000000\nPreço base s/IVA: 31.850,00 EUR\n\n7 - INDICAÇÕES ADICIONAIS\nO contrato envolve aquisição conjunta (satisfação de várias entidades)? Não\nO contrato é adjudicado por uma central de compras? Não\n\n8 - TÉCNICAS\nO concurso destina-se à celebração de um acordo-quadro? Inexistência de acordo-quadro\nÉ utilizado um leilão eletrónico? Não\nÉ adotada uma fase de negociação? Não\nSistema de Aquisição Dinâmico: Inexistência de sistema de aquisição dinâmico\n\n9 - LOCAL DA EXECUÇÃO DO CONTRATO\nLOCAL DA EXECUÇÃO DO CONTRATO (PROCEDIMENTO)\nPaís: Portugal\nNUT III: PT16H\nLocalidade: Fundão\nDistrito: Castelo Branco\nConcelho: Fundão\nFreguesia: Freguesia de Fatela\n\n10 - PRAZO DE EXECUÇÃO DO CONTRATO\nPrazo de execução do contrato: 1 MESES\nPrevisão de renovações: Não\n\n11 - FUNDOS EU\nTêm fundos EU? Não\n\n12 - DOCUMENTOS DE HABILITAÇÃO\nHabilitação para o exercício da atividade profissional: Não\n\n13 - CONDIÇÕES DE APRESENTAÇÃO\nPlataforma eletrónica utilizada pela entidade adjudicante: ANOGOV\nURL para Apresentação: https://www.anogov.com/infraestruturasdeportugal-ip/faces/app/dashboard.jsp/\nAdmissibilidade da apresentação de propostas variantes: Não autorizado\nPrazo para apresentação das propostas: 14-11-2025 17:00\nPrazo durante o qual os concorrentes são obrigados a manter as respetivas propostas: 120 dias a contar do termo do prazo para a apresentação das propostas\nApresentação de Catálogo Eletrónico: Não autorizado\nIndicação de Subcontratação na Proposta: Inexistência de indicação de subcontratação\n\n14 - PRESTAÇÃO DE CAUÇÃO\nPrestação de caução: Não\n\n15 - FORNECIMENTO DAS PEÇAS DO CONCURSO, APRESENTAÇÃO DE PEDIDOS DE PARTICIPAÇÃO E APRESENTAÇÃO DAS PROPOSTAS\nLink para acesso às peças do concurso (URL): https://www.anogov.com/infraestruturasdeportugal-ip/faces/app/dashboard.jsp/\n\n20 - OUTROS REQUISITOS\nInformação sobre contratos reservados. Aplica-se a contratos reservados (54º-A)? Não\n\n21 - CRITÉRIO DE ADJUDICAÇÃO\nMultifator: Não\nMonofator:\nNome: Preço\n\n24 - CONDIÇÕES DO CONTRATO\nFaturação Eletrónica: Permitido\nObrigação de Subcontratação:\nCódigo da Obrigação de Subcontratação: Não é aplicável nenhuma obrigação de subcontratação.\n\n25 - COMPRA PÚBLICA ESTRATÉGICA\nCompra Pública Estratégica: Inexistência de contratação pública estratégica\n\n26 - INFORMAÇÕES ADICIONAIS\nContrato adequado para PME: Sim\nCobertura ACP (Acordo dos Contratos Públicos da Organização Mundial do Comércio): Não\n\n27 - IDENTIFICAÇÃO E CONTACTOS DO ÓRGÃO DE RECURSOS ADMINISTRATIVOS\nDesignação: Conselho de Administração da Infraestruturas de Portugal, S.A.\nEndereço: Praça da Portagem\nCódigo postal: 2809-013\nLocalidade: Almada\nEndereço eletrónico: vendas@infraestruturasdeportugal.pt\n\n28 - IDENTIFICAÇÃO DO(S) AUTOR(ES) DE ANÚNCIO\nNome: Ricardo Correia\nCargo: Diretor do Departamento de Gestão de Materiais\n419659685",
    "nipc": "503933813",
    "distrito": "Setúbal",
    "concelho": "Almada",
    "freguesia": "União das Freguesias de Almada, Cova da Piedade, Pragal e Cacilhas",
    "site": null,
    "email": "vendas@infraestruturasdeportugal.pt",
    "designacao_contrato": "Alienação de resíduos ferrosos",
    "descricao": "Os resíduos objeto da presente alienação encontram-se depositados em instalações no Complexo Logístico do Entroncamento, conforme descrito no número 2 do Caderno de Encargos - Parte II - Cláusulas Específicas",
    "preco_base": "31.850,00 EUR",
    "prazo_execucao": "1 MESES",
    "prazo_apresentacao_propostas": "14-11-2025 17:00",
    "fundos_eu": "Não",
    "plataforma_eletronica": "ANOGOV",
    "url_procedimento": "https://www.anogov.com/infraestruturasdeportugal-ip/faces/app/dashboard.jsp/",
    "autor_nome": "Ricardo Correia",
    "autor_cargo": "Diretor do Departamento de Gestão de Materiais"
  },
  {
    "numero_procedimento": "N/A",
    "entidade": "Lusa - Agência de Notícias de Portugal, S. A.",
    "link": "https://diariodarepublica.pt/dr/detalhe/contrato-publico/27280-940416195",
    "detalhes_completos": "1 - IDENTIFICAÇÃO E CONTACTOS DA ENTIDADE ADJUDICANTE\nDesignação da entidade adjudicante: Lusa - Agência de Notícias de Portugal, S. A.\nNIPC: 503935107\nEndereço: Rua Drº João Couto Lt. C\nCódigo postal: 1500-236\nLocalidade: Lisboa\nPaís: Portugal\nNUT III: PT170\nDistrito: Lisboa\nConcelho: Lisboa\nFreguesia: Freguesia de Benfica\nTelefone: 217116500\nFax: 217116500\nEndereço da Entidade (URL): http://www.lusa.pt\nEndereço Eletrónico: compras@lusa.pt\neDelivery Gateway (URL): https://community.vortal.biz/public/\nFunção da Organização: Adquirente\nNorma jurídica da Entidade Adjudicante: Autoridade da administração central\nÁrea de atividade da Autoridade Adjudicante: Serviços públicos das administrações públicas\n\n2 - JORNAL OFICIAL DA UNIÃO EUROPEIA\nO procedimento a que este anúncio diz respeito também é publicitado no Jornal Oficial da União Europeia? Não\n\n3 - AVISO\nModelo de Anúncio: Concurso público\nData de Envio do Anúncio: 15-10-2025\n\n5 - PROCESSO\nTipo de Procedimento: Concurso público\nPreço base do procedimento: Sim\nValor do preço base do procedimento: 170.000,00 EUR\nProcedimento com lotes? Não\n\n6 - OBJETO DO CONTRATO\nNúmero de referência interna: LUSA-CP-005-2025\nDesignação do contrato: servidores, storage, backups e switching\nDescrição: Aquisição de servidores, storage, backups e switching\nTipo de Contrato Principal: Aquisição de Bens Móveis\nTipo de Contrato: Aquisição de Bens Móveis\nClassificação CPV (Vocabulário Comum para os Contratos Públicos)\nObjeto principal\nVocabulário Principal: 30200000\nPreço base s/IVA: 170.000,00 EUR\n\n7 - INDICAÇÕES ADICIONAIS\nO contrato envolve aquisição conjunta (satisfação de várias entidades)? Não\nO contrato é adjudicado por uma central de compras? Não\n\n8 - TÉCNICAS\nO concurso destina-se à celebração de um acordo-quadro? Inexistência de acordo-quadro\nÉ utilizado um leilão eletrónico? Não\nÉ adotada uma fase de negociação? Não\nSistema de Aquisição Dinâmico: Inexistência de sistema de aquisição dinâmico\n\n9 - LOCAL DA EXECUÇÃO DO CONTRATO\nLOCAL DA EXECUÇÃO DO CONTRATO (PROCEDIMENTO)\nPaís: Portugal\nNUT III: PT170\nLocalidade: Lisboa\nDistrito: Lisboa\nConcelho: Lisboa\nFreguesia: Freguesia de Benfica\n\n10 - PRAZO DE EXECUÇÃO DO CONTRATO\nPrazo de execução do contrato: 45 DIAS\nPrevisão de renovações: Não\n\n11 - FUNDOS EU\nTêm fundos EU? Não\n\n12 - DOCUMENTOS DE HABILITAÇÃO\nHabilitação para o exercício da atividade profissional: Não\n\n13 - CONDIÇÕES DE APRESENTAÇÃO\nPlataforma eletrónica utilizada pela entidade adjudicante: VORTAL\nURL para Apresentação: https://community.vortal.biz/public/\nAdmissibilidade da apresentação de propostas variantes: Não autorizado\nPrazo para apresentação das propostas: 30-10-2025 23:59\nPrazo durante o qual os concorrentes são obrigados a manter as respetivas propostas: 66 dias a contar do termo do prazo para a apresentação das propostas\nIndicação de Subcontratação na Proposta: Inexistência de indicação de subcontratação\n\n14 - PRESTAÇÃO DE CAUÇÃO\nPrestação de caução: Sim\nPercentagem: 3%\nDescrição da Garantia Exigida: De acordo com o Anexo V do programa do concurso\n\n15 - FORNECIMENTO DAS PEÇAS DO CONCURSO, APRESENTAÇÃO DE PEDIDOS DE PARTICIPAÇÃO E APRESENTAÇÃO DAS PROPOSTAS\nLink para acesso às peças do concurso (URL): https://community.vortal.biz/Public/public-tender-documents/bGVEU0lYeDBsUURUamdlWTJvK3FERVRISXB4MjdMZ1dHZWZJTHBHUmw1eW53OW1yYzVmNW9wOTRKOGZwcHVsMkJyaFFEeGp2K29iTkVndW0zU0hQK3c9PWlqQnhF\n\n20 - OUTROS REQUISITOS\nInformação sobre contratos reservados. Aplica-se a contratos reservados (54º-A)? Não\n\n21 - CRITÉRIO DE ADJUDICAÇÃO\nMultifator: Sim\nFator: \nNome: Preço\nPonderação: 50%\nSubfatores: Não\nFator: \nNome: Qualidade\nPonderação: 20%\nSubfatores: Não\nFator: \nNome: Qualidade\nPonderação: 15%\nSubfatores: Não\nFator: \nNome: Qualidade\nPonderação: 10%\nSubfatores: Não\nFator: \nNome: Qualidade\nPonderação: 5%\nSubfatores: Não\n\n24 - CONDIÇÕES DO CONTRATO\nFaturação Eletrónica: Permitido\nObrigação de Subcontratação:\nCódigo da Obrigação de Subcontratação: Não é aplicável nenhuma obrigação de subcontratação.\n\n25 - COMPRA PÚBLICA ESTRATÉGICA\nCompra Pública Estratégica: Redução dos impactos ambientais\nDescrição do Processo de Adjudicação Estratégico: Conforme as peças do procedimento\nCritérios de contratos Públicos Ecológicos: Critérios de contratação pública ecológica nacional\nCategorias da estratégia nacional: Outros\nOutra categoria (Descrição): Manuais online\nDiretiva Veículos Não Poluentes: Não\nCritério de Acessibilidade: Os critérios de acessibilidade para as pessoas com deficiência não estão incluídos porque o contrato não se destina a pessoas singulares\n\n26 - INFORMAÇÕES ADICIONAIS\nContrato adequado para PME: Sim\nCobertura ACP (Acordo dos Contratos Públicos da Organização Mundial do Comércio): Não\n\n27 - IDENTIFICAÇÃO E CONTACTOS DO ÓRGÃO DE RECURSOS ADMINISTRATIVOS\nDesignação: Presidente do Conselho de Administração\nEndereço: Rua Dr. João Couto Lote C\nCódigo postal: 1500-236\nLocalidade: Lisboa\nTelefone: +351 217116500\nFax: +351 217116531\nEndereço eletrónico: compras@lusa.pt\n\n28 - IDENTIFICAÇÃO DO(S) AUTOR(ES) DE ANÚNCIO\nNome: Bruno Antunes Calejo\nCargo: Chefe do Departamento de Operações e Compras\n419663053",
    "nipc": "503935107",
    "distrito": "Lisboa",
    "concelho": "Lisboa",
    "freguesia": "Freguesia de Benfica",
    "site": "http://www.lusa.pt",
    "email": "compras@lusa.pt",
    "designacao_contrato": "servidores, storage, backups e switching",
    "descricao": "Aquisição de servidores, storage, backups e switching",
    "preco_base": "170.000,00 EUR",
    "prazo_execucao": "45 DIAS",
    "prazo_apresentacao_propostas": "30-10-2025 23:59",
    "fundos_eu": "Não",
    "plataforma_eletronica": "VORTAL",
    "url_procedimento": "https://community.vortal.biz/public/",
    "autor_nome": "Bruno Antunes Calejo",
    "autor_cargo": "Chefe do Departamento de Operações e Compras"
  },
  {
    "numero_procedimento": "N/A",
    "entidade": "Unidade Local de Saúde do Alentejo Central, E.P.E",
    "link": "https://diariodarepublica.pt/dr/detalhe/contrato-publico/27284-940416197",
    "detalhes_completos": "Alteração do Anúncio de procedimento n.º 25876/2025, de 2025-10-02, com o ID 419601371\n\n1 - IDENTIFICAÇÃO E CONTACTOS DA ENTIDADE ADJUDICANTE\nDesignação da entidade adjudicante: Unidade Local de Saúde do Alentejo Central, E.P.E\nNIPC: 508085888\nEndereço: Largo Sr. da Pobreza\nCódigo postal: 7000-811\nLocalidade: Évora\nPaís: Portugal\nNUT III: PT187\nDistrito: Évora\nConcelho: Évora\nFreguesia: Todas\nTelefone: 266740111\nFax: 266744212\nEndereço da Entidade (URL): www.hevora.min-saude.pt\nEndereço Eletrónico: concursos.aprov@ulsac.min-saude.pt\neDelivery Gateway (URL): https://community.vortal.biz/public/\nFunção da Organização: Adquirente\nNorma jurídica da Entidade Adjudicante: Organismo de direito público\nÁrea de atividade da Autoridade Adjudicante: Saúde\n\n2 - JORNAL OFICIAL DA UNIÃO EUROPEIA\nO procedimento a que este anúncio diz respeito também é publicitado no Jornal Oficial da União Europeia? Não\n\n3 - AVISO\nModelo de Anúncio: Concurso público\nData de Envio do Anúncio: 15-10-2025\n\n5 - PROCESSO\nTipo de Procedimento: Concurso público\nPreço base do procedimento: Sim\nValor do preço base do procedimento: 124.000,00 EUR\nProcedimento com lotes? Sim\nNº Máx. de Lotes Autorizado: 3\nNúmero máximo de lotes que podem ser adjudicados a um concorrente: 3\n\n6 - OBJETO DO CONTRATO\nNúmero de referência interna: 180116.25\nDesignação do contrato: Equipamentos para Serviço de Neonatologia\nDescrição: Aquisição de Equipamentos para Serviço de Neonatologia\nTipo de Contrato Principal: Aquisição de Bens Móveis\nTipo de Contrato: Aquisição de Bens Móveis\nClassificação CPV (Vocabulário Comum para os Contratos Públicos)\nObjeto principal\nVocabulário Principal: 33100000\nPreço base s/IVA: 124.000,00 EUR\nLotes: \nNº: LOT-0001\nDescrição do Lote: Lote 1\nPreço base s/IVA: 32.000,00 EUR\nClassificação CPV (Vocabulário Comum para os Contratos Públicos)\nObjeto principal\nVocabulário Principal: 33100000\nNº: LOT-0002\nDescrição do Lote: Lote 2\nPreço base s/IVA: 32.000,00 EUR\nClassificação CPV (Vocabulário Comum para os Contratos Públicos)\nObjeto principal\nVocabulário Principal: 33100000\nNº: LOT-0003\nDescrição do Lote: Lote 3\nPreço base s/IVA: 60.000,00 EUR\nClassificação CPV (Vocabulário Comum para os Contratos Públicos)\nObjeto principal\nVocabulário Principal: 33100000\n\n7 - INDICAÇÕES ADICIONAIS\nO contrato envolve aquisição conjunta (satisfação de várias entidades)? Não\nO contrato é adjudicado por uma central de compras? Não\n\n8 - TÉCNICAS\nO concurso destina-se à celebração de um acordo-quadro? Inexistência de acordo-quadro\nÉ utilizado um leilão eletrónico? Não\nÉ adotada uma fase de negociação? Não\nSistema de Aquisição Dinâmico: Inexistência de sistema de aquisição dinâmico\n\n9 - LOCAL DA EXECUÇÃO DO CONTRATO\nLOCAL DA EXECUÇÃO DO CONTRATO (PROCEDIMENTO)\nPaís: Portugal\nNUT III: PT187\nLocalidade: Évora\nDistrito: Évora\nConcelho: Évora\nFreguesia: União das Freguesias de Évora (São Mamede, Sé, São Pedro e Santo Antão)\nLOCAL DA EXECUÇÃO DO CONTRATO (LOTE)\nIdentificador do Lote: LOT-0001; LOT-0002; LOT-0003\nPaís: Portugal\nNUT III: PT187\nLocalidade: Évora\nDistrito: Évora\nConcelho: Évora\nFreguesia: União das Freguesias de Évora (São Mamede, Sé, São Pedro e Santo Antão)\n\n10 - PRAZO DE EXECUÇÃO DO CONTRATO\nIdentificador do Lote: LOT-0001; LOT-0002; LOT-0003\nPrazo de execução do contrato: 20 DIAS\nPrevisão de renovações: Não\n\n11 - FUNDOS EU\nIdentificador do Lote: LOT-0001; LOT-0002; LOT-0003\nTêm fundos EU? Não\n\n12 - DOCUMENTOS DE HABILITAÇÃO\nHabilitação para o exercício da atividade profissional: Não\n\n13 - CONDIÇÕES DE APRESENTAÇÃO\nPlataforma eletrónica utilizada pela entidade adjudicante: VORTAL\nURL para Apresentação: https://community.vortal.biz/public/\nAdmissibilidade da apresentação de propostas variantes: Não autorizado\nPrazo para apresentação das propostas: 31-10-2025 18:00\nPrazo durante o qual os concorrentes são obrigados a manter as respetivas propostas: 120 dias a contar do termo do prazo para a apresentação das propostas\nIndicação de Subcontratação na Proposta: Inexistência de indicação de subcontratação\n\n14 - PRESTAÇÃO DE CAUÇÃO\nPrestação de caução: Não\n\n15 - FORNECIMENTO DAS PEÇAS DO CONCURSO, APRESENTAÇÃO DE PEDIDOS DE PARTICIPAÇÃO E APRESENTAÇÃO DAS PROPOSTAS\nLink para acesso às peças do concurso (URL): https://community.vortal.biz/Public/public-tender-documents/UmdNQUd0VzV3Q3NicnRzb0FjczJkTUJGcXJaaldhdUE3Mkk5NncyWFhpVkNncG9pWThZaUZWSTJPWk9RODVmQUR5WkYvdzROVCtVbWd3Ym85aVkwRnc9PSlGY01E\n\n20 - OUTROS REQUISITOS\nIdentificador do Lote: LOT-0001; LOT-0002; LOT-0003\nInformação sobre contratos reservados. Aplica-se a contratos reservados (54º-A)? Não\n\n21 - CRITÉRIO DE ADJUDICAÇÃO\nO Critério de adjudicação é diferenciado por lote? Sim\nIdentificador do lote: LOT-0001\nMultifator: Sim\nFator: \nNome: Preço\nPonderação: 60%\nSubfatores: Não\nFator: \nNome: Qualidade\nPonderação: 10%\nSubfatores: Não\nFator: \nNome: Qualidade\nPonderação: 20%\nSubfatores: Não\nFator: \nNome: Qualidade\nPonderação: 10%\nSubfatores: Não\nO Critério de adjudicação é diferenciado por lote? Sim\nIdentificador do lote: LOT-0002\nMultifator: Não\nMonofator:\nNome: Preço\nO Critério de adjudicação é diferenciado por lote? Sim\nIdentificador do lote: LOT-0003\nMultifator: Não\nMonofator:\nNome: Preço\n\n24 - CONDIÇÕES DO CONTRATO\nIdentificador do Lote: LOT-0001; LOT-0002; LOT-0003\nFaturação Eletrónica: Permitido\nObrigação de Subcontratação:\nCódigo da Obrigação de Subcontratação: Não é aplicável nenhuma obrigação de subcontratação.\n\n25 - COMPRA PÚBLICA ESTRATÉGICA\nCompra Pública Estratégica: Inexistência de contratação pública estratégica\n\n26 - INFORMAÇÕES ADICIONAIS\nIdentificador do Lote: LOT-0001; LOT-0002; LOT-0003\nContrato adequado para PME: Sim\nCobertura ACP (Acordo dos Contratos Públicos da Organização Mundial do Comércio): Não\n\n27 - IDENTIFICAÇÃO E CONTACTOS DO ÓRGÃO DE RECURSOS ADMINISTRATIVOS\nDesignação: Conselho de Administração\nEndereço: Largo Sr. da Pobreza\nCódigo postal: 7005-811\nLocalidade: Évora\nTelefone: +351 266740111\nFax: +351 266744212\nEndereço eletrónico: concursos.aprov@ulsac.min-saude.pt\n\n28 - IDENTIFICAÇÃO DO(S) AUTOR(ES) DE ANÚNCIO\nNome: Vitor Rui Gomes Fialho\nCargo: Presidente do Conselho de Administração\n\n29 - ALTERAÇÃO\nMotivo da Alteração: Correção pelo editor\nIdentificador da Versão do Anúncio a Alterar: 30149c3d-12a6-475f-beca-d1e5992061fd-01\nIdentificador das Secções Alteradas do Anúncio Anterior: Condições de Apresentação\nDescrição das Alterações: Prorrogação do Prazo de Apresentação de Propostas\nAlteração dos Documentos do Concurso: Não\n419663142",
    "nipc": "508085888",
    "distrito": "Évora",
    "concelho": "Évora",
    "freguesia": "Todas",
    "site": "www.hevora.min-saude.pt",
    "email": "concursos.aprov@ulsac.min-saude.pt",
    "designacao_contrato": "Equipamentos para Serviço de Neonatologia",
    "descricao": "Aquisição de Equipamentos para Serviço de Neonatologia",
    "preco_base": "124.000,00 EUR",
    "prazo_execucao": "20 DIAS",
    "prazo_apresentacao_propostas": "31-10-2025 18:00",
    "fundos_eu": "Não",
    "plataforma_eletronica": "VORTAL",
    "url_procedimento": "https://community.vortal.biz/public/",
    "autor_nome": "Vitor Rui Gomes Fialho",
    "autor_cargo": "Presidente do Conselho de Administração"
  }
]