[
  {
    "numero_procedimento": "N/A",
    "entidade": "Centro Formação Profissional Para o Sector Alimentar",
    "link": "https://diariodarepublica.pt/dr/detalhe/contrato-publico/27374-940560147",
    "detalhes_completos": "1 - IDENTIFICAÇÃO E CONTACTOS DA ENTIDADE ADJUDICANTE\nDesignação da entidade adjudicante: Centro Formação Profissional Para o Sector Alimentar\nNIPC: 506024717\nEndereço: Av  25 de Abril  22\nCódigo postal: 1675-183\nLocalidade: Pontinha\nPaís: Portugal\nNUT III: PT170\nDistrito: Lisboa\nConcelho: Odivelas\nFreguesia: União das Freguesias de Pontinha e Famões\nTelefone: 214789500\nFax: 214789500\nEndereço da Entidade (URL): www.cfpsa.pt\nEndereço Eletrónico: cfpsa@cfpsa.pt\nFunção da Organização: Adquirente\nNorma jurídica da Entidade Adjudicante: Organismo de direito público\nÁrea de atividade da Autoridade Adjudicante: Assuntos económicos\n\n2 - JORNAL OFICIAL DA UNIÃO EUROPEIA\nO procedimento a que este anúncio diz respeito também é publicitado no Jornal Oficial da União Europeia? Sim\n\n3 - AVISO\nModelo de Anúncio: Concurso público\nData de Envio do Anúncio: 14-10-2025\n\n5 - PROCESSO\nTipo de Procedimento: Concurso público\nPreço base do procedimento: Sim\nValor do preço base do procedimento: 162.420,00 EUR\nProcedimento com lotes? Sim\nNº Máx. de Lotes Autorizado: 2\nNúmero máximo de lotes que podem ser adjudicados a um concorrente: 2\n\n6 - OBJETO DO CONTRATO\nNúmero de referência interna: AQS/CPI/060/25\nDesignação do contrato: AQS/CPI/060/25 Prestação de serviços de limpeza das instalações do CFPSA na Pontinha e na Delegação Coimbra para 2026\nDescrição: Prestação de serviços de limpeza das instalações do CFPSA na Pontinha e na Delegação Coimbra para 2026\nOpções: Não\nTipo de Contrato Principal: Aquisição de Serviços\nTipo de Contrato: Aquisição de Serviços\nClassificação CPV (Vocabulário Comum para os Contratos Públicos)\nObjeto principal\nVocabulário Principal: 90910000\nPreço base s/IVA: 162.420,00 EUR\nLotes: \nNº: LOT-0001\nDescrição do Lote: 1 - Prestação serviços limpeza instalações CFPSA Pontinha\nPreço base s/IVA: 146.880,00 EUR\nClassificação CPV (Vocabulário Comum para os Contratos Públicos)\nObjeto principal\nVocabulário Principal: 90910000\nNº: LOT-0002\nDescrição do Lote: 2 - Prestação serviços limpeza instalações CFPSA Delegação Coimbra\nPreço base s/IVA: 15.540,00 EUR\nClassificação CPV (Vocabulário Comum para os Contratos Públicos)\nObjeto principal\nVocabulário Principal: 90910000\n\n7 - INDICAÇÕES ADICIONAIS\nO contrato envolve aquisição conjunta (satisfação de várias entidades)? Não\nO contrato é adjudicado por uma central de compras? Não\n\n8 - TÉCNICAS\nO concurso destina-se à celebração de um acordo-quadro? Inexistência de acordo-quadro\nÉ utilizado um leilão eletrónico? Não\nÉ adotada uma fase de negociação? Não\nSistema de Aquisição Dinâmico: Inexistência de sistema de aquisição dinâmico\n\n9 - LOCAL DA EXECUÇÃO DO CONTRATO\nLOCAL DA EXECUÇÃO DO CONTRATO (PROCEDIMENTO)\nLOCAL DA EXECUÇÃO DO CONTRATO (LOTE)\nIdentificador do Lote: LOT-0001\nPaís: Portugal\nNUT III: PT170\nLocalidade: Pontinha\nDistrito: Lisboa\nConcelho: Odivelas\nFreguesia: União das Freguesias de Pontinha e Famões\nIdentificador do Lote: LOT-0002\nPaís: Portugal\nNUT III: PT16E\nLocalidade: Coimbra\nDistrito: Coimbra\nConcelho: Coimbra\nFreguesia: Freguesia de Santo António dos Olivais\n\n10 - PRAZO DE EXECUÇÃO DO CONTRATO\nIdentificador do Lote: LOT-0001\nData de Início: 01-01-2026\nData de Fim: 31-12-2026\nPrevisão de renovações: Não\nIdentificador do Lote: LOT-0002\nData de Início: 01-01-2026\nData de Fim: 31-12-2026\nPrevisão de renovações: Não\n\n11 - FUNDOS EU\nIdentificador do Lote: LOT-0001; LOT-0002\nTêm fundos EU? Não\n\n12 - DOCUMENTOS DE HABILITAÇÃO\nHabilitação para o exercício da atividade profissional: Não\n\n13 - CONDIÇÕES DE APRESENTAÇÃO\nPlataforma eletrónica utilizada pela entidade adjudicante: COMPRASPT\nURL para Apresentação: https://www.compraspt.com/cpt-cfpsa/faces/\nAdmissibilidade da apresentação de propostas variantes: Não autorizado\nPrazo para apresentação das propostas: 13-11-2025 23:59\nPrazo durante o qual os concorrentes são obrigados a manter as respetivas propostas: 66 dias a contar do termo do prazo para a apresentação das propostas\nApresentação de Catálogo Eletrónico: Permitido\nIndicação de Subcontratação na Proposta: A parte do contrato que o proponente tenciona subcontratar\n\n14 - PRESTAÇÃO DE CAUÇÃO\nPrestação de caução: Sim\nPercentagem: 5%\nDescrição da Garantia Exigida: Garantia bancária, seguro caução, depósito bancário\n\n15 - FORNECIMENTO DAS PEÇAS DO CONCURSO, APRESENTAÇÃO DE PEDIDOS DE PARTICIPAÇÃO E APRESENTAÇÃO DAS PROPOSTAS\nLink para acesso às peças do concurso (URL): https://www.compraspt.com/cpt-cfpsa/faces/app/acessoDocs.jsp?codigoAcesso=4ojXyFyVvWL0hVobukAuklCZwWuL3QadhedCctR1JiOfQ2r6Eg\n\n20 - OUTROS REQUISITOS\nIdentificador do Lote: LOT-0001; LOT-0002\nInformação sobre contratos reservados. Aplica-se a contratos reservados (54º-A)? Não\n\n21 - CRITÉRIO DE ADJUDICAÇÃO\nO Critério de adjudicação é diferenciado por lote? Não\nMultifator: Não\nMonofator:\nNome: Preço\n\n24 - CONDIÇÕES DO CONTRATO\nIdentificador do Lote: LOT-0001; LOT-0002\nFaturação Eletrónica: Necessário\nObrigação de Subcontratação:\nCódigo da Obrigação de Subcontratação: Não é aplicável nenhuma obrigação de subcontratação.\n\n25 - COMPRA PÚBLICA ESTRATÉGICA\nCompra Pública Estratégica: Inexistência de contratação pública estratégica\n\n26 - INFORMAÇÕES ADICIONAIS\nIdentificador do Lote: LOT-0001\nContrato adequado para PME: Sim\nCobertura ACP (Acordo dos Contratos Públicos da Organização Mundial do Comércio): Não\nIdentificador do Lote: LOT-0002\nContrato adequado para PME: Sim\nCobertura ACP (Acordo dos Contratos Públicos da Organização Mundial do Comércio): Não\n\n27 - IDENTIFICAÇÃO E CONTACTOS DO ÓRGÃO DE RECURSOS ADMINISTRATIVOS\nDesignação: Conselho de Administração\nEndereço: cfpsa@cfpsa.pt\nCódigo postal: 1675-183\nLocalidade: Pontinha\nEndereço eletrónico: cfpsa@cfpsa.pt\nPrazo de interposição do recurso: 15 dias\n\n28 - IDENTIFICAÇÃO DO(S) AUTOR(ES) DE ANÚNCIO\nNome: Jorge Silva\nCargo: Responsável Divisão Aquisições e Serviços\n419656996",
    "nipc": "506024717",
    "distrito": "Lisboa",
    "concelho": "Odivelas",
    "freguesia": "União das Freguesias de Pontinha e Famões",
    "site": "www.cfpsa.pt",
    "email": "cfpsa@cfpsa.pt",
    "designacao_contrato": "AQS/CPI/060/25 Prestação de serviços de limpeza das instalações do CFPSA na Pontinha e na Delegação Coimbra para 2026",
    "descricao": "Prestação de serviços de limpeza das instalações do CFPSA na Pontinha e na Delegação Coimbra para 2026",
    "preco_base": "162.420,00 EUR",
    "prazo_execucao": null,
    "prazo_apresentacao_propostas": "13-11-2025 23:59",
    "fundos_eu": "Não",
    "plataforma_eletronica": "COMPRASPT",
    "url_procedimento": "https://www.compraspt.com/cpt-cfpsa/faces/",
    "autor_nome": "Jorge Silva",
    "autor_cargo": "Responsável Divisão Aquisições e Serviços"
  },
  {
    "numero_procedimento": "N/A",
    "entidade": "Cooptécnica - Gustave Eiffel, Cooperativa de Ensino e Formação Técnico Profissional, C. R. L.",
    "link": "https://diariodarepublica.pt/dr/detalhe/contrato-publico/27375-940560148",
    "detalhes_completos": "1 - IDENTIFICAÇÃO E CONTACTOS DA ENTIDADE ADJUDICANTE\nDesignação da entidade adjudicante: Cooptécnica - Gustave Eiffel, Cooperativa de Ensino e Formação Técnico Profissional, C. R. L.\nNIPC: 502327669\nEndereço: Rua Elias Garcia, nº 29, Amadora\nCódigo postal: 2700-312\nLocalidade: Lisboa\nPaís: Portugal\nNUT III: PT170\nDistrito: Lisboa\nConcelho: Amadora\nFreguesia: Freguesia de Falagueira-Venda Nova\nTelefone: 214996440\nFax: 214966449\nEndereço da Entidade (URL): www.cooptecnica.pt\nEndereço Eletrónico: contratacao.publica@gustaveeiffel.pt\neDelivery Gateway (URL): https://community.vortal.biz/public/\nFunção da Organização: Adquirente\nNorma jurídica da Entidade Adjudicante: Organismo de direito público\nÁrea de atividade da Autoridade Adjudicante: Educação\n\n2 - JORNAL OFICIAL DA UNIÃO EUROPEIA\nO procedimento a que este anúncio diz respeito também é publicitado no Jornal Oficial da União Europeia? Sim\n\n3 - AVISO\nModelo de Anúncio: Concurso público\nData de Envio do Anúncio: 14-10-2025\n\n5 - PROCESSO\nTipo de Procedimento: Concurso público\nPreço base do procedimento: Sim\nValor do preço base do procedimento: 219.884,59 EUR\nProcedimento com lotes? Sim\nNº Máx. de Lotes Autorizado: 8\nNúmero máximo de lotes que podem ser adjudicados a um concorrente: 8\n\n6 - OBJETO DO CONTRATO\nNúmero de referência interna: CPI 017 CCP 2025\nDesignação do contrato: Aquisição de Serviço de Implementação de Infraestrutura de Cablagem de Fibra Ótica e Cobre\nDescrição: Aquisição de Serviço de Implementação de Infraestrutura de Cablagem de Fibra Ótica e Cobre\nOpções: Não\nTipo de Contrato Principal: Aquisição de Bens Móveis\nTipo de Contrato: Aquisição de Bens Móveis; Locação de Bens Móveis\nClassificação CPV (Vocabulário Comum para os Contratos Públicos)\nObjeto principal\nVocabulário Principal: 32424000\nPreço base s/IVA: 219.884,59 EUR\nLotes: \nNº: LOT-0001\nDescrição do Lote: Lote 1 – Escola da Amadora Centro – Informática\nPreço base s/IVA: 28.747,74 EUR\nClassificação CPV (Vocabulário Comum para os Contratos Públicos)\nObjeto principal\nVocabulário Principal: 32424000\nNº: LOT-0002\nDescrição do Lote: Lote 2 – Escola da Amadora Sede – Digital\nPreço base s/IVA: 40.226,93 EUR\nClassificação CPV (Vocabulário Comum para os Contratos Públicos)\nObjeto principal\nVocabulário Principal: 32424000\nNº: LOT-0003\nDescrição do Lote: Lote 3 - Escola da Amadora Sede – Industrial\nPreço base s/IVA: 39.504,81 EUR\nClassificação CPV (Vocabulário Comum para os Contratos Públicos)\nObjeto principal\nVocabulário Principal: 32424000\nNº: LOT-0004\nDescrição do Lote: Lote 4 - Escola da Amadora Sede – Informática\nPreço base s/IVA: 17.066,18 EUR\nClassificação CPV (Vocabulário Comum para os Contratos Públicos)\nObjeto principal\nVocabulário Principal: 32424000\nNº: LOT-0005\nDescrição do Lote: Lote 5 - Escola do Entroncamento – Industrial\nPreço base s/IVA: 31.509,15 EUR\nClassificação CPV (Vocabulário Comum para os Contratos Públicos)\nObjeto principal\nVocabulário Principal: 32424000\nNº: LOT-0006\nDescrição do Lote: Lote 6 - Escola do Entroncamento – Energias Renováveis\nPreço base s/IVA: 17.328,48 EUR\nClassificação CPV (Vocabulário Comum para os Contratos Públicos)\nObjeto principal\nVocabulário Principal: 32424000\nNº: LOT-0007\nDescrição do Lote: Lote 7 - Escola do Lumiar – Industrial\nPreço base s/IVA: 26.173,38 EUR\nClassificação CPV (Vocabulário Comum para os Contratos Públicos)\nObjeto principal\nVocabulário Principal: 32424000\nNº: LOT-0008\nDescrição do Lote: Lote 8 - Escola do Lumiar – Energias Renováveis\nPreço base s/IVA: 19.327,92 EUR\nClassificação CPV (Vocabulário Comum para os Contratos Públicos)\nObjeto principal\nVocabulário Principal: 32424000\n\n7 - INDICAÇÕES ADICIONAIS\nO contrato envolve aquisição conjunta (satisfação de várias entidades)? Não\nO contrato é adjudicado por uma central de compras? Não\n\n8 - TÉCNICAS\nO concurso destina-se à celebração de um acordo-quadro? Inexistência de acordo-quadro\nÉ utilizado um leilão eletrónico? Não\nÉ adotada uma fase de negociação? Não\nSistema de Aquisição Dinâmico: Inexistência de sistema de aquisição dinâmico\n\n9 - LOCAL DA EXECUÇÃO DO CONTRATO\nLOCAL DA EXECUÇÃO DO CONTRATO (PROCEDIMENTO)\nPaís: Portugal\nNUT III: PT170\nLocalidade: Lisboa\nDistrito: Lisboa\nConcelho: Amadora\nFreguesia: Todas\nLOCAL DA EXECUÇÃO DO CONTRATO (LOTE)\nIdentificador do Lote: LOT-0001; LOT-0002; LOT-0003; LOT-0004; LOT-0005; LOT-0006; LOT-0007; LOT-0008\nPaís: Portugal\nNUT III: PT170\nLocalidade: Lisboa\nDistrito: Lisboa\nConcelho: Amadora\nFreguesia: Todas\nIdentificador do Lote: LOT-0001; LOT-0002; LOT-0003; LOT-0004; LOT-0005; LOT-0006; LOT-0007; LOT-0008\nPaís: Portugal\nNUT III: PT170\nLocalidade: Lisboa\nDistrito: Lisboa\nConcelho: Lisboa\nFreguesia: Freguesia de Lumiar\nIdentificador do Lote: LOT-0001; LOT-0002; LOT-0003; LOT-0004; LOT-0005; LOT-0006; LOT-0007; LOT-0008\nPaís: Portugal\nNUT III: PT16I\nLocalidade: Santarém\nDistrito: Santarém\nConcelho: Entroncamento\nFreguesia: Todas\nIdentificador do Lote: LOT-0001; LOT-0002; LOT-0003; LOT-0004; LOT-0005; LOT-0006; LOT-0007; LOT-0008\nPaís: Portugal\nNUT III: PT170\nLocalidade: Lisboa\nDistrito: Lisboa\nConcelho: Amadora\nFreguesia: Todas\n\n10 - PRAZO DE EXECUÇÃO DO CONTRATO\nIdentificador do Lote: LOT-0001; LOT-0002; LOT-0003; LOT-0004; LOT-0005; LOT-0006; LOT-0007; LOT-0008\nPrazo de execução do contrato: 15 DIAS\nPrevisão de renovações: Não\n\n11 - FUNDOS EU\nIdentificador do Lote: LOT-0001; LOT-0002; LOT-0003; LOT-0004; LOT-0005; LOT-0006; LOT-0007; LOT-0008\nTêm fundos EU? Sim\n\n12 - DOCUMENTOS DE HABILITAÇÃO\nHabilitação para o exercício da atividade profissional: Não\n\n13 - CONDIÇÕES DE APRESENTAÇÃO\nPlataforma eletrónica utilizada pela entidade adjudicante: VORTAL\nURL para Apresentação: https://community.vortal.biz/public/\nAdmissibilidade da apresentação de propostas variantes: Não autorizado\nPrazo para apresentação das propostas: 02-11-2025 23:59\nPrazo durante o qual os concorrentes são obrigados a manter as respetivas propostas: 10 dias a contar do termo do prazo para a apresentação das propostas\nApresentação de Catálogo Eletrónico: Não autorizado\nIndicação de Subcontratação na Proposta: Inexistência de indicação de subcontratação\n\n14 - PRESTAÇÃO DE CAUÇÃO\nPrestação de caução: Sim\nPercentagem: 5%\nDescrição da Garantia Exigida: O adjudicatário deve prestar a caução devida no prazo de 10 (dez) dias úteis a contar da notificação da decisão de adjudicação, no valor de 5% do preço contratual, em benefício da Cooptécnica Gustave Eiffel, devendo comprovar essa prestação no dia imediatamente subsequente.\n\n15 - FORNECIMENTO DAS PEÇAS DO CONCURSO, APRESENTAÇÃO DE PEDIDOS DE PARTICIPAÇÃO E APRESENTAÇÃO DAS PROPOSTAS\nLink para acesso às peças do concurso (URL): https://community.vortal.biz/Public/public-tender-documents/QWRXMWJBYXZMWFZOUUFnMC9UWlB4d1E4QWFGS212cSt1UjQyZHNlZGg0eW4zdjFEMkxNZ1hGMllXcENZWFl1ZFJMbnhPc3JwQjc4OUVHQXFRcUdVZHc9PUR5aEJZ\n\n20 - OUTROS REQUISITOS\nIdentificador do Lote: LOT-0001; LOT-0002; LOT-0003; LOT-0004; LOT-0005; LOT-0006; LOT-0007; LOT-0008\nInformação sobre contratos reservados. Aplica-se a contratos reservados (54º-A)? Não\n\n21 - CRITÉRIO DE ADJUDICAÇÃO\nO Critério de adjudicação é diferenciado por lote? Não\nMultifator: Não\nMonofator:\nNome: Outros\nOutro nome: Preço\n\n24 - CONDIÇÕES DO CONTRATO\nIdentificador do Lote: LOT-0001; LOT-0002; LOT-0003; LOT-0004; LOT-0005; LOT-0006; LOT-0007; LOT-0008\nFaturação Eletrónica: Permitido\nObrigação de Subcontratação:\nCódigo da Obrigação de Subcontratação: Não é aplicável nenhuma obrigação de subcontratação.\n\n25 - COMPRA PÚBLICA ESTRATÉGICA\nCompra Pública Estratégica: Inexistência de contratação pública estratégica\n\n26 - INFORMAÇÕES ADICIONAIS\nIdentificador do Lote: LOT-0001; LOT-0002; LOT-0003; LOT-0004; LOT-0005; LOT-0006; LOT-0007; LOT-0008\nContrato adequado para PME: Sim\nCobertura ACP (Acordo dos Contratos Públicos da Organização Mundial do Comércio): Não\n\n27 - IDENTIFICAÇÃO E CONTACTOS DO ÓRGÃO DE RECURSOS ADMINISTRATIVOS\nDesignação: Susana Fernandes\nEndereço: RUA ELIAS GARCIA Nº 29 - VENDA NOVA\nCódigo postal: 2700-312\nLocalidade: Amadora\nTelefone: +351 912355271\nFax: +351 214996449\nEndereço eletrónico: contratacaopublica@gustaveeiffel.pt\n\n28 - IDENTIFICAÇÃO DO(S) AUTOR(ES) DE ANÚNCIO\nNome: Susana Fernandes\nCargo: Técnico\n419657124",
    "nipc": "502327669",
    "distrito": "Lisboa",
    "concelho": "Amadora",
    "freguesia": "Freguesia de Falagueira-Venda Nova",
    "site": "www.cooptecnica.pt",
    "email": "contratacao.publica@gustaveeiffel.pt",
    "designacao_contrato": "Aquisição de Serviço de Implementação de Infraestrutura de Cablagem de Fibra Ótica e Cobre",
    "descricao": "Aquisição de Serviço de Implementação de Infraestrutura de Cablagem de Fibra Ótica e Cobre",
    "preco_base": "219.884,59 EUR",
    "prazo_execucao": "15 DIAS",
    "prazo_apresentacao_propostas": "02-11-2025 23:59",
    "fundos_eu": "Sim",
    "plataforma_eletronica": "VORTAL",
    "url_procedimento": "https://community.vortal.biz/public/",
    "autor_nome": "Susana Fernandes",
    "autor_cargo": "Técnico"
  },
  {
    "numero_procedimento": "N/A",
    "entidade": "TML - Transportes Metropolitanos de Lisboa, E. M. T., S. A.",
    "link": "https://diariodarepublica.pt/dr/detalhe/contrato-publico/27376-940560149",
    "detalhes_completos": "1 - IDENTIFICAÇÃO E CONTACTOS DA ENTIDADE ADJUDICANTE\nDesignação da entidade adjudicante: TML - Transportes Metropolitanos de Lisboa, E. M. T., S. A.\nNIPC: 516150359\nEndereço: Rua Cruz de Santa Apolónia, 23, 25 e 25-A \nCódigo postal: 1100-187\nLocalidade: Lisboa\nPaís: Portugal\nNUT III: PT170\nDistrito: Lisboa\nConcelho: Lisboa\nFreguesia: Freguesia de São Vicente\nTelefone: 218121379\nFax: 218121379\nEndereço da Entidade (URL): https://www.tmlmobilidade.pt/\nEndereço Eletrónico: contratacao@tmlmobilidade.pt\neDelivery Gateway (URL): https://community.vortal.biz/public/\nFunção da Organização: Adquirente\nNorma jurídica da Entidade Adjudicante: Autoridade da administração central\nÁrea de atividade da Autoridade Adjudicante: Serviços públicos das administrações públicas\n\n2 - JORNAL OFICIAL DA UNIÃO EUROPEIA\nO procedimento a que este anúncio diz respeito também é publicitado no Jornal Oficial da União Europeia? Sim\n\n3 - AVISO\nModelo de Anúncio: Concurso público\nData de Envio do Anúncio: 14-10-2025\n\n5 - PROCESSO\nTipo de Procedimento: Concurso público\nPreço base do procedimento: Sim\nValor do preço base do procedimento: 946.000,00 EUR\nProcedimento com lotes? Não\n\n6 - OBJETO DO CONTRATO\nNúmero de referência interna: CPI03/2025\nDesignação do contrato: Aquisição de licenciamento Microsoft 365 para software de produtividade, colaboração, gestão e segurança\nDescrição: Aquisição de licenciamento Microsoft 365 para software de produtividade, colaboração, gestão e segurança\nOpções: Não\nTipo de Contrato Principal: Aquisição de Bens Móveis\nTipo de Contrato: Aquisição de Bens Móveis\nClassificação CPV (Vocabulário Comum para os Contratos Públicos)\nObjeto principal\nVocabulário Principal: 22456000\nPreço base s/IVA: 946.000,00 EUR\n\n7 - INDICAÇÕES ADICIONAIS\nO contrato envolve aquisição conjunta (satisfação de várias entidades)? Não\nO contrato é adjudicado por uma central de compras? Não\n\n8 - TÉCNICAS\nO concurso destina-se à celebração de um acordo-quadro? Inexistência de acordo-quadro\nÉ utilizado um leilão eletrónico? Não\nÉ adotada uma fase de negociação? Não\nSistema de Aquisição Dinâmico: Inexistência de sistema de aquisição dinâmico\n\n9 - LOCAL DA EXECUÇÃO DO CONTRATO\nLOCAL DA EXECUÇÃO DO CONTRATO (PROCEDIMENTO)\nPaís: Portugal\nNUT III: PT170\nLocalidade: Lisboa\nDistrito: Lisboa\nConcelho: Lisboa\nFreguesia: Freguesia de São Vicente\n\n10 - PRAZO DE EXECUÇÃO DO CONTRATO\nPrazo de execução do contrato: 36 MESES\nPrevisão de renovações: Não\n\n11 - FUNDOS EU\nTêm fundos EU? Não\n\n12 - DOCUMENTOS DE HABILITAÇÃO\nHabilitação para o exercício da atividade profissional: Não\n\n13 - CONDIÇÕES DE APRESENTAÇÃO\nPlataforma eletrónica utilizada pela entidade adjudicante: VORTAL\nURL para Apresentação: https://community.vortal.biz/public/\nAdmissibilidade da apresentação de propostas variantes: Não autorizado\nPrazo para apresentação das propostas: 12-11-2025 17:00\nPrazo durante o qual os concorrentes são obrigados a manter as respetivas propostas: 66 dias a contar do termo do prazo para a apresentação das propostas\nApresentação de Catálogo Eletrónico: Permitido\nIndicação de Subcontratação na Proposta: Inexistência de indicação de subcontratação\n\n14 - PRESTAÇÃO DE CAUÇÃO\nPrestação de caução: Sim\nPercentagem: 5%\nDescrição da Garantia Exigida: Em conformidade com um dos modelos constantes do ANEXO VII ao Programa do Concurso\n\n15 - FORNECIMENTO DAS PEÇAS DO CONCURSO, APRESENTAÇÃO DE PEDIDOS DE PARTICIPAÇÃO E APRESENTAÇÃO DAS PROPOSTAS\nLink para acesso às peças do concurso (URL): https://community.vortal.biz/Public/public-tender-documents/em1ZM3FzSWZDTzFmOEZ2WEFKUkJ5L0ZrMmVZOGJPWlMyYXllemlVUVNtWFByVmtLS2NYaEhVaU93dnNsUHhhSHVYS2JPaXhOM1B5eUNqNGFnVTdDVGc9PTl0NEEp\n\n20 - OUTROS REQUISITOS\nInformação sobre contratos reservados. Aplica-se a contratos reservados (54º-A)? Não\n\n21 - CRITÉRIO DE ADJUDICAÇÃO\nMultifator: Sim\nFator: \nNome: Preço\nPonderação: 60%\nSubfatores: Não\nFator: \nNome: Preço\nPonderação: 35%\nSubfatores: Não\nFator: \nNome: Preço\nPonderação: 5%\nSubfatores: Não\n\n24 - CONDIÇÕES DO CONTRATO\nFaturação Eletrónica: Permitido\nObrigação de Subcontratação:\nCódigo da Obrigação de Subcontratação: Não é aplicável nenhuma obrigação de subcontratação.\n\n25 - COMPRA PÚBLICA ESTRATÉGICA\nCompra Pública Estratégica: Inexistência de contratação pública estratégica\n\n26 - INFORMAÇÕES ADICIONAIS\nContrato adequado para PME: Sim\nCobertura ACP (Acordo dos Contratos Públicos da Organização Mundial do Comércio): Não\n\n27 - IDENTIFICAÇÃO E CONTACTOS DO ÓRGÃO DE RECURSOS ADMINISTRATIVOS\nDesignação: Conselho de Administração da TML\nEndereço: Rua Cruz de Santa Apolónia 23, 25 e 25 A\nCódigo postal: 1100-187\nLocalidade: Lisboa\nTelefone: +351 218121379\nFax: +351 218121379\nEndereço eletrónico: contratacao@tmlmobilidade.pt\n\n28 - IDENTIFICAÇÃO DO(S) AUTOR(ES) DE ANÚNCIO\nNome: Luís Carrondo\nCargo: Técnico Superior Principal DJR\n419648263",
    "nipc": "516150359",
    "distrito": "Lisboa",
    "concelho": "Lisboa",
    "freguesia": "Freguesia de São Vicente",
    "site": "https://www.tmlmobilidade.pt/",
    "email": "contratacao@tmlmobilidade.pt",
    "designacao_contrato": "Aquisição de licenciamento Microsoft 365 para software de produtividade, colaboração, gestão e segurança",
    "descricao": "Aquisição de licenciamento Microsoft 365 para software de produtividade, colaboração, gestão e segurança",
    "preco_base": "946.000,00 EUR",
    "prazo_execucao": "36 MESES",
    "prazo_apresentacao_propostas": "12-11-2025 17:00",
    "fundos_eu": "Não",
    "plataforma_eletronica": "VORTAL",
    "url_procedimento": "https://community.vortal.biz/public/",
    "autor_nome": "Luís Carrondo",
    "autor_cargo": "Técnico Superior Principal DJR"
  },
  {
    "numero_procedimento": "N/A",
    "entidade": "Arsenal do Alfeite, S. A.",
    "link": "https://diariodarepublica.pt/dr/detalhe/contrato-publico/27377-940560150",
    "detalhes_completos": "1 - IDENTIFICAÇÃO E CONTACTOS DA ENTIDADE ADJUDICANTE\nDesignação da entidade adjudicante: Arsenal do Alfeite, S. A.\nNIPC: 508881048\nEndereço: Alfeite (Laranjeiro) - Almada\nCódigo postal: 2810-001\nLocalidade: Setúbal\nPaís: Portugal\nNUT III: PT170\nDistrito: Setúbal\nConcelho: Almada\nFreguesia: Todas\nTelefone: 210950836\nFax: 210950873\nEndereço da Entidade (URL): www.arsenal-alfeite.pt\nEndereço Eletrónico: mario.peixe@arsenal-alfeite.pt\neDelivery Gateway (URL): https://community.vortal.biz/public/\nFunção da Organização: Adquirente\nNorma jurídica da Entidade Adjudicante: Organismo de direito público\nÁrea de atividade da Autoridade Adjudicante: Defesa\n\n2 - JORNAL OFICIAL DA UNIÃO EUROPEIA\nO procedimento a que este anúncio diz respeito também é publicitado no Jornal Oficial da União Europeia? Sim\n\n3 - AVISO\nModelo de Anúncio: Concurso público\nData de Envio do Anúncio: 14-10-2025\n\n5 - PROCESSO\nTipo de Procedimento: Concurso público\nPreço base do procedimento: Sim\nValor do preço base do procedimento: 99.900,00 EUR\nProcedimento com lotes? Sim\nNº Máx. de Lotes Autorizado: 13\nNúmero máximo de lotes que podem ser adjudicados a um concorrente: 13\n\n6 - OBJETO DO CONTRATO\nNúmero de referência interna: CPI 02 -2025\nDesignação do contrato: CPI 02-2025 - Aquisição de serviços de recolha, transporte e encaminhamento de resíduos da  Arsenal do Alfeite, S.A. (Lotes 1 a 13)\nDescrição: CPI 02-2025 - Aquisição de serviços de recolha, transporte e encaminhamento de resíduos da  Arsenal do Alfeite, S.A. (Lotes 1 a 13)\nOpções: Não\nTipo de Contrato Principal: Aquisição de Serviços\nTipo de Contrato: Aquisição de Serviços\nClassificação CPV (Vocabulário Comum para os Contratos Públicos)\nObjeto principal\nVocabulário Principal: 90500000\nPreço base s/IVA: 99.900,00 EUR\nLotes: \nNº: LOT-0001\nDescrição do Lote: Lote 1\nPreço base s/IVA: 13.070,00 EUR\nClassificação CPV (Vocabulário Comum para os Contratos Públicos)\nObjeto principal\nVocabulário Principal: 90500000\nNº: LOT-0002\nDescrição do Lote: Lote 2\nPreço base s/IVA: 2.490,00 EUR\nClassificação CPV (Vocabulário Comum para os Contratos Públicos)\nObjeto principal\nVocabulário Principal: 90500000\nNº: LOT-0003\nDescrição do Lote: Lote 3\nPreço base s/IVA: 1.280,00 EUR\nClassificação CPV (Vocabulário Comum para os Contratos Públicos)\nObjeto principal\nVocabulário Principal: 90500000\nNº: LOT-0004\nDescrição do Lote: Lote 4\nPreço base s/IVA: 7.310,00 EUR\nClassificação CPV (Vocabulário Comum para os Contratos Públicos)\nObjeto principal\nVocabulário Principal: 90500000\nNº: LOT-0005\nDescrição do Lote: Lote 5\nPreço base s/IVA: 3.780,00 EUR\nClassificação CPV (Vocabulário Comum para os Contratos Públicos)\nObjeto principal\nVocabulário Principal: 90500000\nNº: LOT-0006\nDescrição do Lote: Lote 6\nPreço base s/IVA: 2.600,00 EUR\nClassificação CPV (Vocabulário Comum para os Contratos Públicos)\nObjeto principal\nVocabulário Principal: 90500000\nNº: LOT-0007\nDescrição do Lote: Lote 7\nPreço base s/IVA: 3.650,00 EUR\nClassificação CPV (Vocabulário Comum para os Contratos Públicos)\nObjeto principal\nVocabulário Principal: 90500000\nNº: LOT-0008\nDescrição do Lote: Lote 8\nPreço base s/IVA: 9.000,00 EUR\nClassificação CPV (Vocabulário Comum para os Contratos Públicos)\nObjeto principal\nVocabulário Principal: 90500000\nNº: LOT-0009\nDescrição do Lote: Lote 9\nPreço base s/IVA: 4.960,00 EUR\nClassificação CPV (Vocabulário Comum para os Contratos Públicos)\nObjeto principal\nVocabulário Principal: 90500000\nNº: LOT-0010\nDescrição do Lote: Lote 10\nPreço base s/IVA: 15.400,00 EUR\nClassificação CPV (Vocabulário Comum para os Contratos Públicos)\nObjeto principal\nVocabulário Principal: 90500000\nNº: LOT-0011\nDescrição do Lote: Lote 11\nPreço base s/IVA: 6.740,00 EUR\nClassificação CPV (Vocabulário Comum para os Contratos Públicos)\nObjeto principal\nVocabulário Principal: 90500000\nNº: LOT-0012\nDescrição do Lote: Lote 12\nPreço base s/IVA: 27.920,00 EUR\nClassificação CPV (Vocabulário Comum para os Contratos Públicos)\nObjeto principal\nVocabulário Principal: 90500000\nNº: LOT-0013\nDescrição do Lote: Lote 13\nPreço base s/IVA: 1.700,00 EUR\nClassificação CPV (Vocabulário Comum para os Contratos Públicos)\nObjeto principal\nVocabulário Principal: 90500000\n\n7 - INDICAÇÕES ADICIONAIS\nO contrato envolve aquisição conjunta (satisfação de várias entidades)? Não\nO contrato é adjudicado por uma central de compras? Não\n\n8 - TÉCNICAS\nO concurso destina-se à celebração de um acordo-quadro? Inexistência de acordo-quadro\nÉ utilizado um leilão eletrónico? Não\nÉ adotada uma fase de negociação? Não\nSistema de Aquisição Dinâmico: Inexistência de sistema de aquisição dinâmico\n\n9 - LOCAL DA EXECUÇÃO DO CONTRATO\nLOCAL DA EXECUÇÃO DO CONTRATO (PROCEDIMENTO)\nPaís: Portugal\nNUT III: PT170\nLocalidade: Setúbal\nDistrito: Setúbal\nConcelho: Almada\nFreguesia: União das Freguesias de Laranjeiro e Feijó\nLOCAL DA EXECUÇÃO DO CONTRATO (LOTE)\nIdentificador do Lote: LOT-0001; LOT-0002; LOT-0003; LOT-0004; LOT-0005; LOT-0006; LOT-0007; LOT-0008; LOT-0009; LOT-0010; LOT-0011; LOT-0012; LOT-0013\nPaís: Portugal\nNUT III: PT170\nLocalidade: Setúbal\nDistrito: Setúbal\nConcelho: Almada\nFreguesia: União das Freguesias de Laranjeiro e Feijó\n\n10 - PRAZO DE EXECUÇÃO DO CONTRATO\nIdentificador do Lote: LOT-0001; LOT-0002; LOT-0003; LOT-0004; LOT-0005; LOT-0006; LOT-0007; LOT-0008; LOT-0009; LOT-0010; LOT-0011; LOT-0012; LOT-0013\nPrazo de execução do contrato: 1 ANOS\nPrevisão de renovações: Sim\nIndicar número máximo de renovações: 2\nPrazo de renovações diferente do prazo inicial: Não\n\n11 - FUNDOS EU\nIdentificador do Lote: LOT-0001; LOT-0002; LOT-0003; LOT-0004; LOT-0005; LOT-0006; LOT-0007; LOT-0008; LOT-0009; LOT-0010; LOT-0011; LOT-0012; LOT-0013\nTêm fundos EU? Não\n\n12 - DOCUMENTOS DE HABILITAÇÃO\nHabilitação para o exercício da atividade profissional: Sim\nTipo: Outros\nDescrição - Outros: Conforme Caderno de Encargos\nDescrição: n.a.\n\n13 - CONDIÇÕES DE APRESENTAÇÃO\nPlataforma eletrónica utilizada pela entidade adjudicante: VORTAL\nURL para Apresentação: https://community.vortal.biz/public/\nAdmissibilidade da apresentação de propostas variantes: Não autorizado\nPrazo para apresentação das propostas: 13-11-2025 23:59\nPrazo durante o qual os concorrentes são obrigados a manter as respetivas propostas: 66 dias a contar do termo do prazo para a apresentação das propostas\nApresentação de Catálogo Eletrónico: Permitido\nIndicação de Subcontratação na Proposta: Inexistência de indicação de subcontratação\n\n14 - PRESTAÇÃO DE CAUÇÃO\nPrestação de caução: Não\n\n15 - FORNECIMENTO DAS PEÇAS DO CONCURSO, APRESENTAÇÃO DE PEDIDOS DE PARTICIPAÇÃO E APRESENTAÇÃO DAS PROPOSTAS\nLink para acesso às peças do concurso (URL): https://community.vortal.biz/Public/public-tender-documents/dnowVWR4Z0hCMEk2TFNtNG1YcUkxdnBFaUUxMDAvelVzUWhBQTBOUkdUczZKOXdLanJ0cjZkUm40eFFWZGwyMDBESXhRUjZFVFpqRUhOSk11TXgwbEE9PWVJTkdH\n\n20 - OUTROS REQUISITOS\nIdentificador do Lote: LOT-0001; LOT-0002; LOT-0003; LOT-0004; LOT-0005; LOT-0006; LOT-0007; LOT-0008; LOT-0009; LOT-0010; LOT-0011; LOT-0012; LOT-0013\nInformação sobre contratos reservados. Aplica-se a contratos reservados (54º-A)? Não\n\n21 - CRITÉRIO DE ADJUDICAÇÃO\nO Critério de adjudicação é diferenciado por lote? Não\nMultifator: Não\nMonofator:\nNome: Preço\n\n24 - CONDIÇÕES DO CONTRATO\nIdentificador do Lote: LOT-0001; LOT-0002; LOT-0003; LOT-0004; LOT-0005; LOT-0006; LOT-0007; LOT-0008; LOT-0009; LOT-0010; LOT-0011; LOT-0012; LOT-0013\nFaturação Eletrónica: Permitido\nObrigação de Subcontratação:\nCódigo da Obrigação de Subcontratação: Não é aplicável nenhuma obrigação de subcontratação.\n\n25 - COMPRA PÚBLICA ESTRATÉGICA\nCompra Pública Estratégica: Inexistência de contratação pública estratégica\n\n26 - INFORMAÇÕES ADICIONAIS\nIdentificador do Lote: LOT-0001; LOT-0002; LOT-0003; LOT-0004; LOT-0005; LOT-0006; LOT-0007; LOT-0008; LOT-0009; LOT-0010; LOT-0011; LOT-0012; LOT-0013\nContrato adequado para PME: Sim\nCobertura ACP (Acordo dos Contratos Públicos da Organização Mundial do Comércio): Não\n\n27 - IDENTIFICAÇÃO E CONTACTOS DO ÓRGÃO DE RECURSOS ADMINISTRATIVOS\nDesignação: Conselho de Administração\nEndereço: Alfeite - Base Naval de Lisboa\nCódigo postal: 2810-001\nLocalidade: Almada\nTelefone: +351 210950800\nFax: +351 210950873\nEndereço eletrónico: contratos@arsenal-alfeite.pt\n\n28 - IDENTIFICAÇÃO DO(S) AUTOR(ES) DE ANÚNCIO\nNome: Sara Muacho\nCargo: Chefe de Divisão de Contratação e Aprovisionamento\n419657408",
    "nipc": "508881048",
    "distrito": "Setúbal",
    "concelho": "Almada",
    "freguesia": "Todas",
    "site": "www.arsenal-alfeite.pt",
    "email": "mario.peixe@arsenal-alfeite.pt",
    "designacao_contrato": "CPI 02-2025 - Aquisição de serviços de recolha, transporte e encaminhamento de resíduos da Arsenal do Alfeite, S.A. (Lotes 1 a 13)",
    "descricao": "CPI 02-2025 - Aquisição de serviços de recolha, transporte e encaminhamento de resíduos da Arsenal do Alfeite, S.A. (Lotes 1 a 13)",
    "preco_base": "99.900,00 EUR",
    "prazo_execucao": "1 ANOS",
    "prazo_apresentacao_propostas": "13-11-2025 23:59",
    "fundos_eu": "Não",
    "plataforma_eletronica": "VORTAL",
    "url_procedimento": "https://community.vortal.biz/public/",
    "autor_nome": "Sara Muacho",
    "autor_cargo": "Chefe de Divisão de Contratação e Aprovisionamento"
  },
  {
    "numero_procedimento": "N/A",
    "entidade": "Instituto Politécnico do Porto",
    "link": "https://diariodarepublica.pt/dr/detalhe/contrato-publico/27378-940560151",
    "detalhes_completos": "1 - IDENTIFICAÇÃO E CONTACTOS DA ENTIDADE ADJUDICANTE\nDesignação da entidade adjudicante: Instituto Politécnico do Porto\nNIPC: 503606251\nServiço/Órgão/Pessoa de contacto: Central de Compras\nEndereço: RUA DR. ROBERTO FRIAS, 712\nCódigo postal: 4200-465\nLocalidade: Porto\nPaís: Portugal\nNUT III: PT11A\nDistrito: Porto\nConcelho: Porto\nFreguesia: Freguesia de Paranhos - Porto\nTelefone: 225571000\nFax: 225020772\nEndereço da Entidade (URL): http://www.ipp.pt\nEndereço Eletrónico: centralcompras@sc.ipp.pt\neDelivery Gateway (URL): https://www.acingov.pt\nFunção da Organização: Adquirente\nNorma jurídica da Entidade Adjudicante: Organismo de direito público\nÁrea de atividade da Autoridade Adjudicante: Educação\n\n2 - JORNAL OFICIAL DA UNIÃO EUROPEIA\nO procedimento a que este anúncio diz respeito também é publicitado no Jornal Oficial da União Europeia? Não\n\n3 - AVISO\nModelo de Anúncio: Concurso público\nData de Envio do Anúncio: 16-10-2025\n\n5 - PROCESSO\nTipo de Procedimento: Concurso público\nPreço base do procedimento: Sim\nValor do preço base do procedimento: 131.329,40 EUR\nProcedimento com lotes? Sim\nNº Máx. de Lotes Autorizado: 4\nNúmero máximo de lotes que podem ser adjudicados a um concorrente: 4\n\n6 - OBJETO DO CONTRATO\nNúmero de referência interna: 28/000/A/841_2025\nDesignação do contrato: Aquisição de Equipamento e Mobiliário para o Edifício do PORTIC do Instituto Politécnico do Porto\nDescrição: Aquisição de Equipamento e Mobiliário para o Edifício do PORTIC do Instituto Politécnico do Porto \nTipo de Contrato Principal: Aquisição de Bens Móveis\nTipo de Contrato: Aquisição de Bens Móveis\nClassificação CPV (Vocabulário Comum para os Contratos Públicos)\nObjeto principal\nVocabulário Principal: 39112000\nPreço base s/IVA: 51.927,90 EUR\nObjeto Complementar\nVocabulário Principal: 44220000\nPreço base s/IVA: 46.755,50 EUR\nObjeto Complementar\nVocabulário Principal: 39515410\nPreço base s/IVA: 26.812,00 EUR\nObjeto Complementar\nVocabulário Principal: 39711000\nPreço base s/IVA: 5.834,00 EUR\nLotes: \nNº: LOT-0001\nDescrição do Lote: Estores\nPreço base s/IVA: 26.812,00 EUR\nClassificação CPV (Vocabulário Comum para os Contratos Públicos)\nObjeto principal\nVocabulário Principal: 39515410\nNº: LOT-0002\nDescrição do Lote: Bancadas, armários e bancadas de anfiteatro\nPreço base s/IVA: 46.755,50 EUR\nClassificação CPV (Vocabulário Comum para os Contratos Públicos)\nObjeto principal\nVocabulário Principal: 44220000\nNº: LOT-0003\nDescrição do Lote: Equipamentos eletrodomésticos e utensílios de cozinha\nPreço base s/IVA: 5.834,00 EUR\nClassificação CPV (Vocabulário Comum para os Contratos Públicos)\nObjeto principal\nVocabulário Principal: 39710000\nNº: LOT-0004\nDescrição do Lote: Mobiliário de escritório e sala de aula\nPreço base s/IVA: 51.927,90 EUR\nClassificação CPV (Vocabulário Comum para os Contratos Públicos)\nObjeto principal\nVocabulário Principal: 39130000\n\n7 - INDICAÇÕES ADICIONAIS\nO contrato envolve aquisição conjunta (satisfação de várias entidades)? Não\nO contrato é adjudicado por uma central de compras? Não\n\n8 - TÉCNICAS\nO concurso destina-se à celebração de um acordo-quadro? Inexistência de acordo-quadro\nÉ utilizado um leilão eletrónico? Não\nÉ adotada uma fase de negociação? Não\nSistema de Aquisição Dinâmico: Inexistência de sistema de aquisição dinâmico\n\n9 - LOCAL DA EXECUÇÃO DO CONTRATO\nLOCAL DA EXECUÇÃO DO CONTRATO (PROCEDIMENTO)\nPaís: Portugal\nNUT III: PT11A\nLocalidade: Freguesia de Paranhos - Porto\nDistrito: Porto\nConcelho: Porto\nFreguesia: Freguesia de Paranhos - Porto\nLOCAL DA EXECUÇÃO DO CONTRATO (LOTE)\nIdentificador do Lote: LOT-0001; LOT-0002; LOT-0003; LOT-0004\nPaís: Portugal\nNUT III: PT11A\nLocalidade: Freguesia de Paranhos - Porto\nDistrito: Porto\nConcelho: Porto\nFreguesia: Freguesia de Paranhos - Porto\n\n10 - PRAZO DE EXECUÇÃO DO CONTRATO\nIdentificador do Lote: LOT-0001; LOT-0002; LOT-0003; LOT-0004\nPrazo de execução do contrato: 60 DIAS\nPrevisão de renovações: Não\n\n11 - FUNDOS EU\nIdentificador do Lote: LOT-0001; LOT-0002; LOT-0003; LOT-0004\nTêm fundos EU? Sim\n\n12 - DOCUMENTOS DE HABILITAÇÃO\nHabilitação para o exercício da atividade profissional: Não\n\n13 - CONDIÇÕES DE APRESENTAÇÃO\nPlataforma eletrónica utilizada pela entidade adjudicante: ACIN\nURL para Apresentação: https://www.acingov.pt\nAdmissibilidade da apresentação de propostas variantes: Não autorizado\nPrazo para apresentação das propostas: 28-10-2025 23:59\nPrazo durante o qual os concorrentes são obrigados a manter as respetivas propostas: 120 dias a contar do termo do prazo para a apresentação das propostas\nIndicação de Subcontratação na Proposta: Inexistência de indicação de subcontratação\n\n14 - PRESTAÇÃO DE CAUÇÃO\nPrestação de caução: Não\n\n15 - FORNECIMENTO DAS PEÇAS DO CONCURSO, APRESENTAÇÃO DE PEDIDOS DE PARTICIPAÇÃO E APRESENTAÇÃO DAS PROPOSTAS\nLink para acesso às peças do concurso (URL): https://www.acingov.pt/acingovprod/2/zonaPublica/zona_publica_c/donwloadProcedurePiece/OTc3ODAx\n\n20 - OUTROS REQUISITOS\nIdentificador do Lote: LOT-0001; LOT-0002; LOT-0003; LOT-0004\nInformação sobre contratos reservados. Aplica-se a contratos reservados (54º-A)? Não\n\n21 - CRITÉRIO DE ADJUDICAÇÃO\nO Critério de adjudicação é diferenciado por lote? Não\nMultifator: Sim\nFator: \nNome: Preço\nPonderação: 80%\nSubfatores: Não\nFator: \nNome: Outros\nOutro Nome: Prazo de Garantia\nPonderação: 20%\nSubfatores: Não\n\n24 - CONDIÇÕES DO CONTRATO\nIdentificador do Lote: LOT-0001; LOT-0002; LOT-0003; LOT-0004\nFaturação Eletrónica: Necessário\nObrigação de Subcontratação:\nCódigo da Obrigação de Subcontratação: Não é aplicável nenhuma obrigação de subcontratação.\n\n25 - COMPRA PÚBLICA ESTRATÉGICA\nCompra Pública Estratégica: Redução dos impactos ambientais\nDescrição do Processo de Adjudicação Estratégico: Conforme peças do procedimento\nCritérios de contratos Públicos Ecológicos: Critérios de contratação pública ecológica nacional\nCategorias da estratégia nacional: Mobiliário\nContratos Públicos Ecológicos: Outros\nDiretiva Veículos Não Poluentes: Não\nCritério de Acessibilidade: Os critérios de acessibilidade para as pessoas com deficiência não estão incluídos porque o contrato não se destina a pessoas singulares\n\n26 - INFORMAÇÕES ADICIONAIS\nIdentificador do Lote: LOT-0001; LOT-0002; LOT-0003; LOT-0004\nContrato adequado para PME: Sim\nCobertura ACP (Acordo dos Contratos Públicos da Organização Mundial do Comércio): Não\n\n27 - IDENTIFICAÇÃO E CONTACTOS DO ÓRGÃO DE RECURSOS ADMINISTRATIVOS\nDesignação: Presidente do P.PORTO\nEndereço: RUA DR. ROBERTO FRIAS, 712\nCódigo postal: 4200-465\nLocalidade: Paranhos\nTelefone: 225571000\nFax: 225020772\nEndereço eletrónico: centralcompras@sc.ipp.pt\nPrazo de interposição do recurso: 10 dias\n\n28 - IDENTIFICAÇÃO DO(S) AUTOR(ES) DE ANÚNCIO\nNome: Paulo Alberto da Silva Pereira\nCargo: Presidente do Instituto Politécnico do Porto\n419667088",
    "nipc": "503606251",
    "distrito": "Porto",
    "concelho": "Porto",
    "freguesia": "Freguesia de Paranhos - Porto",
    "site": "http://www.ipp.pt",
    "email": "centralcompras@sc.ipp.pt",
    "designacao_contrato": "Aquisição de Equipamento e Mobiliário para o Edifício do PORTIC do Instituto Politécnico do Porto",
    "descricao": "Aquisição de Equipamento e Mobiliário para o Edifício do PORTIC do Instituto Politécnico do Porto",
    "preco_base": "51.927,90 EUR",
    "prazo_execucao": "60 DIAS",
    "prazo_apresentacao_propostas": "28-10-2025 23:59",
    "fundos_eu": "Sim",
    "plataforma_eletronica": "ACIN",
    "url_procedimento": "https://www.acingov.pt",
    "autor_nome": "Paulo Alberto da Silva Pereira",
    "autor_cargo": "Presidente do Instituto Politécnico do Porto"
  },
  {
    "numero_procedimento": "N/A",
    "entidade": "Laboratório Nacional de Engenharia Civil, I. P.",
    "link": "https://diariodarepublica.pt/dr/detalhe/contrato-publico/27381-940560153",
    "detalhes_completos": "Alteração do Anúncio de procedimento n.º 27180/2025, de 2025-10-15, com o ID 419649535\n\n1 - IDENTIFICAÇÃO E CONTACTOS DA ENTIDADE ADJUDICANTE\nDesignação da entidade adjudicante: Laboratório Nacional de Engenharia Civil, I. P.\nNIPC: 501389660\nEndereço: Av.  do Brasil, 101\nCódigo postal: 1700-066\nLocalidade: Lisboa\nPaís: Portugal\nNUT III: PT170\nDistrito: Lisboa\nConcelho: Lisboa\nFreguesia: Freguesia de Alvalade - Lisboa\nTelefone: 218443000\nFax: 218443021\nEndereço da Entidade (URL): www.lnec.pt\nEndereço Eletrónico: aprovisionamento@lnec.pt\neDelivery Gateway (URL): https://community.vortal.biz/public/\nFunção da Organização: Adquirente\nNorma jurídica da Entidade Adjudicante: Organismo de direito público\nÁrea de atividade da Autoridade Adjudicante: Serviços públicos das administrações públicas\n\n2 - JORNAL OFICIAL DA UNIÃO EUROPEIA\nO procedimento a que este anúncio diz respeito também é publicitado no Jornal Oficial da União Europeia? Não\n\n3 - AVISO\nModelo de Anúncio: Concurso público\nData de Envio do Anúncio: 16-10-2025\n\n5 - PROCESSO\nTipo de Procedimento: Concurso público\nPreço base do procedimento: Sim\nValor do preço base do procedimento: 88.792,00 EUR\nProcedimento com lotes? Não\n\n6 - OBJETO DO CONTRATO\nNúmero de referência interna: 0305/A07/318\nDesignação do contrato: Sistema \"motion tracking\" de modelos com grandes dimensões\nDescrição: Sistema \"motion tracking\" de modelos com grandes dimensões\nTipo de Contrato Principal: Aquisição de Bens Móveis\nTipo de Contrato: Aquisição de Bens Móveis\nClassificação CPV (Vocabulário Comum para os Contratos Públicos)\nObjeto principal\nVocabulário Principal: 35710000\nPreço base s/IVA: 88.792,00 EUR\n\n7 - INDICAÇÕES ADICIONAIS\nO contrato envolve aquisição conjunta (satisfação de várias entidades)? Não\nO contrato é adjudicado por uma central de compras? Não\n\n8 - TÉCNICAS\nO concurso destina-se à celebração de um acordo-quadro? Inexistência de acordo-quadro\nÉ utilizado um leilão eletrónico? Não\nÉ adotada uma fase de negociação? Não\nSistema de Aquisição Dinâmico: Inexistência de sistema de aquisição dinâmico\n\n9 - LOCAL DA EXECUÇÃO DO CONTRATO\nLOCAL DA EXECUÇÃO DO CONTRATO (PROCEDIMENTO)\nPaís: Portugal\nNUT III: PT170\nLocalidade: Lisboa\nDistrito: Lisboa\nConcelho: Lisboa\nFreguesia: Todas\n\n10 - PRAZO DE EXECUÇÃO DO CONTRATO\nPrazo de execução do contrato: 45 DIAS\nPrevisão de renovações: Não\n\n11 - FUNDOS EU\nTêm fundos EU? Não\n\n12 - DOCUMENTOS DE HABILITAÇÃO\nHabilitação para o exercício da atividade profissional: Não\n\n13 - CONDIÇÕES DE APRESENTAÇÃO\nPlataforma eletrónica utilizada pela entidade adjudicante: VORTAL\nURL para Apresentação: https://community.vortal.biz/public/\nAdmissibilidade da apresentação de propostas variantes: Não autorizado\nPrazo para apresentação das propostas: 19-10-2025 23:59\nPrazo durante o qual os concorrentes são obrigados a manter as respetivas propostas: 66 dias a contar do termo do prazo para a apresentação das propostas\nApresentação de Catálogo Eletrónico: Permitido\nIndicação de Subcontratação na Proposta: Inexistência de indicação de subcontratação\n\n14 - PRESTAÇÃO DE CAUÇÃO\nPrestação de caução: Não\n\n15 - FORNECIMENTO DAS PEÇAS DO CONCURSO, APRESENTAÇÃO DE PEDIDOS DE PARTICIPAÇÃO E APRESENTAÇÃO DAS PROPOSTAS\nLink para acesso às peças do concurso (URL): https://community.vortal.biz/Public/public-tender-documents/WkZsR1ZpQUZPTmRiN2syRFh5elMra1pMTFdsbExjdUFJUkkxc01wUGlLWW1rNUdoKzMzSnN3OUlsVGdaTjNCK0lTWjR5MmRkSHRtYlVHai9xTG5SelE9PXJ1dEtQ\n\n20 - OUTROS REQUISITOS\nInformação sobre contratos reservados. Aplica-se a contratos reservados (54º-A)? Não\n\n21 - CRITÉRIO DE ADJUDICAÇÃO\nMultifator: Não\nMonofator:\nNome: Outros\nOutro nome: Preço\n\n24 - CONDIÇÕES DO CONTRATO\nFaturação Eletrónica: Permitido\nObrigação de Subcontratação:\nCódigo da Obrigação de Subcontratação: Não é aplicável nenhuma obrigação de subcontratação.\n\n25 - COMPRA PÚBLICA ESTRATÉGICA\nCompra Pública Estratégica: Redução dos impactos ambientais\nDescrição do Processo de Adjudicação Estratégico: Conforme as peças do procedimento\nCritérios de contratos Públicos Ecológicos: Critérios de contratação pública ecológica nacional\nCategorias da estratégia nacional: Outros\nOutra categoria (Descrição): Contratos de aquisição ou locação de equipamento informático\nContratos Públicos Ecológicos: Outros\nDiretiva Veículos Não Poluentes: Não\nCritério de Acessibilidade: Os critérios de acessibilidade para as pessoas com deficiência não estão incluídos porque o contrato não se destina a pessoas singulares\n\n26 - INFORMAÇÕES ADICIONAIS\nContrato adequado para PME: Sim\nCobertura ACP (Acordo dos Contratos Públicos da Organização Mundial do Comércio): Não\n\n27 - IDENTIFICAÇÃO E CONTACTOS DO ÓRGÃO DE RECURSOS ADMINISTRATIVOS\nDesignação: Conselho Diretivo\nEndereço: Avenida do Brasil, 101\nCódigo postal: 1700-066\nLocalidade: Lisboa\nTelefone: +351 218443000\nFax: +351 218443021\nEndereço eletrónico: lnec@lnec.pt\n\n28 - IDENTIFICAÇÃO DO(S) AUTOR(ES) DE ANÚNCIO\nNome: Laura Maria Mello Saraiva Caldeira\nCargo: Presidente do Conselho Diretivo\n\n29 - ALTERAÇÃO\nMotivo da Alteração: Correção pelo adquirente\nIdentificador da Versão do Anúncio a Alterar: 2773489b-c562-4924-8b67-2c3e8711d31a-01\nIdentificador das Secções Alteradas do Anúncio Anterior: Condições de Apresentação\nDescrição das Alterações: Alteração do prazo para apresentação de propostas\nAlteração dos Documentos do Concurso: Não\n419662851",
    "nipc": "501389660",
    "distrito": "Lisboa",
    "concelho": "Lisboa",
    "freguesia": "Freguesia de Alvalade - Lisboa",
    "site": "www.lnec.pt",
    "email": "aprovisionamento@lnec.pt",
    "designacao_contrato": "Sistema \"motion tracking\" de modelos com grandes dimensões",
    "descricao": "Sistema \"motion tracking\" de modelos com grandes dimensões",
    "preco_base": "88.792,00 EUR",
    "prazo_execucao": "45 DIAS",
    "prazo_apresentacao_propostas": "19-10-2025 23:59",
    "fundos_eu": "Não",
    "plataforma_eletronica": "VORTAL",
    "url_procedimento": "https://community.vortal.biz/public/",
    "autor_nome": "Laura Maria Mello Saraiva Caldeira",
    "autor_cargo": "Presidente do Conselho Diretivo"
  },
  {
    "numero_procedimento": "N/A",
    "entidade": "Município de Valença",
    "link": "https://diariodarepublica.pt/dr/detalhe/contrato-publico/27385-940560154",
    "detalhes_completos": "1 - IDENTIFICAÇÃO E CONTACTOS DA ENTIDADE ADJUDICANTE\nDesignação da entidade adjudicante: Município de Valença\nNIPC: 506728897\nEndereço: Pç. Da República, Valença\nCódigo postal: 4930-702\nLocalidade: Valença\nPaís: Portugal\nNUT III: PT111\nDistrito: Viana do Castelo\nConcelho: Valença\nFreguesia: Todas\nTelefone: 251809500\nFax: 251809519\nEndereço da Entidade (URL): www.cm-valenca.pt\nEndereço Eletrónico: geral@cm-valenca.pt\neDelivery Gateway (URL): https://community.vortal.biz/public/\nFunção da Organização: Adquirente\nNorma jurídica da Entidade Adjudicante: Autoridade local\nÁrea de atividade da Autoridade Adjudicante: Serviços públicos das administrações públicas\n\n2 - JORNAL OFICIAL DA UNIÃO EUROPEIA\nO procedimento a que este anúncio diz respeito também é publicitado no Jornal Oficial da União Europeia? Não\n\n3 - AVISO\nModelo de Anúncio: Concurso público\nData de Envio do Anúncio: 16-10-2025\n\n5 - PROCESSO\nTipo de Procedimento: Concurso público\nPreço base do procedimento: Sim\nValor do preço base do procedimento: 56.920,69 EUR\nProcedimento com lotes? Não\n\n6 - OBJETO DO CONTRATO\nNúmero de referência interna: CP-ABS-16/2025\nDesignação do contrato: FORNECIMENTO DE PRODUTOS ALIMENTARES – CONGELADOS para a confeção de Refeições ESCOLARES nos Refeitórios do Agrupamento de Escolas de Muralhas do Minho\nDescrição: FORNECIMENTO DE PRODUTOS ALIMENTARES – CONGELADOS para a confeção de Refeições ESCOLARES nos Refeitórios do Agrupamento de Escolas de Muralhas do Minho\nTipo de Contrato Principal: Aquisição de Bens Móveis\nTipo de Contrato: Aquisição de Bens Móveis\nClassificação CPV (Vocabulário Comum para os Contratos Públicos)\nObjeto principal\nVocabulário Principal: 15220000\nPreço base s/IVA: 56.920,69 EUR\n\n7 - INDICAÇÕES ADICIONAIS\nO contrato envolve aquisição conjunta (satisfação de várias entidades)? Não\nO contrato é adjudicado por uma central de compras? Não\n\n8 - TÉCNICAS\nO concurso destina-se à celebração de um acordo-quadro? Inexistência de acordo-quadro\nÉ utilizado um leilão eletrónico? Não\nÉ adotada uma fase de negociação? Não\nSistema de Aquisição Dinâmico: Inexistência de sistema de aquisição dinâmico\n\n9 - LOCAL DA EXECUÇÃO DO CONTRATO\nLOCAL DA EXECUÇÃO DO CONTRATO (PROCEDIMENTO)\nPaís: Portugal\nNUT III: PT111\nLocalidade: Viana do Castelo\nDistrito: Viana do Castelo\nConcelho: Valença\nFreguesia: Todas\n\n10 - PRAZO DE EXECUÇÃO DO CONTRATO\nPrazo de execução do contrato: 7 MESES\nPrevisão de renovações: Não\n\n11 - FUNDOS EU\nTêm fundos EU? Não\n\n12 - DOCUMENTOS DE HABILITAÇÃO\nHabilitação para o exercício da atividade profissional: Sim\nTipo: Outros\nDescrição - Outros: Os previstos no ponto 28 do PC\nDescrição: Os previstos no ponto 28 do PC\n\n13 - CONDIÇÕES DE APRESENTAÇÃO\nPlataforma eletrónica utilizada pela entidade adjudicante: VORTAL\nURL para Apresentação: https://community.vortal.biz/public/\nAdmissibilidade da apresentação de propostas variantes: Não autorizado\nPrazo para apresentação das propostas: 22-10-2025 17:00\nPrazo durante o qual os concorrentes são obrigados a manter as respetivas propostas: 66 dias a contar do termo do prazo para a apresentação das propostas\nIndicação de Subcontratação na Proposta: Inexistência de indicação de subcontratação\n\n14 - PRESTAÇÃO DE CAUÇÃO\nPrestação de caução: Não\n\n15 - FORNECIMENTO DAS PEÇAS DO CONCURSO, APRESENTAÇÃO DE PEDIDOS DE PARTICIPAÇÃO E APRESENTAÇÃO DAS PROPOSTAS\nLink para acesso às peças do concurso (URL): https://community.vortal.biz/Public/public-tender-documents/d2JVaXhBZXp2VzdXQ1kzTERCOWtrbVFNUWVRNHhPeGxKMC92aHgxcjJUZFRLQVc4WXJQWnM4Y1l3RjZ5WFNEZHBBaDAvMm1ZdE1ycVhoc1A4M1Z3Y2c9PWs4Wk9w\n\n20 - OUTROS REQUISITOS\nInformação sobre contratos reservados. Aplica-se a contratos reservados (54º-A)? Não\n\n21 - CRITÉRIO DE ADJUDICAÇÃO\nMultifator: Não\nMonofator:\nNome: Preço\n\n24 - CONDIÇÕES DO CONTRATO\nFaturação Eletrónica: Permitido\nObrigação de Subcontratação:\nCódigo da Obrigação de Subcontratação: Não é aplicável nenhuma obrigação de subcontratação.\n\n25 - COMPRA PÚBLICA ESTRATÉGICA\nCompra Pública Estratégica: Inexistência de contratação pública estratégica\n\n26 - INFORMAÇÕES ADICIONAIS\nContrato adequado para PME: Sim\nCobertura ACP (Acordo dos Contratos Públicos da Organização Mundial do Comércio): Não\n\n27 - IDENTIFICAÇÃO E CONTACTOS DO ÓRGÃO DE RECURSOS ADMINISTRATIVOS\nDesignação: José Manuel Vaz Carpinteira\nEndereço: Praça da Republica nº702\nCódigo postal: 4930-702\nLocalidade: Valença\nTelefone: +351 251809500\nFax: +351 251809518\nEndereço eletrónico: aprovisionamento@cm-valenca.pt\n\n28 - IDENTIFICAÇÃO DO(S) AUTOR(ES) DE ANÚNCIO\nNome: José Manuel Vaz Capinteira\nCargo: Presidente Câmara Municipal\n419666748",
    "nipc": "506728897",
    "distrito": "Viana do Castelo",
    "concelho": "Valença",
    "freguesia": "Todas",
    "site": "www.cm-valenca.pt",
    "email": "geral@cm-valenca.pt",
    "designacao_contrato": "FORNECIMENTO DE PRODUTOS ALIMENTARES – CONGELADOS para a confeção de Refeições ESCOLARES nos Refeitórios do Agrupamento de Escolas de Muralhas do Minho",
    "descricao": "FORNECIMENTO DE PRODUTOS ALIMENTARES – CONGELADOS para a confeção de Refeições ESCOLARES nos Refeitórios do Agrupamento de Escolas de Muralhas do Minho",
    "preco_base": "56.920,69 EUR",
    "prazo_execucao": "7 MESES",
    "prazo_apresentacao_propostas": "22-10-2025 17:00",
    "fundos_eu": "Não",
    "plataforma_eletronica": "VORTAL",
    "url_procedimento": "https://community.vortal.biz/public/",
    "autor_nome": "José Manuel Vaz Capinteira",
    "autor_cargo": "Presidente Câmara Municipal"
  },
  {
    "numero_procedimento": "N/A",
    "entidade": "TTSL - Transtejo Soflusa, SA",
    "link": "https://diariodarepublica.pt/dr/detalhe/contrato-publico/27387-940560155",
    "detalhes_completos": "1 - IDENTIFICAÇÃO E CONTACTOS DA ENTIDADE ADJUDICANTE\nDesignação da entidade adjudicante: TTSL - Transtejo Soflusa, SA\nNIPC: 500723770\nEndereço: Rua da Cintura do Porto de Lisboa- Terminal Fluvial do Cais do Sodré\nCódigo postal: 1249-249\nLocalidade: Lisboa\nPaís: Portugal\nNUT III: PT170\nDistrito: Lisboa\nConcelho: Lisboa\nFreguesia: Todas\nTelefone: 210422400\nFax: 210422499\nEndereço da Entidade (URL): www.transtejo.pt\nEndereço Eletrónico: contratacao@transtejo.pt\neDelivery Gateway (URL): https://community.vortal.biz/public/\nFunção da Organização: Adquirente\nNorma jurídica da Entidade Adjudicante: Organismo de direito público\nÁrea de atividade da Autoridade Adjudicante: Serviços públicos das administrações públicas\n\n2 - JORNAL OFICIAL DA UNIÃO EUROPEIA\nO procedimento a que este anúncio diz respeito também é publicitado no Jornal Oficial da União Europeia? Não\n\n3 - AVISO\nModelo de Anúncio: Concurso público\nData de Envio do Anúncio: 16-10-2025\n\n5 - PROCESSO\nTipo de Procedimento: Concurso público\nPreço base do procedimento: Sim\nValor do preço base do procedimento: 107.250,00 EUR\nProcedimento com lotes? Não\n\n6 - OBJETO DO CONTRATO\nNúmero de referência interna: 115/2025\nDesignação do contrato: Aquisição de serviços de  recolha, transporte, tratamento e contagem de valores de valores de bilheteiras  assistidas e MAVTS \nDescrição: Aquisição de serviços de recolha, transporte, tratamento e contagem de valores de valores de bilheteiras assistidas e MAVTS de todos os Terminais e estações Fluviais da TTSL.\nTipo de Contrato Principal: Aquisição de Serviços\nTipo de Contrato: Aquisição de Serviços\nClassificação CPV (Vocabulário Comum para os Contratos Públicos)\nObjeto principal\nVocabulário Principal: 79710000\nPreço base s/IVA: 107.250,00 EUR\n\n7 - INDICAÇÕES ADICIONAIS\nO contrato envolve aquisição conjunta (satisfação de várias entidades)? Não\nO contrato é adjudicado por uma central de compras? Não\n\n8 - TÉCNICAS\nO concurso destina-se à celebração de um acordo-quadro? Inexistência de acordo-quadro\nÉ utilizado um leilão eletrónico? Não\nÉ adotada uma fase de negociação? Não\nSistema de Aquisição Dinâmico: Inexistência de sistema de aquisição dinâmico\n\n9 - LOCAL DA EXECUÇÃO DO CONTRATO\nLOCAL DA EXECUÇÃO DO CONTRATO (PROCEDIMENTO)\nPaís: Portugal\nNUT III: PT170\nLocalidade: Lisboa\nDistrito: Lisboa\nConcelho: Lisboa\nFreguesia: Todas\n\n10 - PRAZO DE EXECUÇÃO DO CONTRATO\nPrazo de execução do contrato: 13 MESES\nPrevisão de renovações: Não\n\n11 - FUNDOS EU\nTêm fundos EU? Não\n\n12 - DOCUMENTOS DE HABILITAÇÃO\nHabilitação para o exercício da atividade profissional: Não\n\n13 - CONDIÇÕES DE APRESENTAÇÃO\nPlataforma eletrónica utilizada pela entidade adjudicante: VORTAL\nURL para Apresentação: https://community.vortal.biz/public/\nAdmissibilidade da apresentação de propostas variantes: Não autorizado\nPrazo para apresentação das propostas: 28-10-2025 17:00\nPrazo durante o qual os concorrentes são obrigados a manter as respetivas propostas: 180 dias a contar do termo do prazo para a apresentação das propostas\nIndicação de Subcontratação na Proposta: Inexistência de indicação de subcontratação\n\n14 - PRESTAÇÃO DE CAUÇÃO\nPrestação de caução: Não\n\n15 - FORNECIMENTO DAS PEÇAS DO CONCURSO, APRESENTAÇÃO DE PEDIDOS DE PARTICIPAÇÃO E APRESENTAÇÃO DAS PROPOSTAS\nLink para acesso às peças do concurso (URL): https://community.vortal.biz/Public/public-tender-documents/QWNNaXd3a1UwVS9nUTBmNWkrV0RVYUNuYnJwMWxRZzBodklHTG1vek1CQ3IyVG0wYWw2YXk1VGErd0hVMUZWKzBTWmhxcFJHellqMUZuc1J5QVA1WVE9PVA3NThT\n\n20 - OUTROS REQUISITOS\nInformação sobre contratos reservados. Aplica-se a contratos reservados (54º-A)? Não\n\n21 - CRITÉRIO DE ADJUDICAÇÃO\nMultifator: Não\nMonofator:\nNome: Preço\n\n24 - CONDIÇÕES DO CONTRATO\nFaturação Eletrónica: Permitido\nObrigação de Subcontratação:\nCódigo da Obrigação de Subcontratação: Não é aplicável nenhuma obrigação de subcontratação.\n\n25 - COMPRA PÚBLICA ESTRATÉGICA\nCompra Pública Estratégica: Inexistência de contratação pública estratégica\n\n26 - INFORMAÇÕES ADICIONAIS\nContrato adequado para PME: Sim\nCobertura ACP (Acordo dos Contratos Públicos da Organização Mundial do Comércio): Não\n\n27 - IDENTIFICAÇÃO E CONTACTOS DO ÓRGÃO DE RECURSOS ADMINISTRATIVOS\nDesignação: TTSL-Transtejo Soflusa, S.A.\nEndereço: Rua da Cintura do Porto de Lisboa, Terminal Fluvial do Cais do Sodré\nCódigo postal: 1249-249\nLocalidade: Lisboa\nTelefone: +351 210422400\nFax: +351 210422499\nEndereço eletrónico: contratacao@ttsl.pt\n\n28 - IDENTIFICAÇÃO DO(S) AUTOR(ES) DE ANÚNCIO\nNome: Carolina Fernandes Gaspar Alberto\nCargo: Técnico Superior\n419664641",
    "nipc": "500723770",
    "distrito": "Lisboa",
    "concelho": "Lisboa",
    "freguesia": "Todas",
    "site": "www.transtejo.pt",
    "email": "contratacao@transtejo.pt",
    "designacao_contrato": "Aquisição de serviços de recolha, transporte, tratamento e contagem de valores de valores de bilheteiras assistidas e MAVTS",
    "descricao": "Aquisição de serviços de recolha, transporte, tratamento e contagem de valores de valores de bilheteiras assistidas e MAVTS de todos os Terminais e estações Fluviais da TTSL.",
    "preco_base": "107.250,00 EUR",
    "prazo_execucao": "13 MESES",
    "prazo_apresentacao_propostas": "28-10-2025 17:00",
    "fundos_eu": "Não",
    "plataforma_eletronica": "VORTAL",
    "url_procedimento": "https://community.vortal.biz/public/",
    "autor_nome": "Carolina Fernandes Gaspar Alberto",
    "autor_cargo": "Técnico Superior"
  },
  {
    "numero_procedimento": "N/A",
    "entidade": "Serviços Municipalizados de Alcobaça",
    "link": "https://diariodarepublica.pt/dr/detalhe/contrato-publico/27388-940560156",
    "detalhes_completos": "Alteração do Anúncio de procedimento n.º 26460/2025, de 2025-10-08, com o ID 419628823\n\n1 - IDENTIFICAÇÃO E CONTACTOS DA ENTIDADE ADJUDICANTE\nDesignação da entidade adjudicante: Serviços Municipalizados de Alcobaça\nNIPC: 680014942\nServiço/Órgão/Pessoa de contacto: Divisão Jurídica e de Contratação Pública\nEndereço: Rua da Liberdade, n.º 9\nCódigo postal: 2460-060\nLocalidade: Alcobaça\nPaís: Portugal\nNUT III: PT16B\nDistrito: Leiria\nConcelho: Alcobaça\nFreguesia: Todas\nTelefone: 262580910\nFax: 262580905\nEndereço da Entidade (URL): www.smalcobaca.pt\nEndereço Eletrónico: geral@sm-alcobaca.pt\neDelivery Gateway (URL): https://www.acingov.pt\nFunção da Organização: Adquirente\nNorma jurídica da Entidade Adjudicante: Organismo de direito público\nÁrea de atividade da Entidade Adjudicante: Atividades relacionadas com a água\n\n2 - JORNAL OFICIAL DA UNIÃO EUROPEIA\nO procedimento a que este anúncio diz respeito também é publicitado no Jornal Oficial da União Europeia? Não\n\n3 - AVISO\nModelo de Anúncio: Concurso público\nData de Envio do Anúncio: 16-10-2025\n\n5 - PROCESSO\nTipo de Procedimento: Concurso público\nPreço base do procedimento: Sim\nValor do preço base do procedimento: 122.976,00 EUR\nProcedimento com lotes? Não\n\n6 - OBJETO DO CONTRATO\nNúmero de referência interna: 51/25/CP\nDesignação do contrato: Procedimento n.º 51/25/CP - Aquisição de Serviços de Seguros (Frota Automóvel e Responsabilidade Civil)\nDescrição: Procedimento n.º 51/25/CP - Aquisição de Serviços de Seguros (Frota Automóvel e Responsabilidade Civil)\nTipo de Contrato Principal: Aquisição de Serviços\nTipo de Contrato: Aquisição de Serviços\nClassificação CPV (Vocabulário Comum para os Contratos Públicos)\nObjeto principal\nVocabulário Principal: 66510000\nPreço base s/IVA: 122.976,00 EUR\n\n7 - INDICAÇÕES ADICIONAIS\nO contrato envolve aquisição conjunta (satisfação de várias entidades)? Não\nO contrato é adjudicado por uma central de compras? Não\n\n8 - TÉCNICAS\nO concurso destina-se à celebração de um acordo-quadro? Inexistência de acordo-quadro\nÉ utilizado um leilão eletrónico? Não\nÉ adotada uma fase de negociação? Não\nSistema de Aquisição Dinâmico: Inexistência de sistema de aquisição dinâmico\n\n9 - LOCAL DA EXECUÇÃO DO CONTRATO\nLOCAL DA EXECUÇÃO DO CONTRATO (PROCEDIMENTO)\nPaís: Portugal\nNUT III: PT16B\nLocalidade: União das Freguesias de Alcobaça e Vestiaria\nDistrito: Leiria\nConcelho: Alcobaça\nFreguesia: União das Freguesias de Alcobaça e Vestiaria\n\n10 - PRAZO DE EXECUÇÃO DO CONTRATO\nPrazo de execução do contrato: 36 MESES\nPrevisão de renovações: Sim\nIndicar número máximo de renovações: 2\nPrazo de renovações diferente do prazo inicial: Não\n\n11 - FUNDOS EU\nTêm fundos EU? Não\n\n12 - DOCUMENTOS DE HABILITAÇÃO\nHabilitação para o exercício da atividade profissional: Não\n\n13 - CONDIÇÕES DE APRESENTAÇÃO\nPlataforma eletrónica utilizada pela entidade adjudicante: ACIN\nURL para Apresentação: https://www.acingov.pt\nAdmissibilidade da apresentação de propostas variantes: Não autorizado\nPrazo para apresentação das propostas: 31-10-2025 23:59\nPrazo durante o qual os concorrentes são obrigados a manter as respetivas propostas: 120 dias a contar do termo do prazo para a apresentação das propostas\nIndicação de Subcontratação na Proposta: Inexistência de indicação de subcontratação\n\n14 - PRESTAÇÃO DE CAUÇÃO\nPrestação de caução: Não\n\n15 - FORNECIMENTO DAS PEÇAS DO CONCURSO, APRESENTAÇÃO DE PEDIDOS DE PARTICIPAÇÃO E APRESENTAÇÃO DAS PROPOSTAS\nLink para acesso às peças do concurso (URL): https://www.acingov.pt/acingovprod/2/zonaPublica/zona_publica_c/donwloadProcedurePiece/OTg0MTI3\n\n20 - OUTROS REQUISITOS\nInformação sobre contratos reservados. Aplica-se a contratos reservados (54º-A)? Não\n\n21 - CRITÉRIO DE ADJUDICAÇÃO\nMultifator: Não\nMonofator:\nNome: Outros\nOutro nome: Fator Preço\n\n24 - CONDIÇÕES DO CONTRATO\nFaturação Eletrónica: Permitido\nObrigação de Subcontratação:\nCódigo da Obrigação de Subcontratação: Não é aplicável nenhuma obrigação de subcontratação.\n\n25 - COMPRA PÚBLICA ESTRATÉGICA\nCompra Pública Estratégica: Inexistência de contratação pública estratégica\n\n26 - INFORMAÇÕES ADICIONAIS\nContrato adequado para PME: Não\nCobertura ACP (Acordo dos Contratos Públicos da Organização Mundial do Comércio): Não\n\n27 - IDENTIFICAÇÃO E CONTACTOS DO ÓRGÃO DE RECURSOS ADMINISTRATIVOS\nDesignação: Conselho de Administração\nEndereço: Rua da Liberdade, n.º 9\nCódigo postal: 2460-060\nLocalidade: Alcobaça\nTelefone: 262580910\nFax: \nEndereço eletrónico: geral@sm-alcobaca.pt\n\n28 - IDENTIFICAÇÃO DO(S) AUTOR(ES) DE ANÚNCIO\nNome: Susana Paula Ferreira Guerra Jordão\nCargo: Presidente do Conselho de Administração\n\n29 - ALTERAÇÃO\nMotivo da Alteração: Correção pelo adquirente\nIdentificador da Versão do Anúncio a Alterar: 5c14e752-85a4-4d94-a454-7918862aba99-02\nIdentificador das Secções Alteradas do Anúncio Anterior: Condições de Apresentação\nDescrição das Alterações: Modificação do prazo para a apresentação de propostas\nAlteração dos Documentos do Concurso: Sim\nData de alteração dos documentos do concurso: 16-10-2025\n419668246",
    "nipc": "680014942",
    "distrito": "Leiria",
    "concelho": "Alcobaça",
    "freguesia": "Todas",
    "site": "www.smalcobaca.pt",
    "email": "geral@sm-alcobaca.pt",
    "designacao_contrato": "Procedimento n.º 51/25/CP - Aquisição de Serviços de Seguros (Frota Automóvel e Responsabilidade Civil)",
    "descricao": "Procedimento n.º 51/25/CP - Aquisição de Serviços de Seguros (Frota Automóvel e Responsabilidade Civil)",
    "preco_base": "122.976,00 EUR",
    "prazo_execucao": "36 MESES",
    "prazo_apresentacao_propostas": "31-10-2025 23:59",
    "fundos_eu": "Não",
    "plataforma_eletronica": "ACIN",
    "url_procedimento": "https://www.acingov.pt",
    "autor_nome": "Susana Paula Ferreira Guerra Jordão",
    "autor_cargo": "Presidente do Conselho de Administração"
  },
  {
    "numero_procedimento": "N/A",
    "entidade": "AR - Águas do Ribatejo, E. I. M., S. A.",
    "link": "https://diariodarepublica.pt/dr/detalhe/contrato-publico/27389-940560157",
    "detalhes_completos": "1 - IDENTIFICAÇÃO E CONTACTOS DA ENTIDADE ADJUDICANTE\nDesignação da entidade adjudicante: AR - Águas do Ribatejo, E. I. M., S. A.\nNIPC: 508345464\nEndereço: Rua Gaspar Costa Ramalho, nº38\nCódigo postal: 2120-098\nLocalidade: Santarém\nPaís: Portugal\nNUT III: PT185\nDistrito: Santarém\nConcelho: Salvaterra de Magos\nFreguesia: União das Freguesias de Salvaterra de Magos e Foros de Salvaterra\nTelefone: 243303240\nEndereço da Entidade (URL): www.aguasdoribatejo.com\nEndereço Eletrónico: geral@aguasdoribatejo.com\neDelivery Gateway (URL): https://community.vortal.biz/public/\nFunção da Organização: Adquirente\nNorma jurídica da Entidade Adjudicante: Empresa pública, controlada por uma autoridade local\nÁrea de atividade da Autoridade Adjudicante: Proteção ambiental\n\n2 - JORNAL OFICIAL DA UNIÃO EUROPEIA\nO procedimento a que este anúncio diz respeito também é publicitado no Jornal Oficial da União Europeia? Sim\n\n3 - AVISO\nModelo de Anúncio: Concurso público\nData de Envio do Anúncio: 14-10-2025\n\n5 - PROCESSO\nTipo de Procedimento: Concurso público\nPreço base do procedimento: Sim\nValor do preço base do procedimento: 2.200.000,00 EUR\nProcedimento com lotes? Não\n\n6 - OBJETO DO CONTRATO\nNúmero de referência interna: EMP/011/2025\nDesignação do contrato: Empreitada para a reabilitação de infraestruturas no subsistema de abastecimento de água de Coruche / Valverde / Fajarda\nDescrição: Reabilitação de infraestruturas no subsistema de abastecimento de água de Coruche / Valverde / Fajarda\nOpções: Não\nTipo de Contrato Principal: Empreitada de Obras Públicas\nTipo de Contrato: Empreitada de Obras Públicas\nClassificação CPV (Vocabulário Comum para os Contratos Públicos)\nObjeto principal\nVocabulário Principal: 45232151\nPreço base s/IVA: 2.200.000,00 EUR\n\n7 - INDICAÇÕES ADICIONAIS\nO contrato envolve aquisição conjunta (satisfação de várias entidades)? Não\nO contrato é adjudicado por uma central de compras? Não\n\n8 - TÉCNICAS\nO concurso destina-se à celebração de um acordo-quadro? Inexistência de acordo-quadro\nÉ utilizado um leilão eletrónico? Não\nÉ adotada uma fase de negociação? Não\nSistema de Aquisição Dinâmico: Inexistência de sistema de aquisição dinâmico\n\n9 - LOCAL DA EXECUÇÃO DO CONTRATO\nLOCAL DA EXECUÇÃO DO CONTRATO (PROCEDIMENTO)\nPaís: Portugal\nNUT III: PT185\nLocalidade: Coruche\nDistrito: Santarém\nConcelho: Coruche\nFreguesia: União das Freguesias de Coruche, Fajarda e Erra\n\n10 - PRAZO DE EXECUÇÃO DO CONTRATO\nPrazo de execução do contrato: 660 DIAS\nPrevisão de renovações: Não\n\n11 - FUNDOS EU\nTêm fundos EU? Sim\n\n12 - DOCUMENTOS DE HABILITAÇÃO\nHabilitação para o exercício da atividade profissional: Sim\nTipo: Outros\nDescrição - Outros: Conforme programa de concurso\nDescrição: Conforme programa do concurso.\n\n13 - CONDIÇÕES DE APRESENTAÇÃO\nPlataforma eletrónica utilizada pela entidade adjudicante: VORTAL\nURL para Apresentação: https://community.vortal.biz/public/\nAdmissibilidade da apresentação de propostas variantes: Não autorizado\nPrazo para apresentação das propostas: 13-11-2025 23:59\nPrazo durante o qual os concorrentes são obrigados a manter as respetivas propostas: 180 dias a contar do termo do prazo para a apresentação das propostas\nApresentação de Catálogo Eletrónico: Permitido\nIndicação de Subcontratação na Proposta: Inexistência de indicação de subcontratação\n\n14 - PRESTAÇÃO DE CAUÇÃO\nPrestação de caução: Sim\nPercentagem: 5%\nDescrição da Garantia Exigida: Conforme programa do concurso.\n\n15 - FORNECIMENTO DAS PEÇAS DO CONCURSO, APRESENTAÇÃO DE PEDIDOS DE PARTICIPAÇÃO E APRESENTAÇÃO DAS PROPOSTAS\nLink para acesso às peças do concurso (URL): https://community.vortal.biz/Public/public-tender-documents/Z01jU2hlWWNENzFIWTRXWUVBbkZtOWUrVVZEcllCQzkzY1BNRlAyRlFTbkdHUFNLcFF1cStSYi9IMjF1U3licGtHVkpBbjE3WStueUhpQ1VLY1ZKb2c9PUxIX3RY\n\n20 - OUTROS REQUISITOS\nInformação sobre contratos reservados. Aplica-se a contratos reservados (54º-A)? Não\n\n21 - CRITÉRIO DE ADJUDICAÇÃO\nMultifator: Não\nMonofator:\nNome: Preço\n\n24 - CONDIÇÕES DO CONTRATO\nFaturação Eletrónica: Permitido\nObrigação de Subcontratação:\nCódigo da Obrigação de Subcontratação: Não é aplicável nenhuma obrigação de subcontratação.\n\n25 - COMPRA PÚBLICA ESTRATÉGICA\nCompra Pública Estratégica: Inexistência de contratação pública estratégica\n\n26 - INFORMAÇÕES ADICIONAIS\nContrato adequado para PME: Sim\nCobertura ACP (Acordo dos Contratos Públicos da Organização Mundial do Comércio): Não\n\n27 - IDENTIFICAÇÃO E CONTACTOS DO ÓRGÃO DE RECURSOS ADMINISTRATIVOS\nDesignação: Conselho de Administração da AR - Águas do Ribatejo, EIM, SA\nEndereço: Rua Gaspar Costa Ramalho, 38\nCódigo postal: 2120-098\nLocalidade: Salvaterra de Magos\nTelefone: +351 263509400\nFax: +351 263509499\nEndereço eletrónico: geral@aguasdoribatejo.com\n\n28 - IDENTIFICAÇÃO DO(S) AUTOR(ES) DE ANÚNCIO\nNome: Francisco Silvestre de Oliveira\nCargo: Presidente do Conselho de Administração\n419653211",
    "nipc": "508345464",
    "distrito": "Santarém",
    "concelho": "Salvaterra de Magos",
    "freguesia": "União das Freguesias de Salvaterra de Magos e Foros de Salvaterra",
    "site": "www.aguasdoribatejo.com",
    "email": "geral@aguasdoribatejo.com",
    "designacao_contrato": "Empreitada para a reabilitação de infraestruturas no subsistema de abastecimento de água de Coruche / Valverde / Fajarda",
    "descricao": "Reabilitação de infraestruturas no subsistema de abastecimento de água de Coruche / Valverde / Fajarda",
    "preco_base": "2.200.000,00 EUR",
    "prazo_execucao": "660 DIAS",
    "prazo_apresentacao_propostas": "13-11-2025 23:59",
    "fundos_eu": "Sim",
    "plataforma_eletronica": "VORTAL",
    "url_procedimento": "https://community.vortal.biz/public/",
    "autor_nome": "Francisco Silvestre de Oliveira",
    "autor_cargo": "Presidente do Conselho de Administração"
  },
  {
    "numero_procedimento": "N/A",
    "entidade": "Agrupamento Vertical de Canelas",
    "link": "https://diariodarepublica.pt/dr/detalhe/contrato-publico/27391-940560158",
    "detalhes_completos": "1 - IDENTIFICAÇÃO E CONTACTOS DA ENTIDADE ADJUDICANTE\nDesignação da entidade adjudicante: Agrupamento Vertical de Canelas\nNIPC: 600077080\nEndereço: Rua Delfim Lima, Apartado 512\nCódigo postal: 4411-701\nLocalidade: Área Metropolitana do Porto\nPaís: Portugal\nNUT III: PT11A\nDistrito: Porto\nConcelho: Vila Nova de Gaia\nFreguesia: Freguesia de Canelas - Vila Nova de Gaia\nTelefone: +351227116852\nFax: +351227169759\nEndereço da Entidade (URL): https://agrcanelas.edu.pt/\nEndereço Eletrónico: direcao.geral@agrcanelas.edu.pt\neDelivery Gateway (URL): https://community.vortal.biz/public/\nFunção da Organização: Adquirente\nNorma jurídica da Entidade Adjudicante: Organismo de direito público\nÁrea de atividade da Autoridade Adjudicante: Educação\n\n2 - JORNAL OFICIAL DA UNIÃO EUROPEIA\nO procedimento a que este anúncio diz respeito também é publicitado no Jornal Oficial da União Europeia? Não\n\n3 - AVISO\nModelo de Anúncio: Concurso público\nData de Envio do Anúncio: 16-10-2025\n\n5 - PROCESSO\nTipo de Procedimento: Concurso público\nPreço base do procedimento: Sim\nValor do preço base do procedimento: 116.918,00 EUR\nProcedimento com lotes? Não\n\n6 - OBJETO DO CONTRATO\nNúmero de referência interna: CTE_2025_06\nDesignação do contrato: Aquisição de mobiliário\nDescrição: Aquisição de mobiliário\nTipo de Contrato Principal: Aquisição de Bens Móveis\nTipo de Contrato: Aquisição de Bens Móveis\nClassificação CPV (Vocabulário Comum para os Contratos Públicos)\nObjeto principal\nVocabulário Principal: 39160000\nPreço base s/IVA: 116.918,00 EUR\n\n7 - INDICAÇÕES ADICIONAIS\nO contrato envolve aquisição conjunta (satisfação de várias entidades)? Não\nO contrato é adjudicado por uma central de compras? Não\n\n8 - TÉCNICAS\nO concurso destina-se à celebração de um acordo-quadro? Inexistência de acordo-quadro\nÉ utilizado um leilão eletrónico? Não\nÉ adotada uma fase de negociação? Não\nSistema de Aquisição Dinâmico: Inexistência de sistema de aquisição dinâmico\n\n9 - LOCAL DA EXECUÇÃO DO CONTRATO\nLOCAL DA EXECUÇÃO DO CONTRATO (PROCEDIMENTO)\nPaís: Portugal\nNUT III: PT11A\nLocalidade: Área Metropolitana do Porto\nDistrito: Porto\nConcelho: Vila Nova de Gaia\nFreguesia: Todas\n\n10 - PRAZO DE EXECUÇÃO DO CONTRATO\nPrazo de execução do contrato: 60 DIAS\nPrevisão de renovações: Não\n\n11 - FUNDOS EU\nTêm fundos EU? Sim\n\n12 - DOCUMENTOS DE HABILITAÇÃO\nHabilitação para o exercício da atividade profissional: Não\n\n13 - CONDIÇÕES DE APRESENTAÇÃO\nPlataforma eletrónica utilizada pela entidade adjudicante: VORTAL\nURL para Apresentação: https://community.vortal.biz/public/\nAdmissibilidade da apresentação de propostas variantes: Não autorizado\nPrazo para apresentação das propostas: 24-10-2025 23:59\nPrazo durante o qual os concorrentes são obrigados a manter as respetivas propostas: 66 dias a contar do termo do prazo para a apresentação das propostas\nIndicação de Subcontratação na Proposta: Inexistência de indicação de subcontratação\n\n14 - PRESTAÇÃO DE CAUÇÃO\nPrestação de caução: Não\n\n15 - FORNECIMENTO DAS PEÇAS DO CONCURSO, APRESENTAÇÃO DE PEDIDOS DE PARTICIPAÇÃO E APRESENTAÇÃO DAS PROPOSTAS\nLink para acesso às peças do concurso (URL): https://community.vortal.biz/Public/public-tender-documents/S09LWVNJTkxvS3hwcDdnUitpSzhxT3R5UWlyQmVSNnZmNy9xRW5HekNhekdwR0VhMUlKQnB0VXl2eEMzQWxXZE1MbjlKTnd3d2tHZVJWMFhJMXRwSmc9PXJOKlhz\n\n20 - OUTROS REQUISITOS\nInformação sobre contratos reservados. Aplica-se a contratos reservados (54º-A)? Não\n\n21 - CRITÉRIO DE ADJUDICAÇÃO\nMultifator: Não\nMonofator:\nNome: Preço\n\n24 - CONDIÇÕES DO CONTRATO\nFaturação Eletrónica: Permitido\nObrigação de Subcontratação:\nCódigo da Obrigação de Subcontratação: Não é aplicável nenhuma obrigação de subcontratação.\n\n25 - COMPRA PÚBLICA ESTRATÉGICA\nCompra Pública Estratégica: Inexistência de contratação pública estratégica\n\n26 - INFORMAÇÕES ADICIONAIS\nContrato adequado para PME: Sim\nCobertura ACP (Acordo dos Contratos Públicos da Organização Mundial do Comércio): Não\n\n27 - IDENTIFICAÇÃO E CONTACTOS DO ÓRGÃO DE RECURSOS ADMINISTRATIVOS\nDesignação: Conselho Administrativo do Agrupamento de Escolas de Canelas\nEndereço: Rua Delfim de Lima, Apartado 512\nCódigo postal: 4411-701\nLocalidade: Vila Nova de Gaia\nTelefone: +351 227116852\nFax: +351 227169759\nEndereço eletrónico: propostas.ccp@agrcanelas.edu.pt\n\n28 - IDENTIFICAÇÃO DO(S) AUTOR(ES) DE ANÚNCIO\nNome: Filipe José Serra Moreira Ferreira\nCargo: Diretor do Agrupamento de Escolas de Canelas\n419663418",
    "nipc": "600077080",
    "distrito": "Porto",
    "concelho": "Vila Nova de Gaia",
    "freguesia": "Freguesia de Canelas - Vila Nova de Gaia",
    "site": "https://agrcanelas.edu.pt/",
    "email": "direcao.geral@agrcanelas.edu.pt",
    "designacao_contrato": "Aquisição de mobiliário",
    "descricao": "Aquisição de mobiliário",
    "preco_base": "116.918,00 EUR",
    "prazo_execucao": "60 DIAS",
    "prazo_apresentacao_propostas": "24-10-2025 23:59",
    "fundos_eu": "Sim",
    "plataforma_eletronica": "VORTAL",
    "url_procedimento": "https://community.vortal.biz/public/",
    "autor_nome": "Filipe José Serra Moreira Ferreira",
    "autor_cargo": "Diretor do Agrupamento de Escolas de Canelas"
  },
  {
    "numero_procedimento": "N/A",
    "entidade": "Instituto da Conservação da Natureza e das Florestas, I. P.",
    "link": "https://diariodarepublica.pt/dr/detalhe/contrato-publico/27392-940560159",
    "detalhes_completos": "1 - IDENTIFICAÇÃO E CONTACTOS DA ENTIDADE ADJUDICANTE\nDesignação da entidade adjudicante: Instituto da Conservação da Natureza e das Florestas, I. P.\nNIPC: 510342647\nEndereço: Av. Dr. Alfredo Magalhães Ramalho, nº 1\nCódigo postal: 1495-165\nLocalidade: Lisboa\nPaís: Portugal\nNUT III: PT170\nDistrito: Lisboa\nConcelho: Oeiras\nFreguesia: União das Freguesias de Algés, Linda-a-Velha e Cruz Quebrada-Dafundo\nTelefone: 213124800\nFax: 213124800\nEndereço da Entidade (URL): https://www.icnf.pt/\nEndereço Eletrónico: geral@icnf.pt\neDelivery Gateway (URL): https://community.vortal.biz/public/\nFunção da Organização: Adquirente\nNorma jurídica da Entidade Adjudicante: Instituição, órgão ou agência da UE\nÁrea de atividade da Autoridade Adjudicante: Proteção ambiental\n\n2 - JORNAL OFICIAL DA UNIÃO EUROPEIA\nO procedimento a que este anúncio diz respeito também é publicitado no Jornal Oficial da União Europeia? Sim\n\n3 - AVISO\nModelo de Anúncio: Concurso público\nData de Envio do Anúncio: 14-10-2025\n\n5 - PROCESSO\nTipo de Procedimento: Concurso público\nPreço base do procedimento: Sim\nValor do preço base do procedimento: 22.544.500,00 EUR\nProcedimento com lotes? Sim\nNº Máx. de Lotes Autorizado: 2\nNúmero máximo de lotes que podem ser adjudicados a um concorrente: 2\n\n6 - OBJETO DO CONTRATO\nNúmero de referência interna: CP/39/2025/ICNF/SEDE\nDesignação do contrato: Aquisição de 218 unidades de maquinaria pesada (tratores) e respetivas alfaias destinadas à prevenção e combate de fogos rurais\nDescrição: Aquisição de 218 unidades de maquinaria pesada (tratores) e respetivas alfaias destinadas à prevenção e combate de fogos rurais\nOpções: Não\nTipo de Contrato Principal: Aquisição de Bens Móveis\nTipo de Contrato: Aquisição de Bens Móveis\nClassificação CPV (Vocabulário Comum para os Contratos Públicos)\nObjeto principal\nVocabulário Principal: 34100000\nPreço base s/IVA: 22.544.500,00 EUR\nLotes: \nNº: LOT-0001\nDescrição do Lote: Trator florestal de tipo 1 (51 unidades) e respetivas alfaias\nPreço base s/IVA: 5.176.500,00 EUR\nClassificação CPV (Vocabulário Comum para os Contratos Públicos)\nObjeto principal\nVocabulário Principal: 34100000\nNº: LOT-0002\nDescrição do Lote: Trator florestal de tipo 2 (167 unidades) e respetiva alfaia\nPreço base s/IVA: 17.368.000,00 EUR\nClassificação CPV (Vocabulário Comum para os Contratos Públicos)\nObjeto principal\nVocabulário Principal: 34100000\n\n7 - INDICAÇÕES ADICIONAIS\nO contrato envolve aquisição conjunta (satisfação de várias entidades)? Não\nO contrato é adjudicado por uma central de compras? Não\n\n8 - TÉCNICAS\nO concurso destina-se à celebração de um acordo-quadro? Inexistência de acordo-quadro\nÉ utilizado um leilão eletrónico? Não\nÉ adotada uma fase de negociação? Não\nSistema de Aquisição Dinâmico: Inexistência de sistema de aquisição dinâmico\n\n9 - LOCAL DA EXECUÇÃO DO CONTRATO\nLOCAL DA EXECUÇÃO DO CONTRATO (PROCEDIMENTO)\nPaís: Portugal\nNUT III: PT170\nLocalidade: Lisboa\nDistrito: Lisboa\nConcelho: Lisboa\nFreguesia: Freguesia de Avenidas Novas\nLOCAL DA EXECUÇÃO DO CONTRATO (LOTE)\nIdentificador do Lote: LOT-0001; LOT-0002\nPaís: Portugal\nNUT III: PT170\nLocalidade: Lisboa\nDistrito: Lisboa\nConcelho: Lisboa\nFreguesia: Freguesia de Avenidas Novas\n\n10 - PRAZO DE EXECUÇÃO DO CONTRATO\nIdentificador do Lote: LOT-0001; LOT-0002\nPrazo de execução do contrato: 150 DIAS\nPrevisão de renovações: Não\n\n11 - FUNDOS EU\nIdentificador do Lote: LOT-0001; LOT-0002\nTêm fundos EU? Sim\n\n12 - DOCUMENTOS DE HABILITAÇÃO\nHabilitação para o exercício da atividade profissional: Não\n\n13 - CONDIÇÕES DE APRESENTAÇÃO\nPlataforma eletrónica utilizada pela entidade adjudicante: VORTAL\nURL para Apresentação: https://community.vortal.biz/public/\nAdmissibilidade da apresentação de propostas variantes: Não autorizado\nPrazo para apresentação das propostas: 13-11-2025 23:59\nPrazo durante o qual os concorrentes são obrigados a manter as respetivas propostas: 88 dias a contar do termo do prazo para a apresentação das propostas\nApresentação de Catálogo Eletrónico: Não autorizado\nIndicação de Subcontratação na Proposta: Inexistência de indicação de subcontratação\n\n14 - PRESTAÇÃO DE CAUÇÃO\nPrestação de caução: Sim\nPercentagem: 3.5%\nDescrição da Garantia Exigida: Conforme peças do procedimento\n\n15 - FORNECIMENTO DAS PEÇAS DO CONCURSO, APRESENTAÇÃO DE PEDIDOS DE PARTICIPAÇÃO E APRESENTAÇÃO DAS PROPOSTAS\nLink para acesso às peças do concurso (URL): https://community.vortal.biz/Public/public-tender-documents/YUhzaUw2ZlYyTnNkbXNJQXJib2QxdC9zd3FoM2ZUaUs4UGgvVm1zZTRyMUx2N21yMkdYN216WFN3bStYNkN4NUdLZXdoVUo0K1hSWnVXYk5ya3NpMVE9PU5sRUs4\n\n20 - OUTROS REQUISITOS\nIdentificador do Lote: LOT-0001; LOT-0002\nInformação sobre contratos reservados. Aplica-se a contratos reservados (54º-A)? Não\n\n21 - CRITÉRIO DE ADJUDICAÇÃO\nO Critério de adjudicação é diferenciado por lote? Não\nMultifator: Não\nMonofator:\nNome: Outros\nOutro nome: Preço global\n\n24 - CONDIÇÕES DO CONTRATO\nIdentificador do Lote: LOT-0001; LOT-0002\nFaturação Eletrónica: Permitido\nObrigação de Subcontratação:\nCódigo da Obrigação de Subcontratação: Não é aplicável nenhuma obrigação de subcontratação.\n\n25 - COMPRA PÚBLICA ESTRATÉGICA\nCompra Pública Estratégica: Inexistência de contratação pública estratégica\n\n26 - INFORMAÇÕES ADICIONAIS\nIdentificador do Lote: LOT-0001; LOT-0002\nContrato adequado para PME: Sim\nCobertura ACP (Acordo dos Contratos Públicos da Organização Mundial do Comércio): Não\n\n27 - IDENTIFICAÇÃO E CONTACTOS DO ÓRGÃO DE RECURSOS ADMINISTRATIVOS\nDesignação: Conselho Diretivo do ICNF, I. P.\nEndereço: Av. Dr. Alfredo Magalhães Ramalho 1\nCódigo postal: 1495-165\nLocalidade: Oeiras\nTelefone: +351 213507900\nFax: +351 000000000\nEndereço eletrónico: geral@icnf.pt\n\n28 - IDENTIFICAÇÃO DO(S) AUTOR(ES) DE ANÚNCIO\nNome: José Nascimento\nCargo: Perito\n419655456",
    "nipc": "510342647",
    "distrito": "Lisboa",
    "concelho": "Oeiras",
    "freguesia": "União das Freguesias de Algés, Linda-a-Velha e Cruz Quebrada-Dafundo",
    "site": "https://www.icnf.pt/",
    "email": "geral@icnf.pt",
    "designacao_contrato": "Aquisição de 218 unidades de maquinaria pesada (tratores) e respetivas alfaias destinadas à prevenção e combate de fogos rurais",
    "descricao": "Aquisição de 218 unidades de maquinaria pesada (tratores) e respetivas alfaias destinadas à prevenção e combate de fogos rurais",
    "preco_base": "22.544.500,00 EUR",
    "prazo_execucao": "150 DIAS",
    "prazo_apresentacao_propostas": "13-11-2025 23:59",
    "fundos_eu": "Sim",
    "plataforma_eletronica": "VORTAL",
    "url_procedimento": "https://community.vortal.biz/public/",
    "autor_nome": "José Nascimento",
    "autor_cargo": "Perito"
  },
  {
    "numero_procedimento": "N/A",
    "entidade": "INEGI - Instituto de Engenharia Mecânica e Gestão Industrial",
    "link": "https://diariodarepublica.pt/dr/detalhe/contrato-publico/27393-940560160",
    "detalhes_completos": "1 - IDENTIFICAÇÃO E CONTACTOS DA ENTIDADE ADJUDICANTE\nDesignação da entidade adjudicante: INEGI - Instituto de Engenharia Mecânica e Gestão Industrial\nNIPC: 501814957\nServiço/Órgão/Pessoa de contacto: Gestão Administrativa e Financeira\nEndereço: Campus da FEUP, R. Dr. Roberto Frias 400\nCódigo postal: 4200-465\nLocalidade: Paranhos\nPaís: Portugal\nNUT III: PT11A\nDistrito: Porto\nConcelho: Porto\nFreguesia: Freguesia de Paranhos - Porto\nTelefone: 229578710\nFax: 229537352\nEndereço da Entidade (URL): www.inegi.pt\nEndereço Eletrónico: inegi@inegi.up.pt\neDelivery Gateway (URL): https://www.acingov.pt\nFunção da Organização: Adquirente\nNorma jurídica da Entidade Adjudicante: Organismo de direito público\nÁrea de atividade da Autoridade Adjudicante: Serviços públicos das administrações públicas\n\n2 - JORNAL OFICIAL DA UNIÃO EUROPEIA\nO procedimento a que este anúncio diz respeito também é publicitado no Jornal Oficial da União Europeia? Não\n\n3 - AVISO\nModelo de Anúncio: Concurso público\nData de Envio do Anúncio: 16-10-2025\n\n5 - PROCESSO\nTipo de Procedimento: Concurso público\nPreço base do procedimento: Sim\nValor do preço base do procedimento: 110.000,00 EUR\nProcedimento com lotes? Não\n\n6 - OBJETO DO CONTRATO\nNúmero de referência interna: CP/6/2025\nDesignação do contrato: Alteração da entrada principal e remodelação do átrio no piso 0 do edifício Torre do INEGI\nDescrição: Alteração da entrada principal e remodelação do átrio no piso 0 do edifício Torre do INEGI\nTipo de Contrato Principal: Empreitada de Obras Públicas\nTipo de Contrato: Empreitada de Obras Públicas\nClassificação CPV (Vocabulário Comum para os Contratos Públicos)\nObjeto principal\nVocabulário Principal: 45454000\nPreço base s/IVA: 110.000,00 EUR\n\n7 - INDICAÇÕES ADICIONAIS\nO contrato envolve aquisição conjunta (satisfação de várias entidades)? Não\nO contrato é adjudicado por uma central de compras? Não\n\n8 - TÉCNICAS\nO concurso destina-se à celebração de um acordo-quadro? Inexistência de acordo-quadro\nÉ utilizado um leilão eletrónico? Não\nÉ adotada uma fase de negociação? Não\nSistema de Aquisição Dinâmico: Inexistência de sistema de aquisição dinâmico\n\n9 - LOCAL DA EXECUÇÃO DO CONTRATO\nLOCAL DA EXECUÇÃO DO CONTRATO (PROCEDIMENTO)\nPaís: Portugal\nNUT III: PT11A\nLocalidade: Paranhos\nDistrito: Porto\nConcelho: Porto\nFreguesia: Freguesia de Paranhos - Porto\n\n10 - PRAZO DE EXECUÇÃO DO CONTRATO\nPrazo de execução do contrato: 90 DIAS\nPrevisão de renovações: Não\n\n11 - FUNDOS EU\nTêm fundos EU? Não\n\n12 - DOCUMENTOS DE HABILITAÇÃO\nHabilitação para o exercício da atividade profissional: Sim\nTipo: Alvará\nDescrição: Documentos de Habilitação\n\n13 - CONDIÇÕES DE APRESENTAÇÃO\nPlataforma eletrónica utilizada pela entidade adjudicante: ACIN\nURL para Apresentação: https://www.acingov.pt\nAdmissibilidade da apresentação de propostas variantes: Não autorizado\nPrazo para apresentação das propostas: 14-11-2025 23:59\nPrazo durante o qual os concorrentes são obrigados a manter as respetivas propostas: 90 dias a contar do termo do prazo para a apresentação das propostas\nIndicação de Subcontratação na Proposta: Inexistência de indicação de subcontratação\n\n14 - PRESTAÇÃO DE CAUÇÃO\nPrestação de caução: Sim\nPercentagem: 5%\nDescrição da Garantia Exigida: O valor da caução é de 5.00% do preço contratual.\n\n15 - FORNECIMENTO DAS PEÇAS DO CONCURSO, APRESENTAÇÃO DE PEDIDOS DE PARTICIPAÇÃO E APRESENTAÇÃO DAS PROPOSTAS\nLink para acesso às peças do concurso (URL): https://www.acingov.pt/acingovprod/2/zonaPublica/zona_publica_c/donwloadProcedurePiece/OTg2OTIw\n\n20 - OUTROS REQUISITOS\nInformação sobre contratos reservados. Aplica-se a contratos reservados (54º-A)? Não\n\n21 - CRITÉRIO DE ADJUDICAÇÃO\nMultifator: Sim\nFator: \nNome: Preço\nPonderação: 70%\nSubfatores: Não\nFator: \nNome: Outros\nOutro Nome: Valia Técnica\nPonderação: 30%\nSubfatores: Não\n\n24 - CONDIÇÕES DO CONTRATO\nFaturação Eletrónica: Necessário\nObrigação de Subcontratação:\nCódigo da Obrigação de Subcontratação: Não é aplicável nenhuma obrigação de subcontratação.\n\n25 - COMPRA PÚBLICA ESTRATÉGICA\nCompra Pública Estratégica: Inexistência de contratação pública estratégica\n\n26 - INFORMAÇÕES ADICIONAIS\nContrato adequado para PME: Sim\nCobertura ACP (Acordo dos Contratos Públicos da Organização Mundial do Comércio): Não\n\n27 - IDENTIFICAÇÃO E CONTACTOS DO ÓRGÃO DE RECURSOS ADMINISTRATIVOS\nDesignação: Conselho Geral de Supervisão\nEndereço: Campus da FEUP, R. Dr. Roberto Frias 400\nCódigo postal: 4200-465\nLocalidade: Paranhos\nTelefone: 229578710\nFax: \nEndereço eletrónico: inegi@inegi.up.pt\nPrazo de interposição do recurso: 10 dias\n\n28 - IDENTIFICAÇÃO DO(S) AUTOR(ES) DE ANÚNCIO\nNome: Emanuel Reis\nCargo: Jurista\n419659377",
    "nipc": "501814957",
    "distrito": "Porto",
    "concelho": "Porto",
    "freguesia": "Freguesia de Paranhos - Porto",
    "site": "www.inegi.pt",
    "email": "inegi@inegi.up.pt",
    "designacao_contrato": "Alteração da entrada principal e remodelação do átrio no piso 0 do edifício Torre do INEGI",
    "descricao": "Alteração da entrada principal e remodelação do átrio no piso 0 do edifício Torre do INEGI",
    "preco_base": "110.000,00 EUR",
    "prazo_execucao": "90 DIAS",
    "prazo_apresentacao_propostas": "14-11-2025 23:59",
    "fundos_eu": "Não",
    "plataforma_eletronica": "ACIN",
    "url_procedimento": "https://www.acingov.pt",
    "autor_nome": "Emanuel Reis",
    "autor_cargo": "Jurista"
  },
  {
    "numero_procedimento": "N/A",
    "entidade": "Convergência - Formadores Associados, L.da",
    "link": "https://diariodarepublica.pt/dr/detalhe/contrato-publico/27395-940560161",
    "detalhes_completos": "1 - IDENTIFICAÇÃO E CONTACTOS DA ENTIDADE ADJUDICANTE\nDesignação da entidade adjudicante: Convergência - Formadores Associados, L.da\nNIPC: 502465905\nEndereço: Rua Paio Peres Correia, 8 - 8A\nCódigo postal: 1900-364\nLocalidade: Santarém\nPaís: Portugal\nNUT III: PT185\nDistrito: Santarém\nConcelho: Coruche\nFreguesia: União das Freguesias de Coruche, Fajarda e Erra\nTelefone: 218148890\nFax: 218148891\nEndereço da Entidade (URL): www.ephtl.edu.pt\nEndereço Eletrónico: geral@ephtl.edu.pt\neDelivery Gateway (URL): https://community.vortal.biz/public/\nFunção da Organização: Adquirente\nNorma jurídica da Entidade Adjudicante: Autoridade da administração central\nÁrea de atividade da Autoridade Adjudicante: Educação\n\n2 - JORNAL OFICIAL DA UNIÃO EUROPEIA\nO procedimento a que este anúncio diz respeito também é publicitado no Jornal Oficial da União Europeia? Sim\n\n3 - AVISO\nModelo de Anúncio: Concurso público\nData de Envio do Anúncio: 14-10-2025\n\n5 - PROCESSO\nTipo de Procedimento: Concurso público\nPreço base do procedimento: Sim\nValor do preço base do procedimento: 723.016,29 EUR\nProcedimento com lotes? Não\n\n6 - OBJETO DO CONTRATO\nNúmero de referência interna: CPI04.CTE.EPHTL.2025\nDesignação do contrato: Aquisição de equipamento mobiliário no âmbito dos Centros Tecnológicos Especializados (CTE)\nDescrição: Aquisição de equipamento mobiliário no âmbito dos Centros Tecnológicos Especializados (CTE)\nOpções: Não\nTipo de Contrato Principal: Aquisição de Bens Móveis\nTipo de Contrato: Aquisição de Bens Móveis\nClassificação CPV (Vocabulário Comum para os Contratos Públicos)\nObjeto principal\nVocabulário Principal: 39100000\nPreço base s/IVA: 723.016,29 EUR\n\n7 - INDICAÇÕES ADICIONAIS\nO contrato envolve aquisição conjunta (satisfação de várias entidades)? Não\nO contrato é adjudicado por uma central de compras? Não\n\n8 - TÉCNICAS\nO concurso destina-se à celebração de um acordo-quadro? Inexistência de acordo-quadro\nÉ utilizado um leilão eletrónico? Não\nÉ adotada uma fase de negociação? Não\nSistema de Aquisição Dinâmico: Inexistência de sistema de aquisição dinâmico\n\n9 - LOCAL DA EXECUÇÃO DO CONTRATO\nLOCAL DA EXECUÇÃO DO CONTRATO (PROCEDIMENTO)\nPaís: Portugal\nNUT III: PT170\nLocalidade: Lisboa\nDistrito: Lisboa\nConcelho: Lisboa\nFreguesia: Freguesia de Penha de França\n\n10 - PRAZO DE EXECUÇÃO DO CONTRATO\nPrazo de execução do contrato: 150 DIAS\nPrevisão de renovações: Não\n\n11 - FUNDOS EU\nTêm fundos EU? Não\n\n12 - DOCUMENTOS DE HABILITAÇÃO\nHabilitação para o exercício da atividade profissional: Sim\nTipo: Outros\nDescrição - Outros: não aplicavel\nDescrição: n.a\n\n13 - CONDIÇÕES DE APRESENTAÇÃO\nPlataforma eletrónica utilizada pela entidade adjudicante: VORTAL\nURL para Apresentação: https://community.vortal.biz/public/\nAdmissibilidade da apresentação de propostas variantes: Não autorizado\nPrazo para apresentação das propostas: 13-11-2025 18:00\nPrazo durante o qual os concorrentes são obrigados a manter as respetivas propostas: 90 dias a contar do termo do prazo para a apresentação das propostas\nApresentação de Catálogo Eletrónico: Permitido\nIndicação de Subcontratação na Proposta: Inexistência de indicação de subcontratação\n\n14 - PRESTAÇÃO DE CAUÇÃO\nPrestação de caução: Sim\nPercentagem: 5%\nDescrição da Garantia Exigida: Modelo de Seguro - Caução; Modelo de garantia bancária; Modelo de guia de depósito bancário\n\n15 - FORNECIMENTO DAS PEÇAS DO CONCURSO, APRESENTAÇÃO DE PEDIDOS DE PARTICIPAÇÃO E APRESENTAÇÃO DAS PROPOSTAS\nLink para acesso às peças do concurso (URL): https://community.vortal.biz/Public/public-tender-documents/Rmx4SGlZRVM5bUsvQjgwbmIxWkhxeGxaaG1jbWd6bzVTcjYwcjVYWnk3TCs4SWhMbzVyZWlHYTVXV2hGRWdLRko4cTRRVDNSSm82aHVSc0gvYmZpREE9PWVnQE1t\n\n20 - OUTROS REQUISITOS\nInformação sobre contratos reservados. Aplica-se a contratos reservados (54º-A)? Não\n\n21 - CRITÉRIO DE ADJUDICAÇÃO\nMultifator: Não\nMonofator:\nNome: Outros\nOutro nome: Preço\n\n24 - CONDIÇÕES DO CONTRATO\nFaturação Eletrónica: Permitido\nObrigação de Subcontratação:\nCódigo da Obrigação de Subcontratação: Não é aplicável nenhuma obrigação de subcontratação.\n\n25 - COMPRA PÚBLICA ESTRATÉGICA\nCompra Pública Estratégica: Inexistência de contratação pública estratégica\n\n26 - INFORMAÇÕES ADICIONAIS\nContrato adequado para PME: Sim\nCobertura ACP (Acordo dos Contratos Públicos da Organização Mundial do Comércio): Não\n\n27 - IDENTIFICAÇÃO E CONTACTOS DO ÓRGÃO DE RECURSOS ADMINISTRATIVOS\nDesignação: Gerente\nEndereço: Rua Paio Peres Correia, 8 - 8A\nCódigo postal: 1900-364\nLocalidade: Lisboa\nTelefone: +351 218148890\nFax: +351 218148890\nEndereço eletrónico: geral@ephtl.edu.pt\n\n28 - IDENTIFICAÇÃO DO(S) AUTOR(ES) DE ANÚNCIO\nNome: João Carapinha\nCargo: Técnico Contratação Pública\n419658226",
    "nipc": "502465905",
    "distrito": "Santarém",
    "concelho": "Coruche",
    "freguesia": "União das Freguesias de Coruche, Fajarda e Erra",
    "site": "www.ephtl.edu.pt",
    "email": "geral@ephtl.edu.pt",
    "designacao_contrato": "Aquisição de equipamento mobiliário no âmbito dos Centros Tecnológicos Especializados (CTE)",
    "descricao": "Aquisição de equipamento mobiliário no âmbito dos Centros Tecnológicos Especializados (CTE)",
    "preco_base": "723.016,29 EUR",
    "prazo_execucao": "150 DIAS",
    "prazo_apresentacao_propostas": "13-11-2025 18:00",
    "fundos_eu": "Não",
    "plataforma_eletronica": "VORTAL",
    "url_procedimento": "https://community.vortal.biz/public/",
    "autor_nome": "João Carapinha",
    "autor_cargo": "Técnico Contratação Pública"
  },
  {
    "numero_procedimento": "N/A",
    "entidade": "Feira Viva - Cultura e Desporto, E. M.",
    "link": "https://diariodarepublica.pt/dr/detalhe/contrato-publico/27379-940618780",
    "detalhes_completos": "1 - IDENTIFICAÇÃO E CONTACTOS DA ENTIDADE ADJUDICANTE\nDesignação da entidade adjudicante: Feira Viva - Cultura e Desporto, E. M.\nNIPC: 505120151\nEndereço: Rua Interior do Europarque\nCódigo postal: 4520-153\nLocalidade: Aveiro\nPaís: Portugal\nNUT III: PT11A\nDistrito: Aveiro\nConcelho: Santa Maria da Feira\nFreguesia: União das Freguesias de Santa Maria da Feira, Travanca, Sanfins e Espargo\nTelefone: 256330900\nFax: 256330909\nEndereço Eletrónico: procedimentos@feiraviva.com\neDelivery Gateway (URL): https://community.vortal.biz/public/\nFunção da Organização: Adquirente\nNorma jurídica da Entidade Adjudicante: Autoridade da administração central\nÁrea de atividade da Autoridade Adjudicante: Serviços públicos das administrações públicas\n\n2 - JORNAL OFICIAL DA UNIÃO EUROPEIA\nO procedimento a que este anúncio diz respeito também é publicitado no Jornal Oficial da União Europeia? Não\n\n3 - AVISO\nModelo de Anúncio: Concurso público\nData de Envio do Anúncio: 16-10-2025\n\n5 - PROCESSO\nTipo de Procedimento: Concurso público\nPreço base do procedimento: Sim\nValor do preço base do procedimento: 20.000,00 EUR\nProcedimento com lotes? Não\n\n6 - OBJETO DO CONTRATO\nNúmero de referência interna: 320_2025_CP_BS\nDesignação do contrato: 320_2025_CP_BS - Aquisição de Serviços Audiovisuais para Perlim - Castelo\nDescrição: 320_2025_CP_BS - Aquisição de Serviços Audiovisuais para Perlim - Castelo\nTipo de Contrato Principal: Aquisição de Serviços\nTipo de Contrato: Aquisição de Serviços\nClassificação CPV (Vocabulário Comum para os Contratos Públicos)\nObjeto principal\nVocabulário Principal: 92370000\nPreço base s/IVA: 20.000,00 EUR\n\n7 - INDICAÇÕES ADICIONAIS\nO contrato envolve aquisição conjunta (satisfação de várias entidades)? Não\nO contrato é adjudicado por uma central de compras? Não\n\n8 - TÉCNICAS\nO concurso destina-se à celebração de um acordo-quadro? Inexistência de acordo-quadro\nÉ utilizado um leilão eletrónico? Não\nÉ adotada uma fase de negociação? Não\nSistema de Aquisição Dinâmico: Inexistência de sistema de aquisição dinâmico\n\n9 - LOCAL DA EXECUÇÃO DO CONTRATO\nLOCAL DA EXECUÇÃO DO CONTRATO (PROCEDIMENTO)\nPaís: Portugal\nNUT III: PT11A\nLocalidade: Aveiro\nDistrito: Aveiro\nConcelho: Santa Maria da Feira\nFreguesia: Todas\n\n10 - PRAZO DE EXECUÇÃO DO CONTRATO\nPrazo de execução do contrato: 60 DIAS\nPrevisão de renovações: Não\n\n11 - FUNDOS EU\nTêm fundos EU? Não\n\n12 - DOCUMENTOS DE HABILITAÇÃO\nHabilitação para o exercício da atividade profissional: Não\n\n13 - CONDIÇÕES DE APRESENTAÇÃO\nPlataforma eletrónica utilizada pela entidade adjudicante: VORTAL\nURL para Apresentação: https://community.vortal.biz/public/\nAdmissibilidade da apresentação de propostas variantes: Não autorizado\nPrazo para apresentação das propostas: 22-10-2025 23:59\nPrazo durante o qual os concorrentes são obrigados a manter as respetivas propostas: 120 dias a contar do termo do prazo para a apresentação das propostas\nIndicação de Subcontratação na Proposta: Inexistência de indicação de subcontratação\n\n14 - PRESTAÇÃO DE CAUÇÃO\nPrestação de caução: Não\n\n15 - FORNECIMENTO DAS PEÇAS DO CONCURSO, APRESENTAÇÃO DE PEDIDOS DE PARTICIPAÇÃO E APRESENTAÇÃO DAS PROPOSTAS\nLink para acesso às peças do concurso (URL): https://community.vortal.biz/Public/public-tender-documents/R3Iyb0V0LzJsWit3ZkxxNHV6NmNRcHFIWmpPRGpUbVJwL0FEenN5dVJkL1JZNHpEeVdBTmhFbnhTcHdISkpnME9uWTVpNTRBZWVlb0JXNDdoSUJGMnc9PXdVMygo\n\n20 - OUTROS REQUISITOS\nInformação sobre contratos reservados. Aplica-se a contratos reservados (54º-A)? Não\n\n21 - CRITÉRIO DE ADJUDICAÇÃO\nMultifator: Não\nMonofator:\nNome: Preço\n\n24 - CONDIÇÕES DO CONTRATO\nFaturação Eletrónica: Permitido\nObrigação de Subcontratação:\nCódigo da Obrigação de Subcontratação: Não é aplicável nenhuma obrigação de subcontratação.\n\n25 - COMPRA PÚBLICA ESTRATÉGICA\nCompra Pública Estratégica: Inexistência de contratação pública estratégica\n\n26 - INFORMAÇÕES ADICIONAIS\nContrato adequado para PME: Sim\nCobertura ACP (Acordo dos Contratos Públicos da Organização Mundial do Comércio): Não\n\n27 - IDENTIFICAÇÃO E CONTACTOS DO ÓRGÃO DE RECURSOS ADMINISTRATIVOS\nDesignação: Conselho de Administração Feira Viva Cultura e Desporto, E.M\nEndereço: Rua Interior do Europarque, Apartado 160\nCódigo postal: 4520-153\nLocalidade: Santa Maria da Feira\nTelefone: +351 256330900\nFax: +351 256330900\nEndereço eletrónico: procedimentos@feiraviva.com\n\n28 - IDENTIFICAÇÃO DO(S) AUTOR(ES) DE ANÚNCIO\nNome: Paulo Sérgio Pais\nCargo: Diretor Geral\n419667063",
    "nipc": "505120151",
    "distrito": "Aveiro",
    "concelho": "Santa Maria da Feira",
    "freguesia": "União das Freguesias de Santa Maria da Feira, Travanca, Sanfins e Espargo",
    "site": null,
    "email": "procedimentos@feiraviva.com",
    "designacao_contrato": "320_2025_CP_BS - Aquisição de Serviços Audiovisuais para Perlim - Castelo",
    "descricao": "320_2025_CP_BS - Aquisição de Serviços Audiovisuais para Perlim - Castelo",
    "preco_base": "20.000,00 EUR",
    "prazo_execucao": "60 DIAS",
    "prazo_apresentacao_propostas": "22-10-2025 23:59",
    "fundos_eu": "Não",
    "plataforma_eletronica": "VORTAL",
    "url_procedimento": "https://community.vortal.biz/public/",
    "autor_nome": "Paulo Sérgio Pais",
    "autor_cargo": "Diretor Geral"
  },
  {
    "numero_procedimento": "N/A",
    "entidade": "Município de Matosinhos",
    "link": "https://diariodarepublica.pt/dr/detalhe/contrato-publico/27380-940618781",
    "detalhes_completos": "1 - IDENTIFICAÇÃO E CONTACTOS DA ENTIDADE ADJUDICANTE\nDesignação da entidade adjudicante: Município de Matosinhos\nNIPC: 501305912\nEndereço: Av. D. Afonso Henriques\nCódigo postal: 4454-510\nLocalidade: Matosinhos\nPaís: Portugal\nNUT III: PT11A\nDistrito: Porto\nConcelho: Matosinhos\nFreguesia: Todas\nTelefone: 229390900\nFax: 229351645\nEndereço da Entidade (URL): http://www.cm-matosinhos.pt\nEndereço Eletrónico: contratacaopublica@cm-matosinhos.pt\neDelivery Gateway (URL): https://www.acingov.pt\nFunção da Organização: Adquirente\nSubfunção da Organização: Organização que recebe as propostas\nNorma jurídica da Entidade Adjudicante: Organismo de direito público\nÁrea de atividade da Autoridade Adjudicante: Serviços públicos das administrações públicas\n\n2 - JORNAL OFICIAL DA UNIÃO EUROPEIA\nO procedimento a que este anúncio diz respeito também é publicitado no Jornal Oficial da União Europeia? Sim\n\n3 - AVISO\nModelo de Anúncio: Concurso público\nData de Envio do Anúncio: 14-10-2025\n\n5 - PROCESSO\nTipo de Procedimento: Concurso público\nPreço base do procedimento: Sim\nValor do preço base do procedimento: 225.191,50 EUR\nProcedimento com lotes? Não\n\n6 - OBJETO DO CONTRATO\nNúmero de referência interna: 2025/15633\nDesignação do contrato: MANUTENÇÃO DE SISTEMAS SEMAFÓRICOS NO CONCELHO DE MATOSINHOS\nDescrição: MANUTENÇÃO DE SISTEMAS SEMAFÓRICOS NO CONCELHO DE MATOSINHOS\nOpções: Não\nTipo de Contrato Principal: Aquisição de Serviços\nTipo de Contrato: Aquisição de Serviços\nClassificação CPV (Vocabulário Comum para os Contratos Públicos)\nObjeto principal\nVocabulário Principal: 50800000\nPreço base s/IVA: 225.191,50 EUR\n\n7 - INDICAÇÕES ADICIONAIS\nO contrato envolve aquisição conjunta (satisfação de várias entidades)? Não\nO contrato é adjudicado por uma central de compras? Não\n\n8 - TÉCNICAS\nO concurso destina-se à celebração de um acordo-quadro? Inexistência de acordo-quadro\nÉ utilizado um leilão eletrónico? Não\nÉ adotada uma fase de negociação? Não\nSistema de Aquisição Dinâmico: Inexistência de sistema de aquisição dinâmico\n\n9 - LOCAL DA EXECUÇÃO DO CONTRATO\nLOCAL DA EXECUÇÃO DO CONTRATO (PROCEDIMENTO)\nPaís: Portugal\nNUT III: PT11A\nLocalidade: Matosinhos\nDistrito: Porto\nConcelho: Matosinhos\nFreguesia: Todas\n\n10 - PRAZO DE EXECUÇÃO DO CONTRATO\nPrazo de execução do contrato: 36 MESES\nPrevisão de renovações: Não\n\n11 - FUNDOS EU\nTêm fundos EU? Não\n\n12 - DOCUMENTOS DE HABILITAÇÃO\nHabilitação para o exercício da atividade profissional: Não\n\n13 - CONDIÇÕES DE APRESENTAÇÃO\nPlataforma eletrónica utilizada pela entidade adjudicante: ACIN\nURL para Apresentação: https://www.acingov.pt\nAdmissibilidade da apresentação de propostas variantes: Não autorizado\nPrazo para apresentação das propostas: 16-11-2025 23:59\nPrazo durante o qual os concorrentes são obrigados a manter as respetivas propostas: 66 dias a contar do termo do prazo para a apresentação das propostas\nApresentação de Catálogo Eletrónico: Permitido\nIndicação de Subcontratação na Proposta: Inexistência de indicação de subcontratação\n\n14 - PRESTAÇÃO DE CAUÇÃO\nPrestação de caução: Não\n\n15 - FORNECIMENTO DAS PEÇAS DO CONCURSO, APRESENTAÇÃO DE PEDIDOS DE PARTICIPAÇÃO E APRESENTAÇÃO DAS PROPOSTAS\nLink para acesso às peças do concurso (URL): https://www.acingov.pt/acingovprod/2/zonaPublica/zona_publica_c/donwloadProcedurePiece/OTg2MTYw\n\n20 - OUTROS REQUISITOS\nInformação sobre contratos reservados. Aplica-se a contratos reservados (54º-A)? Não\n\n21 - CRITÉRIO DE ADJUDICAÇÃO\nMultifator: Não\nMonofator:\nNome: Preço\n\n24 - CONDIÇÕES DO CONTRATO\nFaturação Eletrónica: Não autorizado\nObrigação de Subcontratação:\nCódigo da Obrigação de Subcontratação: Não é aplicável nenhuma obrigação de subcontratação.\n\n25 - COMPRA PÚBLICA ESTRATÉGICA\nCompra Pública Estratégica: Inexistência de contratação pública estratégica\n\n26 - INFORMAÇÕES ADICIONAIS\nContrato adequado para PME: Não\nCobertura ACP (Acordo dos Contratos Públicos da Organização Mundial do Comércio): Não\n\n27 - IDENTIFICAÇÃO E CONTACTOS DO ÓRGÃO DE RECURSOS ADMINISTRATIVOS\nDesignação: Município de Matosinhos\nEndereço: Matosinhos\nCódigo postal: 4454-510\nLocalidade: Matosinhos\nTelefone: 229390900\nFax: \nEndereço eletrónico: contratacaopublica@cm-matosinhos.pt\nPrazo de interposição do recurso: 5 dias\n\n28 - IDENTIFICAÇÃO DO(S) AUTOR(ES) DE ANÚNCIO\nNome: Luísa Maria Neves Salgueiro\nCargo: Presidente da Câmara\n419648733",
    "nipc": "501305912",
    "distrito": "Porto",
    "concelho": "Matosinhos",
    "freguesia": "Todas",
    "site": "http://www.cm-matosinhos.pt",
    "email": "contratacaopublica@cm-matosinhos.pt",
    "designacao_contrato": "MANUTENÇÃO DE SISTEMAS SEMAFÓRICOS NO CONCELHO DE MATOSINHOS",
    "descricao": "MANUTENÇÃO DE SISTEMAS SEMAFÓRICOS NO CONCELHO DE MATOSINHOS",
    "preco_base": "225.191,50 EUR",
    "prazo_execucao": "36 MESES",
    "prazo_apresentacao_propostas": "16-11-2025 23:59",
    "fundos_eu": "Não",
    "plataforma_eletronica": "ACIN",
    "url_procedimento": "https://www.acingov.pt",
    "autor_nome": "Luísa Maria Neves Salgueiro",
    "autor_cargo": "Presidente da Câmara"
  },
  {
    "numero_procedimento": "N/A",
    "entidade": "Universidade de Aveiro",
    "link": "https://diariodarepublica.pt/dr/detalhe/contrato-publico/27382-940618782",
    "detalhes_completos": "1 - IDENTIFICAÇÃO E CONTACTOS DA ENTIDADE ADJUDICANTE\nDesignação da entidade adjudicante: Universidade de Aveiro\nNIPC: 501461108\nServiço/Órgão/Pessoa de contacto: Reitor da Universidade de Aveiro\nEndereço: Campus Universitário de Santiago\nCódigo postal: 3810-193\nLocalidade: Aveiro\nPaís: Portugal\nNUT III: PT16D\nDistrito: Aveiro\nConcelho: Aveiro\nFreguesia: União das Freguesias de Glória e Vera Cruz\nTelefone: 234370200\nEndereço da Entidade (URL): https://www.ua.pt/\nEndereço Eletrónico: contratacao@ua.pt\neDelivery Gateway (URL): https://www.acingov.pt\nFunção da Organização: Adquirente\nSubfunção da Organização: Organização que recebe as propostas\nNorma jurídica da Entidade Adjudicante: Organismo de direito público\nÁrea de atividade da Autoridade Adjudicante: Serviços públicos das administrações públicas\n\n2 - JORNAL OFICIAL DA UNIÃO EUROPEIA\nO procedimento a que este anúncio diz respeito também é publicitado no Jornal Oficial da União Europeia? Não\n\n3 - AVISO\nModelo de Anúncio: Concurso público\nData de Envio do Anúncio: 16-10-2025\n\n5 - PROCESSO\nTipo de Procedimento: Concurso público\nPreço base do procedimento: Sim\nValor do preço base do procedimento: 80.000,00 EUR\nProcedimento com lotes? Não\n\n6 - OBJETO DO CONTRATO\nNúmero de referência interna: CP 338 - AAC/SGT - 09/25\nDesignação do contrato: Aquisição de manutenção de Geradores e de Postos de Transformação da Universidade de Aveiro\nDescrição: Aquisição de manutenção de Geradores e de Postos de Transformação da Universidade de Aveiro\nTipo de Contrato Principal: Aquisição de Serviços\nTipo de Contrato: Aquisição de Serviços\nClassificação CPV (Vocabulário Comum para os Contratos Públicos)\nObjeto principal\nVocabulário Principal: 50532300\nPreço base s/IVA: 80.000,00 EUR\n\n7 - INDICAÇÕES ADICIONAIS\nO contrato envolve aquisição conjunta (satisfação de várias entidades)? Não\nO contrato é adjudicado por uma central de compras? Não\n\n8 - TÉCNICAS\nO concurso destina-se à celebração de um acordo-quadro? Inexistência de acordo-quadro\nÉ utilizado um leilão eletrónico? Não\nÉ adotada uma fase de negociação? Não\nSistema de Aquisição Dinâmico: Inexistência de sistema de aquisição dinâmico\n\n9 - LOCAL DA EXECUÇÃO DO CONTRATO\nLOCAL DA EXECUÇÃO DO CONTRATO (PROCEDIMENTO)\nPaís: Portugal\nNUT III: PT16D\nLocalidade: União das Freguesias de Glória e Vera Cruz\nDistrito: Aveiro\nConcelho: Aveiro\nFreguesia: União das Freguesias de Glória e Vera Cruz\n\n10 - PRAZO DE EXECUÇÃO DO CONTRATO\nPrazo de execução do contrato: 24 MESES\nPrevisão de renovações: Não\n\n11 - FUNDOS EU\nTêm fundos EU? Não\n\n12 - DOCUMENTOS DE HABILITAÇÃO\nHabilitação para o exercício da atividade profissional: Não\n\n13 - CONDIÇÕES DE APRESENTAÇÃO\nPlataforma eletrónica utilizada pela entidade adjudicante: ACIN\nURL para Apresentação: https://www.acingov.pt\nAdmissibilidade da apresentação de propostas variantes: Não autorizado\nPrazo para apresentação das propostas: 28-10-2025 23:59\nPrazo durante o qual os concorrentes são obrigados a manter as respetivas propostas: 132 dias a contar do termo do prazo para a apresentação das propostas\nIndicação de Subcontratação na Proposta: Inexistência de indicação de subcontratação\n\n14 - PRESTAÇÃO DE CAUÇÃO\nPrestação de caução: Não\n\n15 - FORNECIMENTO DAS PEÇAS DO CONCURSO, APRESENTAÇÃO DE PEDIDOS DE PARTICIPAÇÃO E APRESENTAÇÃO DAS PROPOSTAS\nLink para acesso às peças do concurso (URL): https://www.acingov.pt/acingovprod/2/zonaPublica/zona_publica_c/donwloadProcedurePiece/OTg4MTk1\n\n20 - OUTROS REQUISITOS\nInformação sobre contratos reservados. Aplica-se a contratos reservados (54º-A)? Não\n\n21 - CRITÉRIO DE ADJUDICAÇÃO\nMultifator: Não\nMonofator:\nNome: Preço\n\n24 - CONDIÇÕES DO CONTRATO\nFaturação Eletrónica: Permitido\nObrigação de Subcontratação:\nCódigo da Obrigação de Subcontratação: Não é aplicável nenhuma obrigação de subcontratação.\n\n25 - COMPRA PÚBLICA ESTRATÉGICA\nCompra Pública Estratégica: Inexistência de contratação pública estratégica\n\n26 - INFORMAÇÕES ADICIONAIS\nContrato adequado para PME: Sim\nCobertura ACP (Acordo dos Contratos Públicos da Organização Mundial do Comércio): Não\n\n27 - IDENTIFICAÇÃO E CONTACTOS DO ÓRGÃO DE RECURSOS ADMINISTRATIVOS\nDesignação: Reitor da Universidade de Aveiro\nEndereço: Campus Universitário de Santiago\nCódigo postal: 3810-193\nLocalidade: Aveiro\nTelefone: 234370200\nFax: \nEndereço eletrónico: contratacao@ua.pt\n\n28 - IDENTIFICAÇÃO DO(S) AUTOR(ES) DE ANÚNCIO\nNome: Ana Isabel Pires Sousa da Silva Braga\nCargo: Chefe de Divisão da Área de Aquisições e Contratos\n419665379",
    "nipc": "501461108",
    "distrito": "Aveiro",
    "concelho": "Aveiro",
    "freguesia": "União das Freguesias de Glória e Vera Cruz",
    "site": "https://www.ua.pt/",
    "email": "contratacao@ua.pt",
    "designacao_contrato": "Aquisição de manutenção de Geradores e de Postos de Transformação da Universidade de Aveiro",
    "descricao": "Aquisição de manutenção de Geradores e de Postos de Transformação da Universidade de Aveiro",
    "preco_base": "80.000,00 EUR",
    "prazo_execucao": "24 MESES",
    "prazo_apresentacao_propostas": "28-10-2025 23:59",
    "fundos_eu": "Não",
    "plataforma_eletronica": "ACIN",
    "url_procedimento": "https://www.acingov.pt",
    "autor_nome": "Ana Isabel Pires Sousa da Silva Braga",
    "autor_cargo": "Chefe de Divisão da Área de Aquisições e Contratos"
  },
  {
    "numero_procedimento": "N/A",
    "entidade": "AnÃºncio de procedimento  n.Âº 27383/2025  -  DiÃ¡rio da RepÃºblica n.Âº 201/2025, SÃ©rie II de 2025-10-17",
    "link": "https://diariodarepublica.pt/dr/detalhe/contrato-publico/27383-940618785"
  },
  {
    "numero_procedimento": "N/A",
    "entidade": "AnÃºncio de procedimento  n.Âº 27384/2025  -  DiÃ¡rio da RepÃºblica n.Âº 201/2025, SÃ©rie II de 2025-10-17",
    "link": "https://diariodarepublica.pt/dr/detalhe/contrato-publico/27384-940618786"
  },
  {
    "numero_procedimento": "N/A",
    "entidade": "Município de Valença",
    "link": "https://diariodarepublica.pt/dr/detalhe/contrato-publico/27386-940618787",
    "detalhes_completos": "1 - IDENTIFICAÇÃO E CONTACTOS DA ENTIDADE ADJUDICANTE\nDesignação da entidade adjudicante: Município de Valença\nNIPC: 506728897\nEndereço: Pç. Da República, Valença\nCódigo postal: 4930-702\nLocalidade: Valença\nPaís: Portugal\nNUT III: PT111\nDistrito: Viana do Castelo\nConcelho: Valença\nFreguesia: Todas\nTelefone: 251809500\nFax: 251809519\nEndereço da Entidade (URL): www.cm-valenca.pt\nEndereço Eletrónico: geral@cm-valenca.pt\neDelivery Gateway (URL): https://community.vortal.biz/public/\nFunção da Organização: Adquirente\nNorma jurídica da Entidade Adjudicante: Autoridade local\nÁrea de atividade da Autoridade Adjudicante: Serviços públicos das administrações públicas\n\n2 - JORNAL OFICIAL DA UNIÃO EUROPEIA\nO procedimento a que este anúncio diz respeito também é publicitado no Jornal Oficial da União Europeia? Não\n\n3 - AVISO\nModelo de Anúncio: Concurso público\nData de Envio do Anúncio: 16-10-2025\n\n5 - PROCESSO\nTipo de Procedimento: Concurso público\nPreço base do procedimento: Sim\nValor do preço base do procedimento: 6.941,61 EUR\nProcedimento com lotes? Não\n\n6 - OBJETO DO CONTRATO\nNúmero de referência interna: CP-ABS-17/2025\nDesignação do contrato: FORNECIMENTO DE FRUTA PARA OS ALUNOS DO 1º CICLO DO ENSINO BÁSICO DO CONCELHO DE VALENÇA\nDescrição: FORNECIMENTO DE FRUTA PARA OS ALUNOS DO 1º CICLO DO ENSINO BÁSICO DO CONCELHO DE VALENÇA\nTipo de Contrato Principal: Aquisição de Bens Móveis\nTipo de Contrato: Aquisição de Bens Móveis\nClassificação CPV (Vocabulário Comum para os Contratos Públicos)\nObjeto principal\nVocabulário Principal: 03220000\nPreço base s/IVA: 6.941,61 EUR\n\n7 - INDICAÇÕES ADICIONAIS\nO contrato envolve aquisição conjunta (satisfação de várias entidades)? Não\nO contrato é adjudicado por uma central de compras? Não\n\n8 - TÉCNICAS\nO concurso destina-se à celebração de um acordo-quadro? Inexistência de acordo-quadro\nÉ utilizado um leilão eletrónico? Não\nÉ adotada uma fase de negociação? Não\nSistema de Aquisição Dinâmico: Inexistência de sistema de aquisição dinâmico\n\n9 - LOCAL DA EXECUÇÃO DO CONTRATO\nLOCAL DA EXECUÇÃO DO CONTRATO (PROCEDIMENTO)\nPaís: Portugal\nNUT III: PT111\nLocalidade: Viana do Castelo\nDistrito: Viana do Castelo\nConcelho: Valença\nFreguesia: Todas\n\n10 - PRAZO DE EXECUÇÃO DO CONTRATO\nPrazo de execução do contrato: 7 MESES\nPrevisão de renovações: Não\n\n11 - FUNDOS EU\nTêm fundos EU? Não\n\n12 - DOCUMENTOS DE HABILITAÇÃO\nHabilitação para o exercício da atividade profissional: Sim\nTipo: Outros\nDescrição - Outros: Os previstos no ponto 28 do PC\nDescrição: Os previstos no ponto 28 do PC\n\n13 - CONDIÇÕES DE APRESENTAÇÃO\nPlataforma eletrónica utilizada pela entidade adjudicante: VORTAL\nURL para Apresentação: https://community.vortal.biz/public/\nAdmissibilidade da apresentação de propostas variantes: Não autorizado\nPrazo para apresentação das propostas: 22-10-2025 17:00\nPrazo durante o qual os concorrentes são obrigados a manter as respetivas propostas: 66 dias a contar do termo do prazo para a apresentação das propostas\nIndicação de Subcontratação na Proposta: Inexistência de indicação de subcontratação\n\n14 - PRESTAÇÃO DE CAUÇÃO\nPrestação de caução: Não\n\n15 - FORNECIMENTO DAS PEÇAS DO CONCURSO, APRESENTAÇÃO DE PEDIDOS DE PARTICIPAÇÃO E APRESENTAÇÃO DAS PROPOSTAS\nLink para acesso às peças do concurso (URL): https://community.vortal.biz/Public/public-tender-documents/YnJVa0dQd3RpVTdUU3k3UVlDMWJrYW5qSEoxSUpyY0FxNUhSeE1EZEZBOXdMakprMURWM003QldRcVFaRjFTTm9iUHZMMkZwNVpwWldMYk1vN29OZXc9PUpfMGJv\n\n20 - OUTROS REQUISITOS\nInformação sobre contratos reservados. Aplica-se a contratos reservados (54º-A)? Não\n\n21 - CRITÉRIO DE ADJUDICAÇÃO\nMultifator: Não\nMonofator:\nNome: Preço\n\n24 - CONDIÇÕES DO CONTRATO\nFaturação Eletrónica: Permitido\nObrigação de Subcontratação:\nCódigo da Obrigação de Subcontratação: Não é aplicável nenhuma obrigação de subcontratação.\n\n25 - COMPRA PÚBLICA ESTRATÉGICA\nCompra Pública Estratégica: Inexistência de contratação pública estratégica\n\n26 - INFORMAÇÕES ADICIONAIS\nContrato adequado para PME: Sim\nCobertura ACP (Acordo dos Contratos Públicos da Organização Mundial do Comércio): Não\n\n27 - IDENTIFICAÇÃO E CONTACTOS DO ÓRGÃO DE RECURSOS ADMINISTRATIVOS\nDesignação: José Manuel Vaz Carpinteira\nEndereço: Praça da Republica nº702\nCódigo postal: 4930-702\nLocalidade: Valença\nTelefone: +351 251809500\nFax: +351 251809512\nEndereço eletrónico: aprovisionamento@cm-valenca.pt\n\n28 - IDENTIFICAÇÃO DO(S) AUTOR(ES) DE ANÚNCIO\nNome: José Manuel Vaz Carpinteira\nCargo: Presidente da Câmara Municipal\n419666326",
    "nipc": "506728897",
    "distrito": "Viana do Castelo",
    "concelho": "Valença",
    "freguesia": "Todas",
    "site": "www.cm-valenca.pt",
    "email": "geral@cm-valenca.pt",
    "designacao_contrato": "FORNECIMENTO DE FRUTA PARA OS ALUNOS DO 1º CICLO DO ENSINO BÁSICO DO CONCELHO DE VALENÇA",
    "descricao": "FORNECIMENTO DE FRUTA PARA OS ALUNOS DO 1º CICLO DO ENSINO BÁSICO DO CONCELHO DE VALENÇA",
    "preco_base": "6.941,61 EUR",
    "prazo_execucao": "7 MESES",
    "prazo_apresentacao_propostas": "22-10-2025 17:00",
    "fundos_eu": "Não",
    "plataforma_eletronica": "VORTAL",
    "url_procedimento": "https://community.vortal.biz/public/",
    "autor_nome": "José Manuel Vaz Carpinteira",
    "autor_cargo": "Presidente da Câmara Municipal"
  },
  {
    "numero_procedimento": "N/A",
    "entidade": "AR - Águas do Ribatejo, E. I. M., S. A.",
    "link": "https://diariodarepublica.pt/dr/detalhe/contrato-publico/27390-940618789",
    "detalhes_completos": "1 - IDENTIFICAÇÃO E CONTACTOS DA ENTIDADE ADJUDICANTE\nDesignação da entidade adjudicante: AR - Águas do Ribatejo, E. I. M., S. A.\nNIPC: 508345464\nEndereço: Rua Gaspar Costa Ramalho, nº38\nCódigo postal: 2120-098\nLocalidade: Santarém\nPaís: Portugal\nNUT III: PT185\nDistrito: Santarém\nConcelho: Salvaterra de Magos\nFreguesia: União das Freguesias de Salvaterra de Magos e Foros de Salvaterra\nTelefone: 243303240\nEndereço da Entidade (URL): www.aguasdoribatejo.com\nEndereço Eletrónico: geral@aguasdoribatejo.com\neDelivery Gateway (URL): https://community.vortal.biz/public/\nFunção da Organização: Adquirente\nNorma jurídica da Entidade Adjudicante: Empresa pública, controlada por uma autoridade local\nÁrea de atividade da Autoridade Adjudicante: Proteção ambiental\n\n2 - JORNAL OFICIAL DA UNIÃO EUROPEIA\nO procedimento a que este anúncio diz respeito também é publicitado no Jornal Oficial da União Europeia? Sim\n\n3 - AVISO\nModelo de Anúncio: Concurso público\nData de Envio do Anúncio: 14-10-2025\n\n5 - PROCESSO\nTipo de Procedimento: Concurso público\nPreço base do procedimento: Sim\nValor do preço base do procedimento: 130.000,00 EUR\nProcedimento com lotes? Não\n\n6 - OBJETO DO CONTRATO\nNúmero de referência interna: FPS/046/2025\nDesignação do contrato: Fiscalização da empreitada para a reabilitação de infraestruturas no subsistema de abastecimento de água de Coruche / Valverde / Fajarda\nDescrição: Prestação de serviços para a fiscalização da empreitada para a reabilitação de infraestruturas no subsistema de abastecimento de água de Coruche / Valverde / Fajarda\nOpções: Não\nTipo de Contrato Principal: Aquisição de Serviços\nTipo de Contrato: Aquisição de Serviços\nClassificação CPV (Vocabulário Comum para os Contratos Públicos)\nObjeto principal\nVocabulário Principal: 71247000\nPreço base s/IVA: 130.000,00 EUR\n\n7 - INDICAÇÕES ADICIONAIS\nO contrato envolve aquisição conjunta (satisfação de várias entidades)? Não\nO contrato é adjudicado por uma central de compras? Não\n\n8 - TÉCNICAS\nO concurso destina-se à celebração de um acordo-quadro? Inexistência de acordo-quadro\nÉ utilizado um leilão eletrónico? Não\nÉ adotada uma fase de negociação? Não\nSistema de Aquisição Dinâmico: Inexistência de sistema de aquisição dinâmico\n\n9 - LOCAL DA EXECUÇÃO DO CONTRATO\nLOCAL DA EXECUÇÃO DO CONTRATO (PROCEDIMENTO)\nPaís: Portugal\nNUT III: PT185\nLocalidade: Coruche\nDistrito: Santarém\nConcelho: Coruche\nFreguesia: União das Freguesias de Coruche, Fajarda e Erra\n\n10 - PRAZO DE EXECUÇÃO DO CONTRATO\nPrazo de execução do contrato: 24 MESES\nPrevisão de renovações: Não\n\n11 - FUNDOS EU\nTêm fundos EU? Sim\n\n12 - DOCUMENTOS DE HABILITAÇÃO\nHabilitação para o exercício da atividade profissional: Sim\nTipo: Outros\nDescrição - Outros: Conforme programa do concurso.\nDescrição: Conforme programa do concurso.\n\n13 - CONDIÇÕES DE APRESENTAÇÃO\nPlataforma eletrónica utilizada pela entidade adjudicante: VORTAL\nURL para Apresentação: https://community.vortal.biz/public/\nAdmissibilidade da apresentação de propostas variantes: Não autorizado\nPrazo para apresentação das propostas: 13-11-2025 23:59\nPrazo durante o qual os concorrentes são obrigados a manter as respetivas propostas: 180 dias a contar do termo do prazo para a apresentação das propostas\nApresentação de Catálogo Eletrónico: Permitido\nIndicação de Subcontratação na Proposta: Inexistência de indicação de subcontratação\n\n14 - PRESTAÇÃO DE CAUÇÃO\nPrestação de caução: Sim\nPercentagem: 5%\nDescrição da Garantia Exigida: Conforme programa do concurso.\n\n15 - FORNECIMENTO DAS PEÇAS DO CONCURSO, APRESENTAÇÃO DE PEDIDOS DE PARTICIPAÇÃO E APRESENTAÇÃO DAS PROPOSTAS\nLink para acesso às peças do concurso (URL): https://community.vortal.biz/Public/public-tender-documents/YnNLcjVvb0pGQW5UU0lmajYyN1hPanZtc3VoZk1zSVFTS09EbENIVzJnVkFzS1hLQ1E5dmlqUW1BaHlJZmdFMjJYa0g1eXJ5bHJCd3daaVRvOWxMRGc9PSsjUVdZ\n\n20 - OUTROS REQUISITOS\nInformação sobre contratos reservados. Aplica-se a contratos reservados (54º-A)? Não\n\n21 - CRITÉRIO DE ADJUDICAÇÃO\nMultifator: Não\nMonofator:\nNome: Preço\n\n24 - CONDIÇÕES DO CONTRATO\nFaturação Eletrónica: Permitido\nObrigação de Subcontratação:\nCódigo da Obrigação de Subcontratação: Não é aplicável nenhuma obrigação de subcontratação.\n\n25 - COMPRA PÚBLICA ESTRATÉGICA\nCompra Pública Estratégica: Inexistência de contratação pública estratégica\n\n26 - INFORMAÇÕES ADICIONAIS\nContrato adequado para PME: Sim\nCobertura ACP (Acordo dos Contratos Públicos da Organização Mundial do Comércio): Não\n\n27 - IDENTIFICAÇÃO E CONTACTOS DO ÓRGÃO DE RECURSOS ADMINISTRATIVOS\nDesignação: Conselho de Administração da AR - Águas do Ribatejo, EIM, SA\nEndereço: Rua Gaspar Costa Ramalho, 38\nCódigo postal: 2120-098\nLocalidade: Salvaterra de Magos\nTelefone: +351 263509400\nFax: +351 263509499\nEndereço eletrónico: geral@aguasdoribatejo.com\n\n28 - IDENTIFICAÇÃO DO(S) AUTOR(ES) DE ANÚNCIO\nNome: Francisco Silvestre de Oliveira\nCargo: Presidente do Conselho de Administração\n419653244",
    "nipc": "508345464",
    "distrito": "Santarém",
    "concelho": "Salvaterra de Magos",
    "freguesia": "União das Freguesias de Salvaterra de Magos e Foros de Salvaterra",
    "site": "www.aguasdoribatejo.com",
    "email": "geral@aguasdoribatejo.com",
    "designacao_contrato": "Fiscalização da empreitada para a reabilitação de infraestruturas no subsistema de abastecimento de água de Coruche / Valverde / Fajarda",
    "descricao": "Prestação de serviços para a fiscalização da empreitada para a reabilitação de infraestruturas no subsistema de abastecimento de água de Coruche / Valverde / Fajarda",
    "preco_base": "130.000,00 EUR",
    "prazo_execucao": "24 MESES",
    "prazo_apresentacao_propostas": "13-11-2025 23:59",
    "fundos_eu": "Sim",
    "plataforma_eletronica": "VORTAL",
    "url_procedimento": "https://community.vortal.biz/public/",
    "autor_nome": "Francisco Silvestre de Oliveira",
    "autor_cargo": "Presidente do Conselho de Administração"
  },
  {
    "numero_procedimento": "N/A",
    "entidade": "Instituto de Telecomunicações",
    "link": "https://diariodarepublica.pt/dr/detalhe/contrato-publico/27394-940618790",
    "detalhes_completos": "1 - IDENTIFICAÇÃO E CONTACTOS DA ENTIDADE ADJUDICANTE\nDesignação da entidade adjudicante: Instituto de Telecomunicações\nNIPC: 502854200\nEndereço: Universidade de Aveiro, Campus Universitário de Santiago\nCódigo postal: 3810-193\nLocalidade: Aveiro\nPaís: Portugal\nNUT III: PT16D\nDistrito: Aveiro\nConcelho: Aveiro\nFreguesia: Todas\nTelefone: 234377900\nFax: 234377901\nEndereço da Entidade (URL): www.it.pt\nEndereço Eletrónico: contratacao@av.it.pt\neDelivery Gateway (URL): https://community.vortal.biz/public/\nFunção da Organização: Adquirente\nNorma jurídica da Entidade Adjudicante: Organismo de direito público\nÁrea de atividade da Autoridade Adjudicante: Educação\n\n2 - JORNAL OFICIAL DA UNIÃO EUROPEIA\nO procedimento a que este anúncio diz respeito também é publicitado no Jornal Oficial da União Europeia? Não\n\n3 - AVISO\nModelo de Anúncio: Concurso público\nData de Envio do Anúncio: 16-10-2025\n\n5 - PROCESSO\nTipo de Procedimento: Concurso público\nPreço base do procedimento: Sim\nValor do preço base do procedimento: 105.000,00 EUR\nProcedimento com lotes? Não\n\n6 - OBJETO DO CONTRATO\nNúmero de referência interna: CP-01-ITAV-10-25.\nDesignação do contrato: Contratação de uma Ferramenta de Gestão de Recursos Humanos\nDescrição: Contratação de uma Ferramenta de Gestão de Recursos Humanos\nTipo de Contrato Principal: Aquisição de Serviços\nTipo de Contrato: Aquisição de Serviços\nClassificação CPV (Vocabulário Comum para os Contratos Públicos)\nObjeto principal\nVocabulário Principal: 72268000\nPreço base s/IVA: 105.000,00 EUR\n\n7 - INDICAÇÕES ADICIONAIS\nO contrato envolve aquisição conjunta (satisfação de várias entidades)? Não\nO contrato é adjudicado por uma central de compras? Não\n\n8 - TÉCNICAS\nO concurso destina-se à celebração de um acordo-quadro? Inexistência de acordo-quadro\nÉ utilizado um leilão eletrónico? Não\nÉ adotada uma fase de negociação? Não\nSistema de Aquisição Dinâmico: Inexistência de sistema de aquisição dinâmico\n\n9 - LOCAL DA EXECUÇÃO DO CONTRATO\nLOCAL DA EXECUÇÃO DO CONTRATO (PROCEDIMENTO)\nPaís: Portugal\nNUT III: PT16D\nLocalidade: Aveiro\nDistrito: Aveiro\nConcelho: Aveiro\nFreguesia: União das Freguesias de Glória e Vera Cruz\n\n10 - PRAZO DE EXECUÇÃO DO CONTRATO\nPrazo de execução do contrato: 3 ANOS\nPrevisão de renovações: Não\n\n11 - FUNDOS EU\nTêm fundos EU? Não\n\n12 - DOCUMENTOS DE HABILITAÇÃO\nHabilitação para o exercício da atividade profissional: Não\n\n13 - CONDIÇÕES DE APRESENTAÇÃO\nPlataforma eletrónica utilizada pela entidade adjudicante: VORTAL\nURL para Apresentação: https://community.vortal.biz/public/\nAdmissibilidade da apresentação de propostas variantes: Não autorizado\nPrazo para apresentação das propostas: 31-10-2025 18:00\nPrazo durante o qual os concorrentes são obrigados a manter as respetivas propostas: 66 dias a contar do termo do prazo para a apresentação das propostas\nIndicação de Subcontratação na Proposta: Inexistência de indicação de subcontratação\n\n14 - PRESTAÇÃO DE CAUÇÃO\nPrestação de caução: Não\n\n15 - FORNECIMENTO DAS PEÇAS DO CONCURSO, APRESENTAÇÃO DE PEDIDOS DE PARTICIPAÇÃO E APRESENTAÇÃO DAS PROPOSTAS\nLink para acesso às peças do concurso (URL): https://community.vortal.biz/Public/public-tender-documents/ZGdvTmliVXdBQkJrNHplNG5NaG4yVWVlcGgxSkg2OTlhRmxLVk5vVGI0dzZxQ3dtajhZQ2IyUzViM0RWMUtJcW1hZWVVY290elY5M295cWpycTh1cEE9PWx6ZGln\n\n20 - OUTROS REQUISITOS\nInformação sobre contratos reservados. Aplica-se a contratos reservados (54º-A)? Não\n\n21 - CRITÉRIO DE ADJUDICAÇÃO\nMultifator: Sim\nFator: \nNome: Preço\nPonderação: 60%\nSubfatores: Não\nFator: \nNome: Qualidade\nPonderação: 40%\nSubfatores: Não\n\n24 - CONDIÇÕES DO CONTRATO\nFaturação Eletrónica: Permitido\nObrigação de Subcontratação:\nCódigo da Obrigação de Subcontratação: Não é aplicável nenhuma obrigação de subcontratação.\n\n25 - COMPRA PÚBLICA ESTRATÉGICA\nCompra Pública Estratégica: Inexistência de contratação pública estratégica\n\n26 - INFORMAÇÕES ADICIONAIS\nContrato adequado para PME: Sim\nCobertura ACP (Acordo dos Contratos Públicos da Organização Mundial do Comércio): Não\n\n27 - IDENTIFICAÇÃO E CONTACTOS DO ÓRGÃO DE RECURSOS ADMINISTRATIVOS\nDesignação: Direção do Instituto de Telecomunicações\nEndereço: Campus Universitário de Santiago\nCódigo postal: 3810-193\nLocalidade: Aveiro\nTelefone: +351 234377900\nFax: +351 234377901\nEndereço eletrónico: contratacao@av.it.pt\n\n28 - IDENTIFICAÇÃO DO(S) AUTOR(ES) DE ANÚNCIO\nNome: José Marcelino Pousa\nCargo: Diretor Geral\n419668562",
    "nipc": "502854200",
    "distrito": "Aveiro",
    "concelho": "Aveiro",
    "freguesia": "Todas",
    "site": "www.it.pt",
    "email": "contratacao@av.it.pt",
    "designacao_contrato": "Contratação de uma Ferramenta de Gestão de Recursos Humanos",
    "descricao": "Contratação de uma Ferramenta de Gestão de Recursos Humanos",
    "preco_base": "105.000,00 EUR",
    "prazo_execucao": "3 ANOS",
    "prazo_apresentacao_propostas": "31-10-2025 18:00",
    "fundos_eu": "Não",
    "plataforma_eletronica": "VORTAL",
    "url_procedimento": "https://community.vortal.biz/public/",
    "autor_nome": "José Marcelino Pousa",
    "autor_cargo": "Diretor Geral"
  },
  {
    "numero_procedimento": "N/A",
    "entidade": "Instituto da Conservação da Natureza e das Florestas, I. P.",
    "link": "https://diariodarepublica.pt/dr/detalhe/contrato-publico/27396-940618794",
    "detalhes_completos": "1 - IDENTIFICAÇÃO E CONTACTOS DA ENTIDADE ADJUDICANTE\nDesignação da entidade adjudicante: Instituto da Conservação da Natureza e das Florestas, I. P.\nNIPC: 510342647\nEndereço: Av. Dr. Alfredo Magalhães Ramalho, nº 1\nCódigo postal: 1495-165\nLocalidade: Lisboa\nPaís: Portugal\nNUT III: PT170\nDistrito: Lisboa\nConcelho: Oeiras\nFreguesia: União das Freguesias de Algés, Linda-a-Velha e Cruz Quebrada-Dafundo\nTelefone: 213124800\nFax: 213124800\nEndereço da Entidade (URL): https://www.icnf.pt/\nEndereço Eletrónico: geral@icnf.pt\neDelivery Gateway (URL): https://community.vortal.biz/public/\nFunção da Organização: Adquirente\nNorma jurídica da Entidade Adjudicante: Instituição, órgão ou agência da UE\nÁrea de atividade da Autoridade Adjudicante: Proteção ambiental\n\n2 - JORNAL OFICIAL DA UNIÃO EUROPEIA\nO procedimento a que este anúncio diz respeito também é publicitado no Jornal Oficial da União Europeia? Sim\n\n3 - AVISO\nModelo de Anúncio: Concurso público\nData de Envio do Anúncio: 15-10-2025\n\n5 - PROCESSO\nTipo de Procedimento: Concurso público\nPreço base do procedimento: Sim\nValor do preço base do procedimento: 4.400.000,00 EUR\nProcedimento com lotes? Não\n\n6 - OBJETO DO CONTRATO\nNúmero de referência interna: CP/38/2025/ICNF/SEDE\nDesignação do contrato: Aquisição de 55 veículos ligeiros de combate a incêndios para as equipas de sapadores florestais\nDescrição: Aquisição de 55 veículos ligeiros de combate a incêndios para as equipas de sapadores florestais\nOpções: Não\nTipo de Contrato Principal: Aquisição de Bens Móveis\nTipo de Contrato: Aquisição de Bens Móveis\nClassificação CPV (Vocabulário Comum para os Contratos Públicos)\nObjeto principal\nVocabulário Principal: 34100000\nPreço base s/IVA: 4.400.000,00 EUR\n\n7 - INDICAÇÕES ADICIONAIS\nO contrato envolve aquisição conjunta (satisfação de várias entidades)? Não\nO contrato é adjudicado por uma central de compras? Não\n\n8 - TÉCNICAS\nO concurso destina-se à celebração de um acordo-quadro? Inexistência de acordo-quadro\nÉ utilizado um leilão eletrónico? Não\nÉ adotada uma fase de negociação? Não\nSistema de Aquisição Dinâmico: Inexistência de sistema de aquisição dinâmico\n\n9 - LOCAL DA EXECUÇÃO DO CONTRATO\nLOCAL DA EXECUÇÃO DO CONTRATO (PROCEDIMENTO)\nPaís: Portugal\nNUT III: PT170\nLocalidade: Lisboa\nDistrito: Lisboa\nConcelho: Lisboa\nFreguesia: Freguesia de Avenidas Novas\n\n10 - PRAZO DE EXECUÇÃO DO CONTRATO\nPrazo de execução do contrato: 150 DIAS\nPrevisão de renovações: Não\n\n11 - FUNDOS EU\nTêm fundos EU? Sim\n\n12 - DOCUMENTOS DE HABILITAÇÃO\nHabilitação para o exercício da atividade profissional: Não\n\n13 - CONDIÇÕES DE APRESENTAÇÃO\nPlataforma eletrónica utilizada pela entidade adjudicante: VORTAL\nURL para Apresentação: https://community.vortal.biz/public/\nAdmissibilidade da apresentação de propostas variantes: Não autorizado\nPrazo para apresentação das propostas: 14-11-2025 23:59\nPrazo durante o qual os concorrentes são obrigados a manter as respetivas propostas: 88 dias a contar do termo do prazo para a apresentação das propostas\nApresentação de Catálogo Eletrónico: Não autorizado\nIndicação de Subcontratação na Proposta: Inexistência de indicação de subcontratação\n\n14 - PRESTAÇÃO DE CAUÇÃO\nPrestação de caução: Sim\nPercentagem: 3.5%\nDescrição da Garantia Exigida: Conforme peças do procedimento\n\n15 - FORNECIMENTO DAS PEÇAS DO CONCURSO, APRESENTAÇÃO DE PEDIDOS DE PARTICIPAÇÃO E APRESENTAÇÃO DAS PROPOSTAS\nLink para acesso às peças do concurso (URL): https://community.vortal.biz/Public/public-tender-documents/TGxydG8rUlhsbWlGelV1R1gvUmlCZGZxUUJDOU9zWHFhTDNFUW01V05TbzRYcHd4OHJPZUpMbnNRQUc5MXg2Q1h2clorcmhjM0VEQnJtZGtEa1hrNHc9PTRJJkBy\n\n20 - OUTROS REQUISITOS\nInformação sobre contratos reservados. Aplica-se a contratos reservados (54º-A)? Não\n\n21 - CRITÉRIO DE ADJUDICAÇÃO\nMultifator: Não\nMonofator:\nNome: Outros\nOutro nome: Preço\n\n24 - CONDIÇÕES DO CONTRATO\nFaturação Eletrónica: Permitido\nObrigação de Subcontratação:\nCódigo da Obrigação de Subcontratação: Não é aplicável nenhuma obrigação de subcontratação.\n\n25 - COMPRA PÚBLICA ESTRATÉGICA\nCompra Pública Estratégica: Redução dos impactos ambientais\nDescrição do Processo de Adjudicação Estratégico: Conforme as peças do procedimento\nCritérios de contratos Públicos Ecológicos: Critérios de contratação pública ecológica nacional\nCategorias da estratégia nacional: Outros\nOutra categoria (Descrição): Desempenho energético\nDiretiva Veículos Não Poluentes: Não\nCritério de Acessibilidade: Os critérios de acessibilidade para as pessoas com deficiência não estão incluídos porque o contrato não se destina a pessoas singulares\n\n26 - INFORMAÇÕES ADICIONAIS\nContrato adequado para PME: Sim\nCobertura ACP (Acordo dos Contratos Públicos da Organização Mundial do Comércio): Não\n\n27 - IDENTIFICAÇÃO E CONTACTOS DO ÓRGÃO DE RECURSOS ADMINISTRATIVOS\nDesignação: Conselho Diretivo do ICNF, I. P.\nEndereço: Av. Dr.Alfredo Magalhães Ramalho 1\nCódigo postal: 1495-165\nLocalidade: Oeiras\nTelefone: +351 213507900\nFax: +351 000000000\nEndereço eletrónico: geral@icnf.pt\n\n28 - IDENTIFICAÇÃO DO(S) AUTOR(ES) DE ANÚNCIO\nNome: José Nascimento\nCargo: Perito\n419658218",
    "nipc": "510342647",
    "distrito": "Lisboa",
    "concelho": "Oeiras",
    "freguesia": "União das Freguesias de Algés, Linda-a-Velha e Cruz Quebrada-Dafundo",
    "site": "https://www.icnf.pt/",
    "email": "geral@icnf.pt",
    "designacao_contrato": "Aquisição de 55 veículos ligeiros de combate a incêndios para as equipas de sapadores florestais",
    "descricao": "Aquisição de 55 veículos ligeiros de combate a incêndios para as equipas de sapadores florestais",
    "preco_base": "4.400.000,00 EUR",
    "prazo_execucao": "150 DIAS",
    "prazo_apresentacao_propostas": "14-11-2025 23:59",
    "fundos_eu": "Sim",
    "plataforma_eletronica": "VORTAL",
    "url_procedimento": "https://community.vortal.biz/public/",
    "autor_nome": "José Nascimento",
    "autor_cargo": "Perito"
  },
  {
    "numero_procedimento": "N/A",
    "entidade": "Município de Silves",
    "link": "https://diariodarepublica.pt/dr/detalhe/contrato-publico/27397-940618795",
    "detalhes_completos": "1 - IDENTIFICAÇÃO E CONTACTOS DA ENTIDADE ADJUDICANTE\nDesignação da entidade adjudicante: Município de Silves\nNIPC: 506818837\nServiço/Órgão/Pessoa de contacto: Divisão de Obras Municipais e Trânsito\nEndereço: Rua da Sé, 6 - 1º\nCódigo postal: 8300-140\nLocalidade: Silves\nPaís: Portugal\nNUT III: PT150\nDistrito: Faro\nConcelho: Silves\nFreguesia: União das Freguesias de Algoz e Tunes\nTelefone: 282440800\nFax: 282440850\nEndereço da Entidade (URL): https://www.acingov.pt\nEndereço Eletrónico: obras.municipais@cm-silves.pt\neDelivery Gateway (URL): https://www.acingov.pt\nFunção da Organização: Adquirente\nNorma jurídica da Entidade Adjudicante: Organismo de direito público\nÁrea de atividade da Autoridade Adjudicante: Serviços públicos das administrações públicas\n\n2 - JORNAL OFICIAL DA UNIÃO EUROPEIA\nO procedimento a que este anúncio diz respeito também é publicitado no Jornal Oficial da União Europeia? Não\n\n3 - AVISO\nModelo de Anúncio: Concurso público\nData de Envio do Anúncio: 17-10-2025\n\n5 - PROCESSO\nTipo de Procedimento: Concurso público\nPreço base do procedimento: Sim\nValor do preço base do procedimento: 75.000,00 EUR\nProcedimento com lotes? Não\n\n6 - OBJETO DO CONTRATO\nNúmero de referência interna: 1351/DOMT\nDesignação do contrato: Reparação do Pavimento na VAL 2028, Urbanização dos Vales do Algoz\nDescrição: Reparação do Pavimento na VAL 2028, Urbanização dos Vales do Algoz.\nTipo de Contrato Principal: Empreitada de Obras Públicas\nTipo de Contrato: Empreitada de Obras Públicas\nClassificação CPV (Vocabulário Comum para os Contratos Públicos)\nObjeto principal\nVocabulário Principal: 45233142\nPreço base s/IVA: 75.000,00 EUR\n\n7 - INDICAÇÕES ADICIONAIS\nO contrato envolve aquisição conjunta (satisfação de várias entidades)? Não\nO contrato é adjudicado por uma central de compras? Não\n\n8 - TÉCNICAS\nO concurso destina-se à celebração de um acordo-quadro? Inexistência de acordo-quadro\nÉ utilizado um leilão eletrónico? Não\nÉ adotada uma fase de negociação? Não\nSistema de Aquisição Dinâmico: Inexistência de sistema de aquisição dinâmico\n\n9 - LOCAL DA EXECUÇÃO DO CONTRATO\nLOCAL DA EXECUÇÃO DO CONTRATO (PROCEDIMENTO)\nPaís: Portugal\nNUT III: PT150\nLocalidade: União das Freguesias de Algoz e Tunes\nDistrito: Faro\nConcelho: Silves\nFreguesia: União das Freguesias de Algoz e Tunes\n\n10 - PRAZO DE EXECUÇÃO DO CONTRATO\nPrazo de execução do contrato: 60 DIAS\nPrevisão de renovações: Não\n\n11 - FUNDOS EU\nTêm fundos EU? Não\n\n12 - DOCUMENTOS DE HABILITAÇÃO\nHabilitação para o exercício da atividade profissional: Sim\nTipo: Alvará\nDescrição: A 1º subcategoria da 2ª categoria, em classe que cubra o valor global da proposta.\n\n13 - CONDIÇÕES DE APRESENTAÇÃO\nPlataforma eletrónica utilizada pela entidade adjudicante: ACIN\nURL para Apresentação: https://www.acingov.pt\nAdmissibilidade da apresentação de propostas variantes: Não autorizado\nPrazo para apresentação das propostas: 16-11-2025 23:59\nPrazo durante o qual os concorrentes são obrigados a manter as respetivas propostas: 120 dias a contar do termo do prazo para a apresentação das propostas\nIndicação de Subcontratação na Proposta: Inexistência de indicação de subcontratação\n\n14 - PRESTAÇÃO DE CAUÇÃO\nPrestação de caução: Sim\nPercentagem: 5%\nDescrição da Garantia Exigida: O valor da caução é de 5.00% do preço contratual.\n\n15 - FORNECIMENTO DAS PEÇAS DO CONCURSO, APRESENTAÇÃO DE PEDIDOS DE PARTICIPAÇÃO E APRESENTAÇÃO DAS PROPOSTAS\nLink para acesso às peças do concurso (URL): https://www.acingov.pt/acingovprod/2/zonaPublica/zona_publica_c/donwloadProcedurePiece/OTg2NDY0\n\n20 - OUTROS REQUISITOS\nInformação sobre contratos reservados. Aplica-se a contratos reservados (54º-A)? Não\n\n21 - CRITÉRIO DE ADJUDICAÇÃO\nMultifator: Não\nMonofator:\nNome: Preço\n\n24 - CONDIÇÕES DO CONTRATO\nFaturação Eletrónica: Permitido\nObrigação de Subcontratação:\nCódigo da Obrigação de Subcontratação: Não é aplicável nenhuma obrigação de subcontratação.\n\n25 - COMPRA PÚBLICA ESTRATÉGICA\nCompra Pública Estratégica: Inexistência de contratação pública estratégica\n\n26 - INFORMAÇÕES ADICIONAIS\nContrato adequado para PME: Sim\nCobertura ACP (Acordo dos Contratos Públicos da Organização Mundial do Comércio): Não\n\n27 - IDENTIFICAÇÃO E CONTACTOS DO ÓRGÃO DE RECURSOS ADMINISTRATIVOS\nDesignação: Município de Silves\nEndereço: Rua Pintor Bernardo Marques\nCódigo postal: 8300-175\nLocalidade: Silves\nTelefone: 351282440800\nFax: 351282440850\nEndereço eletrónico: gabinete.presidente@cm-silves.pt\nPrazo de interposição do recurso: 5 dias\n\n28 - IDENTIFICAÇÃO DO(S) AUTOR(ES) DE ANÚNCIO\nNome: Rosa Cristina Gonçalves da Palma\nCargo: Presidente da Câmara\n419660745",
    "nipc": "506818837",
    "distrito": "Faro",
    "concelho": "Silves",
    "freguesia": "União das Freguesias de Algoz e Tunes",
    "site": "https://www.acingov.pt",
    "email": "obras.municipais@cm-silves.pt",
    "designacao_contrato": "Reparação do Pavimento na VAL 2028, Urbanização dos Vales do Algoz",
    "descricao": "Reparação do Pavimento na VAL 2028, Urbanização dos Vales do Algoz.",
    "preco_base": "75.000,00 EUR",
    "prazo_execucao": "60 DIAS",
    "prazo_apresentacao_propostas": "16-11-2025 23:59",
    "fundos_eu": "Não",
    "plataforma_eletronica": "ACIN",
    "url_procedimento": "https://www.acingov.pt",
    "autor_nome": "Rosa Cristina Gonçalves da Palma",
    "autor_cargo": "Presidente da Câmara"
  },
  {
    "numero_procedimento": "N/A",
    "entidade": "Serviços Municipalizados de Viseu",
    "link": "https://diariodarepublica.pt/dr/detalhe/contrato-publico/27398-940641011",
    "detalhes_completos": "1 - IDENTIFICAÇÃO E CONTACTOS DA ENTIDADE ADJUDICANTE\nDesignação da entidade adjudicante: Serviços Municipalizados de Viseu\nNIPC: 680020063\nEndereço: Rua Conselheiro Afonso de Melo\nCódigo postal: 3510-024\nLocalidade: Viseu\nPaís: Portugal\nNUT III: PT16G\nDistrito: Viseu\nConcelho: Viseu\nFreguesia: Freguesia de Viseu\nTelefone: 232470670\nFax: 232424080\nEndereço da Entidade (URL): www.smasviseu.pt\nEndereço Eletrónico: geral@smasviseu.pt\neDelivery Gateway (URL): https://www.acingov.pt\nFunção da Organização: Adquirente\nNorma jurídica da Entidade Adjudicante: Autoridade local\nÁrea de atividade da Autoridade Adjudicante: Serviços públicos das administrações públicas\n\n2 - JORNAL OFICIAL DA UNIÃO EUROPEIA\nO procedimento a que este anúncio diz respeito também é publicitado no Jornal Oficial da União Europeia? Não\n\n3 - AVISO\nModelo de Anúncio: Concurso público\nData de Envio do Anúncio: 17-10-2025\n\n5 - PROCESSO\nTipo de Procedimento: Concurso público\nPreço base do procedimento: Sim\nValor do preço base do procedimento: 644.355,92 EUR\nProcedimento com lotes? Não\n\n6 - OBJETO DO CONTRATO\nNúmero de referência interna: E1213\nDesignação do contrato: Remodelação do Saneamento Básico na Av. Manuel Loureiro e Transversais em Pascoal - 3º Procedimento\nDescrição: Remodelação do Saneamento Básico na Av. Manuel Loureiro e Transversais em Pascoal - 3º Procedimento\nTipo de Contrato Principal: Empreitada de Obras Públicas\nTipo de Contrato: Empreitada de Obras Públicas\nClassificação CPV (Vocabulário Comum para os Contratos Públicos)\nObjeto principal\nVocabulário Principal: 45232460\nPreço base s/IVA: 644.355,92 EUR\n\n7 - INDICAÇÕES ADICIONAIS\nO contrato envolve aquisição conjunta (satisfação de várias entidades)? Não\nO contrato é adjudicado por uma central de compras? Não\n\n8 - TÉCNICAS\nO concurso destina-se à celebração de um acordo-quadro? Inexistência de acordo-quadro\nÉ utilizado um leilão eletrónico? Não\nÉ adotada uma fase de negociação? Não\nSistema de Aquisição Dinâmico: Inexistência de sistema de aquisição dinâmico\n\n9 - LOCAL DA EXECUÇÃO DO CONTRATO\nLOCAL DA EXECUÇÃO DO CONTRATO (PROCEDIMENTO)\nPaís: Portugal\nNUT III: PT16G\nLocalidade: Freguesia de Abraveses\nDistrito: Viseu\nConcelho: Viseu\nFreguesia: Freguesia de Abraveses\n\n10 - PRAZO DE EXECUÇÃO DO CONTRATO\nPrazo de execução do contrato: 365 DIAS\nPrevisão de renovações: Não\n\n11 - FUNDOS EU\nTêm fundos EU? Não\n\n12 - DOCUMENTOS DE HABILITAÇÃO\nHabilitação para o exercício da atividade profissional: Sim\nTipo: Alvará\nDescrição: O certificado do alvará de construção previsto deve conter:\nA 6ª subcategoria da 2ª categoria, sendo que a classe da 6ª subcategoria da 2ª categoria tem de ser de classe que cubra o valor global da proposta e integrar-se na categoria em que o tipo da obra se enquadra.\n\n13 - CONDIÇÕES DE APRESENTAÇÃO\nPlataforma eletrónica utilizada pela entidade adjudicante: ACIN\nURL para Apresentação: https://www.acingov.pt\nAdmissibilidade da apresentação de propostas variantes: Não autorizado\nPrazo para apresentação das propostas: 16-11-2025 23:59\nPrazo durante o qual os concorrentes são obrigados a manter as respetivas propostas: 120 dias a contar do termo do prazo para a apresentação das propostas\nIndicação de Subcontratação na Proposta: Inexistência de indicação de subcontratação\n\n14 - PRESTAÇÃO DE CAUÇÃO\nPrestação de caução: Sim\nPercentagem: 5%\nDescrição da Garantia Exigida: O valor da caução é de 5.00% do preço contratual.\n\n15 - FORNECIMENTO DAS PEÇAS DO CONCURSO, APRESENTAÇÃO DE PEDIDOS DE PARTICIPAÇÃO E APRESENTAÇÃO DAS PROPOSTAS\nLink para acesso às peças do concurso (URL): https://www.acingov.pt/acingovprod/2/zonaPublica/zona_publica_c/donwloadProcedurePiece/OTg2MTQy\n\n20 - OUTROS REQUISITOS\nInformação sobre contratos reservados. Aplica-se a contratos reservados (54º-A)? Não\n\n21 - CRITÉRIO DE ADJUDICAÇÃO\nMultifator: Não\nMonofator:\nNome: Preço\n\n24 - CONDIÇÕES DO CONTRATO\nFaturação Eletrónica: Permitido\nObrigação de Subcontratação:\nCódigo da Obrigação de Subcontratação: Não é aplicável nenhuma obrigação de subcontratação.\n\n25 - COMPRA PÚBLICA ESTRATÉGICA\nCompra Pública Estratégica: Inexistência de contratação pública estratégica\n\n26 - INFORMAÇÕES ADICIONAIS\nContrato adequado para PME: Sim\nCobertura ACP (Acordo dos Contratos Públicos da Organização Mundial do Comércio): Não\n\n27 - IDENTIFICAÇÃO E CONTACTOS DO ÓRGÃO DE RECURSOS ADMINISTRATIVOS\nDesignação: Município de Viseu\nEndereço: Praça da República S/N\nCódigo postal: 3514-501\nLocalidade: Viseu\nTelefone: 00351232427427\nFax: 00351232423112\nEndereço eletrónico: geral@cmviseu.pt\nPrazo de interposição do recurso: 5 dias\n\n28 - IDENTIFICAÇÃO DO(S) AUTOR(ES) DE ANÚNCIO\nNome: João Paulo Lopes Gouveia\nCargo: Vogal do Conselho de Administração\n419648741",
    "nipc": "680020063",
    "distrito": "Viseu",
    "concelho": "Viseu",
    "freguesia": "Freguesia de Viseu",
    "site": "www.smasviseu.pt",
    "email": "geral@smasviseu.pt",
    "designacao_contrato": "Remodelação do Saneamento Básico na Av. Manuel Loureiro e Transversais em Pascoal - 3º Procedimento",
    "descricao": "Remodelação do Saneamento Básico na Av. Manuel Loureiro e Transversais em Pascoal - 3º Procedimento",
    "preco_base": "644.355,92 EUR",
    "prazo_execucao": "365 DIAS",
    "prazo_apresentacao_propostas": "16-11-2025 23:59",
    "fundos_eu": "Não",
    "plataforma_eletronica": "ACIN",
    "url_procedimento": "https://www.acingov.pt",
    "autor_nome": "João Paulo Lopes Gouveia",
    "autor_cargo": "Vogal do Conselho de Administração"
  },
  {
    "numero_procedimento": "N/A",
    "entidade": "Município de Paços de Ferreira",
    "link": "https://diariodarepublica.pt/dr/detalhe/contrato-publico/27399-940641012",
    "detalhes_completos": "1 - IDENTIFICAÇÃO E CONTACTOS DA ENTIDADE ADJUDICANTE\nDesignação da entidade adjudicante: Município de Paços de Ferreira\nNIPC: 502173297\nServiço/Órgão/Pessoa de contacto: Município de Paços de Ferreira\nEndereço: Praça da República, n.º 46\nCódigo postal: 4595-527\nLocalidade: Paços de Ferreira\nPaís: Portugal\nNUT III: PT11C\nDistrito: Porto\nConcelho: Paços de Ferreira\nFreguesia: Freguesia de Paços de Ferreira\nTelefone: 255860700\nFax: 255860734\nEndereço da Entidade (URL): www.cm-pacosdeferreira.pt\nEndereço Eletrónico: geral@cm-pacosdeferreira.pt\neDelivery Gateway (URL): https://www.acingov.pt\nFunção da Organização: Adquirente\nNorma jurídica da Entidade Adjudicante: Organismo de direito público\nÁrea de atividade da Autoridade Adjudicante: Serviços públicos das administrações públicas\n\n2 - JORNAL OFICIAL DA UNIÃO EUROPEIA\nO procedimento a que este anúncio diz respeito também é publicitado no Jornal Oficial da União Europeia? Não\n\n3 - AVISO\nModelo de Anúncio: Concurso público\nData de Envio do Anúncio: 17-10-2025\n\n5 - PROCESSO\nTipo de Procedimento: Concurso público\nPreço base do procedimento: Sim\nValor do preço base do procedimento: 955.932,00 EUR\nProcedimento com lotes? Não\n\n6 - OBJETO DO CONTRATO\nNúmero de referência interna: 23/E/2023\nDesignação do contrato: Requalificação das Avenidas da Trindade e Águas Altas e Ruas da Pancada e Prof. Vieira Dinis, freguesia de Meixomil\nDescrição: Requalificação das Avenidas da Trindade e Águas Altas e Ruas da Pancada e Prof. Vieira Dinis, freguesia de Meixomil\nTipo de Contrato Principal: Empreitada de Obras Públicas\nTipo de Contrato: Empreitada de Obras Públicas\nClassificação CPV (Vocabulário Comum para os Contratos Públicos)\nObjeto principal\nVocabulário Principal: 45232451\nPreço base s/IVA: 955.932,00 EUR\n\n7 - INDICAÇÕES ADICIONAIS\nO contrato envolve aquisição conjunta (satisfação de várias entidades)? Não\nO contrato é adjudicado por uma central de compras? Não\n\n8 - TÉCNICAS\nO concurso destina-se à celebração de um acordo-quadro? Inexistência de acordo-quadro\nÉ utilizado um leilão eletrónico? Não\nÉ adotada uma fase de negociação? Não\nSistema de Aquisição Dinâmico: Inexistência de sistema de aquisição dinâmico\n\n9 - LOCAL DA EXECUÇÃO DO CONTRATO\nLOCAL DA EXECUÇÃO DO CONTRATO (PROCEDIMENTO)\nPaís: Portugal\nNUT III: PT11C\nLocalidade: Freguesia de Meixomil\nDistrito: Porto\nConcelho: Paços de Ferreira\nFreguesia: Freguesia de Meixomil\n\n10 - PRAZO DE EXECUÇÃO DO CONTRATO\nPrazo de execução do contrato: 16 MESES\nPrevisão de renovações: Não\n\n11 - FUNDOS EU\nTêm fundos EU? Não\n\n12 - DOCUMENTOS DE HABILITAÇÃO\nHabilitação para o exercício da atividade profissional: Sim\nTipo: Alvará\nDescrição: a 1.ª subcategoria da 2.ª categoria, a qual tem de ser de classe que cubra o valor global da proposta e integrar-se na categoria em que o tipo da obra se enquadra e as 6.ª e 8.ª subcategorias da 2.ª categoria, nas classes correspondente à parte dos trabalhos a que respeitem, caso o concorrente não recorra à declarações de compromisso de sub-empreiteiros.\n\n13 - CONDIÇÕES DE APRESENTAÇÃO\nPlataforma eletrónica utilizada pela entidade adjudicante: ACIN\nURL para Apresentação: https://www.acingov.pt\nAdmissibilidade da apresentação de propostas variantes: Não autorizado\nPrazo para apresentação das propostas: 10-11-2025 23:59\nPrazo durante o qual os concorrentes são obrigados a manter as respetivas propostas: 90 dias a contar do termo do prazo para a apresentação das propostas\nIndicação de Subcontratação na Proposta: Inexistência de indicação de subcontratação\n\n14 - PRESTAÇÃO DE CAUÇÃO\nPrestação de caução: Sim\nPercentagem: 5%\nDescrição da Garantia Exigida: O valor da caução é de 5.00% do preço contratual.\n\n15 - FORNECIMENTO DAS PEÇAS DO CONCURSO, APRESENTAÇÃO DE PEDIDOS DE PARTICIPAÇÃO E APRESENTAÇÃO DAS PROPOSTAS\nLink para acesso às peças do concurso (URL): https://www.acingov.pt/acingovprod/2/zonaPublica/zona_publica_c/donwloadProcedurePiece/OTg2NTI1\n\n20 - OUTROS REQUISITOS\nInformação sobre contratos reservados. Aplica-se a contratos reservados (54º-A)? Não\n\n21 - CRITÉRIO DE ADJUDICAÇÃO\nMultifator: Não\nMonofator:\nNome: Preço\n\n24 - CONDIÇÕES DO CONTRATO\nFaturação Eletrónica: Permitido\nObrigação de Subcontratação:\nCódigo da Obrigação de Subcontratação: Não é aplicável nenhuma obrigação de subcontratação.\n\n25 - COMPRA PÚBLICA ESTRATÉGICA\nCompra Pública Estratégica: Inexistência de contratação pública estratégica\n\n26 - INFORMAÇÕES ADICIONAIS\nContrato adequado para PME: Não\nCobertura ACP (Acordo dos Contratos Públicos da Organização Mundial do Comércio): Não\n\n27 - IDENTIFICAÇÃO E CONTACTOS DO ÓRGÃO DE RECURSOS ADMINISTRATIVOS\nDesignação: Câmara Municipal\nEndereço: Praça da República, n.º 46\nCódigo postal: 4590-527\nLocalidade: Paços de Ferreira\nTelefone: 255860700\nFax: 255860734\nEndereço eletrónico: geral@cm-pacosdeferreira.pt\nPrazo de interposição do recurso: 5 dias\n\n28 - IDENTIFICAÇÃO DO(S) AUTOR(ES) DE ANÚNCIO\nNome: Paulo Ferreira\nCargo: Presidente da Câmara Municipal\n419655326",
    "nipc": "502173297",
    "distrito": "Porto",
    "concelho": "Paços de Ferreira",
    "freguesia": "Freguesia de Paços de Ferreira",
    "site": "www.cm-pacosdeferreira.pt",
    "email": "geral@cm-pacosdeferreira.pt",
    "designacao_contrato": "Requalificação das Avenidas da Trindade e Águas Altas e Ruas da Pancada e Prof. Vieira Dinis, freguesia de Meixomil",
    "descricao": "Requalificação das Avenidas da Trindade e Águas Altas e Ruas da Pancada e Prof. Vieira Dinis, freguesia de Meixomil",
    "preco_base": "955.932,00 EUR",
    "prazo_execucao": "16 MESES",
    "prazo_apresentacao_propostas": "10-11-2025 23:59",
    "fundos_eu": "Não",
    "plataforma_eletronica": "ACIN",
    "url_procedimento": "https://www.acingov.pt",
    "autor_nome": "Paulo Ferreira",
    "autor_cargo": "Presidente da Câmara Municipal"
  }
]