[
  {
    "numero_procedimento": "N/A",
    "entidade": "Museus e Monumentos de Portugal, E. P. E.",
    "link": "https://diariodarepublica.pt/dr/detalhe/contrato-publico/24579-935742298",
    "detalhes_completos": "1 - IDENTIFICAÇÃO E CONTACTOS DA ENTIDADE ADJUDICANTE\nDesignação da entidade adjudicante: Museus e Monumentos de Portugal, E. P. E.\nNIPC: 517804417\nServiço/Órgão/Pessoa de contacto: Direção de Gestão\nEndereço: Palácio Nacional da Ajuda, Ala Sul\nCódigo postal: 1349-021\nLocalidade: Lisboa\nPaís: Portugal\nNUT III: PTZZZ\nDistrito: Todos\nConcelho: Todos\nFreguesia: Todas\nTelefone: 213650800\nEndereço da Entidade (URL): https://www.museusemonumentos.pt/pt\nEndereço Eletrónico: contratos@museusemonumentos.pt\neDelivery Gateway (URL): https://www.acingov.pt\nFunção da Organização: Adquirente\nSubfunção da Organização: Organização que fornece informações adicionais sobre o processo de adjudicação; Organização que fornece mais informações sobre os prazos dos procedimentos de recurso; Organização responsável pelo tratamento das propostas; Organização que recebe as propostas; Organização que trata os pedidos de participação; Organização que recebe pedidos de participação; Organização que fornece mais informações sobre os procedimentos de recurso; Organização que assina o contrato\nNorma jurídica da Entidade Adjudicante: Organismo de direito público\nÁrea de atividade da Autoridade Adjudicante: Serviços públicos das administrações públicas\n\n2 - JORNAL OFICIAL DA UNIÃO EUROPEIA\nO procedimento a que este anúncio diz respeito também é publicitado no Jornal Oficial da União Europeia? Não\n\n3 - AVISO\nModelo de Anúncio: Concurso público\nData de Envio do Anúncio: 17-09-2025\n\n5 - PROCESSO\nTipo de Procedimento: Concurso público\nPreço base do procedimento: Sim\nValor do preço base do procedimento: 112.000,00 EUR\nProcedimento com lotes? Não\n\n6 - OBJETO DO CONTRATO\nNúmero de referência interna: CP/14/2025\nDesignação do contrato: Locação de 17 veículos, em regime de rent a car\nDescrição: Locação de 17 veículos, em regime de rent a car\nTipo de Contrato Principal: Locação de Bens Móveis\nTipo de Contrato: Locação de Bens Móveis\nClassificação CPV (Vocabulário Comum para os Contratos Públicos)\nObjeto principal\nVocabulário Principal: 34110000\nPreço base s/IVA: 112.000,00 EUR\n\n7 - INDICAÇÕES ADICIONAIS\nO contrato envolve aquisição conjunta (satisfação de várias entidades)? Não\nO contrato é adjudicado por uma central de compras? Não\n\n8 - TÉCNICAS\nO concurso destina-se à celebração de um acordo-quadro? Inexistência de acordo-quadro\nÉ utilizado um leilão eletrónico? Não\nÉ adotada uma fase de negociação? Não\nSistema de Aquisição Dinâmico: Inexistência de sistema de aquisição dinâmico\n\n9 - LOCAL DA EXECUÇÃO DO CONTRATO\nLOCAL DA EXECUÇÃO DO CONTRATO (PROCEDIMENTO)\nPaís: Portugal\nNUT III: PTZZZ\nLocalidade: Todos\nDistrito: Todos\nConcelho: Todos\nFreguesia: Todas\n\n10 - PRAZO DE EXECUÇÃO DO CONTRATO\nPrazo de execução do contrato: 12 MESES\nPrevisão de renovações: Não\n\n11 - FUNDOS EU\nTêm fundos EU? Não\n\n12 - DOCUMENTOS DE HABILITAÇÃO\nHabilitação para o exercício da atividade profissional: Não\n\n13 - CONDIÇÕES DE APRESENTAÇÃO\nPlataforma eletrónica utilizada pela entidade adjudicante: ACIN\nURL para Apresentação: https://www.acingov.pt\nAdmissibilidade da apresentação de propostas variantes: Não autorizado\nPrazo para apresentação das propostas: 24-09-2025 23:59\nPrazo durante o qual os concorrentes são obrigados a manter as respetivas propostas: 66 dias a contar do termo do prazo para a apresentação das propostas\nIndicação de Subcontratação na Proposta: Inexistência de indicação de subcontratação\n\n14 - PRESTAÇÃO DE CAUÇÃO\nPrestação de caução: Não\n\n15 - FORNECIMENTO DAS PEÇAS DO CONCURSO, APRESENTAÇÃO DE PEDIDOS DE PARTICIPAÇÃO E APRESENTAÇÃO DAS PROPOSTAS\nLink para acesso às peças do concurso (URL): https://www.acingov.pt/acingovprod/2/zonaPublica/zona_publica_c/donwloadProcedurePiece/OTc4Mjg2\n\n20 - OUTROS REQUISITOS\nInformação sobre contratos reservados. Aplica-se a contratos reservados (54º-A)? Não\n\n21 - CRITÉRIO DE ADJUDICAÇÃO\nMultifator: Sim\nFator: \nNome: Preço\nPonderação: 80%\nSubfatores: Não\nFator: \nNome: Sustentabilidade ambiental ou social\nPonderação: 20%\nSubfatores: Não\n\n24 - CONDIÇÕES DO CONTRATO\nFaturação Eletrónica: Necessário\nObrigação de Subcontratação:\nCódigo da Obrigação de Subcontratação: Não é aplicável nenhuma obrigação de subcontratação.\n\n25 - COMPRA PÚBLICA ESTRATÉGICA\nCompra Pública Estratégica: Inexistência de contratação pública estratégica\n\n26 - INFORMAÇÕES ADICIONAIS\nContrato adequado para PME: Sim\nCobertura ACP (Acordo dos Contratos Públicos da Organização Mundial do Comércio): Não\n\n27 - IDENTIFICAÇÃO E CONTACTOS DO ÓRGÃO DE RECURSOS ADMINISTRATIVOS\nDesignação: Tribunal Administrativo de Círculo de Lisboa\nEndereço: Av D. João II, nº 1.08.01 Edif, G - 6º andar, 1900-097 Lisboa\nCódigo postal: 1900-097\nLocalidade: Lisboa\nEndereço eletrónico: lisboa.tacl@tribunais.org.pt\nPrazo de interposição do recurso: 5 dias\n\n28 - IDENTIFICAÇÃO DO(S) AUTOR(ES) DE ANÚNCIO\nNome: Márcia Martins\nCargo: Técnica de Contratação Pública\n419544923",
    "nipc": "517804417",
    "distrito": "Todos",
    "concelho": "Todos",
    "freguesia": "Todas",
    "site": "https://www.museusemonumentos.pt/pt",
    "email": "contratos@museusemonumentos.pt",
    "designacao_contrato": "Locação de 17 veículos, em regime de rent a car",
    "descricao": "Locação de 17 veículos, em regime de rent a car",
    "preco_base": "112.000,00 EUR",
    "prazo_execucao": "12 MESES",
    "prazo_apresentacao_propostas": "24-09-2025 23:59",
    "fundos_eu": "Não",
    "plataforma_eletronica": "ACIN",
    "url_procedimento": "https://www.acingov.pt",
    "autor_nome": "Márcia Martins",
    "autor_cargo": "Técnica de Contratação Pública"
  },
  {
    "numero_procedimento": "N/A",
    "entidade": "Serviços Municipalizados de Sintra (SMAS)",
    "link": "https://diariodarepublica.pt/dr/detalhe/contrato-publico/24581-935742300",
    "detalhes_completos": "1 - IDENTIFICAÇÃO E CONTACTOS DA ENTIDADE ADJUDICANTE\nDesignação da entidade adjudicante: Serviços Municipalizados de Sintra (SMAS)\nNIPC: 680000054\nServiço/Órgão/Pessoa de contacto: aprov.stocks@smas-sintra.pt\nEndereço: Avenida Movimento Da Forças Armadas, 16\nCódigo postal: 2714-503\nLocalidade: Sintra\nPaís: Portugal\nNUT III: PT170\nDistrito: Lisboa\nConcelho: Sintra\nFreguesia: Todas\nTelefone: 219119016\nFax: 219232650\nEndereço da Entidade (URL): www.smas-sintra.pt\nEndereço Eletrónico: aprov.stocks@smas-sintra.pt\neDelivery Gateway (URL): https://community.vortal.biz/public/\nFunção da Organização: Adquirente\nNorma jurídica da Entidade Adjudicante: Autoridade local\nÁrea de atividade da Autoridade Adjudicante: Serviços públicos das administrações públicas\n\n2 - JORNAL OFICIAL DA UNIÃO EUROPEIA\nO procedimento a que este anúncio diz respeito também é publicitado no Jornal Oficial da União Europeia? Sim\n\n3 - AVISO\nModelo de Anúncio: Concurso público\nData de Envio do Anúncio: 15-09-2025\n\n5 - PROCESSO\nTipo de Procedimento: Concurso público\nPreço base do procedimento: Sim\nValor do preço base do procedimento: 493.900,00 EUR\nProcedimento com lotes? Sim\nNº Máx. de Lotes Autorizado: 2\nNúmero máximo de lotes que podem ser adjudicados a um concorrente: 2\n\n6 - OBJETO DO CONTRATO\nNúmero de referência interna: Concurso Público N.º 32PF/2025 \nDesignação do contrato: Concurso Público N.º 32PF/2025  - «Aquisição de Seguros, por Lotes, para 2 Anos (2026 – 2027)»\nDescrição: Aquisição de Seguros, por Lotes, para 2 Anos (2026 – 2027)\nOpções: Não\nTipo de Contrato Principal: Aquisição de Serviços\nTipo de Contrato: Aquisição de Serviços\nClassificação CPV (Vocabulário Comum para os Contratos Públicos)\nObjeto principal\nVocabulário Principal: 66510000\nPreço base s/IVA: 493.900,00 EUR\nLotes: \nNº: LOT-0001\nDescrição do Lote: Lote 1\nPreço base s/IVA: 453.900,00 EUR\nClassificação CPV (Vocabulário Comum para os Contratos Públicos)\nObjeto principal\nVocabulário Principal: 66510000\nNº: LOT-0002\nDescrição do Lote: Lote 2\nPreço base s/IVA: 40.000,00 EUR\nClassificação CPV (Vocabulário Comum para os Contratos Públicos)\nObjeto principal\nVocabulário Principal: 66510000\n\n7 - INDICAÇÕES ADICIONAIS\nO contrato envolve aquisição conjunta (satisfação de várias entidades)? Não\nO contrato é adjudicado por uma central de compras? Não\n\n8 - TÉCNICAS\nO concurso destina-se à celebração de um acordo-quadro? Inexistência de acordo-quadro\nÉ utilizado um leilão eletrónico? Não\nÉ adotada uma fase de negociação? Não\nSistema de Aquisição Dinâmico: Inexistência de sistema de aquisição dinâmico\n\n9 - LOCAL DA EXECUÇÃO DO CONTRATO\nLOCAL DA EXECUÇÃO DO CONTRATO (PROCEDIMENTO)\nPaís: Portugal\nNUT III: PT170\nLocalidade: Lisboa\nDistrito: Lisboa\nConcelho: Sintra\nFreguesia: União das Freguesias de Sintra (Santa Maria e São Miguel, São Martinho e São Pedro de Penaferrim)\nLOCAL DA EXECUÇÃO DO CONTRATO (LOTE)\nIdentificador do Lote: LOT-0001; LOT-0002\nPaís: Portugal\nNUT III: PT170\nLocalidade: Lisboa\nDistrito: Lisboa\nConcelho: Sintra\nFreguesia: União das Freguesias de Sintra (Santa Maria e São Miguel, São Martinho e São Pedro de Penaferrim)\n\n10 - PRAZO DE EXECUÇÃO DO CONTRATO\nIdentificador do Lote: LOT-0001; LOT-0002\nPrazo de execução do contrato: 2 ANOS\nPrevisão de renovações: Não\n\n11 - FUNDOS EU\nIdentificador do Lote: LOT-0001; LOT-0002\nTêm fundos EU? Não\n\n12 - DOCUMENTOS DE HABILITAÇÃO\nHabilitação para o exercício da atividade profissional: Sim\nTipo: Outros\nDescrição - Outros: De acordo com o previsto nas Peças do Procedimento\nDescrição: De acordo com o previsto nas Peças do Procedimento\n\n13 - CONDIÇÕES DE APRESENTAÇÃO\nPlataforma eletrónica utilizada pela entidade adjudicante: VORTAL\nURL para Apresentação: https://community.vortal.biz/public/\nAdmissibilidade da apresentação de propostas variantes: Não autorizado\nPrazo para apresentação das propostas: 21-10-2025 17:00\nPrazo durante o qual os concorrentes são obrigados a manter as respetivas propostas: 90 dias a contar do termo do prazo para a apresentação das propostas\nApresentação de Catálogo Eletrónico: Não autorizado\nIndicação de Subcontratação na Proposta: Inexistência de indicação de subcontratação\n\n14 - PRESTAÇÃO DE CAUÇÃO\nPrestação de caução: Sim\nPercentagem: 5%\nDescrição da Garantia Exigida: De acordo com o previsto nas Peças do Procedimento\n\n15 - FORNECIMENTO DAS PEÇAS DO CONCURSO, APRESENTAÇÃO DE PEDIDOS DE PARTICIPAÇÃO E APRESENTAÇÃO DAS PROPOSTAS\nLink para acesso às peças do concurso (URL): https://community.vortal.biz/Public/public-tender-documents/WjNLTTVOYTRSMFcwZGYvZ084U1IwbTZnZWRlWE1ZM2dGdHdSZHY2U1lKc1B4eWN6WHRLaVZ4azNiVGVDRTQ2Ukk2WjJCMjAxQzdGeFRtU0Y5S3FQVFE9PUM2SVZD\n\n20 - OUTROS REQUISITOS\nIdentificador do Lote: LOT-0001; LOT-0002\nInformação sobre contratos reservados. Aplica-se a contratos reservados (54º-A)? Não\n\n21 - CRITÉRIO DE ADJUDICAÇÃO\nO Critério de adjudicação é diferenciado por lote? Não\nMultifator: Não\nMonofator:\nNome: Preço\n\n24 - CONDIÇÕES DO CONTRATO\nIdentificador do Lote: LOT-0001; LOT-0002\nFaturação Eletrónica: Permitido\nObrigação de Subcontratação:\nCódigo da Obrigação de Subcontratação: Não é aplicável nenhuma obrigação de subcontratação.\n\n25 - COMPRA PÚBLICA ESTRATÉGICA\nCompra Pública Estratégica: Inexistência de contratação pública estratégica\n\n26 - INFORMAÇÕES ADICIONAIS\nIdentificador do Lote: LOT-0001; LOT-0002\nContrato adequado para PME: Sim\nCobertura ACP (Acordo dos Contratos Públicos da Organização Mundial do Comércio): Não\n\n27 - IDENTIFICAÇÃO E CONTACTOS DO ÓRGÃO DE RECURSOS ADMINISTRATIVOS\nDesignação: Câmara Municipal de Sintra\nEndereço: Largo Dr. Virgílio Horta\nCódigo postal: 2714-501\nLocalidade: Sintra\nTelefone: +351 219238500\nFax: +351 219238657\nEndereço eletrónico: geral@cm-sintra.pt\n\n28 - IDENTIFICAÇÃO DO(S) AUTOR(ES) DE ANÚNCIO\nNome: Basílio Adolfo Mendonça Horta da Franca\nCargo: Presidente do Conselho de Administração dos SMAS-Sintra\n419527135",
    "nipc": "680000054",
    "distrito": "Lisboa",
    "concelho": "Sintra",
    "freguesia": "Todas",
    "site": "www.smas-sintra.pt",
    "email": "aprov.stocks@smas-sintra.pt",
    "designacao_contrato": "Concurso Público N.º 32PF/2025 - «Aquisição de Seguros, por Lotes, para 2 Anos (2026 – 2027)»",
    "descricao": "Aquisição de Seguros, por Lotes, para 2 Anos (2026 – 2027)",
    "preco_base": "493.900,00 EUR",
    "prazo_execucao": "2 ANOS",
    "prazo_apresentacao_propostas": "21-10-2025 17:00",
    "fundos_eu": "Não",
    "plataforma_eletronica": "VORTAL",
    "url_procedimento": "https://community.vortal.biz/public/",
    "autor_nome": "Basílio Adolfo Mendonça Horta da Franca",
    "autor_cargo": "Presidente do Conselho de Administração dos SMAS-Sintra"
  },
  {
    "numero_procedimento": "N/A",
    "entidade": "Serviços Municipalizados de Sintra (SMAS)",
    "link": "https://diariodarepublica.pt/dr/detalhe/contrato-publico/24582-935742301",
    "detalhes_completos": "1 - IDENTIFICAÇÃO E CONTACTOS DA ENTIDADE ADJUDICANTE\nDesignação da entidade adjudicante: Serviços Municipalizados de Sintra (SMAS)\nNIPC: 680000054\nServiço/Órgão/Pessoa de contacto: aprov.stocks@smas-sintra.pt\nEndereço: Avenida Movimento Da Forças Armadas, 16\nCódigo postal: 2714-503\nLocalidade: Sintra\nPaís: Portugal\nNUT III: PT170\nDistrito: Lisboa\nConcelho: Sintra\nFreguesia: Todas\nTelefone: 219119016\nFax: 219232650\nEndereço da Entidade (URL): www.smas-sintra.pt\nEndereço Eletrónico: aprov.stocks@smas-sintra.pt\neDelivery Gateway (URL): https://community.vortal.biz/public/\nFunção da Organização: Adquirente\nNorma jurídica da Entidade Adjudicante: Autoridade local\nÁrea de atividade da Autoridade Adjudicante: Serviços públicos das administrações públicas\n\n2 - JORNAL OFICIAL DA UNIÃO EUROPEIA\nO procedimento a que este anúncio diz respeito também é publicitado no Jornal Oficial da União Europeia? Sim\n\n3 - AVISO\nModelo de Anúncio: Concurso público\nData de Envio do Anúncio: 15-09-2025\n\n5 - PROCESSO\nTipo de Procedimento: Concurso público\nPreço base do procedimento: Sim\nValor do preço base do procedimento: 1.409.420,98 EUR\nProcedimento com lotes? Não\n\n6 - OBJETO DO CONTRATO\nNúmero de referência interna: Concurso Público N.º 38PF/2025 \nDesignação do contrato: Concurso Público N.º 38PF/2025  - «Aquisição do Licenciamento do Software SAP S/4HANA Private Cloud Edition e Sucess Factors - Módulos de Recursos Humanos»\nDescrição: Aquisição do Licenciamento do Software SAP S/4HANA Private Cloud Edition e Sucess Factors - Módulos de Recursos Humanos\nOpções: Não\nTipo de Contrato Principal: Aquisição de Bens Móveis\nTipo de Contrato: Aquisição de Bens Móveis\nClassificação CPV (Vocabulário Comum para os Contratos Públicos)\nObjeto principal\nVocabulário Principal: 48100000\nPreço base s/IVA: 1.409.420,98 EUR\n\n7 - INDICAÇÕES ADICIONAIS\nO contrato envolve aquisição conjunta (satisfação de várias entidades)? Não\nO contrato é adjudicado por uma central de compras? Não\n\n8 - TÉCNICAS\nO concurso destina-se à celebração de um acordo-quadro? Inexistência de acordo-quadro\nÉ utilizado um leilão eletrónico? Não\nÉ adotada uma fase de negociação? Não\nSistema de Aquisição Dinâmico: Inexistência de sistema de aquisição dinâmico\n\n9 - LOCAL DA EXECUÇÃO DO CONTRATO\nLOCAL DA EXECUÇÃO DO CONTRATO (PROCEDIMENTO)\nPaís: Portugal\nNUT III: PT170\nLocalidade: Lisboa\nDistrito: Lisboa\nConcelho: Sintra\nFreguesia: União das Freguesias de Sintra (Santa Maria e São Miguel, São Martinho e São Pedro de Penaferrim)\n\n10 - PRAZO DE EXECUÇÃO DO CONTRATO\nPrazo de execução do contrato: 36 MESES\nPrevisão de renovações: Não\n\n11 - FUNDOS EU\nTêm fundos EU? Não\n\n12 - DOCUMENTOS DE HABILITAÇÃO\nHabilitação para o exercício da atividade profissional: Sim\nTipo: Outros\nDescrição - Outros: De acordo com o previsto nas Peças do Procedimento\nDescrição: De acordo com o previsto nas Peças do Procedimento\n\n13 - CONDIÇÕES DE APRESENTAÇÃO\nPlataforma eletrónica utilizada pela entidade adjudicante: VORTAL\nURL para Apresentação: https://community.vortal.biz/public/\nAdmissibilidade da apresentação de propostas variantes: Não autorizado\nPrazo para apresentação das propostas: 21-10-2025 17:00\nPrazo durante o qual os concorrentes são obrigados a manter as respetivas propostas: 120 dias a contar do termo do prazo para a apresentação das propostas\nApresentação de Catálogo Eletrónico: Não autorizado\nIndicação de Subcontratação na Proposta: Inexistência de indicação de subcontratação\n\n14 - PRESTAÇÃO DE CAUÇÃO\nPrestação de caução: Não\n\n15 - FORNECIMENTO DAS PEÇAS DO CONCURSO, APRESENTAÇÃO DE PEDIDOS DE PARTICIPAÇÃO E APRESENTAÇÃO DAS PROPOSTAS\nLink para acesso às peças do concurso (URL): https://community.vortal.biz/Public/public-tender-documents/ZE9FNTcrcG9neWQyenorZjA4aVBNWmZLV2RkeHZCMnlWQ05VRG5nU1NWVFJCSnptMXk2WFBRRHdpbTMvVXdUbXk3TDdITmIybG1tenRIUlM2eTM1QkE9PXlMc0p5\n\n20 - OUTROS REQUISITOS\nInformação sobre contratos reservados. Aplica-se a contratos reservados (54º-A)? Não\n\n21 - CRITÉRIO DE ADJUDICAÇÃO\nMultifator: Não\nMonofator:\nNome: Preço\n\n24 - CONDIÇÕES DO CONTRATO\nFaturação Eletrónica: Permitido\nObrigação de Subcontratação:\nCódigo da Obrigação de Subcontratação: Não é aplicável nenhuma obrigação de subcontratação.\n\n25 - COMPRA PÚBLICA ESTRATÉGICA\nCompra Pública Estratégica: Inexistência de contratação pública estratégica\n\n26 - INFORMAÇÕES ADICIONAIS\nContrato adequado para PME: Sim\nCobertura ACP (Acordo dos Contratos Públicos da Organização Mundial do Comércio): Não\n\n27 - IDENTIFICAÇÃO E CONTACTOS DO ÓRGÃO DE RECURSOS ADMINISTRATIVOS\nDesignação: Câmara Municipal de Sintra\nEndereço: Largo Dr. Virgílio Horta\nCódigo postal: 2714-501\nLocalidade: Sintra\nTelefone: +351 219238500\nFax: +351 219238657\nEndereço eletrónico: geral@cm-sintra.pt\n\n28 - IDENTIFICAÇÃO DO(S) AUTOR(ES) DE ANÚNCIO\nNome: Basílio Adolfo Mendonça Horta da Franca\nCargo: Presidente do Conselho de Administração dos SMAS-Sintra\n419526966",
    "nipc": "680000054",
    "distrito": "Lisboa",
    "concelho": "Sintra",
    "freguesia": "Todas",
    "site": "www.smas-sintra.pt",
    "email": "aprov.stocks@smas-sintra.pt",
    "designacao_contrato": "Concurso Público N.º 38PF/2025 - «Aquisição do Licenciamento do Software SAP S/4HANA Private Cloud Edition e Sucess Factors - Módulos de Recursos Humanos»",
    "descricao": "Aquisição do Licenciamento do Software SAP S/4HANA Private Cloud Edition e Sucess Factors - Módulos de Recursos Humanos",
    "preco_base": "1.409.420,98 EUR",
    "prazo_execucao": "36 MESES",
    "prazo_apresentacao_propostas": "21-10-2025 17:00",
    "fundos_eu": "Não",
    "plataforma_eletronica": "VORTAL",
    "url_procedimento": "https://community.vortal.biz/public/",
    "autor_nome": "Basílio Adolfo Mendonça Horta da Franca",
    "autor_cargo": "Presidente do Conselho de Administração dos SMAS-Sintra"
  },
  {
    "numero_procedimento": "N/A",
    "entidade": "Conselho de Administração",
    "link": "https://diariodarepublica.pt/dr/detalhe/contrato-publico/24584-935742302",
    "detalhes_completos": "1 - IDENTIFICAÇÃO E CONTACTOS DA ENTIDADE ADJUDICANTE\nDesignação da entidade adjudicante: Conselho de Administração\nNIPC: 511228848\nServiço/Órgão/Pessoa de contacto: Conselho de Administração\nEndereço: Avenida Luís Camões nº57\nCódigo postal: 9004-514\nLocalidade: Funchal\nPaís: Portugal\nNUT III: PT300\nDistrito: Região Autónoma da Madeira\nConcelho: Funchal\nFreguesia: Freguesia de São Pedro (Funchal)\nTelefone: 291705610\nFax: 291742545\nEndereço da Entidade (URL): https://www.sesaram.pt/portal/\nEndereço Eletrónico: aprovisionamento@sesaram.pt\neDelivery Gateway (URL): https://www.acingov.pt\nFunção da Organização: Adquirente\nNorma jurídica da Entidade Adjudicante: Organismo de direito público\nÁrea de atividade da Autoridade Adjudicante: Serviços públicos das administrações públicas\n\n2 - JORNAL OFICIAL DA UNIÃO EUROPEIA\nO procedimento a que este anúncio diz respeito também é publicitado no Jornal Oficial da União Europeia? Não\n\n3 - AVISO\nModelo de Anúncio: Concurso público\nData de Envio do Anúncio: 17-09-2025\n\n5 - PROCESSO\nTipo de Procedimento: Concurso público\nPreço base do procedimento: Sim\nValor do preço base do procedimento: 127.570,00 EUR\nProcedimento com lotes? Sim\nNº Máx. de Lotes Autorizado: 16\nNúmero máximo de lotes que podem ser adjudicados a um concorrente: 16\n\n6 - OBJETO DO CONTRATO\nNúmero de referência interna: NCP20250116\nDesignação do contrato: NCP20250116-MATERIAL PARA ELECTROFISIOLOGIA\nDescrição: NCP20250116-MATERIAL PARA ELECTROFISIOLOGIA\nTipo de Contrato Principal: Aquisição de Bens Móveis\nTipo de Contrato: Aquisição de Bens Móveis\nClassificação CPV (Vocabulário Comum para os Contratos Públicos)\nObjeto principal\nVocabulário Principal: 33190000\nPreço base s/IVA: 127.570,00 EUR\nLotes: \nNº: LOT-0001\nDescrição do Lote: INTRODUTOR DE JUGULAR COMPLETO C/MANGA DE REPOSICIONAMENTO 8FR\nPreço base s/IVA: 1.000,00 EUR\nClassificação CPV (Vocabulário Comum para os Contratos Públicos)\nObjeto principal\nVocabulário Principal: 33190000\nNº: LOT-0002\nDescrição do Lote: AGULHA PUNCAO TRANSEPTAL\nPreço base s/IVA: 2.250,00 EUR\nClassificação CPV (Vocabulário Comum para os Contratos Públicos)\nObjeto principal\nVocabulário Principal: 33190000\nNº: LOT-0003\nDescrição do Lote: CATETER DIAGNOSTICO QUADRIPOLAR 6F CURVA FIXA\nPreço base s/IVA: 9.000,00 EUR\nClassificação CPV (Vocabulário Comum para os Contratos Públicos)\nObjeto principal\nVocabulário Principal: 33190000\nNº: LOT-0004\nDescrição do Lote: CABO CONEXAO CATETER DIAG. BI E QUADRICULAR 150CM\nPreço base s/IVA: 2.000,00 EUR\nClassificação CPV (Vocabulário Comum para os Contratos Públicos)\nObjeto principal\nVocabulário Principal: 33190000\nNº: LOT-0005\nDescrição do Lote: CABO CONEXAO CATETER DIAGNOSTICO 10 PIN\nPreço base s/IVA: 1.600,00 EUR\nClassificação CPV (Vocabulário Comum para os Contratos Públicos)\nObjeto principal\nVocabulário Principal: 33190000\nNº: LOT-0006\nDescrição do Lote: CABO CONEXAO CATETER ABLACAO 250CM\nPreço base s/IVA: 2.400,00 EUR\nClassificação CPV (Vocabulário Comum para os Contratos Públicos)\nObjeto principal\nVocabulário Principal: 33190000\nNº: LOT-0007\nDescrição do Lote: CATETER ABLACAO IRRIGADO 8F BIDIREC.CURVA DF C/PONTA FLEX. E SENSOR MAGNETICO\nPreço base s/IVA: 10.800,00 EUR\nClassificação CPV (Vocabulário Comum para os Contratos Públicos)\nObjeto principal\nVocabulário Principal: 33190000\nNº: LOT-0008\nDescrição do Lote: CATETER ABLACAO IRRIG.8F SENSOR D/FORCA D/CONTACTO E SENSOR MAGNETICO\nPreço base s/IVA: 8.000,00 EUR\nClassificação CPV (Vocabulário Comum para os Contratos Públicos)\nObjeto principal\nVocabulário Principal: 33190000\nNº: LOT-0009\nDescrição do Lote: CONJUNTO DE ELECTRODOS DE SUPERFICIE P/SISTEMA TRIDIMENCIONAL\nPreço base s/IVA: 34.500,00 EUR\nClassificação CPV (Vocabulário Comum para os Contratos Públicos)\nObjeto principal\nVocabulário Principal: 33190000\nNº: LOT-0010\nDescrição do Lote: CATETER DIAGNOSTICO DEFLECTIVEL DECAPOLAR 6F CURVA L\nPreço base s/IVA: 36.000,00 EUR\nClassificação CPV (Vocabulário Comum para os Contratos Públicos)\nObjeto principal\nVocabulário Principal: 33190000\nNº: LOT-0011\nDescrição do Lote: CATETER DE ABLACAO NAO IRRIGADO 4MM\nPreço base s/IVA: 9.500,00 EUR\nClassificação CPV (Vocabulário Comum para os Contratos Públicos)\nObjeto principal\nVocabulário Principal: 33190000\nNº: LOT-0012\nDescrição do Lote: SISTEMA DE IRRIGACAO\nPreço base s/IVA: 400,00 EUR\nClassificação CPV (Vocabulário Comum para os Contratos Públicos)\nObjeto principal\nVocabulário Principal: 33190000\nNº: LOT-0013\nDescrição do Lote: ELECTRODO DISPERSIVO DE RADIOFREQUENCIA\nPreço base s/IVA: 320,00 EUR\nClassificação CPV (Vocabulário Comum para os Contratos Públicos)\nObjeto principal\nVocabulário Principal: 33190000\nNº: LOT-0014\nDescrição do Lote: CABO PARA CATETER DE MAPEAMENTO DE ALTA DENSIDADE\nPreço base s/IVA: 600,00 EUR\nClassificação CPV (Vocabulário Comum para os Contratos Públicos)\nObjeto principal\nVocabulário Principal: 33190000\nNº: LOT-0015\nDescrição do Lote: CATETER CONEXAO DE ABLACAO 4 PINS 150CM\nPreço base s/IVA: 400,00 EUR\nClassificação CPV (Vocabulário Comum para os Contratos Públicos)\nObjeto principal\nVocabulário Principal: 33190000\nNº: LOT-0016\nDescrição do Lote: CATETER DE MAPEAMENTO DE ALTA DENSIDADE\nPreço base s/IVA: 8.800,00 EUR\nClassificação CPV (Vocabulário Comum para os Contratos Públicos)\nObjeto principal\nVocabulário Principal: 33190000\n\n7 - INDICAÇÕES ADICIONAIS\nO contrato envolve aquisição conjunta (satisfação de várias entidades)? Não\nO contrato é adjudicado por uma central de compras? Não\n\n8 - TÉCNICAS\nO concurso destina-se à celebração de um acordo-quadro? Inexistência de acordo-quadro\nÉ utilizado um leilão eletrónico? Não\nÉ adotada uma fase de negociação? Não\nSistema de Aquisição Dinâmico: Inexistência de sistema de aquisição dinâmico\n\n9 - LOCAL DA EXECUÇÃO DO CONTRATO\nLOCAL DA EXECUÇÃO DO CONTRATO (PROCEDIMENTO)\nPaís: Portugal\nNUT III: PT300\nLocalidade: Freguesia de São Pedro (Funchal)\nDistrito: Região Autónoma da Madeira\nConcelho: Funchal\nFreguesia: Freguesia de São Pedro (Funchal)\nLOCAL DA EXECUÇÃO DO CONTRATO (LOTE)\nIdentificador do Lote: LOT-0001; LOT-0002; LOT-0003; LOT-0004; LOT-0005; LOT-0006; LOT-0007; LOT-0008; LOT-0009; LOT-0010; LOT-0011; LOT-0012; LOT-0013; LOT-0014; LOT-0015; LOT-0016\nPaís: Portugal\nNUT III: PT300\nLocalidade: Funchal\nDistrito: Região Autónoma da Madeira\nConcelho: Funchal\nFreguesia: Freguesia de São Pedro (Funchal)\n\n10 - PRAZO DE EXECUÇÃO DO CONTRATO\nIdentificador do Lote: LOT-0001; LOT-0002; LOT-0003; LOT-0004; LOT-0005; LOT-0006; LOT-0007; LOT-0008; LOT-0009; LOT-0010; LOT-0011; LOT-0012; LOT-0013; LOT-0014; LOT-0015; LOT-0016\nPrazo de execução do contrato: 3 MESES\nPrevisão de renovações: Não\n\n11 - FUNDOS EU\nIdentificador do Lote: LOT-0001; LOT-0002; LOT-0003; LOT-0004; LOT-0005; LOT-0006; LOT-0007; LOT-0008; LOT-0009; LOT-0010; LOT-0011; LOT-0012; LOT-0013; LOT-0014; LOT-0015; LOT-0016\nTêm fundos EU? Não\n\n12 - DOCUMENTOS DE HABILITAÇÃO\nHabilitação para o exercício da atividade profissional: Não\n\n13 - CONDIÇÕES DE APRESENTAÇÃO\nPlataforma eletrónica utilizada pela entidade adjudicante: ACIN\nURL para Apresentação: https://www.acingov.pt\nAdmissibilidade da apresentação de propostas variantes: Não autorizado\nPrazo para apresentação das propostas: 29-09-2025 17:00\nPrazo durante o qual os concorrentes são obrigados a manter as respetivas propostas: 66 dias a contar do termo do prazo para a apresentação das propostas\nIndicação de Subcontratação na Proposta: Inexistência de indicação de subcontratação\n\n14 - PRESTAÇÃO DE CAUÇÃO\nPrestação de caução: Não\n\n15 - FORNECIMENTO DAS PEÇAS DO CONCURSO, APRESENTAÇÃO DE PEDIDOS DE PARTICIPAÇÃO E APRESENTAÇÃO DAS PROPOSTAS\nLink para acesso às peças do concurso (URL): https://www.acingov.pt/acingovprod/2/zonaPublica/zona_publica_c/donwloadProcedurePiece/OTc4NDc0\n\n20 - OUTROS REQUISITOS\nIdentificador do Lote: LOT-0001; LOT-0002; LOT-0003; LOT-0004; LOT-0005; LOT-0006; LOT-0007; LOT-0008; LOT-0009; LOT-0010; LOT-0011; LOT-0012; LOT-0013; LOT-0014; LOT-0015; LOT-0016\nInformação sobre contratos reservados. Aplica-se a contratos reservados (54º-A)? Não\n\n21 - CRITÉRIO DE ADJUDICAÇÃO\nO Critério de adjudicação é diferenciado por lote? Não\nMultifator: Não\nMonofator:\nNome: Preço\n\n24 - CONDIÇÕES DO CONTRATO\nIdentificador do Lote: LOT-0001; LOT-0002; LOT-0003; LOT-0004; LOT-0005; LOT-0006; LOT-0007; LOT-0008; LOT-0009; LOT-0010; LOT-0011; LOT-0012; LOT-0013; LOT-0014; LOT-0015; LOT-0016\nFaturação Eletrónica: Permitido\nObrigação de Subcontratação:\nCódigo da Obrigação de Subcontratação: Não é aplicável nenhuma obrigação de subcontratação.\n\n25 - COMPRA PÚBLICA ESTRATÉGICA\nCompra Pública Estratégica: Inexistência de contratação pública estratégica\n\n26 - INFORMAÇÕES ADICIONAIS\nIdentificador do Lote: LOT-0001; LOT-0002; LOT-0003; LOT-0004; LOT-0005; LOT-0006; LOT-0007; LOT-0008; LOT-0009; LOT-0010; LOT-0011; LOT-0012; LOT-0013; LOT-0014; LOT-0015; LOT-0016\nContrato adequado para PME: Não\nCobertura ACP (Acordo dos Contratos Públicos da Organização Mundial do Comércio): Não\n\n27 - IDENTIFICAÇÃO E CONTACTOS DO ÓRGÃO DE RECURSOS ADMINISTRATIVOS\nDesignação: Conselho de Administração\nEndereço: Avenida Luís Camões nº57\nCódigo postal: 9004-514\nLocalidade: Funchal\nTelefone: 291705610\nFax: \nEndereço eletrónico: aprovisionamento@sesaram.pt\n\n28 - IDENTIFICAÇÃO DO(S) AUTOR(ES) DE ANÚNCIO\nNome: Patrícia José Fernandes Aveiro\nCargo: Assistente Operacional\n419543116",
    "nipc": "511228848",
    "distrito": "Região Autónoma da Madeira",
    "concelho": "Funchal",
    "freguesia": "Freguesia de São Pedro (Funchal)",
    "site": "https://www.sesaram.pt/portal/",
    "email": "aprovisionamento@sesaram.pt",
    "designacao_contrato": "NCP20250116-MATERIAL PARA ELECTROFISIOLOGIA",
    "descricao": "NCP20250116-MATERIAL PARA ELECTROFISIOLOGIA",
    "preco_base": "127.570,00 EUR",
    "prazo_execucao": "3 MESES",
    "prazo_apresentacao_propostas": "29-09-2025 17:00",
    "fundos_eu": "Não",
    "plataforma_eletronica": "ACIN",
    "url_procedimento": "https://www.acingov.pt",
    "autor_nome": "Patrícia José Fernandes Aveiro",
    "autor_cargo": "Assistente Operacional"
  },
  {
    "numero_procedimento": "N/A",
    "entidade": "APPACDM de Lisboa - Associação Portuguesa de Pais e Amigos do Cidadão Deficiente Mental",
    "link": "https://diariodarepublica.pt/dr/detalhe/contrato-publico/24585-935742303",
    "detalhes_completos": "1 - IDENTIFICAÇÃO E CONTACTOS DA ENTIDADE ADJUDICANTE\nDesignação da entidade adjudicante: APPACDM de Lisboa - Associação Portuguesa de Pais e Amigos do Cidadão Deficiente Mental\nNIPC: 504646788\nServiço/Órgão/Pessoa de contacto: Direção\nEndereço: Rua Adolfo Coelho, n.º 9 A\nCódigo postal: 1900-801\nLocalidade: Lisboa\nPaís: Portugal\nNUT III: PT170\nDistrito: Lisboa\nConcelho: Lisboa\nFreguesia: Freguesia de Penha de França\nTelefone: 217928720\nFax: 000000000\nEndereço da Entidade (URL): https://appacdm-lisboa.pt/\nEndereço Eletrónico: patrimonio@appacdm-lisboa.pt\neDelivery Gateway (URL): https://www.acingov.pt\nFunção da Organização: Adquirente\nNorma jurídica da Entidade Adjudicante: Organismo de direito público\nÁrea de atividade da Autoridade Adjudicante: Serviços públicos das administrações públicas\n\n2 - JORNAL OFICIAL DA UNIÃO EUROPEIA\nO procedimento a que este anúncio diz respeito também é publicitado no Jornal Oficial da União Europeia? Não\n\n3 - AVISO\nModelo de Anúncio: Concurso público\nData de Envio do Anúncio: 17-09-2025\n\n5 - PROCESSO\nTipo de Procedimento: Concurso público\nPreço base do procedimento: Sim\nValor do preço base do procedimento: 76.488,46 EUR\nProcedimento com lotes? Não\n\n6 - OBJETO DO CONTRATO\nNúmero de referência interna: CP 05/2025\nDesignação do contrato: Fornecimento contínuo de consumíveis e utensílios de higiene e limpeza\nDescrição: Fornecimento contínuo de consumíveis e utensílios de higiene e limpeza\nTipo de Contrato Principal: Aquisição de Bens Móveis\nTipo de Contrato: Aquisição de Bens Móveis\nClassificação CPV (Vocabulário Comum para os Contratos Públicos)\nObjeto principal\nVocabulário Principal: 39800000\nPreço base s/IVA: 76.488,46 EUR\n\n7 - INDICAÇÕES ADICIONAIS\nO contrato envolve aquisição conjunta (satisfação de várias entidades)? Não\nO contrato é adjudicado por uma central de compras? Não\n\n8 - TÉCNICAS\nO concurso destina-se à celebração de um acordo-quadro? Inexistência de acordo-quadro\nÉ utilizado um leilão eletrónico? Não\nÉ adotada uma fase de negociação? Não\nSistema de Aquisição Dinâmico: Inexistência de sistema de aquisição dinâmico\n\n9 - LOCAL DA EXECUÇÃO DO CONTRATO\nLOCAL DA EXECUÇÃO DO CONTRATO (PROCEDIMENTO)\nPaís: Portugal\nNUT III: PT170\nLocalidade: Freguesia de Penha de França\nDistrito: Lisboa\nConcelho: Lisboa\nFreguesia: Freguesia de Penha de França\nPaís: Portugal\nNUT III: PT170\nLocalidade: Freguesia de Benfica\nDistrito: Lisboa\nConcelho: Lisboa\nFreguesia: Freguesia de Benfica\nPaís: Portugal\nNUT III: PT170\nLocalidade: União das Freguesias de Cascais e Estoril\nDistrito: Lisboa\nConcelho: Cascais\nFreguesia: União das Freguesias de Cascais e Estoril\nPaís: Portugal\nNUT III: PT170\nLocalidade: Freguesia de Ajuda\nDistrito: Lisboa\nConcelho: Lisboa\nFreguesia: Freguesia de Ajuda\nPaís: Portugal\nNUT III: PT170\nLocalidade: Freguesia de Alvalade - Lisboa\nDistrito: Lisboa\nConcelho: Lisboa\nFreguesia: Freguesia de Alvalade - Lisboa\nPaís: Portugal\nNUT III: PT170\nLocalidade: União das Freguesias de Caparica e Trafaria\nDistrito: Setúbal\nConcelho: Almada\nFreguesia: União das Freguesias de Caparica e Trafaria\n\n10 - PRAZO DE EXECUÇÃO DO CONTRATO\nPrazo de execução do contrato: 12 MESES\nPrevisão de renovações: Sim\nIndicar número máximo de renovações: 1\nPrazo de renovações diferente do prazo inicial: Não\n\n11 - FUNDOS EU\nTêm fundos EU? Não\n\n12 - DOCUMENTOS DE HABILITAÇÃO\nHabilitação para o exercício da atividade profissional: Não\n\n13 - CONDIÇÕES DE APRESENTAÇÃO\nPlataforma eletrónica utilizada pela entidade adjudicante: ACIN\nURL para Apresentação: https://www.acingov.pt\nAdmissibilidade da apresentação de propostas variantes: Não autorizado\nPrazo para apresentação das propostas: 26-09-2025 17:00\nPrazo durante o qual os concorrentes são obrigados a manter as respetivas propostas: 66 dias a contar do termo do prazo para a apresentação das propostas\nIndicação de Subcontratação na Proposta: Inexistência de indicação de subcontratação\n\n14 - PRESTAÇÃO DE CAUÇÃO\nPrestação de caução: Não\n\n15 - FORNECIMENTO DAS PEÇAS DO CONCURSO, APRESENTAÇÃO DE PEDIDOS DE PARTICIPAÇÃO E APRESENTAÇÃO DAS PROPOSTAS\nLink para acesso às peças do concurso (URL): https://www.acingov.pt/acingovprod/2/zonaPublica/zona_publica_c/donwloadProcedurePiece/OTc4ODE4\n\n20 - OUTROS REQUISITOS\nInformação sobre contratos reservados. Aplica-se a contratos reservados (54º-A)? Não\n\n21 - CRITÉRIO DE ADJUDICAÇÃO\nMultifator: Não\nMonofator:\nNome: Preço\n\n24 - CONDIÇÕES DO CONTRATO\nFaturação Eletrónica: Permitido\nObrigação de Subcontratação:\nCódigo da Obrigação de Subcontratação: Não é aplicável nenhuma obrigação de subcontratação.\n\n25 - COMPRA PÚBLICA ESTRATÉGICA\nCompra Pública Estratégica: Inexistência de contratação pública estratégica\n\n26 - INFORMAÇÕES ADICIONAIS\nContrato adequado para PME: Sim\nCobertura ACP (Acordo dos Contratos Públicos da Organização Mundial do Comércio): Não\n\n27 - IDENTIFICAÇÃO E CONTACTOS DO ÓRGÃO DE RECURSOS ADMINISTRATIVOS\nDesignação: Direção\nEndereço: Rua Adolfo Coelho, n.º 9 A\nCódigo postal: 1900-801\nLocalidade: Lisboa\nTelefone: 217928720\nFax: 000000000\nEndereço eletrónico: patrimonio@appacdm-lisboa.pt\nPrazo de interposição do recurso: 10 dias\n\n28 - IDENTIFICAÇÃO DO(S) AUTOR(ES) DE ANÚNCIO\nNome: Anabela Carrilho Leitão Marques\nCargo: Tesoureira\n419547134",
    "nipc": "504646788",
    "distrito": "Lisboa",
    "concelho": "Lisboa",
    "freguesia": "Freguesia de Penha de França",
    "site": "https://appacdm-lisboa.pt/",
    "email": "patrimonio@appacdm-lisboa.pt",
    "designacao_contrato": "Fornecimento contínuo de consumíveis e utensílios de higiene e limpeza",
    "descricao": "Fornecimento contínuo de consumíveis e utensílios de higiene e limpeza",
    "preco_base": "76.488,46 EUR",
    "prazo_execucao": "12 MESES",
    "prazo_apresentacao_propostas": "26-09-2025 17:00",
    "fundos_eu": "Não",
    "plataforma_eletronica": "ACIN",
    "url_procedimento": "https://www.acingov.pt",
    "autor_nome": "Anabela Carrilho Leitão Marques",
    "autor_cargo": "Tesoureira"
  },
  {
    "numero_procedimento": "N/A",
    "entidade": "Município de Vale de Cambra",
    "link": "https://diariodarepublica.pt/dr/detalhe/contrato-publico/24587-935742304",
    "detalhes_completos": "1 - IDENTIFICAÇÃO E CONTACTOS DA ENTIDADE ADJUDICANTE\nDesignação da entidade adjudicante: Município de Vale de Cambra\nNIPC: 506735524\nEndereço: Av. Camilo Tavares de Matos, n.º 19\nCódigo postal: 3730-901\nLocalidade: Vale de Cambra\nPaís: Portugal\nNUT III: PT11A\nDistrito: Aveiro\nConcelho: Vale de Cambra\nFreguesia: Todas\nTelefone: 256420510\nFax: 256420519\nEndereço da Entidade (URL): www.cm-valedecambra.pt\nEndereço Eletrónico: vortal@cm-valedecambra.pt\neDelivery Gateway (URL): https://community.vortal.biz/public/\nFunção da Organização: Adquirente\nNorma jurídica da Entidade Adjudicante: Autoridade local\nÁrea de atividade da Autoridade Adjudicante: Serviços públicos das administrações públicas\n\n2 - JORNAL OFICIAL DA UNIÃO EUROPEIA\nO procedimento a que este anúncio diz respeito também é publicitado no Jornal Oficial da União Europeia? Não\n\n3 - AVISO\nModelo de Anúncio: Concurso público\nData de Envio do Anúncio: 17-09-2025\n\n5 - PROCESSO\nTipo de Procedimento: Concurso público\nPreço base do procedimento: Sim\nValor do preço base do procedimento: 257.235,50 EUR\nProcedimento com lotes? Não\n\n6 - OBJETO DO CONTRATO\nNúmero de referência interna: OE-CP Nº 16/2025 REQUAL CENTRO DESPORT FORM DAIRAS\nDesignação do contrato: OE-CP Nº 16/2025 REQUALIFICAÇÃO DO CENTRO DESPORTIVO DE FORMAÇÃO DAS DAIRAS\nDescrição: OE-CP Nº 16/2025 REQUALIFICAÇÃO DO CENTRO DESPORTIVO DE FORMAÇÃO DAS DAIRAS\nTipo de Contrato Principal: Empreitada de Obras Públicas\nTipo de Contrato: Empreitada de Obras Públicas\nClassificação CPV (Vocabulário Comum para os Contratos Públicos)\nObjeto principal\nVocabulário Principal: 45236119\nPreço base s/IVA: 257.235,50 EUR\n\n7 - INDICAÇÕES ADICIONAIS\nO contrato envolve aquisição conjunta (satisfação de várias entidades)? Não\nO contrato é adjudicado por uma central de compras? Não\n\n8 - TÉCNICAS\nO concurso destina-se à celebração de um acordo-quadro? Inexistência de acordo-quadro\nÉ utilizado um leilão eletrónico? Não\nÉ adotada uma fase de negociação? Não\nSistema de Aquisição Dinâmico: Inexistência de sistema de aquisição dinâmico\n\n9 - LOCAL DA EXECUÇÃO DO CONTRATO\nLOCAL DA EXECUÇÃO DO CONTRATO (PROCEDIMENTO)\nPaís: Portugal\nNUT III: PT11A\nLocalidade: Aveiro\nDistrito: Aveiro\nConcelho: Vale de Cambra\nFreguesia: União das Freguesias de Vila Chã, Codal e Vila Cova de Perrinho\n\n10 - PRAZO DE EXECUÇÃO DO CONTRATO\nPrazo de execução do contrato: 60 DIAS\nPrevisão de renovações: Não\n\n11 - FUNDOS EU\nTêm fundos EU? Não\n\n12 - DOCUMENTOS DE HABILITAÇÃO\nHabilitação para o exercício da atividade profissional: Sim\nTipo: Alvará\nDescrição: a) Declaração emitida conforme modelo constante do anexo II do Código dos contratos Públicos;\nb) Documento comprovativo de não se encontrar nas situações previstas nas alíneas b), d), e) e i) do artigo 55º do CCP;\nc) Documentos previstos no nº 1 do artigo 81 do CCP;\nd) Alvará emitido pelo InCI, contendo as seguintes habilitações adequadas á realização da obra:\nd.1)  2ª Subcategoria da 10ª Categoria da classe correspondente ao valor da proposta.\n\n13 - CONDIÇÕES DE APRESENTAÇÃO\nPlataforma eletrónica utilizada pela entidade adjudicante: VORTAL\nURL para Apresentação: https://community.vortal.biz/public/\nAdmissibilidade da apresentação de propostas variantes: Não autorizado\nPrazo para apresentação das propostas: 18-10-2025 17:00\nPrazo durante o qual os concorrentes são obrigados a manter as respetivas propostas: 66 dias a contar do termo do prazo para a apresentação das propostas\nIndicação de Subcontratação na Proposta: Inexistência de indicação de subcontratação\n\n14 - PRESTAÇÃO DE CAUÇÃO\nPrestação de caução: Sim\nPercentagem: 5%\nDescrição da Garantia Exigida: De acordo com o Programa do Procedimento\n\n15 - FORNECIMENTO DAS PEÇAS DO CONCURSO, APRESENTAÇÃO DE PEDIDOS DE PARTICIPAÇÃO E APRESENTAÇÃO DAS PROPOSTAS\nLink para acesso às peças do concurso (URL): https://community.vortal.biz/Public/public-tender-documents/L3FqcEo2K3lnckF1Njl3Vy90N1B0QkNZM2RDMVdYaVVQMFFaYkx2SVZRUE5oK3pPR0tHT0liTmpGdHVKNTMyTHhaVUtGV3dCdHd3LzFTZlJrN0hBRVE9PTJaNVlX\n\n20 - OUTROS REQUISITOS\nInformação sobre contratos reservados. Aplica-se a contratos reservados (54º-A)? Não\n\n21 - CRITÉRIO DE ADJUDICAÇÃO\nMultifator: Não\nMonofator:\nNome: Preço\n\n24 - CONDIÇÕES DO CONTRATO\nFaturação Eletrónica: Permitido\nObrigação de Subcontratação:\nCódigo da Obrigação de Subcontratação: Não é aplicável nenhuma obrigação de subcontratação.\n\n25 - COMPRA PÚBLICA ESTRATÉGICA\nCompra Pública Estratégica: Inexistência de contratação pública estratégica\n\n26 - INFORMAÇÕES ADICIONAIS\nContrato adequado para PME: Sim\nCobertura ACP (Acordo dos Contratos Públicos da Organização Mundial do Comércio): Não\n\n27 - IDENTIFICAÇÃO E CONTACTOS DO ÓRGÃO DE RECURSOS ADMINISTRATIVOS\nDesignação: José Alberto Freitas Soares Pinheiro e Silva\nEndereço: Av. Camilo Tavares de Matos, 19\nCódigo postal: 3730-240\nLocalidade: Vale de Cambra\nTelefone: +351 256420510\nFax: +351 256420519\nEndereço eletrónico: gap@cm-valedecambra.pt\nPrazo de interposição do recurso: 10 dias\n\n28 - IDENTIFICAÇÃO DO(S) AUTOR(ES) DE ANÚNCIO\nNome: José Alberto Freitas Soares Pinheiro e Silva\nCargo: Presidente da Câmara Municipal de Vale de Cambra\n419544259",
    "nipc": "506735524",
    "distrito": "Aveiro",
    "concelho": "Vale de Cambra",
    "freguesia": "Todas",
    "site": "www.cm-valedecambra.pt",
    "email": "vortal@cm-valedecambra.pt",
    "designacao_contrato": "OE-CP Nº 16/2025 REQUALIFICAÇÃO DO CENTRO DESPORTIVO DE FORMAÇÃO DAS DAIRAS",
    "descricao": "OE-CP Nº 16/2025 REQUALIFICAÇÃO DO CENTRO DESPORTIVO DE FORMAÇÃO DAS DAIRAS",
    "preco_base": "257.235,50 EUR",
    "prazo_execucao": "60 DIAS",
    "prazo_apresentacao_propostas": "18-10-2025 17:00",
    "fundos_eu": "Não",
    "plataforma_eletronica": "VORTAL",
    "url_procedimento": "https://community.vortal.biz/public/",
    "autor_nome": "José Alberto Freitas Soares Pinheiro e Silva",
    "autor_cargo": "Presidente da Câmara Municipal de Vale de Cambra"
  },
  {
    "numero_procedimento": "N/A",
    "entidade": "Município de Vila Nova de Foz Côa",
    "link": "https://diariodarepublica.pt/dr/detalhe/contrato-publico/24588-935742305",
    "detalhes_completos": "1 - IDENTIFICAÇÃO E CONTACTOS DA ENTIDADE ADJUDICANTE\nDesignação da entidade adjudicante: Município de Vila Nova de Foz Côa\nNIPC: 506829197\nServiço/Órgão/Pessoa de contacto: Divisão de Obras Municipais e Infraestruturas\nEndereço: PRAÇA DO MUNICÍPIO\nCódigo postal: 5150-642\nLocalidade: VILA NOVA DE FOZ CÔA\nPaís: Portugal\nNUT III: PT11D\nDistrito: Guarda\nConcelho: Vila Nova de Foz Coa\nFreguesia: Freguesia de Vila Nova de Foz Côa\nTelefone: 279760400\nFax: 279760438\nEndereço da Entidade (URL): http://cm-fozcoa.pt/\nEndereço Eletrónico: correio@cm-fozcoa.pt\neDelivery Gateway (URL): https://www.acingov.pt\nFunção da Organização: Adquirente\nNorma jurídica da Entidade Adjudicante: Organismo de direito público\nÁrea de atividade da Autoridade Adjudicante: Serviços públicos das administrações públicas\n\n2 - JORNAL OFICIAL DA UNIÃO EUROPEIA\nO procedimento a que este anúncio diz respeito também é publicitado no Jornal Oficial da União Europeia? Não\n\n3 - AVISO\nModelo de Anúncio: Concurso público\nData de Envio do Anúncio: 17-09-2025\n\n5 - PROCESSO\nTipo de Procedimento: Concurso público\nPreço base do procedimento: Sim\nValor do preço base do procedimento: 66.603,27 EUR\nProcedimento com lotes? Sim\nNº Máx. de Lotes Autorizado: 2\nNúmero máximo de lotes que podem ser adjudicados a um concorrente: 2\n\n6 - OBJETO DO CONTRATO\nNúmero de referência interna: 2/2025/DOUMA\nDesignação do contrato: 2/2025/DOUMA - Aquisição de três viaturas ligeiras de mercadorias\nDescrição: Aquisição de três viaturas ligeiras de mercadorias\nTipo de Contrato Principal: Aquisição de Bens Móveis\nTipo de Contrato: Aquisição de Bens Móveis\nClassificação CPV (Vocabulário Comum para os Contratos Públicos)\nObjeto principal\nVocabulário Principal: 34131000\nPreço base s/IVA: 30.261,79 EUR\nObjeto Complementar\nVocabulário Principal: 34136100\nPreço base s/IVA: 36.341,48 EUR\nLotes: \nNº: LOT-0001\nDescrição do Lote: Um veiculo ligeiro de mercadorias de caixa aberta\nPreço base s/IVA: 30.261,79 EUR\nClassificação CPV (Vocabulário Comum para os Contratos Públicos)\nObjeto principal\nVocabulário Principal: 34131000\nNº: LOT-0002\nDescrição do Lote: Dois furgões com volume de carga individual de 4,30m3\nPreço base s/IVA: 36.341,48 EUR\nClassificação CPV (Vocabulário Comum para os Contratos Públicos)\nObjeto principal\nVocabulário Principal: 34136100\n\n7 - INDICAÇÕES ADICIONAIS\nO contrato envolve aquisição conjunta (satisfação de várias entidades)? Não\nO contrato é adjudicado por uma central de compras? Não\n\n8 - TÉCNICAS\nO concurso destina-se à celebração de um acordo-quadro? Inexistência de acordo-quadro\nÉ utilizado um leilão eletrónico? Não\nÉ adotada uma fase de negociação? Não\nSistema de Aquisição Dinâmico: Inexistência de sistema de aquisição dinâmico\n\n9 - LOCAL DA EXECUÇÃO DO CONTRATO\nLOCAL DA EXECUÇÃO DO CONTRATO (PROCEDIMENTO)\nPaís: Portugal\nNUT III: PT11D\nLocalidade: Freguesia de Vila Nova de Foz Côa\nDistrito: Guarda\nConcelho: Vila Nova de Foz Coa\nFreguesia: Freguesia de Vila Nova de Foz Côa\nLOCAL DA EXECUÇÃO DO CONTRATO (LOTE)\nIdentificador do Lote: LOT-0001; LOT-0002\nPaís: Portugal\nNUT III: PT11D\nLocalidade: Freguesia de Vila Nova de Foz Côa\nDistrito: Guarda\nConcelho: Vila Nova de Foz Coa\nFreguesia: Freguesia de Vila Nova de Foz Côa\n\n10 - PRAZO DE EXECUÇÃO DO CONTRATO\nIdentificador do Lote: LOT-0001\nPrazo de execução do contrato: 75 DIAS\nPrevisão de renovações: Não\nIdentificador do Lote: LOT-0002\nPrazo de execução do contrato: 30 DIAS\nPrevisão de renovações: Não\n\n11 - FUNDOS EU\nIdentificador do Lote: LOT-0001; LOT-0002\nTêm fundos EU? Não\n\n12 - DOCUMENTOS DE HABILITAÇÃO\nHabilitação para o exercício da atividade profissional: Não\n\n13 - CONDIÇÕES DE APRESENTAÇÃO\nPlataforma eletrónica utilizada pela entidade adjudicante: ACIN\nURL para Apresentação: https://www.acingov.pt\nAdmissibilidade da apresentação de propostas variantes: Não autorizado\nPrazo para apresentação das propostas: 02-10-2025 23:59\nPrazo durante o qual os concorrentes são obrigados a manter as respetivas propostas: 66 dias a contar do termo do prazo para a apresentação das propostas\nIndicação de Subcontratação na Proposta: Inexistência de indicação de subcontratação\n\n14 - PRESTAÇÃO DE CAUÇÃO\nPrestação de caução: Não\n\n15 - FORNECIMENTO DAS PEÇAS DO CONCURSO, APRESENTAÇÃO DE PEDIDOS DE PARTICIPAÇÃO E APRESENTAÇÃO DAS PROPOSTAS\nLink para acesso às peças do concurso (URL): https://www.acingov.pt/acingovprod/2/zonaPublica/zona_publica_c/donwloadProcedurePiece/OTc4NTAw\n\n20 - OUTROS REQUISITOS\nIdentificador do Lote: LOT-0001; LOT-0002\nInformação sobre contratos reservados. Aplica-se a contratos reservados (54º-A)? Não\n\n21 - CRITÉRIO DE ADJUDICAÇÃO\nO Critério de adjudicação é diferenciado por lote? Não\nMultifator: Não\nMonofator:\nNome: Preço\n\n24 - CONDIÇÕES DO CONTRATO\nIdentificador do Lote: LOT-0001; LOT-0002\nFaturação Eletrónica: Permitido\nObrigação de Subcontratação:\nCódigo da Obrigação de Subcontratação: Não é aplicável nenhuma obrigação de subcontratação.\n\n25 - COMPRA PÚBLICA ESTRATÉGICA\nCompra Pública Estratégica: Inexistência de contratação pública estratégica\n\n26 - INFORMAÇÕES ADICIONAIS\nIdentificador do Lote: LOT-0001; LOT-0002\nContrato adequado para PME: Sim\nCobertura ACP (Acordo dos Contratos Públicos da Organização Mundial do Comércio): Não\n\n27 - IDENTIFICAÇÃO E CONTACTOS DO ÓRGÃO DE RECURSOS ADMINISTRATIVOS\nDesignação: Presidente da Câmara Municipal\nEndereço: Câmara Municipal - Praça do Munícipio\nCódigo postal: 5150-642\nLocalidade: VILA NOVA DE FOZ CÔA\nTelefone: 279760400\nFax: \nEndereço eletrónico: correio@cm-fozcoa.pt\n\n28 - IDENTIFICAÇÃO DO(S) AUTOR(ES) DE ANÚNCIO\nNome: Pedro Miguel de Carvalho Duarte\nCargo: Presidente da Câmara Municipal\n419543708",
    "nipc": "506829197",
    "distrito": "Guarda",
    "concelho": "Vila Nova de Foz Coa",
    "freguesia": "Freguesia de Vila Nova de Foz Côa",
    "site": "http://cm-fozcoa.pt/",
    "email": "correio@cm-fozcoa.pt",
    "designacao_contrato": "2/2025/DOUMA - Aquisição de três viaturas ligeiras de mercadorias",
    "descricao": "Aquisição de três viaturas ligeiras de mercadorias",
    "preco_base": "30.261,79 EUR",
    "prazo_execucao": "75 DIAS",
    "prazo_apresentacao_propostas": "02-10-2025 23:59",
    "fundos_eu": "Não",
    "plataforma_eletronica": "ACIN",
    "url_procedimento": "https://www.acingov.pt",
    "autor_nome": "Pedro Miguel de Carvalho Duarte",
    "autor_cargo": "Presidente da Câmara Municipal"
  },
  {
    "numero_procedimento": "N/A",
    "entidade": "MUNICÍPIO DE LOULÉ",
    "link": "https://diariodarepublica.pt/dr/detalhe/contrato-publico/24589-935742306",
    "detalhes_completos": "1 - IDENTIFICAÇÃO E CONTACTOS DA ENTIDADE ADJUDICANTE\nDesignação da entidade adjudicante: MUNICÍPIO DE LOULÉ\nNIPC: 502098139\nEndereço: Praça da República\nCódigo postal: 8104-001\nLocalidade: Faro\nPaís: Portugal\nNUT III: PT150\nDistrito: Faro\nConcelho: Loulé\nFreguesia: Todas\nTelefone: 289400834\nFax: 289415557\nEndereço da Entidade (URL): www.cm-loule.pt\nEndereço Eletrónico: aprovisionamento@cm-loule.pt\neDelivery Gateway (URL): https://community.vortal.biz/public/\nFunção da Organização: Adquirente\nNorma jurídica da Entidade Adjudicante: Organismo de direito público\nÁrea de atividade da Autoridade Adjudicante: Serviços públicos das administrações públicas\n\n2 - JORNAL OFICIAL DA UNIÃO EUROPEIA\nO procedimento a que este anúncio diz respeito também é publicitado no Jornal Oficial da União Europeia? Sim\n\n3 - AVISO\nModelo de Anúncio: Concurso limitado por prévia qualificação\nData de Envio do Anúncio: 15-09-2025\n\n5 - PROCESSO\nTipo de Procedimento: Concurso limitado por prévia qualificação\nPreço base do procedimento: Sim\nValor do preço base do procedimento: 24.000.000,00 EUR\nProcedimento com lotes? Não\n\n6 - OBJETO DO CONTRATO\nNúmero de referência interna: OM-060-2025-DGPME\nDesignação do contrato: CONSTRUÇÃO DE EDIFÍCIO MUNICIPAL EM LOULÉ\nDescrição: CONSTRUÇÃO DE EDIFÍCIO MUNICIPAL EM LOULÉ\nOpções: Não\nTipo de Contrato Principal: Empreitada de Obras Públicas\nTipo de Contrato: Empreitada de Obras Públicas\nClassificação CPV (Vocabulário Comum para os Contratos Públicos)\nObjeto principal\nVocabulário Principal: 45214600\nPreço base s/IVA: 24.000.000,00 EUR\n\n7 - INDICAÇÕES ADICIONAIS\nO contrato envolve aquisição conjunta (satisfação de várias entidades)? Não\nO contrato é adjudicado por uma central de compras? Não\n\n8 - TÉCNICAS\nO concurso destina-se à celebração de um acordo-quadro? Inexistência de acordo-quadro\nÉ utilizado um leilão eletrónico? Não\nSistema de Aquisição Dinâmico: Inexistência de sistema de aquisição dinâmico\n\n9 - LOCAL DA EXECUÇÃO DO CONTRATO\nLOCAL DA EXECUÇÃO DO CONTRATO (PROCEDIMENTO)\nPaís: Portugal\nNUT III: PT150\nLocalidade: Faro\nDistrito: Faro\nConcelho: Loulé\nFreguesia: Todas\n\n10 - PRAZO DE EXECUÇÃO DO CONTRATO\nPrazo de execução do contrato: 1275 DIAS\nPrevisão de renovações: Não\n\n11 - FUNDOS EU\nTêm fundos EU? Não\n\n12 - DOCUMENTOS DE HABILITAÇÃO\nHabilitação para o exercício da atividade profissional: Não\n\n13 - CONDIÇÕES DE APRESENTAÇÃO\nPlataforma eletrónica utilizada pela entidade adjudicante: VORTAL\nURL para Apresentação: https://community.vortal.biz/public/\nAdmissibilidade da apresentação de propostas variantes: Não autorizado\nPrazo para apresentação das candidaturas: 15-11-2025 17:00\nRequisitos mínimos \nRequisitos mínimos de capacidade técnica: Conforme as peças do procedimento\nRequisitos mínimos de capacidade financeira: Conforme as peças do procedimento\nPrazo durante o qual os concorrentes são obrigados a manter as respetivas propostas: 180 dias a contar do termo do prazo para a apresentação das propostas\nApresentação de Catálogo Eletrónico: Não autorizado\nIndicação de Subcontratação na Proposta: Inexistência de indicação de subcontratação\n\n14 - PRESTAÇÃO DE CAUÇÃO\nPrestação de caução: Sim\nPercentagem: 5%\nDescrição da Garantia Exigida: Depósito em dinheiro ou em títulos emitidos ou garantidos pelo Estado, ou mediante garantia bancária ou seguro caução.\n\n15 - FORNECIMENTO DAS PEÇAS DO CONCURSO, APRESENTAÇÃO DE PEDIDOS DE PARTICIPAÇÃO E APRESENTAÇÃO DAS PROPOSTAS\nLink para acesso às peças do concurso (URL): https://community.vortal.biz/Public/public-tender-documents/a3NmRHp4a1lGS1RpM21IWmZMRmRkUnhjYlFSNWtMd3BTWU9Jdm0wb1pnNlNMZmFKL2JBZW4rUlZRaXhZSUk4SW1iQlRleHNLMitxTUxaM3c1NHpBanc9PUYrNG1W\n\n20 - OUTROS REQUISITOS\nInformação sobre contratos reservados. Aplica-se a contratos reservados (54º-A)? Não\n\n21 - CRITÉRIO DE ADJUDICAÇÃO\nMultifator: Sim\nFator: \nNome: Preço\nPonderação: 60%\nSubfatores: Não\nFator: \nNome: Qualidade\nPonderação: 40%\nSubfatores: Não\n\n24 - CONDIÇÕES DO CONTRATO\nFaturação Eletrónica: Permitido\nObrigação de Subcontratação:\nCódigo da Obrigação de Subcontratação: Não é aplicável nenhuma obrigação de subcontratação.\n\n25 - COMPRA PÚBLICA ESTRATÉGICA\nCompra Pública Estratégica: Inexistência de contratação pública estratégica\n\n26 - INFORMAÇÕES ADICIONAIS\nContrato adequado para PME: Sim\nCobertura ACP (Acordo dos Contratos Públicos da Organização Mundial do Comércio): Não\n\n27 - IDENTIFICAÇÃO E CONTACTOS DO ÓRGÃO DE RECURSOS ADMINISTRATIVOS\nDesignação: Munícipio de Loulé\nEndereço: Praça da República\nCódigo postal: 8100-001\nLocalidade: Loulé\nTelefone: +351 289400600\nFax: +351 289415557\nEndereço eletrónico: geral@cm-loule.ot\n\n28 - IDENTIFICAÇÃO DO(S) AUTOR(ES) DE ANÚNCIO\nNome: Vítor Manuel Gonçalves Aleixo\nCargo: Presidente\n419533761",
    "nipc": "502098139",
    "distrito": "Faro",
    "concelho": "Loulé",
    "freguesia": "Todas",
    "site": "www.cm-loule.pt",
    "email": "aprovisionamento@cm-loule.pt",
    "designacao_contrato": "CONSTRUÇÃO DE EDIFÍCIO MUNICIPAL EM LOULÉ",
    "descricao": "CONSTRUÇÃO DE EDIFÍCIO MUNICIPAL EM LOULÉ",
    "preco_base": "24.000.000,00 EUR",
    "prazo_execucao": "1275 DIAS",
    "prazo_apresentacao_propostas": null,
    "fundos_eu": "Não",
    "plataforma_eletronica": "VORTAL",
    "url_procedimento": "https://community.vortal.biz/public/",
    "autor_nome": "Vítor Manuel Gonçalves Aleixo",
    "autor_cargo": "Presidente"
  },
  {
    "numero_procedimento": "N/A",
    "entidade": "MUNICÍPIO DE LOULÉ",
    "link": "https://diariodarepublica.pt/dr/detalhe/contrato-publico/24591-935742307",
    "detalhes_completos": "1 - IDENTIFICAÇÃO E CONTACTOS DA ENTIDADE ADJUDICANTE\nDesignação da entidade adjudicante: MUNICÍPIO DE LOULÉ\nNIPC: 502098139\nEndereço: Praça da República\nCódigo postal: 8104-001\nLocalidade: Faro\nPaís: Portugal\nNUT III: PT150\nDistrito: Faro\nConcelho: Loulé\nFreguesia: Todas\nTelefone: 289400834\nFax: 289415557\nEndereço da Entidade (URL): www.cm-loule.pt\nEndereço Eletrónico: aprovisionamento@cm-loule.pt\neDelivery Gateway (URL): https://community.vortal.biz/public/\nFunção da Organização: Adquirente\nNorma jurídica da Entidade Adjudicante: Organismo de direito público\nÁrea de atividade da Autoridade Adjudicante: Serviços públicos das administrações públicas\n\n2 - JORNAL OFICIAL DA UNIÃO EUROPEIA\nO procedimento a que este anúncio diz respeito também é publicitado no Jornal Oficial da União Europeia? Sim\n\n3 - AVISO\nModelo de Anúncio: Concurso público\nData de Envio do Anúncio: 15-09-2025\n\n5 - PROCESSO\nTipo de Procedimento: Concurso público\nPreço base do procedimento: Sim\nValor do preço base do procedimento: 150.000,00 EUR\nProcedimento com lotes? Não\n\n6 - OBJETO DO CONTRATO\nNúmero de referência interna: FM-2025-403 DACP\nDesignação do contrato: CONTRATAÇÃO DO UPGRADE E RENOVAÇÃO DO LICENCIAMENTO DAS SOLUÇÕES UNIFICADAS DE COMUNICAÇÕES IP PARA OS PAÇOS DO CONCELHO, QUARTEL DOS BOMBEIROS MUNICIPAIS E ESCOLAS DO CONCELHO DE LOULÉ\nDescrição: CONTRATAÇÃO DO UPGRADE E RENOVAÇÃO DO LICENCIAMENTO DAS SOLUÇÕES UNIFICADAS DE COMUNICAÇÕES IP PARA OS PAÇOS DO CONCELHO, QUARTEL DOS BOMBEIROS MUNICIPAIS E ESCOLAS DO CONCELHO DE LOULÉ\nOpções: Não\nTipo de Contrato Principal: Aquisição de Serviços\nTipo de Contrato: Aquisição de Serviços\nClassificação CPV (Vocabulário Comum para os Contratos Públicos)\nObjeto principal\nVocabulário Principal: 72610000\nPreço base s/IVA: 150.000,00 EUR\n\n7 - INDICAÇÕES ADICIONAIS\nO contrato envolve aquisição conjunta (satisfação de várias entidades)? Não\nO contrato é adjudicado por uma central de compras? Não\n\n8 - TÉCNICAS\nO concurso destina-se à celebração de um acordo-quadro? Inexistência de acordo-quadro\nÉ utilizado um leilão eletrónico? Não\nÉ adotada uma fase de negociação? Não\nSistema de Aquisição Dinâmico: Inexistência de sistema de aquisição dinâmico\n\n9 - LOCAL DA EXECUÇÃO DO CONTRATO\nLOCAL DA EXECUÇÃO DO CONTRATO (PROCEDIMENTO)\nPaís: Portugal\nNUT III: PT150\nLocalidade: Loulé\nDistrito: Faro\nConcelho: Loulé\nFreguesia: Todas\n\n10 - PRAZO DE EXECUÇÃO DO CONTRATO\nPrazo de execução do contrato: 36 MESES\nPrevisão de renovações: Não\n\n11 - FUNDOS EU\nTêm fundos EU? Não\n\n12 - DOCUMENTOS DE HABILITAÇÃO\nHabilitação para o exercício da atividade profissional: Não\n\n13 - CONDIÇÕES DE APRESENTAÇÃO\nPlataforma eletrónica utilizada pela entidade adjudicante: VORTAL\nURL para Apresentação: https://community.vortal.biz/public/\nAdmissibilidade da apresentação de propostas variantes: Não autorizado\nPrazo para apresentação das propostas: 20-10-2025 18:00\nPrazo durante o qual os concorrentes são obrigados a manter as respetivas propostas: 90 dias a contar do termo do prazo para a apresentação das propostas\nApresentação de Catálogo Eletrónico: Não autorizado\nIndicação de Subcontratação na Proposta: Inexistência de indicação de subcontratação\n\n14 - PRESTAÇÃO DE CAUÇÃO\nPrestação de caução: Não\n\n15 - FORNECIMENTO DAS PEÇAS DO CONCURSO, APRESENTAÇÃO DE PEDIDOS DE PARTICIPAÇÃO E APRESENTAÇÃO DAS PROPOSTAS\nLink para acesso às peças do concurso (URL): https://community.vortal.biz/Public/public-tender-documents/dmVSSWVzK2FkdHJBKy9ZUXIxRE01MkR4b203QUJmck9iZ1VkbWZ2dXhLSTMxNEM2U0Qrd1M3cGVOMEs2cVBkdjJkNkl4S0Jhbmh2NTMyTTdTbngzK3c9PXNaRFF0\n\n20 - OUTROS REQUISITOS\nInformação sobre contratos reservados. Aplica-se a contratos reservados (54º-A)? Não\n\n21 - CRITÉRIO DE ADJUDICAÇÃO\nMultifator: Não\nMonofator:\nNome: Preço\n\n24 - CONDIÇÕES DO CONTRATO\nFaturação Eletrónica: Permitido\nObrigação de Subcontratação:\nCódigo da Obrigação de Subcontratação: Não é aplicável nenhuma obrigação de subcontratação.\n\n25 - COMPRA PÚBLICA ESTRATÉGICA\nCompra Pública Estratégica: Inexistência de contratação pública estratégica\n\n26 - INFORMAÇÕES ADICIONAIS\nContrato adequado para PME: Sim\nCobertura ACP (Acordo dos Contratos Públicos da Organização Mundial do Comércio): Não\n\n27 - IDENTIFICAÇÃO E CONTACTOS DO ÓRGÃO DE RECURSOS ADMINISTRATIVOS\nDesignação: Câmara Municipal de Loulé\nEndereço: Praça da República\nCódigo postal: 8104-001\nLocalidade: Loulé\nTelefone: +351 289400600\nFax: +351 289415557\nEndereço eletrónico: geral@cm-loule.pt\n\n28 - IDENTIFICAÇÃO DO(S) AUTOR(ES) DE ANÚNCIO\nNome: Vítor Manuel Gonçalves Aleixo\nCargo: Presidente da Câmara\n419534482",
    "nipc": "502098139",
    "distrito": "Faro",
    "concelho": "Loulé",
    "freguesia": "Todas",
    "site": "www.cm-loule.pt",
    "email": "aprovisionamento@cm-loule.pt",
    "designacao_contrato": "CONTRATAÇÃO DO UPGRADE E RENOVAÇÃO DO LICENCIAMENTO DAS SOLUÇÕES UNIFICADAS DE COMUNICAÇÕES IP PARA OS PAÇOS DO CONCELHO, QUARTEL DOS BOMBEIROS MUNICIPAIS E ESCOLAS DO CONCELHO DE LOULÉ",
    "descricao": "CONTRATAÇÃO DO UPGRADE E RENOVAÇÃO DO LICENCIAMENTO DAS SOLUÇÕES UNIFICADAS DE COMUNICAÇÕES IP PARA OS PAÇOS DO CONCELHO, QUARTEL DOS BOMBEIROS MUNICIPAIS E ESCOLAS DO CONCELHO DE LOULÉ",
    "preco_base": "150.000,00 EUR",
    "prazo_execucao": "36 MESES",
    "prazo_apresentacao_propostas": "20-10-2025 18:00",
    "fundos_eu": "Não",
    "plataforma_eletronica": "VORTAL",
    "url_procedimento": "https://community.vortal.biz/public/",
    "autor_nome": "Vítor Manuel Gonçalves Aleixo",
    "autor_cargo": "Presidente da Câmara"
  },
  {
    "numero_procedimento": "N/A",
    "entidade": "Ordem Dos Engenheiros",
    "link": "https://diariodarepublica.pt/dr/detalhe/contrato-publico/24592-935742308",
    "detalhes_completos": "1 - IDENTIFICAÇÃO E CONTACTOS DA ENTIDADE ADJUDICANTE\nDesignação da entidade adjudicante: Ordem Dos Engenheiros\nNIPC: 500839166\nEndereço: Avenida António Augusto de Aguiar,3D\nCódigo postal: 1069-030\nLocalidade: Lisboa\nPaís: Portugal\nNUT III: PT170\nDistrito: Lisboa\nConcelho: Lisboa\nFreguesia: Todas\nTelefone: 213132611\nFax: 213524632\nEndereço da Entidade (URL): www.ordemengenheiros.pt\nEndereço Eletrónico: secretariageral@oep.pt\neDelivery Gateway (URL): https://community.vortal.biz/public/\nFunção da Organização: Adquirente\nNorma jurídica da Entidade Adjudicante: Organismo de direito público\nÁrea de atividade da Autoridade Adjudicante: Serviços públicos das administrações públicas\n\n2 - JORNAL OFICIAL DA UNIÃO EUROPEIA\nO procedimento a que este anúncio diz respeito também é publicitado no Jornal Oficial da União Europeia? Não\n\n3 - AVISO\nModelo de Anúncio: Concurso público\nData de Envio do Anúncio: 17-09-2025\n\n5 - PROCESSO\nTipo de Procedimento: Concurso público\nPreço base do procedimento: Sim\nValor do preço base do procedimento: 209.250,00 EUR\nProcedimento com lotes? Não\n\n6 - OBJETO DO CONTRATO\nNúmero de referência interna: CDN 28/2025 \nDesignação do contrato: Aquisição de Serviços de Limpeza, com fornecimento de consumíveis e equipamentos de limpeza, das instalações das Sedes Nacional e da Região Sul e de dois escritórios\nDescrição: Aquisição de Serviços de Limpeza, com fornecimento de consumíveis e equipamentos de limpeza, das instalações das Sedes Nacional e da Região Sul e de dois escritórios\nTipo de Contrato Principal: Aquisição de Serviços\nTipo de Contrato: Aquisição de Serviços\nClassificação CPV (Vocabulário Comum para os Contratos Públicos)\nObjeto principal\nVocabulário Principal: 90919200\nPreço base s/IVA: 209.250,00 EUR\n\n7 - INDICAÇÕES ADICIONAIS\nO contrato envolve aquisição conjunta (satisfação de várias entidades)? Não\nO contrato é adjudicado por uma central de compras? Não\n\n8 - TÉCNICAS\nO concurso destina-se à celebração de um acordo-quadro? Inexistência de acordo-quadro\nÉ utilizado um leilão eletrónico? Não\nÉ adotada uma fase de negociação? Não\nSistema de Aquisição Dinâmico: Inexistência de sistema de aquisição dinâmico\n\n9 - LOCAL DA EXECUÇÃO DO CONTRATO\nLOCAL DA EXECUÇÃO DO CONTRATO (PROCEDIMENTO)\nPaís: Portugal\nNUT III: PT170\nLocalidade: Lisboa\nDistrito: Lisboa\nConcelho: Lisboa\nFreguesia: Todas\n\n10 - PRAZO DE EXECUÇÃO DO CONTRATO\nPrazo de execução do contrato: 1 ANOS\nPrevisão de renovações: Sim\nIndicar número máximo de renovações: 2\nPrazo de renovações diferente do prazo inicial: Não\n\n11 - FUNDOS EU\nTêm fundos EU? Não\n\n12 - DOCUMENTOS DE HABILITAÇÃO\nHabilitação para o exercício da atividade profissional: Não\n\n13 - CONDIÇÕES DE APRESENTAÇÃO\nPlataforma eletrónica utilizada pela entidade adjudicante: VORTAL\nURL para Apresentação: https://community.vortal.biz/public/\nAdmissibilidade da apresentação de propostas variantes: Não autorizado\nPrazo para apresentação das propostas: 02-10-2025 23:59\nPrazo durante o qual os concorrentes são obrigados a manter as respetivas propostas: 180 dias a contar do termo do prazo para a apresentação das propostas\nIndicação de Subcontratação na Proposta: Inexistência de indicação de subcontratação\n\n14 - PRESTAÇÃO DE CAUÇÃO\nPrestação de caução: Não\n\n15 - FORNECIMENTO DAS PEÇAS DO CONCURSO, APRESENTAÇÃO DE PEDIDOS DE PARTICIPAÇÃO E APRESENTAÇÃO DAS PROPOSTAS\nLink para acesso às peças do concurso (URL): https://community.vortal.biz/Public/public-tender-documents/SGFQQTY4UDFTTWY1Y21mUm41MTZib1VPZEx2WnVWS295cUJjem5mRSt4cWcrRmlFamdtaVJOb0lMbGVNZlUyckREV211OVdMRW1NY0M1ekVhNXRncVE9PVUhOHVp\n\n20 - OUTROS REQUISITOS\nInformação sobre contratos reservados. Aplica-se a contratos reservados (54º-A)? Não\n\n21 - CRITÉRIO DE ADJUDICAÇÃO\nMultifator: Sim\nFator: \nNome: Preço\nPonderação: 50%\nSubfatores: Sim\nSubfatores: \nNome: Preço Mensal do Serviço Regular de Limpeza\nPonderação : 75%; \nNome: Preço por Intervenção do Serviço de Limpeza húmida da face exterior dos vidros, dos estores e da estrutura de sombreamento do edifício Sidónio Pais\nPonderação : 7%; \nNome: Preço por Hora do Serviços Pontuais\nPonderação : 10%; \nNome: Preço Mensal para a alocação de uma auto-lavadora\nPonderação : 4%; \nNome: Preço Mensal para a limpeza do escritório sito na Av. António Augusto de Aguiar, n.º 5 – 3.º B\nPonderação : 2%; \nNome: Preço Mensal para a limpeza do escritório sito na Av. Fontes Pereira de Melo, n.º 17 – 1.º\nPonderação : 2%; \nFator: \nNome: Qualidade\nPonderação: 40%\nSubfatores: Não\nFator: \nNome: Qualidade\nPonderação: 10%\nSubfatores: Não\n\n24 - CONDIÇÕES DO CONTRATO\nFaturação Eletrónica: Permitido\nObrigação de Subcontratação:\nCódigo da Obrigação de Subcontratação: Não é aplicável nenhuma obrigação de subcontratação.\n\n25 - COMPRA PÚBLICA ESTRATÉGICA\nCompra Pública Estratégica: Inexistência de contratação pública estratégica\n\n26 - INFORMAÇÕES ADICIONAIS\nContrato adequado para PME: Sim\nCobertura ACP (Acordo dos Contratos Públicos da Organização Mundial do Comércio): Não\n\n27 - IDENTIFICAÇÃO E CONTACTOS DO ÓRGÃO DE RECURSOS ADMINISTRATIVOS\nDesignação: CDN\nEndereço: Av. António Augusto de Aguiar, 3D\nCódigo postal: 1069-030\nLocalidade: Lisboa\nTelefone: +351 213132611\nFax: +351 213132201\nEndereço eletrónico: liliana.carvalho@oep.pt\n\n28 - IDENTIFICAÇÃO DO(S) AUTOR(ES) DE ANÚNCIO\nNome: Nelson Jerónimo\nCargo: Secretário-geral\n419544486",
    "nipc": "500839166",
    "distrito": "Lisboa",
    "concelho": "Lisboa",
    "freguesia": "Todas",
    "site": "www.ordemengenheiros.pt",
    "email": "secretariageral@oep.pt",
    "designacao_contrato": "Aquisição de Serviços de Limpeza, com fornecimento de consumíveis e equipamentos de limpeza, das instalações das Sedes Nacional e da Região Sul e de dois escritórios",
    "descricao": "Aquisição de Serviços de Limpeza, com fornecimento de consumíveis e equipamentos de limpeza, das instalações das Sedes Nacional e da Região Sul e de dois escritórios",
    "preco_base": "209.250,00 EUR",
    "prazo_execucao": "1 ANOS",
    "prazo_apresentacao_propostas": "02-10-2025 23:59",
    "fundos_eu": "Não",
    "plataforma_eletronica": "VORTAL",
    "url_procedimento": "https://community.vortal.biz/public/",
    "autor_nome": "Nelson Jerónimo",
    "autor_cargo": "Secretário-geral"
  },
  {
    "numero_procedimento": "N/A",
    "entidade": "Unidade Local Saúde de Braga, E.P.E.",
    "link": "https://diariodarepublica.pt/dr/detalhe/contrato-publico/24596-935742309",
    "detalhes_completos": "1 - IDENTIFICAÇÃO E CONTACTOS DA ENTIDADE ADJUDICANTE\nDesignação da entidade adjudicante: Unidade Local Saúde de Braga, E.P.E.\nNIPC: 515545180\nEndereço: Sete Fontes – São Victor  \nCódigo postal: 4710-243\nLocalidade: Braga\nPaís: Portugal\nNUT III: PT112\nDistrito: Braga\nConcelho: Braga\nFreguesia: Todas\nTelefone: 220411150\nEndereço da Entidade (URL): https://www.hospitaldebraga.pt/\nEndereço Eletrónico: hospitaldebraga@arsnorte.min-saude.pt\neDelivery Gateway (URL): https://community.vortal.biz/public/\nFunção da Organização: Adquirente\nNorma jurídica da Entidade Adjudicante: Empresa pública\nÁrea de atividade da Autoridade Adjudicante: Saúde\n\n2 - JORNAL OFICIAL DA UNIÃO EUROPEIA\nO procedimento a que este anúncio diz respeito também é publicitado no Jornal Oficial da União Europeia? Sim\n\n3 - AVISO\nModelo de Anúncio: Concurso público\nData de Envio do Anúncio: 15-09-2025\n\n5 - PROCESSO\nTipo de Procedimento: Concurso público\nPreço base do procedimento: Sim\nValor do preço base do procedimento: 269.788,44 EUR\nProcedimento com lotes? Sim\nNº Máx. de Lotes Autorizado: 29\nNúmero máximo de lotes que podem ser adjudicados a um concorrente: 29\n\n6 - OBJETO DO CONTRATO\nNúmero de referência interna: 5/04237/25\nDesignação do contrato: Aquisição de Meios de Cultura\nDescrição: Aquisição de Meios de Cultura\nOpções: Não\nTipo de Contrato Principal: Aquisição de Bens Móveis\nTipo de Contrato: Aquisição de Bens Móveis\nClassificação CPV (Vocabulário Comum para os Contratos Públicos)\nObjeto principal\nVocabulário Principal: 33696500\nPreço base s/IVA: 269.788,44 EUR\nLotes: \nNº: LOT-0001\nDescrição do Lote: Lote 1\nPreço base s/IVA: 13.744,50 EUR\nClassificação CPV (Vocabulário Comum para os Contratos Públicos)\nObjeto principal\nVocabulário Principal: 33696500\nNº: LOT-0002\nDescrição do Lote: Lote 2\nPreço base s/IVA: 408,24 EUR\nClassificação CPV (Vocabulário Comum para os Contratos Públicos)\nObjeto principal\nVocabulário Principal: 33696500\nNº: LOT-0003\nDescrição do Lote: Lote 3\nPreço base s/IVA: 24.191,37 EUR\nClassificação CPV (Vocabulário Comum para os Contratos Públicos)\nObjeto principal\nVocabulário Principal: 33696500\nNº: LOT-0004\nDescrição do Lote: Lote 4\nPreço base s/IVA: 7.270,56 EUR\nClassificação CPV (Vocabulário Comum para os Contratos Públicos)\nObjeto principal\nVocabulário Principal: 33696500\nNº: LOT-0005\nDescrição do Lote: Lote 5\nPreço base s/IVA: 9.741,00 EUR\nClassificação CPV (Vocabulário Comum para os Contratos Públicos)\nObjeto principal\nVocabulário Principal: 33696500\nNº: LOT-0006\nDescrição do Lote: Lote 6\nPreço base s/IVA: 1.848,00 EUR\nClassificação CPV (Vocabulário Comum para os Contratos Públicos)\nObjeto principal\nVocabulário Principal: 33696500\nNº: LOT-0007\nDescrição do Lote: Lote 7\nPreço base s/IVA: 4.200,00 EUR\nClassificação CPV (Vocabulário Comum para os Contratos Públicos)\nObjeto principal\nVocabulário Principal: 33696500\nNº: LOT-0008\nDescrição do Lote: Lote 8\nPreço base s/IVA: 8.352,00 EUR\nClassificação CPV (Vocabulário Comum para os Contratos Públicos)\nObjeto principal\nVocabulário Principal: 33696500\nNº: LOT-0009\nDescrição do Lote: Lote 9\nPreço base s/IVA: 214,50 EUR\nClassificação CPV (Vocabulário Comum para os Contratos Públicos)\nObjeto principal\nVocabulário Principal: 33696500\nNº: LOT-0010\nDescrição do Lote: Lote 10\nPreço base s/IVA: 4.989,60 EUR\nClassificação CPV (Vocabulário Comum para os Contratos Públicos)\nObjeto principal\nVocabulário Principal: 33696500\nNº: LOT-0011\nDescrição do Lote: Lote 11\nPreço base s/IVA: 230,40 EUR\nClassificação CPV (Vocabulário Comum para os Contratos Públicos)\nObjeto principal\nVocabulário Principal: 33696500\nNº: LOT-0012\nDescrição do Lote: Lote 12\nPreço base s/IVA: 7.809,60 EUR\nClassificação CPV (Vocabulário Comum para os Contratos Públicos)\nObjeto principal\nVocabulário Principal: 33696500\nNº: LOT-0013\nDescrição do Lote: Lote 13\nPreço base s/IVA: 1.371,27 EUR\nClassificação CPV (Vocabulário Comum para os Contratos Públicos)\nObjeto principal\nVocabulário Principal: 33696500\nNº: LOT-0014\nDescrição do Lote: Lote 14\nPreço base s/IVA: 15.466,50 EUR\nClassificação CPV (Vocabulário Comum para os Contratos Públicos)\nObjeto principal\nVocabulário Principal: 33696500\nNº: LOT-0015\nDescrição do Lote: Lote 15\nPreço base s/IVA: 974,70 EUR\nClassificação CPV (Vocabulário Comum para os Contratos Públicos)\nObjeto principal\nVocabulário Principal: 33696500\nNº: LOT-0016\nDescrição do Lote: Lote 16\nPreço base s/IVA: 516,24 EUR\nClassificação CPV (Vocabulário Comum para os Contratos Públicos)\nObjeto principal\nVocabulário Principal: 33696500\nNº: LOT-0017\nDescrição do Lote: Lote 17\nPreço base s/IVA: 3.024,00 EUR\nClassificação CPV (Vocabulário Comum para os Contratos Públicos)\nObjeto principal\nVocabulário Principal: 33696500\nNº: LOT-0018\nDescrição do Lote: Lote 18\nPreço base s/IVA: 128,10 EUR\nClassificação CPV (Vocabulário Comum para os Contratos Públicos)\nObjeto principal\nVocabulário Principal: 33696500\nNº: LOT-0019\nDescrição do Lote: Lote 19\nPreço base s/IVA: 162,30 EUR\nClassificação CPV (Vocabulário Comum para os Contratos Públicos)\nObjeto principal\nVocabulário Principal: 33696500\nNº: LOT-0020\nDescrição do Lote: Lote 20\nPreço base s/IVA: 7.047,00 EUR\nClassificação CPV (Vocabulário Comum para os Contratos Públicos)\nObjeto principal\nVocabulário Principal: 33696500\nNº: LOT-0021\nDescrição do Lote: Lote 21\nPreço base s/IVA: 9.360,00 EUR\nClassificação CPV (Vocabulário Comum para os Contratos Públicos)\nObjeto principal\nVocabulário Principal: 33696500\nNº: LOT-0022\nDescrição do Lote: Lote 22\nPreço base s/IVA: 2.971,80 EUR\nClassificação CPV (Vocabulário Comum para os Contratos Públicos)\nObjeto principal\nVocabulário Principal: 33696500\nNº: LOT-0023\nDescrição do Lote: Lote 23\nPreço base s/IVA: 2.152,80 EUR\nClassificação CPV (Vocabulário Comum para os Contratos Públicos)\nObjeto principal\nVocabulário Principal: 33696500\nNº: LOT-0024\nDescrição do Lote: Lote 24\nPreço base s/IVA: 4.476,75 EUR\nClassificação CPV (Vocabulário Comum para os Contratos Públicos)\nObjeto principal\nVocabulário Principal: 33696500\nNº: LOT-0025\nDescrição do Lote: Lote 25\nPreço base s/IVA: 36.000,00 EUR\nClassificação CPV (Vocabulário Comum para os Contratos Públicos)\nObjeto principal\nVocabulário Principal: 33696500\nNº: LOT-0026\nDescrição do Lote: Lote 26\nPreço base s/IVA: 25.003,50 EUR\nClassificação CPV (Vocabulário Comum para os Contratos Públicos)\nObjeto principal\nVocabulário Principal: 33696500\nNº: LOT-0027\nDescrição do Lote: Lote 27\nPreço base s/IVA: 2.895,75 EUR\nClassificação CPV (Vocabulário Comum para os Contratos Públicos)\nObjeto principal\nVocabulário Principal: 33696500\nNº: LOT-0028\nDescrição do Lote: Lote 28\nPreço base s/IVA: 23.526,30 EUR\nClassificação CPV (Vocabulário Comum para os Contratos Públicos)\nObjeto principal\nVocabulário Principal: 33696500\nNº: LOT-0029\nDescrição do Lote: Lote 29\nPreço base s/IVA: 51.711,66 EUR\nClassificação CPV (Vocabulário Comum para os Contratos Públicos)\nObjeto principal\nVocabulário Principal: 33696500\n\n7 - INDICAÇÕES ADICIONAIS\nO contrato envolve aquisição conjunta (satisfação de várias entidades)? Não\nO contrato é adjudicado por uma central de compras? Não\n\n8 - TÉCNICAS\nO concurso destina-se à celebração de um acordo-quadro? Inexistência de acordo-quadro\nÉ utilizado um leilão eletrónico? Não\nÉ adotada uma fase de negociação? Não\nSistema de Aquisição Dinâmico: Inexistência de sistema de aquisição dinâmico\n\n9 - LOCAL DA EXECUÇÃO DO CONTRATO\nLOCAL DA EXECUÇÃO DO CONTRATO (PROCEDIMENTO)\nPaís: Portugal\nNUT III: PT112\nLocalidade: Braga\nDistrito: Braga\nConcelho: Braga\nFreguesia: Todas\nLOCAL DA EXECUÇÃO DO CONTRATO (LOTE)\nIdentificador do Lote: LOT-0001; LOT-0002; LOT-0003; LOT-0004; LOT-0005; LOT-0006; LOT-0007; LOT-0008; LOT-0009; LOT-0010; LOT-0011; LOT-0012; LOT-0013; LOT-0014; LOT-0015; LOT-0016; LOT-0017; LOT-0018; LOT-0019; LOT-0020; LOT-0021; LOT-0022; LOT-0023; LOT-0024; LOT-0025; LOT-0026; LOT-0027; LOT-0028; LOT-0029\nPaís: Portugal\nNUT III: PT112\nLocalidade: Braga\nDistrito: Braga\nConcelho: Braga\nFreguesia: Todas\n\n10 - PRAZO DE EXECUÇÃO DO CONTRATO\nIdentificador do Lote: LOT-0001; LOT-0002; LOT-0003; LOT-0004; LOT-0005; LOT-0006; LOT-0007; LOT-0008; LOT-0009; LOT-0010; LOT-0011; LOT-0012; LOT-0013; LOT-0014; LOT-0015; LOT-0016; LOT-0017; LOT-0018; LOT-0019; LOT-0020; LOT-0021; LOT-0022; LOT-0023; LOT-0024; LOT-0025; LOT-0026; LOT-0027; LOT-0028; LOT-0029\nPrazo de execução do contrato: 36 MESES\nPrevisão de renovações: Não\n\n11 - FUNDOS EU\nIdentificador do Lote: LOT-0001; LOT-0002; LOT-0003; LOT-0004; LOT-0005; LOT-0006; LOT-0007; LOT-0008; LOT-0009; LOT-0010; LOT-0011; LOT-0012; LOT-0013; LOT-0014; LOT-0015; LOT-0016; LOT-0017; LOT-0018; LOT-0019; LOT-0020; LOT-0021; LOT-0022; LOT-0023; LOT-0024; LOT-0025; LOT-0026; LOT-0027; LOT-0028; LOT-0029\nTêm fundos EU? Não\n\n12 - DOCUMENTOS DE HABILITAÇÃO\nHabilitação para o exercício da atividade profissional: Não\n\n13 - CONDIÇÕES DE APRESENTAÇÃO\nPlataforma eletrónica utilizada pela entidade adjudicante: VORTAL\nURL para Apresentação: https://community.vortal.biz/public/\nAdmissibilidade da apresentação de propostas variantes: Não autorizado\nPrazo para apresentação das propostas: 15-10-2025 17:00\nPrazo durante o qual os concorrentes são obrigados a manter as respetivas propostas: 120 dias a contar do termo do prazo para a apresentação das propostas\nApresentação de Catálogo Eletrónico: Permitido\nIndicação de Subcontratação na Proposta: Inexistência de indicação de subcontratação\n\n14 - PRESTAÇÃO DE CAUÇÃO\nPrestação de caução: Não\n\n15 - FORNECIMENTO DAS PEÇAS DO CONCURSO, APRESENTAÇÃO DE PEDIDOS DE PARTICIPAÇÃO E APRESENTAÇÃO DAS PROPOSTAS\nLink para acesso às peças do concurso (URL): https://community.vortal.biz/Public/public-tender-documents/QnM0NkYzQzB2WGlCNVFFV2VqVFdCNEpVTXVBMDFoak5rSkRBNVNFRk5veitmUGdNd2Q0RnA3Y3c2KzMwVVNkWktRTy9wL3NlMTlWbzFUTThxbEc0dGc9PVBReXBC\n\n20 - OUTROS REQUISITOS\nIdentificador do Lote: LOT-0001; LOT-0002; LOT-0003; LOT-0004; LOT-0005; LOT-0006; LOT-0007; LOT-0008; LOT-0009; LOT-0010; LOT-0011; LOT-0012; LOT-0013; LOT-0014; LOT-0015; LOT-0016; LOT-0017; LOT-0018; LOT-0019; LOT-0020; LOT-0021; LOT-0022; LOT-0023; LOT-0024; LOT-0025; LOT-0026; LOT-0027; LOT-0028; LOT-0029\nInformação sobre contratos reservados. Aplica-se a contratos reservados (54º-A)? Não\n\n21 - CRITÉRIO DE ADJUDICAÇÃO\nO Critério de adjudicação é diferenciado por lote? Não\nMultifator: Sim\nFator: \nNome: Preço\nPonderação: 60%\nSubfatores: Não\nFator: \nNome: Qualidade\nPonderação: 40%\nSubfatores: Não\n\n24 - CONDIÇÕES DO CONTRATO\nIdentificador do Lote: LOT-0001; LOT-0002; LOT-0003; LOT-0004; LOT-0005; LOT-0006; LOT-0007; LOT-0008; LOT-0009; LOT-0010; LOT-0011; LOT-0012; LOT-0013; LOT-0014; LOT-0015; LOT-0016; LOT-0017; LOT-0018; LOT-0019; LOT-0020; LOT-0021; LOT-0022; LOT-0023; LOT-0024; LOT-0025; LOT-0026; LOT-0027; LOT-0028; LOT-0029\nFaturação Eletrónica: Permitido\nObrigação de Subcontratação:\nCódigo da Obrigação de Subcontratação: Não é aplicável nenhuma obrigação de subcontratação.\n\n25 - COMPRA PÚBLICA ESTRATÉGICA\nCompra Pública Estratégica: Inexistência de contratação pública estratégica\n\n26 - INFORMAÇÕES ADICIONAIS\nIdentificador do Lote: LOT-0001; LOT-0002; LOT-0003; LOT-0004; LOT-0005; LOT-0006; LOT-0007; LOT-0008; LOT-0009; LOT-0010; LOT-0011; LOT-0012; LOT-0013; LOT-0014; LOT-0015; LOT-0016; LOT-0017; LOT-0018; LOT-0019; LOT-0020; LOT-0021; LOT-0022; LOT-0023; LOT-0024; LOT-0025; LOT-0026; LOT-0027; LOT-0028; LOT-0029\nContrato adequado para PME: Sim\nCobertura ACP (Acordo dos Contratos Públicos da Organização Mundial do Comércio): Não\n\n27 - IDENTIFICAÇÃO E CONTACTOS DO ÓRGÃO DE RECURSOS ADMINISTRATIVOS\nDesignação: Conselho de Administração\nEndereço: Sete Fontes- São Victor\nCódigo postal: 4710-243\nLocalidade: Braga\nTelefone: +351 253027000\nFax: +351 253027999\nEndereço eletrónico: hbraga@uls.min-saude.pt\n\n28 - IDENTIFICAÇÃO DO(S) AUTOR(ES) DE ANÚNCIO\nNome: Cristina Freitas\nCargo: Técnico Superior\n419536889",
    "nipc": "515545180",
    "distrito": "Braga",
    "concelho": "Braga",
    "freguesia": "Todas",
    "site": "https://www.hospitaldebraga.pt/",
    "email": "hospitaldebraga@arsnorte.min-saude.pt",
    "designacao_contrato": "Aquisição de Meios de Cultura",
    "descricao": "Aquisição de Meios de Cultura",
    "preco_base": "269.788,44 EUR",
    "prazo_execucao": "36 MESES",
    "prazo_apresentacao_propostas": "15-10-2025 17:00",
    "fundos_eu": "Não",
    "plataforma_eletronica": "VORTAL",
    "url_procedimento": "https://community.vortal.biz/public/",
    "autor_nome": "Cristina Freitas",
    "autor_cargo": "Técnico Superior"
  },
  {
    "numero_procedimento": "N/A",
    "entidade": "Construção Pública, E.P.E.",
    "link": "https://diariodarepublica.pt/dr/detalhe/contrato-publico/24597-935742310",
    "detalhes_completos": "1 - IDENTIFICAÇÃO E CONTACTOS DA ENTIDADE ADJUDICANTE\nDesignação da entidade adjudicante: Construção Pública, E.P.E.\nNIPC: 508069645\nEndereço: Avenida Infante Santo n.º 2\nCódigo postal: 1350-178\nLocalidade: Lisboa\nPaís: Portugal\nNUT III: PT170\nDistrito: Lisboa\nConcelho: Lisboa\nFreguesia: Freguesia da Estrela\nTelefone: 213944710\nFax: 213944710\nEndereço da Entidade (URL): https://construcaopublica.gov.pt\nEndereço Eletrónico: geral@construcaopublica.gov.pt\neDelivery Gateway (URL): https://community.vortal.biz/public/\nFunção da Organização: Adquirente\nNorma jurídica da Entidade Adjudicante: Organismo de direito público\nÁrea de atividade da Autoridade Adjudicante: Serviços públicos das administrações públicas\n\n2 - JORNAL OFICIAL DA UNIÃO EUROPEIA\nO procedimento a que este anúncio diz respeito também é publicitado no Jornal Oficial da União Europeia? Sim\n\n3 - AVISO\nModelo de Anúncio: Concurso público\nData de Envio do Anúncio: 15-09-2025\n\n5 - PROCESSO\nTipo de Procedimento: Concurso público\nPreço base do procedimento: Sim\nValor do preço base do procedimento: 400.000,00 EUR\nProcedimento com lotes? Não\n\n6 - OBJETO DO CONTRATO\nNúmero de referência interna: PE_25136_CIB\nDesignação do contrato: PE_25136_CIB - CONC. PÚB. INTERNAC. PARA AQUISIÇÃO DE APLIC. INFORMÁTICA INTEGRADA PARA GESTÃO DE PROCEDIMENTOS DE CONTRATAÇÃO PÚBLICA E GESTÃO DE CONTRATOS DE EMPREITADA, INC. MANUTENÇÃO E SUPORTE\nDescrição: PE_25136_CIB - CONCURSO PÚBLICO INTERNACIONAL PARA AQUISIÇÃO DE APLICAÇÃO INFORMÁTICA INTEGRADA PARA GESTÃO DE PROCEDIMENTOS DE CONTRATAÇÃO PÚBLICA E GESTÃO DE CONTRATOS DE EMPREITADA, INCLUINDO MANUTENÇÃO E SUPORTE\nOpções: Não\nTipo de Contrato Principal: Aquisição de Bens Móveis\nTipo de Contrato: Aquisição de Bens Móveis\nClassificação CPV (Vocabulário Comum para os Contratos Públicos)\nObjeto principal\nVocabulário Principal: 48330000\nPreço base s/IVA: 400.000,00 EUR\n\n7 - INDICAÇÕES ADICIONAIS\nO contrato envolve aquisição conjunta (satisfação de várias entidades)? Não\nO contrato é adjudicado por uma central de compras? Não\n\n8 - TÉCNICAS\nO concurso destina-se à celebração de um acordo-quadro? Inexistência de acordo-quadro\nÉ utilizado um leilão eletrónico? Não\nÉ adotada uma fase de negociação? Não\nSistema de Aquisição Dinâmico: Inexistência de sistema de aquisição dinâmico\n\n9 - LOCAL DA EXECUÇÃO DO CONTRATO\nLOCAL DA EXECUÇÃO DO CONTRATO (PROCEDIMENTO)\nPaís: Portugal\nNUT III: PT170\nLocalidade: Lisboa\nDistrito: Lisboa\nConcelho: Lisboa\nFreguesia: Freguesia da Estrela\n\n10 - PRAZO DE EXECUÇÃO DO CONTRATO\nPrazo de execução do contrato: 36 MESES\nPrevisão de renovações: Não\n\n11 - FUNDOS EU\nTêm fundos EU? Não\n\n12 - DOCUMENTOS DE HABILITAÇÃO\nHabilitação para o exercício da atividade profissional: Não\n\n13 - CONDIÇÕES DE APRESENTAÇÃO\nPlataforma eletrónica utilizada pela entidade adjudicante: VORTAL\nURL para Apresentação: https://community.vortal.biz/public/\nAdmissibilidade da apresentação de propostas variantes: Não autorizado\nPrazo para apresentação das propostas: 20-10-2025 17:00\nPrazo durante o qual os concorrentes são obrigados a manter as respetivas propostas: 180 dias a contar do termo do prazo para a apresentação das propostas\nApresentação de Catálogo Eletrónico: Não autorizado\nIndicação de Subcontratação na Proposta: Inexistência de indicação de subcontratação\n\n14 - PRESTAÇÃO DE CAUÇÃO\nPrestação de caução: Não\n\n15 - FORNECIMENTO DAS PEÇAS DO CONCURSO, APRESENTAÇÃO DE PEDIDOS DE PARTICIPAÇÃO E APRESENTAÇÃO DAS PROPOSTAS\nLink para acesso às peças do concurso (URL): https://community.vortal.biz/Public/public-tender-documents/bk1vQXB6TzdSZ2czckhwckZwSkFDWjdwSDE5bUFKTThQUDdrUWhSWGZmbWxMaXpUcHp4Ly9WeldtbXlnRW1aN0g0Sjd1QzNtVXR5c2hzVkVtcGFpS1E9PUtXVCZo\n\n20 - OUTROS REQUISITOS\nInformação sobre contratos reservados. Aplica-se a contratos reservados (54º-A)? Não\n\n21 - CRITÉRIO DE ADJUDICAÇÃO\nMultifator: Sim\nFator: \nNome: Preço\nPonderação: 70%\nSubfatores: Não\nFator: \nNome: Outros\nOutro Nome: Funcionalidades propostas para a versão base do módulo de gestão de contratos de empreitada - Fator B\nPonderação: 20%\nSubfatores: Não\nFator: \nNome: Outros\nOutro Nome: Prazos de execução - Fator C\nPonderação: 10%\nSubfatores: Sim\nSubfatores: \nNome: Prazo para disponibilização da versão base do módulo de gestão de contratos de empreitada - Subfator C1\nPonderação : 60%; \nNome: Prazo para disponibilização da versão completa do módulo de gestão de contratos de empreitada - - Subfator C2\nPonderação : 20%; \nNome: Prazo para disponibilização do módulo de contratação pública -- Subfator C3\nPonderação : 20%; \n\n24 - CONDIÇÕES DO CONTRATO\nFaturação Eletrónica: Permitido\nObrigação de Subcontratação:\nCódigo da Obrigação de Subcontratação: Não é aplicável nenhuma obrigação de subcontratação.\n\n25 - COMPRA PÚBLICA ESTRATÉGICA\nCompra Pública Estratégica: Inexistência de contratação pública estratégica\n\n26 - INFORMAÇÕES ADICIONAIS\nContrato adequado para PME: Sim\nCobertura ACP (Acordo dos Contratos Públicos da Organização Mundial do Comércio): Não\n\n27 - IDENTIFICAÇÃO E CONTACTOS DO ÓRGÃO DE RECURSOS ADMINISTRATIVOS\nDesignação: Conselho de Administração da Construção Pública, E.P.E.\nEndereço: Avenida Infante Santo n.º 2\nCódigo postal: 1350-178\nLocalidade: Lisboa\nTelefone: +351 213944710\nFax: +351 213944775\nEndereço eletrónico: concursos@construcaopublica.gov.pt\n\n28 - IDENTIFICAÇÃO DO(S) AUTOR(ES) DE ANÚNCIO\nNome: Nélia Marisa Araújo Lemos\nCargo: Coordenadora da Equipa de Formação de Contratos\n419536142",
    "nipc": "508069645",
    "distrito": "Lisboa",
    "concelho": "Lisboa",
    "freguesia": "Freguesia da Estrela",
    "site": "https://construcaopublica.gov.pt",
    "email": "geral@construcaopublica.gov.pt",
    "designacao_contrato": "PE_25136_CIB - CONC. PÚB. INTERNAC. PARA AQUISIÇÃO DE APLIC. INFORMÁTICA INTEGRADA PARA GESTÃO DE PROCEDIMENTOS DE CONTRATAÇÃO PÚBLICA E GESTÃO DE CONTRATOS DE EMPREITADA, INC. MANUTENÇÃO E SUPORTE",
    "descricao": "PE_25136_CIB - CONCURSO PÚBLICO INTERNACIONAL PARA AQUISIÇÃO DE APLICAÇÃO INFORMÁTICA INTEGRADA PARA GESTÃO DE PROCEDIMENTOS DE CONTRATAÇÃO PÚBLICA E GESTÃO DE CONTRATOS DE EMPREITADA, INCLUINDO MANUTENÇÃO E SUPORTE",
    "preco_base": "400.000,00 EUR",
    "prazo_execucao": "36 MESES",
    "prazo_apresentacao_propostas": "20-10-2025 17:00",
    "fundos_eu": "Não",
    "plataforma_eletronica": "VORTAL",
    "url_procedimento": "https://community.vortal.biz/public/",
    "autor_nome": "Nélia Marisa Araújo Lemos",
    "autor_cargo": "Coordenadora da Equipa de Formação de Contratos"
  },
  {
    "numero_procedimento": "N/A",
    "entidade": "Águas e Energia do Porto E.M",
    "link": "https://diariodarepublica.pt/dr/detalhe/contrato-publico/24601-935742311",
    "detalhes_completos": "1 - IDENTIFICAÇÃO E CONTACTOS DA ENTIDADE ADJUDICANTE\nDesignação da entidade adjudicante: Águas e Energia do Porto E.M\nNIPC: 507718666\nServiço/Órgão/Pessoa de contacto: Administrador\nEndereço: Rua Barão de Nova Sintra, Nº 285\nCódigo postal: 4300-367\nLocalidade: Porto\nPaís: Portugal\nNUT III: PTZZZ\nDistrito: Todos\nConcelho: Todos\nFreguesia: Todas\nTelefone: 225190854\nFax: 225190807\nEndereço da Entidade (URL): www.aguasdoporto.pt\nEndereço Eletrónico: contratos@aguasdoporto.pt\neDelivery Gateway (URL): https://www.acingov.pt\nFunção da Organização: Adquirente\nNorma jurídica da Entidade Adjudicante: Organismo de direito público\nÁrea de atividade da Autoridade Adjudicante: Serviços públicos das administrações públicas\n\n2 - JORNAL OFICIAL DA UNIÃO EUROPEIA\nO procedimento a que este anúncio diz respeito também é publicitado no Jornal Oficial da União Europeia? Sim\n\n3 - AVISO\nModelo de Anúncio: Concurso público\nData de Envio do Anúncio: 15-09-2025\n\n5 - PROCESSO\nTipo de Procedimento: Concurso público\nPreço base do procedimento: Sim\nValor do preço base do procedimento: 707.500,00 EUR\nProcedimento com lotes? Sim\nNº Máx. de Lotes Autorizado: 2\nNúmero máximo de lotes que podem ser adjudicados a um concorrente: 2\n\n6 - OBJETO DO CONTRATO\nNúmero de referência interna: 2168CPI25\nDesignação do contrato: Aquisição de Viaturas\nDescrição: Aquisição de Viaturas\nOpções: Não\nTipo de Contrato Principal: Aquisição de Bens Móveis\nTipo de Contrato: Aquisição de Bens Móveis\nClassificação CPV (Vocabulário Comum para os Contratos Públicos)\nObjeto principal\nVocabulário Principal: 34140000\nPreço base s/IVA: 707.500,00 EUR\nLotes: \nNº: LOT-0001\nDescrição do Lote: Veículo Pesado\nPreço base s/IVA: 507.000,00 EUR\nClassificação CPV (Vocabulário Comum para os Contratos Públicos)\nObjeto principal\nVocabulário Principal: 34140000\nNº: LOT-0002\nDescrição do Lote: Veículo Piquete\nPreço base s/IVA: 200.500,00 EUR\nClassificação CPV (Vocabulário Comum para os Contratos Públicos)\nObjeto principal\nVocabulário Principal: 34140000\n\n7 - INDICAÇÕES ADICIONAIS\nO contrato envolve aquisição conjunta (satisfação de várias entidades)? Não\nO contrato é adjudicado por uma central de compras? Não\n\n8 - TÉCNICAS\nO concurso destina-se à celebração de um acordo-quadro? Inexistência de acordo-quadro\nÉ utilizado um leilão eletrónico? Não\nÉ adotada uma fase de negociação? Não\nSistema de Aquisição Dinâmico: Inexistência de sistema de aquisição dinâmico\n\n9 - LOCAL DA EXECUÇÃO DO CONTRATO\nLOCAL DA EXECUÇÃO DO CONTRATO (PROCEDIMENTO)\nPaís: Portugal\nNUT III: PT11A\nLocalidade: Freguesia de Bonfim\nDistrito: Porto\nConcelho: Porto\nFreguesia: Freguesia de Bonfim\nLOCAL DA EXECUÇÃO DO CONTRATO (LOTE)\nIdentificador do Lote: LOT-0001; LOT-0002\nPaís: Portugal\nNUT III: PT11A\nLocalidade: Freguesia de Bonfim\nDistrito: Porto\nConcelho: Porto\nFreguesia: Freguesia de Bonfim\n\n10 - PRAZO DE EXECUÇÃO DO CONTRATO\nIdentificador do Lote: LOT-0001; LOT-0002\nPrazo de execução do contrato: 180 DIAS\nPrevisão de renovações: Não\n\n11 - FUNDOS EU\nIdentificador do Lote: LOT-0001; LOT-0002\nTêm fundos EU? Não\n\n12 - DOCUMENTOS DE HABILITAÇÃO\nHabilitação para o exercício da atividade profissional: Não\n\n13 - CONDIÇÕES DE APRESENTAÇÃO\nPlataforma eletrónica utilizada pela entidade adjudicante: ACIN\nURL para Apresentação: https://www.acingov.pt\nAdmissibilidade da apresentação de propostas variantes: Não autorizado\nPrazo para apresentação das propostas: 15-10-2025 17:00\nPrazo durante o qual os concorrentes são obrigados a manter as respetivas propostas: 66 dias a contar do termo do prazo para a apresentação das propostas\nApresentação de Catálogo Eletrónico: Permitido\nIndicação de Subcontratação na Proposta: Inexistência de indicação de subcontratação\n\n14 - PRESTAÇÃO DE CAUÇÃO\nPrestação de caução: Sim\nPercentagem: 5%\nDescrição da Garantia Exigida: O valor da caução é de 5.00% do preço contratual.\n\n15 - FORNECIMENTO DAS PEÇAS DO CONCURSO, APRESENTAÇÃO DE PEDIDOS DE PARTICIPAÇÃO E APRESENTAÇÃO DAS PROPOSTAS\nLink para acesso às peças do concurso (URL): https://www.acingov.pt/acingovprod/2/zonaPublica/zona_publica_c/donwloadProcedurePiece/OTc3ODEz\n\n20 - OUTROS REQUISITOS\nIdentificador do Lote: LOT-0001; LOT-0002\nInformação sobre contratos reservados. Aplica-se a contratos reservados (54º-A)? Não\n\n21 - CRITÉRIO DE ADJUDICAÇÃO\nO Critério de adjudicação é diferenciado por lote? Não\nMultifator: Sim\nFator: \nNome: Preço\nPonderação: 50%\nSubfatores: Não\nFator: \nNome: Outros\nOutro Nome: Avaliação das Características Técnicas\nPonderação: 35%\nSubfatores: Não\nFator: \nNome: Outros\nOutro Nome: Avaliação do Prazo de Entrega\nPonderação: 15%\nSubfatores: Não\n\n24 - CONDIÇÕES DO CONTRATO\nIdentificador do Lote: LOT-0001; LOT-0002\nFaturação Eletrónica: Permitido\nObrigação de Subcontratação:\nCódigo da Obrigação de Subcontratação: Não é aplicável nenhuma obrigação de subcontratação.\n\n25 - COMPRA PÚBLICA ESTRATÉGICA\nCompra Pública Estratégica: Inexistência de contratação pública estratégica\n\n26 - INFORMAÇÕES ADICIONAIS\nIdentificador do Lote: LOT-0001; LOT-0002\nContrato adequado para PME: Sim\nCobertura ACP (Acordo dos Contratos Públicos da Organização Mundial do Comércio): Não\n\n27 - IDENTIFICAÇÃO E CONTACTOS DO ÓRGÃO DE RECURSOS ADMINISTRATIVOS\nDesignação: Águas e Energia do Porto\nEndereço: R. do Barão de Nova Sintra 285\nCódigo postal: 4300-367\nLocalidade: Bonfim\nTelefone: 220100220\nFax: \nEndereço eletrónico: contratos@aguasdoporto.pt\nPrazo de interposição do recurso: 30 dias\n\n28 - IDENTIFICAÇÃO DO(S) AUTOR(ES) DE ANÚNCIO\nNome: Ruben Fernandes\nCargo: Administrador Executivo\n419535649",
    "nipc": "507718666",
    "distrito": "Todos",
    "concelho": "Todos",
    "freguesia": "Todas",
    "site": "www.aguasdoporto.pt",
    "email": "contratos@aguasdoporto.pt",
    "designacao_contrato": "Aquisição de Viaturas",
    "descricao": "Aquisição de Viaturas",
    "preco_base": "707.500,00 EUR",
    "prazo_execucao": "180 DIAS",
    "prazo_apresentacao_propostas": "15-10-2025 17:00",
    "fundos_eu": "Não",
    "plataforma_eletronica": "ACIN",
    "url_procedimento": "https://www.acingov.pt",
    "autor_nome": "Ruben Fernandes",
    "autor_cargo": "Administrador Executivo"
  },
  {
    "numero_procedimento": "N/A",
    "entidade": "Cinemateca Portuguesa  Museu do Cinema, I.P.",
    "link": "https://diariodarepublica.pt/dr/detalhe/contrato-publico/24602-935742312",
    "detalhes_completos": "1 - IDENTIFICAÇÃO E CONTACTOS DA ENTIDADE ADJUDICANTE\nDesignação da entidade adjudicante: Cinemateca Portuguesa  Museu do Cinema, I.P.\nNIPC: 501603409\nServiço/Órgão/Pessoa de contacto: Divisão de Gestão\nEndereço: Rua Barata Salgueiro, n.º 39\nCódigo postal: 1269-059\nLocalidade: Lisboa\nPaís: Portugal\nNUT III: PT170\nDistrito: Lisboa\nConcelho: Lisboa\nFreguesia: Freguesia de Santo António - Lisboa\nTelefone: 213596200\nEndereço da Entidade (URL): www.cinemateca.pt\nEndereço Eletrónico: compras@cinemateca.pt\neDelivery Gateway (URL): https://www.acingov.pt\nFunção da Organização: Adquirente\nNorma jurídica da Entidade Adjudicante: Organismo de direito público\nÁrea de atividade da Autoridade Adjudicante: Serviços públicos das administrações públicas\n\n2 - JORNAL OFICIAL DA UNIÃO EUROPEIA\nO procedimento a que este anúncio diz respeito também é publicitado no Jornal Oficial da União Europeia? Não\n\n3 - AVISO\nModelo de Anúncio: Concurso público\nData de Envio do Anúncio: 17-09-2025\n\n5 - PROCESSO\nTipo de Procedimento: Concurso público\nPreço base do procedimento: Sim\nValor do preço base do procedimento: 194.912,96 EUR\nProcedimento com lotes? Não\n\n6 - OBJETO DO CONTRATO\nNúmero de referência interna: CP/02/2025\nDesignação do contrato: Empreitada de obra pública para reabilitação de vias internas\nDescrição: Contrato de empreitada de obras públicas para reabilitação de vias internas no âmbito de uma intervenção a levar a cabo nos espaços exteriores do edifício principal do ANIM  Aquivo Nacional das Imagens em Movimento\nTipo de Contrato Principal: Empreitada de Obras Públicas\nTipo de Contrato: Empreitada de Obras Públicas\nClassificação CPV (Vocabulário Comum para os Contratos Públicos)\nObjeto principal\nVocabulário Principal: 45233140\nPreço base s/IVA: 194.912,96 EUR\n\n7 - INDICAÇÕES ADICIONAIS\nO contrato envolve aquisição conjunta (satisfação de várias entidades)? Não\nO contrato é adjudicado por uma central de compras? Não\n\n8 - TÉCNICAS\nO concurso destina-se à celebração de um acordo-quadro? Inexistência de acordo-quadro\nÉ utilizado um leilão eletrónico? Não\nÉ adotada uma fase de negociação? Não\nSistema de Aquisição Dinâmico: Inexistência de sistema de aquisição dinâmico\n\n9 - LOCAL DA EXECUÇÃO DO CONTRATO\nLOCAL DA EXECUÇÃO DO CONTRATO (PROCEDIMENTO)\nPaís: Portugal\nNUT III: PT170\nLocalidade: Freixial\nDistrito: Lisboa\nConcelho: Loures\nFreguesia: Freguesia de Bucelas\n\n10 - PRAZO DE EXECUÇÃO DO CONTRATO\nPrazo de execução do contrato: 6 MESES\nPrevisão de renovações: Não\n\n11 - FUNDOS EU\nTêm fundos EU? Não\n\n12 - DOCUMENTOS DE HABILITAÇÃO\nHabilitação para o exercício da atividade profissional: Sim\nTipo: Alvará\nDescrição: Alvará ou certificado de empreiteiro de obras públicas emitido pelo Instituto dos Mercados Públicos do Imobiliário e da Construção, I.P., contendo a seguinte habilitação: 1.ª subcategoria da 2.ª categoria (Vias de circulação rodoviária e aeródromos)\n\n13 - CONDIÇÕES DE APRESENTAÇÃO\nPlataforma eletrónica utilizada pela entidade adjudicante: ACIN\nURL para Apresentação: https://www.acingov.pt\nAdmissibilidade da apresentação de propostas variantes: Não autorizado\nPrazo para apresentação das propostas: 02-10-2025 23:59\nPrazo durante o qual os concorrentes são obrigados a manter as respetivas propostas: 66 dias a contar do termo do prazo para a apresentação das propostas\nIndicação de Subcontratação na Proposta: Inexistência de indicação de subcontratação\n\n14 - PRESTAÇÃO DE CAUÇÃO\nPrestação de caução: Não\n\n15 - FORNECIMENTO DAS PEÇAS DO CONCURSO, APRESENTAÇÃO DE PEDIDOS DE PARTICIPAÇÃO E APRESENTAÇÃO DAS PROPOSTAS\nLink para acesso às peças do concurso (URL): https://www.acingov.pt/acingovprod/2/zonaPublica/zona_publica_c/donwloadProcedurePiece/OTc4NDQ0\n\n20 - OUTROS REQUISITOS\nInformação sobre contratos reservados. Aplica-se a contratos reservados (54º-A)? Não\n\n21 - CRITÉRIO DE ADJUDICAÇÃO\nMultifator: Sim\nFator: \nNome: Preço\nPonderação: 75%\nSubfatores: Não\nFator: \nNome: Outros\nOutro Nome: Prazo de execução\nPonderação: 20%\nSubfatores: Não\nFator: \nNome: Outros\nOutro Nome: Utilização de materiais reutilizados ou reciclados\nPonderação: 5%\nSubfatores: Não\n\n24 - CONDIÇÕES DO CONTRATO\nFaturação Eletrónica: Permitido\nObrigação de Subcontratação:\nCódigo da Obrigação de Subcontratação: Não é aplicável nenhuma obrigação de subcontratação.\n\n25 - COMPRA PÚBLICA ESTRATÉGICA\nCompra Pública Estratégica: Inexistência de contratação pública estratégica\n\n26 - INFORMAÇÕES ADICIONAIS\nContrato adequado para PME: Sim\nCobertura ACP (Acordo dos Contratos Públicos da Organização Mundial do Comércio): Não\n\n27 - IDENTIFICAÇÃO E CONTACTOS DO ÓRGÃO DE RECURSOS ADMINISTRATIVOS\nDesignação: Diretor\nEndereço: Rua Barata Salgueiro, n.º 39\nCódigo postal: 1269-059\nLocalidade: Lisboa\nTelefone: 213596230\nFax: \nEndereço eletrónico: compras@cinemateca.pt\n\n28 - IDENTIFICAÇÃO DO(S) AUTOR(ES) DE ANÚNCIO\nNome: Isabel Juliana Schedel Arouca\nCargo: Chefe da Divisão de Gestão\n419545466",
    "nipc": "501603409",
    "distrito": "Lisboa",
    "concelho": "Lisboa",
    "freguesia": "Freguesia de Santo António - Lisboa",
    "site": "www.cinemateca.pt",
    "email": "compras@cinemateca.pt",
    "designacao_contrato": "Empreitada de obra pública para reabilitação de vias internas",
    "descricao": "Contrato de empreitada de obras públicas para reabilitação de vias internas no âmbito de uma intervenção a levar a cabo nos espaços exteriores do edifício principal do ANIM  Aquivo Nacional das Imagens em Movimento",
    "preco_base": "194.912,96 EUR",
    "prazo_execucao": "6 MESES",
    "prazo_apresentacao_propostas": "02-10-2025 23:59",
    "fundos_eu": "Não",
    "plataforma_eletronica": "ACIN",
    "url_procedimento": "https://www.acingov.pt",
    "autor_nome": "Isabel Juliana Schedel Arouca",
    "autor_cargo": "Chefe da Divisão de Gestão"
  },
  {
    "numero_procedimento": "N/A",
    "entidade": "Ordem dos Notários",
    "link": "https://diariodarepublica.pt/dr/detalhe/contrato-publico/24603-935742313",
    "detalhes_completos": "1 - IDENTIFICAÇÃO E CONTACTOS DA ENTIDADE ADJUDICANTE\nDesignação da entidade adjudicante: Ordem dos Notários\nNIPC: 507680316\nEndereço: Av. Visconde Valmor, n 19 A  \nCódigo postal: 1000-290\nLocalidade: Lisboa\nPaís: Portugal\nNUT III: PT170\nDistrito: Lisboa\nConcelho: Lisboa\nFreguesia: Freguesia de Avenidas Novas\nTelefone: 213468176\nEndereço Eletrónico: geral@notarios.pt\neDelivery Gateway (URL): https://community.vortal.biz/public/\nFunção da Organização: Adquirente\nNorma jurídica da Entidade Adjudicante: Autoridade da administração central\nÁrea de atividade da Autoridade Adjudicante: Assuntos económicos\n\n2 - JORNAL OFICIAL DA UNIÃO EUROPEIA\nO procedimento a que este anúncio diz respeito também é publicitado no Jornal Oficial da União Europeia? Não\n\n3 - AVISO\nModelo de Anúncio: Concurso limitado por prévia qualificação\nData de Envio do Anúncio: 17-09-2025\n\n5 - PROCESSO\nTipo de Procedimento: Concurso limitado por prévia qualificação\nPreço base do procedimento: Sim\nValor do preço base do procedimento: 220.000,00 EUR\nProcedimento com lotes? Não\n\n6 - OBJETO DO CONTRATO\nNúmero de referência interna: CPUB-3/25 - Arquivo eletrónico\nDesignação do contrato: AQUISIÇÃO DO DESENVOLVIMENTO DE NOVA PLATAFORMA DE ARQUIVO ELETRÓNICO E RESPETIVOS SERVIÇOS DE MANUTENÇÃO\nDescrição: AQUISIÇÃO DO DESENVOLVIMENTO DE NOVA PLATAFORMA DE ARQUIVO ELETRÓNICO E\nRESPETIVOS SERVIÇOS DE MANUTENÇÃO\nTipo de Contrato Principal: Aquisição de Serviços\nTipo de Contrato: Aquisição de Serviços\nClassificação CPV (Vocabulário Comum para os Contratos Públicos)\nObjeto principal\nVocabulário Principal: 72268000\nPreço base s/IVA: 220.000,00 EUR\n\n7 - INDICAÇÕES ADICIONAIS\nO contrato envolve aquisição conjunta (satisfação de várias entidades)? Não\nO contrato é adjudicado por uma central de compras? Não\n\n8 - TÉCNICAS\nO concurso destina-se à celebração de um acordo-quadro? Inexistência de acordo-quadro\nÉ utilizado um leilão eletrónico? Não\nSistema de Aquisição Dinâmico: Inexistência de sistema de aquisição dinâmico\n\n9 - LOCAL DA EXECUÇÃO DO CONTRATO\nLOCAL DA EXECUÇÃO DO CONTRATO (PROCEDIMENTO)\nPaís: Portugal\nNUT III: PT170\nLocalidade: Lisboa\nDistrito: Lisboa\nConcelho: Lisboa\nFreguesia: Freguesia de Avenidas Novas\n\n10 - PRAZO DE EXECUÇÃO DO CONTRATO\nPrazo de execução do contrato: 3 ANOS\nPrevisão de renovações: Não\n\n11 - FUNDOS EU\nTêm fundos EU? Não\n\n12 - DOCUMENTOS DE HABILITAÇÃO\nHabilitação para o exercício da atividade profissional: Sim\nTipo: Certificado\nDescrição: Possuir certificação ISO/IEC 20000-1:2018 e NP 4457 (IDI – Investigação, Desenvolvimento e Inovação);\nPossuir certificação ISO/IEC 27001:2022 (Sistemas de Gestão de Segurança da Informação)\nPossuir credenciação de segurança, no grau SECRETO, pelo Gabinete Nacional de Segurança;\nPossuir mais de três anos de experiência em softwares e plataformas na área da justiça;\nPossuir recursos humanos dotados com Certificação IPMA Level D – Certified Project Management Associate.\nPossuir software de faturação certificado pela Autoridade Tributária;\nPossuir experiência comprovada de integrações desenvolvidas com:\n \ni.    Serviços da área da justiça (pelo menos uma das seguintes entidades ou de outras equiparadas):\n               1 - CITIUS (exemplo: processos de múltiplas tipológicas, Exec, EQC, Balcão Nacional de Arrendamentos);\n               2 - IRN – Instituto dos Registos e Notariado (exemplo: penhora de automóveis, consultas no Registo Automóvel, no Instituto dos Registos e do Notariado, I.P. (IRN), Registo Nacional de Pessoas Coletivas (RNPC), registo comercial, registo predial, registo predial, registo automóvel, registo de execuções);\n               3 - Tribunais (exemplo: distribuição de processos),\n               4 - SIEJ – Sistema de Informação das Estatísticas da Justiça (exemplo: Estatísticas da Justiça);\n5 - Tribunal de Contas (exemplo: prestação de contas);\nii.  Sistemas de Finanças (pelo menos uma das seguintes entidades ou de outras equiparadas):\n1.            Autoridade Tributária (exemplo: Consultas faturação/SAFT, SAFT-PT, guias de expedição, remessa, transporte, IMT, Modelo 11, DMIS – Declaração Mensal do Imposto selo, consulta NIF/nome);\n2.            Banco de Portugal (exemplo: consultas, extratos e conciliação bancária, sistema de prevenção de branqueamento de capitais);\n3.            IGCP – Agência de Gestão da Tesouraria e da Dívida Pública (exemplo: Documento único de Cobrança – emissão e pagamento, recebimento de valores penhorados);\n4.            CNP – Centro Nacional de Pensões (exemplo: recebimento de valores penhorados);\niii. Outras entidades (pelo menos uma das seguintes ou de outras equiparadas):                                                                            1.  AMA – Agência para a Modernização Administrativa , I.P. (exemplo: Chave Móvel Digital, autenticação.gov.pt, ePortugal, certidão permanente de registo comercial);\n2.  Comissão Europeia (exemplo: Vies-VAT Information Exchange System);\n3.  Entidades bancárias nacionais (exemplo: faturação de taxas de pedidos de penhoras bancárias);\n\n13 - CONDIÇÕES DE APRESENTAÇÃO\nPlataforma eletrónica utilizada pela entidade adjudicante: VORTAL\nURL para Apresentação: https://community.vortal.biz/public/\nAdmissibilidade da apresentação de propostas variantes: Não autorizado\nPrazo para apresentação das candidaturas: 23-09-2025 23:59\nRequisitos mínimos \nRequisitos mínimos de capacidade técnica: Possuir certificação ISO/IEC 20000-1:2018 e NP 4457 (IDI – Investigação, Desenvolvimento e Inovação); Possuir certificação ISO/IEC 27001:2022 (Sistemas de Gestão de Segurança da Informação) Possuir credenciação de segurança, no grau SECRETO, pelo Gabinete Nacional de Segurança; Possuir mais de três anos de experiência em softwares e plataformas na área da justiça; Possuir recursos humanos dotados com Certificação IPMA Level D – Certified Project Management Associate. Possuir software de faturação certificado pela Autoridade Tributária; Possuir experiência comprovada de integrações desenvolvidas com:   i.    Serviços da área da justiça (pelo menos uma das seguintes entidades ou de outras equiparadas):                1 - CITIUS (exemplo: processos de múltiplas tipológicas, Exec, EQC, Balcão Nacional de Arrendamentos);                2 - IRN – Instituto dos Registos e Notariado (exemplo: penhora de automóveis, consultas no Registo Automóvel, no Instituto dos Registos e do Notariado, I.P. (IRN), Registo Nacional de Pessoas Coletivas (RNPC), registo comercial, registo predial, registo predial, registo automóvel, registo de execuções);                3 - Tribunais (exemplo: distribuição de processos),                4 - SIEJ – Sistema de Informação das Estatísticas da Justiça (exemplo: Estatísticas da Justiça); 5 - Tribunal de Contas (exemplo: prestação de contas); ii.  Sistemas de Finanças (pelo menos uma das seguintes entidades ou de outras equiparadas): 1.            Autoridade Tributária (exemplo: Consultas faturação/SAFT, SAFT-PT, guias de expedição, remessa, transporte, IMT, Modelo 11, DMIS – Declaração Mensal do Imposto selo, consulta NIF/nome); 2.            Banco de Portugal (exemplo: consultas, extratos e conciliação bancária, sistema de prevenção de branqueamento de capitais); 3.            IGCP – Agência de Gestão da Tesouraria e da Dívida Pública (exemplo: Documento único de Cobrança – emissão e pagamento, recebimento de valores penhorados); 4.            CNP – Centro Nacional de Pensões (exemplo: recebimento de valores penhorados); iii. Outras entidades (pelo menos uma das seguintes ou de outras equiparadas):                                                                            1.  AMA – Agência para a Modernização Administrativa , I.P. (exemplo: Chave Móvel Digital, autenticação.gov.pt, ePortugal, certidão permanente de registo comercial); 2.  Comissão Europeia (exemplo: Vies-VAT Information Exchange System); 3.  Entidades bancárias nacionais (exemplo: faturação de taxas de pedidos de penhoras bancárias);\nRequisitos mínimos de capacidade financeira: Conforme as peças do procedimento\nPrazo durante o qual os concorrentes são obrigados a manter as respetivas propostas: 66 dias a contar do termo do prazo para a apresentação das propostas\nIndicação de Subcontratação na Proposta: Inexistência de indicação de subcontratação\n\n14 - PRESTAÇÃO DE CAUÇÃO\nPrestação de caução: Não\n\n15 - FORNECIMENTO DAS PEÇAS DO CONCURSO, APRESENTAÇÃO DE PEDIDOS DE PARTICIPAÇÃO E APRESENTAÇÃO DAS PROPOSTAS\nLink para acesso às peças do concurso (URL): https://community.vortal.biz/Public/public-tender-documents/aGVyMjYvTWhiRUYwUW0xSDhzbDNZWVNlMDh5MHFkZmh4SVlWcVlrWGdOU0tRQWRRQWdtTG1kaUVRWkpuRzVtMURwbmFkTXltaDRNTzJidEZST01KZnc9PVQjeWV2\n\n20 - OUTROS REQUISITOS\nInformação sobre contratos reservados. Aplica-se a contratos reservados (54º-A)? Não\n\n21 - CRITÉRIO DE ADJUDICAÇÃO\nMultifator: Não\nMonofator:\nNome: Outros\nOutro nome: Preço\n\n24 - CONDIÇÕES DO CONTRATO\nFaturação Eletrónica: Permitido\nObrigação de Subcontratação:\nCódigo da Obrigação de Subcontratação: Não é aplicável nenhuma obrigação de subcontratação.\n\n25 - COMPRA PÚBLICA ESTRATÉGICA\nCompra Pública Estratégica: Inexistência de contratação pública estratégica\n\n26 - INFORMAÇÕES ADICIONAIS\nContrato adequado para PME: Sim\nCobertura ACP (Acordo dos Contratos Públicos da Organização Mundial do Comércio): Não\n\n27 - IDENTIFICAÇÃO E CONTACTOS DO ÓRGÃO DE RECURSOS ADMINISTRATIVOS\nDesignação: Direção - Ordem dos Notários\nEndereço: Av. Visconde Valmor, n 19 A\nCódigo postal: 1000-290\nLocalidade: Lisboa\nTelefone: +351 213468176\nFax: +351 213468178\nEndereço eletrónico: geral@notarios.pt\n\n28 - IDENTIFICAÇÃO DO(S) AUTOR(ES) DE ANÚNCIO\nNome: João Pina\nCargo: Coordenador do Departamento Tecnológico\n419547775",
    "nipc": "507680316",
    "distrito": "Lisboa",
    "concelho": "Lisboa",
    "freguesia": "Freguesia de Avenidas Novas",
    "site": null,
    "email": "geral@notarios.pt",
    "designacao_contrato": "AQUISIÇÃO DO DESENVOLVIMENTO DE NOVA PLATAFORMA DE ARQUIVO ELETRÓNICO E RESPETIVOS SERVIÇOS DE MANUTENÇÃO",
    "descricao": "AQUISIÇÃO DO DESENVOLVIMENTO DE NOVA PLATAFORMA DE ARQUIVO ELETRÓNICO E",
    "preco_base": "220.000,00 EUR",
    "prazo_execucao": "3 ANOS",
    "prazo_apresentacao_propostas": null,
    "fundos_eu": "Não",
    "plataforma_eletronica": "VORTAL",
    "url_procedimento": "https://community.vortal.biz/public/",
    "autor_nome": "João Pina",
    "autor_cargo": "Coordenador do Departamento Tecnológico"
  },
  {
    "numero_procedimento": "N/A",
    "entidade": "SOENPROL Soc. de Ensino Profissional, Ldª",
    "link": "https://diariodarepublica.pt/dr/detalhe/contrato-publico/24604-935742314",
    "detalhes_completos": "1 - IDENTIFICAÇÃO E CONTACTOS DA ENTIDADE ADJUDICANTE\nDesignação da entidade adjudicante: SOENPROL Soc. de Ensino Profissional, Ldª\nNIPC: 504534440\nEndereço: R. do Matadouro 4\nCódigo postal: 3080-014\nLocalidade: Figueira da Foz\nPaís: Portugal\nNUT III: PT187\nDistrito: Coimbra\nConcelho: Figueira da Foz\nFreguesia: Freguesia de São Pedro - Figueira da Foz\nTelefone: 233411202\nFax: 233411202\nEndereço da Entidade (URL): www.epff-intep.pt\nEndereço Eletrónico: intep@sgps.mail.pt\nFunção da Organização: Adquirente\nNorma jurídica da Entidade Adjudicante: Autoridade da administração central\nÁrea de atividade da Autoridade Adjudicante: Assuntos económicos\n\n2 - JORNAL OFICIAL DA UNIÃO EUROPEIA\nO procedimento a que este anúncio diz respeito também é publicitado no Jornal Oficial da União Europeia? Sim\n\n3 - AVISO\nModelo de Anúncio: Concurso público\nData de Envio do Anúncio: 15-09-2025\n\n5 - PROCESSO\nTipo de Procedimento: Concurso público\nPreço base do procedimento: Sim\nValor do preço base do procedimento: 751.871,82 EUR\nProcedimento com lotes? Sim\nNº Máx. de Lotes Autorizado: 3\nNúmero máximo de lotes que podem ser adjudicados a um concorrente: 3\n\n6 - OBJETO DO CONTRATO\nNúmero de referência interna: INTEP_CTE_CPi03/2526\nDesignação do contrato: Aquisição e instalação de equipamento didático, mobiliário e servidores, para a escola Instituto Tecnológico e Profissional (INTEP), Projeto nº 4180-CTE Informática.\nDescrição: Aquisição e instalação de equipamento didático, mobiliário e servidores, para a escola Instituto Tecnológico e Profissional (INTEP), Projeto nº 4180-CTE Informática.\nOpções: Não\nTipo de Contrato Principal: Aquisição de Bens Móveis\nTipo de Contrato: Aquisição de Bens Móveis\nClassificação CPV (Vocabulário Comum para os Contratos Públicos)\nObjeto principal\nVocabulário Principal: 39162000\nPreço base s/IVA: 505.437,72 EUR\nObjeto Complementar\nVocabulário Principal: 39160000\nPreço base s/IVA: 67.320,60 EUR\nObjeto Complementar\nVocabulário Principal: 48822000\nPreço base s/IVA: 179.113,50 EUR\nLotes: \nNº: LOT-0001\nDescrição do Lote: Lote 1 - Equipamento didático\nPreço base s/IVA: 505.437,72 EUR\nClassificação CPV (Vocabulário Comum para os Contratos Públicos)\nObjeto principal\nVocabulário Principal: 39162000\nNº: LOT-0002\nDescrição do Lote: Lote 2 - Mobiliário\nPreço base s/IVA: 67.320,60 EUR\nClassificação CPV (Vocabulário Comum para os Contratos Públicos)\nObjeto principal\nVocabulário Principal: 39160000\nNº: LOT-0003\nDescrição do Lote: Lote 3 - Servidores\nPreço base s/IVA: 179.113,50 EUR\nClassificação CPV (Vocabulário Comum para os Contratos Públicos)\nObjeto principal\nVocabulário Principal: 48822000\n\n7 - INDICAÇÕES ADICIONAIS\nO contrato envolve aquisição conjunta (satisfação de várias entidades)? Não\nO contrato é adjudicado por uma central de compras? Não\n\n8 - TÉCNICAS\nO concurso destina-se à celebração de um acordo-quadro? Inexistência de acordo-quadro\nÉ utilizado um leilão eletrónico? Não\nÉ adotada uma fase de negociação? Não\nSistema de Aquisição Dinâmico: Inexistência de sistema de aquisição dinâmico\n\n9 - LOCAL DA EXECUÇÃO DO CONTRATO\nLOCAL DA EXECUÇÃO DO CONTRATO (PROCEDIMENTO)\nLOCAL DA EXECUÇÃO DO CONTRATO (LOTE)\nIdentificador do Lote: LOT-0001\nPaís: Portugal\nNUT III: PT16E\nLocalidade: Figueira da Foz\nDistrito: Coimbra\nConcelho: Figueira da Foz\nFreguesia: Freguesia de Buarcos e São Julião\nIdentificador do Lote: LOT-0002\nPaís: Portugal\nNUT III: PT16E\nLocalidade: Figueira da Foz\nDistrito: Coimbra\nConcelho: Figueira da Foz\nFreguesia: Freguesia de Buarcos e São Julião\nIdentificador do Lote: LOT-0003\nPaís: Portugal\nNUT III: PT16E\nLocalidade: Figueira da Foz\nDistrito: Coimbra\nConcelho: Figueira da Foz\nFreguesia: Freguesia de Buarcos e São Julião\n\n10 - PRAZO DE EXECUÇÃO DO CONTRATO\nIdentificador do Lote: LOT-0001\nPrazo de execução do contrato: 60 DIAS\nPrevisão de renovações: Não\nIdentificador do Lote: LOT-0002\nPrazo de execução do contrato: 60 DIAS\nPrevisão de renovações: Não\nIdentificador do Lote: LOT-0003\nPrazo de execução do contrato: 60 DIAS\nPrevisão de renovações: Não\n\n11 - FUNDOS EU\nIdentificador do Lote: LOT-0001; LOT-0002; LOT-0003\nTêm fundos EU? Sim\n\n12 - DOCUMENTOS DE HABILITAÇÃO\nHabilitação para o exercício da atividade profissional: Não\n\n13 - CONDIÇÕES DE APRESENTAÇÃO\nPlataforma eletrónica utilizada pela entidade adjudicante: ANOGOV\nURL para Apresentação: https://www.anogov.com/me-intep/faces/\nAdmissibilidade da apresentação de propostas variantes: Não autorizado\nPrazo para apresentação das propostas: 15-10-2025 23:59\nPrazo durante o qual os concorrentes são obrigados a manter as respetivas propostas: 66 dias a contar do termo do prazo para a apresentação das propostas\nApresentação de Catálogo Eletrónico: Necessário\nIndicação de Subcontratação na Proposta: A parte do contrato que o proponente tenciona subcontratar\n\n14 - PRESTAÇÃO DE CAUÇÃO\nPrestação de caução: Sim\nPercentagem: 3%\nDescrição da Garantia Exigida: Depósito em dinheiro ou em títulos emitidos ou garantidos pelo Estado ou mediante garantia bancária, ou ainda por seguro-caução.\n\n15 - FORNECIMENTO DAS PEÇAS DO CONCURSO, APRESENTAÇÃO DE PEDIDOS DE PARTICIPAÇÃO E APRESENTAÇÃO DAS PROPOSTAS\nLink para acesso às peças do concurso (URL): https://www.anogov.com/me-intep/faces/app/acessoDocs.jsp?codigoAcesso=aVKUnOrk3BIZSlFOblygb2eKczFNtKLDzYy2XDxpgZ2X81T43B\n\n20 - OUTROS REQUISITOS\nIdentificador do Lote: LOT-0001; LOT-0002; LOT-0003\nInformação sobre contratos reservados. Aplica-se a contratos reservados (54º-A)? Não\n\n21 - CRITÉRIO DE ADJUDICAÇÃO\nO Critério de adjudicação é diferenciado por lote? Não\nMultifator: Não\nMonofator:\nNome: Preço\n\n24 - CONDIÇÕES DO CONTRATO\nIdentificador do Lote: LOT-0001; LOT-0002; LOT-0003\nFaturação Eletrónica: Necessário\nObrigação de Subcontratação:\nCódigo da Obrigação de Subcontratação: Não é aplicável nenhuma obrigação de subcontratação.\n\n25 - COMPRA PÚBLICA ESTRATÉGICA\nCompra Pública Estratégica: Inexistência de contratação pública estratégica\n\n26 - INFORMAÇÕES ADICIONAIS\nIdentificador do Lote: LOT-0001\nContrato adequado para PME: Sim\nCobertura ACP (Acordo dos Contratos Públicos da Organização Mundial do Comércio): Não\nIdentificador do Lote: LOT-0002\nContrato adequado para PME: Sim\nCobertura ACP (Acordo dos Contratos Públicos da Organização Mundial do Comércio): Não\nIdentificador do Lote: LOT-0003\nContrato adequado para PME: Sim\nCobertura ACP (Acordo dos Contratos Públicos da Organização Mundial do Comércio): Não\n\n27 - IDENTIFICAÇÃO E CONTACTOS DO ÓRGÃO DE RECURSOS ADMINISTRATIVOS\nDesignação: SOENPROL - Sociedade de Ensino Profissional, Lda.\nEndereço: Rua do Matadouro, nº 22\nCódigo postal: 3080-014\nLocalidade: Figueira da Foz\nEndereço eletrónico: contratacao@intep.pt\n\n28 - IDENTIFICAÇÃO DO(S) AUTOR(ES) DE ANÚNCIO\nNome: Nuno Madama\nCargo: Gerente\n419537122",
    "nipc": "504534440",
    "distrito": "Coimbra",
    "concelho": "Figueira da Foz",
    "freguesia": "Freguesia de São Pedro - Figueira da Foz",
    "site": "www.epff-intep.pt",
    "email": "intep@sgps.mail.pt",
    "designacao_contrato": "Aquisição e instalação de equipamento didático, mobiliário e servidores, para a escola Instituto Tecnológico e Profissional (INTEP), Projeto nº 4180-CTE Informática.",
    "descricao": "Aquisição e instalação de equipamento didático, mobiliário e servidores, para a escola Instituto Tecnológico e Profissional (INTEP), Projeto nº 4180-CTE Informática.",
    "preco_base": "505.437,72 EUR",
    "prazo_execucao": "60 DIAS",
    "prazo_apresentacao_propostas": "15-10-2025 23:59",
    "fundos_eu": "Sim",
    "plataforma_eletronica": "ANOGOV",
    "url_procedimento": "https://www.anogov.com/me-intep/faces/",
    "autor_nome": "Nuno Madama",
    "autor_cargo": "Gerente"
  },
  {
    "numero_procedimento": "N/A",
    "entidade": "Autoridade da Concorrência (AdC)",
    "link": "https://diariodarepublica.pt/dr/detalhe/contrato-publico/24605-935742315",
    "detalhes_completos": "1 - IDENTIFICAÇÃO E CONTACTOS DA ENTIDADE ADJUDICANTE\nDesignação da entidade adjudicante: Autoridade da Concorrência (AdC)\nNIPC: 506557057\nServiço/Órgão/Pessoa de contacto: Unidade de Recursos Financeiros e Patrimoniais\nEndereço: Avenida de Berna, n.º 19\nCódigo postal: 1050-037\nLocalidade: Lisboa\nPaís: Portugal\nNUT III: PT170\nDistrito: Lisboa\nConcelho: Lisboa\nFreguesia: Freguesia de Campolide\nTelefone: 217902000\nFax: 217902099\nEndereço da Entidade (URL): www.concorrencia.pt\nEndereço Eletrónico: adc@concorrencia.pt\neDelivery Gateway (URL): https://www.acingov.pt\nFunção da Organização: Adquirente\nNorma jurídica da Entidade Adjudicante: Organismo de direito público\nÁrea de atividade da Autoridade Adjudicante: Serviços públicos das administrações públicas\n\n2 - JORNAL OFICIAL DA UNIÃO EUROPEIA\nO procedimento a que este anúncio diz respeito também é publicitado no Jornal Oficial da União Europeia? Não\n\n3 - AVISO\nModelo de Anúncio: Concurso público\nData de Envio do Anúncio: 17-09-2025\n\n5 - PROCESSO\nTipo de Procedimento: Concurso público\nPreço base do procedimento: Sim\nValor do preço base do procedimento: 140.000,00 EUR\nProcedimento com lotes? Não\n\n6 - OBJETO DO CONTRATO\nNúmero de referência interna: 152/URF/2025\nDesignação do contrato: Aquisição e implementação da Infraestrutura de Rede e de Segurança\nDescrição: Aquisição e Implementação da Infraestrutura de Rede e de Segurança,\nTipo de Contrato Principal: Aquisição de Bens Móveis\nTipo de Contrato: Aquisição de Bens Móveis\nClassificação CPV (Vocabulário Comum para os Contratos Públicos)\nObjeto principal\nVocabulário Principal: 32410000\nPreço base s/IVA: 140.000,00 EUR\n\n7 - INDICAÇÕES ADICIONAIS\nO contrato envolve aquisição conjunta (satisfação de várias entidades)? Não\nO contrato é adjudicado por uma central de compras? Não\n\n8 - TÉCNICAS\nO concurso destina-se à celebração de um acordo-quadro? Inexistência de acordo-quadro\nÉ utilizado um leilão eletrónico? Não\nÉ adotada uma fase de negociação? Não\nSistema de Aquisição Dinâmico: Inexistência de sistema de aquisição dinâmico\n\n9 - LOCAL DA EXECUÇÃO DO CONTRATO\nLOCAL DA EXECUÇÃO DO CONTRATO (PROCEDIMENTO)\nPaís: Portugal\nNUT III: PT170\nLocalidade: Freguesia de Campolide\nDistrito: Lisboa\nConcelho: Lisboa\nFreguesia: Freguesia de Campolide\n\n10 - PRAZO DE EXECUÇÃO DO CONTRATO\nPrazo de execução do contrato: 36 MESES\nPrevisão de renovações: Não\n\n11 - FUNDOS EU\nTêm fundos EU? Não\n\n12 - DOCUMENTOS DE HABILITAÇÃO\nHabilitação para o exercício da atividade profissional: Não\n\n13 - CONDIÇÕES DE APRESENTAÇÃO\nPlataforma eletrónica utilizada pela entidade adjudicante: ACIN\nURL para Apresentação: https://www.acingov.pt\nAdmissibilidade da apresentação de propostas variantes: Não autorizado\nPrazo para apresentação das propostas: 29-09-2025 23:59\nPrazo durante o qual os concorrentes são obrigados a manter as respetivas propostas: 120 dias a contar do termo do prazo para a apresentação das propostas\nIndicação de Subcontratação na Proposta: Inexistência de indicação de subcontratação\n\n14 - PRESTAÇÃO DE CAUÇÃO\nPrestação de caução: Não\n\n15 - FORNECIMENTO DAS PEÇAS DO CONCURSO, APRESENTAÇÃO DE PEDIDOS DE PARTICIPAÇÃO E APRESENTAÇÃO DAS PROPOSTAS\nLink para acesso às peças do concurso (URL): https://www.acingov.pt/acingovprod/2/zonaPublica/zona_publica_c/donwloadProcedurePiece/OTc4ODY0\n\n20 - OUTROS REQUISITOS\nInformação sobre contratos reservados. Aplica-se a contratos reservados (54º-A)? Não\n\n21 - CRITÉRIO DE ADJUDICAÇÃO\nMultifator: Sim\nFator: \nNome: Outros\nOutro Nome: Custo anual de manutenção, suporte técnico, licenciamentos e subscrições associadas à solução proposta\nPonderação: 40%\nSubfatores: Não\nFator: \nNome: Preço\nPonderação: 60%\nSubfatores: Não\n\n24 - CONDIÇÕES DO CONTRATO\nFaturação Eletrónica: Permitido\nObrigação de Subcontratação:\nCódigo da Obrigação de Subcontratação: Não é aplicável nenhuma obrigação de subcontratação.\n\n25 - COMPRA PÚBLICA ESTRATÉGICA\nCompra Pública Estratégica: Inexistência de contratação pública estratégica\n\n26 - INFORMAÇÕES ADICIONAIS\nContrato adequado para PME: Não\nCobertura ACP (Acordo dos Contratos Públicos da Organização Mundial do Comércio): Não\n\n27 - IDENTIFICAÇÃO E CONTACTOS DO ÓRGÃO DE RECURSOS ADMINISTRATIVOS\nDesignação: Conselho de Administração da Autoridade da Concorrência\nEndereço: Avenida de Berna, n.º 19\nCódigo postal: 1050-037\nLocalidade: Avenida de Berna, 19, 1050-037 Lisboa\nTelefone: 217902094\nFax: \nEndereço eletrónico: adc@concorrencia.pt\n\n28 - IDENTIFICAÇÃO DO(S) AUTOR(ES) DE ANÚNCIO\nNome: Maria Cristina Chora Fernandes\nCargo: Chefe de Unidade\n419547856",
    "nipc": "506557057",
    "distrito": "Lisboa",
    "concelho": "Lisboa",
    "freguesia": "Freguesia de Campolide",
    "site": "www.concorrencia.pt",
    "email": "adc@concorrencia.pt",
    "designacao_contrato": "Aquisição e implementação da Infraestrutura de Rede e de Segurança",
    "descricao": "Aquisição e Implementação da Infraestrutura de Rede e de Segurança,",
    "preco_base": "140.000,00 EUR",
    "prazo_execucao": "36 MESES",
    "prazo_apresentacao_propostas": "29-09-2025 23:59",
    "fundos_eu": "Não",
    "plataforma_eletronica": "ACIN",
    "url_procedimento": "https://www.acingov.pt",
    "autor_nome": "Maria Cristina Chora Fernandes",
    "autor_cargo": "Chefe de Unidade"
  },
  {
    "numero_procedimento": "N/A",
    "entidade": "SILOTAGUS, S.A.",
    "link": "https://diariodarepublica.pt/dr/detalhe/contrato-publico/24606-935742316",
    "detalhes_completos": "1 - IDENTIFICAÇÃO E CONTACTOS DA ENTIDADE ADJUDICANTE\nDesignação da entidade adjudicante: SILOTAGUS, S.A.\nNIPC: 518730581\nEndereço: Terminal Portuário do Beato, Rua da Cintura do Porto de Lisboa\nCódigo postal: 1950-318\nLocalidade: Lisboa\nPaís: Portugal\nNUT III: PT170\nDistrito: Lisboa\nConcelho: Lisboa\nFreguesia: Freguesia de Beato\nTelefone: 213923200\nFax: 213923342\nEndereço da Entidade (URL): www.silopor.pt\nEndereço Eletrónico: cristina.matos@silotagus.pt\neDelivery Gateway (URL): https://community.vortal.biz/public/\nFunção da Organização: Adquirente\nNorma jurídica da Entidade Adjudicante: Autoridade da administração central\nÁrea de atividade da Autoridade Adjudicante: Assuntos económicos\n\n2 - JORNAL OFICIAL DA UNIÃO EUROPEIA\nO procedimento a que este anúncio diz respeito também é publicitado no Jornal Oficial da União Europeia? Sim\n\n3 - AVISO\nModelo de Anúncio: Concurso público\nData de Envio do Anúncio: 15-09-2025\n\n5 - PROCESSO\nTipo de Procedimento: Concurso público\nPreço base do procedimento: Sim\nValor do preço base do procedimento: 220.000,00 EUR\nProcedimento com lotes? Não\n\n6 - OBJETO DO CONTRATO\nNúmero de referência interna: CP042025\nDesignação do contrato: Concurso Público para prestação de serviços de saúde e segurança no trabalho no TPB, TPT e Vale de Figueira da Silotagus, S.A.\nDescrição: Concurso Público para prestação de serviços de saúde e segurança no trabalho no TPB, TPT e Vale de Figueira da Silotagus, S.A.\nOpções: Não\nTipo de Contrato Principal: Aquisição de Serviços\nTipo de Contrato: Aquisição de Serviços\nClassificação CPV (Vocabulário Comum para os Contratos Públicos)\nObjeto principal\nVocabulário Principal: 85100000\nPreço base s/IVA: 220.000,00 EUR\n\n7 - INDICAÇÕES ADICIONAIS\nO contrato envolve aquisição conjunta (satisfação de várias entidades)? Não\nO contrato é adjudicado por uma central de compras? Não\n\n8 - TÉCNICAS\nO concurso destina-se à celebração de um acordo-quadro? Inexistência de acordo-quadro\nÉ utilizado um leilão eletrónico? Não\nÉ adotada uma fase de negociação? Não\nSistema de Aquisição Dinâmico: Inexistência de sistema de aquisição dinâmico\n\n9 - LOCAL DA EXECUÇÃO DO CONTRATO\nLOCAL DA EXECUÇÃO DO CONTRATO (PROCEDIMENTO)\nPaís: Portugal\nNUT III: PT170\nLocalidade: Lisboa\nDistrito: Lisboa\nConcelho: Lisboa\nFreguesia: Freguesia de Beato\n\n10 - PRAZO DE EXECUÇÃO DO CONTRATO\nPrazo de execução do contrato: 3 ANOS\nPrevisão de renovações: Sim\nIndicar número máximo de renovações: 2\nPrazo de renovações diferente do prazo inicial: Não\n\n11 - FUNDOS EU\nTêm fundos EU? Não\n\n12 - DOCUMENTOS DE HABILITAÇÃO\nHabilitação para o exercício da atividade profissional: Não\n\n13 - CONDIÇÕES DE APRESENTAÇÃO\nPlataforma eletrónica utilizada pela entidade adjudicante: VORTAL\nURL para Apresentação: https://community.vortal.biz/public/\nAdmissibilidade da apresentação de propostas variantes: Não autorizado\nPrazo para apresentação das propostas: 20-10-2025 17:00\nPrazo durante o qual os concorrentes são obrigados a manter as respetivas propostas: 66 dias a contar do termo do prazo para a apresentação das propostas\nApresentação de Catálogo Eletrónico: Não autorizado\nIndicação de Subcontratação na Proposta: Inexistência de indicação de subcontratação\n\n14 - PRESTAÇÃO DE CAUÇÃO\nPrestação de caução: Sim\nPercentagem: 5%\nDescrição da Garantia Exigida: Garantia Bancária\n\n15 - FORNECIMENTO DAS PEÇAS DO CONCURSO, APRESENTAÇÃO DE PEDIDOS DE PARTICIPAÇÃO E APRESENTAÇÃO DAS PROPOSTAS\nLink para acesso às peças do concurso (URL): https://community.vortal.biz/Public/public-tender-documents/U2M4cmxqbDc3b0RFcEczLzQ3Y0hLYTRPTHdoRTFkNUdydmN3VEZIOG04eVVxd3lqWmpmSEQ2MzVaMmxhZXVBN056V1JmVnZndVRsVkwwd3BIVHJNQmc9PSFld0t0\n\n20 - OUTROS REQUISITOS\nInformação sobre contratos reservados. Aplica-se a contratos reservados (54º-A)? Não\n\n21 - CRITÉRIO DE ADJUDICAÇÃO\nMultifator: Não\nMonofator:\nNome: Outros\nOutro nome: Preço\n\n24 - CONDIÇÕES DO CONTRATO\nFaturação Eletrónica: Permitido\nObrigação de Subcontratação:\nCódigo da Obrigação de Subcontratação: Não é aplicável nenhuma obrigação de subcontratação.\n\n25 - COMPRA PÚBLICA ESTRATÉGICA\nCompra Pública Estratégica: Inexistência de contratação pública estratégica\n\n26 - INFORMAÇÕES ADICIONAIS\nContrato adequado para PME: Sim\nCobertura ACP (Acordo dos Contratos Públicos da Organização Mundial do Comércio): Não\n\n27 - IDENTIFICAÇÃO E CONTACTOS DO ÓRGÃO DE RECURSOS ADMINISTRATIVOS\nDesignação: SILOTAGUS, S.A.\nEndereço: Terminal Portuário do Beato, Rua da Cintura do Porto de Lisboa\nCódigo postal: 1950-318\nLocalidade: Lisboa\nTelefone: +351 213923200\nFax: +351 213923207\nEndereço eletrónico: daf@silotagus.pt\n\n28 - IDENTIFICAÇÃO DO(S) AUTOR(ES) DE ANÚNCIO\nNome: Cristina Matos\nCargo: Técnica Superior\n419537366",
    "nipc": "518730581",
    "distrito": "Lisboa",
    "concelho": "Lisboa",
    "freguesia": "Freguesia de Beato",
    "site": "www.silopor.pt",
    "email": "cristina.matos@silotagus.pt",
    "designacao_contrato": "Concurso Público para prestação de serviços de saúde e segurança no trabalho no TPB, TPT e Vale de Figueira da Silotagus, S.A.",
    "descricao": "Concurso Público para prestação de serviços de saúde e segurança no trabalho no TPB, TPT e Vale de Figueira da Silotagus, S.A.",
    "preco_base": "220.000,00 EUR",
    "prazo_execucao": "3 ANOS",
    "prazo_apresentacao_propostas": "20-10-2025 17:00",
    "fundos_eu": "Não",
    "plataforma_eletronica": "VORTAL",
    "url_procedimento": "https://community.vortal.biz/public/",
    "autor_nome": "Cristina Matos",
    "autor_cargo": "Técnica Superior"
  },
  {
    "numero_procedimento": "N/A",
    "entidade": "AnÃºncio de procedimento  n.Âº 24607/2025  -  DiÃ¡rio da RepÃºblica n.Âº 180/2025, SÃ©rie II de 2025-09-18",
    "link": "https://diariodarepublica.pt/dr/detalhe/contrato-publico/24607-935742317"
  },
  {
    "numero_procedimento": "N/A",
    "entidade": "Município de Paços de Ferreira",
    "link": "https://diariodarepublica.pt/dr/detalhe/contrato-publico/24608-935742318",
    "detalhes_completos": "1 - IDENTIFICAÇÃO E CONTACTOS DA ENTIDADE ADJUDICANTE\nDesignação da entidade adjudicante: Município de Paços de Ferreira\nNIPC: 502173297\nServiço/Órgão/Pessoa de contacto: Departamento de Organização Administrativa\nEndereço: Praça da República, n.º 46\nCódigo postal: 4590-527\nLocalidade: Paços de Ferreira\nPaís: Portugal\nNUT III: PTZZZ\nDistrito: Todos\nConcelho: Todos\nFreguesia: Todas\nTelefone: 255860700\nFax: 255860734\nEndereço da Entidade (URL): http://www.cm-pacosdeferreira.pt\nEndereço Eletrónico: geral@cm-pacosdeferreira.pt\neDelivery Gateway (URL): https://www.acingov.pt\nFunção da Organização: Adquirente\nNorma jurídica da Entidade Adjudicante: Organismo de direito público\nÁrea de atividade da Autoridade Adjudicante: Serviços públicos das administrações públicas\n\n2 - JORNAL OFICIAL DA UNIÃO EUROPEIA\nO procedimento a que este anúncio diz respeito também é publicitado no Jornal Oficial da União Europeia? Não\n\n3 - AVISO\nModelo de Anúncio: Concurso público\nData de Envio do Anúncio: 17-09-2025\n\n5 - PROCESSO\nTipo de Procedimento: Concurso público\nPreço base do procedimento: Sim\nValor do preço base do procedimento: 22.145,83 EUR\nProcedimento com lotes? Não\n\n6 - OBJETO DO CONTRATO\nNúmero de referência interna: 157/F/2025\nDesignação do contrato: Substituição dos projetores convencionais do Campo de Futebol de Freamunde\nDescrição: Substituição dos projetores convencionais do Campo de Futebol de Freamunde\nTipo de Contrato Principal: Aquisição de Bens Móveis\nTipo de Contrato: Aquisição de Bens Móveis\nClassificação CPV (Vocabulário Comum para os Contratos Públicos)\nObjeto principal\nVocabulário Principal: 31527000\nPreço base s/IVA: 22.145,83 EUR\n\n7 - INDICAÇÕES ADICIONAIS\nO contrato envolve aquisição conjunta (satisfação de várias entidades)? Não\nO contrato é adjudicado por uma central de compras? Não\n\n8 - TÉCNICAS\nO concurso destina-se à celebração de um acordo-quadro? Inexistência de acordo-quadro\nÉ utilizado um leilão eletrónico? Não\nÉ adotada uma fase de negociação? Não\nSistema de Aquisição Dinâmico: Inexistência de sistema de aquisição dinâmico\n\n9 - LOCAL DA EXECUÇÃO DO CONTRATO\nLOCAL DA EXECUÇÃO DO CONTRATO (PROCEDIMENTO)\nPaís: Portugal\nNUT III: PT11C\nLocalidade: Freguesia de Freamunde\nDistrito: Porto\nConcelho: Paços de Ferreira\nFreguesia: Freguesia de Freamunde\n\n10 - PRAZO DE EXECUÇÃO DO CONTRATO\nPrazo de execução do contrato: 40 DIAS\nPrevisão de renovações: Não\n\n11 - FUNDOS EU\nTêm fundos EU? Não\n\n12 - DOCUMENTOS DE HABILITAÇÃO\nHabilitação para o exercício da atividade profissional: Não\n\n13 - CONDIÇÕES DE APRESENTAÇÃO\nPlataforma eletrónica utilizada pela entidade adjudicante: ACIN\nURL para Apresentação: https://www.acingov.pt\nAdmissibilidade da apresentação de propostas variantes: Não autorizado\nPrazo para apresentação das propostas: 23-09-2025 23:59\nPrazo durante o qual os concorrentes são obrigados a manter as respetivas propostas: 66 dias a contar do termo do prazo para a apresentação das propostas\nIndicação de Subcontratação na Proposta: Inexistência de indicação de subcontratação\n\n14 - PRESTAÇÃO DE CAUÇÃO\nPrestação de caução: Não\n\n15 - FORNECIMENTO DAS PEÇAS DO CONCURSO, APRESENTAÇÃO DE PEDIDOS DE PARTICIPAÇÃO E APRESENTAÇÃO DAS PROPOSTAS\nLink para acesso às peças do concurso (URL): https://www.acingov.pt/acingovprod/2/zonaPublica/zona_publica_c/donwloadProcedurePiece/OTc4ODgz\n\n20 - OUTROS REQUISITOS\nInformação sobre contratos reservados. Aplica-se a contratos reservados (54º-A)? Não\n\n21 - CRITÉRIO DE ADJUDICAÇÃO\nMultifator: Não\nMonofator:\nNome: Preço\n\n24 - CONDIÇÕES DO CONTRATO\nFaturação Eletrónica: Permitido\nObrigação de Subcontratação:\nCódigo da Obrigação de Subcontratação: Não é aplicável nenhuma obrigação de subcontratação.\n\n25 - COMPRA PÚBLICA ESTRATÉGICA\nCompra Pública Estratégica: Inexistência de contratação pública estratégica\n\n26 - INFORMAÇÕES ADICIONAIS\nContrato adequado para PME: Sim\nCobertura ACP (Acordo dos Contratos Públicos da Organização Mundial do Comércio): Não\n\n27 - IDENTIFICAÇÃO E CONTACTOS DO ÓRGÃO DE RECURSOS ADMINISTRATIVOS\nDesignação: Departamento de Organização Administrativa\nEndereço: Praça da República, n.º 46\nCódigo postal: 4590-527\nLocalidade: Paços de Ferreira\nTelefone: 255860700\nFax: \nEndereço eletrónico: geral@cm-pacosdeferreira.pt\nPrazo de interposição do recurso: 5 dias\n\n28 - IDENTIFICAÇÃO DO(S) AUTOR(ES) DE ANÚNCIO\nNome: Paulo Jorge Rodrigues Ferreira\nCargo: Presidente da Câmara Municipal\n419547726",
    "nipc": "502173297",
    "distrito": "Todos",
    "concelho": "Todos",
    "freguesia": "Todas",
    "site": "http://www.cm-pacosdeferreira.pt",
    "email": "geral@cm-pacosdeferreira.pt",
    "designacao_contrato": "Substituição dos projetores convencionais do Campo de Futebol de Freamunde",
    "descricao": "Substituição dos projetores convencionais do Campo de Futebol de Freamunde",
    "preco_base": "22.145,83 EUR",
    "prazo_execucao": "40 DIAS",
    "prazo_apresentacao_propostas": "23-09-2025 23:59",
    "fundos_eu": "Não",
    "plataforma_eletronica": "ACIN",
    "url_procedimento": "https://www.acingov.pt",
    "autor_nome": "Paulo Jorge Rodrigues Ferreira",
    "autor_cargo": "Presidente da Câmara Municipal"
  },
  {
    "numero_procedimento": "N/A",
    "entidade": "Serviços Municipalizados de Transportes Urbanos de Coimbra",
    "link": "https://diariodarepublica.pt/dr/detalhe/contrato-publico/24574-935747877",
    "detalhes_completos": "1 - IDENTIFICAÇÃO E CONTACTOS DA ENTIDADE ADJUDICANTE\nDesignação da entidade adjudicante: Serviços Municipalizados de Transportes Urbanos de Coimbra\nNIPC: 680015965\nEndereço: Guarda Inglesa - Apartado 5015 - EC ROSSIO\nCódigo postal: 3041-901\nLocalidade: Coimbra\nPaís: Portugal\nNUT III: PT16E\nDistrito: Coimbra\nConcelho: Coimbra\nFreguesia: União das Freguesias de Santa Clara e Castelo Viegas\nTelefone: 239801100\nFax: 239440348\nEndereço da Entidade (URL): www.smtuc.pt\nEndereço Eletrónico: geral@smtuc.pt\neDelivery Gateway (URL): https://community.vortal.biz/public/\nFunção da Organização: Adquirente\nNorma jurídica da Entidade Adjudicante: Organismo de direito público\nÁrea de atividade da Autoridade Adjudicante: Serviços públicos das administrações públicas\n\n2 - JORNAL OFICIAL DA UNIÃO EUROPEIA\nO procedimento a que este anúncio diz respeito também é publicitado no Jornal Oficial da União Europeia? Não\n\n3 - AVISO\nModelo de Anúncio: Concurso público\nData de Envio do Anúncio: 17-09-2025\n\n5 - PROCESSO\nTipo de Procedimento: Concurso público\nPreço base do procedimento: Sim\nValor do preço base do procedimento: 50.000,00 EUR\nProcedimento com lotes? Não\n\n6 - OBJETO DO CONTRATO\nNúmero de referência interna: CP3/8/2025\nDesignação do contrato: Concurso Público Ref.ª CP3/8/2025 – Prestação de serviço de reparação de caixas de velocidades da frota de viaturas (autocarros e miniautocarros) dos SMTUC. \nDescrição: Prestação de serviço de reparação de caixas de velocidades da frota de viaturas (autocarros e miniautocarros) dos SMTUC. \nTipo de Contrato Principal: Aquisição de Serviços\nTipo de Contrato: Aquisição de Serviços\nClassificação CPV (Vocabulário Comum para os Contratos Públicos)\nObjeto principal\nVocabulário Principal: 50113000\nPreço base s/IVA: 50.000,00 EUR\n\n7 - INDICAÇÕES ADICIONAIS\nO contrato envolve aquisição conjunta (satisfação de várias entidades)? Não\nO contrato é adjudicado por uma central de compras? Não\n\n8 - TÉCNICAS\nO concurso destina-se à celebração de um acordo-quadro? Inexistência de acordo-quadro\nÉ utilizado um leilão eletrónico? Não\nÉ adotada uma fase de negociação? Não\nSistema de Aquisição Dinâmico: Inexistência de sistema de aquisição dinâmico\n\n9 - LOCAL DA EXECUÇÃO DO CONTRATO\nLOCAL DA EXECUÇÃO DO CONTRATO (PROCEDIMENTO)\nPaís: Portugal\nNUT III: PT16E\nLocalidade: Coimbra\nDistrito: Coimbra\nConcelho: Coimbra\nFreguesia: União das Freguesias de Santa Clara e Castelo Viegas\n\n10 - PRAZO DE EXECUÇÃO DO CONTRATO\nPrazo de execução do contrato: 24 MESES\nPrevisão de renovações: Não\n\n11 - FUNDOS EU\nTêm fundos EU? Não\n\n12 - DOCUMENTOS DE HABILITAÇÃO\nHabilitação para o exercício da atividade profissional: Sim\nTipo: Outros\nDescrição - Outros: Não aplicável.\nDescrição: Não aplicável a aptidão para o exercício da atividade profissional. \n\n13 - CONDIÇÕES DE APRESENTAÇÃO\nPlataforma eletrónica utilizada pela entidade adjudicante: VORTAL\nURL para Apresentação: https://community.vortal.biz/public/\nAdmissibilidade da apresentação de propostas variantes: Não autorizado\nPrazo para apresentação das propostas: 29-09-2025 23:59\nPrazo durante o qual os concorrentes são obrigados a manter as respetivas propostas: 132 dias a contar do termo do prazo para a apresentação das propostas\nIndicação de Subcontratação na Proposta: Inexistência de indicação de subcontratação\n\n14 - PRESTAÇÃO DE CAUÇÃO\nPrestação de caução: Não\n\n15 - FORNECIMENTO DAS PEÇAS DO CONCURSO, APRESENTAÇÃO DE PEDIDOS DE PARTICIPAÇÃO E APRESENTAÇÃO DAS PROPOSTAS\nLink para acesso às peças do concurso (URL): https://community.vortal.biz/Public/public-tender-documents/cFhPZjUyaFdWcm1LNnRoL0JabmRoNENOb2xSNGZsTkczNlR3MERuREZNTVJHZVZhdWc5WXc3SjNJK2JqMEdRb2hGdzVVVUJiWDlkVy9kd1lVRE42MHc9PVRUX2xq\n\n20 - OUTROS REQUISITOS\nInformação sobre contratos reservados. Aplica-se a contratos reservados (54º-A)? Não\n\n21 - CRITÉRIO DE ADJUDICAÇÃO\nMultifator: Não\nMonofator:\nNome: Preço\n\n24 - CONDIÇÕES DO CONTRATO\nFaturação Eletrónica: Permitido\nObrigação de Subcontratação:\nCódigo da Obrigação de Subcontratação: Não é aplicável nenhuma obrigação de subcontratação.\n\n25 - COMPRA PÚBLICA ESTRATÉGICA\nCompra Pública Estratégica: Inexistência de contratação pública estratégica\n\n26 - INFORMAÇÕES ADICIONAIS\nContrato adequado para PME: Sim\nCobertura ACP (Acordo dos Contratos Públicos da Organização Mundial do Comércio): Não\n\n27 - IDENTIFICAÇÃO E CONTACTOS DO ÓRGÃO DE RECURSOS ADMINISTRATIVOS\nDesignação: Câmara Municipal de Coimbra\nEndereço: Praça 8.º de Maio\nCódigo postal: 3000-300\nLocalidade: Coimbra\nTelefone: +351 239857500\nFax: +351 239800114\nEndereço eletrónico: geral@cm-coimbra.pt\n\n28 - IDENTIFICAÇÃO DO(S) AUTOR(ES) DE ANÚNCIO\nNome: Jorge Miguel da Silva de Jesus\nCargo: Presidente do Conselho de Administração dos SMTUC\n419545247",
    "nipc": "680015965",
    "distrito": "Coimbra",
    "concelho": "Coimbra",
    "freguesia": "União das Freguesias de Santa Clara e Castelo Viegas",
    "site": "www.smtuc.pt",
    "email": "geral@smtuc.pt",
    "designacao_contrato": "Concurso Público Ref.ª CP3/8/2025 – Prestação de serviço de reparação de caixas de velocidades da frota de viaturas (autocarros e miniautocarros) dos SMTUC.",
    "descricao": "Prestação de serviço de reparação de caixas de velocidades da frota de viaturas (autocarros e miniautocarros) dos SMTUC.",
    "preco_base": "50.000,00 EUR",
    "prazo_execucao": "24 MESES",
    "prazo_apresentacao_propostas": "29-09-2025 23:59",
    "fundos_eu": "Não",
    "plataforma_eletronica": "VORTAL",
    "url_procedimento": "https://community.vortal.biz/public/",
    "autor_nome": "Jorge Miguel da Silva de Jesus",
    "autor_cargo": "Presidente do Conselho de Administração dos SMTUC"
  },
  {
    "numero_procedimento": "N/A",
    "entidade": "Serviços Municipalizados de Transportes Urbanos de Coimbra",
    "link": "https://diariodarepublica.pt/dr/detalhe/contrato-publico/24575-935747878",
    "detalhes_completos": "1 - IDENTIFICAÇÃO E CONTACTOS DA ENTIDADE ADJUDICANTE\nDesignação da entidade adjudicante: Serviços Municipalizados de Transportes Urbanos de Coimbra\nNIPC: 680015965\nEndereço: Guarda Inglesa - Apartado 5015 - EC ROSSIO\nCódigo postal: 3041-901\nLocalidade: Coimbra\nPaís: Portugal\nNUT III: PT16E\nDistrito: Coimbra\nConcelho: Coimbra\nFreguesia: União das Freguesias de Santa Clara e Castelo Viegas\nTelefone: 239801100\nFax: 239440348\nEndereço da Entidade (URL): www.smtuc.pt\nEndereço Eletrónico: geral@smtuc.pt\neDelivery Gateway (URL): https://community.vortal.biz/public/\nFunção da Organização: Adquirente\nNorma jurídica da Entidade Adjudicante: Organismo de direito público\nÁrea de atividade da Autoridade Adjudicante: Serviços públicos das administrações públicas\n\n2 - JORNAL OFICIAL DA UNIÃO EUROPEIA\nO procedimento a que este anúncio diz respeito também é publicitado no Jornal Oficial da União Europeia? Não\n\n3 - AVISO\nModelo de Anúncio: Concurso público\nData de Envio do Anúncio: 17-09-2025\n\n5 - PROCESSO\nTipo de Procedimento: Concurso público\nPreço base do procedimento: Sim\nValor do preço base do procedimento: 50.975,70 EUR\nProcedimento com lotes? Sim\nNº Máx. de Lotes Autorizado: 3\nNúmero máximo de lotes que podem ser adjudicados a um concorrente: 3\n\n6 - OBJETO DO CONTRATO\nNúmero de referência interna: CP3/53/2025\nDesignação do contrato: Concurso Público Ref.ª CP3/53/2025 – Fornecimento contínuo de material de stock OEM (original) para autocarros Mercedes-Benz. \nDescrição: Fornecimento contínuo de material de stock OEM (original) para autocarros Mercedes-Benz. \nTipo de Contrato Principal: Aquisição de Bens Móveis\nTipo de Contrato: Aquisição de Bens Móveis\nClassificação CPV (Vocabulário Comum para os Contratos Públicos)\nObjeto principal\nVocabulário Principal: 34300000\nPreço base s/IVA: 50.975,70 EUR\nLotes: \nNº: LOT-0001\nDescrição do Lote: Material pneumático/Travões\nPreço base s/IVA: 25.514,65 EUR\nClassificação CPV (Vocabulário Comum para os Contratos Públicos)\nObjeto principal\nVocabulário Principal: 34300000\nNº: LOT-0002\nDescrição do Lote: Material de motor\nPreço base s/IVA: 15.827,71 EUR\nClassificação CPV (Vocabulário Comum para os Contratos Públicos)\nObjeto principal\nVocabulário Principal: 34300000\nNº: LOT-0003\nDescrição do Lote: Material de carroçaria e chassi\nPreço base s/IVA: 9.633,34 EUR\nClassificação CPV (Vocabulário Comum para os Contratos Públicos)\nObjeto principal\nVocabulário Principal: 34300000\n\n7 - INDICAÇÕES ADICIONAIS\nO contrato envolve aquisição conjunta (satisfação de várias entidades)? Não\nO contrato é adjudicado por uma central de compras? Não\n\n8 - TÉCNICAS\nO concurso destina-se à celebração de um acordo-quadro? Inexistência de acordo-quadro\nÉ utilizado um leilão eletrónico? Não\nÉ adotada uma fase de negociação? Não\nSistema de Aquisição Dinâmico: Inexistência de sistema de aquisição dinâmico\n\n9 - LOCAL DA EXECUÇÃO DO CONTRATO\nLOCAL DA EXECUÇÃO DO CONTRATO (PROCEDIMENTO)\nPaís: Portugal\nNUT III: PT16E\nLocalidade: Coimbra\nDistrito: Coimbra\nConcelho: Coimbra\nFreguesia: União das Freguesias de Santa Clara e Castelo Viegas\nLOCAL DA EXECUÇÃO DO CONTRATO (LOTE)\nIdentificador do Lote: LOT-0001; LOT-0002; LOT-0003\nPaís: Portugal\nNUT III: PT16E\nLocalidade: Coimbra\nDistrito: Coimbra\nConcelho: Coimbra\nFreguesia: União das Freguesias de Santa Clara e Castelo Viegas\n\n10 - PRAZO DE EXECUÇÃO DO CONTRATO\nIdentificador do Lote: LOT-0001; LOT-0002; LOT-0003\nPrazo de execução do contrato: 12 MESES\nPrevisão de renovações: Não\n\n11 - FUNDOS EU\nIdentificador do Lote: LOT-0001; LOT-0002; LOT-0003\nTêm fundos EU? Não\n\n12 - DOCUMENTOS DE HABILITAÇÃO\nHabilitação para o exercício da atividade profissional: Sim\nTipo: Outros\nDescrição - Outros: Não aplicável.\nDescrição: Não aplicável a aptidão para o exercício da atividade profissional. \n\n13 - CONDIÇÕES DE APRESENTAÇÃO\nPlataforma eletrónica utilizada pela entidade adjudicante: VORTAL\nURL para Apresentação: https://community.vortal.biz/public/\nAdmissibilidade da apresentação de propostas variantes: Não autorizado\nPrazo para apresentação das propostas: 29-09-2025 23:59\nPrazo durante o qual os concorrentes são obrigados a manter as respetivas propostas: 132 dias a contar do termo do prazo para a apresentação das propostas\nIndicação de Subcontratação na Proposta: Inexistência de indicação de subcontratação\n\n14 - PRESTAÇÃO DE CAUÇÃO\nPrestação de caução: Não\n\n15 - FORNECIMENTO DAS PEÇAS DO CONCURSO, APRESENTAÇÃO DE PEDIDOS DE PARTICIPAÇÃO E APRESENTAÇÃO DAS PROPOSTAS\nLink para acesso às peças do concurso (URL): https://community.vortal.biz/Public/public-tender-documents/SEIvMlo3dWVYZEljcDAzaVFNYk5kc1RjRlgzTm5SK1lNbHZUNnl5VEpsakY3NTdrWVZrUkd4cTFoOG1PN0JVYkFmc3BJNjlTNWJ0QVpWeWg1b0lyRmc9PU9ATExz\n\n20 - OUTROS REQUISITOS\nIdentificador do Lote: LOT-0001; LOT-0002; LOT-0003\nInformação sobre contratos reservados. Aplica-se a contratos reservados (54º-A)? Não\n\n21 - CRITÉRIO DE ADJUDICAÇÃO\nO Critério de adjudicação é diferenciado por lote? Não\nMultifator: Não\nMonofator:\nNome: Preço\n\n24 - CONDIÇÕES DO CONTRATO\nIdentificador do Lote: LOT-0001; LOT-0002; LOT-0003\nFaturação Eletrónica: Permitido\nObrigação de Subcontratação:\nCódigo da Obrigação de Subcontratação: Não é aplicável nenhuma obrigação de subcontratação.\n\n25 - COMPRA PÚBLICA ESTRATÉGICA\nCompra Pública Estratégica: Inexistência de contratação pública estratégica\n\n26 - INFORMAÇÕES ADICIONAIS\nIdentificador do Lote: LOT-0001; LOT-0002; LOT-0003\nContrato adequado para PME: Sim\nCobertura ACP (Acordo dos Contratos Públicos da Organização Mundial do Comércio): Não\n\n27 - IDENTIFICAÇÃO E CONTACTOS DO ÓRGÃO DE RECURSOS ADMINISTRATIVOS\nDesignação: Câmara Municipal de Coimbra\nEndereço: Praça 8.º de Maio\nCódigo postal: 3000-300\nLocalidade: Coimbra\nTelefone: +351 239857500\nFax: +351 239800114\nEndereço eletrónico: geral@cm-coimbra.pt\n\n28 - IDENTIFICAÇÃO DO(S) AUTOR(ES) DE ANÚNCIO\nNome: Jorge Miguel da Silva de Jesus\nCargo: Presidente do Conselho de Administração dos SMTUC\n419546049",
    "nipc": "680015965",
    "distrito": "Coimbra",
    "concelho": "Coimbra",
    "freguesia": "União das Freguesias de Santa Clara e Castelo Viegas",
    "site": "www.smtuc.pt",
    "email": "geral@smtuc.pt",
    "designacao_contrato": "Concurso Público Ref.ª CP3/53/2025 – Fornecimento contínuo de material de stock OEM (original) para autocarros Mercedes-Benz.",
    "descricao": "Fornecimento contínuo de material de stock OEM (original) para autocarros Mercedes-Benz.",
    "preco_base": "50.975,70 EUR",
    "prazo_execucao": "12 MESES",
    "prazo_apresentacao_propostas": "29-09-2025 23:59",
    "fundos_eu": "Não",
    "plataforma_eletronica": "VORTAL",
    "url_procedimento": "https://community.vortal.biz/public/",
    "autor_nome": "Jorge Miguel da Silva de Jesus",
    "autor_cargo": "Presidente do Conselho de Administração dos SMTUC"
  },
  {
    "numero_procedimento": "N/A",
    "entidade": "Municipio de Aveiro",
    "link": "https://diariodarepublica.pt/dr/detalhe/contrato-publico/24576-935747879",
    "detalhes_completos": "1 - IDENTIFICAÇÃO E CONTACTOS DA ENTIDADE ADJUDICANTE\nDesignação da entidade adjudicante: Municipio de Aveiro\nNIPC: 505931192\nServiço/Órgão/Pessoa de contacto: Divisão Compras e Património\nEndereço: Cais da Fonte Nova\nCódigo postal: 3810-200\nLocalidade: Aveiro\nPaís: Portugal\nNUT III: PT16D\nDistrito: Aveiro\nConcelho: Aveiro\nFreguesia: União das Freguesias de Glória e Vera Cruz\nTelefone: 234406496\nFax: 234406301\nEndereço da Entidade (URL): www.cm-aveiro.pt\nEndereço Eletrónico: geral@cm-aveiro.pt\neDelivery Gateway (URL): https://www.acingov.pt\nFunção da Organização: Adquirente\nNorma jurídica da Entidade Adjudicante: Organismo de direito público\nÁrea de atividade da Autoridade Adjudicante: Serviços públicos das administrações públicas\n\n2 - JORNAL OFICIAL DA UNIÃO EUROPEIA\nO procedimento a que este anúncio diz respeito também é publicitado no Jornal Oficial da União Europeia? Não\n\n3 - AVISO\nModelo de Anúncio: Concurso público\nData de Envio do Anúncio: 17-09-2025\n\n5 - PROCESSO\nTipo de Procedimento: Concurso público\nPreço base do procedimento: Sim\nValor do preço base do procedimento: 32.520,32 EUR\nProcedimento com lotes? Não\n\n6 - OBJETO DO CONTRATO\nNúmero de referência interna: 26/2025\nDesignação do contrato: FORNECIMENTO CONTÍNUO DE FERRAMENTAS, MÁQUINAS E UTENSILIOS\nDescrição: FORNECIMENTO CONTÍNUO DE FERRAMENTAS, MÁQUINAS E UTENSILIOS\nTipo de Contrato Principal: Aquisição de Bens Móveis\nTipo de Contrato: Aquisição de Bens Móveis\nClassificação CPV (Vocabulário Comum para os Contratos Públicos)\nObjeto principal\nVocabulário Principal: 44510000\nPreço base s/IVA: 32.520,32 EUR\n\n7 - INDICAÇÕES ADICIONAIS\nO contrato envolve aquisição conjunta (satisfação de várias entidades)? Não\nO contrato é adjudicado por uma central de compras? Não\n\n8 - TÉCNICAS\nO concurso destina-se à celebração de um acordo-quadro? Inexistência de acordo-quadro\nÉ utilizado um leilão eletrónico? Não\nÉ adotada uma fase de negociação? Não\nSistema de Aquisição Dinâmico: Inexistência de sistema de aquisição dinâmico\n\n9 - LOCAL DA EXECUÇÃO DO CONTRATO\nLOCAL DA EXECUÇÃO DO CONTRATO (PROCEDIMENTO)\nPaís: Portugal\nNUT III: PT16D\nLocalidade: Taboeira\nDistrito: Aveiro\nConcelho: Aveiro\nFreguesia: Freguesia de Esgueira\n\n10 - PRAZO DE EXECUÇÃO DO CONTRATO\nPrazo de execução do contrato: 365 DIAS\nPrevisão de renovações: Não\n\n11 - FUNDOS EU\nTêm fundos EU? Não\n\n12 - DOCUMENTOS DE HABILITAÇÃO\nHabilitação para o exercício da atividade profissional: Não\n\n13 - CONDIÇÕES DE APRESENTAÇÃO\nPlataforma eletrónica utilizada pela entidade adjudicante: ACIN\nURL para Apresentação: https://www.acingov.pt\nAdmissibilidade da apresentação de propostas variantes: Não autorizado\nPrazo para apresentação das propostas: 27-09-2025 17:00\nPrazo durante o qual os concorrentes são obrigados a manter as respetivas propostas: 120 dias a contar do termo do prazo para a apresentação das propostas\nIndicação de Subcontratação na Proposta: Inexistência de indicação de subcontratação\n\n14 - PRESTAÇÃO DE CAUÇÃO\nPrestação de caução: Não\n\n15 - FORNECIMENTO DAS PEÇAS DO CONCURSO, APRESENTAÇÃO DE PEDIDOS DE PARTICIPAÇÃO E APRESENTAÇÃO DAS PROPOSTAS\nLink para acesso às peças do concurso (URL): https://www.acingov.pt/acingovprod/2/zonaPublica/zona_publica_c/donwloadProcedurePiece/OTc4NDcw\n\n20 - OUTROS REQUISITOS\nInformação sobre contratos reservados. Aplica-se a contratos reservados (54º-A)? Não\n\n21 - CRITÉRIO DE ADJUDICAÇÃO\nMultifator: Não\nMonofator:\nNome: Preço\n\n24 - CONDIÇÕES DO CONTRATO\nFaturação Eletrónica: Permitido\nObrigação de Subcontratação:\nCódigo da Obrigação de Subcontratação: Não é aplicável nenhuma obrigação de subcontratação.\n\n25 - COMPRA PÚBLICA ESTRATÉGICA\nCompra Pública Estratégica: Inexistência de contratação pública estratégica\n\n26 - INFORMAÇÕES ADICIONAIS\nContrato adequado para PME: Sim\nCobertura ACP (Acordo dos Contratos Públicos da Organização Mundial do Comércio): Não\n\n27 - IDENTIFICAÇÃO E CONTACTOS DO ÓRGÃO DE RECURSOS ADMINISTRATIVOS\nDesignação: Câmara Municipal de Aveiro\nEndereço: Praça da República\nCódigo postal: 3810-200\nLocalidade: Aveiro\nTelefone: 234406300\nFax: \nEndereço eletrónico: geral@cm-aveiro.pt\nPrazo de interposição do recurso: 5 dias\n\n28 - IDENTIFICAÇÃO DO(S) AUTOR(ES) DE ANÚNCIO\nNome: José Agostinho Ribau Esteves\nCargo: Presidente\n419542688",
    "nipc": "505931192",
    "distrito": "Aveiro",
    "concelho": "Aveiro",
    "freguesia": "União das Freguesias de Glória e Vera Cruz",
    "site": "www.cm-aveiro.pt",
    "email": "geral@cm-aveiro.pt",
    "designacao_contrato": "FORNECIMENTO CONTÍNUO DE FERRAMENTAS, MÁQUINAS E UTENSILIOS",
    "descricao": "FORNECIMENTO CONTÍNUO DE FERRAMENTAS, MÁQUINAS E UTENSILIOS",
    "preco_base": "32.520,32 EUR",
    "prazo_execucao": "365 DIAS",
    "prazo_apresentacao_propostas": "27-09-2025 17:00",
    "fundos_eu": "Não",
    "plataforma_eletronica": "ACIN",
    "url_procedimento": "https://www.acingov.pt",
    "autor_nome": "José Agostinho Ribau Esteves",
    "autor_cargo": "Presidente"
  },
  {
    "numero_procedimento": "N/A",
    "entidade": "Unidade Local de Saúde de Coimbra, E. P. E.",
    "link": "https://diariodarepublica.pt/dr/detalhe/contrato-publico/24577-935747880",
    "detalhes_completos": "1 - IDENTIFICAÇÃO E CONTACTOS DA ENTIDADE ADJUDICANTE\nDesignação da entidade adjudicante: Unidade Local de Saúde de Coimbra, E. P. E.\nNIPC: 510103448\nEndereço: Praceta Prof. Mota Pinto\nCódigo postal: 3004-561\nLocalidade: Coimbra\nPaís: Portugal\nNUT III: PT16E\nDistrito: Coimbra\nConcelho: Coimbra\nFreguesia: Todas\nTelefone: 239400605\nFax: 239400605\nEndereço da Entidade (URL): https://www.chuc.min-saude.pt\nEndereço Eletrónico: ana.rosete@ulscoimbra.min-saude.pt\neDelivery Gateway (URL): https://community.vortal.biz/public/\nFunção da Organização: Adquirente\nNorma jurídica da Entidade Adjudicante: Organismo de direito público\nÁrea de atividade da Autoridade Adjudicante: Saúde\n\n2 - JORNAL OFICIAL DA UNIÃO EUROPEIA\nO procedimento a que este anúncio diz respeito também é publicitado no Jornal Oficial da União Europeia? Não\n\n3 - AVISO\nModelo de Anúncio: Concurso público\nData de Envio do Anúncio: 17-09-2025\n\n5 - PROCESSO\nTipo de Procedimento: Concurso público\nPreço base do procedimento: Sim\nValor do preço base do procedimento: 85.595,00 EUR\nProcedimento com lotes? Sim\nNº Máx. de Lotes Autorizado: 5\nNúmero máximo de lotes que podem ser adjudicados a um concorrente: 5\n\n6 - OBJETO DO CONTRATO\nNúmero de referência interna: 010900252025\nDesignação do contrato: Aquisição de produtos de apoio pediátricos para o Serviço de Consulta de Ortopedia Pediátrica do polo Hospital Pediátrico\nDescrição: Aquisição de produtos de apoio pediátricos para o Serviço de Consulta de Ortopedia Pediátrica do polo Hospital Pediátrico\nTipo de Contrato Principal: Aquisição de Bens Móveis\nTipo de Contrato: Aquisição de Bens Móveis\nClassificação CPV (Vocabulário Comum para os Contratos Públicos)\nObjeto principal\nVocabulário Principal: 33180000\nPreço base s/IVA: 85.595,00 EUR\nLotes: \nNº: LOT-0001\nDescrição do Lote: Lote 1 - Órtoteses da anca\nPreço base s/IVA: 10.440,00 EUR\nClassificação CPV (Vocabulário Comum para os Contratos Públicos)\nObjeto principal\nVocabulário Principal: 33180000\nNº: LOT-0002\nDescrição do Lote: Lote 2 - Ortóteses do joelho\nPreço base s/IVA: 2.105,00 EUR\nClassificação CPV (Vocabulário Comum para os Contratos Públicos)\nObjeto principal\nVocabulário Principal: 33180000\nNº: LOT-0003\nDescrição do Lote: Lote 3 - Ortóteses de pé\nPreço base s/IVA: 27.040,00 EUR\nClassificação CPV (Vocabulário Comum para os Contratos Públicos)\nObjeto principal\nVocabulário Principal: 33180000\nNº: LOT-0004\nDescrição do Lote: Lote 4 - Ortóteses da coluna\nPreço base s/IVA: 45.210,00 EUR\nClassificação CPV (Vocabulário Comum para os Contratos Públicos)\nObjeto principal\nVocabulário Principal: 33180000\nNº: LOT-0005\nDescrição do Lote: Lote 5 - Ortóteses de membro superior\nPreço base s/IVA: 800,00 EUR\nClassificação CPV (Vocabulário Comum para os Contratos Públicos)\nObjeto principal\nVocabulário Principal: 33180000\n\n7 - INDICAÇÕES ADICIONAIS\nO contrato envolve aquisição conjunta (satisfação de várias entidades)? Não\nO contrato é adjudicado por uma central de compras? Não\n\n8 - TÉCNICAS\nO concurso destina-se à celebração de um acordo-quadro? Inexistência de acordo-quadro\nÉ utilizado um leilão eletrónico? Não\nÉ adotada uma fase de negociação? Não\nSistema de Aquisição Dinâmico: Inexistência de sistema de aquisição dinâmico\n\n9 - LOCAL DA EXECUÇÃO DO CONTRATO\nLOCAL DA EXECUÇÃO DO CONTRATO (PROCEDIMENTO)\nPaís: Portugal\nNUT III: PT16E\nLocalidade: Coimbra\nDistrito: Coimbra\nConcelho: Coimbra\nFreguesia: Freguesia de Santo António dos Olivais\nLOCAL DA EXECUÇÃO DO CONTRATO (LOTE)\nIdentificador do Lote: LOT-0001; LOT-0002; LOT-0003; LOT-0004; LOT-0005\nPaís: Portugal\nNUT III: PT16E\nLocalidade: Coimbra\nDistrito: Coimbra\nConcelho: Coimbra\nFreguesia: Freguesia de Santo António dos Olivais\n\n10 - PRAZO DE EXECUÇÃO DO CONTRATO\nIdentificador do Lote: LOT-0001; LOT-0002; LOT-0003; LOT-0004; LOT-0005\nPrazo de execução do contrato: 7 DIAS\nPrevisão de renovações: Não\n\n11 - FUNDOS EU\nIdentificador do Lote: LOT-0001; LOT-0002; LOT-0003; LOT-0004; LOT-0005\nTêm fundos EU? Não\n\n12 - DOCUMENTOS DE HABILITAÇÃO\nHabilitação para o exercício da atividade profissional: Não\n\n13 - CONDIÇÕES DE APRESENTAÇÃO\nPlataforma eletrónica utilizada pela entidade adjudicante: VORTAL\nURL para Apresentação: https://community.vortal.biz/public/\nAdmissibilidade da apresentação de propostas variantes: Não autorizado\nPrazo para apresentação das propostas: 14-10-2025 23:59\nPrazo durante o qual os concorrentes são obrigados a manter as respetivas propostas: 90 dias a contar do termo do prazo para a apresentação das propostas\nIndicação de Subcontratação na Proposta: Inexistência de indicação de subcontratação\n\n14 - PRESTAÇÃO DE CAUÇÃO\nPrestação de caução: Não\n\n15 - FORNECIMENTO DAS PEÇAS DO CONCURSO, APRESENTAÇÃO DE PEDIDOS DE PARTICIPAÇÃO E APRESENTAÇÃO DAS PROPOSTAS\nLink para acesso às peças do concurso (URL): https://community.vortal.biz/Public/public-tender-documents/bEhiLzVLYWV1dWZlVkZqNm9WRnJ0NFRwN0VzdUx4cWpERW1qODhaT05tVkpSQmFjNUZVWGw2cEV0MlFlRHkxRlNBakNyQjNobWtJUmtVdk0xZnVsc2c9PWQkX0Q2\n\n20 - OUTROS REQUISITOS\nIdentificador do Lote: LOT-0001; LOT-0002; LOT-0003; LOT-0004; LOT-0005\nInformação sobre contratos reservados. Aplica-se a contratos reservados (54º-A)? Não\n\n21 - CRITÉRIO DE ADJUDICAÇÃO\nO Critério de adjudicação é diferenciado por lote? Não\nMultifator: Sim\nFator: \nNome: Preço\nPonderação: 50%\nSubfatores: Não\nFator: \nNome: Qualidade\nPonderação: 50%\nSubfatores: Não\n\n24 - CONDIÇÕES DO CONTRATO\nIdentificador do Lote: LOT-0001; LOT-0002; LOT-0003; LOT-0004; LOT-0005\nFaturação Eletrónica: Permitido\nObrigação de Subcontratação:\nCódigo da Obrigação de Subcontratação: Não é aplicável nenhuma obrigação de subcontratação.\n\n25 - COMPRA PÚBLICA ESTRATÉGICA\nCompra Pública Estratégica: Inexistência de contratação pública estratégica\n\n26 - INFORMAÇÕES ADICIONAIS\nIdentificador do Lote: LOT-0001; LOT-0002; LOT-0003; LOT-0004; LOT-0005\nContrato adequado para PME: Sim\nCobertura ACP (Acordo dos Contratos Públicos da Organização Mundial do Comércio): Não\n\n27 - IDENTIFICAÇÃO E CONTACTOS DO ÓRGÃO DE RECURSOS ADMINISTRATIVOS\nDesignação: Conselho de Administração da ULS Coimbra, EPE\nEndereço: Praceta Prof. Mota Pinto\nCódigo postal: 3004-561\nLocalidade: Coimbra\nTelefone: +351 239400400\nFax: +351 239400400\nEndereço eletrónico: casec@ulscoimbra.min-saude.pt\n\n28 - IDENTIFICAÇÃO DO(S) AUTOR(ES) DE ANÚNCIO\nNome: Rita Santos\nCargo: Assistente Técnica\n419544348",
    "nipc": "510103448",
    "distrito": "Coimbra",
    "concelho": "Coimbra",
    "freguesia": "Todas",
    "site": "https://www.chuc.min-saude.pt",
    "email": "ana.rosete@ulscoimbra.min-saude.pt",
    "designacao_contrato": "Aquisição de produtos de apoio pediátricos para o Serviço de Consulta de Ortopedia Pediátrica do polo Hospital Pediátrico",
    "descricao": "Aquisição de produtos de apoio pediátricos para o Serviço de Consulta de Ortopedia Pediátrica do polo Hospital Pediátrico",
    "preco_base": "85.595,00 EUR",
    "prazo_execucao": "7 DIAS",
    "prazo_apresentacao_propostas": "14-10-2025 23:59",
    "fundos_eu": "Não",
    "plataforma_eletronica": "VORTAL",
    "url_procedimento": "https://community.vortal.biz/public/",
    "autor_nome": "Rita Santos",
    "autor_cargo": "Assistente Técnica"
  },
  {
    "numero_procedimento": "N/A",
    "entidade": "Serviços Municipalizados de Sintra (SMAS)",
    "link": "https://diariodarepublica.pt/dr/detalhe/contrato-publico/24578-935747881",
    "detalhes_completos": "1 - IDENTIFICAÇÃO E CONTACTOS DA ENTIDADE ADJUDICANTE\nDesignação da entidade adjudicante: Serviços Municipalizados de Sintra (SMAS)\nNIPC: 680000054\nEndereço: Avenida Movimento Da Forças Armadas, 16\nCódigo postal: 2714-503\nLocalidade: Sintra\nPaís: Portugal\nNUT III: PT170\nDistrito: Lisboa\nConcelho: Sintra\nFreguesia: Todas\nTelefone: 219119016\nFax: 219232650\nEndereço da Entidade (URL): www.smas-sintra.pt\nEndereço Eletrónico: aprov.stocks@smas-sintra.pt\neDelivery Gateway (URL): https://community.vortal.biz/public/\nFunção da Organização: Adquirente\nNorma jurídica da Entidade Adjudicante: Autoridade local\nÁrea de atividade da Autoridade Adjudicante: Serviços públicos das administrações públicas\n\n2 - JORNAL OFICIAL DA UNIÃO EUROPEIA\nO procedimento a que este anúncio diz respeito também é publicitado no Jornal Oficial da União Europeia? Sim\n\n3 - AVISO\nModelo de Anúncio: Concurso público\nData de Envio do Anúncio: 15-09-2025\n\n5 - PROCESSO\nTipo de Procedimento: Concurso público\nPreço base do procedimento: Sim\nValor do preço base do procedimento: 350.395,40 EUR\nProcedimento com lotes? Sim\nNº Máx. de Lotes Autorizado: 5\nNúmero máximo de lotes que podem ser adjudicados a um concorrente: 5\n\n6 - OBJETO DO CONTRATO\nNúmero de referência interna: Concurso Público N.º 34PF/2025 \nDesignação do contrato: Concurso Público N.º 34PF/2025 - «Aquisição de Viaturas para Substituição de Veículos Ligeiros, Pick-Ups e Comerciais da Frota SMAS-Sintra, por Lotes»\nDescrição: Aquisição de Viaturas para Substituição de Veículos Ligeiros, Pick-Ups e Comerciais da Frota SMAS-Sintra, por Lotes\nOpções: Não\nTipo de Contrato Principal: Aquisição de Bens Móveis\nTipo de Contrato: Aquisição de Bens Móveis\nClassificação CPV (Vocabulário Comum para os Contratos Públicos)\nObjeto principal\nVocabulário Principal: 34100000\nPreço base s/IVA: 350.395,40 EUR\nLotes: \nNº: LOT-0001\nDescrição do Lote: Lote 1\nPreço base s/IVA: 62.999,52 EUR\nClassificação CPV (Vocabulário Comum para os Contratos Públicos)\nObjeto principal\nVocabulário Principal: 34100000\nNº: LOT-0002\nDescrição do Lote: Lote 2\nPreço base s/IVA: 40.251,38 EUR\nClassificação CPV (Vocabulário Comum para os Contratos Públicos)\nObjeto principal\nVocabulário Principal: 34100000\nNº: LOT-0003\nDescrição do Lote: Lote 3\nPreço base s/IVA: 52.204,50 EUR\nClassificação CPV (Vocabulário Comum para os Contratos Públicos)\nObjeto principal\nVocabulário Principal: 34100000\nNº: LOT-0004\nDescrição do Lote: Lote 4\nPreço base s/IVA: 130.940,00 EUR\nClassificação CPV (Vocabulário Comum para os Contratos Públicos)\nObjeto principal\nVocabulário Principal: 34100000\nNº: LOT-0005\nDescrição do Lote: Lote 5\nPreço base s/IVA: 64.000,00 EUR\nClassificação CPV (Vocabulário Comum para os Contratos Públicos)\nObjeto principal\nVocabulário Principal: 34100000\n\n7 - INDICAÇÕES ADICIONAIS\nO contrato envolve aquisição conjunta (satisfação de várias entidades)? Não\nO contrato é adjudicado por uma central de compras? Não\n\n8 - TÉCNICAS\nO concurso destina-se à celebração de um acordo-quadro? Inexistência de acordo-quadro\nÉ utilizado um leilão eletrónico? Não\nÉ adotada uma fase de negociação? Não\nSistema de Aquisição Dinâmico: Inexistência de sistema de aquisição dinâmico\n\n9 - LOCAL DA EXECUÇÃO DO CONTRATO\nLOCAL DA EXECUÇÃO DO CONTRATO (PROCEDIMENTO)\nPaís: Portugal\nNUT III: PT170\nLocalidade: Lisboa\nDistrito: Lisboa\nConcelho: Sintra\nFreguesia: União das Freguesias de Sintra (Santa Maria e São Miguel, São Martinho e São Pedro de Penaferrim)\nLOCAL DA EXECUÇÃO DO CONTRATO (LOTE)\nIdentificador do Lote: LOT-0001; LOT-0002; LOT-0003; LOT-0004; LOT-0005\nPaís: Portugal\nNUT III: PT170\nLocalidade: Lisboa\nDistrito: Lisboa\nConcelho: Sintra\nFreguesia: União das Freguesias de Sintra (Santa Maria e São Miguel, São Martinho e São Pedro de Penaferrim)\n\n10 - PRAZO DE EXECUÇÃO DO CONTRATO\nIdentificador do Lote: LOT-0001; LOT-0002; LOT-0003; LOT-0004; LOT-0005\nPrazo de execução do contrato: 36 MESES\nPrevisão de renovações: Não\n\n11 - FUNDOS EU\nIdentificador do Lote: LOT-0001; LOT-0002; LOT-0003; LOT-0004; LOT-0005\nTêm fundos EU? Não\n\n12 - DOCUMENTOS DE HABILITAÇÃO\nHabilitação para o exercício da atividade profissional: Sim\nTipo: Outros\nDescrição - Outros: De acordo com o previsto nas Peças do Procedimento\nDescrição: De acordo com o previsto nas Peças do Procedimento\n\n13 - CONDIÇÕES DE APRESENTAÇÃO\nPlataforma eletrónica utilizada pela entidade adjudicante: VORTAL\nURL para Apresentação: https://community.vortal.biz/public/\nAdmissibilidade da apresentação de propostas variantes: Não autorizado\nPrazo para apresentação das propostas: 21-10-2025 17:00\nPrazo durante o qual os concorrentes são obrigados a manter as respetivas propostas: 90 dias a contar do termo do prazo para a apresentação das propostas\nApresentação de Catálogo Eletrónico: Não autorizado\nIndicação de Subcontratação na Proposta: Inexistência de indicação de subcontratação\n\n14 - PRESTAÇÃO DE CAUÇÃO\nPrestação de caução: Sim\nPercentagem: 5%\nDescrição da Garantia Exigida: De acordo com o previsto nas Peças do Procedimento\n\n15 - FORNECIMENTO DAS PEÇAS DO CONCURSO, APRESENTAÇÃO DE PEDIDOS DE PARTICIPAÇÃO E APRESENTAÇÃO DAS PROPOSTAS\nLink para acesso às peças do concurso (URL): https://community.vortal.biz/Public/public-tender-documents/L01YNXR0QjRNZGlHcjZpNWxmc1VjYThXRFMrejdqbUtSUTdYYVlkbjg2NURVL1BOQlBZME01bWN3TW5mTnBWcmNjOUFyMkVyc0QrWllQYkJBWDlOQmc9PU4oKipD\n\n20 - OUTROS REQUISITOS\nIdentificador do Lote: LOT-0001; LOT-0002; LOT-0003; LOT-0004; LOT-0005\nInformação sobre contratos reservados. Aplica-se a contratos reservados (54º-A)? Não\n\n21 - CRITÉRIO DE ADJUDICAÇÃO\nO Critério de adjudicação é diferenciado por lote? Não\nMultifator: Não\nMonofator:\nNome: Preço\n\n24 - CONDIÇÕES DO CONTRATO\nIdentificador do Lote: LOT-0001; LOT-0002; LOT-0003; LOT-0004; LOT-0005\nFaturação Eletrónica: Permitido\nObrigação de Subcontratação:\nCódigo da Obrigação de Subcontratação: Não é aplicável nenhuma obrigação de subcontratação.\n\n25 - COMPRA PÚBLICA ESTRATÉGICA\nCompra Pública Estratégica: Inexistência de contratação pública estratégica\n\n26 - INFORMAÇÕES ADICIONAIS\nIdentificador do Lote: LOT-0001; LOT-0002; LOT-0003; LOT-0004; LOT-0005\nContrato adequado para PME: Sim\nCobertura ACP (Acordo dos Contratos Públicos da Organização Mundial do Comércio): Não\n\n27 - IDENTIFICAÇÃO E CONTACTOS DO ÓRGÃO DE RECURSOS ADMINISTRATIVOS\nDesignação: Câmara Municipal de Sintra\nEndereço: Largo Dr. Virgílio Horta\nCódigo postal: 2714-501\nLocalidade: Sintra\nTelefone: +351 219238500\nFax: +351 219238657\nEndereço eletrónico: geral@cm-sintra.pt\n\n28 - IDENTIFICAÇÃO DO(S) AUTOR(ES) DE ANÚNCIO\nNome: Basílio Adolfo Mendonça Horta da Franca\nCargo: Presidente do Conselho de Administração dos SMAS-Sintra\n419526155",
    "nipc": "680000054",
    "distrito": "Lisboa",
    "concelho": "Sintra",
    "freguesia": "Todas",
    "site": "www.smas-sintra.pt",
    "email": "aprov.stocks@smas-sintra.pt",
    "designacao_contrato": "Concurso Público N.º 34PF/2025 - «Aquisição de Viaturas para Substituição de Veículos Ligeiros, Pick-Ups e Comerciais da Frota SMAS-Sintra, por Lotes»",
    "descricao": "Aquisição de Viaturas para Substituição de Veículos Ligeiros, Pick-Ups e Comerciais da Frota SMAS-Sintra, por Lotes",
    "preco_base": "350.395,40 EUR",
    "prazo_execucao": "36 MESES",
    "prazo_apresentacao_propostas": "21-10-2025 17:00",
    "fundos_eu": "Não",
    "plataforma_eletronica": "VORTAL",
    "url_procedimento": "https://community.vortal.biz/public/",
    "autor_nome": "Basílio Adolfo Mendonça Horta da Franca",
    "autor_cargo": "Presidente do Conselho de Administração dos SMAS-Sintra"
  },
  {
    "numero_procedimento": "N/A",
    "entidade": "HEN, Serviços Energéticos Lda",
    "link": "https://diariodarepublica.pt/dr/detalhe/contrato-publico/24580-935747882",
    "detalhes_completos": "Alteração do Anúncio de procedimento n.º 23546/2025, de 2025-09-04, com o ID 419490848\n\n1 - IDENTIFICAÇÃO E CONTACTOS DA ENTIDADE ADJUDICANTE\nDesignação da entidade adjudicante: HEN, Serviços Energéticos Lda\nNIPC: 510287050\nServiço/Órgão/Pessoa de contacto: HEN - Serviços Energéticos Lda contato telefónico nº 927592824\nEndereço: Plataforma Logistica de Iniciativa Empresarial da Guarda (Plie), Lote 3\nCódigo postal: 6300-070\nLocalidade: Casal de Cinza - Guarda\nPaís: Portugal\nNUT III: PT16J\nDistrito: Guarda\nConcelho: Guarda\nFreguesia: Freguesia de Casal de Cinza\nTelefone: 271023041\nEndereço da Entidade (URL): www.hen.pt\nEndereço Eletrónico: geral@hen.pt\neDelivery Gateway (URL): https://www.acingov.pt\nFunção da Organização: Adquirente\nNorma jurídica da Entidade Adjudicante: Organismo de direito público\nÁrea de atividade da Autoridade Adjudicante: Serviços públicos das administrações públicas\n\n2 - JORNAL OFICIAL DA UNIÃO EUROPEIA\nO procedimento a que este anúncio diz respeito também é publicitado no Jornal Oficial da União Europeia? Sim\n\n3 - AVISO\nModelo de Anúncio: Concurso público\nData de Envio do Anúncio: 15-09-2025\n\n5 - PROCESSO\nTipo de Procedimento: Concurso público\nPreço base do procedimento: Sim\nValor do preço base do procedimento: 9.000.000,00 EUR\nProcedimento com lotes? Não\n\n6 - OBJETO DO CONTRATO\nNúmero de referência interna: CPI 003/2025\nDesignação do contrato: O objeto do contrato pretende a \"Aquisição de Bens e Serviços de Fornecimento e Instalação de Equipamentos\" no âmbito da candidatura nº 66 da HEN - SERVIÇOS ENERGÉTICOS, LDA ao aviso 01/C14-i01/2021 - Apoio à produção de hidrogénio renovável e outros gases renováveis.\nDescrição: O objeto do contrato pretende a Aquisição de Bens e Serviços de Fornecimento e Instalação de Equipamentos\\\" no âmbito da candidatura nº 66 da HEN - SERVIÇOS ENERGÉTICOS, LDA ao aviso 01/C14-i01/2021 - Apoio à produção de hidrogénio renovável e outros gases renováveis.\nOpções: Não\nTipo de Contrato Principal: Aquisição de Serviços\nTipo de Contrato: Aquisição de Serviços\nClassificação CPV (Vocabulário Comum para os Contratos Públicos)\nObjeto principal\nVocabulário Principal: 51100000\nPreço base s/IVA: 9.000.000,00 EUR\n\n7 - INDICAÇÕES ADICIONAIS\nO contrato envolve aquisição conjunta (satisfação de várias entidades)? Não\nO contrato é adjudicado por uma central de compras? Não\n\n8 - TÉCNICAS\nO concurso destina-se à celebração de um acordo-quadro? Inexistência de acordo-quadro\nÉ utilizado um leilão eletrónico? Não\nÉ adotada uma fase de negociação? Não\nSistema de Aquisição Dinâmico: Inexistência de sistema de aquisição dinâmico\n\n9 - LOCAL DA EXECUÇÃO DO CONTRATO\nLOCAL DA EXECUÇÃO DO CONTRATO (PROCEDIMENTO)\nPaís: Portugal\nNUT III: PT16J\nLocalidade: União das Freguesias de Seia, São Romão e Lapa dos Dinheiros\nDistrito: Guarda\nConcelho: Seia\nFreguesia: União das Freguesias de Seia, São Romão e Lapa dos Dinheiros\n\n10 - PRAZO DE EXECUÇÃO DO CONTRATO\nPrazo de execução do contrato: 92 DIAS\nPrevisão de renovações: Não\n\n11 - FUNDOS EU\nTêm fundos EU? Sim\n\n12 - DOCUMENTOS DE HABILITAÇÃO\nHabilitação para o exercício da atividade profissional: Sim\nTipo: Alvará\nDescrição: Alvará de Construção emitido pelo Instituto dos Mercados Públicos, do Imobiliário e da Construção, IMPIC, contendo as seguintes habilitações: alvará empreiteiro de obras públicas com a classe máxima que cubra o valor da proposta e que tenha também a 4.ª categoria (Instalações Elétricas e Mecânicas) e 4.ª subcategoria (Redes e instalações elétricas de tensão de serviço superior a 30kV) e classificação da atividade económica (CAE) que habilita a empresa ao fornecimento de equipamentos, mais especificamente os CAE 46690 (Comércio por grosso de outras máquinas e equipamentos) da Rev.3 ou CAE 46642 (Comércio por grosso de outras máquinas e equipamentos, n.e.) da Rev.4 e CAE 43210 (Instalação elétrica, de canalizações, de climatização e outras instalações) da Rev. 3 e 4.\n\n13 - CONDIÇÕES DE APRESENTAÇÃO\nPlataforma eletrónica utilizada pela entidade adjudicante: ACIN\nURL para Apresentação: https://www.acingov.pt\nAdmissibilidade da apresentação de propostas variantes: Não autorizado\nPrazo para apresentação das propostas: 19-09-2025 17:00\nPrazo durante o qual os concorrentes são obrigados a manter as respetivas propostas: 66 dias a contar do termo do prazo para a apresentação das propostas\nApresentação de Catálogo Eletrónico: Permitido\nIndicação de Subcontratação na Proposta: Inexistência de indicação de subcontratação\n\n14 - PRESTAÇÃO DE CAUÇÃO\nPrestação de caução: Sim\nPercentagem: 0.1%\nDescrição da Garantia Exigida: O valor da caução é de 0.10% do preço contratual.\n\n15 - FORNECIMENTO DAS PEÇAS DO CONCURSO, APRESENTAÇÃO DE PEDIDOS DE PARTICIPAÇÃO E APRESENTAÇÃO DAS PROPOSTAS\nLink para acesso às peças do concurso (URL): https://www.acingov.pt/acingovprod/2/zonaPublica/zona_publica_c/donwloadProcedurePiece/OTM0MzQ1\n\n20 - OUTROS REQUISITOS\nInformação sobre contratos reservados. Aplica-se a contratos reservados (54º-A)? Não\n\n21 - CRITÉRIO DE ADJUDICAÇÃO\nMultifator: Sim\nFator: \nNome: Preço\nPonderação: 50%\nSubfatores: Não\nFator: \nNome: Outros\nOutro Nome: B1 - Memória Descritiva/Justificativa\nPonderação: 25%\nSubfatores: Não\nFator: \nNome: Outros\nOutro Nome: B2 - Garantia Total\nPonderação: 20%\nSubfatores: Não\nFator: \nNome: Outros\nOutro Nome: B3 - Prazo de Entrega e instalação dos Equipamentos (Eletrolisador, Compressor, Buffer e Armazenamento Secundário)\nPonderação: 5%\nSubfatores: Não\n\n24 - CONDIÇÕES DO CONTRATO\nFaturação Eletrónica: Permitido\nObrigação de Subcontratação:\nCódigo da Obrigação de Subcontratação: Não é aplicável nenhuma obrigação de subcontratação.\n\n25 - COMPRA PÚBLICA ESTRATÉGICA\nCompra Pública Estratégica: Inexistência de contratação pública estratégica\n\n26 - INFORMAÇÕES ADICIONAIS\nContrato adequado para PME: Sim\nCobertura ACP (Acordo dos Contratos Públicos da Organização Mundial do Comércio): Não\n\n27 - IDENTIFICAÇÃO E CONTACTOS DO ÓRGÃO DE RECURSOS ADMINISTRATIVOS\nDesignação: HEN- Serviços Energéticos Lda\nEndereço: Plataforma Logistica de Iniciativa Empresarial da Guarda (Plie), Lote 3\nCódigo postal: 6300-070\nLocalidade: Casal de Cinza - Guarda\nTelefone: 927592824\nFax: \nEndereço eletrónico: administracao@hen.pt\n\n28 - IDENTIFICAÇÃO DO(S) AUTOR(ES) DE ANÚNCIO\nNome: Catarina Paulo\nCargo: Diretora de Operações\n\n29 - ALTERAÇÃO\nMotivo da Alteração: Informações atualizadas\nIdentificador da Versão do Anúncio a Alterar: a32bb567-bf34-4962-9b23-74aa826f2784-01\nIdentificador das Secções Alteradas do Anúncio Anterior: Condições de Apresentação\nDescrição das Alterações: Modificação do prazo para a apresentação de propostas\nAlteração dos Documentos do Concurso: Não\n419536556",
    "nipc": "510287050",
    "distrito": "Guarda",
    "concelho": "Guarda",
    "freguesia": "Freguesia de Casal de Cinza",
    "site": "www.hen.pt",
    "email": "geral@hen.pt",
    "designacao_contrato": "O objeto do contrato pretende a \"Aquisição de Bens e Serviços de Fornecimento e Instalação de Equipamentos\" no âmbito da candidatura nº 66 da HEN - SERVIÇOS ENERGÉTICOS, LDA ao aviso 01/C14-i01/2021 - Apoio à produção de hidrogénio renovável e outros gases renováveis.",
    "descricao": "O objeto do contrato pretende a Aquisição de Bens e Serviços de Fornecimento e Instalação de Equipamentos\\\" no âmbito da candidatura nº 66 da HEN - SERVIÇOS ENERGÉTICOS, LDA ao aviso 01/C14-i01/2021 - Apoio à produção de hidrogénio renovável e outros gases renováveis.",
    "preco_base": "9.000.000,00 EUR",
    "prazo_execucao": "92 DIAS",
    "prazo_apresentacao_propostas": "19-09-2025 17:00",
    "fundos_eu": "Sim",
    "plataforma_eletronica": "ACIN",
    "url_procedimento": "https://www.acingov.pt",
    "autor_nome": "Catarina Paulo",
    "autor_cargo": "Diretora de Operações"
  },
  {
    "numero_procedimento": "N/A",
    "entidade": "Serviços Municipalizados de Sintra (SMAS)",
    "link": "https://diariodarepublica.pt/dr/detalhe/contrato-publico/24583-935747883",
    "detalhes_completos": "1 - IDENTIFICAÇÃO E CONTACTOS DA ENTIDADE ADJUDICANTE\nDesignação da entidade adjudicante: Serviços Municipalizados de Sintra (SMAS)\nNIPC: 680000054\nEndereço: Avenida Movimento Da Forças Armadas, 16\nCódigo postal: 2714-503\nLocalidade: Sintra\nPaís: Portugal\nNUT III: PT170\nDistrito: Lisboa\nConcelho: Sintra\nFreguesia: Todas\nTelefone: 219119016\nFax: 219232650\nEndereço da Entidade (URL): www.smas-sintra.pt\nEndereço Eletrónico: aprov.stocks@smas-sintra.pt\neDelivery Gateway (URL): https://community.vortal.biz/public/\nFunção da Organização: Adquirente\nNorma jurídica da Entidade Adjudicante: Autoridade local\nÁrea de atividade da Autoridade Adjudicante: Serviços públicos das administrações públicas\n\n2 - JORNAL OFICIAL DA UNIÃO EUROPEIA\nO procedimento a que este anúncio diz respeito também é publicitado no Jornal Oficial da União Europeia? Sim\n\n3 - AVISO\nModelo de Anúncio: Concurso público\nData de Envio do Anúncio: 15-09-2025\n\n5 - PROCESSO\nTipo de Procedimento: Concurso público\nPreço base do procedimento: Sim\nValor do preço base do procedimento: 1.037.496,00 EUR\nProcedimento com lotes? Não\n\n6 - OBJETO DO CONTRATO\nNúmero de referência interna: Concurso Público N.º 36PF/2025 \nDesignação do contrato: «Aquisição de Serviços de Upgrade da Solução SAP/ERPública em Utilização nos SMAS de Sintra para SAP ERP S/4 HANA em Private Cloud Edition, com Implementação dos Módulos de Employee Central e Time Tra\nDescrição: Aquisição de Serviços de Upgrade da Solução SAP/ERPública em Utilização nos SMAS de Sintra para SAP ERP S/4 HANA em Private Cloud Edition, com Implementação dos Módulos de Employee Central e Time Tracking da Solução SAP Success Factors\nOpções: Não\nTipo de Contrato Principal: Aquisição de Serviços\nTipo de Contrato: Aquisição de Serviços\nClassificação CPV (Vocabulário Comum para os Contratos Públicos)\nObjeto principal\nVocabulário Principal: 72263000\nPreço base s/IVA: 1.037.496,00 EUR\n\n7 - INDICAÇÕES ADICIONAIS\nO contrato envolve aquisição conjunta (satisfação de várias entidades)? Não\nO contrato é adjudicado por uma central de compras? Não\n\n8 - TÉCNICAS\nO concurso destina-se à celebração de um acordo-quadro? Inexistência de acordo-quadro\nÉ utilizado um leilão eletrónico? Não\nÉ adotada uma fase de negociação? Não\nSistema de Aquisição Dinâmico: Inexistência de sistema de aquisição dinâmico\n\n9 - LOCAL DA EXECUÇÃO DO CONTRATO\nLOCAL DA EXECUÇÃO DO CONTRATO (PROCEDIMENTO)\nPaís: Portugal\nNUT III: PT170\nLocalidade: Lisboa\nDistrito: Lisboa\nConcelho: Sintra\nFreguesia: União das Freguesias de Sintra (Santa Maria e São Miguel, São Martinho e São Pedro de Penaferrim)\n\n10 - PRAZO DE EXECUÇÃO DO CONTRATO\nPrazo de execução do contrato: 18 MESES\nPrevisão de renovações: Não\n\n11 - FUNDOS EU\nTêm fundos EU? Não\n\n12 - DOCUMENTOS DE HABILITAÇÃO\nHabilitação para o exercício da atividade profissional: Sim\nTipo: Outros\nDescrição - Outros: De acordo com o previsto nas Peças do Procedimento\nDescrição: De acordo com o previsto nas Peças do Procedimento\n\n13 - CONDIÇÕES DE APRESENTAÇÃO\nPlataforma eletrónica utilizada pela entidade adjudicante: VORTAL\nURL para Apresentação: https://community.vortal.biz/public/\nAdmissibilidade da apresentação de propostas variantes: Não autorizado\nPrazo para apresentação das propostas: 21-10-2025 17:00\nPrazo durante o qual os concorrentes são obrigados a manter as respetivas propostas: 120 dias a contar do termo do prazo para a apresentação das propostas\nApresentação de Catálogo Eletrónico: Não autorizado\nIndicação de Subcontratação na Proposta: Inexistência de indicação de subcontratação\n\n14 - PRESTAÇÃO DE CAUÇÃO\nPrestação de caução: Sim\nPercentagem: 5%\nDescrição da Garantia Exigida: De acordo com o previsto nas Peças do Procedimento\n\n15 - FORNECIMENTO DAS PEÇAS DO CONCURSO, APRESENTAÇÃO DE PEDIDOS DE PARTICIPAÇÃO E APRESENTAÇÃO DAS PROPOSTAS\nLink para acesso às peças do concurso (URL): https://community.vortal.biz/Public/public-tender-documents/UmRRMVRtSUw3L1dDOUlZa3gvOVdMeFg2NUVJUFRVTmxtRm9ZdGNqZ1pzZ3dXTzJiM2NNMWRNY1JNQ0J6RDE3L1l4Rm5YWDFnbER6cTRLcktJUTBiV3c9PUIramYj\n\n20 - OUTROS REQUISITOS\nInformação sobre contratos reservados. Aplica-se a contratos reservados (54º-A)? Não\n\n21 - CRITÉRIO DE ADJUDICAÇÃO\nMultifator: Sim\nFator: \nNome: Preço\nPonderação: 60%\nSubfatores: Não\nFator: \nNome: Qualidade\nPonderação: 40%\nSubfatores: Não\n\n24 - CONDIÇÕES DO CONTRATO\nFaturação Eletrónica: Permitido\nObrigação de Subcontratação:\nCódigo da Obrigação de Subcontratação: Não é aplicável nenhuma obrigação de subcontratação.\n\n25 - COMPRA PÚBLICA ESTRATÉGICA\nCompra Pública Estratégica: Inexistência de contratação pública estratégica\n\n26 - INFORMAÇÕES ADICIONAIS\nContrato adequado para PME: Sim\nCobertura ACP (Acordo dos Contratos Públicos da Organização Mundial do Comércio): Não\n\n27 - IDENTIFICAÇÃO E CONTACTOS DO ÓRGÃO DE RECURSOS ADMINISTRATIVOS\nDesignação: Câmara Municipal de Sintra\nEndereço: Largo Dr. Virgílio Horta\nCódigo postal: 2714-501\nLocalidade: Sintra\nTelefone: +351 219238500\nFax: +351 219238657\nEndereço eletrónico: geral@cm-sintra.pt\n\n28 - IDENTIFICAÇÃO DO(S) AUTOR(ES) DE ANÚNCIO\nNome: Basílio Adolfo Mendonça Horta da Franca\nCargo: Presidente do Conselho de Administração dos SMAS-Sintra\n419526633",
    "nipc": "680000054",
    "distrito": "Lisboa",
    "concelho": "Sintra",
    "freguesia": "Todas",
    "site": "www.smas-sintra.pt",
    "email": "aprov.stocks@smas-sintra.pt",
    "designacao_contrato": "«Aquisição de Serviços de Upgrade da Solução SAP/ERPública em Utilização nos SMAS de Sintra para SAP ERP S/4 HANA em Private Cloud Edition, com Implementação dos Módulos de Employee Central e Time Tra",
    "descricao": "Aquisição de Serviços de Upgrade da Solução SAP/ERPública em Utilização nos SMAS de Sintra para SAP ERP S/4 HANA em Private Cloud Edition, com Implementação dos Módulos de Employee Central e Time Tracking da Solução SAP Success Factors",
    "preco_base": "1.037.496,00 EUR",
    "prazo_execucao": "18 MESES",
    "prazo_apresentacao_propostas": "21-10-2025 17:00",
    "fundos_eu": "Não",
    "plataforma_eletronica": "VORTAL",
    "url_procedimento": "https://community.vortal.biz/public/",
    "autor_nome": "Basílio Adolfo Mendonça Horta da Franca",
    "autor_cargo": "Presidente do Conselho de Administração dos SMAS-Sintra"
  },
  {
    "numero_procedimento": "N/A",
    "entidade": "Município de Vale de Cambra",
    "link": "https://diariodarepublica.pt/dr/detalhe/contrato-publico/24586-935747885",
    "detalhes_completos": "1 - IDENTIFICAÇÃO E CONTACTOS DA ENTIDADE ADJUDICANTE\nDesignação da entidade adjudicante: Município de Vale de Cambra\nNIPC: 506735524\nServiço/Órgão/Pessoa de contacto: Divisão de Obras Municipais e Equipamentos\nEndereço: Av. Camilo Tavares de Matos, n.º 19\nCódigo postal: 3730-901\nLocalidade: Vale de Cambra\nPaís: Portugal\nNUT III: PT11A\nDistrito: Aveiro\nConcelho: Vale de Cambra\nFreguesia: Todas\nTelefone: 256420510\nFax: 256420519\nEndereço da Entidade (URL): www.cm-valedecambra.pt\nEndereço Eletrónico: vortal@cm-valedecambra.pt\neDelivery Gateway (URL): https://community.vortal.biz/public/\nFunção da Organização: Adquirente\nNorma jurídica da Entidade Adjudicante: Autoridade local\nÁrea de atividade da Autoridade Adjudicante: Serviços públicos das administrações públicas\n\n2 - JORNAL OFICIAL DA UNIÃO EUROPEIA\nO procedimento a que este anúncio diz respeito também é publicitado no Jornal Oficial da União Europeia? Não\n\n3 - AVISO\nModelo de Anúncio: Concurso público\nData de Envio do Anúncio: 17-09-2025\n\n5 - PROCESSO\nTipo de Procedimento: Concurso público\nPreço base do procedimento: Sim\nValor do preço base do procedimento: 278.570,65 EUR\nProcedimento com lotes? Não\n\n6 - OBJETO DO CONTRATO\nNúmero de referência interna: OE-CP Nº 17/25 \"REQUALIF CENTRO DESP GANDARINHAS\"\nDesignação do contrato: OE-CP Nº 17/25 \"REQUALIFICAÇÃO DO CENTRO DESPORTIVO DAS GANDARINHAS\"\nDescrição: REABILITAÇÃO DE CAMPO DESPORTIVO\nTipo de Contrato Principal: Empreitada de Obras Públicas\nTipo de Contrato: Empreitada de Obras Públicas\nClassificação CPV (Vocabulário Comum para os Contratos Públicos)\nObjeto principal\nVocabulário Principal: 45236119\nPreço base s/IVA: 278.570,65 EUR\n\n7 - INDICAÇÕES ADICIONAIS\nO contrato envolve aquisição conjunta (satisfação de várias entidades)? Não\nO contrato é adjudicado por uma central de compras? Não\n\n8 - TÉCNICAS\nO concurso destina-se à celebração de um acordo-quadro? Inexistência de acordo-quadro\nÉ utilizado um leilão eletrónico? Não\nÉ adotada uma fase de negociação? Não\nSistema de Aquisição Dinâmico: Inexistência de sistema de aquisição dinâmico\n\n9 - LOCAL DA EXECUÇÃO DO CONTRATO\nLOCAL DA EXECUÇÃO DO CONTRATO (PROCEDIMENTO)\nPaís: Portugal\nNUT III: PT11A\nLocalidade: Aveiro\nDistrito: Aveiro\nConcelho: Vale de Cambra\nFreguesia: União das Freguesias de Vila Chã, Codal e Vila Cova de Perrinho\n\n10 - PRAZO DE EXECUÇÃO DO CONTRATO\nPrazo de execução do contrato: 180 DIAS\nPrevisão de renovações: Não\n\n11 - FUNDOS EU\nTêm fundos EU? Não\n\n12 - DOCUMENTOS DE HABILITAÇÃO\nHabilitação para o exercício da atividade profissional: Sim\nTipo: Alvará\nDescrição: 1. O adjudicatário deve apresentar, no prazo de  05  dias a contar da notificação da decisão de adjudicação, os documentos de habilitação referidos no n.º 1, no n.º 2, no n.º 3 e na alínea a) do n.º 5 do artigo 81.º do Código dos Contratos Públicos.\n2. Para efeitos do disposto no n.º 2 do artigo 81.º do Código dos Contratos Públicos, o Alvará de Construção deve conter:\na) A classificação na  2ª  subcategoria da  10ª  categoria, em classe correspondente ao valor global da proposta.\n\n13 - CONDIÇÕES DE APRESENTAÇÃO\nPlataforma eletrónica utilizada pela entidade adjudicante: VORTAL\nURL para Apresentação: https://community.vortal.biz/public/\nAdmissibilidade da apresentação de propostas variantes: Não autorizado\nPrazo para apresentação das propostas: 18-10-2025 17:00\nPrazo durante o qual os concorrentes são obrigados a manter as respetivas propostas: 66 dias a contar do termo do prazo para a apresentação das propostas\nIndicação de Subcontratação na Proposta: Inexistência de indicação de subcontratação\n\n14 - PRESTAÇÃO DE CAUÇÃO\nPrestação de caução: Sim\nPercentagem: 5%\nDescrição da Garantia Exigida: De acordo com o programa de procedimento.\n\n15 - FORNECIMENTO DAS PEÇAS DO CONCURSO, APRESENTAÇÃO DE PEDIDOS DE PARTICIPAÇÃO E APRESENTAÇÃO DAS PROPOSTAS\nLink para acesso às peças do concurso (URL): https://community.vortal.biz/Public/public-tender-documents/d0p2WDc2MXk3RXphcEJxNEdLamJTaVNDSmpjaWZ5b3ZDaysvZTZqQU9Nd213TVZBUkx0Q3U2Q2t5SWxZTnJvMmV0V1k2VWtwK2FGTFVsZXNsM29RV0E9PWRheE1i\n\n20 - OUTROS REQUISITOS\nInformação sobre contratos reservados. Aplica-se a contratos reservados (54º-A)? Não\n\n21 - CRITÉRIO DE ADJUDICAÇÃO\nMultifator: Não\nMonofator:\nNome: Preço\n\n24 - CONDIÇÕES DO CONTRATO\nFaturação Eletrónica: Permitido\nObrigação de Subcontratação:\nCódigo da Obrigação de Subcontratação: Não é aplicável nenhuma obrigação de subcontratação.\n\n25 - COMPRA PÚBLICA ESTRATÉGICA\nCompra Pública Estratégica: Inexistência de contratação pública estratégica\n\n26 - INFORMAÇÕES ADICIONAIS\nContrato adequado para PME: Sim\nCobertura ACP (Acordo dos Contratos Públicos da Organização Mundial do Comércio): Não\n\n27 - IDENTIFICAÇÃO E CONTACTOS DO ÓRGÃO DE RECURSOS ADMINISTRATIVOS\nDesignação: José Alberto Freitas Soares Pinheiro e Silva\nEndereço: Av. Camilo Tavares de Matos, 19\nCódigo postal: 3730-240\nLocalidade: Vale de Cambra\nTelefone: +351 256420510\nFax: +351 256420519\nEndereço eletrónico: gap@cm-valedecambra.pt\nPrazo de interposição do recurso: 10 dias\n\n28 - IDENTIFICAÇÃO DO(S) AUTOR(ES) DE ANÚNCIO\nNome: José Alberto Freitas Soares Pinheiro e Silva\nCargo: Presidente da Câmara Municipal de Vale de Cambra\n419544275",
    "nipc": "506735524",
    "distrito": "Aveiro",
    "concelho": "Vale de Cambra",
    "freguesia": "Todas",
    "site": "www.cm-valedecambra.pt",
    "email": "vortal@cm-valedecambra.pt",
    "designacao_contrato": "OE-CP Nº 17/25 \"REQUALIFICAÇÃO DO CENTRO DESPORTIVO DAS GANDARINHAS\"",
    "descricao": "REABILITAÇÃO DE CAMPO DESPORTIVO",
    "preco_base": "278.570,65 EUR",
    "prazo_execucao": "180 DIAS",
    "prazo_apresentacao_propostas": "18-10-2025 17:00",
    "fundos_eu": "Não",
    "plataforma_eletronica": "VORTAL",
    "url_procedimento": "https://community.vortal.biz/public/",
    "autor_nome": "José Alberto Freitas Soares Pinheiro e Silva",
    "autor_cargo": "Presidente da Câmara Municipal de Vale de Cambra"
  },
  {
    "numero_procedimento": "N/A",
    "entidade": "ECOLEZIRIA-Tratamento Resíduos Sólidos, E.I.M.",
    "link": "https://diariodarepublica.pt/dr/detalhe/contrato-publico/24590-935747886",
    "detalhes_completos": "1 - IDENTIFICAÇÃO E CONTACTOS DA ENTIDADE ADJUDICANTE\nDesignação da entidade adjudicante: ECOLEZIRIA-Tratamento Resíduos Sólidos, E.I.M.\nNIPC: 504871650\nEndereço: Estrada Nacional 114, Raposa\nCódigo postal: 2080-701\nLocalidade: Santarém\nPaís: Portugal\nNUT III: PT185\nDistrito: Santarém\nConcelho: Almeirim\nFreguesia: Freguesia de Raposa\nTelefone: 243599003\nFax: 243599004\nEndereço da Entidade (URL): https://ecoleziria.pt/\nEndereço Eletrónico: ecoleziria@ecoleziria.pt\neDelivery Gateway (URL): https://community.vortal.biz/public/\nFunção da Organização: Adquirente\nNorma jurídica da Entidade Adjudicante: Organismo de direito público\nÁrea de atividade da Autoridade Adjudicante: Proteção ambiental\n\n2 - JORNAL OFICIAL DA UNIÃO EUROPEIA\nO procedimento a que este anúncio diz respeito também é publicitado no Jornal Oficial da União Europeia? Não\n\n3 - AVISO\nModelo de Anúncio: Concurso público\nData de Envio do Anúncio: 17-09-2025\n\n5 - PROCESSO\nTipo de Procedimento: Concurso público\nPreço base do procedimento: Sim\nValor do preço base do procedimento: 180.000,00 EUR\nProcedimento com lotes? Não\n\n6 - OBJETO DO CONTRATO\nNúmero de referência interna: 02/CP/ECO/2025\nDesignação do contrato: AQUISIÇÃO DE SERVIÇOS DE ALUGUER OPERACIONAL, HIGIENIZAÇÃO E MANUTENÇÃO DE VESTUÁRIO PROFISSIONAL PARA A ECOLEZÍRIA\nDescrição: AQUISIÇÃO DE SERVIÇOS DE ALUGUER OPERACIONAL, HIGIENIZAÇÃO E MANUTENÇÃO DE VESTUÁRIO PROFISSIONAL PARA A ECOLEZÍRIA\nTipo de Contrato Principal: Aquisição de Serviços\nTipo de Contrato: Aquisição de Serviços\nClassificação CPV (Vocabulário Comum para os Contratos Públicos)\nObjeto principal\nVocabulário Principal: 98312000\nPreço base s/IVA: 180.000,00 EUR\n\n7 - INDICAÇÕES ADICIONAIS\nO contrato envolve aquisição conjunta (satisfação de várias entidades)? Não\nO contrato é adjudicado por uma central de compras? Não\n\n8 - TÉCNICAS\nO concurso destina-se à celebração de um acordo-quadro? Inexistência de acordo-quadro\nÉ utilizado um leilão eletrónico? Não\nÉ adotada uma fase de negociação? Não\nSistema de Aquisição Dinâmico: Inexistência de sistema de aquisição dinâmico\n\n9 - LOCAL DA EXECUÇÃO DO CONTRATO\nLOCAL DA EXECUÇÃO DO CONTRATO (PROCEDIMENTO)\nPaís: Portugal\nNUT III: PT185\nLocalidade: Santarém\nDistrito: Santarém\nConcelho: Almeirim\nFreguesia: Freguesia de Raposa\n\n10 - PRAZO DE EXECUÇÃO DO CONTRATO\nPrazo de execução do contrato: 12 MESES\nPrevisão de renovações: Não\n\n11 - FUNDOS EU\nTêm fundos EU? Não\n\n12 - DOCUMENTOS DE HABILITAÇÃO\nHabilitação para o exercício da atividade profissional: Não\n\n13 - CONDIÇÕES DE APRESENTAÇÃO\nPlataforma eletrónica utilizada pela entidade adjudicante: VORTAL\nURL para Apresentação: https://community.vortal.biz/public/\nAdmissibilidade da apresentação de propostas variantes: Não autorizado\nPrazo para apresentação das propostas: 27-09-2025 23:59\nPrazo durante o qual os concorrentes são obrigados a manter as respetivas propostas: 66 dias a contar do termo do prazo para a apresentação das propostas\nIndicação de Subcontratação na Proposta: Inexistência de indicação de subcontratação\n\n14 - PRESTAÇÃO DE CAUÇÃO\nPrestação de caução: Não\n\n15 - FORNECIMENTO DAS PEÇAS DO CONCURSO, APRESENTAÇÃO DE PEDIDOS DE PARTICIPAÇÃO E APRESENTAÇÃO DAS PROPOSTAS\nLink para acesso às peças do concurso (URL): https://community.vortal.biz/Public/public-tender-documents/dEpuNmxUVzdpZ3JiM1JCTG9YZ1RGWmU3NDJDb2lOb0h4dGx2bk1SK0ZxWUptVzh6ZCtHRW9WZ1gxblJUVUE2SXZyRHRoR2ZJWWp5ZXAwQ2oxTWpGVlE9PTgwIzVH\n\n20 - OUTROS REQUISITOS\nInformação sobre contratos reservados. Aplica-se a contratos reservados (54º-A)? Não\n\n21 - CRITÉRIO DE ADJUDICAÇÃO\nMultifator: Não\nMonofator:\nNome: Preço\n\n24 - CONDIÇÕES DO CONTRATO\nFaturação Eletrónica: Permitido\nObrigação de Subcontratação:\nCódigo da Obrigação de Subcontratação: Não é aplicável nenhuma obrigação de subcontratação.\n\n25 - COMPRA PÚBLICA ESTRATÉGICA\nCompra Pública Estratégica: Inexistência de contratação pública estratégica\n\n26 - INFORMAÇÕES ADICIONAIS\nContrato adequado para PME: Sim\nCobertura ACP (Acordo dos Contratos Públicos da Organização Mundial do Comércio): Não\n\n27 - IDENTIFICAÇÃO E CONTACTOS DO ÓRGÃO DE RECURSOS ADMINISTRATIVOS\nDesignação: Rui Brites\nEndereço: Estrada Nacional 114, Raposa\nCódigo postal: 2080-701\nLocalidade: Almeirim\nTelefone: +351 243599002\nFax: +351 243599004\nEndereço eletrónico: ecoleziria@ecoleziria.pt\n\n28 - IDENTIFICAÇÃO DO(S) AUTOR(ES) DE ANÚNCIO\nNome: Vera Nunes\nCargo: Direção Técnica\n419544883",
    "nipc": "504871650",
    "distrito": "Santarém",
    "concelho": "Almeirim",
    "freguesia": "Freguesia de Raposa",
    "site": "https://ecoleziria.pt/",
    "email": "ecoleziria@ecoleziria.pt",
    "designacao_contrato": "AQUISIÇÃO DE SERVIÇOS DE ALUGUER OPERACIONAL, HIGIENIZAÇÃO E MANUTENÇÃO DE VESTUÁRIO PROFISSIONAL PARA A ECOLEZÍRIA",
    "descricao": "AQUISIÇÃO DE SERVIÇOS DE ALUGUER OPERACIONAL, HIGIENIZAÇÃO E MANUTENÇÃO DE VESTUÁRIO PROFISSIONAL PARA A ECOLEZÍRIA",
    "preco_base": "180.000,00 EUR",
    "prazo_execucao": "12 MESES",
    "prazo_apresentacao_propostas": "27-09-2025 23:59",
    "fundos_eu": "Não",
    "plataforma_eletronica": "VORTAL",
    "url_procedimento": "https://community.vortal.biz/public/",
    "autor_nome": "Vera Nunes",
    "autor_cargo": "Direção Técnica"
  },
  {
    "numero_procedimento": "N/A",
    "entidade": "AnÃºncio de procedimento  n.Âº 24593/2025  -  DiÃ¡rio da RepÃºblica n.Âº 180/2025, SÃ©rie II de 2025-09-18",
    "link": "https://diariodarepublica.pt/dr/detalhe/contrato-publico/24593-935747887"
  },
  {
    "numero_procedimento": "N/A",
    "entidade": "AnÃºncio de procedimento  n.Âº 24594/2025  -  DiÃ¡rio da RepÃºblica n.Âº 180/2025, SÃ©rie II de 2025-09-18",
    "link": "https://diariodarepublica.pt/dr/detalhe/contrato-publico/24594-935747888"
  },
  {
    "numero_procedimento": "N/A",
    "entidade": "AnÃºncio de procedimento  n.Âº 24595/2025  -  DiÃ¡rio da RepÃºblica n.Âº 180/2025, SÃ©rie II de 2025-09-18",
    "link": "https://diariodarepublica.pt/dr/detalhe/contrato-publico/24595-935747889"
  },
  {
    "numero_procedimento": "N/A",
    "entidade": "Comunidade Intermunicipal das Terras de Trás-os-Montes",
    "link": "https://diariodarepublica.pt/dr/detalhe/contrato-publico/24598-935747890",
    "detalhes_completos": "1 - IDENTIFICAÇÃO E CONTACTOS DA ENTIDADE ADJUDICANTE\nDesignação da entidade adjudicante: Comunidade Intermunicipal das Terras de Trás-os-Montes\nNIPC: 510957544\nEndereço: Rua Visconde da Bouça, apartado 238\nCódigo postal: 5300-318\nLocalidade: Bragança\nPaís: Portugal\nNUT III: PT11E\nDistrito: Braganca\nConcelho: Bragança\nFreguesia: Todas\nTelefone: 273327680\nEndereço da Entidade (URL): www.cim-ttm.pt\nEndereço Eletrónico: geral@cim-ttm.pt\neDelivery Gateway (URL): https://community.vortal.biz/public/\nFunção da Organização: Adquirente\nNorma jurídica da Entidade Adjudicante: Organismo de direito público\nÁrea de atividade da Autoridade Adjudicante: Serviços públicos das administrações públicas\n\n2 - JORNAL OFICIAL DA UNIÃO EUROPEIA\nO procedimento a que este anúncio diz respeito também é publicitado no Jornal Oficial da União Europeia? Sim\n\n3 - AVISO\nModelo de Anúncio: Concurso público\nData de Envio do Anúncio: 15-09-2025\n\n5 - PROCESSO\nTipo de Procedimento: Concurso público\nPreço base do procedimento: Sim\nValor do preço base do procedimento: 715.000,00 EUR\nProcedimento com lotes? Sim\nNº Máx. de Lotes Autorizado: 2\nNúmero máximo de lotes que podem ser adjudicados a um concorrente: 2\n\n6 - OBJETO DO CONTRATO\nNúmero de referência interna: PPA 117.CP_JOUE_Infraestrutura IoT e Verticais sen\nDesignação do contrato: Infraestrutura IoT e Verticais sensorizados\nDescrição: Infraestrutura IoT e Verticais sensorizados\nOpções: Não\nTipo de Contrato Principal: Aquisição de Bens Móveis\nTipo de Contrato: Aquisição de Bens Móveis\nClassificação CPV (Vocabulário Comum para os Contratos Públicos)\nObjeto principal\nVocabulário Principal: 35125100\nPreço base s/IVA: 715.000,00 EUR\nLotes: \nNº: LOT-0001\nDescrição do Lote: Lote 1 - Infraestrutura IoT\nPreço base s/IVA: 145.000,00 EUR\nClassificação CPV (Vocabulário Comum para os Contratos Públicos)\nObjeto principal\nVocabulário Principal: 35125100\nNº: LOT-0002\nDescrição do Lote: Lote 2 - Verticais sensorizados\nPreço base s/IVA: 570.000,00 EUR\nClassificação CPV (Vocabulário Comum para os Contratos Públicos)\nObjeto principal\nVocabulário Principal: 35125100\n\n7 - INDICAÇÕES ADICIONAIS\nO contrato envolve aquisição conjunta (satisfação de várias entidades)? Não\nO contrato é adjudicado por uma central de compras? Não\n\n8 - TÉCNICAS\nO concurso destina-se à celebração de um acordo-quadro? Inexistência de acordo-quadro\nÉ utilizado um leilão eletrónico? Não\nÉ adotada uma fase de negociação? Não\nSistema de Aquisição Dinâmico: Inexistência de sistema de aquisição dinâmico\n\n9 - LOCAL DA EXECUÇÃO DO CONTRATO\nLOCAL DA EXECUÇÃO DO CONTRATO (PROCEDIMENTO)\nPaís: Portugal\nNUT III: PT11E\nLocalidade: Bragança\nDistrito: Braganca\nConcelho: Bragança\nFreguesia: União das Freguesias de Sé, Santa Maria e Meixedo\nLOCAL DA EXECUÇÃO DO CONTRATO (LOTE)\nIdentificador do Lote: LOT-0001; LOT-0002\nPaís: Portugal\nNUT III: PT11E\nLocalidade: Bragança\nDistrito: Braganca\nConcelho: Bragança\nFreguesia: União das Freguesias de Sé, Santa Maria e Meixedo\n\n10 - PRAZO DE EXECUÇÃO DO CONTRATO\nIdentificador do Lote: LOT-0001; LOT-0002\nPrazo de execução do contrato: 133 DIAS\nPrevisão de renovações: Não\n\n11 - FUNDOS EU\nIdentificador do Lote: LOT-0001; LOT-0002\nTêm fundos EU? Sim\n\n12 - DOCUMENTOS DE HABILITAÇÃO\nHabilitação para o exercício da atividade profissional: Não\n\n13 - CONDIÇÕES DE APRESENTAÇÃO\nPlataforma eletrónica utilizada pela entidade adjudicante: VORTAL\nURL para Apresentação: https://community.vortal.biz/public/\nAdmissibilidade da apresentação de propostas variantes: Não autorizado\nPrazo para apresentação das propostas: 15-10-2025 17:30\nPrazo durante o qual os concorrentes são obrigados a manter as respetivas propostas: 120 dias a contar do termo do prazo para a apresentação das propostas\nApresentação de Catálogo Eletrónico: Não autorizado\nIndicação de Subcontratação na Proposta: Inexistência de indicação de subcontratação\n\n14 - PRESTAÇÃO DE CAUÇÃO\nPrestação de caução: Sim\nPercentagem: 5%\nDescrição da Garantia Exigida: Conforme Programa de Procedimento\n\n15 - FORNECIMENTO DAS PEÇAS DO CONCURSO, APRESENTAÇÃO DE PEDIDOS DE PARTICIPAÇÃO E APRESENTAÇÃO DAS PROPOSTAS\nLink para acesso às peças do concurso (URL): https://community.vortal.biz/Public/public-tender-documents/Z0Y4TjRYKy9rZytjeFJBSGJpeXhhVFVPamgwVGJOK29weVZsL1Fhak1WNWNWQlMzYk1tRHVhek9pSlZvSW43b3lqcFhlSTVGWWRteVhZMGlyWnNSVmc9PXo2KHhU\n\n20 - OUTROS REQUISITOS\nIdentificador do Lote: LOT-0001; LOT-0002\nInformação sobre contratos reservados. Aplica-se a contratos reservados (54º-A)? Não\n\n21 - CRITÉRIO DE ADJUDICAÇÃO\nO Critério de adjudicação é diferenciado por lote? Não\nMultifator: Sim\nFator: \nNome: Preço\nPonderação: 20%\nSubfatores: Não\nFator: \nNome: Qualidade\nPonderação: 25%\nSubfatores: Não\nFator: \nNome: Qualidade\nPonderação: 55%\nSubfatores: Não\n\n24 - CONDIÇÕES DO CONTRATO\nIdentificador do Lote: LOT-0001; LOT-0002\nFaturação Eletrónica: Permitido\nObrigação de Subcontratação:\nCódigo da Obrigação de Subcontratação: Não é aplicável nenhuma obrigação de subcontratação.\n\n25 - COMPRA PÚBLICA ESTRATÉGICA\nCompra Pública Estratégica: Inexistência de contratação pública estratégica\n\n26 - INFORMAÇÕES ADICIONAIS\nIdentificador do Lote: LOT-0001; LOT-0002\nContrato adequado para PME: Sim\nCobertura ACP (Acordo dos Contratos Públicos da Organização Mundial do Comércio): Não\n\n27 - IDENTIFICAÇÃO E CONTACTOS DO ÓRGÃO DE RECURSOS ADMINISTRATIVOS\nDesignação: Conselho Intermunicipal\nEndereço: Rua Visconde da Bouça, apartado 238\nCódigo postal: 5300-318\nLocalidade: Bragança\nTelefone: +351 273327680\nFax: +351 273331938\nEndereço eletrónico: compras@cim-ttm.pt\n\n28 - IDENTIFICAÇÃO DO(S) AUTOR(ES) DE ANÚNCIO\nNome: Manuel António Alves Miranda\nCargo: Secretário Intermunicipal\n419534888",
    "nipc": "510957544",
    "distrito": "Braganca",
    "concelho": "Bragança",
    "freguesia": "Todas",
    "site": "www.cim-ttm.pt",
    "email": "geral@cim-ttm.pt",
    "designacao_contrato": "Infraestrutura IoT e Verticais sensorizados",
    "descricao": "Infraestrutura IoT e Verticais sensorizados",
    "preco_base": "715.000,00 EUR",
    "prazo_execucao": "133 DIAS",
    "prazo_apresentacao_propostas": "15-10-2025 17:30",
    "fundos_eu": "Sim",
    "plataforma_eletronica": "VORTAL",
    "url_procedimento": "https://community.vortal.biz/public/",
    "autor_nome": "Manuel António Alves Miranda",
    "autor_cargo": "Secretário Intermunicipal"
  },
  {
    "numero_procedimento": "N/A",
    "entidade": "Comunidade Intermunicipal das Terras de Trás-os-Montes",
    "link": "https://diariodarepublica.pt/dr/detalhe/contrato-publico/24599-935747891",
    "detalhes_completos": "1 - IDENTIFICAÇÃO E CONTACTOS DA ENTIDADE ADJUDICANTE\nDesignação da entidade adjudicante: Comunidade Intermunicipal das Terras de Trás-os-Montes\nNIPC: 510957544\nEndereço: Rua Visconde da Bouça, apartado 238\nCódigo postal: 5300-318\nLocalidade: Bragança\nPaís: Portugal\nNUT III: PT11E\nDistrito: Braganca\nConcelho: Bragança\nFreguesia: Todas\nTelefone: 273327680\nEndereço da Entidade (URL): www.cim-ttm.pt\nEndereço Eletrónico: geral@cim-ttm.pt\neDelivery Gateway (URL): https://community.vortal.biz/public/\nFunção da Organização: Adquirente\nNorma jurídica da Entidade Adjudicante: Organismo de direito público\nÁrea de atividade da Autoridade Adjudicante: Serviços públicos das administrações públicas\n\n2 - JORNAL OFICIAL DA UNIÃO EUROPEIA\nO procedimento a que este anúncio diz respeito também é publicitado no Jornal Oficial da União Europeia? Sim\n\n3 - AVISO\nModelo de Anúncio: Concurso público\nData de Envio do Anúncio: 15-09-2025\n\n5 - PROCESSO\nTipo de Procedimento: Concurso público\nPreço base do procedimento: Sim\nValor do preço base do procedimento: 645.000,00 EUR\nProcedimento com lotes? Não\n\n6 - OBJETO DO CONTRATO\nNúmero de referência interna: PPA 116.CP_JOUE_Plataforma de Gestão Urbana\nDesignação do contrato: Plataforma de Gestão Urbana, Verticais e Integrações\nDescrição: Plataforma de Gestão Urbana, Verticais e Integrações\nOpções: Não\nTipo de Contrato Principal: Aquisição de Bens Móveis\nTipo de Contrato: Aquisição de Bens Móveis\nClassificação CPV (Vocabulário Comum para os Contratos Públicos)\nObjeto principal\nVocabulário Principal: 48211000\nPreço base s/IVA: 645.000,00 EUR\n\n7 - INDICAÇÕES ADICIONAIS\nO contrato envolve aquisição conjunta (satisfação de várias entidades)? Não\nO contrato é adjudicado por uma central de compras? Não\n\n8 - TÉCNICAS\nO concurso destina-se à celebração de um acordo-quadro? Inexistência de acordo-quadro\nÉ utilizado um leilão eletrónico? Não\nÉ adotada uma fase de negociação? Não\nSistema de Aquisição Dinâmico: Inexistência de sistema de aquisição dinâmico\n\n9 - LOCAL DA EXECUÇÃO DO CONTRATO\nLOCAL DA EXECUÇÃO DO CONTRATO (PROCEDIMENTO)\nPaís: Portugal\nNUT III: PT11E\nLocalidade: Bragança\nDistrito: Braganca\nConcelho: Bragança\nFreguesia: União das Freguesias de Sé, Santa Maria e Meixedo\n\n10 - PRAZO DE EXECUÇÃO DO CONTRATO\nPrazo de execução do contrato: 133 DIAS\nPrevisão de renovações: Não\n\n11 - FUNDOS EU\nTêm fundos EU? Sim\n\n12 - DOCUMENTOS DE HABILITAÇÃO\nHabilitação para o exercício da atividade profissional: Sim\nTipo: Outros\nDescrição - Outros: Conforme Programa de Procedimento\nDescrição: De acordo com o Programa de Procedimento\n\n13 - CONDIÇÕES DE APRESENTAÇÃO\nPlataforma eletrónica utilizada pela entidade adjudicante: VORTAL\nURL para Apresentação: https://community.vortal.biz/public/\nAdmissibilidade da apresentação de propostas variantes: Não autorizado\nPrazo para apresentação das propostas: 15-10-2025 17:30\nPrazo durante o qual os concorrentes são obrigados a manter as respetivas propostas: 120 dias a contar do termo do prazo para a apresentação das propostas\nApresentação de Catálogo Eletrónico: Não autorizado\nIndicação de Subcontratação na Proposta: Inexistência de indicação de subcontratação\n\n14 - PRESTAÇÃO DE CAUÇÃO\nPrestação de caução: Sim\nPercentagem: 5%\nDescrição da Garantia Exigida: Cf. Programa de Procedimento\n\n15 - FORNECIMENTO DAS PEÇAS DO CONCURSO, APRESENTAÇÃO DE PEDIDOS DE PARTICIPAÇÃO E APRESENTAÇÃO DAS PROPOSTAS\nLink para acesso às peças do concurso (URL): https://community.vortal.biz/Public/public-tender-documents/blJ4Mk9lL0dHQnZyWmEwQWo0RWhlREdMVGtSa0E4OVY5dVBQdnlJMnUwMm9CTmdVZHYrUWt3NDFSWlhqQkY0ZGMxc3huNE5QNDRnZDFuTlprYnBzQUE9PTlAdV9U\n\n20 - OUTROS REQUISITOS\nInformação sobre contratos reservados. Aplica-se a contratos reservados (54º-A)? Não\n\n21 - CRITÉRIO DE ADJUDICAÇÃO\nMultifator: Sim\nFator: \nNome: Preço\nPonderação: 20%\nSubfatores: Não\nFator: \nNome: Qualidade\nPonderação: 25%\nSubfatores: Não\nFator: \nNome: Qualidade\nPonderação: 55%\nSubfatores: Não\n\n24 - CONDIÇÕES DO CONTRATO\nFaturação Eletrónica: Permitido\nObrigação de Subcontratação:\nCódigo da Obrigação de Subcontratação: Não é aplicável nenhuma obrigação de subcontratação.\n\n25 - COMPRA PÚBLICA ESTRATÉGICA\nCompra Pública Estratégica: Inexistência de contratação pública estratégica\n\n26 - INFORMAÇÕES ADICIONAIS\nContrato adequado para PME: Sim\nCobertura ACP (Acordo dos Contratos Públicos da Organização Mundial do Comércio): Não\n\n27 - IDENTIFICAÇÃO E CONTACTOS DO ÓRGÃO DE RECURSOS ADMINISTRATIVOS\nDesignação: Conselho Intermunicipal\nEndereço: Rua Visconde da Bouça, apartado 238\nCódigo postal: 5300-318\nLocalidade: Bragança\nTelefone: +351 273327680\nFax: +351 273331938\nEndereço eletrónico: compras@cim-ttm.pt\n\n28 - IDENTIFICAÇÃO DO(S) AUTOR(ES) DE ANÚNCIO\nNome: Manuel António Alves Miranda\nCargo: Secretário Intermunicipal\n419534385",
    "nipc": "510957544",
    "distrito": "Braganca",
    "concelho": "Bragança",
    "freguesia": "Todas",
    "site": "www.cim-ttm.pt",
    "email": "geral@cim-ttm.pt",
    "designacao_contrato": "Plataforma de Gestão Urbana, Verticais e Integrações",
    "descricao": "Plataforma de Gestão Urbana, Verticais e Integrações",
    "preco_base": "645.000,00 EUR",
    "prazo_execucao": "133 DIAS",
    "prazo_apresentacao_propostas": "15-10-2025 17:30",
    "fundos_eu": "Sim",
    "plataforma_eletronica": "VORTAL",
    "url_procedimento": "https://community.vortal.biz/public/",
    "autor_nome": "Manuel António Alves Miranda",
    "autor_cargo": "Secretário Intermunicipal"
  },
  {
    "numero_procedimento": "N/A",
    "entidade": "Município da Moita",
    "link": "https://diariodarepublica.pt/dr/detalhe/contrato-publico/24600-935747892",
    "detalhes_completos": "1 - IDENTIFICAÇÃO E CONTACTOS DA ENTIDADE ADJUDICANTE\nDesignação da entidade adjudicante: Município da Moita\nNIPC: 506791220\nServiço/Órgão/Pessoa de contacto: Júri\nEndereço: Praça da República\nCódigo postal: 2860-397\nLocalidade: Moita\nPaís: Portugal\nNUT III: PT170\nDistrito: Setúbal\nConcelho: Moita\nFreguesia: Todas\nTelefone: 212806700\nFax: 212806700\nEndereço da Entidade (URL): https://www.cm-moita.pt/\nEndereço Eletrónico: gab.aprovisionamento@cm-moita.pt\nFunção da Organização: Adquirente\nNorma jurídica da Entidade Adjudicante: Organismo de direito público\nÁrea de atividade da Autoridade Adjudicante: Serviços públicos das administrações públicas\n\n2 - JORNAL OFICIAL DA UNIÃO EUROPEIA\nO procedimento a que este anúncio diz respeito também é publicitado no Jornal Oficial da União Europeia? Sim\n\n3 - AVISO\nModelo de Anúncio: Concurso público\nData de Envio do Anúncio: 15-09-2025\n\n5 - PROCESSO\nTipo de Procedimento: Concurso público\nPreço base do procedimento: Sim\nValor do preço base do procedimento: 0,14 EUR\nProcedimento com lotes? Não\n\n6 - OBJETO DO CONTRATO\nNúmero de referência interna: 19/CP/CMM/2025\nDesignação do contrato: Cedência Temporária de Espaços/Instalações Municipais (coberturas dos edifícios, outros equipamentos e solos) para instalação de unidades de produção para auto consumo coletivo/comunidade de energia renovável\nDescrição: Cedência Temporária de Espaços/Instalações Municipais (coberturas dos edifícios, outros\nequipamentos e solos) para instalação de unidades de produção para auto consumo coletivo/comunidade de\nenergia renovável\nOpções: Não\nTipo de Contrato Principal: Aquisição de Serviços\nTipo de Contrato: Aquisição de Serviços\nClassificação CPV (Vocabulário Comum para os Contratos Públicos)\nObjeto principal\nVocabulário Principal: 71314000\nPreço base s/IVA: 0,14 EUR\n\n7 - INDICAÇÕES ADICIONAIS\nO contrato envolve aquisição conjunta (satisfação de várias entidades)? Não\nO contrato é adjudicado por uma central de compras? Não\n\n8 - TÉCNICAS\nO concurso destina-se à celebração de um acordo-quadro? Inexistência de acordo-quadro\nÉ utilizado um leilão eletrónico? Não\nÉ adotada uma fase de negociação? Não\nSistema de Aquisição Dinâmico: Inexistência de sistema de aquisição dinâmico\n\n9 - LOCAL DA EXECUÇÃO DO CONTRATO\nLOCAL DA EXECUÇÃO DO CONTRATO (PROCEDIMENTO)\nPaís: Portugal\nNUT III: PT170\nLocalidade: Moita\nDistrito: Setúbal\nConcelho: Moita\nFreguesia: Todas\n\n10 - PRAZO DE EXECUÇÃO DO CONTRATO\nPrazo de execução do contrato: 15 ANOS\nPrevisão de renovações: Não\n\n11 - FUNDOS EU\nTêm fundos EU? Não\n\n12 - DOCUMENTOS DE HABILITAÇÃO\nHabilitação para o exercício da atividade profissional: Não\n\n13 - CONDIÇÕES DE APRESENTAÇÃO\nPlataforma eletrónica utilizada pela entidade adjudicante: ACIN\nURL para Apresentação: https://www.acingov.pt\nAdmissibilidade da apresentação de propostas variantes: Não autorizado\nPrazo para apresentação das propostas: 06-10-2025 23:59\nPrazo durante o qual os concorrentes são obrigados a manter as respetivas propostas: 90 dias a contar do termo do prazo para a apresentação das propostas\nApresentação de Catálogo Eletrónico: Não autorizado\nIndicação de Subcontratação na Proposta: Inexistência de indicação de subcontratação\n\n14 - PRESTAÇÃO DE CAUÇÃO\nPrestação de caução: Sim\nPercentagem: 1%\nDescrição da Garantia Exigida: O valor da caução é de 1.00% do preço contratual.\n\n15 - FORNECIMENTO DAS PEÇAS DO CONCURSO, APRESENTAÇÃO DE PEDIDOS DE PARTICIPAÇÃO E APRESENTAÇÃO DAS PROPOSTAS\nLink para acesso às peças do concurso (URL): https://www.acingov.pt/acingovprod/2/zonaPublica/zona_publica_c/donwloadProcedurePiece/OTI2NjEy\n\n20 - OUTROS REQUISITOS\nInformação sobre contratos reservados. Aplica-se a contratos reservados (54º-A)? Não\n\n21 - CRITÉRIO DE ADJUDICAÇÃO\nMultifator: Não\nMonofator:\nNome: Preço\n\n24 - CONDIÇÕES DO CONTRATO\nFaturação Eletrónica: Permitido\nObrigação de Subcontratação:\nCódigo da Obrigação de Subcontratação: Não é aplicável nenhuma obrigação de subcontratação.\n\n25 - COMPRA PÚBLICA ESTRATÉGICA\nCompra Pública Estratégica: Inexistência de contratação pública estratégica\n\n26 - INFORMAÇÕES ADICIONAIS\nContrato adequado para PME: Sim\nCobertura ACP (Acordo dos Contratos Públicos da Organização Mundial do Comércio): Não\n\n27 - IDENTIFICAÇÃO E CONTACTOS DO ÓRGÃO DE RECURSOS ADMINISTRATIVOS\nDesignação: Presidente da Câmara\nEndereço: Praça da República\nCódigo postal: 2860-397\nLocalidade: Moita\nTelefone: 212806700\nFax: \nEndereço eletrónico: gab.aprovisionamento@cm-moita.pt\nPrazo de interposição do recurso: 10 dias\n\n28 - IDENTIFICAÇÃO DO(S) AUTOR(ES) DE ANÚNCIO\nNome: Carlos Edgar Rodrigues Sá Albino\nCargo: Presidente de Câmara\n419536215",
    "nipc": "506791220",
    "distrito": "Setúbal",
    "concelho": "Moita",
    "freguesia": "Todas",
    "site": "https://www.cm-moita.pt/",
    "email": "gab.aprovisionamento@cm-moita.pt",
    "designacao_contrato": "Cedência Temporária de Espaços/Instalações Municipais (coberturas dos edifícios, outros equipamentos e solos) para instalação de unidades de produção para auto consumo coletivo/comunidade de energia renovável",
    "descricao": "Cedência Temporária de Espaços/Instalações Municipais (coberturas dos edifícios, outros",
    "preco_base": "0,14 EUR",
    "prazo_execucao": "15 ANOS",
    "prazo_apresentacao_propostas": "06-10-2025 23:59",
    "fundos_eu": "Não",
    "plataforma_eletronica": "ACIN",
    "url_procedimento": "https://www.acingov.pt",
    "autor_nome": "Carlos Edgar Rodrigues Sá Albino",
    "autor_cargo": "Presidente de Câmara"
  },
  {
    "numero_procedimento": "N/A",
    "entidade": "ASSOCIAÇÃO PARA FORMAÇÃO PROFISSIONAL E DESENVOLVIMENTO DO MONTIJO",
    "link": "https://diariodarepublica.pt/dr/detalhe/contrato-publico/24609-935747894",
    "detalhes_completos": "1 - IDENTIFICAÇÃO E CONTACTOS DA ENTIDADE ADJUDICANTE\nDesignação da entidade adjudicante: ASSOCIAÇÃO PARA FORMAÇÃO PROFISSIONAL E DESENVOLVIMENTO DO MONTIJO\nNIPC: 504514547\nEndereço: Rua José de Almada Negreiros, 217\nCódigo postal: 2870-442\nLocalidade: Setúbal\nPaís: Portugal\nNUT III: PT170\nDistrito: Setúbal\nConcelho: Montijo\nFreguesia: União das Freguesias de Montijo e Afonsoeiro\nTelefone: 212313685\nFax: 212313685\nEndereço da Entidade (URL): https://afpdm.com/\nEndereço Eletrónico: contratacao.publica@epmontijo.edu.pt\neDelivery Gateway (URL): https://community.vortal.biz/public/\nFunção da Organização: Adquirente\nNorma jurídica da Entidade Adjudicante: Organismo de direito público\nÁrea de atividade da Autoridade Adjudicante: Educação\n\n2 - JORNAL OFICIAL DA UNIÃO EUROPEIA\nO procedimento a que este anúncio diz respeito também é publicitado no Jornal Oficial da União Europeia? Sim\n\n3 - AVISO\nModelo de Anúncio: Concurso público\nData de Envio do Anúncio: 15-09-2025\n\n5 - PROCESSO\nTipo de Procedimento: Concurso público\nPreço base do procedimento: Sim\nValor do preço base do procedimento: 7.222,20 EUR\nProcedimento com lotes? Não\n\n6 - OBJETO DO CONTRATO\nNúmero de referência interna: 35/2025\nDesignação do contrato: Aquisição de equipamento didático para formação de hidrogénio, no âmbito do PRR\nDescrição: Aquisição de equipamento didático para formação de hidrogénio, no âmbito do PRR\nOpções: Não\nTipo de Contrato Principal: Aquisição de Bens Móveis\nTipo de Contrato: Aquisição de Bens Móveis\nClassificação CPV (Vocabulário Comum para os Contratos Públicos)\nObjeto principal\nVocabulário Principal: 39162000\nPreço base s/IVA: 7.222,20 EUR\n\n7 - INDICAÇÕES ADICIONAIS\nO contrato envolve aquisição conjunta (satisfação de várias entidades)? Não\nO contrato é adjudicado por uma central de compras? Não\n\n8 - TÉCNICAS\nO concurso destina-se à celebração de um acordo-quadro? Inexistência de acordo-quadro\nÉ utilizado um leilão eletrónico? Não\nÉ adotada uma fase de negociação? Não\nSistema de Aquisição Dinâmico: Inexistência de sistema de aquisição dinâmico\n\n9 - LOCAL DA EXECUÇÃO DO CONTRATO\nLOCAL DA EXECUÇÃO DO CONTRATO (PROCEDIMENTO)\nPaís: Portugal\nNUT III: PT170\nLocalidade: Setúbal\nDistrito: Setúbal\nConcelho: Montijo\nFreguesia: União das Freguesias de Montijo e Afonsoeiro\n\n10 - PRAZO DE EXECUÇÃO DO CONTRATO\nPrazo de execução do contrato: 25 DIAS\nPrevisão de renovações: Não\n\n11 - FUNDOS EU\nTêm fundos EU? Sim\n\n12 - DOCUMENTOS DE HABILITAÇÃO\nHabilitação para o exercício da atividade profissional: Não\n\n13 - CONDIÇÕES DE APRESENTAÇÃO\nPlataforma eletrónica utilizada pela entidade adjudicante: VORTAL\nURL para Apresentação: https://community.vortal.biz/public/\nAdmissibilidade da apresentação de propostas variantes: Não autorizado\nPrazo para apresentação das propostas: 15-10-2025 18:00\nPrazo durante o qual os concorrentes são obrigados a manter as respetivas propostas: 120 dias a contar do termo do prazo para a apresentação das propostas\nApresentação de Catálogo Eletrónico: Não autorizado\nIndicação de Subcontratação na Proposta: Inexistência de indicação de subcontratação\n\n14 - PRESTAÇÃO DE CAUÇÃO\nPrestação de caução: Não\n\n15 - FORNECIMENTO DAS PEÇAS DO CONCURSO, APRESENTAÇÃO DE PEDIDOS DE PARTICIPAÇÃO E APRESENTAÇÃO DAS PROPOSTAS\nLink para acesso às peças do concurso (URL): https://community.vortal.biz/Public/public-tender-documents/QThPVjkyS0pMLy9TSnJtMFdtMk02T1RsUFpRc0RCVlE2ZHY4SHVjeXI5Qm9lLyt2N0NaNjVjYlFtaVlMS0lORWM2cjM2N0QwS09POHZ3RExrYUIxZXc9PVhjd3JN\n\n20 - OUTROS REQUISITOS\nInformação sobre contratos reservados. Aplica-se a contratos reservados (54º-A)? Não\n\n21 - CRITÉRIO DE ADJUDICAÇÃO\nMultifator: Não\nMonofator:\nNome: Preço\n\n24 - CONDIÇÕES DO CONTRATO\nFaturação Eletrónica: Permitido\nObrigação de Subcontratação:\nCódigo da Obrigação de Subcontratação: Não é aplicável nenhuma obrigação de subcontratação.\n\n25 - COMPRA PÚBLICA ESTRATÉGICA\nCompra Pública Estratégica: Inexistência de contratação pública estratégica\n\n26 - INFORMAÇÕES ADICIONAIS\nContrato adequado para PME: Sim\nCobertura ACP (Acordo dos Contratos Públicos da Organização Mundial do Comércio): Não\n\n27 - IDENTIFICAÇÃO E CONTACTOS DO ÓRGÃO DE RECURSOS ADMINISTRATIVOS\nDesignação: Associação para Formação Profissional e Desenvolvimento do Montijo\nEndereço: Rua José de Almada Negreiros n.º 217\nCódigo postal: 2870-442\nLocalidade: Montijo\nTelefone: +351 212313862\nFax: +351 000000000\nEndereço eletrónico: contratacao.publica@epmontijo.edu.pt\n\n28 - IDENTIFICAÇÃO DO(S) AUTOR(ES) DE ANÚNCIO\nNome: Teresa Isabel Roberto Carvalho\nCargo: Presidente da Associação para Formação Profissional e Desenvolvimento do Montijo\n419537488",
    "nipc": "504514547",
    "distrito": "Setúbal",
    "concelho": "Montijo",
    "freguesia": "União das Freguesias de Montijo e Afonsoeiro",
    "site": "https://afpdm.com/",
    "email": "contratacao.publica@epmontijo.edu.pt",
    "designacao_contrato": "Aquisição de equipamento didático para formação de hidrogénio, no âmbito do PRR",
    "descricao": "Aquisição de equipamento didático para formação de hidrogénio, no âmbito do PRR",
    "preco_base": "7.222,20 EUR",
    "prazo_execucao": "25 DIAS",
    "prazo_apresentacao_propostas": "15-10-2025 18:00",
    "fundos_eu": "Sim",
    "plataforma_eletronica": "VORTAL",
    "url_procedimento": "https://community.vortal.biz/public/",
    "autor_nome": "Teresa Isabel Roberto Carvalho",
    "autor_cargo": "Presidente da Associação para Formação Profissional e Desenvolvimento do Montijo"
  },
  {
    "numero_procedimento": "N/A",
    "entidade": "Águas do Norte, S.A.",
    "link": "https://diariodarepublica.pt/dr/detalhe/contrato-publico/24610-935752322",
    "detalhes_completos": "1 - IDENTIFICAÇÃO E CONTACTOS DA ENTIDADE ADJUDICANTE\nDesignação da entidade adjudicante: Águas do Norte, S.A.\nNIPC: 513606084\nServiço/Órgão/Pessoa de contacto: Compras e Logística\nEndereço: Rua Dom Pedro de Castro, n.º 1A\nCódigo postal: 5000-669\nLocalidade: Vila Real\nPaís: Portugal\nNUT III: PT11D\nDistrito: Vila Real\nConcelho: Vila Real\nFreguesia: Freguesia de Vila Real\nTelefone: 259309370\nFax: 259309371\nEndereço da Entidade (URL): www.adnorte.pt\nEndereço Eletrónico: geral.adnorte@adp.pt\neDelivery Gateway (URL): https://www.acingov.pt\nFunção da Organização: Adquirente\nNorma jurídica da Entidade Adjudicante: Organismo de direito público\nÁrea de atividade da Autoridade Adjudicante: Serviços públicos das administrações públicas\n\n2 - JORNAL OFICIAL DA UNIÃO EUROPEIA\nO procedimento a que este anúncio diz respeito também é publicitado no Jornal Oficial da União Europeia? Sim\n\n3 - AVISO\nModelo de Anúncio: Concurso público\nData de Envio do Anúncio: 16-09-2025\n\n5 - PROCESSO\nTipo de Procedimento: Concurso público\nPreço base do procedimento: Sim\nValor do preço base do procedimento: 1.031.500,00 EUR\nProcedimento com lotes? Sim\nNº Máx. de Lotes Autorizado: 7\nNúmero máximo de lotes que podem ser adjudicados a um concorrente: 7\n\n6 - OBJETO DO CONTRATO\nNúmero de referência interna: PRC_0054/2025_DEX\nDesignação do contrato: PRC_0054/2025_DEX -Aquisição de grupos eletrobomba para a Águas do Norte, S.A..\nDescrição: PRC_0054/2025_DEX -Aquisição de grupos eletrobomba para a Águas do Norte, S.A..\nOpções: Não\nTipo de Contrato Principal: Aquisição de Bens Móveis\nTipo de Contrato: Aquisição de Bens Móveis\nClassificação CPV (Vocabulário Comum para os Contratos Públicos)\nObjeto principal\nVocabulário Principal: 42122000\nPreço base s/IVA: 1.031.500,00 EUR\nLotes: \nNº: LOT-0001\nDescrição do Lote: Lote 1 - EE Feirão\nPreço base s/IVA: 318.500,00 EUR\nClassificação CPV (Vocabulário Comum para os Contratos Públicos)\nObjeto principal\nVocabulário Principal: 42122000\nNº: LOT-0002\nDescrição do Lote: Lote 2 - EE Parafita\nPreço base s/IVA: 178.000,00 EUR\nClassificação CPV (Vocabulário Comum para os Contratos Públicos)\nObjeto principal\nVocabulário Principal: 42122000\nNº: LOT-0003\nDescrição do Lote: Lote 3  EE Intermédia Rabagão\nPreço base s/IVA: 95.000,00 EUR\nClassificação CPV (Vocabulário Comum para os Contratos Públicos)\nObjeto principal\nVocabulário Principal: 42122000\nNº: LOT-0004\nDescrição do Lote: Lote 4  EE Ceivães\nPreço base s/IVA: 83.000,00 EUR\nClassificação CPV (Vocabulário Comum para os Contratos Públicos)\nObjeto principal\nVocabulário Principal: 42122000\nNº: LOT-0005\nDescrição do Lote: Lote 5  EE-ETA Lara Pinheiros\nPreço base s/IVA: 191.000,00 EUR\nClassificação CPV (Vocabulário Comum para os Contratos Públicos)\nObjeto principal\nVocabulário Principal: 42122000\nNº: LOT-0006\nDescrição do Lote: Lote 6  ETA Lapela\nPreço base s/IVA: 8.000,00 EUR\nClassificação CPV (Vocabulário Comum para os Contratos Públicos)\nObjeto principal\nVocabulário Principal: 42122000\nNº: LOT-0007\nDescrição do Lote: Lote 7  EE Barradas- Cerite\nPreço base s/IVA: 158.000,00 EUR\nClassificação CPV (Vocabulário Comum para os Contratos Públicos)\nObjeto principal\nVocabulário Principal: 42122000\n\n7 - INDICAÇÕES ADICIONAIS\nO contrato envolve aquisição conjunta (satisfação de várias entidades)? Não\nO contrato é adjudicado por uma central de compras? Não\n\n8 - TÉCNICAS\nO concurso destina-se à celebração de um acordo-quadro? Inexistência de acordo-quadro\nÉ utilizado um leilão eletrónico? Não\nÉ adotada uma fase de negociação? Não\nSistema de Aquisição Dinâmico: Inexistência de sistema de aquisição dinâmico\n\n9 - LOCAL DA EXECUÇÃO DO CONTRATO\nLOCAL DA EXECUÇÃO DO CONTRATO (PROCEDIMENTO)\nPaís: Portugal\nNUT III: PT119\nLocalidade: União das Freguesias de Ruivães e Campos\nDistrito: Braga\nConcelho: Vieira do Minho\nFreguesia: União das Freguesias de Ruivães e Campos\nPaís: Portugal\nNUT III: PT119\nLocalidade: Freguesia de Louro\nDistrito: Braga\nConcelho: Vila Nova de Famalicão\nFreguesia: Freguesia de Louro\nPaís: Portugal\nNUT III: PT111\nLocalidade: União das Freguesias de Ceivães e Badim\nDistrito: Viana do Castelo\nConcelho: Monção\nFreguesia: União das Freguesias de Ceivães e Badim\nPaís: Portugal\nNUT III: PT111\nLocalidade: Freguesia de Lara\nDistrito: Viana do Castelo\nConcelho: Monção\nFreguesia: Freguesia de Lara\nPaís: Portugal\nNUT III: PT111\nLocalidade: União das Freguesias de Troporiz e Lapela\nDistrito: Viana do Castelo\nConcelho: Monção\nFreguesia: União das Freguesias de Troporiz e Lapela\nPaís: Portugal\nNUT III: PT11D\nLocalidade: União das Freguesias de Bigorne, Magueija e Pretarouca\nDistrito: Viseu\nConcelho: Lamego\nFreguesia: União das Freguesias de Bigorne, Magueija e Pretarouca\nLOCAL DA EXECUÇÃO DO CONTRATO (LOTE)\nIdentificador do Lote: LOT-0001; LOT-0002; LOT-0003; LOT-0004; LOT-0005; LOT-0006; LOT-0007\nPaís: Portugal\nNUT III: PT119\nLocalidade: Freguesia de Louro\nDistrito: Braga\nConcelho: Vila Nova de Famalicão\nFreguesia: Freguesia de Louro\nIdentificador do Lote: LOT-0001; LOT-0002; LOT-0003; LOT-0004; LOT-0005; LOT-0006; LOT-0007\nPaís: Portugal\nNUT III: PT119\nLocalidade: União das Freguesias de Ruivães e Campos\nDistrito: Braga\nConcelho: Vieira do Minho\nFreguesia: União das Freguesias de Ruivães e Campos\nIdentificador do Lote: LOT-0001; LOT-0002; LOT-0003; LOT-0004; LOT-0005; LOT-0006; LOT-0007\nPaís: Portugal\nNUT III: PT111\nLocalidade: Freguesia de Lara\nDistrito: Viana do Castelo\nConcelho: Monção\nFreguesia: Freguesia de Lara\nIdentificador do Lote: LOT-0001; LOT-0002; LOT-0003; LOT-0004; LOT-0005; LOT-0006; LOT-0007\nPaís: Portugal\nNUT III: PT111\nLocalidade: União das Freguesias de Ceivães e Badim\nDistrito: Viana do Castelo\nConcelho: Monção\nFreguesia: União das Freguesias de Ceivães e Badim\nIdentificador do Lote: LOT-0001; LOT-0002; LOT-0003; LOT-0004; LOT-0005; LOT-0006; LOT-0007\nPaís: Portugal\nNUT III: PT111\nLocalidade: União das Freguesias de Troporiz e Lapela\nDistrito: Viana do Castelo\nConcelho: Monção\nFreguesia: União das Freguesias de Troporiz e Lapela\nIdentificador do Lote: LOT-0001; LOT-0002; LOT-0003; LOT-0004; LOT-0005; LOT-0006; LOT-0007\nPaís: Portugal\nNUT III: PT11D\nLocalidade: União das Freguesias de Bigorne, Magueija e Pretarouca\nDistrito: Viseu\nConcelho: Lamego\nFreguesia: União das Freguesias de Bigorne, Magueija e Pretarouca\n\n10 - PRAZO DE EXECUÇÃO DO CONTRATO\nIdentificador do Lote: LOT-0001; LOT-0002; LOT-0003; LOT-0004; LOT-0005; LOT-0006; LOT-0007\nPrazo de execução do contrato: 10 MESES\nPrevisão de renovações: Não\n\n11 - FUNDOS EU\nIdentificador do Lote: LOT-0001; LOT-0002; LOT-0003; LOT-0004; LOT-0005; LOT-0006; LOT-0007\nTêm fundos EU? Não\n\n12 - DOCUMENTOS DE HABILITAÇÃO\nHabilitação para o exercício da atividade profissional: Não\n\n13 - CONDIÇÕES DE APRESENTAÇÃO\nPlataforma eletrónica utilizada pela entidade adjudicante: ACIN\nURL para Apresentação: https://www.acingov.pt\nAdmissibilidade da apresentação de propostas variantes: Não autorizado\nPrazo para apresentação das propostas: 16-10-2025 17:00\nPrazo durante o qual os concorrentes são obrigados a manter as respetivas propostas: 90 dias a contar do termo do prazo para a apresentação das propostas\nApresentação de Catálogo Eletrónico: Não autorizado\nIndicação de Subcontratação na Proposta: Inexistência de indicação de subcontratação\n\n14 - PRESTAÇÃO DE CAUÇÃO\nPrestação de caução: Sim\nPercentagem: 1%\nDescrição da Garantia Exigida: O valor da caução é de 1.00% do preço contratual.\n\n15 - FORNECIMENTO DAS PEÇAS DO CONCURSO, APRESENTAÇÃO DE PEDIDOS DE PARTICIPAÇÃO E APRESENTAÇÃO DAS PROPOSTAS\nLink para acesso às peças do concurso (URL): https://www.acingov.pt/acingovprod/2/zonaPublica/zona_publica_c/donwloadProcedurePiece/OTc3NzM0\n\n20 - OUTROS REQUISITOS\nIdentificador do Lote: LOT-0001; LOT-0002; LOT-0003; LOT-0004; LOT-0005; LOT-0006; LOT-0007\nInformação sobre contratos reservados. Aplica-se a contratos reservados (54º-A)? Não\n\n21 - CRITÉRIO DE ADJUDICAÇÃO\nO Critério de adjudicação é diferenciado por lote? Não\nMultifator: Sim\nFator: \nNome: Outros\nOutro Nome: Custo de aquisição (CA)\nPonderação: 40%\nSubfatores: Não\nFator: \nNome: Outros\nOutro Nome: Eficiência energética (EE)\nPonderação: 60%\nSubfatores: Não\n\n24 - CONDIÇÕES DO CONTRATO\nIdentificador do Lote: LOT-0001; LOT-0002; LOT-0003; LOT-0004; LOT-0005; LOT-0006; LOT-0007\nFaturação Eletrónica: Permitido\nObrigação de Subcontratação:\nCódigo da Obrigação de Subcontratação: Não é aplicável nenhuma obrigação de subcontratação.\n\n25 - COMPRA PÚBLICA ESTRATÉGICA\nCompra Pública Estratégica: Inexistência de contratação pública estratégica\n\n26 - INFORMAÇÕES ADICIONAIS\nIdentificador do Lote: LOT-0001; LOT-0002; LOT-0003; LOT-0004; LOT-0005; LOT-0006; LOT-0007\nContrato adequado para PME: Sim\nCobertura ACP (Acordo dos Contratos Públicos da Organização Mundial do Comércio): Não\n\n27 - IDENTIFICAÇÃO E CONTACTOS DO ÓRGÃO DE RECURSOS ADMINISTRATIVOS\nDesignação: Conselho de Administração da Águas do Norte, S.A.\nEndereço: Rua Dom Pedro de Castro, n.º 1A\nCódigo postal: 5000-669\nLocalidade: Vila Real\nTelefone: 259309370\nFax: 259309371\nEndereço eletrónico: geral.adnorte@adp.pt\n\n28 - IDENTIFICAÇÃO DO(S) AUTOR(ES) DE ANÚNCIO\nNome: Alice Maria Carvalho Alves\nCargo: Técnica Superior de Compras e Logística\n419534044",
    "nipc": "513606084",
    "distrito": "Vila Real",
    "concelho": "Vila Real",
    "freguesia": "Freguesia de Vila Real",
    "site": "www.adnorte.pt",
    "email": "geral.adnorte@adp.pt",
    "designacao_contrato": "PRC_0054/2025_DEX -Aquisição de grupos eletrobomba para a Águas do Norte, S.A..",
    "descricao": "PRC_0054/2025_DEX -Aquisição de grupos eletrobomba para a Águas do Norte, S.A..",
    "preco_base": "1.031.500,00 EUR",
    "prazo_execucao": "10 MESES",
    "prazo_apresentacao_propostas": "16-10-2025 17:00",
    "fundos_eu": "Não",
    "plataforma_eletronica": "ACIN",
    "url_procedimento": "https://www.acingov.pt",
    "autor_nome": "Alice Maria Carvalho Alves",
    "autor_cargo": "Técnica Superior de Compras e Logística"
  },
  {
    "numero_procedimento": "N/A",
    "entidade": "AnÃºncio de procedimento  n.Âº 24611/2025  -  DiÃ¡rio da RepÃºblica n.Âº 180/2025, SÃ©rie II de 2025-09-18",
    "link": "https://diariodarepublica.pt/dr/detalhe/contrato-publico/24611-935752323"
  },
  {
    "numero_procedimento": "N/A",
    "entidade": "Águas do Norte, S.A.",
    "link": "https://diariodarepublica.pt/dr/detalhe/contrato-publico/24612-935752324",
    "detalhes_completos": "Alteração do Anúncio de procedimento n.º 24387/2025, de 2025-09-15, com o ID 419535543\n\n1 - IDENTIFICAÇÃO E CONTACTOS DA ENTIDADE ADJUDICANTE\nDesignação da entidade adjudicante: Águas do Norte, S.A.\nNIPC: 513606084\nServiço/Órgão/Pessoa de contacto: -\nEndereço: Rua Dom Pedro de Castro, N.º 1A\nCódigo postal: 5000-669\nLocalidade: Vila Real\nPaís: Portugal\nNUT III: PT11D\nDistrito: Vila Real\nConcelho: Vila Real\nFreguesia: Freguesia de Vila Real\nTelefone: 259309370\nFax: 259309371\nEndereço da Entidade (URL): https://www.adnorte.pt/\nEndereço Eletrónico: geral.adnorte@adp.pt\neDelivery Gateway (URL): https://www.acingov.pt\nFunção da Organização: Adquirente\nNorma jurídica da Entidade Adjudicante: Organismo de direito público\nÁrea de atividade da Autoridade Adjudicante: Serviços públicos das administrações públicas\n\n2 - JORNAL OFICIAL DA UNIÃO EUROPEIA\nO procedimento a que este anúncio diz respeito também é publicitado no Jornal Oficial da União Europeia? Não\n\n3 - AVISO\nModelo de Anúncio: Concurso público\nData de Envio do Anúncio: 18-09-2025\n\n5 - PROCESSO\nTipo de Procedimento: Concurso público\nPreço base do procedimento: Sim\nValor do preço base do procedimento: 110.000,00 EUR\nProcedimento com lotes? Não\n\n6 - OBJETO DO CONTRATO\nNúmero de referência interna: PRC_0078/2025_GAE-EB1231\nDesignação do contrato: PRC_0078/2025_GAE-EB1231 - Empreitada de Execução da ETAR de Crasto (Freguesia de S. João da Cova)\nDescrição: PRC_0078/2025_GAE-EB1231 - Empreitada de Execução da ETAR de Crasto (Freguesia de S. João da Cova)\nTipo de Contrato Principal: Empreitada de Obras Públicas\nTipo de Contrato: Empreitada de Obras Públicas\nClassificação CPV (Vocabulário Comum para os Contratos Públicos)\nObjeto principal\nVocabulário Principal: 45232420\nPreço base s/IVA: 110.000,00 EUR\n\n7 - INDICAÇÕES ADICIONAIS\nO contrato envolve aquisição conjunta (satisfação de várias entidades)? Não\nO contrato é adjudicado por uma central de compras? Não\n\n8 - TÉCNICAS\nO concurso destina-se à celebração de um acordo-quadro? Inexistência de acordo-quadro\nÉ utilizado um leilão eletrónico? Não\nÉ adotada uma fase de negociação? Não\nSistema de Aquisição Dinâmico: Inexistência de sistema de aquisição dinâmico\n\n9 - LOCAL DA EXECUÇÃO DO CONTRATO\nLOCAL DA EXECUÇÃO DO CONTRATO (PROCEDIMENTO)\nPaís: Portugal\nNUT III: PT119\nLocalidade: União das Freguesias de Ventosa e Cova\nDistrito: Braga\nConcelho: Vieira do Minho\nFreguesia: União das Freguesias de Ventosa e Cova\n\n10 - PRAZO DE EXECUÇÃO DO CONTRATO\nPrazo de execução do contrato: 180 DIAS\nPrevisão de renovações: Não\n\n11 - FUNDOS EU\nTêm fundos EU? Não\n\n12 - DOCUMENTOS DE HABILITAÇÃO\nHabilitação para o exercício da atividade profissional: Sim\nTipo: Alvará\nDescrição: Documentos de Habilitação\n\n13 - CONDIÇÕES DE APRESENTAÇÃO\nPlataforma eletrónica utilizada pela entidade adjudicante: ACIN\nURL para Apresentação: https://www.acingov.pt\nAdmissibilidade da apresentação de propostas variantes: Não autorizado\nPrazo para apresentação das propostas: 22-09-2025 18:00\nPrazo durante o qual os concorrentes são obrigados a manter as respetivas propostas: 90 dias a contar do termo do prazo para a apresentação das propostas\nIndicação de Subcontratação na Proposta: Inexistência de indicação de subcontratação\n\n14 - PRESTAÇÃO DE CAUÇÃO\nPrestação de caução: Sim\nPercentagem: 5%\nDescrição da Garantia Exigida: O valor da caução é de 5.00% do preço contratual.\n\n15 - FORNECIMENTO DAS PEÇAS DO CONCURSO, APRESENTAÇÃO DE PEDIDOS DE PARTICIPAÇÃO E APRESENTAÇÃO DAS PROPOSTAS\nLink para acesso às peças do concurso (URL): https://www.acingov.pt/acingovprod/2/zonaPublica/zona_publica_c/donwloadProcedurePiece/OTIwODYy\n\n20 - OUTROS REQUISITOS\nInformação sobre contratos reservados. Aplica-se a contratos reservados (54º-A)? Não\n\n21 - CRITÉRIO DE ADJUDICAÇÃO\nMultifator: Não\nMonofator:\nNome: Preço\n\n24 - CONDIÇÕES DO CONTRATO\nFaturação Eletrónica: Permitido\nObrigação de Subcontratação:\nCódigo da Obrigação de Subcontratação: Não é aplicável nenhuma obrigação de subcontratação.\n\n25 - COMPRA PÚBLICA ESTRATÉGICA\nCompra Pública Estratégica: Inexistência de contratação pública estratégica\n\n26 - INFORMAÇÕES ADICIONAIS\nContrato adequado para PME: Não\nCobertura ACP (Acordo dos Contratos Públicos da Organização Mundial do Comércio): Não\n\n27 - IDENTIFICAÇÃO E CONTACTOS DO ÓRGÃO DE RECURSOS ADMINISTRATIVOS\nDesignação: Conselho de Administração da Águas do Norte, S.A.\nEndereço: Rua Dom Pedro de Castro, N.º 1A\nCódigo postal: 5000-669\nLocalidade: Vila Real\nTelefone: 259309370\nFax: \nEndereço eletrónico: geral.adnorte@adp.pt\nPrazo de interposição do recurso: 5 dias\n\n28 - IDENTIFICAÇÃO DO(S) AUTOR(ES) DE ANÚNCIO\nNome: Alexandra Bezelga\nCargo: Técnica Superior de Gestão de Ativos e Engenharia\n\n29 - ALTERAÇÃO\nMotivo da Alteração: Correção pelo adquirente\nIdentificador da Versão do Anúncio a Alterar: 548d28a9-8153-4ba0-9122-291743ee2b6e-03\nIdentificador das Secções Alteradas do Anúncio Anterior: Condições de Apresentação\nDescrição das Alterações: Modificação do prazo para a apresentação de propostas\nAlteração dos Documentos do Concurso: Não\n419545303",
    "nipc": "513606084",
    "distrito": "Vila Real",
    "concelho": "Vila Real",
    "freguesia": "Freguesia de Vila Real",
    "site": "https://www.adnorte.pt/",
    "email": "geral.adnorte@adp.pt",
    "designacao_contrato": "PRC_0078/2025_GAE-EB1231 - Empreitada de Execução da ETAR de Crasto (Freguesia de S. João da Cova)",
    "descricao": "PRC_0078/2025_GAE-EB1231 - Empreitada de Execução da ETAR de Crasto (Freguesia de S. João da Cova)",
    "preco_base": "110.000,00 EUR",
    "prazo_execucao": "180 DIAS",
    "prazo_apresentacao_propostas": "22-09-2025 18:00",
    "fundos_eu": "Não",
    "plataforma_eletronica": "ACIN",
    "url_procedimento": "https://www.acingov.pt",
    "autor_nome": "Alexandra Bezelga",
    "autor_cargo": "Técnica Superior de Gestão de Ativos e Engenharia"
  }
]