[
  {
    "numero_procedimento": "N/A",
    "entidade": "AnÃºncio de procedimento  n.Âº 27374/2025  -  DiÃ¡rio da RepÃºblica n.Âº 201/2025, SÃ©rie II de 2025-10-17",
    "link": "https://diariodarepublica.pt/dr/detalhe/contrato-publico/27374-940560147"
  },
  {
    "numero_procedimento": "N/A",
    "entidade": "Cooptécnica - Gustave Eiffel, Cooperativa de Ensino e Formação Técnico Profissional, C. R. L.",
    "link": "https://diariodarepublica.pt/dr/detalhe/contrato-publico/27375-940560148",
    "detalhes_completos": "1 - IDENTIFICAÇÃO E CONTACTOS DA ENTIDADE ADJUDICANTE\nDesignação da entidade adjudicante: Cooptécnica - Gustave Eiffel, Cooperativa de Ensino e Formação Técnico Profissional, C. R. L.\nNIPC: 502327669\nEndereço: Rua Elias Garcia, nº 29, Amadora\nCódigo postal: 2700-312\nLocalidade: Lisboa\nPaís: Portugal\nNUT III: PT170\nDistrito: Lisboa\nConcelho: Amadora\nFreguesia: Freguesia de Falagueira-Venda Nova\nTelefone: 214996440\nFax: 214966449\nEndereço da Entidade (URL): www.cooptecnica.pt\nEndereço Eletrónico: contratacao.publica@gustaveeiffel.pt\neDelivery Gateway (URL): https://community.vortal.biz/public/\nFunção da Organização: Adquirente\nNorma jurídica da Entidade Adjudicante: Organismo de direito público\nÁrea de atividade da Autoridade Adjudicante: Educação\n\n2 - JORNAL OFICIAL DA UNIÃO EUROPEIA\nO procedimento a que este anúncio diz respeito também é publicitado no Jornal Oficial da União Europeia? Sim\n\n3 - AVISO\nModelo de Anúncio: Concurso público\nData de Envio do Anúncio: 14-10-2025\n\n5 - PROCESSO\nTipo de Procedimento: Concurso público\nPreço base do procedimento: Sim\nValor do preço base do procedimento: 219.884,59 EUR\nProcedimento com lotes? Sim\nNº Máx. de Lotes Autorizado: 8\nNúmero máximo de lotes que podem ser adjudicados a um concorrente: 8\n\n6 - OBJETO DO CONTRATO\nNúmero de referência interna: CPI 017 CCP 2025\nDesignação do contrato: Aquisição de Serviço de Implementação de Infraestrutura de Cablagem de Fibra Ótica e Cobre\nDescrição: Aquisição de Serviço de Implementação de Infraestrutura de Cablagem de Fibra Ótica e Cobre\nOpções: Não\nTipo de Contrato Principal: Aquisição de Bens Móveis\nTipo de Contrato: Aquisição de Bens Móveis; Locação de Bens Móveis\nClassificação CPV (Vocabulário Comum para os Contratos Públicos)\nObjeto principal\nVocabulário Principal: 32424000\nPreço base s/IVA: 219.884,59 EUR\nLotes: \nNº: LOT-0001\nDescrição do Lote: Lote 1 – Escola da Amadora Centro – Informática\nPreço base s/IVA: 28.747,74 EUR\nClassificação CPV (Vocabulário Comum para os Contratos Públicos)\nObjeto principal\nVocabulário Principal: 32424000\nNº: LOT-0002\nDescrição do Lote: Lote 2 – Escola da Amadora Sede – Digital\nPreço base s/IVA: 40.226,93 EUR\nClassificação CPV (Vocabulário Comum para os Contratos Públicos)\nObjeto principal\nVocabulário Principal: 32424000\nNº: LOT-0003\nDescrição do Lote: Lote 3 - Escola da Amadora Sede – Industrial\nPreço base s/IVA: 39.504,81 EUR\nClassificação CPV (Vocabulário Comum para os Contratos Públicos)\nObjeto principal\nVocabulário Principal: 32424000\nNº: LOT-0004\nDescrição do Lote: Lote 4 - Escola da Amadora Sede – Informática\nPreço base s/IVA: 17.066,18 EUR\nClassificação CPV (Vocabulário Comum para os Contratos Públicos)\nObjeto principal\nVocabulário Principal: 32424000\nNº: LOT-0005\nDescrição do Lote: Lote 5 - Escola do Entroncamento – Industrial\nPreço base s/IVA: 31.509,15 EUR\nClassificação CPV (Vocabulário Comum para os Contratos Públicos)\nObjeto principal\nVocabulário Principal: 32424000\nNº: LOT-0006\nDescrição do Lote: Lote 6 - Escola do Entroncamento – Energias Renováveis\nPreço base s/IVA: 17.328,48 EUR\nClassificação CPV (Vocabulário Comum para os Contratos Públicos)\nObjeto principal\nVocabulário Principal: 32424000\nNº: LOT-0007\nDescrição do Lote: Lote 7 - Escola do Lumiar – Industrial\nPreço base s/IVA: 26.173,38 EUR\nClassificação CPV (Vocabulário Comum para os Contratos Públicos)\nObjeto principal\nVocabulário Principal: 32424000\nNº: LOT-0008\nDescrição do Lote: Lote 8 - Escola do Lumiar – Energias Renováveis\nPreço base s/IVA: 19.327,92 EUR\nClassificação CPV (Vocabulário Comum para os Contratos Públicos)\nObjeto principal\nVocabulário Principal: 32424000\n\n7 - INDICAÇÕES ADICIONAIS\nO contrato envolve aquisição conjunta (satisfação de várias entidades)? Não\nO contrato é adjudicado por uma central de compras? Não\n\n8 - TÉCNICAS\nO concurso destina-se à celebração de um acordo-quadro? Inexistência de acordo-quadro\nÉ utilizado um leilão eletrónico? Não\nÉ adotada uma fase de negociação? Não\nSistema de Aquisição Dinâmico: Inexistência de sistema de aquisição dinâmico\n\n9 - LOCAL DA EXECUÇÃO DO CONTRATO\nLOCAL DA EXECUÇÃO DO CONTRATO (PROCEDIMENTO)\nPaís: Portugal\nNUT III: PT170\nLocalidade: Lisboa\nDistrito: Lisboa\nConcelho: Amadora\nFreguesia: Todas\nLOCAL DA EXECUÇÃO DO CONTRATO (LOTE)\nIdentificador do Lote: LOT-0001; LOT-0002; LOT-0003; LOT-0004; LOT-0005; LOT-0006; LOT-0007; LOT-0008\nPaís: Portugal\nNUT III: PT170\nLocalidade: Lisboa\nDistrito: Lisboa\nConcelho: Amadora\nFreguesia: Todas\nIdentificador do Lote: LOT-0001; LOT-0002; LOT-0003; LOT-0004; LOT-0005; LOT-0006; LOT-0007; LOT-0008\nPaís: Portugal\nNUT III: PT170\nLocalidade: Lisboa\nDistrito: Lisboa\nConcelho: Lisboa\nFreguesia: Freguesia de Lumiar\nIdentificador do Lote: LOT-0001; LOT-0002; LOT-0003; LOT-0004; LOT-0005; LOT-0006; LOT-0007; LOT-0008\nPaís: Portugal\nNUT III: PT16I\nLocalidade: Santarém\nDistrito: Santarém\nConcelho: Entroncamento\nFreguesia: Todas\nIdentificador do Lote: LOT-0001; LOT-0002; LOT-0003; LOT-0004; LOT-0005; LOT-0006; LOT-0007; LOT-0008\nPaís: Portugal\nNUT III: PT170\nLocalidade: Lisboa\nDistrito: Lisboa\nConcelho: Amadora\nFreguesia: Todas\n\n10 - PRAZO DE EXECUÇÃO DO CONTRATO\nIdentificador do Lote: LOT-0001; LOT-0002; LOT-0003; LOT-0004; LOT-0005; LOT-0006; LOT-0007; LOT-0008\nPrazo de execução do contrato: 15 DIAS\nPrevisão de renovações: Não\n\n11 - FUNDOS EU\nIdentificador do Lote: LOT-0001; LOT-0002; LOT-0003; LOT-0004; LOT-0005; LOT-0006; LOT-0007; LOT-0008\nTêm fundos EU? Sim\n\n12 - DOCUMENTOS DE HABILITAÇÃO\nHabilitação para o exercício da atividade profissional: Não\n\n13 - CONDIÇÕES DE APRESENTAÇÃO\nPlataforma eletrónica utilizada pela entidade adjudicante: VORTAL\nURL para Apresentação: https://community.vortal.biz/public/\nAdmissibilidade da apresentação de propostas variantes: Não autorizado\nPrazo para apresentação das propostas: 02-11-2025 23:59\nPrazo durante o qual os concorrentes são obrigados a manter as respetivas propostas: 10 dias a contar do termo do prazo para a apresentação das propostas\nApresentação de Catálogo Eletrónico: Não autorizado\nIndicação de Subcontratação na Proposta: Inexistência de indicação de subcontratação\n\n14 - PRESTAÇÃO DE CAUÇÃO\nPrestação de caução: Sim\nPercentagem: 5%\nDescrição da Garantia Exigida: O adjudicatário deve prestar a caução devida no prazo de 10 (dez) dias úteis a contar da notificação da decisão de adjudicação, no valor de 5% do preço contratual, em benefício da Cooptécnica Gustave Eiffel, devendo comprovar essa prestação no dia imediatamente subsequente.\n\n15 - FORNECIMENTO DAS PEÇAS DO CONCURSO, APRESENTAÇÃO DE PEDIDOS DE PARTICIPAÇÃO E APRESENTAÇÃO DAS PROPOSTAS\nLink para acesso às peças do concurso (URL): https://community.vortal.biz/Public/public-tender-documents/QWRXMWJBYXZMWFZOUUFnMC9UWlB4d1E4QWFGS212cSt1UjQyZHNlZGg0eW4zdjFEMkxNZ1hGMllXcENZWFl1ZFJMbnhPc3JwQjc4OUVHQXFRcUdVZHc9PUR5aEJZ\n\n20 - OUTROS REQUISITOS\nIdentificador do Lote: LOT-0001; LOT-0002; LOT-0003; LOT-0004; LOT-0005; LOT-0006; LOT-0007; LOT-0008\nInformação sobre contratos reservados. Aplica-se a contratos reservados (54º-A)? Não\n\n21 - CRITÉRIO DE ADJUDICAÇÃO\nO Critério de adjudicação é diferenciado por lote? Não\nMultifator: Não\nMonofator:\nNome: Outros\nOutro nome: Preço\n\n24 - CONDIÇÕES DO CONTRATO\nIdentificador do Lote: LOT-0001; LOT-0002; LOT-0003; LOT-0004; LOT-0005; LOT-0006; LOT-0007; LOT-0008\nFaturação Eletrónica: Permitido\nObrigação de Subcontratação:\nCódigo da Obrigação de Subcontratação: Não é aplicável nenhuma obrigação de subcontratação.\n\n25 - COMPRA PÚBLICA ESTRATÉGICA\nCompra Pública Estratégica: Inexistência de contratação pública estratégica\n\n26 - INFORMAÇÕES ADICIONAIS\nIdentificador do Lote: LOT-0001; LOT-0002; LOT-0003; LOT-0004; LOT-0005; LOT-0006; LOT-0007; LOT-0008\nContrato adequado para PME: Sim\nCobertura ACP (Acordo dos Contratos Públicos da Organização Mundial do Comércio): Não\n\n27 - IDENTIFICAÇÃO E CONTACTOS DO ÓRGÃO DE RECURSOS ADMINISTRATIVOS\nDesignação: Susana Fernandes\nEndereço: RUA ELIAS GARCIA Nº 29 - VENDA NOVA\nCódigo postal: 2700-312\nLocalidade: Amadora\nTelefone: +351 912355271\nFax: +351 214996449\nEndereço eletrónico: contratacaopublica@gustaveeiffel.pt\n\n28 - IDENTIFICAÇÃO DO(S) AUTOR(ES) DE ANÚNCIO\nNome: Susana Fernandes\nCargo: Técnico\n419657124",
    "nipc": "502327669",
    "distrito": "Lisboa",
    "concelho": "Amadora",
    "freguesia": "Freguesia de Falagueira-Venda Nova",
    "site": "www.cooptecnica.pt",
    "email": "contratacao.publica@gustaveeiffel.pt",
    "designacao_contrato": "Aquisição de Serviço de Implementação de Infraestrutura de Cablagem de Fibra Ótica e Cobre",
    "descricao": "Aquisição de Serviço de Implementação de Infraestrutura de Cablagem de Fibra Ótica e Cobre",
    "preco_base": "219.884,59 EUR",
    "prazo_execucao": "15 DIAS",
    "prazo_apresentacao_propostas": "02-11-2025 23:59",
    "fundos_eu": "Sim",
    "plataforma_eletronica": "VORTAL",
    "url_procedimento": "https://community.vortal.biz/public/",
    "autor_nome": "Susana Fernandes",
    "autor_cargo": "Técnico"
  },
  {
    "numero_procedimento": "N/A",
    "entidade": "TML - Transportes Metropolitanos de Lisboa, E. M. T., S. A.",
    "link": "https://diariodarepublica.pt/dr/detalhe/contrato-publico/27376-940560149",
    "detalhes_completos": "1 - IDENTIFICAÇÃO E CONTACTOS DA ENTIDADE ADJUDICANTE\nDesignação da entidade adjudicante: TML - Transportes Metropolitanos de Lisboa, E. M. T., S. A.\nNIPC: 516150359\nEndereço: Rua Cruz de Santa Apolónia, 23, 25 e 25-A \nCódigo postal: 1100-187\nLocalidade: Lisboa\nPaís: Portugal\nNUT III: PT170\nDistrito: Lisboa\nConcelho: Lisboa\nFreguesia: Freguesia de São Vicente\nTelefone: 218121379\nFax: 218121379\nEndereço da Entidade (URL): https://www.tmlmobilidade.pt/\nEndereço Eletrónico: contratacao@tmlmobilidade.pt\neDelivery Gateway (URL): https://community.vortal.biz/public/\nFunção da Organização: Adquirente\nNorma jurídica da Entidade Adjudicante: Autoridade da administração central\nÁrea de atividade da Autoridade Adjudicante: Serviços públicos das administrações públicas\n\n2 - JORNAL OFICIAL DA UNIÃO EUROPEIA\nO procedimento a que este anúncio diz respeito também é publicitado no Jornal Oficial da União Europeia? Sim\n\n3 - AVISO\nModelo de Anúncio: Concurso público\nData de Envio do Anúncio: 14-10-2025\n\n5 - PROCESSO\nTipo de Procedimento: Concurso público\nPreço base do procedimento: Sim\nValor do preço base do procedimento: 946.000,00 EUR\nProcedimento com lotes? Não\n\n6 - OBJETO DO CONTRATO\nNúmero de referência interna: CPI03/2025\nDesignação do contrato: Aquisição de licenciamento Microsoft 365 para software de produtividade, colaboração, gestão e segurança\nDescrição: Aquisição de licenciamento Microsoft 365 para software de produtividade, colaboração, gestão e segurança\nOpções: Não\nTipo de Contrato Principal: Aquisição de Bens Móveis\nTipo de Contrato: Aquisição de Bens Móveis\nClassificação CPV (Vocabulário Comum para os Contratos Públicos)\nObjeto principal\nVocabulário Principal: 22456000\nPreço base s/IVA: 946.000,00 EUR\n\n7 - INDICAÇÕES ADICIONAIS\nO contrato envolve aquisição conjunta (satisfação de várias entidades)? Não\nO contrato é adjudicado por uma central de compras? Não\n\n8 - TÉCNICAS\nO concurso destina-se à celebração de um acordo-quadro? Inexistência de acordo-quadro\nÉ utilizado um leilão eletrónico? Não\nÉ adotada uma fase de negociação? Não\nSistema de Aquisição Dinâmico: Inexistência de sistema de aquisição dinâmico\n\n9 - LOCAL DA EXECUÇÃO DO CONTRATO\nLOCAL DA EXECUÇÃO DO CONTRATO (PROCEDIMENTO)\nPaís: Portugal\nNUT III: PT170\nLocalidade: Lisboa\nDistrito: Lisboa\nConcelho: Lisboa\nFreguesia: Freguesia de São Vicente\n\n10 - PRAZO DE EXECUÇÃO DO CONTRATO\nPrazo de execução do contrato: 36 MESES\nPrevisão de renovações: Não\n\n11 - FUNDOS EU\nTêm fundos EU? Não\n\n12 - DOCUMENTOS DE HABILITAÇÃO\nHabilitação para o exercício da atividade profissional: Não\n\n13 - CONDIÇÕES DE APRESENTAÇÃO\nPlataforma eletrónica utilizada pela entidade adjudicante: VORTAL\nURL para Apresentação: https://community.vortal.biz/public/\nAdmissibilidade da apresentação de propostas variantes: Não autorizado\nPrazo para apresentação das propostas: 12-11-2025 17:00\nPrazo durante o qual os concorrentes são obrigados a manter as respetivas propostas: 66 dias a contar do termo do prazo para a apresentação das propostas\nApresentação de Catálogo Eletrónico: Permitido\nIndicação de Subcontratação na Proposta: Inexistência de indicação de subcontratação\n\n14 - PRESTAÇÃO DE CAUÇÃO\nPrestação de caução: Sim\nPercentagem: 5%\nDescrição da Garantia Exigida: Em conformidade com um dos modelos constantes do ANEXO VII ao Programa do Concurso\n\n15 - FORNECIMENTO DAS PEÇAS DO CONCURSO, APRESENTAÇÃO DE PEDIDOS DE PARTICIPAÇÃO E APRESENTAÇÃO DAS PROPOSTAS\nLink para acesso às peças do concurso (URL): https://community.vortal.biz/Public/public-tender-documents/em1ZM3FzSWZDTzFmOEZ2WEFKUkJ5L0ZrMmVZOGJPWlMyYXllemlVUVNtWFByVmtLS2NYaEhVaU93dnNsUHhhSHVYS2JPaXhOM1B5eUNqNGFnVTdDVGc9PTl0NEEp\n\n20 - OUTROS REQUISITOS\nInformação sobre contratos reservados. Aplica-se a contratos reservados (54º-A)? Não\n\n21 - CRITÉRIO DE ADJUDICAÇÃO\nMultifator: Sim\nFator: \nNome: Preço\nPonderação: 60%\nSubfatores: Não\nFator: \nNome: Preço\nPonderação: 35%\nSubfatores: Não\nFator: \nNome: Preço\nPonderação: 5%\nSubfatores: Não\n\n24 - CONDIÇÕES DO CONTRATO\nFaturação Eletrónica: Permitido\nObrigação de Subcontratação:\nCódigo da Obrigação de Subcontratação: Não é aplicável nenhuma obrigação de subcontratação.\n\n25 - COMPRA PÚBLICA ESTRATÉGICA\nCompra Pública Estratégica: Inexistência de contratação pública estratégica\n\n26 - INFORMAÇÕES ADICIONAIS\nContrato adequado para PME: Sim\nCobertura ACP (Acordo dos Contratos Públicos da Organização Mundial do Comércio): Não\n\n27 - IDENTIFICAÇÃO E CONTACTOS DO ÓRGÃO DE RECURSOS ADMINISTRATIVOS\nDesignação: Conselho de Administração da TML\nEndereço: Rua Cruz de Santa Apolónia 23, 25 e 25 A\nCódigo postal: 1100-187\nLocalidade: Lisboa\nTelefone: +351 218121379\nFax: +351 218121379\nEndereço eletrónico: contratacao@tmlmobilidade.pt\n\n28 - IDENTIFICAÇÃO DO(S) AUTOR(ES) DE ANÚNCIO\nNome: Luís Carrondo\nCargo: Técnico Superior Principal DJR\n419648263",
    "nipc": "516150359",
    "distrito": "Lisboa",
    "concelho": "Lisboa",
    "freguesia": "Freguesia de São Vicente",
    "site": "https://www.tmlmobilidade.pt/",
    "email": "contratacao@tmlmobilidade.pt",
    "designacao_contrato": "Aquisição de licenciamento Microsoft 365 para software de produtividade, colaboração, gestão e segurança",
    "descricao": "Aquisição de licenciamento Microsoft 365 para software de produtividade, colaboração, gestão e segurança",
    "preco_base": "946.000,00 EUR",
    "prazo_execucao": "36 MESES",
    "prazo_apresentacao_propostas": "12-11-2025 17:00",
    "fundos_eu": "Não",
    "plataforma_eletronica": "VORTAL",
    "url_procedimento": "https://community.vortal.biz/public/",
    "autor_nome": "Luís Carrondo",
    "autor_cargo": "Técnico Superior Principal DJR"
  },
  {
    "numero_procedimento": "N/A",
    "entidade": "Arsenal do Alfeite, S. A.",
    "link": "https://diariodarepublica.pt/dr/detalhe/contrato-publico/27377-940560150",
    "detalhes_completos": "1 - IDENTIFICAÇÃO E CONTACTOS DA ENTIDADE ADJUDICANTE\nDesignação da entidade adjudicante: Arsenal do Alfeite, S. A.\nNIPC: 508881048\nEndereço: Alfeite (Laranjeiro) - Almada\nCódigo postal: 2810-001\nLocalidade: Setúbal\nPaís: Portugal\nNUT III: PT170\nDistrito: Setúbal\nConcelho: Almada\nFreguesia: Todas\nTelefone: 210950836\nFax: 210950873\nEndereço da Entidade (URL): www.arsenal-alfeite.pt\nEndereço Eletrónico: mario.peixe@arsenal-alfeite.pt\neDelivery Gateway (URL): https://community.vortal.biz/public/\nFunção da Organização: Adquirente\nNorma jurídica da Entidade Adjudicante: Organismo de direito público\nÁrea de atividade da Autoridade Adjudicante: Defesa\n\n2 - JORNAL OFICIAL DA UNIÃO EUROPEIA\nO procedimento a que este anúncio diz respeito também é publicitado no Jornal Oficial da União Europeia? Sim\n\n3 - AVISO\nModelo de Anúncio: Concurso público\nData de Envio do Anúncio: 14-10-2025\n\n5 - PROCESSO\nTipo de Procedimento: Concurso público\nPreço base do procedimento: Sim\nValor do preço base do procedimento: 99.900,00 EUR\nProcedimento com lotes? Sim\nNº Máx. de Lotes Autorizado: 13\nNúmero máximo de lotes que podem ser adjudicados a um concorrente: 13\n\n6 - OBJETO DO CONTRATO\nNúmero de referência interna: CPI 02 -2025\nDesignação do contrato: CPI 02-2025 - Aquisição de serviços de recolha, transporte e encaminhamento de resíduos da  Arsenal do Alfeite, S.A. (Lotes 1 a 13)\nDescrição: CPI 02-2025 - Aquisição de serviços de recolha, transporte e encaminhamento de resíduos da  Arsenal do Alfeite, S.A. (Lotes 1 a 13)\nOpções: Não\nTipo de Contrato Principal: Aquisição de Serviços\nTipo de Contrato: Aquisição de Serviços\nClassificação CPV (Vocabulário Comum para os Contratos Públicos)\nObjeto principal\nVocabulário Principal: 90500000\nPreço base s/IVA: 99.900,00 EUR\nLotes: \nNº: LOT-0001\nDescrição do Lote: Lote 1\nPreço base s/IVA: 13.070,00 EUR\nClassificação CPV (Vocabulário Comum para os Contratos Públicos)\nObjeto principal\nVocabulário Principal: 90500000\nNº: LOT-0002\nDescrição do Lote: Lote 2\nPreço base s/IVA: 2.490,00 EUR\nClassificação CPV (Vocabulário Comum para os Contratos Públicos)\nObjeto principal\nVocabulário Principal: 90500000\nNº: LOT-0003\nDescrição do Lote: Lote 3\nPreço base s/IVA: 1.280,00 EUR\nClassificação CPV (Vocabulário Comum para os Contratos Públicos)\nObjeto principal\nVocabulário Principal: 90500000\nNº: LOT-0004\nDescrição do Lote: Lote 4\nPreço base s/IVA: 7.310,00 EUR\nClassificação CPV (Vocabulário Comum para os Contratos Públicos)\nObjeto principal\nVocabulário Principal: 90500000\nNº: LOT-0005\nDescrição do Lote: Lote 5\nPreço base s/IVA: 3.780,00 EUR\nClassificação CPV (Vocabulário Comum para os Contratos Públicos)\nObjeto principal\nVocabulário Principal: 90500000\nNº: LOT-0006\nDescrição do Lote: Lote 6\nPreço base s/IVA: 2.600,00 EUR\nClassificação CPV (Vocabulário Comum para os Contratos Públicos)\nObjeto principal\nVocabulário Principal: 90500000\nNº: LOT-0007\nDescrição do Lote: Lote 7\nPreço base s/IVA: 3.650,00 EUR\nClassificação CPV (Vocabulário Comum para os Contratos Públicos)\nObjeto principal\nVocabulário Principal: 90500000\nNº: LOT-0008\nDescrição do Lote: Lote 8\nPreço base s/IVA: 9.000,00 EUR\nClassificação CPV (Vocabulário Comum para os Contratos Públicos)\nObjeto principal\nVocabulário Principal: 90500000\nNº: LOT-0009\nDescrição do Lote: Lote 9\nPreço base s/IVA: 4.960,00 EUR\nClassificação CPV (Vocabulário Comum para os Contratos Públicos)\nObjeto principal\nVocabulário Principal: 90500000\nNº: LOT-0010\nDescrição do Lote: Lote 10\nPreço base s/IVA: 15.400,00 EUR\nClassificação CPV (Vocabulário Comum para os Contratos Públicos)\nObjeto principal\nVocabulário Principal: 90500000\nNº: LOT-0011\nDescrição do Lote: Lote 11\nPreço base s/IVA: 6.740,00 EUR\nClassificação CPV (Vocabulário Comum para os Contratos Públicos)\nObjeto principal\nVocabulário Principal: 90500000\nNº: LOT-0012\nDescrição do Lote: Lote 12\nPreço base s/IVA: 27.920,00 EUR\nClassificação CPV (Vocabulário Comum para os Contratos Públicos)\nObjeto principal\nVocabulário Principal: 90500000\nNº: LOT-0013\nDescrição do Lote: Lote 13\nPreço base s/IVA: 1.700,00 EUR\nClassificação CPV (Vocabulário Comum para os Contratos Públicos)\nObjeto principal\nVocabulário Principal: 90500000\n\n7 - INDICAÇÕES ADICIONAIS\nO contrato envolve aquisição conjunta (satisfação de várias entidades)? Não\nO contrato é adjudicado por uma central de compras? Não\n\n8 - TÉCNICAS\nO concurso destina-se à celebração de um acordo-quadro? Inexistência de acordo-quadro\nÉ utilizado um leilão eletrónico? Não\nÉ adotada uma fase de negociação? Não\nSistema de Aquisição Dinâmico: Inexistência de sistema de aquisição dinâmico\n\n9 - LOCAL DA EXECUÇÃO DO CONTRATO\nLOCAL DA EXECUÇÃO DO CONTRATO (PROCEDIMENTO)\nPaís: Portugal\nNUT III: PT170\nLocalidade: Setúbal\nDistrito: Setúbal\nConcelho: Almada\nFreguesia: União das Freguesias de Laranjeiro e Feijó\nLOCAL DA EXECUÇÃO DO CONTRATO (LOTE)\nIdentificador do Lote: LOT-0001; LOT-0002; LOT-0003; LOT-0004; LOT-0005; LOT-0006; LOT-0007; LOT-0008; LOT-0009; LOT-0010; LOT-0011; LOT-0012; LOT-0013\nPaís: Portugal\nNUT III: PT170\nLocalidade: Setúbal\nDistrito: Setúbal\nConcelho: Almada\nFreguesia: União das Freguesias de Laranjeiro e Feijó\n\n10 - PRAZO DE EXECUÇÃO DO CONTRATO\nIdentificador do Lote: LOT-0001; LOT-0002; LOT-0003; LOT-0004; LOT-0005; LOT-0006; LOT-0007; LOT-0008; LOT-0009; LOT-0010; LOT-0011; LOT-0012; LOT-0013\nPrazo de execução do contrato: 1 ANOS\nPrevisão de renovações: Sim\nIndicar número máximo de renovações: 2\nPrazo de renovações diferente do prazo inicial: Não\n\n11 - FUNDOS EU\nIdentificador do Lote: LOT-0001; LOT-0002; LOT-0003; LOT-0004; LOT-0005; LOT-0006; LOT-0007; LOT-0008; LOT-0009; LOT-0010; LOT-0011; LOT-0012; LOT-0013\nTêm fundos EU? Não\n\n12 - DOCUMENTOS DE HABILITAÇÃO\nHabilitação para o exercício da atividade profissional: Sim\nTipo: Outros\nDescrição - Outros: Conforme Caderno de Encargos\nDescrição: n.a.\n\n13 - CONDIÇÕES DE APRESENTAÇÃO\nPlataforma eletrónica utilizada pela entidade adjudicante: VORTAL\nURL para Apresentação: https://community.vortal.biz/public/\nAdmissibilidade da apresentação de propostas variantes: Não autorizado\nPrazo para apresentação das propostas: 13-11-2025 23:59\nPrazo durante o qual os concorrentes são obrigados a manter as respetivas propostas: 66 dias a contar do termo do prazo para a apresentação das propostas\nApresentação de Catálogo Eletrónico: Permitido\nIndicação de Subcontratação na Proposta: Inexistência de indicação de subcontratação\n\n14 - PRESTAÇÃO DE CAUÇÃO\nPrestação de caução: Não\n\n15 - FORNECIMENTO DAS PEÇAS DO CONCURSO, APRESENTAÇÃO DE PEDIDOS DE PARTICIPAÇÃO E APRESENTAÇÃO DAS PROPOSTAS\nLink para acesso às peças do concurso (URL): https://community.vortal.biz/Public/public-tender-documents/dnowVWR4Z0hCMEk2TFNtNG1YcUkxdnBFaUUxMDAvelVzUWhBQTBOUkdUczZKOXdLanJ0cjZkUm40eFFWZGwyMDBESXhRUjZFVFpqRUhOSk11TXgwbEE9PWVJTkdH\n\n20 - OUTROS REQUISITOS\nIdentificador do Lote: LOT-0001; LOT-0002; LOT-0003; LOT-0004; LOT-0005; LOT-0006; LOT-0007; LOT-0008; LOT-0009; LOT-0010; LOT-0011; LOT-0012; LOT-0013\nInformação sobre contratos reservados. Aplica-se a contratos reservados (54º-A)? Não\n\n21 - CRITÉRIO DE ADJUDICAÇÃO\nO Critério de adjudicação é diferenciado por lote? Não\nMultifator: Não\nMonofator:\nNome: Preço\n\n24 - CONDIÇÕES DO CONTRATO\nIdentificador do Lote: LOT-0001; LOT-0002; LOT-0003; LOT-0004; LOT-0005; LOT-0006; LOT-0007; LOT-0008; LOT-0009; LOT-0010; LOT-0011; LOT-0012; LOT-0013\nFaturação Eletrónica: Permitido\nObrigação de Subcontratação:\nCódigo da Obrigação de Subcontratação: Não é aplicável nenhuma obrigação de subcontratação.\n\n25 - COMPRA PÚBLICA ESTRATÉGICA\nCompra Pública Estratégica: Inexistência de contratação pública estratégica\n\n26 - INFORMAÇÕES ADICIONAIS\nIdentificador do Lote: LOT-0001; LOT-0002; LOT-0003; LOT-0004; LOT-0005; LOT-0006; LOT-0007; LOT-0008; LOT-0009; LOT-0010; LOT-0011; LOT-0012; LOT-0013\nContrato adequado para PME: Sim\nCobertura ACP (Acordo dos Contratos Públicos da Organização Mundial do Comércio): Não\n\n27 - IDENTIFICAÇÃO E CONTACTOS DO ÓRGÃO DE RECURSOS ADMINISTRATIVOS\nDesignação: Conselho de Administração\nEndereço: Alfeite - Base Naval de Lisboa\nCódigo postal: 2810-001\nLocalidade: Almada\nTelefone: +351 210950800\nFax: +351 210950873\nEndereço eletrónico: contratos@arsenal-alfeite.pt\n\n28 - IDENTIFICAÇÃO DO(S) AUTOR(ES) DE ANÚNCIO\nNome: Sara Muacho\nCargo: Chefe de Divisão de Contratação e Aprovisionamento\n419657408",
    "nipc": "508881048",
    "distrito": "Setúbal",
    "concelho": "Almada",
    "freguesia": "Todas",
    "site": "www.arsenal-alfeite.pt",
    "email": "mario.peixe@arsenal-alfeite.pt",
    "designacao_contrato": "CPI 02-2025 - Aquisição de serviços de recolha, transporte e encaminhamento de resíduos da Arsenal do Alfeite, S.A. (Lotes 1 a 13)",
    "descricao": "CPI 02-2025 - Aquisição de serviços de recolha, transporte e encaminhamento de resíduos da Arsenal do Alfeite, S.A. (Lotes 1 a 13)",
    "preco_base": "99.900,00 EUR",
    "prazo_execucao": "1 ANOS",
    "prazo_apresentacao_propostas": "13-11-2025 23:59",
    "fundos_eu": "Não",
    "plataforma_eletronica": "VORTAL",
    "url_procedimento": "https://community.vortal.biz/public/",
    "autor_nome": "Sara Muacho",
    "autor_cargo": "Chefe de Divisão de Contratação e Aprovisionamento"
  },
  {
    "numero_procedimento": "N/A",
    "entidade": "AnÃºncio de procedimento  n.Âº 27378/2025  -  DiÃ¡rio da RepÃºblica n.Âº 201/2025, SÃ©rie II de 2025-10-17",
    "link": "https://diariodarepublica.pt/dr/detalhe/contrato-publico/27378-940560151"
  },
  {
    "numero_procedimento": "N/A",
    "entidade": "Laboratório Nacional de Engenharia Civil, I. P.",
    "link": "https://diariodarepublica.pt/dr/detalhe/contrato-publico/27381-940560153",
    "detalhes_completos": "Alteração do Anúncio de procedimento n.º 27180/2025, de 2025-10-15, com o ID 419649535\n\n1 - IDENTIFICAÇÃO E CONTACTOS DA ENTIDADE ADJUDICANTE\nDesignação da entidade adjudicante: Laboratório Nacional de Engenharia Civil, I. P.\nNIPC: 501389660\nEndereço: Av.  do Brasil, 101\nCódigo postal: 1700-066\nLocalidade: Lisboa\nPaís: Portugal\nNUT III: PT170\nDistrito: Lisboa\nConcelho: Lisboa\nFreguesia: Freguesia de Alvalade - Lisboa\nTelefone: 218443000\nFax: 218443021\nEndereço da Entidade (URL): www.lnec.pt\nEndereço Eletrónico: aprovisionamento@lnec.pt\neDelivery Gateway (URL): https://community.vortal.biz/public/\nFunção da Organização: Adquirente\nNorma jurídica da Entidade Adjudicante: Organismo de direito público\nÁrea de atividade da Autoridade Adjudicante: Serviços públicos das administrações públicas\n\n2 - JORNAL OFICIAL DA UNIÃO EUROPEIA\nO procedimento a que este anúncio diz respeito também é publicitado no Jornal Oficial da União Europeia? Não\n\n3 - AVISO\nModelo de Anúncio: Concurso público\nData de Envio do Anúncio: 16-10-2025\n\n5 - PROCESSO\nTipo de Procedimento: Concurso público\nPreço base do procedimento: Sim\nValor do preço base do procedimento: 88.792,00 EUR\nProcedimento com lotes? Não\n\n6 - OBJETO DO CONTRATO\nNúmero de referência interna: 0305/A07/318\nDesignação do contrato: Sistema \"motion tracking\" de modelos com grandes dimensões\nDescrição: Sistema \"motion tracking\" de modelos com grandes dimensões\nTipo de Contrato Principal: Aquisição de Bens Móveis\nTipo de Contrato: Aquisição de Bens Móveis\nClassificação CPV (Vocabulário Comum para os Contratos Públicos)\nObjeto principal\nVocabulário Principal: 35710000\nPreço base s/IVA: 88.792,00 EUR\n\n7 - INDICAÇÕES ADICIONAIS\nO contrato envolve aquisição conjunta (satisfação de várias entidades)? Não\nO contrato é adjudicado por uma central de compras? Não\n\n8 - TÉCNICAS\nO concurso destina-se à celebração de um acordo-quadro? Inexistência de acordo-quadro\nÉ utilizado um leilão eletrónico? Não\nÉ adotada uma fase de negociação? Não\nSistema de Aquisição Dinâmico: Inexistência de sistema de aquisição dinâmico\n\n9 - LOCAL DA EXECUÇÃO DO CONTRATO\nLOCAL DA EXECUÇÃO DO CONTRATO (PROCEDIMENTO)\nPaís: Portugal\nNUT III: PT170\nLocalidade: Lisboa\nDistrito: Lisboa\nConcelho: Lisboa\nFreguesia: Todas\n\n10 - PRAZO DE EXECUÇÃO DO CONTRATO\nPrazo de execução do contrato: 45 DIAS\nPrevisão de renovações: Não\n\n11 - FUNDOS EU\nTêm fundos EU? Não\n\n12 - DOCUMENTOS DE HABILITAÇÃO\nHabilitação para o exercício da atividade profissional: Não\n\n13 - CONDIÇÕES DE APRESENTAÇÃO\nPlataforma eletrónica utilizada pela entidade adjudicante: VORTAL\nURL para Apresentação: https://community.vortal.biz/public/\nAdmissibilidade da apresentação de propostas variantes: Não autorizado\nPrazo para apresentação das propostas: 19-10-2025 23:59\nPrazo durante o qual os concorrentes são obrigados a manter as respetivas propostas: 66 dias a contar do termo do prazo para a apresentação das propostas\nApresentação de Catálogo Eletrónico: Permitido\nIndicação de Subcontratação na Proposta: Inexistência de indicação de subcontratação\n\n14 - PRESTAÇÃO DE CAUÇÃO\nPrestação de caução: Não\n\n15 - FORNECIMENTO DAS PEÇAS DO CONCURSO, APRESENTAÇÃO DE PEDIDOS DE PARTICIPAÇÃO E APRESENTAÇÃO DAS PROPOSTAS\nLink para acesso às peças do concurso (URL): https://community.vortal.biz/Public/public-tender-documents/WkZsR1ZpQUZPTmRiN2syRFh5elMra1pMTFdsbExjdUFJUkkxc01wUGlLWW1rNUdoKzMzSnN3OUlsVGdaTjNCK0lTWjR5MmRkSHRtYlVHai9xTG5SelE9PXJ1dEtQ\n\n20 - OUTROS REQUISITOS\nInformação sobre contratos reservados. Aplica-se a contratos reservados (54º-A)? Não\n\n21 - CRITÉRIO DE ADJUDICAÇÃO\nMultifator: Não\nMonofator:\nNome: Outros\nOutro nome: Preço\n\n24 - CONDIÇÕES DO CONTRATO\nFaturação Eletrónica: Permitido\nObrigação de Subcontratação:\nCódigo da Obrigação de Subcontratação: Não é aplicável nenhuma obrigação de subcontratação.\n\n25 - COMPRA PÚBLICA ESTRATÉGICA\nCompra Pública Estratégica: Redução dos impactos ambientais\nDescrição do Processo de Adjudicação Estratégico: Conforme as peças do procedimento\nCritérios de contratos Públicos Ecológicos: Critérios de contratação pública ecológica nacional\nCategorias da estratégia nacional: Outros\nOutra categoria (Descrição): Contratos de aquisição ou locação de equipamento informático\nContratos Públicos Ecológicos: Outros\nDiretiva Veículos Não Poluentes: Não\nCritério de Acessibilidade: Os critérios de acessibilidade para as pessoas com deficiência não estão incluídos porque o contrato não se destina a pessoas singulares\n\n26 - INFORMAÇÕES ADICIONAIS\nContrato adequado para PME: Sim\nCobertura ACP (Acordo dos Contratos Públicos da Organização Mundial do Comércio): Não\n\n27 - IDENTIFICAÇÃO E CONTACTOS DO ÓRGÃO DE RECURSOS ADMINISTRATIVOS\nDesignação: Conselho Diretivo\nEndereço: Avenida do Brasil, 101\nCódigo postal: 1700-066\nLocalidade: Lisboa\nTelefone: +351 218443000\nFax: +351 218443021\nEndereço eletrónico: lnec@lnec.pt\n\n28 - IDENTIFICAÇÃO DO(S) AUTOR(ES) DE ANÚNCIO\nNome: Laura Maria Mello Saraiva Caldeira\nCargo: Presidente do Conselho Diretivo\n\n29 - ALTERAÇÃO\nMotivo da Alteração: Correção pelo adquirente\nIdentificador da Versão do Anúncio a Alterar: 2773489b-c562-4924-8b67-2c3e8711d31a-01\nIdentificador das Secções Alteradas do Anúncio Anterior: Condições de Apresentação\nDescrição das Alterações: Alteração do prazo para apresentação de propostas\nAlteração dos Documentos do Concurso: Não\n419662851",
    "nipc": "501389660",
    "distrito": "Lisboa",
    "concelho": "Lisboa",
    "freguesia": "Freguesia de Alvalade - Lisboa",
    "site": "www.lnec.pt",
    "email": "aprovisionamento@lnec.pt",
    "designacao_contrato": "Sistema \"motion tracking\" de modelos com grandes dimensões",
    "descricao": "Sistema \"motion tracking\" de modelos com grandes dimensões",
    "preco_base": "88.792,00 EUR",
    "prazo_execucao": "45 DIAS",
    "prazo_apresentacao_propostas": "19-10-2025 23:59",
    "fundos_eu": "Não",
    "plataforma_eletronica": "VORTAL",
    "url_procedimento": "https://community.vortal.biz/public/",
    "autor_nome": "Laura Maria Mello Saraiva Caldeira",
    "autor_cargo": "Presidente do Conselho Diretivo"
  },
  {
    "numero_procedimento": "N/A",
    "entidade": "Município de Valença",
    "link": "https://diariodarepublica.pt/dr/detalhe/contrato-publico/27385-940560154",
    "detalhes_completos": "1 - IDENTIFICAÇÃO E CONTACTOS DA ENTIDADE ADJUDICANTE\nDesignação da entidade adjudicante: Município de Valença\nNIPC: 506728897\nEndereço: Pç. Da República, Valença\nCódigo postal: 4930-702\nLocalidade: Valença\nPaís: Portugal\nNUT III: PT111\nDistrito: Viana do Castelo\nConcelho: Valença\nFreguesia: Todas\nTelefone: 251809500\nFax: 251809519\nEndereço da Entidade (URL): www.cm-valenca.pt\nEndereço Eletrónico: geral@cm-valenca.pt\neDelivery Gateway (URL): https://community.vortal.biz/public/\nFunção da Organização: Adquirente\nNorma jurídica da Entidade Adjudicante: Autoridade local\nÁrea de atividade da Autoridade Adjudicante: Serviços públicos das administrações públicas\n\n2 - JORNAL OFICIAL DA UNIÃO EUROPEIA\nO procedimento a que este anúncio diz respeito também é publicitado no Jornal Oficial da União Europeia? Não\n\n3 - AVISO\nModelo de Anúncio: Concurso público\nData de Envio do Anúncio: 16-10-2025\n\n5 - PROCESSO\nTipo de Procedimento: Concurso público\nPreço base do procedimento: Sim\nValor do preço base do procedimento: 56.920,69 EUR\nProcedimento com lotes? Não\n\n6 - OBJETO DO CONTRATO\nNúmero de referência interna: CP-ABS-16/2025\nDesignação do contrato: FORNECIMENTO DE PRODUTOS ALIMENTARES – CONGELADOS para a confeção de Refeições ESCOLARES nos Refeitórios do Agrupamento de Escolas de Muralhas do Minho\nDescrição: FORNECIMENTO DE PRODUTOS ALIMENTARES – CONGELADOS para a confeção de Refeições ESCOLARES nos Refeitórios do Agrupamento de Escolas de Muralhas do Minho\nTipo de Contrato Principal: Aquisição de Bens Móveis\nTipo de Contrato: Aquisição de Bens Móveis\nClassificação CPV (Vocabulário Comum para os Contratos Públicos)\nObjeto principal\nVocabulário Principal: 15220000\nPreço base s/IVA: 56.920,69 EUR\n\n7 - INDICAÇÕES ADICIONAIS\nO contrato envolve aquisição conjunta (satisfação de várias entidades)? Não\nO contrato é adjudicado por uma central de compras? Não\n\n8 - TÉCNICAS\nO concurso destina-se à celebração de um acordo-quadro? Inexistência de acordo-quadro\nÉ utilizado um leilão eletrónico? Não\nÉ adotada uma fase de negociação? Não\nSistema de Aquisição Dinâmico: Inexistência de sistema de aquisição dinâmico\n\n9 - LOCAL DA EXECUÇÃO DO CONTRATO\nLOCAL DA EXECUÇÃO DO CONTRATO (PROCEDIMENTO)\nPaís: Portugal\nNUT III: PT111\nLocalidade: Viana do Castelo\nDistrito: Viana do Castelo\nConcelho: Valença\nFreguesia: Todas\n\n10 - PRAZO DE EXECUÇÃO DO CONTRATO\nPrazo de execução do contrato: 7 MESES\nPrevisão de renovações: Não\n\n11 - FUNDOS EU\nTêm fundos EU? Não\n\n12 - DOCUMENTOS DE HABILITAÇÃO\nHabilitação para o exercício da atividade profissional: Sim\nTipo: Outros\nDescrição - Outros: Os previstos no ponto 28 do PC\nDescrição: Os previstos no ponto 28 do PC\n\n13 - CONDIÇÕES DE APRESENTAÇÃO\nPlataforma eletrónica utilizada pela entidade adjudicante: VORTAL\nURL para Apresentação: https://community.vortal.biz/public/\nAdmissibilidade da apresentação de propostas variantes: Não autorizado\nPrazo para apresentação das propostas: 22-10-2025 17:00\nPrazo durante o qual os concorrentes são obrigados a manter as respetivas propostas: 66 dias a contar do termo do prazo para a apresentação das propostas\nIndicação de Subcontratação na Proposta: Inexistência de indicação de subcontratação\n\n14 - PRESTAÇÃO DE CAUÇÃO\nPrestação de caução: Não\n\n15 - FORNECIMENTO DAS PEÇAS DO CONCURSO, APRESENTAÇÃO DE PEDIDOS DE PARTICIPAÇÃO E APRESENTAÇÃO DAS PROPOSTAS\nLink para acesso às peças do concurso (URL): https://community.vortal.biz/Public/public-tender-documents/d2JVaXhBZXp2VzdXQ1kzTERCOWtrbVFNUWVRNHhPeGxKMC92aHgxcjJUZFRLQVc4WXJQWnM4Y1l3RjZ5WFNEZHBBaDAvMm1ZdE1ycVhoc1A4M1Z3Y2c9PWs4Wk9w\n\n20 - OUTROS REQUISITOS\nInformação sobre contratos reservados. Aplica-se a contratos reservados (54º-A)? Não\n\n21 - CRITÉRIO DE ADJUDICAÇÃO\nMultifator: Não\nMonofator:\nNome: Preço\n\n24 - CONDIÇÕES DO CONTRATO\nFaturação Eletrónica: Permitido\nObrigação de Subcontratação:\nCódigo da Obrigação de Subcontratação: Não é aplicável nenhuma obrigação de subcontratação.\n\n25 - COMPRA PÚBLICA ESTRATÉGICA\nCompra Pública Estratégica: Inexistência de contratação pública estratégica\n\n26 - INFORMAÇÕES ADICIONAIS\nContrato adequado para PME: Sim\nCobertura ACP (Acordo dos Contratos Públicos da Organização Mundial do Comércio): Não\n\n27 - IDENTIFICAÇÃO E CONTACTOS DO ÓRGÃO DE RECURSOS ADMINISTRATIVOS\nDesignação: José Manuel Vaz Carpinteira\nEndereço: Praça da Republica nº702\nCódigo postal: 4930-702\nLocalidade: Valença\nTelefone: +351 251809500\nFax: +351 251809518\nEndereço eletrónico: aprovisionamento@cm-valenca.pt\n\n28 - IDENTIFICAÇÃO DO(S) AUTOR(ES) DE ANÚNCIO\nNome: José Manuel Vaz Capinteira\nCargo: Presidente Câmara Municipal\n419666748",
    "nipc": "506728897",
    "distrito": "Viana do Castelo",
    "concelho": "Valença",
    "freguesia": "Todas",
    "site": "www.cm-valenca.pt",
    "email": "geral@cm-valenca.pt",
    "designacao_contrato": "FORNECIMENTO DE PRODUTOS ALIMENTARES – CONGELADOS para a confeção de Refeições ESCOLARES nos Refeitórios do Agrupamento de Escolas de Muralhas do Minho",
    "descricao": "FORNECIMENTO DE PRODUTOS ALIMENTARES – CONGELADOS para a confeção de Refeições ESCOLARES nos Refeitórios do Agrupamento de Escolas de Muralhas do Minho",
    "preco_base": "56.920,69 EUR",
    "prazo_execucao": "7 MESES",
    "prazo_apresentacao_propostas": "22-10-2025 17:00",
    "fundos_eu": "Não",
    "plataforma_eletronica": "VORTAL",
    "url_procedimento": "https://community.vortal.biz/public/",
    "autor_nome": "José Manuel Vaz Capinteira",
    "autor_cargo": "Presidente Câmara Municipal"
  },
  {
    "numero_procedimento": "N/A",
    "entidade": "TTSL - Transtejo Soflusa, SA",
    "link": "https://diariodarepublica.pt/dr/detalhe/contrato-publico/27387-940560155",
    "detalhes_completos": "1 - IDENTIFICAÇÃO E CONTACTOS DA ENTIDADE ADJUDICANTE\nDesignação da entidade adjudicante: TTSL - Transtejo Soflusa, SA\nNIPC: 500723770\nEndereço: Rua da Cintura do Porto de Lisboa- Terminal Fluvial do Cais do Sodré\nCódigo postal: 1249-249\nLocalidade: Lisboa\nPaís: Portugal\nNUT III: PT170\nDistrito: Lisboa\nConcelho: Lisboa\nFreguesia: Todas\nTelefone: 210422400\nFax: 210422499\nEndereço da Entidade (URL): www.transtejo.pt\nEndereço Eletrónico: contratacao@transtejo.pt\neDelivery Gateway (URL): https://community.vortal.biz/public/\nFunção da Organização: Adquirente\nNorma jurídica da Entidade Adjudicante: Organismo de direito público\nÁrea de atividade da Autoridade Adjudicante: Serviços públicos das administrações públicas\n\n2 - JORNAL OFICIAL DA UNIÃO EUROPEIA\nO procedimento a que este anúncio diz respeito também é publicitado no Jornal Oficial da União Europeia? Não\n\n3 - AVISO\nModelo de Anúncio: Concurso público\nData de Envio do Anúncio: 16-10-2025\n\n5 - PROCESSO\nTipo de Procedimento: Concurso público\nPreço base do procedimento: Sim\nValor do preço base do procedimento: 107.250,00 EUR\nProcedimento com lotes? Não\n\n6 - OBJETO DO CONTRATO\nNúmero de referência interna: 115/2025\nDesignação do contrato: Aquisição de serviços de  recolha, transporte, tratamento e contagem de valores de valores de bilheteiras  assistidas e MAVTS \nDescrição: Aquisição de serviços de recolha, transporte, tratamento e contagem de valores de valores de bilheteiras assistidas e MAVTS de todos os Terminais e estações Fluviais da TTSL.\nTipo de Contrato Principal: Aquisição de Serviços\nTipo de Contrato: Aquisição de Serviços\nClassificação CPV (Vocabulário Comum para os Contratos Públicos)\nObjeto principal\nVocabulário Principal: 79710000\nPreço base s/IVA: 107.250,00 EUR\n\n7 - INDICAÇÕES ADICIONAIS\nO contrato envolve aquisição conjunta (satisfação de várias entidades)? Não\nO contrato é adjudicado por uma central de compras? Não\n\n8 - TÉCNICAS\nO concurso destina-se à celebração de um acordo-quadro? Inexistência de acordo-quadro\nÉ utilizado um leilão eletrónico? Não\nÉ adotada uma fase de negociação? Não\nSistema de Aquisição Dinâmico: Inexistência de sistema de aquisição dinâmico\n\n9 - LOCAL DA EXECUÇÃO DO CONTRATO\nLOCAL DA EXECUÇÃO DO CONTRATO (PROCEDIMENTO)\nPaís: Portugal\nNUT III: PT170\nLocalidade: Lisboa\nDistrito: Lisboa\nConcelho: Lisboa\nFreguesia: Todas\n\n10 - PRAZO DE EXECUÇÃO DO CONTRATO\nPrazo de execução do contrato: 13 MESES\nPrevisão de renovações: Não\n\n11 - FUNDOS EU\nTêm fundos EU? Não\n\n12 - DOCUMENTOS DE HABILITAÇÃO\nHabilitação para o exercício da atividade profissional: Não\n\n13 - CONDIÇÕES DE APRESENTAÇÃO\nPlataforma eletrónica utilizada pela entidade adjudicante: VORTAL\nURL para Apresentação: https://community.vortal.biz/public/\nAdmissibilidade da apresentação de propostas variantes: Não autorizado\nPrazo para apresentação das propostas: 28-10-2025 17:00\nPrazo durante o qual os concorrentes são obrigados a manter as respetivas propostas: 180 dias a contar do termo do prazo para a apresentação das propostas\nIndicação de Subcontratação na Proposta: Inexistência de indicação de subcontratação\n\n14 - PRESTAÇÃO DE CAUÇÃO\nPrestação de caução: Não\n\n15 - FORNECIMENTO DAS PEÇAS DO CONCURSO, APRESENTAÇÃO DE PEDIDOS DE PARTICIPAÇÃO E APRESENTAÇÃO DAS PROPOSTAS\nLink para acesso às peças do concurso (URL): https://community.vortal.biz/Public/public-tender-documents/QWNNaXd3a1UwVS9nUTBmNWkrV0RVYUNuYnJwMWxRZzBodklHTG1vek1CQ3IyVG0wYWw2YXk1VGErd0hVMUZWKzBTWmhxcFJHellqMUZuc1J5QVA1WVE9PVA3NThT\n\n20 - OUTROS REQUISITOS\nInformação sobre contratos reservados. Aplica-se a contratos reservados (54º-A)? Não\n\n21 - CRITÉRIO DE ADJUDICAÇÃO\nMultifator: Não\nMonofator:\nNome: Preço\n\n24 - CONDIÇÕES DO CONTRATO\nFaturação Eletrónica: Permitido\nObrigação de Subcontratação:\nCódigo da Obrigação de Subcontratação: Não é aplicável nenhuma obrigação de subcontratação.\n\n25 - COMPRA PÚBLICA ESTRATÉGICA\nCompra Pública Estratégica: Inexistência de contratação pública estratégica\n\n26 - INFORMAÇÕES ADICIONAIS\nContrato adequado para PME: Sim\nCobertura ACP (Acordo dos Contratos Públicos da Organização Mundial do Comércio): Não\n\n27 - IDENTIFICAÇÃO E CONTACTOS DO ÓRGÃO DE RECURSOS ADMINISTRATIVOS\nDesignação: TTSL-Transtejo Soflusa, S.A.\nEndereço: Rua da Cintura do Porto de Lisboa, Terminal Fluvial do Cais do Sodré\nCódigo postal: 1249-249\nLocalidade: Lisboa\nTelefone: +351 210422400\nFax: +351 210422499\nEndereço eletrónico: contratacao@ttsl.pt\n\n28 - IDENTIFICAÇÃO DO(S) AUTOR(ES) DE ANÚNCIO\nNome: Carolina Fernandes Gaspar Alberto\nCargo: Técnico Superior\n419664641",
    "nipc": "500723770",
    "distrito": "Lisboa",
    "concelho": "Lisboa",
    "freguesia": "Todas",
    "site": "www.transtejo.pt",
    "email": "contratacao@transtejo.pt",
    "designacao_contrato": "Aquisição de serviços de recolha, transporte, tratamento e contagem de valores de valores de bilheteiras assistidas e MAVTS",
    "descricao": "Aquisição de serviços de recolha, transporte, tratamento e contagem de valores de valores de bilheteiras assistidas e MAVTS de todos os Terminais e estações Fluviais da TTSL.",
    "preco_base": "107.250,00 EUR",
    "prazo_execucao": "13 MESES",
    "prazo_apresentacao_propostas": "28-10-2025 17:00",
    "fundos_eu": "Não",
    "plataforma_eletronica": "VORTAL",
    "url_procedimento": "https://community.vortal.biz/public/",
    "autor_nome": "Carolina Fernandes Gaspar Alberto",
    "autor_cargo": "Técnico Superior"
  },
  {
    "numero_procedimento": "N/A",
    "entidade": "Serviços Municipalizados de Alcobaça",
    "link": "https://diariodarepublica.pt/dr/detalhe/contrato-publico/27388-940560156",
    "detalhes_completos": "Alteração do Anúncio de procedimento n.º 26460/2025, de 2025-10-08, com o ID 419628823\n\n1 - IDENTIFICAÇÃO E CONTACTOS DA ENTIDADE ADJUDICANTE\nDesignação da entidade adjudicante: Serviços Municipalizados de Alcobaça\nNIPC: 680014942\nServiço/Órgão/Pessoa de contacto: Divisão Jurídica e de Contratação Pública\nEndereço: Rua da Liberdade, n.º 9\nCódigo postal: 2460-060\nLocalidade: Alcobaça\nPaís: Portugal\nNUT III: PT16B\nDistrito: Leiria\nConcelho: Alcobaça\nFreguesia: Todas\nTelefone: 262580910\nFax: 262580905\nEndereço da Entidade (URL): www.smalcobaca.pt\nEndereço Eletrónico: geral@sm-alcobaca.pt\neDelivery Gateway (URL): https://www.acingov.pt\nFunção da Organização: Adquirente\nNorma jurídica da Entidade Adjudicante: Organismo de direito público\nÁrea de atividade da Entidade Adjudicante: Atividades relacionadas com a água\n\n2 - JORNAL OFICIAL DA UNIÃO EUROPEIA\nO procedimento a que este anúncio diz respeito também é publicitado no Jornal Oficial da União Europeia? Não\n\n3 - AVISO\nModelo de Anúncio: Concurso público\nData de Envio do Anúncio: 16-10-2025\n\n5 - PROCESSO\nTipo de Procedimento: Concurso público\nPreço base do procedimento: Sim\nValor do preço base do procedimento: 122.976,00 EUR\nProcedimento com lotes? Não\n\n6 - OBJETO DO CONTRATO\nNúmero de referência interna: 51/25/CP\nDesignação do contrato: Procedimento n.º 51/25/CP - Aquisição de Serviços de Seguros (Frota Automóvel e Responsabilidade Civil)\nDescrição: Procedimento n.º 51/25/CP - Aquisição de Serviços de Seguros (Frota Automóvel e Responsabilidade Civil)\nTipo de Contrato Principal: Aquisição de Serviços\nTipo de Contrato: Aquisição de Serviços\nClassificação CPV (Vocabulário Comum para os Contratos Públicos)\nObjeto principal\nVocabulário Principal: 66510000\nPreço base s/IVA: 122.976,00 EUR\n\n7 - INDICAÇÕES ADICIONAIS\nO contrato envolve aquisição conjunta (satisfação de várias entidades)? Não\nO contrato é adjudicado por uma central de compras? Não\n\n8 - TÉCNICAS\nO concurso destina-se à celebração de um acordo-quadro? Inexistência de acordo-quadro\nÉ utilizado um leilão eletrónico? Não\nÉ adotada uma fase de negociação? Não\nSistema de Aquisição Dinâmico: Inexistência de sistema de aquisição dinâmico\n\n9 - LOCAL DA EXECUÇÃO DO CONTRATO\nLOCAL DA EXECUÇÃO DO CONTRATO (PROCEDIMENTO)\nPaís: Portugal\nNUT III: PT16B\nLocalidade: União das Freguesias de Alcobaça e Vestiaria\nDistrito: Leiria\nConcelho: Alcobaça\nFreguesia: União das Freguesias de Alcobaça e Vestiaria\n\n10 - PRAZO DE EXECUÇÃO DO CONTRATO\nPrazo de execução do contrato: 36 MESES\nPrevisão de renovações: Sim\nIndicar número máximo de renovações: 2\nPrazo de renovações diferente do prazo inicial: Não\n\n11 - FUNDOS EU\nTêm fundos EU? Não\n\n12 - DOCUMENTOS DE HABILITAÇÃO\nHabilitação para o exercício da atividade profissional: Não\n\n13 - CONDIÇÕES DE APRESENTAÇÃO\nPlataforma eletrónica utilizada pela entidade adjudicante: ACIN\nURL para Apresentação: https://www.acingov.pt\nAdmissibilidade da apresentação de propostas variantes: Não autorizado\nPrazo para apresentação das propostas: 31-10-2025 23:59\nPrazo durante o qual os concorrentes são obrigados a manter as respetivas propostas: 120 dias a contar do termo do prazo para a apresentação das propostas\nIndicação de Subcontratação na Proposta: Inexistência de indicação de subcontratação\n\n14 - PRESTAÇÃO DE CAUÇÃO\nPrestação de caução: Não\n\n15 - FORNECIMENTO DAS PEÇAS DO CONCURSO, APRESENTAÇÃO DE PEDIDOS DE PARTICIPAÇÃO E APRESENTAÇÃO DAS PROPOSTAS\nLink para acesso às peças do concurso (URL): https://www.acingov.pt/acingovprod/2/zonaPublica/zona_publica_c/donwloadProcedurePiece/OTg0MTI3\n\n20 - OUTROS REQUISITOS\nInformação sobre contratos reservados. Aplica-se a contratos reservados (54º-A)? Não\n\n21 - CRITÉRIO DE ADJUDICAÇÃO\nMultifator: Não\nMonofator:\nNome: Outros\nOutro nome: Fator Preço\n\n24 - CONDIÇÕES DO CONTRATO\nFaturação Eletrónica: Permitido\nObrigação de Subcontratação:\nCódigo da Obrigação de Subcontratação: Não é aplicável nenhuma obrigação de subcontratação.\n\n25 - COMPRA PÚBLICA ESTRATÉGICA\nCompra Pública Estratégica: Inexistência de contratação pública estratégica\n\n26 - INFORMAÇÕES ADICIONAIS\nContrato adequado para PME: Não\nCobertura ACP (Acordo dos Contratos Públicos da Organização Mundial do Comércio): Não\n\n27 - IDENTIFICAÇÃO E CONTACTOS DO ÓRGÃO DE RECURSOS ADMINISTRATIVOS\nDesignação: Conselho de Administração\nEndereço: Rua da Liberdade, n.º 9\nCódigo postal: 2460-060\nLocalidade: Alcobaça\nTelefone: 262580910\nFax: \nEndereço eletrónico: geral@sm-alcobaca.pt\n\n28 - IDENTIFICAÇÃO DO(S) AUTOR(ES) DE ANÚNCIO\nNome: Susana Paula Ferreira Guerra Jordão\nCargo: Presidente do Conselho de Administração\n\n29 - ALTERAÇÃO\nMotivo da Alteração: Correção pelo adquirente\nIdentificador da Versão do Anúncio a Alterar: 5c14e752-85a4-4d94-a454-7918862aba99-02\nIdentificador das Secções Alteradas do Anúncio Anterior: Condições de Apresentação\nDescrição das Alterações: Modificação do prazo para a apresentação de propostas\nAlteração dos Documentos do Concurso: Sim\nData de alteração dos documentos do concurso: 16-10-2025\n419668246",
    "nipc": "680014942",
    "distrito": "Leiria",
    "concelho": "Alcobaça",
    "freguesia": "Todas",
    "site": "www.smalcobaca.pt",
    "email": "geral@sm-alcobaca.pt",
    "designacao_contrato": "Procedimento n.º 51/25/CP - Aquisição de Serviços de Seguros (Frota Automóvel e Responsabilidade Civil)",
    "descricao": "Procedimento n.º 51/25/CP - Aquisição de Serviços de Seguros (Frota Automóvel e Responsabilidade Civil)",
    "preco_base": "122.976,00 EUR",
    "prazo_execucao": "36 MESES",
    "prazo_apresentacao_propostas": "31-10-2025 23:59",
    "fundos_eu": "Não",
    "plataforma_eletronica": "ACIN",
    "url_procedimento": "https://www.acingov.pt",
    "autor_nome": "Susana Paula Ferreira Guerra Jordão",
    "autor_cargo": "Presidente do Conselho de Administração"
  },
  {
    "numero_procedimento": "N/A",
    "entidade": "AR - Águas do Ribatejo, E. I. M., S. A.",
    "link": "https://diariodarepublica.pt/dr/detalhe/contrato-publico/27389-940560157",
    "detalhes_completos": "1 - IDENTIFICAÇÃO E CONTACTOS DA ENTIDADE ADJUDICANTE\nDesignação da entidade adjudicante: AR - Águas do Ribatejo, E. I. M., S. A.\nNIPC: 508345464\nEndereço: Rua Gaspar Costa Ramalho, nº38\nCódigo postal: 2120-098\nLocalidade: Santarém\nPaís: Portugal\nNUT III: PT185\nDistrito: Santarém\nConcelho: Salvaterra de Magos\nFreguesia: União das Freguesias de Salvaterra de Magos e Foros de Salvaterra\nTelefone: 243303240\nEndereço da Entidade (URL): www.aguasdoribatejo.com\nEndereço Eletrónico: geral@aguasdoribatejo.com\neDelivery Gateway (URL): https://community.vortal.biz/public/\nFunção da Organização: Adquirente\nNorma jurídica da Entidade Adjudicante: Empresa pública, controlada por uma autoridade local\nÁrea de atividade da Autoridade Adjudicante: Proteção ambiental\n\n2 - JORNAL OFICIAL DA UNIÃO EUROPEIA\nO procedimento a que este anúncio diz respeito também é publicitado no Jornal Oficial da União Europeia? Sim\n\n3 - AVISO\nModelo de Anúncio: Concurso público\nData de Envio do Anúncio: 14-10-2025\n\n5 - PROCESSO\nTipo de Procedimento: Concurso público\nPreço base do procedimento: Sim\nValor do preço base do procedimento: 2.200.000,00 EUR\nProcedimento com lotes? Não\n\n6 - OBJETO DO CONTRATO\nNúmero de referência interna: EMP/011/2025\nDesignação do contrato: Empreitada para a reabilitação de infraestruturas no subsistema de abastecimento de água de Coruche / Valverde / Fajarda\nDescrição: Reabilitação de infraestruturas no subsistema de abastecimento de água de Coruche / Valverde / Fajarda\nOpções: Não\nTipo de Contrato Principal: Empreitada de Obras Públicas\nTipo de Contrato: Empreitada de Obras Públicas\nClassificação CPV (Vocabulário Comum para os Contratos Públicos)\nObjeto principal\nVocabulário Principal: 45232151\nPreço base s/IVA: 2.200.000,00 EUR\n\n7 - INDICAÇÕES ADICIONAIS\nO contrato envolve aquisição conjunta (satisfação de várias entidades)? Não\nO contrato é adjudicado por uma central de compras? Não\n\n8 - TÉCNICAS\nO concurso destina-se à celebração de um acordo-quadro? Inexistência de acordo-quadro\nÉ utilizado um leilão eletrónico? Não\nÉ adotada uma fase de negociação? Não\nSistema de Aquisição Dinâmico: Inexistência de sistema de aquisição dinâmico\n\n9 - LOCAL DA EXECUÇÃO DO CONTRATO\nLOCAL DA EXECUÇÃO DO CONTRATO (PROCEDIMENTO)\nPaís: Portugal\nNUT III: PT185\nLocalidade: Coruche\nDistrito: Santarém\nConcelho: Coruche\nFreguesia: União das Freguesias de Coruche, Fajarda e Erra\n\n10 - PRAZO DE EXECUÇÃO DO CONTRATO\nPrazo de execução do contrato: 660 DIAS\nPrevisão de renovações: Não\n\n11 - FUNDOS EU\nTêm fundos EU? Sim\n\n12 - DOCUMENTOS DE HABILITAÇÃO\nHabilitação para o exercício da atividade profissional: Sim\nTipo: Outros\nDescrição - Outros: Conforme programa de concurso\nDescrição: Conforme programa do concurso.\n\n13 - CONDIÇÕES DE APRESENTAÇÃO\nPlataforma eletrónica utilizada pela entidade adjudicante: VORTAL\nURL para Apresentação: https://community.vortal.biz/public/\nAdmissibilidade da apresentação de propostas variantes: Não autorizado\nPrazo para apresentação das propostas: 13-11-2025 23:59\nPrazo durante o qual os concorrentes são obrigados a manter as respetivas propostas: 180 dias a contar do termo do prazo para a apresentação das propostas\nApresentação de Catálogo Eletrónico: Permitido\nIndicação de Subcontratação na Proposta: Inexistência de indicação de subcontratação\n\n14 - PRESTAÇÃO DE CAUÇÃO\nPrestação de caução: Sim\nPercentagem: 5%\nDescrição da Garantia Exigida: Conforme programa do concurso.\n\n15 - FORNECIMENTO DAS PEÇAS DO CONCURSO, APRESENTAÇÃO DE PEDIDOS DE PARTICIPAÇÃO E APRESENTAÇÃO DAS PROPOSTAS\nLink para acesso às peças do concurso (URL): https://community.vortal.biz/Public/public-tender-documents/Z01jU2hlWWNENzFIWTRXWUVBbkZtOWUrVVZEcllCQzkzY1BNRlAyRlFTbkdHUFNLcFF1cStSYi9IMjF1U3licGtHVkpBbjE3WStueUhpQ1VLY1ZKb2c9PUxIX3RY\n\n20 - OUTROS REQUISITOS\nInformação sobre contratos reservados. Aplica-se a contratos reservados (54º-A)? Não\n\n21 - CRITÉRIO DE ADJUDICAÇÃO\nMultifator: Não\nMonofator:\nNome: Preço\n\n24 - CONDIÇÕES DO CONTRATO\nFaturação Eletrónica: Permitido\nObrigação de Subcontratação:\nCódigo da Obrigação de Subcontratação: Não é aplicável nenhuma obrigação de subcontratação.\n\n25 - COMPRA PÚBLICA ESTRATÉGICA\nCompra Pública Estratégica: Inexistência de contratação pública estratégica\n\n26 - INFORMAÇÕES ADICIONAIS\nContrato adequado para PME: Sim\nCobertura ACP (Acordo dos Contratos Públicos da Organização Mundial do Comércio): Não\n\n27 - IDENTIFICAÇÃO E CONTACTOS DO ÓRGÃO DE RECURSOS ADMINISTRATIVOS\nDesignação: Conselho de Administração da AR - Águas do Ribatejo, EIM, SA\nEndereço: Rua Gaspar Costa Ramalho, 38\nCódigo postal: 2120-098\nLocalidade: Salvaterra de Magos\nTelefone: +351 263509400\nFax: +351 263509499\nEndereço eletrónico: geral@aguasdoribatejo.com\n\n28 - IDENTIFICAÇÃO DO(S) AUTOR(ES) DE ANÚNCIO\nNome: Francisco Silvestre de Oliveira\nCargo: Presidente do Conselho de Administração\n419653211",
    "nipc": "508345464",
    "distrito": "Santarém",
    "concelho": "Salvaterra de Magos",
    "freguesia": "União das Freguesias de Salvaterra de Magos e Foros de Salvaterra",
    "site": "www.aguasdoribatejo.com",
    "email": "geral@aguasdoribatejo.com",
    "designacao_contrato": "Empreitada para a reabilitação de infraestruturas no subsistema de abastecimento de água de Coruche / Valverde / Fajarda",
    "descricao": "Reabilitação de infraestruturas no subsistema de abastecimento de água de Coruche / Valverde / Fajarda",
    "preco_base": "2.200.000,00 EUR",
    "prazo_execucao": "660 DIAS",
    "prazo_apresentacao_propostas": "13-11-2025 23:59",
    "fundos_eu": "Sim",
    "plataforma_eletronica": "VORTAL",
    "url_procedimento": "https://community.vortal.biz/public/",
    "autor_nome": "Francisco Silvestre de Oliveira",
    "autor_cargo": "Presidente do Conselho de Administração"
  },
  {
    "numero_procedimento": "N/A",
    "entidade": "Agrupamento Vertical de Canelas",
    "link": "https://diariodarepublica.pt/dr/detalhe/contrato-publico/27391-940560158",
    "detalhes_completos": "1 - IDENTIFICAÇÃO E CONTACTOS DA ENTIDADE ADJUDICANTE\nDesignação da entidade adjudicante: Agrupamento Vertical de Canelas\nNIPC: 600077080\nEndereço: Rua Delfim Lima, Apartado 512\nCódigo postal: 4411-701\nLocalidade: Área Metropolitana do Porto\nPaís: Portugal\nNUT III: PT11A\nDistrito: Porto\nConcelho: Vila Nova de Gaia\nFreguesia: Freguesia de Canelas - Vila Nova de Gaia\nTelefone: +351227116852\nFax: +351227169759\nEndereço da Entidade (URL): https://agrcanelas.edu.pt/\nEndereço Eletrónico: direcao.geral@agrcanelas.edu.pt\neDelivery Gateway (URL): https://community.vortal.biz/public/\nFunção da Organização: Adquirente\nNorma jurídica da Entidade Adjudicante: Organismo de direito público\nÁrea de atividade da Autoridade Adjudicante: Educação\n\n2 - JORNAL OFICIAL DA UNIÃO EUROPEIA\nO procedimento a que este anúncio diz respeito também é publicitado no Jornal Oficial da União Europeia? Não\n\n3 - AVISO\nModelo de Anúncio: Concurso público\nData de Envio do Anúncio: 16-10-2025\n\n5 - PROCESSO\nTipo de Procedimento: Concurso público\nPreço base do procedimento: Sim\nValor do preço base do procedimento: 116.918,00 EUR\nProcedimento com lotes? Não\n\n6 - OBJETO DO CONTRATO\nNúmero de referência interna: CTE_2025_06\nDesignação do contrato: Aquisição de mobiliário\nDescrição: Aquisição de mobiliário\nTipo de Contrato Principal: Aquisição de Bens Móveis\nTipo de Contrato: Aquisição de Bens Móveis\nClassificação CPV (Vocabulário Comum para os Contratos Públicos)\nObjeto principal\nVocabulário Principal: 39160000\nPreço base s/IVA: 116.918,00 EUR\n\n7 - INDICAÇÕES ADICIONAIS\nO contrato envolve aquisição conjunta (satisfação de várias entidades)? Não\nO contrato é adjudicado por uma central de compras? Não\n\n8 - TÉCNICAS\nO concurso destina-se à celebração de um acordo-quadro? Inexistência de acordo-quadro\nÉ utilizado um leilão eletrónico? Não\nÉ adotada uma fase de negociação? Não\nSistema de Aquisição Dinâmico: Inexistência de sistema de aquisição dinâmico\n\n9 - LOCAL DA EXECUÇÃO DO CONTRATO\nLOCAL DA EXECUÇÃO DO CONTRATO (PROCEDIMENTO)\nPaís: Portugal\nNUT III: PT11A\nLocalidade: Área Metropolitana do Porto\nDistrito: Porto\nConcelho: Vila Nova de Gaia\nFreguesia: Todas\n\n10 - PRAZO DE EXECUÇÃO DO CONTRATO\nPrazo de execução do contrato: 60 DIAS\nPrevisão de renovações: Não\n\n11 - FUNDOS EU\nTêm fundos EU? Sim\n\n12 - DOCUMENTOS DE HABILITAÇÃO\nHabilitação para o exercício da atividade profissional: Não\n\n13 - CONDIÇÕES DE APRESENTAÇÃO\nPlataforma eletrónica utilizada pela entidade adjudicante: VORTAL\nURL para Apresentação: https://community.vortal.biz/public/\nAdmissibilidade da apresentação de propostas variantes: Não autorizado\nPrazo para apresentação das propostas: 24-10-2025 23:59\nPrazo durante o qual os concorrentes são obrigados a manter as respetivas propostas: 66 dias a contar do termo do prazo para a apresentação das propostas\nIndicação de Subcontratação na Proposta: Inexistência de indicação de subcontratação\n\n14 - PRESTAÇÃO DE CAUÇÃO\nPrestação de caução: Não\n\n15 - FORNECIMENTO DAS PEÇAS DO CONCURSO, APRESENTAÇÃO DE PEDIDOS DE PARTICIPAÇÃO E APRESENTAÇÃO DAS PROPOSTAS\nLink para acesso às peças do concurso (URL): https://community.vortal.biz/Public/public-tender-documents/S09LWVNJTkxvS3hwcDdnUitpSzhxT3R5UWlyQmVSNnZmNy9xRW5HekNhekdwR0VhMUlKQnB0VXl2eEMzQWxXZE1MbjlKTnd3d2tHZVJWMFhJMXRwSmc9PXJOKlhz\n\n20 - OUTROS REQUISITOS\nInformação sobre contratos reservados. Aplica-se a contratos reservados (54º-A)? Não\n\n21 - CRITÉRIO DE ADJUDICAÇÃO\nMultifator: Não\nMonofator:\nNome: Preço\n\n24 - CONDIÇÕES DO CONTRATO\nFaturação Eletrónica: Permitido\nObrigação de Subcontratação:\nCódigo da Obrigação de Subcontratação: Não é aplicável nenhuma obrigação de subcontratação.\n\n25 - COMPRA PÚBLICA ESTRATÉGICA\nCompra Pública Estratégica: Inexistência de contratação pública estratégica\n\n26 - INFORMAÇÕES ADICIONAIS\nContrato adequado para PME: Sim\nCobertura ACP (Acordo dos Contratos Públicos da Organização Mundial do Comércio): Não\n\n27 - IDENTIFICAÇÃO E CONTACTOS DO ÓRGÃO DE RECURSOS ADMINISTRATIVOS\nDesignação: Conselho Administrativo do Agrupamento de Escolas de Canelas\nEndereço: Rua Delfim de Lima, Apartado 512\nCódigo postal: 4411-701\nLocalidade: Vila Nova de Gaia\nTelefone: +351 227116852\nFax: +351 227169759\nEndereço eletrónico: propostas.ccp@agrcanelas.edu.pt\n\n28 - IDENTIFICAÇÃO DO(S) AUTOR(ES) DE ANÚNCIO\nNome: Filipe José Serra Moreira Ferreira\nCargo: Diretor do Agrupamento de Escolas de Canelas\n419663418",
    "nipc": "600077080",
    "distrito": "Porto",
    "concelho": "Vila Nova de Gaia",
    "freguesia": "Freguesia de Canelas - Vila Nova de Gaia",
    "site": "https://agrcanelas.edu.pt/",
    "email": "direcao.geral@agrcanelas.edu.pt",
    "designacao_contrato": "Aquisição de mobiliário",
    "descricao": "Aquisição de mobiliário",
    "preco_base": "116.918,00 EUR",
    "prazo_execucao": "60 DIAS",
    "prazo_apresentacao_propostas": "24-10-2025 23:59",
    "fundos_eu": "Sim",
    "plataforma_eletronica": "VORTAL",
    "url_procedimento": "https://community.vortal.biz/public/",
    "autor_nome": "Filipe José Serra Moreira Ferreira",
    "autor_cargo": "Diretor do Agrupamento de Escolas de Canelas"
  },
  {
    "numero_procedimento": "N/A",
    "entidade": "AnÃºncio de procedimento  n.Âº 27392/2025  -  DiÃ¡rio da RepÃºblica n.Âº 201/2025, SÃ©rie II de 2025-10-17",
    "link": "https://diariodarepublica.pt/dr/detalhe/contrato-publico/27392-940560159"
  },
  {
    "numero_procedimento": "N/A",
    "entidade": "AnÃºncio de procedimento  n.Âº 27393/2025  -  DiÃ¡rio da RepÃºblica n.Âº 201/2025, SÃ©rie II de 2025-10-17",
    "link": "https://diariodarepublica.pt/dr/detalhe/contrato-publico/27393-940560160"
  },
  {
    "numero_procedimento": "N/A",
    "entidade": "Convergência - Formadores Associados, L.da",
    "link": "https://diariodarepublica.pt/dr/detalhe/contrato-publico/27395-940560161",
    "detalhes_completos": "1 - IDENTIFICAÇÃO E CONTACTOS DA ENTIDADE ADJUDICANTE\nDesignação da entidade adjudicante: Convergência - Formadores Associados, L.da\nNIPC: 502465905\nEndereço: Rua Paio Peres Correia, 8 - 8A\nCódigo postal: 1900-364\nLocalidade: Santarém\nPaís: Portugal\nNUT III: PT185\nDistrito: Santarém\nConcelho: Coruche\nFreguesia: União das Freguesias de Coruche, Fajarda e Erra\nTelefone: 218148890\nFax: 218148891\nEndereço da Entidade (URL): www.ephtl.edu.pt\nEndereço Eletrónico: geral@ephtl.edu.pt\neDelivery Gateway (URL): https://community.vortal.biz/public/\nFunção da Organização: Adquirente\nNorma jurídica da Entidade Adjudicante: Autoridade da administração central\nÁrea de atividade da Autoridade Adjudicante: Educação\n\n2 - JORNAL OFICIAL DA UNIÃO EUROPEIA\nO procedimento a que este anúncio diz respeito também é publicitado no Jornal Oficial da União Europeia? Sim\n\n3 - AVISO\nModelo de Anúncio: Concurso público\nData de Envio do Anúncio: 14-10-2025\n\n5 - PROCESSO\nTipo de Procedimento: Concurso público\nPreço base do procedimento: Sim\nValor do preço base do procedimento: 723.016,29 EUR\nProcedimento com lotes? Não\n\n6 - OBJETO DO CONTRATO\nNúmero de referência interna: CPI04.CTE.EPHTL.2025\nDesignação do contrato: Aquisição de equipamento mobiliário no âmbito dos Centros Tecnológicos Especializados (CTE)\nDescrição: Aquisição de equipamento mobiliário no âmbito dos Centros Tecnológicos Especializados (CTE)\nOpções: Não\nTipo de Contrato Principal: Aquisição de Bens Móveis\nTipo de Contrato: Aquisição de Bens Móveis\nClassificação CPV (Vocabulário Comum para os Contratos Públicos)\nObjeto principal\nVocabulário Principal: 39100000\nPreço base s/IVA: 723.016,29 EUR\n\n7 - INDICAÇÕES ADICIONAIS\nO contrato envolve aquisição conjunta (satisfação de várias entidades)? Não\nO contrato é adjudicado por uma central de compras? Não\n\n8 - TÉCNICAS\nO concurso destina-se à celebração de um acordo-quadro? Inexistência de acordo-quadro\nÉ utilizado um leilão eletrónico? Não\nÉ adotada uma fase de negociação? Não\nSistema de Aquisição Dinâmico: Inexistência de sistema de aquisição dinâmico\n\n9 - LOCAL DA EXECUÇÃO DO CONTRATO\nLOCAL DA EXECUÇÃO DO CONTRATO (PROCEDIMENTO)\nPaís: Portugal\nNUT III: PT170\nLocalidade: Lisboa\nDistrito: Lisboa\nConcelho: Lisboa\nFreguesia: Freguesia de Penha de França\n\n10 - PRAZO DE EXECUÇÃO DO CONTRATO\nPrazo de execução do contrato: 150 DIAS\nPrevisão de renovações: Não\n\n11 - FUNDOS EU\nTêm fundos EU? Não\n\n12 - DOCUMENTOS DE HABILITAÇÃO\nHabilitação para o exercício da atividade profissional: Sim\nTipo: Outros\nDescrição - Outros: não aplicavel\nDescrição: n.a\n\n13 - CONDIÇÕES DE APRESENTAÇÃO\nPlataforma eletrónica utilizada pela entidade adjudicante: VORTAL\nURL para Apresentação: https://community.vortal.biz/public/\nAdmissibilidade da apresentação de propostas variantes: Não autorizado\nPrazo para apresentação das propostas: 13-11-2025 18:00\nPrazo durante o qual os concorrentes são obrigados a manter as respetivas propostas: 90 dias a contar do termo do prazo para a apresentação das propostas\nApresentação de Catálogo Eletrónico: Permitido\nIndicação de Subcontratação na Proposta: Inexistência de indicação de subcontratação\n\n14 - PRESTAÇÃO DE CAUÇÃO\nPrestação de caução: Sim\nPercentagem: 5%\nDescrição da Garantia Exigida: Modelo de Seguro - Caução; Modelo de garantia bancária; Modelo de guia de depósito bancário\n\n15 - FORNECIMENTO DAS PEÇAS DO CONCURSO, APRESENTAÇÃO DE PEDIDOS DE PARTICIPAÇÃO E APRESENTAÇÃO DAS PROPOSTAS\nLink para acesso às peças do concurso (URL): https://community.vortal.biz/Public/public-tender-documents/Rmx4SGlZRVM5bUsvQjgwbmIxWkhxeGxaaG1jbWd6bzVTcjYwcjVYWnk3TCs4SWhMbzVyZWlHYTVXV2hGRWdLRko4cTRRVDNSSm82aHVSc0gvYmZpREE9PWVnQE1t\n\n20 - OUTROS REQUISITOS\nInformação sobre contratos reservados. Aplica-se a contratos reservados (54º-A)? Não\n\n21 - CRITÉRIO DE ADJUDICAÇÃO\nMultifator: Não\nMonofator:\nNome: Outros\nOutro nome: Preço\n\n24 - CONDIÇÕES DO CONTRATO\nFaturação Eletrónica: Permitido\nObrigação de Subcontratação:\nCódigo da Obrigação de Subcontratação: Não é aplicável nenhuma obrigação de subcontratação.\n\n25 - COMPRA PÚBLICA ESTRATÉGICA\nCompra Pública Estratégica: Inexistência de contratação pública estratégica\n\n26 - INFORMAÇÕES ADICIONAIS\nContrato adequado para PME: Sim\nCobertura ACP (Acordo dos Contratos Públicos da Organização Mundial do Comércio): Não\n\n27 - IDENTIFICAÇÃO E CONTACTOS DO ÓRGÃO DE RECURSOS ADMINISTRATIVOS\nDesignação: Gerente\nEndereço: Rua Paio Peres Correia, 8 - 8A\nCódigo postal: 1900-364\nLocalidade: Lisboa\nTelefone: +351 218148890\nFax: +351 218148890\nEndereço eletrónico: geral@ephtl.edu.pt\n\n28 - IDENTIFICAÇÃO DO(S) AUTOR(ES) DE ANÚNCIO\nNome: João Carapinha\nCargo: Técnico Contratação Pública\n419658226",
    "nipc": "502465905",
    "distrito": "Santarém",
    "concelho": "Coruche",
    "freguesia": "União das Freguesias de Coruche, Fajarda e Erra",
    "site": "www.ephtl.edu.pt",
    "email": "geral@ephtl.edu.pt",
    "designacao_contrato": "Aquisição de equipamento mobiliário no âmbito dos Centros Tecnológicos Especializados (CTE)",
    "descricao": "Aquisição de equipamento mobiliário no âmbito dos Centros Tecnológicos Especializados (CTE)",
    "preco_base": "723.016,29 EUR",
    "prazo_execucao": "150 DIAS",
    "prazo_apresentacao_propostas": "13-11-2025 18:00",
    "fundos_eu": "Não",
    "plataforma_eletronica": "VORTAL",
    "url_procedimento": "https://community.vortal.biz/public/",
    "autor_nome": "João Carapinha",
    "autor_cargo": "Técnico Contratação Pública"
  },
  {
    "numero_procedimento": "N/A",
    "entidade": "Feira Viva - Cultura e Desporto, E. M.",
    "link": "https://diariodarepublica.pt/dr/detalhe/contrato-publico/27379-940618780",
    "detalhes_completos": "1 - IDENTIFICAÇÃO E CONTACTOS DA ENTIDADE ADJUDICANTE\nDesignação da entidade adjudicante: Feira Viva - Cultura e Desporto, E. M.\nNIPC: 505120151\nEndereço: Rua Interior do Europarque\nCódigo postal: 4520-153\nLocalidade: Aveiro\nPaís: Portugal\nNUT III: PT11A\nDistrito: Aveiro\nConcelho: Santa Maria da Feira\nFreguesia: União das Freguesias de Santa Maria da Feira, Travanca, Sanfins e Espargo\nTelefone: 256330900\nFax: 256330909\nEndereço Eletrónico: procedimentos@feiraviva.com\neDelivery Gateway (URL): https://community.vortal.biz/public/\nFunção da Organização: Adquirente\nNorma jurídica da Entidade Adjudicante: Autoridade da administração central\nÁrea de atividade da Autoridade Adjudicante: Serviços públicos das administrações públicas\n\n2 - JORNAL OFICIAL DA UNIÃO EUROPEIA\nO procedimento a que este anúncio diz respeito também é publicitado no Jornal Oficial da União Europeia? Não\n\n3 - AVISO\nModelo de Anúncio: Concurso público\nData de Envio do Anúncio: 16-10-2025\n\n5 - PROCESSO\nTipo de Procedimento: Concurso público\nPreço base do procedimento: Sim\nValor do preço base do procedimento: 20.000,00 EUR\nProcedimento com lotes? Não\n\n6 - OBJETO DO CONTRATO\nNúmero de referência interna: 320_2025_CP_BS\nDesignação do contrato: 320_2025_CP_BS - Aquisição de Serviços Audiovisuais para Perlim - Castelo\nDescrição: 320_2025_CP_BS - Aquisição de Serviços Audiovisuais para Perlim - Castelo\nTipo de Contrato Principal: Aquisição de Serviços\nTipo de Contrato: Aquisição de Serviços\nClassificação CPV (Vocabulário Comum para os Contratos Públicos)\nObjeto principal\nVocabulário Principal: 92370000\nPreço base s/IVA: 20.000,00 EUR\n\n7 - INDICAÇÕES ADICIONAIS\nO contrato envolve aquisição conjunta (satisfação de várias entidades)? Não\nO contrato é adjudicado por uma central de compras? Não\n\n8 - TÉCNICAS\nO concurso destina-se à celebração de um acordo-quadro? Inexistência de acordo-quadro\nÉ utilizado um leilão eletrónico? Não\nÉ adotada uma fase de negociação? Não\nSistema de Aquisição Dinâmico: Inexistência de sistema de aquisição dinâmico\n\n9 - LOCAL DA EXECUÇÃO DO CONTRATO\nLOCAL DA EXECUÇÃO DO CONTRATO (PROCEDIMENTO)\nPaís: Portugal\nNUT III: PT11A\nLocalidade: Aveiro\nDistrito: Aveiro\nConcelho: Santa Maria da Feira\nFreguesia: Todas\n\n10 - PRAZO DE EXECUÇÃO DO CONTRATO\nPrazo de execução do contrato: 60 DIAS\nPrevisão de renovações: Não\n\n11 - FUNDOS EU\nTêm fundos EU? Não\n\n12 - DOCUMENTOS DE HABILITAÇÃO\nHabilitação para o exercício da atividade profissional: Não\n\n13 - CONDIÇÕES DE APRESENTAÇÃO\nPlataforma eletrónica utilizada pela entidade adjudicante: VORTAL\nURL para Apresentação: https://community.vortal.biz/public/\nAdmissibilidade da apresentação de propostas variantes: Não autorizado\nPrazo para apresentação das propostas: 22-10-2025 23:59\nPrazo durante o qual os concorrentes são obrigados a manter as respetivas propostas: 120 dias a contar do termo do prazo para a apresentação das propostas\nIndicação de Subcontratação na Proposta: Inexistência de indicação de subcontratação\n\n14 - PRESTAÇÃO DE CAUÇÃO\nPrestação de caução: Não\n\n15 - FORNECIMENTO DAS PEÇAS DO CONCURSO, APRESENTAÇÃO DE PEDIDOS DE PARTICIPAÇÃO E APRESENTAÇÃO DAS PROPOSTAS\nLink para acesso às peças do concurso (URL): https://community.vortal.biz/Public/public-tender-documents/R3Iyb0V0LzJsWit3ZkxxNHV6NmNRcHFIWmpPRGpUbVJwL0FEenN5dVJkL1JZNHpEeVdBTmhFbnhTcHdISkpnME9uWTVpNTRBZWVlb0JXNDdoSUJGMnc9PXdVMygo\n\n20 - OUTROS REQUISITOS\nInformação sobre contratos reservados. Aplica-se a contratos reservados (54º-A)? Não\n\n21 - CRITÉRIO DE ADJUDICAÇÃO\nMultifator: Não\nMonofator:\nNome: Preço\n\n24 - CONDIÇÕES DO CONTRATO\nFaturação Eletrónica: Permitido\nObrigação de Subcontratação:\nCódigo da Obrigação de Subcontratação: Não é aplicável nenhuma obrigação de subcontratação.\n\n25 - COMPRA PÚBLICA ESTRATÉGICA\nCompra Pública Estratégica: Inexistência de contratação pública estratégica\n\n26 - INFORMAÇÕES ADICIONAIS\nContrato adequado para PME: Sim\nCobertura ACP (Acordo dos Contratos Públicos da Organização Mundial do Comércio): Não\n\n27 - IDENTIFICAÇÃO E CONTACTOS DO ÓRGÃO DE RECURSOS ADMINISTRATIVOS\nDesignação: Conselho de Administração Feira Viva Cultura e Desporto, E.M\nEndereço: Rua Interior do Europarque, Apartado 160\nCódigo postal: 4520-153\nLocalidade: Santa Maria da Feira\nTelefone: +351 256330900\nFax: +351 256330900\nEndereço eletrónico: procedimentos@feiraviva.com\n\n28 - IDENTIFICAÇÃO DO(S) AUTOR(ES) DE ANÚNCIO\nNome: Paulo Sérgio Pais\nCargo: Diretor Geral\n419667063",
    "nipc": "505120151",
    "distrito": "Aveiro",
    "concelho": "Santa Maria da Feira",
    "freguesia": "União das Freguesias de Santa Maria da Feira, Travanca, Sanfins e Espargo",
    "site": null,
    "email": "procedimentos@feiraviva.com",
    "designacao_contrato": "320_2025_CP_BS - Aquisição de Serviços Audiovisuais para Perlim - Castelo",
    "descricao": "320_2025_CP_BS - Aquisição de Serviços Audiovisuais para Perlim - Castelo",
    "preco_base": "20.000,00 EUR",
    "prazo_execucao": "60 DIAS",
    "prazo_apresentacao_propostas": "22-10-2025 23:59",
    "fundos_eu": "Não",
    "plataforma_eletronica": "VORTAL",
    "url_procedimento": "https://community.vortal.biz/public/",
    "autor_nome": "Paulo Sérgio Pais",
    "autor_cargo": "Diretor Geral"
  },
  {
    "numero_procedimento": "N/A",
    "entidade": "Município de Matosinhos",
    "link": "https://diariodarepublica.pt/dr/detalhe/contrato-publico/27380-940618781",
    "detalhes_completos": "1 - IDENTIFICAÇÃO E CONTACTOS DA ENTIDADE ADJUDICANTE\nDesignação da entidade adjudicante: Município de Matosinhos\nNIPC: 501305912\nEndereço: Av. D. Afonso Henriques\nCódigo postal: 4454-510\nLocalidade: Matosinhos\nPaís: Portugal\nNUT III: PT11A\nDistrito: Porto\nConcelho: Matosinhos\nFreguesia: Todas\nTelefone: 229390900\nFax: 229351645\nEndereço da Entidade (URL): http://www.cm-matosinhos.pt\nEndereço Eletrónico: contratacaopublica@cm-matosinhos.pt\neDelivery Gateway (URL): https://www.acingov.pt\nFunção da Organização: Adquirente\nSubfunção da Organização: Organização que recebe as propostas\nNorma jurídica da Entidade Adjudicante: Organismo de direito público\nÁrea de atividade da Autoridade Adjudicante: Serviços públicos das administrações públicas\n\n2 - JORNAL OFICIAL DA UNIÃO EUROPEIA\nO procedimento a que este anúncio diz respeito também é publicitado no Jornal Oficial da União Europeia? Sim\n\n3 - AVISO\nModelo de Anúncio: Concurso público\nData de Envio do Anúncio: 14-10-2025\n\n5 - PROCESSO\nTipo de Procedimento: Concurso público\nPreço base do procedimento: Sim\nValor do preço base do procedimento: 225.191,50 EUR\nProcedimento com lotes? Não\n\n6 - OBJETO DO CONTRATO\nNúmero de referência interna: 2025/15633\nDesignação do contrato: MANUTENÇÃO DE SISTEMAS SEMAFÓRICOS NO CONCELHO DE MATOSINHOS\nDescrição: MANUTENÇÃO DE SISTEMAS SEMAFÓRICOS NO CONCELHO DE MATOSINHOS\nOpções: Não\nTipo de Contrato Principal: Aquisição de Serviços\nTipo de Contrato: Aquisição de Serviços\nClassificação CPV (Vocabulário Comum para os Contratos Públicos)\nObjeto principal\nVocabulário Principal: 50800000\nPreço base s/IVA: 225.191,50 EUR\n\n7 - INDICAÇÕES ADICIONAIS\nO contrato envolve aquisição conjunta (satisfação de várias entidades)? Não\nO contrato é adjudicado por uma central de compras? Não\n\n8 - TÉCNICAS\nO concurso destina-se à celebração de um acordo-quadro? Inexistência de acordo-quadro\nÉ utilizado um leilão eletrónico? Não\nÉ adotada uma fase de negociação? Não\nSistema de Aquisição Dinâmico: Inexistência de sistema de aquisição dinâmico\n\n9 - LOCAL DA EXECUÇÃO DO CONTRATO\nLOCAL DA EXECUÇÃO DO CONTRATO (PROCEDIMENTO)\nPaís: Portugal\nNUT III: PT11A\nLocalidade: Matosinhos\nDistrito: Porto\nConcelho: Matosinhos\nFreguesia: Todas\n\n10 - PRAZO DE EXECUÇÃO DO CONTRATO\nPrazo de execução do contrato: 36 MESES\nPrevisão de renovações: Não\n\n11 - FUNDOS EU\nTêm fundos EU? Não\n\n12 - DOCUMENTOS DE HABILITAÇÃO\nHabilitação para o exercício da atividade profissional: Não\n\n13 - CONDIÇÕES DE APRESENTAÇÃO\nPlataforma eletrónica utilizada pela entidade adjudicante: ACIN\nURL para Apresentação: https://www.acingov.pt\nAdmissibilidade da apresentação de propostas variantes: Não autorizado\nPrazo para apresentação das propostas: 16-11-2025 23:59\nPrazo durante o qual os concorrentes são obrigados a manter as respetivas propostas: 66 dias a contar do termo do prazo para a apresentação das propostas\nApresentação de Catálogo Eletrónico: Permitido\nIndicação de Subcontratação na Proposta: Inexistência de indicação de subcontratação\n\n14 - PRESTAÇÃO DE CAUÇÃO\nPrestação de caução: Não\n\n15 - FORNECIMENTO DAS PEÇAS DO CONCURSO, APRESENTAÇÃO DE PEDIDOS DE PARTICIPAÇÃO E APRESENTAÇÃO DAS PROPOSTAS\nLink para acesso às peças do concurso (URL): https://www.acingov.pt/acingovprod/2/zonaPublica/zona_publica_c/donwloadProcedurePiece/OTg2MTYw\n\n20 - OUTROS REQUISITOS\nInformação sobre contratos reservados. Aplica-se a contratos reservados (54º-A)? Não\n\n21 - CRITÉRIO DE ADJUDICAÇÃO\nMultifator: Não\nMonofator:\nNome: Preço\n\n24 - CONDIÇÕES DO CONTRATO\nFaturação Eletrónica: Não autorizado\nObrigação de Subcontratação:\nCódigo da Obrigação de Subcontratação: Não é aplicável nenhuma obrigação de subcontratação.\n\n25 - COMPRA PÚBLICA ESTRATÉGICA\nCompra Pública Estratégica: Inexistência de contratação pública estratégica\n\n26 - INFORMAÇÕES ADICIONAIS\nContrato adequado para PME: Não\nCobertura ACP (Acordo dos Contratos Públicos da Organização Mundial do Comércio): Não\n\n27 - IDENTIFICAÇÃO E CONTACTOS DO ÓRGÃO DE RECURSOS ADMINISTRATIVOS\nDesignação: Município de Matosinhos\nEndereço: Matosinhos\nCódigo postal: 4454-510\nLocalidade: Matosinhos\nTelefone: 229390900\nFax: \nEndereço eletrónico: contratacaopublica@cm-matosinhos.pt\nPrazo de interposição do recurso: 5 dias\n\n28 - IDENTIFICAÇÃO DO(S) AUTOR(ES) DE ANÚNCIO\nNome: Luísa Maria Neves Salgueiro\nCargo: Presidente da Câmara\n419648733",
    "nipc": "501305912",
    "distrito": "Porto",
    "concelho": "Matosinhos",
    "freguesia": "Todas",
    "site": "http://www.cm-matosinhos.pt",
    "email": "contratacaopublica@cm-matosinhos.pt",
    "designacao_contrato": "MANUTENÇÃO DE SISTEMAS SEMAFÓRICOS NO CONCELHO DE MATOSINHOS",
    "descricao": "MANUTENÇÃO DE SISTEMAS SEMAFÓRICOS NO CONCELHO DE MATOSINHOS",
    "preco_base": "225.191,50 EUR",
    "prazo_execucao": "36 MESES",
    "prazo_apresentacao_propostas": "16-11-2025 23:59",
    "fundos_eu": "Não",
    "plataforma_eletronica": "ACIN",
    "url_procedimento": "https://www.acingov.pt",
    "autor_nome": "Luísa Maria Neves Salgueiro",
    "autor_cargo": "Presidente da Câmara"
  },
  {
    "numero_procedimento": "N/A",
    "entidade": "AnÃºncio de procedimento  n.Âº 27382/2025  -  DiÃ¡rio da RepÃºblica n.Âº 201/2025, SÃ©rie II de 2025-10-17",
    "link": "https://diariodarepublica.pt/dr/detalhe/contrato-publico/27382-940618782"
  },
  {
    "numero_procedimento": "N/A",
    "entidade": "AnÃºncio de procedimento  n.Âº 27383/2025  -  DiÃ¡rio da RepÃºblica n.Âº 201/2025, SÃ©rie II de 2025-10-17",
    "link": "https://diariodarepublica.pt/dr/detalhe/contrato-publico/27383-940618785"
  },
  {
    "numero_procedimento": "N/A",
    "entidade": "AnÃºncio de procedimento  n.Âº 27384/2025  -  DiÃ¡rio da RepÃºblica n.Âº 201/2025, SÃ©rie II de 2025-10-17",
    "link": "https://diariodarepublica.pt/dr/detalhe/contrato-publico/27384-940618786"
  },
  {
    "numero_procedimento": "N/A",
    "entidade": "Município de Valença",
    "link": "https://diariodarepublica.pt/dr/detalhe/contrato-publico/27386-940618787",
    "detalhes_completos": "1 - IDENTIFICAÇÃO E CONTACTOS DA ENTIDADE ADJUDICANTE\nDesignação da entidade adjudicante: Município de Valença\nNIPC: 506728897\nEndereço: Pç. Da República, Valença\nCódigo postal: 4930-702\nLocalidade: Valença\nPaís: Portugal\nNUT III: PT111\nDistrito: Viana do Castelo\nConcelho: Valença\nFreguesia: Todas\nTelefone: 251809500\nFax: 251809519\nEndereço da Entidade (URL): www.cm-valenca.pt\nEndereço Eletrónico: geral@cm-valenca.pt\neDelivery Gateway (URL): https://community.vortal.biz/public/\nFunção da Organização: Adquirente\nNorma jurídica da Entidade Adjudicante: Autoridade local\nÁrea de atividade da Autoridade Adjudicante: Serviços públicos das administrações públicas\n\n2 - JORNAL OFICIAL DA UNIÃO EUROPEIA\nO procedimento a que este anúncio diz respeito também é publicitado no Jornal Oficial da União Europeia? Não\n\n3 - AVISO\nModelo de Anúncio: Concurso público\nData de Envio do Anúncio: 16-10-2025\n\n5 - PROCESSO\nTipo de Procedimento: Concurso público\nPreço base do procedimento: Sim\nValor do preço base do procedimento: 6.941,61 EUR\nProcedimento com lotes? Não\n\n6 - OBJETO DO CONTRATO\nNúmero de referência interna: CP-ABS-17/2025\nDesignação do contrato: FORNECIMENTO DE FRUTA PARA OS ALUNOS DO 1º CICLO DO ENSINO BÁSICO DO CONCELHO DE VALENÇA\nDescrição: FORNECIMENTO DE FRUTA PARA OS ALUNOS DO 1º CICLO DO ENSINO BÁSICO DO CONCELHO DE VALENÇA\nTipo de Contrato Principal: Aquisição de Bens Móveis\nTipo de Contrato: Aquisição de Bens Móveis\nClassificação CPV (Vocabulário Comum para os Contratos Públicos)\nObjeto principal\nVocabulário Principal: 03220000\nPreço base s/IVA: 6.941,61 EUR\n\n7 - INDICAÇÕES ADICIONAIS\nO contrato envolve aquisição conjunta (satisfação de várias entidades)? Não\nO contrato é adjudicado por uma central de compras? Não\n\n8 - TÉCNICAS\nO concurso destina-se à celebração de um acordo-quadro? Inexistência de acordo-quadro\nÉ utilizado um leilão eletrónico? Não\nÉ adotada uma fase de negociação? Não\nSistema de Aquisição Dinâmico: Inexistência de sistema de aquisição dinâmico\n\n9 - LOCAL DA EXECUÇÃO DO CONTRATO\nLOCAL DA EXECUÇÃO DO CONTRATO (PROCEDIMENTO)\nPaís: Portugal\nNUT III: PT111\nLocalidade: Viana do Castelo\nDistrito: Viana do Castelo\nConcelho: Valença\nFreguesia: Todas\n\n10 - PRAZO DE EXECUÇÃO DO CONTRATO\nPrazo de execução do contrato: 7 MESES\nPrevisão de renovações: Não\n\n11 - FUNDOS EU\nTêm fundos EU? Não\n\n12 - DOCUMENTOS DE HABILITAÇÃO\nHabilitação para o exercício da atividade profissional: Sim\nTipo: Outros\nDescrição - Outros: Os previstos no ponto 28 do PC\nDescrição: Os previstos no ponto 28 do PC\n\n13 - CONDIÇÕES DE APRESENTAÇÃO\nPlataforma eletrónica utilizada pela entidade adjudicante: VORTAL\nURL para Apresentação: https://community.vortal.biz/public/\nAdmissibilidade da apresentação de propostas variantes: Não autorizado\nPrazo para apresentação das propostas: 22-10-2025 17:00\nPrazo durante o qual os concorrentes são obrigados a manter as respetivas propostas: 66 dias a contar do termo do prazo para a apresentação das propostas\nIndicação de Subcontratação na Proposta: Inexistência de indicação de subcontratação\n\n14 - PRESTAÇÃO DE CAUÇÃO\nPrestação de caução: Não\n\n15 - FORNECIMENTO DAS PEÇAS DO CONCURSO, APRESENTAÇÃO DE PEDIDOS DE PARTICIPAÇÃO E APRESENTAÇÃO DAS PROPOSTAS\nLink para acesso às peças do concurso (URL): https://community.vortal.biz/Public/public-tender-documents/YnJVa0dQd3RpVTdUU3k3UVlDMWJrYW5qSEoxSUpyY0FxNUhSeE1EZEZBOXdMakprMURWM003QldRcVFaRjFTTm9iUHZMMkZwNVpwWldMYk1vN29OZXc9PUpfMGJv\n\n20 - OUTROS REQUISITOS\nInformação sobre contratos reservados. Aplica-se a contratos reservados (54º-A)? Não\n\n21 - CRITÉRIO DE ADJUDICAÇÃO\nMultifator: Não\nMonofator:\nNome: Preço\n\n24 - CONDIÇÕES DO CONTRATO\nFaturação Eletrónica: Permitido\nObrigação de Subcontratação:\nCódigo da Obrigação de Subcontratação: Não é aplicável nenhuma obrigação de subcontratação.\n\n25 - COMPRA PÚBLICA ESTRATÉGICA\nCompra Pública Estratégica: Inexistência de contratação pública estratégica\n\n26 - INFORMAÇÕES ADICIONAIS\nContrato adequado para PME: Sim\nCobertura ACP (Acordo dos Contratos Públicos da Organização Mundial do Comércio): Não\n\n27 - IDENTIFICAÇÃO E CONTACTOS DO ÓRGÃO DE RECURSOS ADMINISTRATIVOS\nDesignação: José Manuel Vaz Carpinteira\nEndereço: Praça da Republica nº702\nCódigo postal: 4930-702\nLocalidade: Valença\nTelefone: +351 251809500\nFax: +351 251809512\nEndereço eletrónico: aprovisionamento@cm-valenca.pt\n\n28 - IDENTIFICAÇÃO DO(S) AUTOR(ES) DE ANÚNCIO\nNome: José Manuel Vaz Carpinteira\nCargo: Presidente da Câmara Municipal\n419666326",
    "nipc": "506728897",
    "distrito": "Viana do Castelo",
    "concelho": "Valença",
    "freguesia": "Todas",
    "site": "www.cm-valenca.pt",
    "email": "geral@cm-valenca.pt",
    "designacao_contrato": "FORNECIMENTO DE FRUTA PARA OS ALUNOS DO 1º CICLO DO ENSINO BÁSICO DO CONCELHO DE VALENÇA",
    "descricao": "FORNECIMENTO DE FRUTA PARA OS ALUNOS DO 1º CICLO DO ENSINO BÁSICO DO CONCELHO DE VALENÇA",
    "preco_base": "6.941,61 EUR",
    "prazo_execucao": "7 MESES",
    "prazo_apresentacao_propostas": "22-10-2025 17:00",
    "fundos_eu": "Não",
    "plataforma_eletronica": "VORTAL",
    "url_procedimento": "https://community.vortal.biz/public/",
    "autor_nome": "José Manuel Vaz Carpinteira",
    "autor_cargo": "Presidente da Câmara Municipal"
  },
  {
    "numero_procedimento": "N/A",
    "entidade": "AnÃºncio de procedimento  n.Âº 27390/2025  -  DiÃ¡rio da RepÃºblica n.Âº 201/2025, SÃ©rie II de 2025-10-17",
    "link": "https://diariodarepublica.pt/dr/detalhe/contrato-publico/27390-940618789"
  },
  {
    "numero_procedimento": "N/A",
    "entidade": "AnÃºncio de procedimento  n.Âº 27394/2025  -  DiÃ¡rio da RepÃºblica n.Âº 201/2025, SÃ©rie II de 2025-10-17",
    "link": "https://diariodarepublica.pt/dr/detalhe/contrato-publico/27394-940618790"
  },
  {
    "numero_procedimento": "N/A",
    "entidade": "Instituto da Conservação da Natureza e das Florestas, I. P.",
    "link": "https://diariodarepublica.pt/dr/detalhe/contrato-publico/27396-940618794",
    "detalhes_completos": "1 - IDENTIFICAÇÃO E CONTACTOS DA ENTIDADE ADJUDICANTE\nDesignação da entidade adjudicante: Instituto da Conservação da Natureza e das Florestas, I. P.\nNIPC: 510342647\nEndereço: Av. Dr. Alfredo Magalhães Ramalho, nº 1\nCódigo postal: 1495-165\nLocalidade: Lisboa\nPaís: Portugal\nNUT III: PT170\nDistrito: Lisboa\nConcelho: Oeiras\nFreguesia: União das Freguesias de Algés, Linda-a-Velha e Cruz Quebrada-Dafundo\nTelefone: 213124800\nFax: 213124800\nEndereço da Entidade (URL): https://www.icnf.pt/\nEndereço Eletrónico: geral@icnf.pt\neDelivery Gateway (URL): https://community.vortal.biz/public/\nFunção da Organização: Adquirente\nNorma jurídica da Entidade Adjudicante: Instituição, órgão ou agência da UE\nÁrea de atividade da Autoridade Adjudicante: Proteção ambiental\n\n2 - JORNAL OFICIAL DA UNIÃO EUROPEIA\nO procedimento a que este anúncio diz respeito também é publicitado no Jornal Oficial da União Europeia? Sim\n\n3 - AVISO\nModelo de Anúncio: Concurso público\nData de Envio do Anúncio: 15-10-2025\n\n5 - PROCESSO\nTipo de Procedimento: Concurso público\nPreço base do procedimento: Sim\nValor do preço base do procedimento: 4.400.000,00 EUR\nProcedimento com lotes? Não\n\n6 - OBJETO DO CONTRATO\nNúmero de referência interna: CP/38/2025/ICNF/SEDE\nDesignação do contrato: Aquisição de 55 veículos ligeiros de combate a incêndios para as equipas de sapadores florestais\nDescrição: Aquisição de 55 veículos ligeiros de combate a incêndios para as equipas de sapadores florestais\nOpções: Não\nTipo de Contrato Principal: Aquisição de Bens Móveis\nTipo de Contrato: Aquisição de Bens Móveis\nClassificação CPV (Vocabulário Comum para os Contratos Públicos)\nObjeto principal\nVocabulário Principal: 34100000\nPreço base s/IVA: 4.400.000,00 EUR\n\n7 - INDICAÇÕES ADICIONAIS\nO contrato envolve aquisição conjunta (satisfação de várias entidades)? Não\nO contrato é adjudicado por uma central de compras? Não\n\n8 - TÉCNICAS\nO concurso destina-se à celebração de um acordo-quadro? Inexistência de acordo-quadro\nÉ utilizado um leilão eletrónico? Não\nÉ adotada uma fase de negociação? Não\nSistema de Aquisição Dinâmico: Inexistência de sistema de aquisição dinâmico\n\n9 - LOCAL DA EXECUÇÃO DO CONTRATO\nLOCAL DA EXECUÇÃO DO CONTRATO (PROCEDIMENTO)\nPaís: Portugal\nNUT III: PT170\nLocalidade: Lisboa\nDistrito: Lisboa\nConcelho: Lisboa\nFreguesia: Freguesia de Avenidas Novas\n\n10 - PRAZO DE EXECUÇÃO DO CONTRATO\nPrazo de execução do contrato: 150 DIAS\nPrevisão de renovações: Não\n\n11 - FUNDOS EU\nTêm fundos EU? Sim\n\n12 - DOCUMENTOS DE HABILITAÇÃO\nHabilitação para o exercício da atividade profissional: Não\n\n13 - CONDIÇÕES DE APRESENTAÇÃO\nPlataforma eletrónica utilizada pela entidade adjudicante: VORTAL\nURL para Apresentação: https://community.vortal.biz/public/\nAdmissibilidade da apresentação de propostas variantes: Não autorizado\nPrazo para apresentação das propostas: 14-11-2025 23:59\nPrazo durante o qual os concorrentes são obrigados a manter as respetivas propostas: 88 dias a contar do termo do prazo para a apresentação das propostas\nApresentação de Catálogo Eletrónico: Não autorizado\nIndicação de Subcontratação na Proposta: Inexistência de indicação de subcontratação\n\n14 - PRESTAÇÃO DE CAUÇÃO\nPrestação de caução: Sim\nPercentagem: 3.5%\nDescrição da Garantia Exigida: Conforme peças do procedimento\n\n15 - FORNECIMENTO DAS PEÇAS DO CONCURSO, APRESENTAÇÃO DE PEDIDOS DE PARTICIPAÇÃO E APRESENTAÇÃO DAS PROPOSTAS\nLink para acesso às peças do concurso (URL): https://community.vortal.biz/Public/public-tender-documents/TGxydG8rUlhsbWlGelV1R1gvUmlCZGZxUUJDOU9zWHFhTDNFUW01V05TbzRYcHd4OHJPZUpMbnNRQUc5MXg2Q1h2clorcmhjM0VEQnJtZGtEa1hrNHc9PTRJJkBy\n\n20 - OUTROS REQUISITOS\nInformação sobre contratos reservados. Aplica-se a contratos reservados (54º-A)? Não\n\n21 - CRITÉRIO DE ADJUDICAÇÃO\nMultifator: Não\nMonofator:\nNome: Outros\nOutro nome: Preço\n\n24 - CONDIÇÕES DO CONTRATO\nFaturação Eletrónica: Permitido\nObrigação de Subcontratação:\nCódigo da Obrigação de Subcontratação: Não é aplicável nenhuma obrigação de subcontratação.\n\n25 - COMPRA PÚBLICA ESTRATÉGICA\nCompra Pública Estratégica: Redução dos impactos ambientais\nDescrição do Processo de Adjudicação Estratégico: Conforme as peças do procedimento\nCritérios de contratos Públicos Ecológicos: Critérios de contratação pública ecológica nacional\nCategorias da estratégia nacional: Outros\nOutra categoria (Descrição): Desempenho energético\nDiretiva Veículos Não Poluentes: Não\nCritério de Acessibilidade: Os critérios de acessibilidade para as pessoas com deficiência não estão incluídos porque o contrato não se destina a pessoas singulares\n\n26 - INFORMAÇÕES ADICIONAIS\nContrato adequado para PME: Sim\nCobertura ACP (Acordo dos Contratos Públicos da Organização Mundial do Comércio): Não\n\n27 - IDENTIFICAÇÃO E CONTACTOS DO ÓRGÃO DE RECURSOS ADMINISTRATIVOS\nDesignação: Conselho Diretivo do ICNF, I. P.\nEndereço: Av. Dr.Alfredo Magalhães Ramalho 1\nCódigo postal: 1495-165\nLocalidade: Oeiras\nTelefone: +351 213507900\nFax: +351 000000000\nEndereço eletrónico: geral@icnf.pt\n\n28 - IDENTIFICAÇÃO DO(S) AUTOR(ES) DE ANÚNCIO\nNome: José Nascimento\nCargo: Perito\n419658218",
    "nipc": "510342647",
    "distrito": "Lisboa",
    "concelho": "Oeiras",
    "freguesia": "União das Freguesias de Algés, Linda-a-Velha e Cruz Quebrada-Dafundo",
    "site": "https://www.icnf.pt/",
    "email": "geral@icnf.pt",
    "designacao_contrato": "Aquisição de 55 veículos ligeiros de combate a incêndios para as equipas de sapadores florestais",
    "descricao": "Aquisição de 55 veículos ligeiros de combate a incêndios para as equipas de sapadores florestais",
    "preco_base": "4.400.000,00 EUR",
    "prazo_execucao": "150 DIAS",
    "prazo_apresentacao_propostas": "14-11-2025 23:59",
    "fundos_eu": "Sim",
    "plataforma_eletronica": "VORTAL",
    "url_procedimento": "https://community.vortal.biz/public/",
    "autor_nome": "José Nascimento",
    "autor_cargo": "Perito"
  },
  {
    "numero_procedimento": "N/A",
    "entidade": "Município de Silves",
    "link": "https://diariodarepublica.pt/dr/detalhe/contrato-publico/27397-940618795",
    "detalhes_completos": "1 - IDENTIFICAÇÃO E CONTACTOS DA ENTIDADE ADJUDICANTE\nDesignação da entidade adjudicante: Município de Silves\nNIPC: 506818837\nServiço/Órgão/Pessoa de contacto: Divisão de Obras Municipais e Trânsito\nEndereço: Rua da Sé, 6 - 1º\nCódigo postal: 8300-140\nLocalidade: Silves\nPaís: Portugal\nNUT III: PT150\nDistrito: Faro\nConcelho: Silves\nFreguesia: União das Freguesias de Algoz e Tunes\nTelefone: 282440800\nFax: 282440850\nEndereço da Entidade (URL): https://www.acingov.pt\nEndereço Eletrónico: obras.municipais@cm-silves.pt\neDelivery Gateway (URL): https://www.acingov.pt\nFunção da Organização: Adquirente\nNorma jurídica da Entidade Adjudicante: Organismo de direito público\nÁrea de atividade da Autoridade Adjudicante: Serviços públicos das administrações públicas\n\n2 - JORNAL OFICIAL DA UNIÃO EUROPEIA\nO procedimento a que este anúncio diz respeito também é publicitado no Jornal Oficial da União Europeia? Não\n\n3 - AVISO\nModelo de Anúncio: Concurso público\nData de Envio do Anúncio: 17-10-2025\n\n5 - PROCESSO\nTipo de Procedimento: Concurso público\nPreço base do procedimento: Sim\nValor do preço base do procedimento: 75.000,00 EUR\nProcedimento com lotes? Não\n\n6 - OBJETO DO CONTRATO\nNúmero de referência interna: 1351/DOMT\nDesignação do contrato: Reparação do Pavimento na VAL 2028, Urbanização dos Vales do Algoz\nDescrição: Reparação do Pavimento na VAL 2028, Urbanização dos Vales do Algoz.\nTipo de Contrato Principal: Empreitada de Obras Públicas\nTipo de Contrato: Empreitada de Obras Públicas\nClassificação CPV (Vocabulário Comum para os Contratos Públicos)\nObjeto principal\nVocabulário Principal: 45233142\nPreço base s/IVA: 75.000,00 EUR\n\n7 - INDICAÇÕES ADICIONAIS\nO contrato envolve aquisição conjunta (satisfação de várias entidades)? Não\nO contrato é adjudicado por uma central de compras? Não\n\n8 - TÉCNICAS\nO concurso destina-se à celebração de um acordo-quadro? Inexistência de acordo-quadro\nÉ utilizado um leilão eletrónico? Não\nÉ adotada uma fase de negociação? Não\nSistema de Aquisição Dinâmico: Inexistência de sistema de aquisição dinâmico\n\n9 - LOCAL DA EXECUÇÃO DO CONTRATO\nLOCAL DA EXECUÇÃO DO CONTRATO (PROCEDIMENTO)\nPaís: Portugal\nNUT III: PT150\nLocalidade: União das Freguesias de Algoz e Tunes\nDistrito: Faro\nConcelho: Silves\nFreguesia: União das Freguesias de Algoz e Tunes\n\n10 - PRAZO DE EXECUÇÃO DO CONTRATO\nPrazo de execução do contrato: 60 DIAS\nPrevisão de renovações: Não\n\n11 - FUNDOS EU\nTêm fundos EU? Não\n\n12 - DOCUMENTOS DE HABILITAÇÃO\nHabilitação para o exercício da atividade profissional: Sim\nTipo: Alvará\nDescrição: A 1º subcategoria da 2ª categoria, em classe que cubra o valor global da proposta.\n\n13 - CONDIÇÕES DE APRESENTAÇÃO\nPlataforma eletrónica utilizada pela entidade adjudicante: ACIN\nURL para Apresentação: https://www.acingov.pt\nAdmissibilidade da apresentação de propostas variantes: Não autorizado\nPrazo para apresentação das propostas: 16-11-2025 23:59\nPrazo durante o qual os concorrentes são obrigados a manter as respetivas propostas: 120 dias a contar do termo do prazo para a apresentação das propostas\nIndicação de Subcontratação na Proposta: Inexistência de indicação de subcontratação\n\n14 - PRESTAÇÃO DE CAUÇÃO\nPrestação de caução: Sim\nPercentagem: 5%\nDescrição da Garantia Exigida: O valor da caução é de 5.00% do preço contratual.\n\n15 - FORNECIMENTO DAS PEÇAS DO CONCURSO, APRESENTAÇÃO DE PEDIDOS DE PARTICIPAÇÃO E APRESENTAÇÃO DAS PROPOSTAS\nLink para acesso às peças do concurso (URL): https://www.acingov.pt/acingovprod/2/zonaPublica/zona_publica_c/donwloadProcedurePiece/OTg2NDY0\n\n20 - OUTROS REQUISITOS\nInformação sobre contratos reservados. Aplica-se a contratos reservados (54º-A)? Não\n\n21 - CRITÉRIO DE ADJUDICAÇÃO\nMultifator: Não\nMonofator:\nNome: Preço\n\n24 - CONDIÇÕES DO CONTRATO\nFaturação Eletrónica: Permitido\nObrigação de Subcontratação:\nCódigo da Obrigação de Subcontratação: Não é aplicável nenhuma obrigação de subcontratação.\n\n25 - COMPRA PÚBLICA ESTRATÉGICA\nCompra Pública Estratégica: Inexistência de contratação pública estratégica\n\n26 - INFORMAÇÕES ADICIONAIS\nContrato adequado para PME: Sim\nCobertura ACP (Acordo dos Contratos Públicos da Organização Mundial do Comércio): Não\n\n27 - IDENTIFICAÇÃO E CONTACTOS DO ÓRGÃO DE RECURSOS ADMINISTRATIVOS\nDesignação: Município de Silves\nEndereço: Rua Pintor Bernardo Marques\nCódigo postal: 8300-175\nLocalidade: Silves\nTelefone: 351282440800\nFax: 351282440850\nEndereço eletrónico: gabinete.presidente@cm-silves.pt\nPrazo de interposição do recurso: 5 dias\n\n28 - IDENTIFICAÇÃO DO(S) AUTOR(ES) DE ANÚNCIO\nNome: Rosa Cristina Gonçalves da Palma\nCargo: Presidente da Câmara\n419660745",
    "nipc": "506818837",
    "distrito": "Faro",
    "concelho": "Silves",
    "freguesia": "União das Freguesias de Algoz e Tunes",
    "site": "https://www.acingov.pt",
    "email": "obras.municipais@cm-silves.pt",
    "designacao_contrato": "Reparação do Pavimento na VAL 2028, Urbanização dos Vales do Algoz",
    "descricao": "Reparação do Pavimento na VAL 2028, Urbanização dos Vales do Algoz.",
    "preco_base": "75.000,00 EUR",
    "prazo_execucao": "60 DIAS",
    "prazo_apresentacao_propostas": "16-11-2025 23:59",
    "fundos_eu": "Não",
    "plataforma_eletronica": "ACIN",
    "url_procedimento": "https://www.acingov.pt",
    "autor_nome": "Rosa Cristina Gonçalves da Palma",
    "autor_cargo": "Presidente da Câmara"
  },
  {
    "numero_procedimento": "N/A",
    "entidade": "Município de Odemira",
    "link": "https://diariodarepublica.pt/dr/detalhe/contrato-publico/27402-940618796",
    "detalhes_completos": "1 - IDENTIFICAÇÃO E CONTACTOS DA ENTIDADE ADJUDICANTE\nDesignação da entidade adjudicante: Município de Odemira\nNIPC: 505311313\nServiço/Órgão/Pessoa de contacto: Divisão de Obras Municipais \nEndereço: Praça da República\nCódigo postal: 7630-139\nLocalidade: Beja\nPaís: Portugal\nNUT III: PT181\nDistrito: Beja\nConcelho: Odemira\nFreguesia: Freguesia de São Salvador e Santa Maria\nTelefone: 283320900\nFax: 283327323\nEndereço da Entidade (URL): www.cm-odemira.pt\nEndereço Eletrónico: geral@cm-odemira.pt\neDelivery Gateway (URL): https://community.vortal.biz/public/\nFunção da Organização: Adquirente\nNorma jurídica da Entidade Adjudicante: Autoridade regional\nÁrea de atividade da Autoridade Adjudicante: Serviços públicos das administrações públicas\n\n2 - JORNAL OFICIAL DA UNIÃO EUROPEIA\nO procedimento a que este anúncio diz respeito também é publicitado no Jornal Oficial da União Europeia? Não\n\n3 - AVISO\nModelo de Anúncio: Concurso público\nData de Envio do Anúncio: 17-10-2025\n\n5 - PROCESSO\nTipo de Procedimento: Concurso público\nPreço base do procedimento: Sim\nValor do preço base do procedimento: 81.531,23 EUR\nProcedimento com lotes? Não\n\n6 - OBJETO DO CONTRATO\nNúmero de referência interna: CMO/1750/CPN/E/25\nDesignação do contrato: EMPREITADA DE ARRANJO DOS ESPAÇOS EXTERIORES DO CLUBE NÁUTICO MILFONTES\nDescrição: EMPREITADA DE ARRANJO DOS ESPAÇOS EXTERIORES DO CLUBE NÁUTICO MILFONTES\nTipo de Contrato Principal: Empreitada de Obras Públicas\nTipo de Contrato: Empreitada de Obras Públicas\nClassificação CPV (Vocabulário Comum para os Contratos Públicos)\nObjeto principal\nVocabulário Principal: 45112712\nPreço base s/IVA: 81.531,23 EUR\n\n7 - INDICAÇÕES ADICIONAIS\nO contrato envolve aquisição conjunta (satisfação de várias entidades)? Não\nO contrato é adjudicado por uma central de compras? Não\n\n8 - TÉCNICAS\nO concurso destina-se à celebração de um acordo-quadro? Inexistência de acordo-quadro\nÉ utilizado um leilão eletrónico? Não\nÉ adotada uma fase de negociação? Não\nSistema de Aquisição Dinâmico: Inexistência de sistema de aquisição dinâmico\n\n9 - LOCAL DA EXECUÇÃO DO CONTRATO\nLOCAL DA EXECUÇÃO DO CONTRATO (PROCEDIMENTO)\nPaís: Portugal\nNUT III: PT181\nLocalidade: Vila Nova de Milfontes\nDistrito: Beja\nConcelho: Odemira\nFreguesia: Freguesia de Vila Nova de Milfontes\n\n10 - PRAZO DE EXECUÇÃO DO CONTRATO\nPrazo de execução do contrato: 120 DIAS\nPrevisão de renovações: Não\n\n11 - FUNDOS EU\nTêm fundos EU? Não\n\n12 - DOCUMENTOS DE HABILITAÇÃO\nHabilitação para o exercício da atividade profissional: Sim\nTipo: Alvará\nDescrição: a) Nos procedimentos de formação de qualquer contrato o adjudicatário deve apresentar os seguintes \ndocumentos de habilitação: \n- Declaração emitida conforme anexo II que faz parte integrante do programa de procedimento. \n- Documentos comprovativos de que não se encontra nas situações previstas nas alíneas b), d), e) e i) do artigo 55.º do CCP. \nb) Alvará ou os títulos de registo emitidos pelo Instituto dos Mercados Públicos, do Imobiliário e da Construção, I. P., contendo as habilitações adequadas e necessárias à execução da obra a realizar: \n2ª Categoria - Vias de comunicação, obras de urbanização e outras infraestruturas, 6.ª - Saneamento básico, 8.ª - Calcetamentos, 9.ª - Ajardinamentos, em classe que cubra o valor global da proposta \n13 - CONDIÇÕES DE APRESENTAÇÃO\nPlataforma eletrónica utilizada pela entidade adjudicante: VORTAL\nURL para Apresentação: https://community.vortal.biz/public/\nAdmissibilidade da apresentação de propostas variantes: Não autorizado\nPrazo para apresentação das propostas: 07-11-2025 23:59\nPrazo durante o qual os concorrentes são obrigados a manter as respetivas propostas: 90 dias a contar do termo do prazo para a apresentação das propostas\nIndicação de Subcontratação na Proposta: Inexistência de indicação de subcontratação\n\n14 - PRESTAÇÃO DE CAUÇÃO\nPrestação de caução: Sim\nPercentagem: 5%\nDescrição da Garantia Exigida: Por depósito em dinheiro ou em títulos emitidos ou garantidos pelo Estado, ou  mediante garantia bancária ou seguro-caução.\n\n15 - FORNECIMENTO DAS PEÇAS DO CONCURSO, APRESENTAÇÃO DE PEDIDOS DE PARTICIPAÇÃO E APRESENTAÇÃO DAS PROPOSTAS\nLink para acesso às peças do concurso (URL): https://community.vortal.biz/Public/public-tender-documents/ZkZjdnAxSlJoTFhUVlBwY1JRdjNTNlJLSitFcE95aUtNeCtCV21sNzJOS2hPbG9MRXhDV2NRRU5XSTd1dkRlQVF3b3pmWG5TakFXSnhWK3h4VU84dVE9PVJxdjRv\n\n20 - OUTROS REQUISITOS\nInformação sobre contratos reservados. Aplica-se a contratos reservados (54º-A)? Não\n\n21 - CRITÉRIO DE ADJUDICAÇÃO\nMultifator: Não\nMonofator:\nNome: Outros\nOutro nome: Preço\n\n24 - CONDIÇÕES DO CONTRATO\nFaturação Eletrónica: Permitido\nObrigação de Subcontratação:\nCódigo da Obrigação de Subcontratação: Não é aplicável nenhuma obrigação de subcontratação.\n\n25 - COMPRA PÚBLICA ESTRATÉGICA\nCompra Pública Estratégica: Inexistência de contratação pública estratégica\n\n26 - INFORMAÇÕES ADICIONAIS\nContrato adequado para PME: Sim\nCobertura ACP (Acordo dos Contratos Públicos da Organização Mundial do Comércio): Não\n\n27 - IDENTIFICAÇÃO E CONTACTOS DO ÓRGÃO DE RECURSOS ADMINISTRATIVOS\nDesignação: Tribunal Administrativo e Fiscal de Beja\nEndereço: Rua de Angola\nCódigo postal: 7800-429\nLocalidade: Beja\nTelefone: +351 284311550\nFax: +351 213506009\nEndereço eletrónico: correio@beja.taf.mj.pt\nPrazo de interposição do recurso: 5 dias\n\n28 - IDENTIFICAÇÃO DO(S) AUTOR(ES) DE ANÚNCIO\nNome: Hélder António Guerreiro\nCargo: Presidente da Câmara Municipal de Odemira\n419651568",
    "nipc": "505311313",
    "distrito": "Beja",
    "concelho": "Odemira",
    "freguesia": "Freguesia de São Salvador e Santa Maria",
    "site": "www.cm-odemira.pt",
    "email": "geral@cm-odemira.pt",
    "designacao_contrato": "EMPREITADA DE ARRANJO DOS ESPAÇOS EXTERIORES DO CLUBE NÁUTICO MILFONTES",
    "descricao": "EMPREITADA DE ARRANJO DOS ESPAÇOS EXTERIORES DO CLUBE NÁUTICO MILFONTES",
    "preco_base": "81.531,23 EUR",
    "prazo_execucao": "120 DIAS",
    "prazo_apresentacao_propostas": "07-11-2025 23:59",
    "fundos_eu": "Não",
    "plataforma_eletronica": "VORTAL",
    "url_procedimento": "https://community.vortal.biz/public/",
    "autor_nome": "Hélder António Guerreiro",
    "autor_cargo": "Presidente da Câmara Municipal de Odemira"
  },
  {
    "numero_procedimento": "N/A",
    "entidade": "AnÃºncio de procedimento  n.Âº 27404/2025  -  DiÃ¡rio da RepÃºblica n.Âº 201/2025, SÃ©rie II de 2025-10-17",
    "link": "https://diariodarepublica.pt/dr/detalhe/contrato-publico/27404-940618797"
  },
  {
    "numero_procedimento": "N/A",
    "entidade": "AnÃºncio de procedimento  n.Âº 27405/2025  -  DiÃ¡rio da RepÃºblica n.Âº 201/2025, SÃ©rie II de 2025-10-17",
    "link": "https://diariodarepublica.pt/dr/detalhe/contrato-publico/27405-940618798"
  },
  {
    "numero_procedimento": "N/A",
    "entidade": "AnÃºncio de procedimento  n.Âº 27406/2025  -  DiÃ¡rio da RepÃºblica n.Âº 201/2025, SÃ©rie II de 2025-10-17",
    "link": "https://diariodarepublica.pt/dr/detalhe/contrato-publico/27406-940618805"
  },
  {
    "numero_procedimento": "N/A",
    "entidade": "AnÃºncio de procedimento  n.Âº 27408/2025  -  DiÃ¡rio da RepÃºblica n.Âº 201/2025, SÃ©rie II de 2025-10-17",
    "link": "https://diariodarepublica.pt/dr/detalhe/contrato-publico/27408-940618806"
  },
  {
    "numero_procedimento": "N/A",
    "entidade": "AnÃºncio de procedimento  n.Âº 27409/2025  -  DiÃ¡rio da RepÃºblica n.Âº 201/2025, SÃ©rie II de 2025-10-17",
    "link": "https://diariodarepublica.pt/dr/detalhe/contrato-publico/27409-940618807"
  },
  {
    "numero_procedimento": "N/A",
    "entidade": "Serviços Municipalizados de Água e Saneamento de Almada",
    "link": "https://diariodarepublica.pt/dr/detalhe/contrato-publico/27411-940618808",
    "detalhes_completos": "1 - IDENTIFICAÇÃO E CONTACTOS DA ENTIDADE ADJUDICANTE\nDesignação da entidade adjudicante: Serviços Municipalizados de Água e Saneamento de Almada\nNIPC: 680017763\nEndereço: Praceta Ricardo Jorge, n.º2 Pragal\nCódigo postal: 2804-543\nLocalidade: Setúbal\nPaís: Portugal\nNUT III: PT170\nDistrito: Setúbal\nConcelho: Almada\nFreguesia: Todas\nTelefone: 212726000\nFax: 212721629\nEndereço da Entidade (URL): www.smasalmada.pt\nEndereço Eletrónico: geral@smasalmada.pt\neDelivery Gateway (URL): https://community.vortal.biz/public/\nFunção da Organização: Adquirente\nNorma jurídica da Entidade Adjudicante: Organismo de direito público, controlado por uma autoridade local\nÁrea de atividade da Autoridade Adjudicante: Serviços públicos das administrações públicas\n\n2 - JORNAL OFICIAL DA UNIÃO EUROPEIA\nO procedimento a que este anúncio diz respeito também é publicitado no Jornal Oficial da União Europeia? Sim\n\n3 - AVISO\nModelo de Anúncio: Concurso público\nData de Envio do Anúncio: 15-10-2025\n\n5 - PROCESSO\nTipo de Procedimento: Concurso público\nPreço base do procedimento: Sim\nValor do preço base do procedimento: 745.000,00 EUR\nProcedimento com lotes? Sim\nNº Máx. de Lotes Autorizado: 2\nNúmero máximo de lotes que podem ser adjudicados a um concorrente: 2\n\n6 - OBJETO DO CONTRATO\nNúmero de referência interna: CPI 114/2025\nDesignação do contrato: Aquisição de Serviços de Seguros para os SMAS de Almada\nDescrição: Aquisição de Serviços de Seguros para os SMAS de Almada\nOpções: Não\nTipo de Contrato Principal: Aquisição de Serviços\nTipo de Contrato: Aquisição de Serviços\nClassificação CPV (Vocabulário Comum para os Contratos Públicos)\nObjeto principal\nVocabulário Principal: 66510000\nPreço base s/IVA: 745.000,00 EUR\nLotes: \nNº: LOT-0001\nDescrição do Lote: Lote 1 - Seguro de Acidentes em Trabalho; Seguro de Frota Automóvel; Seguro Multirriscos, em conformidade com Especificações Técnicas do Caderno Encargos (Anexos A e B) e Anexo I do Programa\nPreço base s/IVA: 476.513,59 EUR\nClassificação CPV (Vocabulário Comum para os Contratos Públicos)\nObjeto principal\nVocabulário Principal: 66510000\nNº: LOT-0002\nDescrição do Lote: Lote 2 - Seguro de Responsabilidade Civil Exploração; Responsabilidade Civil Ambiental, em conformidade com Especificações Técnicas do Caderno Encargos e Anexo I do Programa\nPreço base s/IVA: 268.486,41 EUR\nClassificação CPV (Vocabulário Comum para os Contratos Públicos)\nObjeto principal\nVocabulário Principal: 66510000\n\n7 - INDICAÇÕES ADICIONAIS\nO contrato envolve aquisição conjunta (satisfação de várias entidades)? Não\nO contrato é adjudicado por uma central de compras? Não\n\n8 - TÉCNICAS\nO concurso destina-se à celebração de um acordo-quadro? Inexistência de acordo-quadro\nÉ utilizado um leilão eletrónico? Não\nÉ adotada uma fase de negociação? Não\nSistema de Aquisição Dinâmico: Inexistência de sistema de aquisição dinâmico\n\n9 - LOCAL DA EXECUÇÃO DO CONTRATO\nLOCAL DA EXECUÇÃO DO CONTRATO (PROCEDIMENTO)\nPaís: Portugal\nNUT III: PT170\nLocalidade: Almada\nDistrito: Setúbal\nConcelho: Almada\nFreguesia: União das Freguesias de Almada, Cova da Piedade, Pragal e Cacilhas\nLOCAL DA EXECUÇÃO DO CONTRATO (LOTE)\nIdentificador do Lote: LOT-0001; LOT-0002\nPaís: Portugal\nNUT III: PT170\nLocalidade: Almada\nDistrito: Setúbal\nConcelho: Almada\nFreguesia: União das Freguesias de Almada, Cova da Piedade, Pragal e Cacilhas\n\n10 - PRAZO DE EXECUÇÃO DO CONTRATO\nIdentificador do Lote: LOT-0001; LOT-0002\nPrazo de execução do contrato: 18 MESES\nPrevisão de renovações: Não\n\n11 - FUNDOS EU\nIdentificador do Lote: LOT-0001; LOT-0002\nTêm fundos EU? Não\n\n12 - DOCUMENTOS DE HABILITAÇÃO\nHabilitação para o exercício da atividade profissional: Não\n\n13 - CONDIÇÕES DE APRESENTAÇÃO\nPlataforma eletrónica utilizada pela entidade adjudicante: VORTAL\nURL para Apresentação: https://community.vortal.biz/public/\nAdmissibilidade da apresentação de propostas variantes: Não autorizado\nPrazo para apresentação das propostas: 16-11-2025 23:59\nPrazo durante o qual os concorrentes são obrigados a manter as respetivas propostas: 180 dias a contar do termo do prazo para a apresentação das propostas\nApresentação de Catálogo Eletrónico: Não autorizado\nIndicação de Subcontratação na Proposta: Inexistência de indicação de subcontratação\n\n14 - PRESTAÇÃO DE CAUÇÃO\nPrestação de caução: Sim\nPercentagem: 5%\nDescrição da Garantia Exigida: De acordo com Cláusula 24º do Programa de Procedimento\n\n15 - FORNECIMENTO DAS PEÇAS DO CONCURSO, APRESENTAÇÃO DE PEDIDOS DE PARTICIPAÇÃO E APRESENTAÇÃO DAS PROPOSTAS\nLink para acesso às peças do concurso (URL): https://community.vortal.biz/Public/public-tender-documents/S1BQcGI4Yytaa3NvWFRackZad2NGTXRJYkpMVUk3bHFuSXRkQm9mYXAzREp5STE5bXcvK1diTTVLWjhESGFHZllyK2JyTy81UlZOR1FrZVFidGZQUWc9PW14RSUy\n\n20 - OUTROS REQUISITOS\nIdentificador do Lote: LOT-0001; LOT-0002\nInformação sobre contratos reservados. Aplica-se a contratos reservados (54º-A)? Não\n\n21 - CRITÉRIO DE ADJUDICAÇÃO\nO Critério de adjudicação é diferenciado por lote? Não\nMultifator: Não\nMonofator:\nNome: Preço\n\n24 - CONDIÇÕES DO CONTRATO\nIdentificador do Lote: LOT-0001; LOT-0002\nFaturação Eletrónica: Permitido\nObrigação de Subcontratação:\nCódigo da Obrigação de Subcontratação: Não é aplicável nenhuma obrigação de subcontratação.\n\n25 - COMPRA PÚBLICA ESTRATÉGICA\nCompra Pública Estratégica: Inexistência de contratação pública estratégica\n\n26 - INFORMAÇÕES ADICIONAIS\nIdentificador do Lote: LOT-0001; LOT-0002\nContrato adequado para PME: Sim\nCobertura ACP (Acordo dos Contratos Públicos da Organização Mundial do Comércio): Não\n\n27 - IDENTIFICAÇÃO E CONTACTOS DO ÓRGÃO DE RECURSOS ADMINISTRATIVOS\nDesignação: Município de Almada - Câmara Municipal de Almada\nEndereço: Largo Luís de Camões\nCódigo postal: 2800-158\nLocalidade: Almada\nTelefone: +351 212724534\nFax: +351 212724555\nEndereço eletrónico: gab.presidencia@cma.m-almada.pt\n\n28 - IDENTIFICAÇÃO DO(S) AUTOR(ES) DE ANÚNCIO\nNome: José Pedro Ribeiro\nCargo: Presidente do Conselho de Administração\n419645063",
    "nipc": "680017763",
    "distrito": "Setúbal",
    "concelho": "Almada",
    "freguesia": "Todas",
    "site": "www.smasalmada.pt",
    "email": "geral@smasalmada.pt",
    "designacao_contrato": "Aquisição de Serviços de Seguros para os SMAS de Almada",
    "descricao": "Aquisição de Serviços de Seguros para os SMAS de Almada",
    "preco_base": "745.000,00 EUR",
    "prazo_execucao": "18 MESES",
    "prazo_apresentacao_propostas": "16-11-2025 23:59",
    "fundos_eu": "Não",
    "plataforma_eletronica": "VORTAL",
    "url_procedimento": "https://community.vortal.biz/public/",
    "autor_nome": "José Pedro Ribeiro",
    "autor_cargo": "Presidente do Conselho de Administração"
  },
  {
    "numero_procedimento": "N/A",
    "entidade": "Instituto Superior de Engenharia de Lisboa",
    "link": "https://diariodarepublica.pt/dr/detalhe/contrato-publico/27412-940618809",
    "detalhes_completos": "Alteração do Anúncio de procedimento n.º 26495/2025, de 2025-10-09, com o ID 419629577\n\n1 - IDENTIFICAÇÃO E CONTACTOS DA ENTIDADE ADJUDICANTE\nDesignação da entidade adjudicante: Instituto Superior de Engenharia de Lisboa\nNIPC: 600016234\nServiço/Órgão/Pessoa de contacto: Núcleo de Aprovisionamento e Património do ISEL\nEndereço: Rua Conselheiro Emídio Navarro n.º 1\nCódigo postal: 1959-007\nLocalidade: Lisboa\nPaís: Portugal\nNUT III: PT170\nDistrito: Lisboa\nConcelho: Lisboa\nFreguesia: Freguesia de Marvila - Lisboa\nTelefone: 218317240\nFax: 218317240\nEndereço da Entidade (URL): www.isel.pt\nEndereço Eletrónico: procedimentos.nap@isel.pt\nFunção da Organização: Adquirente\nNorma jurídica da Entidade Adjudicante: Autoridade da administração central\nÁrea de atividade da Autoridade Adjudicante: Educação\n\n2 - JORNAL OFICIAL DA UNIÃO EUROPEIA\nO procedimento a que este anúncio diz respeito também é publicitado no Jornal Oficial da União Europeia? Não\n\n3 - AVISO\nModelo de Anúncio: Concurso público\nData de Envio do Anúncio: 17-10-2025\n\n5 - PROCESSO\nTipo de Procedimento: Concurso público\nPreço base do procedimento: Sim\nValor do preço base do procedimento: 97.000,00 EUR\nProcedimento com lotes? Não\n\n6 - OBJETO DO CONTRATO\nNúmero de referência interna: 53/ISEL/2025\nDesignação do contrato: Concurso Público para Reabilitação do Laboratório de Desenvolvimento de Novos Processos\nDescrição: Empreitada para Reabilitação do Laboratório de Desenvolvimento de Novos Processos\nTipo de Contrato Principal: Empreitada de Obras Públicas\nTipo de Contrato: Empreitada de Obras Públicas\nClassificação CPV (Vocabulário Comum para os Contratos Públicos)\nObjeto principal\nVocabulário Principal: 45453000\nPreço base s/IVA: 97.000,00 EUR\n\n7 - INDICAÇÕES ADICIONAIS\nO contrato envolve aquisição conjunta (satisfação de várias entidades)? Não\nO contrato é adjudicado por uma central de compras? Não\n\n8 - TÉCNICAS\nO concurso destina-se à celebração de um acordo-quadro? Inexistência de acordo-quadro\nÉ utilizado um leilão eletrónico? Não\nÉ adotada uma fase de negociação? Não\nSistema de Aquisição Dinâmico: Inexistência de sistema de aquisição dinâmico\n\n9 - LOCAL DA EXECUÇÃO DO CONTRATO\nLOCAL DA EXECUÇÃO DO CONTRATO (PROCEDIMENTO)\nPaís: Portugal\nNUT III: PT170\nLocalidade: Lisboa\nDistrito: Lisboa\nConcelho: Lisboa\nFreguesia: Freguesia de Marvila - Lisboa\n\n10 - PRAZO DE EXECUÇÃO DO CONTRATO\nPrazo de execução do contrato: 120 DIAS\nPrevisão de renovações: Não\n\n11 - FUNDOS EU\nTêm fundos EU? Sim\n\n12 - DOCUMENTOS DE HABILITAÇÃO\nHabilitação para o exercício da atividade profissional: Não\n\n13 - CONDIÇÕES DE APRESENTAÇÃO\nPlataforma eletrónica utilizada pela entidade adjudicante: COMPRASPT\nURL para Apresentação: https://www.compraspt.com/cpt-isel/faces/\nAdmissibilidade da apresentação de propostas variantes: Não autorizado\nPrazo para apresentação das propostas: 03-11-2025 23:59\nPrazo durante o qual os concorrentes são obrigados a manter as respetivas propostas: 66 dias a contar do termo do prazo para a apresentação das propostas\nApresentação de Catálogo Eletrónico: Permitido\nIndicação de Subcontratação na Proposta: O(s) subcontratante(s) proposto(s) necessário(s) para cumprir a obrigação de subcontratar uma percentagem mínima do contrato\n\n14 - PRESTAÇÃO DE CAUÇÃO\nPrestação de caução: Sim\nPercentagem: 5%\nDescrição da Garantia Exigida: de acordo com o previsto no artigo 21 do programa\n\n15 - FORNECIMENTO DAS PEÇAS DO CONCURSO, APRESENTAÇÃO DE PEDIDOS DE PARTICIPAÇÃO E APRESENTAÇÃO DAS PROPOSTAS\nLink para acesso às peças do concurso (URL): https://www.compraspt.com/cpt-isel/faces/app/acessoDocs.jsp?codigoAcesso=wnUav4Wrq8KZjioX4ijP0YpCG5mu32D6yvXCLIWZW4MFehQKBZ\n\n20 - OUTROS REQUISITOS\nInformação sobre contratos reservados. Aplica-se a contratos reservados (54º-A)? Não\n\n21 - CRITÉRIO DE ADJUDICAÇÃO\nMultifator: Sim\nFator: \nNome: Preço\nPonderação: 75%\nSubfatores: Não\nFator: \nNome: Outros\nOutro Nome: Prazo de execução\nPonderação: 25%\nSubfatores: Não\n\n24 - CONDIÇÕES DO CONTRATO\nFaturação Eletrónica: Permitido\nObrigação de Subcontratação:\nCódigo da Obrigação de Subcontratação: Não é aplicável nenhuma obrigação de subcontratação.\n\n25 - COMPRA PÚBLICA ESTRATÉGICA\nCompra Pública Estratégica: Inexistência de contratação pública estratégica\n\n26 - INFORMAÇÕES ADICIONAIS\nContrato adequado para PME: Sim\nCobertura ACP (Acordo dos Contratos Públicos da Organização Mundial do Comércio): Não\n\n27 - IDENTIFICAÇÃO E CONTACTOS DO ÓRGÃO DE RECURSOS ADMINISTRATIVOS\nDesignação: Presidente do ISEL\nEndereço: presidente@isel.pt\nCódigo postal: 1959-007\nLocalidade: Lisboa\nEndereço eletrónico: procedimentos.nap@isel.pt\nPrazo de interposição do recurso: 5 dias\n\n28 - IDENTIFICAÇÃO DO(S) AUTOR(ES) DE ANÚNCIO\nNome: José M. P. do Nascimento\nCargo: Presidente do ISEL\n\n29 - ALTERAÇÃO\nMotivo da Alteração: Correção pelo adquirente\nIdentificador da Versão do Anúncio a Alterar: 96516eca-1be6-4486-a1fa-ccca655cd1d2-01\nIdentificador das Secções Alteradas do Anúncio Anterior: Condições de Apresentação\nDescrição das Alterações: Prorrogação do prazo para apresentação de propostas, \nAlteração dos Documentos do Concurso: Sim\nData de alteração dos documentos do concurso: 15-10-2025\n419665046",
    "nipc": "600016234",
    "distrito": "Lisboa",
    "concelho": "Lisboa",
    "freguesia": "Freguesia de Marvila - Lisboa",
    "site": "www.isel.pt",
    "email": "procedimentos.nap@isel.pt",
    "designacao_contrato": "Concurso Público para Reabilitação do Laboratório de Desenvolvimento de Novos Processos",
    "descricao": "Empreitada para Reabilitação do Laboratório de Desenvolvimento de Novos Processos",
    "preco_base": "97.000,00 EUR",
    "prazo_execucao": "120 DIAS",
    "prazo_apresentacao_propostas": "03-11-2025 23:59",
    "fundos_eu": "Sim",
    "plataforma_eletronica": "COMPRASPT",
    "url_procedimento": "https://www.compraspt.com/cpt-isel/faces/",
    "autor_nome": "José M. P. do Nascimento",
    "autor_cargo": "Presidente do ISEL"
  },
  {
    "numero_procedimento": "N/A",
    "entidade": "Agência Portuguesa do Ambiente, I. P.",
    "link": "https://diariodarepublica.pt/dr/detalhe/contrato-publico/27414-940618820",
    "detalhes_completos": "1 - IDENTIFICAÇÃO E CONTACTOS DA ENTIDADE ADJUDICANTE\nDesignação da entidade adjudicante: Agência Portuguesa do Ambiente, I. P.\nNIPC: 510306624\nServiço/Órgão/Pessoa de contacto: ARH do Algarve\nEndereço: Rua da Murgueira, 9/9A- Zambujal -Ap. 7585\nCódigo postal: 2610-124\nLocalidade: Amadora\nPaís: Portugal\nNUT III: PT170\nDistrito: Lisboa\nConcelho: Amadora\nFreguesia: Freguesia de Alfragide\nTelefone: 214728200\nFax: 214719074\nEndereço da Entidade (URL): www.apambiente.pt\nEndereço Eletrónico: geral@apambiente.pt\neDelivery Gateway (URL): https://www.acingov.pt\nFunção da Organização: Adquirente\nNorma jurídica da Entidade Adjudicante: Organismo de direito público\nÁrea de atividade da Autoridade Adjudicante: Proteção ambiental\n\n2 - JORNAL OFICIAL DA UNIÃO EUROPEIA\nO procedimento a que este anúncio diz respeito também é publicitado no Jornal Oficial da União Europeia? Sim\n\n3 - AVISO\nModelo de Anúncio: Concurso público\nData de Envio do Anúncio: 15-10-2025\n\n5 - PROCESSO\nTipo de Procedimento: Concurso público\nPreço base do procedimento: Sim\nValor do preço base do procedimento: 160.000,00 EUR\nProcedimento com lotes? Não\n\n6 - OBJETO DO CONTRATO\nNúmero de referência interna: CPI/18/2025\nDesignação do contrato: Aquisição de equipamento de telemetria e instalação em estações hidrométricas e em sensores de medição do nível e condutividade de água subterrânea.\nDescrição: Aquisição de equipamento de telemetria e instalação em estações hidrométricas e em sensores de medição do nível e condutividade de água subterrânea, no âmbito do PRR.\nOpções: Não\nTipo de Contrato Principal: Aquisição de Bens Móveis\nTipo de Contrato: Aquisição de Bens Móveis\nClassificação CPV (Vocabulário Comum para os Contratos Públicos)\nObjeto principal\nVocabulário Principal: 38424000\nPreço base s/IVA: 160.000,00 EUR\n\n7 - INDICAÇÕES ADICIONAIS\nO contrato envolve aquisição conjunta (satisfação de várias entidades)? Não\nO contrato é adjudicado por uma central de compras? Não\n\n8 - TÉCNICAS\nO concurso destina-se à celebração de um acordo-quadro? Inexistência de acordo-quadro\nÉ utilizado um leilão eletrónico? Não\nÉ adotada uma fase de negociação? Não\nSistema de Aquisição Dinâmico: Inexistência de sistema de aquisição dinâmico\n\n9 - LOCAL DA EXECUÇÃO DO CONTRATO\nLOCAL DA EXECUÇÃO DO CONTRATO (PROCEDIMENTO)\nPaís: Portugal\nNUT III: PT150\nLocalidade: União das Freguesias de Estômbar e Parchal\nDistrito: Faro\nConcelho: Lagoa\nFreguesia: União das Freguesias de Estômbar e Parchal\nPaís: Portugal\nNUT III: PT150\nLocalidade: Freguesia de Vila Real de Santo António\nDistrito: Faro\nConcelho: Vila Real Sto Antonio\nFreguesia: Freguesia de Vila Real de Santo António\nPaís: Portugal\nNUT III: PT150\nLocalidade: Freguesia de Almancil\nDistrito: Faro\nConcelho: Loulé\nFreguesia: Freguesia de Almancil\nPaís: Portugal\nNUT III: PT150\nLocalidade: União das Freguesias de Faro (Sé e São Pedro)\nDistrito: Faro\nConcelho: Faro\nFreguesia: União das Freguesias de Faro (Sé e São Pedro)\nPaís: Portugal\nNUT III: PT150\nLocalidade: Freguesia de Pechão\nDistrito: Faro\nConcelho: Olhão\nFreguesia: Freguesia de Pechão\nPaís: Portugal\nNUT III: PT150\nLocalidade: Freguesia de Portimão\nDistrito: Faro\nConcelho: Portimão\nFreguesia: Freguesia de Portimão\nPaís: Portugal\nNUT III: PT150\nLocalidade: Freguesia de Mexilhoeira Grande\nDistrito: Faro\nConcelho: Portimão\nFreguesia: Freguesia de Mexilhoeira Grande\nPaís: Portugal\nNUT III: PT150\nLocalidade: Freguesia de São Bartolomeu de Messines\nDistrito: Faro\nConcelho: Silves\nFreguesia: Freguesia de São Bartolomeu de Messines\nPaís: Portugal\nNUT III: PT150\nLocalidade: Freguesia de Silves\nDistrito: Faro\nConcelho: Silves\nFreguesia: Freguesia de Silves\nPaís: Portugal\nNUT III: PT150\nLocalidade: União das Freguesias de Algoz e Tunes\nDistrito: Faro\nConcelho: Silves\nFreguesia: União das Freguesias de Algoz e Tunes\nPaís: Portugal\nNUT III: PT150\nLocalidade: Freguesia de Paderne - Albufeira\nDistrito: Faro\nConcelho: Albufeira\nFreguesia: Freguesia de Paderne - Albufeira\nPaís: Portugal\nNUT III: PT150\nLocalidade: Freguesia de Alte\nDistrito: Faro\nConcelho: Loulé\nFreguesia: Freguesia de Alte\nPaís: Portugal\nNUT III: PT150\nLocalidade: Freguesia de Salir\nDistrito: Faro\nConcelho: Loulé\nFreguesia: Freguesia de Salir\nPaís: Portugal\nNUT III: PT150\nLocalidade: União das Freguesias de Bensafrim e Barão de São João\nDistrito: Faro\nConcelho: Lagos\nFreguesia: União das Freguesias de Bensafrim e Barão de São João\nPaís: Portugal\nNUT III: PT150\nLocalidade: Freguesia de Luz - Lagos\nDistrito: Faro\nConcelho: Lagos\nFreguesia: Freguesia de Luz - Lagos\nPaís: Portugal\nNUT III: PT150\nLocalidade: Freguesia de Boliqueime\nDistrito: Faro\nConcelho: Loulé\nFreguesia: Freguesia de Boliqueime\nPaís: Portugal\nNUT III: PT150\nLocalidade: Freguesia de Ferreiras\nDistrito: Faro\nConcelho: Albufeira\nFreguesia: Freguesia de Ferreiras\nPaís: Portugal\nNUT III: PT150\nLocalidade: Freguesia de Loulé (São Sebastião)\nDistrito: Faro\nConcelho: Loulé\nFreguesia: Freguesia de Loulé (São Sebastião)\nPaís: Portugal\nNUT III: PT150\nLocalidade: Freguesia de Quarteira\nDistrito: Faro\nConcelho: Loulé\nFreguesia: Freguesia de Quarteira\nPaís: Portugal\nNUT III: PT150\nLocalidade: União das Freguesias de Moncarapacho e Fuseta\nDistrito: Faro\nConcelho: Olhão\nFreguesia: União das Freguesias de Moncarapacho e Fuseta\nPaís: Portugal\nNUT III: PT150\nLocalidade: Freguesia de Quelfes\nDistrito: Faro\nConcelho: Olhão\nFreguesia: Freguesia de Quelfes\nPaís: Portugal\nNUT III: PT150\nLocalidade: União das Freguesias de Conceição e Estoi\nDistrito: Faro\nConcelho: Faro\nFreguesia: União das Freguesias de Conceição e Estoi\nPaís: Portugal\nNUT III: PT150\nLocalidade: União das Freguesias de Luz de Tavira e Santo Estêvão\nDistrito: Faro\nConcelho: Tavira\nFreguesia: União das Freguesias de Luz de Tavira e Santo Estêvão\nPaís: Portugal\nNUT III: PT150\nLocalidade: Freguesia de Santa Luzia - Tavira\nDistrito: Faro\nConcelho: Tavira\nFreguesia: Freguesia de Santa Luzia - Tavira\nPaís: Portugal\nNUT III: PT150\nLocalidade: Freguesia de Santa Catarina da Fonte do Bispo\nDistrito: Faro\nConcelho: Tavira\nFreguesia: Freguesia de Santa Catarina da Fonte do Bispo\nPaís: Portugal\nNUT III: PT150\nLocalidade: União de Freguesias de Querença, Tôr e Benafim\nDistrito: Faro\nConcelho: Loulé\nFreguesia: União de Freguesias de Querença, Tôr e Benafim\nPaís: Portugal\nNUT III: PT150\nLocalidade: Freguesia de São Gonçalo de Lagos\nDistrito: Faro\nConcelho: Lagos\nFreguesia: Freguesia de São Gonçalo de Lagos\nPaís: Portugal\nNUT III: PT150\nLocalidade: Freguesia de Vila Nova de Cacela\nDistrito: Faro\nConcelho: Vila Real Sto Antonio\nFreguesia: Freguesia de Vila Nova de Cacela\n\n10 - PRAZO DE EXECUÇÃO DO CONTRATO\nPrazo de execução do contrato: 180 DIAS\nPrevisão de renovações: Não\n\n11 - FUNDOS EU\nTêm fundos EU? Sim\n\n12 - DOCUMENTOS DE HABILITAÇÃO\nHabilitação para o exercício da atividade profissional: Não\n\n13 - CONDIÇÕES DE APRESENTAÇÃO\nPlataforma eletrónica utilizada pela entidade adjudicante: ACIN\nURL para Apresentação: https://www.acingov.pt\nAdmissibilidade da apresentação de propostas variantes: Não autorizado\nPrazo para apresentação das propostas: 13-11-2025 23:59\nPrazo durante o qual os concorrentes são obrigados a manter as respetivas propostas: 66 dias a contar do termo do prazo para a apresentação das propostas\nApresentação de Catálogo Eletrónico: Não autorizado\nIndicação de Subcontratação na Proposta: Inexistência de indicação de subcontratação\n\n14 - PRESTAÇÃO DE CAUÇÃO\nPrestação de caução: Sim\nPercentagem: 5%\nDescrição da Garantia Exigida: O valor da caução é de 5.00% do preço contratual.\n\n15 - FORNECIMENTO DAS PEÇAS DO CONCURSO, APRESENTAÇÃO DE PEDIDOS DE PARTICIPAÇÃO E APRESENTAÇÃO DAS PROPOSTAS\nLink para acesso às peças do concurso (URL): https://www.acingov.pt/acingovprod/2/zonaPublica/zona_publica_c/donwloadProcedurePiece/OTg2Mzk4\n\n20 - OUTROS REQUISITOS\nInformação sobre contratos reservados. Aplica-se a contratos reservados (54º-A)? Não\n\n21 - CRITÉRIO DE ADJUDICAÇÃO\nMultifator: Não\nMonofator:\nNome: Preço\n\n24 - CONDIÇÕES DO CONTRATO\nFaturação Eletrónica: Permitido\nObrigação de Subcontratação:\nCódigo da Obrigação de Subcontratação: Não é aplicável nenhuma obrigação de subcontratação.\n\n25 - COMPRA PÚBLICA ESTRATÉGICA\nCompra Pública Estratégica: Inexistência de contratação pública estratégica\n\n26 - INFORMAÇÕES ADICIONAIS\nContrato adequado para PME: Sim\nCobertura ACP (Acordo dos Contratos Públicos da Organização Mundial do Comércio): Não\n\n27 - IDENTIFICAÇÃO E CONTACTOS DO ÓRGÃO DE RECURSOS ADMINISTRATIVOS\nDesignação: Agência Portuguesa do Ambiente. I.P.\nEndereço: Rua da Murgueira, 9/9A- Zambujal -Ap. 7585\nCódigo postal: 2610-124\nLocalidade: Amadora\nTelefone: 214728200\nFax: 214719074\nEndereço eletrónico: geral@apambiente.pt\nPrazo de interposição do recurso: 30 dias\n\n28 - IDENTIFICAÇÃO DO(S) AUTOR(ES) DE ANÚNCIO\nNome: Luís Miguel Guerra\nCargo: Chefe Divisão DAAF ARH Algarve\n419657668",
    "nipc": "510306624",
    "distrito": "Lisboa",
    "concelho": "Amadora",
    "freguesia": "Freguesia de Alfragide",
    "site": "www.apambiente.pt",
    "email": "geral@apambiente.pt",
    "designacao_contrato": "Aquisição de equipamento de telemetria e instalação em estações hidrométricas e em sensores de medição do nível e condutividade de água subterrânea.",
    "descricao": "Aquisição de equipamento de telemetria e instalação em estações hidrométricas e em sensores de medição do nível e condutividade de água subterrânea, no âmbito do PRR.",
    "preco_base": "160.000,00 EUR",
    "prazo_execucao": "180 DIAS",
    "prazo_apresentacao_propostas": "13-11-2025 23:59",
    "fundos_eu": "Sim",
    "plataforma_eletronica": "ACIN",
    "url_procedimento": "https://www.acingov.pt",
    "autor_nome": "Luís Miguel Guerra",
    "autor_cargo": "Chefe Divisão DAAF ARH Algarve"
  },
  {
    "numero_procedimento": "N/A",
    "entidade": "URZE - Associação Florestal da Encosta da Serra da Estrela",
    "link": "https://diariodarepublica.pt/dr/detalhe/contrato-publico/27415-940618821",
    "detalhes_completos": "1 - IDENTIFICAÇÃO E CONTACTOS DA ENTIDADE ADJUDICANTE\nDesignação da entidade adjudicante: URZE - Associação Florestal da Encosta da Serra da Estrela\nNIPC: 504495160\nEndereço: Rua Cidade da Guarda - Edifício da Estação de Transportes, r/c\nCódigo postal: 6290-361\nLocalidade: Guarda\nPaís: Portugal\nNUT III: PT16J\nDistrito: Guarda\nConcelho: Gouveia\nFreguesia: Todas\nTelefone: 238498160\nEndereço da Entidade (URL): www.urze.org\nEndereço Eletrónico: urze.estrela@gmail.com\neDelivery Gateway (URL): https://community.vortal.biz/public/\nFunção da Organização: Adquirente\nNorma jurídica da Entidade Adjudicante: Autoridade da administração central\nÁrea de atividade da Autoridade Adjudicante: Serviços públicos das administrações públicas\n\n2 - JORNAL OFICIAL DA UNIÃO EUROPEIA\nO procedimento a que este anúncio diz respeito também é publicitado no Jornal Oficial da União Europeia? Sim\n\n3 - AVISO\nModelo de Anúncio: Concurso público\nData de Envio do Anúncio: 15-10-2025\n\n5 - PROCESSO\nTipo de Procedimento: Concurso público\nPreço base do procedimento: Sim\nValor do preço base do procedimento: 1.255.654,81 EUR\nProcedimento com lotes? Sim\nNº Máx. de Lotes Autorizado: 3\nNúmero máximo de lotes que podem ser adjudicados a um concorrente: 2\n\n6 - OBJETO DO CONTRATO\nNúmero de referência interna: 10 OIGP URZE\nDesignação do contrato: Aquisição de serviços\nDescrição: AQUISIÇÃO DE SERVIÇOS, POR LOTES, DE OPERAÇÃO INTEGRADA DE GESTÃO DE PAISAGEM (OIGP) SOCORRO, COFINANCIADO POR FUNDOS COMUNITÁRIOS NO ÂMBITO DO PLANO DE RECUPERAÇÃO E RESILIÊNCIA \nOpções: Não\nTipo de Contrato Principal: Aquisição de Serviços\nTipo de Contrato: Aquisição de Serviços\nClassificação CPV (Vocabulário Comum para os Contratos Públicos)\nObjeto principal\nVocabulário Principal: 77200000\nPreço base s/IVA: 1.255.654,81 EUR\nLotes: \nNº: LOT-0001\nDescrição do Lote: Lote 1\nPreço base s/IVA: 388.112,62 EUR\nClassificação CPV (Vocabulário Comum para os Contratos Públicos)\nObjeto principal\nVocabulário Principal: 77200000\nNº: LOT-0002\nDescrição do Lote: Lote 2\nPreço base s/IVA: 456.560,33 EUR\nClassificação CPV (Vocabulário Comum para os Contratos Públicos)\nObjeto principal\nVocabulário Principal: 77200000\nNº: LOT-0003\nDescrição do Lote: Lote 3\nPreço base s/IVA: 410.981,86 EUR\nClassificação CPV (Vocabulário Comum para os Contratos Públicos)\nObjeto principal\nVocabulário Principal: 77200000\n\n7 - INDICAÇÕES ADICIONAIS\nO contrato envolve aquisição conjunta (satisfação de várias entidades)? Não\nO contrato é adjudicado por uma central de compras? Não\n\n8 - TÉCNICAS\nO concurso destina-se à celebração de um acordo-quadro? Inexistência de acordo-quadro\nÉ utilizado um leilão eletrónico? Não\nÉ adotada uma fase de negociação? Não\nSistema de Aquisição Dinâmico: Inexistência de sistema de aquisição dinâmico\n\n9 - LOCAL DA EXECUÇÃO DO CONTRATO\nLOCAL DA EXECUÇÃO DO CONTRATO (PROCEDIMENTO)\nPaís: Portugal\nNUT III: PT16J\nLocalidade: Guarda\nDistrito: Guarda\nConcelho: Gouveia\nFreguesia: Freguesia de Gouveia - Gouveia\nLOCAL DA EXECUÇÃO DO CONTRATO (LOTE)\nIdentificador do Lote: LOT-0001; LOT-0002; LOT-0003\nPaís: Portugal\nNUT III: PT16J\nLocalidade: Guarda\nDistrito: Guarda\nConcelho: Gouveia\nFreguesia: Freguesia de Gouveia - Gouveia\n\n10 - PRAZO DE EXECUÇÃO DO CONTRATO\nIdentificador do Lote: LOT-0001; LOT-0002; LOT-0003\nPrazo de execução do contrato: 180 MESES\nPrevisão de renovações: Não\n\n11 - FUNDOS EU\nIdentificador do Lote: LOT-0001; LOT-0002; LOT-0003\nTêm fundos EU? Sim\n\n12 - DOCUMENTOS DE HABILITAÇÃO\nHabilitação para o exercício da atividade profissional: Não\n\n13 - CONDIÇÕES DE APRESENTAÇÃO\nPlataforma eletrónica utilizada pela entidade adjudicante: VORTAL\nURL para Apresentação: https://community.vortal.biz/public/\nAdmissibilidade da apresentação de propostas variantes: Não autorizado\nPrazo para apresentação das propostas: 13-11-2025 23:59\nPrazo durante o qual os concorrentes são obrigados a manter as respetivas propostas: 66 dias a contar do termo do prazo para a apresentação das propostas\nApresentação de Catálogo Eletrónico: Não autorizado\nIndicação de Subcontratação na Proposta: Inexistência de indicação de subcontratação\n\n14 - PRESTAÇÃO DE CAUÇÃO\nPrestação de caução: Não\n\n15 - FORNECIMENTO DAS PEÇAS DO CONCURSO, APRESENTAÇÃO DE PEDIDOS DE PARTICIPAÇÃO E APRESENTAÇÃO DAS PROPOSTAS\nLink para acesso às peças do concurso (URL): https://community.vortal.biz/Public/public-tender-documents/UmxxV00rWHlHYWNXRng5SzVjd2VYRWI2OVlhRG1SUWxJTXAreFNLbk1aUkFhQktsdjU1TVFFV3dZMVJ0a1FBenNjZ1BuYjJIUmlTNmxFa1lpNlJIbUE9PTUwcnBj\n\n20 - OUTROS REQUISITOS\nIdentificador do Lote: LOT-0001; LOT-0002; LOT-0003\nInformação sobre contratos reservados. Aplica-se a contratos reservados (54º-A)? Não\n\n21 - CRITÉRIO DE ADJUDICAÇÃO\nO Critério de adjudicação é diferenciado por lote? Não\nMultifator: Não\nMonofator:\nNome: Preço\n\n24 - CONDIÇÕES DO CONTRATO\nIdentificador do Lote: LOT-0001; LOT-0002; LOT-0003\nFaturação Eletrónica: Permitido\nObrigação de Subcontratação:\nCódigo da Obrigação de Subcontratação: Não é aplicável nenhuma obrigação de subcontratação.\n\n25 - COMPRA PÚBLICA ESTRATÉGICA\nCompra Pública Estratégica: Inexistência de contratação pública estratégica\n\n26 - INFORMAÇÕES ADICIONAIS\nIdentificador do Lote: LOT-0001; LOT-0002; LOT-0003\nContrato adequado para PME: Sim\nCobertura ACP (Acordo dos Contratos Públicos da Organização Mundial do Comércio): Não\n\n27 - IDENTIFICAÇÃO E CONTACTOS DO ÓRGÃO DE RECURSOS ADMINISTRATIVOS\nDesignação: URZE - Associação Florestal da Encsta da Serra da Estrela\nEndereço: Rua Cidade da Guarda - Ed Central Camionagem R/C\nCódigo postal: 6290-361\nLocalidade: Gouveia\nTelefone: +351 238498160\nFax: +351 238498160\nEndereço eletrónico: urze.estrela@gmail.com\n\n28 - IDENTIFICAÇÃO DO(S) AUTOR(ES) DE ANÚNCIO\nNome: João Castilho\nCargo: Técnico\n419658389",
    "nipc": "504495160",
    "distrito": "Guarda",
    "concelho": "Gouveia",
    "freguesia": "Todas",
    "site": "www.urze.org",
    "email": "urze.estrela@gmail.com",
    "designacao_contrato": "Aquisição de serviços",
    "descricao": "AQUISIÇÃO DE SERVIÇOS, POR LOTES, DE OPERAÇÃO INTEGRADA DE GESTÃO DE PAISAGEM (OIGP) SOCORRO, COFINANCIADO POR FUNDOS COMUNITÁRIOS NO ÂMBITO DO PLANO DE RECUPERAÇÃO E RESILIÊNCIA",
    "preco_base": "1.255.654,81 EUR",
    "prazo_execucao": "180 MESES",
    "prazo_apresentacao_propostas": "13-11-2025 23:59",
    "fundos_eu": "Sim",
    "plataforma_eletronica": "VORTAL",
    "url_procedimento": "https://community.vortal.biz/public/",
    "autor_nome": "João Castilho",
    "autor_cargo": "Técnico"
  },
  {
    "numero_procedimento": "N/A",
    "entidade": "AnÃºncio de procedimento  n.Âº 27416/2025  -  DiÃ¡rio da RepÃºblica n.Âº 201/2025, SÃ©rie II de 2025-10-17",
    "link": "https://diariodarepublica.pt/dr/detalhe/contrato-publico/27416-940618822"
  },
  {
    "numero_procedimento": "N/A",
    "entidade": "Município de Paredes de Coura",
    "link": "https://diariodarepublica.pt/dr/detalhe/contrato-publico/27417-940618823",
    "detalhes_completos": "1 - IDENTIFICAÇÃO E CONTACTOS DA ENTIDADE ADJUDICANTE\nDesignação da entidade adjudicante: Município de Paredes de Coura\nNIPC: 506632938\nEndereço: Lg. Viscde Moselos Aptd. 6\nCódigo postal: 4940-525\nLocalidade: Paredes de Coura\nPaís: Portugal\nNUT III: PT111\nDistrito: Viana do Castelo\nConcelho: Paredes de Coura\nFreguesia: Todas\nTelefone: 251780100\nFax: 251780118\nEndereço da Entidade (URL): www.paredesdecoura.pt\nEndereço Eletrónico: geral@paredesdecoura.pt\neDelivery Gateway (URL): https://community.vortal.biz/public/\nFunção da Organização: Adquirente\nNorma jurídica da Entidade Adjudicante: Autoridade local\nÁrea de atividade da Autoridade Adjudicante: Serviços públicos das administrações públicas\n\n2 - JORNAL OFICIAL DA UNIÃO EUROPEIA\nO procedimento a que este anúncio diz respeito também é publicitado no Jornal Oficial da União Europeia? Não\n\n3 - AVISO\nModelo de Anúncio: Concurso público\nData de Envio do Anúncio: 17-10-2025\n\n5 - PROCESSO\nTipo de Procedimento: Concurso público\nPreço base do procedimento: Sim\nValor do preço base do procedimento: 59.150,00 EUR\nProcedimento com lotes? Não\n\n6 - OBJETO DO CONTRATO\nNúmero de referência interna: 85/25_S\nDesignação do contrato: Aquisição de serviços de Técnico de Psicomotricidade, no âmbito da candidatura aos Programas intermunicipais de promoção do Sucesso Escolar (PIPSE), com o código de operação Norte2030-FSE+-02275200\nDescrição: Aquisição de serviços de Técnico de Psicomotricidade, no âmbito da candidatura aos Programas intermunicipais de promoção do Sucesso Escolar (PIPSE), com o código de operação Norte2030-FSE+-02275200\nTipo de Contrato Principal: Aquisição de Serviços\nTipo de Contrato: Aquisição de Serviços\nClassificação CPV (Vocabulário Comum para os Contratos Públicos)\nObjeto principal\nVocabulário Principal: 80410000\nPreço base s/IVA: 59.150,00 EUR\n\n7 - INDICAÇÕES ADICIONAIS\nO contrato envolve aquisição conjunta (satisfação de várias entidades)? Não\nO contrato é adjudicado por uma central de compras? Não\n\n8 - TÉCNICAS\nO concurso destina-se à celebração de um acordo-quadro? Inexistência de acordo-quadro\nÉ utilizado um leilão eletrónico? Não\nÉ adotada uma fase de negociação? Não\nSistema de Aquisição Dinâmico: Inexistência de sistema de aquisição dinâmico\n\n9 - LOCAL DA EXECUÇÃO DO CONTRATO\nLOCAL DA EXECUÇÃO DO CONTRATO (PROCEDIMENTO)\nPaís: Portugal\nNUT III: PT111\nLocalidade: Viana do Castelo\nDistrito: Viana do Castelo\nConcelho: Paredes de Coura\nFreguesia: União das Freguesias de Paredes de Coura e Resende\n\n10 - PRAZO DE EXECUÇÃO DO CONTRATO\nPrazo de execução do contrato: 881 DIAS\nPrevisão de renovações: Não\n\n11 - FUNDOS EU\nTêm fundos EU? Sim\n\n12 - DOCUMENTOS DE HABILITAÇÃO\nHabilitação para o exercício da atividade profissional: Sim\nTipo: Outros\nDescrição - Outros: Licenciatura\nDescrição: Licenciatura\n\n13 - CONDIÇÕES DE APRESENTAÇÃO\nPlataforma eletrónica utilizada pela entidade adjudicante: VORTAL\nURL para Apresentação: https://community.vortal.biz/public/\nAdmissibilidade da apresentação de propostas variantes: Não autorizado\nPrazo para apresentação das propostas: 23-10-2025 16:00\nPrazo durante o qual os concorrentes são obrigados a manter as respetivas propostas: 66 dias a contar do termo do prazo para a apresentação das propostas\nIndicação de Subcontratação na Proposta: Inexistência de indicação de subcontratação\n\n14 - PRESTAÇÃO DE CAUÇÃO\nPrestação de caução: Não\n\n15 - FORNECIMENTO DAS PEÇAS DO CONCURSO, APRESENTAÇÃO DE PEDIDOS DE PARTICIPAÇÃO E APRESENTAÇÃO DAS PROPOSTAS\nLink para acesso às peças do concurso (URL): https://community.vortal.biz/Public/public-tender-documents/QmtLNlBTZGR1bmtoMzUrMXY3cDlBTWxwWlRZVGJrdFpPY2tPNjk0WTRlcVl0ZTVXL1dKVWNpS3c1M2NtY3dPVlpNZ1BDY2NkT1R5bUVuNFIweHp0cUE9PUc5Jldm\n\n20 - OUTROS REQUISITOS\nInformação sobre contratos reservados. Aplica-se a contratos reservados (54º-A)? Não\n\n21 - CRITÉRIO DE ADJUDICAÇÃO\nMultifator: Não\nMonofator:\nNome: Preço\n\n24 - CONDIÇÕES DO CONTRATO\nFaturação Eletrónica: Permitido\nObrigação de Subcontratação:\nCódigo da Obrigação de Subcontratação: Não é aplicável nenhuma obrigação de subcontratação.\n\n25 - COMPRA PÚBLICA ESTRATÉGICA\nCompra Pública Estratégica: Inexistência de contratação pública estratégica\n\n26 - INFORMAÇÕES ADICIONAIS\nContrato adequado para PME: Sim\nCobertura ACP (Acordo dos Contratos Públicos da Organização Mundial do Comércio): Não\n\n27 - IDENTIFICAÇÃO E CONTACTOS DO ÓRGÃO DE RECURSOS ADMINISTRATIVOS\nDesignação: Município de Paredes de Coura\nEndereço: Largo Visconde de Mozelos, Ap.6\nCódigo postal: 4941-909\nLocalidade: Paredes de Coura\nTelefone: +351 251780100\nFax: +351 251780100\nEndereço eletrónico: geral@paredesdecoura.pt\n\n28 - IDENTIFICAÇÃO DO(S) AUTOR(ES) DE ANÚNCIO\nNome: Vitor Paulo Gomes Pereira\nCargo: Presidente\n419669907",
    "nipc": "506632938",
    "distrito": "Viana do Castelo",
    "concelho": "Paredes de Coura",
    "freguesia": "Todas",
    "site": "www.paredesdecoura.pt",
    "email": "geral@paredesdecoura.pt",
    "designacao_contrato": "Aquisição de serviços de Técnico de Psicomotricidade, no âmbito da candidatura aos Programas intermunicipais de promoção do Sucesso Escolar (PIPSE), com o código de operação Norte2030-FSE+-02275200",
    "descricao": "Aquisição de serviços de Técnico de Psicomotricidade, no âmbito da candidatura aos Programas intermunicipais de promoção do Sucesso Escolar (PIPSE), com o código de operação Norte2030-FSE+-02275200",
    "preco_base": "59.150,00 EUR",
    "prazo_execucao": "881 DIAS",
    "prazo_apresentacao_propostas": "23-10-2025 16:00",
    "fundos_eu": "Sim",
    "plataforma_eletronica": "VORTAL",
    "url_procedimento": "https://community.vortal.biz/public/",
    "autor_nome": "Vitor Paulo Gomes Pereira",
    "autor_cargo": "Presidente"
  },
  {
    "numero_procedimento": "N/A",
    "entidade": "Comunidade Intermunicipal da Lezíria do Tejo",
    "link": "https://diariodarepublica.pt/dr/detalhe/contrato-publico/27419-940618824",
    "detalhes_completos": "Alteração do Anúncio de procedimento n.º 26115/2025, de 2025-10-06, com o ID 419602416\n\n1 - IDENTIFICAÇÃO E CONTACTOS DA ENTIDADE ADJUDICANTE\nDesignação da entidade adjudicante: Comunidade Intermunicipal da Lezíria do Tejo\nNIPC: 508787033\nEndereço: QUINTA DAS CEGONHAS \nCódigo postal: 2001-907\nLocalidade: Santarém\nPaís: Portugal\nNUT III: PT185\nDistrito: Santarém\nConcelho: Santarém\nFreguesia: União de Freguesias da Cidade de Santarém\nTelefone: 243303240\nFax: 243303240\nEndereço da Entidade (URL): https://www.cimlt.eu\nEndereço Eletrónico: geral@cimlt.eu\neDelivery Gateway (URL): https://community.vortal.biz/public/\nFunção da Organização: Adquirente\nNorma jurídica da Entidade Adjudicante: Organismo de direito público\nÁrea de atividade da Autoridade Adjudicante: Serviços públicos das administrações públicas\n\n2 - JORNAL OFICIAL DA UNIÃO EUROPEIA\nO procedimento a que este anúncio diz respeito também é publicitado no Jornal Oficial da União Europeia? Sim\n\n3 - AVISO\nModelo de Anúncio: Concurso público\nData de Envio do Anúncio: 15-10-2025\n\n5 - PROCESSO\nTipo de Procedimento: Concurso público\nPreço base do procedimento: Sim\nValor do preço base do procedimento: 244.000,00 EUR\nProcedimento com lotes? Não\n\n6 - OBJETO DO CONTRATO\nNúmero de referência interna: CP/05/2025\nDesignação do contrato: CP/05/2025, para a Aquisição de Licença de Plataforma Vertical de Regas Inteligentes e Aquisição de Sistema de Controladores de Rega e Estações Meteorológicas.\nDescrição: Aquisição de Licença de Plataforma Vertical de Regas Inteligentes e Aquisição de Sistema de Controladores de Rega e Estações Meteorológicas.\nOpções: Não\nTipo de Contrato Principal: Aquisição de Bens Móveis\nTipo de Contrato: Aquisição de Bens Móveis\nClassificação CPV (Vocabulário Comum para os Contratos Públicos)\nObjeto principal\nVocabulário Principal: 16160000\nPreço base s/IVA: 244.000,00 EUR\n\n7 - INDICAÇÕES ADICIONAIS\nO contrato envolve aquisição conjunta (satisfação de várias entidades)? Não\nO contrato é adjudicado por uma central de compras? Não\n\n8 - TÉCNICAS\nO concurso destina-se à celebração de um acordo-quadro? Inexistência de acordo-quadro\nÉ utilizado um leilão eletrónico? Não\nÉ adotada uma fase de negociação? Não\nSistema de Aquisição Dinâmico: Inexistência de sistema de aquisição dinâmico\n\n9 - LOCAL DA EXECUÇÃO DO CONTRATO\nLOCAL DA EXECUÇÃO DO CONTRATO (PROCEDIMENTO)\nPaís: Portugal\nNUT III: PT185\nLocalidade: Santarém\nDistrito: Santarém\nConcelho: Santarém\nFreguesia: União de Freguesias da Cidade de Santarém\n\n10 - PRAZO DE EXECUÇÃO DO CONTRATO\nPrazo de execução do contrato: 4 MESES\nPrevisão de renovações: Não\n\n11 - FUNDOS EU\nTêm fundos EU? Sim\n\n12 - DOCUMENTOS DE HABILITAÇÃO\nHabilitação para o exercício da atividade profissional: Não\n\n13 - CONDIÇÕES DE APRESENTAÇÃO\nPlataforma eletrónica utilizada pela entidade adjudicante: VORTAL\nURL para Apresentação: https://community.vortal.biz/public/\nAdmissibilidade da apresentação de propostas variantes: Não autorizado\nPrazo para apresentação das propostas: 09-11-2025 23:59\nPrazo durante o qual os concorrentes são obrigados a manter as respetivas propostas: 66 dias a contar do termo do prazo para a apresentação das propostas\nApresentação de Catálogo Eletrónico: Não autorizado\nIndicação de Subcontratação na Proposta: Inexistência de indicação de subcontratação\n\n14 - PRESTAÇÃO DE CAUÇÃO\nPrestação de caução: Não\n\n15 - FORNECIMENTO DAS PEÇAS DO CONCURSO, APRESENTAÇÃO DE PEDIDOS DE PARTICIPAÇÃO E APRESENTAÇÃO DAS PROPOSTAS\nLink para acesso às peças do concurso (URL): https://community.vortal.biz/Public/public-tender-documents/WTdXZ00wMDFLSjVMWTZmSy9telRPWGhVdEFCcG0vczZ5UWN2bjhsOTc5dzlVKyt1TkprL0lqRVBKL0I3UmpCYTlGVUJVTmJqM3NmYWd0MkZtMHgvQWc9PUx5SWJJ\n\n20 - OUTROS REQUISITOS\nInformação sobre contratos reservados. Aplica-se a contratos reservados (54º-A)? Não\n\n21 - CRITÉRIO DE ADJUDICAÇÃO\nMultifator: Sim\nFator: \nNome: Outros\nOutro Nome: Preço\nPonderação: 50%\nSubfatores: Não\nFator: \nNome: Outros\nOutro Nome: Projetos Concluídos pelo Coordenador da Equipa\nPonderação: 30%\nSubfatores: Não\nFator: \nNome: Qualidade\nPonderação: 20%\nSubfatores: Não\n\n24 - CONDIÇÕES DO CONTRATO\nFaturação Eletrónica: Permitido\nObrigação de Subcontratação:\nCódigo da Obrigação de Subcontratação: Não é aplicável nenhuma obrigação de subcontratação.\n\n25 - COMPRA PÚBLICA ESTRATÉGICA\nCompra Pública Estratégica: Inexistência de contratação pública estratégica\n\n26 - INFORMAÇÕES ADICIONAIS\nContrato adequado para PME: Sim\nCobertura ACP (Acordo dos Contratos Públicos da Organização Mundial do Comércio): Não\n\n27 - IDENTIFICAÇÃO E CONTACTOS DO ÓRGÃO DE RECURSOS ADMINISTRATIVOS\nDesignação: Conselho Intermunicipal da Lezíria do Tejo\nEndereço: Quinta das Cegonhas, Apartado 577\nCódigo postal: 2001-907\nLocalidade: Santarém\nTelefone: +351 243303240\nFax: +351 243303240\nEndereço eletrónico: geral@cimlt.eu\n\n28 - IDENTIFICAÇÃO DO(S) AUTOR(ES) DE ANÚNCIO\nNome: Mário Rui Gonçalves Ruas\nCargo: Assistente Técnico\n\n29 - ALTERAÇÃO\nMotivo da Alteração: Informações atualizadas\nIdentificador da Versão do Anúncio a Alterar: dd0d1c1f-8e92-474d-8711-0bf0dec49ed5-01\nIdentificador das Secções Alteradas do Anúncio Anterior: Alteração\nAlteração dos Documentos do Concurso: Sim\nData de alteração dos documentos do concurso: 10-10-2025\n419646562",
    "nipc": "508787033",
    "distrito": "Santarém",
    "concelho": "Santarém",
    "freguesia": "União de Freguesias da Cidade de Santarém",
    "site": "https://www.cimlt.eu",
    "email": "geral@cimlt.eu",
    "designacao_contrato": "CP/05/2025, para a Aquisição de Licença de Plataforma Vertical de Regas Inteligentes e Aquisição de Sistema de Controladores de Rega e Estações Meteorológicas.",
    "descricao": "Aquisição de Licença de Plataforma Vertical de Regas Inteligentes e Aquisição de Sistema de Controladores de Rega e Estações Meteorológicas.",
    "preco_base": "244.000,00 EUR",
    "prazo_execucao": "4 MESES",
    "prazo_apresentacao_propostas": "09-11-2025 23:59",
    "fundos_eu": "Sim",
    "plataforma_eletronica": "VORTAL",
    "url_procedimento": "https://community.vortal.biz/public/",
    "autor_nome": "Mário Rui Gonçalves Ruas",
    "autor_cargo": "Assistente Técnico"
  },
  {
    "numero_procedimento": "N/A",
    "entidade": "AnÃºncio de procedimento  n.Âº 27421/2025  -  DiÃ¡rio da RepÃºblica n.Âº 201/2025, SÃ©rie II de 2025-10-17",
    "link": "https://diariodarepublica.pt/dr/detalhe/contrato-publico/27421-940618825"
  },
  {
    "numero_procedimento": "N/A",
    "entidade": "Unidade Local de Saúde de Castelo Branco, E. P. E.",
    "link": "https://diariodarepublica.pt/dr/detalhe/contrato-publico/27422-940618826",
    "detalhes_completos": "1 - IDENTIFICAÇÃO E CONTACTOS DA ENTIDADE ADJUDICANTE\nDesignação da entidade adjudicante: Unidade Local de Saúde de Castelo Branco, E. P. E.\nNIPC: 509309844\nServiço/Órgão/Pessoa de contacto: Serviço de Compras e Logística | Área de Contratação Pública\nEndereço: Av. Pedro Alvares Cabral, s/n\nCódigo postal: 6000-085\nLocalidade: Castelo Branco\nPaís: Portugal\nNUT III: PT16H\nDistrito: Castelo Branco\nConcelho: Castelo Branco\nFreguesia: Freguesia de Castelo Branco - Castelo Branco\nTelefone: 272000272\nFax: 272000121\nEndereço da Entidade (URL): https://www.ulscb.min-saude.pt/\nEndereço Eletrónico: concursos@ulscb.min-saude.pt\neDelivery Gateway (URL): https://www.acingov.pt\nFunção da Organização: Adquirente\nNorma jurídica da Entidade Adjudicante: Organismo de direito público\nÁrea de atividade da Autoridade Adjudicante: Saúde\n\n2 - JORNAL OFICIAL DA UNIÃO EUROPEIA\nO procedimento a que este anúncio diz respeito também é publicitado no Jornal Oficial da União Europeia? Não\n\n3 - AVISO\nModelo de Anúncio: Concurso público\nData de Envio do Anúncio: 17-10-2025\n\n5 - PROCESSO\nTipo de Procedimento: Concurso público\nPreço base do procedimento: Sim\nValor do preço base do procedimento: 88.726,03 EUR\nProcedimento com lotes? Não\n\n6 - OBJETO DO CONTRATO\nNúmero de referência interna: 5631825\nDesignação do contrato: AQUISIÇÃO DE SEGUROS NO RAMO DE MULTIRRISCO PATRIMONIAL PARA A ULSCB DURANTE O ANO DE 2026\nDescrição: AQUISIÇÃO DE SEGUROS NO RAMO DE MULTIRRISCO PATRIMONIAL PARA A ULSCB DURANTE O ANO DE 2026\nTipo de Contrato Principal: Aquisição de Serviços\nTipo de Contrato: Aquisição de Serviços\nClassificação CPV (Vocabulário Comum para os Contratos Públicos)\nObjeto principal\nVocabulário Principal: 66510000\nPreço base s/IVA: 88.726,03 EUR\n\n7 - INDICAÇÕES ADICIONAIS\nO contrato envolve aquisição conjunta (satisfação de várias entidades)? Não\nO contrato é adjudicado por uma central de compras? Sim\n\n8 - TÉCNICAS\nO concurso destina-se à celebração de um acordo-quadro? Inexistência de acordo-quadro\nÉ utilizado um leilão eletrónico? Não\nÉ adotada uma fase de negociação? Não\nSistema de Aquisição Dinâmico: Inexistência de sistema de aquisição dinâmico\n\n9 - LOCAL DA EXECUÇÃO DO CONTRATO\nLOCAL DA EXECUÇÃO DO CONTRATO (PROCEDIMENTO)\nPaís: Portugal\nNUT III: PT16H\nLocalidade: Freguesia de Castelo Branco - Castelo Branco\nDistrito: Castelo Branco\nConcelho: Castelo Branco\nFreguesia: Freguesia de Castelo Branco - Castelo Branco\n\n10 - PRAZO DE EXECUÇÃO DO CONTRATO\nPrazo de execução do contrato: 365 DIAS\nPrevisão de renovações: Não\n\n11 - FUNDOS EU\nTêm fundos EU? Não\n\n12 - DOCUMENTOS DE HABILITAÇÃO\nHabilitação para o exercício da atividade profissional: Não\n\n13 - CONDIÇÕES DE APRESENTAÇÃO\nPlataforma eletrónica utilizada pela entidade adjudicante: ACIN\nURL para Apresentação: https://www.acingov.pt\nAdmissibilidade da apresentação de propostas variantes: Não autorizado\nPrazo para apresentação das propostas: 03-11-2025 17:00\nPrazo durante o qual os concorrentes são obrigados a manter as respetivas propostas: 120 dias a contar do termo do prazo para a apresentação das propostas\nIndicação de Subcontratação na Proposta: Inexistência de indicação de subcontratação\n\n14 - PRESTAÇÃO DE CAUÇÃO\nPrestação de caução: Não\n\n15 - FORNECIMENTO DAS PEÇAS DO CONCURSO, APRESENTAÇÃO DE PEDIDOS DE PARTICIPAÇÃO E APRESENTAÇÃO DAS PROPOSTAS\nLink para acesso às peças do concurso (URL): https://www.acingov.pt/acingovprod/2/zonaPublica/zona_publica_c/donwloadProcedurePiece/OTg4MjQ2\n\n20 - OUTROS REQUISITOS\nInformação sobre contratos reservados. Aplica-se a contratos reservados (54º-A)? Não\n\n21 - CRITÉRIO DE ADJUDICAÇÃO\nMultifator: Não\nMonofator:\nNome: Outros\nOutro nome: Preço Global Proposto\n\n24 - CONDIÇÕES DO CONTRATO\nFaturação Eletrónica: Permitido\nObrigação de Subcontratação:\nCódigo da Obrigação de Subcontratação: Não é aplicável nenhuma obrigação de subcontratação.\n\n25 - COMPRA PÚBLICA ESTRATÉGICA\nCompra Pública Estratégica: Inexistência de contratação pública estratégica\n\n26 - INFORMAÇÕES ADICIONAIS\nContrato adequado para PME: Não\nCobertura ACP (Acordo dos Contratos Públicos da Organização Mundial do Comércio): Não\n\n27 - IDENTIFICAÇÃO E CONTACTOS DO ÓRGÃO DE RECURSOS ADMINISTRATIVOS\nDesignação: CONSELHO DE ADMINISTRAÇÃO DA ULSCB, E.P.E.\nEndereço: Av. Pedro Alvares Cabral, s/n\nCódigo postal: 6000-085\nLocalidade: Castelo Branco\nTelefone: 272000272\nFax: 272000121\nEndereço eletrónico: concursos@ulscb.min-saude.pt\nPrazo de interposição do recurso: 5 dias\n\n28 - IDENTIFICAÇÃO DO(S) AUTOR(ES) DE ANÚNCIO\nNome: Luis Manuel Mateus Correia Dias\nCargo: Coordenador Técnico do Serviço de Compras e Logística\n419668351",
    "nipc": "509309844",
    "distrito": "Castelo Branco",
    "concelho": "Castelo Branco",
    "freguesia": "Freguesia de Castelo Branco - Castelo Branco",
    "site": "https://www.ulscb.min-saude.pt/",
    "email": "concursos@ulscb.min-saude.pt",
    "designacao_contrato": "AQUISIÇÃO DE SEGUROS NO RAMO DE MULTIRRISCO PATRIMONIAL PARA A ULSCB DURANTE O ANO DE 2026",
    "descricao": "AQUISIÇÃO DE SEGUROS NO RAMO DE MULTIRRISCO PATRIMONIAL PARA A ULSCB DURANTE O ANO DE 2026",
    "preco_base": "88.726,03 EUR",
    "prazo_execucao": "365 DIAS",
    "prazo_apresentacao_propostas": "03-11-2025 17:00",
    "fundos_eu": "Não",
    "plataforma_eletronica": "ACIN",
    "url_procedimento": "https://www.acingov.pt",
    "autor_nome": "Luis Manuel Mateus Correia Dias",
    "autor_cargo": "Coordenador Técnico do Serviço de Compras e Logística"
  },
  {
    "numero_procedimento": "N/A",
    "entidade": "Universidade de Coimbra",
    "link": "https://diariodarepublica.pt/dr/detalhe/contrato-publico/27423-940618834",
    "detalhes_completos": "1 - IDENTIFICAÇÃO E CONTACTOS DA ENTIDADE ADJUDICANTE\nDesignação da entidade adjudicante: Universidade de Coimbra\nNIPC: 501617582\nServiço/Órgão/Pessoa de contacto: Serviço de Gestão Financeira  Divisão de Compras\nEndereço: Rua Larga  Ed. FMUC\nCódigo postal: 3004-504\nLocalidade: Coimbra\nPaís: Portugal\nNUT III: PT16E\nDistrito: Coimbra\nConcelho: Coimbra\nFreguesia: União das Freguesias de Coimbra (Sé Nova, Santa Cruz, Almedina e São Bartolomeu)\nTelefone: 239242750\nFax: 239242750\nEndereço da Entidade (URL): www.uc.pt\nEndereço Eletrónico: dca@uc.pt\neDelivery Gateway (URL): https://www.acingov.pt\nFunção da Organização: Adquirente\nNorma jurídica da Entidade Adjudicante: Organismo de direito público\nÁrea de atividade da Autoridade Adjudicante: Serviços públicos das administrações públicas\n\n2 - JORNAL OFICIAL DA UNIÃO EUROPEIA\nO procedimento a que este anúncio diz respeito também é publicitado no Jornal Oficial da União Europeia? Não\n\n3 - AVISO\nModelo de Anúncio: Concurso público\nData de Envio do Anúncio: 17-10-2025\n\n5 - PROCESSO\nTipo de Procedimento: Concurso público\nPreço base do procedimento: Sim\nValor do preço base do procedimento: 219.000,00 EUR\nProcedimento com lotes? Não\n\n6 - OBJETO DO CONTRATO\nNúmero de referência interna: 25A00048\nDesignação do contrato: 25A00048 - Aquisição de alocação de equipamentos multifuncionais de impressão, incluindo os serviços de impressão, cópia e digitalização, bem como a respetiva manutenção e fornecimento de consumíveis, às Unidades Orgânicas (UO), Unidades de Extensão Cultural e de Apoio à Formação (UECAF's) e Serviços da Universidade de Coimbra (UC).\nDescrição: 25A00048 - Aquisição de alocação de equipamentos multifuncionais de impressão, incluindo os serviços de impressão, cópia e digitalização, bem como a respetiva manutenção e fornecimento de consumíveis, às Unidades Orgânicas (UO), Unidades de Extensão Cultural e de Apoio à Formação (UECAF's) e Serviços da Universidade de Coimbra (UC).\nTipo de Contrato Principal: Aquisição de Serviços\nTipo de Contrato: Aquisição de Serviços\nClassificação CPV (Vocabulário Comum para os Contratos Públicos)\nObjeto principal\nVocabulário Principal: 79810000\nPreço base s/IVA: 219.000,00 EUR\n\n7 - INDICAÇÕES ADICIONAIS\nO contrato envolve aquisição conjunta (satisfação de várias entidades)? Não\nO contrato é adjudicado por uma central de compras? Não\n\n8 - TÉCNICAS\nO concurso destina-se à celebração de um acordo-quadro? Inexistência de acordo-quadro\nÉ utilizado um leilão eletrónico? Não\nÉ adotada uma fase de negociação? Não\nSistema de Aquisição Dinâmico: Inexistência de sistema de aquisição dinâmico\n\n9 - LOCAL DA EXECUÇÃO DO CONTRATO\nLOCAL DA EXECUÇÃO DO CONTRATO (PROCEDIMENTO)\nPaís: Portugal\nNUT III: PT16E\nLocalidade: União das Freguesias de Coimbra (Sé Nova, Santa Cruz, Almedina e São Bartolomeu)\nDistrito: Coimbra\nConcelho: Coimbra\nFreguesia: União das Freguesias de Coimbra (Sé Nova, Santa Cruz, Almedina e São Bartolomeu)\n\n10 - PRAZO DE EXECUÇÃO DO CONTRATO\nPrazo de execução do contrato: 6 MESES\nPrevisão de renovações: Não\n\n11 - FUNDOS EU\nTêm fundos EU? Não\n\n12 - DOCUMENTOS DE HABILITAÇÃO\nHabilitação para o exercício da atividade profissional: Não\n\n13 - CONDIÇÕES DE APRESENTAÇÃO\nPlataforma eletrónica utilizada pela entidade adjudicante: ACIN\nURL para Apresentação: https://www.acingov.pt\nAdmissibilidade da apresentação de propostas variantes: Não autorizado\nPrazo para apresentação das propostas: 23-10-2025 23:59\nPrazo durante o qual os concorrentes são obrigados a manter as respetivas propostas: 66 dias a contar do termo do prazo para a apresentação das propostas\nIndicação de Subcontratação na Proposta: Inexistência de indicação de subcontratação\n\n14 - PRESTAÇÃO DE CAUÇÃO\nPrestação de caução: Não\n\n15 - FORNECIMENTO DAS PEÇAS DO CONCURSO, APRESENTAÇÃO DE PEDIDOS DE PARTICIPAÇÃO E APRESENTAÇÃO DAS PROPOSTAS\nLink para acesso às peças do concurso (URL): https://www.acingov.pt/acingovprod/2/zonaPublica/zona_publica_c/donwloadProcedurePiece/OTg4Mzkx\n\n20 - OUTROS REQUISITOS\nInformação sobre contratos reservados. Aplica-se a contratos reservados (54º-A)? Não\n\n21 - CRITÉRIO DE ADJUDICAÇÃO\nMultifator: Não\nMonofator:\nNome: Preço\n\n24 - CONDIÇÕES DO CONTRATO\nFaturação Eletrónica: Necessário\nObrigação de Subcontratação:\nCódigo da Obrigação de Subcontratação: Não é aplicável nenhuma obrigação de subcontratação.\n\n25 - COMPRA PÚBLICA ESTRATÉGICA\nCompra Pública Estratégica: Inexistência de contratação pública estratégica\n\n26 - INFORMAÇÕES ADICIONAIS\nContrato adequado para PME: Sim\nCobertura ACP (Acordo dos Contratos Públicos da Organização Mundial do Comércio): Não\n\n27 - IDENTIFICAÇÃO E CONTACTOS DO ÓRGÃO DE RECURSOS ADMINISTRATIVOS\nDesignação: Reitor da Universidade de Coimbra\nEndereço: Paço das Escolas\nCódigo postal: 3004-531\nLocalidade: Coimbra\nTelefone: 239859810\nFax: 239859810\nEndereço eletrónico: gbreitor@uc.pt\n\n28 - IDENTIFICAÇÃO DO(S) AUTOR(ES) DE ANÚNCIO\nNome: Amílcar Celta Falcão Ramos Ferreira\nCargo: Reitor da Universidade de Coimbra\n419669753",
    "nipc": "501617582",
    "distrito": "Coimbra",
    "concelho": "Coimbra",
    "freguesia": "União das Freguesias de Coimbra (Sé Nova, Santa Cruz, Almedina e São Bartolomeu)",
    "site": "www.uc.pt",
    "email": "dca@uc.pt",
    "designacao_contrato": "25A00048 - Aquisição de alocação de equipamentos multifuncionais de impressão, incluindo os serviços de impressão, cópia e digitalização, bem como a respetiva manutenção e fornecimento de consumíveis, às Unidades Orgânicas (UO), Unidades de Extensão Cultural e de Apoio à Formação (UECAF's) e Serviços da Universidade de Coimbra (UC).",
    "descricao": "25A00048 - Aquisição de alocação de equipamentos multifuncionais de impressão, incluindo os serviços de impressão, cópia e digitalização, bem como a respetiva manutenção e fornecimento de consumíveis, às Unidades Orgânicas (UO), Unidades de Extensão Cultural e de Apoio à Formação (UECAF's) e Serviços da Universidade de Coimbra (UC).",
    "preco_base": "219.000,00 EUR",
    "prazo_execucao": "6 MESES",
    "prazo_apresentacao_propostas": "23-10-2025 23:59",
    "fundos_eu": "Não",
    "plataforma_eletronica": "ACIN",
    "url_procedimento": "https://www.acingov.pt",
    "autor_nome": "Amílcar Celta Falcão Ramos Ferreira",
    "autor_cargo": "Reitor da Universidade de Coimbra"
  },
  {
    "numero_procedimento": "N/A",
    "entidade": "AnÃºncio de procedimento  n.Âº 27431/2025  -  DiÃ¡rio da RepÃºblica n.Âº 201/2025, SÃ©rie II de 2025-10-17",
    "link": "https://diariodarepublica.pt/dr/detalhe/contrato-publico/27431-940618850"
  },
  {
    "numero_procedimento": "N/A",
    "entidade": "Serviços Municipalizados de Viseu",
    "link": "https://diariodarepublica.pt/dr/detalhe/contrato-publico/27398-940641011",
    "detalhes_completos": "1 - IDENTIFICAÇÃO E CONTACTOS DA ENTIDADE ADJUDICANTE\nDesignação da entidade adjudicante: Serviços Municipalizados de Viseu\nNIPC: 680020063\nEndereço: Rua Conselheiro Afonso de Melo\nCódigo postal: 3510-024\nLocalidade: Viseu\nPaís: Portugal\nNUT III: PT16G\nDistrito: Viseu\nConcelho: Viseu\nFreguesia: Freguesia de Viseu\nTelefone: 232470670\nFax: 232424080\nEndereço da Entidade (URL): www.smasviseu.pt\nEndereço Eletrónico: geral@smasviseu.pt\neDelivery Gateway (URL): https://www.acingov.pt\nFunção da Organização: Adquirente\nNorma jurídica da Entidade Adjudicante: Autoridade local\nÁrea de atividade da Autoridade Adjudicante: Serviços públicos das administrações públicas\n\n2 - JORNAL OFICIAL DA UNIÃO EUROPEIA\nO procedimento a que este anúncio diz respeito também é publicitado no Jornal Oficial da União Europeia? Não\n\n3 - AVISO\nModelo de Anúncio: Concurso público\nData de Envio do Anúncio: 17-10-2025\n\n5 - PROCESSO\nTipo de Procedimento: Concurso público\nPreço base do procedimento: Sim\nValor do preço base do procedimento: 644.355,92 EUR\nProcedimento com lotes? Não\n\n6 - OBJETO DO CONTRATO\nNúmero de referência interna: E1213\nDesignação do contrato: Remodelação do Saneamento Básico na Av. Manuel Loureiro e Transversais em Pascoal - 3º Procedimento\nDescrição: Remodelação do Saneamento Básico na Av. Manuel Loureiro e Transversais em Pascoal - 3º Procedimento\nTipo de Contrato Principal: Empreitada de Obras Públicas\nTipo de Contrato: Empreitada de Obras Públicas\nClassificação CPV (Vocabulário Comum para os Contratos Públicos)\nObjeto principal\nVocabulário Principal: 45232460\nPreço base s/IVA: 644.355,92 EUR\n\n7 - INDICAÇÕES ADICIONAIS\nO contrato envolve aquisição conjunta (satisfação de várias entidades)? Não\nO contrato é adjudicado por uma central de compras? Não\n\n8 - TÉCNICAS\nO concurso destina-se à celebração de um acordo-quadro? Inexistência de acordo-quadro\nÉ utilizado um leilão eletrónico? Não\nÉ adotada uma fase de negociação? Não\nSistema de Aquisição Dinâmico: Inexistência de sistema de aquisição dinâmico\n\n9 - LOCAL DA EXECUÇÃO DO CONTRATO\nLOCAL DA EXECUÇÃO DO CONTRATO (PROCEDIMENTO)\nPaís: Portugal\nNUT III: PT16G\nLocalidade: Freguesia de Abraveses\nDistrito: Viseu\nConcelho: Viseu\nFreguesia: Freguesia de Abraveses\n\n10 - PRAZO DE EXECUÇÃO DO CONTRATO\nPrazo de execução do contrato: 365 DIAS\nPrevisão de renovações: Não\n\n11 - FUNDOS EU\nTêm fundos EU? Não\n\n12 - DOCUMENTOS DE HABILITAÇÃO\nHabilitação para o exercício da atividade profissional: Sim\nTipo: Alvará\nDescrição: O certificado do alvará de construção previsto deve conter:\nA 6ª subcategoria da 2ª categoria, sendo que a classe da 6ª subcategoria da 2ª categoria tem de ser de classe que cubra o valor global da proposta e integrar-se na categoria em que o tipo da obra se enquadra.\n\n13 - CONDIÇÕES DE APRESENTAÇÃO\nPlataforma eletrónica utilizada pela entidade adjudicante: ACIN\nURL para Apresentação: https://www.acingov.pt\nAdmissibilidade da apresentação de propostas variantes: Não autorizado\nPrazo para apresentação das propostas: 16-11-2025 23:59\nPrazo durante o qual os concorrentes são obrigados a manter as respetivas propostas: 120 dias a contar do termo do prazo para a apresentação das propostas\nIndicação de Subcontratação na Proposta: Inexistência de indicação de subcontratação\n\n14 - PRESTAÇÃO DE CAUÇÃO\nPrestação de caução: Sim\nPercentagem: 5%\nDescrição da Garantia Exigida: O valor da caução é de 5.00% do preço contratual.\n\n15 - FORNECIMENTO DAS PEÇAS DO CONCURSO, APRESENTAÇÃO DE PEDIDOS DE PARTICIPAÇÃO E APRESENTAÇÃO DAS PROPOSTAS\nLink para acesso às peças do concurso (URL): https://www.acingov.pt/acingovprod/2/zonaPublica/zona_publica_c/donwloadProcedurePiece/OTg2MTQy\n\n20 - OUTROS REQUISITOS\nInformação sobre contratos reservados. Aplica-se a contratos reservados (54º-A)? Não\n\n21 - CRITÉRIO DE ADJUDICAÇÃO\nMultifator: Não\nMonofator:\nNome: Preço\n\n24 - CONDIÇÕES DO CONTRATO\nFaturação Eletrónica: Permitido\nObrigação de Subcontratação:\nCódigo da Obrigação de Subcontratação: Não é aplicável nenhuma obrigação de subcontratação.\n\n25 - COMPRA PÚBLICA ESTRATÉGICA\nCompra Pública Estratégica: Inexistência de contratação pública estratégica\n\n26 - INFORMAÇÕES ADICIONAIS\nContrato adequado para PME: Sim\nCobertura ACP (Acordo dos Contratos Públicos da Organização Mundial do Comércio): Não\n\n27 - IDENTIFICAÇÃO E CONTACTOS DO ÓRGÃO DE RECURSOS ADMINISTRATIVOS\nDesignação: Município de Viseu\nEndereço: Praça da República S/N\nCódigo postal: 3514-501\nLocalidade: Viseu\nTelefone: 00351232427427\nFax: 00351232423112\nEndereço eletrónico: geral@cmviseu.pt\nPrazo de interposição do recurso: 5 dias\n\n28 - IDENTIFICAÇÃO DO(S) AUTOR(ES) DE ANÚNCIO\nNome: João Paulo Lopes Gouveia\nCargo: Vogal do Conselho de Administração\n419648741",
    "nipc": "680020063",
    "distrito": "Viseu",
    "concelho": "Viseu",
    "freguesia": "Freguesia de Viseu",
    "site": "www.smasviseu.pt",
    "email": "geral@smasviseu.pt",
    "designacao_contrato": "Remodelação do Saneamento Básico na Av. Manuel Loureiro e Transversais em Pascoal - 3º Procedimento",
    "descricao": "Remodelação do Saneamento Básico na Av. Manuel Loureiro e Transversais em Pascoal - 3º Procedimento",
    "preco_base": "644.355,92 EUR",
    "prazo_execucao": "365 DIAS",
    "prazo_apresentacao_propostas": "16-11-2025 23:59",
    "fundos_eu": "Não",
    "plataforma_eletronica": "ACIN",
    "url_procedimento": "https://www.acingov.pt",
    "autor_nome": "João Paulo Lopes Gouveia",
    "autor_cargo": "Vogal do Conselho de Administração"
  },
  {
    "numero_procedimento": "N/A",
    "entidade": "AnÃºncio de procedimento  n.Âº 27399/2025  -  DiÃ¡rio da RepÃºblica n.Âº 201/2025, SÃ©rie II de 2025-10-17",
    "link": "https://diariodarepublica.pt/dr/detalhe/contrato-publico/27399-940641012"
  },
  {
    "numero_procedimento": "N/A",
    "entidade": "AnÃºncio de procedimento  n.Âº 27401/2025  -  DiÃ¡rio da RepÃºblica n.Âº 201/2025, SÃ©rie II de 2025-10-17",
    "link": "https://diariodarepublica.pt/dr/detalhe/contrato-publico/27401-940641013"
  },
  {
    "numero_procedimento": "N/A",
    "entidade": "Estado-Maior-General das Forças Armadas (EMGFA)",
    "link": "https://diariodarepublica.pt/dr/detalhe/contrato-publico/27403-940641014",
    "detalhes_completos": "1 - IDENTIFICAÇÃO E CONTACTOS DA ENTIDADE ADJUDICANTE\nDesignação da entidade adjudicante: Estado-Maior-General das Forças Armadas (EMGFA)\nNIPC: 600010180\nServiço/Órgão/Pessoa de contacto: DepComp/DF/HFAR\nEndereço: AVENIDA ILHA DA MADEIRA\nCódigo postal: 1449-004\nLocalidade: Lisboa\nPaís: Portugal\nNUT III: PT170\nDistrito: Lisboa\nConcelho: Lisboa\nFreguesia: Freguesia de Lumiar\nTelefone: 2130100001\nEndereço da Entidade (URL): www.emgfa.pt\nEndereço Eletrónico: DIRFIN_Contratos@emgfa.pt\neDelivery Gateway (URL): https://www.acingov.pt\nFunção da Organização: Adquirente\nNorma jurídica da Entidade Adjudicante: Organismo de direito público\nÁrea de atividade da Autoridade Adjudicante: Serviços públicos das administrações públicas\n\n2 - JORNAL OFICIAL DA UNIÃO EUROPEIA\nO procedimento a que este anúncio diz respeito também é publicitado no Jornal Oficial da União Europeia? Não\n\n3 - AVISO\nModelo de Anúncio: Concurso público\nData de Envio do Anúncio: 17-10-2025\n\n5 - PROCESSO\nTipo de Procedimento: Concurso público\nPreço base do procedimento: Sim\nValor do preço base do procedimento: 18.909,00 EUR\nProcedimento com lotes? Sim\nNº Máx. de Lotes Autorizado: 4\nNúmero máximo de lotes que podem ser adjudicados a um concorrente: 4\n\n6 - OBJETO DO CONTRATO\nNúmero de referência interna: HFAR-PL 2025007927\nDesignação do contrato: 2025007927/HFAR-Aquisição de algalias, bisturis, seringas, agulhas e outros dispositivos médicos\nDescrição: 2025007927/HFAR-Aquisição de algalias, bisturis, seringas, agulhas e outros dispositivos médicos\nTipo de Contrato Principal: Aquisição de Bens Móveis\nTipo de Contrato: Aquisição de Bens Móveis\nClassificação CPV (Vocabulário Comum para os Contratos Públicos)\nObjeto principal\nVocabulário Principal: 33140000\nPreço base s/IVA: 18.909,00 EUR\nLotes: \nNº: LOT-0001\nDescrição do Lote: ALGALIAS E SONDAS\nPreço base s/IVA: 6.289,00 EUR\nClassificação CPV (Vocabulário Comum para os Contratos Públicos)\nObjeto principal\nVocabulário Principal: 33140000\nNº: LOT-0002\nDescrição do Lote: BIOTOMO, BISTURIS E CURETA\nPreço base s/IVA: 913,00 EUR\nClassificação CPV (Vocabulário Comum para os Contratos Públicos)\nObjeto principal\nVocabulário Principal: 33140000\nNº: LOT-0003\nDescrição do Lote: ACESSORIOS ELECTROBISTURI\nPreço base s/IVA: 2.200,00 EUR\nClassificação CPV (Vocabulário Comum para os Contratos Públicos)\nObjeto principal\nVocabulário Principal: 33140000\nNº: LOT-0004\nDescrição do Lote: SERINGAS E AGULHAS\nPreço base s/IVA: 9.507,00 EUR\nClassificação CPV (Vocabulário Comum para os Contratos Públicos)\nObjeto principal\nVocabulário Principal: 33140000\n\n7 - INDICAÇÕES ADICIONAIS\nO contrato envolve aquisição conjunta (satisfação de várias entidades)? Não\nO contrato é adjudicado por uma central de compras? Não\n\n8 - TÉCNICAS\nO concurso destina-se à celebração de um acordo-quadro? Inexistência de acordo-quadro\nÉ utilizado um leilão eletrónico? Não\nÉ adotada uma fase de negociação? Não\nSistema de Aquisição Dinâmico: Inexistência de sistema de aquisição dinâmico\n\n9 - LOCAL DA EXECUÇÃO DO CONTRATO\nLOCAL DA EXECUÇÃO DO CONTRATO (PROCEDIMENTO)\nPaís: Portugal\nNUT III: PT170\nLocalidade: Lumiar\nDistrito: Lisboa\nConcelho: Todos\nFreguesia: Todas\nLOCAL DA EXECUÇÃO DO CONTRATO (LOTE)\nIdentificador do Lote: LOT-0001; LOT-0002; LOT-0003; LOT-0004\nPaís: Portugal\nNUT III: PT170\nLocalidade: Lumiar\nDistrito: Lisboa\nConcelho: Lisboa\nFreguesia: Todas\n\n10 - PRAZO DE EXECUÇÃO DO CONTRATO\nIdentificador do Lote: LOT-0001; LOT-0002; LOT-0003; LOT-0004\nPrazo de execução do contrato: 15 DIAS\nPrevisão de renovações: Não\n\n11 - FUNDOS EU\nIdentificador do Lote: LOT-0001; LOT-0002; LOT-0003; LOT-0004\nTêm fundos EU? Não\n\n12 - DOCUMENTOS DE HABILITAÇÃO\nHabilitação para o exercício da atividade profissional: Não\n\n13 - CONDIÇÕES DE APRESENTAÇÃO\nPlataforma eletrónica utilizada pela entidade adjudicante: ACIN\nURL para Apresentação: https://www.acingov.pt\nAdmissibilidade da apresentação de propostas variantes: Não autorizado\nPrazo para apresentação das propostas: 27-10-2025 23:59\nPrazo durante o qual os concorrentes são obrigados a manter as respetivas propostas: 66 dias a contar do termo do prazo para a apresentação das propostas\nIndicação de Subcontratação na Proposta: Inexistência de indicação de subcontratação\n\n14 - PRESTAÇÃO DE CAUÇÃO\nPrestação de caução: Não\n\n15 - FORNECIMENTO DAS PEÇAS DO CONCURSO, APRESENTAÇÃO DE PEDIDOS DE PARTICIPAÇÃO E APRESENTAÇÃO DAS PROPOSTAS\nLink para acesso às peças do concurso (URL): https://www.acingov.pt/acingovprod/2/zonaPublica/zona_publica_c/donwloadProcedurePiece/OTg4Mjk0\n\n20 - OUTROS REQUISITOS\nIdentificador do Lote: LOT-0001; LOT-0002; LOT-0003; LOT-0004\nInformação sobre contratos reservados. Aplica-se a contratos reservados (54º-A)? Não\n\n21 - CRITÉRIO DE ADJUDICAÇÃO\nO Critério de adjudicação é diferenciado por lote? Não\nMultifator: Não\nMonofator:\nNome: Preço\n\n24 - CONDIÇÕES DO CONTRATO\nIdentificador do Lote: LOT-0001; LOT-0002; LOT-0003; LOT-0004\nFaturação Eletrónica: Necessário\nObrigação de Subcontratação:\nCódigo da Obrigação de Subcontratação: Não é aplicável nenhuma obrigação de subcontratação.\n\n25 - COMPRA PÚBLICA ESTRATÉGICA\nCompra Pública Estratégica: Inexistência de contratação pública estratégica\n\n26 - INFORMAÇÕES ADICIONAIS\nIdentificador do Lote: LOT-0001; LOT-0002; LOT-0003; LOT-0004\nContrato adequado para PME: Sim\nCobertura ACP (Acordo dos Contratos Públicos da Organização Mundial do Comércio): Não\n\n27 - IDENTIFICAÇÃO E CONTACTOS DO ÓRGÃO DE RECURSOS ADMINISTRATIVOS\nDesignação: EMGFA\nEndereço: Av. Ilha da Madeira N.º 1, 1449-004 Lisboa\nCódigo postal: 1449-004\nLocalidade: Lisboa\nTelefone: 213043000\nFax: 213043000\nEndereço eletrónico: emgfa@emgfa.pt\n\n28 - IDENTIFICAÇÃO DO(S) AUTOR(ES) DE ANÚNCIO\nNome: José Carlos Candeias Pinheiro Monge\nCargo: Diretor HFAR\n419668732",
    "nipc": "600010180",
    "distrito": "Lisboa",
    "concelho": "Lisboa",
    "freguesia": "Freguesia de Lumiar",
    "site": "www.emgfa.pt",
    "email": "DIRFIN_Contratos@emgfa.pt",
    "designacao_contrato": "2025007927/HFAR-Aquisição de algalias, bisturis, seringas, agulhas e outros dispositivos médicos",
    "descricao": "2025007927/HFAR-Aquisição de algalias, bisturis, seringas, agulhas e outros dispositivos médicos",
    "preco_base": "18.909,00 EUR",
    "prazo_execucao": "15 DIAS",
    "prazo_apresentacao_propostas": "27-10-2025 23:59",
    "fundos_eu": "Não",
    "plataforma_eletronica": "ACIN",
    "url_procedimento": "https://www.acingov.pt",
    "autor_nome": "José Carlos Candeias Pinheiro Monge",
    "autor_cargo": "Diretor HFAR"
  },
  {
    "numero_procedimento": "N/A",
    "entidade": "AnÃºncio de procedimento  n.Âº 27407/2025  -  DiÃ¡rio da RepÃºblica n.Âº 201/2025, SÃ©rie II de 2025-10-17",
    "link": "https://diariodarepublica.pt/dr/detalhe/contrato-publico/27407-940641015"
  },
  {
    "numero_procedimento": "N/A",
    "entidade": "Serviços Municipalizados de Água e Saneamento de Almada",
    "link": "https://diariodarepublica.pt/dr/detalhe/contrato-publico/27410-940641016",
    "detalhes_completos": "1 - IDENTIFICAÇÃO E CONTACTOS DA ENTIDADE ADJUDICANTE\nDesignação da entidade adjudicante: Serviços Municipalizados de Água e Saneamento de Almada\nNIPC: 680017763\nEndereço: Praceta Ricardo Jorge, n.º2 Pragal\nCódigo postal: 2804-543\nLocalidade: Setúbal\nPaís: Portugal\nNUT III: PT170\nDistrito: Setúbal\nConcelho: Almada\nFreguesia: Todas\nTelefone: 212726000\nFax: 212721629\nEndereço da Entidade (URL): www.smasalmada.pt\nEndereço Eletrónico: geral@smasalmada.pt\neDelivery Gateway (URL): https://community.vortal.biz/public/\nFunção da Organização: Adquirente\nNorma jurídica da Entidade Adjudicante: Organismo de direito público, controlado por uma autoridade local\nÁrea de atividade da Entidade Adjudicante: Atividades relacionadas com a água\n\n2 - JORNAL OFICIAL DA UNIÃO EUROPEIA\nO procedimento a que este anúncio diz respeito também é publicitado no Jornal Oficial da União Europeia? Não\n\n3 - AVISO\nModelo de Anúncio: Concurso público\nData de Envio do Anúncio: 17-10-2025\n\n5 - PROCESSO\nTipo de Procedimento: Concurso público\nPreço base do procedimento: Sim\nValor do preço base do procedimento: 70.000,00 EUR\nProcedimento com lotes? Não\n\n6 - OBJETO DO CONTRATO\nNúmero de referência interna: CP 107/2025\nDesignação do contrato: Aquisição de material elétrico para os SMAS de Almada\nDescrição: Aquisição de material elétrico para os SMAS de Almada\nTipo de Contrato Principal: Aquisição de Bens Móveis\nTipo de Contrato: Aquisição de Bens Móveis\nClassificação CPV (Vocabulário Comum para os Contratos Públicos)\nObjeto principal\nVocabulário Principal: 31681410\nPreço base s/IVA: 70.000,00 EUR\n\n7 - INDICAÇÕES ADICIONAIS\nO contrato envolve aquisição conjunta (satisfação de várias entidades)? Não\nO contrato é adjudicado por uma central de compras? Não\n\n8 - TÉCNICAS\nO concurso destina-se à celebração de um acordo-quadro? Inexistência de acordo-quadro\nÉ utilizado um leilão eletrónico? Não\nÉ adotada uma fase de negociação? Não\nSistema de Aquisição Dinâmico: Inexistência de sistema de aquisição dinâmico\n\n9 - LOCAL DA EXECUÇÃO DO CONTRATO\nLOCAL DA EXECUÇÃO DO CONTRATO (PROCEDIMENTO)\nPaís: Portugal\nNUT III: PT170\nLocalidade: Almada\nDistrito: Setúbal\nConcelho: Almada\nFreguesia: União das Freguesias de Almada, Cova da Piedade, Pragal e Cacilhas\n\n10 - PRAZO DE EXECUÇÃO DO CONTRATO\nPrazo de execução do contrato: 12 MESES\nPrevisão de renovações: Não\n\n11 - FUNDOS EU\nTêm fundos EU? Não\n\n12 - DOCUMENTOS DE HABILITAÇÃO\nHabilitação para o exercício da atividade profissional: Não\n\n13 - CONDIÇÕES DE APRESENTAÇÃO\nPlataforma eletrónica utilizada pela entidade adjudicante: VORTAL\nURL para Apresentação: https://community.vortal.biz/public/\nAdmissibilidade da apresentação de propostas variantes: Não autorizado\nPrazo para apresentação das propostas: 06-11-2025 23:59\nPrazo durante o qual os concorrentes são obrigados a manter as respetivas propostas: 180 dias a contar do termo do prazo para a apresentação das propostas\nIndicação de Subcontratação na Proposta: Inexistência de indicação de subcontratação\n\n14 - PRESTAÇÃO DE CAUÇÃO\nPrestação de caução: Não\n\n15 - FORNECIMENTO DAS PEÇAS DO CONCURSO, APRESENTAÇÃO DE PEDIDOS DE PARTICIPAÇÃO E APRESENTAÇÃO DAS PROPOSTAS\nLink para acesso às peças do concurso (URL): https://community.vortal.biz/Public/public-tender-documents/NWtZdk1BUDltUkRMR2pacDJ6YkVmZ0RLa0RFdkU4NFJYUDh0QlN5ZVMwakZyRTBFZU5CLzhnajlYenNUVlRYRUxBenY3TEtMWTliRnVnRmFaVThxMlE9PXckdG0m\n\n20 - OUTROS REQUISITOS\nInformação sobre contratos reservados. Aplica-se a contratos reservados (54º-A)? Não\n\n21 - CRITÉRIO DE ADJUDICAÇÃO\nMultifator: Não\nMonofator:\nNome: Preço\n\n24 - CONDIÇÕES DO CONTRATO\nFaturação Eletrónica: Permitido\nObrigação de Subcontratação:\nCódigo da Obrigação de Subcontratação: Não é aplicável nenhuma obrigação de subcontratação.\n\n25 - COMPRA PÚBLICA ESTRATÉGICA\nCompra Pública Estratégica: Inexistência de contratação pública estratégica\n\n26 - INFORMAÇÕES ADICIONAIS\nContrato adequado para PME: Sim\nCobertura ACP (Acordo dos Contratos Públicos da Organização Mundial do Comércio): Não\n\n27 - IDENTIFICAÇÃO E CONTACTOS DO ÓRGÃO DE RECURSOS ADMINISTRATIVOS\nDesignação: Município de Almada - Câmara Municipal de Almada - Presidência\nEndereço: Câmara Municipal de Almada - Largo Luís de Camões\nCódigo postal: 2800-158\nLocalidade: Almada\nTelefone: +351 212724534\nFax: +351 212724555\nEndereço eletrónico: gab.presidencia@cma.m-almada.pt\n\n28 - IDENTIFICAÇÃO DO(S) AUTOR(ES) DE ANÚNCIO\nNome: José Pedro Ribeiro\nCargo: Presidente do Conselho de Administração\n419667096",
    "nipc": "680017763",
    "distrito": "Setúbal",
    "concelho": "Almada",
    "freguesia": "Todas",
    "site": "www.smasalmada.pt",
    "email": "geral@smasalmada.pt",
    "designacao_contrato": "Aquisição de material elétrico para os SMAS de Almada",
    "descricao": "Aquisição de material elétrico para os SMAS de Almada",
    "preco_base": "70.000,00 EUR",
    "prazo_execucao": "12 MESES",
    "prazo_apresentacao_propostas": "06-11-2025 23:59",
    "fundos_eu": "Não",
    "plataforma_eletronica": "VORTAL",
    "url_procedimento": "https://community.vortal.biz/public/",
    "autor_nome": "José Pedro Ribeiro",
    "autor_cargo": "Presidente do Conselho de Administração"
  },
  {
    "numero_procedimento": "N/A",
    "entidade": "AnÃºncio de procedimento  n.Âº 27413/2025  -  DiÃ¡rio da RepÃºblica n.Âº 201/2025, SÃ©rie II de 2025-10-17",
    "link": "https://diariodarepublica.pt/dr/detalhe/contrato-publico/27413-940641017"
  },
  {
    "numero_procedimento": "N/A",
    "entidade": "AnÃºncio de procedimento  n.Âº 27418/2025  -  DiÃ¡rio da RepÃºblica n.Âº 201/2025, SÃ©rie II de 2025-10-17",
    "link": "https://diariodarepublica.pt/dr/detalhe/contrato-publico/27418-940641035"
  },
  {
    "numero_procedimento": "N/A",
    "entidade": "AnÃºncio de procedimento  n.Âº 27420/2025  -  DiÃ¡rio da RepÃºblica n.Âº 201/2025, SÃ©rie II de 2025-10-17",
    "link": "https://diariodarepublica.pt/dr/detalhe/contrato-publico/27420-940641036"
  },
  {
    "numero_procedimento": "N/A",
    "entidade": "AnÃºncio de procedimento  n.Âº 27424/2025  -  DiÃ¡rio da RepÃºblica n.Âº 201/2025, SÃ©rie II de 2025-10-17",
    "link": "https://diariodarepublica.pt/dr/detalhe/contrato-publico/27424-940641043"
  },
  {
    "numero_procedimento": "N/A",
    "entidade": "AnÃºncio de procedimento  n.Âº 27425/2025  -  DiÃ¡rio da RepÃºblica n.Âº 201/2025, SÃ©rie II de 2025-10-17",
    "link": "https://diariodarepublica.pt/dr/detalhe/contrato-publico/27425-940641044"
  },
  {
    "numero_procedimento": "N/A",
    "entidade": "AnÃºncio de procedimento  n.Âº 27426/2025  -  DiÃ¡rio da RepÃºblica n.Âº 201/2025, SÃ©rie II de 2025-10-17",
    "link": "https://diariodarepublica.pt/dr/detalhe/contrato-publico/27426-940641045"
  },
  {
    "numero_procedimento": "N/A",
    "entidade": "AnÃºncio de procedimento  n.Âº 27427/2025  -  DiÃ¡rio da RepÃºblica n.Âº 201/2025, SÃ©rie II de 2025-10-17",
    "link": "https://diariodarepublica.pt/dr/detalhe/contrato-publico/27427-940641046"
  },
  {
    "numero_procedimento": "N/A",
    "entidade": "Agrupamento de Escolas Dr. Jorge Augusto Correia, Tavira",
    "link": "https://diariodarepublica.pt/dr/detalhe/contrato-publico/27428-940641047",
    "detalhes_completos": "1 - IDENTIFICAÇÃO E CONTACTOS DA ENTIDADE ADJUDICANTE\nDesignação da entidade adjudicante: Agrupamento de Escolas Dr. Jorge Augusto Correia, Tavira\nNIPC: 600078442\nServiço/Órgão/Pessoa de contacto: Agrupamento de Escolas Dr. Jorge Augusto Correia - Raúl Pina\nEndereço: Rua Luís de Camões\nCódigo postal: 8800-415\nLocalidade: Tavira\nPaís: Portugal\nNUT III: PT150\nDistrito: Faro\nConcelho: Tavira\nFreguesia: União das Freguesias de Tavira (Santa Maria e Santiago)\nTelefone: 281320440\nEndereço da Entidade (URL): www.aejactavira.pt\nEndereço Eletrónico: director@aejactavira.pt\neDelivery Gateway (URL): https://www.acingov.pt\nFunção da Organização: Beneficiário efetivo\nSubfunção da Organização: Líder do grupo\nNorma jurídica da Entidade Adjudicante: Organismo de direito público\nÁrea de atividade da Autoridade Adjudicante: Educação\n\n2 - JORNAL OFICIAL DA UNIÃO EUROPEIA\nO procedimento a que este anúncio diz respeito também é publicitado no Jornal Oficial da União Europeia? Sim\n\n3 - AVISO\nModelo de Anúncio: Concurso público\nData de Envio do Anúncio: 15-10-2025\n\n5 - PROCESSO\nTipo de Procedimento: Concurso público\nPreço base do procedimento: Sim\nValor do preço base do procedimento: 398.400,00 EUR\nProcedimento com lotes? Sim\nNº Máx. de Lotes Autorizado: 10\nNúmero máximo de lotes que podem ser adjudicados a um concorrente: 10\n\n6 - OBJETO DO CONTRATO\nNúmero de referência interna: CTE03 - AEJACTAVIRA - 2025\nDesignação do contrato: Aquisição de equipamentos destinados à prática educativa e infraestrutura tecnológica no âmbito do Centro Tecnológico Especializado de Informática\nDescrição: Aquisição de equipamentos destinados à prática educativa e infraestrutura tecnológica no âmbito do Centro Tecnológico Especializado de Informática\nOpções: Não\nTipo de Contrato Principal: Aquisição de Bens Móveis\nTipo de Contrato: Aquisição de Bens Móveis\nClassificação CPV (Vocabulário Comum para os Contratos Públicos)\nObjeto principal\nVocabulário Principal: 30200000\nPreço base s/IVA: 355.800,00 EUR\nObjeto Complementar\nVocabulário Principal: 32300000\nPreço base s/IVA: 42.600,00 EUR\nLotes: \nNº: LOT-0001\nDescrição do Lote: Workstations Móveis, Fixas e Monitores\nPreço base s/IVA: 214.400,00 EUR\nClassificação CPV (Vocabulário Comum para os Contratos Públicos)\nObjeto principal\nVocabulário Principal: 30200000\nNº: LOT-0002\nDescrição do Lote: Computadores Portáteis\nPreço base s/IVA: 31.900,00 EUR\nClassificação CPV (Vocabulário Comum para os Contratos Públicos)\nObjeto principal\nVocabulário Principal: 30200000\nNº: LOT-0003\nDescrição do Lote: Servidores, Rede e Infraestrutura Passiva\nPreço base s/IVA: 11.800,00 EUR\nClassificação CPV (Vocabulário Comum para os Contratos Públicos)\nObjeto principal\nVocabulário Principal: 30200000\nNº: LOT-0004\nDescrição do Lote: Vídeoprojetores\nPreço base s/IVA: 11.500,00 EUR\nClassificação CPV (Vocabulário Comum para os Contratos Públicos)\nObjeto principal\nVocabulário Principal: 30200000\nNº: LOT-0005\nDescrição do Lote: Multimédia\nPreço base s/IVA: 16.900,00 EUR\nClassificação CPV (Vocabulário Comum para os Contratos Públicos)\nObjeto principal\nVocabulário Principal: 30200000\nNº: LOT-0006\nDescrição do Lote: Microcomputadores Integrados, Robótica e Ferramentas\nPreço base s/IVA: 9.400,00 EUR\nClassificação CPV (Vocabulário Comum para os Contratos Públicos)\nObjeto principal\nVocabulário Principal: 30200000\nNº: LOT-0007\nDescrição do Lote: Drones\nPreço base s/IVA: 42.600,00 EUR\nClassificação CPV (Vocabulário Comum para os Contratos Públicos)\nObjeto principal\nVocabulário Principal: 32300000\nNº: LOT-0008\nDescrição do Lote: Componentes para Montagem\nPreço base s/IVA: 1.500,00 EUR\nClassificação CPV (Vocabulário Comum para os Contratos Públicos)\nObjeto principal\nVocabulário Principal: 30200000\nNº: LOT-0009\nDescrição do Lote: Impressão 3D e consumíveis\nPreço base s/IVA: 8.400,00 EUR\nClassificação CPV (Vocabulário Comum para os Contratos Públicos)\nObjeto principal\nVocabulário Principal: 30200000\nNº: LOT-0010\nDescrição do Lote: Equipamentos e Software adaptado\nPreço base s/IVA: 50.000,00 EUR\nClassificação CPV (Vocabulário Comum para os Contratos Públicos)\nObjeto principal\nVocabulário Principal: 30200000\n\n7 - INDICAÇÕES ADICIONAIS\nO contrato envolve aquisição conjunta (satisfação de várias entidades)? Não\nO contrato é adjudicado por uma central de compras? Não\n\n8 - TÉCNICAS\nO concurso destina-se à celebração de um acordo-quadro? Inexistência de acordo-quadro\nÉ utilizado um leilão eletrónico? Não\nÉ adotada uma fase de negociação? Não\nSistema de Aquisição Dinâmico: Inexistência de sistema de aquisição dinâmico\n\n9 - LOCAL DA EXECUÇÃO DO CONTRATO\nLOCAL DA EXECUÇÃO DO CONTRATO (PROCEDIMENTO)\nPaís: Portugal\nNUT III: PT150\nLocalidade: Tavira\nDistrito: Faro\nConcelho: Tavira\nFreguesia: União das Freguesias de Tavira (Santa Maria e Santiago)\nLOCAL DA EXECUÇÃO DO CONTRATO (LOTE)\nIdentificador do Lote: LOT-0001; LOT-0002; LOT-0003; LOT-0004; LOT-0005; LOT-0006; LOT-0007; LOT-0008; LOT-0009; LOT-0010\nPaís: Portugal\nNUT III: PT150\nLocalidade: Tavira\nDistrito: Faro\nConcelho: Tavira\nFreguesia: União das Freguesias de Tavira (Santa Maria e Santiago)\n\n10 - PRAZO DE EXECUÇÃO DO CONTRATO\nIdentificador do Lote: LOT-0001; LOT-0002; LOT-0003; LOT-0004; LOT-0005; LOT-0006; LOT-0007; LOT-0008; LOT-0009; LOT-0010\nPrazo de execução do contrato: 60 DIAS\nPrevisão de renovações: Não\n\n11 - FUNDOS EU\nIdentificador do Lote: LOT-0001; LOT-0002; LOT-0003; LOT-0004; LOT-0005; LOT-0006; LOT-0007; LOT-0008; LOT-0009; LOT-0010\nTêm fundos EU? Sim\n\n12 - DOCUMENTOS DE HABILITAÇÃO\nHabilitação para o exercício da atividade profissional: Não\n\n13 - CONDIÇÕES DE APRESENTAÇÃO\nPlataforma eletrónica utilizada pela entidade adjudicante: ACIN\nURL para Apresentação: https://www.acingov.pt\nAdmissibilidade da apresentação de propostas variantes: Não autorizado\nPrazo para apresentação das propostas: 14-11-2025 17:00\nPrazo durante o qual os concorrentes são obrigados a manter as respetivas propostas: 66 dias a contar do termo do prazo para a apresentação das propostas\nApresentação de Catálogo Eletrónico: Não autorizado\nIndicação de Subcontratação na Proposta: A parte do contrato que o proponente tenciona subcontratar\n\n14 - PRESTAÇÃO DE CAUÇÃO\nPrestação de caução: Não\n\n15 - FORNECIMENTO DAS PEÇAS DO CONCURSO, APRESENTAÇÃO DE PEDIDOS DE PARTICIPAÇÃO E APRESENTAÇÃO DAS PROPOSTAS\nLink para acesso às peças do concurso (URL): https://www.acingov.pt/acingovprod/2/zonaPublica/zona_publica_c/donwloadProcedurePiece/OTg2NTc4\n\n20 - OUTROS REQUISITOS\nIdentificador do Lote: LOT-0001; LOT-0002; LOT-0003; LOT-0004; LOT-0005; LOT-0006; LOT-0007; LOT-0008; LOT-0009; LOT-0010\nInformação sobre contratos reservados. Aplica-se a contratos reservados (54º-A)? Não\n\n21 - CRITÉRIO DE ADJUDICAÇÃO\nO Critério de adjudicação é diferenciado por lote? Não\nMultifator: Não\nMonofator:\nNome: Preço\n\n24 - CONDIÇÕES DO CONTRATO\nIdentificador do Lote: LOT-0001; LOT-0002; LOT-0003; LOT-0004; LOT-0005; LOT-0006; LOT-0007; LOT-0008; LOT-0009; LOT-0010\nFaturação Eletrónica: Permitido\nObrigação de Subcontratação:\nCódigo da Obrigação de Subcontratação: Não é aplicável nenhuma obrigação de subcontratação.\n\n25 - COMPRA PÚBLICA ESTRATÉGICA\nCompra Pública Estratégica: Inexistência de contratação pública estratégica\n\n26 - INFORMAÇÕES ADICIONAIS\nIdentificador do Lote: LOT-0001; LOT-0002; LOT-0003; LOT-0004; LOT-0005; LOT-0006; LOT-0007; LOT-0008; LOT-0009; LOT-0010\nContrato adequado para PME: Sim\nCobertura ACP (Acordo dos Contratos Públicos da Organização Mundial do Comércio): Não\n\n27 - IDENTIFICAÇÃO E CONTACTOS DO ÓRGÃO DE RECURSOS ADMINISTRATIVOS\nDesignação: Agrupamento de Escolas Dr. Jorge Augusto Correia\nEndereço: Rua Luís de Camões\nCódigo postal: 8800-415\nLocalidade: Tavira\nTelefone: 281320440\nFax: \nEndereço eletrónico: director@aejactavira.pt\nPrazo de interposição do recurso: 5 dias\n\n28 - IDENTIFICAÇÃO DO(S) AUTOR(ES) DE ANÚNCIO\nNome: Raul Pina\nCargo: Diretor do Agrupamento de Escolas Dr. Jorge Augusto Correia\n419659903",
    "nipc": "600078442",
    "distrito": "Faro",
    "concelho": "Tavira",
    "freguesia": "União das Freguesias de Tavira (Santa Maria e Santiago)",
    "site": "www.aejactavira.pt",
    "email": "director@aejactavira.pt",
    "designacao_contrato": "Aquisição de equipamentos destinados à prática educativa e infraestrutura tecnológica no âmbito do Centro Tecnológico Especializado de Informática",
    "descricao": "Aquisição de equipamentos destinados à prática educativa e infraestrutura tecnológica no âmbito do Centro Tecnológico Especializado de Informática",
    "preco_base": "355.800,00 EUR",
    "prazo_execucao": "60 DIAS",
    "prazo_apresentacao_propostas": "14-11-2025 17:00",
    "fundos_eu": "Sim",
    "plataforma_eletronica": "ACIN",
    "url_procedimento": "https://www.acingov.pt",
    "autor_nome": "Raul Pina",
    "autor_cargo": "Diretor do Agrupamento de Escolas Dr. Jorge Augusto Correia"
  },
  {
    "numero_procedimento": "N/A",
    "entidade": "EDIA - Empresa de Desenvolvimento e Infra Estruturas do Alqueva, S. A.",
    "link": "https://diariodarepublica.pt/dr/detalhe/contrato-publico/27429-940641048",
    "detalhes_completos": "1 - IDENTIFICAÇÃO E CONTACTOS DA ENTIDADE ADJUDICANTE\nDesignação da entidade adjudicante: EDIA - Empresa de Desenvolvimento e Infra Estruturas do Alqueva, S. A.\nNIPC: 503450189\nEndereço: Rua Zeca Afonso, nº  2 Beja\nCódigo postal: 7800-522\nLocalidade: Beja\nPaís: Portugal\nNUT III: PT184\nDistrito: Beja\nConcelho: Beja\nFreguesia: União das Freguesias de Beja (Santiago Maior e São João Baptista)\nTelefone: 284315100\nFax: 284315101\nEndereço da Entidade (URL): www.edia.pt\nEndereço Eletrónico: edia@edia.pt\neDelivery Gateway (URL): https://community.vortal.biz/public/\nFunção da Organização: Adquirente\nNorma jurídica da Entidade Adjudicante: Organismo de direito público, controlado por uma autoridade da administração central\nÁrea de atividade da Autoridade Adjudicante: Serviços públicos das administrações públicas\n\n2 - JORNAL OFICIAL DA UNIÃO EUROPEIA\nO procedimento a que este anúncio diz respeito também é publicitado no Jornal Oficial da União Europeia? Não\n\n3 - AVISO\nModelo de Anúncio: Concurso público\nData de Envio do Anúncio: 17-10-2025\n\n5 - PROCESSO\nTipo de Procedimento: Concurso público\nPreço base do procedimento: Sim\nValor do preço base do procedimento: 10.000,00 EUR\nProcedimento com lotes? Não\n\n6 - OBJETO DO CONTRATO\nNúmero de referência interna: CP 34/2025\nDesignação do contrato: Prestação de Serviços de Manutenção dos Ascensores da Barragem de Alqueva, da Estação Elevatória dos Álamos, da Estação Elevatória de Pedrógão - Margem Esquerda e do POC da Barragem de Alqueva\nDescrição: Constitui objeto da prestação de serviços a manutenção preventiva dos ascensores instalados na Barragem de Alqueva, na Estação Elevatória dos Álamos, na Estação Elevatória de Pedrógão - Margem Esquerda e no POC da Barragem de Alqueva, de acordo com as condições estipuladas no Caderno de Encargos. \nTipo de Contrato Principal: Aquisição de Serviços\nTipo de Contrato: Aquisição de Serviços\nClassificação CPV (Vocabulário Comum para os Contratos Públicos)\nObjeto principal\nVocabulário Principal: 50750000\nPreço base s/IVA: 10.000,00 EUR\n\n7 - INDICAÇÕES ADICIONAIS\nO contrato envolve aquisição conjunta (satisfação de várias entidades)? Não\nO contrato é adjudicado por uma central de compras? Não\n\n8 - TÉCNICAS\nO concurso destina-se à celebração de um acordo-quadro? Inexistência de acordo-quadro\nÉ utilizado um leilão eletrónico? Não\nÉ adotada uma fase de negociação? Não\nSistema de Aquisição Dinâmico: Inexistência de sistema de aquisição dinâmico\n\n9 - LOCAL DA EXECUÇÃO DO CONTRATO\nLOCAL DA EXECUÇÃO DO CONTRATO (PROCEDIMENTO)\nPaís: Portugal\nNUT III: PT184\nLocalidade: Beja\nDistrito: Beja\nConcelho: Beja\nFreguesia: União das Freguesias de Beja (Santiago Maior e São João Baptista)\n\n10 - PRAZO DE EXECUÇÃO DO CONTRATO\nPrazo de execução do contrato: 3 ANOS\nPrevisão de renovações: Não\n\n11 - FUNDOS EU\nTêm fundos EU? Não\n\n12 - DOCUMENTOS DE HABILITAÇÃO\nHabilitação para o exercício da atividade profissional: Não\n\n13 - CONDIÇÕES DE APRESENTAÇÃO\nPlataforma eletrónica utilizada pela entidade adjudicante: VORTAL\nURL para Apresentação: https://community.vortal.biz/public/\nAdmissibilidade da apresentação de propostas variantes: Não autorizado\nPrazo para apresentação das propostas: 01-11-2025 18:00\nPrazo durante o qual os concorrentes são obrigados a manter as respetivas propostas: 180 dias a contar do termo do prazo para a apresentação das propostas\nIndicação de Subcontratação na Proposta: Inexistência de indicação de subcontratação\n\n14 - PRESTAÇÃO DE CAUÇÃO\nPrestação de caução: Sim\nPercentagem: 5%\nDescrição da Garantia Exigida: A caução será prestada por depósito em dinheiro ou títulos, garantia bancária ou por seguro-caução, utilizando-se um dos modelos (IV, V e VI) anexos ao Programa de Concurso.\n\n15 - FORNECIMENTO DAS PEÇAS DO CONCURSO, APRESENTAÇÃO DE PEDIDOS DE PARTICIPAÇÃO E APRESENTAÇÃO DAS PROPOSTAS\nLink para acesso às peças do concurso (URL): https://community.vortal.biz/Public/public-tender-documents/ODd3M2dNcy9uRHFoeSsvU21BSlpob09SZHRldW1KZGhFNnFhZHF2bitFbnJKd3FFMnNjZDBkNU85RmNrWHdRMktVM1BxR2N3OW5xU1pxaXYrTmEzRFE9PXRDSjRG\n\n20 - OUTROS REQUISITOS\nInformação sobre contratos reservados. Aplica-se a contratos reservados (54º-A)? Não\n\n21 - CRITÉRIO DE ADJUDICAÇÃO\nMultifator: Não\nMonofator:\nNome: Outros\nOutro nome: Preço\n\n24 - CONDIÇÕES DO CONTRATO\nFaturação Eletrónica: Permitido\nObrigação de Subcontratação:\nCódigo da Obrigação de Subcontratação: Não é aplicável nenhuma obrigação de subcontratação.\n\n25 - COMPRA PÚBLICA ESTRATÉGICA\nCompra Pública Estratégica: Inexistência de contratação pública estratégica\n\n26 - INFORMAÇÕES ADICIONAIS\nContrato adequado para PME: Sim\nCobertura ACP (Acordo dos Contratos Públicos da Organização Mundial do Comércio): Não\n\n27 - IDENTIFICAÇÃO E CONTACTOS DO ÓRGÃO DE RECURSOS ADMINISTRATIVOS\nDesignação: Conselho de Administração da EDIA, S.A.\nEndereço: Rua Zeca Afonso, 2\nCódigo postal: 7800-522\nLocalidade: Beja\nTelefone: +351 284315200\nFax: +351 284315223\nEndereço eletrónico: edia@edia.pt\n\n28 - IDENTIFICAÇÃO DO(S) AUTOR(ES) DE ANÚNCIO\nNome: Ana Maria Queiroga\nCargo: Técnica Superior do Gabinete de Apoio Jurídico\n419670416",
    "nipc": "503450189",
    "distrito": "Beja",
    "concelho": "Beja",
    "freguesia": "União das Freguesias de Beja (Santiago Maior e São João Baptista)",
    "site": "www.edia.pt",
    "email": "edia@edia.pt",
    "designacao_contrato": "Prestação de Serviços de Manutenção dos Ascensores da Barragem de Alqueva, da Estação Elevatória dos Álamos, da Estação Elevatória de Pedrógão - Margem Esquerda e do POC da Barragem de Alqueva",
    "descricao": "Constitui objeto da prestação de serviços a manutenção preventiva dos ascensores instalados na Barragem de Alqueva, na Estação Elevatória dos Álamos, na Estação Elevatória de Pedrógão - Margem Esquerda e no POC da Barragem de Alqueva, de acordo com as condições estipuladas no Caderno de Encargos.",
    "preco_base": "10.000,00 EUR",
    "prazo_execucao": "3 ANOS",
    "prazo_apresentacao_propostas": "01-11-2025 18:00",
    "fundos_eu": "Não",
    "plataforma_eletronica": "VORTAL",
    "url_procedimento": "https://community.vortal.biz/public/",
    "autor_nome": "Ana Maria Queiroga",
    "autor_cargo": "Técnica Superior do Gabinete de Apoio Jurídico"
  },
  {
    "numero_procedimento": "N/A",
    "entidade": "AnÃºncio de procedimento  n.Âº 27430/2025  -  DiÃ¡rio da RepÃºblica n.Âº 201/2025, SÃ©rie II de 2025-10-17",
    "link": "https://diariodarepublica.pt/dr/detalhe/contrato-publico/27430-940641049"
  },
  {
    "numero_procedimento": "N/A",
    "entidade": "AnÃºncio de procedimento  n.Âº 27432/2025  -  DiÃ¡rio da RepÃºblica n.Âº 201/2025, SÃ©rie II de 2025-10-17",
    "link": "https://diariodarepublica.pt/dr/detalhe/contrato-publico/27432-940641050"
  },
  {
    "numero_procedimento": "N/A",
    "entidade": "AnÃºncio de procedimento  n.Âº 27436/2025  -  DiÃ¡rio da RepÃºblica n.Âº 201/2025, SÃ©rie II de 2025-10-17",
    "link": "https://diariodarepublica.pt/dr/detalhe/contrato-publico/27436-940641053"
  },
  {
    "numero_procedimento": "N/A",
    "entidade": "AnÃºncio de procedimento  n.Âº 27433/2025  -  DiÃ¡rio da RepÃºblica n.Âº 201/2025, SÃ©rie II de 2025-10-17",
    "link": "https://diariodarepublica.pt/dr/detalhe/contrato-publico/27433-940780708"
  },
  {
    "numero_procedimento": "N/A",
    "entidade": "AnÃºncio de procedimento  n.Âº 27434/2025  -  DiÃ¡rio da RepÃºblica n.Âº 201/2025, SÃ©rie II de 2025-10-17",
    "link": "https://diariodarepublica.pt/dr/detalhe/contrato-publico/27434-940780709"
  },
  {
    "numero_procedimento": "N/A",
    "entidade": "CERCIGUI - Cooperativa de Educação e Reabilitação de Cidadãos Inadaptados do Concelho de Guimarães, C. R. L.",
    "link": "https://diariodarepublica.pt/dr/detalhe/contrato-publico/27435-940780710",
    "detalhes_completos": "1 - IDENTIFICAÇÃO E CONTACTOS DA ENTIDADE ADJUDICANTE\nDesignação da entidade adjudicante: CERCIGUI - Cooperativa de Educação e Reabilitação de Cidadãos Inadaptados do Concelho de Guimarães, C. R. L.\nNIPC: 500636834\nEndereço: Rua Raúl Brandão, Nº 195\nCódigo postal: 4810-282\nLocalidade:  Braga \nPaís: Portugal\nNUT III: PT119\nDistrito: Braga\nConcelho: Guimarães\nFreguesia: Todas\nTelefone: 253423370\nFax: 253423370\nEndereço da Entidade (URL): www.cercigui.pt\nEndereço Eletrónico: cercigui@cercigui.pt\neDelivery Gateway (URL): https://community.vortal.biz/public/\nFunção da Organização: Adquirente\nNorma jurídica da Entidade Adjudicante: Organismo de direito público\nÁrea de atividade da Autoridade Adjudicante: Educação\n\n2 - JORNAL OFICIAL DA UNIÃO EUROPEIA\nO procedimento a que este anúncio diz respeito também é publicitado no Jornal Oficial da União Europeia? Não\n\n3 - AVISO\nModelo de Anúncio: Concurso público\nData de Envio do Anúncio: 17-10-2025\n\n5 - PROCESSO\nTipo de Procedimento: Concurso público\nPreço base do procedimento: Sim\nValor do preço base do procedimento: 21.708,00 EUR\nProcedimento com lotes? Sim\nNº Máx. de Lotes Autorizado: 14\nNúmero máximo de lotes que podem ser adjudicados a um concorrente: 14\n\n6 - OBJETO DO CONTRATO\nNúmero de referência interna: CP 04/2025\nDesignação do contrato: CP 04/2025 - FORNECIMENTO CONTÍNUO DE PRODUTOS ALIMENTARES, POR LOTES \nDescrição: CP 04/2025 - FORNECIMENTO CONTÍNUO DE PRODUTOS ALIMENTARES, POR LOTES \nTipo de Contrato Principal: Aquisição de Bens Móveis\nTipo de Contrato: Aquisição de Bens Móveis\nClassificação CPV (Vocabulário Comum para os Contratos Públicos)\nObjeto principal\nVocabulário Principal: 15100000\nPreço base s/IVA: 21.708,00 EUR\nLotes: \nNº: LOT-0001\nDescrição do Lote: Lote 1 - Produtos de panificação, produtos frescos de pastelaria e bolos \nPreço base s/IVA: 1.412,00 EUR\nClassificação CPV (Vocabulário Comum para os Contratos Públicos)\nObjeto principal\nVocabulário Principal: 15100000\nNº: LOT-0002\nDescrição do Lote: Lote 2 - Frutos e Produtos hortícolas \nPreço base s/IVA: 1.000,00 EUR\nClassificação CPV (Vocabulário Comum para os Contratos Públicos)\nObjeto principal\nVocabulário Principal: 15100000\nNº: LOT-0003\nDescrição do Lote: Lote 3 - Bebidas não Alcoólicas \nPreço base s/IVA: 1.339,00 EUR\nClassificação CPV (Vocabulário Comum para os Contratos Públicos)\nObjeto principal\nVocabulário Principal: 15100000\nNº: LOT-0004\nDescrição do Lote: Lote 4 - Batatas Fritas; Bolachas; Gelatinas; Chocolates; Chá; Doces e Mel – Snacks \nPreço base s/IVA: 742,00 EUR\nClassificação CPV (Vocabulário Comum para os Contratos Públicos)\nObjeto principal\nVocabulário Principal: 15100000\nNº: LOT-0005\nDescrição do Lote: Lote 5 - Produtos Enlatados e Conservas \nPreço base s/IVA: 502,00 EUR\nClassificação CPV (Vocabulário Comum para os Contratos Públicos)\nObjeto principal\nVocabulário Principal: 15100000\nNº: LOT-0006\nDescrição do Lote: Lote 6 - Massa e Arroz \nPreço base s/IVA: 365,00 EUR\nClassificação CPV (Vocabulário Comum para os Contratos Públicos)\nObjeto principal\nVocabulário Principal: 15100000\nNº: LOT-0007\nDescrição do Lote: Lote 7 - Condimentos e temperos; Óleos e gorduras animais e vegetais \nPreço base s/IVA: 1.868,00 EUR\nClassificação CPV (Vocabulário Comum para os Contratos Públicos)\nObjeto principal\nVocabulário Principal: 15100000\nNº: LOT-0008\nDescrição do Lote: Lote 8 – Lacticínios \nPreço base s/IVA: 2.187,00 EUR\nClassificação CPV (Vocabulário Comum para os Contratos Públicos)\nObjeto principal\nVocabulário Principal: 15100000\nNº: LOT-0009\nDescrição do Lote: Lote 9 – Carne \nPreço base s/IVA: 3.200,00 EUR\nClassificação CPV (Vocabulário Comum para os Contratos Públicos)\nObjeto principal\nVocabulário Principal: 15100000\nNº: LOT-0010\nDescrição do Lote: Lote 10 – Ovos \nPreço base s/IVA: 2.474,00 EUR\nClassificação CPV (Vocabulário Comum para os Contratos Públicos)\nObjeto principal\nVocabulário Principal: 15100000\nNº: LOT-0011\nDescrição do Lote: Lote 11 - Fornecimento contínuo de Produtos de pastelaria _Granel \nPreço base s/IVA: 2.888,00 EUR\nClassificação CPV (Vocabulário Comum para os Contratos Públicos)\nObjeto principal\nVocabulário Principal: 15100000\nNº: LOT-0012\nDescrição do Lote: Lote 12 - Açúcar; Farinha; Produtos de confeitaria – Sobremesas \nPreço base s/IVA: 1.549,00 EUR\nClassificação CPV (Vocabulário Comum para os Contratos Públicos)\nObjeto principal\nVocabulário Principal: 15100000\nNº: LOT-0013\nDescrição do Lote: Lote 13 – Cervejas \nPreço base s/IVA: 323,00 EUR\nClassificação CPV (Vocabulário Comum para os Contratos Públicos)\nObjeto principal\nVocabulário Principal: 15100000\nNº: LOT-0014\nDescrição do Lote: Lote 14 - Peixe: Congelado \nPreço base s/IVA: 1.859,00 EUR\nClassificação CPV (Vocabulário Comum para os Contratos Públicos)\nObjeto principal\nVocabulário Principal: 15100000\n\n7 - INDICAÇÕES ADICIONAIS\nO contrato envolve aquisição conjunta (satisfação de várias entidades)? Não\nO contrato é adjudicado por uma central de compras? Não\n\n8 - TÉCNICAS\nO concurso destina-se à celebração de um acordo-quadro? Inexistência de acordo-quadro\nÉ utilizado um leilão eletrónico? Não\nÉ adotada uma fase de negociação? Não\nSistema de Aquisição Dinâmico: Inexistência de sistema de aquisição dinâmico\n\n9 - LOCAL DA EXECUÇÃO DO CONTRATO\nLOCAL DA EXECUÇÃO DO CONTRATO (PROCEDIMENTO)\nPaís: Portugal\nNUT III: PT119\nLocalidade: Braga\nDistrito: Braga\nConcelho: Guimarães\nFreguesia: União das Freguesias de Oliveira, São Paio e São Sebastião\nLOCAL DA EXECUÇÃO DO CONTRATO (LOTE)\nIdentificador do Lote: LOT-0001; LOT-0002; LOT-0003; LOT-0004; LOT-0005; LOT-0006; LOT-0007; LOT-0008; LOT-0009; LOT-0010; LOT-0011; LOT-0012; LOT-0013; LOT-0014\nPaís: Portugal\nNUT III: PT119\nLocalidade: Braga\nDistrito: Braga\nConcelho: Guimarães\nFreguesia: União das Freguesias de Oliveira, São Paio e São Sebastião\n\n10 - PRAZO DE EXECUÇÃO DO CONTRATO\nIdentificador do Lote: LOT-0001; LOT-0002; LOT-0003; LOT-0004; LOT-0005; LOT-0006; LOT-0007; LOT-0008; LOT-0009; LOT-0010; LOT-0011; LOT-0012; LOT-0013; LOT-0014\nPrazo de execução do contrato: 365 DIAS\nPrevisão de renovações: Não\n\n11 - FUNDOS EU\nIdentificador do Lote: LOT-0001; LOT-0002; LOT-0003; LOT-0004; LOT-0005; LOT-0006; LOT-0007; LOT-0008; LOT-0009; LOT-0010; LOT-0011; LOT-0012; LOT-0013; LOT-0014\nTêm fundos EU? Sim\n\n12 - DOCUMENTOS DE HABILITAÇÃO\nHabilitação para o exercício da atividade profissional: Não\n\n13 - CONDIÇÕES DE APRESENTAÇÃO\nPlataforma eletrónica utilizada pela entidade adjudicante: VORTAL\nURL para Apresentação: https://community.vortal.biz/public/\nAdmissibilidade da apresentação de propostas variantes: Não autorizado\nPrazo para apresentação das propostas: 29-10-2025 23:59\nPrazo durante o qual os concorrentes são obrigados a manter as respetivas propostas: 90 dias a contar do termo do prazo para a apresentação das propostas\nIndicação de Subcontratação na Proposta: Inexistência de indicação de subcontratação\n\n14 - PRESTAÇÃO DE CAUÇÃO\nPrestação de caução: Não\n\n15 - FORNECIMENTO DAS PEÇAS DO CONCURSO, APRESENTAÇÃO DE PEDIDOS DE PARTICIPAÇÃO E APRESENTAÇÃO DAS PROPOSTAS\nLink para acesso às peças do concurso (URL): https://community.vortal.biz/Public/public-tender-documents/NGZweEZFN2tpREluVVRDNnd0L2o3eG5kRU1aMkxQSWw5M2dPNUdQWlhvNGNmU3FtTkNvQXRDejNLWlRyOHEzUzJrM0MwNXRLdHZ3MGJVRFdsNVJQaUE9PXh1UWMp\n\n20 - OUTROS REQUISITOS\nIdentificador do Lote: LOT-0001; LOT-0002; LOT-0003; LOT-0004; LOT-0005; LOT-0006; LOT-0007; LOT-0008; LOT-0009; LOT-0010; LOT-0011; LOT-0012; LOT-0013; LOT-0014\nInformação sobre contratos reservados. Aplica-se a contratos reservados (54º-A)? Não\n\n21 - CRITÉRIO DE ADJUDICAÇÃO\nO Critério de adjudicação é diferenciado por lote? Não\nMultifator: Não\nMonofator:\nNome: Preço\n\n24 - CONDIÇÕES DO CONTRATO\nIdentificador do Lote: LOT-0001; LOT-0002; LOT-0003; LOT-0004; LOT-0005; LOT-0006; LOT-0007; LOT-0008; LOT-0009; LOT-0010; LOT-0011; LOT-0012; LOT-0013; LOT-0014\nFaturação Eletrónica: Permitido\nObrigação de Subcontratação:\nCódigo da Obrigação de Subcontratação: Não é aplicável nenhuma obrigação de subcontratação.\n\n25 - COMPRA PÚBLICA ESTRATÉGICA\nCompra Pública Estratégica: Inexistência de contratação pública estratégica\n\n26 - INFORMAÇÕES ADICIONAIS\nIdentificador do Lote: LOT-0001; LOT-0002; LOT-0003; LOT-0004; LOT-0005; LOT-0006; LOT-0007; LOT-0008; LOT-0009; LOT-0010; LOT-0011; LOT-0012; LOT-0013; LOT-0014\nContrato adequado para PME: Sim\nCobertura ACP (Acordo dos Contratos Públicos da Organização Mundial do Comércio): Não\n\n27 - IDENTIFICAÇÃO E CONTACTOS DO ÓRGÃO DE RECURSOS ADMINISTRATIVOS\nDesignação: Conselho de administração\nEndereço: Rua raul brandão nº 195\nCódigo postal: 4810-282\nLocalidade: Guimarães\nTelefone: +351 919904072\nFax: +351 919904072\nEndereço eletrónico: cercigui@cercigui.pt\n\n28 - IDENTIFICAÇÃO DO(S) AUTOR(ES) DE ANÚNCIO\nNome: Bruno Faria\nCargo: Presidente do conselho de administração\n419671048",
    "nipc": "500636834",
    "distrito": "Braga",
    "concelho": "Guimarães",
    "freguesia": "Todas",
    "site": "www.cercigui.pt",
    "email": "cercigui@cercigui.pt",
    "designacao_contrato": "CP 04/2025 - FORNECIMENTO CONTÍNUO DE PRODUTOS ALIMENTARES, POR LOTES",
    "descricao": "CP 04/2025 - FORNECIMENTO CONTÍNUO DE PRODUTOS ALIMENTARES, POR LOTES",
    "preco_base": "21.708,00 EUR",
    "prazo_execucao": "365 DIAS",
    "prazo_apresentacao_propostas": "29-10-2025 23:59",
    "fundos_eu": "Sim",
    "plataforma_eletronica": "VORTAL",
    "url_procedimento": "https://community.vortal.biz/public/",
    "autor_nome": "Bruno Faria",
    "autor_cargo": "Presidente do conselho de administração"
  },
  {
    "numero_procedimento": "N/A",
    "entidade": "AnÃºncio de procedimento  n.Âº 27437/2025  -  DiÃ¡rio da RepÃºblica n.Âº 201/2025, SÃ©rie II de 2025-10-17",
    "link": "https://diariodarepublica.pt/dr/detalhe/contrato-publico/27437-940780711"
  },
  {
    "numero_procedimento": "N/A",
    "entidade": "Secretaria Regional do Turismo e Cultura",
    "link": "https://diariodarepublica.pt/dr/detalhe/contrato-publico/27438-940780712",
    "detalhes_completos": "Alteração do Anúncio de procedimento n.º 26560/2025, de 2025-10-09, com o ID 419623833\n\n1 - IDENTIFICAÇÃO E CONTACTOS DA ENTIDADE ADJUDICANTE\nDesignação da entidade adjudicante: Secretaria Regional do Turismo e Cultura\nNIPC: 671000527\nServiço/Órgão/Pessoa de contacto: Direção de Serviços de Contratação Pública e Aprovisionamento\nEndereço: Avenida Arriaga, 18\nCódigo postal: 9004-519\nLocalidade: Funchal\nPaís: Portugal\nNUT III: PT300\nDistrito: Região Autónoma da Madeira\nConcelho: Funchal\nFreguesia: Freguesia de Sé (Funchal)\nTelefone: 291145300\nFax: 291145300\nEndereço da Entidade (URL): www.madeira.gov.pt/srtac\nEndereço Eletrónico: gabinete.srtac@madeira.gov.pt\neDelivery Gateway (URL): https://www.acingov.pt\nFunção da Organização: Adquirente\nNorma jurídica da Entidade Adjudicante: Organismo de direito público\nÁrea de atividade da Autoridade Adjudicante: Serviços públicos das administrações públicas\n\n2 - JORNAL OFICIAL DA UNIÃO EUROPEIA\nO procedimento a que este anúncio diz respeito também é publicitado no Jornal Oficial da União Europeia? Sim\n\n3 - AVISO\nModelo de Anúncio: Concurso de conceção\nData de Envio do Anúncio: 15-10-2025\n\n5 - PROCESSO\nTipo de Procedimento: Concurso público\nPreço base do procedimento: Sim\nValor do preço base do procedimento: 160.687,50 EUR\nProcedimento com lotes? Sim\nNº Máx. de Lotes Autorizado: 3\nNúmero máximo de lotes que podem ser adjudicados a um concorrente: 3\n\n6 - OBJETO DO CONTRATO\nNúmero de referência interna: 23/2025/SRTAC\nDesignação do contrato: Decorações de Espaços para as Festas de Natal e Fim do Ano 2025/2026, Festa da Flor 2026 e Festas de Natal e Fim do Ano 2026/2027\nDescrição: Decorações de Espaços para as Festas de Natal e Fim do Ano 2025/2026, Festa da Flor 2026 e Festas de Natal e Fim do Ano 2026/2027\nOpções: Não\nTipo de Contrato Principal: Aquisição de Serviços\nTipo de Contrato: Aquisição de Serviços\nClassificação CPV (Vocabulário Comum para os Contratos Públicos)\nObjeto principal\nVocabulário Principal: 98390000\nPreço base s/IVA: 160.687,50 EUR\nLotes: \nNº: LOT-0001\nDescrição do Lote: LOTE 1  Decorações de Espaços para as Festas de Natal e Fim do Ano 2025/2026 - Custo Global/Parâmetro Base: 48.600,00 EUR\nPreço base s/IVA: 48.600,00 EUR\nClassificação CPV (Vocabulário Comum para os Contratos Públicos)\nObjeto principal\nVocabulário Principal: 98390000\nNº: LOT-0002\nDescrição do Lote: LOTE 2  Decorações de Espaços para a Festa da Flor 2026- Custo Global/Parâmetro Base: 61.057.50 EUR\nPreço base s/IVA: 61.057,50 EUR\nClassificação CPV (Vocabulário Comum para os Contratos Públicos)\nObjeto principal\nVocabulário Principal: 98390000\nNº: LOT-0003\nDescrição do Lote: LOTE 3  Decorações de Espaços para as Festas de Natal e Fim do Ano 2026/2027 - Custo Global/Parâmetro Base: 51.030,00 EUR\nPreço base s/IVA: 51.030,00 EUR\nClassificação CPV (Vocabulário Comum para os Contratos Públicos)\nObjeto principal\nVocabulário Principal: 98390000\n\n7 - INDICAÇÕES ADICIONAIS\nEstá prevista a possibilidade de o(s) vencedor(es) do concurso de conceção realizar(em) o desenvolvimento de parte(s) do projeto vencedor, mediante procedimento por ajuste direto? Sim\nO contrato envolve aquisição conjunta (satisfação de várias entidades)? Não\n\n8 - TÉCNICAS\nSistema de Aquisição Dinâmico: Inexistência de sistema de aquisição dinâmico\n\n9 - LOCAL DA EXECUÇÃO DO CONTRATO\nLOCAL DA EXECUÇÃO DO CONTRATO (PROCEDIMENTO)\nPaís: Portugal\nNUT III: PT300\nLocalidade: Todas\nDistrito: Região Autónoma da Madeira\nConcelho: Todos\nFreguesia: Todas\nLOCAL DA EXECUÇÃO DO CONTRATO (LOTE)\nIdentificador do Lote: LOT-0001; LOT-0002; LOT-0003\nPaís: Portugal\nNUT III: PT300\nLocalidade: Todas\nDistrito: Região Autónoma da Madeira\nConcelho: Todos\nFreguesia: Todas\n\n11 - FUNDOS EU\nIdentificador do Lote: LOT-0001; LOT-0002; LOT-0003\nTêm fundos EU? Não\n\n12 - DOCUMENTOS DE HABILITAÇÃO\nHabilitação para o exercício da atividade profissional: Não\n\n13 - CONDIÇÕES DE APRESENTAÇÃO\nPlataforma eletrónica utilizada pela entidade adjudicante: ACIN\nURL para Apresentação: https://www.acingov.pt\nIndicação de Subcontratação na Proposta: Inexistência de indicação de subcontratação\nModo de apresentação dos trabalhos de conceção: Os documentos que constituem a proposta devem ser apresentados através da plataforma eletrónica acinGov\n\n15 - FORNECIMENTO DAS PEÇAS DO CONCURSO, APRESENTAÇÃO DE PEDIDOS DE PARTICIPAÇÃO E APRESENTAÇÃO DAS PROPOSTAS\nLink para acesso às peças do concurso (URL): https://www.acingov.pt/acingovprod/2/zonaPublica/zona_publica_c/donwloadProcedurePiece/OTg0MTg2\n\n16 - MODALIDADE DO CONCURSO DE CONCEÇÃO/IDEIAS\nÉ um concurso de conceção simplificado? Não\nModalidade do concurso: Concurso Público\nPrazo para apresentação dos trabalhos de conceção/ideias: 30 DIAS\nRequisitos mínimos de capacidade técnica: Não definido\n\n20 - OUTROS REQUISITOS\nIdentificador do Lote: LOT-0001; LOT-0002; LOT-0003\nInformação sobre contratos reservados. Aplica-se a contratos reservados (54º-A)? Não\n\n22 - NÚMERO DE TRABALHOS DE CONCEÇÃO / IDEIAS A SELECIONAR\nNúmero de trabalhos de VII/ideias a selecionar: 1\n\n23 - PRÉMIOS\nPrémios: Sim\nMontante global dos prémios de participação: 3000\n\n24 - CONDIÇÕES DO CONTRATO\nIdentificador do Lote: LOT-0001; LOT-0002; LOT-0003\nFaturação Eletrónica: Não autorizado\nObrigação de Subcontratação:\nCódigo da Obrigação de Subcontratação: Não é aplicável nenhuma obrigação de subcontratação.\n\n25 - COMPRA PÚBLICA ESTRATÉGICA\nCompra Pública Estratégica: Inexistência de contratação pública estratégica\n\n26 - INFORMAÇÕES ADICIONAIS\nIdentificador do Lote: LOT-0001; LOT-0002; LOT-0003\nContrato adequado para PME: Sim\nCobertura ACP (Acordo dos Contratos Públicos da Organização Mundial do Comércio): Não\n\n27 - IDENTIFICAÇÃO E CONTACTOS DO ÓRGÃO DE RECURSOS ADMINISTRATIVOS\nDesignação: Secretário Regional de Turismo, Ambiente e Cultura\nEndereço: Avenida Arriaga, 18\nCódigo postal: 9004-519\nLocalidade: Funchal\nTelefone: 291145300\nFax: 291145300\nEndereço eletrónico: gabinete.srtac@madeira.gov.pt\nPrazo de interposição do recurso: 10 dias\n\n28 - IDENTIFICAÇÃO DO(S) AUTOR(ES) DE ANÚNCIO\nNome: António Eduardo de Freitas Jesus\nCargo: Secretário Regional de Turismo, Ambiente e Cultura\n\n29 - ALTERAÇÃO\nMotivo da Alteração: Correção pelo adquirente\nIdentificador da Versão do Anúncio a Alterar: 5d0a8a00-5dca-41f9-8778-7c5ef3dd73b0-01\nIdentificador das Secções Alteradas do Anúncio Anterior: Processo; Objeto do contrato; Prémios\nDescrição das Alterações: Os parâmetros definidos na plataforma Acingov, no âmbito do procedimento de conceção, não permitem transmitir para o anúncio a informação correta acerca do preço base do procedimento e dos prémios de consagração. Assim, procedeu-se à correção respeitante ao valor do preço base no Anúncio e correção respeitante ao Prémio no Anúncio, uma vez que aquando do preenchimento do preço base e do prémio na plataforma Acingov, o Anúncio foi gerado automaticamente com incorreções.\n\nNão há prémio de participação, apenas prémio de consagração ao(s) concorrente(s) cujo(s) trabalho(s) de conceção venha(m) a ser selecionado(s). \nNúmero de trabalhos a selecionar por cada lote: 1. \nValor do prémio de consagração por Lote (1.º classificado): 1.000,00 EUR\nClassificação: 1\nValor total: 3.000,00 EUR\nAlteração dos Documentos do Concurso: Não\n419660072",
    "nipc": "671000527",
    "distrito": "Região Autónoma da Madeira",
    "concelho": "Funchal",
    "freguesia": "Freguesia de Sé (Funchal)",
    "site": "www.madeira.gov.pt/srtac",
    "email": "gabinete.srtac@madeira.gov.pt",
    "designacao_contrato": "Decorações de Espaços para as Festas de Natal e Fim do Ano 2025/2026, Festa da Flor 2026 e Festas de Natal e Fim do Ano 2026/2027",
    "descricao": "Decorações de Espaços para as Festas de Natal e Fim do Ano 2025/2026, Festa da Flor 2026 e Festas de Natal e Fim do Ano 2026/2027",
    "preco_base": "160.687,50 EUR",
    "prazo_execucao": null,
    "prazo_apresentacao_propostas": null,
    "fundos_eu": "Não",
    "plataforma_eletronica": "ACIN",
    "url_procedimento": "https://www.acingov.pt",
    "autor_nome": "António Eduardo de Freitas Jesus",
    "autor_cargo": "Secretário Regional de Turismo, Ambiente e Cultura"
  },
  {
    "numero_procedimento": "N/A",
    "entidade": "Serviços de Acção Social do Instituto Politécnico de Leiria",
    "link": "https://diariodarepublica.pt/dr/detalhe/contrato-publico/27439-940780713",
    "detalhes_completos": "1 - IDENTIFICAÇÃO E CONTACTOS DA ENTIDADE ADJUDICANTE\nDesignação da entidade adjudicante: Serviços de Acção Social do Instituto Politécnico de Leiria\nNIPC: 600041581\nServiço/Órgão/Pessoa de contacto: Serviços de Ação Social do Instituto Politécnico de Leiria\nEndereço: Edificio Sede - Rua General Norton de Matos\nCódigo postal: 2411-901\nLocalidade: Leiria\nPaís: Portugal\nNUT III: PTZZZ\nDistrito: Todos\nConcelho: Todos\nFreguesia: Todas\nTelefone: 244830640\nEndereço da Entidade (URL): http://www.ipleiria.pt/sas/apresentacao/\nEndereço Eletrónico: sas@ipleiria.pt\neDelivery Gateway (URL): https://www.acingov.pt\nFunção da Organização: Adquirente\nNorma jurídica da Entidade Adjudicante: Organismo de direito público\nÁrea de atividade da Autoridade Adjudicante: Serviços públicos das administrações públicas\n\n2 - JORNAL OFICIAL DA UNIÃO EUROPEIA\nO procedimento a que este anúncio diz respeito também é publicitado no Jornal Oficial da União Europeia? Não\n\n3 - AVISO\nModelo de Anúncio: Concurso público\nData de Envio do Anúncio: 17-10-2025\n\n5 - PROCESSO\nTipo de Procedimento: Concurso público\nPreço base do procedimento: Sim\nValor do preço base do procedimento: 187.300,00 EUR\nProcedimento com lotes? Sim\nNº Máx. de Lotes Autorizado: 17\nNúmero máximo de lotes que podem ser adjudicados a um concorrente: 17\n\n6 - OBJETO DO CONTRATO\nNúmero de referência interna: CP.SAS.005/2025/2955\nDesignação do contrato: Concurso Público SAS. 005/2025/2955 - Aquisição por lotes de produtos alimentares de mercearia\nDescrição:  Concurso Público SAS. 005/2025/2955 -  Aquisição por lotes de produtos alimentares de mercearia\nTipo de Contrato Principal: Aquisição de Bens Móveis\nTipo de Contrato: Aquisição de Bens Móveis\nClassificação CPV (Vocabulário Comum para os Contratos Públicos)\nObjeto principal\nVocabulário Principal: 15000000\nPreço base s/IVA: 187.300,00 EUR\nLotes: \nNº: LOT-0001\nDescrição do Lote: Laticínios e derivados\nPreço base s/IVA: 38.500,00 EUR\nClassificação CPV (Vocabulário Comum para os Contratos Públicos)\nObjeto principal\nVocabulário Principal: 15500000\nNº: LOT-0002\nDescrição do Lote: Charcutaria\nPreço base s/IVA: 9.000,00 EUR\nClassificação CPV (Vocabulário Comum para os Contratos Públicos)\nObjeto principal\nVocabulário Principal: 15131130\nNº: LOT-0003\nDescrição do Lote: Conservas\nPreço base s/IVA: 18.000,00 EUR\nClassificação CPV (Vocabulário Comum para os Contratos Públicos)\nObjeto principal\nVocabulário Principal: 15897200\nNº: LOT-0004\nDescrição do Lote: Arroz, cereais, farináceos, massas e sementes\nPreço base s/IVA: 25.000,00 EUR\nClassificação CPV (Vocabulário Comum para os Contratos Públicos)\nObjeto principal\nVocabulário Principal: 15600000\nNº: LOT-0005\nDescrição do Lote: Bolachas, biscoitos e snacks\nPreço base s/IVA: 400,00 EUR\nClassificação CPV (Vocabulário Comum para os Contratos Públicos)\nObjeto principal\nVocabulário Principal: 15820000\nNº: LOT-0006\nDescrição do Lote: Chocolates, pastilhas e outros doces\nPreço base s/IVA: 4.500,00 EUR\nClassificação CPV (Vocabulário Comum para os Contratos Públicos)\nObjeto principal\nVocabulário Principal: 15842000\nNº: LOT-0007\nDescrição do Lote: Compotas, patês e molhos\nPreço base s/IVA: 3.700,00 EUR\nClassificação CPV (Vocabulário Comum para os Contratos Públicos)\nObjeto principal\nVocabulário Principal: 15871200\nNº: LOT-0008\nDescrição do Lote: Azeite, óleo alimentar e vinagre\nPreço base s/IVA: 42.000,00 EUR\nClassificação CPV (Vocabulário Comum para os Contratos Públicos)\nObjeto principal\nVocabulário Principal: 15400000\nNº: LOT-0009\nDescrição do Lote: Especiarias, ervas aromáticas e caldos\nPreço base s/IVA: 6.000,00 EUR\nClassificação CPV (Vocabulário Comum para os Contratos Públicos)\nObjeto principal\nVocabulário Principal: 15870000\nNº: LOT-0010\nDescrição do Lote: Produtos para confeitaria\nPreço base s/IVA: 3.500,00 EUR\nClassificação CPV (Vocabulário Comum para os Contratos Públicos)\nObjeto principal\nVocabulário Principal: 15842300\nNº: LOT-0011\nDescrição do Lote: Preparados para sobremesas\nPreço base s/IVA: 5.000,00 EUR\nClassificação CPV (Vocabulário Comum para os Contratos Públicos)\nObjeto principal\nVocabulário Principal: 15833100\nNº: LOT-0012\nDescrição do Lote: Produtos vegetarianos\nPreço base s/IVA: 9.000,00 EUR\nClassificação CPV (Vocabulário Comum para os Contratos Públicos)\nObjeto principal\nVocabulário Principal: 15894100\nNº: LOT-0013\nDescrição do Lote: Chás e infusões em saquinhos\nPreço base s/IVA: 300,00 EUR\nClassificação CPV (Vocabulário Comum para os Contratos Públicos)\nObjeto principal\nVocabulário Principal: 15863000\nNº: LOT-0014\nDescrição do Lote: Vinhos\nPreço base s/IVA: 1.300,00 EUR\nClassificação CPV (Vocabulário Comum para os Contratos Públicos)\nObjeto principal\nVocabulário Principal: 15930000\nNº: LOT-0015\nDescrição do Lote: Águas\nPreço base s/IVA: 17.500,00 EUR\nClassificação CPV (Vocabulário Comum para os Contratos Públicos)\nObjeto principal\nVocabulário Principal: 15981000\nNº: LOT-0016\nDescrição do Lote: Bebidas diversas\nPreço base s/IVA: 1.500,00 EUR\nClassificação CPV (Vocabulário Comum para os Contratos Públicos)\nObjeto principal\nVocabulário Principal: 15982000\nNº: LOT-0017\nDescrição do Lote: Produtos diversos\nPreço base s/IVA: 2.100,00 EUR\nClassificação CPV (Vocabulário Comum para os Contratos Públicos)\nObjeto principal\nVocabulário Principal: 15000000\n\n7 - INDICAÇÕES ADICIONAIS\nO contrato envolve aquisição conjunta (satisfação de várias entidades)? Não\nO contrato é adjudicado por uma central de compras? Não\n\n8 - TÉCNICAS\nO concurso destina-se à celebração de um acordo-quadro? Inexistência de acordo-quadro\nÉ utilizado um leilão eletrónico? Não\nÉ adotada uma fase de negociação? Não\nSistema de Aquisição Dinâmico: Inexistência de sistema de aquisição dinâmico\n\n9 - LOCAL DA EXECUÇÃO DO CONTRATO\nLOCAL DA EXECUÇÃO DO CONTRATO (PROCEDIMENTO)\nPaís: Portugal\nNUT III: PT16F\nLocalidade: Leiria\nDistrito: Leiria\nConcelho: Leiria\nFreguesia: Todas\nPaís: Portugal\nNUT III: PT16F\nLocalidade: Caldas da Rainha\nDistrito: Leiria\nConcelho: Caldas da Rainha\nFreguesia: Todas\nPaís: Portugal\nNUT III: PT16F\nLocalidade: Peniche\nDistrito: Leiria\nConcelho: Peniche\nFreguesia: Todas\nLOCAL DA EXECUÇÃO DO CONTRATO (LOTE)\nIdentificador do Lote: LOT-0001; LOT-0002; LOT-0003; LOT-0004; LOT-0005; LOT-0006; LOT-0007; LOT-0008; LOT-0009; LOT-0010; LOT-0011; LOT-0012; LOT-0013; LOT-0014; LOT-0015; LOT-0016; LOT-0017\nPaís: Portugal\nNUT III: PT16F\nLocalidade: Peniche\nDistrito: Leiria\nConcelho: Peniche\nFreguesia: Todas\nIdentificador do Lote: LOT-0001; LOT-0002; LOT-0003; LOT-0004; LOT-0005; LOT-0006; LOT-0007; LOT-0008; LOT-0009; LOT-0010; LOT-0011; LOT-0012; LOT-0013; LOT-0014; LOT-0015; LOT-0016; LOT-0017\nPaís: Portugal\nNUT III: PT16F\nLocalidade: Caldas da Rainha\nDistrito: Leiria\nConcelho: Caldas da Rainha\nFreguesia: Todas\nIdentificador do Lote: LOT-0001; LOT-0002; LOT-0003; LOT-0004; LOT-0005; LOT-0006; LOT-0007; LOT-0008; LOT-0009; LOT-0010; LOT-0011; LOT-0012; LOT-0013; LOT-0014; LOT-0015; LOT-0016; LOT-0017\nPaís: Portugal\nNUT III: PT16F\nLocalidade: Leiria\nDistrito: Leiria\nConcelho: Leiria\nFreguesia: Todas\n\n10 - PRAZO DE EXECUÇÃO DO CONTRATO\nIdentificador do Lote: LOT-0001; LOT-0002; LOT-0003; LOT-0004; LOT-0005; LOT-0006; LOT-0007; LOT-0008; LOT-0009; LOT-0010; LOT-0011; LOT-0012; LOT-0013; LOT-0014; LOT-0015; LOT-0016; LOT-0017\nPrazo de execução do contrato: 12 MESES\nPrevisão de renovações: Não\n\n11 - FUNDOS EU\nIdentificador do Lote: LOT-0001; LOT-0002; LOT-0003; LOT-0004; LOT-0005; LOT-0006; LOT-0007; LOT-0008; LOT-0009; LOT-0010; LOT-0011; LOT-0012; LOT-0013; LOT-0014; LOT-0015; LOT-0016; LOT-0017\nTêm fundos EU? Não\n\n12 - DOCUMENTOS DE HABILITAÇÃO\nHabilitação para o exercício da atividade profissional: Não\n\n13 - CONDIÇÕES DE APRESENTAÇÃO\nPlataforma eletrónica utilizada pela entidade adjudicante: ACIN\nURL para Apresentação: https://www.acingov.pt\nAdmissibilidade da apresentação de propostas variantes: Não autorizado\nPrazo para apresentação das propostas: 24-10-2025 23:59\nPrazo durante o qual os concorrentes são obrigados a manter as respetivas propostas: 66 dias a contar do termo do prazo para a apresentação das propostas\nIndicação de Subcontratação na Proposta: Inexistência de indicação de subcontratação\n\n14 - PRESTAÇÃO DE CAUÇÃO\nPrestação de caução: Não\n\n15 - FORNECIMENTO DAS PEÇAS DO CONCURSO, APRESENTAÇÃO DE PEDIDOS DE PARTICIPAÇÃO E APRESENTAÇÃO DAS PROPOSTAS\nLink para acesso às peças do concurso (URL): https://www.acingov.pt/acingovprod/2/zonaPublica/zona_publica_c/donwloadProcedurePiece/OTg2OTMx\n\n20 - OUTROS REQUISITOS\nIdentificador do Lote: LOT-0001; LOT-0002; LOT-0003; LOT-0004; LOT-0005; LOT-0006; LOT-0007; LOT-0008; LOT-0009; LOT-0010; LOT-0011; LOT-0012; LOT-0013; LOT-0014; LOT-0015; LOT-0016; LOT-0017\nInformação sobre contratos reservados. Aplica-se a contratos reservados (54º-A)? Não\n\n21 - CRITÉRIO DE ADJUDICAÇÃO\nO Critério de adjudicação é diferenciado por lote? Não\nMultifator: Não\nMonofator:\nNome: Preço\n\n24 - CONDIÇÕES DO CONTRATO\nIdentificador do Lote: LOT-0001; LOT-0002; LOT-0003; LOT-0004; LOT-0005; LOT-0006; LOT-0007; LOT-0008; LOT-0009; LOT-0010; LOT-0011; LOT-0012; LOT-0013; LOT-0014; LOT-0015; LOT-0016; LOT-0017\nFaturação Eletrónica: Permitido\nObrigação de Subcontratação:\nCódigo da Obrigação de Subcontratação: Não é aplicável nenhuma obrigação de subcontratação.\n\n25 - COMPRA PÚBLICA ESTRATÉGICA\nCompra Pública Estratégica: Inexistência de contratação pública estratégica\n\n26 - INFORMAÇÕES ADICIONAIS\nIdentificador do Lote: LOT-0001; LOT-0002; LOT-0003; LOT-0004; LOT-0005; LOT-0006; LOT-0007; LOT-0008; LOT-0009; LOT-0010; LOT-0011; LOT-0012; LOT-0013; LOT-0014; LOT-0015; LOT-0016; LOT-0017\nContrato adequado para PME: Não\nCobertura ACP (Acordo dos Contratos Públicos da Organização Mundial do Comércio): Não\n\n27 - IDENTIFICAÇÃO E CONTACTOS DO ÓRGÃO DE RECURSOS ADMINISTRATIVOS\nDesignação: Presidente do Politécnico de Leiria\nEndereço: Rua General Norton de Matos, Ed. Sede do Instituto Politécnico de Leiria\nCódigo postal: 2410-191\nLocalidade: Leiria\nTelefone: 244830010\nFax: \nEndereço eletrónico: ipleiria@ipleiria.pt\nPrazo de interposição do recurso: 10 dias\n\n28 - IDENTIFICAÇÃO DO(S) AUTOR(ES) DE ANÚNCIO\nNome: Carlos Manuel da Silva Rabadão\nCargo: Presidente do IPLeiria\n419659652",
    "nipc": "600041581",
    "distrito": "Todos",
    "concelho": "Todos",
    "freguesia": "Todas",
    "site": "http://www.ipleiria.pt/sas/apresentacao/",
    "email": "sas@ipleiria.pt",
    "designacao_contrato": "Concurso Público SAS. 005/2025/2955 - Aquisição por lotes de produtos alimentares de mercearia",
    "descricao": "Concurso Público SAS. 005/2025/2955 - Aquisição por lotes de produtos alimentares de mercearia",
    "preco_base": "187.300,00 EUR",
    "prazo_execucao": "12 MESES",
    "prazo_apresentacao_propostas": "24-10-2025 23:59",
    "fundos_eu": "Não",
    "plataforma_eletronica": "ACIN",
    "url_procedimento": "https://www.acingov.pt",
    "autor_nome": "Carlos Manuel da Silva Rabadão",
    "autor_cargo": "Presidente do IPLeiria"
  },
  {
    "numero_procedimento": "N/A",
    "entidade": "Secretaria Regional das Finanças",
    "link": "https://diariodarepublica.pt/dr/detalhe/contrato-publico/27444-940780714",
    "detalhes_completos": "1 - IDENTIFICAÇÃO E CONTACTOS DA ENTIDADE ADJUDICANTE\nDesignação da entidade adjudicante: Secretaria Regional das Finanças\nNIPC: 671001310\nServiço/Órgão/Pessoa de contacto: Direção Regional de Informática\nEndereço: Palácio do Governo, Avenida Zarco\nCódigo postal: 9004-527\nLocalidade: Funchal\nPaís: Portugal\nNUT III: PT300\nDistrito: Região Autónoma da Madeira\nConcelho: Funchal\nFreguesia: Todas\nTelefone: 291212183\nFax: 291228418\nEndereço da Entidade (URL): https://www.madeira.gov.pt/srfinancas\nEndereço Eletrónico: gabinete.srf@madeira.gov.pt\neDelivery Gateway (URL): https://www.acingov.pt\nFunção da Organização: Adquirente\nNorma jurídica da Entidade Adjudicante: Organismo de direito público\nÁrea de atividade da Autoridade Adjudicante: Serviços públicos das administrações públicas\n\n2 - JORNAL OFICIAL DA UNIÃO EUROPEIA\nO procedimento a que este anúncio diz respeito também é publicitado no Jornal Oficial da União Europeia? Sim\n\n3 - AVISO\nModelo de Anúncio: Concurso público\nData de Envio do Anúncio: 15-10-2025\n\n5 - PROCESSO\nTipo de Procedimento: Concurso público\nPreço base do procedimento: Sim\nValor do preço base do procedimento: 543.482,83 EUR\nProcedimento com lotes? Não\n\n6 - OBJETO DO CONTRATO\nNúmero de referência interna: DRI-50/CP/2025\nDesignação do contrato: Aquisição de soluções tecnológicas para reforçar a Cibersegurança na Administração Pública Regional - Processo n.º DRI-50/CP/2025\nDescrição: Aquisição de soluções tecnológicas para reforçar a Cibersegurança na Administração Pública Regional - Processo n.º DRI-50/CP/2025\nOpções: Não\nTipo de Contrato Principal: Aquisição de Bens Móveis\nTipo de Contrato: Aquisição de Bens Móveis\nClassificação CPV (Vocabulário Comum para os Contratos Públicos)\nObjeto principal\nVocabulário Principal: 32420000\nPreço base s/IVA: 543.482,83 EUR\n\n7 - INDICAÇÕES ADICIONAIS\nO contrato envolve aquisição conjunta (satisfação de várias entidades)? Não\nO contrato é adjudicado por uma central de compras? Não\n\n8 - TÉCNICAS\nO concurso destina-se à celebração de um acordo-quadro? Inexistência de acordo-quadro\nÉ utilizado um leilão eletrónico? Não\nÉ adotada uma fase de negociação? Não\nSistema de Aquisição Dinâmico: Inexistência de sistema de aquisição dinâmico\n\n9 - LOCAL DA EXECUÇÃO DO CONTRATO\nLOCAL DA EXECUÇÃO DO CONTRATO (PROCEDIMENTO)\nPaís: Portugal\nNUT III: PT300\nLocalidade: Funchal\nDistrito: Região Autónoma da Madeira\nConcelho: Funchal\nFreguesia: Todas\n\n10 - PRAZO DE EXECUÇÃO DO CONTRATO\nPrazo de execução do contrato: 20 DIAS\nPrevisão de renovações: Não\n\n11 - FUNDOS EU\nTêm fundos EU? Sim\n\n12 - DOCUMENTOS DE HABILITAÇÃO\nHabilitação para o exercício da atividade profissional: Não\n\n13 - CONDIÇÕES DE APRESENTAÇÃO\nPlataforma eletrónica utilizada pela entidade adjudicante: ACIN\nURL para Apresentação: https://www.acingov.pt\nAdmissibilidade da apresentação de propostas variantes: Não autorizado\nPrazo para apresentação das propostas: 14-11-2025 17:00\nPrazo durante o qual os concorrentes são obrigados a manter as respetivas propostas: 120 dias a contar do termo do prazo para a apresentação das propostas\nApresentação de Catálogo Eletrónico: Permitido\nIndicação de Subcontratação na Proposta: Inexistência de indicação de subcontratação\n\n14 - PRESTAÇÃO DE CAUÇÃO\nPrestação de caução: Sim\nPercentagem: 2%\nDescrição da Garantia Exigida: O valor da caução é de 2.00% do preço contratual.\n\n15 - FORNECIMENTO DAS PEÇAS DO CONCURSO, APRESENTAÇÃO DE PEDIDOS DE PARTICIPAÇÃO E APRESENTAÇÃO DAS PROPOSTAS\nLink para acesso às peças do concurso (URL): https://www.acingov.pt/acingovprod/2/zonaPublica/zona_publica_c/donwloadProcedurePiece/OTg2OTIy\n\n20 - OUTROS REQUISITOS\nInformação sobre contratos reservados. Aplica-se a contratos reservados (54º-A)? Não\n\n21 - CRITÉRIO DE ADJUDICAÇÃO\nMultifator: Não\nMonofator:\nNome: Preço\n\n24 - CONDIÇÕES DO CONTRATO\nFaturação Eletrónica: Permitido\nObrigação de Subcontratação:\nCódigo da Obrigação de Subcontratação: Não é aplicável nenhuma obrigação de subcontratação.\n\n25 - COMPRA PÚBLICA ESTRATÉGICA\nCompra Pública Estratégica: Inexistência de contratação pública estratégica\n\n26 - INFORMAÇÕES ADICIONAIS\nContrato adequado para PME: Sim\nCobertura ACP (Acordo dos Contratos Públicos da Organização Mundial do Comércio): Não\n\n27 - IDENTIFICAÇÃO E CONTACTOS DO ÓRGÃO DE RECURSOS ADMINISTRATIVOS\nDesignação: Secretário Regional das Finanças\nEndereço: Palácio do Governo, Avenida Zarco\nCódigo postal: 9004-527\nLocalidade: Funchal\nTelefone: 291212183\nFax: 291212183\nEndereço eletrónico: gabinete.srf@madeira.gov.pt\nPrazo de interposição do recurso: 5 dias\n\n28 - IDENTIFICAÇÃO DO(S) AUTOR(ES) DE ANÚNCIO\nNome: César Martim Aguiar Baptista Rosa\nCargo: Diretor Regional de Informática\n419659977",
    "nipc": "671001310",
    "distrito": "Região Autónoma da Madeira",
    "concelho": "Funchal",
    "freguesia": "Todas",
    "site": "https://www.madeira.gov.pt/srfinancas",
    "email": "gabinete.srf@madeira.gov.pt",
    "designacao_contrato": "Aquisição de soluções tecnológicas para reforçar a Cibersegurança na Administração Pública Regional - Processo n.º DRI-50/CP/2025",
    "descricao": "Aquisição de soluções tecnológicas para reforçar a Cibersegurança na Administração Pública Regional - Processo n.º DRI-50/CP/2025",
    "preco_base": "543.482,83 EUR",
    "prazo_execucao": "20 DIAS",
    "prazo_apresentacao_propostas": "14-11-2025 17:00",
    "fundos_eu": "Sim",
    "plataforma_eletronica": "ACIN",
    "url_procedimento": "https://www.acingov.pt",
    "autor_nome": "César Martim Aguiar Baptista Rosa",
    "autor_cargo": "Diretor Regional de Informática"
  },
  {
    "numero_procedimento": "N/A",
    "entidade": "AnÃºncio de procedimento  n.Âº 27448/2025  -  DiÃ¡rio da RepÃºblica n.Âº 201/2025, SÃ©rie II de 2025-10-17",
    "link": "https://diariodarepublica.pt/dr/detalhe/contrato-publico/27448-940780722"
  },
  {
    "numero_procedimento": "N/A",
    "entidade": "AnÃºncio de procedimento  n.Âº 27449/2025  -  DiÃ¡rio da RepÃºblica n.Âº 201/2025, SÃ©rie II de 2025-10-17",
    "link": "https://diariodarepublica.pt/dr/detalhe/contrato-publico/27449-940780723"
  },
  {
    "numero_procedimento": "N/A",
    "entidade": "AnÃºncio de procedimento  n.Âº 27450/2025  -  DiÃ¡rio da RepÃºblica n.Âº 201/2025, SÃ©rie II de 2025-10-17",
    "link": "https://diariodarepublica.pt/dr/detalhe/contrato-publico/27450-940780724"
  },
  {
    "numero_procedimento": "N/A",
    "entidade": "AnÃºncio de procedimento  n.Âº 27451/2025  -  DiÃ¡rio da RepÃºblica n.Âº 201/2025, SÃ©rie II de 2025-10-17",
    "link": "https://diariodarepublica.pt/dr/detalhe/contrato-publico/27451-940780725"
  },
  {
    "numero_procedimento": "N/A",
    "entidade": "Fundação INATEL",
    "link": "https://diariodarepublica.pt/dr/detalhe/contrato-publico/27454-940780730",
    "detalhes_completos": "1 - IDENTIFICAÇÃO E CONTACTOS DA ENTIDADE ADJUDICANTE\nDesignação da entidade adjudicante: Fundação INATEL\nNIPC: 500122237\nServiço/Órgão/Pessoa de contacto: Marta Franco\nEndereço: marta.franco@inatel.pt\nCódigo postal: 1169-062\nLocalidade: Lisboa\nPaís: Portugal\nNUT III: PT170\nDistrito: Lisboa\nConcelho: Lisboa\nFreguesia: Freguesia de Arroios - Lisboa\nTelefone: 210027000\nFax: 210027000\nEndereço da Entidade (URL): https://www.inatel.pt/\nEndereço Eletrónico: marta.franco@inatel.pt\neDelivery Gateway (URL): https://www.acingov.pt\nFunção da Organização: Adquirente\nSubfunção da Organização: Organização cujo orçamento é utilizado para pagar o contrato; Organização que executa o pagamento; Organização que fornece informações adicionais sobre o processo de adjudicação; Organização que fornece mais informações sobre os prazos dos procedimentos de recurso; Organização que fornece acesso fora de linha aos documentos do concurso; Organização responsável pelo tratamento das propostas; Organização que recebe as propostas; Organização que trata os pedidos de participação; Organização que recebe pedidos de participação; Organização que fornece mais informações sobre os procedimentos de recurso; Organização que assina o contrato\nNorma jurídica da Entidade Adjudicante: Organismo de direito público\nÁrea de atividade da Autoridade Adjudicante: Atividades recreativas, culturais e religiosas\n\n2 - JORNAL OFICIAL DA UNIÃO EUROPEIA\nO procedimento a que este anúncio diz respeito também é publicitado no Jornal Oficial da União Europeia? Não\n\n3 - AVISO\nModelo de Anúncio: Concurso público\nData de Envio do Anúncio: 17-10-2025\n\n5 - PROCESSO\nTipo de Procedimento: Concurso público\nPreço base do procedimento: Sim\nValor do preço base do procedimento: 51.306,79 EUR\nProcedimento com lotes? Sim\nNº Máx. de Lotes Autorizado: 15\nNúmero máximo de lotes que podem ser adjudicados a um concorrente: 15\n\n6 - OBJETO DO CONTRATO\nNúmero de referência interna: P.25.214/NCP\nDesignação do contrato: Concurso público para aquisição de arroz, massas, leguminosas secas e farinha para o Restaurante Sant´Ana e para as Unidades Hoteleiras em Portugal Continental e na Região Autónoma da Madeira da Fundação INATEL\nDescrição: Aquisição de para arroz, massas, leguminosas secas e farinha para o Restaurante Sant´Ana e para as Unidades Hoteleiras em Portugal Continental e na Região Autónoma da Madeira da Fundação INATEL\nTipo de Contrato Principal: Aquisição de Bens Móveis\nTipo de Contrato: Aquisição de Bens Móveis\nClassificação CPV (Vocabulário Comum para os Contratos Públicos)\nObjeto principal\nVocabulário Principal: 15890000\nPreço base s/IVA: 51.306,79 EUR\nLotes: \nNº: LOT-0001\nDescrição do Lote: Arroz, Massas, Leguminosas Secas e Farinha\nPreço base s/IVA: 4.462,21 EUR\nClassificação CPV (Vocabulário Comum para os Contratos Públicos)\nObjeto principal\nVocabulário Principal: 15890000\nNº: LOT-0002\nDescrição do Lote: Arroz, Massas, Leguminosas Secas e Farinha\nPreço base s/IVA: 1.228,70 EUR\nClassificação CPV (Vocabulário Comum para os Contratos Públicos)\nObjeto principal\nVocabulário Principal: 15890000\nNº: LOT-0003\nDescrição do Lote: Arroz, Massas, Leguminosas Secas e Farinha\nPreço base s/IVA: 2.651,43 EUR\nClassificação CPV (Vocabulário Comum para os Contratos Públicos)\nObjeto principal\nVocabulário Principal: 15890000\nNº: LOT-0004\nDescrição do Lote: Arroz, Massas, Leguminosas Secas e Farinha\nPreço base s/IVA: 2.425,74 EUR\nClassificação CPV (Vocabulário Comum para os Contratos Públicos)\nObjeto principal\nVocabulário Principal: 15890000\nNº: LOT-0005\nDescrição do Lote: Arroz, Massas, Leguminosas Secas e Farinha\nPreço base s/IVA: 2.093,22 EUR\nClassificação CPV (Vocabulário Comum para os Contratos Públicos)\nObjeto principal\nVocabulário Principal: 15890000\nNº: LOT-0006\nDescrição do Lote: Arroz, Massas, Leguminosas Secas e Farinha\nPreço base s/IVA: 4.436,15 EUR\nClassificação CPV (Vocabulário Comum para os Contratos Públicos)\nObjeto principal\nVocabulário Principal: 15890000\nNº: LOT-0007\nDescrição do Lote: Arroz, Massas, Leguminosas Secas e Farinha\nPreço base s/IVA: 2.052,05 EUR\nClassificação CPV (Vocabulário Comum para os Contratos Públicos)\nObjeto principal\nVocabulário Principal: 15890000\nNº: LOT-0008\nDescrição do Lote: Arroz, Massas, Leguminosas Secas e Farinha\nPreço base s/IVA: 1.354,51 EUR\nClassificação CPV (Vocabulário Comum para os Contratos Públicos)\nObjeto principal\nVocabulário Principal: 15890000\nNº: LOT-0009\nDescrição do Lote: Arroz, Massas, Leguminosas Secas e Farinha\nPreço base s/IVA: 1.290,58 EUR\nClassificação CPV (Vocabulário Comum para os Contratos Públicos)\nObjeto principal\nVocabulário Principal: 15890000\nNº: LOT-0010\nDescrição do Lote: Arroz, Massas, Leguminosas Secas e Farinha\nPreço base s/IVA: 5.616,85 EUR\nClassificação CPV (Vocabulário Comum para os Contratos Públicos)\nObjeto principal\nVocabulário Principal: 15890000\nNº: LOT-0011\nDescrição do Lote: Arroz, Massas, Leguminosas Secas e Farinha\nPreço base s/IVA: 5.317,58 EUR\nClassificação CPV (Vocabulário Comum para os Contratos Públicos)\nObjeto principal\nVocabulário Principal: 15890000\nNº: LOT-0012\nDescrição do Lote: Arroz, Massas, Leguminosas Secas e Farinha\nPreço base s/IVA: 3.155,46 EUR\nClassificação CPV (Vocabulário Comum para os Contratos Públicos)\nObjeto principal\nVocabulário Principal: 15890000\nNº: LOT-0013\nDescrição do Lote: Arroz, Massas, Leguminosas Secas e Farinha\nPreço base s/IVA: 4.658,84 EUR\nClassificação CPV (Vocabulário Comum para os Contratos Públicos)\nObjeto principal\nVocabulário Principal: 15890000\nNº: LOT-0014\nDescrição do Lote: Arroz, Massas, Leguminosas Secas e Farinha\nPreço base s/IVA: 8.360,44 EUR\nClassificação CPV (Vocabulário Comum para os Contratos Públicos)\nObjeto principal\nVocabulário Principal: 15890000\nNº: LOT-0015\nDescrição do Lote: Arroz, Massas, Leguminosas Secas e Farinha\nPreço base s/IVA: 2.203,03 EUR\nClassificação CPV (Vocabulário Comum para os Contratos Públicos)\nObjeto principal\nVocabulário Principal: 15890000\n\n7 - INDICAÇÕES ADICIONAIS\nO contrato envolve aquisição conjunta (satisfação de várias entidades)? Não\nO contrato é adjudicado por uma central de compras? Não\n\n8 - TÉCNICAS\nO concurso destina-se à celebração de um acordo-quadro? Inexistência de acordo-quadro\nÉ utilizado um leilão eletrónico? Não\nÉ adotada uma fase de negociação? Não\nSistema de Aquisição Dinâmico: Inexistência de sistema de aquisição dinâmico\n\n9 - LOCAL DA EXECUÇÃO DO CONTRATO\nLOCAL DA EXECUÇÃO DO CONTRATO (PROCEDIMENTO)\nPaís: Portugal\nNUT III: PT111\nLocalidade: todas\nDistrito: Todos\nConcelho: Todos\nFreguesia: Todas\nLOCAL DA EXECUÇÃO DO CONTRATO (LOTE)\nIdentificador do Lote: LOT-0001; LOT-0002; LOT-0003; LOT-0004; LOT-0005; LOT-0006; LOT-0007; LOT-0008; LOT-0009; LOT-0010; LOT-0011; LOT-0012; LOT-0013; LOT-0014; LOT-0015\nPaís: Portugal\nNUT III: PT111\nLocalidade: todas\nDistrito: Todos\nConcelho: Todos\nFreguesia: Todas\n\n10 - PRAZO DE EXECUÇÃO DO CONTRATO\nIdentificador do Lote: LOT-0001; LOT-0002; LOT-0003; LOT-0004; LOT-0005; LOT-0006; LOT-0007; LOT-0008; LOT-0009; LOT-0010; LOT-0011; LOT-0012; LOT-0013; LOT-0014; LOT-0015\nData de Início: 10-12-2025\nData de Fim: 09-12-2026\nPrevisão de renovações: Não\n\n11 - FUNDOS EU\nIdentificador do Lote: LOT-0001; LOT-0002; LOT-0003; LOT-0004; LOT-0005; LOT-0006; LOT-0007; LOT-0008; LOT-0009; LOT-0010; LOT-0011; LOT-0012; LOT-0013; LOT-0014; LOT-0015\nTêm fundos EU? Não\n\n12 - DOCUMENTOS DE HABILITAÇÃO\nHabilitação para o exercício da atividade profissional: Não\n\n13 - CONDIÇÕES DE APRESENTAÇÃO\nPlataforma eletrónica utilizada pela entidade adjudicante: ACIN\nURL para Apresentação: https://www.acingov.pt\nAdmissibilidade da apresentação de propostas variantes: Não autorizado\nPrazo para apresentação das propostas: 23-10-2025 23:59\nPrazo durante o qual os concorrentes são obrigados a manter as respetivas propostas: 90 dias a contar do termo do prazo para a apresentação das propostas\nIndicação de Subcontratação na Proposta: Inexistência de indicação de subcontratação\n\n14 - PRESTAÇÃO DE CAUÇÃO\nPrestação de caução: Não\n\n15 - FORNECIMENTO DAS PEÇAS DO CONCURSO, APRESENTAÇÃO DE PEDIDOS DE PARTICIPAÇÃO E APRESENTAÇÃO DAS PROPOSTAS\nLink para acesso às peças do concurso (URL): https://www.acingov.pt/acingovprod/2/zonaPublica/zona_publica_c/donwloadProcedurePiece/OTg4MzEz\n\n20 - OUTROS REQUISITOS\nIdentificador do Lote: LOT-0001; LOT-0002; LOT-0003; LOT-0004; LOT-0005; LOT-0006; LOT-0007; LOT-0008; LOT-0009; LOT-0010; LOT-0011; LOT-0012; LOT-0013; LOT-0014; LOT-0015\nInformação sobre contratos reservados. Aplica-se a contratos reservados (54º-A)? Não\n\n21 - CRITÉRIO DE ADJUDICAÇÃO\nO Critério de adjudicação é diferenciado por lote? Não\nMultifator: Não\nMonofator:\nNome: Preço\n\n24 - CONDIÇÕES DO CONTRATO\nIdentificador do Lote: LOT-0001; LOT-0002; LOT-0003; LOT-0004; LOT-0005; LOT-0006; LOT-0007; LOT-0008; LOT-0009; LOT-0010; LOT-0011; LOT-0012; LOT-0013; LOT-0014; LOT-0015\nFaturação Eletrónica: Permitido\nObrigação de Subcontratação:\nCódigo da Obrigação de Subcontratação: Não é aplicável nenhuma obrigação de subcontratação.\n\n25 - COMPRA PÚBLICA ESTRATÉGICA\nCompra Pública Estratégica: Inexistência de contratação pública estratégica\n\n26 - INFORMAÇÕES ADICIONAIS\nIdentificador do Lote: LOT-0001; LOT-0002; LOT-0003; LOT-0004; LOT-0005; LOT-0006; LOT-0007; LOT-0008; LOT-0009; LOT-0010; LOT-0011; LOT-0012; LOT-0013; LOT-0014; LOT-0015\nContrato adequado para PME: Sim\nCobertura ACP (Acordo dos Contratos Públicos da Organização Mundial do Comércio): Não\n\n27 - IDENTIFICAÇÃO E CONTACTOS DO ÓRGÃO DE RECURSOS ADMINISTRATIVOS\nDesignação: Conselho de Administração\nEndereço: Calçada de Santana, nº 180\nCódigo postal: 1169-062\nLocalidade: Lisboa\nTelefone: 210027000\nFax: 210027000\nEndereço eletrónico: marta.franco@inatel.pt\n\n28 - IDENTIFICAÇÃO DO(S) AUTOR(ES) DE ANÚNCIO\nNome: Tiago Tenreiro Alves\nCargo: Técnico\n419671826",
    "nipc": "500122237",
    "distrito": "Lisboa",
    "concelho": "Lisboa",
    "freguesia": "Freguesia de Arroios - Lisboa",
    "site": "https://www.inatel.pt/",
    "email": "marta.franco@inatel.pt",
    "designacao_contrato": "Concurso público para aquisição de arroz, massas, leguminosas secas e farinha para o Restaurante Sant´Ana e para as Unidades Hoteleiras em Portugal Continental e na Região Autónoma da Madeira da Fundação INATEL",
    "descricao": "Aquisição de para arroz, massas, leguminosas secas e farinha para o Restaurante Sant´Ana e para as Unidades Hoteleiras em Portugal Continental e na Região Autónoma da Madeira da Fundação INATEL",
    "preco_base": "51.306,79 EUR",
    "prazo_execucao": null,
    "prazo_apresentacao_propostas": "23-10-2025 23:59",
    "fundos_eu": "Não",
    "plataforma_eletronica": "ACIN",
    "url_procedimento": "https://www.acingov.pt",
    "autor_nome": "Tiago Tenreiro Alves",
    "autor_cargo": "Técnico"
  },
  {
    "numero_procedimento": "N/A",
    "entidade": "AnÃºncio de procedimento  n.Âº 27456/2025  -  DiÃ¡rio da RepÃºblica n.Âº 201/2025, SÃ©rie II de 2025-10-17",
    "link": "https://diariodarepublica.pt/dr/detalhe/contrato-publico/27456-940780739"
  },
  {
    "numero_procedimento": "N/A",
    "entidade": "Serviço de Saúde da Região Autónoma da Madeira, EPE-RAM",
    "link": "https://diariodarepublica.pt/dr/detalhe/contrato-publico/27457-940780740",
    "detalhes_completos": "1 - IDENTIFICAÇÃO E CONTACTOS DA ENTIDADE ADJUDICANTE\nDesignação da entidade adjudicante: Serviço de Saúde da Região Autónoma da Madeira, EPE-RAM\nNIPC: 511228848\nServiço/Órgão/Pessoa de contacto: Núcleo Aprovisionamento\nEndereço: Avenida Luís Camões nº57\nCódigo postal: 9004-514\nLocalidade: Funchal\nPaís: Portugal\nNUT III: PT300\nDistrito: Região Autónoma da Madeira\nConcelho: Funchal\nFreguesia: Freguesia de São Pedro (Funchal)\nTelefone: 291705610\nFax: 291742545\nEndereço da Entidade (URL): www.sesaram.pt\nEndereço Eletrónico: aprovisionamento@sesaram.pt\neDelivery Gateway (URL): https://www.acingov.pt\nFunção da Organização: Adquirente\nNorma jurídica da Entidade Adjudicante: Organismo de direito público\nÁrea de atividade da Autoridade Adjudicante: Serviços públicos das administrações públicas\n\n2 - JORNAL OFICIAL DA UNIÃO EUROPEIA\nO procedimento a que este anúncio diz respeito também é publicitado no Jornal Oficial da União Europeia? Sim\n\n3 - AVISO\nModelo de Anúncio: Concurso público\nData de Envio do Anúncio: 15-10-2025\n\n5 - PROCESSO\nTipo de Procedimento: Concurso público\nPreço base do procedimento: Sim\nValor do preço base do procedimento: 786.750,00 EUR\nProcedimento com lotes? Sim\nNº Máx. de Lotes Autorizado: 11\nNúmero máximo de lotes que podem ser adjudicados a um concorrente: 11\n\n6 - OBJETO DO CONTRATO\nNúmero de referência interna: ICP20250088\nDesignação do contrato: ICP20250088-MAT. TERAPEUT. DA DOR - RADIOFREQUENCIA\nDescrição: ICP20250088-MAT. TERAPEUT. DA DOR - RADIOFREQUENCIA\nOpções: Não\nTipo de Contrato Principal: Aquisição de Bens Móveis\nTipo de Contrato: Aquisição de Bens Móveis\nClassificação CPV (Vocabulário Comum para os Contratos Públicos)\nObjeto principal\nVocabulário Principal: 33190000\nPreço base s/IVA: 786.750,00 EUR\nLotes: \nNº: LOT-0001\nDescrição do Lote: CONJ.DESC. P/RADIOFREQ. C/AG RETA 22G 5CM COMP. C/ PONTA ATIVA 5MM\nPreço base s/IVA: 11.700,00 EUR\nClassificação CPV (Vocabulário Comum para os Contratos Públicos)\nObjeto principal\nVocabulário Principal: 33190000\nNº: LOT-0002\nDescrição do Lote: CONJ. DESC. P/ RADIOFREQ. C/AGULHA RETA 20G 10CM COMP. C/PONTA ATIVA 10MM\nPreço base s/IVA: 64.800,00 EUR\nClassificação CPV (Vocabulário Comum para os Contratos Públicos)\nObjeto principal\nVocabulário Principal: 33190000\nNº: LOT-0003\nDescrição do Lote: CONJ.DESC.P/RADIOFREQ.C/AGULHA 22G 10CM COMP.C/PONTA ATIVA5MM(BLUNT CURVED)\nPreço base s/IVA: 5.910,00 EUR\nClassificação CPV (Vocabulário Comum para os Contratos Públicos)\nObjeto principal\nVocabulário Principal: 33190000\nNº: LOT-0004\nDescrição do Lote: CONJ.DESC.P/RADIOFREQ.C/CAN.HIBRIDA RETA 22G 10CM COMP.C/PONTA ATIVA 5MM\nPreço base s/IVA: 18.600,00 EUR\nClassificação CPV (Vocabulário Comum para os Contratos Públicos)\nObjeto principal\nVocabulário Principal: 33190000\nNº: LOT-0005\nDescrição do Lote: CONJ.DESC.RADIOF.C/3CAN.HIBRIDAS RETA 20G 10CM COMP.C/PONTA ATIVA 10MM\nPreço base s/IVA: 111.360,00 EUR\nClassificação CPV (Vocabulário Comum para os Contratos Públicos)\nObjeto principal\nVocabulário Principal: 33190000\nNº: LOT-0006\nDescrição do Lote: CONJ.DESC.P/RADIOFREQ. C/CAN.HIBRIDA RETA 20G 10CM COMP.C/PONTA ATIVA 10MM\nPreço base s/IVA: 464.160,00 EUR\nClassificação CPV (Vocabulário Comum para os Contratos Públicos)\nObjeto principal\nVocabulário Principal: 33190000\nNº: LOT-0007\nDescrição do Lote: CONJ.DESC.P/RADIOFREQ.BIPOL(2CANAIS)C/CAN.HIBRIDA.RETA20G C/10CM P. ATIVA 5MM\nPreço base s/IVA: 44.400,00 EUR\nClassificação CPV (Vocabulário Comum para os Contratos Públicos)\nObjeto principal\nVocabulário Principal: 33190000\nNº: LOT-0008\nDescrição do Lote: CONJ.DESC.P/RADIOFREQ. C/CAN.HIBRIDA RETA 20G 15CM COMP.C/PONTA ATIVA 10MM\nPreço base s/IVA: 11.160,00 EUR\nClassificação CPV (Vocabulário Comum para os Contratos Públicos)\nObjeto principal\nVocabulário Principal: 33190000\nNº: LOT-0009\nDescrição do Lote: CANULA ECOGENICA DESC.RETA DE 10CM C/PONTA ACTIVA 10MM 22G\nPreço base s/IVA: 15.960,00 EUR\nClassificação CPV (Vocabulário Comum para os Contratos Públicos)\nObjeto principal\nVocabulário Principal: 33190000\nNº: LOT-0010\nDescrição do Lote: SISTEMA RCE DE RADIOFREQUENCIA EPIDURAL\nPreço base s/IVA: 21.900,00 EUR\nClassificação CPV (Vocabulário Comum para os Contratos Públicos)\nObjeto principal\nVocabulário Principal: 33190000\nNº: LOT-0011\nDescrição do Lote: ELECTRODO (PLACA) DE DISPERSAO\nPreço base s/IVA: 16.800,00 EUR\nClassificação CPV (Vocabulário Comum para os Contratos Públicos)\nObjeto principal\nVocabulário Principal: 33190000\n\n7 - INDICAÇÕES ADICIONAIS\nO contrato envolve aquisição conjunta (satisfação de várias entidades)? Não\nO contrato é adjudicado por uma central de compras? Não\n\n8 - TÉCNICAS\nO concurso destina-se à celebração de um acordo-quadro? Inexistência de acordo-quadro\nÉ utilizado um leilão eletrónico? Não\nÉ adotada uma fase de negociação? Não\nSistema de Aquisição Dinâmico: Inexistência de sistema de aquisição dinâmico\n\n9 - LOCAL DA EXECUÇÃO DO CONTRATO\nLOCAL DA EXECUÇÃO DO CONTRATO (PROCEDIMENTO)\nPaís: Portugal\nNUT III: PT300\nLocalidade: Freguesia de São Pedro (Funchal)\nDistrito: Região Autónoma da Madeira\nConcelho: Funchal\nFreguesia: Freguesia de São Pedro (Funchal)\nLOCAL DA EXECUÇÃO DO CONTRATO (LOTE)\nIdentificador do Lote: LOT-0001; LOT-0002; LOT-0003; LOT-0004; LOT-0005; LOT-0006; LOT-0007; LOT-0008; LOT-0009; LOT-0010; LOT-0011\nPaís: Portugal\nNUT III: PT300\nLocalidade: Funchal\nDistrito: Região Autónoma da Madeira\nConcelho: Funchal\nFreguesia: Freguesia de São Pedro (Funchal)\n\n10 - PRAZO DE EXECUÇÃO DO CONTRATO\nIdentificador do Lote: LOT-0001; LOT-0002; LOT-0003; LOT-0004; LOT-0005; LOT-0006; LOT-0007; LOT-0008; LOT-0009; LOT-0010; LOT-0011\nPrazo de execução do contrato: 36 MESES\nPrevisão de renovações: Não\n\n11 - FUNDOS EU\nIdentificador do Lote: LOT-0001; LOT-0002; LOT-0003; LOT-0004; LOT-0005; LOT-0006; LOT-0007; LOT-0008; LOT-0009; LOT-0010; LOT-0011\nTêm fundos EU? Não\n\n12 - DOCUMENTOS DE HABILITAÇÃO\nHabilitação para o exercício da atividade profissional: Não\n\n13 - CONDIÇÕES DE APRESENTAÇÃO\nPlataforma eletrónica utilizada pela entidade adjudicante: ACIN\nURL para Apresentação: https://www.acingov.pt\nAdmissibilidade da apresentação de propostas variantes: Não autorizado\nPrazo para apresentação das propostas: 17-11-2025 17:00\nPrazo durante o qual os concorrentes são obrigados a manter as respetivas propostas: 66 dias a contar do termo do prazo para a apresentação das propostas\nApresentação de Catálogo Eletrónico: Permitido\nIndicação de Subcontratação na Proposta: Inexistência de indicação de subcontratação\n\n14 - PRESTAÇÃO DE CAUÇÃO\nPrestação de caução: Sim\nPercentagem: 2%\nDescrição da Garantia Exigida: O valor da caução é de 2.00% do preço contratual.\n\n15 - FORNECIMENTO DAS PEÇAS DO CONCURSO, APRESENTAÇÃO DE PEDIDOS DE PARTICIPAÇÃO E APRESENTAÇÃO DAS PROPOSTAS\nLink para acesso às peças do concurso (URL): https://www.acingov.pt/acingovprod/2/zonaPublica/zona_publica_c/donwloadProcedurePiece/OTg2MTQz\n\n20 - OUTROS REQUISITOS\nIdentificador do Lote: LOT-0001; LOT-0002; LOT-0003; LOT-0004; LOT-0005; LOT-0006; LOT-0007; LOT-0008; LOT-0009; LOT-0010; LOT-0011\nInformação sobre contratos reservados. Aplica-se a contratos reservados (54º-A)? Não\n\n21 - CRITÉRIO DE ADJUDICAÇÃO\nO Critério de adjudicação é diferenciado por lote? Não\nMultifator: Sim\nFator: \nNome: Preço\nPonderação: 50%\nSubfatores: Não\nFator: \nNome: Outros\nOutro Nome: Valia Técnica\nPonderação: 30%\nSubfatores: Não\nFator: \nNome: Outros\nOutro Nome: Formação\nPonderação: 20%\nSubfatores: Não\n\n24 - CONDIÇÕES DO CONTRATO\nIdentificador do Lote: LOT-0001; LOT-0002; LOT-0003; LOT-0004; LOT-0005; LOT-0006; LOT-0007; LOT-0008; LOT-0009; LOT-0010; LOT-0011\nFaturação Eletrónica: Permitido\nObrigação de Subcontratação:\nCódigo da Obrigação de Subcontratação: Não é aplicável nenhuma obrigação de subcontratação.\n\n25 - COMPRA PÚBLICA ESTRATÉGICA\nCompra Pública Estratégica: Inexistência de contratação pública estratégica\n\n26 - INFORMAÇÕES ADICIONAIS\nIdentificador do Lote: LOT-0001; LOT-0002; LOT-0003; LOT-0004; LOT-0005; LOT-0006; LOT-0007; LOT-0008; LOT-0009; LOT-0010; LOT-0011\nContrato adequado para PME: Não\nCobertura ACP (Acordo dos Contratos Públicos da Organização Mundial do Comércio): Não\n\n27 - IDENTIFICAÇÃO E CONTACTOS DO ÓRGÃO DE RECURSOS ADMINISTRATIVOS\nDesignação: Conselho de Administração\nEndereço: Avenida Luís Camões nº57\nCódigo postal: 9004-514\nLocalidade: Funchal\nTelefone: 291705610\nFax: \nEndereço eletrónico: aprovisionamento@sesaram.pt\n\n28 - IDENTIFICAÇÃO DO(S) AUTOR(ES) DE ANÚNCIO\nNome: Patrícia José Fernandes Aveiro\nCargo: Assistente Operacional\n419658729",
    "nipc": "511228848",
    "distrito": "Região Autónoma da Madeira",
    "concelho": "Funchal",
    "freguesia": "Freguesia de São Pedro (Funchal)",
    "site": "www.sesaram.pt",
    "email": "aprovisionamento@sesaram.pt",
    "designacao_contrato": "ICP20250088-MAT. TERAPEUT. DA DOR - RADIOFREQUENCIA",
    "descricao": "ICP20250088-MAT. TERAPEUT. DA DOR - RADIOFREQUENCIA",
    "preco_base": "786.750,00 EUR",
    "prazo_execucao": "36 MESES",
    "prazo_apresentacao_propostas": "17-11-2025 17:00",
    "fundos_eu": "Não",
    "plataforma_eletronica": "ACIN",
    "url_procedimento": "https://www.acingov.pt",
    "autor_nome": "Patrícia José Fernandes Aveiro",
    "autor_cargo": "Assistente Operacional"
  },
  {
    "numero_procedimento": "N/A",
    "entidade": "Município de Alijó",
    "link": "https://diariodarepublica.pt/dr/detalhe/contrato-publico/27458-940780741",
    "detalhes_completos": "1 - IDENTIFICAÇÃO E CONTACTOS DA ENTIDADE ADJUDICANTE\nDesignação da entidade adjudicante: Município de Alijó\nNIPC: 506859487\nServiço/Órgão/Pessoa de contacto: Presidente\nEndereço: Rua General Alves Pedrosa, 13\nCódigo postal: 5070-051\nLocalidade: Alijó\nPaís: Portugal\nNUT III: PT11D\nDistrito: Vila Real\nConcelho: Alijó\nFreguesia: Todas\nTelefone: 259957100\nFax: 259959738\nEndereço da Entidade (URL): www.cm-alijo.pt\nEndereço Eletrónico: geral@cm-alijo.pt\neDelivery Gateway (URL): https://www.acingov.pt\nFunção da Organização: Adquirente\nNorma jurídica da Entidade Adjudicante: Organismo de direito público\nÁrea de atividade da Autoridade Adjudicante: Serviços públicos das administrações públicas\n\n2 - JORNAL OFICIAL DA UNIÃO EUROPEIA\nO procedimento a que este anúncio diz respeito também é publicitado no Jornal Oficial da União Europeia? Sim\n\n3 - AVISO\nModelo de Anúncio: Concurso público\nData de Envio do Anúncio: 15-10-2025\n\n5 - PROCESSO\nTipo de Procedimento: Concurso público\nPreço base do procedimento: Sim\nValor do preço base do procedimento: 545.500,00 EUR\nProcedimento com lotes? Sim\nNº Máx. de Lotes Autorizado: 4\nNúmero máximo de lotes que podem ser adjudicados a um concorrente: 4\n\n6 - OBJETO DO CONTRATO\nNúmero de referência interna: Proc.-452/2025 AA DGO\nDesignação do contrato: Aquisição de serviços na área de Seguros\nDescrição: Aquisição de serviços na área de Seguros\nOpções: Não\nTipo de Contrato Principal: Aquisição de Serviços\nTipo de Contrato: Aquisição de Serviços\nClassificação CPV (Vocabulário Comum para os Contratos Públicos)\nObjeto principal\nVocabulário Principal: 66510000\nPreço base s/IVA: 545.500,00 EUR\nLotes: \nNº: LOT-0001\nDescrição do Lote: Aquisição de serviços na área de Seguros em Acidente de Trabalho\nPreço base s/IVA: 215.000,00 EUR\nClassificação CPV (Vocabulário Comum para os Contratos Públicos)\nObjeto principal\nVocabulário Principal: 66510000\nNº: LOT-0002\nDescrição do Lote: Aquisição de serviços na área de Seguros Pessoais\nPreço base s/IVA: 105.000,00 EUR\nClassificação CPV (Vocabulário Comum para os Contratos Públicos)\nObjeto principal\nVocabulário Principal: 66510000\nNº: LOT-0003\nDescrição do Lote: Aquisição de serviços na área de Seguros Património e Responsabilidade Civil\nPreço base s/IVA: 210.000,00 EUR\nClassificação CPV (Vocabulário Comum para os Contratos Públicos)\nObjeto principal\nVocabulário Principal: 66510000\nNº: LOT-0004\nDescrição do Lote: Aquisição de serviços na área de Seguros Responsabilidade Ambiental\nPreço base s/IVA: 15.500,00 EUR\nClassificação CPV (Vocabulário Comum para os Contratos Públicos)\nObjeto principal\nVocabulário Principal: 66510000\n\n7 - INDICAÇÕES ADICIONAIS\nO contrato envolve aquisição conjunta (satisfação de várias entidades)? Não\nO contrato é adjudicado por uma central de compras? Não\n\n8 - TÉCNICAS\nO concurso destina-se à celebração de um acordo-quadro? Inexistência de acordo-quadro\nÉ utilizado um leilão eletrónico? Não\nÉ adotada uma fase de negociação? Não\nSistema de Aquisição Dinâmico: Inexistência de sistema de aquisição dinâmico\n\n9 - LOCAL DA EXECUÇÃO DO CONTRATO\nLOCAL DA EXECUÇÃO DO CONTRATO (PROCEDIMENTO)\nPaís: Portugal\nNUT III: PT11D\nLocalidade: Freguesia de Alijó\nDistrito: Vila Real\nConcelho: Alijó\nFreguesia: Freguesia de Alijó\nLOCAL DA EXECUÇÃO DO CONTRATO (LOTE)\nIdentificador do Lote: LOT-0001; LOT-0002; LOT-0003; LOT-0004\nPaís: Portugal\nNUT III: PT11D\nLocalidade: Freguesia de Alijó\nDistrito: Vila Real\nConcelho: Alijó\nFreguesia: Freguesia de Alijó\n\n10 - PRAZO DE EXECUÇÃO DO CONTRATO\nIdentificador do Lote: LOT-0001; LOT-0002; LOT-0003; LOT-0004\nPrazo de execução do contrato: 3 ANOS\nPrevisão de renovações: Não\n\n11 - FUNDOS EU\nIdentificador do Lote: LOT-0001; LOT-0002; LOT-0003; LOT-0004\nTêm fundos EU? Não\n\n12 - DOCUMENTOS DE HABILITAÇÃO\nHabilitação para o exercício da atividade profissional: Sim\nTipo: Certificado\nDescrição: Certidão emitida pela ASF  Autoridade de Supervisão de Seguros e Fundos de Pensões a declarar que o concorrente está autorizado a exercer a atividade seguradora em Portugal\n\n13 - CONDIÇÕES DE APRESENTAÇÃO\nPlataforma eletrónica utilizada pela entidade adjudicante: ACIN\nURL para Apresentação: https://www.acingov.pt\nAdmissibilidade da apresentação de propostas variantes: Não autorizado\nPrazo para apresentação das propostas: 14-11-2025 23:59\nPrazo durante o qual os concorrentes são obrigados a manter as respetivas propostas: 66 dias a contar do termo do prazo para a apresentação das propostas\nApresentação de Catálogo Eletrónico: Permitido\nIndicação de Subcontratação na Proposta: Inexistência de indicação de subcontratação\n\n14 - PRESTAÇÃO DE CAUÇÃO\nPrestação de caução: Não\n\n15 - FORNECIMENTO DAS PEÇAS DO CONCURSO, APRESENTAÇÃO DE PEDIDOS DE PARTICIPAÇÃO E APRESENTAÇÃO DAS PROPOSTAS\nLink para acesso às peças do concurso (URL): https://www.acingov.pt/acingovprod/2/zonaPublica/zona_publica_c/donwloadProcedurePiece/OTg1MjMx\n\n20 - OUTROS REQUISITOS\nIdentificador do Lote: LOT-0001; LOT-0002; LOT-0003; LOT-0004\nInformação sobre contratos reservados. Aplica-se a contratos reservados (54º-A)? Não\n\n21 - CRITÉRIO DE ADJUDICAÇÃO\nO Critério de adjudicação é diferenciado por lote? Não\nMultifator: Não\nMonofator:\nNome: Preço\n\n24 - CONDIÇÕES DO CONTRATO\nIdentificador do Lote: LOT-0001; LOT-0002; LOT-0003; LOT-0004\nFaturação Eletrónica: Permitido\nObrigação de Subcontratação:\nCódigo da Obrigação de Subcontratação: Não é aplicável nenhuma obrigação de subcontratação.\n\n25 - COMPRA PÚBLICA ESTRATÉGICA\nCompra Pública Estratégica: Inexistência de contratação pública estratégica\n\n26 - INFORMAÇÕES ADICIONAIS\nIdentificador do Lote: LOT-0001; LOT-0002; LOT-0003; LOT-0004\nContrato adequado para PME: Não\nCobertura ACP (Acordo dos Contratos Públicos da Organização Mundial do Comércio): Não\n\n27 - IDENTIFICAÇÃO E CONTACTOS DO ÓRGÃO DE RECURSOS ADMINISTRATIVOS\nDesignação: Tribunal Administrativo e Fiscal de Mirandela\nEndereço: Rua da República, 70\nCódigo postal: 5370-347\nLocalidade: Mirandela\nTelefone: 278201770\nFax: 213506001\nEndereço eletrónico: mirandela.taf@tribunais.org.pt\nPrazo de interposição do recurso: 30 dias\n\n28 - IDENTIFICAÇÃO DO(S) AUTOR(ES) DE ANÚNCIO\nNome: José Rodrigues Paredes\nCargo: Presidente da Câmara\n419658494",
    "nipc": "506859487",
    "distrito": "Vila Real",
    "concelho": "Alijó",
    "freguesia": "Todas",
    "site": "www.cm-alijo.pt",
    "email": "geral@cm-alijo.pt",
    "designacao_contrato": "Aquisição de serviços na área de Seguros",
    "descricao": "Aquisição de serviços na área de Seguros",
    "preco_base": "545.500,00 EUR",
    "prazo_execucao": "3 ANOS",
    "prazo_apresentacao_propostas": "14-11-2025 23:59",
    "fundos_eu": "Não",
    "plataforma_eletronica": "ACIN",
    "url_procedimento": "https://www.acingov.pt",
    "autor_nome": "José Rodrigues Paredes",
    "autor_cargo": "Presidente da Câmara"
  },
  {
    "numero_procedimento": "N/A",
    "entidade": "AnÃºncio de procedimento  n.Âº 27459/2025  -  DiÃ¡rio da RepÃºblica n.Âº 201/2025, SÃ©rie II de 2025-10-17",
    "link": "https://diariodarepublica.pt/dr/detalhe/contrato-publico/27459-940780750"
  },
  {
    "numero_procedimento": "N/A",
    "entidade": "AnÃºncio de procedimento  n.Âº 27400/2025  -  DiÃ¡rio da RepÃºblica n.Âº 201/2025, SÃ©rie II de 2025-10-17",
    "link": "https://diariodarepublica.pt/dr/detalhe/contrato-publico/27400-940780753"
  },
  {
    "numero_procedimento": "N/A",
    "entidade": "Município da Póvoa de Lanhoso",
    "link": "https://diariodarepublica.pt/dr/detalhe/contrato-publico/27464-940780754",
    "detalhes_completos": "Alteração do Anúncio de procedimento n.º 26541/2025, de 2025-10-09, com o ID 419635635\n\n1 - IDENTIFICAÇÃO E CONTACTOS DA ENTIDADE ADJUDICANTE\nDesignação da entidade adjudicante: Município da Póvoa de Lanhoso\nNIPC: 506632920\nEndereço: Av. República, Póvoa De Lanhoso\nCódigo postal: 4830-513\nLocalidade: Póvoa de Lanhoso\nPaís: Portugal\nNUT III: PT119\nDistrito: Braga\nConcelho: Póvoa de Lanhoso\nFreguesia: Freguesia de Póvoa de Lanhoso (Nossa Senhora do Amparo)\nTelefone: 253639700\nFax: 000000000\nEndereço da Entidade (URL): www.mun-planhoso.pt\nEndereço Eletrónico: geral@mun-planhoso.pt\neDelivery Gateway (URL): https://community.vortal.biz/public/\nFunção da Organização: Adquirente\nNorma jurídica da Entidade Adjudicante: Autoridade local\nÁrea de atividade da Autoridade Adjudicante: Serviços públicos das administrações públicas\n\n2 - JORNAL OFICIAL DA UNIÃO EUROPEIA\nO procedimento a que este anúncio diz respeito também é publicitado no Jornal Oficial da União Europeia? Não\n\n3 - AVISO\nModelo de Anúncio: Concurso limitado por prévia qualificação\nData de Envio do Anúncio: 17-10-2025\n\n5 - PROCESSO\nTipo de Procedimento: Concurso limitado por prévia qualificação\nPreço base do procedimento: Sim\nValor do preço base do procedimento: 734.230,11 EUR\nProcedimento com lotes? Não\n\n6 - OBJETO DO CONTRATO\nNúmero de referência interna: CP-PC 3003-2025\nDesignação do contrato: Requalificação do Pavilhão Desportivo da EB Gonçalo Sampaio\nDescrição: Execução de alvenarias, substituição de caixilharia, substituição de revestimentos, intervenção nas redes de infraestruturas.\nTipo de Contrato Principal: Empreitada de Obras Públicas\nTipo de Contrato: Empreitada de Obras Públicas\nClassificação CPV (Vocabulário Comum para os Contratos Públicos)\nObjeto principal\nVocabulário Principal: 45212290\nPreço base s/IVA: 734.230,11 EUR\n\n7 - INDICAÇÕES ADICIONAIS\nO contrato envolve aquisição conjunta (satisfação de várias entidades)? Não\nO contrato é adjudicado por uma central de compras? Não\n\n8 - TÉCNICAS\nO concurso destina-se à celebração de um acordo-quadro? Inexistência de acordo-quadro\nÉ utilizado um leilão eletrónico? Não\nSistema de Aquisição Dinâmico: Inexistência de sistema de aquisição dinâmico\n\n9 - LOCAL DA EXECUÇÃO DO CONTRATO\nLOCAL DA EXECUÇÃO DO CONTRATO (PROCEDIMENTO)\nPaís: Portugal\nNUT III: PT119\nLocalidade: Braga\nDistrito: Braga\nConcelho: Póvoa de Lanhoso\nFreguesia: Freguesia de Póvoa de Lanhoso (Nossa Senhora do Amparo)\n\n10 - PRAZO DE EXECUÇÃO DO CONTRATO\nPrazo de execução do contrato: 210 DIAS\nPrevisão de renovações: Não\n\n11 - FUNDOS EU\nTêm fundos EU? Sim\n\n12 - DOCUMENTOS DE HABILITAÇÃO\nHabilitação para o exercício da atividade profissional: Sim\nTipo: Alvará\nDescrição: Alvará, remete-se para o Programa de Concurso.\n\n13 - CONDIÇÕES DE APRESENTAÇÃO\nPlataforma eletrónica utilizada pela entidade adjudicante: VORTAL\nURL para Apresentação: https://community.vortal.biz/public/\nAdmissibilidade da apresentação de propostas variantes: Não autorizado\nPrazo para apresentação das candidaturas: 27-10-2025 18:00\nRequisitos mínimos \nRequisitos mínimos de capacidade técnica: Remete-se para o Programa de Concurso.\nRequisitos mínimos de capacidade financeira: Remete-se para o Programa de Concurso.\nPrazo durante o qual os concorrentes são obrigados a manter as respetivas propostas: 66 dias a contar do termo do prazo para a apresentação das propostas\nApresentação de Catálogo Eletrónico: Permitido\nIndicação de Subcontratação na Proposta: Inexistência de indicação de subcontratação\n\n14 - PRESTAÇÃO DE CAUÇÃO\nPrestação de caução: Sim\nPercentagem: 5%\nDescrição da Garantia Exigida: Remete-se para o Programa de Concurso\n\n15 - FORNECIMENTO DAS PEÇAS DO CONCURSO, APRESENTAÇÃO DE PEDIDOS DE PARTICIPAÇÃO E APRESENTAÇÃO DAS PROPOSTAS\nLink para acesso às peças do concurso (URL): https://community.vortal.biz/Public/public-tender-documents/UmFVS1FOc2N0QVZTaTVzOWwxcWZDWVYxdEp6cXJSYVE1NUdTdGJvTlc4TlkwY1dEWnVpRUlIbm1vRzBNQ3o4L0ZwSlZ0Q0tpaW51bklDQmxSVUtwRGc9PXFPQmtN\n\n20 - OUTROS REQUISITOS\nInformação sobre contratos reservados. Aplica-se a contratos reservados (54º-A)? Não\n\n21 - CRITÉRIO DE ADJUDICAÇÃO\nMultifator: Sim\nFator: \nNome: Preço\nPonderação: 50%\nSubfatores: Não\nFator: \nNome: Qualidade\nPonderação: 50%\nSubfatores: Sim\nSubfatores: \nNome: Memória descritiva\nPonderação : 50%; \nNome: Plano de Trabalhos \nPonderação : 50%; \n\n24 - CONDIÇÕES DO CONTRATO\nFaturação Eletrónica: Permitido\nObrigação de Subcontratação:\nCódigo da Obrigação de Subcontratação: Não é aplicável nenhuma obrigação de subcontratação.\n\n25 - COMPRA PÚBLICA ESTRATÉGICA\nCompra Pública Estratégica: Inexistência de contratação pública estratégica\n\n26 - INFORMAÇÕES ADICIONAIS\nContrato adequado para PME: Sim\nCobertura ACP (Acordo dos Contratos Públicos da Organização Mundial do Comércio): Não\n\n27 - IDENTIFICAÇÃO E CONTACTOS DO ÓRGÃO DE RECURSOS ADMINISTRATIVOS\nDesignação: Câmara Municipal da Póvoa de Lanhoso\nEndereço: AV DA REPUBLICA 4830-513 POVOA DE LANHOSO\nCódigo postal: 4830-513\nLocalidade: Póvoa de Lanhoso\nTelefone: +351 253639700\nFax: +351 000000000\nEndereço eletrónico: geral@mun-planhoso.pt\n\n28 - IDENTIFICAÇÃO DO(S) AUTOR(ES) DE ANÚNCIO\nNome: Frederico de Oliveira Castro\nCargo: Presidente da Câmara Municipal\n\n29 - ALTERAÇÃO\nMotivo da Alteração: Correção pelo adquirente\nIdentificador da Versão do Anúncio a Alterar: ba836438-758f-46df-8384-aa37baf3820a-01\nIdentificador das Secções Alteradas do Anúncio Anterior: Alteração\nDescrição das Alterações: Retificação das Peças do Procedimento, Programa de Concurso.\nAlteração dos Documentos do Concurso: Sim\nData de alteração dos documentos do concurso: 17-10-2025\n419672125",
    "nipc": "506632920",
    "distrito": "Braga",
    "concelho": "Póvoa de Lanhoso",
    "freguesia": "Freguesia de Póvoa de Lanhoso (Nossa Senhora do Amparo)",
    "site": "www.mun-planhoso.pt",
    "email": "geral@mun-planhoso.pt",
    "designacao_contrato": "Requalificação do Pavilhão Desportivo da EB Gonçalo Sampaio",
    "descricao": "Execução de alvenarias, substituição de caixilharia, substituição de revestimentos, intervenção nas redes de infraestruturas.",
    "preco_base": "734.230,11 EUR",
    "prazo_execucao": "210 DIAS",
    "prazo_apresentacao_propostas": null,
    "fundos_eu": "Sim",
    "plataforma_eletronica": "VORTAL",
    "url_procedimento": "https://community.vortal.biz/public/",
    "autor_nome": "Frederico de Oliveira Castro",
    "autor_cargo": "Presidente da Câmara Municipal"
  },
  {
    "numero_procedimento": "N/A",
    "entidade": "AnÃºncio de procedimento  n.Âº 27465/2025  -  DiÃ¡rio da RepÃºblica n.Âº 201/2025, SÃ©rie II de 2025-10-17",
    "link": "https://diariodarepublica.pt/dr/detalhe/contrato-publico/27465-940780755"
  },
  {
    "numero_procedimento": "N/A",
    "entidade": "Município do Porto",
    "link": "https://diariodarepublica.pt/dr/detalhe/contrato-publico/27466-940780756",
    "detalhes_completos": "1 - IDENTIFICAÇÃO E CONTACTOS DA ENTIDADE ADJUDICANTE\nDesignação da entidade adjudicante: Município do Porto\nNIPC: 501306099\nServiço/Órgão/Pessoa de contacto: Divisão Municipal de Compras Gerais\nEndereço: Rua do Bolhão, 162, 6.º piso\nCódigo postal: 4000-111\nLocalidade: Porto\nPaís: Portugal\nNUT III: PT11A\nDistrito: Porto\nConcelho: Porto\nFreguesia: União das Freguesias de Cedofeita, Santo Ildefonso, Sé, Miragaia, São Nicolau e Vitória\nTelefone: 222097216\nFax: 222097296\nEndereço da Entidade (URL): http://www.cm-porto.pt\nEndereço Eletrónico: suportepce@cm-porto.pt\neDelivery Gateway (URL): https://www.acingov.pt\nFunção da Organização: Adquirente\nNorma jurídica da Entidade Adjudicante: Autoridade local\nÁrea de atividade da Autoridade Adjudicante: Serviços públicos das administrações públicas\n\n2 - JORNAL OFICIAL DA UNIÃO EUROPEIA\nO procedimento a que este anúncio diz respeito também é publicitado no Jornal Oficial da União Europeia? Não\n\n3 - AVISO\nModelo de Anúncio: Concurso público\nData de Envio do Anúncio: 17-10-2025\n\n5 - PROCESSO\nTipo de Procedimento: Concurso público\nPreço base do procedimento: Sim\nValor do preço base do procedimento: 111.115,30 EUR\nProcedimento com lotes? Não\n\n6 - OBJETO DO CONTRATO\nNúmero de referência interna: CP/48/2025/DMCG\nDesignação do contrato: Requalificação dos balneários do edifício administrativo das Oficinas do Carvalhido\nDescrição: Requalificação dos balneários do edifício administrativo das Oficinas do Carvalhido\nTipo de Contrato Principal: Empreitada de Obras Públicas\nTipo de Contrato: Empreitada de Obras Públicas\nClassificação CPV (Vocabulário Comum para os Contratos Públicos)\nObjeto principal\nVocabulário Principal: 45453000\nPreço base s/IVA: 111.115,30 EUR\n\n7 - INDICAÇÕES ADICIONAIS\nO contrato envolve aquisição conjunta (satisfação de várias entidades)? Não\nO contrato é adjudicado por uma central de compras? Não\n\n8 - TÉCNICAS\nO concurso destina-se à celebração de um acordo-quadro? Inexistência de acordo-quadro\nÉ utilizado um leilão eletrónico? Não\nÉ adotada uma fase de negociação? Não\nSistema de Aquisição Dinâmico: Inexistência de sistema de aquisição dinâmico\n\n9 - LOCAL DA EXECUÇÃO DO CONTRATO\nLOCAL DA EXECUÇÃO DO CONTRATO (PROCEDIMENTO)\nPaís: Portugal\nNUT III: PT11A\nLocalidade: Freguesia de Paranhos - Porto\nDistrito: Porto\nConcelho: Porto\nFreguesia: Freguesia de Paranhos - Porto\n\n10 - PRAZO DE EXECUÇÃO DO CONTRATO\nPrazo de execução do contrato: 365 DIAS\nPrevisão de renovações: Não\n\n11 - FUNDOS EU\nTêm fundos EU? Não\n\n12 - DOCUMENTOS DE HABILITAÇÃO\nHabilitação para o exercício da atividade profissional: Sim\nTipo: Alvará\nDescrição: Conforme n.º 7 do ponto 22 do Programa do Procedimento\n\n13 - CONDIÇÕES DE APRESENTAÇÃO\nPlataforma eletrónica utilizada pela entidade adjudicante: ACIN\nURL para Apresentação: https://www.acingov.pt\nAdmissibilidade da apresentação de propostas variantes: Não autorizado\nPrazo para apresentação das propostas: 17-11-2025 17:00\nPrazo durante o qual os concorrentes são obrigados a manter as respetivas propostas: 90 dias a contar do termo do prazo para a apresentação das propostas\nIndicação de Subcontratação na Proposta: Inexistência de indicação de subcontratação\n\n14 - PRESTAÇÃO DE CAUÇÃO\nPrestação de caução: Não\n\n15 - FORNECIMENTO DAS PEÇAS DO CONCURSO, APRESENTAÇÃO DE PEDIDOS DE PARTICIPAÇÃO E APRESENTAÇÃO DAS PROPOSTAS\nLink para acesso às peças do concurso (URL): https://www.acingov.pt/acingovprod/2/zonaPublica/zona_publica_c/donwloadProcedurePiece/OTcyMTEw\n\n20 - OUTROS REQUISITOS\nInformação sobre contratos reservados. Aplica-se a contratos reservados (54º-A)? Não\n\n21 - CRITÉRIO DE ADJUDICAÇÃO\nMultifator: Não\nMonofator:\nNome: Preço\n\n24 - CONDIÇÕES DO CONTRATO\nFaturação Eletrónica: Necessário\nObrigação de Subcontratação:\nCódigo da Obrigação de Subcontratação: Não é aplicável nenhuma obrigação de subcontratação.\n\n25 - COMPRA PÚBLICA ESTRATÉGICA\nCompra Pública Estratégica: Redução dos impactos ambientais\nDescrição do Processo de Adjudicação Estratégico: Conforme a cláusula 45ª do caderno de encargos.\nCritérios de contratos Públicos Ecológicos: Critérios de contratação pública ecológica nacional\nCategorias da estratégia nacional: Manutenção de espaços públicos\nContratos Públicos Ecológicos: A utilização sustentável e proteção dos recursos hídricos e marinhos\nDiretiva Veículos Não Poluentes: Não\nCritério de Acessibilidade: Os critérios de acessibilidade para as pessoas com deficiência não estão incluídos porque o contrato não se destina a pessoas singulares\n\n26 - INFORMAÇÕES ADICIONAIS\nContrato adequado para PME: Sim\nCobertura ACP (Acordo dos Contratos Públicos da Organização Mundial do Comércio): Não\n\n27 - IDENTIFICAÇÃO E CONTACTOS DO ÓRGÃO DE RECURSOS ADMINISTRATIVOS\nDesignação: Divisão Municipal de Compras Gerais\nEndereço: Rua do Bolhão,162.º-6.º\nCódigo postal: 4000-111\nLocalidade: Porto\nTelefone: 222097216\nFax: \nEndereço eletrónico: dmcompras@cm-porto.pt\n\n28 - IDENTIFICAÇÃO DO(S) AUTOR(ES) DE ANÚNCIO\nNome: Vera Sampaio\nCargo: Chefe de Divisão Municipal de Compras Gerais\n419670019",
    "nipc": "501306099",
    "distrito": "Porto",
    "concelho": "Porto",
    "freguesia": "União das Freguesias de Cedofeita, Santo Ildefonso, Sé, Miragaia, São Nicolau e Vitória",
    "site": "http://www.cm-porto.pt",
    "email": "suportepce@cm-porto.pt",
    "designacao_contrato": "Requalificação dos balneários do edifício administrativo das Oficinas do Carvalhido",
    "descricao": "Requalificação dos balneários do edifício administrativo das Oficinas do Carvalhido",
    "preco_base": "111.115,30 EUR",
    "prazo_execucao": "365 DIAS",
    "prazo_apresentacao_propostas": "17-11-2025 17:00",
    "fundos_eu": "Não",
    "plataforma_eletronica": "ACIN",
    "url_procedimento": "https://www.acingov.pt",
    "autor_nome": "Vera Sampaio",
    "autor_cargo": "Chefe de Divisão Municipal de Compras Gerais"
  },
  {
    "numero_procedimento": "N/A",
    "entidade": "AnÃºncio de procedimento  n.Âº 27471/2025  -  DiÃ¡rio da RepÃºblica n.Âº 201/2025, SÃ©rie II de 2025-10-17",
    "link": "https://diariodarepublica.pt/dr/detalhe/contrato-publico/27471-940780757"
  },
  {
    "numero_procedimento": "N/A",
    "entidade": "AnÃºncio de procedimento  n.Âº 27473/2025  -  DiÃ¡rio da RepÃºblica n.Âº 201/2025, SÃ©rie II de 2025-10-17",
    "link": "https://diariodarepublica.pt/dr/detalhe/contrato-publico/27473-940780758"
  },
  {
    "numero_procedimento": "N/A",
    "entidade": "Unidade Local de Saúde do Algarve, E. P. E.",
    "link": "https://diariodarepublica.pt/dr/detalhe/contrato-publico/27477-940780760",
    "detalhes_completos": "1 - IDENTIFICAÇÃO E CONTACTOS DA ENTIDADE ADJUDICANTE\nDesignação da entidade adjudicante: Unidade Local de Saúde do Algarve, E. P. E.\nNIPC: 510745997\nEndereço: Rua Leão Penedo\nCódigo postal: 8000-386\nLocalidade: Faro\nPaís: Portugal\nNUT III: PT150\nDistrito: Faro\nConcelho: Faro\nFreguesia: União das Freguesias de Faro (Sé e São Pedro)\nTelefone: 289891100\nFax: 289891159\nEndereço da Entidade (URL): https://www.chualgarve.min-saude.pt\nEndereço Eletrónico: concursos@ulsalg.min-saude.pt\neDelivery Gateway (URL): https://community.vortal.biz/public/\nFunção da Organização: Adquirente\nNorma jurídica da Entidade Adjudicante: Organismo de direito público\nÁrea de atividade da Autoridade Adjudicante: Saúde\n\n2 - JORNAL OFICIAL DA UNIÃO EUROPEIA\nO procedimento a que este anúncio diz respeito também é publicitado no Jornal Oficial da União Europeia? Não\n\n3 - AVISO\nModelo de Anúncio: Concurso público\nData de Envio do Anúncio: 17-10-2025\n\n5 - PROCESSO\nTipo de Procedimento: Concurso público\nPreço base do procedimento: Sim\nValor do preço base do procedimento: 30.000,00 EUR\nProcedimento com lotes? Não\n\n6 - OBJETO DO CONTRATO\nNúmero de referência interna: 27/4496/2025\nDesignação do contrato: Aquisição de Viatura Elétrica\nDescrição: Aquisição de Viatura Elétrica\nTipo de Contrato Principal: Aquisição de Bens Móveis\nTipo de Contrato: Aquisição de Bens Móveis\nClassificação CPV (Vocabulário Comum para os Contratos Públicos)\nObjeto principal\nVocabulário Principal: 34144900\nPreço base s/IVA: 30.000,00 EUR\n\n7 - INDICAÇÕES ADICIONAIS\nO contrato envolve aquisição conjunta (satisfação de várias entidades)? Não\nO contrato é adjudicado por uma central de compras? Não\n\n8 - TÉCNICAS\nO concurso destina-se à celebração de um acordo-quadro? Inexistência de acordo-quadro\nÉ utilizado um leilão eletrónico? Não\nÉ adotada uma fase de negociação? Não\nSistema de Aquisição Dinâmico: Inexistência de sistema de aquisição dinâmico\n\n9 - LOCAL DA EXECUÇÃO DO CONTRATO\nLOCAL DA EXECUÇÃO DO CONTRATO (PROCEDIMENTO)\nPaís: Portugal\nNUT III: PT150\nLocalidade: Faro\nDistrito: Faro\nConcelho: Faro\nFreguesia: União das Freguesias de Faro (Sé e São Pedro)\n\n10 - PRAZO DE EXECUÇÃO DO CONTRATO\nPrazo de execução do contrato: 120 DIAS\nPrevisão de renovações: Não\n\n11 - FUNDOS EU\nTêm fundos EU? Não\n\n12 - DOCUMENTOS DE HABILITAÇÃO\nHabilitação para o exercício da atividade profissional: Não\n\n13 - CONDIÇÕES DE APRESENTAÇÃO\nPlataforma eletrónica utilizada pela entidade adjudicante: VORTAL\nURL para Apresentação: https://community.vortal.biz/public/\nAdmissibilidade da apresentação de propostas variantes: Não autorizado\nPrazo para apresentação das propostas: 29-10-2025 17:00\nPrazo durante o qual os concorrentes são obrigados a manter as respetivas propostas: 120 dias a contar do termo do prazo para a apresentação das propostas\nIndicação de Subcontratação na Proposta: Inexistência de indicação de subcontratação\n\n14 - PRESTAÇÃO DE CAUÇÃO\nPrestação de caução: Não\n\n15 - FORNECIMENTO DAS PEÇAS DO CONCURSO, APRESENTAÇÃO DE PEDIDOS DE PARTICIPAÇÃO E APRESENTAÇÃO DAS PROPOSTAS\nLink para acesso às peças do concurso (URL): https://community.vortal.biz/Public/public-tender-documents/aFZpTWRPYmxZYjlzQ1ZuOVRyM2xJU0NkWGNJWDJPRHNqWktrSG91VWwxdnlxQ0ZXcnJZb3FqVFU0ZGFVMG9rYU4xRzdmeW9ySmU0Q0U3aTQzbFF5ZVE9PV9KV0Ir\n\n20 - OUTROS REQUISITOS\nInformação sobre contratos reservados. Aplica-se a contratos reservados (54º-A)? Não\n\n21 - CRITÉRIO DE ADJUDICAÇÃO\nMultifator: Sim\nFator: \nNome: Preço\nPonderação: 40%\nSubfatores: Não\nFator: \nNome: Qualidade\nPonderação: 60%\nSubfatores: Não\n\n24 - CONDIÇÕES DO CONTRATO\nFaturação Eletrónica: Permitido\nObrigação de Subcontratação:\nCódigo da Obrigação de Subcontratação: Não é aplicável nenhuma obrigação de subcontratação.\n\n25 - COMPRA PÚBLICA ESTRATÉGICA\nCompra Pública Estratégica: Inexistência de contratação pública estratégica\n\n26 - INFORMAÇÕES ADICIONAIS\nContrato adequado para PME: Sim\nCobertura ACP (Acordo dos Contratos Públicos da Organização Mundial do Comércio): Não\n\n27 - IDENTIFICAÇÃO E CONTACTOS DO ÓRGÃO DE RECURSOS ADMINISTRATIVOS\nDesignação: ULSALG, EPE.\nEndereço: Rua Leão Penedo\nCódigo postal: 8000-386\nLocalidade: Faro\nTelefone: +351 282450311\nFax: +351 282450311\nEndereço eletrónico: concursos@ulsalg.min-saude.pt\n\n28 - IDENTIFICAÇÃO DO(S) AUTOR(ES) DE ANÚNCIO\nNome: Dr. Gonçalves Junior\nCargo: Vogal do Conselho de Administração\n419671697",
    "nipc": "510745997",
    "distrito": "Faro",
    "concelho": "Faro",
    "freguesia": "União das Freguesias de Faro (Sé e São Pedro)",
    "site": "https://www.chualgarve.min-saude.pt",
    "email": "concursos@ulsalg.min-saude.pt",
    "designacao_contrato": "Aquisição de Viatura Elétrica",
    "descricao": "Aquisição de Viatura Elétrica",
    "preco_base": "30.000,00 EUR",
    "prazo_execucao": "120 DIAS",
    "prazo_apresentacao_propostas": "29-10-2025 17:00",
    "fundos_eu": "Não",
    "plataforma_eletronica": "VORTAL",
    "url_procedimento": "https://community.vortal.biz/public/",
    "autor_nome": "Dr. Gonçalves Junior",
    "autor_cargo": "Vogal do Conselho de Administração"
  },
  {
    "numero_procedimento": "N/A",
    "entidade": "AnÃºncio de procedimento  n.Âº 27478/2025  -  DiÃ¡rio da RepÃºblica n.Âº 201/2025, SÃ©rie II de 2025-10-17",
    "link": "https://diariodarepublica.pt/dr/detalhe/contrato-publico/27478-940780761"
  },
  {
    "numero_procedimento": "N/A",
    "entidade": "AnÃºncio de procedimento  n.Âº 27440/2025  -  DiÃ¡rio da RepÃºblica n.Âº 201/2025, SÃ©rie II de 2025-10-17",
    "link": "https://diariodarepublica.pt/dr/detalhe/contrato-publico/27440-940848503"
  },
  {
    "numero_procedimento": "N/A",
    "entidade": "AnÃºncio de procedimento  n.Âº 27441/2025  -  DiÃ¡rio da RepÃºblica n.Âº 201/2025, SÃ©rie II de 2025-10-17",
    "link": "https://diariodarepublica.pt/dr/detalhe/contrato-publico/27441-940848504"
  },
  {
    "numero_procedimento": "N/A",
    "entidade": "Estado-Maior do Exército",
    "link": "https://diariodarepublica.pt/dr/detalhe/contrato-publico/27442-940848505",
    "detalhes_completos": "Alteração do Anúncio de procedimento n.º 26585/2025, de 2025-10-09, com o ID 419623647\n\n1 - IDENTIFICAÇÃO E CONTACTOS DA ENTIDADE ADJUDICANTE\nDesignação da entidade adjudicante: Estado-Maior do Exército\nNIPC: 600021610\nServiço/Órgão/Pessoa de contacto: DA/DCC\nEndereço: Av. Infante Santo nº 49, 2º Piso\nCódigo postal: 1399-056\nLocalidade: Lisboa\nPaís: Portugal\nNUT III: PT170\nDistrito: Lisboa\nConcelho: Lisboa\nFreguesia: Freguesia da Estrela\nTelefone: 213912000\nFax: 213912009\nEndereço da Entidade (URL): https://www.exercito.pt/\nEndereço Eletrónico: cmdlog.da@exercito.pt\neDelivery Gateway (URL): https://www.acingov.pt\nFunção da Organização: Adquirente\nSubfunção da Organização: Organização cujo orçamento é utilizado para pagar o contrato; Organização que executa o pagamento; Organização que fornece mais informações sobre os prazos dos procedimentos de recurso; Organização responsável pelo tratamento das propostas; Organização que recebe as propostas; Organização que trata os pedidos de participação; Organização que recebe pedidos de participação; Organização que assina o contrato\nNorma jurídica da Entidade Adjudicante: Organismo de direito público\nÁrea de atividade da Autoridade Adjudicante: Defesa\n\n2 - JORNAL OFICIAL DA UNIÃO EUROPEIA\nO procedimento a que este anúncio diz respeito também é publicitado no Jornal Oficial da União Europeia? Sim\n\n3 - AVISO\nModelo de Anúncio: Concurso público\nData de Envio do Anúncio: 15-10-2025\n\n5 - PROCESSO\nTipo de Procedimento: Concurso público\nPreço base do procedimento: Sim\nValor do preço base do procedimento: 210.000,00 EUR\nProcedimento com lotes? Não\n\n6 - OBJETO DO CONTRATO\nNúmero de referência interna: P0015/2025\nDesignação do contrato: 4025021086/DA/P0015/2025-Contratação de Voo dedicado (Charter) para rendição da CAtMec/Roménia\nDescrição: 4025021086/DA/P0015/2025-Contratação de Voo dedicado (Charter) para rendição da CAtMec/Roménia\nOpções: Não\nTipo de Contrato Principal: Aquisição de Serviços\nTipo de Contrato: Aquisição de Serviços\nClassificação CPV (Vocabulário Comum para os Contratos Públicos)\nObjeto principal\nVocabulário Principal: 63510000\nPreço base s/IVA: 210.000,00 EUR\n\n7 - INDICAÇÕES ADICIONAIS\nO contrato envolve aquisição conjunta (satisfação de várias entidades)? Não\nO contrato é adjudicado por uma central de compras? Não\n\n8 - TÉCNICAS\nO concurso destina-se à celebração de um acordo-quadro? Inexistência de acordo-quadro\nÉ utilizado um leilão eletrónico? Não\nÉ adotada uma fase de negociação? Não\nSistema de Aquisição Dinâmico: Inexistência de sistema de aquisição dinâmico\n\n9 - LOCAL DA EXECUÇÃO DO CONTRATO\nLOCAL DA EXECUÇÃO DO CONTRATO (PROCEDIMENTO)\nPaís: Portugal\nNUT III: PT170\nLocalidade: Freguesia da Estrela\nDistrito: Lisboa\nConcelho: Lisboa\nFreguesia: Freguesia da Estrela\n\n10 - PRAZO DE EXECUÇÃO DO CONTRATO\nData de Início: 20-01-2026\nData de Fim: 22-01-2026\nPrevisão de renovações: Não\n\n11 - FUNDOS EU\nTêm fundos EU? Não\n\n12 - DOCUMENTOS DE HABILITAÇÃO\nHabilitação para o exercício da atividade profissional: Não\n\n13 - CONDIÇÕES DE APRESENTAÇÃO\nPlataforma eletrónica utilizada pela entidade adjudicante: ACIN\nURL para Apresentação: https://www.acingov.pt\nAdmissibilidade da apresentação de propostas variantes: Não autorizado\nPrazo para apresentação das propostas: 18-11-2025 23:59\nPrazo durante o qual os concorrentes são obrigados a manter as respetivas propostas: 66 dias a contar do termo do prazo para a apresentação das propostas\nApresentação de Catálogo Eletrónico: Permitido\nIndicação de Subcontratação na Proposta: Inexistência de indicação de subcontratação\n\n14 - PRESTAÇÃO DE CAUÇÃO\nPrestação de caução: Não\n\n15 - FORNECIMENTO DAS PEÇAS DO CONCURSO, APRESENTAÇÃO DE PEDIDOS DE PARTICIPAÇÃO E APRESENTAÇÃO DAS PROPOSTAS\nLink para acesso às peças do concurso (URL): https://www.acingov.pt/acingovprod/2/zonaPublica/zona_publica_c/donwloadProcedurePiece/OTg0MTgw\n\n20 - OUTROS REQUISITOS\nInformação sobre contratos reservados. Aplica-se a contratos reservados (54º-A)? Não\n\n21 - CRITÉRIO DE ADJUDICAÇÃO\nMultifator: Não\nMonofator:\nNome: Preço\n\n24 - CONDIÇÕES DO CONTRATO\nFaturação Eletrónica: Permitido\nObrigação de Subcontratação:\nCódigo da Obrigação de Subcontratação: Não é aplicável nenhuma obrigação de subcontratação.\n\n25 - COMPRA PÚBLICA ESTRATÉGICA\nCompra Pública Estratégica: Inexistência de contratação pública estratégica\n\n26 - INFORMAÇÕES ADICIONAIS\nContrato adequado para PME: Sim\nCobertura ACP (Acordo dos Contratos Públicos da Organização Mundial do Comércio): Não\n\n27 - IDENTIFICAÇÃO E CONTACTOS DO ÓRGÃO DE RECURSOS ADMINISTRATIVOS\nDesignação: Conforme Direito Contencioso Administrativo\nEndereço: Comando da Logística do Exército- Avenida Infante Santo, nº.49\nCódigo postal: 1399-056\nLocalidade: Lisboa\nTelefone: 213912000\nFax: 213912000\nEndereço eletrónico: cmdlog.da@exercito.pt\nPrazo de interposição do recurso: 10 dias\n\n28 - IDENTIFICAÇÃO DO(S) AUTOR(ES) DE ANÚNCIO\nNome: Brigadeiro - General Albino Marques Lameiras\nCargo: Diretor de Aquisições\n\n29 - ALTERAÇÃO\nMotivo da Alteração: Correção pelo adquirente\nIdentificador da Versão do Anúncio a Alterar: 7e4c184b-72c7-4af7-88c5-bbba5cb6404a-01\nIdentificador das Secções Alteradas do Anúncio Anterior: Condições de Apresentação\nDescrição das Alterações: Modificação do prazo para a apresentação de propostas\nAlteração dos Documentos do Concurso: Sim\nData de alteração dos documentos do concurso: 15-10-2025\n419660575",
    "nipc": "600021610",
    "distrito": "Lisboa",
    "concelho": "Lisboa",
    "freguesia": "Freguesia da Estrela",
    "site": "https://www.exercito.pt/",
    "email": "cmdlog.da@exercito.pt",
    "designacao_contrato": "4025021086/DA/P0015/2025-Contratação de Voo dedicado (Charter) para rendição da CAtMec/Roménia",
    "descricao": "4025021086/DA/P0015/2025-Contratação de Voo dedicado (Charter) para rendição da CAtMec/Roménia",
    "preco_base": "210.000,00 EUR",
    "prazo_execucao": null,
    "prazo_apresentacao_propostas": "18-11-2025 23:59",
    "fundos_eu": "Não",
    "plataforma_eletronica": "ACIN",
    "url_procedimento": "https://www.acingov.pt",
    "autor_nome": "Brigadeiro - General Albino Marques Lameiras",
    "autor_cargo": "Diretor de Aquisições"
  },
  {
    "numero_procedimento": "N/A",
    "entidade": "Unidade Local de Saúde do Algarve, E. P. E.",
    "link": "https://diariodarepublica.pt/dr/detalhe/contrato-publico/27443-940848506",
    "detalhes_completos": "Alteração do Anúncio de procedimento n.º 26395/2025, de 2025-10-08, com o ID 419624627\n\n1 - IDENTIFICAÇÃO E CONTACTOS DA ENTIDADE ADJUDICANTE\nDesignação da entidade adjudicante: Unidade Local de Saúde do Algarve, E. P. E.\nNIPC: 510745997\nEndereço: Rua Leão Penedo\nCódigo postal: 8000-386\nLocalidade: Faro\nPaís: Portugal\nNUT III: PT150\nDistrito: Faro\nConcelho: Faro\nFreguesia: União das Freguesias de Faro (Sé e São Pedro)\nTelefone: 289891100\nFax: 289891159\nEndereço da Entidade (URL): https://www.chualgarve.min-saude.pt\nEndereço Eletrónico: concursos@ulsalg.min-saude.pt\neDelivery Gateway (URL): https://community.vortal.biz/public/\nFunção da Organização: Adquirente\nNorma jurídica da Entidade Adjudicante: Organismo de direito público\nÁrea de atividade da Autoridade Adjudicante: Saúde\n\n2 - JORNAL OFICIAL DA UNIÃO EUROPEIA\nO procedimento a que este anúncio diz respeito também é publicitado no Jornal Oficial da União Europeia? Não\n\n3 - AVISO\nModelo de Anúncio: Concurso público\nData de Envio do Anúncio: 17-10-2025\n\n5 - PROCESSO\nTipo de Procedimento: Concurso público\nPreço base do procedimento: Sim\nValor do preço base do procedimento: 68.700,00 EUR\nProcedimento com lotes? Não\n\n6 - OBJETO DO CONTRATO\nNúmero de referência interna: 27/3860/2025\nDesignação do contrato: Aquisição de Ecógrafo\nDescrição: Aquisição de Ecógrafo\nTipo de Contrato Principal: Aquisição de Bens Móveis\nTipo de Contrato: Aquisição de Bens Móveis\nClassificação CPV (Vocabulário Comum para os Contratos Públicos)\nObjeto principal\nVocabulário Principal: 33112000\nPreço base s/IVA: 68.700,00 EUR\n\n7 - INDICAÇÕES ADICIONAIS\nO contrato envolve aquisição conjunta (satisfação de várias entidades)? Não\nO contrato é adjudicado por uma central de compras? Não\n\n8 - TÉCNICAS\nO concurso destina-se à celebração de um acordo-quadro? Inexistência de acordo-quadro\nÉ utilizado um leilão eletrónico? Não\nÉ adotada uma fase de negociação? Não\nSistema de Aquisição Dinâmico: Inexistência de sistema de aquisição dinâmico\n\n9 - LOCAL DA EXECUÇÃO DO CONTRATO\nLOCAL DA EXECUÇÃO DO CONTRATO (PROCEDIMENTO)\nPaís: Portugal\nNUT III: PT150\nLocalidade: Faro\nDistrito: Faro\nConcelho: Faro\nFreguesia: União das Freguesias de Faro (Sé e São Pedro)\n\n10 - PRAZO DE EXECUÇÃO DO CONTRATO\nPrazo de execução do contrato: 45 DIAS\nPrevisão de renovações: Não\n\n11 - FUNDOS EU\nTêm fundos EU? Não\n\n12 - DOCUMENTOS DE HABILITAÇÃO\nHabilitação para o exercício da atividade profissional: Não\n\n13 - CONDIÇÕES DE APRESENTAÇÃO\nPlataforma eletrónica utilizada pela entidade adjudicante: VORTAL\nURL para Apresentação: https://community.vortal.biz/public/\nAdmissibilidade da apresentação de propostas variantes: Não autorizado\nPrazo para apresentação das propostas: 20-10-2025 17:00\nPrazo durante o qual os concorrentes são obrigados a manter as respetivas propostas: 120 dias a contar do termo do prazo para a apresentação das propostas\nIndicação de Subcontratação na Proposta: Inexistência de indicação de subcontratação\n\n14 - PRESTAÇÃO DE CAUÇÃO\nPrestação de caução: Não\n\n15 - FORNECIMENTO DAS PEÇAS DO CONCURSO, APRESENTAÇÃO DE PEDIDOS DE PARTICIPAÇÃO E APRESENTAÇÃO DAS PROPOSTAS\nLink para acesso às peças do concurso (URL): https://community.vortal.biz/Public/public-tender-documents/VytnNjUxNHA2WTdNc2UvaXdNNWRoQVg5SXFab011WHljZjM2d2RlS0xtTm1vdVppU3FpTDhzSFdqbXpnT0paNEpqdUh5cWN1MVFmcUtoKzUyOTNIa2c9PVA4KCFJ\n\n20 - OUTROS REQUISITOS\nInformação sobre contratos reservados. Aplica-se a contratos reservados (54º-A)? Não\n\n21 - CRITÉRIO DE ADJUDICAÇÃO\nMultifator: Sim\nFator: \nNome: Preço\nPonderação: 60%\nSubfatores: Não\nFator: \nNome: Qualidade\nPonderação: 40%\nSubfatores: Não\n\n24 - CONDIÇÕES DO CONTRATO\nFaturação Eletrónica: Permitido\nObrigação de Subcontratação:\nCódigo da Obrigação de Subcontratação: Não é aplicável nenhuma obrigação de subcontratação.\n\n25 - COMPRA PÚBLICA ESTRATÉGICA\nCompra Pública Estratégica: Inexistência de contratação pública estratégica\n\n26 - INFORMAÇÕES ADICIONAIS\nContrato adequado para PME: Sim\nCobertura ACP (Acordo dos Contratos Públicos da Organização Mundial do Comércio): Não\n\n27 - IDENTIFICAÇÃO E CONTACTOS DO ÓRGÃO DE RECURSOS ADMINISTRATIVOS\nDesignação: ULSALG, EPE.\nEndereço: Rua Leão Penedo\nCódigo postal: 8000-386\nLocalidade: Faro\nTelefone: +351 282450311\nFax: +351 282450311\nEndereço eletrónico: concursos@ulsalg.min-sdaude.pt\n\n28 - IDENTIFICAÇÃO DO(S) AUTOR(ES) DE ANÚNCIO\nNome: Dr. Gonçalves Junior\nCargo: Vogal do Conselho de Administração\n\n29 - ALTERAÇÃO\nMotivo da Alteração: Informações atualizadas\nIdentificador da Versão do Anúncio a Alterar: 38482665-bff5-4997-b2ca-66b4f22b5b4e-01\nIdentificador das Secções Alteradas do Anúncio Anterior: Acesso às peças do concurso, pedidos de participação e apresentação das propostas\nDescrição das Alterações: Prorrogação de Prazo\nAlteração dos Documentos do Concurso: Sim\nData de alteração dos documentos do concurso: 17-10-2025\n419668821",
    "nipc": "510745997",
    "distrito": "Faro",
    "concelho": "Faro",
    "freguesia": "União das Freguesias de Faro (Sé e São Pedro)",
    "site": "https://www.chualgarve.min-saude.pt",
    "email": "concursos@ulsalg.min-saude.pt",
    "designacao_contrato": "Aquisição de Ecógrafo",
    "descricao": "Aquisição de Ecógrafo",
    "preco_base": "68.700,00 EUR",
    "prazo_execucao": "45 DIAS",
    "prazo_apresentacao_propostas": "20-10-2025 17:00",
    "fundos_eu": "Não",
    "plataforma_eletronica": "VORTAL",
    "url_procedimento": "https://community.vortal.biz/public/",
    "autor_nome": "Dr. Gonçalves Junior",
    "autor_cargo": "Vogal do Conselho de Administração"
  },
  {
    "numero_procedimento": "N/A",
    "entidade": "AnÃºncio de procedimento  n.Âº 27445/2025  -  DiÃ¡rio da RepÃºblica n.Âº 201/2025, SÃ©rie II de 2025-10-17",
    "link": "https://diariodarepublica.pt/dr/detalhe/contrato-publico/27445-940848527"
  },
  {
    "numero_procedimento": "N/A",
    "entidade": "AnÃºncio de procedimento  n.Âº 27446/2025  -  DiÃ¡rio da RepÃºblica n.Âº 201/2025, SÃ©rie II de 2025-10-17",
    "link": "https://diariodarepublica.pt/dr/detalhe/contrato-publico/27446-940848528"
  },
  {
    "numero_procedimento": "N/A",
    "entidade": "ASSOCIAÇÃO PARA FORMAÇÃO PROFISSIONAL E DESENVOLVIMENTO DO MONTIJO",
    "link": "https://diariodarepublica.pt/dr/detalhe/contrato-publico/27447-940848529",
    "detalhes_completos": "Alteração do Anúncio de procedimento n.º 24890/2025, de 2025-09-22, com o ID 419553566\n\n1 - IDENTIFICAÇÃO E CONTACTOS DA ENTIDADE ADJUDICANTE\nDesignação da entidade adjudicante: ASSOCIAÇÃO PARA FORMAÇÃO PROFISSIONAL E DESENVOLVIMENTO DO MONTIJO\nNIPC: 504514547\nEndereço: Rua José de Almada Negreiros, 217\nCódigo postal: 2870-442\nLocalidade: Setúbal\nPaís: Portugal\nNUT III: PT170\nDistrito: Setúbal\nConcelho: Montijo\nFreguesia: União das Freguesias de Montijo e Afonsoeiro\nTelefone: 212313685\nFax: 212313685\nEndereço da Entidade (URL): https://afpdm.com/\nEndereço Eletrónico: contratacao.publica@epmontijo.edu.pt\neDelivery Gateway (URL): https://community.vortal.biz/public/\nFunção da Organização: Adquirente\nNorma jurídica da Entidade Adjudicante: Organismo de direito público\nÁrea de atividade da Autoridade Adjudicante: Educação\n\n2 - JORNAL OFICIAL DA UNIÃO EUROPEIA\nO procedimento a que este anúncio diz respeito também é publicitado no Jornal Oficial da União Europeia? Sim\n\n3 - AVISO\nModelo de Anúncio: Concurso público\nData de Envio do Anúncio: 15-10-2025\n\n5 - PROCESSO\nTipo de Procedimento: Concurso público\nPreço base do procedimento: Sim\nValor do preço base do procedimento: 12.305,07 EUR\nProcedimento com lotes? Não\n\n6 - OBJETO DO CONTRATO\nNúmero de referência interna: 38/2025\nDesignação do contrato: Aquisição de equipamentos informáticos para os projetos locais promotores de qualificações de nível B1/B2/B3, no âmbito do PRR\nDescrição: Aquisição de equipamentos informáticos para os projetos locais promotores de qualificações de nível B1/B2/B3, no âmbito do PRR\nOpções: Não\nTipo de Contrato Principal: Aquisição de Bens Móveis\nTipo de Contrato: Aquisição de Bens Móveis\nClassificação CPV (Vocabulário Comum para os Contratos Públicos)\nObjeto principal\nVocabulário Principal: 30236000\nPreço base s/IVA: 12.305,07 EUR\n\n7 - INDICAÇÕES ADICIONAIS\nO contrato envolve aquisição conjunta (satisfação de várias entidades)? Não\nO contrato é adjudicado por uma central de compras? Não\n\n8 - TÉCNICAS\nO concurso destina-se à celebração de um acordo-quadro? Inexistência de acordo-quadro\nÉ utilizado um leilão eletrónico? Não\nÉ adotada uma fase de negociação? Não\nSistema de Aquisição Dinâmico: Inexistência de sistema de aquisição dinâmico\n\n9 - LOCAL DA EXECUÇÃO DO CONTRATO\nLOCAL DA EXECUÇÃO DO CONTRATO (PROCEDIMENTO)\nPaís: Portugal\nNUT III: PT170\nLocalidade: Setúbal\nDistrito: Setúbal\nConcelho: Montijo\nFreguesia: União das Freguesias de Montijo e Afonsoeiro\n\n10 - PRAZO DE EXECUÇÃO DO CONTRATO\nPrazo de execução do contrato: 25 DIAS\nPrevisão de renovações: Não\n\n11 - FUNDOS EU\nTêm fundos EU? Sim\n\n12 - DOCUMENTOS DE HABILITAÇÃO\nHabilitação para o exercício da atividade profissional: Não\n\n13 - CONDIÇÕES DE APRESENTAÇÃO\nPlataforma eletrónica utilizada pela entidade adjudicante: VORTAL\nURL para Apresentação: https://community.vortal.biz/public/\nAdmissibilidade da apresentação de propostas variantes: Não autorizado\nPrazo para apresentação das propostas: 20-10-2025 18:00\nPrazo durante o qual os concorrentes são obrigados a manter as respetivas propostas: 120 dias a contar do termo do prazo para a apresentação das propostas\nApresentação de Catálogo Eletrónico: Não autorizado\nIndicação de Subcontratação na Proposta: Inexistência de indicação de subcontratação\n\n14 - PRESTAÇÃO DE CAUÇÃO\nPrestação de caução: Não\n\n15 - FORNECIMENTO DAS PEÇAS DO CONCURSO, APRESENTAÇÃO DE PEDIDOS DE PARTICIPAÇÃO E APRESENTAÇÃO DAS PROPOSTAS\nLink para acesso às peças do concurso (URL): https://community.vortal.biz/Public/public-tender-documents/UExZeEZHcTI5MW5KNUE0MzNML3JSZWFuVXpHVFZKRW9LaXZzc3hEdWJLeHNSc1c0TzBnUnd5S1hBRmprMW9YMXVaR2prc2RPK2FUakdlMWRuc0pzRXc9PWU5aypH\n\n20 - OUTROS REQUISITOS\nInformação sobre contratos reservados. Aplica-se a contratos reservados (54º-A)? Não\n\n21 - CRITÉRIO DE ADJUDICAÇÃO\nMultifator: Não\nMonofator:\nNome: Preço\n\n24 - CONDIÇÕES DO CONTRATO\nFaturação Eletrónica: Permitido\nObrigação de Subcontratação:\nCódigo da Obrigação de Subcontratação: Não é aplicável nenhuma obrigação de subcontratação.\n\n25 - COMPRA PÚBLICA ESTRATÉGICA\nCompra Pública Estratégica: Inexistência de contratação pública estratégica\n\n26 - INFORMAÇÕES ADICIONAIS\nContrato adequado para PME: Sim\nCobertura ACP (Acordo dos Contratos Públicos da Organização Mundial do Comércio): Não\n\n27 - IDENTIFICAÇÃO E CONTACTOS DO ÓRGÃO DE RECURSOS ADMINISTRATIVOS\nDesignação: Associação para Formação Profissional e Desenvolvimento do Montijo\nEndereço: Rua José de Almada Negreiros n.º 217\nCódigo postal: 2870-442\nLocalidade: Montijo\nTelefone: +351 212313862\nFax: +351 000000000\nEndereço eletrónico: contratacao.publica@epmontijo.edu.pt\n\n28 - IDENTIFICAÇÃO DO(S) AUTOR(ES) DE ANÚNCIO\nNome: Teresa Isabel Roberto Carvalho\nCargo: Presidente da Associação para Formação Profissional e Desenvolvimento do Montijo\n\n29 - ALTERAÇÃO\nMotivo da Alteração: Correção pelo adquirente\nIdentificador da Versão do Anúncio a Alterar: 9882a704-b408-4b0c-a067-90bdc946c00c-01\nIdentificador das Secções Alteradas do Anúncio Anterior: Condições de Apresentação; Fundos EU\nDescrição das Alterações: Prorrogação do prazo para apresentação das proposta\nInformação sobre os Fundos Europeus\nAlteração dos Documentos do Concurso: Não\n419659222",
    "nipc": "504514547",
    "distrito": "Setúbal",
    "concelho": "Montijo",
    "freguesia": "União das Freguesias de Montijo e Afonsoeiro",
    "site": "https://afpdm.com/",
    "email": "contratacao.publica@epmontijo.edu.pt",
    "designacao_contrato": "Aquisição de equipamentos informáticos para os projetos locais promotores de qualificações de nível B1/B2/B3, no âmbito do PRR",
    "descricao": "Aquisição de equipamentos informáticos para os projetos locais promotores de qualificações de nível B1/B2/B3, no âmbito do PRR",
    "preco_base": "12.305,07 EUR",
    "prazo_execucao": "25 DIAS",
    "prazo_apresentacao_propostas": "20-10-2025 18:00",
    "fundos_eu": "Sim",
    "plataforma_eletronica": "VORTAL",
    "url_procedimento": "https://community.vortal.biz/public/",
    "autor_nome": "Teresa Isabel Roberto Carvalho",
    "autor_cargo": "Presidente da Associação para Formação Profissional e Desenvolvimento do Montijo"
  },
  {
    "numero_procedimento": "N/A",
    "entidade": "AnÃºncio de procedimento  n.Âº 27452/2025  -  DiÃ¡rio da RepÃºblica n.Âº 201/2025, SÃ©rie II de 2025-10-17",
    "link": "https://diariodarepublica.pt/dr/detalhe/contrato-publico/27452-940848531"
  },
  {
    "numero_procedimento": "N/A",
    "entidade": "Município da Póvoa de Lanhoso",
    "link": "https://diariodarepublica.pt/dr/detalhe/contrato-publico/27453-940848534",
    "detalhes_completos": "Alteração do Anúncio de procedimento n.º 26533/2025, de 2025-10-09, com o ID 419634882\n\n1 - IDENTIFICAÇÃO E CONTACTOS DA ENTIDADE ADJUDICANTE\nDesignação da entidade adjudicante: Município da Póvoa de Lanhoso\nNIPC: 506632920\nEndereço: Av. República, Póvoa De Lanhoso\nCódigo postal: 4830-513\nLocalidade: Braga\nPaís: Portugal\nNUT III: PT119\nDistrito: Braga\nConcelho: Póvoa de Lanhoso\nFreguesia: Freguesia de Póvoa de Lanhoso (Nossa Senhora do Amparo)\nTelefone: 253639700\nFax: 000000000\nEndereço da Entidade (URL): www.mun-planhoso.pt\nEndereço Eletrónico: geral@mun-planhoso.pt\neDelivery Gateway (URL): https://community.vortal.biz/public/\nFunção da Organização: Adquirente\nNorma jurídica da Entidade Adjudicante: Autoridade local\nÁrea de atividade da Autoridade Adjudicante: Serviços públicos das administrações públicas\n\n2 - JORNAL OFICIAL DA UNIÃO EUROPEIA\nO procedimento a que este anúncio diz respeito também é publicitado no Jornal Oficial da União Europeia? Não\n\n3 - AVISO\nModelo de Anúncio: Concurso limitado por prévia qualificação\nData de Envio do Anúncio: 17-10-2025\n\n5 - PROCESSO\nTipo de Procedimento: Concurso limitado por prévia qualificação\nPreço base do procedimento: Sim\nValor do preço base do procedimento: 860.000,00 EUR\nProcedimento com lotes? Não\n\n6 - OBJETO DO CONTRATO\nNúmero de referência interna: CP-PC 3019-2025 \nDesignação do contrato: Central Idades Reabilitação de Escolas para Inclusão Social - Taíde\nDescrição: Reabilitação de antiga escola primária – melhoramentos nas coberturas, substituição de caixilharias e revestimentos.\nTipo de Contrato Principal: Empreitada de Obras Públicas\nTipo de Contrato: Empreitada de Obras Públicas\nClassificação CPV (Vocabulário Comum para os Contratos Públicos)\nObjeto principal\nVocabulário Principal: 45210000\nPreço base s/IVA: 860.000,00 EUR\n\n7 - INDICAÇÕES ADICIONAIS\nO contrato envolve aquisição conjunta (satisfação de várias entidades)? Não\nO contrato é adjudicado por uma central de compras? Não\n\n8 - TÉCNICAS\nO concurso destina-se à celebração de um acordo-quadro? Inexistência de acordo-quadro\nÉ utilizado um leilão eletrónico? Não\nSistema de Aquisição Dinâmico: Inexistência de sistema de aquisição dinâmico\n\n9 - LOCAL DA EXECUÇÃO DO CONTRATO\nLOCAL DA EXECUÇÃO DO CONTRATO (PROCEDIMENTO)\nPaís: Portugal\nNUT III: PT119\nLocalidade: Braga\nDistrito: Braga\nConcelho: Póvoa de Lanhoso\nFreguesia: Freguesia de Taíde\n\n10 - PRAZO DE EXECUÇÃO DO CONTRATO\nPrazo de execução do contrato: 300 DIAS\nPrevisão de renovações: Não\n\n11 - FUNDOS EU\nTêm fundos EU? Sim\n\n12 - DOCUMENTOS DE HABILITAÇÃO\nHabilitação para o exercício da atividade profissional: Sim\nTipo: Alvará\nDescrição: Alvará, remete-se para o Programa de Concurso.\n\n13 - CONDIÇÕES DE APRESENTAÇÃO\nPlataforma eletrónica utilizada pela entidade adjudicante: VORTAL\nURL para Apresentação: https://community.vortal.biz/public/\nAdmissibilidade da apresentação de propostas variantes: Não autorizado\nPrazo para apresentação das candidaturas: 27-10-2025 18:00\nRequisitos mínimos \nRequisitos mínimos de capacidade técnica: Remete-se para o Programa de Concurso.\nRequisitos mínimos de capacidade financeira: Remete-se para o Programa de Concurso.\nPrazo durante o qual os concorrentes são obrigados a manter as respetivas propostas: 66 dias a contar do termo do prazo para a apresentação das propostas\nApresentação de Catálogo Eletrónico: Permitido\nIndicação de Subcontratação na Proposta: Inexistência de indicação de subcontratação\n\n14 - PRESTAÇÃO DE CAUÇÃO\nPrestação de caução: Sim\nPercentagem: 5%\nDescrição da Garantia Exigida: Remete-se para o Programa do Procedimento\n\n15 - FORNECIMENTO DAS PEÇAS DO CONCURSO, APRESENTAÇÃO DE PEDIDOS DE PARTICIPAÇÃO E APRESENTAÇÃO DAS PROPOSTAS\nLink para acesso às peças do concurso (URL): https://community.vortal.biz/Public/public-tender-documents/Y0FCUHo3b2N5ZHdvNFFqV0RvODY4cGhRZEhHTFlLWkpkMXN1dUFWZi9keW53TFJhWDZxZExTZC9WU3VvS1dKZStsOWVmNzZaVWNxVWwxOVhFZ0FYQlE9PUhHTyRt\n\n20 - OUTROS REQUISITOS\nInformação sobre contratos reservados. Aplica-se a contratos reservados (54º-A)? Não\n\n21 - CRITÉRIO DE ADJUDICAÇÃO\nMultifator: Sim\nFator: \nNome: Preço\nPonderação: 50%\nSubfatores: Não\nFator: \nNome: Qualidade\nPonderação: 50%\nSubfatores: Sim\nSubfatores: \nNome: Memória descritiva e justificativa \nPonderação : 50%; \nNome: Plano de Trabalhos\nPonderação : 50%; \n\n24 - CONDIÇÕES DO CONTRATO\nFaturação Eletrónica: Permitido\nObrigação de Subcontratação:\nCódigo da Obrigação de Subcontratação: Não é aplicável nenhuma obrigação de subcontratação.\n\n25 - COMPRA PÚBLICA ESTRATÉGICA\nCompra Pública Estratégica: Inexistência de contratação pública estratégica\n\n26 - INFORMAÇÕES ADICIONAIS\nContrato adequado para PME: Sim\nCobertura ACP (Acordo dos Contratos Públicos da Organização Mundial do Comércio): Não\n\n27 - IDENTIFICAÇÃO E CONTACTOS DO ÓRGÃO DE RECURSOS ADMINISTRATIVOS\nDesignação: Câmara Municipal da Póvoa de Lanhoso\nEndereço: AV DA REPUBLICA 4830-513 POVOA DE LANHOSO\nCódigo postal: 4830-513\nLocalidade: Póvoa de Lanhoso\nTelefone: +351 253639700\nFax: +351 000000000\nEndereço eletrónico: geral@mun-planhoso.pt\n\n28 - IDENTIFICAÇÃO DO(S) AUTOR(ES) DE ANÚNCIO\nNome: Frederico de Oliveira Castro\nCargo: Presidente da Câmara Municipal\n\n29 - ALTERAÇÃO\nMotivo da Alteração: Correção pelo adquirente\nIdentificador da Versão do Anúncio a Alterar: 99dd4546-b457-43d8-bee4-ab0aa709b5df-01\nIdentificador das Secções Alteradas do Anúncio Anterior: Alteração\nDescrição das Alterações: Esclarecimentos, retificação das peças do procedimento.\nAlteração dos Documentos do Concurso: Sim\nData de alteração dos documentos do concurso: 17-10-2025\n419671931",
    "nipc": "506632920",
    "distrito": "Braga",
    "concelho": "Póvoa de Lanhoso",
    "freguesia": "Freguesia de Póvoa de Lanhoso (Nossa Senhora do Amparo)",
    "site": "www.mun-planhoso.pt",
    "email": "geral@mun-planhoso.pt",
    "designacao_contrato": "Central Idades Reabilitação de Escolas para Inclusão Social - Taíde",
    "descricao": "Reabilitação de antiga escola primária – melhoramentos nas coberturas, substituição de caixilharias e revestimentos.",
    "preco_base": "860.000,00 EUR",
    "prazo_execucao": "300 DIAS",
    "prazo_apresentacao_propostas": null,
    "fundos_eu": "Sim",
    "plataforma_eletronica": "VORTAL",
    "url_procedimento": "https://community.vortal.biz/public/",
    "autor_nome": "Frederico de Oliveira Castro",
    "autor_cargo": "Presidente da Câmara Municipal"
  },
  {
    "numero_procedimento": "N/A",
    "entidade": "AnÃºncio de procedimento  n.Âº 27455/2025  -  DiÃ¡rio da RepÃºblica n.Âº 201/2025, SÃ©rie II de 2025-10-17",
    "link": "https://diariodarepublica.pt/dr/detalhe/contrato-publico/27455-940848538"
  },
  {
    "numero_procedimento": "N/A",
    "entidade": "AnÃºncio de procedimento  n.Âº 27460/2025  -  DiÃ¡rio da RepÃºblica n.Âº 201/2025, SÃ©rie II de 2025-10-17",
    "link": "https://diariodarepublica.pt/dr/detalhe/contrato-publico/27460-940848540"
  },
  {
    "numero_procedimento": "N/A",
    "entidade": "AnÃºncio de procedimento  n.Âº 27461/2025  -  DiÃ¡rio da RepÃºblica n.Âº 201/2025, SÃ©rie II de 2025-10-17",
    "link": "https://diariodarepublica.pt/dr/detalhe/contrato-publico/27461-940848542"
  },
  {
    "numero_procedimento": "N/A",
    "entidade": "AnÃºncio de procedimento  n.Âº 27462/2025  -  DiÃ¡rio da RepÃºblica n.Âº 201/2025, SÃ©rie II de 2025-10-17",
    "link": "https://diariodarepublica.pt/dr/detalhe/contrato-publico/27462-940848543"
  },
  {
    "numero_procedimento": "N/A",
    "entidade": "Santa Casa da Misericórdia de Lisboa",
    "link": "https://diariodarepublica.pt/dr/detalhe/contrato-publico/27463-940848544",
    "detalhes_completos": "1 - IDENTIFICAÇÃO E CONTACTOS DA ENTIDADE ADJUDICANTE\nDesignação da entidade adjudicante: Santa Casa da Misericórdia de Lisboa\nNIPC: 500745471\nServiço/Órgão/Pessoa de contacto: Exma. Mesa\nEndereço: Largo Trindade Coelho\nCódigo postal: 1200-470\nLocalidade: lisboa\nPaís: Portugal\nNUT III: PT170\nDistrito: Lisboa\nConcelho: Lisboa\nFreguesia: Freguesia de Misericórdia\nTelefone: 213235000\nFax: 213235013\nEndereço da Entidade (URL): http://www.scml.pt/\nEndereço Eletrónico: dicom.neei@scml.pt\neDelivery Gateway (URL): https://www.acingov.pt\nFunção da Organização: Adquirente\nSubfunção da Organização: Organização cujo orçamento é utilizado para pagar o contrato; Organização que executa o pagamento; Organização que fornece informações adicionais sobre o processo de adjudicação; Organização que fornece mais informações sobre os prazos dos procedimentos de recurso; Organização que fornece acesso fora de linha aos documentos do concurso; Organização responsável pelo tratamento das propostas; Organização que recebe as propostas; Organização que trata os pedidos de participação; Organização que recebe pedidos de participação; Organização que fornece mais informações sobre os procedimentos de recurso; Organização que assina o contrato\nNorma jurídica da Entidade Adjudicante: Organismo de direito público, controlado por uma autoridade da administração central\nÁrea de atividade da Autoridade Adjudicante: Proteção social\n\n2 - JORNAL OFICIAL DA UNIÃO EUROPEIA\nO procedimento a que este anúncio diz respeito também é publicitado no Jornal Oficial da União Europeia? Não\n\n3 - AVISO\nModelo de Anúncio: Concurso público\nData de Envio do Anúncio: 17-10-2025\n\n5 - PROCESSO\nTipo de Procedimento: Concurso público\nPreço base do procedimento: Sim\nValor do preço base do procedimento: 33.080,00 EUR\nProcedimento com lotes? Não\n\n6 - OBJETO DO CONTRATO\nNúmero de referência interna: 25DC17CP009\nDesignação do contrato: Prestação de Serviços de Manutenção aos Equipamentos de Embalamento do Departamento de Jogos\nDescrição: Prestação de Serviços de Manutenção aos Equipamentos de Embalamento do Departamento de Jogos\nTipo de Contrato Principal: Aquisição de Serviços\nTipo de Contrato: Aquisição de Serviços\nClassificação CPV (Vocabulário Comum para os Contratos Públicos)\nObjeto principal\nVocabulário Principal: 50000000\nPreço base s/IVA: 33.080,00 EUR\n\n7 - INDICAÇÕES ADICIONAIS\nO contrato envolve aquisição conjunta (satisfação de várias entidades)? Não\nO contrato é adjudicado por uma central de compras? Não\n\n8 - TÉCNICAS\nO concurso destina-se à celebração de um acordo-quadro? Inexistência de acordo-quadro\nÉ utilizado um leilão eletrónico? Não\nÉ adotada uma fase de negociação? Não\nSistema de Aquisição Dinâmico: Inexistência de sistema de aquisição dinâmico\n\n9 - LOCAL DA EXECUÇÃO DO CONTRATO\nLOCAL DA EXECUÇÃO DO CONTRATO (PROCEDIMENTO)\nPaís: Portugal\nNUT III: PT170\nLocalidade: Freguesia de Misericórdia\nDistrito: Lisboa\nConcelho: Lisboa\nFreguesia: Freguesia de Misericórdia\n\n10 - PRAZO DE EXECUÇÃO DO CONTRATO\nPrazo de execução do contrato: 36 MESES\nPrevisão de renovações: Não\n\n11 - FUNDOS EU\nTêm fundos EU? Não\n\n12 - DOCUMENTOS DE HABILITAÇÃO\nHabilitação para o exercício da atividade profissional: Não\n\n13 - CONDIÇÕES DE APRESENTAÇÃO\nPlataforma eletrónica utilizada pela entidade adjudicante: ACIN\nURL para Apresentação: https://www.acingov.pt\nAdmissibilidade da apresentação de propostas variantes: Não autorizado\nPrazo para apresentação das propostas: 07-11-2025 17:00\nPrazo durante o qual os concorrentes são obrigados a manter as respetivas propostas: 120 dias a contar do termo do prazo para a apresentação das propostas\nIndicação de Subcontratação na Proposta: Inexistência de indicação de subcontratação\n\n14 - PRESTAÇÃO DE CAUÇÃO\nPrestação de caução: Não\n\n15 - FORNECIMENTO DAS PEÇAS DO CONCURSO, APRESENTAÇÃO DE PEDIDOS DE PARTICIPAÇÃO E APRESENTAÇÃO DAS PROPOSTAS\nLink para acesso às peças do concurso (URL): https://www.acingov.pt/acingovprod/2/zonaPublica/zona_publica_c/donwloadProcedurePiece/OTg2NTA5\n\n20 - OUTROS REQUISITOS\nInformação sobre contratos reservados. Aplica-se a contratos reservados (54º-A)? Não\n\n21 - CRITÉRIO DE ADJUDICAÇÃO\nMultifator: Sim\nFator: \nNome: Outros\nOutro Nome: Fator A - Preço dos serviços de manutenção aos equipamentos de Embalamento do Departamento de Jogos\nPonderação: 22%\nSubfatores: Não\nFator: \nNome: Outros\nOutro Nome: Fator B - Preço do somatório dos materiais a fornecer listados no Anexo A do Caderno de Encargos\nPonderação: 12%\nSubfatores: Não\nFator: \nNome: Outros\nOutro Nome: Fator C - Fornecimento de filme retrátil poliolefina manga dobrada, medida 400mm x 19my x 1067mts, encomenda mínima de 30 rolos\nPonderação: 48%\nSubfatores: Não\nFator: \nNome: Outros\nOutro Nome: Fator D - Preço da Mão-de-Obra/Hora de uma equipa composta por oficial e ajudante, em dias úteis no horário compreendido entre as 9:00 e as 18:00 horas\nPonderação: 6%\nSubfatores: Não\nFator: \nNome: Outros\nOutro Nome: Fator E - Preço da Mão-de-Obra/Hora de uma equipa composta por oficial e ajudante, em dias úteis no horário compreendido entre as 18:01 e as 08:59 horas\nPonderação: 6%\nSubfatores: Não\nFator: \nNome: Outros\nOutro Nome: Fator F - Percentagem do lucro a aplicar aos preços secos dos materiais a substituir\nPonderação: 3%\nSubfatores: Não\nFator: \nNome: Outros\nOutro Nome: Fator G - Preço deslocação\nPonderação: 3%\nSubfatores: Não\n\n24 - CONDIÇÕES DO CONTRATO\nFaturação Eletrónica: Necessário\nObrigação de Subcontratação:\nCódigo da Obrigação de Subcontratação: Não é aplicável nenhuma obrigação de subcontratação.\n\n25 - COMPRA PÚBLICA ESTRATÉGICA\nCompra Pública Estratégica: Inexistência de contratação pública estratégica\n\n26 - INFORMAÇÕES ADICIONAIS\nContrato adequado para PME: Sim\nCobertura ACP (Acordo dos Contratos Públicos da Organização Mundial do Comércio): Não\n\n27 - IDENTIFICAÇÃO E CONTACTOS DO ÓRGÃO DE RECURSOS ADMINISTRATIVOS\nDesignação: Exma. Mesa\nEndereço: Largo Trindade Coelho\nCódigo postal: 1200-470\nLocalidade: Lisboa\nTelefone: 213235000\nFax: 213235013\nEndereço eletrónico: compras@scml.pt\nPrazo de interposição do recurso: 10 dias\n\n28 - IDENTIFICAÇÃO DO(S) AUTOR(ES) DE ANÚNCIO\nNome: Vanda Simão\nCargo: Diretora da Direção de Compras\n419671526",
    "nipc": "500745471",
    "distrito": "Lisboa",
    "concelho": "Lisboa",
    "freguesia": "Freguesia de Misericórdia",
    "site": "http://www.scml.pt/",
    "email": "dicom.neei@scml.pt",
    "designacao_contrato": "Prestação de Serviços de Manutenção aos Equipamentos de Embalamento do Departamento de Jogos",
    "descricao": "Prestação de Serviços de Manutenção aos Equipamentos de Embalamento do Departamento de Jogos",
    "preco_base": "33.080,00 EUR",
    "prazo_execucao": "36 MESES",
    "prazo_apresentacao_propostas": "07-11-2025 17:00",
    "fundos_eu": "Não",
    "plataforma_eletronica": "ACIN",
    "url_procedimento": "https://www.acingov.pt",
    "autor_nome": "Vanda Simão",
    "autor_cargo": "Diretora da Direção de Compras"
  },
  {
    "numero_procedimento": "N/A",
    "entidade": "Comissão de Coordenação e Desenvolvimento Regional do Norte, I. P.",
    "link": "https://diariodarepublica.pt/dr/detalhe/contrato-publico/27467-940848545",
    "detalhes_completos": "1 - IDENTIFICAÇÃO E CONTACTOS DA ENTIDADE ADJUDICANTE\nDesignação da entidade adjudicante: Comissão de Coordenação e Desenvolvimento Regional do Norte, I. P.\nNIPC: 517713233\nServiço/Órgão/Pessoa de contacto: Divisão de Contratação Pública\nEndereço: Rua Rainha D.ª Estefânia, n.º 251\nCódigo postal: 4150-304\nLocalidade: Porto\nPaís: Portugal\nNUT III: PT11A\nDistrito: Porto\nConcelho: Porto\nFreguesia: União das Freguesias de Lordelo do Ouro e Massarelos\nTelefone: 226086300\nFax: 226061480\nEndereço da Entidade (URL): https://www.ccdr-n.pt/\nEndereço Eletrónico: contratacao.publica@ccdr-n.pt\neDelivery Gateway (URL): https://www.acingov.pt\nFunção da Organização: Adquirente\nNorma jurídica da Entidade Adjudicante: Organismo de direito público\nÁrea de atividade da Autoridade Adjudicante: Serviços públicos das administrações públicas\n\n2 - JORNAL OFICIAL DA UNIÃO EUROPEIA\nO procedimento a que este anúncio diz respeito também é publicitado no Jornal Oficial da União Europeia? Não\n\n3 - AVISO\nModelo de Anúncio: Concurso público\nData de Envio do Anúncio: 17-10-2025\n\n5 - PROCESSO\nTipo de Procedimento: Concurso público\nPreço base do procedimento: Sim\nValor do preço base do procedimento: 199.884,83 EUR\nProcedimento com lotes? Não\n\n6 - OBJETO DO CONTRATO\nNúmero de referência interna: CP.PA.2025.501\nDesignação do contrato: Aquisição de salas de videoconferência\nDescrição: Aquisição de salas de videoconferência\nTipo de Contrato Principal: Aquisição de Bens Móveis\nTipo de Contrato: Aquisição de Bens Móveis\nClassificação CPV (Vocabulário Comum para os Contratos Públicos)\nObjeto principal\nVocabulário Principal: 32232000\nPreço base s/IVA: 199.884,83 EUR\n\n7 - INDICAÇÕES ADICIONAIS\nO contrato envolve aquisição conjunta (satisfação de várias entidades)? Não\nO contrato é adjudicado por uma central de compras? Não\n\n8 - TÉCNICAS\nO concurso destina-se à celebração de um acordo-quadro? Inexistência de acordo-quadro\nÉ utilizado um leilão eletrónico? Não\nÉ adotada uma fase de negociação? Não\nSistema de Aquisição Dinâmico: Inexistência de sistema de aquisição dinâmico\n\n9 - LOCAL DA EXECUÇÃO DO CONTRATO\nLOCAL DA EXECUÇÃO DO CONTRATO (PROCEDIMENTO)\nPaís: Portugal\nNUT III: PT112\nLocalidade: Freguesia de Braga (São Vítor)\nDistrito: Braga\nConcelho: Braga\nFreguesia: Freguesia de Braga (São Vítor)\nPaís: Portugal\nNUT III: PT112\nLocalidade: União das Freguesias de Braga (São José de São Lázaro e São João do Souto)\nDistrito: Braga\nConcelho: Braga\nFreguesia: União das Freguesias de Braga (São José de São Lázaro e São João do Souto)\nPaís: Portugal\nNUT III: PT112\nLocalidade: União das Freguesias de Merelim (São Pedro) e Frossos\nDistrito: Braga\nConcelho: Braga\nFreguesia: União das Freguesias de Merelim (São Pedro) e Frossos\nPaís: Portugal\nNUT III: PT11E\nLocalidade: Freguesia de Mirandela\nDistrito: Braganca\nConcelho: Mirandela\nFreguesia: Freguesia de Mirandela\nPaís: Portugal\nNUT III: PT11E\nLocalidade: União das Freguesias de Sé, Santa Maria e Meixedo\nDistrito: Braganca\nConcelho: Bragança\nFreguesia: União das Freguesias de Sé, Santa Maria e Meixedo\nPaís: Portugal\nNUT III: PT11A\nLocalidade: União das Freguesias de Lordelo do Ouro e Massarelos\nDistrito: Porto\nConcelho: Porto\nFreguesia: União das Freguesias de Lordelo do Ouro e Massarelos\nPaís: Portugal\nNUT III: PT11A\nLocalidade: União das Freguesias de São Mamede de Infesta e Senhora da Hora\nDistrito: Porto\nConcelho: Matosinhos\nFreguesia: União das Freguesias de São Mamede de Infesta e Senhora da Hora\nPaís: Portugal\nNUT III: PT11A\nLocalidade: Freguesia de Penafiel\nDistrito: Porto\nConcelho: Penafiel\nFreguesia: Freguesia de Penafiel\nPaís: Portugal\nNUT III: PT11D\nLocalidade: Freguesia de Vila Real\nDistrito: Vila Real\nConcelho: Vila Real\nFreguesia: Freguesia de Vila Real\nPaís: Portugal\nNUT III: PT11D\nLocalidade: União das Freguesias da Madalena e Samaiões\nDistrito: Vila Real\nConcelho: Chaves\nFreguesia: União das Freguesias da Madalena e Samaiões\nPaís: Portugal\nNUT III: PT11D\nLocalidade: União das Freguesias de Peso da Régua e Godim\nDistrito: Vila Real\nConcelho: Peso da Régua\nFreguesia: União das Freguesias de Peso da Régua e Godim\nPaís: Portugal\nNUT III: PT11D\nLocalidade: Freguesia de Lamego (Almacave e Sé)\nDistrito: Viseu\nConcelho: Lamego\nFreguesia: Freguesia de Lamego (Almacave e Sé)\n\n10 - PRAZO DE EXECUÇÃO DO CONTRATO\nPrazo de execução do contrato: 35 DIAS\nPrevisão de renovações: Não\n\n11 - FUNDOS EU\nTêm fundos EU? Sim\n\n12 - DOCUMENTOS DE HABILITAÇÃO\nHabilitação para o exercício da atividade profissional: Não\n\n13 - CONDIÇÕES DE APRESENTAÇÃO\nPlataforma eletrónica utilizada pela entidade adjudicante: ACIN\nURL para Apresentação: https://www.acingov.pt\nAdmissibilidade da apresentação de propostas variantes: Não autorizado\nPrazo para apresentação das propostas: 01-11-2025 23:59\nPrazo durante o qual os concorrentes são obrigados a manter as respetivas propostas: 90 dias a contar do termo do prazo para a apresentação das propostas\nIndicação de Subcontratação na Proposta: Inexistência de indicação de subcontratação\n\n14 - PRESTAÇÃO DE CAUÇÃO\nPrestação de caução: Não\n\n15 - FORNECIMENTO DAS PEÇAS DO CONCURSO, APRESENTAÇÃO DE PEDIDOS DE PARTICIPAÇÃO E APRESENTAÇÃO DAS PROPOSTAS\nLink para acesso às peças do concurso (URL): https://www.acingov.pt/acingovprod/2/zonaPublica/zona_publica_c/donwloadProcedurePiece/OTgyOTU3\n\n20 - OUTROS REQUISITOS\nInformação sobre contratos reservados. Aplica-se a contratos reservados (54º-A)? Não\n\n21 - CRITÉRIO DE ADJUDICAÇÃO\nMultifator: Não\nMonofator:\nNome: Preço\n\n24 - CONDIÇÕES DO CONTRATO\nFaturação Eletrónica: Necessário\nObrigação de Subcontratação:\nCódigo da Obrigação de Subcontratação: Não é aplicável nenhuma obrigação de subcontratação.\n\n25 - COMPRA PÚBLICA ESTRATÉGICA\nCompra Pública Estratégica: Inexistência de contratação pública estratégica\n\n26 - INFORMAÇÕES ADICIONAIS\nContrato adequado para PME: Sim\nCobertura ACP (Acordo dos Contratos Públicos da Organização Mundial do Comércio): Não\n\n27 - IDENTIFICAÇÃO E CONTACTOS DO ÓRGÃO DE RECURSOS ADMINISTRATIVOS\nDesignação: Conselho Diretivo da CCDR-NORTE, I.P.\nEndereço: Rua Rainha D.ª Estefânia, n.º 251\nCódigo postal: 4150-304\nLocalidade: Porto\nTelefone: 226086300\nFax: \nEndereço eletrónico: contratacao.publica@ccdr-n.pt\nPrazo de interposição do recurso: 5 dias\n\n28 - IDENTIFICAÇÃO DO(S) AUTOR(ES) DE ANÚNCIO\nNome: António M. Cunha\nCargo: Presidente da CCDR NORTE, I.P.\n419671583",
    "nipc": "517713233",
    "distrito": "Porto",
    "concelho": "Porto",
    "freguesia": "União das Freguesias de Lordelo do Ouro e Massarelos",
    "site": "https://www.ccdr-n.pt/",
    "email": "contratacao.publica@ccdr-n.pt",
    "designacao_contrato": "Aquisição de salas de videoconferência",
    "descricao": "Aquisição de salas de videoconferência",
    "preco_base": "199.884,83 EUR",
    "prazo_execucao": "35 DIAS",
    "prazo_apresentacao_propostas": "01-11-2025 23:59",
    "fundos_eu": "Sim",
    "plataforma_eletronica": "ACIN",
    "url_procedimento": "https://www.acingov.pt",
    "autor_nome": "António M. Cunha",
    "autor_cargo": "Presidente da CCDR NORTE, I.P."
  },
  {
    "numero_procedimento": "N/A",
    "entidade": "AnÃºncio de procedimento  n.Âº 27468/2025  -  DiÃ¡rio da RepÃºblica n.Âº 201/2025, SÃ©rie II de 2025-10-17",
    "link": "https://diariodarepublica.pt/dr/detalhe/contrato-publico/27468-940848546"
  },
  {
    "numero_procedimento": "N/A",
    "entidade": "Estado Maior da Força Aérea",
    "link": "https://diariodarepublica.pt/dr/detalhe/contrato-publico/27469-940848547",
    "detalhes_completos": "1 - IDENTIFICAÇÃO E CONTACTOS DA ENTIDADE ADJUDICANTE\nDesignação da entidade adjudicante: Estado Maior da Força Aérea\nNIPC: 600010686\nServiço/Órgão/Pessoa de contacto: Ministério da Defesa Nacional  Comando da Logística da Força Aérea  Direção de Manutenção de Sistemas de Armas\nEndereço: Avenida da Força Aérea Portuguesa, Nº1\nCódigo postal: 2614-506\nLocalidade: Amadora\nPaís: Portugal\nNUT III: PT170\nDistrito: Lisboa\nConcelho: Amadora\nFreguesia: Freguesia de Alfragide\nTelefone: 214723726\nFax: 214723850\nEndereço da Entidade (URL): http://www.emfa.pt/www/contactos\nEndereço Eletrónico: CLAFA.AQUIS@emfa.gov.pt\neDelivery Gateway (URL): https://www.acingov.pt\nFunção da Organização: Adquirente\nNorma jurídica da Entidade Adjudicante: Organismo de direito público\nÁrea de atividade da Autoridade Adjudicante: Defesa\n\n2 - JORNAL OFICIAL DA UNIÃO EUROPEIA\nO procedimento a que este anúncio diz respeito também é publicitado no Jornal Oficial da União Europeia? Sim\n\n3 - AVISO\nModelo de Anúncio: Concurso público\nData de Envio do Anúncio: 15-10-2025\n\n5 - PROCESSO\nTipo de Procedimento: Concurso público\nPreço base do procedimento: Sim\nValor do preço base do procedimento: 352.648,40 EUR\nProcedimento com lotes? Não\n\n6 - OBJETO DO CONTRATO\nNúmero de referência interna: DAT 5025011672\nDesignação do contrato: DAT 5025011672 - CONCURSO PÚBLICO PLURIANUAL 2026-2027 PARA A REPARAÇÃO DE HELICES DO C-130H\nDescrição: DAT 5025011672 - CONCURSO PÚBLICO PLURIANUAL 2026-2027 PARA A REPARAÇÃO DE HELICES DO C-130H\nOpções: Não\nTipo de Contrato Principal: Aquisição de Serviços\nTipo de Contrato: Aquisição de Serviços\nClassificação CPV (Vocabulário Comum para os Contratos Públicos)\nObjeto principal\nVocabulário Principal: 50210000\nPreço base s/IVA: 352.648,40 EUR\n\n7 - INDICAÇÕES ADICIONAIS\nO contrato envolve aquisição conjunta (satisfação de várias entidades)? Não\nO contrato é adjudicado por uma central de compras? Não\n\n8 - TÉCNICAS\nO concurso destina-se à celebração de um acordo-quadro? Inexistência de acordo-quadro\nÉ utilizado um leilão eletrónico? Não\nÉ adotada uma fase de negociação? Não\nSistema de Aquisição Dinâmico: Inexistência de sistema de aquisição dinâmico\n\n9 - LOCAL DA EXECUÇÃO DO CONTRATO\nLOCAL DA EXECUÇÃO DO CONTRATO (PROCEDIMENTO)\nPaís: Portugal\nNUT III: PT170\nLocalidade: União das Freguesias de Montijo e Afonsoeiro\nDistrito: Setúbal\nConcelho: Montijo\nFreguesia: União das Freguesias de Montijo e Afonsoeiro\n\n10 - PRAZO DE EXECUÇÃO DO CONTRATO\nPrazo de execução do contrato: 2 ANOS\nPrevisão de renovações: Não\n\n11 - FUNDOS EU\nTêm fundos EU? Não\n\n12 - DOCUMENTOS DE HABILITAÇÃO\nHabilitação para o exercício da atividade profissional: Não\n\n13 - CONDIÇÕES DE APRESENTAÇÃO\nPlataforma eletrónica utilizada pela entidade adjudicante: ACIN\nURL para Apresentação: https://www.acingov.pt\nAdmissibilidade da apresentação de propostas variantes: Não autorizado\nPrazo para apresentação das propostas: 14-11-2025 23:00\nPrazo durante o qual os concorrentes são obrigados a manter as respetivas propostas: 66 dias a contar do termo do prazo para a apresentação das propostas\nApresentação de Catálogo Eletrónico: Permitido\nIndicação de Subcontratação na Proposta: Inexistência de indicação de subcontratação\n\n14 - PRESTAÇÃO DE CAUÇÃO\nPrestação de caução: Sim\nPercentagem: 5%\nDescrição da Garantia Exigida: O valor da caução é de 5.00% do preço contratual.\n\n15 - FORNECIMENTO DAS PEÇAS DO CONCURSO, APRESENTAÇÃO DE PEDIDOS DE PARTICIPAÇÃO E APRESENTAÇÃO DAS PROPOSTAS\nLink para acesso às peças do concurso (URL): https://www.acingov.pt/acingovprod/2/zonaPublica/zona_publica_c/donwloadProcedurePiece/OTg3MTc3\n\n20 - OUTROS REQUISITOS\nInformação sobre contratos reservados. Aplica-se a contratos reservados (54º-A)? Não\n\n21 - CRITÉRIO DE ADJUDICAÇÃO\nMultifator: Sim\nFator: \nNome: Outros\nOutro Nome: Outros\nPonderação: 100%\nSubfatores: Não\n\n24 - CONDIÇÕES DO CONTRATO\nFaturação Eletrónica: Permitido\nObrigação de Subcontratação:\nCódigo da Obrigação de Subcontratação: Não é aplicável nenhuma obrigação de subcontratação.\n\n25 - COMPRA PÚBLICA ESTRATÉGICA\nCompra Pública Estratégica: Inexistência de contratação pública estratégica\n\n26 - INFORMAÇÕES ADICIONAIS\nContrato adequado para PME: Sim\nCobertura ACP (Acordo dos Contratos Públicos da Organização Mundial do Comércio): Não\n\n27 - IDENTIFICAÇÃO E CONTACTOS DO ÓRGÃO DE RECURSOS ADMINISTRATIVOS\nDesignação: CHEFE DE ESTADO-MAIOR DA FORÇA AÉREA\nEndereço: Avenida da Força Aérea Portuguesa, Nº1\nCódigo postal: 2614-506\nLocalidade: Amadora\nTelefone: 214723726\nFax: 214723850\nEndereço eletrónico: clafa.aquis@emfa.gov.pt\n\n28 - IDENTIFICAÇÃO DO(S) AUTOR(ES) DE ANÚNCIO\nNome: COR/AMDAER/FILIPE RODRIGUES\nCargo: CHEFE DO GAP\n419661328",
    "nipc": "600010686",
    "distrito": "Lisboa",
    "concelho": "Amadora",
    "freguesia": "Freguesia de Alfragide",
    "site": "http://www.emfa.pt/www/contactos",
    "email": "CLAFA.AQUIS@emfa.gov.pt",
    "designacao_contrato": "DAT 5025011672 - CONCURSO PÚBLICO PLURIANUAL 2026-2027 PARA A REPARAÇÃO DE HELICES DO C-130H",
    "descricao": "DAT 5025011672 - CONCURSO PÚBLICO PLURIANUAL 2026-2027 PARA A REPARAÇÃO DE HELICES DO C-130H",
    "preco_base": "352.648,40 EUR",
    "prazo_execucao": "2 ANOS",
    "prazo_apresentacao_propostas": "14-11-2025 23:00",
    "fundos_eu": "Não",
    "plataforma_eletronica": "ACIN",
    "url_procedimento": "https://www.acingov.pt",
    "autor_nome": "COR/AMDAER/FILIPE RODRIGUES",
    "autor_cargo": "CHEFE DO GAP"
  },
  {
    "numero_procedimento": "N/A",
    "entidade": "AnÃºncio de procedimento  n.Âº 27470/2025  -  DiÃ¡rio da RepÃºblica n.Âº 201/2025, SÃ©rie II de 2025-10-17",
    "link": "https://diariodarepublica.pt/dr/detalhe/contrato-publico/27470-940848548"
  },
  {
    "numero_procedimento": "N/A",
    "entidade": "AnÃºncio de procedimento  n.Âº 27472/2025  -  DiÃ¡rio da RepÃºblica n.Âº 201/2025, SÃ©rie II de 2025-10-17",
    "link": "https://diariodarepublica.pt/dr/detalhe/contrato-publico/27472-940848549"
  },
  {
    "numero_procedimento": "N/A",
    "entidade": "AnÃºncio de procedimento  n.Âº 27474/2025  -  DiÃ¡rio da RepÃºblica n.Âº 201/2025, SÃ©rie II de 2025-10-17",
    "link": "https://diariodarepublica.pt/dr/detalhe/contrato-publico/27474-940848550"
  },
  {
    "numero_procedimento": "N/A",
    "entidade": "AnÃºncio de procedimento  n.Âº 27475/2025  -  DiÃ¡rio da RepÃºblica n.Âº 201/2025, SÃ©rie II de 2025-10-17",
    "link": "https://diariodarepublica.pt/dr/detalhe/contrato-publico/27475-940848551"
  },
  {
    "numero_procedimento": "N/A",
    "entidade": "Unidade Local de Saúde do Algarve, E. P. E.",
    "link": "https://diariodarepublica.pt/dr/detalhe/contrato-publico/27476-940848552",
    "detalhes_completos": "1 - IDENTIFICAÇÃO E CONTACTOS DA ENTIDADE ADJUDICANTE\nDesignação da entidade adjudicante: Unidade Local de Saúde do Algarve, E. P. E.\nNIPC: 510745997\nEndereço: Rua Leão Penedo\nCódigo postal: 8000-386\nLocalidade: Faro\nPaís: Portugal\nNUT III: PT150\nDistrito: Faro\nConcelho: Faro\nFreguesia: União das Freguesias de Faro (Sé e São Pedro)\nTelefone: 289891100\nFax: 289891159\nEndereço da Entidade (URL): https://www.chualgarve.min-saude.pt\nEndereço Eletrónico: concursos@ulsalg.min-saude.pt\neDelivery Gateway (URL): https://community.vortal.biz/public/\nFunção da Organização: Adquirente\nNorma jurídica da Entidade Adjudicante: Organismo de direito público\nÁrea de atividade da Autoridade Adjudicante: Saúde\n\n2 - JORNAL OFICIAL DA UNIÃO EUROPEIA\nO procedimento a que este anúncio diz respeito também é publicitado no Jornal Oficial da União Europeia? Não\n\n3 - AVISO\nModelo de Anúncio: Concurso público\nData de Envio do Anúncio: 17-10-2025\n\n5 - PROCESSO\nTipo de Procedimento: Concurso público\nPreço base do procedimento: Sim\nValor do preço base do procedimento: 45.897,80 EUR\nProcedimento com lotes? Não\n\n6 - OBJETO DO CONTRATO\nNúmero de referência interna: 21/103/2026\nDesignação do contrato: Medicamentos Vários Citotóxicos\nDescrição: Medicamentos Vários Citotóxicos\nTipo de Contrato Principal: Aquisição de Bens Móveis\nTipo de Contrato: Aquisição de Bens Móveis\nClassificação CPV (Vocabulário Comum para os Contratos Públicos)\nObjeto principal\nVocabulário Principal: 33690000\nPreço base s/IVA: 45.897,80 EUR\n\n7 - INDICAÇÕES ADICIONAIS\nO contrato envolve aquisição conjunta (satisfação de várias entidades)? Não\nO contrato é adjudicado por uma central de compras? Não\n\n8 - TÉCNICAS\nO concurso destina-se à celebração de um acordo-quadro? Inexistência de acordo-quadro\nÉ utilizado um leilão eletrónico? Não\nÉ adotada uma fase de negociação? Não\nSistema de Aquisição Dinâmico: Inexistência de sistema de aquisição dinâmico\n\n9 - LOCAL DA EXECUÇÃO DO CONTRATO\nLOCAL DA EXECUÇÃO DO CONTRATO (PROCEDIMENTO)\nPaís: Portugal\nNUT III: PT150\nLocalidade: Faro\nDistrito: Faro\nConcelho: Faro\nFreguesia: União das Freguesias de Faro (Sé e São Pedro)\n\n10 - PRAZO DE EXECUÇÃO DO CONTRATO\nPrazo de execução do contrato: 1 ANOS\nPrevisão de renovações: Não\n\n11 - FUNDOS EU\nTêm fundos EU? Não\n\n12 - DOCUMENTOS DE HABILITAÇÃO\nHabilitação para o exercício da atividade profissional: Não\n\n13 - CONDIÇÕES DE APRESENTAÇÃO\nPlataforma eletrónica utilizada pela entidade adjudicante: VORTAL\nURL para Apresentação: https://community.vortal.biz/public/\nAdmissibilidade da apresentação de propostas variantes: Não autorizado\nPrazo para apresentação das propostas: 29-10-2025 17:00\nPrazo durante o qual os concorrentes são obrigados a manter as respetivas propostas: 120 dias a contar do termo do prazo para a apresentação das propostas\nIndicação de Subcontratação na Proposta: Inexistência de indicação de subcontratação\n\n14 - PRESTAÇÃO DE CAUÇÃO\nPrestação de caução: Não\n\n15 - FORNECIMENTO DAS PEÇAS DO CONCURSO, APRESENTAÇÃO DE PEDIDOS DE PARTICIPAÇÃO E APRESENTAÇÃO DAS PROPOSTAS\nLink para acesso às peças do concurso (URL): https://community.vortal.biz/Public/public-tender-documents/VTEvMFJFb0hBUW1KT1BlTytheTE0NVVRRHdXNGFnS0FJNHQweHJiTzhLMmVqdWpQR3krcTRvVHJ2ZVN2Q2Z0cGNHVzVFVTJNU1Y1OUdPSEk5OGN5M0E9PXhRVTRD\n\n20 - OUTROS REQUISITOS\nInformação sobre contratos reservados. Aplica-se a contratos reservados (54º-A)? Não\n\n21 - CRITÉRIO DE ADJUDICAÇÃO\nMultifator: Sim\nFator: \nNome: Preço\nPonderação: 50%\nSubfatores: Não\nFator: \nNome: Qualidade\nPonderação: 50%\nSubfatores: Não\n\n24 - CONDIÇÕES DO CONTRATO\nFaturação Eletrónica: Permitido\nObrigação de Subcontratação:\nCódigo da Obrigação de Subcontratação: Não é aplicável nenhuma obrigação de subcontratação.\n\n25 - COMPRA PÚBLICA ESTRATÉGICA\nCompra Pública Estratégica: Inexistência de contratação pública estratégica\n\n26 - INFORMAÇÕES ADICIONAIS\nContrato adequado para PME: Sim\nCobertura ACP (Acordo dos Contratos Públicos da Organização Mundial do Comércio): Não\n\n27 - IDENTIFICAÇÃO E CONTACTOS DO ÓRGÃO DE RECURSOS ADMINISTRATIVOS\nDesignação: Unidade Local de Saúde do Algarve, EPE\nEndereço: Rua Leão Penedo\nCódigo postal: 8000-386\nLocalidade: Faro\nTelefone: +351 289891100\nFax: +351 289891159\nEndereço eletrónico: administracao@ulsalg.min-saude.pt\n\n28 - IDENTIFICAÇÃO DO(S) AUTOR(ES) DE ANÚNCIO\nNome: Tiago Botelho\nCargo: Presidente do Conselho de Administração\n419671891",
    "nipc": "510745997",
    "distrito": "Faro",
    "concelho": "Faro",
    "freguesia": "União das Freguesias de Faro (Sé e São Pedro)",
    "site": "https://www.chualgarve.min-saude.pt",
    "email": "concursos@ulsalg.min-saude.pt",
    "designacao_contrato": "Medicamentos Vários Citotóxicos",
    "descricao": "Medicamentos Vários Citotóxicos",
    "preco_base": "45.897,80 EUR",
    "prazo_execucao": "1 ANOS",
    "prazo_apresentacao_propostas": "29-10-2025 17:00",
    "fundos_eu": "Não",
    "plataforma_eletronica": "VORTAL",
    "url_procedimento": "https://community.vortal.biz/public/",
    "autor_nome": "Tiago Botelho",
    "autor_cargo": "Presidente do Conselho de Administração"
  }
]