[
  {
    "numero_procedimento": "N/A",
    "entidade": "Município de Albergaria-a-Velha",
    "link": "https://diariodarepublica.pt/dr/detalhe/contrato-publico/22346-932837032",
    "detalhes_completos": "1 - IDENTIFICAÇÃO E CONTACTOS DA ENTIDADE ADJUDICANTE\nDesignação da entidade adjudicante: Município de Albergaria-a-Velha\nNIPC: 506783146\nServiço/Órgão/Pessoa de contacto: Restabelecimento da Floresta de Albergaria-a-Velha afetada por agentes bióticas e abióticos ou por acontecimento catastróficos\nEndereço: Praça Ferreira Tavares\nCódigo postal: 3850-053\nLocalidade: Albergaria-a-Velha\nPaís: Portugal\nNUT III: PT16D\nDistrito: Aveiro\nConcelho: Albergaria-a-Velha\nFreguesia: Freguesia de Albergaria-a-Velha e Valmaior\nTelefone: 234529300\nEndereço da Entidade (URL): www.cm-albergaria.pt\nEndereço Eletrónico: geral@cm-albergaria.pt\neDelivery Gateway (URL): https://www.acingov.pt\nFunção da Organização: Adquirente\nNorma jurídica da Entidade Adjudicante: Organismo de direito público\nÁrea de atividade da Autoridade Adjudicante: Serviços públicos das administrações públicas\n\n2 - JORNAL OFICIAL DA UNIÃO EUROPEIA\nO procedimento a que este anúncio diz respeito também é publicitado no Jornal Oficial da União Europeia? Não\n\n3 - AVISO\nModelo de Anúncio: Concurso público\nData de Envio do Anúncio: 20-08-2025\n\n5 - PROCESSO\nTipo de Procedimento: Concurso público\nPreço base do procedimento: Sim\nValor do preço base do procedimento: 481.364,00 EUR\nProcedimento com lotes? Não\n\n6 - OBJETO DO CONTRATO\nNúmero de referência interna: CP/2025/122/CMAAV\nDesignação do contrato: Restabelecimento da Floresta de Albergaria-a-Velha afetada por agentes bióticas e abióticos ou por acontecimento catastróficos\nDescrição: Restabelecimento da Floresta de Albergaria-a-Velha afetada por agentes bióticas e abióticos ou por acontecimento catastróficos\nTipo de Contrato Principal: Empreitada de Obras Públicas\nTipo de Contrato: Empreitada de Obras Públicas\nClassificação CPV (Vocabulário Comum para os Contratos Públicos)\nObjeto principal\nVocabulário Principal: 45112320\nPreço base s/IVA: 481.364,00 EUR\n\n7 - INDICAÇÕES ADICIONAIS\nO contrato envolve aquisição conjunta (satisfação de várias entidades)? Não\nO contrato é adjudicado por uma central de compras? Não\n\n8 - TÉCNICAS\nO concurso destina-se à celebração de um acordo-quadro? Inexistência de acordo-quadro\nÉ utilizado um leilão eletrónico? Não\nÉ adotada uma fase de negociação? Não\nSistema de Aquisição Dinâmico: Inexistência de sistema de aquisição dinâmico\n\n9 - LOCAL DA EXECUÇÃO DO CONTRATO\nLOCAL DA EXECUÇÃO DO CONTRATO (PROCEDIMENTO)\nPaís: Portugal\nNUT III: PT16D\nLocalidade: Freguesia de Albergaria-a-Velha e Valmaior\nDistrito: Aveiro\nConcelho: Albergaria-a-Velha\nFreguesia: Freguesia de Albergaria-a-Velha e Valmaior\n\n10 - PRAZO DE EXECUÇÃO DO CONTRATO\nPrazo de execução do contrato: 150 DIAS\nPrevisão de renovações: Não\n\n11 - FUNDOS EU\nTêm fundos EU? Não\n\n12 - DOCUMENTOS DE HABILITAÇÃO\nHabilitação para o exercício da atividade profissional: Sim\nTipo: Alvará\nDescrição: 13.ª subcategoria - Caminhos agrícolas e florestais  da 5ª Categoria - Outros trabalhos da classe correspondente ao valor  total  da proposta.\n\n13 - CONDIÇÕES DE APRESENTAÇÃO\nPlataforma eletrónica utilizada pela entidade adjudicante: ACIN\nURL para Apresentação: https://www.acingov.pt\nAdmissibilidade da apresentação de propostas variantes: Não autorizado\nPrazo para apresentação das propostas: 09-09-2025 23:59\nPrazo durante o qual os concorrentes são obrigados a manter as respetivas propostas: 66 dias a contar do termo do prazo para a apresentação das propostas\nIndicação de Subcontratação na Proposta: Inexistência de indicação de subcontratação\n\n14 - PRESTAÇÃO DE CAUÇÃO\nPrestação de caução: Sim\nPercentagem: 5%\nDescrição da Garantia Exigida: O valor da caução é de 5.00% do preço contratual.\n\n15 - FORNECIMENTO DAS PEÇAS DO CONCURSO, APRESENTAÇÃO DE PEDIDOS DE PARTICIPAÇÃO E APRESENTAÇÃO DAS PROPOSTAS\nLink para acesso às peças do concurso (URL): https://www.acingov.pt/acingovprod/2/zonaPublica/zona_publica_c/donwloadProcedurePiece/OTM1MTA2\n\n20 - OUTROS REQUISITOS\nInformação sobre contratos reservados. Aplica-se a contratos reservados (54º-A)? Não\n\n21 - CRITÉRIO DE ADJUDICAÇÃO\nMultifator: Não\nMonofator:\nNome: Preço\n\n24 - CONDIÇÕES DO CONTRATO\nFaturação Eletrónica: Permitido\nObrigação de Subcontratação:\nCódigo da Obrigação de Subcontratação: Não é aplicável nenhuma obrigação de subcontratação.\n\n25 - COMPRA PÚBLICA ESTRATÉGICA\nCompra Pública Estratégica: Inexistência de contratação pública estratégica\n\n26 - INFORMAÇÕES ADICIONAIS\nContrato adequado para PME: Sim\nCobertura ACP (Acordo dos Contratos Públicos da Organização Mundial do Comércio): Não\n\n27 - IDENTIFICAÇÃO E CONTACTOS DO ÓRGÃO DE RECURSOS ADMINISTRATIVOS\nDesignação: Câmara Municipal de Albergaria-a-Velha\nEndereço: Praça Comendador Ferreira Tavares 3850-053 Albergaria-a-Velha\nCódigo postal: 3850-053\nLocalidade: Albergaria-a-Velha\nTelefone: 234529300\nFax: 234529300\nEndereço eletrónico: geral@cm-albergaria.pt\n\n28 - IDENTIFICAÇÃO DO(S) AUTOR(ES) DE ANÚNCIO\nNome: António Augusto Amaral Loureiro e Santos\nCargo: Presidente da Câmara Municipal de Albergaria-a-Velha\n419446484",
    "nipc": "506783146",
    "distrito": "Aveiro",
    "concelho": "Albergaria-a-Velha",
    "freguesia": "Freguesia de Albergaria-a-Velha e Valmaior",
    "site": "www.cm-albergaria.pt",
    "email": "geral@cm-albergaria.pt",
    "designacao_contrato": "Restabelecimento da Floresta de Albergaria-a-Velha afetada por agentes bióticas e abióticos ou por acontecimento catastróficos",
    "descricao": "Restabelecimento da Floresta de Albergaria-a-Velha afetada por agentes bióticas e abióticos ou por acontecimento catastróficos",
    "preco_base": "481.364,00 EUR",
    "prazo_execucao": "150 DIAS",
    "prazo_apresentacao_propostas": "09-09-2025 23:59",
    "fundos_eu": "Não",
    "plataforma_eletronica": "ACIN",
    "url_procedimento": "https://www.acingov.pt",
    "autor_nome": "António Augusto Amaral Loureiro e Santos",
    "autor_cargo": "Presidente da Câmara Municipal de Albergaria-a-Velha"
  },
  {
    "numero_procedimento": "N/A",
    "entidade": "Município de Montemor-o-Velho",
    "link": "https://diariodarepublica.pt/dr/detalhe/contrato-publico/22347-932837033",
    "detalhes_completos": "1 - IDENTIFICAÇÃO E CONTACTOS DA ENTIDADE ADJUDICANTE\nDesignação da entidade adjudicante: Município de Montemor-o-Velho\nNIPC: 501272976\nServiço/Órgão/Pessoa de contacto: Unidade de educação e ensino profissional\nEndereço: Praça da República\nCódigo postal: 3140-258\nLocalidade: Montemor-o-Velho\nPaís: Portugal\nNUT III: PT16E\nDistrito: Coimbra\nConcelho: Montemor-o-Velho\nFreguesia: União das Freguesias de Montemor-o-Velho e Gatões\nTelefone: 239687300\nFax: 239687318\nEndereço da Entidade (URL): www.cm-montemorvelho.pt\nEndereço Eletrónico: geral@cm-montemorvelho.pt\neDelivery Gateway (URL): https://www.acingov.pt\nFunção da Organização: Adquirente\nSubfunção da Organização: Organização que recebe as propostas\nNorma jurídica da Entidade Adjudicante: Organismo de direito público\nÁrea de atividade da Autoridade Adjudicante: Serviços públicos das administrações públicas\n\n2 - JORNAL OFICIAL DA UNIÃO EUROPEIA\nO procedimento a que este anúncio diz respeito também é publicitado no Jornal Oficial da União Europeia? Não\n\n3 - AVISO\nModelo de Anúncio: Concurso público\nData de Envio do Anúncio: 20-08-2025\n\n5 - PROCESSO\nTipo de Procedimento: Concurso público\nPreço base do procedimento: Sim\nValor do preço base do procedimento: 149.536,60 EUR\nProcedimento com lotes? Sim\nNº Máx. de Lotes Autorizado: 5\nNúmero máximo de lotes que podem ser adjudicados a um concorrente: 5\n\n6 - OBJETO DO CONTRATO\nNúmero de referência interna: DAGF/129/2025\nDesignação do contrato: Transportes escolares para o ano letivo de 2025/2026  aquisição de transporte especial para crianças e jovens com necessidades de saúde especiais\nDescrição: Transportes escolares para o ano letivo de 2025/2026  aquisição de transporte especial para crianças e jovens com necessidades de saúde especiais\nTipo de Contrato Principal: Aquisição de Serviços\nTipo de Contrato: Aquisição de Serviços\nClassificação CPV (Vocabulário Comum para os Contratos Públicos)\nObjeto principal\nVocabulário Principal: 63712000\nPreço base s/IVA: 149.536,60 EUR\nLotes: \nNº: LOT-0001\nDescrição do Lote: Aluno 1, residente na Rua Dr. João Martins, n.º 3, Pereira, para a Escola Básica de Pereira\nPreço base s/IVA: 1.342,50 EUR\nClassificação CPV (Vocabulário Comum para os Contratos Públicos)\nObjeto principal\nVocabulário Principal: 63712000\nNº: LOT-0002\nDescrição do Lote: Aluno 1, residente na Rua das Flores, n.º 885, Resgatados, para a Escola Básica Infante D. Pedro, Buarcos  Figueira da Foz. Aluno 2, residente na Travessa do Vale Forno, nº 240  Valcanosa, Meãs do Campo, para a Escola Básica do Serrado\nPreço base s/IVA: 42.673,60 EUR\nClassificação CPV (Vocabulário Comum para os Contratos Públicos)\nObjeto principal\nVocabulário Principal: 63712000\nNº: LOT-0003\nDescrição do Lote: Aluno 1, residente na Rua D. Nuno Álvares Pereira, n.º 485, Tentúgal, para a EB 2,3 Martim de Freitas, Coimbra\nPreço base s/IVA: 39.469,50 EUR\nClassificação CPV (Vocabulário Comum para os Contratos Públicos)\nObjeto principal\nVocabulário Principal: 63712000\nNº: LOT-0004\nDescrição do Lote: Aluna 1, residente na Trav. Principal dos Catarruchos, n.º 23, para a sede do Agrupamento de Escolas de Montemor-o-Velho  transporte adaptado para cadeira de rodas\nPreço base s/IVA: 53.700,00 EUR\nClassificação CPV (Vocabulário Comum para os Contratos Públicos)\nObjeto principal\nVocabulário Principal: 63712000\nNº: LOT-0005\nDescrição do Lote: Aluno 1, residente na Rua do Cabeço, n.º 421, Vila Franca, Arazede, para a EB 2,3 Poeta Manuel Silva Gaio, Coimbra\nPreço base s/IVA: 12.351,00 EUR\nClassificação CPV (Vocabulário Comum para os Contratos Públicos)\nObjeto principal\nVocabulário Principal: 63712000\n\n7 - INDICAÇÕES ADICIONAIS\nO contrato envolve aquisição conjunta (satisfação de várias entidades)? Não\nO contrato é adjudicado por uma central de compras? Não\n\n8 - TÉCNICAS\nO concurso destina-se à celebração de um acordo-quadro? Inexistência de acordo-quadro\nÉ utilizado um leilão eletrónico? Não\nÉ adotada uma fase de negociação? Não\nSistema de Aquisição Dinâmico: Inexistência de sistema de aquisição dinâmico\n\n9 - LOCAL DA EXECUÇÃO DO CONTRATO\nLOCAL DA EXECUÇÃO DO CONTRATO (PROCEDIMENTO)\nPaís: Portugal\nNUT III: PT16E\nLocalidade: Montemor-o-velho\nDistrito: Coimbra\nConcelho: Montemor-o-Velho\nFreguesia: Todas\nLOCAL DA EXECUÇÃO DO CONTRATO (LOTE)\nIdentificador do Lote: LOT-0001; LOT-0002; LOT-0003; LOT-0004; LOT-0005\nPaís: Portugal\nNUT III: PT16E\nLocalidade: Montemor-o-velho\nDistrito: Coimbra\nConcelho: Montemor-o-Velho\nFreguesia: Todas\n\n10 - PRAZO DE EXECUÇÃO DO CONTRATO\nIdentificador do Lote: LOT-0001; LOT-0002; LOT-0003; LOT-0004; LOT-0005\nPrazo de execução do contrato: 179 DIAS\nPrevisão de renovações: Não\n\n11 - FUNDOS EU\nIdentificador do Lote: LOT-0001; LOT-0002; LOT-0003; LOT-0004; LOT-0005\nTêm fundos EU? Não\n\n12 - DOCUMENTOS DE HABILITAÇÃO\nHabilitação para o exercício da atividade profissional: Não\n\n13 - CONDIÇÕES DE APRESENTAÇÃO\nPlataforma eletrónica utilizada pela entidade adjudicante: ACIN\nURL para Apresentação: https://www.acingov.pt\nAdmissibilidade da apresentação de propostas variantes: Não autorizado\nPrazo para apresentação das propostas: 26-08-2025 23:59\nPrazo durante o qual os concorrentes são obrigados a manter as respetivas propostas: 66 dias a contar do termo do prazo para a apresentação das propostas\nIndicação de Subcontratação na Proposta: Inexistência de indicação de subcontratação\n\n14 - PRESTAÇÃO DE CAUÇÃO\nPrestação de caução: Não\n\n15 - FORNECIMENTO DAS PEÇAS DO CONCURSO, APRESENTAÇÃO DE PEDIDOS DE PARTICIPAÇÃO E APRESENTAÇÃO DAS PROPOSTAS\nLink para acesso às peças do concurso (URL): https://www.acingov.pt/acingovprod/2/zonaPublica/zona_publica_c/donwloadProcedurePiece/OTM1NzUz\n\n20 - OUTROS REQUISITOS\nIdentificador do Lote: LOT-0001; LOT-0002; LOT-0003; LOT-0004; LOT-0005\nInformação sobre contratos reservados. Aplica-se a contratos reservados (54º-A)? Não\n\n21 - CRITÉRIO DE ADJUDICAÇÃO\nO Critério de adjudicação é diferenciado por lote? Não\nMultifator: Não\nMonofator:\nNome: Preço\n\n24 - CONDIÇÕES DO CONTRATO\nIdentificador do Lote: LOT-0001; LOT-0002; LOT-0003; LOT-0004; LOT-0005\nFaturação Eletrónica: Permitido\nObrigação de Subcontratação:\nCódigo da Obrigação de Subcontratação: Não é aplicável nenhuma obrigação de subcontratação.\n\n25 - COMPRA PÚBLICA ESTRATÉGICA\nCompra Pública Estratégica: Inexistência de contratação pública estratégica\n\n26 - INFORMAÇÕES ADICIONAIS\nIdentificador do Lote: LOT-0001; LOT-0002; LOT-0003; LOT-0004; LOT-0005\nContrato adequado para PME: Sim\nCobertura ACP (Acordo dos Contratos Públicos da Organização Mundial do Comércio): Não\n\n27 - IDENTIFICAÇÃO E CONTACTOS DO ÓRGÃO DE RECURSOS ADMINISTRATIVOS\nDesignação: Câmara Municipal\nEndereço: Praça da República\nCódigo postal: 3140-258\nLocalidade: Montemor-o-Velho\nTelefone: 351239687300\nFax: 351239687319\nEndereço eletrónico: compras.publicas@cm-montemorvelho.pt\n\n28 - IDENTIFICAÇÃO DO(S) AUTOR(ES) DE ANÚNCIO\nNome: Emílio Augusto Ferreira Torrão\nCargo: Presidente da Câmara Municipal\n419453352",
    "nipc": "501272976",
    "distrito": "Coimbra",
    "concelho": "Montemor-o-Velho",
    "freguesia": "União das Freguesias de Montemor-o-Velho e Gatões",
    "site": "www.cm-montemorvelho.pt",
    "email": "geral@cm-montemorvelho.pt",
    "designacao_contrato": "Transportes escolares para o ano letivo de 2025/2026  aquisição de transporte especial para crianças e jovens com necessidades de saúde especiais",
    "descricao": "Transportes escolares para o ano letivo de 2025/2026  aquisição de transporte especial para crianças e jovens com necessidades de saúde especiais",
    "preco_base": "149.536,60 EUR",
    "prazo_execucao": "179 DIAS",
    "prazo_apresentacao_propostas": "26-08-2025 23:59",
    "fundos_eu": "Não",
    "plataforma_eletronica": "ACIN",
    "url_procedimento": "https://www.acingov.pt",
    "autor_nome": "Emílio Augusto Ferreira Torrão",
    "autor_cargo": "Presidente da Câmara Municipal"
  },
  {
    "numero_procedimento": "N/A",
    "entidade": "MUNICIPIO DE LAGOA",
    "link": "https://diariodarepublica.pt/dr/detalhe/contrato-publico/22349-932837034",
    "detalhes_completos": "1 - IDENTIFICAÇÃO E CONTACTOS DA ENTIDADE ADJUDICANTE\nDesignação da entidade adjudicante: MUNICIPIO DE LAGOA\nNIPC: 506804240\nEndereço: Edifício Paços do Concelho, Largo do Município\nCódigo postal: 8401-851\nLocalidade: Faro\nPaís: Portugal\nNUT III: PT150\nDistrito: Faro\nConcelho: Lagoa\nFreguesia: Todas\nTelefone: 282380400\nFax: 282380444\nEndereço da Entidade (URL): www.cm-lagoa.pt\nEndereço Eletrónico: geral@cm-lagoa.pt\neDelivery Gateway (URL): https://community.vortal.biz/public/\nFunção da Organização: Adquirente\nNorma jurídica da Entidade Adjudicante: Organismo de direito público\nÁrea de atividade da Autoridade Adjudicante: Serviços públicos das administrações públicas\n\n2 - JORNAL OFICIAL DA UNIÃO EUROPEIA\nO procedimento a que este anúncio diz respeito também é publicitado no Jornal Oficial da União Europeia? Sim\n\n3 - AVISO\nModelo de Anúncio: Concurso público\nData de Envio do Anúncio: 18-08-2025\n\n5 - PROCESSO\nTipo de Procedimento: Concurso público\nPreço base do procedimento: Sim\nValor do preço base do procedimento: 498.210,00 EUR\nProcedimento com lotes? Não\n\n6 - OBJETO DO CONTRATO\nNúmero de referência interna: 471/2025\nDesignação do contrato: Implementação de sistema de videovigilância CCTV em Carvoeiro\nDescrição: Implementação de sistema de videovigilância CCTV em Carvoeiro, com mecanismo de gravação na sala técnica do posto territorial (SPTER) de Lagoa, software de controlo com sistema de interligação das câmaras na rede, incluindo todos os equipamentos e a sua montagem, configuração e colocação em serviço, ações de formação no âmbito da operação e configuração e, ainda, instalação de infraestruturas.\nOpções: Não\nTipo de Contrato Principal: Aquisição de Bens Móveis\nTipo de Contrato: Aquisição de Bens Móveis; Aquisição de Serviços\nClassificação CPV (Vocabulário Comum para os Contratos Públicos)\nObjeto principal\nVocabulário Principal: 35120000\nPreço base s/IVA: 276.711,00 EUR\nObjeto Complementar\nVocabulário Principal: 51314000\nPreço base s/IVA: 209.130,00 EUR\nObjeto Complementar\nVocabulário Principal: 50324100\nPreço base s/IVA: 12.369,00 EUR\n\n7 - INDICAÇÕES ADICIONAIS\nO contrato envolve aquisição conjunta (satisfação de várias entidades)? Não\nO contrato é adjudicado por uma central de compras? Não\n\n8 - TÉCNICAS\nO concurso destina-se à celebração de um acordo-quadro? Inexistência de acordo-quadro\nÉ utilizado um leilão eletrónico? Não\nÉ adotada uma fase de negociação? Não\nSistema de Aquisição Dinâmico: Inexistência de sistema de aquisição dinâmico\n\n9 - LOCAL DA EXECUÇÃO DO CONTRATO\nLOCAL DA EXECUÇÃO DO CONTRATO (PROCEDIMENTO)\nPaís: Portugal\nNUT III: PT150\nLocalidade: Faro\nDistrito: Faro\nConcelho: Lagoa\nFreguesia: União das Freguesias de Lagoa e Carvoeiro\n\n10 - PRAZO DE EXECUÇÃO DO CONTRATO\nPrazo de execução do contrato: 5 MESES\nPrevisão de renovações: Não\n\n11 - FUNDOS EU\nTêm fundos EU? Não\n\n12 - DOCUMENTOS DE HABILITAÇÃO\nHabilitação para o exercício da atividade profissional: Não\n\n13 - CONDIÇÕES DE APRESENTAÇÃO\nPlataforma eletrónica utilizada pela entidade adjudicante: VORTAL\nURL para Apresentação: https://community.vortal.biz/public/\nAdmissibilidade da apresentação de propostas variantes: Não autorizado\nPrazo para apresentação das propostas: 15-09-2025 17:00\nPrazo durante o qual os concorrentes são obrigados a manter as respetivas propostas: 66 dias a contar do termo do prazo para a apresentação das propostas\nApresentação de Catálogo Eletrónico: Não autorizado\nIndicação de Subcontratação na Proposta: Inexistência de indicação de subcontratação\n\n14 - PRESTAÇÃO DE CAUÇÃO\nPrestação de caução: Não\n\n15 - FORNECIMENTO DAS PEÇAS DO CONCURSO, APRESENTAÇÃO DE PEDIDOS DE PARTICIPAÇÃO E APRESENTAÇÃO DAS PROPOSTAS\nLink para acesso às peças do concurso (URL): https://community.vortal.biz/Public/public-tender-documents/Z2Vqd1RlTHhIUUczWG9UdXUxSk5ieWNJZHNlbHUvVEFYcmZLdFowSUxId2RXM1hMWEk1c3JuemJPYnNBU3d0dC9tTTY3YnNDY1AzY0tNZmxaWlRpcnc9PShFREYp\n\n20 - OUTROS REQUISITOS\nInformação sobre contratos reservados. Aplica-se a contratos reservados (54º-A)? Não\n\n21 - CRITÉRIO DE ADJUDICAÇÃO\nMultifator: Não\nMonofator:\nNome: Preço\n\n24 - CONDIÇÕES DO CONTRATO\nFaturação Eletrónica: Permitido\nObrigação de Subcontratação:\nCódigo da Obrigação de Subcontratação: Não é aplicável nenhuma obrigação de subcontratação.\n\n25 - COMPRA PÚBLICA ESTRATÉGICA\nCompra Pública Estratégica: Inexistência de contratação pública estratégica\n\n26 - INFORMAÇÕES ADICIONAIS\nContrato adequado para PME: Sim\nCobertura ACP (Acordo dos Contratos Públicos da Organização Mundial do Comércio): Sim\n\n27 - IDENTIFICAÇÃO E CONTACTOS DO ÓRGÃO DE RECURSOS ADMINISTRATIVOS\nDesignação: Município de Lagoa\nEndereço: LARGO DO MUNICÍPIO\nCódigo postal: 8401-851\nLocalidade: Lagoa\nTelefone: +351 282380400\nFax: +351 282380444\nEndereço eletrónico: geral@cm-lagoa.pt\n\n28 - IDENTIFICAÇÃO DO(S) AUTOR(ES) DE ANÚNCIO\nNome: Ana Cristina Tiago Martins\nCargo: Vereadora\n419428178",
    "nipc": "506804240",
    "distrito": "Faro",
    "concelho": "Lagoa",
    "freguesia": "Todas",
    "site": "www.cm-lagoa.pt",
    "email": "geral@cm-lagoa.pt",
    "designacao_contrato": "Implementação de sistema de videovigilância CCTV em Carvoeiro",
    "descricao": "Implementação de sistema de videovigilância CCTV em Carvoeiro, com mecanismo de gravação na sala técnica do posto territorial (SPTER) de Lagoa, software de controlo com sistema de interligação das câmaras na rede, incluindo todos os equipamentos e a sua montagem, configuração e colocação em serviço, ações de formação no âmbito da operação e configuração e, ainda, instalação de infraestruturas.",
    "preco_base": "276.711,00 EUR",
    "prazo_execucao": "5 MESES",
    "prazo_apresentacao_propostas": "15-09-2025 17:00",
    "fundos_eu": "Não",
    "plataforma_eletronica": "VORTAL",
    "url_procedimento": "https://community.vortal.biz/public/",
    "autor_nome": "Ana Cristina Tiago Martins",
    "autor_cargo": "Vereadora"
  },
  {
    "numero_procedimento": "N/A",
    "entidade": "MUNICIPIO DE LAGOA",
    "link": "https://diariodarepublica.pt/dr/detalhe/contrato-publico/22350-932837035",
    "detalhes_completos": "1 - IDENTIFICAÇÃO E CONTACTOS DA ENTIDADE ADJUDICANTE\nDesignação da entidade adjudicante: MUNICIPIO DE LAGOA\nNIPC: 506804240\nEndereço: Edifício Paços do Concelho, Largo do Município\nCódigo postal: 8401-851\nLocalidade: Faro\nPaís: Portugal\nNUT III: PT150\nDistrito: Faro\nConcelho: Lagoa\nFreguesia: Todas\nTelefone: 282380400\nFax: 282380444\nEndereço da Entidade (URL): www.cm-lagoa.pt\nEndereço Eletrónico: geral@cm-lagoa.pt\neDelivery Gateway (URL): https://community.vortal.biz/public/\nFunção da Organização: Adquirente\nNorma jurídica da Entidade Adjudicante: Organismo de direito público\nÁrea de atividade da Autoridade Adjudicante: Serviços públicos das administrações públicas\n\n2 - JORNAL OFICIAL DA UNIÃO EUROPEIA\nO procedimento a que este anúncio diz respeito também é publicitado no Jornal Oficial da União Europeia? Sim\n\n3 - AVISO\nModelo de Anúncio: Concurso público\nData de Envio do Anúncio: 18-08-2025\n\n5 - PROCESSO\nTipo de Procedimento: Concurso público\nPreço base do procedimento: Sim\nValor do preço base do procedimento: 2.053.944,00 EUR\nProcedimento com lotes? Sim\nNº Máx. de Lotes Autorizado: 2\nNúmero máximo de lotes que podem ser adjudicados a um concorrente: 2\n\n6 - OBJETO DO CONTRATO\nNúmero de referência interna: 691/2025\nDesignação do contrato: Manutenção e conservação de espaços verdes no concelho de lagoa e campos desportivos\nDescrição: Manutenção e conservação de espaços verdes no concelho de lagoa e campos desportivos\nOpções: Não\nTipo de Contrato Principal: Aquisição de Serviços\nTipo de Contrato: Aquisição de Serviços\nClassificação CPV (Vocabulário Comum para os Contratos Públicos)\nObjeto principal\nVocabulário Principal: 77310000\nPreço base s/IVA: 1.499.976,00 EUR\nObjeto Complementar\nVocabulário Principal: 77320000\nPreço base s/IVA: 553.968,00 EUR\nLotes: \nNº: LOT-0001\nDescrição do Lote: Lote 1\nPreço base s/IVA: 1.499.976,00 EUR\nClassificação CPV (Vocabulário Comum para os Contratos Públicos)\nObjeto principal\nVocabulário Principal: 77310000\nObjeto Complementar\nVocabulário Principal: 77320000\nNº: LOT-0002\nDescrição do Lote: Lote 2\nPreço base s/IVA: 553.968,00 EUR\nClassificação CPV (Vocabulário Comum para os Contratos Públicos)\nObjeto principal\nVocabulário Principal: 77310000\nObjeto Complementar\nVocabulário Principal: 77320000\n\n7 - INDICAÇÕES ADICIONAIS\nO contrato envolve aquisição conjunta (satisfação de várias entidades)? Não\nO contrato é adjudicado por uma central de compras? Não\n\n8 - TÉCNICAS\nO concurso destina-se à celebração de um acordo-quadro? Inexistência de acordo-quadro\nÉ utilizado um leilão eletrónico? Não\nÉ adotada uma fase de negociação? Não\nSistema de Aquisição Dinâmico: Inexistência de sistema de aquisição dinâmico\n\n9 - LOCAL DA EXECUÇÃO DO CONTRATO\nLOCAL DA EXECUÇÃO DO CONTRATO (PROCEDIMENTO)\nPaís: Portugal\nNUT III: PT150\nLocalidade: Faro\nDistrito: Faro\nConcelho: Lagoa\nFreguesia: União das Freguesias de Lagoa e Carvoeiro\nLOCAL DA EXECUÇÃO DO CONTRATO (LOTE)\nIdentificador do Lote: LOT-0001; LOT-0002\nPaís: Portugal\nNUT III: PT150\nLocalidade: Faro\nDistrito: Faro\nConcelho: Lagoa\nFreguesia: União das Freguesias de Lagoa e Carvoeiro\n\n10 - PRAZO DE EXECUÇÃO DO CONTRATO\nIdentificador do Lote: LOT-0001; LOT-0002\nPrazo de execução do contrato: 36 MESES\nPrevisão de renovações: Não\n\n11 - FUNDOS EU\nIdentificador do Lote: LOT-0001; LOT-0002\nTêm fundos EU? Não\n\n12 - DOCUMENTOS DE HABILITAÇÃO\nHabilitação para o exercício da atividade profissional: Não\n\n13 - CONDIÇÕES DE APRESENTAÇÃO\nPlataforma eletrónica utilizada pela entidade adjudicante: VORTAL\nURL para Apresentação: https://community.vortal.biz/public/\nAdmissibilidade da apresentação de propostas variantes: Não autorizado\nPrazo para apresentação das propostas: 17-09-2025 17:00\nPrazo durante o qual os concorrentes são obrigados a manter as respetivas propostas: 66 dias a contar do termo do prazo para a apresentação das propostas\nApresentação de Catálogo Eletrónico: Não autorizado\nIndicação de Subcontratação na Proposta: Inexistência de indicação de subcontratação\n\n14 - PRESTAÇÃO DE CAUÇÃO\nPrestação de caução: Sim\nPercentagem: 5%\nDescrição da Garantia Exigida: Conforme peças.\n\n15 - FORNECIMENTO DAS PEÇAS DO CONCURSO, APRESENTAÇÃO DE PEDIDOS DE PARTICIPAÇÃO E APRESENTAÇÃO DAS PROPOSTAS\nLink para acesso às peças do concurso (URL): https://community.vortal.biz/Public/public-tender-documents/K0lZYTZ1NzNZK2Jkc2RVYWlKeWRhdDlTblNScVRzS3ZZckFCTXdGcTZCRXhRdnJjS0FuN3p5bVd1NW90QVFOQ25EVk5xWUxNcUIyb1Z6NEx1c1NIWVE9PUZhWipV\n\n20 - OUTROS REQUISITOS\nIdentificador do Lote: LOT-0001; LOT-0002\nInformação sobre contratos reservados. Aplica-se a contratos reservados (54º-A)? Não\n\n21 - CRITÉRIO DE ADJUDICAÇÃO\nO Critério de adjudicação é diferenciado por lote? Sim\nIdentificador do lote: LOT-0001\nMultifator: Sim\nFator: \nNome: Preço\nPonderação: 55%\nSubfatores: Não\nFator: \nNome: Qualidade\nPonderação: 45%\nSubfatores: SimSubfatores: \nNome: A1 - Apresentação de Memória descritiva e justificativa do modo de execução de todas as atividades e tarefas a desenvolver nos campos desportivos\nPonderação : 30%; \nNome: A2 - Apresentação de um plano de trabalhos com a descrição da coordenação entre as várias tarefas, dimensionamentos de equipas, rendimento, equipamentos afetos aos relvados desportivos e melhorias técnicas das tarefas a desempenhar com cronograma de intervenções anual\nPonderação : 70%; \n\nO Critério de adjudicação é diferenciado por lote? Sim\nIdentificador do lote: LOT-0002\nMultifator: Sim\nFator: \nNome: Preço\nPonderação: 55%\nSubfatores: Não\nFator: \nNome: Qualidade\nPonderação: 45%\nSubfatores: SimSubfatores: \nNome: A1 - Apresentação de Memória descritiva e justificativa do modo de execução de todas as atividades e tarefas a desenvolver nas áreas de manutenção\nPonderação : 30%; \nNome: A2 - Apresentação de um plano de trabalhos com a descrição da coordenação entre as várias tarefas, dimensionamentos de equipas, rendimento, equipamentos afetos e melhorias técnicas das tarefas a desempenhar\nPonderação : 70%; \n\n24 - CONDIÇÕES DO CONTRATO\nIdentificador do Lote: LOT-0001; LOT-0002\nFaturação Eletrónica: Permitido\nObrigação de Subcontratação:\nCódigo da Obrigação de Subcontratação: Não é aplicável nenhuma obrigação de subcontratação.\n\n25 - COMPRA PÚBLICA ESTRATÉGICA\nCompra Pública Estratégica: Inexistência de contratação pública estratégica\n\n26 - INFORMAÇÕES ADICIONAIS\nIdentificador do Lote: LOT-0001; LOT-0002\nContrato adequado para PME: Sim\nCobertura ACP (Acordo dos Contratos Públicos da Organização Mundial do Comércio): Sim\n\n27 - IDENTIFICAÇÃO E CONTACTOS DO ÓRGÃO DE RECURSOS ADMINISTRATIVOS\nDesignação: Município de Lagoa\nEndereço: Edifício Paços do Concelho, Largo do Município\nCódigo postal: 8401-851\nLocalidade: Lagoa\nTelefone: +351 282380400\nFax: +351 282380444\nEndereço eletrónico: geral@cm-lagoa.pt\n\n28 - IDENTIFICAÇÃO DO(S) AUTOR(ES) DE ANÚNCIO\nNome: Ana Cristina Tiago Martins\nCargo: Vereadora\n419427205",
    "nipc": "506804240",
    "distrito": "Faro",
    "concelho": "Lagoa",
    "freguesia": "Todas",
    "site": "www.cm-lagoa.pt",
    "email": "geral@cm-lagoa.pt",
    "designacao_contrato": "Manutenção e conservação de espaços verdes no concelho de lagoa e campos desportivos",
    "descricao": "Manutenção e conservação de espaços verdes no concelho de lagoa e campos desportivos",
    "preco_base": "1.499.976,00 EUR",
    "prazo_execucao": "36 MESES",
    "prazo_apresentacao_propostas": "17-09-2025 17:00",
    "fundos_eu": "Não",
    "plataforma_eletronica": "VORTAL",
    "url_procedimento": "https://community.vortal.biz/public/",
    "autor_nome": "Ana Cristina Tiago Martins",
    "autor_cargo": "Vereadora"
  },
  {
    "numero_procedimento": "N/A",
    "entidade": "Município da Lousã",
    "link": "https://diariodarepublica.pt/dr/detalhe/contrato-publico/22351-932837036",
    "detalhes_completos": "1 - IDENTIFICAÇÃO E CONTACTOS DA ENTIDADE ADJUDICANTE\nDesignação da entidade adjudicante: Município da Lousã\nNIPC: 501121528\nServiço/Órgão/Pessoa de contacto: Serviço de Contratação Pública e Gestão de Stocks\nEndereço: Rua Dr. João Santos\nCódigo postal: 3200-953\nLocalidade: Lousã\nPaís: Portugal\nNUT III: PT16E\nDistrito: Coimbra\nConcelho: Lousã\nFreguesia: União das Freguesias de Lousã e Vilarinho\nTelefone: 239990370\nFax: 239990381\nEndereço da Entidade (URL): www.cm-lousa.pt\nEndereço Eletrónico: aprovisionamento@cm-lousa.pt\neDelivery Gateway (URL): https://www.acingov.pt\nFunção da Organização: Adquirente\nNorma jurídica da Entidade Adjudicante: Organismo de direito público\nÁrea de atividade da Autoridade Adjudicante: Serviços públicos das administrações públicas\n\n2 - JORNAL OFICIAL DA UNIÃO EUROPEIA\nO procedimento a que este anúncio diz respeito também é publicitado no Jornal Oficial da União Europeia? Não\n\n3 - AVISO\nModelo de Anúncio: Concurso público\nData de Envio do Anúncio: 20-08-2025\n\n5 - PROCESSO\nTipo de Procedimento: Concurso público\nPreço base do procedimento: Sim\nValor do preço base do procedimento: 117.000,00 EUR\nProcedimento com lotes? Não\n\n6 - OBJETO DO CONTRATO\nNúmero de referência interna: Concurso Público n.º 7/2025\nDesignação do contrato: Concurso Público n.º 7/2025 - Fornecimento de uma solução de segurança (Cluster de Firewall e XDR)\nDescrição: Concurso Público n.º 7/2025 - Fornecimento de uma solução de segurança (Cluster de Firewall e XDR)\nTipo de Contrato Principal: Aquisição de Bens Móveis\nTipo de Contrato: Aquisição de Bens Móveis\nClassificação CPV (Vocabulário Comum para os Contratos Públicos)\nObjeto principal\nVocabulário Principal: 30200000\nPreço base s/IVA: 117.000,00 EUR\n\n7 - INDICAÇÕES ADICIONAIS\nO contrato envolve aquisição conjunta (satisfação de várias entidades)? Não\nO contrato é adjudicado por uma central de compras? Não\n\n8 - TÉCNICAS\nO concurso destina-se à celebração de um acordo-quadro? Inexistência de acordo-quadro\nÉ utilizado um leilão eletrónico? Não\nÉ adotada uma fase de negociação? Não\nSistema de Aquisição Dinâmico: Inexistência de sistema de aquisição dinâmico\n\n9 - LOCAL DA EXECUÇÃO DO CONTRATO\nLOCAL DA EXECUÇÃO DO CONTRATO (PROCEDIMENTO)\nPaís: Portugal\nNUT III: PT16E\nLocalidade: Lousã\nDistrito: Coimbra\nConcelho: Lousã\nFreguesia: União das Freguesias de Lousã e Vilarinho\n\n10 - PRAZO DE EXECUÇÃO DO CONTRATO\nPrazo de execução do contrato: 3 ANOS\nPrevisão de renovações: Não\n\n11 - FUNDOS EU\nTêm fundos EU? Não\n\n12 - DOCUMENTOS DE HABILITAÇÃO\nHabilitação para o exercício da atividade profissional: Não\n\n13 - CONDIÇÕES DE APRESENTAÇÃO\nPlataforma eletrónica utilizada pela entidade adjudicante: ACIN\nURL para Apresentação: https://www.acingov.pt\nAdmissibilidade da apresentação de propostas variantes: Não autorizado\nPrazo para apresentação das propostas: 31-08-2025 23:59\nPrazo durante o qual os concorrentes são obrigados a manter as respetivas propostas: 66 dias a contar do termo do prazo para a apresentação das propostas\nIndicação de Subcontratação na Proposta: Inexistência de indicação de subcontratação\n\n14 - PRESTAÇÃO DE CAUÇÃO\nPrestação de caução: Não\n\n15 - FORNECIMENTO DAS PEÇAS DO CONCURSO, APRESENTAÇÃO DE PEDIDOS DE PARTICIPAÇÃO E APRESENTAÇÃO DAS PROPOSTAS\nLink para acesso às peças do concurso (URL): https://www.acingov.pt/acingovprod/2/zonaPublica/zona_publica_c/donwloadProcedurePiece/OTM1NjI3\n\n20 - OUTROS REQUISITOS\nInformação sobre contratos reservados. Aplica-se a contratos reservados (54º-A)? Não\n\n21 - CRITÉRIO DE ADJUDICAÇÃO\nMultifator: Não\nMonofator:\nNome: Preço\n\n24 - CONDIÇÕES DO CONTRATO\nFaturação Eletrónica: Permitido\nObrigação de Subcontratação:\nCódigo da Obrigação de Subcontratação: Não é aplicável nenhuma obrigação de subcontratação.\n\n25 - COMPRA PÚBLICA ESTRATÉGICA\nCompra Pública Estratégica: Inexistência de contratação pública estratégica\n\n26 - INFORMAÇÕES ADICIONAIS\nContrato adequado para PME: Não\nCobertura ACP (Acordo dos Contratos Públicos da Organização Mundial do Comércio): Não\n\n27 - IDENTIFICAÇÃO E CONTACTOS DO ÓRGÃO DE RECURSOS ADMINISTRATIVOS\nDesignação: Presidente da Câmara Municipal\nEndereço: Rua Dr. João Santos\nCódigo postal: 3200-953\nLocalidade: Lousã\nTelefone: 239990370\nFax: 239990381\nEndereço eletrónico: geral@cm-lousa.pt\n\n28 - IDENTIFICAÇÃO DO(S) AUTOR(ES) DE ANÚNCIO\nNome: Luís Miguel Correia Antunes\nCargo: Presidente da Câmara\n419452583",
    "nipc": "501121528",
    "distrito": "Coimbra",
    "concelho": "Lousã",
    "freguesia": "União das Freguesias de Lousã e Vilarinho",
    "site": "www.cm-lousa.pt",
    "email": "aprovisionamento@cm-lousa.pt",
    "designacao_contrato": "Concurso Público n.º 7/2025 - Fornecimento de uma solução de segurança (Cluster de Firewall e XDR)",
    "descricao": "Concurso Público n.º 7/2025 - Fornecimento de uma solução de segurança (Cluster de Firewall e XDR)",
    "preco_base": "117.000,00 EUR",
    "prazo_execucao": "3 ANOS",
    "prazo_apresentacao_propostas": "31-08-2025 23:59",
    "fundos_eu": "Não",
    "plataforma_eletronica": "ACIN",
    "url_procedimento": "https://www.acingov.pt",
    "autor_nome": "Luís Miguel Correia Antunes",
    "autor_cargo": "Presidente da Câmara"
  },
  {
    "numero_procedimento": "N/A",
    "entidade": "Fundação INATEL",
    "link": "https://diariodarepublica.pt/dr/detalhe/contrato-publico/22352-932837037",
    "detalhes_completos": "1 - IDENTIFICAÇÃO E CONTACTOS DA ENTIDADE ADJUDICANTE\nDesignação da entidade adjudicante: Fundação INATEL\nNIPC: 500122237\nServiço/Órgão/Pessoa de contacto: Núcleo de Contratação Pública\nEndereço: Calçada de Santana, nº 180\nCódigo postal: 1169-062\nLocalidade: Lisboa\nPaís: Portugal\nNUT III: PT170\nDistrito: Lisboa\nConcelho: Lisboa\nFreguesia: Freguesia de Arroios - Lisboa\nTelefone: 210027000\nFax: 210027000\nEndereço da Entidade (URL): https://www.inatel.pt\nEndereço Eletrónico: fundacao.inatel@inatel.pt\neDelivery Gateway (URL): https://www.acingov.pt\nFunção da Organização: Adquirente\nSubfunção da Organização: Organização cujo orçamento é utilizado para pagar o contrato; Organização que executa o pagamento; Organização que fornece informações adicionais sobre o processo de adjudicação; Organização que fornece mais informações sobre os prazos dos procedimentos de recurso; Organização que fornece acesso fora de linha aos documentos do concurso; Organização responsável pelo tratamento das propostas; Organização que recebe as propostas; Organização que trata os pedidos de participação; Organização que recebe pedidos de participação; Organização que fornece mais informações sobre os procedimentos de recurso; Organização que assina o contrato\nNorma jurídica da Entidade Adjudicante: Organismo de direito público\nÁrea de atividade da Autoridade Adjudicante: Atividades recreativas, culturais e religiosas\n\n2 - JORNAL OFICIAL DA UNIÃO EUROPEIA\nO procedimento a que este anúncio diz respeito também é publicitado no Jornal Oficial da União Europeia? Sim\n\n3 - AVISO\nModelo de Anúncio: Concurso público\nData de Envio do Anúncio: 18-08-2025\n\n5 - PROCESSO\nTipo de Procedimento: Concurso público\nPreço base do procedimento: Sim\nValor do preço base do procedimento: 327.008,80 EUR\nProcedimento com lotes? Sim\nNº Máx. de Lotes Autorizado: 26\nNúmero máximo de lotes que podem ser adjudicados a um concorrente: 26\n\n6 - OBJETO DO CONTRATO\nNúmero de referência interna: P.25.175/NCP\nDesignação do contrato: Carne de Bovino\nDescrição: Carne de Bovino \nOpções: Não\nTipo de Contrato Principal: Aquisição de Bens Móveis\nTipo de Contrato: Aquisição de Bens Móveis\nClassificação CPV (Vocabulário Comum para os Contratos Públicos)\nObjeto principal\nVocabulário Principal: 15111000\nPreço base s/IVA: 327.008,80 EUR\nLotes: \nNº: LOT-0001\nDescrição do Lote: Lote 1  Vila Nova de Cerveira (congelada)\nPreço base s/IVA: 21.809,20 EUR\nClassificação CPV (Vocabulário Comum para os Contratos Públicos)\nObjeto principal\nVocabulário Principal: 15111000\nNº: LOT-0002\nDescrição do Lote: Lote 2  Santa Maria da Feira (fresca)\nPreço base s/IVA: 308,00 EUR\nClassificação CPV (Vocabulário Comum para os Contratos Públicos)\nObjeto principal\nVocabulário Principal: 15111000\nNº: LOT-0003\nDescrição do Lote: Lote 3  Santa Maria da Feira (congelada)\nPreço base s/IVA: 7.206,90 EUR\nClassificação CPV (Vocabulário Comum para os Contratos Públicos)\nObjeto principal\nVocabulário Principal: 15111000\nNº: LOT-0004\nDescrição do Lote: Lote 4  Luso (fresca)\nPreço base s/IVA: 638,00 EUR\nClassificação CPV (Vocabulário Comum para os Contratos Públicos)\nObjeto principal\nVocabulário Principal: 15111000\nNº: LOT-0005\nDescrição do Lote: Lote 5  Luso (congelada)\nPreço base s/IVA: 5.478,80 EUR\nClassificação CPV (Vocabulário Comum para os Contratos Públicos)\nObjeto principal\nVocabulário Principal: 15111000\nNº: LOT-0006\nDescrição do Lote: Lote 6  São Pedro do Sul (fresca)\nPreço base s/IVA: 26.346,50 EUR\nClassificação CPV (Vocabulário Comum para os Contratos Públicos)\nObjeto principal\nVocabulário Principal: 15111000\nNº: LOT-0007\nDescrição do Lote: Lote 7  São Pedro do Sul (congelada)\nPreço base s/IVA: 1.950,40 EUR\nClassificação CPV (Vocabulário Comum para os Contratos Públicos)\nObjeto principal\nVocabulário Principal: 15111000\nNº: LOT-0008\nDescrição do Lote: Lote 8  Vila Ruiva (fresca)\nPreço base s/IVA: 8.905,70 EUR\nClassificação CPV (Vocabulário Comum para os Contratos Públicos)\nObjeto principal\nVocabulário Principal: 15111000\nNº: LOT-0009\nDescrição do Lote: Lote 9  Vila Ruiva (congelada)\nPreço base s/IVA: 13.299,60 EUR\nClassificação CPV (Vocabulário Comum para os Contratos Públicos)\nObjeto principal\nVocabulário Principal: 15111000\nNº: LOT-0010\nDescrição do Lote: Lote 10  Manteigas (congelada)\nPreço base s/IVA: 8.683,75 EUR\nClassificação CPV (Vocabulário Comum para os Contratos Públicos)\nObjeto principal\nVocabulário Principal: 15111000\nNº: LOT-0011\nDescrição do Lote: Lote 11  Piódão (fresca)\nPreço base s/IVA: 920,25 EUR\nClassificação CPV (Vocabulário Comum para os Contratos Públicos)\nObjeto principal\nVocabulário Principal: 15111000\nNº: LOT-0012\nDescrição do Lote: Lote 12  Piódão (congelada)\nPreço base s/IVA: 2.365,75 EUR\nClassificação CPV (Vocabulário Comum para os Contratos Públicos)\nObjeto principal\nVocabulário Principal: 15111000\nNº: LOT-0013\nDescrição do Lote: Lote 13  Castelo de Vide (fresca)\nPreço base s/IVA: 2.642,85 EUR\nClassificação CPV (Vocabulário Comum para os Contratos Públicos)\nObjeto principal\nVocabulário Principal: 15111000\nNº: LOT-0014\nDescrição do Lote: Lote 14  Castelo de Vide (congelada)\nPreço base s/IVA: 7.956,20 EUR\nClassificação CPV (Vocabulário Comum para os Contratos Públicos)\nObjeto principal\nVocabulário Principal: 15111000\nNº: LOT-0015\nDescrição do Lote: Lote 15  Foz do Arelho (fresca)\nPreço base s/IVA: 2.999,50 EUR\nClassificação CPV (Vocabulário Comum para os Contratos Públicos)\nObjeto principal\nVocabulário Principal: 15111000\nNº: LOT-0016\nDescrição do Lote: Lote 16  Foz do Arelho (congelada)\nPreço base s/IVA: 27.631,50 EUR\nClassificação CPV (Vocabulário Comum para os Contratos Públicos)\nObjeto principal\nVocabulário Principal: 15111000\nNº: LOT-0017\nDescrição do Lote: Lote 17  Oeiras (fresca)\nPreço base s/IVA: 13.878,50 EUR\nClassificação CPV (Vocabulário Comum para os Contratos Públicos)\nObjeto principal\nVocabulário Principal: 15111000\nNº: LOT-0018\nDescrição do Lote: Lote 18  Oeiras (congelada)\nPreço base s/IVA: 9.786,70 EUR\nClassificação CPV (Vocabulário Comum para os Contratos Públicos)\nObjeto principal\nVocabulário Principal: 15111000\nNº: LOT-0019\nDescrição do Lote: Lote 19  Sede/Lisboa (fresca)\nPreço base s/IVA: 6.364,20 EUR\nClassificação CPV (Vocabulário Comum para os Contratos Públicos)\nObjeto principal\nVocabulário Principal: 15111000\nNº: LOT-0020\nDescrição do Lote: Lote 20  Sede/Lisboa (congelada)\nPreço base s/IVA: 385,40 EUR\nClassificação CPV (Vocabulário Comum para os Contratos Públicos)\nObjeto principal\nVocabulário Principal: 15111000\nNº: LOT-0021\nDescrição do Lote: Lote 21  Costa da Caparica (fresca)\nPreço base s/IVA: 6.929,15 EUR\nClassificação CPV (Vocabulário Comum para os Contratos Públicos)\nObjeto principal\nVocabulário Principal: 15111000\nNº: LOT-0022\nDescrição do Lote: Lote 22  Costa da Caparica (congelada)\nPreço base s/IVA: 26.133,60 EUR\nClassificação CPV (Vocabulário Comum para os Contratos Públicos)\nObjeto principal\nVocabulário Principal: 15111000\nNº: LOT-0023\nDescrição do Lote: Lote 23  Albufeira (fresca)\nPreço base s/IVA: 44.550,40 EUR\nClassificação CPV (Vocabulário Comum para os Contratos Públicos)\nObjeto principal\nVocabulário Principal: 15111000\nNº: LOT-0024\nDescrição do Lote: Lote 24  Albufeira (congelada)\nPreço base s/IVA: 60.840,90 EUR\nClassificação CPV (Vocabulário Comum para os Contratos Públicos)\nObjeto principal\nVocabulário Principal: 15111000\nNº: LOT-0025\nDescrição do Lote: Lote 25  Porto Santo, Madeira (fresca)\nPreço base s/IVA: 2.505,80 EUR\nClassificação CPV (Vocabulário Comum para os Contratos Públicos)\nObjeto principal\nVocabulário Principal: 15111000\nNº: LOT-0026\nDescrição do Lote: Lote 26  Porto Santo, Madeira (congelada)\nPreço base s/IVA: 16.491,25 EUR\nClassificação CPV (Vocabulário Comum para os Contratos Públicos)\nObjeto principal\nVocabulário Principal: 15111000\n\n7 - INDICAÇÕES ADICIONAIS\nO contrato envolve aquisição conjunta (satisfação de várias entidades)? Não\nO contrato é adjudicado por uma central de compras? Não\n\n8 - TÉCNICAS\nO concurso destina-se à celebração de um acordo-quadro? Inexistência de acordo-quadro\nÉ utilizado um leilão eletrónico? Não\nÉ adotada uma fase de negociação? Não\nSistema de Aquisição Dinâmico: Inexistência de sistema de aquisição dinâmico\n\n9 - LOCAL DA EXECUÇÃO DO CONTRATO\nLOCAL DA EXECUÇÃO DO CONTRATO (PROCEDIMENTO)\nPaís: Portugal\nNUT III: PT170\nLocalidade: todos\nDistrito: Todos\nConcelho: Todos\nFreguesia: Todas\nLOCAL DA EXECUÇÃO DO CONTRATO (LOTE)\nIdentificador do Lote: LOT-0001; LOT-0002; LOT-0003; LOT-0004; LOT-0005; LOT-0006; LOT-0007; LOT-0008; LOT-0009; LOT-0010; LOT-0011; LOT-0012; LOT-0013; LOT-0014; LOT-0015; LOT-0016; LOT-0017; LOT-0018; LOT-0019; LOT-0020; LOT-0021; LOT-0022; LOT-0023; LOT-0024; LOT-0025; LOT-0026\nPaís: Portugal\nNUT III: PT170\nLocalidade: todos\nDistrito: Todos\nConcelho: Todos\nFreguesia: Todas\n\n10 - PRAZO DE EXECUÇÃO DO CONTRATO\nIdentificador do Lote: LOT-0001; LOT-0002; LOT-0003; LOT-0004; LOT-0005; LOT-0006; LOT-0007; LOT-0008; LOT-0009; LOT-0010; LOT-0011; LOT-0012; LOT-0013; LOT-0014; LOT-0015; LOT-0016; LOT-0017; LOT-0018; LOT-0019; LOT-0020; LOT-0021; LOT-0022; LOT-0023; LOT-0024; LOT-0025; LOT-0026\nPrazo de execução do contrato: 6 MESES\nPrevisão de renovações: Não\n\n11 - FUNDOS EU\nIdentificador do Lote: LOT-0001; LOT-0002; LOT-0003; LOT-0004; LOT-0005; LOT-0006; LOT-0007; LOT-0008; LOT-0009; LOT-0010; LOT-0011; LOT-0012; LOT-0013; LOT-0014; LOT-0015; LOT-0016; LOT-0017; LOT-0018; LOT-0019; LOT-0020; LOT-0021; LOT-0022; LOT-0023; LOT-0024; LOT-0025; LOT-0026\nTêm fundos EU? Não\n\n12 - DOCUMENTOS DE HABILITAÇÃO\nHabilitação para o exercício da atividade profissional: Não\n\n13 - CONDIÇÕES DE APRESENTAÇÃO\nPlataforma eletrónica utilizada pela entidade adjudicante: ACIN\nURL para Apresentação: https://www.acingov.pt\nAdmissibilidade da apresentação de propostas variantes: Não autorizado\nPrazo para apresentação das propostas: 17-09-2025 23:59\nPrazo durante o qual os concorrentes são obrigados a manter as respetivas propostas: 66 dias a contar do termo do prazo para a apresentação das propostas\nApresentação de Catálogo Eletrónico: Permitido\nIndicação de Subcontratação na Proposta: Inexistência de indicação de subcontratação\n\n14 - PRESTAÇÃO DE CAUÇÃO\nPrestação de caução: Não\n\n15 - FORNECIMENTO DAS PEÇAS DO CONCURSO, APRESENTAÇÃO DE PEDIDOS DE PARTICIPAÇÃO E APRESENTAÇÃO DAS PROPOSTAS\nLink para acesso às peças do concurso (URL): https://www.acingov.pt/acingovprod/2/zonaPublica/zona_publica_c/donwloadProcedurePiece/OTM0NjM0\n\n20 - OUTROS REQUISITOS\nIdentificador do Lote: LOT-0001; LOT-0002; LOT-0003; LOT-0004; LOT-0005; LOT-0006; LOT-0007; LOT-0008; LOT-0009; LOT-0010; LOT-0011; LOT-0012; LOT-0013; LOT-0014; LOT-0015; LOT-0016; LOT-0017; LOT-0018; LOT-0019; LOT-0020; LOT-0021; LOT-0022; LOT-0023; LOT-0024; LOT-0025; LOT-0026\nInformação sobre contratos reservados. Aplica-se a contratos reservados (54º-A)? Não\n\n21 - CRITÉRIO DE ADJUDICAÇÃO\nO Critério de adjudicação é diferenciado por lote? Não\nMultifator: Não\nMonofator:\nNome: Preço\n\n24 - CONDIÇÕES DO CONTRATO\nIdentificador do Lote: LOT-0001; LOT-0002; LOT-0003; LOT-0004; LOT-0005; LOT-0006; LOT-0007; LOT-0008; LOT-0009; LOT-0010; LOT-0011; LOT-0012; LOT-0013; LOT-0014; LOT-0015; LOT-0016; LOT-0017; LOT-0018; LOT-0019; LOT-0020; LOT-0021; LOT-0022; LOT-0023; LOT-0024; LOT-0025; LOT-0026\nFaturação Eletrónica: Permitido\nObrigação de Subcontratação:\nCódigo da Obrigação de Subcontratação: Não é aplicável nenhuma obrigação de subcontratação.\n\n25 - COMPRA PÚBLICA ESTRATÉGICA\nCompra Pública Estratégica: Inexistência de contratação pública estratégica\n\n26 - INFORMAÇÕES ADICIONAIS\nIdentificador do Lote: LOT-0001; LOT-0002; LOT-0003; LOT-0004; LOT-0005; LOT-0006; LOT-0007; LOT-0008; LOT-0009; LOT-0010; LOT-0011; LOT-0012; LOT-0013; LOT-0014; LOT-0015; LOT-0016; LOT-0017; LOT-0018; LOT-0019; LOT-0020; LOT-0021; LOT-0022; LOT-0023; LOT-0024; LOT-0025; LOT-0026\nContrato adequado para PME: Sim\nCobertura ACP (Acordo dos Contratos Públicos da Organização Mundial do Comércio): Não\n\n27 - IDENTIFICAÇÃO E CONTACTOS DO ÓRGÃO DE RECURSOS ADMINISTRATIVOS\nDesignação: Conselho de Administração\nEndereço: Calçada de Santana 180\nCódigo postal: 1169-062\nLocalidade: Lisboa\nTelefone: 210027000\nFax: 210027000\nEndereço eletrónico: ncp-procedimentos@inatel.pt\nPrazo de interposição do recurso: 5 dias\n\n28 - IDENTIFICAÇÃO DO(S) AUTOR(ES) DE ANÚNCIO\nNome: Tiago Tenreiro Alves\nCargo: Técnico\n419444231",
    "nipc": "500122237",
    "distrito": "Lisboa",
    "concelho": "Lisboa",
    "freguesia": "Freguesia de Arroios - Lisboa",
    "site": "https://www.inatel.pt",
    "email": "fundacao.inatel@inatel.pt",
    "designacao_contrato": "Carne de Bovino",
    "descricao": "Carne de Bovino",
    "preco_base": "327.008,80 EUR",
    "prazo_execucao": "6 MESES",
    "prazo_apresentacao_propostas": "17-09-2025 23:59",
    "fundos_eu": "Não",
    "plataforma_eletronica": "ACIN",
    "url_procedimento": "https://www.acingov.pt",
    "autor_nome": "Tiago Tenreiro Alves",
    "autor_cargo": "Técnico"
  },
  {
    "numero_procedimento": "N/A",
    "entidade": "Ordem Dos Engenheiros",
    "link": "https://diariodarepublica.pt/dr/detalhe/contrato-publico/22354-932837043",
    "detalhes_completos": "1 - IDENTIFICAÇÃO E CONTACTOS DA ENTIDADE ADJUDICANTE\nDesignação da entidade adjudicante: Ordem Dos Engenheiros\nNIPC: 500839166\nEndereço: Avenida António Augusto de Aguiar,3D\nCódigo postal: 1069-030\nLocalidade: Lisboa\nPaís: Portugal\nNUT III: PT170\nDistrito: Lisboa\nConcelho: Lisboa\nFreguesia: Todas\nTelefone: 213132611\nFax: 213524632\nEndereço da Entidade (URL): www.ordemengenheiros.pt\nEndereço Eletrónico: secretariageral@oep.pt\neDelivery Gateway (URL): https://community.vortal.biz/public/\nFunção da Organização: Adquirente\nNorma jurídica da Entidade Adjudicante: Organismo de direito público\nÁrea de atividade da Autoridade Adjudicante: Serviços públicos das administrações públicas\n\n2 - JORNAL OFICIAL DA UNIÃO EUROPEIA\nO procedimento a que este anúncio diz respeito também é publicitado no Jornal Oficial da União Europeia? Não\n\n3 - AVISO\nModelo de Anúncio: Concurso limitado por prévia qualificação\nData de Envio do Anúncio: 20-08-2025\n\n5 - PROCESSO\nTipo de Procedimento: Concurso limitado por prévia qualificação\nPreço base do procedimento: Sim\nValor do preço base do procedimento: 180.000,00 EUR\nProcedimento com lotes? Não\n\n6 - OBJETO DO CONTRATO\nNúmero de referência interna: CDN 08/2025\nDesignação do contrato: AQUISIÇÃO DE SERVIÇOS DE VIAGENS, TRANSPORTE AÉREO, ALOJAMENTO E SERVIÇOS COMPLEMENTARES INTERNACIONAIS PARA A ORDEM DOS ENGENHEIROS\nDescrição: AQUISIÇÃO DE SERVIÇOS DE VIAGENS, TRANSPORTE AÉREO, ALOJAMENTO E SERVIÇOS COMPLEMENTARES INTERNACIONAIS PARA A ORDEM DOS ENGENHEIROS\nTipo de Contrato Principal: Aquisição de Serviços\nTipo de Contrato: Aquisição de Serviços\nClassificação CPV (Vocabulário Comum para os Contratos Públicos)\nObjeto principal\nVocabulário Principal: 60440000\nPreço base s/IVA: 180.000,00 EUR\n\n7 - INDICAÇÕES ADICIONAIS\nO contrato envolve aquisição conjunta (satisfação de várias entidades)? Não\nO contrato é adjudicado por uma central de compras? Não\n\n8 - TÉCNICAS\nO concurso destina-se à celebração de um acordo-quadro? Inexistência de acordo-quadro\nÉ utilizado um leilão eletrónico? Não\nSistema de Aquisição Dinâmico: Inexistência de sistema de aquisição dinâmico\n\n9 - LOCAL DA EXECUÇÃO DO CONTRATO\nLOCAL DA EXECUÇÃO DO CONTRATO (PROCEDIMENTO)\nPaís: Portugal\nNUT III: PT170\nLocalidade: Lisboa\nDistrito: Lisboa\nConcelho: Lisboa\nFreguesia: Todas\n\n10 - PRAZO DE EXECUÇÃO DO CONTRATO\nPrazo de execução do contrato: 1 ANOS\nPrevisão de renovações: Não\n\n11 - FUNDOS EU\nTêm fundos EU? Não\n\n12 - DOCUMENTOS DE HABILITAÇÃO\nHabilitação para o exercício da atividade profissional: Sim\nTipo: Certificado\nDescrição: Cfr. Programa do Procedimento \n\n13 - CONDIÇÕES DE APRESENTAÇÃO\nPlataforma eletrónica utilizada pela entidade adjudicante: VORTAL\nURL para Apresentação: https://community.vortal.biz/public/\nAdmissibilidade da apresentação de propostas variantes: Não autorizado\nPrazo para apresentação das candidaturas: 30-08-2025 23:59\nRequisitos mínimos \nRequisitos mínimos de capacidade técnica: Cfr. Programa do Procedimento \nRequisitos mínimos de capacidade financeira: Cfr. Programa do Procedimento \nPrazo durante o qual os concorrentes são obrigados a manter as respetivas propostas: 180 dias a contar do termo do prazo para a apresentação das propostas\nIndicação de Subcontratação na Proposta: Inexistência de indicação de subcontratação\n\n14 - PRESTAÇÃO DE CAUÇÃO\nPrestação de caução: Não\n\n15 - FORNECIMENTO DAS PEÇAS DO CONCURSO, APRESENTAÇÃO DE PEDIDOS DE PARTICIPAÇÃO E APRESENTAÇÃO DAS PROPOSTAS\nLink para acesso às peças do concurso (URL): https://community.vortal.biz/Public/public-tender-documents/MG44RUpVc1FkREpSR3dnc2gxSElPRVFCMkZmR2krbTJZYUtxL3AvWlVaSlhuV3hRSm9PODZBNmhRRzJQaWFGQ2o3bXlKKzV6TU5wMjF4ZDJKUDBZVFE9PXRUZWdB\n\n20 - OUTROS REQUISITOS\nInformação sobre contratos reservados. Aplica-se a contratos reservados (54º-A)? Não\n\n21 - CRITÉRIO DE ADJUDICAÇÃO\nMultifator: Não\nMonofator:\nNome: Preço\n\n24 - CONDIÇÕES DO CONTRATO\nFaturação Eletrónica: Permitido\nObrigação de Subcontratação:\nCódigo da Obrigação de Subcontratação: Não é aplicável nenhuma obrigação de subcontratação.\n\n25 - COMPRA PÚBLICA ESTRATÉGICA\nCompra Pública Estratégica: Inexistência de contratação pública estratégica\n\n26 - INFORMAÇÕES ADICIONAIS\nContrato adequado para PME: Sim\nCobertura ACP (Acordo dos Contratos Públicos da Organização Mundial do Comércio): Não\n\n27 - IDENTIFICAÇÃO E CONTACTOS DO ÓRGÃO DE RECURSOS ADMINISTRATIVOS\nDesignação: CDN\nEndereço: Av. António Augusto de Aguiar, 3D\nCódigo postal: 1069-030\nLocalidade: Lisboa\nTelefone: +351 213132611\nFax: +351 213132601\nEndereço eletrónico: liliana.carvalho@oep.pt\n\n28 - IDENTIFICAÇÃO DO(S) AUTOR(ES) DE ANÚNCIO\nNome: Nelson Jerónimo\nCargo: Secretário-geral\n419451424",
    "nipc": "500839166",
    "distrito": "Lisboa",
    "concelho": "Lisboa",
    "freguesia": "Todas",
    "site": "www.ordemengenheiros.pt",
    "email": "secretariageral@oep.pt",
    "designacao_contrato": "AQUISIÇÃO DE SERVIÇOS DE VIAGENS, TRANSPORTE AÉREO, ALOJAMENTO E SERVIÇOS COMPLEMENTARES INTERNACIONAIS PARA A ORDEM DOS ENGENHEIROS",
    "descricao": "AQUISIÇÃO DE SERVIÇOS DE VIAGENS, TRANSPORTE AÉREO, ALOJAMENTO E SERVIÇOS COMPLEMENTARES INTERNACIONAIS PARA A ORDEM DOS ENGENHEIROS",
    "preco_base": "180.000,00 EUR",
    "prazo_execucao": "1 ANOS",
    "prazo_apresentacao_propostas": null,
    "fundos_eu": "Não",
    "plataforma_eletronica": "VORTAL",
    "url_procedimento": "https://community.vortal.biz/public/",
    "autor_nome": "Nelson Jerónimo",
    "autor_cargo": "Secretário-geral"
  },
  {
    "numero_procedimento": "N/A",
    "entidade": "Câmara Municipal de Matosinhos",
    "link": "https://diariodarepublica.pt/dr/detalhe/contrato-publico/22357-932837044",
    "detalhes_completos": "1 - IDENTIFICAÇÃO E CONTACTOS DA ENTIDADE ADJUDICANTE\nDesignação da entidade adjudicante: Câmara Municipal de Matosinhos\nNIPC: 501305912\nServiço/Órgão/Pessoa de contacto: Departamento Financeiro - Divisão de Contratação Pública\nEndereço: Av. D. Afonso Henriques\nCódigo postal: 4454-510\nLocalidade: Matosinhos\nPaís: Portugal\nNUT III: PT11A\nDistrito: Porto\nConcelho: Matosinhos\nFreguesia: Todas\nTelefone: 229390900\nFax: 229351645\nEndereço da Entidade (URL): http://www.cm-matosinhos.pt\nEndereço Eletrónico: contratacaopublica@cm-matosinhos.pt\neDelivery Gateway (URL): https://www.acingov.pt\nFunção da Organização: Adquirente\nSubfunção da Organização: Organização que recebe as propostas\nNorma jurídica da Entidade Adjudicante: Organismo de direito público\nÁrea de atividade da Autoridade Adjudicante: Serviços públicos das administrações públicas\n\n2 - JORNAL OFICIAL DA UNIÃO EUROPEIA\nO procedimento a que este anúncio diz respeito também é publicitado no Jornal Oficial da União Europeia? Não\n\n3 - AVISO\nModelo de Anúncio: Concurso público\nData de Envio do Anúncio: 20-08-2025\n\n5 - PROCESSO\nTipo de Procedimento: Concurso público\nPreço base do procedimento: Sim\nValor do preço base do procedimento: 67.630,78 EUR\nProcedimento com lotes? Não\n\n6 - OBJETO DO CONTRATO\nNúmero de referência interna: CP/2024/26463-4\nDesignação do contrato: EMPREITADA PARA A VENTILAÇÃO DE ESPAÇOS EM SOBREAQUECIMENTO NAS ÁREAS TÉCNICAS E REPARAÇÃO DE FUGAS EM DIVERSAS ESCOLAS DO CONCELHO\nDescrição: EMPREITADA PARA A VENTILAÇÃO DE ESPAÇOS EM SOBREAQUECIMENTO NAS ÁREAS TÉCNICAS E REPARAÇÃO DE FUGAS EM DIVERSAS ESCOLAS DO CONCELHO\nTipo de Contrato Principal: Empreitada de Obras Públicas\nTipo de Contrato: Empreitada de Obras Públicas\nClassificação CPV (Vocabulário Comum para os Contratos Públicos)\nObjeto principal\nVocabulário Principal: 45351000\nPreço base s/IVA: 67.630,78 EUR\n\n7 - INDICAÇÕES ADICIONAIS\nO contrato envolve aquisição conjunta (satisfação de várias entidades)? Não\nO contrato é adjudicado por uma central de compras? Não\n\n8 - TÉCNICAS\nO concurso destina-se à celebração de um acordo-quadro? Inexistência de acordo-quadro\nÉ utilizado um leilão eletrónico? Não\nÉ adotada uma fase de negociação? Não\nSistema de Aquisição Dinâmico: Inexistência de sistema de aquisição dinâmico\n\n9 - LOCAL DA EXECUÇÃO DO CONTRATO\nLOCAL DA EXECUÇÃO DO CONTRATO (PROCEDIMENTO)\nPaís: Portugal\nNUT III: PT11A\nLocalidade: Matosinhos\nDistrito: Porto\nConcelho: Matosinhos\nFreguesia: Todas\n\n10 - PRAZO DE EXECUÇÃO DO CONTRATO\nPrazo de execução do contrato: 90 DIAS\nPrevisão de renovações: Não\n\n11 - FUNDOS EU\nTêm fundos EU? Não\n\n12 - DOCUMENTOS DE HABILITAÇÃO\nHabilitação para o exercício da atividade profissional: Sim\nTipo: Alvará\nDescrição: Categoria: 4ª Instalações elétricas e mecânicas\nSub-Categoria: 12ª Aquecimento, ventilação, ar condicionado e refrigeração\n\n13 - CONDIÇÕES DE APRESENTAÇÃO\nPlataforma eletrónica utilizada pela entidade adjudicante: ACIN\nURL para Apresentação: https://www.acingov.pt\nAdmissibilidade da apresentação de propostas variantes: Não autorizado\nPrazo para apresentação das propostas: 04-09-2025 23:59\nPrazo durante o qual os concorrentes são obrigados a manter as respetivas propostas: 66 dias a contar do termo do prazo para a apresentação das propostas\nIndicação de Subcontratação na Proposta: Inexistência de indicação de subcontratação\n\n14 - PRESTAÇÃO DE CAUÇÃO\nPrestação de caução: Não\n\n15 - FORNECIMENTO DAS PEÇAS DO CONCURSO, APRESENTAÇÃO DE PEDIDOS DE PARTICIPAÇÃO E APRESENTAÇÃO DAS PROPOSTAS\nLink para acesso às peças do concurso (URL): https://www.acingov.pt/acingovprod/2/zonaPublica/zona_publica_c/donwloadProcedurePiece/OTM1MjYx\n\n20 - OUTROS REQUISITOS\nInformação sobre contratos reservados. Aplica-se a contratos reservados (54º-A)? Não\n\n21 - CRITÉRIO DE ADJUDICAÇÃO\nMultifator: Não\nMonofator:\nNome: Outros\nOutro nome: Fator Preço\n\n24 - CONDIÇÕES DO CONTRATO\nFaturação Eletrónica: Não autorizado\nObrigação de Subcontratação:\nCódigo da Obrigação de Subcontratação: Não é aplicável nenhuma obrigação de subcontratação.\n\n25 - COMPRA PÚBLICA ESTRATÉGICA\nCompra Pública Estratégica: Inexistência de contratação pública estratégica\n\n26 - INFORMAÇÕES ADICIONAIS\nContrato adequado para PME: Sim\nCobertura ACP (Acordo dos Contratos Públicos da Organização Mundial do Comércio): Não\n\n27 - IDENTIFICAÇÃO E CONTACTOS DO ÓRGÃO DE RECURSOS ADMINISTRATIVOS\nDesignação: Câmara Municipal de Matosinhos\nEndereço: Av. Dom Afonso Henriques, S/N 4454-510 Matosinhos\nCódigo postal: 4454-510\nLocalidade: Matosinhos\nTelefone: 229390900\nFax: \nEndereço eletrónico: contratacaopublica@cm-matosinhos.pt\nPrazo de interposição do recurso: 5 dias\n\n28 - IDENTIFICAÇÃO DO(S) AUTOR(ES) DE ANÚNCIO\nNome: Luísa Maria Neves Salgueiro\nCargo: Presidente de Câmara\n419448866",
    "nipc": "501305912",
    "distrito": "Porto",
    "concelho": "Matosinhos",
    "freguesia": "Todas",
    "site": "http://www.cm-matosinhos.pt",
    "email": "contratacaopublica@cm-matosinhos.pt",
    "designacao_contrato": "EMPREITADA PARA A VENTILAÇÃO DE ESPAÇOS EM SOBREAQUECIMENTO NAS ÁREAS TÉCNICAS E REPARAÇÃO DE FUGAS EM DIVERSAS ESCOLAS DO CONCELHO",
    "descricao": "EMPREITADA PARA A VENTILAÇÃO DE ESPAÇOS EM SOBREAQUECIMENTO NAS ÁREAS TÉCNICAS E REPARAÇÃO DE FUGAS EM DIVERSAS ESCOLAS DO CONCELHO",
    "preco_base": "67.630,78 EUR",
    "prazo_execucao": "90 DIAS",
    "prazo_apresentacao_propostas": "04-09-2025 23:59",
    "fundos_eu": "Não",
    "plataforma_eletronica": "ACIN",
    "url_procedimento": "https://www.acingov.pt",
    "autor_nome": "Luísa Maria Neves Salgueiro",
    "autor_cargo": "Presidente de Câmara"
  },
  {
    "numero_procedimento": "N/A",
    "entidade": "Direção-Geral de Recursos Naturais, Segurança e Serviços Marítimos",
    "link": "https://diariodarepublica.pt/dr/detalhe/contrato-publico/22363-932837055",
    "detalhes_completos": "1 - IDENTIFICAÇÃO E CONTACTOS DA ENTIDADE ADJUDICANTE\nDesignação da entidade adjudicante: Direção-Geral de Recursos Naturais, Segurança e Serviços Marítimos\nNIPC: 600084973\nEndereço: Avenida de Brasília\nCódigo postal: 1449-030\nLocalidade: Lisboa\nPaís: Portugal\nNUT III: PT170\nDistrito: Lisboa\nConcelho: Lisboa\nFreguesia: Freguesia de Belém\nTelefone: 213035700\nFax: 213035702\nEndereço da Entidade (URL): http://www.dgrm.mm.gov.pt\nEndereço Eletrónico: dgrm@dgrm.mm.gov.pt\nFunção da Organização: Adquirente\nNorma jurídica da Entidade Adjudicante: Organismo de direito público\nÁrea de atividade da Autoridade Adjudicante: Serviços públicos das administrações públicas\n\n2 - JORNAL OFICIAL DA UNIÃO EUROPEIA\nO procedimento a que este anúncio diz respeito também é publicitado no Jornal Oficial da União Europeia? Sim\n\n3 - AVISO\nModelo de Anúncio: Concurso público\nData de Envio do Anúncio: 18-08-2025\n\n5 - PROCESSO\nTipo de Procedimento: Concurso público\nPreço base do procedimento: Sim\nValor do preço base do procedimento: 150.368,00 EUR\nProcedimento com lotes? Não\n\n6 - OBJETO DO CONTRATO\nNúmero de referência interna: FIREWALL\nDesignação do contrato: AQUISIÇÃO DE SERVIÇOS DE COMUNICAÇÕES FIREWALL CUSTOM- SSN PORTUGAL\nDescrição: Aquisição de Serviços de Comunicações FW Custom - SSN Portugal \nOpções: Não\nTipo de Contrato Principal: Aquisição de Serviços\nTipo de Contrato: Aquisição de Serviços\nClassificação CPV (Vocabulário Comum para os Contratos Públicos)\nObjeto principal\nVocabulário Principal: 72318000\nPreço base s/IVA: 150.368,00 EUR\n\n7 - INDICAÇÕES ADICIONAIS\nO contrato envolve aquisição conjunta (satisfação de várias entidades)? Não\nO contrato é adjudicado por uma central de compras? Não\n\n8 - TÉCNICAS\nO concurso destina-se à celebração de um acordo-quadro? Inexistência de acordo-quadro\nÉ utilizado um leilão eletrónico? Não\nÉ adotada uma fase de negociação? Não\nSistema de Aquisição Dinâmico: Inexistência de sistema de aquisição dinâmico\n\n9 - LOCAL DA EXECUÇÃO DO CONTRATO\nLOCAL DA EXECUÇÃO DO CONTRATO (PROCEDIMENTO)\nPaís: Portugal\nNUT III: PT170\nLocalidade: Paço de Arcos\nDistrito: Lisboa\nConcelho: Oeiras\nFreguesia: União das Freguesias de Oeiras e São Julião da Barra, Paço de Arcos e Caxias\nPaís: Portugal\nNUT III: PT150\nLocalidade: Ferragudo\nDistrito: Faro\nConcelho: Lagoa\nFreguesia: Freguesia de Ferragudo\n\n10 - PRAZO DE EXECUÇÃO DO CONTRATO\nPrazo de execução do contrato: 32 MESES\nPrevisão de renovações: Não\n\n11 - FUNDOS EU\nTêm fundos EU? Não\n\n12 - DOCUMENTOS DE HABILITAÇÃO\nHabilitação para o exercício da atividade profissional: Não\n\n13 - CONDIÇÕES DE APRESENTAÇÃO\nPlataforma eletrónica utilizada pela entidade adjudicante: ANOGOV\nURL para Apresentação: https://www.anogov.com/op-dgrm/faces/\nAdmissibilidade da apresentação de propostas variantes: Não autorizado\nPrazo para apresentação das propostas: 17-09-2025 23:59\nPrazo durante o qual os concorrentes são obrigados a manter as respetivas propostas: 66 dias a contar do termo do prazo para a apresentação das propostas\nApresentação de Catálogo Eletrónico: Necessário\nIndicação de Subcontratação na Proposta: O(s) subcontratante(s) proposto(s) necessário(s) para cumprir a obrigação de subcontratar uma percentagem mínima do contrato\n\n14 - PRESTAÇÃO DE CAUÇÃO\nPrestação de caução: Não\n\n15 - FORNECIMENTO DAS PEÇAS DO CONCURSO, APRESENTAÇÃO DE PEDIDOS DE PARTICIPAÇÃO E APRESENTAÇÃO DAS PROPOSTAS\nLink para acesso às peças do concurso (URL): https://www.anogov.com/op-dgrm/faces/app/acessoDocs.jsp?codigoAcesso=AVc03hRhG7b68AqTxBWVm4501OSAZuMPcS27iLTcjeewrNo5oX\n\n20 - OUTROS REQUISITOS\nInformação sobre contratos reservados. Aplica-se a contratos reservados (54º-A)? Não\n\n21 - CRITÉRIO DE ADJUDICAÇÃO\nMultifator: Não\nMonofator:\nNome: Preço\n\n24 - CONDIÇÕES DO CONTRATO\nFaturação Eletrónica: Necessário\nObrigação de Subcontratação:\nCódigo da Obrigação de Subcontratação: Não é aplicável nenhuma obrigação de subcontratação.\n\n25 - COMPRA PÚBLICA ESTRATÉGICA\nCompra Pública Estratégica: Inexistência de contratação pública estratégica\n\n26 - INFORMAÇÕES ADICIONAIS\nContrato adequado para PME: Não\nCobertura ACP (Acordo dos Contratos Públicos da Organização Mundial do Comércio): Não\n\n27 - IDENTIFICAÇÃO E CONTACTOS DO ÓRGÃO DE RECURSOS ADMINISTRATIVOS\nDesignação: Ministério da Agricultura e Mar\nEndereço: Praça do Comércio\nCódigo postal: 1149-010\nLocalidade: Lisboa\nEndereço eletrónico: geral@gpp.pt\n\n28 - IDENTIFICAÇÃO DO(S) AUTOR(ES) DE ANÚNCIO\nNome: Isabel Ventura\nCargo: Subdiretora-Gera\n419444645",
    "nipc": "600084973",
    "distrito": "Lisboa",
    "concelho": "Lisboa",
    "freguesia": "Freguesia de Belém",
    "site": "http://www.dgrm.mm.gov.pt",
    "email": "dgrm@dgrm.mm.gov.pt",
    "designacao_contrato": "AQUISIÇÃO DE SERVIÇOS DE COMUNICAÇÕES FIREWALL CUSTOM- SSN PORTUGAL",
    "descricao": "Aquisição de Serviços de Comunicações FW Custom - SSN Portugal",
    "preco_base": "150.368,00 EUR",
    "prazo_execucao": "32 MESES",
    "prazo_apresentacao_propostas": "17-09-2025 23:59",
    "fundos_eu": "Não",
    "plataforma_eletronica": "ANOGOV",
    "url_procedimento": "https://www.anogov.com/op-dgrm/faces/",
    "autor_nome": "Isabel Ventura",
    "autor_cargo": "Subdiretora-Gera"
  },
  {
    "numero_procedimento": "N/A",
    "entidade": "Unidade Local de Saúde do Alentejo Central, E.P.E",
    "link": "https://diariodarepublica.pt/dr/detalhe/contrato-publico/22365-932837056",
    "detalhes_completos": "1 - IDENTIFICAÇÃO E CONTACTOS DA ENTIDADE ADJUDICANTE\nDesignação da entidade adjudicante: Unidade Local de Saúde do Alentejo Central, E.P.E\nNIPC: 508085888\nEndereço: Largo Sr. da Pobreza\nCódigo postal: 7000-811\nLocalidade: Évora\nPaís: Portugal\nNUT III: PT187\nDistrito: Évora\nConcelho: Évora\nFreguesia: Todas\nTelefone: 266740111\nFax: 266744212\nEndereço da Entidade (URL): www.hevora.min-saude.pt\nEndereço Eletrónico: concursos.aprov@ulsac.min-saude.pt\neDelivery Gateway (URL): https://community.vortal.biz/public/\nFunção da Organização: Adquirente\nNorma jurídica da Entidade Adjudicante: Organismo de direito público\nÁrea de atividade da Autoridade Adjudicante: Saúde\n\n2 - JORNAL OFICIAL DA UNIÃO EUROPEIA\nO procedimento a que este anúncio diz respeito também é publicitado no Jornal Oficial da União Europeia? Sim\n\n3 - AVISO\nModelo de Anúncio: Concurso público\nData de Envio do Anúncio: 18-08-2025\n\n5 - PROCESSO\nTipo de Procedimento: Concurso público\nPreço base do procedimento: Sim\nValor do preço base do procedimento: 427.713,36 EUR\nProcedimento com lotes? Sim\nNº Máx. de Lotes Autorizado: 59\nNúmero máximo de lotes que podem ser adjudicados a um concorrente: 59\n\n6 - OBJETO DO CONTRATO\nNúmero de referência interna: 120040/26\nDesignação do contrato: Aquisição de Dispositivos Médicos e Outros Produtos para Esterilização\nDescrição: Aquisição de Dispositivos Médicos e Outros Produtos para Esterilização\nOpções: Não\nTipo de Contrato Principal: Aquisição de Bens Móveis\nTipo de Contrato: Aquisição de Bens Móveis\nClassificação CPV (Vocabulário Comum para os Contratos Públicos)\nObjeto principal\nVocabulário Principal: 33198200\nPreço base s/IVA: 427.713,36 EUR\nLotes: \nNº: LOT-0001\nDescrição do Lote: Lote 1\nPreço base s/IVA: 13.440,00 EUR\nClassificação CPV (Vocabulário Comum para os Contratos Públicos)\nObjeto principal\nVocabulário Principal: 33198200\nNº: LOT-0002\nDescrição do Lote: Lote 2\nPreço base s/IVA: 1.728,00 EUR\nClassificação CPV (Vocabulário Comum para os Contratos Públicos)\nObjeto principal\nVocabulário Principal: 33198200\nNº: LOT-0003\nDescrição do Lote: Lote 3\nPreço base s/IVA: 6.240,00 EUR\nClassificação CPV (Vocabulário Comum para os Contratos Públicos)\nObjeto principal\nVocabulário Principal: 33198200\nNº: LOT-0004\nDescrição do Lote: Lote 4\nPreço base s/IVA: 259,20 EUR\nClassificação CPV (Vocabulário Comum para os Contratos Públicos)\nObjeto principal\nVocabulário Principal: 33198200\nNº: LOT-0005\nDescrição do Lote: Lote 5\nPreço base s/IVA: 2.035,20 EUR\nClassificação CPV (Vocabulário Comum para os Contratos Públicos)\nObjeto principal\nVocabulário Principal: 33198200\nNº: LOT-0006\nDescrição do Lote: Lote 6\nPreço base s/IVA: 1.209,60 EUR\nClassificação CPV (Vocabulário Comum para os Contratos Públicos)\nObjeto principal\nVocabulário Principal: 33198200\nNº: LOT-0007\nDescrição do Lote: Lote 7\nPreço base s/IVA: 1.512,00 EUR\nClassificação CPV (Vocabulário Comum para os Contratos Públicos)\nObjeto principal\nVocabulário Principal: 33198200\nNº: LOT-0008\nDescrição do Lote: Lote 8\nPreço base s/IVA: 10.886,40 EUR\nClassificação CPV (Vocabulário Comum para os Contratos Públicos)\nObjeto principal\nVocabulário Principal: 33198200\nNº: LOT-0009\nDescrição do Lote: Lote 9\nPreço base s/IVA: 840,00 EUR\nClassificação CPV (Vocabulário Comum para os Contratos Públicos)\nObjeto principal\nVocabulário Principal: 33198200\nNº: LOT-0010\nDescrição do Lote: Lote 10\nPreço base s/IVA: 1.680,00 EUR\nClassificação CPV (Vocabulário Comum para os Contratos Públicos)\nObjeto principal\nVocabulário Principal: 33198200\nNº: LOT-0011\nDescrição do Lote: Lote 11\nPreço base s/IVA: 648,00 EUR\nClassificação CPV (Vocabulário Comum para os Contratos Públicos)\nObjeto principal\nVocabulário Principal: 33198200\nNº: LOT-0012\nDescrição do Lote: Lote 12\nPreço base s/IVA: 9.600,00 EUR\nClassificação CPV (Vocabulário Comum para os Contratos Públicos)\nObjeto principal\nVocabulário Principal: 33198200\nNº: LOT-0013\nDescrição do Lote: Lote 13\nPreço base s/IVA: 21.600,00 EUR\nClassificação CPV (Vocabulário Comum para os Contratos Públicos)\nObjeto principal\nVocabulário Principal: 33198200\nNº: LOT-0014\nDescrição do Lote: Lote 14\nPreço base s/IVA: 36.720,00 EUR\nClassificação CPV (Vocabulário Comum para os Contratos Públicos)\nObjeto principal\nVocabulário Principal: 33198200\nNº: LOT-0015\nDescrição do Lote: Lote 15\nPreço base s/IVA: 10.260,00 EUR\nClassificação CPV (Vocabulário Comum para os Contratos Públicos)\nObjeto principal\nVocabulário Principal: 33198200\nNº: LOT-0016\nDescrição do Lote: Lote 16\nPreço base s/IVA: 13.200,00 EUR\nClassificação CPV (Vocabulário Comum para os Contratos Públicos)\nObjeto principal\nVocabulário Principal: 33198200\nNº: LOT-0017\nDescrição do Lote: Lote 17\nPreço base s/IVA: 231,00 EUR\nClassificação CPV (Vocabulário Comum para os Contratos Públicos)\nObjeto principal\nVocabulário Principal: 33198200\nNº: LOT-0018\nDescrição do Lote: Lote 18\nPreço base s/IVA: 6.600,00 EUR\nClassificação CPV (Vocabulário Comum para os Contratos Públicos)\nObjeto principal\nVocabulário Principal: 33198200\nNº: LOT-0019\nDescrição do Lote: Lote 19\nPreço base s/IVA: 900,00 EUR\nClassificação CPV (Vocabulário Comum para os Contratos Públicos)\nObjeto principal\nVocabulário Principal: 33198200\nNº: LOT-0020\nDescrição do Lote: Lote 20\nPreço base s/IVA: 1.008,00 EUR\nClassificação CPV (Vocabulário Comum para os Contratos Públicos)\nObjeto principal\nVocabulário Principal: 33198200\nNº: LOT-0021\nDescrição do Lote: Lote 21\nPreço base s/IVA: 6.720,00 EUR\nClassificação CPV (Vocabulário Comum para os Contratos Públicos)\nObjeto principal\nVocabulário Principal: 33198200\nNº: LOT-0022\nDescrição do Lote: Lote 22\nPreço base s/IVA: 7.650,00 EUR\nClassificação CPV (Vocabulário Comum para os Contratos Públicos)\nObjeto principal\nVocabulário Principal: 33198200\nNº: LOT-0023\nDescrição do Lote: Lote 23\nPreço base s/IVA: 105,00 EUR\nClassificação CPV (Vocabulário Comum para os Contratos Públicos)\nObjeto principal\nVocabulário Principal: 33198200\nNº: LOT-0024\nDescrição do Lote: Lote 24\nPreço base s/IVA: 2.580,00 EUR\nClassificação CPV (Vocabulário Comum para os Contratos Públicos)\nObjeto principal\nVocabulário Principal: 33198200\nNº: LOT-0025\nDescrição do Lote: Lote 25\nPreço base s/IVA: 3.324,24 EUR\nClassificação CPV (Vocabulário Comum para os Contratos Públicos)\nObjeto principal\nVocabulário Principal: 33198200\nNº: LOT-0026\nDescrição do Lote: Lote 26\nPreço base s/IVA: 14.580,00 EUR\nClassificação CPV (Vocabulário Comum para os Contratos Públicos)\nObjeto principal\nVocabulário Principal: 33198200\nNº: LOT-0027\nDescrição do Lote: Lote 27\nPreço base s/IVA: 2.400,00 EUR\nClassificação CPV (Vocabulário Comum para os Contratos Públicos)\nObjeto principal\nVocabulário Principal: 33198200\nNº: LOT-0028\nDescrição do Lote: Lote 28\nPreço base s/IVA: 114.462,72 EUR\nClassificação CPV (Vocabulário Comum para os Contratos Públicos)\nObjeto principal\nVocabulário Principal: 33198200\nNº: LOT-0029\nDescrição do Lote: Lote 29\nPreço base s/IVA: 4.500,00 EUR\nClassificação CPV (Vocabulário Comum para os Contratos Públicos)\nObjeto principal\nVocabulário Principal: 33198200\nNº: LOT-0030\nDescrição do Lote: Lote 30\nPreço base s/IVA: 7.776,00 EUR\nClassificação CPV (Vocabulário Comum para os Contratos Públicos)\nObjeto principal\nVocabulário Principal: 33198200\nNº: LOT-0031\nDescrição do Lote: Lote 31\nPreço base s/IVA: 10.080,00 EUR\nClassificação CPV (Vocabulário Comum para os Contratos Públicos)\nObjeto principal\nVocabulário Principal: 33198200\nNº: LOT-0032\nDescrição do Lote: Lote 32\nPreço base s/IVA: 7.020,00 EUR\nClassificação CPV (Vocabulário Comum para os Contratos Públicos)\nObjeto principal\nVocabulário Principal: 33198200\nNº: LOT-0033\nDescrição do Lote: Lote 33\nPreço base s/IVA: 2.400,00 EUR\nClassificação CPV (Vocabulário Comum para os Contratos Públicos)\nObjeto principal\nVocabulário Principal: 33198200\nNº: LOT-0034\nDescrição do Lote: Lote 34\nPreço base s/IVA: 996,00 EUR\nClassificação CPV (Vocabulário Comum para os Contratos Públicos)\nObjeto principal\nVocabulário Principal: 33198200\nNº: LOT-0035\nDescrição do Lote: Lote 35\nPreço base s/IVA: 936,00 EUR\nClassificação CPV (Vocabulário Comum para os Contratos Públicos)\nObjeto principal\nVocabulário Principal: 33198200\nNº: LOT-0036\nDescrição do Lote: Lote 36\nPreço base s/IVA: 2.040,00 EUR\nClassificação CPV (Vocabulário Comum para os Contratos Públicos)\nObjeto principal\nVocabulário Principal: 33198200\nNº: LOT-0037\nDescrição do Lote: Lote 37\nPreço base s/IVA: 960,00 EUR\nClassificação CPV (Vocabulário Comum para os Contratos Públicos)\nObjeto principal\nVocabulário Principal: 33198200\nNº: LOT-0038\nDescrição do Lote: Lote 38\nPreço base s/IVA: 2.520,00 EUR\nClassificação CPV (Vocabulário Comum para os Contratos Públicos)\nObjeto principal\nVocabulário Principal: 33198200\nNº: LOT-0039\nDescrição do Lote: Lote 39\nPreço base s/IVA: 1.590,00 EUR\nClassificação CPV (Vocabulário Comum para os Contratos Públicos)\nObjeto principal\nVocabulário Principal: 33198200\nNº: LOT-0040\nDescrição do Lote: Lote 40\nPreço base s/IVA: 792,00 EUR\nClassificação CPV (Vocabulário Comum para os Contratos Públicos)\nObjeto principal\nVocabulário Principal: 33198200\nNº: LOT-0041\nDescrição do Lote: Lote 41\nPreço base s/IVA: 15.600,00 EUR\nClassificação CPV (Vocabulário Comum para os Contratos Públicos)\nObjeto principal\nVocabulário Principal: 33198200\nNº: LOT-0042\nDescrição do Lote: Lote 42\nPreço base s/IVA: 7.200,00 EUR\nClassificação CPV (Vocabulário Comum para os Contratos Públicos)\nObjeto principal\nVocabulário Principal: 33198200\nNº: LOT-0043\nDescrição do Lote: Lote 43\nPreço base s/IVA: 5.508,00 EUR\nClassificação CPV (Vocabulário Comum para os Contratos Públicos)\nObjeto principal\nVocabulário Principal: 33198200\nNº: LOT-0044\nDescrição do Lote: Lote 44\nPreço base s/IVA: 2.184,00 EUR\nClassificação CPV (Vocabulário Comum para os Contratos Públicos)\nObjeto principal\nVocabulário Principal: 33198200\nNº: LOT-0045\nDescrição do Lote: Lote 45\nPreço base s/IVA: 468,00 EUR\nClassificação CPV (Vocabulário Comum para os Contratos Públicos)\nObjeto principal\nVocabulário Principal: 33198200\nNº: LOT-0046\nDescrição do Lote: Lote 46\nPreço base s/IVA: 2.262,00 EUR\nClassificação CPV (Vocabulário Comum para os Contratos Públicos)\nObjeto principal\nVocabulário Principal: 33198200\nNº: LOT-0047\nDescrição do Lote: Lote 47\nPreço base s/IVA: 780,00 EUR\nClassificação CPV (Vocabulário Comum para os Contratos Públicos)\nObjeto principal\nVocabulário Principal: 33198200\nNº: LOT-0048\nDescrição do Lote: Lote 48\nPreço base s/IVA: 1.404,00 EUR\nClassificação CPV (Vocabulário Comum para os Contratos Públicos)\nObjeto principal\nVocabulário Principal: 33198200\nNº: LOT-0049\nDescrição do Lote: Lote 49\nPreço base s/IVA: 468,00 EUR\nClassificação CPV (Vocabulário Comum para os Contratos Públicos)\nObjeto principal\nVocabulário Principal: 33198200\nNº: LOT-0050\nDescrição do Lote: Lote 50\nPreço base s/IVA: 390,00 EUR\nClassificação CPV (Vocabulário Comum para os Contratos Públicos)\nObjeto principal\nVocabulário Principal: 33198200\nNº: LOT-0051\nDescrição do Lote: Lote 51\nPreço base s/IVA: 1.440,00 EUR\nClassificação CPV (Vocabulário Comum para os Contratos Públicos)\nObjeto principal\nVocabulário Principal: 33198200\nNº: LOT-0052\nDescrição do Lote: Lote 52\nPreço base s/IVA: 7.686,00 EUR\nClassificação CPV (Vocabulário Comum para os Contratos Públicos)\nObjeto principal\nVocabulário Principal: 33198200\nNº: LOT-0053\nDescrição do Lote: Lote 53\nPreço base s/IVA: 1.980,00 EUR\nClassificação CPV (Vocabulário Comum para os Contratos Públicos)\nObjeto principal\nVocabulário Principal: 33198200\nNº: LOT-0054\nDescrição do Lote: Lote 54\nPreço base s/IVA: 2.160,00 EUR\nClassificação CPV (Vocabulário Comum para os Contratos Públicos)\nObjeto principal\nVocabulário Principal: 33198200\nNº: LOT-0055\nDescrição do Lote: Lote 55\nPreço base s/IVA: 18.792,00 EUR\nClassificação CPV (Vocabulário Comum para os Contratos Públicos)\nObjeto principal\nVocabulário Principal: 33198200\nNº: LOT-0056\nDescrição do Lote: Lote 56\nPreço base s/IVA: 2.880,00 EUR\nClassificação CPV (Vocabulário Comum para os Contratos Públicos)\nObjeto principal\nVocabulário Principal: 33198200\nNº: LOT-0057\nDescrição do Lote: Lote 57\nPreço base s/IVA: 8.640,00 EUR\nClassificação CPV (Vocabulário Comum para os Contratos Públicos)\nObjeto principal\nVocabulário Principal: 33198200\nNº: LOT-0058\nDescrição do Lote: Lote 58\nPreço base s/IVA: 11.178,00 EUR\nClassificação CPV (Vocabulário Comum para os Contratos Públicos)\nObjeto principal\nVocabulário Principal: 33198200\nNº: LOT-0059\nDescrição do Lote: Lote 59\nPreço base s/IVA: 2.664,00 EUR\nClassificação CPV (Vocabulário Comum para os Contratos Públicos)\nObjeto principal\nVocabulário Principal: 33198200\n\n7 - INDICAÇÕES ADICIONAIS\nO contrato envolve aquisição conjunta (satisfação de várias entidades)? Não\nO contrato é adjudicado por uma central de compras? Não\n\n8 - TÉCNICAS\nO concurso destina-se à celebração de um acordo-quadro? Inexistência de acordo-quadro\nÉ utilizado um leilão eletrónico? Não\nÉ adotada uma fase de negociação? Não\nSistema de Aquisição Dinâmico: Inexistência de sistema de aquisição dinâmico\n\n9 - LOCAL DA EXECUÇÃO DO CONTRATO\nLOCAL DA EXECUÇÃO DO CONTRATO (PROCEDIMENTO)\nPaís: Portugal\nNUT III: PT187\nLocalidade: Évora\nDistrito: Évora\nConcelho: Évora\nFreguesia: União das Freguesias de Évora (São Mamede, Sé, São Pedro e Santo Antão)\nLOCAL DA EXECUÇÃO DO CONTRATO (LOTE)\nIdentificador do Lote: LOT-0001; LOT-0002; LOT-0003; LOT-0004; LOT-0005; LOT-0006; LOT-0007; LOT-0008; LOT-0009; LOT-0010; LOT-0011; LOT-0012; LOT-0013; LOT-0014; LOT-0015; LOT-0016; LOT-0017; LOT-0018; LOT-0019; LOT-0020; LOT-0021; LOT-0022; LOT-0023; LOT-0024; LOT-0025; LOT-0026; LOT-0027; LOT-0028; LOT-0029; LOT-0030; LOT-0031; LOT-0032; LOT-0033; LOT-0034; LOT-0035; LOT-0036; LOT-0037; LOT-0038; LOT-0039; LOT-0040; LOT-0041; LOT-0042; LOT-0043; LOT-0044; LOT-0045; LOT-0046; LOT-0047; LOT-0048; LOT-0049; LOT-0050; LOT-0051; LOT-0052; LOT-0053; LOT-0054; LOT-0055; LOT-0056; LOT-0057; LOT-0058; LOT-0059\nPaís: Portugal\nNUT III: PT187\nLocalidade: Évora\nDistrito: Évora\nConcelho: Évora\nFreguesia: União das Freguesias de Évora (São Mamede, Sé, São Pedro e Santo Antão)\n\n10 - PRAZO DE EXECUÇÃO DO CONTRATO\nIdentificador do Lote: LOT-0001; LOT-0002; LOT-0003; LOT-0004; LOT-0005; LOT-0006; LOT-0007; LOT-0008; LOT-0009; LOT-0010; LOT-0011; LOT-0012; LOT-0013; LOT-0014; LOT-0015; LOT-0016; LOT-0017; LOT-0018; LOT-0019; LOT-0020; LOT-0021; LOT-0022; LOT-0023; LOT-0024; LOT-0025; LOT-0026; LOT-0027; LOT-0028; LOT-0029; LOT-0030; LOT-0031; LOT-0032; LOT-0033; LOT-0034; LOT-0035; LOT-0036; LOT-0037; LOT-0038; LOT-0039; LOT-0040; LOT-0041; LOT-0042; LOT-0043; LOT-0044; LOT-0045; LOT-0046; LOT-0047; LOT-0048; LOT-0049; LOT-0050; LOT-0051; LOT-0052; LOT-0053; LOT-0054; LOT-0055; LOT-0056; LOT-0057; LOT-0058; LOT-0059\nPrazo de execução do contrato: 36 MESES\nPrevisão de renovações: Sim\nIndicar número máximo de renovações: 2\nPrazo de renovações diferente do prazo inicial: Não\n\n11 - FUNDOS EU\nIdentificador do Lote: LOT-0001; LOT-0002; LOT-0003; LOT-0004; LOT-0005; LOT-0006; LOT-0007; LOT-0008; LOT-0009; LOT-0010; LOT-0011; LOT-0012; LOT-0013; LOT-0014; LOT-0015; LOT-0016; LOT-0017; LOT-0018; LOT-0019; LOT-0020; LOT-0021; LOT-0022; LOT-0023; LOT-0024; LOT-0025; LOT-0026; LOT-0027; LOT-0028; LOT-0029; LOT-0030; LOT-0031; LOT-0032; LOT-0033; LOT-0034; LOT-0035; LOT-0036; LOT-0037; LOT-0038; LOT-0039; LOT-0040; LOT-0041; LOT-0042; LOT-0043; LOT-0044; LOT-0045; LOT-0046; LOT-0047; LOT-0048; LOT-0049; LOT-0050; LOT-0051; LOT-0052; LOT-0053; LOT-0054; LOT-0055; LOT-0056; LOT-0057; LOT-0058; LOT-0059\nTêm fundos EU? Não\n\n12 - DOCUMENTOS DE HABILITAÇÃO\nHabilitação para o exercício da atividade profissional: Não\n\n13 - CONDIÇÕES DE APRESENTAÇÃO\nPlataforma eletrónica utilizada pela entidade adjudicante: VORTAL\nURL para Apresentação: https://community.vortal.biz/public/\nAdmissibilidade da apresentação de propostas variantes: Não autorizado\nPrazo para apresentação das propostas: 18-09-2025 18:00\nPrazo durante o qual os concorrentes são obrigados a manter as respetivas propostas: 120 dias a contar do termo do prazo para a apresentação das propostas\nApresentação de Catálogo Eletrónico: Permitido\nIndicação de Subcontratação na Proposta: Inexistência de indicação de subcontratação\n\n14 - PRESTAÇÃO DE CAUÇÃO\nPrestação de caução: Não\n\n15 - FORNECIMENTO DAS PEÇAS DO CONCURSO, APRESENTAÇÃO DE PEDIDOS DE PARTICIPAÇÃO E APRESENTAÇÃO DAS PROPOSTAS\nLink para acesso às peças do concurso (URL): https://community.vortal.biz/Public/public-tender-documents/YWpPVjY4UHhqZUNoU0J1MEtYMmlpR1pWNzRiL0NDcm9vc1piTE04cGNtTmRsQXRveldsOHNXY2d6SDJ4eEYzaHdrMGxNSk8wbmZkU0RIbkIvVkdwNVE9PTdFRHAz\n\n20 - OUTROS REQUISITOS\nIdentificador do Lote: LOT-0001; LOT-0002; LOT-0003; LOT-0004; LOT-0005; LOT-0006; LOT-0007; LOT-0008; LOT-0009; LOT-0010; LOT-0011; LOT-0012; LOT-0013; LOT-0014; LOT-0015; LOT-0016; LOT-0017; LOT-0018; LOT-0019; LOT-0020; LOT-0021; LOT-0022; LOT-0023; LOT-0024; LOT-0025; LOT-0026; LOT-0027; LOT-0028; LOT-0029; LOT-0030; LOT-0031; LOT-0032; LOT-0033; LOT-0034; LOT-0035; LOT-0036; LOT-0037; LOT-0038; LOT-0039; LOT-0040; LOT-0041; LOT-0042; LOT-0043; LOT-0044; LOT-0045; LOT-0046; LOT-0047; LOT-0048; LOT-0049; LOT-0050; LOT-0051; LOT-0052; LOT-0053; LOT-0054; LOT-0055; LOT-0056; LOT-0057; LOT-0058; LOT-0059\nInformação sobre contratos reservados. Aplica-se a contratos reservados (54º-A)? Não\n\n21 - CRITÉRIO DE ADJUDICAÇÃO\nO Critério de adjudicação é diferenciado por lote? Não\nMultifator: Não\nMonofator:\nNome: Preço\n\n24 - CONDIÇÕES DO CONTRATO\nIdentificador do Lote: LOT-0001; LOT-0002; LOT-0003; LOT-0004; LOT-0005; LOT-0006; LOT-0007; LOT-0008; LOT-0009; LOT-0010; LOT-0011; LOT-0012; LOT-0013; LOT-0014; LOT-0015; LOT-0016; LOT-0017; LOT-0018; LOT-0019; LOT-0020; LOT-0021; LOT-0022; LOT-0023; LOT-0024; LOT-0025; LOT-0026; LOT-0027; LOT-0028; LOT-0029; LOT-0030; LOT-0031; LOT-0032; LOT-0033; LOT-0034; LOT-0035; LOT-0036; LOT-0037; LOT-0038; LOT-0039; LOT-0040; LOT-0041; LOT-0042; LOT-0043; LOT-0044; LOT-0045; LOT-0046; LOT-0047; LOT-0048; LOT-0049; LOT-0050; LOT-0051; LOT-0052; LOT-0053; LOT-0054; LOT-0055; LOT-0056; LOT-0057; LOT-0058; LOT-0059\nFaturação Eletrónica: Permitido\nObrigação de Subcontratação:\nCódigo da Obrigação de Subcontratação: Não é aplicável nenhuma obrigação de subcontratação.\n\n25 - COMPRA PÚBLICA ESTRATÉGICA\nCompra Pública Estratégica: Inexistência de contratação pública estratégica\n\n26 - INFORMAÇÕES ADICIONAIS\nIdentificador do Lote: LOT-0001; LOT-0002; LOT-0003; LOT-0004; LOT-0005; LOT-0006; LOT-0007; LOT-0008; LOT-0009; LOT-0010; LOT-0011; LOT-0012; LOT-0013; LOT-0014; LOT-0015; LOT-0016; LOT-0017; LOT-0018; LOT-0019; LOT-0020; LOT-0021; LOT-0022; LOT-0023; LOT-0024; LOT-0025; LOT-0026; LOT-0027; LOT-0028; LOT-0029; LOT-0030; LOT-0031; LOT-0032; LOT-0033; LOT-0034; LOT-0035; LOT-0036; LOT-0037; LOT-0038; LOT-0039; LOT-0040; LOT-0041; LOT-0042; LOT-0043; LOT-0044; LOT-0045; LOT-0046; LOT-0047; LOT-0048; LOT-0049; LOT-0050; LOT-0051; LOT-0052; LOT-0053; LOT-0054; LOT-0055; LOT-0056; LOT-0057; LOT-0058; LOT-0059\nContrato adequado para PME: Sim\nCobertura ACP (Acordo dos Contratos Públicos da Organização Mundial do Comércio): Não\n\n27 - IDENTIFICAÇÃO E CONTACTOS DO ÓRGÃO DE RECURSOS ADMINISTRATIVOS\nDesignação: Unidade Local De Saúde do Alentejo Central, E.P.E.\nEndereço: Largo Senhor da Pobreza\nCódigo postal: 7000-811\nLocalidade: Évora\nTelefone: +351 266740111\nFax: +351 266744212\nEndereço eletrónico: concursos.aprov@ulsac.min-saude.pt\n\n28 - IDENTIFICAÇÃO DO(S) AUTOR(ES) DE ANÚNCIO\nNome: Vitor Rui Gomes Fialho\nCargo: Presidente do Conselho de Administração\n419442839",
    "nipc": "508085888",
    "distrito": "Évora",
    "concelho": "Évora",
    "freguesia": "Todas",
    "site": "www.hevora.min-saude.pt",
    "email": "concursos.aprov@ulsac.min-saude.pt",
    "designacao_contrato": "Aquisição de Dispositivos Médicos e Outros Produtos para Esterilização",
    "descricao": "Aquisição de Dispositivos Médicos e Outros Produtos para Esterilização",
    "preco_base": "427.713,36 EUR",
    "prazo_execucao": "36 MESES",
    "prazo_apresentacao_propostas": "18-09-2025 18:00",
    "fundos_eu": "Não",
    "plataforma_eletronica": "VORTAL",
    "url_procedimento": "https://community.vortal.biz/public/",
    "autor_nome": "Vitor Rui Gomes Fialho",
    "autor_cargo": "Presidente do Conselho de Administração"
  },
  {
    "numero_procedimento": "N/A",
    "entidade": "PACT – Parque do Alentejo de Ciência e Tecnologia, SA",
    "link": "https://diariodarepublica.pt/dr/detalhe/contrato-publico/22368-932837057",
    "detalhes_completos": "1 - IDENTIFICAÇÃO E CONTACTOS DA ENTIDADE ADJUDICANTE\nDesignação da entidade adjudicante: PACT – Parque do Alentejo de Ciência e Tecnologia, SA\nNIPC: 510055710\nEndereço: Herdade da Barba Rala   |   Rua Luís Adelino Fonseca, lote 1-A   |   EVORA\nCódigo postal: 7005-345\nLocalidade: Évora\nPaís: Portugal\nNUT III: PT187\nDistrito: Évora\nConcelho: Évora\nFreguesia: União das Freguesias de Malagueira e Horta das Figueiras\nTelefone: 924396890\nFax: 924396890\nEndereço da Entidade (URL): www.pact.pt\nEndereço Eletrónico: geral@pact.pt\neDelivery Gateway (URL): https://community.vortal.biz/public/\nFunção da Organização: Adquirente\nNorma jurídica da Entidade Adjudicante: Autoridade da administração central\nÁrea de atividade da Autoridade Adjudicante: Serviços públicos das administrações públicas\n\n2 - JORNAL OFICIAL DA UNIÃO EUROPEIA\nO procedimento a que este anúncio diz respeito também é publicitado no Jornal Oficial da União Europeia? Não\n\n3 - AVISO\nModelo de Anúncio: Concurso público\nData de Envio do Anúncio: 20-08-2025\n\n5 - PROCESSO\nTipo de Procedimento: Concurso público\nPreço base do procedimento: Sim\nValor do preço base do procedimento: 107.800,00 EUR\nProcedimento com lotes? Sim\nNº Máx. de Lotes Autorizado: 2\nNúmero máximo de lotes que podem ser adjudicados a um concorrente: 2\n\n6 - OBJETO DO CONTRATO\nNúmero de referência interna: 009/PACT-CPub/2025\nDesignação do contrato: Aquisição de Equipamentos Informáticos para o “Future Lab”\nDescrição: Aquisição de Equipamentos Informáticos para o “Future Lab”\nTipo de Contrato Principal: Aquisição de Bens Móveis\nTipo de Contrato: Aquisição de Bens Móveis\nClassificação CPV (Vocabulário Comum para os Contratos Públicos)\nObjeto principal\nVocabulário Principal: 48820000\nPreço base s/IVA: 80.000,00 EUR\nObjeto Complementar\nVocabulário Principal: 30213000\nPreço base s/IVA: 27.800,00 EUR\nLotes: \nNº: LOT-0001\nDescrição do Lote: Lote 1 - Aquisição de Servidor\nPreço base s/IVA: 80.000,00 EUR\nClassificação CPV (Vocabulário Comum para os Contratos Públicos)\nObjeto principal\nVocabulário Principal: 48820000\nObjeto Complementar\nVocabulário Principal: 30213000\nNº: LOT-0002\nDescrição do Lote: Lote 2 - Aquisição de Computadores\nPreço base s/IVA: 27.800,00 EUR\nClassificação CPV (Vocabulário Comum para os Contratos Públicos)\nObjeto principal\nVocabulário Principal: 48820000\nObjeto Complementar\nVocabulário Principal: 30213000\n\n7 - INDICAÇÕES ADICIONAIS\nO contrato envolve aquisição conjunta (satisfação de várias entidades)? Não\nO contrato é adjudicado por uma central de compras? Não\n\n8 - TÉCNICAS\nO concurso destina-se à celebração de um acordo-quadro? Inexistência de acordo-quadro\nÉ utilizado um leilão eletrónico? Não\nÉ adotada uma fase de negociação? Não\nSistema de Aquisição Dinâmico: Inexistência de sistema de aquisição dinâmico\n\n9 - LOCAL DA EXECUÇÃO DO CONTRATO\nLOCAL DA EXECUÇÃO DO CONTRATO (PROCEDIMENTO)\nPaís: Portugal\nNUT III: PT187\nLocalidade: Évora\nDistrito: Évora\nConcelho: Évora\nFreguesia: União das Freguesias de Malagueira e Horta das Figueiras\nLOCAL DA EXECUÇÃO DO CONTRATO (LOTE)\nIdentificador do Lote: LOT-0001; LOT-0002\nPaís: Portugal\nNUT III: PT187\nLocalidade: Évora\nDistrito: Évora\nConcelho: Évora\nFreguesia: União das Freguesias de Malagueira e Horta das Figueiras\n\n10 - PRAZO DE EXECUÇÃO DO CONTRATO\nIdentificador do Lote: LOT-0001; LOT-0002\nPrazo de execução do contrato: 30 DIAS\nPrevisão de renovações: Não\n\n11 - FUNDOS EU\nIdentificador do Lote: LOT-0001; LOT-0002\nTêm fundos EU? Sim\n\n12 - DOCUMENTOS DE HABILITAÇÃO\nHabilitação para o exercício da atividade profissional: Não\n\n13 - CONDIÇÕES DE APRESENTAÇÃO\nPlataforma eletrónica utilizada pela entidade adjudicante: VORTAL\nURL para Apresentação: https://community.vortal.biz/public/\nAdmissibilidade da apresentação de propostas variantes: Não autorizado\nPrazo para apresentação das propostas: 29-08-2025 23:59\nPrazo durante o qual os concorrentes são obrigados a manter as respetivas propostas: 150 dias a contar do termo do prazo para a apresentação das propostas\nIndicação de Subcontratação na Proposta: Inexistência de indicação de subcontratação\n\n14 - PRESTAÇÃO DE CAUÇÃO\nPrestação de caução: Não\n\n15 - FORNECIMENTO DAS PEÇAS DO CONCURSO, APRESENTAÇÃO DE PEDIDOS DE PARTICIPAÇÃO E APRESENTAÇÃO DAS PROPOSTAS\nLink para acesso às peças do concurso (URL): https://community.vortal.biz/Public/public-tender-documents/TXNDdmFMdzYvT2NBd2R6Z2tVNWRQMmI2eDB2cE4zczBua0U5WWgrTWgybk5RTWpiYlNaQWpKYUVWYVE1VTNSK3pvOU5HUk5PRDlKVGNGc2hkRDk2OFE9PUYmITVT\n\n20 - OUTROS REQUISITOS\nIdentificador do Lote: LOT-0001; LOT-0002\nInformação sobre contratos reservados. Aplica-se a contratos reservados (54º-A)? Não\n\n21 - CRITÉRIO DE ADJUDICAÇÃO\nO Critério de adjudicação é diferenciado por lote? Não\nMultifator: Sim\nFator: \nNome: Preço\nPonderação: 80%\nSubfatores: Não\nFator: \nNome: Outros\nOutro Nome: Prazo de Entrega\nPonderação: 20%\nSubfatores: Não\n\n24 - CONDIÇÕES DO CONTRATO\nIdentificador do Lote: LOT-0001; LOT-0002\nFaturação Eletrónica: Permitido\nObrigação de Subcontratação:\nCódigo da Obrigação de Subcontratação: Não é aplicável nenhuma obrigação de subcontratação.\n\n25 - COMPRA PÚBLICA ESTRATÉGICA\nCompra Pública Estratégica: Redução dos impactos ambientais\nDescrição do Processo de Adjudicação Estratégico: Conforme as peças do procedimento\nCritérios de contratos Públicos Ecológicos: Critérios de contratação pública ecológica nacional\nCategorias da estratégia nacional: Outros\nOutra categoria (Descrição): N.A.\nDiretiva Veículos Não Poluentes: Não\nCritério de Acessibilidade: Os critérios de acessibilidade para as pessoas com deficiência não estão incluídos porque o contrato não se destina a pessoas singulares\n\n26 - INFORMAÇÕES ADICIONAIS\nIdentificador do Lote: LOT-0001; LOT-0002\nContrato adequado para PME: Sim\nCobertura ACP (Acordo dos Contratos Públicos da Organização Mundial do Comércio): Não\n\n27 - IDENTIFICAÇÃO E CONTACTOS DO ÓRGÃO DE RECURSOS ADMINISTRATIVOS\nDesignação: Conselho de Administração do Parque do Alentejo de Ciência e Tecnologia\nEndereço: Herdade da Barba Rala   |   Rua Luís Adelino Fonseca, lote 1-A   |   EVORA\nCódigo postal: 7005-345\nLocalidade: Évora\nTelefone: +351 924396890\nFax: +351 924396890\nEndereço eletrónico: ssarkar@pact.pt\n\n28 - IDENTIFICAÇÃO DO(S) AUTOR(ES) DE ANÚNCIO\nNome: João Assunção\nCargo: Operations Executive & Board Advisor\n419454308",
    "nipc": "510055710",
    "distrito": "Évora",
    "concelho": "Évora",
    "freguesia": "União das Freguesias de Malagueira e Horta das Figueiras",
    "site": "www.pact.pt",
    "email": "geral@pact.pt",
    "designacao_contrato": "Aquisição de Equipamentos Informáticos para o “Future Lab”",
    "descricao": "Aquisição de Equipamentos Informáticos para o “Future Lab”",
    "preco_base": "80.000,00 EUR",
    "prazo_execucao": "30 DIAS",
    "prazo_apresentacao_propostas": "29-08-2025 23:59",
    "fundos_eu": "Sim",
    "plataforma_eletronica": "VORTAL",
    "url_procedimento": "https://community.vortal.biz/public/",
    "autor_nome": "João Assunção",
    "autor_cargo": "Operations Executive & Board Advisor"
  },
  {
    "numero_procedimento": "N/A",
    "entidade": "PACT – Parque do Alentejo de Ciência e Tecnologia, SA",
    "link": "https://diariodarepublica.pt/dr/detalhe/contrato-publico/22369-932837058",
    "detalhes_completos": "1 - IDENTIFICAÇÃO E CONTACTOS DA ENTIDADE ADJUDICANTE\nDesignação da entidade adjudicante: PACT – Parque do Alentejo de Ciência e Tecnologia, SA\nNIPC: 510055710\nEndereço: Herdade da Barba Rala   |   Rua Luís Adelino Fonseca, lote 1-A   |   EVORA\nCódigo postal: 7005-345\nLocalidade: Évora\nPaís: Portugal\nNUT III: PT187\nDistrito: Évora\nConcelho: Évora\nFreguesia: União das Freguesias de Malagueira e Horta das Figueiras\nTelefone: 924396890\nFax: 924396890\nEndereço da Entidade (URL): www.pact.pt\nEndereço Eletrónico: geral@pact.pt\neDelivery Gateway (URL): https://community.vortal.biz/public/\nFunção da Organização: Adquirente\nNorma jurídica da Entidade Adjudicante: Autoridade da administração central\nÁrea de atividade da Autoridade Adjudicante: Serviços públicos das administrações públicas\n\n2 - JORNAL OFICIAL DA UNIÃO EUROPEIA\nO procedimento a que este anúncio diz respeito também é publicitado no Jornal Oficial da União Europeia? Não\n\n3 - AVISO\nModelo de Anúncio: Concurso público\nData de Envio do Anúncio: 20-08-2025\n\n5 - PROCESSO\nTipo de Procedimento: Concurso público\nPreço base do procedimento: Sim\nValor do preço base do procedimento: 205.618,00 EUR\nProcedimento com lotes? Sim\nNº Máx. de Lotes Autorizado: 3\nNúmero máximo de lotes que podem ser adjudicados a um concorrente: 3\n\n6 - OBJETO DO CONTRATO\nNúmero de referência interna: 015/PACT-CPub/2025\nDesignação do contrato: Aquisição de Equipamentos de Digitalização, Impressão 3D, Robótica, Imersão e Software para o “Future Lab”\nDescrição: Aquisição de Equipamentos de Digitalização, Impressão 3D, Robótica, Imersão e Software para o “Future Lab”\nTipo de Contrato Principal: Aquisição de Bens Móveis\nTipo de Contrato: Aquisição de Bens Móveis\nClassificação CPV (Vocabulário Comum para os Contratos Públicos)\nObjeto principal\nVocabulário Principal: 30216110\nPreço base s/IVA: 61.200,00 EUR\nObjeto Complementar\nVocabulário Principal: 48900000\nPreço base s/IVA: 19.000,00 EUR\nObjeto Complementar\nVocabulário Principal: 32322000\nPreço base s/IVA: 125.418,00 EUR\nLotes: \nNº: LOT-0001\nDescrição do Lote: Lote 1 - Aquisição de Equipamento de Digitalização 3D\nPreço base s/IVA: 61.200,00 EUR\nClassificação CPV (Vocabulário Comum para os Contratos Públicos)\nObjeto principal\nVocabulário Principal: 30216110\nObjeto Complementar\nVocabulário Principal: 48900000\nObjeto Complementar\nVocabulário Principal: 32322000\nNº: LOT-0002\nDescrição do Lote: Lote 2 - Aquisição de Software para Engenharia Inversa\nPreço base s/IVA: 19.000,00 EUR\nClassificação CPV (Vocabulário Comum para os Contratos Públicos)\nObjeto principal\nVocabulário Principal: 30216110\nObjeto Complementar\nVocabulário Principal: 48900000\nObjeto Complementar\nVocabulário Principal: 32322000\nNº: LOT-0003\nDescrição do Lote: Lote 3 - Aquisição de Equipamento de Fabrico Aditivo, de Realidade Aumentada, Realidade Virtual e de Robótica\nPreço base s/IVA: 125.418,00 EUR\nClassificação CPV (Vocabulário Comum para os Contratos Públicos)\nObjeto principal\nVocabulário Principal: 30216110\nObjeto Complementar\nVocabulário Principal: 48900000\nObjeto Complementar\nVocabulário Principal: 32322000\n\n7 - INDICAÇÕES ADICIONAIS\nO contrato envolve aquisição conjunta (satisfação de várias entidades)? Não\nO contrato é adjudicado por uma central de compras? Não\n\n8 - TÉCNICAS\nO concurso destina-se à celebração de um acordo-quadro? Inexistência de acordo-quadro\nÉ utilizado um leilão eletrónico? Não\nÉ adotada uma fase de negociação? Não\nSistema de Aquisição Dinâmico: Inexistência de sistema de aquisição dinâmico\n\n9 - LOCAL DA EXECUÇÃO DO CONTRATO\nLOCAL DA EXECUÇÃO DO CONTRATO (PROCEDIMENTO)\nPaís: Portugal\nNUT III: PT187\nLocalidade: Évora\nDistrito: Évora\nConcelho: Évora\nFreguesia: União das Freguesias de Malagueira e Horta das Figueiras\nLOCAL DA EXECUÇÃO DO CONTRATO (LOTE)\nIdentificador do Lote: LOT-0001; LOT-0002; LOT-0003\nPaís: Portugal\nNUT III: PT187\nLocalidade: Évora\nDistrito: Évora\nConcelho: Évora\nFreguesia: União das Freguesias de Malagueira e Horta das Figueiras\n\n10 - PRAZO DE EXECUÇÃO DO CONTRATO\nIdentificador do Lote: LOT-0001; LOT-0002; LOT-0003\nPrazo de execução do contrato: 45 DIAS\nPrevisão de renovações: Não\n\n11 - FUNDOS EU\nIdentificador do Lote: LOT-0001; LOT-0002; LOT-0003\nTêm fundos EU? Sim\n\n12 - DOCUMENTOS DE HABILITAÇÃO\nHabilitação para o exercício da atividade profissional: Não\n\n13 - CONDIÇÕES DE APRESENTAÇÃO\nPlataforma eletrónica utilizada pela entidade adjudicante: VORTAL\nURL para Apresentação: https://community.vortal.biz/public/\nAdmissibilidade da apresentação de propostas variantes: Não autorizado\nPrazo para apresentação das propostas: 29-08-2025 23:59\nPrazo durante o qual os concorrentes são obrigados a manter as respetivas propostas: 150 dias a contar do termo do prazo para a apresentação das propostas\nIndicação de Subcontratação na Proposta: Inexistência de indicação de subcontratação\n\n14 - PRESTAÇÃO DE CAUÇÃO\nPrestação de caução: Não\n\n15 - FORNECIMENTO DAS PEÇAS DO CONCURSO, APRESENTAÇÃO DE PEDIDOS DE PARTICIPAÇÃO E APRESENTAÇÃO DAS PROPOSTAS\nLink para acesso às peças do concurso (URL): https://community.vortal.biz/Public/public-tender-documents/aWYyRmRBMDIzcFI1a2dUV2g0Q05rUm1qOVdqcVNnZldzM1QzRnpZa0tGQ0p2VStnVENwM0tVS3hMVEJQWmxXVTlyWEFIQ2JHc3hPclNGNWtLRlJqRGc9PVpoKjBE\n\n20 - OUTROS REQUISITOS\nIdentificador do Lote: LOT-0001; LOT-0002; LOT-0003\nInformação sobre contratos reservados. Aplica-se a contratos reservados (54º-A)? Não\n\n21 - CRITÉRIO DE ADJUDICAÇÃO\nO Critério de adjudicação é diferenciado por lote? Não\nMultifator: Sim\nFator: \nNome: Preço\nPonderação: 80%\nSubfatores: Não\nFator: \nNome: Outros\nOutro Nome: Prazo de Entrega\nPonderação: 20%\nSubfatores: Não\n\n24 - CONDIÇÕES DO CONTRATO\nIdentificador do Lote: LOT-0001; LOT-0002; LOT-0003\nFaturação Eletrónica: Permitido\nObrigação de Subcontratação:\nCódigo da Obrigação de Subcontratação: Não é aplicável nenhuma obrigação de subcontratação.\n\n25 - COMPRA PÚBLICA ESTRATÉGICA\nCompra Pública Estratégica: Redução dos impactos ambientais\nDescrição do Processo de Adjudicação Estratégico: Conforme as peças do procedimento\nCritérios de contratos Públicos Ecológicos: Critérios de contratação pública ecológica nacional\nCategorias da estratégia nacional: Outros\nOutra categoria (Descrição): N.A.\nDiretiva Veículos Não Poluentes: Não\nCritério de Acessibilidade: Os critérios de acessibilidade para as pessoas com deficiência não estão incluídos porque o contrato não se destina a pessoas singulares\n\n26 - INFORMAÇÕES ADICIONAIS\nIdentificador do Lote: LOT-0001; LOT-0002; LOT-0003\nContrato adequado para PME: Sim\nCobertura ACP (Acordo dos Contratos Públicos da Organização Mundial do Comércio): Não\n\n27 - IDENTIFICAÇÃO E CONTACTOS DO ÓRGÃO DE RECURSOS ADMINISTRATIVOS\nDesignação: Conselho de Administração do Parque do Alentejo de Ciência e Tecnologia\nEndereço: Herdade da Barba Rala   |   Rua Luís Adelino Fonseca, lote 1-A   |   EVORA\nCódigo postal: 7005-345\nLocalidade: Évora\nTelefone: +351 924396890\nFax: +351 924396890\nEndereço eletrónico: ssarkar@pact.pt\n\n28 - IDENTIFICAÇÃO DO(S) AUTOR(ES) DE ANÚNCIO\nNome: João Assunção\nCargo: Operations Executive & Board Advisor\n419454349",
    "nipc": "510055710",
    "distrito": "Évora",
    "concelho": "Évora",
    "freguesia": "União das Freguesias de Malagueira e Horta das Figueiras",
    "site": "www.pact.pt",
    "email": "geral@pact.pt",
    "designacao_contrato": "Aquisição de Equipamentos de Digitalização, Impressão 3D, Robótica, Imersão e Software para o “Future Lab”",
    "descricao": "Aquisição de Equipamentos de Digitalização, Impressão 3D, Robótica, Imersão e Software para o “Future Lab”",
    "preco_base": "61.200,00 EUR",
    "prazo_execucao": "45 DIAS",
    "prazo_apresentacao_propostas": "29-08-2025 23:59",
    "fundos_eu": "Sim",
    "plataforma_eletronica": "VORTAL",
    "url_procedimento": "https://community.vortal.biz/public/",
    "autor_nome": "João Assunção",
    "autor_cargo": "Operations Executive & Board Advisor"
  },
  {
    "numero_procedimento": "N/A",
    "entidade": "Municipio de Idanha-a-Nova",
    "link": "https://diariodarepublica.pt/dr/detalhe/contrato-publico/22373-932837059",
    "detalhes_completos": "1 - IDENTIFICAÇÃO E CONTACTOS DA ENTIDADE ADJUDICANTE\nDesignação da entidade adjudicante: Municipio de Idanha-a-Nova\nNIPC: 501121030\nServiço/Órgão/Pessoa de contacto: Serviço de Educação - Divisão de Educação, Ação Social, Cultura, Turismo, Desporto e Tempos Livres\nEndereço: Largo do Município\nCódigo postal: 6060-163\nLocalidade: Idanha-a-Nova\nPaís: Portugal\nNUT III: PT16H\nDistrito: Castelo Branco\nConcelho: Idanha-a-Nova\nFreguesia: União das Freguesias de Idanha-a-Nova e Alcafozes\nTelefone: 277200570\nFax: 277200580\nEndereço da Entidade (URL): http://www.cm-idanhanova.pt/\nEndereço Eletrónico: geral@cm-idanhanova.pt\neDelivery Gateway (URL): https://www.acingov.pt\nFunção da Organização: Adquirente\nNorma jurídica da Entidade Adjudicante: Organismo de direito público\nÁrea de atividade da Autoridade Adjudicante: Serviços públicos das administrações públicas\n\n2 - JORNAL OFICIAL DA UNIÃO EUROPEIA\nO procedimento a que este anúncio diz respeito também é publicitado no Jornal Oficial da União Europeia? Não\n\n3 - AVISO\nModelo de Anúncio: Concurso público\nData de Envio do Anúncio: 21-08-2025\n\n5 - PROCESSO\nTipo de Procedimento: Concurso público\nPreço base do procedimento: Sim\nValor do preço base do procedimento: 195.776,80 EUR\nProcedimento com lotes? Sim\nNº Máx. de Lotes Autorizado: 7\nNúmero máximo de lotes que podem ser adjudicados a um concorrente: 7\n\n6 - OBJETO DO CONTRATO\nNúmero de referência interna: CPS057-2025\nDesignação do contrato: Aquisição de serviços por lotes, para o fornecimento contínuo de refeições confecionadas e lanches aos alunos das escolas, em refeitórios escolares\nDescrição: Aquisição de serviços por lotes, para o fornecimento contínuo de refeições confecionadas e lanches aos alunos das escolas, em refeitórios escolares\nTipo de Contrato Principal: Aquisição de Serviços\nTipo de Contrato: Aquisição de Bens Móveis; Aquisição de Serviços\nClassificação CPV (Vocabulário Comum para os Contratos Públicos)\nObjeto principal\nVocabulário Principal: 55524000\nPreço base s/IVA: 195.776,80 EUR\nLotes: \nNº: LOT-0001\nDescrição do Lote: LOTE 1: Jardim de Infância e Escola EB1 do Ladoeiro;\nPreço base s/IVA: 43.756,00 EUR\nClassificação CPV (Vocabulário Comum para os Contratos Públicos)\nObjeto principal\nVocabulário Principal: 55524000\nNº: LOT-0002\nDescrição do Lote: LOTE 2: Jardim de Infância e Escola EB1 de Penha Garcia;\nPreço base s/IVA: 10.608,00 EUR\nClassificação CPV (Vocabulário Comum para os Contratos Públicos)\nObjeto principal\nVocabulário Principal: 55524000\nNº: LOT-0003\nDescrição do Lote: LOTE 3: Jardim de Infância e Creche do Rosmaninhal;\nPreço base s/IVA: 19.584,00 EUR\nClassificação CPV (Vocabulário Comum para os Contratos Públicos)\nObjeto principal\nVocabulário Principal: 55524000\nNº: LOT-0004\nDescrição do Lote: LOTE 4: Jardim de Infância e Escola EB1 de Monsanto;\nPreço base s/IVA: 41.616,00 EUR\nClassificação CPV (Vocabulário Comum para os Contratos Públicos)\nObjeto principal\nVocabulário Principal: 55524000\nNº: LOT-0005\nDescrição do Lote: LOTE 5: Jardim de Infância e Escola EB1 da Zebreira;\nPreço base s/IVA: 41.616,00 EUR\nClassificação CPV (Vocabulário Comum para os Contratos Públicos)\nObjeto principal\nVocabulário Principal: 55524000\nNº: LOT-0006\nDescrição do Lote: LOTE 6: Jardim de Infância e Creche de Termas de Monfortinho; e\nPreço base s/IVA: 14.596,80 EUR\nClassificação CPV (Vocabulário Comum para os Contratos Públicos)\nObjeto principal\nVocabulário Principal: 55524000\nNº: LOT-0007\nDescrição do Lote: LOTE 7: Jardim de Infância e Creche de S. Miguel De Acha\nPreço base s/IVA: 24.000,00 EUR\nClassificação CPV (Vocabulário Comum para os Contratos Públicos)\nObjeto principal\nVocabulário Principal: 55524000\n\n7 - INDICAÇÕES ADICIONAIS\nO contrato envolve aquisição conjunta (satisfação de várias entidades)? Não\nO contrato é adjudicado por uma central de compras? Não\n\n8 - TÉCNICAS\nO concurso destina-se à celebração de um acordo-quadro? Inexistência de acordo-quadro\nÉ utilizado um leilão eletrónico? Não\nÉ adotada uma fase de negociação? Não\nSistema de Aquisição Dinâmico: Inexistência de sistema de aquisição dinâmico\n\n9 - LOCAL DA EXECUÇÃO DO CONTRATO\nLOCAL DA EXECUÇÃO DO CONTRATO (PROCEDIMENTO)\nPaís: Portugal\nNUT III: PT16H\nLocalidade: Ladoeiro\nDistrito: Castelo Branco\nConcelho: Idanha-a-Nova\nFreguesia: Freguesia de Ladoeiro\nPaís: Portugal\nNUT III: PT16H\nLocalidade: Penha Garcia\nDistrito: Castelo Branco\nConcelho: Idanha-a-Nova\nFreguesia: Freguesia de Penha Garcia\nPaís: Portugal\nNUT III: PT16H\nLocalidade: Rosmaninhal\nDistrito: Castelo Branco\nConcelho: Idanha-a-Nova\nFreguesia: Freguesia de Rosmaninhal\nPaís: Portugal\nNUT III: PT16H\nLocalidade: Monsanto\nDistrito: Castelo Branco\nConcelho: Idanha-a-Nova\nFreguesia: União das Freguesias de Monsanto e Idanha-a-Velha\nPaís: Portugal\nNUT III: PT16H\nLocalidade: Termas de Monfortinho\nDistrito: Castelo Branco\nConcelho: Idanha-a-Nova\nFreguesia: União das Freguesias de Monfortinho e Salvaterra do Extremo\nPaís: Portugal\nNUT III: PT16H\nLocalidade: São Miguel de Acha\nDistrito: Castelo Branco\nConcelho: Idanha-a-Nova\nFreguesia: Freguesia de São Miguel de Acha\nLOCAL DA EXECUÇÃO DO CONTRATO (LOTE)\nIdentificador do Lote: LOT-0001\nPaís: Portugal\nNUT III: PT16H\nLocalidade: Ladoeiro\nDistrito: Castelo Branco\nConcelho: Idanha-a-Nova\nFreguesia: Freguesia de Ladoeiro\nIdentificador do Lote: LOT-0002\nPaís: Portugal\nNUT III: PT16H\nLocalidade: Penha Garcia\nDistrito: Castelo Branco\nConcelho: Idanha-a-Nova\nFreguesia: Freguesia de Penha Garcia\nIdentificador do Lote: LOT-0003\nPaís: Portugal\nNUT III: PT16H\nLocalidade: Rosmaninhal\nDistrito: Castelo Branco\nConcelho: Idanha-a-Nova\nFreguesia: Freguesia de Rosmaninhal\nIdentificador do Lote: LOT-0004\nPaís: Portugal\nNUT III: PT16H\nLocalidade: Monsanto\nDistrito: Castelo Branco\nConcelho: Idanha-a-Nova\nFreguesia: União das Freguesias de Monsanto e Idanha-a-Velha\nIdentificador do Lote: LOT-0005\nPaís: Portugal\nNUT III: PT16H\nLocalidade: Zebreira\nDistrito: Castelo Branco\nConcelho: Idanha-a-Nova\nFreguesia: União das Freguesias de Zebreira e Segura\nIdentificador do Lote: LOT-0006\nPaís: Portugal\nNUT III: PT16H\nLocalidade: Termas de Monfortinho\nDistrito: Castelo Branco\nConcelho: Idanha-a-Nova\nFreguesia: União das Freguesias de Monfortinho e Salvaterra do Extremo\nIdentificador do Lote: LOT-0007\nPaís: Portugal\nNUT III: PT16H\nLocalidade: S. Miguel D-Acha\nDistrito: Castelo Branco\nConcelho: Idanha-a-Nova\nFreguesia: Freguesia de São Miguel de Acha\n\n10 - PRAZO DE EXECUÇÃO DO CONTRATO\nIdentificador do Lote: LOT-0001; LOT-0002; LOT-0003; LOT-0004; LOT-0005; LOT-0006; LOT-0007\nPrazo de execução do contrato: 365 DIAS\nPrevisão de renovações: Não\n\n11 - FUNDOS EU\nIdentificador do Lote: LOT-0001; LOT-0002; LOT-0003; LOT-0004; LOT-0005; LOT-0006; LOT-0007\nTêm fundos EU? Não\n\n12 - DOCUMENTOS DE HABILITAÇÃO\nHabilitação para o exercício da atividade profissional: Não\n\n13 - CONDIÇÕES DE APRESENTAÇÃO\nPlataforma eletrónica utilizada pela entidade adjudicante: ACIN\nURL para Apresentação: https://www.acingov.pt\nAdmissibilidade da apresentação de propostas variantes: Não autorizado\nPrazo para apresentação das propostas: 30-08-2025 23:59\nPrazo durante o qual os concorrentes são obrigados a manter as respetivas propostas: 66 dias a contar do termo do prazo para a apresentação das propostas\nIndicação de Subcontratação na Proposta: Inexistência de indicação de subcontratação\n\n14 - PRESTAÇÃO DE CAUÇÃO\nPrestação de caução: Não\n\n15 - FORNECIMENTO DAS PEÇAS DO CONCURSO, APRESENTAÇÃO DE PEDIDOS DE PARTICIPAÇÃO E APRESENTAÇÃO DAS PROPOSTAS\nLink para acesso às peças do concurso (URL): https://www.acingov.pt/acingovprod/2/zonaPublica/zona_publica_c/donwloadProcedurePiece/OTMyMjc1\n\n20 - OUTROS REQUISITOS\nIdentificador do Lote: LOT-0001; LOT-0002; LOT-0003; LOT-0004; LOT-0005; LOT-0006; LOT-0007\nInformação sobre contratos reservados. Aplica-se a contratos reservados (54º-A)? Não\n\n21 - CRITÉRIO DE ADJUDICAÇÃO\nO Critério de adjudicação é diferenciado por lote? Não\nMultifator: Sim\nFator: \nNome: Outros\nOutro Nome: Ponderação do fator Distância (D)\nPonderação: 70%\nSubfatores: Não\nFator: \nNome: Outros\nOutro Nome: Ponderação do fator Preço (PR)\nPonderação: 30%\nSubfatores: Não\n\n24 - CONDIÇÕES DO CONTRATO\nIdentificador do Lote: LOT-0001; LOT-0002; LOT-0003; LOT-0004; LOT-0005; LOT-0006; LOT-0007\nFaturação Eletrónica: Permitido\nObrigação de Subcontratação:\nCódigo da Obrigação de Subcontratação: Não é aplicável nenhuma obrigação de subcontratação.\n\n25 - COMPRA PÚBLICA ESTRATÉGICA\nCompra Pública Estratégica: Inexistência de contratação pública estratégica\n\n26 - INFORMAÇÕES ADICIONAIS\nIdentificador do Lote: LOT-0001; LOT-0002; LOT-0003; LOT-0004; LOT-0005; LOT-0006; LOT-0007\nContrato adequado para PME: Sim\nCobertura ACP (Acordo dos Contratos Públicos da Organização Mundial do Comércio): Não\n\n27 - IDENTIFICAÇÃO E CONTACTOS DO ÓRGÃO DE RECURSOS ADMINISTRATIVOS\nDesignação: Executivo Camarário\nEndereço: Largo do Município\nCódigo postal: 6060-163\nLocalidade: Idanha-a-Nova\nTelefone: 277200570\nFax: 277200580\nEndereço eletrónico: geral@idanha.pt\n\n28 - IDENTIFICAÇÃO DO(S) AUTOR(ES) DE ANÚNCIO\nNome: Armindo Moreira Palma Jacinto\nCargo: Presidente da Câmara Municipal de Idanha-a-Nova\n419446476",
    "nipc": "501121030",
    "distrito": "Castelo Branco",
    "concelho": "Idanha-a-Nova",
    "freguesia": "União das Freguesias de Idanha-a-Nova e Alcafozes",
    "site": "http://www.cm-idanhanova.pt/",
    "email": "geral@cm-idanhanova.pt",
    "designacao_contrato": "Aquisição de serviços por lotes, para o fornecimento contínuo de refeições confecionadas e lanches aos alunos das escolas, em refeitórios escolares",
    "descricao": "Aquisição de serviços por lotes, para o fornecimento contínuo de refeições confecionadas e lanches aos alunos das escolas, em refeitórios escolares",
    "preco_base": "195.776,80 EUR",
    "prazo_execucao": "365 DIAS",
    "prazo_apresentacao_propostas": "30-08-2025 23:59",
    "fundos_eu": "Não",
    "plataforma_eletronica": "ACIN",
    "url_procedimento": "https://www.acingov.pt",
    "autor_nome": "Armindo Moreira Palma Jacinto",
    "autor_cargo": "Presidente da Câmara Municipal de Idanha-a-Nova"
  },
  {
    "numero_procedimento": "N/A",
    "entidade": "ESTADO-MAIOR-GENERAL DAS FORÇAS ARMADAS",
    "link": "https://diariodarepublica.pt/dr/detalhe/contrato-publico/22348-932849647",
    "detalhes_completos": "1 - IDENTIFICAÇÃO E CONTACTOS DA ENTIDADE ADJUDICANTE\nDesignação da entidade adjudicante: ESTADO-MAIOR-GENERAL DAS FORÇAS ARMADAS\nNIPC: 600010180\nServiço/Órgão/Pessoa de contacto: DIREÇÃO DE FINANÇAS/ SECÇÃO DE AQUISIÇÕES E CONTRATOS\nEndereço: AVENIDA ILHA DA MADEIRA\nCódigo postal: 1449-004\nLocalidade: Lisboa\nPaís: Portugal\nNUT III: PT170\nDistrito: Lisboa\nConcelho: Lisboa\nFreguesia: Freguesia de Lumiar\nTelefone: 2130100001\nEndereço da Entidade (URL): www.emgfa.pt\nEndereço Eletrónico: DIRFIN_Contratos@emgfa.pt\neDelivery Gateway (URL): https://www.acingov.pt\nFunção da Organização: Adquirente\nNorma jurídica da Entidade Adjudicante: Organismo de direito público\nÁrea de atividade da Autoridade Adjudicante: Serviços públicos das administrações públicas\n\n2 - JORNAL OFICIAL DA UNIÃO EUROPEIA\nO procedimento a que este anúncio diz respeito também é publicitado no Jornal Oficial da União Europeia? Sim\n\n3 - AVISO\nModelo de Anúncio: Concurso público\nData de Envio do Anúncio: 18-08-2025\n\n5 - PROCESSO\nTipo de Procedimento: Concurso público\nPreço base do procedimento: Sim\nValor do preço base do procedimento: 154.000,00 EUR\nProcedimento com lotes? Não\n\n6 - OBJETO DO CONTRATO\nNúmero de referência interna: 2025005854\nDesignação do contrato: Licenciamento e Equipamentos CheckPoint\nDescrição: Licenciamento e Equipamentos CheckPoint\nOpções: Não\nTipo de Contrato Principal: Aquisição de Serviços\nTipo de Contrato: Aquisição de Bens Móveis; Aquisição de Serviços\nClassificação CPV (Vocabulário Comum para os Contratos Públicos)\nObjeto principal\nVocabulário Principal: 72100000\nPreço base s/IVA: 106.547,63 EUR\nObjeto Complementar\nVocabulário Principal: 30230000\nPreço base s/IVA: 47.452,37 EUR\n\n7 - INDICAÇÕES ADICIONAIS\nO contrato envolve aquisição conjunta (satisfação de várias entidades)? Não\nO contrato é adjudicado por uma central de compras? Não\n\n8 - TÉCNICAS\nO concurso destina-se à celebração de um acordo-quadro? Inexistência de acordo-quadro\nÉ utilizado um leilão eletrónico? Não\nÉ adotada uma fase de negociação? Não\nSistema de Aquisição Dinâmico: Inexistência de sistema de aquisição dinâmico\n\n9 - LOCAL DA EXECUÇÃO DO CONTRATO\nLOCAL DA EXECUÇÃO DO CONTRATO (PROCEDIMENTO)\nPaís: Portugal\nNUT III: PT170\nLocalidade: Freguesia de Belém\nDistrito: Lisboa\nConcelho: Lisboa\nFreguesia: Freguesia de Belém\n\n10 - PRAZO DE EXECUÇÃO DO CONTRATO\nPrazo de execução do contrato: 30 DIAS\nPrevisão de renovações: Não\n\n11 - FUNDOS EU\nTêm fundos EU? Não\n\n12 - DOCUMENTOS DE HABILITAÇÃO\nHabilitação para o exercício da atividade profissional: Não\n\n13 - CONDIÇÕES DE APRESENTAÇÃO\nPlataforma eletrónica utilizada pela entidade adjudicante: ACIN\nURL para Apresentação: https://www.acingov.pt\nAdmissibilidade da apresentação de propostas variantes: Não autorizado\nPrazo para apresentação das propostas: 19-09-2025 23:59\nPrazo durante o qual os concorrentes são obrigados a manter as respetivas propostas: 88 dias a contar do termo do prazo para a apresentação das propostas\nApresentação de Catálogo Eletrónico: Permitido\nIndicação de Subcontratação na Proposta: Inexistência de indicação de subcontratação\n\n14 - PRESTAÇÃO DE CAUÇÃO\nPrestação de caução: Não\n\n15 - FORNECIMENTO DAS PEÇAS DO CONCURSO, APRESENTAÇÃO DE PEDIDOS DE PARTICIPAÇÃO E APRESENTAÇÃO DAS PROPOSTAS\nLink para acesso às peças do concurso (URL): https://www.acingov.pt/acingovprod/2/zonaPublica/zona_publica_c/donwloadProcedurePiece/OTM0MjE3\n\n20 - OUTROS REQUISITOS\nInformação sobre contratos reservados. Aplica-se a contratos reservados (54º-A)? Não\n\n21 - CRITÉRIO DE ADJUDICAÇÃO\nMultifator: Não\nMonofator:\nNome: Preço\n\n24 - CONDIÇÕES DO CONTRATO\nFaturação Eletrónica: Permitido\nObrigação de Subcontratação:\nCódigo da Obrigação de Subcontratação: Não é aplicável nenhuma obrigação de subcontratação.\n\n25 - COMPRA PÚBLICA ESTRATÉGICA\nCompra Pública Estratégica: Inexistência de contratação pública estratégica\n\n26 - INFORMAÇÕES ADICIONAIS\nContrato adequado para PME: Sim\nCobertura ACP (Acordo dos Contratos Públicos da Organização Mundial do Comércio): Não\n\n27 - IDENTIFICAÇÃO E CONTACTOS DO ÓRGÃO DE RECURSOS ADMINISTRATIVOS\nDesignação: Direção de Finanças\nEndereço: AVENIDA ILHA DA MADEIRA\nCódigo postal: 1449-004\nLocalidade: Lisboa\nTelefone: 213043000\nFax: \nEndereço eletrónico: DIRFIN_Contratos@emgfa.pt\n\n28 - IDENTIFICAÇÃO DO(S) AUTOR(ES) DE ANÚNCIO\nNome: Brigadeiro General Rui Manuel da Silva Pina\nCargo: Diretor de Finanças\n419444686",
    "nipc": "600010180",
    "distrito": "Lisboa",
    "concelho": "Lisboa",
    "freguesia": "Freguesia de Lumiar",
    "site": "www.emgfa.pt",
    "email": "DIRFIN_Contratos@emgfa.pt",
    "designacao_contrato": "Licenciamento e Equipamentos CheckPoint",
    "descricao": "Licenciamento e Equipamentos CheckPoint",
    "preco_base": "106.547,63 EUR",
    "prazo_execucao": "30 DIAS",
    "prazo_apresentacao_propostas": "19-09-2025 23:59",
    "fundos_eu": "Não",
    "plataforma_eletronica": "ACIN",
    "url_procedimento": "https://www.acingov.pt",
    "autor_nome": "Brigadeiro General Rui Manuel da Silva Pina",
    "autor_cargo": "Diretor de Finanças"
  },
  {
    "numero_procedimento": "N/A",
    "entidade": "Município de Vila Nova de Foz Côa",
    "link": "https://diariodarepublica.pt/dr/detalhe/contrato-publico/22353-932849651",
    "detalhes_completos": "1 - IDENTIFICAÇÃO E CONTACTOS DA ENTIDADE ADJUDICANTE\nDesignação da entidade adjudicante: Município de Vila Nova de Foz Côa\nNIPC: 506829197\nServiço/Órgão/Pessoa de contacto: Presidente da Câmara Municipal\nEndereço: Praça do Município,\nCódigo postal: 5150-642\nLocalidade: Vila Nova de Foz Côa\nPaís: Portugal\nNUT III: PT11D\nDistrito: Guarda\nConcelho: Vila Nova de Foz Coa\nFreguesia: Todas\nTelefone: 279760400\nFax: 279760438\nEndereço da Entidade (URL): http://cm-fozcoa.pt/\nEndereço Eletrónico: correio@cm-fozcoa.pt\neDelivery Gateway (URL): https://www.acingov.pt\nFunção da Organização: Adquirente\nNorma jurídica da Entidade Adjudicante: Organismo de direito público\nÁrea de atividade da Autoridade Adjudicante: Serviços públicos das administrações públicas\n\n2 - JORNAL OFICIAL DA UNIÃO EUROPEIA\nO procedimento a que este anúncio diz respeito também é publicitado no Jornal Oficial da União Europeia? Não\n\n3 - AVISO\nModelo de Anúncio: Concurso público\nData de Envio do Anúncio: 20-08-2025\n\n5 - PROCESSO\nTipo de Procedimento: Concurso público\nPreço base do procedimento: Sim\nValor do preço base do procedimento: 96.860,00 EUR\nProcedimento com lotes? Sim\nNº Máx. de Lotes Autorizado: 6\nNúmero máximo de lotes que podem ser adjudicados a um concorrente: 6\n\n6 - OBJETO DO CONTRATO\nNúmero de referência interna: CP/49/2025\nDesignação do contrato: AQUISIÇÃO DE SERVIÇOS TRANSPORTE DE ALUNOS DO ENSINO PRÉ-ESCOLAR E 1º CICLO DO ENSINO BÁSICO E OUTROS para o Ano Letivo 2025/2026\nDescrição: AQUISIÇÃO DE SERVIÇOS TRANSPORTE DE ALUNOS DO ENSINO PRÉ-ESCOLAR E 1º CICLO DO ENSINO BÁSICO E OUTROS para o Ano Letivo 2025/2026\nTipo de Contrato Principal: Aquisição de Serviços\nTipo de Contrato: Aquisição de Serviços\nClassificação CPV (Vocabulário Comum para os Contratos Públicos)\nObjeto principal\nVocabulário Principal: 60130000\nPreço base s/IVA: 96.860,00 EUR\nLotes: \nNº: LOT-0001\nDescrição do Lote: Circuito 1 - Transportes de Alunos do Ensino Pré-Escolar e 1ºciclo do Ensino Básico de Arnozelo Numão e Seixas, para Freixo de Numão\nPreço base s/IVA: 32.743,00 EUR\nClassificação CPV (Vocabulário Comum para os Contratos Públicos)\nObjeto principal\nVocabulário Principal: 60130000\nNº: LOT-0002\nDescrição do Lote: Circuito 2A - Transporte de Alunos do Jardim-De-Infância e 1.º CEB nos períodos de atividades complementares/ferias de Mós, Santo Amaro, Cortes da Veiga, Pocinho para Vila Nova de Foz Côa\nPreço base s/IVA: 5.056,00 EUR\nClassificação CPV (Vocabulário Comum para os Contratos Públicos)\nObjeto principal\nVocabulário Principal: 60130000\nNº: LOT-0003\nDescrição do Lote: Circuito 3A - Transporte de Alunos do Jardim-De-Infância e 1.º CEB nos períodos de atividades complementares/ferias de Almendra, Castelo Melhor, Orgal para Vila Nova de Foz Côa\nPreço base s/IVA: 12.160,00 EUR\nClassificação CPV (Vocabulário Comum para os Contratos Públicos)\nObjeto principal\nVocabulário Principal: 60130000\nNº: LOT-0004\nDescrição do Lote: Circuito 4 - Transporte de Alunos do Ensino do 2º, 3º Ciclo e Secundário de Arnozelo, para Numão\nPreço base s/IVA: 4.890,00 EUR\nClassificação CPV (Vocabulário Comum para os Contratos Públicos)\nObjeto principal\nVocabulário Principal: 60130000\nNº: LOT-0005\nDescrição do Lote: Circuito 5A - Transporte de Alunos do Jardim-De-Infância e 1.º CEB nos períodos de atividades complementares/ferias de Santa Comba, Chãs e Muxagata, para Vila Nova de Foz Côa\nPreço base s/IVA: 6.400,00 EUR\nClassificação CPV (Vocabulário Comum para os Contratos Públicos)\nObjeto principal\nVocabulário Principal: 60130000\nNº: LOT-0006\nDescrição do Lote: Circuito 6 - Transporte de Alunos do Ensino do Pré-escolar e 1º Ciclo de Horta, Sequeira, Sebadelhe e Touça, para Freixo de Numão\nPreço base s/IVA: 35.611,00 EUR\nClassificação CPV (Vocabulário Comum para os Contratos Públicos)\nObjeto principal\nVocabulário Principal: 60130000\n\n7 - INDICAÇÕES ADICIONAIS\nO contrato envolve aquisição conjunta (satisfação de várias entidades)? Não\nO contrato é adjudicado por uma central de compras? Não\n\n8 - TÉCNICAS\nO concurso destina-se à celebração de um acordo-quadro? Inexistência de acordo-quadro\nÉ utilizado um leilão eletrónico? Não\nÉ adotada uma fase de negociação? Não\nSistema de Aquisição Dinâmico: Inexistência de sistema de aquisição dinâmico\n\n9 - LOCAL DA EXECUÇÃO DO CONTRATO\nLOCAL DA EXECUÇÃO DO CONTRATO (PROCEDIMENTO)\nPaís: Portugal\nNUT III: PT11D\nLocalidade: Vila Nova de Foz Côa\nDistrito: Guarda\nConcelho: Vila Nova de Foz Coa\nFreguesia: Todas\nLOCAL DA EXECUÇÃO DO CONTRATO (LOTE)\nIdentificador do Lote: LOT-0001; LOT-0002; LOT-0003; LOT-0004; LOT-0005; LOT-0006\nPaís: Portugal\nNUT III: PT11D\nLocalidade: Vila Nova de Foz Côa\nDistrito: Guarda\nConcelho: Vila Nova de Foz Coa\nFreguesia: Todas\n\n10 - PRAZO DE EXECUÇÃO DO CONTRATO\nIdentificador do Lote: LOT-0001; LOT-0002; LOT-0003; LOT-0004; LOT-0005; LOT-0006\nData de Início: 01-09-2025\nData de Fim: 14-08-2026\nPrevisão de renovações: Não\n\n11 - FUNDOS EU\nIdentificador do Lote: LOT-0001; LOT-0002; LOT-0003; LOT-0004; LOT-0005; LOT-0006\nTêm fundos EU? Não\n\n12 - DOCUMENTOS DE HABILITAÇÃO\nHabilitação para o exercício da atividade profissional: Não\n\n13 - CONDIÇÕES DE APRESENTAÇÃO\nPlataforma eletrónica utilizada pela entidade adjudicante: ACIN\nURL para Apresentação: https://www.acingov.pt\nAdmissibilidade da apresentação de propostas variantes: Não autorizado\nPrazo para apresentação das propostas: 28-08-2025 17:30\nPrazo durante o qual os concorrentes são obrigados a manter as respetivas propostas: 66 dias a contar do termo do prazo para a apresentação das propostas\nIndicação de Subcontratação na Proposta: Inexistência de indicação de subcontratação\n\n14 - PRESTAÇÃO DE CAUÇÃO\nPrestação de caução: Não\n\n15 - FORNECIMENTO DAS PEÇAS DO CONCURSO, APRESENTAÇÃO DE PEDIDOS DE PARTICIPAÇÃO E APRESENTAÇÃO DAS PROPOSTAS\nLink para acesso às peças do concurso (URL): https://www.acingov.pt/acingovprod/2/zonaPublica/zona_publica_c/donwloadProcedurePiece/OTMxMTk5\n\n20 - OUTROS REQUISITOS\nIdentificador do Lote: LOT-0001; LOT-0002; LOT-0003; LOT-0004; LOT-0005; LOT-0006\nInformação sobre contratos reservados. Aplica-se a contratos reservados (54º-A)? Não\n\n21 - CRITÉRIO DE ADJUDICAÇÃO\nO Critério de adjudicação é diferenciado por lote? Não\nMultifator: Não\nMonofator:\nNome: Preço\n\n24 - CONDIÇÕES DO CONTRATO\nIdentificador do Lote: LOT-0001; LOT-0002; LOT-0003; LOT-0004; LOT-0005; LOT-0006\nFaturação Eletrónica: Permitido\nObrigação de Subcontratação:\nCódigo da Obrigação de Subcontratação: Não é aplicável nenhuma obrigação de subcontratação.\n\n25 - COMPRA PÚBLICA ESTRATÉGICA\nCompra Pública Estratégica: Inexistência de contratação pública estratégica\n\n26 - INFORMAÇÕES ADICIONAIS\nIdentificador do Lote: LOT-0001; LOT-0002; LOT-0003; LOT-0004; LOT-0005; LOT-0006\nContrato adequado para PME: Sim\nCobertura ACP (Acordo dos Contratos Públicos da Organização Mundial do Comércio): Não\n\n27 - IDENTIFICAÇÃO E CONTACTOS DO ÓRGÃO DE RECURSOS ADMINISTRATIVOS\nDesignação: Divisão Financeira e Administrativa\nEndereço: Praça do Município\nCódigo postal: 5150-642\nLocalidade: Vila Nova de Foz Côa\nTelefone: 279760400\nFax: \nEndereço eletrónico: correio@cm-fozcoa.pt\n\n28 - IDENTIFICAÇÃO DO(S) AUTOR(ES) DE ANÚNCIO\nNome: Dr. João Paulo Lucas Donas Botto Sousa\nCargo: Presidente da Câmara Municipal de Vila Nova de Foz Côa\n419452591",
    "nipc": "506829197",
    "distrito": "Guarda",
    "concelho": "Vila Nova de Foz Coa",
    "freguesia": "Todas",
    "site": "http://cm-fozcoa.pt/",
    "email": "correio@cm-fozcoa.pt",
    "designacao_contrato": "AQUISIÇÃO DE SERVIÇOS TRANSPORTE DE ALUNOS DO ENSINO PRÉ-ESCOLAR E 1º CICLO DO ENSINO BÁSICO E OUTROS para o Ano Letivo 2025/2026",
    "descricao": "AQUISIÇÃO DE SERVIÇOS TRANSPORTE DE ALUNOS DO ENSINO PRÉ-ESCOLAR E 1º CICLO DO ENSINO BÁSICO E OUTROS para o Ano Letivo 2025/2026",
    "preco_base": "96.860,00 EUR",
    "prazo_execucao": null,
    "prazo_apresentacao_propostas": "28-08-2025 17:30",
    "fundos_eu": "Não",
    "plataforma_eletronica": "ACIN",
    "url_procedimento": "https://www.acingov.pt",
    "autor_nome": "Dr. João Paulo Lucas Donas Botto Sousa",
    "autor_cargo": "Presidente da Câmara Municipal de Vila Nova de Foz Côa"
  },
  {
    "numero_procedimento": "N/A",
    "entidade": "Município das Lajes do Pico",
    "link": "https://diariodarepublica.pt/dr/detalhe/contrato-publico/22355-932849660",
    "detalhes_completos": "Alteração do Anúncio de procedimento n.º 21830/2025, de 2025-08-13, com o ID 419420393\n\n1 - IDENTIFICAÇÃO E CONTACTOS DA ENTIDADE ADJUDICANTE\nDesignação da entidade adjudicante: Município das Lajes do Pico\nNIPC: 512074143\nServiço/Órgão/Pessoa de contacto: Setor de Aprovisionamento/Contratação Pública\nEndereço: Rua de São Francisco\nCódigo postal: 9930-135\nLocalidade: Lajes do Pico\nPaís: Portugal\nNUT III: PT200\nDistrito: Região Autónoma dos Açores\nConcelho: Lajes do Pico\nFreguesia: Freguesia de Lajes do Pico\nTelefone: 292679700\nEndereço da Entidade (URL): http://cm-lajesdopico.pt/\nEndereço Eletrónico: aprovisionamento.cmlp@gmail.com\neDelivery Gateway (URL): https://www.acingov.pt\nFunção da Organização: Adquirente\nNorma jurídica da Entidade Adjudicante: Organismo de direito público\nÁrea de atividade da Autoridade Adjudicante: Serviços públicos das administrações públicas\n\n2 - JORNAL OFICIAL DA UNIÃO EUROPEIA\nO procedimento a que este anúncio diz respeito também é publicitado no Jornal Oficial da União Europeia? Não\n\n3 - AVISO\nModelo de Anúncio: Concurso público\nData de Envio do Anúncio: 20-08-2025\n\n5 - PROCESSO\nTipo de Procedimento: Concurso público\nPreço base do procedimento: Sim\nValor do preço base do procedimento: 81.600,00 EUR\nProcedimento com lotes? Sim\nNº Máx. de Lotes Autorizado: 2\nNúmero máximo de lotes que podem ser adjudicados a um concorrente: 2\n\n6 - OBJETO DO CONTRATO\nNúmero de referência interna: CP/16/CMLP/2025\nDesignação do contrato: Contratação de Aluguer Operacional de Duas Viaturas Ligeiras de Mercadoria para a Câmara Municipal das Lajes do Pico\nDescrição: Contratação de Aluguer Operacional de Duas Viaturas Ligeiras de Mercadoria para a Câmara Municipal das Lajes do Pico\nTipo de Contrato Principal: Locação de Bens Móveis\nTipo de Contrato: Locação de Bens Móveis\nClassificação CPV (Vocabulário Comum para os Contratos Públicos)\nObjeto principal\nVocabulário Principal: 34130000\nPreço base s/IVA: 81.600,00 EUR\nLotes: \nNº: LOT-0001\nDescrição do Lote: Viatura Comercial de 3 lugares com cabine fechada\nPreço base s/IVA: 31.200,00 EUR\nClassificação CPV (Vocabulário Comum para os Contratos Públicos)\nObjeto principal\nVocabulário Principal: 34130000\nNº: LOT-0002\nDescrição do Lote: Viatura 4x4 de 5 pessoas com caixa aberta de madeira\nPreço base s/IVA: 50.400,00 EUR\nClassificação CPV (Vocabulário Comum para os Contratos Públicos)\nObjeto principal\nVocabulário Principal: 34130000\n\n7 - INDICAÇÕES ADICIONAIS\nO contrato envolve aquisição conjunta (satisfação de várias entidades)? Não\nO contrato é adjudicado por uma central de compras? Não\n\n8 - TÉCNICAS\nO concurso destina-se à celebração de um acordo-quadro? Inexistência de acordo-quadro\nÉ utilizado um leilão eletrónico? Não\nÉ adotada uma fase de negociação? Não\nSistema de Aquisição Dinâmico: Inexistência de sistema de aquisição dinâmico\n\n9 - LOCAL DA EXECUÇÃO DO CONTRATO\nLOCAL DA EXECUÇÃO DO CONTRATO (PROCEDIMENTO)\nPaís: Portugal\nNUT III: PT200\nLocalidade: Freguesia de Lajes do Pico\nDistrito: Região Autónoma dos Açores\nConcelho: Lajes do Pico\nFreguesia: Freguesia de Lajes do Pico\nLOCAL DA EXECUÇÃO DO CONTRATO (LOTE)\nIdentificador do Lote: LOT-0001; LOT-0002\nPaís: Portugal\nNUT III: PT200\nLocalidade: Freguesia de Lajes do Pico\nDistrito: Região Autónoma dos Açores\nConcelho: Lajes do Pico\nFreguesia: Freguesia de Lajes do Pico\n\n10 - PRAZO DE EXECUÇÃO DO CONTRATO\nIdentificador do Lote: LOT-0001; LOT-0002\nPrazo de execução do contrato: 48 MESES\nPrevisão de renovações: Não\n\n11 - FUNDOS EU\nIdentificador do Lote: LOT-0001; LOT-0002\nTêm fundos EU? Não\n\n12 - DOCUMENTOS DE HABILITAÇÃO\nHabilitação para o exercício da atividade profissional: Não\n\n13 - CONDIÇÕES DE APRESENTAÇÃO\nPlataforma eletrónica utilizada pela entidade adjudicante: ACIN\nURL para Apresentação: https://www.acingov.pt\nAdmissibilidade da apresentação de propostas variantes: Não autorizado\nPrazo para apresentação das propostas: 11-09-2025 23:59\nPrazo durante o qual os concorrentes são obrigados a manter as respetivas propostas: 66 dias a contar do termo do prazo para a apresentação das propostas\nIndicação de Subcontratação na Proposta: Inexistência de indicação de subcontratação\n\n14 - PRESTAÇÃO DE CAUÇÃO\nPrestação de caução: Não\n\n15 - FORNECIMENTO DAS PEÇAS DO CONCURSO, APRESENTAÇÃO DE PEDIDOS DE PARTICIPAÇÃO E APRESENTAÇÃO DAS PROPOSTAS\nLink para acesso às peças do concurso (URL): https://www.acingov.pt/acingovprod/2/zonaPublica/zona_publica_c/donwloadProcedurePiece/OTMyNTU0\n\n20 - OUTROS REQUISITOS\nIdentificador do Lote: LOT-0001; LOT-0002\nInformação sobre contratos reservados. Aplica-se a contratos reservados (54º-A)? Não\n\n21 - CRITÉRIO DE ADJUDICAÇÃO\nO Critério de adjudicação é diferenciado por lote? Não\nMultifator: Não\nMonofator:\nNome: Preço\n\n24 - CONDIÇÕES DO CONTRATO\nIdentificador do Lote: LOT-0001; LOT-0002\nFaturação Eletrónica: Permitido\nObrigação de Subcontratação:\nCódigo da Obrigação de Subcontratação: Não é aplicável nenhuma obrigação de subcontratação.\n\n25 - COMPRA PÚBLICA ESTRATÉGICA\nCompra Pública Estratégica: Inexistência de contratação pública estratégica\n\n26 - INFORMAÇÕES ADICIONAIS\nIdentificador do Lote: LOT-0001; LOT-0002\nContrato adequado para PME: Não\nCobertura ACP (Acordo dos Contratos Públicos da Organização Mundial do Comércio): Não\n\n27 - IDENTIFICAÇÃO E CONTACTOS DO ÓRGÃO DE RECURSOS ADMINISTRATIVOS\nDesignação: Câmara Municipal das Lajes do Pico\nEndereço: Rua de São Francisco\nCódigo postal: 9930-135\nLocalidade: Lajes do Pico\nTelefone: 292679700\nFax: \nEndereço eletrónico: geral@cm-lajesdopico.pt\nPrazo de interposição do recurso: 5 dias\n\n28 - IDENTIFICAÇÃO DO(S) AUTOR(ES) DE ANÚNCIO\nNome: Amílcar Sérgio Oliveira Goulart\nCargo: Vereador da Câmara Municipal das Lajes do Pico\n\n29 - ALTERAÇÃO\nMotivo da Alteração: Correção pelo adquirente\nIdentificador da Versão do Anúncio a Alterar: 3479d1a4-c48e-49ff-9bd4-2b7cc0a4819b-02\nIdentificador das Secções Alteradas do Anúncio Anterior: Condições de Apresentação\nDescrição das Alterações: Alteração de condições constantes do Caderno de Encargos\nAlteração dos Documentos do Concurso: Sim\nData de alteração dos documentos do concurso: 20-08-2025\n419451992",
    "nipc": "512074143",
    "distrito": "Região Autónoma dos Açores",
    "concelho": "Lajes do Pico",
    "freguesia": "Freguesia de Lajes do Pico",
    "site": "http://cm-lajesdopico.pt/",
    "email": "aprovisionamento.cmlp@gmail.com",
    "designacao_contrato": "Contratação de Aluguer Operacional de Duas Viaturas Ligeiras de Mercadoria para a Câmara Municipal das Lajes do Pico",
    "descricao": "Contratação de Aluguer Operacional de Duas Viaturas Ligeiras de Mercadoria para a Câmara Municipal das Lajes do Pico",
    "preco_base": "81.600,00 EUR",
    "prazo_execucao": "48 MESES",
    "prazo_apresentacao_propostas": "11-09-2025 23:59",
    "fundos_eu": "Não",
    "plataforma_eletronica": "ACIN",
    "url_procedimento": "https://www.acingov.pt",
    "autor_nome": "Amílcar Sérgio Oliveira Goulart",
    "autor_cargo": "Vereador da Câmara Municipal das Lajes do Pico"
  },
  {
    "numero_procedimento": "N/A",
    "entidade": "Município de Ílhavo",
    "link": "https://diariodarepublica.pt/dr/detalhe/contrato-publico/22356-932849661",
    "detalhes_completos": "1 - IDENTIFICAÇÃO E CONTACTOS DA ENTIDADE ADJUDICANTE\nDesignação da entidade adjudicante: Município de Ílhavo\nNIPC: 506920887\nServiço/Órgão/Pessoa de contacto: Divisão da Administração Geral\nEndereço: Avenida 25 de Abril\nCódigo postal: 3830-044\nLocalidade: Ílhavo\nPaís: Portugal\nNUT III: PT16D\nDistrito: Aveiro\nConcelho: Ílhavo\nFreguesia: Todas\nTelefone: 234329600\nFax: 234329601\nEndereço da Entidade (URL): www.cm-ilhavo.pt\nEndereço Eletrónico: geralcmi@cm-ilhavo.pt\neDelivery Gateway (URL): https://www.acingov.pt\nFunção da Organização: Adquirente\nSubfunção da Organização: Organização que recebe as propostas\nNorma jurídica da Entidade Adjudicante: Organismo de direito público\nÁrea de atividade da Autoridade Adjudicante: Serviços públicos das administrações públicas\n\n2 - JORNAL OFICIAL DA UNIÃO EUROPEIA\nO procedimento a que este anúncio diz respeito também é publicitado no Jornal Oficial da União Europeia? Sim\n\n3 - AVISO\nModelo de Anúncio: Concurso público\nData de Envio do Anúncio: 18-08-2025\n\n5 - PROCESSO\nTipo de Procedimento: Concurso público\nPreço base do procedimento: Sim\nValor do preço base do procedimento: 282.954,24 EUR\nProcedimento com lotes? Sim\nNº Máx. de Lotes Autorizado: 4\nNúmero máximo de lotes que podem ser adjudicados a um concorrente: 1\n\n6 - OBJETO DO CONTRATO\nNúmero de referência interna: 11/H/S/25\nDesignação do contrato: Prestação de serviços em regime de avença, para apoio nas atividades da Equipa Multidisciplinar de Apoio à Comunidade Educativa (EMACE)\nDescrição: Prestação de serviços em regime de avença, para apoio nas atividades da Equipa Multidisciplinar de Apoio à Comunidade Educativa (EMACE)\nOpções: Não\nTipo de Contrato Principal: Aquisição de Serviços\nTipo de Contrato: Aquisição de Serviços\nClassificação CPV (Vocabulário Comum para os Contratos Públicos)\nObjeto principal\nVocabulário Principal: 85000000\nPreço base s/IVA: 282.954,24 EUR\nLotes: \nNº: LOT-0001\nDescrição do Lote: Educador(a) Social\nPreço base s/IVA: 70.738,56 EUR\nClassificação CPV (Vocabulário Comum para os Contratos Públicos)\nObjeto principal\nVocabulário Principal: 85000000\nNº: LOT-0002\nDescrição do Lote: Psicólogo(a)\nPreço base s/IVA: 70.738,56 EUR\nClassificação CPV (Vocabulário Comum para os Contratos Públicos)\nObjeto principal\nVocabulário Principal: 85000000\nNº: LOT-0003\nDescrição do Lote: Assistente Social\nPreço base s/IVA: 70.738,56 EUR\nClassificação CPV (Vocabulário Comum para os Contratos Públicos)\nObjeto principal\nVocabulário Principal: 85000000\nNº: LOT-0004\nDescrição do Lote: Terapeuta da Fala\nPreço base s/IVA: 70.738,56 EUR\nClassificação CPV (Vocabulário Comum para os Contratos Públicos)\nObjeto principal\nVocabulário Principal: 85000000\n\n7 - INDICAÇÕES ADICIONAIS\nO contrato envolve aquisição conjunta (satisfação de várias entidades)? Não\nO contrato é adjudicado por uma central de compras? Não\n\n8 - TÉCNICAS\nO concurso destina-se à celebração de um acordo-quadro? Inexistência de acordo-quadro\nÉ utilizado um leilão eletrónico? Não\nÉ adotada uma fase de negociação? Não\nSistema de Aquisição Dinâmico: Inexistência de sistema de aquisição dinâmico\n\n9 - LOCAL DA EXECUÇÃO DO CONTRATO\nLOCAL DA EXECUÇÃO DO CONTRATO (PROCEDIMENTO)\nPaís: Portugal\nNUT III: PT16D\nLocalidade: Ílhavo\nDistrito: Aveiro\nConcelho: Ílhavo\nFreguesia: Todas\nLOCAL DA EXECUÇÃO DO CONTRATO (LOTE)\nIdentificador do Lote: LOT-0001; LOT-0002; LOT-0003; LOT-0004\nPaís: Portugal\nNUT III: PT16D\nLocalidade: Ílhavo\nDistrito: Aveiro\nConcelho: Ílhavo\nFreguesia: Todas\n\n10 - PRAZO DE EXECUÇÃO DO CONTRATO\nIdentificador do Lote: LOT-0001; LOT-0002; LOT-0003; LOT-0004\nPrazo de execução do contrato: 36 MESES\nPrevisão de renovações: Não\n\n11 - FUNDOS EU\nIdentificador do Lote: LOT-0001; LOT-0002; LOT-0003; LOT-0004\nTêm fundos EU? Não\n\n12 - DOCUMENTOS DE HABILITAÇÃO\nHabilitação para o exercício da atividade profissional: Não\n\n13 - CONDIÇÕES DE APRESENTAÇÃO\nPlataforma eletrónica utilizada pela entidade adjudicante: ACIN\nURL para Apresentação: https://www.acingov.pt\nAdmissibilidade da apresentação de propostas variantes: Não autorizado\nPrazo para apresentação das propostas: 22-09-2025 17:00\nPrazo durante o qual os concorrentes são obrigados a manter as respetivas propostas: 66 dias a contar do termo do prazo para a apresentação das propostas\nApresentação de Catálogo Eletrónico: Permitido\nIndicação de Subcontratação na Proposta: Inexistência de indicação de subcontratação\n\n14 - PRESTAÇÃO DE CAUÇÃO\nPrestação de caução: Não\n\n15 - FORNECIMENTO DAS PEÇAS DO CONCURSO, APRESENTAÇÃO DE PEDIDOS DE PARTICIPAÇÃO E APRESENTAÇÃO DAS PROPOSTAS\nLink para acesso às peças do concurso (URL): https://www.acingov.pt/acingovprod/2/zonaPublica/zona_publica_c/donwloadProcedurePiece/OTMzNDcz\n\n20 - OUTROS REQUISITOS\nIdentificador do Lote: LOT-0001; LOT-0002; LOT-0003; LOT-0004\nInformação sobre contratos reservados. Aplica-se a contratos reservados (54º-A)? Não\n\n21 - CRITÉRIO DE ADJUDICAÇÃO\nO Critério de adjudicação é diferenciado por lote? Não\nMultifator: Sim\nFator: \nNome: Outros\nOutro Nome: Outros\nPonderação: 100%\nSubfatores: Não\n\n24 - CONDIÇÕES DO CONTRATO\nIdentificador do Lote: LOT-0001; LOT-0002; LOT-0003; LOT-0004\nFaturação Eletrónica: Permitido\nObrigação de Subcontratação:\nCódigo da Obrigação de Subcontratação: Não é aplicável nenhuma obrigação de subcontratação.\n\n25 - COMPRA PÚBLICA ESTRATÉGICA\nCompra Pública Estratégica: Inexistência de contratação pública estratégica\n\n26 - INFORMAÇÕES ADICIONAIS\nIdentificador do Lote: LOT-0001; LOT-0002; LOT-0003; LOT-0004\nContrato adequado para PME: Não\nCobertura ACP (Acordo dos Contratos Públicos da Organização Mundial do Comércio): Não\n\n27 - IDENTIFICAÇÃO E CONTACTOS DO ÓRGÃO DE RECURSOS ADMINISTRATIVOS\nDesignação: Presidente da Câmara Municipal\nEndereço: Av. 25 de Abril\nCódigo postal: 3830-044\nLocalidade: Ílhavo\nTelefone: 234329600\nFax: \nEndereço eletrónico: geralcmi@cm-ilhavo.pt\n\n28 - IDENTIFICAÇÃO DO(S) AUTOR(ES) DE ANÚNCIO\nNome: João António Filipe Campolargo\nCargo: Presidente da Câmara Municipal\n419441842",
    "nipc": "506920887",
    "distrito": "Aveiro",
    "concelho": "Ílhavo",
    "freguesia": "Todas",
    "site": "www.cm-ilhavo.pt",
    "email": "geralcmi@cm-ilhavo.pt",
    "designacao_contrato": "Prestação de serviços em regime de avença, para apoio nas atividades da Equipa Multidisciplinar de Apoio à Comunidade Educativa (EMACE)",
    "descricao": "Prestação de serviços em regime de avença, para apoio nas atividades da Equipa Multidisciplinar de Apoio à Comunidade Educativa (EMACE)",
    "preco_base": "282.954,24 EUR",
    "prazo_execucao": "36 MESES",
    "prazo_apresentacao_propostas": "22-09-2025 17:00",
    "fundos_eu": "Não",
    "plataforma_eletronica": "ACIN",
    "url_procedimento": "https://www.acingov.pt",
    "autor_nome": "João António Filipe Campolargo",
    "autor_cargo": "Presidente da Câmara Municipal"
  },
  {
    "numero_procedimento": "N/A",
    "entidade": "ESTADO-MAIOR-GENERAL DAS FORÇAS ARMADAS",
    "link": "https://diariodarepublica.pt/dr/detalhe/contrato-publico/22358-932849662",
    "detalhes_completos": "Alteração do Anúncio de procedimento n.º 19213/2025, de 2025-07-18, com o ID 419312703\n\n1 - IDENTIFICAÇÃO E CONTACTOS DA ENTIDADE ADJUDICANTE\nDesignação da entidade adjudicante: ESTADO-MAIOR-GENERAL DAS FORÇAS ARMADAS\nNIPC: 600010180\nServiço/Órgão/Pessoa de contacto: DIREÇÃO DE FINANÇAS / SECÇÃO DE AQUISIÇÕES E CONTRATOS\nEndereço: AVENIDA ILHA DA MADEIRA\nCódigo postal: 1449-004\nLocalidade: Lisboa\nPaís: Portugal\nNUT III: PT170\nDistrito: Lisboa\nConcelho: Lisboa\nFreguesia: Freguesia de Lumiar\nTelefone: 2130100001\nEndereço da Entidade (URL): www.emgfa.pt\nEndereço Eletrónico: DIRFIN_Contratos@emgfa.pt\neDelivery Gateway (URL): https://www.acingov.pt\nFunção da Organização: Adquirente\nNorma jurídica da Entidade Adjudicante: Organismo de direito público\nÁrea de atividade da Autoridade Adjudicante: Serviços públicos das administrações públicas\n\n2 - JORNAL OFICIAL DA UNIÃO EUROPEIA\nO procedimento a que este anúncio diz respeito também é publicitado no Jornal Oficial da União Europeia? Sim\n\n3 - AVISO\nModelo de Anúncio: Concurso público\nData de Envio do Anúncio: 18-08-2025\n\n5 - PROCESSO\nTipo de Procedimento: Concurso público\nPreço base do procedimento: Sim\nValor do preço base do procedimento: 143.408,00 EUR\nProcedimento com lotes? Sim\nNº Máx. de Lotes Autorizado: 2\nNúmero máximo de lotes que podem ser adjudicados a um concorrente: 2\n\n6 - OBJETO DO CONTRATO\nNúmero de referência interna: 2025005756\nDesignação do contrato: Equipamentos de rede para telecomunicações\nDescrição: Equipamentos de rede para telecomunicações\nOpções: Não\nTipo de Contrato Principal: Aquisição de Bens Móveis\nTipo de Contrato: Aquisição de Bens Móveis\nClassificação CPV (Vocabulário Comum para os Contratos Públicos)\nObjeto principal\nVocabulário Principal: 32500000\nPreço base s/IVA: 128.197,00 EUR\nObjeto Complementar\nVocabulário Principal: 32570000\nPreço base s/IVA: 15.211,00 EUR\nLotes: \nNº: LOT-0001\nDescrição do Lote: Routers e amplificador de sinal de fibra ótica\nPreço base s/IVA: 128.197,00 EUR\nClassificação CPV (Vocabulário Comum para os Contratos Públicos)\nObjeto principal\nVocabulário Principal: 32500000\nNº: LOT-0002\nDescrição do Lote: Retificador de energia, alimentadores DC e UPS\nPreço base s/IVA: 15.211,00 EUR\nClassificação CPV (Vocabulário Comum para os Contratos Públicos)\nObjeto principal\nVocabulário Principal: 32570000\n\n7 - INDICAÇÕES ADICIONAIS\nO contrato envolve aquisição conjunta (satisfação de várias entidades)? Não\nO contrato é adjudicado por uma central de compras? Não\n\n8 - TÉCNICAS\nO concurso destina-se à celebração de um acordo-quadro? Inexistência de acordo-quadro\nÉ utilizado um leilão eletrónico? Não\nÉ adotada uma fase de negociação? Não\nSistema de Aquisição Dinâmico: Inexistência de sistema de aquisição dinâmico\n\n9 - LOCAL DA EXECUÇÃO DO CONTRATO\nLOCAL DA EXECUÇÃO DO CONTRATO (PROCEDIMENTO)\nPaís: Portugal\nNUT III: PT170\nLocalidade: Freguesia de Belém\nDistrito: Lisboa\nConcelho: Lisboa\nFreguesia: Freguesia de Belém\nLOCAL DA EXECUÇÃO DO CONTRATO (LOTE)\nIdentificador do Lote: LOT-0001; LOT-0002\nPaís: Portugal\nNUT III: PT170\nLocalidade: Freguesia de Belém\nDistrito: Lisboa\nConcelho: Lisboa\nFreguesia: Freguesia de Belém\n\n10 - PRAZO DE EXECUÇÃO DO CONTRATO\nIdentificador do Lote: LOT-0001; LOT-0002\nPrazo de execução do contrato: 30 DIAS\nPrevisão de renovações: Não\n\n11 - FUNDOS EU\nIdentificador do Lote: LOT-0001; LOT-0002\nTêm fundos EU? Não\n\n12 - DOCUMENTOS DE HABILITAÇÃO\nHabilitação para o exercício da atividade profissional: Não\n\n13 - CONDIÇÕES DE APRESENTAÇÃO\nPlataforma eletrónica utilizada pela entidade adjudicante: ACIN\nURL para Apresentação: https://www.acingov.pt\nAdmissibilidade da apresentação de propostas variantes: Não autorizado\nPrazo para apresentação das propostas: 04-09-2025 23:59\nPrazo durante o qual os concorrentes são obrigados a manter as respetivas propostas: 88 dias a contar do termo do prazo para a apresentação das propostas\nApresentação de Catálogo Eletrónico: Permitido\nIndicação de Subcontratação na Proposta: Inexistência de indicação de subcontratação\n\n14 - PRESTAÇÃO DE CAUÇÃO\nPrestação de caução: Não\n\n15 - FORNECIMENTO DAS PEÇAS DO CONCURSO, APRESENTAÇÃO DE PEDIDOS DE PARTICIPAÇÃO E APRESENTAÇÃO DAS PROPOSTAS\nLink para acesso às peças do concurso (URL): https://www.acingov.pt/acingovprod/2/zonaPublica/zona_publica_c/donwloadProcedurePiece/OTIwOTg5\n\n20 - OUTROS REQUISITOS\nIdentificador do Lote: LOT-0001; LOT-0002\nInformação sobre contratos reservados. Aplica-se a contratos reservados (54º-A)? Não\n\n21 - CRITÉRIO DE ADJUDICAÇÃO\nO Critério de adjudicação é diferenciado por lote? Não\nMultifator: Não\nMonofator:\nNome: Preço\n\n24 - CONDIÇÕES DO CONTRATO\nIdentificador do Lote: LOT-0001; LOT-0002\nFaturação Eletrónica: Permitido\nObrigação de Subcontratação:\nCódigo da Obrigação de Subcontratação: Não é aplicável nenhuma obrigação de subcontratação.\n\n25 - COMPRA PÚBLICA ESTRATÉGICA\nCompra Pública Estratégica: Inexistência de contratação pública estratégica\n\n26 - INFORMAÇÕES ADICIONAIS\nIdentificador do Lote: LOT-0001; LOT-0002\nContrato adequado para PME: Sim\nCobertura ACP (Acordo dos Contratos Públicos da Organização Mundial do Comércio): Não\n\n27 - IDENTIFICAÇÃO E CONTACTOS DO ÓRGÃO DE RECURSOS ADMINISTRATIVOS\nDesignação: DIRECÇÃO DE FINANÇAS\nEndereço: AVENIDA ILHA DA MADEIRA\nCódigo postal: 1449-004\nLocalidade: Lisboa\nTelefone: 213043000\nFax: \nEndereço eletrónico: DIRFIN_Contratos@emgfa.pt\n\n28 - IDENTIFICAÇÃO DO(S) AUTOR(ES) DE ANÚNCIO\nNome: Brigadeiro General Rui Manuel da Silva Pina\nCargo: Diretor de Finanças\n\n29 - ALTERAÇÃO\nMotivo da Alteração: Correção pelo editor\nIdentificador da Versão do Anúncio a Alterar: c4179697-0074-45bf-8a4d-e4ffd1de574a-01\nIdentificador das Secções Alteradas do Anúncio Anterior: Condições de Apresentação\nDescrição das Alterações: Foi feito um pedido de prorrogação de prazo, o qual o júri concordou em alterar a data de abertura de propostas para 04/09/2025.\nAlteração dos Documentos do Concurso: Não\n419444986",
    "nipc": "600010180",
    "distrito": "Lisboa",
    "concelho": "Lisboa",
    "freguesia": "Freguesia de Lumiar",
    "site": "www.emgfa.pt",
    "email": "DIRFIN_Contratos@emgfa.pt",
    "designacao_contrato": "Equipamentos de rede para telecomunicações",
    "descricao": "Equipamentos de rede para telecomunicações",
    "preco_base": "128.197,00 EUR",
    "prazo_execucao": "30 DIAS",
    "prazo_apresentacao_propostas": "04-09-2025 23:59",
    "fundos_eu": "Não",
    "plataforma_eletronica": "ACIN",
    "url_procedimento": "https://www.acingov.pt",
    "autor_nome": "Brigadeiro General Rui Manuel da Silva Pina",
    "autor_cargo": "Diretor de Finanças"
  },
  {
    "numero_procedimento": "N/A",
    "entidade": "MUNICIPIO DE LAGOA",
    "link": "https://diariodarepublica.pt/dr/detalhe/contrato-publico/22359-932849663",
    "detalhes_completos": "1 - IDENTIFICAÇÃO E CONTACTOS DA ENTIDADE ADJUDICANTE\nDesignação da entidade adjudicante: MUNICIPIO DE LAGOA\nNIPC: 506804240\nEndereço: Edifício Paços do Concelho, Largo do Município\nCódigo postal: 8401-851\nLocalidade: Faro\nPaís: Portugal\nNUT III: PT150\nDistrito: Faro\nConcelho: Lagoa\nFreguesia: Todas\nTelefone: 282380400\nFax: 282380444\nEndereço da Entidade (URL): www.cm-lagoa.pt\nEndereço Eletrónico: geral@cm-lagoa.pt\neDelivery Gateway (URL): https://community.vortal.biz/public/\nFunção da Organização: Adquirente\nNorma jurídica da Entidade Adjudicante: Organismo de direito público\nÁrea de atividade da Autoridade Adjudicante: Serviços públicos das administrações públicas\n\n2 - JORNAL OFICIAL DA UNIÃO EUROPEIA\nO procedimento a que este anúncio diz respeito também é publicitado no Jornal Oficial da União Europeia? Não\n\n3 - AVISO\nModelo de Anúncio: Concurso público\nData de Envio do Anúncio: 20-08-2025\n\n5 - PROCESSO\nTipo de Procedimento: Concurso público\nPreço base do procedimento: Sim\nValor do preço base do procedimento: 55.000,00 EUR\nProcedimento com lotes? Não\n\n6 - OBJETO DO CONTRATO\nNúmero de referência interna: 932/2025\nDesignação do contrato: Aquisição de acessórios para contentores subterrâneos\nDescrição: Aquisição de acessórios para contentores subterrâneos\nTipo de Contrato Principal: Aquisição de Bens Móveis\nTipo de Contrato: Aquisição de Bens Móveis\nClassificação CPV (Vocabulário Comum para os Contratos Públicos)\nObjeto principal\nVocabulário Principal: 44618500\nPreço base s/IVA: 55.000,00 EUR\n\n7 - INDICAÇÕES ADICIONAIS\nO contrato envolve aquisição conjunta (satisfação de várias entidades)? Não\nO contrato é adjudicado por uma central de compras? Não\n\n8 - TÉCNICAS\nO concurso destina-se à celebração de um acordo-quadro? Inexistência de acordo-quadro\nÉ utilizado um leilão eletrónico? Não\nÉ adotada uma fase de negociação? Não\nSistema de Aquisição Dinâmico: Inexistência de sistema de aquisição dinâmico\n\n9 - LOCAL DA EXECUÇÃO DO CONTRATO\nLOCAL DA EXECUÇÃO DO CONTRATO (PROCEDIMENTO)\nPaís: Portugal\nNUT III: PT150\nLocalidade: Faro\nDistrito: Faro\nConcelho: Lagoa\nFreguesia: União das Freguesias de Lagoa e Carvoeiro\n\n10 - PRAZO DE EXECUÇÃO DO CONTRATO\nPrazo de execução do contrato: 90 DIAS\nPrevisão de renovações: Não\n\n11 - FUNDOS EU\nTêm fundos EU? Não\n\n12 - DOCUMENTOS DE HABILITAÇÃO\nHabilitação para o exercício da atividade profissional: Não\n\n13 - CONDIÇÕES DE APRESENTAÇÃO\nPlataforma eletrónica utilizada pela entidade adjudicante: VORTAL\nURL para Apresentação: https://community.vortal.biz/public/\nAdmissibilidade da apresentação de propostas variantes: Não autorizado\nPrazo para apresentação das propostas: 04-09-2025 17:00\nPrazo durante o qual os concorrentes são obrigados a manter as respetivas propostas: 66 dias a contar do termo do prazo para a apresentação das propostas\nIndicação de Subcontratação na Proposta: Inexistência de indicação de subcontratação\n\n14 - PRESTAÇÃO DE CAUÇÃO\nPrestação de caução: Sim\nPercentagem: 5%\nDescrição da Garantia Exigida: Conforme peças do procedimento.\n\n15 - FORNECIMENTO DAS PEÇAS DO CONCURSO, APRESENTAÇÃO DE PEDIDOS DE PARTICIPAÇÃO E APRESENTAÇÃO DAS PROPOSTAS\nLink para acesso às peças do concurso (URL): https://community.vortal.biz/Public/public-tender-documents/VXUzN245NEVWN1o4RkFadUJJN0hHT1dlcHI3VTF4Sy9hejNsMWVGUU8xaHVmbXRhTldkMTI3ZDd3b1lSeXJjNlpuNXVkWVV3cWlEN0tLYWRucWtMZ3c9PSRGZnpL\n\n20 - OUTROS REQUISITOS\nInformação sobre contratos reservados. Aplica-se a contratos reservados (54º-A)? Não\n\n21 - CRITÉRIO DE ADJUDICAÇÃO\nMultifator: Não\nMonofator:\nNome: Preço\n\n24 - CONDIÇÕES DO CONTRATO\nFaturação Eletrónica: Permitido\nObrigação de Subcontratação:\nCódigo da Obrigação de Subcontratação: Não é aplicável nenhuma obrigação de subcontratação.\n\n25 - COMPRA PÚBLICA ESTRATÉGICA\nCompra Pública Estratégica: Inexistência de contratação pública estratégica\n\n26 - INFORMAÇÕES ADICIONAIS\nContrato adequado para PME: Sim\nCobertura ACP (Acordo dos Contratos Públicos da Organização Mundial do Comércio): Sim\n\n27 - IDENTIFICAÇÃO E CONTACTOS DO ÓRGÃO DE RECURSOS ADMINISTRATIVOS\nDesignação: Município de Lagoa\nEndereço: Lg.  Municipio\nCódigo postal: 8401-851\nLocalidade: Lagoa\nTelefone: +351 282380400\nFax: +351 282380444\nEndereço eletrónico: geral@cm-lagoa.pt\n\n28 - IDENTIFICAÇÃO DO(S) AUTOR(ES) DE ANÚNCIO\nNome: Ana Cristina Tiago Martins\nCargo: Vereadora\n419446427",
    "nipc": "506804240",
    "distrito": "Faro",
    "concelho": "Lagoa",
    "freguesia": "Todas",
    "site": "www.cm-lagoa.pt",
    "email": "geral@cm-lagoa.pt",
    "designacao_contrato": "Aquisição de acessórios para contentores subterrâneos",
    "descricao": "Aquisição de acessórios para contentores subterrâneos",
    "preco_base": "55.000,00 EUR",
    "prazo_execucao": "90 DIAS",
    "prazo_apresentacao_propostas": "04-09-2025 17:00",
    "fundos_eu": "Não",
    "plataforma_eletronica": "VORTAL",
    "url_procedimento": "https://community.vortal.biz/public/",
    "autor_nome": "Ana Cristina Tiago Martins",
    "autor_cargo": "Vereadora"
  },
  {
    "numero_procedimento": "N/A",
    "entidade": "ALRAA - Assembleia Legislativa da Região Autónoma dos Açores",
    "link": "https://diariodarepublica.pt/dr/detalhe/contrato-publico/22360-932849664",
    "detalhes_completos": "1 - IDENTIFICAÇÃO E CONTACTOS DA ENTIDADE ADJUDICANTE\nDesignação da entidade adjudicante: ALRAA - Assembleia Legislativa da Região Autónoma dos Açores\nNIPC: 672000830\nServiço/Órgão/Pessoa de contacto: Secretaria-Geral da Assembleia Legislativa da Região Autónoma dos Açores\nEndereço: Rua Marcelino Lima, s/n\nCódigo postal: 9901-858\nLocalidade: Horta\nPaís: Portugal\nNUT III: PT200\nDistrito: Região Autónoma dos Açores\nConcelho: Horta\nFreguesia: Freguesia de Horta (Matriz)\nTelefone: 292207600\nFax: 292293798\nEndereço da Entidade (URL): www.alra.pt\nEndereço Eletrónico: geral@alra.pt\neDelivery Gateway (URL): https://www.acingov.pt\nFunção da Organização: Adquirente\nNorma jurídica da Entidade Adjudicante: Organismo de direito público\nÁrea de atividade da Autoridade Adjudicante: Serviços públicos das administrações públicas\n\n2 - JORNAL OFICIAL DA UNIÃO EUROPEIA\nO procedimento a que este anúncio diz respeito também é publicitado no Jornal Oficial da União Europeia? Sim\n\n3 - AVISO\nModelo de Anúncio: Concurso público\nData de Envio do Anúncio: 18-08-2025\n\n5 - PROCESSO\nTipo de Procedimento: Concurso público\nPreço base do procedimento: Sim\nValor do preço base do procedimento: 247.500,00 EUR\nProcedimento com lotes? Não\n\n6 - OBJETO DO CONTRATO\nNúmero de referência interna: CPI/2/2025\nDesignação do contrato: Concurso Público Internacional n.º 2/2025/ALRAA, para aquisição dos serviços de cibersegurança para a Assembleia Legislativa da Região Autónoma dos Açores\nDescrição: Aquisição dos serviços de cibersegurança para a Assembleia Legislativa da Região Autónoma dos Açores\n\nOpções: Não\nTipo de Contrato Principal: Aquisição de Serviços\nTipo de Contrato: Aquisição de Serviços\nClassificação CPV (Vocabulário Comum para os Contratos Públicos)\nObjeto principal\nVocabulário Principal: 72910000\nPreço base s/IVA: 247.500,00 EUR\n\n7 - INDICAÇÕES ADICIONAIS\nO contrato envolve aquisição conjunta (satisfação de várias entidades)? Não\nO contrato é adjudicado por uma central de compras? Não\n\n8 - TÉCNICAS\nO concurso destina-se à celebração de um acordo-quadro? Inexistência de acordo-quadro\nÉ utilizado um leilão eletrónico? Não\nÉ adotada uma fase de negociação? Não\nSistema de Aquisição Dinâmico: Inexistência de sistema de aquisição dinâmico\n\n9 - LOCAL DA EXECUÇÃO DO CONTRATO\nLOCAL DA EXECUÇÃO DO CONTRATO (PROCEDIMENTO)\nPaís: Portugal\nNUT III: PT200\nLocalidade: Freguesia de Horta (Matriz)\nDistrito: Região Autónoma dos Açores\nConcelho: Horta\nFreguesia: Freguesia de Horta (Matriz)\n\n10 - PRAZO DE EXECUÇÃO DO CONTRATO\nPrazo de execução do contrato: 36 MESES\nPrevisão de renovações: Não\n\n11 - FUNDOS EU\nTêm fundos EU? Não\n\n12 - DOCUMENTOS DE HABILITAÇÃO\nHabilitação para o exercício da atividade profissional: Sim\nTipo: Certificado\nDescrição: Certificações do gestor de projeto e da equipa do projeto exigidas na Cláusula 33.ª do caderno de encargos;\nCertificações e credenciações do adjudicatário exigidas na Cláusula 34.ª do caderno de encargos.\n\n13 - CONDIÇÕES DE APRESENTAÇÃO\nPlataforma eletrónica utilizada pela entidade adjudicante: ACIN\nURL para Apresentação: https://www.acingov.pt\nAdmissibilidade da apresentação de propostas variantes: Não autorizado\nPrazo para apresentação das propostas: 17-09-2025 17:59\nPrazo durante o qual os concorrentes são obrigados a manter as respetivas propostas: 66 dias a contar do termo do prazo para a apresentação das propostas\nApresentação de Catálogo Eletrónico: Permitido\nIndicação de Subcontratação na Proposta: Inexistência de indicação de subcontratação\n\n14 - PRESTAÇÃO DE CAUÇÃO\nPrestação de caução: Sim\nPercentagem: 2%\nDescrição da Garantia Exigida: O valor da caução é de 2.00% do preço contratual.\n\n15 - FORNECIMENTO DAS PEÇAS DO CONCURSO, APRESENTAÇÃO DE PEDIDOS DE PARTICIPAÇÃO E APRESENTAÇÃO DAS PROPOSTAS\nLink para acesso às peças do concurso (URL): https://www.acingov.pt/acingovprod/2/zonaPublica/zona_publica_c/donwloadProcedurePiece/OTIwNzY0\n\n20 - OUTROS REQUISITOS\nInformação sobre contratos reservados. Aplica-se a contratos reservados (54º-A)? Não\n\n21 - CRITÉRIO DE ADJUDICAÇÃO\nMultifator: Não\nMonofator:\nNome: Preço\n\n24 - CONDIÇÕES DO CONTRATO\nFaturação Eletrónica: Permitido\nObrigação de Subcontratação:\nCódigo da Obrigação de Subcontratação: Não é aplicável nenhuma obrigação de subcontratação.\n\n25 - COMPRA PÚBLICA ESTRATÉGICA\nCompra Pública Estratégica: Inexistência de contratação pública estratégica\n\n26 - INFORMAÇÕES ADICIONAIS\nContrato adequado para PME: Não\nCobertura ACP (Acordo dos Contratos Públicos da Organização Mundial do Comércio): Não\n\n27 - IDENTIFICAÇÃO E CONTACTOS DO ÓRGÃO DE RECURSOS ADMINISTRATIVOS\nDesignação: Mesa da Assembleia Legislativa da Região Autónoma dos Açores\nEndereço: Rua Marcelino Lima, s/n\nCódigo postal: 9901-858\nLocalidade: Horta\nTelefone: 962524447\nFax: \nEndereço eletrónico: arquivo@alra.pt\nPrazo de interposição do recurso: 5 dias\n\n28 - IDENTIFICAÇÃO DO(S) AUTOR(ES) DE ANÚNCIO\nNome: Luís Mesquita\nCargo: Técnico Superior\n419444734",
    "nipc": "672000830",
    "distrito": "Região Autónoma dos Açores",
    "concelho": "Horta",
    "freguesia": "Freguesia de Horta (Matriz)",
    "site": "www.alra.pt",
    "email": "geral@alra.pt",
    "designacao_contrato": "Concurso Público Internacional n.º 2/2025/ALRAA, para aquisição dos serviços de cibersegurança para a Assembleia Legislativa da Região Autónoma dos Açores",
    "descricao": "Aquisição dos serviços de cibersegurança para a Assembleia Legislativa da Região Autónoma dos Açores",
    "preco_base": "247.500,00 EUR",
    "prazo_execucao": "36 MESES",
    "prazo_apresentacao_propostas": "17-09-2025 17:59",
    "fundos_eu": "Não",
    "plataforma_eletronica": "ACIN",
    "url_procedimento": "https://www.acingov.pt",
    "autor_nome": "Luís Mesquita",
    "autor_cargo": "Técnico Superior"
  },
  {
    "numero_procedimento": "N/A",
    "entidade": "Associação Turismo de Lisboa",
    "link": "https://diariodarepublica.pt/dr/detalhe/contrato-publico/22361-932849665",
    "detalhes_completos": "1 - IDENTIFICAÇÃO E CONTACTOS DA ENTIDADE ADJUDICANTE\nDesignação da entidade adjudicante: Associação Turismo de Lisboa\nNIPC: 501880160\nEndereço: R do Arsenal, 15\nCódigo postal: 1100-038\nLocalidade: Lisboa\nPaís: Portugal\nNUT III: PT170\nDistrito: Lisboa\nConcelho: Lisboa\nFreguesia: Todas\nTelefone: 210312700\nFax: 210312899\nEndereço da Entidade (URL): https://www.visitlisboa.com/pt-pt\nEndereço Eletrónico: atl@visitlisboa.com\neDelivery Gateway (URL): https://community.vortal.biz/public/\nFunção da Organização: Adquirente\nNorma jurídica da Entidade Adjudicante: Organização que adjudica um contrato subvencionado por uma autoridade da administração central\nÁrea de atividade da Autoridade Adjudicante: Atividades recreativas, culturais e religiosas\n\n2 - JORNAL OFICIAL DA UNIÃO EUROPEIA\nO procedimento a que este anúncio diz respeito também é publicitado no Jornal Oficial da União Europeia? Sim\n\n3 - AVISO\nModelo de Anúncio: Concurso público\nData de Envio do Anúncio: 18-08-2025\n\n5 - PROCESSO\nTipo de Procedimento: Concurso público\nPreço base do procedimento: Sim\nValor do preço base do procedimento: 6.150.000,00 EUR\nProcedimento com lotes? Não\n\n6 - OBJETO DO CONTRATO\nNúmero de referência interna: 25.IX _EMPREITADA_CPI_01_2025\nDesignação do contrato: CONCURSO PÚBLICO INTERNACIONAL N.º 25.IX _EMPREITADA_CPI_01_2025\nDescrição: CONCURSO PÚBLICO INTERNACIONAL N.º 25.IX _EMPREITADA_CPI_01_2025 para Empreitada de Obra Pública de Recuperação dos Saguões e Coberturas do Palácio Nacional da Ajuda\nOpções: Não\nTipo de Contrato Principal: Empreitada de Obras Públicas\nTipo de Contrato: Empreitada de Obras Públicas\nClassificação CPV (Vocabulário Comum para os Contratos Públicos)\nObjeto principal\nVocabulário Principal: 45200000\nPreço base s/IVA: 6.150.000,00 EUR\n\n7 - INDICAÇÕES ADICIONAIS\nO contrato envolve aquisição conjunta (satisfação de várias entidades)? Não\nO contrato é adjudicado por uma central de compras? Não\n\n8 - TÉCNICAS\nO concurso destina-se à celebração de um acordo-quadro? Inexistência de acordo-quadro\nÉ utilizado um leilão eletrónico? Não\nÉ adotada uma fase de negociação? Não\nSistema de Aquisição Dinâmico: Inexistência de sistema de aquisição dinâmico\n\n9 - LOCAL DA EXECUÇÃO DO CONTRATO\nLOCAL DA EXECUÇÃO DO CONTRATO (PROCEDIMENTO)\nPaís: Portugal\nNUT III: PT170\nLocalidade: Lisboa\nDistrito: Lisboa\nConcelho: Lisboa\nFreguesia: Todas\n\n10 - PRAZO DE EXECUÇÃO DO CONTRATO\nPrazo de execução do contrato: 8 MESES\nPrevisão de renovações: Não\n\n11 - FUNDOS EU\nTêm fundos EU? Sim\n\n12 - DOCUMENTOS DE HABILITAÇÃO\nHabilitação para o exercício da atividade profissional: Sim\nTipo: Alvará\nDescrição: Alvará emitido pelo Instituto dos Mercados Públicos, I.P. (IMPIC, I.P.) que habilite o concorrente a realizar obras de:\ni. 1.ª categoria, 1.ª subcategoria, classe 1;\nii. 1.ª categoria, 2.ª subcategoria, classe 2;\niii. 1.ª categoria, 3.ª subcategoria, classe 4;\niv. 1.ª categoria, 4.ª subcategoria, classe 1;\nv. 1.ª categoria, 5.ª subcategoria, classe 1;\nvi. 1.ª categoria, 9.ª subcategoria, classe 2;\nvii. 1.ª categoria, 10.ª subcategoria, classe 6;\nviii. 4.ª categoria, 1.ª subcategoria, classe 1;\nix. 4.ª categoria, 7.ª subcategoria, classe 1;\nx. 4.ª categoria, 10.ª subcategoria, classe 1;\nxi. 4.ª categoria, 11.ª subcategoria, classe 1;\nxii. 5.ª categoria, 1.ª subcategoria, classe 1;\nxiii. 5.ª categoria, 11.ª subcategoria, classe 2; e\nxiv. 5.ª categoria, 12.ª subcategoria, classe 4;\n\n13 - CONDIÇÕES DE APRESENTAÇÃO\nPlataforma eletrónica utilizada pela entidade adjudicante: VORTAL\nURL para Apresentação: https://community.vortal.biz/public/\nAdmissibilidade da apresentação de propostas variantes: Não autorizado\nPrazo para apresentação das propostas: 17-09-2025 18:00\nPrazo durante o qual os concorrentes são obrigados a manter as respetivas propostas: 66 dias a contar do termo do prazo para a apresentação das propostas\nApresentação de Catálogo Eletrónico: Não autorizado\nIndicação de Subcontratação na Proposta: Inexistência de indicação de subcontratação\n\n14 - PRESTAÇÃO DE CAUÇÃO\nPrestação de caução: Sim\nPercentagem: 5%\nDescrição da Garantia Exigida: Em conformidade com o disposto nos artigos 88.º, n.º 1 e n.º 2 alínea a) e 89.º, n.º 1, ambos do CCP\n\n15 - FORNECIMENTO DAS PEÇAS DO CONCURSO, APRESENTAÇÃO DE PEDIDOS DE PARTICIPAÇÃO E APRESENTAÇÃO DAS PROPOSTAS\nLink para acesso às peças do concurso (URL): https://community.vortal.biz/Public/public-tender-documents/Z0hNdnArYUpXaFY4cS9kTDFRaEY0c0ZzRklia0VTRW9MSGdoL3k2eE5jRDBoSW9CT3J4ZDNleEtnWUUzL3VKeWJaWk51YU4rRE9vTjFhME5TV0xJZHc9PVopKCpm\n\n20 - OUTROS REQUISITOS\nInformação sobre contratos reservados. Aplica-se a contratos reservados (54º-A)? Não\n\n21 - CRITÉRIO DE ADJUDICAÇÃO\nMultifator: Não\nMonofator:\nNome: Preço\n\n24 - CONDIÇÕES DO CONTRATO\nFaturação Eletrónica: Permitido\nObrigação de Subcontratação:\nCódigo da Obrigação de Subcontratação: Não é aplicável nenhuma obrigação de subcontratação.\n\n25 - COMPRA PÚBLICA ESTRATÉGICA\nCompra Pública Estratégica: Inexistência de contratação pública estratégica\n\n26 - INFORMAÇÕES ADICIONAIS\nContrato adequado para PME: Sim\nCobertura ACP (Acordo dos Contratos Públicos da Organização Mundial do Comércio): Não\n\n27 - IDENTIFICAÇÃO E CONTACTOS DO ÓRGÃO DE RECURSOS ADMINISTRATIVOS\nDesignação: Comissão Executiva ATL\nEndereço: Rua do Arsenal n.º 23\nCódigo postal: 1100-038\nLocalidade: Lisboa\nTelefone: +351 210312700\nFax: +351 210312899\nEndereço eletrónico: atl@visitlisboa.com\nPrazo de interposição do recurso: 5 dias\n\n28 - IDENTIFICAÇÃO DO(S) AUTOR(ES) DE ANÚNCIO\nNome: David Mendes Coelho\nCargo: Gabinete de Assessoria Jurídica\n419445511",
    "nipc": "501880160",
    "distrito": "Lisboa",
    "concelho": "Lisboa",
    "freguesia": "Todas",
    "site": "https://www.visitlisboa.com/pt-pt",
    "email": "atl@visitlisboa.com",
    "designacao_contrato": "CONCURSO PÚBLICO INTERNACIONAL N.º 25.IX _EMPREITADA_CPI_01_2025",
    "descricao": "CONCURSO PÚBLICO INTERNACIONAL N.º 25.IX _EMPREITADA_CPI_01_2025 para Empreitada de Obra Pública de Recuperação dos Saguões e Coberturas do Palácio Nacional da Ajuda",
    "preco_base": "6.150.000,00 EUR",
    "prazo_execucao": "8 MESES",
    "prazo_apresentacao_propostas": "17-09-2025 18:00",
    "fundos_eu": "Sim",
    "plataforma_eletronica": "VORTAL",
    "url_procedimento": "https://community.vortal.biz/public/",
    "autor_nome": "David Mendes Coelho",
    "autor_cargo": "Gabinete de Assessoria Jurídica"
  },
  {
    "numero_procedimento": "N/A",
    "entidade": "Sociedade de Transportes Colectivos do Porto, E. I. M., S. A.",
    "link": "https://diariodarepublica.pt/dr/detalhe/contrato-publico/22362-932875486",
    "detalhes_completos": "Alteração do Anúncio de procedimento n.º 20551/2025, de 2025-07-31, com o ID 419367006\n\n1 - IDENTIFICAÇÃO E CONTACTOS DA ENTIDADE ADJUDICANTE\nDesignação da entidade adjudicante: Sociedade de Transportes Colectivos do Porto, E. I. M., S. A.\nNIPC: 500246467\nEndereço: Avenida Fernão Magalhães, 1862, 13.º Piso\nCódigo postal: 4350-158\nLocalidade: Porto\nPaís: Portugal\nNUT III: PT11A\nDistrito: Porto\nConcelho: Porto\nFreguesia: Todas\nTelefone: 225071000\nEndereço da Entidade (URL): http://www.stcp.pt\nEndereço Eletrónico: geral@stcp.pt\nFunção da Organização: Adquirente\nNorma jurídica da Entidade Adjudicante: Organismo de direito público, controlado por uma autoridade local\nÁrea de atividade da Autoridade Adjudicante: Serviços públicos das administrações públicas\n\n2 - JORNAL OFICIAL DA UNIÃO EUROPEIA\nO procedimento a que este anúncio diz respeito também é publicitado no Jornal Oficial da União Europeia? Sim\n\n3 - AVISO\nModelo de Anúncio: Concurso público\nData de Envio do Anúncio: 18-08-2025\n\n5 - PROCESSO\nTipo de Procedimento: Concurso público\nPreço base do procedimento: Sim\nValor do preço base do procedimento: 1.500.000,00 EUR\nProcedimento com lotes? Não\n\n6 - OBJETO DO CONTRATO\nNúmero de referência interna: 15/2025\nDesignação do contrato: Concurso Público Internacional para a prestação de serviços de vigilância através de meios humanos e monitorização de sinais de alarme e de videovigilância\nDescrição: Prestação de serviços de vigilância através de meios humanos e monitorização de sinais de alarme e de videovigilância\nOpções: Não\nTipo de Contrato Principal: Aquisição de Serviços\nTipo de Contrato: Aquisição de Serviços\nClassificação CPV (Vocabulário Comum para os Contratos Públicos)\nObjeto principal\nVocabulário Principal: 79714000\nPreço base s/IVA: 1.500.000,00 EUR\n\n7 - INDICAÇÕES ADICIONAIS\nO contrato envolve aquisição conjunta (satisfação de várias entidades)? Não\nO contrato é adjudicado por uma central de compras? Não\n\n8 - TÉCNICAS\nO concurso destina-se à celebração de um acordo-quadro? Inexistência de acordo-quadro\nÉ utilizado um leilão eletrónico? Não\nÉ adotada uma fase de negociação? Não\nSistema de Aquisição Dinâmico: Inexistência de sistema de aquisição dinâmico\n\n9 - LOCAL DA EXECUÇÃO DO CONTRATO\nLOCAL DA EXECUÇÃO DO CONTRATO (PROCEDIMENTO)\nPaís: Portugal\nNUT III: PT11A\nLocalidade: Porto\nDistrito: Porto\nConcelho: Porto\nFreguesia: Todas\n\n10 - PRAZO DE EXECUÇÃO DO CONTRATO\nPrazo de execução do contrato: 3 ANOS\nPrevisão de renovações: Não\n\n11 - FUNDOS EU\nTêm fundos EU? Não\n\n12 - DOCUMENTOS DE HABILITAÇÃO\nHabilitação para o exercício da atividade profissional: Sim\nTipo: Outros\nDescrição - Outros: Ver programa do procedimento e caderno de encargos\nDescrição: Ver programa do procedimento e caderno de encargos\n\n13 - CONDIÇÕES DE APRESENTAÇÃO\nPlataforma eletrónica utilizada pela entidade adjudicante: VORTAL\nURL para Apresentação: https://community.vortal.biz/publico/\nAdmissibilidade da apresentação de propostas variantes: Não autorizado\nPrazo para apresentação das propostas: 24-09-2025 17:00\nPrazo durante o qual os concorrentes são obrigados a manter as respetivas propostas: 180 dias a contar do termo do prazo para a apresentação das propostas\nApresentação de Catálogo Eletrónico: Não autorizado\nIndicação de Subcontratação na Proposta: Inexistência de indicação de subcontratação\n\n14 - PRESTAÇÃO DE CAUÇÃO\nPrestação de caução: Sim\nPercentagem: 5%\nDescrição da Garantia Exigida: depósito em dinheiro ou em títulos emitidos ou garantidos pelo Estado ou mediante garantia ou seguro – caução\n\n15 - FORNECIMENTO DAS PEÇAS DO CONCURSO, APRESENTAÇÃO DE PEDIDOS DE PARTICIPAÇÃO E APRESENTAÇÃO DAS PROPOSTAS\nLink para acesso às peças do concurso (URL): https://community.vortal.biz/tendersmanagement/procedure-edit/PT1.REQ.25702091/\n\n20 - OUTROS REQUISITOS\nInformação sobre contratos reservados. Aplica-se a contratos reservados (54º-A)? Não\n\n21 - CRITÉRIO DE ADJUDICAÇÃO\nMultifator: Não\nMonofator:\nNome: Preço\n\n24 - CONDIÇÕES DO CONTRATO\nFaturação Eletrónica: Permitido\nObrigação de Subcontratação:\nCódigo da Obrigação de Subcontratação: Não é aplicável nenhuma obrigação de subcontratação.\n\n25 - COMPRA PÚBLICA ESTRATÉGICA\nCompra Pública Estratégica: Inexistência de contratação pública estratégica\n\n26 - INFORMAÇÕES ADICIONAIS\nContrato adequado para PME: Sim\nCobertura ACP (Acordo dos Contratos Públicos da Organização Mundial do Comércio): Não\n\n27 - IDENTIFICAÇÃO E CONTACTOS DO ÓRGÃO DE RECURSOS ADMINISTRATIVOS\nDesignação: Conselho de Administração\nEndereço: Avenida Fernão Magalhães, 1862, 13.º Piso\nCódigo postal: 4350-158\nLocalidade: Porto\nEndereço eletrónico: geral@stcp.pt\n\n28 - IDENTIFICAÇÃO DO(S) AUTOR(ES) DE ANÚNCIO\nNome: Tatiana Bacelar Vilar\nCargo: Advogada\n\n29 - ALTERAÇÃO\nMotivo da Alteração: Correção pelo adquirente\nIdentificador da Versão do Anúncio a Alterar: 7cc9e1cb-3eb8-4045-b8d7-6d3ff4339445-01\nIdentificador das Secções Alteradas do Anúncio Anterior: Condições de Apresentação\nDescrição das Alterações: Prazo para apresentação de propostas\nAlteração dos Documentos do Concurso: Sim\nData de alteração dos documentos do concurso: 18-08-2025\n419443876",
    "nipc": "500246467",
    "distrito": "Porto",
    "concelho": "Porto",
    "freguesia": "Todas",
    "site": "http://www.stcp.pt",
    "email": "geral@stcp.pt",
    "designacao_contrato": "Concurso Público Internacional para a prestação de serviços de vigilância através de meios humanos e monitorização de sinais de alarme e de videovigilância",
    "descricao": "Prestação de serviços de vigilância através de meios humanos e monitorização de sinais de alarme e de videovigilância",
    "preco_base": "1.500.000,00 EUR",
    "prazo_execucao": "3 ANOS",
    "prazo_apresentacao_propostas": "24-09-2025 17:00",
    "fundos_eu": "Não",
    "plataforma_eletronica": "VORTAL",
    "url_procedimento": "https://community.vortal.biz/publico/",
    "autor_nome": "Tatiana Bacelar Vilar",
    "autor_cargo": "Advogada"
  },
  {
    "numero_procedimento": "N/A",
    "entidade": "Colégio de São Gonçalo de Amarante  Escola Católica",
    "link": "https://diariodarepublica.pt/dr/detalhe/contrato-publico/22364-932875487",
    "detalhes_completos": "1 - IDENTIFICAÇÃO E CONTACTOS DA ENTIDADE ADJUDICANTE\nDesignação da entidade adjudicante: Colégio de São Gonçalo de Amarante  Escola Católica\nNIPC: 591001209\nServiço/Órgão/Pessoa de contacto: Direção\nEndereço: Avenida 25 de Abril\nCódigo postal: 4600-014\nLocalidade: Amarante\nPaís: Portugal\nNUT III: PT111\nDistrito: Porto\nConcelho: Amarante\nFreguesia: União das Freguesias de Amarante (São Gonçalo), Madalena, Cepelos e Gatão\nTelefone: 255432020\nFax: 255432020\nEndereço da Entidade (URL): www.colegiosaogoncalo.pt\nEndereço Eletrónico: geral@colegiosaogoncalo.pt\neDelivery Gateway (URL): https://www.acingov.pt\nFunção da Organização: Adquirente\nNorma jurídica da Entidade Adjudicante: Organismo de direito público\nÁrea de atividade da Autoridade Adjudicante: Serviços públicos das administrações públicas\n\n2 - JORNAL OFICIAL DA UNIÃO EUROPEIA\nO procedimento a que este anúncio diz respeito também é publicitado no Jornal Oficial da União Europeia? Não\n\n3 - AVISO\nModelo de Anúncio: Concurso público\nData de Envio do Anúncio: 20-08-2025\n\n5 - PROCESSO\nTipo de Procedimento: Concurso público\nPreço base do procedimento: Sim\nValor do preço base do procedimento: 41.819,00 EUR\nProcedimento com lotes? Sim\nNº Máx. de Lotes Autorizado: 2\nNúmero máximo de lotes que podem ser adjudicados a um concorrente: 2\n\n6 - OBJETO DO CONTRATO\nNúmero de referência interna: CP 04/2025\nDesignação do contrato: Fornecimento contínuo de bens alimentares para o Colégio de São Gonçalo de Amarante  Escola Católica  Ano Letivo 2025/2026, por lotes  Frutas e Legumes e Laticínios\nDescrição: Fornecimento contínuo de bens alimentares para o Colégio de São Gonçalo de Amarante  Escola Católica  Ano Letivo 2025/2026, por lotes  Frutas e Legumes e Laticínios\nTipo de Contrato Principal: Aquisição de Bens Móveis\nTipo de Contrato: Aquisição de Bens Móveis\nClassificação CPV (Vocabulário Comum para os Contratos Públicos)\nObjeto principal\nVocabulário Principal: 15800000\nPreço base s/IVA: 41.819,00 EUR\nLotes: \nNº: LOT-0001\nDescrição do Lote: Frutas e Legumes\nPreço base s/IVA: 40.948,00 EUR\nClassificação CPV (Vocabulário Comum para os Contratos Públicos)\nObjeto principal\nVocabulário Principal: 15800000\nNº: LOT-0002\nDescrição do Lote: Laticínios\nPreço base s/IVA: 871,00 EUR\nClassificação CPV (Vocabulário Comum para os Contratos Públicos)\nObjeto principal\nVocabulário Principal: 15800000\n\n7 - INDICAÇÕES ADICIONAIS\nO contrato envolve aquisição conjunta (satisfação de várias entidades)? Não\nO contrato é adjudicado por uma central de compras? Não\n\n8 - TÉCNICAS\nO concurso destina-se à celebração de um acordo-quadro? Inexistência de acordo-quadro\nÉ utilizado um leilão eletrónico? Não\nÉ adotada uma fase de negociação? Não\nSistema de Aquisição Dinâmico: Inexistência de sistema de aquisição dinâmico\n\n9 - LOCAL DA EXECUÇÃO DO CONTRATO\nLOCAL DA EXECUÇÃO DO CONTRATO (PROCEDIMENTO)\nPaís: Portugal\nNUT III: PT111\nLocalidade: União das Freguesias de Amarante (São Gonçalo), Madalena, Cepelos e Gatão\nDistrito: Porto\nConcelho: Amarante\nFreguesia: União das Freguesias de Amarante (São Gonçalo), Madalena, Cepelos e Gatão\nLOCAL DA EXECUÇÃO DO CONTRATO (LOTE)\nIdentificador do Lote: LOT-0001; LOT-0002\nPaís: Portugal\nNUT III: PT111\nLocalidade: União das Freguesias de Amarante (São Gonçalo), Madalena, Cepelos e Gatão\nDistrito: Porto\nConcelho: Amarante\nFreguesia: União das Freguesias de Amarante (São Gonçalo), Madalena, Cepelos e Gatão\n\n10 - PRAZO DE EXECUÇÃO DO CONTRATO\nIdentificador do Lote: LOT-0001; LOT-0002\nPrazo de execução do contrato: 12 MESES\nPrevisão de renovações: Não\n\n11 - FUNDOS EU\nIdentificador do Lote: LOT-0001; LOT-0002\nTêm fundos EU? Não\n\n12 - DOCUMENTOS DE HABILITAÇÃO\nHabilitação para o exercício da atividade profissional: Não\n\n13 - CONDIÇÕES DE APRESENTAÇÃO\nPlataforma eletrónica utilizada pela entidade adjudicante: ACIN\nURL para Apresentação: https://www.acingov.pt\nAdmissibilidade da apresentação de propostas variantes: Não autorizado\nPrazo para apresentação das propostas: 26-08-2025 17:00\nPrazo durante o qual os concorrentes são obrigados a manter as respetivas propostas: 90 dias a contar do termo do prazo para a apresentação das propostas\nIndicação de Subcontratação na Proposta: Inexistência de indicação de subcontratação\n\n14 - PRESTAÇÃO DE CAUÇÃO\nPrestação de caução: Não\n\n15 - FORNECIMENTO DAS PEÇAS DO CONCURSO, APRESENTAÇÃO DE PEDIDOS DE PARTICIPAÇÃO E APRESENTAÇÃO DAS PROPOSTAS\nLink para acesso às peças do concurso (URL): https://www.acingov.pt/acingovprod/2/zonaPublica/zona_publica_c/donwloadProcedurePiece/OTM1OTEw\n\n20 - OUTROS REQUISITOS\nIdentificador do Lote: LOT-0001; LOT-0002\nInformação sobre contratos reservados. Aplica-se a contratos reservados (54º-A)? Não\n\n21 - CRITÉRIO DE ADJUDICAÇÃO\nO Critério de adjudicação é diferenciado por lote? Não\nMultifator: Não\nMonofator:\nNome: Preço\n\n24 - CONDIÇÕES DO CONTRATO\nIdentificador do Lote: LOT-0001; LOT-0002\nFaturação Eletrónica: Permitido\nObrigação de Subcontratação:\nCódigo da Obrigação de Subcontratação: Não é aplicável nenhuma obrigação de subcontratação.\n\n25 - COMPRA PÚBLICA ESTRATÉGICA\nCompra Pública Estratégica: Inexistência de contratação pública estratégica\n\n26 - INFORMAÇÕES ADICIONAIS\nIdentificador do Lote: LOT-0001; LOT-0002\nContrato adequado para PME: Não\nCobertura ACP (Acordo dos Contratos Públicos da Organização Mundial do Comércio): Não\n\n27 - IDENTIFICAÇÃO E CONTACTOS DO ÓRGÃO DE RECURSOS ADMINISTRATIVOS\nDesignação: Direção do Colégio de São Gonçalo\nEndereço: Avenida 25 de Abril\nCódigo postal: 4600-014\nLocalidade: Amarante\nTelefone: 255432020\nFax: 255432020\nEndereço eletrónico: geral@colegiosaogoncalo.pt\nPrazo de interposição do recurso: 30 dias\n\n28 - IDENTIFICAÇÃO DO(S) AUTOR(ES) DE ANÚNCIO\nNome: Joaquim Samuel Ribeiro Guedes\nCargo: Presidente da Direção\n419454292",
    "nipc": "591001209",
    "distrito": "Porto",
    "concelho": "Amarante",
    "freguesia": "União das Freguesias de Amarante (São Gonçalo), Madalena, Cepelos e Gatão",
    "site": "www.colegiosaogoncalo.pt",
    "email": "geral@colegiosaogoncalo.pt",
    "designacao_contrato": "Fornecimento contínuo de bens alimentares para o Colégio de São Gonçalo de Amarante  Escola Católica  Ano Letivo 2025/2026, por lotes  Frutas e Legumes e Laticínios",
    "descricao": "Fornecimento contínuo de bens alimentares para o Colégio de São Gonçalo de Amarante  Escola Católica  Ano Letivo 2025/2026, por lotes  Frutas e Legumes e Laticínios",
    "preco_base": "41.819,00 EUR",
    "prazo_execucao": "12 MESES",
    "prazo_apresentacao_propostas": "26-08-2025 17:00",
    "fundos_eu": "Não",
    "plataforma_eletronica": "ACIN",
    "url_procedimento": "https://www.acingov.pt",
    "autor_nome": "Joaquim Samuel Ribeiro Guedes",
    "autor_cargo": "Presidente da Direção"
  },
  {
    "numero_procedimento": "N/A",
    "entidade": "Cenintel, Centro de Inteligência Formativa, Ensino e Formação Profissional, Lda.",
    "link": "https://diariodarepublica.pt/dr/detalhe/contrato-publico/22366-932875488",
    "detalhes_completos": "1 - IDENTIFICAÇÃO E CONTACTOS DA ENTIDADE ADJUDICANTE\nDesignação da entidade adjudicante: Cenintel, Centro de Inteligência Formativa, Ensino e Formação Profissional, Lda.\nNIPC: 507261682\nEndereço: AV DOUTOR ANTÓNIO BRANDÃO DE VASCONCELOS QUINTA DA SARRAZOLA\nCódigo postal: 2705-182\nLocalidade: Lisboa\nPaís: Portugal\nNUT III: PT170\nDistrito: Lisboa\nConcelho: Sintra\nFreguesia: Freguesia de Colares\nTelefone: 219290586\nEndereço da Entidade (URL): www.epav.pt\nEndereço Eletrónico: servicosfinanceiros@epav.pt\neDelivery Gateway (URL): https://community.vortal.biz/public/\nFunção da Organização: Adquirente\nNorma jurídica da Entidade Adjudicante: Organismo de direito público\nÁrea de atividade da Autoridade Adjudicante: Educação\n\n2 - JORNAL OFICIAL DA UNIÃO EUROPEIA\nO procedimento a que este anúncio diz respeito também é publicitado no Jornal Oficial da União Europeia? Não\n\n3 - AVISO\nModelo de Anúncio: Concurso público\nData de Envio do Anúncio: 20-08-2025\n\n5 - PROCESSO\nTipo de Procedimento: Concurso público\nPreço base do procedimento: Sim\nValor do preço base do procedimento: 53.425,00 EUR\nProcedimento com lotes? Não\n\n6 - OBJETO DO CONTRATO\nNúmero de referência interna: 098/2025 Cópia\nDesignação do contrato: Reparação do muro e executar escada Metálica Exterior, fundações da Escada para Escolas EPAV Colares e Sintra\nDescrição: Reparação do muro para contenção de terras para a Escola EPAV, em Colares e executar escada Metálica Exterior, fundações da Escada, partir o murete da base de apoio da escada e portão e guarda da escada e na Escola EPAV, em Sintra.\nTipo de Contrato Principal: Empreitada de Obras Públicas\nTipo de Contrato: Empreitada de Obras Públicas\nClassificação CPV (Vocabulário Comum para os Contratos Públicos)\nObjeto principal\nVocabulário Principal: 45214310\nPreço base s/IVA: 53.425,00 EUR\n\n7 - INDICAÇÕES ADICIONAIS\nO contrato envolve aquisição conjunta (satisfação de várias entidades)? Não\nO contrato é adjudicado por uma central de compras? Não\n\n8 - TÉCNICAS\nO concurso destina-se à celebração de um acordo-quadro? Inexistência de acordo-quadro\nÉ utilizado um leilão eletrónico? Não\nÉ adotada uma fase de negociação? Não\nSistema de Aquisição Dinâmico: Inexistência de sistema de aquisição dinâmico\n\n9 - LOCAL DA EXECUÇÃO DO CONTRATO\nLOCAL DA EXECUÇÃO DO CONTRATO (PROCEDIMENTO)\nPaís: Portugal\nNUT III: PT170\nLocalidade: Lisboa\nDistrito: Lisboa\nConcelho: Sintra\nFreguesia: Freguesia de Colares\n\n10 - PRAZO DE EXECUÇÃO DO CONTRATO\nPrazo de execução do contrato: 90 DIAS\nPrevisão de renovações: Não\n\n11 - FUNDOS EU\nTêm fundos EU? Não\n\n12 - DOCUMENTOS DE HABILITAÇÃO\nHabilitação para o exercício da atividade profissional: Não\n\n13 - CONDIÇÕES DE APRESENTAÇÃO\nPlataforma eletrónica utilizada pela entidade adjudicante: VORTAL\nURL para Apresentação: https://community.vortal.biz/public/\nAdmissibilidade da apresentação de propostas variantes: Não autorizado\nPrazo para apresentação das propostas: 03-09-2025 17:30\nPrazo durante o qual os concorrentes são obrigados a manter as respetivas propostas: 66 dias a contar do termo do prazo para a apresentação das propostas\nIndicação de Subcontratação na Proposta: Inexistência de indicação de subcontratação\n\n14 - PRESTAÇÃO DE CAUÇÃO\nPrestação de caução: Sim\nPercentagem: 5%\nDescrição da Garantia Exigida: Depósito caução\n\n15 - FORNECIMENTO DAS PEÇAS DO CONCURSO, APRESENTAÇÃO DE PEDIDOS DE PARTICIPAÇÃO E APRESENTAÇÃO DAS PROPOSTAS\nLink para acesso às peças do concurso (URL): https://community.vortal.biz/Public/public-tender-documents/QnFGS2ZBbmIvdm5uM3QwTFdnWnc1SkMyejVLUUxzMXE5bVNQUEFuNjcwcnFabDA5Rm0xaTRkdlN2anNpU29HK25nYU56aUM1ZDF5NVg0Y3JsVWJqbHc9PV9XNncm\n\n20 - OUTROS REQUISITOS\nInformação sobre contratos reservados. Aplica-se a contratos reservados (54º-A)? Não\n\n21 - CRITÉRIO DE ADJUDICAÇÃO\nMultifator: Sim\nFator: \nNome: Preço\nPonderação: 45%\nSubfatores: Não\nFator: \nNome: Qualidade\nPonderação: 55%\nSubfatores: Não\n\n24 - CONDIÇÕES DO CONTRATO\nFaturação Eletrónica: Permitido\nObrigação de Subcontratação:\nCódigo da Obrigação de Subcontratação: Não é aplicável nenhuma obrigação de subcontratação.\n\n25 - COMPRA PÚBLICA ESTRATÉGICA\nCompra Pública Estratégica: Inexistência de contratação pública estratégica\n\n26 - INFORMAÇÕES ADICIONAIS\nContrato adequado para PME: Sim\nCobertura ACP (Acordo dos Contratos Públicos da Organização Mundial do Comércio): Não\n\n27 - IDENTIFICAÇÃO E CONTACTOS DO ÓRGÃO DE RECURSOS ADMINISTRATIVOS\nDesignação: Gerência CENINTEL/EPAV\nEndereço: AV DOUTOR ANTÓNIO BRANDÃO DE VASCONCELOS QUINTA DA SARRAZOLA\nCódigo postal: 2705-182\nLocalidade: Sintra\nTelefone: +351 219290586\nFax: +351 219290586\nEndereço eletrónico: secretariacolares@epav.pt\n\n28 - IDENTIFICAÇÃO DO(S) AUTOR(ES) DE ANÚNCIO\nNome: José Luís Furtado\nCargo: Gerente\n419453717",
    "nipc": "507261682",
    "distrito": "Lisboa",
    "concelho": "Sintra",
    "freguesia": "Freguesia de Colares",
    "site": "www.epav.pt",
    "email": "servicosfinanceiros@epav.pt",
    "designacao_contrato": "Reparação do muro e executar escada Metálica Exterior, fundações da Escada para Escolas EPAV Colares e Sintra",
    "descricao": "Reparação do muro para contenção de terras para a Escola EPAV, em Colares e executar escada Metálica Exterior, fundações da Escada, partir o murete da base de apoio da escada e portão e guarda da escada e na Escola EPAV, em Sintra.",
    "preco_base": "53.425,00 EUR",
    "prazo_execucao": "90 DIAS",
    "prazo_apresentacao_propostas": "03-09-2025 17:30",
    "fundos_eu": "Não",
    "plataforma_eletronica": "VORTAL",
    "url_procedimento": "https://community.vortal.biz/public/",
    "autor_nome": "José Luís Furtado",
    "autor_cargo": "Gerente"
  },
  {
    "numero_procedimento": "N/A",
    "entidade": "Unidade Local de Saúde do Alentejo Central, E.P.E",
    "link": "https://diariodarepublica.pt/dr/detalhe/contrato-publico/22367-932875489",
    "detalhes_completos": "1 - IDENTIFICAÇÃO E CONTACTOS DA ENTIDADE ADJUDICANTE\nDesignação da entidade adjudicante: Unidade Local de Saúde do Alentejo Central, E.P.E\nNIPC: 508085888\nEndereço: Largo Sr. da Pobreza\nCódigo postal: 7000-811\nLocalidade: Évora\nPaís: Portugal\nNUT III: PT187\nDistrito: Évora\nConcelho: Évora\nFreguesia: Todas\nTelefone: 266740111\nFax: 266744212\nEndereço da Entidade (URL): www.hevora.min-saude.pt\nEndereço Eletrónico: concursos.aprov@ulsac.min-saude.pt\neDelivery Gateway (URL): https://community.vortal.biz/public/\nFunção da Organização: Adquirente\nNorma jurídica da Entidade Adjudicante: Organismo de direito público\nÁrea de atividade da Autoridade Adjudicante: Saúde\n\n2 - JORNAL OFICIAL DA UNIÃO EUROPEIA\nO procedimento a que este anúncio diz respeito também é publicitado no Jornal Oficial da União Europeia? Sim\n\n3 - AVISO\nModelo de Anúncio: Concurso público\nData de Envio do Anúncio: 18-08-2025\n\n5 - PROCESSO\nTipo de Procedimento: Concurso público\nPreço base do procedimento: Sim\nValor do preço base do procedimento: 985.466,30 EUR\nProcedimento com lotes? Sim\nNº Máx. de Lotes Autorizado: 19\nNúmero máximo de lotes que podem ser adjudicados a um concorrente: 19\n\n6 - OBJETO DO CONTRATO\nNúmero de referência interna: 110017/26\nDesignação do contrato: Aquisição de serviços de diálise peritoneal na ULSAC e no domicílio\nDescrição: Aquisição de serviços de diálise peritoneal na ULSAC e no domicílio\nOpções: Não\nTipo de Contrato Principal: Aquisição de Bens Móveis\nTipo de Contrato: Aquisição de Bens Móveis\nClassificação CPV (Vocabulário Comum para os Contratos Públicos)\nObjeto principal\nVocabulário Principal: 33690000\nPreço base s/IVA: 985.466,30 EUR\nLotes: \nNº: LOT-0001\nDescrição do Lote: Lote 1\nPreço base s/IVA: 546.804,00 EUR\nClassificação CPV (Vocabulário Comum para os Contratos Públicos)\nObjeto principal\nVocabulário Principal: 33690000\nNº: LOT-0002\nDescrição do Lote: Lote 2\nPreço base s/IVA: 101.382,00 EUR\nClassificação CPV (Vocabulário Comum para os Contratos Públicos)\nObjeto principal\nVocabulário Principal: 33690000\nNº: LOT-0003\nDescrição do Lote: Lote 3\nPreço base s/IVA: 167.628,00 EUR\nClassificação CPV (Vocabulário Comum para os Contratos Públicos)\nObjeto principal\nVocabulário Principal: 33690000\nNº: LOT-0004\nDescrição do Lote: Lote 4\nPreço base s/IVA: 139.080,00 EUR\nClassificação CPV (Vocabulário Comum para os Contratos Públicos)\nObjeto principal\nVocabulário Principal: 33690000\nNº: LOT-0005\nDescrição do Lote: Lote 5\nPreço base s/IVA: 1.050,00 EUR\nClassificação CPV (Vocabulário Comum para os Contratos Públicos)\nObjeto principal\nVocabulário Principal: 33690000\nNº: LOT-0006\nDescrição do Lote: Lote 6\nPreço base s/IVA: 10.654,00 EUR\nClassificação CPV (Vocabulário Comum para os Contratos Públicos)\nObjeto principal\nVocabulário Principal: 33690000\nNº: LOT-0007\nDescrição do Lote: Lote 7\nPreço base s/IVA: 456,00 EUR\nClassificação CPV (Vocabulário Comum para os Contratos Públicos)\nObjeto principal\nVocabulário Principal: 33690000\nNº: LOT-0008\nDescrição do Lote: Lote 8\nPreço base s/IVA: 5.175,00 EUR\nClassificação CPV (Vocabulário Comum para os Contratos Públicos)\nObjeto principal\nVocabulário Principal: 33690000\nNº: LOT-0009\nDescrição do Lote: Lote 9\nPreço base s/IVA: 2.817,50 EUR\nClassificação CPV (Vocabulário Comum para os Contratos Públicos)\nObjeto principal\nVocabulário Principal: 33690000\nNº: LOT-0010\nDescrição do Lote: Lote 10\nPreço base s/IVA: 720,00 EUR\nClassificação CPV (Vocabulário Comum para os Contratos Públicos)\nObjeto principal\nVocabulário Principal: 33690000\nNº: LOT-0011\nDescrição do Lote: Lote 11\nPreço base s/IVA: 390,00 EUR\nClassificação CPV (Vocabulário Comum para os Contratos Públicos)\nObjeto principal\nVocabulário Principal: 33690000\nNº: LOT-0012\nDescrição do Lote: Lote 12\nPreço base s/IVA: 1.320,00 EUR\nClassificação CPV (Vocabulário Comum para os Contratos Públicos)\nObjeto principal\nVocabulário Principal: 33690000\nNº: LOT-0013\nDescrição do Lote: Lote 13\nPreço base s/IVA: 540,00 EUR\nClassificação CPV (Vocabulário Comum para os Contratos Públicos)\nObjeto principal\nVocabulário Principal: 33690000\nNº: LOT-0014\nDescrição do Lote: Lote 14\nPreço base s/IVA: 33,60 EUR\nClassificação CPV (Vocabulário Comum para os Contratos Públicos)\nObjeto principal\nVocabulário Principal: 33690000\nNº: LOT-0015\nDescrição do Lote: Lote 15\nPreço base s/IVA: 1.596,00 EUR\nClassificação CPV (Vocabulário Comum para os Contratos Públicos)\nObjeto principal\nVocabulário Principal: 33690000\nNº: LOT-0016\nDescrição do Lote: Lote 16\nPreço base s/IVA: 665,00 EUR\nClassificação CPV (Vocabulário Comum para os Contratos Públicos)\nObjeto principal\nVocabulário Principal: 33690000\nNº: LOT-0017\nDescrição do Lote: Lote 17\nPreço base s/IVA: 1.503,00 EUR\nClassificação CPV (Vocabulário Comum para os Contratos Públicos)\nObjeto principal\nVocabulário Principal: 33690000\nNº: LOT-0018\nDescrição do Lote: Lote 18\nPreço base s/IVA: 277,20 EUR\nClassificação CPV (Vocabulário Comum para os Contratos Públicos)\nObjeto principal\nVocabulário Principal: 33690000\nNº: LOT-0019\nDescrição do Lote: Lote 19\nPreço base s/IVA: 3.375,00 EUR\nClassificação CPV (Vocabulário Comum para os Contratos Públicos)\nObjeto principal\nVocabulário Principal: 33690000\n\n7 - INDICAÇÕES ADICIONAIS\nO contrato envolve aquisição conjunta (satisfação de várias entidades)? Não\nO contrato é adjudicado por uma central de compras? Não\n\n8 - TÉCNICAS\nO concurso destina-se à celebração de um acordo-quadro? Inexistência de acordo-quadro\nÉ utilizado um leilão eletrónico? Não\nÉ adotada uma fase de negociação? Não\nSistema de Aquisição Dinâmico: Inexistência de sistema de aquisição dinâmico\n\n9 - LOCAL DA EXECUÇÃO DO CONTRATO\nLOCAL DA EXECUÇÃO DO CONTRATO (PROCEDIMENTO)\nPaís: Portugal\nNUT III: PT187\nLocalidade: Évora\nDistrito: Évora\nConcelho: Évora\nFreguesia: União das Freguesias de Évora (São Mamede, Sé, São Pedro e Santo Antão)\nLOCAL DA EXECUÇÃO DO CONTRATO (LOTE)\nIdentificador do Lote: LOT-0001; LOT-0002; LOT-0003; LOT-0004; LOT-0005; LOT-0006; LOT-0007; LOT-0008; LOT-0009; LOT-0010; LOT-0011; LOT-0012; LOT-0013; LOT-0014; LOT-0015; LOT-0016; LOT-0017; LOT-0018; LOT-0019\nPaís: Portugal\nNUT III: PT187\nLocalidade: Évora\nDistrito: Évora\nConcelho: Évora\nFreguesia: União das Freguesias de Évora (São Mamede, Sé, São Pedro e Santo Antão)\n\n10 - PRAZO DE EXECUÇÃO DO CONTRATO\nIdentificador do Lote: LOT-0001; LOT-0002; LOT-0003; LOT-0004; LOT-0005; LOT-0006; LOT-0007; LOT-0008; LOT-0009; LOT-0010; LOT-0011; LOT-0012; LOT-0013; LOT-0014; LOT-0015; LOT-0016; LOT-0017; LOT-0018; LOT-0019\nPrazo de execução do contrato: 365 DIAS\nPrevisão de renovações: Não\n\n11 - FUNDOS EU\nIdentificador do Lote: LOT-0001; LOT-0002; LOT-0003; LOT-0004; LOT-0005; LOT-0006; LOT-0007; LOT-0008; LOT-0009; LOT-0010; LOT-0011; LOT-0012; LOT-0013; LOT-0014; LOT-0015; LOT-0016; LOT-0017; LOT-0018; LOT-0019\nTêm fundos EU? Não\n\n12 - DOCUMENTOS DE HABILITAÇÃO\nHabilitação para o exercício da atividade profissional: Não\n\n13 - CONDIÇÕES DE APRESENTAÇÃO\nPlataforma eletrónica utilizada pela entidade adjudicante: VORTAL\nURL para Apresentação: https://community.vortal.biz/public/\nAdmissibilidade da apresentação de propostas variantes: Não autorizado\nPrazo para apresentação das propostas: 17-09-2025 18:00\nPrazo durante o qual os concorrentes são obrigados a manter as respetivas propostas: 120 dias a contar do termo do prazo para a apresentação das propostas\nApresentação de Catálogo Eletrónico: Permitido\nIndicação de Subcontratação na Proposta: Inexistência de indicação de subcontratação\n\n14 - PRESTAÇÃO DE CAUÇÃO\nPrestação de caução: Sim\nPercentagem: 5%\nDescrição da Garantia Exigida: 5\n\n15 - FORNECIMENTO DAS PEÇAS DO CONCURSO, APRESENTAÇÃO DE PEDIDOS DE PARTICIPAÇÃO E APRESENTAÇÃO DAS PROPOSTAS\nLink para acesso às peças do concurso (URL): https://community.vortal.biz/Public/public-tender-documents/SXpvSWdhVVNEbWFxTytGbklZQ1JXTTlnN0YyYVgyQnV3N2JHWHFEU0FBcE5LS3MrUzg3eTYwZkZCeThaL0MrU1dkYVpZMUgyRXlJb28zOEo3L1NHNGc9PWkpNG9z\n\n20 - OUTROS REQUISITOS\nIdentificador do Lote: LOT-0001; LOT-0002; LOT-0003; LOT-0004; LOT-0005; LOT-0006; LOT-0007; LOT-0008; LOT-0009; LOT-0010; LOT-0011; LOT-0012; LOT-0013; LOT-0014; LOT-0015; LOT-0016; LOT-0017; LOT-0018; LOT-0019\nInformação sobre contratos reservados. Aplica-se a contratos reservados (54º-A)? Não\n\n21 - CRITÉRIO DE ADJUDICAÇÃO\nO Critério de adjudicação é diferenciado por lote? Não\nMultifator: Não\nMonofator:\nNome: Preço\n\n24 - CONDIÇÕES DO CONTRATO\nIdentificador do Lote: LOT-0001; LOT-0002; LOT-0003; LOT-0004; LOT-0005; LOT-0006; LOT-0007; LOT-0008; LOT-0009; LOT-0010; LOT-0011; LOT-0012; LOT-0013; LOT-0014; LOT-0015; LOT-0016; LOT-0017; LOT-0018; LOT-0019\nFaturação Eletrónica: Permitido\nObrigação de Subcontratação:\nCódigo da Obrigação de Subcontratação: Não é aplicável nenhuma obrigação de subcontratação.\n\n25 - COMPRA PÚBLICA ESTRATÉGICA\nCompra Pública Estratégica: Inexistência de contratação pública estratégica\n\n26 - INFORMAÇÕES ADICIONAIS\nIdentificador do Lote: LOT-0001; LOT-0002; LOT-0003; LOT-0004; LOT-0005; LOT-0006; LOT-0007; LOT-0008; LOT-0009; LOT-0010; LOT-0011; LOT-0012; LOT-0013; LOT-0014; LOT-0015; LOT-0016; LOT-0017; LOT-0018; LOT-0019\nContrato adequado para PME: Sim\nCobertura ACP (Acordo dos Contratos Públicos da Organização Mundial do Comércio): Não\n\n27 - IDENTIFICAÇÃO E CONTACTOS DO ÓRGÃO DE RECURSOS ADMINISTRATIVOS\nDesignação: Unidade Local de Saúde do Alentejo Central E.P.E.\nEndereço: Largo Sr. da Pobreza\nCódigo postal: 7000-811\nLocalidade: Évora\nTelefone: +351 266740111\nFax: +351 266744212\nEndereço eletrónico: concursos.aprov@ulsac.min-saude.pt\n\n28 - IDENTIFICAÇÃO DO(S) AUTOR(ES) DE ANÚNCIO\nNome: Vitor Rui Gomes Fialho\nCargo: Presidente do Conselho de Administração\n419442044",
    "nipc": "508085888",
    "distrito": "Évora",
    "concelho": "Évora",
    "freguesia": "Todas",
    "site": "www.hevora.min-saude.pt",
    "email": "concursos.aprov@ulsac.min-saude.pt",
    "designacao_contrato": "Aquisição de serviços de diálise peritoneal na ULSAC e no domicílio",
    "descricao": "Aquisição de serviços de diálise peritoneal na ULSAC e no domicílio",
    "preco_base": "985.466,30 EUR",
    "prazo_execucao": "365 DIAS",
    "prazo_apresentacao_propostas": "17-09-2025 18:00",
    "fundos_eu": "Não",
    "plataforma_eletronica": "VORTAL",
    "url_procedimento": "https://community.vortal.biz/public/",
    "autor_nome": "Vitor Rui Gomes Fialho",
    "autor_cargo": "Presidente do Conselho de Administração"
  },
  {
    "numero_procedimento": "N/A",
    "entidade": "Infraestruturas de Portugal",
    "link": "https://diariodarepublica.pt/dr/detalhe/contrato-publico/22370-932875490",
    "detalhes_completos": "Alteração do Anúncio de procedimento n.º 21005/2025, de 2025-08-05, com o ID 419394911\n\n1 - IDENTIFICAÇÃO E CONTACTOS DA ENTIDADE ADJUDICANTE\nDesignação da entidade adjudicante: Infraestruturas de Portugal\nNIPC: 503933813\nServiço/Órgão/Pessoa de contacto: Direção de Compras e Logística - Departamento de Compras - Edifício 2\nEndereço: Praça da Portagem\nCódigo postal: 2809-013\nLocalidade: Almada\nPaís: Portugal\nNUT III: PT170\nDistrito: Setúbal\nConcelho: Almada\nFreguesia: União das Freguesias de Almada, Cova da Piedade, Pragal e Cacilhas\nTelefone:  212 879 300 \nFax: 21 287 90 00\nEndereço da Entidade (URL): www.infraestruturasdeportugal.pt\nEndereço Eletrónico: dcl@infraestruturasdeportugal.pt\nFunção da Organização: Adquirente\nNorma jurídica da Entidade Adjudicante: Organismo de direito público\nÁrea de atividade da Entidade Adjudicante: Serviços ferroviários\n\n2 - JORNAL OFICIAL DA UNIÃO EUROPEIA\nO procedimento a que este anúncio diz respeito também é publicitado no Jornal Oficial da União Europeia? Não\n\n3 - AVISO\nModelo de Anúncio: Concurso público\nData de Envio do Anúncio: 20-08-2025\n\n5 - PROCESSO\nTipo de Procedimento: Concurso público\nPreço base do procedimento: Sim\nValor do preço base do procedimento: 400.000,00 EUR\nProcedimento com lotes? Não\n\n6 - OBJETO DO CONTRATO\nNúmero de referência interna: 10019059\nDesignação do contrato: Empreitada - EN106 - PASSAGEM HIDRÁULICA (KM 17+950) - REABILITAÇÃO E REFORÇO DA OBRA DE ARTE\nDescrição:  EN106 - PASSAGEM HIDRÁULICA (KM 17+950) - REABILITAÇÃO E REFORÇO DA OBRA DE ARTE\nTipo de Contrato Principal: Empreitada de Obras Públicas\nTipo de Contrato: Empreitada de Obras Públicas\nClassificação CPV (Vocabulário Comum para os Contratos Públicos)\nObjeto principal\nVocabulário Principal: 45221119\nPreço base s/IVA: 400.000,00 EUR\n\n7 - INDICAÇÕES ADICIONAIS\nO contrato envolve aquisição conjunta (satisfação de várias entidades)? Não\nO contrato é adjudicado por uma central de compras? Não\n\n8 - TÉCNICAS\nO concurso destina-se à celebração de um acordo-quadro? Inexistência de acordo-quadro\nÉ utilizado um leilão eletrónico? Não\nÉ adotada uma fase de negociação? Não\nSistema de Aquisição Dinâmico: Inexistência de sistema de aquisição dinâmico\n\n9 - LOCAL DA EXECUÇÃO DO CONTRATO\nLOCAL DA EXECUÇÃO DO CONTRATO (PROCEDIMENTO)\nPaís: Portugal\nNUT III: PT11C\nLocalidade: UF de Cristelos, Boim e Ordem\nDistrito: Porto\nConcelho: Lousada\nFreguesia: União das Freguesias de Cristelos, Boim e Ordem\n\n10 - PRAZO DE EXECUÇÃO DO CONTRATO\nPrazo de execução do contrato: 150 DIAS\nPrevisão de renovações: Não\n\n11 - FUNDOS EU\nTêm fundos EU? Não\n\n12 - DOCUMENTOS DE HABILITAÇÃO\nHabilitação para o exercício da atividade profissional: Sim\nTipo: Alvará\nDescrição: Alvará de construção a apresentar pelo adjudicatário, emitido pelo Instituto dos Mercados Públicos, do Imobiliário e da Construção, I.P.: 1.ª Subcategoria da 2.ª Categoria e da classe que cubra o valor global da proposta; 5.ª Subcategoria da 2.ª Categoria deve cobrir o valor dos trabalhos correspondentes\n\n13 - CONDIÇÕES DE APRESENTAÇÃO\nPlataforma eletrónica utilizada pela entidade adjudicante: ANOGOV\nURL para Apresentação: https://www.anogov.com/infraestruturasdeportugal-ip/faces/\nAdmissibilidade da apresentação de propostas variantes: Não autorizado\nPrazo para apresentação das propostas: 12-09-2025 17:00\nPrazo durante o qual os concorrentes são obrigados a manter as respetivas propostas: 120 dias a contar do termo do prazo para a apresentação das propostas\nApresentação de Catálogo Eletrónico: Não autorizado\nIndicação de Subcontratação na Proposta: Inexistência de indicação de subcontratação\n\n14 - PRESTAÇÃO DE CAUÇÃO\nPrestação de caução: Sim\nPercentagem: 5%\nDescrição da Garantia Exigida: 5% do preço contratual\n\n15 - FORNECIMENTO DAS PEÇAS DO CONCURSO, APRESENTAÇÃO DE PEDIDOS DE PARTICIPAÇÃO E APRESENTAÇÃO DAS PROPOSTAS\nLink para acesso às peças do concurso (URL): https://www.anogov.com/infraestruturasdeportugal-ip/faces/app/acessoDocs.jsp?codigoAcesso=q6PEoARDQrW0GnjYMSnUl5IOMu9ijCY0ybMflHB6P5BaarBRDv\n\n20 - OUTROS REQUISITOS\nInformação sobre contratos reservados. Aplica-se a contratos reservados (54º-A)? Não\n\n21 - CRITÉRIO DE ADJUDICAÇÃO\nMultifator: Sim\nFator: \nNome: Preço\nPonderação: 80%\nSubfatores: Não\nFator: \nNome: Qualidade\nPonderação: 20%\nSubfatores: Sim\nSubfatores: \nNome: Memória descritiva e justificativa\nPonderação : 30%; \nNome: Programa de trabalhos\nPonderação : 60%; \nNome: Cronograma Financeiro\nPonderação : 10%; \n\n24 - CONDIÇÕES DO CONTRATO\nFaturação Eletrónica: Permitido\nObrigação de Subcontratação:\nCódigo da Obrigação de Subcontratação: Não é aplicável nenhuma obrigação de subcontratação.\n\n25 - COMPRA PÚBLICA ESTRATÉGICA\nCompra Pública Estratégica: Redução dos impactos ambientais\nDescrição do Processo de Adjudicação Estratégico: De acordo com as peças de concurso\nCritérios de contratos Públicos Ecológicos: Critérios de contratação pública ecológica nacional\nCategorias da estratégia nacional: Conceção, construção, reabilitação e conservação de estradas\nDiretiva Veículos Não Poluentes: Não\nCritério de Acessibilidade: Os critérios de acessibilidade para as pessoas com deficiência não estão incluídos porque o contrato não se destina a pessoas singulares\n\n26 - INFORMAÇÕES ADICIONAIS\nContrato adequado para PME: Sim\nCobertura ACP (Acordo dos Contratos Públicos da Organização Mundial do Comércio): Não\n\n27 - IDENTIFICAÇÃO E CONTACTOS DO ÓRGÃO DE RECURSOS ADMINISTRATIVOS\nDesignação: Conselho de Administração da Infraestruturas de Portugal, S.A.\nEndereço: Praça da Portagem\nCódigo postal: 2809-013\nLocalidade: Almada\nEndereço eletrónico: contratos@infraestruturasdeportugal.pt\n\n28 - IDENTIFICAÇÃO DO(S) AUTOR(ES) DE ANÚNCIO\nNome: Margarida Veloso\nCargo: Diretora Adjunta de Compras e Logística (em acumulação Dir. Departamento de Compras)\n\n29 - ALTERAÇÃO\nMotivo da Alteração: Informações atualizadas\nIdentificador da Versão do Anúncio a Alterar: ac3a2cbb-394a-4319-b182-d80c835d43e3-01\nIdentificador das Secções Alteradas do Anúncio Anterior: Condições de Apresentação\nDescrição das Alterações: Prazo para apresentação das propostas: 12 de setembro de 2025\nAlteração dos Documentos do Concurso: Não\n419451902",
    "nipc": "503933813",
    "distrito": "Setúbal",
    "concelho": "Almada",
    "freguesia": "União das Freguesias de Almada, Cova da Piedade, Pragal e Cacilhas",
    "site": "www.infraestruturasdeportugal.pt",
    "email": "dcl@infraestruturasdeportugal.pt",
    "designacao_contrato": "Empreitada - EN106 - PASSAGEM HIDRÁULICA (KM 17+950) - REABILITAÇÃO E REFORÇO DA OBRA DE ARTE",
    "descricao": "EN106 - PASSAGEM HIDRÁULICA (KM 17+950) - REABILITAÇÃO E REFORÇO DA OBRA DE ARTE",
    "preco_base": "400.000,00 EUR",
    "prazo_execucao": "150 DIAS",
    "prazo_apresentacao_propostas": "12-09-2025 17:00",
    "fundos_eu": "Não",
    "plataforma_eletronica": "ANOGOV",
    "url_procedimento": "https://www.anogov.com/infraestruturasdeportugal-ip/faces/",
    "autor_nome": "Margarida Veloso",
    "autor_cargo": "Diretora Adjunta de Compras e Logística (em acumulação Dir. Departamento de Compras)"
  },
  {
    "numero_procedimento": "N/A",
    "entidade": "Infraestruturas de Portugal",
    "link": "https://diariodarepublica.pt/dr/detalhe/contrato-publico/22371-932875491",
    "detalhes_completos": "1 - IDENTIFICAÇÃO E CONTACTOS DA ENTIDADE ADJUDICANTE\nDesignação da entidade adjudicante: Infraestruturas de Portugal\nNIPC: 503933813\nServiço/Órgão/Pessoa de contacto: Direção de Compras e Logística - Departamento de Compras - Edifício 2\nEndereço: Praça da Portagem\nCódigo postal: 2809-013\nLocalidade: Almada\nPaís: Portugal\nNUT III: PT170\nDistrito: Setúbal\nConcelho: Almada\nFreguesia: União das Freguesias de Almada, Cova da Piedade, Pragal e Cacilhas\nTelefone:  212 879 300 \nFax: 21 287 90 00\nEndereço da Entidade (URL): www.infraestruturasdeportugal.pt\nEndereço Eletrónico: dcl@infraestruturasdeportugal.pt\nFunção da Organização: Adquirente\nNorma jurídica da Entidade Adjudicante: Organismo de direito público\nÁrea de atividade da Entidade Adjudicante: Serviços ferroviários\n\n2 - JORNAL OFICIAL DA UNIÃO EUROPEIA\nO procedimento a que este anúncio diz respeito também é publicitado no Jornal Oficial da União Europeia? Não\n\n3 - AVISO\nModelo de Anúncio: Concurso público\nData de Envio do Anúncio: 20-08-2025\n\n5 - PROCESSO\nTipo de Procedimento: Concurso público\nPreço base do procedimento: Sim\nValor do preço base do procedimento: 740.000,00 EUR\nProcedimento com lotes? Não\n\n6 - OBJETO DO CONTRATO\nNúmero de referência interna: 10020747\nDesignação do contrato: EMPREITADA - L. BEIRA ALTA - ESTAÇÃO DA GUARDA - CONSTRUÇÃO DE ARMAZÉM PARA DIREÇÃO DA REDE RODOVIÁRIA E DIREÇÃO DA REDE FERROVIÁRIA\nDescrição: L. BEIRA ALTA - ESTAÇÃO DA GUARDA - CONSTRUÇÃO DE ARMAZÉM PARA DIREÇÃO DA REDE RODOVIÁRIA E DIREÇÃO DA REDE FERROVIÁRIA\nTipo de Contrato Principal: Empreitada de Obras Públicas\nTipo de Contrato: Empreitada de Obras Públicas\nClassificação CPV (Vocabulário Comum para os Contratos Públicos)\nObjeto principal\nVocabulário Principal: 45210000\nPreço base s/IVA: 740.000,00 EUR\n\n7 - INDICAÇÕES ADICIONAIS\nO contrato envolve aquisição conjunta (satisfação de várias entidades)? Não\nO contrato é adjudicado por uma central de compras? Não\n\n8 - TÉCNICAS\nO concurso destina-se à celebração de um acordo-quadro? Inexistência de acordo-quadro\nÉ utilizado um leilão eletrónico? Não\nÉ adotada uma fase de negociação? Não\nSistema de Aquisição Dinâmico: Inexistência de sistema de aquisição dinâmico\n\n9 - LOCAL DA EXECUÇÃO DO CONTRATO\nLOCAL DA EXECUÇÃO DO CONTRATO (PROCEDIMENTO)\nPaís: Portugal\nNUT III: PT16J\nLocalidade: Guarda\nDistrito: Guarda\nConcelho: Guarda\nFreguesia: Freguesia de Guarda\n\n10 - PRAZO DE EXECUÇÃO DO CONTRATO\nPrazo de execução do contrato: 240 DIAS\nPrevisão de renovações: Não\n\n11 - FUNDOS EU\nTêm fundos EU? Não\n\n12 - DOCUMENTOS DE HABILITAÇÃO\nHabilitação para o exercício da atividade profissional: Sim\nTipo: Alvará\nDescrição: Da 1ª Subcategoria da 1ª Categoria na classe que cubra o valor da empreitada;¿ Da 2ª, 4º e 5º Subcategorias da 1º Categoria, 1ª e 6ª Subcategorias da 2ª Categoria e, 1ª e 2º Subcategorias da 5ª Categoria, na classe que cubra o valor dos trabalhos especializados correspondentes\n\n13 - CONDIÇÕES DE APRESENTAÇÃO\nPlataforma eletrónica utilizada pela entidade adjudicante: ANOGOV\nURL para Apresentação: https://www.anogov.com/infraestruturasdeportugal-ip/faces/\nAdmissibilidade da apresentação de propostas variantes: Não autorizado\nPrazo para apresentação das propostas: 19-09-2025 17:00\nPrazo durante o qual os concorrentes são obrigados a manter as respetivas propostas: 120 dias a contar do termo do prazo para a apresentação das propostas\nApresentação de Catálogo Eletrónico: Não autorizado\nIndicação de Subcontratação na Proposta: Inexistência de indicação de subcontratação\n\n14 - PRESTAÇÃO DE CAUÇÃO\nPrestação de caução: Sim\nPercentagem: 5%\nDescrição da Garantia Exigida: 5,00% do preço contratual\n\n15 - FORNECIMENTO DAS PEÇAS DO CONCURSO, APRESENTAÇÃO DE PEDIDOS DE PARTICIPAÇÃO E APRESENTAÇÃO DAS PROPOSTAS\nLink para acesso às peças do concurso (URL): https://www.anogov.com/infraestruturasdeportugal-ip/faces/app/acessoDocs.jsp?codigoAcesso=fPjOQIMnpOe19ZN46OwNJGMpXfevEMVjzVLOTS5LPvdgZ5z6kl\n\n20 - OUTROS REQUISITOS\nInformação sobre contratos reservados. Aplica-se a contratos reservados (54º-A)? Não\n\n21 - CRITÉRIO DE ADJUDICAÇÃO\nMultifator: Não\nMonofator:\nNome: Preço\n\n24 - CONDIÇÕES DO CONTRATO\nFaturação Eletrónica: Permitido\nObrigação de Subcontratação:\nCódigo da Obrigação de Subcontratação: Não é aplicável nenhuma obrigação de subcontratação.\n\n25 - COMPRA PÚBLICA ESTRATÉGICA\nCompra Pública Estratégica: Realização dos objetivos sociais\nContratos Públicos Sociais: Outros\nCritério de Acessibilidade: Os critérios de acessibilidade para as pessoas com deficiência não estão incluídos porque o contrato não se destina a pessoas singulares\n\n26 - INFORMAÇÕES ADICIONAIS\nContrato adequado para PME: Sim\nCobertura ACP (Acordo dos Contratos Públicos da Organização Mundial do Comércio): Não\n\n27 - IDENTIFICAÇÃO E CONTACTOS DO ÓRGÃO DE RECURSOS ADMINISTRATIVOS\nDesignação: Conselho de Administração da Infraestruturas de Portugal, S.A.\nEndereço: Praça da Portagem\nCódigo postal: 2809-013\nLocalidade: Almada\nEndereço eletrónico: contratos@infraestruturasdeportugal.pt\n\n28 - IDENTIFICAÇÃO DO(S) AUTOR(ES) DE ANÚNCIO\nNome: Margarida Veloso\nCargo: Diretora Adjunta de Compras e Logística (em acumulação Dir. Departamento de Compras)\n419452348",
    "nipc": "503933813",
    "distrito": "Setúbal",
    "concelho": "Almada",
    "freguesia": "União das Freguesias de Almada, Cova da Piedade, Pragal e Cacilhas",
    "site": "www.infraestruturasdeportugal.pt",
    "email": "dcl@infraestruturasdeportugal.pt",
    "designacao_contrato": "EMPREITADA - L. BEIRA ALTA - ESTAÇÃO DA GUARDA - CONSTRUÇÃO DE ARMAZÉM PARA DIREÇÃO DA REDE RODOVIÁRIA E DIREÇÃO DA REDE FERROVIÁRIA",
    "descricao": "L. BEIRA ALTA - ESTAÇÃO DA GUARDA - CONSTRUÇÃO DE ARMAZÉM PARA DIREÇÃO DA REDE RODOVIÁRIA E DIREÇÃO DA REDE FERROVIÁRIA",
    "preco_base": "740.000,00 EUR",
    "prazo_execucao": "240 DIAS",
    "prazo_apresentacao_propostas": "19-09-2025 17:00",
    "fundos_eu": "Não",
    "plataforma_eletronica": "ANOGOV",
    "url_procedimento": "https://www.anogov.com/infraestruturasdeportugal-ip/faces/",
    "autor_nome": "Margarida Veloso",
    "autor_cargo": "Diretora Adjunta de Compras e Logística (em acumulação Dir. Departamento de Compras)"
  },
  {
    "numero_procedimento": "N/A",
    "entidade": "Agência para a Modernização Administrativa, I.P.",
    "link": "https://diariodarepublica.pt/dr/detalhe/contrato-publico/22372-932875492",
    "detalhes_completos": "1 - IDENTIFICAÇÃO E CONTACTOS DA ENTIDADE ADJUDICANTE\nDesignação da entidade adjudicante: Agência para a Modernização Administrativa, I.P.\nNIPC: 508184509\nServiço/Órgão/Pessoa de contacto: Divisão de Contratação Pública\nEndereço: Rua de Sta. Marta, n.º 55\nCódigo postal: 1150-294\nLocalidade: Lisboa\nPaís: Portugal\nNUT III: PT170\nDistrito: Lisboa\nConcelho: Lisboa\nFreguesia: Freguesia de Santo António - Lisboa\nTelefone: 217231200\nFax: 217231220\nEndereço da Entidade (URL): www.ama.gov.pt\nEndereço Eletrónico: contratacao@ama.gov.pt\neDelivery Gateway (URL): https://www.acingov.pt\nFunção da Organização: Adquirente\nSubfunção da Organização: Organização que recebe as propostas\nNorma jurídica da Entidade Adjudicante: Organismo de direito público\nÁrea de atividade da Autoridade Adjudicante: Serviços públicos das administrações públicas\n\n2 - JORNAL OFICIAL DA UNIÃO EUROPEIA\nO procedimento a que este anúncio diz respeito também é publicitado no Jornal Oficial da União Europeia? Não\n\n3 - AVISO\nModelo de Anúncio: Concurso público\nData de Envio do Anúncio: 21-08-2025\n\n5 - PROCESSO\nTipo de Procedimento: Concurso público\nPreço base do procedimento: Sim\nValor do preço base do procedimento: 807.181,81 EUR\nProcedimento com lotes? Não\n\n6 - OBJETO DO CONTRATO\nNúmero de referência interna: 134/2025/DCP/EGI\nDesignação do contrato: EMPREITADA DE REMODELAÇÃO DE LOJA CIDADÃO DE FARO E SUBSTITUIÇÃO DOS SISTEMAS DE AVAC E ILUMINAÇÃO\nDescrição: EMPREITADA DE REMODELAÇÃO DE LOJA CIDADÃO DE FARO E SUBSTITUIÇÃO DOS SISTEMAS DE AVAC E ILUMINAÇÃO\nTipo de Contrato Principal: Empreitada de Obras Públicas\nTipo de Contrato: Empreitada de Obras Públicas\nClassificação CPV (Vocabulário Comum para os Contratos Públicos)\nObjeto principal\nVocabulário Principal: 45454000\nPreço base s/IVA: 94.936,56 EUR\nObjeto Complementar\nVocabulário Principal: 45310000\nPreço base s/IVA: 147.391,50 EUR\nObjeto Complementar\nVocabulário Principal: 45331000\nPreço base s/IVA: 564.853,75 EUR\n\n7 - INDICAÇÕES ADICIONAIS\nO contrato envolve aquisição conjunta (satisfação de várias entidades)? Não\nO contrato é adjudicado por uma central de compras? Não\n\n8 - TÉCNICAS\nO concurso destina-se à celebração de um acordo-quadro? Inexistência de acordo-quadro\nÉ utilizado um leilão eletrónico? Não\nÉ adotada uma fase de negociação? Não\nSistema de Aquisição Dinâmico: Inexistência de sistema de aquisição dinâmico\n\n9 - LOCAL DA EXECUÇÃO DO CONTRATO\nLOCAL DA EXECUÇÃO DO CONTRATO (PROCEDIMENTO)\nPaís: Portugal\nNUT III: PT150\nLocalidade: Faro\nDistrito: Faro\nConcelho: Faro\nFreguesia: Todas\n\n10 - PRAZO DE EXECUÇÃO DO CONTRATO\nPrazo de execução do contrato: 150 DIAS\nPrevisão de renovações: Não\n\n11 - FUNDOS EU\nTêm fundos EU? Sim\n\n12 - DOCUMENTOS DE HABILITAÇÃO\nHabilitação para o exercício da atividade profissional: Sim\nTipo: Alvará\nDescrição: 4.ª classe de alvará, nos termos do disposto no n.º 1 da Portaria n.º 212/2022, de 23 de agosto:\n1.ª Categoria  Edifícios e Património Construído Empreiteiro Geral ou construtor Geral de Edifícios de Construção tradicional;\n5.ª Subcategoria  Estuques, pinturas e outros revestimentos.\n6.ª Subcategoria - Carpintarias\n8.ª Subcategoria - Canalizações e condutas em edifícios.\n4.ª Categoria  Instalações elétricas e mecânicas;\n1.ª Subcategoria  Instalações elétricas de utilização de baixa tensão com potência até 50 kVA.\n4.ª Subcategoria  Redes e instalações elétricas de tensão de serviço até 30 kV.\n9.ª Subcategoria  Infraestruturas de telecomunicações\n12.ª Subcategoria  Aquecimento, ventilação, ar condicionado e refrigeração\n18.ª Subcategoria  Gestão técnica centralizada\n5.ª Categoria  Outros trabalhos\n1.ª Subcategoria  Demolições\n11.ª Subcategoria  Impermeabilizações e isolamentos\n12.ª Subcategoria  Andaimes e outras estruturas provisórias.\n\n13 - CONDIÇÕES DE APRESENTAÇÃO\nPlataforma eletrónica utilizada pela entidade adjudicante: ACIN\nURL para Apresentação: https://www.acingov.pt\nAdmissibilidade da apresentação de propostas variantes: Não autorizado\nPrazo para apresentação das propostas: 09-09-2025 23:59\nPrazo durante o qual os concorrentes são obrigados a manter as respetivas propostas: 180 dias a contar do termo do prazo para a apresentação das propostas\nIndicação de Subcontratação na Proposta: Inexistência de indicação de subcontratação\n\n14 - PRESTAÇÃO DE CAUÇÃO\nPrestação de caução: Sim\nPercentagem: 5%\nDescrição da Garantia Exigida: O valor da caução é de 5.00% do preço contratual.\n\n15 - FORNECIMENTO DAS PEÇAS DO CONCURSO, APRESENTAÇÃO DE PEDIDOS DE PARTICIPAÇÃO E APRESENTAÇÃO DAS PROPOSTAS\nLink para acesso às peças do concurso (URL): https://www.acingov.pt/acingovprod/2/zonaPublica/zona_publica_c/donwloadProcedurePiece/OTM1Nzgz\n\n20 - OUTROS REQUISITOS\nInformação sobre contratos reservados. Aplica-se a contratos reservados (54º-A)? Não\n\n21 - CRITÉRIO DE ADJUDICAÇÃO\nMultifator: Sim\nFator: \nNome: Preço\nPonderação: 60%\nSubfatores: Não\nFator: \nNome: Qualidade\nPonderação: 40%\nSubfatores: Não\n\n24 - CONDIÇÕES DO CONTRATO\nFaturação Eletrónica: Permitido\nObrigação de Subcontratação:\nCódigo da Obrigação de Subcontratação: Não é aplicável nenhuma obrigação de subcontratação.\n\n25 - COMPRA PÚBLICA ESTRATÉGICA\nCompra Pública Estratégica: Inexistência de contratação pública estratégica\n\n26 - INFORMAÇÕES ADICIONAIS\nContrato adequado para PME: Sim\nCobertura ACP (Acordo dos Contratos Públicos da Organização Mundial do Comércio): Não\n\n27 - IDENTIFICAÇÃO E CONTACTOS DO ÓRGÃO DE RECURSOS ADMINISTRATIVOS\nDesignação: Conselho Diretivo\nEndereço: Rua de Sta. Marta, n.º 55\nCódigo postal: 1150-294\nLocalidade: Lisboa\nTelefone: 217231200\nFax: \nEndereço eletrónico: contratacao@ama.gov.pt\nPrazo de interposição do recurso: 10 dias\n\n28 - IDENTIFICAÇÃO DO(S) AUTOR(ES) DE ANÚNCIO\nNome: Sofia Capela Lavrador\nCargo: Técnica Superior\n419453977",
    "nipc": "508184509",
    "distrito": "Lisboa",
    "concelho": "Lisboa",
    "freguesia": "Freguesia de Santo António - Lisboa",
    "site": "www.ama.gov.pt",
    "email": "contratacao@ama.gov.pt",
    "designacao_contrato": "EMPREITADA DE REMODELAÇÃO DE LOJA CIDADÃO DE FARO E SUBSTITUIÇÃO DOS SISTEMAS DE AVAC E ILUMINAÇÃO",
    "descricao": "EMPREITADA DE REMODELAÇÃO DE LOJA CIDADÃO DE FARO E SUBSTITUIÇÃO DOS SISTEMAS DE AVAC E ILUMINAÇÃO",
    "preco_base": "94.936,56 EUR",
    "prazo_execucao": "150 DIAS",
    "prazo_apresentacao_propostas": "09-09-2025 23:59",
    "fundos_eu": "Sim",
    "plataforma_eletronica": "ACIN",
    "url_procedimento": "https://www.acingov.pt",
    "autor_nome": "Sofia Capela Lavrador",
    "autor_cargo": "Técnica Superior"
  }
]