[
  {
    "numero_procedimento": "N/A",
    "entidade": "Comunidade Intermunicipal da Região de Coimbra",
    "link": "https://diariodarepublica.pt/dr/detalhe/contrato-publico/27646-941023866",
    "detalhes_completos": "Alteração do Anúncio de procedimento n.º 27039/2025, de 2025-10-13, com o ID 419648871\n\n1 - IDENTIFICAÇÃO E CONTACTOS DA ENTIDADE ADJUDICANTE\nDesignação da entidade adjudicante: Comunidade Intermunicipal da Região de Coimbra\nNIPC: 508354617\nEndereço: Rua do Brasil, 131\nCódigo postal: 3030-175\nLocalidade: Coimbra\nPaís: Portugal\nNUT III: PTZZZ\nDistrito: Todos\nConcelho: Todos\nFreguesia: Todas\nTelefone: 239795200\nEndereço da Entidade (URL): https://cim-regiaodecoimbra.pt\nEndereço Eletrónico: geral@cim-regiaodecoimbra.pt\neDelivery Gateway (URL): https://www.acingov.pt\nFunção da Organização: Adquirente\nNorma jurídica da Entidade Adjudicante: Organismo de direito público\nÁrea de atividade da Autoridade Adjudicante: Serviços públicos das administrações públicas\n\n2 - JORNAL OFICIAL DA UNIÃO EUROPEIA\nO procedimento a que este anúncio diz respeito também é publicitado no Jornal Oficial da União Europeia? Não\n\n3 - AVISO\nModelo de Anúncio: Concurso público\nData de Envio do Anúncio: 20-10-2025\n\n5 - PROCESSO\nTipo de Procedimento: Concurso público\nPreço base do procedimento: Sim\nValor do preço base do procedimento: 31.954,47 EUR\nProcedimento com lotes? Não\n\n6 - OBJETO DO CONTRATO\nNúmero de referência interna: CP23/2025\nDesignação do contrato: CP23/2025 - Criação e execução do plano de comunicação e de meios do HUB da Costa Atlântica da Região de Coimbra\nDescrição: CP23/2025 - Criação e execução do plano de comunicação e de meios do HUB da Costa Atlântica da Região de Coimbra\nTipo de Contrato Principal: Aquisição de Serviços\nTipo de Contrato: Aquisição de Serviços\nClassificação CPV (Vocabulário Comum para os Contratos Públicos)\nObjeto principal\nVocabulário Principal: 79342000\nPreço base s/IVA: 31.954,47 EUR\n\n7 - INDICAÇÕES ADICIONAIS\nO contrato envolve aquisição conjunta (satisfação de várias entidades)? Não\nO contrato é adjudicado por uma central de compras? Não\n\n8 - TÉCNICAS\nO concurso destina-se à celebração de um acordo-quadro? Inexistência de acordo-quadro\nÉ utilizado um leilão eletrónico? Não\nÉ adotada uma fase de negociação? Não\nSistema de Aquisição Dinâmico: Inexistência de sistema de aquisição dinâmico\n\n9 - LOCAL DA EXECUÇÃO DO CONTRATO\nLOCAL DA EXECUÇÃO DO CONTRATO (PROCEDIMENTO)\nPaís: Portugal\nNUT III: PT16E\nLocalidade: Freguesia de Santo António dos Olivais\nDistrito: Coimbra\nConcelho: Coimbra\nFreguesia: Freguesia de Santo António dos Olivais\n\n10 - PRAZO DE EXECUÇÃO DO CONTRATO\nPrazo de execução do contrato: 242 DIAS\nPrevisão de renovações: Não\n\n11 - FUNDOS EU\nTêm fundos EU? Não\n\n12 - DOCUMENTOS DE HABILITAÇÃO\nHabilitação para o exercício da atividade profissional: Não\n\n13 - CONDIÇÕES DE APRESENTAÇÃO\nPlataforma eletrónica utilizada pela entidade adjudicante: ACIN\nURL para Apresentação: https://www.acingov.pt\nAdmissibilidade da apresentação de propostas variantes: Não autorizado\nPrazo para apresentação das propostas: 22-10-2025 23:59\nPrazo durante o qual os concorrentes são obrigados a manter as respetivas propostas: 120 dias a contar do termo do prazo para a apresentação das propostas\nIndicação de Subcontratação na Proposta: Inexistência de indicação de subcontratação\n\n14 - PRESTAÇÃO DE CAUÇÃO\nPrestação de caução: Não\n\n15 - FORNECIMENTO DAS PEÇAS DO CONCURSO, APRESENTAÇÃO DE PEDIDOS DE PARTICIPAÇÃO E APRESENTAÇÃO DAS PROPOSTAS\nLink para acesso às peças do concurso (URL): https://www.acingov.pt/acingovprod/2/zonaPublica/zona_publica_c/donwloadProcedurePiece/OTg2MTkw\n\n20 - OUTROS REQUISITOS\nInformação sobre contratos reservados. Aplica-se a contratos reservados (54º-A)? Não\n\n21 - CRITÉRIO DE ADJUDICAÇÃO\nMultifator: Não\nMonofator:\nNome: Preço\n\n24 - CONDIÇÕES DO CONTRATO\nFaturação Eletrónica: Permitido\nObrigação de Subcontratação:\nCódigo da Obrigação de Subcontratação: Não é aplicável nenhuma obrigação de subcontratação.\n\n25 - COMPRA PÚBLICA ESTRATÉGICA\nCompra Pública Estratégica: Inexistência de contratação pública estratégica\n\n26 - INFORMAÇÕES ADICIONAIS\nContrato adequado para PME: Sim\nCobertura ACP (Acordo dos Contratos Públicos da Organização Mundial do Comércio): Não\n\n27 - IDENTIFICAÇÃO E CONTACTOS DO ÓRGÃO DE RECURSOS ADMINISTRATIVOS\nDesignação: Conselho Intermunicipal da Comunidade Intermunicipal da Região de Coimbra\nEndereço: Rua do Brasil, 131\nCódigo postal: 3030-175\nLocalidade: Coimbra\nTelefone: 239795200\nFax: 000000000\nEndereço eletrónico: geral@cim-regiaodecoimbra.pt\nPrazo de interposição do recurso: 5 dias\n\n28 - IDENTIFICAÇÃO DO(S) AUTOR(ES) DE ANÚNCIO\nNome: Jorge Brito\nCargo: Secretário Executivo Intermunicipal\n\n29 - ALTERAÇÃO\nMotivo da Alteração: Correção pelo editor\nIdentificador da Versão do Anúncio a Alterar: e6c9c9bb-f60a-4957-b9c5-a33ba7a3a097-01\nIdentificador das Secções Alteradas do Anúncio Anterior: Objeto do contrato\nDescrição das Alterações: O preço base inicialmente definido nas peças contemplava já o valor acrescido de IVA, pelo que verifica-se a necessidade de proceder à respetiva retificação. \nAlteração dos Documentos do Concurso: Sim\nData de alteração dos documentos do concurso: 17-10-2025\nIdentificador das Secções Alteradas do Anúncio Anterior: Condições de Apresentação\nDescrição das Alterações: Na sequência da retificação oficiosa às peças, verifica-se a necessidade de ter de proceder à prorrogação contratual do prazo. \nAlteração dos Documentos do Concurso: Não\n419671745",
    "nipc": "508354617",
    "distrito": "Todos",
    "concelho": "Todos",
    "freguesia": "Todas",
    "site": "https://cim-regiaodecoimbra.pt",
    "email": "geral@cim-regiaodecoimbra.pt",
    "designacao_contrato": "CP23/2025 - Criação e execução do plano de comunicação e de meios do HUB da Costa Atlântica da Região de Coimbra",
    "descricao": "CP23/2025 - Criação e execução do plano de comunicação e de meios do HUB da Costa Atlântica da Região de Coimbra",
    "preco_base": "31.954,47 EUR",
    "prazo_execucao": "242 DIAS",
    "prazo_apresentacao_propostas": "22-10-2025 23:59",
    "fundos_eu": "Não",
    "plataforma_eletronica": "ACIN",
    "url_procedimento": "https://www.acingov.pt",
    "autor_nome": "Jorge Brito",
    "autor_cargo": "Secretário Executivo Intermunicipal"
  },
  {
    "numero_procedimento": "N/A",
    "entidade": "Águas do Interior - Norte, E. I. M., S. A.",
    "link": "https://diariodarepublica.pt/dr/detalhe/contrato-publico/27648-941023867",
    "detalhes_completos": "1 - IDENTIFICAÇÃO E CONTACTOS DA ENTIDADE ADJUDICANTE\nDesignação da entidade adjudicante: Águas do Interior - Norte, E. I. M., S. A.\nNIPC: 515684473\nEndereço: Avenida Rainha Santa Isabel, nº 1\nCódigo postal: 5000-434\nLocalidade:  Vila Real \nPaís: Portugal\nNUT III: PT11D\nDistrito: Vila Real\nConcelho: Vila Real\nFreguesia: Todas\nTelefone: 309101101\nFax: 259321144\nEndereço Eletrónico: geral@adin.pt\neDelivery Gateway (URL): https://community.vortal.biz/public/\nFunção da Organização: Adquirente\nNorma jurídica da Entidade Adjudicante: Empresa pública\nÁrea de atividade da Entidade Adjudicante: Serviços urbanos de caminho de ferro, de elétricos, de tróleis ou de autocarros\n\n2 - JORNAL OFICIAL DA UNIÃO EUROPEIA\nO procedimento a que este anúncio diz respeito também é publicitado no Jornal Oficial da União Europeia? Não\n\n3 - AVISO\nModelo de Anúncio: Concurso público\nData de Envio do Anúncio: 20-10-2025\n\n5 - PROCESSO\nTipo de Procedimento: Concurso público\nPreço base do procedimento: Sim\nValor do preço base do procedimento: 85.000,00 EUR\nProcedimento com lotes? Não\n\n6 - OBJETO DO CONTRATO\nNúmero de referência interna: SACP - 48/2025\nDesignação do contrato: Aluguer de 3 Viaturas Ligeiras de Mercadorias\nDescrição: Aluguer de 3 Viaturas Ligeiras de Mercadorias\nTipo de Contrato Principal: Locação de Bens Móveis\nTipo de Contrato: Locação de Bens Móveis\nClassificação CPV (Vocabulário Comum para os Contratos Públicos)\nObjeto principal\nVocabulário Principal: 34100000\nPreço base s/IVA: 85.000,00 EUR\n\n7 - INDICAÇÕES ADICIONAIS\nO contrato envolve aquisição conjunta (satisfação de várias entidades)? Não\nO contrato é adjudicado por uma central de compras? Não\n\n8 - TÉCNICAS\nO concurso destina-se à celebração de um acordo-quadro? Inexistência de acordo-quadro\nÉ utilizado um leilão eletrónico? Não\nÉ adotada uma fase de negociação? Não\nSistema de Aquisição Dinâmico: Inexistência de sistema de aquisição dinâmico\n\n9 - LOCAL DA EXECUÇÃO DO CONTRATO\nLOCAL DA EXECUÇÃO DO CONTRATO (PROCEDIMENTO)\nPaís: Portugal\nNUT III: PT11D\nLocalidade: Vila Real\nDistrito: Vila Real\nConcelho: Vila Real\nFreguesia: Todas\n\n10 - PRAZO DE EXECUÇÃO DO CONTRATO\nPrazo de execução do contrato: 3 ANOS\nPrevisão de renovações: Não\n\n11 - FUNDOS EU\nTêm fundos EU? Não\n\n12 - DOCUMENTOS DE HABILITAÇÃO\nHabilitação para o exercício da atividade profissional: Não\n\n13 - CONDIÇÕES DE APRESENTAÇÃO\nPlataforma eletrónica utilizada pela entidade adjudicante: VORTAL\nURL para Apresentação: https://community.vortal.biz/public/\nAdmissibilidade da apresentação de propostas variantes: Não autorizado\nPrazo para apresentação das propostas: 30-10-2025 16:00\nPrazo durante o qual os concorrentes são obrigados a manter as respetivas propostas: 66 dias a contar do termo do prazo para a apresentação das propostas\nIndicação de Subcontratação na Proposta: Inexistência de indicação de subcontratação\n\n14 - PRESTAÇÃO DE CAUÇÃO\nPrestação de caução: Sim\nPercentagem: 10%\nDescrição da Garantia Exigida: Conforme Artº 90º do CCP\n\n15 - FORNECIMENTO DAS PEÇAS DO CONCURSO, APRESENTAÇÃO DE PEDIDOS DE PARTICIPAÇÃO E APRESENTAÇÃO DAS PROPOSTAS\nLink para acesso às peças do concurso (URL): https://community.vortal.biz/Public/public-tender-documents/ajlieWpLZERvY0ZWYUxxQ2VvUitmalRSaVV0VmJOUjlpNC84Ny8wZTRGclVQWWpOS1JHVzNzNGF5eUxmeVpPbUF5ZEpFbUFSWmR5NEw2aXZoT2kwNnc9PWUzWExp\n\n20 - OUTROS REQUISITOS\nInformação sobre contratos reservados. Aplica-se a contratos reservados (54º-A)? Não\n\n21 - CRITÉRIO DE ADJUDICAÇÃO\nMultifator: Não\nMonofator:\nNome: Outros\nOutro nome: Preço\n\n24 - CONDIÇÕES DO CONTRATO\nFaturação Eletrónica: Permitido\nObrigação de Subcontratação:\nCódigo da Obrigação de Subcontratação: Não é aplicável nenhuma obrigação de subcontratação.\n\n25 - COMPRA PÚBLICA ESTRATÉGICA\nCompra Pública Estratégica: Inexistência de contratação pública estratégica\n\n26 - INFORMAÇÕES ADICIONAIS\nContrato adequado para PME: Sim\nCobertura ACP (Acordo dos Contratos Públicos da Organização Mundial do Comércio): Não\n\n27 - IDENTIFICAÇÃO E CONTACTOS DO ÓRGÃO DE RECURSOS ADMINISTRATIVOS\nDesignação: Conselho de Administração\nEndereço: Av. Rainha Santa Isabel, Nº 1\nCódigo postal: 5000-434\nLocalidade: Vila Real\nTelefone: +351 309101101\nFax: +351 259321144\nEndereço eletrónico: geral@adin.pt\n\n28 - IDENTIFICAÇÃO DO(S) AUTOR(ES) DE ANÚNCIO\nNome: Antonio Alves Botelho\nCargo: Chefe do Setor Administrativo e Contratação Pública\n419679498",
    "nipc": "515684473",
    "distrito": "Vila Real",
    "concelho": "Vila Real",
    "freguesia": "Todas",
    "site": null,
    "email": "geral@adin.pt",
    "designacao_contrato": "Aluguer de 3 Viaturas Ligeiras de Mercadorias",
    "descricao": "Aluguer de 3 Viaturas Ligeiras de Mercadorias",
    "preco_base": "85.000,00 EUR",
    "prazo_execucao": "3 ANOS",
    "prazo_apresentacao_propostas": "30-10-2025 16:00",
    "fundos_eu": "Não",
    "plataforma_eletronica": "VORTAL",
    "url_procedimento": "https://community.vortal.biz/public/",
    "autor_nome": "Antonio Alves Botelho",
    "autor_cargo": "Chefe do Setor Administrativo e Contratação Pública"
  },
  {
    "numero_procedimento": "N/A",
    "entidade": "Hospital Distrital de Santarém, E. P. E.",
    "link": "https://diariodarepublica.pt/dr/detalhe/contrato-publico/27650-941023868",
    "detalhes_completos": "1 - IDENTIFICAÇÃO E CONTACTOS DA ENTIDADE ADJUDICANTE\nDesignação da entidade adjudicante: Hospital Distrital de Santarém, E. P. E.\nNIPC: 506361462\nEndereço: Av. Bernardo Santareno S/N\nCódigo postal: 2005-177\nLocalidade: Santarém\nPaís: Portugal\nNUT III: PT185\nDistrito: Santarém\nConcelho: Santarém\nFreguesia: União de Freguesias da Cidade de Santarém\nTelefone: 243300200\nFax: 243370220\nEndereço da Entidade (URL): www.hds.min-saude.pt\nEndereço Eletrónico: hdsca@hds.min-saude.pt\neDelivery Gateway (URL): https://community.vortal.biz/public/\nFunção da Organização: Adquirente\nNorma jurídica da Entidade Adjudicante: Organismo de direito público\nÁrea de atividade da Autoridade Adjudicante: Saúde\n\n2 - JORNAL OFICIAL DA UNIÃO EUROPEIA\nO procedimento a que este anúncio diz respeito também é publicitado no Jornal Oficial da União Europeia? Não\n\n3 - AVISO\nModelo de Anúncio: Concurso público\nData de Envio do Anúncio: 20-10-2025\n\n5 - PROCESSO\nTipo de Procedimento: Concurso público\nPreço base do procedimento: Sim\nValor do preço base do procedimento: 95.530,40 EUR\nProcedimento com lotes? Sim\nNº Máx. de Lotes Autorizado: 4\nNúmero máximo de lotes que podem ser adjudicados a um concorrente: 4\n\n6 - OBJETO DO CONTRATO\nNúmero de referência interna: 170022/2025\nDesignação do contrato: Aquisição e Instalação de Camas Elétricas e Carros de Emergência\nDescrição: Aquisição e Instalação de Camas Elétricas e Carros de Emergência\nTipo de Contrato Principal: Aquisição de Bens Móveis\nTipo de Contrato: Aquisição de Bens Móveis\nClassificação CPV (Vocabulário Comum para os Contratos Públicos)\nObjeto principal\nVocabulário Principal: 33192000\nPreço base s/IVA: 95.530,40 EUR\nLotes: \nNº: LOT-0001\nDescrição do Lote: Lote 1\nPreço base s/IVA: 7.000,00 EUR\nClassificação CPV (Vocabulário Comum para os Contratos Públicos)\nObjeto principal\nVocabulário Principal: 33192000\nNº: LOT-0002\nDescrição do Lote: Lote 2\nPreço base s/IVA: 35.000,00 EUR\nClassificação CPV (Vocabulário Comum para os Contratos Públicos)\nObjeto principal\nVocabulário Principal: 33192000\nNº: LOT-0003\nDescrição do Lote: Lote 3\nPreço base s/IVA: 48.000,00 EUR\nClassificação CPV (Vocabulário Comum para os Contratos Públicos)\nObjeto principal\nVocabulário Principal: 33192000\nNº: LOT-0004\nDescrição do Lote: Lote 4\nPreço base s/IVA: 5.530,40 EUR\nClassificação CPV (Vocabulário Comum para os Contratos Públicos)\nObjeto principal\nVocabulário Principal: 33192000\n\n7 - INDICAÇÕES ADICIONAIS\nO contrato envolve aquisição conjunta (satisfação de várias entidades)? Não\nO contrato é adjudicado por uma central de compras? Não\n\n8 - TÉCNICAS\nO concurso destina-se à celebração de um acordo-quadro? Inexistência de acordo-quadro\nÉ utilizado um leilão eletrónico? Não\nÉ adotada uma fase de negociação? Não\nSistema de Aquisição Dinâmico: Inexistência de sistema de aquisição dinâmico\n\n9 - LOCAL DA EXECUÇÃO DO CONTRATO\nLOCAL DA EXECUÇÃO DO CONTRATO (PROCEDIMENTO)\nPaís: Portugal\nNUT III: PT185\nLocalidade: Santarém\nDistrito: Santarém\nConcelho: Santarém\nFreguesia: União de Freguesias da Cidade de Santarém\nLOCAL DA EXECUÇÃO DO CONTRATO (LOTE)\nIdentificador do Lote: LOT-0001; LOT-0002; LOT-0003; LOT-0004\nPaís: Portugal\nNUT III: PT185\nLocalidade: Santarém\nDistrito: Santarém\nConcelho: Santarém\nFreguesia: União de Freguesias da Cidade de Santarém\n\n10 - PRAZO DE EXECUÇÃO DO CONTRATO\nIdentificador do Lote: LOT-0001; LOT-0002; LOT-0003; LOT-0004\nPrazo de execução do contrato: 2 MESES\nPrevisão de renovações: Não\n\n11 - FUNDOS EU\nIdentificador do Lote: LOT-0001; LOT-0002; LOT-0003; LOT-0004\nTêm fundos EU? Não\n\n12 - DOCUMENTOS DE HABILITAÇÃO\nHabilitação para o exercício da atividade profissional: Não\n\n13 - CONDIÇÕES DE APRESENTAÇÃO\nPlataforma eletrónica utilizada pela entidade adjudicante: VORTAL\nURL para Apresentação: https://community.vortal.biz/public/\nAdmissibilidade da apresentação de propostas variantes: Não autorizado\nPrazo para apresentação das propostas: 27-10-2025 23:59\nPrazo durante o qual os concorrentes são obrigados a manter as respetivas propostas: 66 dias a contar do termo do prazo para a apresentação das propostas\nIndicação de Subcontratação na Proposta: Inexistência de indicação de subcontratação\n\n14 - PRESTAÇÃO DE CAUÇÃO\nPrestação de caução: Não\n\n15 - FORNECIMENTO DAS PEÇAS DO CONCURSO, APRESENTAÇÃO DE PEDIDOS DE PARTICIPAÇÃO E APRESENTAÇÃO DAS PROPOSTAS\nLink para acesso às peças do concurso (URL): https://community.vortal.biz/Public/public-tender-documents/eDBpb3hPencxUWpVeWpKK2dWVTNLNzNvbjMzWUlBNTM4OHk0cTVseFlDVWdxRW5IbWR6MnVZZzRwMThpV3ZBNVJ3RGdSS2J0d0FQSUZSTzkxUHdJQ1E9PU0lRnZi\n\n20 - OUTROS REQUISITOS\nIdentificador do Lote: LOT-0001; LOT-0002; LOT-0003; LOT-0004\nInformação sobre contratos reservados. Aplica-se a contratos reservados (54º-A)? Não\n\n21 - CRITÉRIO DE ADJUDICAÇÃO\nO Critério de adjudicação é diferenciado por lote? Sim\nIdentificador do lote: LOT-0001\nMultifator: Sim\nFator: \nNome: Preço\nPonderação: 60%\nSubfatores: Não\nFator: \nNome: Qualidade\nPonderação: 30%\nSubfatores: Não\nFator: \nNome: Outros\nOutro Nome: Garantia e Assistência Técnica\nPonderação: 10%\nSubfatores: Não\nO Critério de adjudicação é diferenciado por lote? Sim\nIdentificador do lote: LOT-0002\nMultifator: Sim\nFator: \nNome: Preço\nPonderação: 60%\nSubfatores: Não\nFator: \nNome: Qualidade\nPonderação: 30%\nSubfatores: Não\nFator: \nNome: Outros\nOutro Nome: Garantia e Assistência Técnica\nPonderação: 10%\nSubfatores: Não\nO Critério de adjudicação é diferenciado por lote? Sim\nIdentificador do lote: LOT-0003\nMultifator: Sim\nFator: \nNome: Preço\nPonderação: 60%\nSubfatores: Não\nFator: \nNome: Qualidade\nPonderação: 30%\nSubfatores: Não\nFator: \nNome: Outros\nOutro Nome: Garantia e Assistência Técnica\nPonderação: 10%\nSubfatores: Não\nO Critério de adjudicação é diferenciado por lote? Sim\nIdentificador do lote: LOT-0004\nMultifator: Não\nMonofator:\nNome: Preço\n\n24 - CONDIÇÕES DO CONTRATO\nIdentificador do Lote: LOT-0001; LOT-0002; LOT-0003; LOT-0004\nFaturação Eletrónica: Permitido\nObrigação de Subcontratação:\nCódigo da Obrigação de Subcontratação: Não é aplicável nenhuma obrigação de subcontratação.\n\n25 - COMPRA PÚBLICA ESTRATÉGICA\nCompra Pública Estratégica: Inexistência de contratação pública estratégica\n\n26 - INFORMAÇÕES ADICIONAIS\nIdentificador do Lote: LOT-0001; LOT-0002; LOT-0003; LOT-0004\nContrato adequado para PME: Sim\nCobertura ACP (Acordo dos Contratos Públicos da Organização Mundial do Comércio): Não\n\n27 - IDENTIFICAÇÃO E CONTACTOS DO ÓRGÃO DE RECURSOS ADMINISTRATIVOS\nDesignação: Conselho de Administração da ULS Lezíria, EPE\nEndereço: Av. Bernardo Santareno\nCódigo postal: 2005-177\nLocalidade: Santarém\nTelefone: +351 243300200\nFax: +351 243300224\nEndereço eletrónico: ca@ulsleziria.min-saude.pt\n\n28 - IDENTIFICAÇÃO DO(S) AUTOR(ES) DE ANÚNCIO\nNome: Pedro Manuel DIas de Figueiredo Pereira Marques\nCargo: Presidente do Conselho de Administração\n419671437",
    "nipc": "506361462",
    "distrito": "Santarém",
    "concelho": "Santarém",
    "freguesia": "União de Freguesias da Cidade de Santarém",
    "site": "www.hds.min-saude.pt",
    "email": "hdsca@hds.min-saude.pt",
    "designacao_contrato": "Aquisição e Instalação de Camas Elétricas e Carros de Emergência",
    "descricao": "Aquisição e Instalação de Camas Elétricas e Carros de Emergência",
    "preco_base": "95.530,40 EUR",
    "prazo_execucao": "2 MESES",
    "prazo_apresentacao_propostas": "27-10-2025 23:59",
    "fundos_eu": "Não",
    "plataforma_eletronica": "VORTAL",
    "url_procedimento": "https://community.vortal.biz/public/",
    "autor_nome": "Pedro Manuel DIas de Figueiredo Pereira Marques",
    "autor_cargo": "Presidente do Conselho de Administração"
  },
  {
    "numero_procedimento": "N/A",
    "entidade": "Construção Pública, E. P. E.",
    "link": "https://diariodarepublica.pt/dr/detalhe/contrato-publico/27652-941023869",
    "detalhes_completos": "1 - IDENTIFICAÇÃO E CONTACTOS DA ENTIDADE ADJUDICANTE\nDesignação da entidade adjudicante: Construção Pública, E. P. E.\nNIPC: 508069645\nEndereço: Avenida Infante Santo n.º 2\nCódigo postal: 1350-178\nLocalidade: Lisboa\nPaís: Portugal\nNUT III: PT170\nDistrito: Lisboa\nConcelho: Lisboa\nFreguesia: Freguesia da Estrela\nTelefone: 213944710\nFax: 213944710\nEndereço da Entidade (URL): https://construcaopublica.gov.pt\nEndereço Eletrónico: geral@construcaopublica.gov.pt\neDelivery Gateway (URL): https://community.vortal.biz/public/\nFunção da Organização: Adquirente\nNorma jurídica da Entidade Adjudicante: Organismo de direito público\nÁrea de atividade da Autoridade Adjudicante: Serviços públicos das administrações públicas\n\n2 - JORNAL OFICIAL DA UNIÃO EUROPEIA\nO procedimento a que este anúncio diz respeito também é publicitado no Jornal Oficial da União Europeia? Não\n\n3 - AVISO\nModelo de Anúncio: Concurso público\nData de Envio do Anúncio: 20-10-2025\n\n5 - PROCESSO\nTipo de Procedimento: Concurso público\nPreço base do procedimento: Sim\nValor do preço base do procedimento: 1.250.607,58 EUR\nProcedimento com lotes? Não\n\n6 - OBJETO DO CONTRATO\nNúmero de referência interna: PE_25155_CNE\nDesignação do contrato: PE_25155_CNE - Concurso Público Nacional para a Empreitada de instalação de rede hidráulica e Unidades de Tratamento de Ar da Escola Secundária João Gonçalves Zarco, em Matosinhos\nDescrição: PE_25155_CNE - Concurso Público Nacional para a Empreitada de instalação de rede hidráulica e Unidades de Tratamento de Ar da Escola Secundária João Gonçalves Zarco, em Matosinhos\nTipo de Contrato Principal: Empreitada de Obras Públicas\nTipo de Contrato: Empreitada de Obras Públicas\nClassificação CPV (Vocabulário Comum para os Contratos Públicos)\nObjeto principal\nVocabulário Principal: 45330000\nPreço base s/IVA: 1.250.607,58 EUR\n\n7 - INDICAÇÕES ADICIONAIS\nO contrato envolve aquisição conjunta (satisfação de várias entidades)? Não\nO contrato é adjudicado por uma central de compras? Não\n\n8 - TÉCNICAS\nO concurso destina-se à celebração de um acordo-quadro? Inexistência de acordo-quadro\nÉ utilizado um leilão eletrónico? Não\nÉ adotada uma fase de negociação? Não\nSistema de Aquisição Dinâmico: Inexistência de sistema de aquisição dinâmico\n\n9 - LOCAL DA EXECUÇÃO DO CONTRATO\nLOCAL DA EXECUÇÃO DO CONTRATO (PROCEDIMENTO)\nPaís: Portugal\nNUT III: PT11A\nLocalidade: Porto\nDistrito: Porto\nConcelho: Matosinhos\nFreguesia: União das Freguesias de Matosinhos e Leça da Palmeira\n\n10 - PRAZO DE EXECUÇÃO DO CONTRATO\nPrazo de execução do contrato: 10 MESES\nPrevisão de renovações: Não\n\n11 - FUNDOS EU\nTêm fundos EU? Não\n\n12 - DOCUMENTOS DE HABILITAÇÃO\nHabilitação para o exercício da atividade profissional: Sim\nTipo: Alvará\nDescrição: De acordo com a habilitação exigida no Programa de Concurso.\n\n13 - CONDIÇÕES DE APRESENTAÇÃO\nPlataforma eletrónica utilizada pela entidade adjudicante: VORTAL\nURL para Apresentação: https://community.vortal.biz/public/\nAdmissibilidade da apresentação de propostas variantes: Não autorizado\nPrazo para apresentação das propostas: 20-11-2025 17:00\nPrazo durante o qual os concorrentes são obrigados a manter as respetivas propostas: 180 dias a contar do termo do prazo para a apresentação das propostas\nIndicação de Subcontratação na Proposta: Inexistência de indicação de subcontratação\n\n14 - PRESTAÇÃO DE CAUÇÃO\nPrestação de caução: Sim\nPercentagem: 5%\nDescrição da Garantia Exigida: O valor da caução é de 5% (cinco por cento) do preço contratual e será prestada pelo Adjudicatário, por depósito em dinheiro, mediante garantia bancária à primeira solicitação ou ainda por seguro-caução, nos termos dos ANEXOS V, VI e VII ao Programa de Concurso, respetivamente\n\n15 - FORNECIMENTO DAS PEÇAS DO CONCURSO, APRESENTAÇÃO DE PEDIDOS DE PARTICIPAÇÃO E APRESENTAÇÃO DAS PROPOSTAS\nLink para acesso às peças do concurso (URL): https://community.vortal.biz/Public/public-tender-documents/VzVJT0dBWmdwamZqQUFWSkJRbHFRNXN1VW1EeEsrdTVCSW9GcG5uWW1TNytRUHBYaTcyVHZCREwvYXdIRzRPRm42QzgvYkdVT28zMHVzNTdta2YyUUE9PUZLVjAj\n\n20 - OUTROS REQUISITOS\nInformação sobre contratos reservados. Aplica-se a contratos reservados (54º-A)? Não\n\n21 - CRITÉRIO DE ADJUDICAÇÃO\nMultifator: Não\nMonofator:\nNome: Preço\n\n24 - CONDIÇÕES DO CONTRATO\nFaturação Eletrónica: Permitido\nObrigação de Subcontratação:\nCódigo da Obrigação de Subcontratação: Não é aplicável nenhuma obrigação de subcontratação.\n\n25 - COMPRA PÚBLICA ESTRATÉGICA\nCompra Pública Estratégica: Inexistência de contratação pública estratégica\n\n26 - INFORMAÇÕES ADICIONAIS\nContrato adequado para PME: Sim\nCobertura ACP (Acordo dos Contratos Públicos da Organização Mundial do Comércio): Não\n\n27 - IDENTIFICAÇÃO E CONTACTOS DO ÓRGÃO DE RECURSOS ADMINISTRATIVOS\nDesignação: Conselho de Administração da Construção Pública, E.P.E.\nEndereço: Avenida Infante Santo n.º 2\nCódigo postal: 1350-178\nLocalidade: Lisboa\nTelefone: +351 213944710\nFax: +351 213944775\nEndereço eletrónico: concursos@construcaopublica.got.pt\n\n28 - IDENTIFICAÇÃO DO(S) AUTOR(ES) DE ANÚNCIO\nNome: Nélia Marisa Araújo Lemos\nCargo: Coordenadora da Equipa de Formação de Contratos\n419677156",
    "nipc": "508069645",
    "distrito": "Lisboa",
    "concelho": "Lisboa",
    "freguesia": "Freguesia da Estrela",
    "site": "https://construcaopublica.gov.pt",
    "email": "geral@construcaopublica.gov.pt",
    "designacao_contrato": "PE_25155_CNE - Concurso Público Nacional para a Empreitada de instalação de rede hidráulica e Unidades de Tratamento de Ar da Escola Secundária João Gonçalves Zarco, em Matosinhos",
    "descricao": "PE_25155_CNE - Concurso Público Nacional para a Empreitada de instalação de rede hidráulica e Unidades de Tratamento de Ar da Escola Secundária João Gonçalves Zarco, em Matosinhos",
    "preco_base": "1.250.607,58 EUR",
    "prazo_execucao": "10 MESES",
    "prazo_apresentacao_propostas": "20-11-2025 17:00",
    "fundos_eu": "Não",
    "plataforma_eletronica": "VORTAL",
    "url_procedimento": "https://community.vortal.biz/public/",
    "autor_nome": "Nélia Marisa Araújo Lemos",
    "autor_cargo": "Coordenadora da Equipa de Formação de Contratos"
  },
  {
    "numero_procedimento": "N/A",
    "entidade": "Estado-Maior-General das Forças Armadas (EMGFA)",
    "link": "https://diariodarepublica.pt/dr/detalhe/contrato-publico/27655-941023870",
    "detalhes_completos": "1 - IDENTIFICAÇÃO E CONTACTOS DA ENTIDADE ADJUDICANTE\nDesignação da entidade adjudicante: Estado-Maior-General das Forças Armadas (EMGFA)\nNIPC: 600010180\nServiço/Órgão/Pessoa de contacto: DepComp/DF/HFAR\nEndereço: AVENIDA ILHA DA MADEIRA\nCódigo postal: 1449-004\nLocalidade: Lisboa\nPaís: Portugal\nNUT III: PT170\nDistrito: Lisboa\nConcelho: Lisboa\nFreguesia: Freguesia de Lumiar\nTelefone: 2130100001\nEndereço da Entidade (URL): www.emgfa.pt\nEndereço Eletrónico: DIRFIN_Contratos@emgfa.pt\neDelivery Gateway (URL): https://www.acingov.pt\nFunção da Organização: Adquirente\nNorma jurídica da Entidade Adjudicante: Organismo de direito público\nÁrea de atividade da Autoridade Adjudicante: Serviços públicos das administrações públicas\n\n2 - JORNAL OFICIAL DA UNIÃO EUROPEIA\nO procedimento a que este anúncio diz respeito também é publicitado no Jornal Oficial da União Europeia? Não\n\n3 - AVISO\nModelo de Anúncio: Concurso público\nData de Envio do Anúncio: 21-10-2025\n\n5 - PROCESSO\nTipo de Procedimento: Concurso público\nPreço base do procedimento: Sim\nValor do preço base do procedimento: 23.619,00 EUR\nProcedimento com lotes? Não\n\n6 - OBJETO DO CONTRATO\nNúmero de referência interna: HFAR-PL 2025007114\nDesignação do contrato: 2025007114/HFAR SCSI - SOLUÇÃO CONTACT CENTER\nDescrição: 2025007114/HFAR SCSI - SOLUÇÃO CONTACT CENTER\nTipo de Contrato Principal: Aquisição de Serviços\nTipo de Contrato: Aquisição de Serviços\nClassificação CPV (Vocabulário Comum para os Contratos Públicos)\nObjeto principal\nVocabulário Principal: 72210000\nPreço base s/IVA: 23.619,00 EUR\n\n7 - INDICAÇÕES ADICIONAIS\nO contrato envolve aquisição conjunta (satisfação de várias entidades)? Não\nO contrato é adjudicado por uma central de compras? Não\n\n8 - TÉCNICAS\nO concurso destina-se à celebração de um acordo-quadro? Inexistência de acordo-quadro\nÉ utilizado um leilão eletrónico? Não\nÉ adotada uma fase de negociação? Não\nSistema de Aquisição Dinâmico: Inexistência de sistema de aquisição dinâmico\n\n9 - LOCAL DA EXECUÇÃO DO CONTRATO\nLOCAL DA EXECUÇÃO DO CONTRATO (PROCEDIMENTO)\nPaís: Portugal\nNUT III: PT170\nLocalidade: LUMIAR\nDistrito: Lisboa\nConcelho: Lisboa\nFreguesia: Freguesia de Lumiar\n\n10 - PRAZO DE EXECUÇÃO DO CONTRATO\nPrazo de execução do contrato: 10 DIAS\nPrevisão de renovações: Não\n\n11 - FUNDOS EU\nTêm fundos EU? Não\n\n12 - DOCUMENTOS DE HABILITAÇÃO\nHabilitação para o exercício da atividade profissional: Não\n\n13 - CONDIÇÕES DE APRESENTAÇÃO\nPlataforma eletrónica utilizada pela entidade adjudicante: ACIN\nURL para Apresentação: https://www.acingov.pt\nAdmissibilidade da apresentação de propostas variantes: Não autorizado\nPrazo para apresentação das propostas: 30-10-2025 23:59\nPrazo durante o qual os concorrentes são obrigados a manter as respetivas propostas: 66 dias a contar do termo do prazo para a apresentação das propostas\nIndicação de Subcontratação na Proposta: Inexistência de indicação de subcontratação\n\n14 - PRESTAÇÃO DE CAUÇÃO\nPrestação de caução: Não\n\n15 - FORNECIMENTO DAS PEÇAS DO CONCURSO, APRESENTAÇÃO DE PEDIDOS DE PARTICIPAÇÃO E APRESENTAÇÃO DAS PROPOSTAS\nLink para acesso às peças do concurso (URL): https://www.acingov.pt/acingovprod/2/zonaPublica/zona_publica_c/donwloadProcedurePiece/OTg5MDQx\n\n20 - OUTROS REQUISITOS\nInformação sobre contratos reservados. Aplica-se a contratos reservados (54º-A)? Não\n\n21 - CRITÉRIO DE ADJUDICAÇÃO\nMultifator: Não\nMonofator:\nNome: Preço\n\n24 - CONDIÇÕES DO CONTRATO\nFaturação Eletrónica: Permitido\nObrigação de Subcontratação:\nCódigo da Obrigação de Subcontratação: Não é aplicável nenhuma obrigação de subcontratação.\n\n25 - COMPRA PÚBLICA ESTRATÉGICA\nCompra Pública Estratégica: Inexistência de contratação pública estratégica\n\n26 - INFORMAÇÕES ADICIONAIS\nContrato adequado para PME: Sim\nCobertura ACP (Acordo dos Contratos Públicos da Organização Mundial do Comércio): Não\n\n27 - IDENTIFICAÇÃO E CONTACTOS DO ÓRGÃO DE RECURSOS ADMINISTRATIVOS\nDesignação: EMGMFA\nEndereço: Av. Ilha da Madeira N.º 1, 1449-004 Lisboa\nCódigo postal: 1449-004\nLocalidade: LISBOA\nTelefone: 213043000\nFax: \nEndereço eletrónico: emgfa@emgfa.pt\n\n28 - IDENTIFICAÇÃO DO(S) AUTOR(ES) DE ANÚNCIO\nNome: BGEN JOSÉ MONGE\nCargo: DIRETOR DO HFAR\n419679351",
    "nipc": "600010180",
    "distrito": "Lisboa",
    "concelho": "Lisboa",
    "freguesia": "Freguesia de Lumiar",
    "site": "www.emgfa.pt",
    "email": "DIRFIN_Contratos@emgfa.pt",
    "designacao_contrato": "2025007114/HFAR SCSI - SOLUÇÃO CONTACT CENTER",
    "descricao": "2025007114/HFAR SCSI - SOLUÇÃO CONTACT CENTER",
    "preco_base": "23.619,00 EUR",
    "prazo_execucao": "10 DIAS",
    "prazo_apresentacao_propostas": "30-10-2025 23:59",
    "fundos_eu": "Não",
    "plataforma_eletronica": "ACIN",
    "url_procedimento": "https://www.acingov.pt",
    "autor_nome": "BGEN JOSÉ MONGE",
    "autor_cargo": "DIRETOR DO HFAR"
  },
  {
    "numero_procedimento": "N/A",
    "entidade": "Instituto de Informática, I. P.",
    "link": "https://diariodarepublica.pt/dr/detalhe/contrato-publico/27656-941023871",
    "detalhes_completos": "Alteração do Anúncio de procedimento n.º 26589/2025, de 2025-10-09, com o ID 419635821\n\n1 - IDENTIFICAÇÃO E CONTACTOS DA ENTIDADE ADJUDICANTE\nDesignação da entidade adjudicante: Instituto de Informática, I. P.\nNIPC: 504322915\nServiço/Órgão/Pessoa de contacto: Área de Contratação Pública\nEndereço: Avenida Professor Dr. Cavaco Silva, n.º 17, Edifício Ciência I\nCódigo postal: 2740-120\nLocalidade: Porto Salvo\nPaís: Portugal\nNUT III: PT170\nDistrito: Lisboa\nConcelho: Oeiras\nFreguesia: Freguesia de Porto Salvo\nTelefone: 214230000\nEndereço da Entidade (URL): http://www.seg-social.pt\nEndereço Eletrónico: ii-contratacao@seg-social.pt\neDelivery Gateway (URL): https://www.acingov.pt\nFunção da Organização: Adquirente\nNorma jurídica da Entidade Adjudicante: Organismo de direito público\nÁrea de atividade da Autoridade Adjudicante: Proteção social\n\n2 - JORNAL OFICIAL DA UNIÃO EUROPEIA\nO procedimento a que este anúncio diz respeito também é publicitado no Jornal Oficial da União Europeia? Não\n\n3 - AVISO\nModelo de Anúncio: Concurso público\nData de Envio do Anúncio: 21-10-2025\n\n5 - PROCESSO\nTipo de Procedimento: Concurso público\nPreço base do procedimento: Sim\nValor do preço base do procedimento: 26.350,00 EUR\nProcedimento com lotes? Não\n\n6 - OBJETO DO CONTRATO\nNúmero de referência interna: 2324000306\nDesignação do contrato: 2324000306 - TD-AP-C17-i03, Transição Digital na Segurança Social - aquisição de solução de Ciberinteligência na modalidade de Software as a Service (SaaS)\nDescrição: 2324000306 - TD-AP-C17-i03, Transição Digital na Segurança Social - aquisição de solução de Ciberinteligência na modalidade de Software as a Service (SaaS)\nTipo de Contrato Principal: Aquisição de Serviços\nTipo de Contrato: Aquisição de Serviços\nClassificação CPV (Vocabulário Comum para os Contratos Públicos)\nObjeto principal\nVocabulário Principal: 72590000\nPreço base s/IVA: 26.350,00 EUR\n\n7 - INDICAÇÕES ADICIONAIS\nO contrato envolve aquisição conjunta (satisfação de várias entidades)? Não\nO contrato é adjudicado por uma central de compras? Não\n\n8 - TÉCNICAS\nO concurso destina-se à celebração de um acordo-quadro? Inexistência de acordo-quadro\nÉ utilizado um leilão eletrónico? Não\nÉ adotada uma fase de negociação? Não\nSistema de Aquisição Dinâmico: Inexistência de sistema de aquisição dinâmico\n\n9 - LOCAL DA EXECUÇÃO DO CONTRATO\nLOCAL DA EXECUÇÃO DO CONTRATO (PROCEDIMENTO)\nPaís: Portugal\nNUT III: PT170\nLocalidade: Freguesia de Porto Salvo\nDistrito: Lisboa\nConcelho: Oeiras\nFreguesia: Freguesia de Porto Salvo\n\n10 - PRAZO DE EXECUÇÃO DO CONTRATO\nPrazo de execução do contrato: 8 MESES\nPrevisão de renovações: Não\n\n11 - FUNDOS EU\nTêm fundos EU? Sim\n\n12 - DOCUMENTOS DE HABILITAÇÃO\nHabilitação para o exercício da atividade profissional: Não\n\n13 - CONDIÇÕES DE APRESENTAÇÃO\nPlataforma eletrónica utilizada pela entidade adjudicante: ACIN\nURL para Apresentação: https://www.acingov.pt\nAdmissibilidade da apresentação de propostas variantes: Não autorizado\nPrazo para apresentação das propostas: 27-10-2025 23:59\nPrazo durante o qual os concorrentes são obrigados a manter as respetivas propostas: 66 dias a contar do termo do prazo para a apresentação das propostas\nIndicação de Subcontratação na Proposta: Inexistência de indicação de subcontratação\n\n14 - PRESTAÇÃO DE CAUÇÃO\nPrestação de caução: Não\n\n15 - FORNECIMENTO DAS PEÇAS DO CONCURSO, APRESENTAÇÃO DE PEDIDOS DE PARTICIPAÇÃO E APRESENTAÇÃO DAS PROPOSTAS\nLink para acesso às peças do concurso (URL): https://www.acingov.pt/acingovprod/2/zonaPublica/zona_publica_c/donwloadProcedurePiece/OTg0OTM3\n\n20 - OUTROS REQUISITOS\nInformação sobre contratos reservados. Aplica-se a contratos reservados (54º-A)? Não\n\n21 - CRITÉRIO DE ADJUDICAÇÃO\nMultifator: Sim\nFator: \nNome: Preço\nPonderação: 40%\nSubfatores: Não\nFator: \nNome: Outros\nOutro Nome: Mérito técnico da Plataforma\nPonderação: 60%\nSubfatores: Não\n\n24 - CONDIÇÕES DO CONTRATO\nFaturação Eletrónica: Permitido\nObrigação de Subcontratação:\nCódigo da Obrigação de Subcontratação: Não é aplicável nenhuma obrigação de subcontratação.\n\n25 - COMPRA PÚBLICA ESTRATÉGICA\nCompra Pública Estratégica: Inexistência de contratação pública estratégica\n\n26 - INFORMAÇÕES ADICIONAIS\nContrato adequado para PME: Sim\nCobertura ACP (Acordo dos Contratos Públicos da Organização Mundial do Comércio): Não\n\n27 - IDENTIFICAÇÃO E CONTACTOS DO ÓRGÃO DE RECURSOS ADMINISTRATIVOS\nDesignação: Conselho Diretivo\nEndereço: Avenida Professor Dr. Cavaco Silva, n.º 17, Edifício Ciência I\nCódigo postal: 2740-120\nLocalidade: Porto Salvo\nTelefone: 214230000\nFax: 214230000\nEndereço eletrónico: ii-contratacao@seg-social.pt\nPrazo de interposição do recurso: 5 dias\n\n28 - IDENTIFICAÇÃO DO(S) AUTOR(ES) DE ANÚNCIO\nNome: Helga Patricia Fino da Silva Beirão Paulo\nCargo: Diretora do Departamento de Gestão de Pessoas\n\n29 - ALTERAÇÃO\nMotivo da Alteração: Correção pelo adquirente\nIdentificador da Versão do Anúncio a Alterar: 70bf52ce-def6-467c-a173-38703609b4e9-01\nIdentificador das Secções Alteradas do Anúncio Anterior: Condições de Apresentação\nDescrição das Alterações: Modificação do prazo para a apresentação de propostas\nAlteração dos Documentos do Concurso: Sim\nData de alteração dos documentos do concurso: 20-10-2025\n419679919",
    "nipc": "504322915",
    "distrito": "Lisboa",
    "concelho": "Oeiras",
    "freguesia": "Freguesia de Porto Salvo",
    "site": "http://www.seg-social.pt",
    "email": "ii-contratacao@seg-social.pt",
    "designacao_contrato": "2324000306 - TD-AP-C17-i03, Transição Digital na Segurança Social - aquisição de solução de Ciberinteligência na modalidade de Software as a Service (SaaS)",
    "descricao": "2324000306 - TD-AP-C17-i03, Transição Digital na Segurança Social - aquisição de solução de Ciberinteligência na modalidade de Software as a Service (SaaS)",
    "preco_base": "26.350,00 EUR",
    "prazo_execucao": "8 MESES",
    "prazo_apresentacao_propostas": "27-10-2025 23:59",
    "fundos_eu": "Sim",
    "plataforma_eletronica": "ACIN",
    "url_procedimento": "https://www.acingov.pt",
    "autor_nome": "Helga Patricia Fino da Silva Beirão Paulo",
    "autor_cargo": "Diretora do Departamento de Gestão de Pessoas"
  },
  {
    "numero_procedimento": "N/A",
    "entidade": "Município da Póvoa de Varzim",
    "link": "https://diariodarepublica.pt/dr/detalhe/contrato-publico/27657-941023872",
    "detalhes_completos": "1 - IDENTIFICAÇÃO E CONTACTOS DA ENTIDADE ADJUDICANTE\nDesignação da entidade adjudicante: Município da Póvoa de Varzim\nNIPC: 506741400\nEndereço: Praça do Almada, 18\nCódigo postal: 4490-438\nLocalidade: Póvoa de Varzim\nPaís: Portugal\nNUT III: PT11A\nDistrito: Porto\nConcelho: Póvoa de Varzim\nFreguesia: Todas\nTelefone: 252090000\nFax: 252090010\nEndereço da Entidade (URL): www.cm-pvarzim.pt\nEndereço Eletrónico: geral@cm-pvarzim.pt\neDelivery Gateway (URL): https://community.vortal.biz/public/\nFunção da Organização: Adquirente\nNorma jurídica da Entidade Adjudicante: Organismo de direito público\nÁrea de atividade da Autoridade Adjudicante: Serviços públicos das administrações públicas\n\n2 - JORNAL OFICIAL DA UNIÃO EUROPEIA\nO procedimento a que este anúncio diz respeito também é publicitado no Jornal Oficial da União Europeia? Não\n\n3 - AVISO\nModelo de Anúncio: Concurso público\nData de Envio do Anúncio: 21-10-2025\n\n5 - PROCESSO\nTipo de Procedimento: Concurso público\nPreço base do procedimento: Sim\nValor do preço base do procedimento: 270.000,00 EUR\nProcedimento com lotes? Não\n\n6 - OBJETO DO CONTRATO\nNúmero de referência interna: CP060/25\nDesignação do contrato: Execução de EEAR 4 - Rua das Pedras Negras - Aguçadoura - Obra (Operação Norte 2030-FEDER- 01930800)\nDescrição: Execução de EEAR 4 - Rua das Pedras Negras - Aguçadoura - Obra (Operação Norte 2030-FEDER- 01930800)\nTipo de Contrato Principal: Empreitada de Obras Públicas\nTipo de Contrato: Empreitada de Obras Públicas\nClassificação CPV (Vocabulário Comum para os Contratos Públicos)\nObjeto principal\nVocabulário Principal: 45252126\nPreço base s/IVA: 270.000,00 EUR\n\n7 - INDICAÇÕES ADICIONAIS\nO contrato envolve aquisição conjunta (satisfação de várias entidades)? Não\nO contrato é adjudicado por uma central de compras? Não\n\n8 - TÉCNICAS\nO concurso destina-se à celebração de um acordo-quadro? Inexistência de acordo-quadro\nÉ utilizado um leilão eletrónico? Não\nÉ adotada uma fase de negociação? Não\nSistema de Aquisição Dinâmico: Inexistência de sistema de aquisição dinâmico\n\n9 - LOCAL DA EXECUÇÃO DO CONTRATO\nLOCAL DA EXECUÇÃO DO CONTRATO (PROCEDIMENTO)\nPaís: Portugal\nNUT III: PT11A\nLocalidade: Área Metropolitana do Porto\nDistrito: Porto\nConcelho: Póvoa de Varzim\nFreguesia: Todas\n\n10 - PRAZO DE EXECUÇÃO DO CONTRATO\nPrazo de execução do contrato: 180 DIAS\nPrevisão de renovações: Não\n\n11 - FUNDOS EU\nTêm fundos EU? Sim\n\n12 - DOCUMENTOS DE HABILITAÇÃO\nHabilitação para o exercício da atividade profissional: Sim\nTipo: Alvará\nDescrição: Indicado no Programa de Procedimento\n\n13 - CONDIÇÕES DE APRESENTAÇÃO\nPlataforma eletrónica utilizada pela entidade adjudicante: VORTAL\nURL para Apresentação: https://community.vortal.biz/public/\nAdmissibilidade da apresentação de propostas variantes: Não autorizado\nPrazo para apresentação das propostas: 20-11-2025 17:00\nPrazo durante o qual os concorrentes são obrigados a manter as respetivas propostas: 66 dias a contar do termo do prazo para a apresentação das propostas\nIndicação de Subcontratação na Proposta: Inexistência de indicação de subcontratação\n\n14 - PRESTAÇÃO DE CAUÇÃO\nPrestação de caução: Não\n\n15 - FORNECIMENTO DAS PEÇAS DO CONCURSO, APRESENTAÇÃO DE PEDIDOS DE PARTICIPAÇÃO E APRESENTAÇÃO DAS PROPOSTAS\nLink para acesso às peças do concurso (URL): https://community.vortal.biz/Public/public-tender-documents/aXl4RWFWMXRPeEFEazc2SlFUU3B1Tm1SNDFKcElpRjZOanhDM1djQXZGTXl3bjlvL2kxVzNISkJUd1BmWE5SK3dEdUswbFUrT3ZSeUV2MVRpR3VlT3c9PUBiM0pu\n\n20 - OUTROS REQUISITOS\nInformação sobre contratos reservados. Aplica-se a contratos reservados (54º-A)? Não\n\n21 - CRITÉRIO DE ADJUDICAÇÃO\nMultifator: Não\nMonofator:\nNome: Preço\n\n24 - CONDIÇÕES DO CONTRATO\nFaturação Eletrónica: Permitido\nObrigação de Subcontratação:\nCódigo da Obrigação de Subcontratação: Não é aplicável nenhuma obrigação de subcontratação.\n\n25 - COMPRA PÚBLICA ESTRATÉGICA\nCompra Pública Estratégica: Inexistência de contratação pública estratégica\n\n26 - INFORMAÇÕES ADICIONAIS\nContrato adequado para PME: Sim\nCobertura ACP (Acordo dos Contratos Públicos da Organização Mundial do Comércio): Não\n\n27 - IDENTIFICAÇÃO E CONTACTOS DO ÓRGÃO DE RECURSOS ADMINISTRATIVOS\nDesignação: Presidente da Câmara Municipal da Póvoa de Varzim\nEndereço: Praça do Almada\nCódigo postal: 4490-438\nLocalidade: Póvoa de Varzim\nTelefone: +351 252090000\nFax: +351 252090010\nEndereço eletrónico: geral@cm-pvarzim.pt\n\n28 - IDENTIFICAÇÃO DO(S) AUTOR(ES) DE ANÚNCIO\nNome: Município da Póvoa de Varzim\nCargo: Coordenadora Técnica \n419679643",
    "nipc": "506741400",
    "distrito": "Porto",
    "concelho": "Póvoa de Varzim",
    "freguesia": "Todas",
    "site": "www.cm-pvarzim.pt",
    "email": "geral@cm-pvarzim.pt",
    "designacao_contrato": "Execução de EEAR 4 - Rua das Pedras Negras - Aguçadoura - Obra (Operação Norte 2030-FEDER- 01930800)",
    "descricao": "Execução de EEAR 4 - Rua das Pedras Negras - Aguçadoura - Obra (Operação Norte 2030-FEDER- 01930800)",
    "preco_base": "270.000,00 EUR",
    "prazo_execucao": "180 DIAS",
    "prazo_apresentacao_propostas": "20-11-2025 17:00",
    "fundos_eu": "Sim",
    "plataforma_eletronica": "VORTAL",
    "url_procedimento": "https://community.vortal.biz/public/",
    "autor_nome": "Município da Póvoa de Varzim",
    "autor_cargo": "Coordenadora Técnica"
  },
  {
    "numero_procedimento": "N/A",
    "entidade": "Unidade Local de Saúde de Coimbra, E. P. E.",
    "link": "https://diariodarepublica.pt/dr/detalhe/contrato-publico/27647-941162526",
    "detalhes_completos": "1 - IDENTIFICAÇÃO E CONTACTOS DA ENTIDADE ADJUDICANTE\nDesignação da entidade adjudicante: Unidade Local de Saúde de Coimbra, E. P. E.\nNIPC: 510103448\nEndereço: Praceta Prof. Mota Pinto\nCódigo postal: 3004-561\nLocalidade: Coimbra\nPaís: Portugal\nNUT III: PT16E\nDistrito: Coimbra\nConcelho: Coimbra\nFreguesia: Todas\nTelefone: 239400605\nFax: 239400605\nEndereço da Entidade (URL): https://www.chuc.min-saude.pt\nEndereço Eletrónico: ana.rosete@ulscoimbra.min-saude.pt\neDelivery Gateway (URL): https://community.vortal.biz/public/\nFunção da Organização: Adquirente\nNorma jurídica da Entidade Adjudicante: Organismo de direito público\nÁrea de atividade da Autoridade Adjudicante: Saúde\n\n2 - JORNAL OFICIAL DA UNIÃO EUROPEIA\nO procedimento a que este anúncio diz respeito também é publicitado no Jornal Oficial da União Europeia? Não\n\n3 - AVISO\nModelo de Anúncio: Concurso público\nData de Envio do Anúncio: 20-10-2025\n\n5 - PROCESSO\nTipo de Procedimento: Concurso público\nPreço base do procedimento: Sim\nValor do preço base do procedimento: 144.000,00 EUR\nProcedimento com lotes? Não\n\n6 - OBJETO DO CONTRATO\nNúmero de referência interna: 010900672025\nDesignação do contrato: Aluguer de 1 (uma) máquina de inclusão automática e fornecimento de 12.000 cassetes/mês e todos os consumíveis em quantidade adequada a produção mensal para um período de 12 meses para o Serviço de An\nDescrição: Aluguer de 1 (uma) máquina de inclusão automática e fornecimento de 12.000 cassetes/mês e todos os consumíveis em quantidade adequada a produção mensal para um período de 12 meses para o Serviço de Anatomia Patológica da Unidade Local de Saúde de Coimbra, E.P.E \nTipo de Contrato Principal: Aquisição de Serviços\nTipo de Contrato: Aquisição de Serviços\nClassificação CPV (Vocabulário Comum para os Contratos Públicos)\nObjeto principal\nVocabulário Principal: 85100000\nPreço base s/IVA: 144.000,00 EUR\n\n7 - INDICAÇÕES ADICIONAIS\nO contrato envolve aquisição conjunta (satisfação de várias entidades)? Não\nO contrato é adjudicado por uma central de compras? Não\n\n8 - TÉCNICAS\nO concurso destina-se à celebração de um acordo-quadro? Inexistência de acordo-quadro\nÉ utilizado um leilão eletrónico? Não\nÉ adotada uma fase de negociação? Não\nSistema de Aquisição Dinâmico: Inexistência de sistema de aquisição dinâmico\n\n9 - LOCAL DA EXECUÇÃO DO CONTRATO\nLOCAL DA EXECUÇÃO DO CONTRATO (PROCEDIMENTO)\nPaís: Portugal\nNUT III: PT16E\nLocalidade: Coimbra\nDistrito: Coimbra\nConcelho: Coimbra\nFreguesia: Freguesia de Santo António dos Olivais\n\n10 - PRAZO DE EXECUÇÃO DO CONTRATO\nPrazo de execução do contrato: 12 MESES\nPrevisão de renovações: Não\n\n11 - FUNDOS EU\nTêm fundos EU? Não\n\n12 - DOCUMENTOS DE HABILITAÇÃO\nHabilitação para o exercício da atividade profissional: Não\n\n13 - CONDIÇÕES DE APRESENTAÇÃO\nPlataforma eletrónica utilizada pela entidade adjudicante: VORTAL\nURL para Apresentação: https://community.vortal.biz/public/\nAdmissibilidade da apresentação de propostas variantes: Não autorizado\nPrazo para apresentação das propostas: 10-11-2025 23:59\nPrazo durante o qual os concorrentes são obrigados a manter as respetivas propostas: 90 dias a contar do termo do prazo para a apresentação das propostas\nIndicação de Subcontratação na Proposta: Inexistência de indicação de subcontratação\n\n14 - PRESTAÇÃO DE CAUÇÃO\nPrestação de caução: Não\n\n15 - FORNECIMENTO DAS PEÇAS DO CONCURSO, APRESENTAÇÃO DE PEDIDOS DE PARTICIPAÇÃO E APRESENTAÇÃO DAS PROPOSTAS\nLink para acesso às peças do concurso (URL): https://community.vortal.biz/Public/public-tender-documents/K2xyaURTbk1McmtjblBCQ25qZmtNWTZ6M3JOSDZOUGtia3A4bXZsZThQWVQxdmh2ai9ZeXJDeUNQOEQ5Tlo3ZzZsRnhxNndYaUNnVmZWcjNjaHdIaXc9PSNBUXFU\n\n20 - OUTROS REQUISITOS\nInformação sobre contratos reservados. Aplica-se a contratos reservados (54º-A)? Não\n\n21 - CRITÉRIO DE ADJUDICAÇÃO\nMultifator: Sim\nFator: \nNome: Qualidade\nPonderação: 65%\nSubfatores: Não\nFator: \nNome: Qualidade\nPonderação: 35%\nSubfatores: Não\n\n24 - CONDIÇÕES DO CONTRATO\nFaturação Eletrónica: Permitido\nObrigação de Subcontratação:\nCódigo da Obrigação de Subcontratação: Não é aplicável nenhuma obrigação de subcontratação.\n\n25 - COMPRA PÚBLICA ESTRATÉGICA\nCompra Pública Estratégica: Inexistência de contratação pública estratégica\n\n26 - INFORMAÇÕES ADICIONAIS\nContrato adequado para PME: Sim\nCobertura ACP (Acordo dos Contratos Públicos da Organização Mundial do Comércio): Não\n\n27 - IDENTIFICAÇÃO E CONTACTOS DO ÓRGÃO DE RECURSOS ADMINISTRATIVOS\nDesignação: Conselho de Administração da ULS Coimbra, E.P.E.\nEndereço: Praceta Prof. Mota Pinto\nCódigo postal: 3004-561\nLocalidade: Coimbra\nTelefone: +351 239400400\nFax: +351 239400400\nEndereço eletrónico: casec@ulscoimbra.min-saude.pt\n\n28 - IDENTIFICAÇÃO DO(S) AUTOR(ES) DE ANÚNCIO\nNome: Teresa Roseiro\nCargo: Assistente Tecnica\n419677131",
    "nipc": "510103448",
    "distrito": "Coimbra",
    "concelho": "Coimbra",
    "freguesia": "Todas",
    "site": "https://www.chuc.min-saude.pt",
    "email": "ana.rosete@ulscoimbra.min-saude.pt",
    "designacao_contrato": "Aluguer de 1 (uma) máquina de inclusão automática e fornecimento de 12.000 cassetes/mês e todos os consumíveis em quantidade adequada a produção mensal para um período de 12 meses para o Serviço de An",
    "descricao": "Aluguer de 1 (uma) máquina de inclusão automática e fornecimento de 12.000 cassetes/mês e todos os consumíveis em quantidade adequada a produção mensal para um período de 12 meses para o Serviço de Anatomia Patológica da Unidade Local de Saúde de Coimbra, E.P.E",
    "preco_base": "144.000,00 EUR",
    "prazo_execucao": "12 MESES",
    "prazo_apresentacao_propostas": "10-11-2025 23:59",
    "fundos_eu": "Não",
    "plataforma_eletronica": "VORTAL",
    "url_procedimento": "https://community.vortal.biz/public/",
    "autor_nome": "Teresa Roseiro",
    "autor_cargo": "Assistente Tecnica"
  },
  {
    "numero_procedimento": "N/A",
    "entidade": "Docapesca - Portos e Lotas, S. A.",
    "link": "https://diariodarepublica.pt/dr/detalhe/contrato-publico/27649-941162527",
    "detalhes_completos": "Alteração do Anúncio de procedimento n.º 27081/2025, de 2025-10-14, com o ID 419653617\n\n1 - IDENTIFICAÇÃO E CONTACTOS DA ENTIDADE ADJUDICANTE\nDesignação da entidade adjudicante: Docapesca - Portos e Lotas, S. A.\nNIPC: 500086826\nEndereço: Av. Brasilia - Porta ES 7 - Pedrouços\nCódigo postal: 1400-038\nLocalidade: Lisboa\nPaís: Portugal\nNUT III: PT170\nDistrito: Lisboa\nConcelho: Lisboa\nFreguesia: Todas\nTelefone: 213936100\nFax: 213936101\nEndereço da Entidade (URL): www.docapesca.pt\nEndereço Eletrónico: docapesca@docapesca.pt\neDelivery Gateway (URL): https://community.vortal.biz/public/\nFunção da Organização: Adquirente\nNorma jurídica da Entidade Adjudicante: Autoridade da administração central\nÁrea de atividade da Autoridade Adjudicante: Serviços públicos das administrações públicas\n\n2 - JORNAL OFICIAL DA UNIÃO EUROPEIA\nO procedimento a que este anúncio diz respeito também é publicitado no Jornal Oficial da União Europeia? Não\n\n3 - AVISO\nModelo de Anúncio: Concurso público\nData de Envio do Anúncio: 20-10-2025\n\n5 - PROCESSO\nTipo de Procedimento: Concurso público\nPreço base do procedimento: Sim\nValor do preço base do procedimento: 146.747,00 EUR\nProcedimento com lotes? Sim\nNº Máx. de Lotes Autorizado: 5\nNúmero máximo de lotes que podem ser adjudicados a um concorrente: 5\n\n6 - OBJETO DO CONTRATO\nNúmero de referência interna: DCM-071-CPu-2025\nDesignação do contrato:  Limpeza e Higienização do interior das instalações dos Portos de Pesca do Algarve.\nDescrição:  Limpeza e Higienização do interior das instalações dos Portos de Pesca do Algarve.\nTipo de Contrato Principal: Aquisição de Serviços\nTipo de Contrato: Aquisição de Serviços\nClassificação CPV (Vocabulário Comum para os Contratos Públicos)\nObjeto principal\nVocabulário Principal: 90910000\nPreço base s/IVA: 146.747,00 EUR\nLotes: \nNº: LOT-0001\nDescrição do Lote: Lote 1\nPreço base s/IVA: 33.570,00 EUR\nClassificação CPV (Vocabulário Comum para os Contratos Públicos)\nObjeto principal\nVocabulário Principal: 90910000\nNº: LOT-0002\nDescrição do Lote: Lote 2\nPreço base s/IVA: 37.070,00 EUR\nClassificação CPV (Vocabulário Comum para os Contratos Públicos)\nObjeto principal\nVocabulário Principal: 90910000\nNº: LOT-0003\nDescrição do Lote: Lote 3\nPreço base s/IVA: 21.750,00 EUR\nClassificação CPV (Vocabulário Comum para os Contratos Públicos)\nObjeto principal\nVocabulário Principal: 90910000\nNº: LOT-0004\nDescrição do Lote: Lote 4\nPreço base s/IVA: 35.565,00 EUR\nClassificação CPV (Vocabulário Comum para os Contratos Públicos)\nObjeto principal\nVocabulário Principal: 90910000\nNº: LOT-0005\nDescrição do Lote: Lote 5\nPreço base s/IVA: 18.792,00 EUR\nClassificação CPV (Vocabulário Comum para os Contratos Públicos)\nObjeto principal\nVocabulário Principal: 90910000\n\n7 - INDICAÇÕES ADICIONAIS\nO contrato envolve aquisição conjunta (satisfação de várias entidades)? Não\nO contrato é adjudicado por uma central de compras? Não\n\n8 - TÉCNICAS\nO concurso destina-se à celebração de um acordo-quadro? Inexistência de acordo-quadro\nÉ utilizado um leilão eletrónico? Não\nÉ adotada uma fase de negociação? Não\nSistema de Aquisição Dinâmico: Inexistência de sistema de aquisição dinâmico\n\n9 - LOCAL DA EXECUÇÃO DO CONTRATO\nLOCAL DA EXECUÇÃO DO CONTRATO (PROCEDIMENTO)\nPaís: Portugal\nNUT III: PT150\nLocalidade: Faro\nDistrito: Faro\nConcelho: Portimão\nFreguesia: Todas\nLOCAL DA EXECUÇÃO DO CONTRATO (LOTE)\nIdentificador do Lote: LOT-0001; LOT-0002; LOT-0003; LOT-0004; LOT-0005\nPaís: Portugal\nNUT III: PT150\nLocalidade: Faro\nDistrito: Faro\nConcelho: Portimão\nFreguesia: Todas\nIdentificador do Lote: LOT-0001; LOT-0002; LOT-0003; LOT-0004; LOT-0005\nPaís: Portugal\nNUT III: PT150\nLocalidade: Faro\nDistrito: Faro\nConcelho: Vila Real Sto Antonio\nFreguesia: Freguesia de Vila Real de Santo António\nIdentificador do Lote: LOT-0001; LOT-0002; LOT-0003; LOT-0004; LOT-0005\nPaís: Portugal\nNUT III: PT150\nLocalidade: Faro\nDistrito: Faro\nConcelho: Loulé\nFreguesia: Freguesia de Quarteira\nIdentificador do Lote: LOT-0001; LOT-0002; LOT-0003; LOT-0004; LOT-0005\nPaís: Portugal\nNUT III: PT150\nLocalidade: Faro\nDistrito: Faro\nConcelho: Lagos\nFreguesia: Todas\nIdentificador do Lote: LOT-0001; LOT-0002; LOT-0003; LOT-0004; LOT-0005\nPaís: Portugal\nNUT III: PT150\nLocalidade: Faro\nDistrito: Faro\nConcelho: Olhão\nFreguesia: Todas\n\n10 - PRAZO DE EXECUÇÃO DO CONTRATO\nIdentificador do Lote: LOT-0001; LOT-0002; LOT-0003; LOT-0004; LOT-0005\nPrazo de execução do contrato: 24 MESES\nPrevisão de renovações: Não\n\n11 - FUNDOS EU\nIdentificador do Lote: LOT-0001; LOT-0002; LOT-0003; LOT-0004; LOT-0005\nTêm fundos EU? Não\n\n12 - DOCUMENTOS DE HABILITAÇÃO\nHabilitação para o exercício da atividade profissional: Não\n\n13 - CONDIÇÕES DE APRESENTAÇÃO\nPlataforma eletrónica utilizada pela entidade adjudicante: VORTAL\nURL para Apresentação: https://community.vortal.biz/public/\nAdmissibilidade da apresentação de propostas variantes: Não autorizado\nPrazo para apresentação das propostas: 01-11-2025 23:59\nPrazo durante o qual os concorrentes são obrigados a manter as respetivas propostas: 66 dias a contar do termo do prazo para a apresentação das propostas\nApresentação de Catálogo Eletrónico: Permitido\nIndicação de Subcontratação na Proposta: Inexistência de indicação de subcontratação\n\n14 - PRESTAÇÃO DE CAUÇÃO\nPrestação de caução: Sim\nPercentagem: 4%\nDescrição da Garantia Exigida: Mediante depósito, garantia bancária ou seguro-caução \n\n15 - FORNECIMENTO DAS PEÇAS DO CONCURSO, APRESENTAÇÃO DE PEDIDOS DE PARTICIPAÇÃO E APRESENTAÇÃO DAS PROPOSTAS\nLink para acesso às peças do concurso (URL): https://community.vortal.biz/Public/public-tender-documents/THd2bStHUmlRTG56S0J4bFM5b2lRNEpGT05NZ3owM0pGWDVvVGh3bHlmYWlRaWgrTTM3VHR3SDVOY1did0R4eXI0QVBaWkRSc3docHBwaklNcEpMVHc9PTYjaW5B\n\n20 - OUTROS REQUISITOS\nIdentificador do Lote: LOT-0001; LOT-0002; LOT-0003; LOT-0004; LOT-0005\nInformação sobre contratos reservados. Aplica-se a contratos reservados (54º-A)? Não\n\n21 - CRITÉRIO DE ADJUDICAÇÃO\nO Critério de adjudicação é diferenciado por lote? Sim\nIdentificador do lote: LOT-0001\nMultifator: Sim\nFator: \nNome: Preço\nPonderação: 85%\nSubfatores: Não\nFator: \nNome: Outros\nOutro Nome: Formação em segurança no trabalho e boas práticas ambientais\nPonderação: 15%\nSubfatores: Não\nO Critério de adjudicação é diferenciado por lote? Sim\nIdentificador do lote: LOT-0002\nMultifator: Sim\nFator: \nNome: Preço\nPonderação: 85%\nSubfatores: Não\nFator: \nNome: Outros\nOutro Nome: Formação em segurança no trabalho e boas práticas ambientais\nPonderação: 15%\nSubfatores: Não\nO Critério de adjudicação é diferenciado por lote? Sim\nIdentificador do lote: LOT-0003\nMultifator: Sim\nFator: \nNome: Preço\nPonderação: 85%\nSubfatores: Não\nFator: \nNome: Outros\nOutro Nome: Formação em segurança no trabalho e boas práticas ambientais\nPonderação: 15%\nSubfatores: Não\nO Critério de adjudicação é diferenciado por lote? Sim\nIdentificador do lote: LOT-0004\nMultifator: Sim\nFator: \nNome: Preço\nPonderação: 85%\nSubfatores: Não\nFator: \nNome: Outros\nOutro Nome: Formação em segurança no trabalho e boas práticas ambientais\nPonderação: 15%\nSubfatores: Não\nO Critério de adjudicação é diferenciado por lote? Sim\nIdentificador do lote: LOT-0005\nMultifator: Sim\nFator: \nNome: Preço\nPonderação: 85%\nSubfatores: Não\nFator: \nNome: Outros\nOutro Nome: Formação em segurança no trabalho e boas práticas ambientais\nPonderação: 15%\nSubfatores: Não\n\n24 - CONDIÇÕES DO CONTRATO\nIdentificador do Lote: LOT-0001; LOT-0002; LOT-0003; LOT-0004; LOT-0005\nFaturação Eletrónica: Permitido\nObrigação de Subcontratação:\nCódigo da Obrigação de Subcontratação: Não é aplicável nenhuma obrigação de subcontratação.\n\n25 - COMPRA PÚBLICA ESTRATÉGICA\nCompra Pública Estratégica: Redução dos impactos ambientais\nDescrição do Processo de Adjudicação Estratégico: Conforme as peças do procedimento\nCritérios de contratos Públicos Ecológicos: Critérios de contratação pública ecológica nacional\nCategorias da estratégia nacional: Serviços de limpeza de interiores\nContratos Públicos Ecológicos: Outros\nDiretiva Veículos Não Poluentes: Não\nCritério de Acessibilidade: Os critérios de acessibilidade para as pessoas com deficiência não estão incluídos porque o contrato não se destina a pessoas singulares\n\n26 - INFORMAÇÕES ADICIONAIS\nIdentificador do Lote: LOT-0001; LOT-0002; LOT-0003; LOT-0004; LOT-0005\nContrato adequado para PME: Sim\nCobertura ACP (Acordo dos Contratos Públicos da Organização Mundial do Comércio): Não\n\n27 - IDENTIFICAÇÃO E CONTACTOS DO ÓRGÃO DE RECURSOS ADMINISTRATIVOS\nDesignação: Docapesca- Portos e Lotas, SA\nEndereço: Avenida Brasília, ES 7\nCódigo postal: 1400-038\nLocalidade: Lisboa\nTelefone: +351 213936100\nFax: +351 213936100\nEndereço eletrónico: docapesca@docapesca.pt\n\n28 - IDENTIFICAÇÃO DO(S) AUTOR(ES) DE ANÚNCIO\nNome: Afonso Gonçalves da Silva Oliveira\nCargo: Presidente do Conselho de Administração\n\n29 - ALTERAÇÃO\nMotivo da Alteração: Correção pelo adquirente\nIdentificador da Versão do Anúncio a Alterar: 4a1b1a85-bcac-49ca-a142-80b9dc77ce59-01\nIdentificador das Secções Alteradas do Anúncio Anterior: Alteração\nAlteração dos Documentos do Concurso: Sim\nData de alteração dos documentos do concurso: 20-10-2025\n419679343",
    "nipc": "500086826",
    "distrito": "Lisboa",
    "concelho": "Lisboa",
    "freguesia": "Todas",
    "site": "www.docapesca.pt",
    "email": "docapesca@docapesca.pt",
    "designacao_contrato": "Limpeza e Higienização do interior das instalações dos Portos de Pesca do Algarve.",
    "descricao": "Limpeza e Higienização do interior das instalações dos Portos de Pesca do Algarve.",
    "preco_base": "146.747,00 EUR",
    "prazo_execucao": "24 MESES",
    "prazo_apresentacao_propostas": "01-11-2025 23:59",
    "fundos_eu": "Não",
    "plataforma_eletronica": "VORTAL",
    "url_procedimento": "https://community.vortal.biz/public/",
    "autor_nome": "Afonso Gonçalves da Silva Oliveira",
    "autor_cargo": "Presidente do Conselho de Administração"
  },
  {
    "numero_procedimento": "N/A",
    "entidade": "Universidade de Aveiro",
    "link": "https://diariodarepublica.pt/dr/detalhe/contrato-publico/27651-941162528",
    "detalhes_completos": "1 - IDENTIFICAÇÃO E CONTACTOS DA ENTIDADE ADJUDICANTE\nDesignação da entidade adjudicante: Universidade de Aveiro\nNIPC: 501461108\nEndereço: Campus de Santiago\nCódigo postal: 3810-193\nLocalidade: Aveiro\nPaís: Portugal\nNUT III: PT16D\nDistrito: Aveiro\nConcelho: Aveiro\nFreguesia: União das Freguesias de Glória e Vera Cruz\nTelefone: 234370200\nFax: 234370040\nEndereço da Entidade (URL): https://www.ua.pt\nEndereço Eletrónico: contratacao@ua.pt\neDelivery Gateway (URL): https://community.vortal.biz/public/\nFunção da Organização: Adquirente\nNorma jurídica da Entidade Adjudicante: Organismo de direito público\nÁrea de atividade da Autoridade Adjudicante: Educação\n\n2 - JORNAL OFICIAL DA UNIÃO EUROPEIA\nO procedimento a que este anúncio diz respeito também é publicitado no Jornal Oficial da União Europeia? Não\n\n3 - AVISO\nModelo de Anúncio: Concurso público\nData de Envio do Anúncio: 20-10-2025\n\n5 - PROCESSO\nTipo de Procedimento: Concurso público\nPreço base do procedimento: Sim\nValor do preço base do procedimento: 98.000,00 EUR\nProcedimento com lotes? Sim\nNº Máx. de Lotes Autorizado: 11\nNúmero máximo de lotes que podem ser adjudicados a um concorrente: 11\n\n6 - OBJETO DO CONTRATO\nNúmero de referência interna: CP 367 - AAC/FIS - 10/25\nDesignação do contrato: Equipamento didático e científico para a criação de um  Laboratório de Engenharia Aeroespacial especializado em Sensores e Dispositivos\nDescrição: Equipamento didático e científico para a criação de um Laboratório de Engenharia Aeroespacial especializado em Sensores e Dispositivos\nTipo de Contrato Principal: Aquisição de Bens Móveis\nTipo de Contrato: Aquisição de Bens Móveis\nClassificação CPV (Vocabulário Comum para os Contratos Públicos)\nObjeto principal\nVocabulário Principal: 38970000\nPreço base s/IVA: 63.500,00 EUR\nObjeto Complementar\nVocabulário Principal: 31642000\nPreço base s/IVA: 16.600,00 EUR\nObjeto Complementar\nVocabulário Principal: 31682210\nPreço base s/IVA: 5.000,00 EUR\nObjeto Complementar\nVocabulário Principal: 30213300\nPreço base s/IVA: 3.850,00 EUR\nObjeto Complementar\nVocabulário Principal: 42514310\nPreço base s/IVA: 4.850,00 EUR\nObjeto Complementar\nVocabulário Principal: 38511000\nPreço base s/IVA: 500,00 EUR\nObjeto Complementar\nVocabulário Principal: 38342000\nPreço base s/IVA: 3.700,00 EUR\nLotes: \nNº: LOT-0001\nDescrição do Lote: Aquisição de Osciloscópio digital\nPreço base s/IVA: 3.700,00 EUR\nClassificação CPV (Vocabulário Comum para os Contratos Públicos)\nObjeto Complementar\nVocabulário Principal: 38342000\nNº: LOT-0002\nDescrição do Lote: Aquisição de Microscópio multidirecional\nPreço base s/IVA: 500,00 EUR\nClassificação CPV (Vocabulário Comum para os Contratos Públicos)\nObjeto Complementar\nVocabulário Principal: 38511000\nNº: LOT-0003\nDescrição do Lote: Aquisição de Câmara de ensaio térmico e vácuo\nPreço base s/IVA: 45.000,00 EUR\nClassificação CPV (Vocabulário Comum para os Contratos Públicos)\nObjeto principal\nVocabulário Principal: 38970000\nNº: LOT-0004\nDescrição do Lote: Aquisição de Hotte química com filtração\nPreço base s/IVA: 4.850,00 EUR\nClassificação CPV (Vocabulário Comum para os Contratos Públicos)\nObjeto Complementar\nVocabulário Principal: 42514310\nNº: LOT-0005\nDescrição do Lote: Aquisição de Computadores de mesa\nPreço base s/IVA: 3.850,00 EUR\nClassificação CPV (Vocabulário Comum para os Contratos Públicos)\nObjeto Complementar\nVocabulário Principal: 30213300\nNº: LOT-0006\nDescrição do Lote: Aquisição de Simulador solar AM1.5G\nPreço base s/IVA: 2.600,00 EUR\nClassificação CPV (Vocabulário Comum para os Contratos Públicos)\nObjeto principal\nVocabulário Principal: 38970000\nNº: LOT-0007\nDescrição do Lote: Aquisição de Kits educacionais Kitsat Pro\nPreço base s/IVA: 5.000,00 EUR\nClassificação CPV (Vocabulário Comum para os Contratos Públicos)\nObjeto Complementar\nVocabulário Principal: 31682210\nNº: LOT-0008\nDescrição do Lote: Aquisição de Board conexão fotodetetores\nPreço base s/IVA: 2.400,00 EUR\nClassificação CPV (Vocabulário Comum para os Contratos Públicos)\nObjeto Complementar\nVocabulário Principal: 31642000\nNº: LOT-0009\nDescrição do Lote: Aquisição de Matrizes fotodetectores\nPreço base s/IVA: 2.600,00 EUR\nClassificação CPV (Vocabulário Comum para os Contratos Públicos)\nObjeto Complementar\nVocabulário Principal: 31642000\nNº: LOT-0010\nDescrição do Lote: Aquisição de Source meter Unit\nPreço base s/IVA: 11.600,00 EUR\nClassificação CPV (Vocabulário Comum para os Contratos Públicos)\nObjeto Complementar\nVocabulário Principal: 31642000\nNº: LOT-0011\nDescrição do Lote: Aquisição de Simulador solar AM0\nPreço base s/IVA: 15.900,00 EUR\nClassificação CPV (Vocabulário Comum para os Contratos Públicos)\nObjeto principal\nVocabulário Principal: 38970000\n\n7 - INDICAÇÕES ADICIONAIS\nO contrato envolve aquisição conjunta (satisfação de várias entidades)? Não\nO contrato é adjudicado por uma central de compras? Não\n\n8 - TÉCNICAS\nO concurso destina-se à celebração de um acordo-quadro? Inexistência de acordo-quadro\nÉ utilizado um leilão eletrónico? Não\nÉ adotada uma fase de negociação? Não\nSistema de Aquisição Dinâmico: Inexistência de sistema de aquisição dinâmico\n\n9 - LOCAL DA EXECUÇÃO DO CONTRATO\nLOCAL DA EXECUÇÃO DO CONTRATO (PROCEDIMENTO)\nPaís: Portugal\nNUT III: PT16D\nLocalidade: Aveiro\nDistrito: Aveiro\nConcelho: Aveiro\nFreguesia: União das Freguesias de Glória e Vera Cruz\nLOCAL DA EXECUÇÃO DO CONTRATO (LOTE)\nIdentificador do Lote: LOT-0001; LOT-0002; LOT-0003; LOT-0004; LOT-0005; LOT-0006; LOT-0007; LOT-0008; LOT-0009; LOT-0010; LOT-0011\nPaís: Portugal\nNUT III: PT16D\nLocalidade: Aveiro\nDistrito: Aveiro\nConcelho: Aveiro\nFreguesia: União das Freguesias de Glória e Vera Cruz\n\n10 - PRAZO DE EXECUÇÃO DO CONTRATO\nIdentificador do Lote: LOT-0001; LOT-0002; LOT-0003; LOT-0004; LOT-0005; LOT-0006; LOT-0007; LOT-0008; LOT-0009; LOT-0010; LOT-0011\nPrazo de execução do contrato: 60 DIAS\nPrevisão de renovações: Não\n\n11 - FUNDOS EU\nIdentificador do Lote: LOT-0001; LOT-0002; LOT-0003; LOT-0004; LOT-0005; LOT-0006; LOT-0007; LOT-0008; LOT-0009; LOT-0010; LOT-0011\nTêm fundos EU? Sim\n\n12 - DOCUMENTOS DE HABILITAÇÃO\nHabilitação para o exercício da atividade profissional: Não\n\n13 - CONDIÇÕES DE APRESENTAÇÃO\nPlataforma eletrónica utilizada pela entidade adjudicante: VORTAL\nURL para Apresentação: https://community.vortal.biz/public/\nAdmissibilidade da apresentação de propostas variantes: Não autorizado\nPrazo para apresentação das propostas: 29-10-2025 23:59\nPrazo durante o qual os concorrentes são obrigados a manter as respetivas propostas: 132 dias a contar do termo do prazo para a apresentação das propostas\nIndicação de Subcontratação na Proposta: Inexistência de indicação de subcontratação\n\n14 - PRESTAÇÃO DE CAUÇÃO\nPrestação de caução: Não\n\n15 - FORNECIMENTO DAS PEÇAS DO CONCURSO, APRESENTAÇÃO DE PEDIDOS DE PARTICIPAÇÃO E APRESENTAÇÃO DAS PROPOSTAS\nLink para acesso às peças do concurso (URL): https://community.vortal.biz/Public/public-tender-documents/ZUo4TngrVHllZ2ZrWVh3ditXMXRkeDdqdVYzamNCQkVqZkRSWUJ6SUdyMUs3YUFndjhXM1owTVdybXA1U01JOWJNTHlNbEl4UFhPWFV3ZDdLdE1HZlE9PWdnSzQm\n\n20 - OUTROS REQUISITOS\nIdentificador do Lote: LOT-0001; LOT-0002; LOT-0003; LOT-0004; LOT-0005; LOT-0006; LOT-0007; LOT-0008; LOT-0009; LOT-0010; LOT-0011\nInformação sobre contratos reservados. Aplica-se a contratos reservados (54º-A)? Não\n\n21 - CRITÉRIO DE ADJUDICAÇÃO\nO Critério de adjudicação é diferenciado por lote? Não\nMultifator: Sim\nFator: \nNome: Preço\nPonderação: 70%\nSubfatores: Não\nFator: \nNome: Outros\nOutro Nome: Prazo\nPonderação: 20%\nSubfatores: Não\nFator: \nNome: Outros\nOutro Nome: Garantia\nPonderação: 10%\nSubfatores: Não\n\n24 - CONDIÇÕES DO CONTRATO\nIdentificador do Lote: LOT-0001; LOT-0002; LOT-0003; LOT-0004; LOT-0005; LOT-0006; LOT-0007; LOT-0008; LOT-0009; LOT-0010; LOT-0011\nFaturação Eletrónica: Permitido\nObrigação de Subcontratação:\nCódigo da Obrigação de Subcontratação: Não é aplicável nenhuma obrigação de subcontratação.\n\n25 - COMPRA PÚBLICA ESTRATÉGICA\nCompra Pública Estratégica: Inexistência de contratação pública estratégica\n\n26 - INFORMAÇÕES ADICIONAIS\nIdentificador do Lote: LOT-0001; LOT-0002; LOT-0003; LOT-0004; LOT-0005; LOT-0006; LOT-0007; LOT-0008; LOT-0009; LOT-0010; LOT-0011\nContrato adequado para PME: Sim\nCobertura ACP (Acordo dos Contratos Públicos da Organização Mundial do Comércio): Não\n\n27 - IDENTIFICAÇÃO E CONTACTOS DO ÓRGÃO DE RECURSOS ADMINISTRATIVOS\nDesignação: Universidade de Aveiro\nEndereço: Campus Universitário de Santiago 25\nCódigo postal: 3810-193\nLocalidade: Aveiro\nTelefone: +351 234372434\nFax: +351 234370040\nEndereço eletrónico: contratacao@ua.pt\n\n28 - IDENTIFICAÇÃO DO(S) AUTOR(ES) DE ANÚNCIO\nNome: Ana Isabel Pires Sousa da Silva Braga\nCargo: Chefe de Divisão da Área de Aquisições e Contratos\n419676354",
    "nipc": "501461108",
    "distrito": "Aveiro",
    "concelho": "Aveiro",
    "freguesia": "União das Freguesias de Glória e Vera Cruz",
    "site": "https://www.ua.pt",
    "email": "contratacao@ua.pt",
    "designacao_contrato": "Equipamento didático e científico para a criação de um Laboratório de Engenharia Aeroespacial especializado em Sensores e Dispositivos",
    "descricao": "Equipamento didático e científico para a criação de um Laboratório de Engenharia Aeroespacial especializado em Sensores e Dispositivos",
    "preco_base": "63.500,00 EUR",
    "prazo_execucao": "60 DIAS",
    "prazo_apresentacao_propostas": "29-10-2025 23:59",
    "fundos_eu": "Sim",
    "plataforma_eletronica": "VORTAL",
    "url_procedimento": "https://community.vortal.biz/public/",
    "autor_nome": "Ana Isabel Pires Sousa da Silva Braga",
    "autor_cargo": "Chefe de Divisão da Área de Aquisições e Contratos"
  },
  {
    "numero_procedimento": "N/A",
    "entidade": "Autoridade da Concorrência",
    "link": "https://diariodarepublica.pt/dr/detalhe/contrato-publico/27653-941162529",
    "detalhes_completos": "Alteração do Anúncio de procedimento n.º 26721/2025, de 2025-10-10, com o ID 419640673\n\n1 - IDENTIFICAÇÃO E CONTACTOS DA ENTIDADE ADJUDICANTE\nDesignação da entidade adjudicante: Autoridade da Concorrência\nNIPC: 506557057\nServiço/Órgão/Pessoa de contacto: Unidade de Recursos Financeiros e Patrimoniais\nEndereço: Avenida de Berna, n.º 19\nCódigo postal: 1050-037\nLocalidade: Lisboa\nPaís: Portugal\nNUT III: PT170\nDistrito: Lisboa\nConcelho: Lisboa\nFreguesia: Freguesia de Campolide\nTelefone: 217902000\nFax: 217902099\nEndereço da Entidade (URL): www.concorrencia.pt\nEndereço Eletrónico: adc@concorrencia.pt\neDelivery Gateway (URL): https://www.acingov.pt\nFunção da Organização: Adquirente\nNorma jurídica da Entidade Adjudicante: Organismo de direito público\nÁrea de atividade da Autoridade Adjudicante: Serviços públicos das administrações públicas\n\n2 - JORNAL OFICIAL DA UNIÃO EUROPEIA\nO procedimento a que este anúncio diz respeito também é publicitado no Jornal Oficial da União Europeia? Não\n\n3 - AVISO\nModelo de Anúncio: Concurso público\nData de Envio do Anúncio: 20-10-2025\n\n5 - PROCESSO\nTipo de Procedimento: Concurso público\nPreço base do procedimento: Sim\nValor do preço base do procedimento: 120.000,00 EUR\nProcedimento com lotes? Não\n\n6 - OBJETO DO CONTRATO\nNúmero de referência interna: 166/URF/2025\nDesignação do contrato: Aquisição de Equipamentos de Videoconferência\nDescrição: Aquisição de Equipamentos de Videoconferência e serviços de instalação, configuração e documentação de toda a infraestrutura, bem como formação na operação e administração.\nTipo de Contrato Principal: Locação de Bens Móveis\nTipo de Contrato: Locação de Bens Móveis\nClassificação CPV (Vocabulário Comum para os Contratos Públicos)\nObjeto principal\nVocabulário Principal: 32232000\nPreço base s/IVA: 120.000,00 EUR\n\n7 - INDICAÇÕES ADICIONAIS\nO contrato envolve aquisição conjunta (satisfação de várias entidades)? Não\nO contrato é adjudicado por uma central de compras? Não\n\n8 - TÉCNICAS\nO concurso destina-se à celebração de um acordo-quadro? Inexistência de acordo-quadro\nÉ utilizado um leilão eletrónico? Não\nÉ adotada uma fase de negociação? Não\nSistema de Aquisição Dinâmico: Inexistência de sistema de aquisição dinâmico\n\n9 - LOCAL DA EXECUÇÃO DO CONTRATO\nLOCAL DA EXECUÇÃO DO CONTRATO (PROCEDIMENTO)\nPaís: Portugal\nNUT III: PT170\nLocalidade: Freguesia de Campolide\nDistrito: Lisboa\nConcelho: Lisboa\nFreguesia: Freguesia de Campolide\n\n10 - PRAZO DE EXECUÇÃO DO CONTRATO\nPrazo de execução do contrato: 6 MESES\nPrevisão de renovações: Não\n\n11 - FUNDOS EU\nTêm fundos EU? Não\n\n12 - DOCUMENTOS DE HABILITAÇÃO\nHabilitação para o exercício da atividade profissional: Não\n\n13 - CONDIÇÕES DE APRESENTAÇÃO\nPlataforma eletrónica utilizada pela entidade adjudicante: ACIN\nURL para Apresentação: https://www.acingov.pt\nAdmissibilidade da apresentação de propostas variantes: Não autorizado\nPrazo para apresentação das propostas: 27-10-2025 23:26\nPrazo durante o qual os concorrentes são obrigados a manter as respetivas propostas: 66 dias a contar do termo do prazo para a apresentação das propostas\nIndicação de Subcontratação na Proposta: Inexistência de indicação de subcontratação\n\n14 - PRESTAÇÃO DE CAUÇÃO\nPrestação de caução: Não\n\n15 - FORNECIMENTO DAS PEÇAS DO CONCURSO, APRESENTAÇÃO DE PEDIDOS DE PARTICIPAÇÃO E APRESENTAÇÃO DAS PROPOSTAS\nLink para acesso às peças do concurso (URL): https://www.acingov.pt/acingovprod/2/zonaPublica/zona_publica_c/donwloadProcedurePiece/OTg1NjY3\n\n20 - OUTROS REQUISITOS\nInformação sobre contratos reservados. Aplica-se a contratos reservados (54º-A)? Não\n\n21 - CRITÉRIO DE ADJUDICAÇÃO\nMultifator: Sim\nFator: \nNome: Preço\nPonderação: 70%\nSubfatores: Não\nFator: \nNome: Outros\nOutro Nome: Custo de manutenção\nPonderação: 30%\nSubfatores: Não\n\n24 - CONDIÇÕES DO CONTRATO\nFaturação Eletrónica: Permitido\nObrigação de Subcontratação:\nCódigo da Obrigação de Subcontratação: Não é aplicável nenhuma obrigação de subcontratação.\n\n25 - COMPRA PÚBLICA ESTRATÉGICA\nCompra Pública Estratégica: Inexistência de contratação pública estratégica\n\n26 - INFORMAÇÕES ADICIONAIS\nContrato adequado para PME: Não\nCobertura ACP (Acordo dos Contratos Públicos da Organização Mundial do Comércio): Não\n\n27 - IDENTIFICAÇÃO E CONTACTOS DO ÓRGÃO DE RECURSOS ADMINISTRATIVOS\nDesignação: Conselho de Administração da Autoridade da Concorrência\nEndereço: Avenida de Berna, n.º 19\nCódigo postal: 1050-037\nLocalidade: Lisboa\nTelefone: 217902000\nFax: \nEndereço eletrónico: adc@concorrencia.pt\n\n28 - IDENTIFICAÇÃO DO(S) AUTOR(ES) DE ANÚNCIO\nNome: Maria Cristina Chora Fernandes\nCargo: Chefe de Unidade de Recursos Financeiros e Patrimoniais\n\n29 - ALTERAÇÃO\nMotivo da Alteração: Informações agora disponíveis\nIdentificador da Versão do Anúncio a Alterar: 795e3146-5ca1-4710-9f04-dc6f243a0f6b-01\nIdentificador das Secções Alteradas do Anúncio Anterior: Condições de Apresentação\nDescrição das Alterações: Modificação do prazo para a apresentação de propostas\nAlteração dos Documentos do Concurso: Não\n419679757",
    "nipc": "506557057",
    "distrito": "Lisboa",
    "concelho": "Lisboa",
    "freguesia": "Freguesia de Campolide",
    "site": "www.concorrencia.pt",
    "email": "adc@concorrencia.pt",
    "designacao_contrato": "Aquisição de Equipamentos de Videoconferência",
    "descricao": "Aquisição de Equipamentos de Videoconferência e serviços de instalação, configuração e documentação de toda a infraestrutura, bem como formação na operação e administração.",
    "preco_base": "120.000,00 EUR",
    "prazo_execucao": "6 MESES",
    "prazo_apresentacao_propostas": "27-10-2025 23:26",
    "fundos_eu": "Não",
    "plataforma_eletronica": "ACIN",
    "url_procedimento": "https://www.acingov.pt",
    "autor_nome": "Maria Cristina Chora Fernandes",
    "autor_cargo": "Chefe de Unidade de Recursos Financeiros e Patrimoniais"
  },
  {
    "numero_procedimento": "N/A",
    "entidade": "Gebalis - Gestão do Arrendamento da Habitação Municipal de Lisboa, E. M., S. A.",
    "link": "https://diariodarepublica.pt/dr/detalhe/contrato-publico/27654-941162533",
    "detalhes_completos": "1 - IDENTIFICAÇÃO E CONTACTOS DA ENTIDADE ADJUDICANTE\nDesignação da entidade adjudicante: Gebalis - Gestão do Arrendamento da Habitação Municipal de Lisboa, E. M., S. A.\nNIPC: 503541567\nServiço/Órgão/Pessoa de contacto: Joana Pereira\nEndereço: Rua Laura Alves, n.º 12, 7º Piso\nCódigo postal: 1050-138\nLocalidade: Lisboa\nPaís: Portugal\nNUT III: PT170\nDistrito: Lisboa\nConcelho: Lisboa\nFreguesia: Freguesia de Avenidas Novas\nTelefone: 217511000\nFax: 217511000\nEndereço da Entidade (URL): www.gebalis.pt\nEndereço Eletrónico: contratacao.publica@gebalis.pt\nFunção da Organização: Adquirente\nNorma jurídica da Entidade Adjudicante: Empresa pública, controlada por uma autoridade local\nÁrea de atividade da Autoridade Adjudicante: Habitação e equipamentos coletivos\n\n2 - JORNAL OFICIAL DA UNIÃO EUROPEIA\nO procedimento a que este anúncio diz respeito também é publicitado no Jornal Oficial da União Europeia? Não\n\n3 - AVISO\nModelo de Anúncio: Concurso público\nData de Envio do Anúncio: 21-10-2025\n\n5 - PROCESSO\nTipo de Procedimento: Concurso público\nPreço base do procedimento: Sim\nValor do preço base do procedimento: 125.513,00 EUR\nProcedimento com lotes? Não\n\n6 - OBJETO DO CONTRATO\nNúmero de referência interna: AQS 142/Gebalis/2025\nDesignação do contrato: AQS 142/Gebalis/2025 - Serviços de Segurança e Saúde no Trabalho\nDescrição: AQS 142/Gebalis/2025 - Serviços de Segurança e Saúde no Trabalho\nTipo de Contrato Principal: Aquisição de Serviços\nTipo de Contrato: Aquisição de Serviços\nClassificação CPV (Vocabulário Comum para os Contratos Públicos)\nObjeto principal\nVocabulário Principal: 71317200\nPreço base s/IVA: 125.513,00 EUR\n\n7 - INDICAÇÕES ADICIONAIS\nO contrato envolve aquisição conjunta (satisfação de várias entidades)? Não\nO contrato é adjudicado por uma central de compras? Não\n\n8 - TÉCNICAS\nO concurso destina-se à celebração de um acordo-quadro? Inexistência de acordo-quadro\nÉ utilizado um leilão eletrónico? Não\nÉ adotada uma fase de negociação? Não\nSistema de Aquisição Dinâmico: Inexistência de sistema de aquisição dinâmico\n\n9 - LOCAL DA EXECUÇÃO DO CONTRATO\nLOCAL DA EXECUÇÃO DO CONTRATO (PROCEDIMENTO)\nPaís: Portugal\nNUT III: PT170\nLocalidade: Lisboa\nDistrito: Lisboa\nConcelho: Lisboa\nFreguesia: Todas\n\n10 - PRAZO DE EXECUÇÃO DO CONTRATO\nPrazo de execução do contrato: 24 MESES\nPrevisão de renovações: Não\n\n11 - FUNDOS EU\nTêm fundos EU? Não\n\n12 - DOCUMENTOS DE HABILITAÇÃO\nHabilitação para o exercício da atividade profissional: Sim\nTipo: Certificado\nDescrição: Comprovativo da autorização para atividade nas áreas da Segurança e da Saúde no trabalho\n\n13 - CONDIÇÕES DE APRESENTAÇÃO\nPlataforma eletrónica utilizada pela entidade adjudicante: ANOGOV\nURL para Apresentação: https://www.anogov.com/em-gebalis/faces/\nAdmissibilidade da apresentação de propostas variantes: Não autorizado\nPrazo para apresentação das propostas: 05-11-2025 23:59\nPrazo durante o qual os concorrentes são obrigados a manter as respetivas propostas: 180 dias a contar do termo do prazo para a apresentação das propostas\nApresentação de Catálogo Eletrónico: Permitido\nIndicação de Subcontratação na Proposta: Inexistência de indicação de subcontratação\n\n14 - PRESTAÇÃO DE CAUÇÃO\nPrestação de caução: Não\n\n15 - FORNECIMENTO DAS PEÇAS DO CONCURSO, APRESENTAÇÃO DE PEDIDOS DE PARTICIPAÇÃO E APRESENTAÇÃO DAS PROPOSTAS\nLink para acesso às peças do concurso (URL): https://www.anogov.com/em-gebalis/faces/app/acessoDocs.jsp?codigoAcesso=mqqKN4F3s0QpvDaclFrOM1cNtQSGxJx0S2ZXLWmB45yAtlitX3\n\n20 - OUTROS REQUISITOS\nInformação sobre contratos reservados. Aplica-se a contratos reservados (54º-A)? Não\n\n21 - CRITÉRIO DE ADJUDICAÇÃO\nMultifator: Não\nMonofator:\nNome: Preço\n\n24 - CONDIÇÕES DO CONTRATO\nFaturação Eletrónica: Permitido\nObrigação de Subcontratação:\nCódigo da Obrigação de Subcontratação: Não é aplicável nenhuma obrigação de subcontratação.\n\n25 - COMPRA PÚBLICA ESTRATÉGICA\nCompra Pública Estratégica: Inexistência de contratação pública estratégica\n\n26 - INFORMAÇÕES ADICIONAIS\nContrato adequado para PME: Não\nCobertura ACP (Acordo dos Contratos Públicos da Organização Mundial do Comércio): Não\n\n27 - IDENTIFICAÇÃO E CONTACTOS DO ÓRGÃO DE RECURSOS ADMINISTRATIVOS\nDesignação: Conselho de Administração\nEndereço: Rua Laura Alves, 12, 7º\nCódigo postal: 1050-138\nLocalidade: Lisboa\nEndereço eletrónico: contratacao.publica@gebalis.pt\n\n28 - IDENTIFICAÇÃO DO(S) AUTOR(ES) DE ANÚNCIO\nNome: Miguel Silva Pereira\nCargo: Vogal Conselho de Administração\n419679165",
    "nipc": "503541567",
    "distrito": "Lisboa",
    "concelho": "Lisboa",
    "freguesia": "Freguesia de Avenidas Novas",
    "site": "www.gebalis.pt",
    "email": "contratacao.publica@gebalis.pt",
    "designacao_contrato": "AQS 142/Gebalis/2025 - Serviços de Segurança e Saúde no Trabalho",
    "descricao": "AQS 142/Gebalis/2025 - Serviços de Segurança e Saúde no Trabalho",
    "preco_base": "125.513,00 EUR",
    "prazo_execucao": "24 MESES",
    "prazo_apresentacao_propostas": "05-11-2025 23:59",
    "fundos_eu": "Não",
    "plataforma_eletronica": "ANOGOV",
    "url_procedimento": "https://www.anogov.com/em-gebalis/faces/",
    "autor_nome": "Miguel Silva Pereira",
    "autor_cargo": "Vogal Conselho de Administração"
  }
]