[
  {
    "numero_procedimento": "N/A",
    "entidade": "Centro Formação Profissional Para o Sector Alimentar",
    "link": "https://diariodarepublica.pt/dr/detalhe/contrato-publico/27701-941547435",
    "detalhes_completos": "1 - IDENTIFICAÇÃO E CONTACTOS DA ENTIDADE ADJUDICANTE\nDesignação da entidade adjudicante: Centro Formação Profissional Para o Sector Alimentar\nNIPC: 506024717\nEndereço: Av  25 de Abril  22\nCódigo postal: 1675-183\nLocalidade: Pontinha\nPaís: Portugal\nNUT III: PT170\nDistrito: Lisboa\nConcelho: Odivelas\nFreguesia: União das Freguesias de Pontinha e Famões\nTelefone: 214789500\nFax: 214789500\nEndereço da Entidade (URL): www.cfpsa.pt\nEndereço Eletrónico: cfpsa@cfpsa.pt\nFunção da Organização: Adquirente\nNorma jurídica da Entidade Adjudicante: Organismo de direito público\nÁrea de atividade da Entidade Adjudicante: Atividades aeroportuárias\n\n2 - JORNAL OFICIAL DA UNIÃO EUROPEIA\nO procedimento a que este anúncio diz respeito também é publicitado no Jornal Oficial da União Europeia? Não\n\n3 - AVISO\nModelo de Anúncio: Concurso público\nData de Envio do Anúncio: 21-10-2025\n\n5 - PROCESSO\nTipo de Procedimento: Concurso público\nPreço base do procedimento: Sim\nValor do preço base do procedimento: 45.240,00 EUR\nProcedimento com lotes? Não\n\n6 - OBJETO DO CONTRATO\nNúmero de referência interna: AQS/CPU/057/25\nDesignação do contrato: AQS/CPU/057/25 Serviço integrado de comunicações fixas de voz, dados e serviço móvel terrestre - 2026/2027\nDescrição: Serviço integrado de comunicações fixas de voz, dados e serviço móvel terrestre - 2026/2027\nTipo de Contrato Principal: Aquisição de Serviços\nTipo de Contrato: Aquisição de Serviços\nClassificação CPV (Vocabulário Comum para os Contratos Públicos)\nObjeto principal\nVocabulário Principal: 64227000\nPreço base s/IVA: 45.240,00 EUR\n\n7 - INDICAÇÕES ADICIONAIS\nO contrato envolve aquisição conjunta (satisfação de várias entidades)? Não\nO contrato é adjudicado por uma central de compras? Não\n\n8 - TÉCNICAS\nO concurso destina-se à celebração de um acordo-quadro? Inexistência de acordo-quadro\nÉ utilizado um leilão eletrónico? Não\nÉ adotada uma fase de negociação? Não\nSistema de Aquisição Dinâmico: Inexistência de sistema de aquisição dinâmico\n\n9 - LOCAL DA EXECUÇÃO DO CONTRATO\nLOCAL DA EXECUÇÃO DO CONTRATO (PROCEDIMENTO)\nPaís: Portugal\nNUT III: PT16E\nLocalidade: Coimbra\nDistrito: Coimbra\nConcelho: Coimbra\nFreguesia: Freguesia de Santo António dos Olivais\nPaís: Portugal\nNUT III: PT170\nLocalidade: Pontinha\nDistrito: Lisboa\nConcelho: Odivelas\nFreguesia: União das Freguesias de Pontinha e Famões\n\n10 - PRAZO DE EXECUÇÃO DO CONTRATO\nData de Início: 01-01-2026\nData de Fim: 31-12-2027\nPrevisão de renovações: Não\n\n11 - FUNDOS EU\nTêm fundos EU? Não\n\n12 - DOCUMENTOS DE HABILITAÇÃO\nHabilitação para o exercício da atividade profissional: Não\n\n13 - CONDIÇÕES DE APRESENTAÇÃO\nPlataforma eletrónica utilizada pela entidade adjudicante: COMPRASPT\nURL para Apresentação: https://www.compraspt.com/cpt-cfpsa/faces/\nAdmissibilidade da apresentação de propostas variantes: Não autorizado\nPrazo para apresentação das propostas: 03-11-2025 23:59\nPrazo durante o qual os concorrentes são obrigados a manter as respetivas propostas: 66 dias a contar do termo do prazo para a apresentação das propostas\nApresentação de Catálogo Eletrónico: Permitido\nIndicação de Subcontratação na Proposta: A parte do contrato que o proponente tenciona subcontratar\n\n14 - PRESTAÇÃO DE CAUÇÃO\nPrestação de caução: Não\n\n15 - FORNECIMENTO DAS PEÇAS DO CONCURSO, APRESENTAÇÃO DE PEDIDOS DE PARTICIPAÇÃO E APRESENTAÇÃO DAS PROPOSTAS\nLink para acesso às peças do concurso (URL): https://www.compraspt.com/cpt-cfpsa/faces/app/acessoDocs.jsp?codigoAcesso=Ml1CekcIgZpCWBP43QPEmDblMtOAPjCMfkpS0Wyt8roqstJwpd\n\n20 - OUTROS REQUISITOS\nInformação sobre contratos reservados. Aplica-se a contratos reservados (54º-A)? Não\n\n21 - CRITÉRIO DE ADJUDICAÇÃO\nMultifator: Sim\nFator: \nNome: Preço\nPonderação: 60%\nSubfatores: Não\nFator: \nNome: Outros\nOutro Nome: Serviços propostos\nPonderação: 40%\nSubfatores: Não\n\n24 - CONDIÇÕES DO CONTRATO\nFaturação Eletrónica: Necessário\nObrigação de Subcontratação:\nCódigo da Obrigação de Subcontratação: Não é aplicável nenhuma obrigação de subcontratação.\n\n25 - COMPRA PÚBLICA ESTRATÉGICA\nCompra Pública Estratégica: Inexistência de contratação pública estratégica\n\n26 - INFORMAÇÕES ADICIONAIS\nContrato adequado para PME: Não\nCobertura ACP (Acordo dos Contratos Públicos da Organização Mundial do Comércio): Não\n\n27 - IDENTIFICAÇÃO E CONTACTOS DO ÓRGÃO DE RECURSOS ADMINISTRATIVOS\nDesignação: Conselho de Administração\nEndereço: Av. 25 de Abril, 22\nCódigo postal: 1675-183\nLocalidade: Pontinha\nEndereço eletrónico: cfpsa@cfpsa.pt\nPrazo de interposição do recurso: 15 dias\n\n28 - IDENTIFICAÇÃO DO(S) AUTOR(ES) DE ANÚNCIO\nNome: Jorge Silva\nCargo: Responsável Divisão Aquisições e Serviços\n419676484",
    "nipc": "506024717",
    "distrito": "Lisboa",
    "concelho": "Odivelas",
    "freguesia": "União das Freguesias de Pontinha e Famões",
    "site": "www.cfpsa.pt",
    "email": "cfpsa@cfpsa.pt",
    "designacao_contrato": "AQS/CPU/057/25 Serviço integrado de comunicações fixas de voz, dados e serviço móvel terrestre - 2026/2027",
    "descricao": "Serviço integrado de comunicações fixas de voz, dados e serviço móvel terrestre - 2026/2027",
    "preco_base": "45.240,00 EUR",
    "prazo_execucao": null,
    "prazo_apresentacao_propostas": "03-11-2025 23:59",
    "fundos_eu": "Não",
    "plataforma_eletronica": "COMPRASPT",
    "url_procedimento": "https://www.compraspt.com/cpt-cfpsa/faces/",
    "autor_nome": "Jorge Silva",
    "autor_cargo": "Responsável Divisão Aquisições e Serviços"
  },
  {
    "numero_procedimento": "N/A",
    "entidade": "Comunidade Intermunicipal da Região de Aveiro",
    "link": "https://diariodarepublica.pt/dr/detalhe/contrato-publico/27704-941547437",
    "detalhes_completos": "Alteração do Anúncio de procedimento n.º 25473/2025, de 2025-09-29, com o ID 419567433\n\n1 - IDENTIFICAÇÃO E CONTACTOS DA ENTIDADE ADJUDICANTE\nDesignação da entidade adjudicante: Comunidade Intermunicipal da Região de Aveiro\nNIPC: 508771935\nServiço/Órgão/Pessoa de contacto: Conselho Intermunicipal da Comunidade Intermunicipal da Região de Aveiro\nEndereço: Rua do Carmo n.º 20\nCódigo postal: 3800-127\nLocalidade: Aveiro\nPaís: Portugal\nNUT III: PT16D\nDistrito: Aveiro\nConcelho: Aveiro\nFreguesia: Todas\nTelefone: 234377650\nFax: 234377659\nEndereço da Entidade (URL): http://www.regiaodeaveiro.pt\nEndereço Eletrónico: geral@regiaodeaveiro.pt\neDelivery Gateway (URL): https://www.acingov.pt\nFunção da Organização: Adquirente\nNorma jurídica da Entidade Adjudicante: Organismo de direito público\nÁrea de atividade da Autoridade Adjudicante: Serviços públicos das administrações públicas\n\n2 - JORNAL OFICIAL DA UNIÃO EUROPEIA\nO procedimento a que este anúncio diz respeito também é publicitado no Jornal Oficial da União Europeia? Não\n\n3 - AVISO\nModelo de Anúncio: Concurso público\nData de Envio do Anúncio: 21-10-2025\n\n5 - PROCESSO\nTipo de Procedimento: Concurso público\nPreço base do procedimento: Sim\nValor do preço base do procedimento: 2.900.000,00 EUR\nProcedimento com lotes? Não\n\n6 - OBJETO DO CONTRATO\nNúmero de referência interna: 2025.300.10.001.003\nDesignação do contrato: Empreitada de Ampliação do Edifício da Sede da Comunidade Intermunicipal da Região de Aveiro\nDescrição: Empreitada de Ampliação do Edifício da Sede da Comunidade Intermunicipal da Região de Aveiro\nTipo de Contrato Principal: Empreitada de Obras Públicas\nTipo de Contrato: Empreitada de Obras Públicas\nClassificação CPV (Vocabulário Comum para os Contratos Públicos)\nObjeto principal\nVocabulário Principal: 45220000\nPreço base s/IVA: 2.900.000,00 EUR\n\n7 - INDICAÇÕES ADICIONAIS\nO contrato envolve aquisição conjunta (satisfação de várias entidades)? Não\nO contrato é adjudicado por uma central de compras? Não\n\n8 - TÉCNICAS\nO concurso destina-se à celebração de um acordo-quadro? Inexistência de acordo-quadro\nÉ utilizado um leilão eletrónico? Não\nÉ adotada uma fase de negociação? Não\nSistema de Aquisição Dinâmico: Inexistência de sistema de aquisição dinâmico\n\n9 - LOCAL DA EXECUÇÃO DO CONTRATO\nLOCAL DA EXECUÇÃO DO CONTRATO (PROCEDIMENTO)\nPaís: Portugal\nNUT III: PT16D\nLocalidade: Aveiro\nDistrito: Aveiro\nConcelho: Todos\nFreguesia: Todas\n\n10 - PRAZO DE EXECUÇÃO DO CONTRATO\nPrazo de execução do contrato: 20 MESES\nPrevisão de renovações: Não\n\n11 - FUNDOS EU\nTêm fundos EU? Não\n\n12 - DOCUMENTOS DE HABILITAÇÃO\nHabilitação para o exercício da atividade profissional: Sim\nTipo: Alvará\nDescrição: Alvará emitido pelo Instituto dos Mercados Públicos, do Imobiliário e da Construção, I.P., contendo as habilitações adequadas e necessárias à execução da obra a realizar, nomeadamente:\n 1.ª subcategoria (Estruturas e elementos de betão), 2.ª subcategoria (Estruturas Metálicas), 4.ª subcategoria (Alvenarias, rebocos e assentamento de cantarias), 5.ª subcategoria (Estuques pinturas e outros revestimentos), 6.ª subcategoria (Carpintarias), 8.º subcategoria (Canalizações e condutas em edifícios) da 1.ª categoria (Edifícios e património construído) em classe que cubra o valor total da proposta;\ne em classe correspondente aos respetivos trabalhos na:\n 1ª subcategoria (Instalações elétricas de utilização de baixa tensão com potência até 50 kVA), 5ª subcategoria (Redes e instalações elétricas de tensão de serviço acima de 30 kV), 9.ª subcategoria (Infraestruturas de telecomunicações); a 10ª subcategoria (Sistemas de extinção de incêndios, de segurança e deteção), 11.ª subcategoria (Instalações de elevação), 12.º subcategoria (Aquecimento, ventilação, ar condicionado e refrigeração) da 4ª categoria (Instalações elétricas e mecânicas);\n2.ª subcategoria (Movimento de terras) da 5.ª categoria (Outros trabalhos)\n\n13 - CONDIÇÕES DE APRESENTAÇÃO\nPlataforma eletrónica utilizada pela entidade adjudicante: ACIN\nURL para Apresentação: https://www.acingov.pt\nAdmissibilidade da apresentação de propostas variantes: Não autorizado\nPrazo para apresentação das propostas: 20-11-2025 23:59\nPrazo durante o qual os concorrentes são obrigados a manter as respetivas propostas: 180 dias a contar do termo do prazo para a apresentação das propostas\nIndicação de Subcontratação na Proposta: Inexistência de indicação de subcontratação\n\n14 - PRESTAÇÃO DE CAUÇÃO\nPrestação de caução: Sim\nPercentagem: 5%\nDescrição da Garantia Exigida: O valor da caução é de 5.00% do preço contratual.\n\n15 - FORNECIMENTO DAS PEÇAS DO CONCURSO, APRESENTAÇÃO DE PEDIDOS DE PARTICIPAÇÃO E APRESENTAÇÃO DAS PROPOSTAS\nLink para acesso às peças do concurso (URL): https://www.acingov.pt/acingovprod/2/zonaPublica/zona_publica_c/donwloadProcedurePiece/OTM1NDc2\n\n20 - OUTROS REQUISITOS\nInformação sobre contratos reservados. Aplica-se a contratos reservados (54º-A)? Não\n\n21 - CRITÉRIO DE ADJUDICAÇÃO\nMultifator: Não\nMonofator:\nNome: Outros\nOutro nome: Fator Preço\n\n24 - CONDIÇÕES DO CONTRATO\nFaturação Eletrónica: Permitido\nObrigação de Subcontratação:\nCódigo da Obrigação de Subcontratação: Não é aplicável nenhuma obrigação de subcontratação.\n\n25 - COMPRA PÚBLICA ESTRATÉGICA\nCompra Pública Estratégica: Inexistência de contratação pública estratégica\n\n26 - INFORMAÇÕES ADICIONAIS\nContrato adequado para PME: Não\nCobertura ACP (Acordo dos Contratos Públicos da Organização Mundial do Comércio): Não\n\n27 - IDENTIFICAÇÃO E CONTACTOS DO ÓRGÃO DE RECURSOS ADMINISTRATIVOS\nDesignação: Conselho Intermunicipal\nEndereço: Rua do Carmo n.º 20\nCódigo postal: 3800-127\nLocalidade: Aveiro\nTelefone: 234377650\nFax: \nEndereço eletrónico: geral@regiaodeaveiro.pt\nPrazo de interposição do recurso: 30 dias\n\n28 - IDENTIFICAÇÃO DO(S) AUTOR(ES) DE ANÚNCIO\nNome: Jorge Henrique Fernandes de Almeida\nCargo: O Presidente do Conselho Intermunicipal\n\n29 - ALTERAÇÃO\nMotivo da Alteração: Informações atualizadas\nIdentificador da Versão do Anúncio a Alterar: 03ca3bea-ebe5-4ae2-b52b-e2e92d87034c-02\nIdentificador das Secções Alteradas do Anúncio Anterior: Condições de Apresentação\nDescrição das Alterações: Modificação do prazo para a apresentação de propostas.\nAlteração dos Documentos do Concurso: Sim\nData de alteração dos documentos do concurso: 21-10-2025\n419683555",
    "nipc": "508771935",
    "distrito": "Aveiro",
    "concelho": "Aveiro",
    "freguesia": "Todas",
    "site": "http://www.regiaodeaveiro.pt",
    "email": "geral@regiaodeaveiro.pt",
    "designacao_contrato": "Empreitada de Ampliação do Edifício da Sede da Comunidade Intermunicipal da Região de Aveiro",
    "descricao": "Empreitada de Ampliação do Edifício da Sede da Comunidade Intermunicipal da Região de Aveiro",
    "preco_base": "2.900.000,00 EUR",
    "prazo_execucao": "20 MESES",
    "prazo_apresentacao_propostas": "20-11-2025 23:59",
    "fundos_eu": "Não",
    "plataforma_eletronica": "ACIN",
    "url_procedimento": "https://www.acingov.pt",
    "autor_nome": "Jorge Henrique Fernandes de Almeida",
    "autor_cargo": "O Presidente do Conselho Intermunicipal"
  },
  {
    "numero_procedimento": "N/A",
    "entidade": "Município de Paços de Ferreira",
    "link": "https://diariodarepublica.pt/dr/detalhe/contrato-publico/27706-941547438",
    "detalhes_completos": "1 - IDENTIFICAÇÃO E CONTACTOS DA ENTIDADE ADJUDICANTE\nDesignação da entidade adjudicante: Município de Paços de Ferreira\nNIPC: 502173297\nServiço/Órgão/Pessoa de contacto: Departamento de Organização Administrativa\nEndereço: Praça da República, n.º 46\nCódigo postal: 4590-527\nLocalidade: Paços de Ferreira\nPaís: Portugal\nNUT III: PTZZZ\nDistrito: Todos\nConcelho: Todos\nFreguesia: Todas\nTelefone: 255860700\nFax: 255860734\nEndereço da Entidade (URL): http://www.cm-pacosdeferreira.pt\nEndereço Eletrónico: geral@cm-pacosdeferreira.pt\neDelivery Gateway (URL): https://www.acingov.pt\nFunção da Organização: Adquirente\nNorma jurídica da Entidade Adjudicante: Organismo de direito público\nÁrea de atividade da Autoridade Adjudicante: Serviços públicos das administrações públicas\n\n2 - JORNAL OFICIAL DA UNIÃO EUROPEIA\nO procedimento a que este anúncio diz respeito também é publicitado no Jornal Oficial da União Europeia? Não\n\n3 - AVISO\nModelo de Anúncio: Concurso público\nData de Envio do Anúncio: 21-10-2025\n\n5 - PROCESSO\nTipo de Procedimento: Concurso público\nPreço base do procedimento: Sim\nValor do preço base do procedimento: 86.000,00 EUR\nProcedimento com lotes? Não\n\n6 - OBJETO DO CONTRATO\nNúmero de referência interna: 166/F/2025\nDesignação do contrato: Fornecimento e colocação de almofadas redutoras de velocidade e marcos balizadores para acalmia de tráfego em diversas ruas do concelho, pelo prazo de 12 meses\nDescrição: Fornecimento e colocação de almofadas redutoras de velocidade e marcos balizadores para acalmia de tráfego em diversas ruas do concelho, pelo prazo de 12 meses\nTipo de Contrato Principal: Aquisição de Bens Móveis\nTipo de Contrato: Aquisição de Bens Móveis\nClassificação CPV (Vocabulário Comum para os Contratos Públicos)\nObjeto principal\nVocabulário Principal: 34996000\nPreço base s/IVA: 68.000,00 EUR\nObjeto Complementar\nVocabulário Principal: 34928000\nPreço base s/IVA: 18.000,00 EUR\n\n7 - INDICAÇÕES ADICIONAIS\nO contrato envolve aquisição conjunta (satisfação de várias entidades)? Não\nO contrato é adjudicado por uma central de compras? Não\n\n8 - TÉCNICAS\nO concurso destina-se à celebração de um acordo-quadro? Inexistência de acordo-quadro\nÉ utilizado um leilão eletrónico? Não\nÉ adotada uma fase de negociação? Não\nSistema de Aquisição Dinâmico: Inexistência de sistema de aquisição dinâmico\n\n9 - LOCAL DA EXECUÇÃO DO CONTRATO\nLOCAL DA EXECUÇÃO DO CONTRATO (PROCEDIMENTO)\nPaís: Portugal\nNUT III: PT11C\nLocalidade: Todas\nDistrito: Porto\nConcelho: Paços de Ferreira\nFreguesia: Todas\n\n10 - PRAZO DE EXECUÇÃO DO CONTRATO\nPrazo de execução do contrato: 12 MESES\nPrevisão de renovações: Não\n\n11 - FUNDOS EU\nTêm fundos EU? Não\n\n12 - DOCUMENTOS DE HABILITAÇÃO\nHabilitação para o exercício da atividade profissional: Não\n\n13 - CONDIÇÕES DE APRESENTAÇÃO\nPlataforma eletrónica utilizada pela entidade adjudicante: ACIN\nURL para Apresentação: https://www.acingov.pt\nAdmissibilidade da apresentação de propostas variantes: Não autorizado\nPrazo para apresentação das propostas: 29-10-2025 23:59\nPrazo durante o qual os concorrentes são obrigados a manter as respetivas propostas: 66 dias a contar do termo do prazo para a apresentação das propostas\nIndicação de Subcontratação na Proposta: Inexistência de indicação de subcontratação\n\n14 - PRESTAÇÃO DE CAUÇÃO\nPrestação de caução: Não\n\n15 - FORNECIMENTO DAS PEÇAS DO CONCURSO, APRESENTAÇÃO DE PEDIDOS DE PARTICIPAÇÃO E APRESENTAÇÃO DAS PROPOSTAS\nLink para acesso às peças do concurso (URL): https://www.acingov.pt/acingovprod/2/zonaPublica/zona_publica_c/donwloadProcedurePiece/OTg4NDE5\n\n20 - OUTROS REQUISITOS\nInformação sobre contratos reservados. Aplica-se a contratos reservados (54º-A)? Não\n\n21 - CRITÉRIO DE ADJUDICAÇÃO\nMultifator: Não\nMonofator:\nNome: Preço\n\n24 - CONDIÇÕES DO CONTRATO\nFaturação Eletrónica: Permitido\nObrigação de Subcontratação:\nCódigo da Obrigação de Subcontratação: Não é aplicável nenhuma obrigação de subcontratação.\n\n25 - COMPRA PÚBLICA ESTRATÉGICA\nCompra Pública Estratégica: Inexistência de contratação pública estratégica\n\n26 - INFORMAÇÕES ADICIONAIS\nContrato adequado para PME: Não\nCobertura ACP (Acordo dos Contratos Públicos da Organização Mundial do Comércio): Não\n\n27 - IDENTIFICAÇÃO E CONTACTOS DO ÓRGÃO DE RECURSOS ADMINISTRATIVOS\nDesignação: Departamento de Organização Administrativa\nEndereço: Praça da República, n.º 46\nCódigo postal: 4590-527\nLocalidade: Paços de Ferreira\nTelefone: 255860700\nFax: \nEndereço eletrónico: geral@cm-pacosdeferreira.pt\nPrazo de interposição do recurso: 5 dias\n\n28 - IDENTIFICAÇÃO DO(S) AUTOR(ES) DE ANÚNCIO\nNome: Paulo Jorge Rodrigues Ferreira\nCargo: Presidente da Câmara Municipal\n419671031",
    "nipc": "502173297",
    "distrito": "Todos",
    "concelho": "Todos",
    "freguesia": "Todas",
    "site": "http://www.cm-pacosdeferreira.pt",
    "email": "geral@cm-pacosdeferreira.pt",
    "designacao_contrato": "Fornecimento e colocação de almofadas redutoras de velocidade e marcos balizadores para acalmia de tráfego em diversas ruas do concelho, pelo prazo de 12 meses",
    "descricao": "Fornecimento e colocação de almofadas redutoras de velocidade e marcos balizadores para acalmia de tráfego em diversas ruas do concelho, pelo prazo de 12 meses",
    "preco_base": "68.000,00 EUR",
    "prazo_execucao": "12 MESES",
    "prazo_apresentacao_propostas": "29-10-2025 23:59",
    "fundos_eu": "Não",
    "plataforma_eletronica": "ACIN",
    "url_procedimento": "https://www.acingov.pt",
    "autor_nome": "Paulo Jorge Rodrigues Ferreira",
    "autor_cargo": "Presidente da Câmara Municipal"
  },
  {
    "numero_procedimento": "N/A",
    "entidade": "Navegação Aérea de Portugal - NAV Portugal, E.P.E.",
    "link": "https://diariodarepublica.pt/dr/detalhe/contrato-publico/27708-941547439",
    "detalhes_completos": "1 - IDENTIFICAÇÃO E CONTACTOS DA ENTIDADE ADJUDICANTE\nDesignação da entidade adjudicante: Navegação Aérea de Portugal - NAV Portugal, E.P.E.\nNIPC: 504448064\nEndereço: Rua D, Edificio 121, Aeroporto de Lisboa\nCódigo postal: 1700-008\nLocalidade: Lisboa\nPaís: Portugal\nNUT III: PT170\nDistrito: Lisboa\nConcelho: Todos\nFreguesia: Todas\nTelefone: 218553100\nFax: 218553100\nEndereço da Entidade (URL): www.nav.pt\nEndereço Eletrónico: compras@nav.pt\nFunção da Organização: Adquirente\nNorma jurídica da Entidade Adjudicante: Autoridade da administração central\nÁrea de atividade da Entidade Adjudicante: Atividades aeroportuárias\n\n2 - JORNAL OFICIAL DA UNIÃO EUROPEIA\nO procedimento a que este anúncio diz respeito também é publicitado no Jornal Oficial da União Europeia? Não\n\n3 - AVISO\nModelo de Anúncio: Concurso público\nData de Envio do Anúncio: 21-10-2025\n\n5 - PROCESSO\nTipo de Procedimento: Concurso público\nPreço base do procedimento: Sim\nValor do preço base do procedimento: 2.469.600,00 EUR\nProcedimento com lotes? Sim\nNº Máx. de Lotes Autorizado: 7\nNúmero máximo de lotes que podem ser adjudicados a um concorrente: 7\n\n6 - OBJETO DO CONTRATO\nNúmero de referência interna: Pº 460/25\nDesignação do contrato: Pº 460/25 - AQUISIÇÃO DE SERVIÇOS DE LIMPEZA E FORNECIMENTO DE PRODUTOS DE HIGIENE E LIMPEZA PARA AS INSTALAÇÕES DA NAV PORTUGAL, E.P.E., SITAS EM LISBOA, CASCAIS, PORTO, FARO, PONTA DELGADA, HORTA, FLORES, SANTA MARIA, MADEIRA E PORTO SANTO\nDescrição: Pº 460/25 - AQUISIÇÃO DE SERVIÇOS DE LIMPEZA E FORNECIMENTO DE PRODUTOS DE HIGIENE E LIMPEZA PARA AS INSTALAÇÕES DA NAV PORTUGAL, E.P.E., SITAS EM LISBOA, CASCAIS, PORTO, FARO, PONTA DELGADA, HORTA, FLORES, SANTA MARIA, MADEIRA E PORTO SANTO\nTipo de Contrato Principal: Aquisição de Serviços\nTipo de Contrato: Aquisição de Serviços\nClassificação CPV (Vocabulário Comum para os Contratos Públicos)\nObjeto principal\nVocabulário Principal: 90900000\nPreço base s/IVA: 2.469.600,00 EUR\nLotes: \nNº: LOT-0001\nDescrição do Lote: Lote 1 - Lisboa, Cacais, Porto e Faro\nPreço base s/IVA: 2.010.000,00 EUR\nClassificação CPV (Vocabulário Comum para os Contratos Públicos)\nObjeto principal\nVocabulário Principal: 90900000\nNº: LOT-0002\nDescrição do Lote: Lote 2 - Ilha Ponta Delgada\nPreço base s/IVA: 73.500,00 EUR\nClassificação CPV (Vocabulário Comum para os Contratos Públicos)\nObjeto principal\nVocabulário Principal: 90900000\nNº: LOT-0003\nDescrição do Lote: Lote 3 - Ilha da Horta\nPreço base s/IVA: 24.000,00 EUR\nClassificação CPV (Vocabulário Comum para os Contratos Públicos)\nObjeto principal\nVocabulário Principal: 90900000\nNº: LOT-0004\nDescrição do Lote: Lote 4 - Ilha das Flores\nPreço base s/IVA: 48.600,00 EUR\nClassificação CPV (Vocabulário Comum para os Contratos Públicos)\nObjeto principal\nVocabulário Principal: 90900000\nNº: LOT-0005\nDescrição do Lote: Lote 5 - Ilha Santa Maria\nPreço base s/IVA: 163.500,00 EUR\nClassificação CPV (Vocabulário Comum para os Contratos Públicos)\nObjeto principal\nVocabulário Principal: 90900000\nNº: LOT-0006\nDescrição do Lote: Lote 6 - Ilha da Madeira\nPreço base s/IVA: 98.400,00 EUR\nClassificação CPV (Vocabulário Comum para os Contratos Públicos)\nObjeto principal\nVocabulário Principal: 90900000\nNº: LOT-0007\nDescrição do Lote: Lote 7 - Ilha Porto Santo\nPreço base s/IVA: 51.600,00 EUR\nClassificação CPV (Vocabulário Comum para os Contratos Públicos)\nObjeto principal\nVocabulário Principal: 90900000\n\n7 - INDICAÇÕES ADICIONAIS\nO contrato envolve aquisição conjunta (satisfação de várias entidades)? Não\nO contrato é adjudicado por uma central de compras? Não\n\n8 - TÉCNICAS\nO concurso destina-se à celebração de um acordo-quadro? Inexistência de acordo-quadro\nÉ utilizado um leilão eletrónico? Não\nÉ adotada uma fase de negociação? Não\nSistema de Aquisição Dinâmico: Inexistência de sistema de aquisição dinâmico\n\n9 - LOCAL DA EXECUÇÃO DO CONTRATO\nLOCAL DA EXECUÇÃO DO CONTRATO (PROCEDIMENTO)\nLOCAL DA EXECUÇÃO DO CONTRATO (LOTE)\nIdentificador do Lote: LOT-0001\nPaís: Portugal\nNUT III: PT170\nLocalidade: Lisboa\nDistrito: Lisboa\nConcelho: Lisboa\nFreguesia: Freguesia de Olivais\nIdentificador do Lote: LOT-0001\nPaís: Portugal\nNUT III: PT170\nLocalidade: Cascais\nDistrito: Lisboa\nConcelho: Cascais\nFreguesia: Todas\nIdentificador do Lote: LOT-0001\nPaís: Portugal\nNUT III: PT11A\nLocalidade: Porto\nDistrito: Porto\nConcelho: Porto\nFreguesia: Todas\nIdentificador do Lote: LOT-0001\nPaís: Portugal\nNUT III: PT150\nLocalidade: Faro\nDistrito: Faro\nConcelho: Faro\nFreguesia: Todas\nIdentificador do Lote: LOT-0002\nPaís: Portugal\nNUT III: PT200\nLocalidade: Ponta Delgada\nDistrito: Região Autónoma dos Açores\nConcelho: Ponta Delgada\nFreguesia: Todas\nIdentificador do Lote: LOT-0003\nPaís: Portugal\nNUT III: PT200\nLocalidade: Horta\nDistrito: Região Autónoma dos Açores\nConcelho: Horta\nFreguesia: Todas\nIdentificador do Lote: LOT-0004\nPaís: Portugal\nNUT III: PT200\nLocalidade: Flores\nDistrito: Região Autónoma dos Açores\nConcelho: Todos\nFreguesia: Todas\nIdentificador do Lote: LOT-0005\nPaís: Portugal\nNUT III: PT200\nLocalidade: Santa Maria\nDistrito: Região Autónoma dos Açores\nConcelho: Vila do Porto\nFreguesia: Todas\nIdentificador do Lote: LOT-0006\nPaís: Portugal\nNUT III: PT300\nLocalidade: Madeira\nDistrito: Região Autónoma da Madeira\nConcelho: Funchal\nFreguesia: Todas\nIdentificador do Lote: LOT-0007\nPaís: Portugal\nNUT III: PT300\nLocalidade: Porto Santo\nDistrito: Região Autónoma da Madeira\nConcelho: Porto Santo\nFreguesia: Todas\n\n10 - PRAZO DE EXECUÇÃO DO CONTRATO\nIdentificador do Lote: LOT-0001\nPrazo de execução do contrato: 3 ANOS\nPrevisão de renovações: Não\nIdentificador do Lote: LOT-0002\nPrazo de execução do contrato: 3 ANOS\nPrevisão de renovações: Não\nIdentificador do Lote: LOT-0003\nPrazo de execução do contrato: 3 ANOS\nPrevisão de renovações: Não\nIdentificador do Lote: LOT-0004\nPrazo de execução do contrato: 3 ANOS\nPrevisão de renovações: Não\nIdentificador do Lote: LOT-0005\nPrazo de execução do contrato: 3 ANOS\nPrevisão de renovações: Não\nIdentificador do Lote: LOT-0006\nPrazo de execução do contrato: 3 ANOS\nPrevisão de renovações: Não\nIdentificador do Lote: LOT-0007\nPrazo de execução do contrato: 3 ANOS\nPrevisão de renovações: Não\n\n11 - FUNDOS EU\nIdentificador do Lote: LOT-0001; LOT-0002; LOT-0003; LOT-0004; LOT-0005; LOT-0006; LOT-0007\nTêm fundos EU? Não\n\n12 - DOCUMENTOS DE HABILITAÇÃO\nHabilitação para o exercício da atividade profissional: Não\n\n13 - CONDIÇÕES DE APRESENTAÇÃO\nPlataforma eletrónica utilizada pela entidade adjudicante: ANOGOV\nURL para Apresentação: https://www.anogov.com/op-nav/faces/\nAdmissibilidade da apresentação de propostas variantes: Não autorizado\nPrazo para apresentação das propostas: 20-11-2025 23:00\nPrazo durante o qual os concorrentes são obrigados a manter as respetivas propostas: 90 dias a contar do termo do prazo para a apresentação das propostas\nApresentação de Catálogo Eletrónico: Permitido\nIndicação de Subcontratação na Proposta: Inexistência de indicação de subcontratação\n\n14 - PRESTAÇÃO DE CAUÇÃO\nPrestação de caução: Não\n\n15 - FORNECIMENTO DAS PEÇAS DO CONCURSO, APRESENTAÇÃO DE PEDIDOS DE PARTICIPAÇÃO E APRESENTAÇÃO DAS PROPOSTAS\nLink para acesso às peças do concurso (URL): https://www.anogov.com/op-nav/faces/app/acessoDocs.jsp?codigoAcesso=3KKTjtg1OOIJWD5vIeP5ycC70TSgfrjntC1WSFe6Eco5sEoSG2\n\n20 - OUTROS REQUISITOS\nIdentificador do Lote: LOT-0001; LOT-0002; LOT-0003; LOT-0004; LOT-0005; LOT-0006; LOT-0007\nInformação sobre contratos reservados. Aplica-se a contratos reservados (54º-A)? Não\n\n21 - CRITÉRIO DE ADJUDICAÇÃO\nO Critério de adjudicação é diferenciado por lote? Não\nMultifator: Não\nMonofator:\nNome: Preço\n\n24 - CONDIÇÕES DO CONTRATO\nIdentificador do Lote: LOT-0001; LOT-0002; LOT-0003; LOT-0004; LOT-0005; LOT-0006; LOT-0007\nFaturação Eletrónica: Permitido\nObrigação de Subcontratação:\nCódigo da Obrigação de Subcontratação: Não é aplicável nenhuma obrigação de subcontratação.\n\n25 - COMPRA PÚBLICA ESTRATÉGICA\nCompra Pública Estratégica: Inexistência de contratação pública estratégica\n\n26 - INFORMAÇÕES ADICIONAIS\nIdentificador do Lote: LOT-0001\nContrato adequado para PME: Não\nCobertura ACP (Acordo dos Contratos Públicos da Organização Mundial do Comércio): Não\nIdentificador do Lote: LOT-0002\nContrato adequado para PME: Não\nCobertura ACP (Acordo dos Contratos Públicos da Organização Mundial do Comércio): Não\nIdentificador do Lote: LOT-0003\nContrato adequado para PME: Não\nCobertura ACP (Acordo dos Contratos Públicos da Organização Mundial do Comércio): Não\nIdentificador do Lote: LOT-0004\nContrato adequado para PME: Não\nCobertura ACP (Acordo dos Contratos Públicos da Organização Mundial do Comércio): Não\nIdentificador do Lote: LOT-0005\nContrato adequado para PME: Não\nCobertura ACP (Acordo dos Contratos Públicos da Organização Mundial do Comércio): Não\nIdentificador do Lote: LOT-0006\nContrato adequado para PME: Não\nCobertura ACP (Acordo dos Contratos Públicos da Organização Mundial do Comércio): Não\nIdentificador do Lote: LOT-0007\nContrato adequado para PME: Não\nCobertura ACP (Acordo dos Contratos Públicos da Organização Mundial do Comércio): Não\n\n27 - IDENTIFICAÇÃO E CONTACTOS DO ÓRGÃO DE RECURSOS ADMINISTRATIVOS\nDesignação: NAV Portugal E.P.E\nEndereço: Edíficio 121, Rua D, Aeroporto de Lisboa\nCódigo postal: 1700-008\nLocalidade: Lisboa\nEndereço eletrónico: geral@nav.pt\n\n28 - IDENTIFICAÇÃO DO(S) AUTOR(ES) DE ANÚNCIO\nNome: Pedro Ângelo\nCargo: Presidente do Conselho de Administração\n419684608",
    "nipc": "504448064",
    "distrito": "Lisboa",
    "concelho": "Todos",
    "freguesia": "Todas",
    "site": "www.nav.pt",
    "email": "compras@nav.pt",
    "designacao_contrato": "Pº 460/25 - AQUISIÇÃO DE SERVIÇOS DE LIMPEZA E FORNECIMENTO DE PRODUTOS DE HIGIENE E LIMPEZA PARA AS INSTALAÇÕES DA NAV PORTUGAL, E.P.E., SITAS EM LISBOA, CASCAIS, PORTO, FARO, PONTA DELGADA, HORTA, FLORES, SANTA MARIA, MADEIRA E PORTO SANTO",
    "descricao": "Pº 460/25 - AQUISIÇÃO DE SERVIÇOS DE LIMPEZA E FORNECIMENTO DE PRODUTOS DE HIGIENE E LIMPEZA PARA AS INSTALAÇÕES DA NAV PORTUGAL, E.P.E., SITAS EM LISBOA, CASCAIS, PORTO, FARO, PONTA DELGADA, HORTA, FLORES, SANTA MARIA, MADEIRA E PORTO SANTO",
    "preco_base": "2.469.600,00 EUR",
    "prazo_execucao": "3 ANOS",
    "prazo_apresentacao_propostas": "20-11-2025 23:00",
    "fundos_eu": "Não",
    "plataforma_eletronica": "ANOGOV",
    "url_procedimento": "https://www.anogov.com/op-nav/faces/",
    "autor_nome": "Pedro Ângelo",
    "autor_cargo": "Presidente do Conselho de Administração"
  },
  {
    "numero_procedimento": "N/A",
    "entidade": "Infraestruturas de Portugal, S. A.",
    "link": "https://diariodarepublica.pt/dr/detalhe/contrato-publico/27702-941568088",
    "detalhes_completos": "1 - IDENTIFICAÇÃO E CONTACTOS DA ENTIDADE ADJUDICANTE\nDesignação da entidade adjudicante: Infraestruturas de Portugal, S. A.\nNIPC: 503933813\nServiço/Órgão/Pessoa de contacto: Direção de Compras e Logística - Departamento de Compras - Edifício 2\nEndereço: Praça da Portagem\nCódigo postal: 2809-013\nLocalidade: Almada\nPaís: Portugal\nNUT III: PT170\nDistrito: Setúbal\nConcelho: Almada\nFreguesia: União das Freguesias de Almada, Cova da Piedade, Pragal e Cacilhas\nTelefone:  212 879 300 \nFax: 21 287 90 00\nEndereço da Entidade (URL): www.infraestruturasdeportugal.pt\nEndereço Eletrónico: dcl@infraestruturasdeportugal.pt\nFunção da Organização: Adquirente\nNorma jurídica da Entidade Adjudicante: Organismo de direito público\nÁrea de atividade da Entidade Adjudicante: Serviços ferroviários\n\n2 - JORNAL OFICIAL DA UNIÃO EUROPEIA\nO procedimento a que este anúncio diz respeito também é publicitado no Jornal Oficial da União Europeia? Não\n\n3 - AVISO\nModelo de Anúncio: Concurso público\nData de Envio do Anúncio: 21-10-2025\n\n5 - PROCESSO\nTipo de Procedimento: Concurso público\nPreço base do procedimento: Sim\nValor do preço base do procedimento: 184.160,00 EUR\nProcedimento com lotes? Sim\nNº Máx. de Lotes Autorizado: 2\nNúmero máximo de lotes que podem ser adjudicados a um concorrente: 2\n\n6 - OBJETO DO CONTRATO\nNúmero de referência interna: 10021458\nDesignação do contrato: Aquisição de serviços de entidade habilitada a efetuar o controlo do álcool e outras substâncias psicoativas em meio laboral nas zonas geográficas Centro (lote 1) e Sul (lote 2)\nDescrição: Aquisição de serviços de entidade habilitada a efetuar o controlo do álcool e outras substâncias psicoativas em meio laboral nas zonas geográficas Cen\nTipo de Contrato Principal: Aquisição de Serviços\nTipo de Contrato: Aquisição de Serviços\nClassificação CPV (Vocabulário Comum para os Contratos Públicos)\nObjeto principal\nVocabulário Principal: 71317200\nPreço base s/IVA: 184.160,00 EUR\nLotes: \nNº: LOT-0001\nDescrição do Lote: Aquisição de serviços de entidade habilitada a efetuar o controlo do álcool e outras substâncias psicoativas em meio laboral na zona geográfica Centro (lote 1)\nPreço base s/IVA: 116.000,00 EUR\nClassificação CPV (Vocabulário Comum para os Contratos Públicos)\nObjeto principal\nVocabulário Principal: 71317200\nNº: LOT-0002\nDescrição do Lote: Aquisição de serviços de entidade habilitada a efetuar o controlo do álcool e outras substâncias psicoativas em meio laboral na zona geográfica Sul (lote 2)\nPreço base s/IVA: 68.160,00 EUR\nClassificação CPV (Vocabulário Comum para os Contratos Públicos)\nObjeto principal\nVocabulário Principal: 71317200\n\n7 - INDICAÇÕES ADICIONAIS\nO contrato envolve aquisição conjunta (satisfação de várias entidades)? Não\nO contrato é adjudicado por uma central de compras? Não\n\n8 - TÉCNICAS\nO concurso destina-se à celebração de um acordo-quadro? Inexistência de acordo-quadro\nÉ utilizado um leilão eletrónico? Não\nÉ adotada uma fase de negociação? Não\nSistema de Aquisição Dinâmico: Inexistência de sistema de aquisição dinâmico\n\n9 - LOCAL DA EXECUÇÃO DO CONTRATO\nLOCAL DA EXECUÇÃO DO CONTRATO (PROCEDIMENTO)\nLOCAL DA EXECUÇÃO DO CONTRATO (LOTE)\nIdentificador do Lote: LOT-0001\nPaís: Portugal\nNUT III: PTZZZ\nLocalidade: Todas\nDistrito: Todos\nConcelho: Todos\nFreguesia: Todas\nIdentificador do Lote: LOT-0002\nPaís: Portugal\nNUT III: PTZZZ\nLocalidade: Todas\nDistrito: Todos\nConcelho: Todos\nFreguesia: Todas\n\n10 - PRAZO DE EXECUÇÃO DO CONTRATO\nIdentificador do Lote: LOT-0001\nPrazo de execução do contrato: 36 MESES\nPrevisão de renovações: Não\nIdentificador do Lote: LOT-0002\nPrazo de execução do contrato: 36 MESES\nPrevisão de renovações: Não\n\n11 - FUNDOS EU\nIdentificador do Lote: LOT-0001; LOT-0002\nTêm fundos EU? Não\n\n12 - DOCUMENTOS DE HABILITAÇÃO\nHabilitação para o exercício da atividade profissional: Não\n\n13 - CONDIÇÕES DE APRESENTAÇÃO\nPlataforma eletrónica utilizada pela entidade adjudicante: ANOGOV\nURL para Apresentação: https://www.anogov.com/infraestruturasdeportugal-ip/faces/\nAdmissibilidade da apresentação de propostas variantes: Não autorizado\nPrazo para apresentação das propostas: 05-11-2025 17:00\nPrazo durante o qual os concorrentes são obrigados a manter as respetivas propostas: 120 dias a contar do termo do prazo para a apresentação das propostas\nApresentação de Catálogo Eletrónico: Não autorizado\nIndicação de Subcontratação na Proposta: Inexistência de indicação de subcontratação\n\n14 - PRESTAÇÃO DE CAUÇÃO\nPrestação de caução: Não\n\n15 - FORNECIMENTO DAS PEÇAS DO CONCURSO, APRESENTAÇÃO DE PEDIDOS DE PARTICIPAÇÃO E APRESENTAÇÃO DAS PROPOSTAS\nLink para acesso às peças do concurso (URL): https://www.anogov.com/infraestruturasdeportugal-ip/faces/app/acessoDocs.jsp?codigoAcesso=yohjQMjboddd6yvQ4NVZOKB8O3FhXXH1lMx98K6Xsr7JvzWR7i\n\n20 - OUTROS REQUISITOS\nIdentificador do Lote: LOT-0001; LOT-0002\nInformação sobre contratos reservados. Aplica-se a contratos reservados (54º-A)? Não\n\n21 - CRITÉRIO DE ADJUDICAÇÃO\nO Critério de adjudicação é diferenciado por lote? Não\nMultifator: Não\nMonofator:\nNome: Preço\n\n24 - CONDIÇÕES DO CONTRATO\nIdentificador do Lote: LOT-0001; LOT-0002\nFaturação Eletrónica: Permitido\nObrigação de Subcontratação:\nCódigo da Obrigação de Subcontratação: Não é aplicável nenhuma obrigação de subcontratação.\n\n25 - COMPRA PÚBLICA ESTRATÉGICA\nCompra Pública Estratégica: Inexistência de contratação pública estratégica\n\n26 - INFORMAÇÕES ADICIONAIS\nIdentificador do Lote: LOT-0001\nContrato adequado para PME: Sim\nCobertura ACP (Acordo dos Contratos Públicos da Organização Mundial do Comércio): Não\nIdentificador do Lote: LOT-0002\nContrato adequado para PME: Sim\nCobertura ACP (Acordo dos Contratos Públicos da Organização Mundial do Comércio): Não\n\n27 - IDENTIFICAÇÃO E CONTACTOS DO ÓRGÃO DE RECURSOS ADMINISTRATIVOS\nDesignação: Conselho de Administração da Infraestruturas de Portugal, S.A.\nEndereço: Praça da Portagem\nCódigo postal: 2809-013\nLocalidade: Almada\nEndereço eletrónico: contratos@infraestruturasdeportugal.pt\n\n28 - IDENTIFICAÇÃO DO(S) AUTOR(ES) DE ANÚNCIO\nNome: Margarida Veloso\nCargo: Diretora Adjunta de Compras e Logística (em acumulação Dir. Departamento de Compras)\n419682542",
    "nipc": "503933813",
    "distrito": "Setúbal",
    "concelho": "Almada",
    "freguesia": "União das Freguesias de Almada, Cova da Piedade, Pragal e Cacilhas",
    "site": "www.infraestruturasdeportugal.pt",
    "email": "dcl@infraestruturasdeportugal.pt",
    "designacao_contrato": "Aquisição de serviços de entidade habilitada a efetuar o controlo do álcool e outras substâncias psicoativas em meio laboral nas zonas geográficas Centro (lote 1) e Sul (lote 2)",
    "descricao": "Aquisição de serviços de entidade habilitada a efetuar o controlo do álcool e outras substâncias psicoativas em meio laboral nas zonas geográficas Cen",
    "preco_base": "184.160,00 EUR",
    "prazo_execucao": "36 MESES",
    "prazo_apresentacao_propostas": "05-11-2025 17:00",
    "fundos_eu": "Não",
    "plataforma_eletronica": "ANOGOV",
    "url_procedimento": "https://www.anogov.com/infraestruturasdeportugal-ip/faces/",
    "autor_nome": "Margarida Veloso",
    "autor_cargo": "Diretora Adjunta de Compras e Logística (em acumulação Dir. Departamento de Compras)"
  },
  {
    "numero_procedimento": "N/A",
    "entidade": "Teatro Nacional D. Maria II, E. P. E.",
    "link": "https://diariodarepublica.pt/dr/detalhe/contrato-publico/27703-941568089",
    "detalhes_completos": "Alteração do Anúncio de procedimento n.º 27407/2025, de 2025-10-17, com o ID 419668765\n\n1 - IDENTIFICAÇÃO E CONTACTOS DA ENTIDADE ADJUDICANTE\nDesignação da entidade adjudicante: Teatro Nacional D. Maria II, E. P. E.\nNIPC: 501058834\nServiço/Órgão/Pessoa de contacto: Contratação Pública / Rute Presado\nEndereço: Praça Dom Pedro IV\nCódigo postal: 1100-201\nLocalidade: LISBOA\nPaís: Portugal\nNUT III: PT170\nDistrito: Lisboa\nConcelho: Lisboa\nFreguesia: Freguesia de Santa Maria Maior - Lisboa\nTelefone: 213250800\nFax: 213250866\nEndereço da Entidade (URL): www.tndm.pt\nEndereço Eletrónico: geral@tndm.pt\neDelivery Gateway (URL): https://www.acingov.pt\nFunção da Organização: Adquirente\nNorma jurídica da Entidade Adjudicante: Empresa pública, controlada por uma autoridade da administração central\nÁrea de atividade da Autoridade Adjudicante: Atividades recreativas, culturais e religiosas\n\n2 - JORNAL OFICIAL DA UNIÃO EUROPEIA\nO procedimento a que este anúncio diz respeito também é publicitado no Jornal Oficial da União Europeia? Não\n\n3 - AVISO\nModelo de Anúncio: Concurso público\nData de Envio do Anúncio: 21-10-2025\n\n5 - PROCESSO\nTipo de Procedimento: Concurso público\nPreço base do procedimento: Sim\nValor do preço base do procedimento: 1.600.000,00 EUR\nProcedimento com lotes? Não\n\n6 - OBJETO DO CONTRATO\nNúmero de referência interna: CP 37/2025\nDesignação do contrato: Empreitada conceção-construção para a remodelação do sistema de palco rotativo e quadro da mecânica de cena do Teatro Nacional D. Maria II\nDescrição: Empreitada conceção-construção para a remodelação do sistema de palco rotativo e quadro da mecânica de cena do Teatro Nacional D. Maria II\nTipo de Contrato Principal: Empreitada de Obras Públicas\nTipo de Contrato: Empreitada de Obras Públicas\nClassificação CPV (Vocabulário Comum para os Contratos Públicos)\nObjeto principal\nVocabulário Principal: 45454000\nPreço base s/IVA: 1.600.000,00 EUR\n\n7 - INDICAÇÕES ADICIONAIS\nO contrato envolve aquisição conjunta (satisfação de várias entidades)? Não\nO contrato é adjudicado por uma central de compras? Não\n\n8 - TÉCNICAS\nO concurso destina-se à celebração de um acordo-quadro? Inexistência de acordo-quadro\nÉ utilizado um leilão eletrónico? Não\nÉ adotada uma fase de negociação? Não\nSistema de Aquisição Dinâmico: Inexistência de sistema de aquisição dinâmico\n\n9 - LOCAL DA EXECUÇÃO DO CONTRATO\nLOCAL DA EXECUÇÃO DO CONTRATO (PROCEDIMENTO)\nPaís: Portugal\nNUT III: PT170\nLocalidade: Freguesia de Santa Maria Maior - Lisboa\nDistrito: Lisboa\nConcelho: Lisboa\nFreguesia: Freguesia de Santa Maria Maior - Lisboa\n\n10 - PRAZO DE EXECUÇÃO DO CONTRATO\nPrazo de execução do contrato: 175 DIAS\nPrevisão de renovações: Não\n\n11 - FUNDOS EU\nTêm fundos EU? Sim\n\n12 - DOCUMENTOS DE HABILITAÇÃO\nHabilitação para o exercício da atividade profissional: Sim\nTipo: Alvará\nDescrição: Pelo menos a 10.ª subcategoria (Restauro dos bens imóveis histórico-artísticos) da 1.ª categoria (Edifícios e património construído), a qual tem de ser de classe que cubra o valor global da proposta e outras autorizações de acordo com a obra em questão\n\n13 - CONDIÇÕES DE APRESENTAÇÃO\nPlataforma eletrónica utilizada pela entidade adjudicante: ACIN\nURL para Apresentação: https://www.acingov.pt\nAdmissibilidade da apresentação de propostas variantes: Não autorizado\nPrazo para apresentação das propostas: 05-11-2025 23:59\nPrazo durante o qual os concorrentes são obrigados a manter as respetivas propostas: 66 dias a contar do termo do prazo para a apresentação das propostas\nIndicação de Subcontratação na Proposta: Inexistência de indicação de subcontratação\n\n14 - PRESTAÇÃO DE CAUÇÃO\nPrestação de caução: Sim\nPercentagem: 5%\nDescrição da Garantia Exigida: O valor da caução é de 5.00% do preço contratual.\n\n15 - FORNECIMENTO DAS PEÇAS DO CONCURSO, APRESENTAÇÃO DE PEDIDOS DE PARTICIPAÇÃO E APRESENTAÇÃO DAS PROPOSTAS\nLink para acesso às peças do concurso (URL): https://www.acingov.pt/acingovprod/2/zonaPublica/zona_publica_c/donwloadProcedurePiece/OTg4MTY0\n\n20 - OUTROS REQUISITOS\nInformação sobre contratos reservados. Aplica-se a contratos reservados (54º-A)? Não\n\n21 - CRITÉRIO DE ADJUDICAÇÃO\nMultifator: Sim\nFator: \nNome: Outros\nOutro Nome: Multifator\nPonderação: 100%\nSubfatores: Não\n\n24 - CONDIÇÕES DO CONTRATO\nFaturação Eletrónica: Permitido\nObrigação de Subcontratação:\nCódigo da Obrigação de Subcontratação: Não é aplicável nenhuma obrigação de subcontratação.\n\n25 - COMPRA PÚBLICA ESTRATÉGICA\nCompra Pública Estratégica: Inexistência de contratação pública estratégica\n\n26 - INFORMAÇÕES ADICIONAIS\nContrato adequado para PME: Não\nCobertura ACP (Acordo dos Contratos Públicos da Organização Mundial do Comércio): Não\n\n27 - IDENTIFICAÇÃO E CONTACTOS DO ÓRGÃO DE RECURSOS ADMINISTRATIVOS\nDesignação: Conselho de Administração TNDM II\nEndereço: Praça Dom Pedro IV\nCódigo postal: 1100-201\nLocalidade: LISBOA\nTelefone: 213250800\nFax: \nEndereço eletrónico: geral@tndm.pt\nPrazo de interposição do recurso: 5 dias\n\n28 - IDENTIFICAÇÃO DO(S) AUTOR(ES) DE ANÚNCIO\nNome: Rute Presado\nCargo: Coordenação Contratação Pública\n\n29 - ALTERAÇÃO\nMotivo da Alteração: Correção pelo adquirente\nIdentificador da Versão do Anúncio a Alterar: 7210dd14-4226-4ca6-9e68-57437eb7f888-01\nIdentificador das Secções Alteradas do Anúncio Anterior: Documentos de habilitação; Condições de Apresentação\nDescrição das Alterações: Modificação do prazo para a apresentação de propostas, uma vez que o Programa do Procedimento foi retificado no artigo 24.º - documentos de habilitação por deliberação de CA de 21/10/2025\nAlteração dos Documentos do Concurso: Sim\nData de alteração dos documentos do concurso: 21-10-2025\n419683814",
    "nipc": "501058834",
    "distrito": "Lisboa",
    "concelho": "Lisboa",
    "freguesia": "Freguesia de Santa Maria Maior - Lisboa",
    "site": "www.tndm.pt",
    "email": "geral@tndm.pt",
    "designacao_contrato": "Empreitada conceção-construção para a remodelação do sistema de palco rotativo e quadro da mecânica de cena do Teatro Nacional D. Maria II",
    "descricao": "Empreitada conceção-construção para a remodelação do sistema de palco rotativo e quadro da mecânica de cena do Teatro Nacional D. Maria II",
    "preco_base": "1.600.000,00 EUR",
    "prazo_execucao": "175 DIAS",
    "prazo_apresentacao_propostas": "05-11-2025 23:59",
    "fundos_eu": "Sim",
    "plataforma_eletronica": "ACIN",
    "url_procedimento": "https://www.acingov.pt",
    "autor_nome": "Rute Presado",
    "autor_cargo": "Coordenação Contratação Pública"
  },
  {
    "numero_procedimento": "N/A",
    "entidade": "Município de Paços de Ferreira",
    "link": "https://diariodarepublica.pt/dr/detalhe/contrato-publico/27705-941568090",
    "detalhes_completos": "1 - IDENTIFICAÇÃO E CONTACTOS DA ENTIDADE ADJUDICANTE\nDesignação da entidade adjudicante: Município de Paços de Ferreira\nNIPC: 502173297\nServiço/Órgão/Pessoa de contacto: Departamento de Organização Administrativa\nEndereço: Praça da República, n.º 46\nCódigo postal: 4590-527\nLocalidade: Paços de Ferreira\nPaís: Portugal\nNUT III: PTZZZ\nDistrito: Todos\nConcelho: Todos\nFreguesia: Todas\nTelefone: 255860700\nFax: 255860734\nEndereço da Entidade (URL): http://www.cm-pacosdeferreira.pt\nEndereço Eletrónico: geral@cm-pacosdeferreira.pt\neDelivery Gateway (URL): https://www.acingov.pt\nFunção da Organização: Adquirente\nNorma jurídica da Entidade Adjudicante: Organismo de direito público\nÁrea de atividade da Autoridade Adjudicante: Serviços públicos das administrações públicas\n\n2 - JORNAL OFICIAL DA UNIÃO EUROPEIA\nO procedimento a que este anúncio diz respeito também é publicitado no Jornal Oficial da União Europeia? Não\n\n3 - AVISO\nModelo de Anúncio: Concurso público\nData de Envio do Anúncio: 21-10-2025\n\n5 - PROCESSO\nTipo de Procedimento: Concurso público\nPreço base do procedimento: Sim\nValor do preço base do procedimento: 112.980,00 EUR\nProcedimento com lotes? Não\n\n6 - OBJETO DO CONTRATO\nNúmero de referência interna: 165/F/2025\nDesignação do contrato: Aquisição de serviços de elaboração de projeto de arquitetura e especialidades com vista a candidatura ao aviso OP5_Norte2030-46 - Casa das Artes de Freamunde\nDescrição: Aquisição de serviços de elaboração de projeto de arquitetura e especialidades com vista a candidatura ao aviso OP5_Norte2030-46 - Casa das Artes de Freamunde\nTipo de Contrato Principal: Aquisição de Serviços\nTipo de Contrato: Aquisição de Serviços\nClassificação CPV (Vocabulário Comum para os Contratos Públicos)\nObjeto principal\nVocabulário Principal: 71242000\nPreço base s/IVA: 112.980,00 EUR\n\n7 - INDICAÇÕES ADICIONAIS\nO contrato envolve aquisição conjunta (satisfação de várias entidades)? Não\nO contrato é adjudicado por uma central de compras? Não\n\n8 - TÉCNICAS\nO concurso destina-se à celebração de um acordo-quadro? Inexistência de acordo-quadro\nÉ utilizado um leilão eletrónico? Não\nÉ adotada uma fase de negociação? Não\nSistema de Aquisição Dinâmico: Inexistência de sistema de aquisição dinâmico\n\n9 - LOCAL DA EXECUÇÃO DO CONTRATO\nLOCAL DA EXECUÇÃO DO CONTRATO (PROCEDIMENTO)\nPaís: Portugal\nNUT III: PT11C\nLocalidade: Freguesia de Paços de Ferreira\nDistrito: Porto\nConcelho: Paços de Ferreira\nFreguesia: Freguesia de Paços de Ferreira\n\n10 - PRAZO DE EXECUÇÃO DO CONTRATO\nPrazo de execução do contrato: 3 MESES\nPrevisão de renovações: Não\n\n11 - FUNDOS EU\nTêm fundos EU? Não\n\n12 - DOCUMENTOS DE HABILITAÇÃO\nHabilitação para o exercício da atividade profissional: Não\n\n13 - CONDIÇÕES DE APRESENTAÇÃO\nPlataforma eletrónica utilizada pela entidade adjudicante: ACIN\nURL para Apresentação: https://www.acingov.pt\nAdmissibilidade da apresentação de propostas variantes: Não autorizado\nPrazo para apresentação das propostas: 29-10-2025 23:59\nPrazo durante o qual os concorrentes são obrigados a manter as respetivas propostas: 66 dias a contar do termo do prazo para a apresentação das propostas\nIndicação de Subcontratação na Proposta: Inexistência de indicação de subcontratação\n\n14 - PRESTAÇÃO DE CAUÇÃO\nPrestação de caução: Não\n\n15 - FORNECIMENTO DAS PEÇAS DO CONCURSO, APRESENTAÇÃO DE PEDIDOS DE PARTICIPAÇÃO E APRESENTAÇÃO DAS PROPOSTAS\nLink para acesso às peças do concurso (URL): https://www.acingov.pt/acingovprod/2/zonaPublica/zona_publica_c/donwloadProcedurePiece/OTg4MjAy\n\n20 - OUTROS REQUISITOS\nInformação sobre contratos reservados. Aplica-se a contratos reservados (54º-A)? Não\n\n21 - CRITÉRIO DE ADJUDICAÇÃO\nMultifator: Sim\nFator: \nNome: Preço\nPonderação: 30%\nSubfatores: Não\nFator: \nNome: Outros\nOutro Nome: Qualidade e Experiência Específica da Equipa Técnica (QEEET)\nPonderação: 70%\nSubfatores: Sim\nSubfatores: \nNome: SC1.1: Experiência do Coordenador de Projeto Comprovação da experiência (número e relevância) em coordenação de projetos de execução multidisciplinares, a comprovar por declaração abonatória.\nPonderação : 30%; \nNome: SC1.2: Experiência dos Projetistas de Arquitetura Experiência comprovada (número e relevância) do responsável técnico de arquitetura em projetos de execução de edifícios de raiz ou reabilitação, culturais similares, a comprovar por declaração abonatória.\nPonderação : 20%; \nNome: SC1.3: Experiência dos Projetistas das Especialistas Qualificações académicas e profissionais dos restantes projetistas de especialidades consideradas mais relevantes atendendo às características do projeto\nPonderação : 50%; \n\n24 - CONDIÇÕES DO CONTRATO\nFaturação Eletrónica: Permitido\nObrigação de Subcontratação:\nCódigo da Obrigação de Subcontratação: Não é aplicável nenhuma obrigação de subcontratação.\n\n25 - COMPRA PÚBLICA ESTRATÉGICA\nCompra Pública Estratégica: Inexistência de contratação pública estratégica\n\n26 - INFORMAÇÕES ADICIONAIS\nContrato adequado para PME: Sim\nCobertura ACP (Acordo dos Contratos Públicos da Organização Mundial do Comércio): Não\n\n27 - IDENTIFICAÇÃO E CONTACTOS DO ÓRGÃO DE RECURSOS ADMINISTRATIVOS\nDesignação: Departamento de Organização Administrativa\nEndereço: Praça da República, n.º 46\nCódigo postal: 4590-527\nLocalidade: Paços de Ferreira\nTelefone: 255860700\nFax: \nEndereço eletrónico: geral@cm-pacosdeferreira.pt\n\n28 - IDENTIFICAÇÃO DO(S) AUTOR(ES) DE ANÚNCIO\nNome: Paulo Jorge Rodrigues Ferreira\nCargo: Presidente da Câmara Municipal\n419665038",
    "nipc": "502173297",
    "distrito": "Todos",
    "concelho": "Todos",
    "freguesia": "Todas",
    "site": "http://www.cm-pacosdeferreira.pt",
    "email": "geral@cm-pacosdeferreira.pt",
    "designacao_contrato": "Aquisição de serviços de elaboração de projeto de arquitetura e especialidades com vista a candidatura ao aviso OP5_Norte2030-46 - Casa das Artes de Freamunde",
    "descricao": "Aquisição de serviços de elaboração de projeto de arquitetura e especialidades com vista a candidatura ao aviso OP5_Norte2030-46 - Casa das Artes de Freamunde",
    "preco_base": "112.980,00 EUR",
    "prazo_execucao": "3 MESES",
    "prazo_apresentacao_propostas": "29-10-2025 23:59",
    "fundos_eu": "Não",
    "plataforma_eletronica": "ACIN",
    "url_procedimento": "https://www.acingov.pt",
    "autor_nome": "Paulo Jorge Rodrigues Ferreira",
    "autor_cargo": "Presidente da Câmara Municipal"
  },
  {
    "numero_procedimento": "N/A",
    "entidade": "Unidade Local de Saúde de Viseu Dão-Lafões, E. P. E.",
    "link": "https://diariodarepublica.pt/dr/detalhe/contrato-publico/27707-941568091",
    "detalhes_completos": "1 - IDENTIFICAÇÃO E CONTACTOS DA ENTIDADE ADJUDICANTE\nDesignação da entidade adjudicante: Unidade Local de Saúde de Viseu Dão-Lafões, E. P. E.\nNIPC: 509822940\nEndereço: Av. Rei D. Duarte\nCódigo postal: 3504-509\nLocalidade: Viseu\nPaís: Portugal\nNUT III: PT16G\nDistrito: Viseu\nConcelho: Viseu\nFreguesia: Todas\nTelefone: 232420589\nFax: 232421217\nEndereço da Entidade (URL): http://www.hstviseu.min-saude.pt/\nEndereço Eletrónico: aprovisionamento.diretor@hstviseu.min-saude.pt\neDelivery Gateway (URL): https://community.vortal.biz/public/\nFunção da Organização: Adquirente\nNorma jurídica da Entidade Adjudicante: Empresa pública\nÁrea de atividade da Autoridade Adjudicante: Saúde\n\n2 - JORNAL OFICIAL DA UNIÃO EUROPEIA\nO procedimento a que este anúncio diz respeito também é publicitado no Jornal Oficial da União Europeia? Não\n\n3 - AVISO\nModelo de Anúncio: Concurso público\nData de Envio do Anúncio: 21-10-2025\n\n5 - PROCESSO\nTipo de Procedimento: Concurso público\nPreço base do procedimento: Sim\nValor do preço base do procedimento: 138.500,00 EUR\nProcedimento com lotes? Sim\nNº Máx. de Lotes Autorizado: 2\nNúmero máximo de lotes que podem ser adjudicados a um concorrente: 2\n\n6 - OBJETO DO CONTRATO\nNúmero de referência interna: 28/08798/2025\nDesignação do contrato: Equipamentos Imagiologia (Raio X Digital + Densitometria Óssea)\nDescrição: Equipamentos Imagiologia (Raio X Digital + Densitometria Óssea)\nTipo de Contrato Principal: Aquisição de Bens Móveis\nTipo de Contrato: Aquisição de Bens Móveis\nClassificação CPV (Vocabulário Comum para os Contratos Públicos)\nObjeto principal\nVocabulário Principal: 33110000\nPreço base s/IVA: 138.500,00 EUR\nLotes: \nNº: LOT-0001\nDescrição do Lote: RAIO X DIGITAL\nPreço base s/IVA: 92.500,00 EUR\nClassificação CPV (Vocabulário Comum para os Contratos Públicos)\nObjeto principal\nVocabulário Principal: 33110000\nNº: LOT-0002\nDescrição do Lote: DENSITOMETRIA ÓSSEA\nPreço base s/IVA: 46.000,00 EUR\nClassificação CPV (Vocabulário Comum para os Contratos Públicos)\nObjeto principal\nVocabulário Principal: 33110000\n\n7 - INDICAÇÕES ADICIONAIS\nO contrato envolve aquisição conjunta (satisfação de várias entidades)? Não\nO contrato é adjudicado por uma central de compras? Não\n\n8 - TÉCNICAS\nO concurso destina-se à celebração de um acordo-quadro? Inexistência de acordo-quadro\nÉ utilizado um leilão eletrónico? Não\nÉ adotada uma fase de negociação? Não\nSistema de Aquisição Dinâmico: Inexistência de sistema de aquisição dinâmico\n\n9 - LOCAL DA EXECUÇÃO DO CONTRATO\nLOCAL DA EXECUÇÃO DO CONTRATO (PROCEDIMENTO)\nPaís: Portugal\nNUT III: PT16G\nLocalidade: Viseu\nDistrito: Viseu\nConcelho: Viseu\nFreguesia: Freguesia de Viseu\nLOCAL DA EXECUÇÃO DO CONTRATO (LOTE)\nIdentificador do Lote: LOT-0001; LOT-0002\nPaís: Portugal\nNUT III: PT16G\nLocalidade: Viseu\nDistrito: Viseu\nConcelho: Viseu\nFreguesia: Freguesia de Viseu\n\n10 - PRAZO DE EXECUÇÃO DO CONTRATO\nIdentificador do Lote: LOT-0001; LOT-0002\nPrazo de execução do contrato: 30 DIAS\nPrevisão de renovações: Não\n\n11 - FUNDOS EU\nIdentificador do Lote: LOT-0001; LOT-0002\nTêm fundos EU? Não\n\n12 - DOCUMENTOS DE HABILITAÇÃO\nHabilitação para o exercício da atividade profissional: Não\n\n13 - CONDIÇÕES DE APRESENTAÇÃO\nPlataforma eletrónica utilizada pela entidade adjudicante: VORTAL\nURL para Apresentação: https://community.vortal.biz/public/\nAdmissibilidade da apresentação de propostas variantes: Não autorizado\nPrazo para apresentação das propostas: 05-11-2025 18:00\nPrazo durante o qual os concorrentes são obrigados a manter as respetivas propostas: 120 dias a contar do termo do prazo para a apresentação das propostas\nIndicação de Subcontratação na Proposta: Inexistência de indicação de subcontratação\n\n14 - PRESTAÇÃO DE CAUÇÃO\nPrestação de caução: Não\n\n15 - FORNECIMENTO DAS PEÇAS DO CONCURSO, APRESENTAÇÃO DE PEDIDOS DE PARTICIPAÇÃO E APRESENTAÇÃO DAS PROPOSTAS\nLink para acesso às peças do concurso (URL): https://community.vortal.biz/Public/public-tender-documents/L0RhZTI4SU5UcnhlSUtaR09MR3dDMG5tdHU1NlFyc1JxdDhVWE1OVHZOTEJCeW5CRXhlMmF2aTNJZ0JxMzZvMzZIZEE5ak5aN0FMNHFLcTdCQ29KS3c9PVE5R1NZ\n\n20 - OUTROS REQUISITOS\nIdentificador do Lote: LOT-0001; LOT-0002\nInformação sobre contratos reservados. Aplica-se a contratos reservados (54º-A)? Não\n\n21 - CRITÉRIO DE ADJUDICAÇÃO\nO Critério de adjudicação é diferenciado por lote? Não\nMultifator: Não\nMonofator:\nNome: Preço\n\n24 - CONDIÇÕES DO CONTRATO\nIdentificador do Lote: LOT-0001; LOT-0002\nFaturação Eletrónica: Permitido\nObrigação de Subcontratação:\nCódigo da Obrigação de Subcontratação: Não é aplicável nenhuma obrigação de subcontratação.\n\n25 - COMPRA PÚBLICA ESTRATÉGICA\nCompra Pública Estratégica: Inexistência de contratação pública estratégica\n\n26 - INFORMAÇÕES ADICIONAIS\nIdentificador do Lote: LOT-0001; LOT-0002\nContrato adequado para PME: Sim\nCobertura ACP (Acordo dos Contratos Públicos da Organização Mundial do Comércio): Não\n\n27 - IDENTIFICAÇÃO E CONTACTOS DO ÓRGÃO DE RECURSOS ADMINISTRATIVOS\nDesignação: CONSELHO DE ADMINISTRAÇÃO\nEndereço: Avenida Rei D. Duarte\nCódigo postal: 3504-509\nLocalidade: Viseu\nTelefone: +351 232420500\nFax: +351 232420217\nEndereço eletrónico: sec.presidente@ulsvdl.min-saude.pt\n\n28 - IDENTIFICAÇÃO DO(S) AUTOR(ES) DE ANÚNCIO\nNome: Adriana Nunes\nCargo: Assistente Técnica\n419681773",
    "nipc": "509822940",
    "distrito": "Viseu",
    "concelho": "Viseu",
    "freguesia": "Todas",
    "site": "http://www.hstviseu.min-saude.pt/",
    "email": "aprovisionamento.diretor@hstviseu.min-saude.pt",
    "designacao_contrato": "Equipamentos Imagiologia (Raio X Digital + Densitometria Óssea)",
    "descricao": "Equipamentos Imagiologia (Raio X Digital + Densitometria Óssea)",
    "preco_base": "138.500,00 EUR",
    "prazo_execucao": "30 DIAS",
    "prazo_apresentacao_propostas": "05-11-2025 18:00",
    "fundos_eu": "Não",
    "plataforma_eletronica": "VORTAL",
    "url_procedimento": "https://community.vortal.biz/public/",
    "autor_nome": "Adriana Nunes",
    "autor_cargo": "Assistente Técnica"
  },
  {
    "numero_procedimento": "N/A",
    "entidade": "AMBILITAL - Investimentos Ambientais no Alentejo, E. I. M.",
    "link": "https://diariodarepublica.pt/dr/detalhe/contrato-publico/27709-941568092",
    "detalhes_completos": "1 - IDENTIFICAÇÃO E CONTACTOS DA ENTIDADE ADJUDICANTE\nDesignação da entidade adjudicante: AMBILITAL - Investimentos Ambientais no Alentejo, E. I. M.\nNIPC: 505255391\nEndereço: MONTE NOVO DOS MODERNOS\nCódigo postal: 7565-255\nLocalidade: Setúbal\nPaís: Portugal\nNUT III: PT181\nDistrito: Setúbal\nConcelho: Santiago do Cacém\nFreguesia: Freguesia de Ermidas-Sado\nTelefone: 269508030\nFax: 269502111\nEndereço da Entidade (URL): www.ambilital.pt\nEndereço Eletrónico: geral@ambilital.pt\neDelivery Gateway (URL): https://community.vortal.biz/public/\nFunção da Organização: Adquirente\nNorma jurídica da Entidade Adjudicante: Organismo de direito público\nÁrea de atividade da Autoridade Adjudicante: Serviços públicos das administrações públicas\n\n2 - JORNAL OFICIAL DA UNIÃO EUROPEIA\nO procedimento a que este anúncio diz respeito também é publicitado no Jornal Oficial da União Europeia? Não\n\n3 - AVISO\nModelo de Anúncio: Concurso público\nData de Envio do Anúncio: 21-10-2025\n\n5 - PROCESSO\nTipo de Procedimento: Concurso público\nPreço base do procedimento: Sim\nValor do preço base do procedimento: 177.500,00 EUR\nProcedimento com lotes? Não\n\n6 - OBJETO DO CONTRATO\nNúmero de referência interna: CP/CCP/09/25\nDesignação do contrato: CP/CCP/09/25 - Aquisição de 5 contentores compactadores para resíduos urbanos\nDescrição: CP/CCP/09/25 - Aquisição de 5 contentores compactadores para resíduos urbanos\n\nTipo de Contrato Principal: Aquisição de Bens Móveis\nTipo de Contrato: Aquisição de Bens Móveis\nClassificação CPV (Vocabulário Comum para os Contratos Públicos)\nObjeto principal\nVocabulário Principal: 39713300\nPreço base s/IVA: 177.500,00 EUR\n\n7 - INDICAÇÕES ADICIONAIS\nO contrato envolve aquisição conjunta (satisfação de várias entidades)? Não\nO contrato é adjudicado por uma central de compras? Não\n\n8 - TÉCNICAS\nO concurso destina-se à celebração de um acordo-quadro? Inexistência de acordo-quadro\nÉ utilizado um leilão eletrónico? Não\nÉ adotada uma fase de negociação? Não\nSistema de Aquisição Dinâmico: Inexistência de sistema de aquisição dinâmico\n\n9 - LOCAL DA EXECUÇÃO DO CONTRATO\nLOCAL DA EXECUÇÃO DO CONTRATO (PROCEDIMENTO)\nPaís: Portugal\nNUT III: PT181\nLocalidade: Setúbal\nDistrito: Setúbal\nConcelho: Santiago do Cacém\nFreguesia: Freguesia de Ermidas-Sado\n\n10 - PRAZO DE EXECUÇÃO DO CONTRATO\nPrazo de execução do contrato: 150 DIAS\nPrevisão de renovações: Não\n\n11 - FUNDOS EU\nTêm fundos EU? Não\n\n12 - DOCUMENTOS DE HABILITAÇÃO\nHabilitação para o exercício da atividade profissional: Não\n\n13 - CONDIÇÕES DE APRESENTAÇÃO\nPlataforma eletrónica utilizada pela entidade adjudicante: VORTAL\nURL para Apresentação: https://community.vortal.biz/public/\nAdmissibilidade da apresentação de propostas variantes: Não autorizado\nPrazo para apresentação das propostas: 30-10-2025 16:00\nPrazo durante o qual os concorrentes são obrigados a manter as respetivas propostas: 120 dias a contar do termo do prazo para a apresentação das propostas\nIndicação de Subcontratação na Proposta: Inexistência de indicação de subcontratação\n\n14 - PRESTAÇÃO DE CAUÇÃO\nPrestação de caução: Não\n\n15 - FORNECIMENTO DAS PEÇAS DO CONCURSO, APRESENTAÇÃO DE PEDIDOS DE PARTICIPAÇÃO E APRESENTAÇÃO DAS PROPOSTAS\nLink para acesso às peças do concurso (URL): https://community.vortal.biz/Public/public-tender-documents/RGJwRlJ4RVJWSzlwSm94MzlVWmNCdC9UN2d2T1kwL05nR3g0YlhmOTdqaTR5a3NFVGhsNnVaVTNrbm1MTzQ5N1VFaWlxcDJJUHczM0VNQysxcEZNcVE9PSM4SiR6\n\n20 - OUTROS REQUISITOS\nInformação sobre contratos reservados. Aplica-se a contratos reservados (54º-A)? Não\n\n21 - CRITÉRIO DE ADJUDICAÇÃO\nMultifator: Sim\nFator: \nNome: Preço\nPonderação: 50%\nSubfatores: Não\nFator: \nNome: Qualidade\nPonderação: 20%\nSubfatores: Não\nFator: \nNome: Qualidade\nPonderação: 15%\nSubfatores: Não\nFator: \nNome: Qualidade\nPonderação: 15%\nSubfatores: Não\n\n24 - CONDIÇÕES DO CONTRATO\nFaturação Eletrónica: Permitido\nObrigação de Subcontratação:\nCódigo da Obrigação de Subcontratação: Não é aplicável nenhuma obrigação de subcontratação.\n\n25 - COMPRA PÚBLICA ESTRATÉGICA\nCompra Pública Estratégica: Redução dos impactos ambientais\nDescrição do Processo de Adjudicação Estratégico: Conforme as peças do procedimento\nCritérios de contratos Públicos Ecológicos: Critérios de contratação pública ecológica nacional\nCategorias da estratégia nacional: Outros\nOutra categoria (Descrição): Gestão de residuos\nDiretiva Veículos Não Poluentes: Não\nCritério de Acessibilidade: Os critérios de acessibilidade para as pessoas com deficiência não estão incluídos porque o contrato não se destina a pessoas singulares\n\n26 - INFORMAÇÕES ADICIONAIS\nContrato adequado para PME: Sim\nCobertura ACP (Acordo dos Contratos Públicos da Organização Mundial do Comércio): Não\n\n27 - IDENTIFICAÇÃO E CONTACTOS DO ÓRGÃO DE RECURSOS ADMINISTRATIVOS\nDesignação: Presidente do conselho de administração Helder Guerreiro\nEndereço: Monte Novo dos Modernos - Ermidas Sado\nCódigo postal: 7565-255\nLocalidade: Santiago do Cacém\nTelefone: +351 269508030\nFax: +351 269502111\nEndereço eletrónico: geral@ambilital.pt\n\n28 - IDENTIFICAÇÃO DO(S) AUTOR(ES) DE ANÚNCIO\nNome: Alexandra Pinheiro\nCargo: Técnico Superior\n419684154",
    "nipc": "505255391",
    "distrito": "Setúbal",
    "concelho": "Santiago do Cacém",
    "freguesia": "Freguesia de Ermidas-Sado",
    "site": "www.ambilital.pt",
    "email": "geral@ambilital.pt",
    "designacao_contrato": "CP/CCP/09/25 - Aquisição de 5 contentores compactadores para resíduos urbanos",
    "descricao": "CP/CCP/09/25 - Aquisição de 5 contentores compactadores para resíduos urbanos",
    "preco_base": "177.500,00 EUR",
    "prazo_execucao": "150 DIAS",
    "prazo_apresentacao_propostas": "30-10-2025 16:00",
    "fundos_eu": "Não",
    "plataforma_eletronica": "VORTAL",
    "url_procedimento": "https://community.vortal.biz/public/",
    "autor_nome": "Alexandra Pinheiro",
    "autor_cargo": "Técnico Superior"
  }
]