[
  {
    "numero_procedimento": "N/A",
    "entidade": "Infraestruturas de Portugal",
    "link": "https://diariodarepublica.pt/dr/detalhe/contrato-publico/25001-936007145",
    "detalhes_completos": "1 - IDENTIFICAÇÃO E CONTACTOS DA ENTIDADE ADJUDICANTE\nDesignação da entidade adjudicante: Infraestruturas de Portugal\nNIPC: 503933813\nServiço/Órgão/Pessoa de contacto: Direção de Compras e Logística - Departamento de Compras - Edifício 2\nEndereço: Praça da Portagem\nCódigo postal: 2809-013\nLocalidade: Almada\nPaís: Portugal\nNUT III: PT170\nDistrito: Setúbal\nConcelho: Almada\nFreguesia: União das Freguesias de Almada, Cova da Piedade, Pragal e Cacilhas\nTelefone:  212 879 300 \nFax: 21 287 90 00\nEndereço da Entidade (URL): www.infraestruturasdeportugal.pt\nEndereço Eletrónico: dcl@infraestruturasdeportugal.pt\nFunção da Organização: Adquirente\nNorma jurídica da Entidade Adjudicante: Organismo de direito público\nÁrea de atividade da Entidade Adjudicante: Serviços ferroviários\n\n2 - JORNAL OFICIAL DA UNIÃO EUROPEIA\nO procedimento a que este anúncio diz respeito também é publicitado no Jornal Oficial da União Europeia? Não\n\n3 - AVISO\nModelo de Anúncio: Concurso público\nData de Envio do Anúncio: 22-09-2025\n\n5 - PROCESSO\nTipo de Procedimento: Concurso público\nPreço base do procedimento: Sim\nValor do preço base do procedimento: 35.000,00 EUR\nProcedimento com lotes? Não\n\n6 - OBJETO DO CONTRATO\nNúmero de referência interna: 10020885\nDesignação do contrato: AQUISIÇÃO VIRTUALIZADOR AMBIENTE GESTÃO CENTRAL\nDescrição: AQUISIÇÃO VIRTUALIZADOR AMBIENTE GESTÃO CENTRAL\nTipo de Contrato Principal: Aquisição de Bens Móveis\nTipo de Contrato: Aquisição de Bens Móveis\nClassificação CPV (Vocabulário Comum para os Contratos Públicos)\nObjeto principal\nVocabulário Principal: 30000000\nPreço base s/IVA: 35.000,00 EUR\n\n7 - INDICAÇÕES ADICIONAIS\nO contrato envolve aquisição conjunta (satisfação de várias entidades)? Não\nO contrato é adjudicado por uma central de compras? Não\n\n8 - TÉCNICAS\nO concurso destina-se à celebração de um acordo-quadro? Inexistência de acordo-quadro\nÉ utilizado um leilão eletrónico? Não\nÉ adotada uma fase de negociação? Não\nSistema de Aquisição Dinâmico: Inexistência de sistema de aquisição dinâmico\n\n9 - LOCAL DA EXECUÇÃO DO CONTRATO\nLOCAL DA EXECUÇÃO DO CONTRATO (PROCEDIMENTO)\nPaís: Portugal\nNUT III: PT170\nLocalidade: Parque das Nações\nDistrito: Lisboa\nConcelho: Lisboa\nFreguesia: Freguesia de Parque das Nações\n\n10 - PRAZO DE EXECUÇÃO DO CONTRATO\nPrazo de execução do contrato: 45 DIAS\nPrevisão de renovações: Não\n\n11 - FUNDOS EU\nTêm fundos EU? Sim\n\n12 - DOCUMENTOS DE HABILITAÇÃO\nHabilitação para o exercício da atividade profissional: Não\n\n13 - CONDIÇÕES DE APRESENTAÇÃO\nPlataforma eletrónica utilizada pela entidade adjudicante: ANOGOV\nURL para Apresentação: https://www.anogov.com/infraestruturasdeportugal-ip/faces/\nAdmissibilidade da apresentação de propostas variantes: Não autorizado\nPrazo para apresentação das propostas: 03-10-2025 17:00\nPrazo durante o qual os concorrentes são obrigados a manter as respetivas propostas: 120 dias a contar do termo do prazo para a apresentação das propostas\nApresentação de Catálogo Eletrónico: Não autorizado\nIndicação de Subcontratação na Proposta: Inexistência de indicação de subcontratação\n\n14 - PRESTAÇÃO DE CAUÇÃO\nPrestação de caução: Não\n\n15 - FORNECIMENTO DAS PEÇAS DO CONCURSO, APRESENTAÇÃO DE PEDIDOS DE PARTICIPAÇÃO E APRESENTAÇÃO DAS PROPOSTAS\nLink para acesso às peças do concurso (URL): https://www.anogov.com/infraestruturasdeportugal-ip/faces/app/acessoDocs.jsp?codigoAcesso=fQOE3lObFXGAZjrInzaf0xaTnWxQKIHrqQQSFJymEVZ2LrcicN\n\n20 - OUTROS REQUISITOS\nInformação sobre contratos reservados. Aplica-se a contratos reservados (54º-A)? Não\n\n21 - CRITÉRIO DE ADJUDICAÇÃO\nMultifator: Não\nMonofator:\nNome: Preço\n\n24 - CONDIÇÕES DO CONTRATO\nFaturação Eletrónica: Necessário\nObrigação de Subcontratação:\nCódigo da Obrigação de Subcontratação: Não é aplicável nenhuma obrigação de subcontratação.\n\n25 - COMPRA PÚBLICA ESTRATÉGICA\nCompra Pública Estratégica: Inexistência de contratação pública estratégica\n\n26 - INFORMAÇÕES ADICIONAIS\nContrato adequado para PME: Sim\nCobertura ACP (Acordo dos Contratos Públicos da Organização Mundial do Comércio): Não\n\n27 - IDENTIFICAÇÃO E CONTACTOS DO ÓRGÃO DE RECURSOS ADMINISTRATIVOS\nDesignação: Conselho de Administração Executivo da Infraestruturas de Portugal, S.A.\nEndereço: Praça da Portagem\nCódigo postal: 2809-013\nLocalidade: Almada\nEndereço eletrónico: contratos@infraestruturasdeportugal.pt\n\n28 - IDENTIFICAÇÃO DO(S) AUTOR(ES) DE ANÚNCIO\nNome: Margarida Veloso\nCargo: Diretora Adjunta de Compras e Logística\n419560767",
    "nipc": "503933813",
    "distrito": "Setúbal",
    "concelho": "Almada",
    "freguesia": "União das Freguesias de Almada, Cova da Piedade, Pragal e Cacilhas",
    "site": "www.infraestruturasdeportugal.pt",
    "email": "dcl@infraestruturasdeportugal.pt",
    "designacao_contrato": "AQUISIÇÃO VIRTUALIZADOR AMBIENTE GESTÃO CENTRAL",
    "descricao": "AQUISIÇÃO VIRTUALIZADOR AMBIENTE GESTÃO CENTRAL",
    "preco_base": "35.000,00 EUR",
    "prazo_execucao": "45 DIAS",
    "prazo_apresentacao_propostas": "03-10-2025 17:00",
    "fundos_eu": "Sim",
    "plataforma_eletronica": "ANOGOV",
    "url_procedimento": "https://www.anogov.com/infraestruturasdeportugal-ip/faces/",
    "autor_nome": "Margarida Veloso",
    "autor_cargo": "Diretora Adjunta de Compras e Logística"
  },
  {
    "numero_procedimento": "N/A",
    "entidade": "Infraestruturas de Portugal",
    "link": "https://diariodarepublica.pt/dr/detalhe/contrato-publico/25003-936007146",
    "detalhes_completos": "1 - IDENTIFICAÇÃO E CONTACTOS DA ENTIDADE ADJUDICANTE\nDesignação da entidade adjudicante: Infraestruturas de Portugal\nNIPC: 503933813\nServiço/Órgão/Pessoa de contacto: Direção de Compras e Logística - Departamento de Compras - Edifício 2\nEndereço: Praça da Portagem\nCódigo postal: 2809-013\nLocalidade: Almada\nPaís: Portugal\nNUT III: PT170\nDistrito: Setúbal\nConcelho: Almada\nFreguesia: União das Freguesias de Almada, Cova da Piedade, Pragal e Cacilhas\nTelefone:  212 879 300 \nFax: 21 287 90 00\nEndereço da Entidade (URL): www.infraestruturasdeportugal.pt\nEndereço Eletrónico: dcl@infraestruturasdeportugal.pt\nFunção da Organização: Adquirente\nNorma jurídica da Entidade Adjudicante: Organismo de direito público\nÁrea de atividade da Entidade Adjudicante: Serviços ferroviários\n\n2 - JORNAL OFICIAL DA UNIÃO EUROPEIA\nO procedimento a que este anúncio diz respeito também é publicitado no Jornal Oficial da União Europeia? Não\n\n3 - AVISO\nModelo de Anúncio: Concurso público\nData de Envio do Anúncio: 22-09-2025\n\n5 - PROCESSO\nTipo de Procedimento: Concurso público\nPreço base do procedimento: Sim\nValor do preço base do procedimento: 350.000,00 EUR\nProcedimento com lotes? Não\n\n6 - OBJETO DO CONTRATO\nNúmero de referência interna: 10013234\nDesignação do contrato: AT-TEL - LINHA SUL - RENOVAÇÃO REDE TELEFÓNICA DE EXPLORAÇÃO  (SETÚBAL-TUNES)\nDescrição: AT-TEL - LINHA SUL - RENOVAÇÃO REDE TELEFÓNICA DE EXPLORAÇÃO  (SETÚBAL-TUNES)\nTipo de Contrato Principal: Aquisição de Bens Móveis\nTipo de Contrato: Aquisição de Bens Móveis\nClassificação CPV (Vocabulário Comum para os Contratos Públicos)\nObjeto principal\nVocabulário Principal: 34632000\nPreço base s/IVA: 350.000,00 EUR\n\n7 - INDICAÇÕES ADICIONAIS\nO contrato envolve aquisição conjunta (satisfação de várias entidades)? Não\nO contrato é adjudicado por uma central de compras? Não\n\n8 - TÉCNICAS\nO concurso destina-se à celebração de um acordo-quadro? Inexistência de acordo-quadro\nÉ utilizado um leilão eletrónico? Não\nÉ adotada uma fase de negociação? Não\nSistema de Aquisição Dinâmico: Inexistência de sistema de aquisição dinâmico\n\n9 - LOCAL DA EXECUÇÃO DO CONTRATO\nLOCAL DA EXECUÇÃO DO CONTRATO (PROCEDIMENTO)\nPaís: Portugal\nNUT III: PT170\nLocalidade: Parque das Nações\nDistrito: Lisboa\nConcelho: Lisboa\nFreguesia: Freguesia de Parque das Nações\n\n10 - PRAZO DE EXECUÇÃO DO CONTRATO\nPrazo de execução do contrato: 240 DIAS\nPrevisão de renovações: Não\n\n11 - FUNDOS EU\nTêm fundos EU? Sim\n\n12 - DOCUMENTOS DE HABILITAÇÃO\nHabilitação para o exercício da atividade profissional: Não\n\n13 - CONDIÇÕES DE APRESENTAÇÃO\nPlataforma eletrónica utilizada pela entidade adjudicante: ANOGOV\nURL para Apresentação: https://www.anogov.com/infraestruturasdeportugal-ip/faces/\nAdmissibilidade da apresentação de propostas variantes: Não autorizado\nPrazo para apresentação das propostas: 13-10-2025 17:00\nPrazo durante o qual os concorrentes são obrigados a manter as respetivas propostas: 120 dias a contar do termo do prazo para a apresentação das propostas\nApresentação de Catálogo Eletrónico: Não autorizado\nIndicação de Subcontratação na Proposta: Inexistência de indicação de subcontratação\n\n14 - PRESTAÇÃO DE CAUÇÃO\nPrestação de caução: Não\n\n15 - FORNECIMENTO DAS PEÇAS DO CONCURSO, APRESENTAÇÃO DE PEDIDOS DE PARTICIPAÇÃO E APRESENTAÇÃO DAS PROPOSTAS\nLink para acesso às peças do concurso (URL): https://www.anogov.com/infraestruturasdeportugal-ip/faces/app/acessoDocs.jsp?codigoAcesso=MOPuY9lOLJC1wA7NQ7ALH0FpQl1lb2j0g4idBmq6ds638pkoT9\n\n20 - OUTROS REQUISITOS\nInformação sobre contratos reservados. Aplica-se a contratos reservados (54º-A)? Não\n\n21 - CRITÉRIO DE ADJUDICAÇÃO\nMultifator: Não\nMonofator:\nNome: Preço\n\n24 - CONDIÇÕES DO CONTRATO\nFaturação Eletrónica: Necessário\nObrigação de Subcontratação:\nCódigo da Obrigação de Subcontratação: Não é aplicável nenhuma obrigação de subcontratação.\n\n25 - COMPRA PÚBLICA ESTRATÉGICA\nCompra Pública Estratégica: Inexistência de contratação pública estratégica\n\n26 - INFORMAÇÕES ADICIONAIS\nContrato adequado para PME: Não\nCobertura ACP (Acordo dos Contratos Públicos da Organização Mundial do Comércio): Não\n\n27 - IDENTIFICAÇÃO E CONTACTOS DO ÓRGÃO DE RECURSOS ADMINISTRATIVOS\nDesignação: Conselho de Administração Executivo da Infraestruturas de Portugal, S.A.\nEndereço: Praça da Portagem\nCódigo postal: 2809-013\nLocalidade: Almada\nEndereço eletrónico: contratos@infraestruturasdeportugal.pt\n\n28 - IDENTIFICAÇÃO DO(S) AUTOR(ES) DE ANÚNCIO\nNome: Margarida Veloso\nCargo: Diretora Adjunta de Compras e Logística\n419561066",
    "nipc": "503933813",
    "distrito": "Setúbal",
    "concelho": "Almada",
    "freguesia": "União das Freguesias de Almada, Cova da Piedade, Pragal e Cacilhas",
    "site": "www.infraestruturasdeportugal.pt",
    "email": "dcl@infraestruturasdeportugal.pt",
    "designacao_contrato": "AT-TEL - LINHA SUL - RENOVAÇÃO REDE TELEFÓNICA DE EXPLORAÇÃO (SETÚBAL-TUNES)",
    "descricao": "AT-TEL - LINHA SUL - RENOVAÇÃO REDE TELEFÓNICA DE EXPLORAÇÃO (SETÚBAL-TUNES)",
    "preco_base": "350.000,00 EUR",
    "prazo_execucao": "240 DIAS",
    "prazo_apresentacao_propostas": "13-10-2025 17:00",
    "fundos_eu": "Sim",
    "plataforma_eletronica": "ANOGOV",
    "url_procedimento": "https://www.anogov.com/infraestruturasdeportugal-ip/faces/",
    "autor_nome": "Margarida Veloso",
    "autor_cargo": "Diretora Adjunta de Compras e Logística"
  },
  {
    "numero_procedimento": "N/A",
    "entidade": "Assembleia da República",
    "link": "https://diariodarepublica.pt/dr/detalhe/contrato-publico/25005-936007147",
    "detalhes_completos": "1 - IDENTIFICAÇÃO E CONTACTOS DA ENTIDADE ADJUDICANTE\nDesignação da entidade adjudicante: Assembleia da República\nNIPC: 600054128\nServiço/Órgão/Pessoa de contacto: Divisão de Contratação\nEndereço: Palácio de S. Bento\nCódigo postal: 1249-069\nLocalidade: Lisboa\nPaís: Portugal\nNUT III: PTZZZ\nDistrito: Todos\nConcelho: Todos\nFreguesia: Todas\nTelefone: 213919000\nFax: 213917440\nEndereço da Entidade (URL): www.parlamento.pt\nEndereço Eletrónico: Correio.Geral@ar.parlamento.pt\neDelivery Gateway (URL): https://www.acingov.pt\nFunção da Organização: Adquirente\nNorma jurídica da Entidade Adjudicante: Organismo de direito público\nÁrea de atividade da Autoridade Adjudicante: Serviços públicos das administrações públicas\n\n2 - JORNAL OFICIAL DA UNIÃO EUROPEIA\nO procedimento a que este anúncio diz respeito também é publicitado no Jornal Oficial da União Europeia? Não\n\n3 - AVISO\nModelo de Anúncio: Concurso público\nData de Envio do Anúncio: 22-09-2025\n\n5 - PROCESSO\nTipo de Procedimento: Concurso público\nPreço base do procedimento: Sim\nValor do preço base do procedimento: 75.600,00 EUR\nProcedimento com lotes? Não\n\n6 - OBJETO DO CONTRATO\nNúmero de referência interna: 1/DC/2025\nDesignação do contrato: Aquisição de serviços de gestão de informação de imprensa, de rádio e de televisão\nDescrição: Aquisição de serviços de gestão de informação de imprensa, de rádio e de televisão\nTipo de Contrato Principal: Aquisição de Serviços\nTipo de Contrato: Aquisição de Serviços\nClassificação CPV (Vocabulário Comum para os Contratos Públicos)\nObjeto principal\nVocabulário Principal: 72320000\nPreço base s/IVA: 75.600,00 EUR\n\n7 - INDICAÇÕES ADICIONAIS\nO contrato envolve aquisição conjunta (satisfação de várias entidades)? Não\nO contrato é adjudicado por uma central de compras? Não\n\n8 - TÉCNICAS\nO concurso destina-se à celebração de um acordo-quadro? Inexistência de acordo-quadro\nÉ utilizado um leilão eletrónico? Não\nÉ adotada uma fase de negociação? Não\nSistema de Aquisição Dinâmico: Inexistência de sistema de aquisição dinâmico\n\n9 - LOCAL DA EXECUÇÃO DO CONTRATO\nLOCAL DA EXECUÇÃO DO CONTRATO (PROCEDIMENTO)\nPaís: Portugal\nNUT III: PT170\nLocalidade: Freguesia da Estrela\nDistrito: Lisboa\nConcelho: Lisboa\nFreguesia: Freguesia da Estrela\n\n10 - PRAZO DE EXECUÇÃO DO CONTRATO\nPrazo de execução do contrato: 1 ANOS\nPrevisão de renovações: Sim\nIndicar número máximo de renovações: 2\nPrazo de renovações diferente do prazo inicial: Não\n\n11 - FUNDOS EU\nTêm fundos EU? Não\n\n12 - DOCUMENTOS DE HABILITAÇÃO\nHabilitação para o exercício da atividade profissional: Não\n\n13 - CONDIÇÕES DE APRESENTAÇÃO\nPlataforma eletrónica utilizada pela entidade adjudicante: ACIN\nURL para Apresentação: https://www.acingov.pt\nAdmissibilidade da apresentação de propostas variantes: Não autorizado\nPrazo para apresentação das propostas: 07-10-2025 23:59\nPrazo durante o qual os concorrentes são obrigados a manter as respetivas propostas: 90 dias a contar do termo do prazo para a apresentação das propostas\nIndicação de Subcontratação na Proposta: Inexistência de indicação de subcontratação\n\n14 - PRESTAÇÃO DE CAUÇÃO\nPrestação de caução: Não\n\n15 - FORNECIMENTO DAS PEÇAS DO CONCURSO, APRESENTAÇÃO DE PEDIDOS DE PARTICIPAÇÃO E APRESENTAÇÃO DAS PROPOSTAS\nLink para acesso às peças do concurso (URL): https://www.acingov.pt/acingovprod/2/zonaPublica/zona_publica_c/donwloadProcedurePiece/OTc4MzEz\n\n20 - OUTROS REQUISITOS\nInformação sobre contratos reservados. Aplica-se a contratos reservados (54º-A)? Não\n\n21 - CRITÉRIO DE ADJUDICAÇÃO\nMultifator: Não\nMonofator:\nNome: Preço\n\n24 - CONDIÇÕES DO CONTRATO\nFaturação Eletrónica: Permitido\nObrigação de Subcontratação:\nCódigo da Obrigação de Subcontratação: Não é aplicável nenhuma obrigação de subcontratação.\n\n25 - COMPRA PÚBLICA ESTRATÉGICA\nCompra Pública Estratégica: Inexistência de contratação pública estratégica\n\n26 - INFORMAÇÕES ADICIONAIS\nContrato adequado para PME: Não\nCobertura ACP (Acordo dos Contratos Públicos da Organização Mundial do Comércio): Não\n\n27 - IDENTIFICAÇÃO E CONTACTOS DO ÓRGÃO DE RECURSOS ADMINISTRATIVOS\nDesignação: Presidente da Assembleia da República\nEndereço: Praça da Constituição de 1976, Palácio de São Bento\nCódigo postal: 1249-068\nLocalidade: Lisboa\nTelefone: 00351213919000\nFax: 00351213917440\nEndereço eletrónico: GABPAR.Correio@ar.parlamento.pt\nPrazo de interposição do recurso: 5 dias\n\n28 - IDENTIFICAÇÃO DO(S) AUTOR(ES) DE ANÚNCIO\nNome: Anabela Cabral Ferreira\nCargo: Secretária-Geral da Assembleia da República\n419556141",
    "nipc": "600054128",
    "distrito": "Todos",
    "concelho": "Todos",
    "freguesia": "Todas",
    "site": "www.parlamento.pt",
    "email": "Correio.Geral@ar.parlamento.pt",
    "designacao_contrato": "Aquisição de serviços de gestão de informação de imprensa, de rádio e de televisão",
    "descricao": "Aquisição de serviços de gestão de informação de imprensa, de rádio e de televisão",
    "preco_base": "75.600,00 EUR",
    "prazo_execucao": "1 ANOS",
    "prazo_apresentacao_propostas": "07-10-2025 23:59",
    "fundos_eu": "Não",
    "plataforma_eletronica": "ACIN",
    "url_procedimento": "https://www.acingov.pt",
    "autor_nome": "Anabela Cabral Ferreira",
    "autor_cargo": "Secretária-Geral da Assembleia da República"
  },
  {
    "numero_procedimento": "N/A",
    "entidade": "UNL - Faculdade de Ciências e Tecnologia",
    "link": "https://diariodarepublica.pt/dr/detalhe/contrato-publico/25007-936007148",
    "detalhes_completos": "1 - IDENTIFICAÇÃO E CONTACTOS DA ENTIDADE ADJUDICANTE\nDesignação da entidade adjudicante: UNL - Faculdade de Ciências e Tecnologia\nNIPC: 501559094\nServiço/Órgão/Pessoa de contacto: Gabinete de Contratação Pública e Património da NOVA FCT\nEndereço: Campus de Caparica\nCódigo postal: 2829-516\nLocalidade: Caparica\nPaís: Portugal\nNUT III: PT170\nDistrito: Setúbal\nConcelho: Almada\nFreguesia: União das Freguesias de Caparica e Trafaria\nTelefone: 212948577\nEndereço da Entidade (URL): http://www.fct.unl.pt/\nEndereço Eletrónico: gab.cpp.c@fct.unl.pt\neDelivery Gateway (URL): https://www.acingov.pt\nFunção da Organização: Adquirente\nNorma jurídica da Entidade Adjudicante: Organismo de direito público\nÁrea de atividade da Autoridade Adjudicante: Serviços públicos das administrações públicas\n\n2 - JORNAL OFICIAL DA UNIÃO EUROPEIA\nO procedimento a que este anúncio diz respeito também é publicitado no Jornal Oficial da União Europeia? Não\n\n3 - AVISO\nModelo de Anúncio: Concurso público\nData de Envio do Anúncio: 22-09-2025\n\n5 - PROCESSO\nTipo de Procedimento: Concurso público\nPreço base do procedimento: Sim\nValor do preço base do procedimento: 142.210,00 EUR\nProcedimento com lotes? Não\n\n6 - OBJETO DO CONTRATO\nNúmero de referência interna: CP N.º 2799/2025\nDesignação do contrato: Aquisição de diversos equipamentos digitais e interativos para a implementação de soluções tecnológicas no âmbito do projeto NOVA TechSphere, destinados à instalação em espaços interiores e exteriores do Campus da NOVA FCT\nDescrição: Aquisição de diversos equipamentos digitais e interativos para a implementação de soluções tecnológicas no âmbito do projeto NOVA TechSphere, destinados à instalação em espaços interiores e exteriores do Campus da NOVA FCT\nTipo de Contrato Principal: Aquisição de Bens Móveis\nTipo de Contrato: Aquisição de Bens Móveis\nClassificação CPV (Vocabulário Comum para os Contratos Públicos)\nObjeto principal\nVocabulário Principal: 32322000\nPreço base s/IVA: 142.210,00 EUR\n\n7 - INDICAÇÕES ADICIONAIS\nO contrato envolve aquisição conjunta (satisfação de várias entidades)? Não\nO contrato é adjudicado por uma central de compras? Não\n\n8 - TÉCNICAS\nO concurso destina-se à celebração de um acordo-quadro? Inexistência de acordo-quadro\nÉ utilizado um leilão eletrónico? Não\nÉ adotada uma fase de negociação? Não\nSistema de Aquisição Dinâmico: Inexistência de sistema de aquisição dinâmico\n\n9 - LOCAL DA EXECUÇÃO DO CONTRATO\nLOCAL DA EXECUÇÃO DO CONTRATO (PROCEDIMENTO)\nPaís: Portugal\nNUT III: PT170\nLocalidade: União das Freguesias de Caparica e Trafaria\nDistrito: Setúbal\nConcelho: Almada\nFreguesia: União das Freguesias de Caparica e Trafaria\n\n10 - PRAZO DE EXECUÇÃO DO CONTRATO\nPrazo de execução do contrato: 60 DIAS\nPrevisão de renovações: Não\n\n11 - FUNDOS EU\nTêm fundos EU? Sim\n\n12 - DOCUMENTOS DE HABILITAÇÃO\nHabilitação para o exercício da atividade profissional: Não\n\n13 - CONDIÇÕES DE APRESENTAÇÃO\nPlataforma eletrónica utilizada pela entidade adjudicante: ACIN\nURL para Apresentação: https://www.acingov.pt\nAdmissibilidade da apresentação de propostas variantes: Não autorizado\nPrazo para apresentação das propostas: 28-09-2025 23:59\nPrazo durante o qual os concorrentes são obrigados a manter as respetivas propostas: 120 dias a contar do termo do prazo para a apresentação das propostas\nIndicação de Subcontratação na Proposta: Inexistência de indicação de subcontratação\n\n14 - PRESTAÇÃO DE CAUÇÃO\nPrestação de caução: Não\n\n15 - FORNECIMENTO DAS PEÇAS DO CONCURSO, APRESENTAÇÃO DE PEDIDOS DE PARTICIPAÇÃO E APRESENTAÇÃO DAS PROPOSTAS\nLink para acesso às peças do concurso (URL): https://www.acingov.pt/acingovprod/2/zonaPublica/zona_publica_c/donwloadProcedurePiece/OTgwMjA0\n\n20 - OUTROS REQUISITOS\nInformação sobre contratos reservados. Aplica-se a contratos reservados (54º-A)? Não\n\n21 - CRITÉRIO DE ADJUDICAÇÃO\nMultifator: Não\nMonofator:\nNome: Outros\nOutro nome: Fator Preço\n\n24 - CONDIÇÕES DO CONTRATO\nFaturação Eletrónica: Permitido\nObrigação de Subcontratação:\nCódigo da Obrigação de Subcontratação: Não é aplicável nenhuma obrigação de subcontratação.\n\n25 - COMPRA PÚBLICA ESTRATÉGICA\nCompra Pública Estratégica: Inexistência de contratação pública estratégica\n\n26 - INFORMAÇÕES ADICIONAIS\nContrato adequado para PME: Sim\nCobertura ACP (Acordo dos Contratos Públicos da Organização Mundial do Comércio): Não\n\n27 - IDENTIFICAÇÃO E CONTACTOS DO ÓRGÃO DE RECURSOS ADMINISTRATIVOS\nDesignação: Universidade Nova de Lisboa - Reitoria\nEndereço: Campus de Campolide\nCódigo postal: 1099-085\nLocalidade: Lisboa\nTelefone: 213715600\nFax: \nEndereço eletrónico: reitoria@unl.pt\n\n28 - IDENTIFICAÇÃO DO(S) AUTOR(ES) DE ANÚNCIO\nNome: Sónia Miriam Mendonça Ferreira\nCargo: Assistente Técnica\n419563934",
    "nipc": "501559094",
    "distrito": "Setúbal",
    "concelho": "Almada",
    "freguesia": "União das Freguesias de Caparica e Trafaria",
    "site": "http://www.fct.unl.pt/",
    "email": "gab.cpp.c@fct.unl.pt",
    "designacao_contrato": "Aquisição de diversos equipamentos digitais e interativos para a implementação de soluções tecnológicas no âmbito do projeto NOVA TechSphere, destinados à instalação em espaços interiores e exteriores do Campus da NOVA FCT",
    "descricao": "Aquisição de diversos equipamentos digitais e interativos para a implementação de soluções tecnológicas no âmbito do projeto NOVA TechSphere, destinados à instalação em espaços interiores e exteriores do Campus da NOVA FCT",
    "preco_base": "142.210,00 EUR",
    "prazo_execucao": "60 DIAS",
    "prazo_apresentacao_propostas": "28-09-2025 23:59",
    "fundos_eu": "Sim",
    "plataforma_eletronica": "ACIN",
    "url_procedimento": "https://www.acingov.pt",
    "autor_nome": "Sónia Miriam Mendonça Ferreira",
    "autor_cargo": "Assistente Técnica"
  },
  {
    "numero_procedimento": "N/A",
    "entidade": "Faculdade de Direito da Universidade de Lisboa",
    "link": "https://diariodarepublica.pt/dr/detalhe/contrato-publico/25008-936007149",
    "detalhes_completos": "1 - IDENTIFICAÇÃO E CONTACTOS DA ENTIDADE ADJUDICANTE\nDesignação da entidade adjudicante: Faculdade de Direito da Universidade de Lisboa\nNIPC: 502736208\nServiço/Órgão/Pessoa de contacto: Ana Ramos\nEndereço: Alameda da Universidade\nCódigo postal: 1649-014\nLocalidade: Lisboa\nPaís: Portugal\nNUT III: PT170\nDistrito: Lisboa\nConcelho: Lisboa\nFreguesia: Freguesia de Alvalade - Lisboa\nTelefone: 217984600\nFax: 217984600\nEndereço da Entidade (URL): www.fd.ulisboa.pt\nEndereço Eletrónico: contratacaopublica@fd.ulisboa.pt\neDelivery Gateway (URL): https://www.acingov.pt\nFunção da Organização: Adquirente\nNorma jurídica da Entidade Adjudicante: Organismo de direito público\nÁrea de atividade da Autoridade Adjudicante: Educação\n\n2 - JORNAL OFICIAL DA UNIÃO EUROPEIA\nO procedimento a que este anúncio diz respeito também é publicitado no Jornal Oficial da União Europeia? Não\n\n3 - AVISO\nModelo de Anúncio: Concurso público\nData de Envio do Anúncio: 22-09-2025\n\n5 - PROCESSO\nTipo de Procedimento: Concurso público\nPreço base do procedimento: Sim\nValor do preço base do procedimento: 153.675,27 EUR\nProcedimento com lotes? Não\n\n6 - OBJETO DO CONTRATO\nNúmero de referência interna: CP/4/2025\nDesignação do contrato: Aquisição de serviços de manutenção preventiva e corretiva de equipamentos AVAC para a Faculdade de Direito da Universidade de Lisboa\nDescrição: Aquisição de serviços de manutenção preventiva e corretiva de equipamentos AVAC para a Faculdade de Direito da Universidade de Lisboa\nTipo de Contrato Principal: Aquisição de Serviços\nTipo de Contrato: Aquisição de Serviços\nClassificação CPV (Vocabulário Comum para os Contratos Públicos)\nObjeto principal\nVocabulário Principal: 50700000\nPreço base s/IVA: 153.675,27 EUR\n\n7 - INDICAÇÕES ADICIONAIS\nO contrato envolve aquisição conjunta (satisfação de várias entidades)? Não\nO contrato é adjudicado por uma central de compras? Não\n\n8 - TÉCNICAS\nO concurso destina-se à celebração de um acordo-quadro? Inexistência de acordo-quadro\nÉ utilizado um leilão eletrónico? Não\nÉ adotada uma fase de negociação? Não\nSistema de Aquisição Dinâmico: Inexistência de sistema de aquisição dinâmico\n\n9 - LOCAL DA EXECUÇÃO DO CONTRATO\nLOCAL DA EXECUÇÃO DO CONTRATO (PROCEDIMENTO)\nPaís: Portugal\nNUT III: PT170\nLocalidade: Freguesia de Alvalade - Lisboa\nDistrito: Lisboa\nConcelho: Lisboa\nFreguesia: Freguesia de Alvalade - Lisboa\n\n10 - PRAZO DE EXECUÇÃO DO CONTRATO\nPrazo de execução do contrato: 1 ANOS\nPrevisão de renovações: Sim\nIndicar número máximo de renovações: 2\nPrazo de renovações diferente do prazo inicial: Não\n\n11 - FUNDOS EU\nTêm fundos EU? Não\n\n12 - DOCUMENTOS DE HABILITAÇÃO\nHabilitação para o exercício da atividade profissional: Não\n\n13 - CONDIÇÕES DE APRESENTAÇÃO\nPlataforma eletrónica utilizada pela entidade adjudicante: ACIN\nURL para Apresentação: https://www.acingov.pt\nAdmissibilidade da apresentação de propostas variantes: Não autorizado\nPrazo para apresentação das propostas: 07-10-2025 23:59\nPrazo durante o qual os concorrentes são obrigados a manter as respetivas propostas: 66 dias a contar do termo do prazo para a apresentação das propostas\nIndicação de Subcontratação na Proposta: Inexistência de indicação de subcontratação\n\n14 - PRESTAÇÃO DE CAUÇÃO\nPrestação de caução: Não\n\n15 - FORNECIMENTO DAS PEÇAS DO CONCURSO, APRESENTAÇÃO DE PEDIDOS DE PARTICIPAÇÃO E APRESENTAÇÃO DAS PROPOSTAS\nLink para acesso às peças do concurso (URL): https://www.acingov.pt/acingovprod/2/zonaPublica/zona_publica_c/donwloadProcedurePiece/OTgwMTIw\n\n20 - OUTROS REQUISITOS\nInformação sobre contratos reservados. Aplica-se a contratos reservados (54º-A)? Não\n\n21 - CRITÉRIO DE ADJUDICAÇÃO\nMultifator: Sim\nFator: \nNome: Outros\nOutro Nome: Multifator\nPonderação: 100%\nSubfatores: Não\n\n24 - CONDIÇÕES DO CONTRATO\nFaturação Eletrónica: Permitido\nObrigação de Subcontratação:\nCódigo da Obrigação de Subcontratação: Não é aplicável nenhuma obrigação de subcontratação.\n\n25 - COMPRA PÚBLICA ESTRATÉGICA\nCompra Pública Estratégica: Inexistência de contratação pública estratégica\n\n26 - INFORMAÇÕES ADICIONAIS\nContrato adequado para PME: Não\nCobertura ACP (Acordo dos Contratos Públicos da Organização Mundial do Comércio): Não\n\n27 - IDENTIFICAÇÃO E CONTACTOS DO ÓRGÃO DE RECURSOS ADMINISTRATIVOS\nDesignação: Diretor\nEndereço: Alameda da Universidade\nCódigo postal: 1649-014\nLocalidade: Lisboa\nTelefone: 217984600\nFax: \nEndereço eletrónico: secretariadodir@fd.ulisboa.pt\nPrazo de interposição do recurso: 3 dias\n\n28 - IDENTIFICAÇÃO DO(S) AUTOR(ES) DE ANÚNCIO\nNome: Ana Sofia Ramos\nCargo: Coordenadora da Área Financeira\n419563448",
    "nipc": "502736208",
    "distrito": "Lisboa",
    "concelho": "Lisboa",
    "freguesia": "Freguesia de Alvalade - Lisboa",
    "site": "www.fd.ulisboa.pt",
    "email": "contratacaopublica@fd.ulisboa.pt",
    "designacao_contrato": "Aquisição de serviços de manutenção preventiva e corretiva de equipamentos AVAC para a Faculdade de Direito da Universidade de Lisboa",
    "descricao": "Aquisição de serviços de manutenção preventiva e corretiva de equipamentos AVAC para a Faculdade de Direito da Universidade de Lisboa",
    "preco_base": "153.675,27 EUR",
    "prazo_execucao": "1 ANOS",
    "prazo_apresentacao_propostas": "07-10-2025 23:59",
    "fundos_eu": "Não",
    "plataforma_eletronica": "ACIN",
    "url_procedimento": "https://www.acingov.pt",
    "autor_nome": "Ana Sofia Ramos",
    "autor_cargo": "Coordenadora da Área Financeira"
  },
  {
    "numero_procedimento": "N/A",
    "entidade": "Município de Santo Tirso",
    "link": "https://diariodarepublica.pt/dr/detalhe/contrato-publico/25009-936007168",
    "detalhes_completos": "1 - IDENTIFICAÇÃO E CONTACTOS DA ENTIDADE ADJUDICANTE\nDesignação da entidade adjudicante: Município de Santo Tirso\nNIPC: 501306870\nEndereço: Praça 25 de Abril\nCódigo postal: 4780-373\nLocalidade: Área Metropolitana do Porto\nPaís: Portugal\nNUT III: PT11A\nDistrito: Porto\nConcelho: Santo Tirso\nFreguesia: União das Freguesias de Santo Tirso, Couto (Santa Cristina e São Miguel) e Burgães\nTelefone: 252830400\nFax: 252856534\nEndereço da Entidade (URL): www.cm-stirso.pt\nEndereço Eletrónico: santotirso@cm-stirso.pt\neDelivery Gateway (URL): https://community.vortal.biz/public/\nFunção da Organização: Adquirente\nNorma jurídica da Entidade Adjudicante: Autoridade local\nÁrea de atividade da Autoridade Adjudicante: Serviços públicos das administrações públicas\n\n2 - JORNAL OFICIAL DA UNIÃO EUROPEIA\nO procedimento a que este anúncio diz respeito também é publicitado no Jornal Oficial da União Europeia? Não\n\n3 - AVISO\nModelo de Anúncio: Concurso público\nData de Envio do Anúncio: 22-09-2025\n\n5 - PROCESSO\nTipo de Procedimento: Concurso público\nPreço base do procedimento: Sim\nValor do preço base do procedimento: 51.370,00 EUR\nProcedimento com lotes? Não\n\n6 - OBJETO DO CONTRATO\nNúmero de referência interna: 812/CPN/B/2025\nDesignação do contrato: Contrato de aquisição de um sistema de rega inteligente para diversos jardins com serviços de manutenção\nDescrição: Contrato de aquisição de um sistema de rega inteligente para diversos jardins com serviços de manutenção\nTipo de Contrato Principal: Aquisição de Bens Móveis\nTipo de Contrato: Aquisição de Bens Móveis\nClassificação CPV (Vocabulário Comum para os Contratos Públicos)\nObjeto principal\nVocabulário Principal: 48921000\nPreço base s/IVA: 51.370,00 EUR\n\n7 - INDICAÇÕES ADICIONAIS\nO contrato envolve aquisição conjunta (satisfação de várias entidades)? Não\nO contrato é adjudicado por uma central de compras? Não\n\n8 - TÉCNICAS\nO concurso destina-se à celebração de um acordo-quadro? Inexistência de acordo-quadro\nÉ utilizado um leilão eletrónico? Não\nÉ adotada uma fase de negociação? Não\nSistema de Aquisição Dinâmico: Inexistência de sistema de aquisição dinâmico\n\n9 - LOCAL DA EXECUÇÃO DO CONTRATO\nLOCAL DA EXECUÇÃO DO CONTRATO (PROCEDIMENTO)\nPaís: Portugal\nNUT III: PT11A\nLocalidade: Área Metropolitana do Porto\nDistrito: Porto\nConcelho: Santo Tirso\nFreguesia: União das Freguesias de Santo Tirso, Couto (Santa Cristina e São Miguel) e Burgães\n\n10 - PRAZO DE EXECUÇÃO DO CONTRATO\nPrazo de execução do contrato: 60 DIAS\nPrevisão de renovações: Não\n\n11 - FUNDOS EU\nTêm fundos EU? Sim\n\n12 - DOCUMENTOS DE HABILITAÇÃO\nHabilitação para o exercício da atividade profissional: Não\n\n13 - CONDIÇÕES DE APRESENTAÇÃO\nPlataforma eletrónica utilizada pela entidade adjudicante: VORTAL\nURL para Apresentação: https://community.vortal.biz/public/\nAdmissibilidade da apresentação de propostas variantes: Não autorizado\nPrazo para apresentação das propostas: 04-10-2025 17:30\nPrazo durante o qual os concorrentes são obrigados a manter as respetivas propostas: 66 dias a contar do termo do prazo para a apresentação das propostas\nIndicação de Subcontratação na Proposta: Inexistência de indicação de subcontratação\n\n14 - PRESTAÇÃO DE CAUÇÃO\nPrestação de caução: Não\n\n15 - FORNECIMENTO DAS PEÇAS DO CONCURSO, APRESENTAÇÃO DE PEDIDOS DE PARTICIPAÇÃO E APRESENTAÇÃO DAS PROPOSTAS\nLink para acesso às peças do concurso (URL): https://community.vortal.biz/Public/public-tender-documents/cFYxeGU0S1Z1d0oyOFVEU0cvd1N4bllxUUI5RXlOZE1nZy9TRHVTa3pFcGVHWjQrcnFDTDdsblkwSFlMaFVsSjhuL1VHQjR0VTBiQXRBVU12TTk4ekE9PUtGazZ4\n\n20 - OUTROS REQUISITOS\nInformação sobre contratos reservados. Aplica-se a contratos reservados (54º-A)? Não\n\n21 - CRITÉRIO DE ADJUDICAÇÃO\nMultifator: Não\nMonofator:\nNome: Preço\n\n24 - CONDIÇÕES DO CONTRATO\nFaturação Eletrónica: Permitido\nObrigação de Subcontratação:\nCódigo da Obrigação de Subcontratação: Não é aplicável nenhuma obrigação de subcontratação.\n\n25 - COMPRA PÚBLICA ESTRATÉGICA\nCompra Pública Estratégica: Inexistência de contratação pública estratégica\n\n26 - INFORMAÇÕES ADICIONAIS\nContrato adequado para PME: Sim\nCobertura ACP (Acordo dos Contratos Públicos da Organização Mundial do Comércio): Não\n\n27 - IDENTIFICAÇÃO E CONTACTOS DO ÓRGÃO DE RECURSOS ADMINISTRATIVOS\nDesignação: Câmara Municipal de Santo Tirso\nEndereço: Praça 25 de abril\nCódigo postal: 4780-373\nLocalidade: Santo Tirso\nTelefone: +351 252830400\nFax: +351 252830400\nEndereço eletrónico: santotirso@cm-stirso.pt\n\n28 - IDENTIFICAÇÃO DO(S) AUTOR(ES) DE ANÚNCIO\nNome: Alberto Manuel Martins da Costa\nCargo: Presidente da Câmara Municipal de Santo Tirso\n419560142",
    "nipc": "501306870",
    "distrito": "Porto",
    "concelho": "Santo Tirso",
    "freguesia": "União das Freguesias de Santo Tirso, Couto (Santa Cristina e São Miguel) e Burgães",
    "site": "www.cm-stirso.pt",
    "email": "santotirso@cm-stirso.pt",
    "designacao_contrato": "Contrato de aquisição de um sistema de rega inteligente para diversos jardins com serviços de manutenção",
    "descricao": "Contrato de aquisição de um sistema de rega inteligente para diversos jardins com serviços de manutenção",
    "preco_base": "51.370,00 EUR",
    "prazo_execucao": "60 DIAS",
    "prazo_apresentacao_propostas": "04-10-2025 17:30",
    "fundos_eu": "Sim",
    "plataforma_eletronica": "VORTAL",
    "url_procedimento": "https://community.vortal.biz/public/",
    "autor_nome": "Alberto Manuel Martins da Costa",
    "autor_cargo": "Presidente da Câmara Municipal de Santo Tirso"
  },
  {
    "numero_procedimento": "N/A",
    "entidade": "Secretaria Regional da Juventude, Habitação e Emprego",
    "link": "https://diariodarepublica.pt/dr/detalhe/contrato-publico/25011-936007169",
    "detalhes_completos": "1 - IDENTIFICAÇÃO E CONTACTOS DA ENTIDADE ADJUDICANTE\nDesignação da entidade adjudicante: Secretaria Regional da Juventude, Habitação e Emprego\nNIPC: 600087549\nServiço/Órgão/Pessoa de contacto: Direção Regional da Habitação\nEndereço: Rua Dr. Bruno Tavares Carreiro s/n\nCódigo postal: 9500-119\nLocalidade: Ponta Delgada\nPaís: Portugal\nNUT III: PT200\nDistrito: Região Autónoma dos Açores\nConcelho: Todos\nFreguesia: Todas\nTelefone: 296308000\nEndereço da Entidade (URL): https://portal.azores.gov.pt/web/srjhe\nEndereço Eletrónico: srjhe@azores.gov.pt\neDelivery Gateway (URL): https://www.acingov.pt\nFunção da Organização: Adquirente\nNorma jurídica da Entidade Adjudicante: Organismo de direito público\nÁrea de atividade da Autoridade Adjudicante: Serviços públicos das administrações públicas\n\n2 - JORNAL OFICIAL DA UNIÃO EUROPEIA\nO procedimento a que este anúncio diz respeito também é publicitado no Jornal Oficial da União Europeia? Não\n\n3 - AVISO\nModelo de Anúncio: Concurso público\nData de Envio do Anúncio: 22-09-2025\n\n5 - PROCESSO\nTipo de Procedimento: Concurso público\nPreço base do procedimento: Sim\nValor do preço base do procedimento: 290.000,00 EUR\nProcedimento com lotes? Não\n\n6 - OBJETO DO CONTRATO\nNúmero de referência interna: CCP/2025/15\nDesignação do contrato: EMPREITADA DE REABILITAÇÃO DE MORADIA NA ESTRADA MUNICIPAL - LOMBA DO POMAR, 12, FREGUESIA DA POVOAÇÃO, CONCELHO DA POVOAÇÃO, ILHA DE SÃO MIGUEL\nDescrição: EMPREITADA DE REABILITAÇÃO DE MORADIA NA ESTRADA MUNICIPAL - LOMBA DO POMAR, 12, FREGUESIA DA POVOAÇÃO, CONCELHO DA POVOAÇÃO, ILHA DE SÃO MIGUEL\nTipo de Contrato Principal: Empreitada de Obras Públicas\nTipo de Contrato: Empreitada de Obras Públicas\nClassificação CPV (Vocabulário Comum para os Contratos Públicos)\nObjeto principal\nVocabulário Principal: 45453100\nPreço base s/IVA: 290.000,00 EUR\n\n7 - INDICAÇÕES ADICIONAIS\nO contrato envolve aquisição conjunta (satisfação de várias entidades)? Não\nO contrato é adjudicado por uma central de compras? Não\n\n8 - TÉCNICAS\nO concurso destina-se à celebração de um acordo-quadro? Inexistência de acordo-quadro\nÉ utilizado um leilão eletrónico? Não\nÉ adotada uma fase de negociação? Não\nSistema de Aquisição Dinâmico: Inexistência de sistema de aquisição dinâmico\n\n9 - LOCAL DA EXECUÇÃO DO CONTRATO\nLOCAL DA EXECUÇÃO DO CONTRATO (PROCEDIMENTO)\nPaís: Portugal\nNUT III: PT200\nLocalidade: Freguesia de Povoação\nDistrito: Região Autónoma dos Açores\nConcelho: Povoação\nFreguesia: Freguesia de Povoação\n\n10 - PRAZO DE EXECUÇÃO DO CONTRATO\nPrazo de execução do contrato: 270 DIAS\nPrevisão de renovações: Não\n\n11 - FUNDOS EU\nTêm fundos EU? Não\n\n12 - DOCUMENTOS DE HABILITAÇÃO\nHabilitação para o exercício da atividade profissional: Sim\nTipo: Alvará\nDescrição: Alvará contendo as habilitações adequadas e necessárias à execução da obra a realizar, designadamente:\ni.a 1ª Subcategoria (Estruturas e elementos de betão) da 1ª Categoria, a qual tem de ser de classe que cubra o valor global da proposta, e integrar-se na categoria em que o tipo de obra se enquadra;\nii.As seguintes subcategorias em classe correspondente ao valor destes trabalhos na sua proposta e integrar-se na categoria em que o tipo de obra se enquadra:\n1ª Categoria (Edifícios e Património Construído)\n2ª Subcategoria (Estruturas metálicas)\n4ª Subcategoria (Alvenarias, rebocos e assentamento de cantarias)\n5ª Subcategoria (Estuques, pinturas e outros revestimentos)\n6ª Subcategoria (Carpintarias)\n7ª Subcategoria (Trabalhos em perfis não estruturais)\n8ª Subcategoria (Canalizações e condutas em edifícios)\n4ª Categoria (Instalações Elétricas e Mecânicas)\n1ª Subcategoria (Instalações elétricas de utilização de baixa tensão com potência até 50 kVA)\n9ª Subcategoria (Infraestruturas de telecomunicações)\n14ª Subcategoria (Redes e ramais de distribuição de gás, instalações e aparelhos a gás)\n5ª Categoria (Outros Trabalhos)\n1ª Subcategoria (Demolições)\n11ª Subcategoria (Impermeabilizações e isolamentos)\n\n13 - CONDIÇÕES DE APRESENTAÇÃO\nPlataforma eletrónica utilizada pela entidade adjudicante: ACIN\nURL para Apresentação: https://www.acingov.pt\nAdmissibilidade da apresentação de propostas variantes: Não autorizado\nPrazo para apresentação das propostas: 22-10-2025 23:59\nPrazo durante o qual os concorrentes são obrigados a manter as respetivas propostas: 180 dias a contar do termo do prazo para a apresentação das propostas\nIndicação de Subcontratação na Proposta: A parte do contrato que o proponente tenciona subcontratar\n\n14 - PRESTAÇÃO DE CAUÇÃO\nPrestação de caução: Sim\nPercentagem: 2%\nDescrição da Garantia Exigida: O valor da caução é de 2.00% do preço contratual.\n\n15 - FORNECIMENTO DAS PEÇAS DO CONCURSO, APRESENTAÇÃO DE PEDIDOS DE PARTICIPAÇÃO E APRESENTAÇÃO DAS PROPOSTAS\nLink para acesso às peças do concurso (URL): https://www.acingov.pt/acingovprod/2/zonaPublica/zona_publica_c/donwloadProcedurePiece/OTc4Nzky\n\n20 - OUTROS REQUISITOS\nInformação sobre contratos reservados. Aplica-se a contratos reservados (54º-A)? Não\n\n21 - CRITÉRIO DE ADJUDICAÇÃO\nMultifator: Sim\nFator: \nNome: Outros\nOutro Nome: K1 - Preço - 60%\nPonderação: 60%\nSubfatores: Não\nFator: \nNome: Outros\nOutro Nome: K2  Qualidade Técnica da Proposta  40%\nPonderação: 40%\nSubfatores: Não\n\n24 - CONDIÇÕES DO CONTRATO\nFaturação Eletrónica: Permitido\nObrigação de Subcontratação:\nCódigo da Obrigação de Subcontratação: O contratante tem de indicar qualquer mudança de subcontratantes durante a execução do contrato.\n\n25 - COMPRA PÚBLICA ESTRATÉGICA\nCompra Pública Estratégica: Inexistência de contratação pública estratégica\n\n26 - INFORMAÇÕES ADICIONAIS\nContrato adequado para PME: Não\nCobertura ACP (Acordo dos Contratos Públicos da Organização Mundial do Comércio): Não\n\n27 - IDENTIFICAÇÃO E CONTACTOS DO ÓRGÃO DE RECURSOS ADMINISTRATIVOS\nDesignação: Secretaria Regional da Juventude, Habitação e Emprego\nEndereço: Rua Dr. Bruno Tavares Carreiro s/n\nCódigo postal: 9500-119\nLocalidade: Ponta Delgada\nTelefone: 296309800\nFax: \nEndereço eletrónico: srjhe@azores.gov.pt\nPrazo de interposição do recurso: 10 dias\n\n28 - IDENTIFICAÇÃO DO(S) AUTOR(ES) DE ANÚNCIO\nNome: Márcio Patricio Medeiros Almeida\nCargo: Técnico Superior\n419561058",
    "nipc": "600087549",
    "distrito": "Região Autónoma dos Açores",
    "concelho": "Todos",
    "freguesia": "Todas",
    "site": "https://portal.azores.gov.pt/web/srjhe",
    "email": "srjhe@azores.gov.pt",
    "designacao_contrato": "EMPREITADA DE REABILITAÇÃO DE MORADIA NA ESTRADA MUNICIPAL - LOMBA DO POMAR, 12, FREGUESIA DA POVOAÇÃO, CONCELHO DA POVOAÇÃO, ILHA DE SÃO MIGUEL",
    "descricao": "EMPREITADA DE REABILITAÇÃO DE MORADIA NA ESTRADA MUNICIPAL - LOMBA DO POMAR, 12, FREGUESIA DA POVOAÇÃO, CONCELHO DA POVOAÇÃO, ILHA DE SÃO MIGUEL",
    "preco_base": "290.000,00 EUR",
    "prazo_execucao": "270 DIAS",
    "prazo_apresentacao_propostas": "22-10-2025 23:59",
    "fundos_eu": "Não",
    "plataforma_eletronica": "ACIN",
    "url_procedimento": "https://www.acingov.pt",
    "autor_nome": "Márcio Patricio Medeiros Almeida",
    "autor_cargo": "Técnico Superior"
  },
  {
    "numero_procedimento": "N/A",
    "entidade": "Município de Valença",
    "link": "https://diariodarepublica.pt/dr/detalhe/contrato-publico/25012-936007170",
    "detalhes_completos": "1 - IDENTIFICAÇÃO E CONTACTOS DA ENTIDADE ADJUDICANTE\nDesignação da entidade adjudicante: Município de Valença\nNIPC: 506728897\nEndereço: Pç. Da República, Valença\nCódigo postal: 4930-702\nLocalidade: Valença\nPaís: Portugal\nNUT III: PT111\nDistrito: Viana do Castelo\nConcelho: Valença\nFreguesia: Todas\nTelefone: 251809500\nFax: 251809519\nEndereço da Entidade (URL): www.cm-valenca.pt\nEndereço Eletrónico: geral@cm-valenca.pt\neDelivery Gateway (URL): https://community.vortal.biz/public/\nFunção da Organização: Adquirente\nNorma jurídica da Entidade Adjudicante: Autoridade local\nÁrea de atividade da Autoridade Adjudicante: Serviços públicos das administrações públicas\n\n2 - JORNAL OFICIAL DA UNIÃO EUROPEIA\nO procedimento a que este anúncio diz respeito também é publicitado no Jornal Oficial da União Europeia? Não\n\n3 - AVISO\nModelo de Anúncio: Concurso público\nData de Envio do Anúncio: 22-09-2025\n\n5 - PROCESSO\nTipo de Procedimento: Concurso público\nPreço base do procedimento: Sim\nValor do preço base do procedimento: 90.631,22 EUR\nProcedimento com lotes? Não\n\n6 - OBJETO DO CONTRATO\nNúmero de referência interna: CP-ABS-12/2025\nDesignação do contrato: TRATOR FLORESTAL E EQUIPAMENTO COMPLEMENTAR PARA AFETAÇÃO AO SERVIÇO MUNICIPAL DE PROTEÇÃO CIVIL E FLORESTAS\nDescrição: TRATOR FLORESTAL E EQUIPAMENTO COMPLEMENTAR PARA AFETAÇÃO AO SERVIÇO MUNICIPAL DE PROTEÇÃO CIVIL E FLORESTAS\nTipo de Contrato Principal: Aquisição de Bens Móveis\nTipo de Contrato: Aquisição de Bens Móveis\nClassificação CPV (Vocabulário Comum para os Contratos Públicos)\nObjeto principal\nVocabulário Principal: 16700000\nPreço base s/IVA: 90.631,22 EUR\n\n7 - INDICAÇÕES ADICIONAIS\nO contrato envolve aquisição conjunta (satisfação de várias entidades)? Não\nO contrato é adjudicado por uma central de compras? Não\n\n8 - TÉCNICAS\nO concurso destina-se à celebração de um acordo-quadro? Inexistência de acordo-quadro\nÉ utilizado um leilão eletrónico? Não\nÉ adotada uma fase de negociação? Não\nSistema de Aquisição Dinâmico: Inexistência de sistema de aquisição dinâmico\n\n9 - LOCAL DA EXECUÇÃO DO CONTRATO\nLOCAL DA EXECUÇÃO DO CONTRATO (PROCEDIMENTO)\nPaís: Portugal\nNUT III: PT111\nLocalidade: Viana do Castelo\nDistrito: Viana do Castelo\nConcelho: Valença\nFreguesia: Todas\n\n10 - PRAZO DE EXECUÇÃO DO CONTRATO\nPrazo de execução do contrato: 80 DIAS\nPrevisão de renovações: Não\n\n11 - FUNDOS EU\nTêm fundos EU? Sim\n\n12 - DOCUMENTOS DE HABILITAÇÃO\nHabilitação para o exercício da atividade profissional: Sim\nTipo: Outros\nDescrição - Outros: Os previstos no ponto 28 do PC\nDescrição: Os previstos no ponto 28 do PC\n\n13 - CONDIÇÕES DE APRESENTAÇÃO\nPlataforma eletrónica utilizada pela entidade adjudicante: VORTAL\nURL para Apresentação: https://community.vortal.biz/public/\nAdmissibilidade da apresentação de propostas variantes: Não autorizado\nPrazo para apresentação das propostas: 29-09-2025 17:00\nPrazo durante o qual os concorrentes são obrigados a manter as respetivas propostas: 66 dias a contar do termo do prazo para a apresentação das propostas\nIndicação de Subcontratação na Proposta: Inexistência de indicação de subcontratação\n\n14 - PRESTAÇÃO DE CAUÇÃO\nPrestação de caução: Não\n\n15 - FORNECIMENTO DAS PEÇAS DO CONCURSO, APRESENTAÇÃO DE PEDIDOS DE PARTICIPAÇÃO E APRESENTAÇÃO DAS PROPOSTAS\nLink para acesso às peças do concurso (URL): https://community.vortal.biz/Public/public-tender-documents/dUoyVWR4NStpeXhhNWhjVEdxbDRsdXIzdDdFeTJjWWFqTlRhUzVzSWZNTEptSHpmZDdwSTI1ckEyemljTmtjdmRSaEFMa1lTT3RHc0Fic3Y3UmxLOWc9PW1XTyVk\n\n20 - OUTROS REQUISITOS\nInformação sobre contratos reservados. Aplica-se a contratos reservados (54º-A)? Não\n\n21 - CRITÉRIO DE ADJUDICAÇÃO\nMultifator: Não\nMonofator:\nNome: Preço\n\n24 - CONDIÇÕES DO CONTRATO\nFaturação Eletrónica: Permitido\nObrigação de Subcontratação:\nCódigo da Obrigação de Subcontratação: Não é aplicável nenhuma obrigação de subcontratação.\n\n25 - COMPRA PÚBLICA ESTRATÉGICA\nCompra Pública Estratégica: Inexistência de contratação pública estratégica\n\n26 - INFORMAÇÕES ADICIONAIS\nContrato adequado para PME: Sim\nCobertura ACP (Acordo dos Contratos Públicos da Organização Mundial do Comércio): Não\n\n27 - IDENTIFICAÇÃO E CONTACTOS DO ÓRGÃO DE RECURSOS ADMINISTRATIVOS\nDesignação: José Manuel Vaz Carpinteira\nEndereço: Praça da Republica nº702\nCódigo postal: 4930-702\nLocalidade: Valença\nTelefone: +351 251809500\nFax: +351 251809518\nEndereço eletrónico: aprovisionamento@cm-valenca.pt\n\n28 - IDENTIFICAÇÃO DO(S) AUTOR(ES) DE ANÚNCIO\nNome: José Manuel Vaz Carpinteira\nCargo: Presidente CM\n419564322",
    "nipc": "506728897",
    "distrito": "Viana do Castelo",
    "concelho": "Valença",
    "freguesia": "Todas",
    "site": "www.cm-valenca.pt",
    "email": "geral@cm-valenca.pt",
    "designacao_contrato": "TRATOR FLORESTAL E EQUIPAMENTO COMPLEMENTAR PARA AFETAÇÃO AO SERVIÇO MUNICIPAL DE PROTEÇÃO CIVIL E FLORESTAS",
    "descricao": "TRATOR FLORESTAL E EQUIPAMENTO COMPLEMENTAR PARA AFETAÇÃO AO SERVIÇO MUNICIPAL DE PROTEÇÃO CIVIL E FLORESTAS",
    "preco_base": "90.631,22 EUR",
    "prazo_execucao": "80 DIAS",
    "prazo_apresentacao_propostas": "29-09-2025 17:00",
    "fundos_eu": "Sim",
    "plataforma_eletronica": "VORTAL",
    "url_procedimento": "https://community.vortal.biz/public/",
    "autor_nome": "José Manuel Vaz Carpinteira",
    "autor_cargo": "Presidente CM"
  },
  {
    "numero_procedimento": "N/A",
    "entidade": "Centro Paroquial de Bem Estra Social de Valverde",
    "link": "https://diariodarepublica.pt/dr/detalhe/contrato-publico/25013-936007171",
    "detalhes_completos": "1 - IDENTIFICAÇÃO E CONTACTOS DA ENTIDADE ADJUDICANTE\nDesignação da entidade adjudicante: Centro Paroquial de Bem Estra Social de Valverde\nNIPC: 500875022\nEndereço: Rua do Adro n. 2\nCódigo postal: 6230-804\nLocalidade:  Castelo Branco \nPaís: Portugal\nNUT III: PT16J\nDistrito: Castelo Branco\nConcelho: Fundão\nFreguesia: Todas\nTelefone: 275753390\nFax: 275753390\nEndereço Eletrónico: centro.paroquial.valverde@gmail.com\neDelivery Gateway (URL): https://community.vortal.biz/public/\nFunção da Organização: Adquirente\nNorma jurídica da Entidade Adjudicante: Organismo de direito público\nÁrea de atividade da Autoridade Adjudicante: Proteção social\n\n2 - JORNAL OFICIAL DA UNIÃO EUROPEIA\nO procedimento a que este anúncio diz respeito também é publicitado no Jornal Oficial da União Europeia? Não\n\n3 - AVISO\nModelo de Anúncio: Concurso público\nData de Envio do Anúncio: 22-09-2025\n\n5 - PROCESSO\nTipo de Procedimento: Concurso público\nPreço base do procedimento: Sim\nValor do preço base do procedimento: 249.755,44 EUR\nProcedimento com lotes? Não\n\n6 - OBJETO DO CONTRATO\nNúmero de referência interna: 2025/06\nDesignação do contrato: Apoio à renovação e aumento do desempenho energético dos edifícios de Serviços\nDescrição: Apoio à renovação e aumento do desempenho energético dos edifícios de Serviços\nTipo de Contrato Principal: Empreitada de Obras Públicas\nTipo de Contrato: Empreitada de Obras Públicas\nClassificação CPV (Vocabulário Comum para os Contratos Públicos)\nObjeto principal\nVocabulário Principal: 45200000\nPreço base s/IVA: 249.755,44 EUR\n\n7 - INDICAÇÕES ADICIONAIS\nO contrato envolve aquisição conjunta (satisfação de várias entidades)? Não\nO contrato é adjudicado por uma central de compras? Não\n\n8 - TÉCNICAS\nO concurso destina-se à celebração de um acordo-quadro? Inexistência de acordo-quadro\nÉ utilizado um leilão eletrónico? Não\nÉ adotada uma fase de negociação? Não\nSistema de Aquisição Dinâmico: Inexistência de sistema de aquisição dinâmico\n\n9 - LOCAL DA EXECUÇÃO DO CONTRATO\nLOCAL DA EXECUÇÃO DO CONTRATO (PROCEDIMENTO)\nPaís: Portugal\nNUT III: PT16J\nLocalidade: Castelo Branco\nDistrito: Castelo Branco\nConcelho: Fundão\nFreguesia: União das Freguesias de Fundão, Valverde, Donas, Aldeia de Joanes e Aldeia Nova do Cabo\n\n10 - PRAZO DE EXECUÇÃO DO CONTRATO\nPrazo de execução do contrato: 150 DIAS\nPrevisão de renovações: Não\n\n11 - FUNDOS EU\nTêm fundos EU? Não\n\n12 - DOCUMENTOS DE HABILITAÇÃO\nHabilitação para o exercício da atividade profissional: Sim\nTipo: Alvará\nDescrição: Alvará emitido pelo IMPIC \n\n13 - CONDIÇÕES DE APRESENTAÇÃO\nPlataforma eletrónica utilizada pela entidade adjudicante: VORTAL\nURL para Apresentação: https://community.vortal.biz/public/\nAdmissibilidade da apresentação de propostas variantes: Não autorizado\nPrazo para apresentação das propostas: 08-10-2025 17:00\nPrazo durante o qual os concorrentes são obrigados a manter as respetivas propostas: 66 dias a contar do termo do prazo para a apresentação das propostas\nIndicação de Subcontratação na Proposta: Inexistência de indicação de subcontratação\n\n14 - PRESTAÇÃO DE CAUÇÃO\nPrestação de caução: Sim\nPercentagem: 5%\nDescrição da Garantia Exigida: nos termos do programa de concurso \n\n15 - FORNECIMENTO DAS PEÇAS DO CONCURSO, APRESENTAÇÃO DE PEDIDOS DE PARTICIPAÇÃO E APRESENTAÇÃO DAS PROPOSTAS\nLink para acesso às peças do concurso (URL): https://community.vortal.biz/Public/public-tender-documents/cForRWp1YkJKa1N0VitJMzkrUk45c1FTa0lqRUhHWThSYSt0TGdEQm54bkFidWdGVkZSZW9KbnZmUFNHanhBbVIrbmZtNms3OXlqR2VmdlZxWUJVMHc9PWVsam5U\n\n20 - OUTROS REQUISITOS\nInformação sobre contratos reservados. Aplica-se a contratos reservados (54º-A)? Não\n\n21 - CRITÉRIO DE ADJUDICAÇÃO\nMultifator: Não\nMonofator:\nNome: Preço\n\n24 - CONDIÇÕES DO CONTRATO\nFaturação Eletrónica: Permitido\nObrigação de Subcontratação:\nCódigo da Obrigação de Subcontratação: Não é aplicável nenhuma obrigação de subcontratação.\n\n25 - COMPRA PÚBLICA ESTRATÉGICA\nCompra Pública Estratégica: Inexistência de contratação pública estratégica\n\n26 - INFORMAÇÕES ADICIONAIS\nContrato adequado para PME: Sim\nCobertura ACP (Acordo dos Contratos Públicos da Organização Mundial do Comércio): Não\n\n27 - IDENTIFICAÇÃO E CONTACTOS DO ÓRGÃO DE RECURSOS ADMINISTRATIVOS\nDesignação: Centro Paroquial de Bem-Estar Social de Valverde\nEndereço: Rua do Adro n. 2\nCódigo postal: 6230-804\nLocalidade: Fundão\nTelefone: +351 275753390\nFax: +351 275753392\nEndereço eletrónico: geral@centroparoquialvalverde.pt\n\n28 - IDENTIFICAÇÃO DO(S) AUTOR(ES) DE ANÚNCIO\nNome: Maria de Lurdes Liberato\nCargo: Vice Presidente da Direcção\n419559503",
    "nipc": "500875022",
    "distrito": "Castelo Branco",
    "concelho": "Fundão",
    "freguesia": "Todas",
    "site": null,
    "email": "centro.paroquial.valverde@gmail.com",
    "designacao_contrato": "Apoio à renovação e aumento do desempenho energético dos edifícios de Serviços",
    "descricao": "Apoio à renovação e aumento do desempenho energético dos edifícios de Serviços",
    "preco_base": "249.755,44 EUR",
    "prazo_execucao": "150 DIAS",
    "prazo_apresentacao_propostas": "08-10-2025 17:00",
    "fundos_eu": "Não",
    "plataforma_eletronica": "VORTAL",
    "url_procedimento": "https://community.vortal.biz/public/",
    "autor_nome": "Maria de Lurdes Liberato",
    "autor_cargo": "Vice Presidente da Direcção"
  },
  {
    "numero_procedimento": "N/A",
    "entidade": "Universidade de Lisboa",
    "link": "https://diariodarepublica.pt/dr/detalhe/contrato-publico/25016-936007172",
    "detalhes_completos": "1 - IDENTIFICAÇÃO E CONTACTOS DA ENTIDADE ADJUDICANTE\nDesignação da entidade adjudicante: Universidade de Lisboa\nNIPC: 510739024\nServiço/Órgão/Pessoa de contacto: Vice-Reitor\nEndereço: Alameda da Universidade, Cidade Universitária\nCódigo postal: 1649-004\nLocalidade: Lisboa\nPaís: Portugal\nNUT III: PT170\nDistrito: Lisboa\nConcelho: Lisboa\nFreguesia: Freguesia de Alvalade - Lisboa\nTelefone: 210113400\nFax: 210113402\nEndereço da Entidade (URL): www.ulisboa.pt\nEndereço Eletrónico: geral.aca@reitoria.ulisboa.pt\neDelivery Gateway (URL): https://www.acingov.pt\nFunção da Organização: Adquirente\nSubfunção da Organização: Organização cujo orçamento é utilizado para pagar o contrato; Organização que executa o pagamento; Organização que fornece informações adicionais sobre o processo de adjudicação; Organização responsável pelo tratamento das propostas; Organização que recebe as propostas; Organização que recebe pedidos de participação; Organização que assina o contrato\nNorma jurídica da Entidade Adjudicante: Organismo de direito público\nÁrea de atividade da Autoridade Adjudicante: Educação\n\n2 - JORNAL OFICIAL DA UNIÃO EUROPEIA\nO procedimento a que este anúncio diz respeito também é publicitado no Jornal Oficial da União Europeia? Não\n\n3 - AVISO\nModelo de Anúncio: Concurso público\nData de Envio do Anúncio: 22-09-2025\n\n5 - PROCESSO\nTipo de Procedimento: Concurso público\nPreço base do procedimento: Sim\nValor do preço base do procedimento: 121.600,00 EUR\nProcedimento com lotes? Não\n\n6 - OBJETO DO CONTRATO\nNúmero de referência interna: 2500000641_HM_184NPP2025\nDesignação do contrato: Aquisição de serviços audiovisuais ao abrigo do projeto PULSARA e Promoção da Saúde Mental\nDescrição: Aquisição de serviços audiovisuais ao abrigo do projeto PULSARA e Promoção da Saúde Mental\nTipo de Contrato Principal: Aquisição de Serviços\nTipo de Contrato: Aquisição de Serviços\nClassificação CPV (Vocabulário Comum para os Contratos Públicos)\nObjeto principal\nVocabulário Principal: 92110000\nPreço base s/IVA: 121.600,00 EUR\n\n7 - INDICAÇÕES ADICIONAIS\nO contrato envolve aquisição conjunta (satisfação de várias entidades)? Não\nO contrato é adjudicado por uma central de compras? Não\n\n8 - TÉCNICAS\nO concurso destina-se à celebração de um acordo-quadro? Inexistência de acordo-quadro\nÉ utilizado um leilão eletrónico? Não\nÉ adotada uma fase de negociação? Não\nSistema de Aquisição Dinâmico: Inexistência de sistema de aquisição dinâmico\n\n9 - LOCAL DA EXECUÇÃO DO CONTRATO\nLOCAL DA EXECUÇÃO DO CONTRATO (PROCEDIMENTO)\nPaís: Portugal\nNUT III: PT170\nLocalidade: Freguesia de Alvalade - Lisboa\nDistrito: Lisboa\nConcelho: Lisboa\nFreguesia: Freguesia de Alvalade - Lisboa\n\n10 - PRAZO DE EXECUÇÃO DO CONTRATO\nPrazo de execução do contrato: 258 DIAS\nPrevisão de renovações: Não\n\n11 - FUNDOS EU\nTêm fundos EU? Sim\n\n12 - DOCUMENTOS DE HABILITAÇÃO\nHabilitação para o exercício da atividade profissional: Não\n\n13 - CONDIÇÕES DE APRESENTAÇÃO\nPlataforma eletrónica utilizada pela entidade adjudicante: ACIN\nURL para Apresentação: https://www.acingov.pt\nAdmissibilidade da apresentação de propostas variantes: Não autorizado\nPrazo para apresentação das propostas: 05-10-2025 23:59\nPrazo durante o qual os concorrentes são obrigados a manter as respetivas propostas: 66 dias a contar do termo do prazo para a apresentação das propostas\nIndicação de Subcontratação na Proposta: Inexistência de indicação de subcontratação\n\n14 - PRESTAÇÃO DE CAUÇÃO\nPrestação de caução: Não\n\n15 - FORNECIMENTO DAS PEÇAS DO CONCURSO, APRESENTAÇÃO DE PEDIDOS DE PARTICIPAÇÃO E APRESENTAÇÃO DAS PROPOSTAS\nLink para acesso às peças do concurso (URL): https://www.acingov.pt/acingovprod/2/zonaPublica/zona_publica_c/donwloadProcedurePiece/OTc4MTE4\n\n20 - OUTROS REQUISITOS\nInformação sobre contratos reservados. Aplica-se a contratos reservados (54º-A)? Não\n\n21 - CRITÉRIO DE ADJUDICAÇÃO\nMultifator: Não\nMonofator:\nNome: Outros\nOutro nome: Fator Preço\n\n24 - CONDIÇÕES DO CONTRATO\nFaturação Eletrónica: Permitido\nObrigação de Subcontratação:\nCódigo da Obrigação de Subcontratação: Não é aplicável nenhuma obrigação de subcontratação.\n\n25 - COMPRA PÚBLICA ESTRATÉGICA\nCompra Pública Estratégica: Inexistência de contratação pública estratégica\n\n26 - INFORMAÇÕES ADICIONAIS\nContrato adequado para PME: Não\nCobertura ACP (Acordo dos Contratos Públicos da Organização Mundial do Comércio): Não\n\n27 - IDENTIFICAÇÃO E CONTACTOS DO ÓRGÃO DE RECURSOS ADMINISTRATIVOS\nDesignação: Serviço Responsável\nEndereço: Alameda da universidade, Cidade Universitária\nCódigo postal: 1649-004\nLocalidade: Lisboa\nTelefone: 210113400\nFax: \nEndereço eletrónico: geral.aca@reitoria.ulisboa.pt\n\n28 - IDENTIFICAÇÃO DO(S) AUTOR(ES) DE ANÚNCIO\nNome: Catarina Faquinéu\nCargo: Técnica Superior\n419563367",
    "nipc": "510739024",
    "distrito": "Lisboa",
    "concelho": "Lisboa",
    "freguesia": "Freguesia de Alvalade - Lisboa",
    "site": "www.ulisboa.pt",
    "email": "geral.aca@reitoria.ulisboa.pt",
    "designacao_contrato": "Aquisição de serviços audiovisuais ao abrigo do projeto PULSARA e Promoção da Saúde Mental",
    "descricao": "Aquisição de serviços audiovisuais ao abrigo do projeto PULSARA e Promoção da Saúde Mental",
    "preco_base": "121.600,00 EUR",
    "prazo_execucao": "258 DIAS",
    "prazo_apresentacao_propostas": "05-10-2025 23:59",
    "fundos_eu": "Sim",
    "plataforma_eletronica": "ACIN",
    "url_procedimento": "https://www.acingov.pt",
    "autor_nome": "Catarina Faquinéu",
    "autor_cargo": "Técnica Superior"
  },
  {
    "numero_procedimento": "N/A",
    "entidade": "Rádio e Televisão de Portugal, SA",
    "link": "https://diariodarepublica.pt/dr/detalhe/contrato-publico/24994-936194624",
    "detalhes_completos": "1 - IDENTIFICAÇÃO E CONTACTOS DA ENTIDADE ADJUDICANTE\nDesignação da entidade adjudicante: Rádio e Televisão de Portugal, SA\nNIPC: 500225680\nEndereço: Avenida Marechal Gomes da Costa, 37\nCódigo postal: 1849-030\nLocalidade: Lisboa\nPaís: Portugal\nNUT III: PT170\nDistrito: Lisboa\nConcelho: Lisboa\nFreguesia: Todas\nTelefone: 217947000\nFax: 217947570\nEndereço da Entidade (URL): www.rpt.pt\nEndereço Eletrónico: dir.comercial@rtp.pt\neDelivery Gateway (URL): https://community.vortal.biz/public/\nFunção da Organização: Adquirente\nNorma jurídica da Entidade Adjudicante: Autoridade da administração central\nÁrea de atividade da Autoridade Adjudicante: Serviços públicos das administrações públicas\n\n2 - JORNAL OFICIAL DA UNIÃO EUROPEIA\nO procedimento a que este anúncio diz respeito também é publicitado no Jornal Oficial da União Europeia? Não\n\n3 - AVISO\nModelo de Anúncio: Concurso limitado por prévia qualificação\nData de Envio do Anúncio: 22-09-2025\n\n5 - PROCESSO\nTipo de Procedimento: Concurso limitado por prévia qualificação\nPreço base do procedimento: Sim\nValor do preço base do procedimento: 78.033,00 EUR\nProcedimento com lotes? Não\n\n6 - OBJETO DO CONTRATO\nNúmero de referência interna: RTP-CP 17/2025-CF\nDesignação do contrato: CP 17/2025 – Aquisição de solução storage central para sistema de emissão ITX GV\nDescrição: CP 17/2025 – Aquisição de solução storage central para sistema de emissão ITX GV\nTipo de Contrato Principal: Aquisição de Bens Móveis\nTipo de Contrato: Aquisição de Bens Móveis\nClassificação CPV (Vocabulário Comum para os Contratos Públicos)\nObjeto principal\nVocabulário Principal: 48900000\nPreço base s/IVA: 78.033,00 EUR\n\n7 - INDICAÇÕES ADICIONAIS\nO contrato envolve aquisição conjunta (satisfação de várias entidades)? Não\nO contrato é adjudicado por uma central de compras? Não\n\n8 - TÉCNICAS\nO concurso destina-se à celebração de um acordo-quadro? Inexistência de acordo-quadro\nÉ utilizado um leilão eletrónico? Não\nSistema de Aquisição Dinâmico: Inexistência de sistema de aquisição dinâmico\n\n9 - LOCAL DA EXECUÇÃO DO CONTRATO\nLOCAL DA EXECUÇÃO DO CONTRATO (PROCEDIMENTO)\nPaís: Portugal\nNUT III: PT170\nLocalidade: Lisboa\nDistrito: Lisboa\nConcelho: Lisboa\nFreguesia: Todas\n\n10 - PRAZO DE EXECUÇÃO DO CONTRATO\nPrazo de execução do contrato: 35 DIAS\nPrevisão de renovações: Não\n\n11 - FUNDOS EU\nTêm fundos EU? Não\n\n12 - DOCUMENTOS DE HABILITAÇÃO\nHabilitação para o exercício da atividade profissional: Não\n\n13 - CONDIÇÕES DE APRESENTAÇÃO\nPlataforma eletrónica utilizada pela entidade adjudicante: VORTAL\nURL para Apresentação: https://community.vortal.biz/public/\nAdmissibilidade da apresentação de propostas variantes: Não autorizado\nPrazo para apresentação das candidaturas: 06-10-2025 18:00\nRequisitos mínimos \nRequisitos mínimos de capacidade técnica: Conforme as peças do procedimento\nRequisitos mínimos de capacidade financeira: Conforme as peças do procedimento\nPrazo durante o qual os concorrentes são obrigados a manter as respetivas propostas: 44 dias a contar do termo do prazo para a apresentação das propostas\nIndicação de Subcontratação na Proposta: Inexistência de indicação de subcontratação\n\n14 - PRESTAÇÃO DE CAUÇÃO\nPrestação de caução: Não\n\n15 - FORNECIMENTO DAS PEÇAS DO CONCURSO, APRESENTAÇÃO DE PEDIDOS DE PARTICIPAÇÃO E APRESENTAÇÃO DAS PROPOSTAS\nLink para acesso às peças do concurso (URL): https://community.vortal.biz/Public/public-tender-documents/OXFadThjcjZWVUlWanlBc3pqVkdHY015VFFMNXdkaWNBeFZBR0grd2NmK0o1RmwrYTdBUzJ4WjJvOUdBYzlSeThBUnpyQjMrM1luYWt5Sno3SjdLNnc9PTQzJG0h\n\n20 - OUTROS REQUISITOS\nInformação sobre contratos reservados. Aplica-se a contratos reservados (54º-A)? Não\n\n21 - CRITÉRIO DE ADJUDICAÇÃO\nMultifator: Não\nMonofator:\nNome: Outros\nOutro nome: Preço\n\n24 - CONDIÇÕES DO CONTRATO\nFaturação Eletrónica: Permitido\nObrigação de Subcontratação:\nCódigo da Obrigação de Subcontratação: Não é aplicável nenhuma obrigação de subcontratação.\n\n25 - COMPRA PÚBLICA ESTRATÉGICA\nCompra Pública Estratégica: Inexistência de contratação pública estratégica\n\n26 - INFORMAÇÕES ADICIONAIS\nContrato adequado para PME: Sim\nCobertura ACP (Acordo dos Contratos Públicos da Organização Mundial do Comércio): Não\n\n27 - IDENTIFICAÇÃO E CONTACTOS DO ÓRGÃO DE RECURSOS ADMINISTRATIVOS\nDesignação: Conselho de Administração da RTP\nEndereço: Av. Marechal Gomes da Costa, 37\nCódigo postal: 1849-030\nLocalidade: Lisboa\nTelefone: +351 217947000\nFax: +351 217947570\nEndereço eletrónico: compras@rtp.pt\n\n28 - IDENTIFICAÇÃO DO(S) AUTOR(ES) DE ANÚNCIO\nNome: Pedro Ries\nCargo: Diretor da Gestão do Património\n419560645",
    "nipc": "500225680",
    "distrito": "Lisboa",
    "concelho": "Lisboa",
    "freguesia": "Todas",
    "site": "www.rpt.pt",
    "email": "dir.comercial@rtp.pt",
    "designacao_contrato": "CP 17/2025 – Aquisição de solução storage central para sistema de emissão ITX GV",
    "descricao": "CP 17/2025 – Aquisição de solução storage central para sistema de emissão ITX GV",
    "preco_base": "78.033,00 EUR",
    "prazo_execucao": "35 DIAS",
    "prazo_apresentacao_propostas": null,
    "fundos_eu": "Não",
    "plataforma_eletronica": "VORTAL",
    "url_procedimento": "https://community.vortal.biz/public/",
    "autor_nome": "Pedro Ries",
    "autor_cargo": "Diretor da Gestão do Património"
  },
  {
    "numero_procedimento": "N/A",
    "entidade": "Comunidade Intermunicipal da Região de Aveiro",
    "link": "https://diariodarepublica.pt/dr/detalhe/contrato-publico/24995-936194625",
    "detalhes_completos": "1 - IDENTIFICAÇÃO E CONTACTOS DA ENTIDADE ADJUDICANTE\nDesignação da entidade adjudicante: Comunidade Intermunicipal da Região de Aveiro\nNIPC: 508771935\nServiço/Órgão/Pessoa de contacto: Conselho Intermunicipal da Comunidade Intermunicipal da Região de Aveiro\nEndereço: Rua do Carmo n.º 20\nCódigo postal: 3800-127\nLocalidade: Aveiro\nPaís: Portugal\nNUT III: PT16D\nDistrito: Aveiro\nConcelho: Aveiro\nFreguesia: Todas\nTelefone: 234377650\nFax: 234377659\nEndereço da Entidade (URL): http://www.regiaodeaveiro.pt\nEndereço Eletrónico: geral@regiaodeaveiro.pt\neDelivery Gateway (URL): https://www.acingov.pt\nFunção da Organização: Adquirente\nNorma jurídica da Entidade Adjudicante: Organismo de direito público\nÁrea de atividade da Autoridade Adjudicante: Serviços públicos das administrações públicas\n\n2 - JORNAL OFICIAL DA UNIÃO EUROPEIA\nO procedimento a que este anúncio diz respeito também é publicitado no Jornal Oficial da União Europeia? Não\n\n3 - AVISO\nModelo de Anúncio: Concurso público\nData de Envio do Anúncio: 22-09-2025\n\n5 - PROCESSO\nTipo de Procedimento: Concurso público\nPreço base do procedimento: Sim\nValor do preço base do procedimento: 2.900.000,00 EUR\nProcedimento com lotes? Não\n\n6 - OBJETO DO CONTRATO\nNúmero de referência interna: 2025.300.10.001.003\nDesignação do contrato: Empreitada de Ampliação do Edifício da Sede da Comunidade Intermunicipal da Região de Aveiro\nDescrição: Empreitada de Ampliação do Edifício da Sede da Comunidade Intermunicipal da Região de Aveiro\nTipo de Contrato Principal: Empreitada de Obras Públicas\nTipo de Contrato: Empreitada de Obras Públicas\nClassificação CPV (Vocabulário Comum para os Contratos Públicos)\nObjeto principal\nVocabulário Principal: 45220000\nPreço base s/IVA: 2.900.000,00 EUR\n\n7 - INDICAÇÕES ADICIONAIS\nO contrato envolve aquisição conjunta (satisfação de várias entidades)? Não\nO contrato é adjudicado por uma central de compras? Não\n\n8 - TÉCNICAS\nO concurso destina-se à celebração de um acordo-quadro? Inexistência de acordo-quadro\nÉ utilizado um leilão eletrónico? Não\nÉ adotada uma fase de negociação? Não\nSistema de Aquisição Dinâmico: Inexistência de sistema de aquisição dinâmico\n\n9 - LOCAL DA EXECUÇÃO DO CONTRATO\nLOCAL DA EXECUÇÃO DO CONTRATO (PROCEDIMENTO)\nPaís: Portugal\nNUT III: PT16D\nLocalidade: Aveiro\nDistrito: Aveiro\nConcelho: Todos\nFreguesia: Todas\n\n10 - PRAZO DE EXECUÇÃO DO CONTRATO\nPrazo de execução do contrato: 20 MESES\nPrevisão de renovações: Não\n\n11 - FUNDOS EU\nTêm fundos EU? Não\n\n12 - DOCUMENTOS DE HABILITAÇÃO\nHabilitação para o exercício da atividade profissional: Sim\nTipo: Alvará\nDescrição: Alvará emitido pelo Instituto dos Mercados Públicos, do Imobiliário e da Construção, I.P., contendo as habilitações adequadas e necessárias à execução da obra a realizar, nomeadamente:\n 1.ª subcategoria (Estruturas e elementos de betão), 2.ª subcategoria (Estruturas Metálicas), 4.ª subcategoria (Alvenarias, rebocos e assentamento de cantarias), 5.ª subcategoria (Estuques pinturas e outros revestimentos), 6.ª subcategoria (Carpintarias), 8.º subcategoria (Canalizações e condutas em edifícios) da 1.ª categoria (Edifícios e património construído) em classe que cubra o valor total da proposta;\ne em classe correspondente aos respetivos trabalhos na:\n 1ª subcategoria (Instalações elétricas de utilização de baixa tensão com potência até 50 kVA), 5ª subcategoria (Redes e instalações elétricas de tensão de serviço acima de 30 kV), 9.ª subcategoria (Infraestruturas de telecomunicações); a 10ª subcategoria (Sistemas de extinção de incêndios, de segurança e deteção), 11.ª subcategoria (Instalações de elevação), 12.º subcategoria (Aquecimento, ventilação, ar condicionado e refrigeração) da 4ª categoria (Instalações elétricas e mecânicas);\n2.ª subcategoria (Movimento de terras) da 5.ª categoria (Outros trabalhos)\n\n13 - CONDIÇÕES DE APRESENTAÇÃO\nPlataforma eletrónica utilizada pela entidade adjudicante: ACIN\nURL para Apresentação: https://www.acingov.pt\nAdmissibilidade da apresentação de propostas variantes: Não autorizado\nPrazo para apresentação das propostas: 23-10-2025 23:59\nPrazo durante o qual os concorrentes são obrigados a manter as respetivas propostas: 180 dias a contar do termo do prazo para a apresentação das propostas\nIndicação de Subcontratação na Proposta: Inexistência de indicação de subcontratação\n\n14 - PRESTAÇÃO DE CAUÇÃO\nPrestação de caução: Sim\nPercentagem: 5%\nDescrição da Garantia Exigida: O valor da caução é de 5.00% do preço contratual.\n\n15 - FORNECIMENTO DAS PEÇAS DO CONCURSO, APRESENTAÇÃO DE PEDIDOS DE PARTICIPAÇÃO E APRESENTAÇÃO DAS PROPOSTAS\nLink para acesso às peças do concurso (URL): https://www.acingov.pt/acingovprod/2/zonaPublica/zona_publica_c/donwloadProcedurePiece/OTM1NDc2\n\n20 - OUTROS REQUISITOS\nInformação sobre contratos reservados. Aplica-se a contratos reservados (54º-A)? Não\n\n21 - CRITÉRIO DE ADJUDICAÇÃO\nMultifator: Não\nMonofator:\nNome: Outros\nOutro nome: Fator Preço\n\n24 - CONDIÇÕES DO CONTRATO\nFaturação Eletrónica: Permitido\nObrigação de Subcontratação:\nCódigo da Obrigação de Subcontratação: Não é aplicável nenhuma obrigação de subcontratação.\n\n25 - COMPRA PÚBLICA ESTRATÉGICA\nCompra Pública Estratégica: Inexistência de contratação pública estratégica\n\n26 - INFORMAÇÕES ADICIONAIS\nContrato adequado para PME: Não\nCobertura ACP (Acordo dos Contratos Públicos da Organização Mundial do Comércio): Não\n\n27 - IDENTIFICAÇÃO E CONTACTOS DO ÓRGÃO DE RECURSOS ADMINISTRATIVOS\nDesignação: Conselho Intermunicipal\nEndereço: Rua do Carmo n.º 20\nCódigo postal: 3800-127\nLocalidade: Aveiro\nTelefone: 234377650\nFax: \nEndereço eletrónico: geral@regiaodeaveiro.pt\nPrazo de interposição do recurso: 30 dias\n\n28 - IDENTIFICAÇÃO DO(S) AUTOR(ES) DE ANÚNCIO\nNome: Jorge Henrique Fernandes de Almeida\nCargo: O Presidente do Conselho Intermunicipal\n419562565",
    "nipc": "508771935",
    "distrito": "Aveiro",
    "concelho": "Aveiro",
    "freguesia": "Todas",
    "site": "http://www.regiaodeaveiro.pt",
    "email": "geral@regiaodeaveiro.pt",
    "designacao_contrato": "Empreitada de Ampliação do Edifício da Sede da Comunidade Intermunicipal da Região de Aveiro",
    "descricao": "Empreitada de Ampliação do Edifício da Sede da Comunidade Intermunicipal da Região de Aveiro",
    "preco_base": "2.900.000,00 EUR",
    "prazo_execucao": "20 MESES",
    "prazo_apresentacao_propostas": "23-10-2025 23:59",
    "fundos_eu": "Não",
    "plataforma_eletronica": "ACIN",
    "url_procedimento": "https://www.acingov.pt",
    "autor_nome": "Jorge Henrique Fernandes de Almeida",
    "autor_cargo": "O Presidente do Conselho Intermunicipal"
  },
  {
    "numero_procedimento": "N/A",
    "entidade": "Unidade Local de Saúde do Estuário do Tejo, E. P. E.",
    "link": "https://diariodarepublica.pt/dr/detalhe/contrato-publico/24996-936194626",
    "detalhes_completos": "1 - IDENTIFICAÇÃO E CONTACTOS DA ENTIDADE ADJUDICANTE\nDesignação da entidade adjudicante: Unidade Local de Saúde do Estuário do Tejo, E. P. E.\nNIPC: 516487493\nEndereço: Estrada Carlos Lima Costa, n.º2, Povos \nCódigo postal: 2600-009\nLocalidade: Lisboa\nPaís: Portugal\nNUT III: PT170\nDistrito: Lisboa\nConcelho: Vila Franca de Xira\nFreguesia: Freguesia de Vila Franca de Xira\nTelefone: 263006500\nEndereço da Entidade (URL): https://www.hospitalvilafrancadexira.pt\nEndereço Eletrónico: hvfxira@hvfx.min-saude.pt\neDelivery Gateway (URL): https://community.vortal.biz/public/\nFunção da Organização: Adquirente\nNorma jurídica da Entidade Adjudicante: Empresa pública\nÁrea de atividade da Autoridade Adjudicante: Saúde\n\n2 - JORNAL OFICIAL DA UNIÃO EUROPEIA\nO procedimento a que este anúncio diz respeito também é publicitado no Jornal Oficial da União Europeia? Não\n\n3 - AVISO\nModelo de Anúncio: Concurso público\nData de Envio do Anúncio: 22-09-2025\n\n5 - PROCESSO\nTipo de Procedimento: Concurso público\nPreço base do procedimento: Sim\nValor do preço base do procedimento: 159.600,00 EUR\nProcedimento com lotes? Não\n\n6 - OBJETO DO CONTRATO\nNúmero de referência interna: 05 / 00020696 / 2025\nDesignação do contrato: Aquisição Reagentes para Biologia Molecular com Cedência de Equipamento I\nDescrição: Aquisição Reagentes para Biologia Molecular com Cedência de Equipamento I\nTipo de Contrato Principal: Aquisição de Bens Móveis\nTipo de Contrato: Aquisição de Bens Móveis\nClassificação CPV (Vocabulário Comum para os Contratos Públicos)\nObjeto principal\nVocabulário Principal: 33600000\nPreço base s/IVA: 159.600,00 EUR\n\n7 - INDICAÇÕES ADICIONAIS\nO contrato envolve aquisição conjunta (satisfação de várias entidades)? Não\nO contrato é adjudicado por uma central de compras? Não\n\n8 - TÉCNICAS\nO concurso destina-se à celebração de um acordo-quadro? Inexistência de acordo-quadro\nÉ utilizado um leilão eletrónico? Não\nÉ adotada uma fase de negociação? Não\nSistema de Aquisição Dinâmico: Inexistência de sistema de aquisição dinâmico\n\n9 - LOCAL DA EXECUÇÃO DO CONTRATO\nLOCAL DA EXECUÇÃO DO CONTRATO (PROCEDIMENTO)\nPaís: Portugal\nNUT III: PT170\nLocalidade: Lisboa\nDistrito: Lisboa\nConcelho: Vila Franca de Xira\nFreguesia: Freguesia de Vila Franca de Xira\n\n10 - PRAZO DE EXECUÇÃO DO CONTRATO\nPrazo de execução do contrato: 24 MESES\nPrevisão de renovações: Não\n\n11 - FUNDOS EU\nTêm fundos EU? Não\n\n12 - DOCUMENTOS DE HABILITAÇÃO\nHabilitação para o exercício da atividade profissional: Não\n\n13 - CONDIÇÕES DE APRESENTAÇÃO\nPlataforma eletrónica utilizada pela entidade adjudicante: VORTAL\nURL para Apresentação: https://community.vortal.biz/public/\nAdmissibilidade da apresentação de propostas variantes: Não autorizado\nPrazo para apresentação das propostas: 02-10-2025 17:00\nPrazo durante o qual os concorrentes são obrigados a manter as respetivas propostas: 120 dias a contar do termo do prazo para a apresentação das propostas\nIndicação de Subcontratação na Proposta: Inexistência de indicação de subcontratação\n\n14 - PRESTAÇÃO DE CAUÇÃO\nPrestação de caução: Não\n\n15 - FORNECIMENTO DAS PEÇAS DO CONCURSO, APRESENTAÇÃO DE PEDIDOS DE PARTICIPAÇÃO E APRESENTAÇÃO DAS PROPOSTAS\nLink para acesso às peças do concurso (URL): https://community.vortal.biz/Public/public-tender-documents/OTBmQ01SWm9TcjJzVFp0akpnUE9rOWU3OGxMYXRlYmhhSjlTMHp1ZG9Da0RyVlRmT3BINGhXTkZubnhHOUdVZDcxUWdCSEVkcjFtOGkwK2MzWnhKQWc9PUM1VV9N\n\n20 - OUTROS REQUISITOS\nInformação sobre contratos reservados. Aplica-se a contratos reservados (54º-A)? Não\n\n21 - CRITÉRIO DE ADJUDICAÇÃO\nMultifator: Sim\nFator: \nNome: Preço\nPonderação: 50%\nSubfatores: Não\nFator: \nNome: Qualidade\nPonderação: 50%\nSubfatores: Não\n\n24 - CONDIÇÕES DO CONTRATO\nFaturação Eletrónica: Permitido\nObrigação de Subcontratação:\nCódigo da Obrigação de Subcontratação: Não é aplicável nenhuma obrigação de subcontratação.\n\n25 - COMPRA PÚBLICA ESTRATÉGICA\nCompra Pública Estratégica: Inexistência de contratação pública estratégica\n\n26 - INFORMAÇÕES ADICIONAIS\nContrato adequado para PME: Sim\nCobertura ACP (Acordo dos Contratos Públicos da Organização Mundial do Comércio): Não\n\n27 - IDENTIFICAÇÃO E CONTACTOS DO ÓRGÃO DE RECURSOS ADMINISTRATIVOS\nDesignação: Unidade de Compras - Serviço de Compras e Aprovisionamento\nEndereço: Estrada Carlos Lima Costa, n.º 2, Povos\nCódigo postal: 2600-009\nLocalidade: Vila Franca de Xira\nTelefone: +351 219579791\nFax: +351 263006637\nEndereço eletrónico: aprov@ulsetejo.min-saude.pt\n\n28 - IDENTIFICAÇÃO DO(S) AUTOR(ES) DE ANÚNCIO\nNome: Susana Tomé\nCargo: Assistente Técnica\n419561577",
    "nipc": "516487493",
    "distrito": "Lisboa",
    "concelho": "Vila Franca de Xira",
    "freguesia": "Freguesia de Vila Franca de Xira",
    "site": "https://www.hospitalvilafrancadexira.pt",
    "email": "hvfxira@hvfx.min-saude.pt",
    "designacao_contrato": "Aquisição Reagentes para Biologia Molecular com Cedência de Equipamento I",
    "descricao": "Aquisição Reagentes para Biologia Molecular com Cedência de Equipamento I",
    "preco_base": "159.600,00 EUR",
    "prazo_execucao": "24 MESES",
    "prazo_apresentacao_propostas": "02-10-2025 17:00",
    "fundos_eu": "Não",
    "plataforma_eletronica": "VORTAL",
    "url_procedimento": "https://community.vortal.biz/public/",
    "autor_nome": "Susana Tomé",
    "autor_cargo": "Assistente Técnica"
  },
  {
    "numero_procedimento": "N/A",
    "entidade": "Município de Arcos de Valdevez",
    "link": "https://diariodarepublica.pt/dr/detalhe/contrato-publico/24997-936194627",
    "detalhes_completos": "1 - IDENTIFICAÇÃO E CONTACTOS DA ENTIDADE ADJUDICANTE\nDesignação da entidade adjudicante: Município de Arcos de Valdevez\nNIPC: 505211696\nEndereço: Praça  Municipal\nCódigo postal: 4974-003\nLocalidade: Viana do Castelo\nPaís: Portugal\nNUT III: PT111\nDistrito: Viana do Castelo\nConcelho: Arcos de Valdevez\nFreguesia: União das Freguesias de Arcos de Valdevez (São Paio) e Giela\nTelefone: 258520500\nFax: 258520509\nEndereço da Entidade (URL): www.cmav.pt\nEndereço Eletrónico: geral@cmav.pt\neDelivery Gateway (URL): https://community.vortal.biz/public/\nFunção da Organização: Adquirente\nNorma jurídica da Entidade Adjudicante: Autoridade local\nÁrea de atividade da Autoridade Adjudicante: Serviços públicos das administrações públicas\n\n2 - JORNAL OFICIAL DA UNIÃO EUROPEIA\nO procedimento a que este anúncio diz respeito também é publicitado no Jornal Oficial da União Europeia? Não\n\n3 - AVISO\nModelo de Anúncio: Concurso público\nData de Envio do Anúncio: 22-09-2025\n\n5 - PROCESSO\nTipo de Procedimento: Concurso público\nPreço base do procedimento: Sim\nValor do preço base do procedimento: 76.237,63 EUR\nProcedimento com lotes? Não\n\n6 - OBJETO DO CONTRATO\nNúmero de referência interna: PO 574/2025\nDesignação do contrato: PO 574/2025 - Adaptação e beneficiação de edifício para residência partilhada de emergência social de Parada\nDescrição: PO 574/2025 - Adaptação e beneficiação de edifício para residência partilhada de emergência social de Parada\nTipo de Contrato Principal: Empreitada de Obras Públicas\nTipo de Contrato: Empreitada de Obras Públicas\nClassificação CPV (Vocabulário Comum para os Contratos Públicos)\nObjeto principal\nVocabulário Principal: 45262700\nPreço base s/IVA: 76.237,63 EUR\n\n7 - INDICAÇÕES ADICIONAIS\nO contrato envolve aquisição conjunta (satisfação de várias entidades)? Não\nO contrato é adjudicado por uma central de compras? Não\n\n8 - TÉCNICAS\nO concurso destina-se à celebração de um acordo-quadro? Inexistência de acordo-quadro\nÉ utilizado um leilão eletrónico? Não\nÉ adotada uma fase de negociação? Não\nSistema de Aquisição Dinâmico: Inexistência de sistema de aquisição dinâmico\n\n9 - LOCAL DA EXECUÇÃO DO CONTRATO\nLOCAL DA EXECUÇÃO DO CONTRATO (PROCEDIMENTO)\nPaís: Portugal\nNUT III: PT111\nLocalidade: Viana do Castelo\nDistrito: Viana do Castelo\nConcelho: Arcos de Valdevez\nFreguesia: União das Freguesias de Arcos de Valdevez (São Paio) e Giela\n\n10 - PRAZO DE EXECUÇÃO DO CONTRATO\nPrazo de execução do contrato: 180 DIAS\nPrevisão de renovações: Não\n\n11 - FUNDOS EU\nTêm fundos EU? Não\n\n12 - DOCUMENTOS DE HABILITAÇÃO\nHabilitação para o exercício da atividade profissional: Sim\nTipo: Alvará\nDescrição: Conforme indicado no artigo 16.º do Programa de Procedimento\n\n13 - CONDIÇÕES DE APRESENTAÇÃO\nPlataforma eletrónica utilizada pela entidade adjudicante: VORTAL\nURL para Apresentação: https://community.vortal.biz/public/\nAdmissibilidade da apresentação de propostas variantes: Não autorizado\nPrazo para apresentação das propostas: 10-10-2025 18:00\nPrazo durante o qual os concorrentes são obrigados a manter as respetivas propostas: 120 dias a contar do termo do prazo para a apresentação das propostas\nIndicação de Subcontratação na Proposta: Inexistência de indicação de subcontratação\n\n14 - PRESTAÇÃO DE CAUÇÃO\nPrestação de caução: Não\n\n15 - FORNECIMENTO DAS PEÇAS DO CONCURSO, APRESENTAÇÃO DE PEDIDOS DE PARTICIPAÇÃO E APRESENTAÇÃO DAS PROPOSTAS\nLink para acesso às peças do concurso (URL): https://community.vortal.biz/Public/public-tender-documents/aFJ2K25weHVGUlA3clFuZE9yQU85MjBSSGs2TVdkZ0lYYWJkaEEvelFiZVp6R2ovZWMzMndyaWtoQmtVWGswaDdZZmdUQ2Z2aXNnUzIyTXpXS2o2YVE9PUklTWJf\n\n20 - OUTROS REQUISITOS\nInformação sobre contratos reservados. Aplica-se a contratos reservados (54º-A)? Não\n\n21 - CRITÉRIO DE ADJUDICAÇÃO\nMultifator: Não\nMonofator:\nNome: Preço\n\n24 - CONDIÇÕES DO CONTRATO\nFaturação Eletrónica: Permitido\nObrigação de Subcontratação:\nCódigo da Obrigação de Subcontratação: Não é aplicável nenhuma obrigação de subcontratação.\n\n25 - COMPRA PÚBLICA ESTRATÉGICA\nCompra Pública Estratégica: Inexistência de contratação pública estratégica\n\n26 - INFORMAÇÕES ADICIONAIS\nContrato adequado para PME: Sim\nCobertura ACP (Acordo dos Contratos Públicos da Organização Mundial do Comércio): Não\n\n27 - IDENTIFICAÇÃO E CONTACTOS DO ÓRGÃO DE RECURSOS ADMINISTRATIVOS\nDesignação: Município de Arcos de Valdevez\nEndereço: Ribeirinho\nCódigo postal: 4970-272\nLocalidade: Arcos de Valdevez\nTelefone: +351 258520500\nFax: +351 258520509\nEndereço eletrónico: geral@cmav.pt\n\n28 - IDENTIFICAÇÃO DO(S) AUTOR(ES) DE ANÚNCIO\nNome: Olegário Gomes Gonçalves\nCargo: Presidente da Câmara\n419558572",
    "nipc": "505211696",
    "distrito": "Viana do Castelo",
    "concelho": "Arcos de Valdevez",
    "freguesia": "União das Freguesias de Arcos de Valdevez (São Paio) e Giela",
    "site": "www.cmav.pt",
    "email": "geral@cmav.pt",
    "designacao_contrato": "PO 574/2025 - Adaptação e beneficiação de edifício para residência partilhada de emergência social de Parada",
    "descricao": "PO 574/2025 - Adaptação e beneficiação de edifício para residência partilhada de emergência social de Parada",
    "preco_base": "76.237,63 EUR",
    "prazo_execucao": "180 DIAS",
    "prazo_apresentacao_propostas": "10-10-2025 18:00",
    "fundos_eu": "Não",
    "plataforma_eletronica": "VORTAL",
    "url_procedimento": "https://community.vortal.biz/public/",
    "autor_nome": "Olegário Gomes Gonçalves",
    "autor_cargo": "Presidente da Câmara"
  },
  {
    "numero_procedimento": "N/A",
    "entidade": "Município de Arcos de Valdevez",
    "link": "https://diariodarepublica.pt/dr/detalhe/contrato-publico/24998-936194628",
    "detalhes_completos": "1 - IDENTIFICAÇÃO E CONTACTOS DA ENTIDADE ADJUDICANTE\nDesignação da entidade adjudicante: Município de Arcos de Valdevez\nNIPC: 505211696\nEndereço: Praça  Municipal\nCódigo postal: 4974-003\nLocalidade: Viana do Castelo\nPaís: Portugal\nNUT III: PT111\nDistrito: Viana do Castelo\nConcelho: Arcos de Valdevez\nFreguesia: União das Freguesias de Arcos de Valdevez (São Paio) e Giela\nTelefone: 258520500\nFax: 258520509\nEndereço da Entidade (URL): www.cmav.pt\nEndereço Eletrónico: geral@cmav.pt\neDelivery Gateway (URL): https://community.vortal.biz/public/\nFunção da Organização: Adquirente\nNorma jurídica da Entidade Adjudicante: Autoridade local\nÁrea de atividade da Autoridade Adjudicante: Serviços públicos das administrações públicas\n\n2 - JORNAL OFICIAL DA UNIÃO EUROPEIA\nO procedimento a que este anúncio diz respeito também é publicitado no Jornal Oficial da União Europeia? Não\n\n3 - AVISO\nModelo de Anúncio: Concurso público\nData de Envio do Anúncio: 22-09-2025\n\n5 - PROCESSO\nTipo de Procedimento: Concurso público\nPreço base do procedimento: Sim\nValor do preço base do procedimento: 131.941,51 EUR\nProcedimento com lotes? Não\n\n6 - OBJETO DO CONTRATO\nNúmero de referência interna: PO 592/2025\nDesignação do contrato: PO 592/2025 - Reabilitação de 1 Fogo - Lugar das Lages (Freguesia de Jolda Madalena e Rio Cabrão)\nDescrição: PO 592/2025 - Reabilitação de 1 Fogo - Lugar das Lages (Freguesia de Jolda Madalena e Rio Cabrão)\nTipo de Contrato Principal: Empreitada de Obras Públicas\nTipo de Contrato: Empreitada de Obras Públicas\nClassificação CPV (Vocabulário Comum para os Contratos Públicos)\nObjeto principal\nVocabulário Principal: 45453100\nPreço base s/IVA: 131.941,51 EUR\n\n7 - INDICAÇÕES ADICIONAIS\nO contrato envolve aquisição conjunta (satisfação de várias entidades)? Não\nO contrato é adjudicado por uma central de compras? Não\n\n8 - TÉCNICAS\nO concurso destina-se à celebração de um acordo-quadro? Inexistência de acordo-quadro\nÉ utilizado um leilão eletrónico? Não\nÉ adotada uma fase de negociação? Não\nSistema de Aquisição Dinâmico: Inexistência de sistema de aquisição dinâmico\n\n9 - LOCAL DA EXECUÇÃO DO CONTRATO\nLOCAL DA EXECUÇÃO DO CONTRATO (PROCEDIMENTO)\nPaís: Portugal\nNUT III: PT111\nLocalidade: Viana do Castelo\nDistrito: Viana do Castelo\nConcelho: Arcos de Valdevez\nFreguesia: Todas\n\n10 - PRAZO DE EXECUÇÃO DO CONTRATO\nPrazo de execução do contrato: 180 DIAS\nPrevisão de renovações: Não\n\n11 - FUNDOS EU\nTêm fundos EU? Sim\n\n12 - DOCUMENTOS DE HABILITAÇÃO\nHabilitação para o exercício da atividade profissional: Não\n\n13 - CONDIÇÕES DE APRESENTAÇÃO\nPlataforma eletrónica utilizada pela entidade adjudicante: VORTAL\nURL para Apresentação: https://community.vortal.biz/public/\nAdmissibilidade da apresentação de propostas variantes: Não autorizado\nPrazo para apresentação das propostas: 10-10-2025 18:00\nPrazo durante o qual os concorrentes são obrigados a manter as respetivas propostas: 120 dias a contar do termo do prazo para a apresentação das propostas\nIndicação de Subcontratação na Proposta: Inexistência de indicação de subcontratação\n\n14 - PRESTAÇÃO DE CAUÇÃO\nPrestação de caução: Não\n\n15 - FORNECIMENTO DAS PEÇAS DO CONCURSO, APRESENTAÇÃO DE PEDIDOS DE PARTICIPAÇÃO E APRESENTAÇÃO DAS PROPOSTAS\nLink para acesso às peças do concurso (URL): https://community.vortal.biz/Public/public-tender-documents/LzFXK2xzQUpUZE4wOWM5MHVSNkhYUG9NckNJRmFXeU1seGVYUVlLUGZTYmh5cW9rdzdvSXB2ek5kUStVL1YrNHpIa3dFeVlxSmxGVkx6QWs5VzUzUVE9PVMpTGha\n\n20 - OUTROS REQUISITOS\nInformação sobre contratos reservados. Aplica-se a contratos reservados (54º-A)? Não\n\n21 - CRITÉRIO DE ADJUDICAÇÃO\nMultifator: Não\nMonofator:\nNome: Preço\n\n24 - CONDIÇÕES DO CONTRATO\nFaturação Eletrónica: Permitido\nObrigação de Subcontratação:\nCódigo da Obrigação de Subcontratação: Não é aplicável nenhuma obrigação de subcontratação.\n\n25 - COMPRA PÚBLICA ESTRATÉGICA\nCompra Pública Estratégica: Inexistência de contratação pública estratégica\n\n26 - INFORMAÇÕES ADICIONAIS\nContrato adequado para PME: Sim\nCobertura ACP (Acordo dos Contratos Públicos da Organização Mundial do Comércio): Não\n\n27 - IDENTIFICAÇÃO E CONTACTOS DO ÓRGÃO DE RECURSOS ADMINISTRATIVOS\nDesignação: Município de Arcos de Valdevez\nEndereço: Lugar das Lages\nCódigo postal: 4970-205\nLocalidade: Arcos de Valdevez\nTelefone: +351 258520500\nFax: +351 258520509\nEndereço eletrónico: geral@cmav.pt\n\n28 - IDENTIFICAÇÃO DO(S) AUTOR(ES) DE ANÚNCIO\nNome: Olegário Gomes Gonçalves\nCargo: Presidente da Câmara\n419558304",
    "nipc": "505211696",
    "distrito": "Viana do Castelo",
    "concelho": "Arcos de Valdevez",
    "freguesia": "União das Freguesias de Arcos de Valdevez (São Paio) e Giela",
    "site": "www.cmav.pt",
    "email": "geral@cmav.pt",
    "designacao_contrato": "PO 592/2025 - Reabilitação de 1 Fogo - Lugar das Lages (Freguesia de Jolda Madalena e Rio Cabrão)",
    "descricao": "PO 592/2025 - Reabilitação de 1 Fogo - Lugar das Lages (Freguesia de Jolda Madalena e Rio Cabrão)",
    "preco_base": "131.941,51 EUR",
    "prazo_execucao": "180 DIAS",
    "prazo_apresentacao_propostas": "10-10-2025 18:00",
    "fundos_eu": "Sim",
    "plataforma_eletronica": "VORTAL",
    "url_procedimento": "https://community.vortal.biz/public/",
    "autor_nome": "Olegário Gomes Gonçalves",
    "autor_cargo": "Presidente da Câmara"
  },
  {
    "numero_procedimento": "N/A",
    "entidade": "Infraestruturas de Portugal",
    "link": "https://diariodarepublica.pt/dr/detalhe/contrato-publico/24999-936194629",
    "detalhes_completos": "1 - IDENTIFICAÇÃO E CONTACTOS DA ENTIDADE ADJUDICANTE\nDesignação da entidade adjudicante: Infraestruturas de Portugal\nNIPC: 503933813\nServiço/Órgão/Pessoa de contacto: Direção de Compras e Logística - Departamento de Compras - Edifício 2\nEndereço: Praça da Portagem\nCódigo postal: 2809-013\nLocalidade: Almada\nPaís: Portugal\nNUT III: PT170\nDistrito: Setúbal\nConcelho: Almada\nFreguesia: União das Freguesias de Almada, Cova da Piedade, Pragal e Cacilhas\nTelefone:  212 879 300 \nFax: 21 287 90 00\nEndereço da Entidade (URL): www.infraestruturasdeportugal.pt\nEndereço Eletrónico: dcl@infraestruturasdeportugal.pt\nFunção da Organização: Adquirente\nNorma jurídica da Entidade Adjudicante: Organismo de direito público\nÁrea de atividade da Entidade Adjudicante: Serviços ferroviários\n\n2 - JORNAL OFICIAL DA UNIÃO EUROPEIA\nO procedimento a que este anúncio diz respeito também é publicitado no Jornal Oficial da União Europeia? Não\n\n3 - AVISO\nModelo de Anúncio: Concurso público\nData de Envio do Anúncio: 22-09-2025\n\n5 - PROCESSO\nTipo de Procedimento: Concurso público\nPreço base do procedimento: Sim\nValor do preço base do procedimento: 350.000,00 EUR\nProcedimento com lotes? Não\n\n6 - OBJETO DO CONTRATO\nNúmero de referência interna: 10021240\nDesignação do contrato: Empreitada - L. MINHO - MELHORAMENTO DAS CONDIÇÕES DE ACESSO E DE DRENAGEM POR CIMA DAS BOCAS DOS TUNEIS DE CHINA II E SEMINÁRIO II\nDescrição: L. MINHO - MELHORAMENTO DAS CONDIÇÕES DE ACESSO E DE DRENAGEM POR CIMA DAS BOCAS DOS TUNEIS DE CHINA II E SEMINÁRIO II\nTipo de Contrato Principal: Empreitada de Obras Públicas\nTipo de Contrato: Empreitada de Obras Públicas\nClassificação CPV (Vocabulário Comum para os Contratos Públicos)\nObjeto principal\nVocabulário Principal: 45221248\nPreço base s/IVA: 350.000,00 EUR\n\n7 - INDICAÇÕES ADICIONAIS\nO contrato envolve aquisição conjunta (satisfação de várias entidades)? Não\nO contrato é adjudicado por uma central de compras? Não\n\n8 - TÉCNICAS\nO concurso destina-se à celebração de um acordo-quadro? Inexistência de acordo-quadro\nÉ utilizado um leilão eletrónico? Não\nÉ adotada uma fase de negociação? Não\nSistema de Aquisição Dinâmico: Inexistência de sistema de aquisição dinâmico\n\n9 - LOCAL DA EXECUÇÃO DO CONTRATO\nLOCAL DA EXECUÇÃO DO CONTRATO (PROCEDIMENTO)\nPaís: Portugal\nNUT III: PT11A\nLocalidade: Bonfim\nDistrito: Porto\nConcelho: Porto\nFreguesia: Freguesia de Bonfim\n\n10 - PRAZO DE EXECUÇÃO DO CONTRATO\nPrazo de execução do contrato: 180 DIAS\nPrevisão de renovações: Não\n\n11 - FUNDOS EU\nTêm fundos EU? Não\n\n12 - DOCUMENTOS DE HABILITAÇÃO\nHabilitação para o exercício da atividade profissional: Sim\nTipo: Alvará\nDescrição: Da 5ª subcategoria da 2ª categoria de classe correspondente que cubra o valor global da proposta; Da 5ª subcategoria, da 6ª da categoria e da classe correspondente, ao valor dos trabalhos especializados que lhe respeitam\n\n13 - CONDIÇÕES DE APRESENTAÇÃO\nPlataforma eletrónica utilizada pela entidade adjudicante: ANOGOV\nURL para Apresentação: https://www.anogov.com/infraestruturasdeportugal-ip/faces/\nAdmissibilidade da apresentação de propostas variantes: Não autorizado\nPrazo para apresentação das propostas: 22-10-2025 17:00\nPrazo durante o qual os concorrentes são obrigados a manter as respetivas propostas: 120 dias a contar do termo do prazo para a apresentação das propostas\nApresentação de Catálogo Eletrónico: Não autorizado\nIndicação de Subcontratação na Proposta: Inexistência de indicação de subcontratação\n\n14 - PRESTAÇÃO DE CAUÇÃO\nPrestação de caução: Sim\nPercentagem: 5%\nDescrição da Garantia Exigida: 5,00% do valor contratual\n\n15 - FORNECIMENTO DAS PEÇAS DO CONCURSO, APRESENTAÇÃO DE PEDIDOS DE PARTICIPAÇÃO E APRESENTAÇÃO DAS PROPOSTAS\nLink para acesso às peças do concurso (URL): https://www.anogov.com/infraestruturasdeportugal-ip/faces/app/acessoDocs.jsp?codigoAcesso=B8tY4rvbBu3rKXy9pYaEBbb2ui2r3nxa3yh5f0sszc1STJ8N5M\n\n20 - OUTROS REQUISITOS\nInformação sobre contratos reservados. Aplica-se a contratos reservados (54º-A)? Não\n\n21 - CRITÉRIO DE ADJUDICAÇÃO\nMultifator: Sim\nFator: \nNome: Qualidade\nPonderação: 40%\nSubfatores: Sim\nSubfatores: \nNome: Memoria Descritiva\nPonderação : 50%; \nNome: Programa de Trabalhos\nPonderação : 50%; \nFator: \nNome: Preço\nPonderação: 60%\nSubfatores: Não\n\n24 - CONDIÇÕES DO CONTRATO\nFaturação Eletrónica: Permitido\nObrigação de Subcontratação:\nCódigo da Obrigação de Subcontratação: Não é aplicável nenhuma obrigação de subcontratação.\n\n25 - COMPRA PÚBLICA ESTRATÉGICA\nCompra Pública Estratégica: Inexistência de contratação pública estratégica\n\n26 - INFORMAÇÕES ADICIONAIS\nContrato adequado para PME: Sim\nCobertura ACP (Acordo dos Contratos Públicos da Organização Mundial do Comércio): Não\n\n27 - IDENTIFICAÇÃO E CONTACTOS DO ÓRGÃO DE RECURSOS ADMINISTRATIVOS\nDesignação: Conselho de Administração da Infraestruturas de Portugal, S.A.\nEndereço: Praça da Portagem\nCódigo postal: 2809-013\nLocalidade: Almada\nEndereço eletrónico: contratos@infraestruturasdeportugal.pt\n\n28 - IDENTIFICAÇÃO DO(S) AUTOR(ES) DE ANÚNCIO\nNome: Margarida Veloso\nCargo: Diretora Adjunta de Compras e Logística (em acumulação Dir. Departamento de Compras)\n419561836",
    "nipc": "503933813",
    "distrito": "Setúbal",
    "concelho": "Almada",
    "freguesia": "União das Freguesias de Almada, Cova da Piedade, Pragal e Cacilhas",
    "site": "www.infraestruturasdeportugal.pt",
    "email": "dcl@infraestruturasdeportugal.pt",
    "designacao_contrato": "Empreitada - L. MINHO - MELHORAMENTO DAS CONDIÇÕES DE ACESSO E DE DRENAGEM POR CIMA DAS BOCAS DOS TUNEIS DE CHINA II E SEMINÁRIO II",
    "descricao": "L. MINHO - MELHORAMENTO DAS CONDIÇÕES DE ACESSO E DE DRENAGEM POR CIMA DAS BOCAS DOS TUNEIS DE CHINA II E SEMINÁRIO II",
    "preco_base": "350.000,00 EUR",
    "prazo_execucao": "180 DIAS",
    "prazo_apresentacao_propostas": "22-10-2025 17:00",
    "fundos_eu": "Não",
    "plataforma_eletronica": "ANOGOV",
    "url_procedimento": "https://www.anogov.com/infraestruturasdeportugal-ip/faces/",
    "autor_nome": "Margarida Veloso",
    "autor_cargo": "Diretora Adjunta de Compras e Logística (em acumulação Dir. Departamento de Compras)"
  },
  {
    "numero_procedimento": "N/A",
    "entidade": "Unidade Local de Saúde de Santo António, E. P. E.",
    "link": "https://diariodarepublica.pt/dr/detalhe/contrato-publico/25000-936194630",
    "detalhes_completos": "1 - IDENTIFICAÇÃO E CONTACTOS DA ENTIDADE ADJUDICANTE\nDesignação da entidade adjudicante: Unidade Local de Saúde de Santo António, E. P. E.\nNIPC: 517392259\nEndereço: Largo Prof. Abel Salazar\nCódigo postal: 4099-001\nLocalidade: Área Metropolitana do Porto\nPaís: Portugal\nNUT III: PT11A\nDistrito: Porto\nConcelho: Porto\nFreguesia: Todas\nTelefone: 222077500\nFax: 223320318\nEndereço da Entidade (URL): www.hgsa.pt\nEndereço Eletrónico: helpdesk.b-on@hgsa.min-saude.pt\neDelivery Gateway (URL): https://community.vortal.biz/public/\nFunção da Organização: Adquirente\nNorma jurídica da Entidade Adjudicante: Organismo de direito público\nÁrea de atividade da Autoridade Adjudicante: Saúde\n\n2 - JORNAL OFICIAL DA UNIÃO EUROPEIA\nO procedimento a que este anúncio diz respeito também é publicitado no Jornal Oficial da União Europeia? Não\n\n3 - AVISO\nModelo de Anúncio: Concurso público\nData de Envio do Anúncio: 22-09-2025\n\n5 - PROCESSO\nTipo de Procedimento: Concurso público\nPreço base do procedimento: Sim\nValor do preço base do procedimento: 65.340,00 EUR\nProcedimento com lotes? Não\n\n6 - OBJETO DO CONTRATO\nNúmero de referência interna: CP/896/2025\nDesignação do contrato: Fornecimento de dispensadores de água para a ULSSA\nDescrição: CP/896/2025 - Fornecimento de dispensadores de água para a ULSSA\nTipo de Contrato Principal: Locação de Bens Móveis\nTipo de Contrato: Locação de Bens Móveis\nClassificação CPV (Vocabulário Comum para os Contratos Públicos)\nObjeto principal\nVocabulário Principal: 39370000\nPreço base s/IVA: 65.340,00 EUR\n\n7 - INDICAÇÕES ADICIONAIS\nO contrato envolve aquisição conjunta (satisfação de várias entidades)? Não\nO contrato é adjudicado por uma central de compras? Não\n\n8 - TÉCNICAS\nO concurso destina-se à celebração de um acordo-quadro? Inexistência de acordo-quadro\nÉ utilizado um leilão eletrónico? Não\nÉ adotada uma fase de negociação? Não\nSistema de Aquisição Dinâmico: Inexistência de sistema de aquisição dinâmico\n\n9 - LOCAL DA EXECUÇÃO DO CONTRATO\nLOCAL DA EXECUÇÃO DO CONTRATO (PROCEDIMENTO)\nPaís: Portugal\nNUT III: PT11A\nLocalidade: Área Metropolitana do Porto\nDistrito: Porto\nConcelho: Porto\nFreguesia: Todas\n\n10 - PRAZO DE EXECUÇÃO DO CONTRATO\nPrazo de execução do contrato: 36 MESES\nPrevisão de renovações: Não\n\n11 - FUNDOS EU\nTêm fundos EU? Não\n\n12 - DOCUMENTOS DE HABILITAÇÃO\nHabilitação para o exercício da atividade profissional: Não\n\n13 - CONDIÇÕES DE APRESENTAÇÃO\nPlataforma eletrónica utilizada pela entidade adjudicante: VORTAL\nURL para Apresentação: https://community.vortal.biz/public/\nAdmissibilidade da apresentação de propostas variantes: Não autorizado\nPrazo para apresentação das propostas: 08-10-2025 23:59\nPrazo durante o qual os concorrentes são obrigados a manter as respetivas propostas: 120 dias a contar do termo do prazo para a apresentação das propostas\nIndicação de Subcontratação na Proposta: Inexistência de indicação de subcontratação\n\n14 - PRESTAÇÃO DE CAUÇÃO\nPrestação de caução: Não\n\n15 - FORNECIMENTO DAS PEÇAS DO CONCURSO, APRESENTAÇÃO DE PEDIDOS DE PARTICIPAÇÃO E APRESENTAÇÃO DAS PROPOSTAS\nLink para acesso às peças do concurso (URL): https://community.vortal.biz/Public/public-tender-documents/aHZVWjJKM21NWmUrSkpZK0Y1djRnTGdock1Sc1MxN0I0RlMxQis1WjVndDJjYndIYXJLNkppRkJpb0JGeWVFR3V3OEZqQmhnQUVWN0trN1hUeEJPMkE9PVZeNyZ5\n\n20 - OUTROS REQUISITOS\nInformação sobre contratos reservados. Aplica-se a contratos reservados (54º-A)? Não\n\n21 - CRITÉRIO DE ADJUDICAÇÃO\nMultifator: Não\nMonofator:\nNome: Preço\n\n24 - CONDIÇÕES DO CONTRATO\nFaturação Eletrónica: Permitido\nObrigação de Subcontratação:\nCódigo da Obrigação de Subcontratação: Não é aplicável nenhuma obrigação de subcontratação.\n\n25 - COMPRA PÚBLICA ESTRATÉGICA\nCompra Pública Estratégica: Inexistência de contratação pública estratégica\n\n26 - INFORMAÇÕES ADICIONAIS\nContrato adequado para PME: Sim\nCobertura ACP (Acordo dos Contratos Públicos da Organização Mundial do Comércio): Não\n\n27 - IDENTIFICAÇÃO E CONTACTOS DO ÓRGÃO DE RECURSOS ADMINISTRATIVOS\nDesignação: Conselho de Administração\nEndereço: Largo do Professor Abel Salazar\nCódigo postal: 4099-001\nLocalidade: Porto\nTelefone: +351 220077500\nFax: +351 223320318\nEndereço eletrónico: secretariado.aprov@chporto.min-saude.pt\n\n28 - IDENTIFICAÇÃO DO(S) AUTOR(ES) DE ANÚNCIO\nNome: Telmo Alves\nCargo: Assistente Técnico\n419556044",
    "nipc": "517392259",
    "distrito": "Porto",
    "concelho": "Porto",
    "freguesia": "Todas",
    "site": "www.hgsa.pt",
    "email": "helpdesk.b-on@hgsa.min-saude.pt",
    "designacao_contrato": "Fornecimento de dispensadores de água para a ULSSA",
    "descricao": "CP/896/2025 - Fornecimento de dispensadores de água para a ULSSA",
    "preco_base": "65.340,00 EUR",
    "prazo_execucao": "36 MESES",
    "prazo_apresentacao_propostas": "08-10-2025 23:59",
    "fundos_eu": "Não",
    "plataforma_eletronica": "VORTAL",
    "url_procedimento": "https://community.vortal.biz/public/",
    "autor_nome": "Telmo Alves",
    "autor_cargo": "Assistente Técnico"
  },
  {
    "numero_procedimento": "N/A",
    "entidade": "Unidade Local de Saúde de Santo António, E. P. E.",
    "link": "https://diariodarepublica.pt/dr/detalhe/contrato-publico/25002-936194631",
    "detalhes_completos": "1 - IDENTIFICAÇÃO E CONTACTOS DA ENTIDADE ADJUDICANTE\nDesignação da entidade adjudicante: Unidade Local de Saúde de Santo António, E. P. E.\nNIPC: 517392259\nEndereço: Largo Prof. Abel Salazar\nCódigo postal: 4099-001\nLocalidade: Área Metropolitana do Porto\nPaís: Portugal\nNUT III: PT11A\nDistrito: Porto\nConcelho: Porto\nFreguesia: Todas\nTelefone: 222077500\nFax: 223320318\nEndereço da Entidade (URL): www.hgsa.pt\nEndereço Eletrónico: helpdesk.b-on@hgsa.min-saude.pt\neDelivery Gateway (URL): https://community.vortal.biz/public/\nFunção da Organização: Adquirente\nNorma jurídica da Entidade Adjudicante: Organismo de direito público\nÁrea de atividade da Autoridade Adjudicante: Saúde\n\n2 - JORNAL OFICIAL DA UNIÃO EUROPEIA\nO procedimento a que este anúncio diz respeito também é publicitado no Jornal Oficial da União Europeia? Não\n\n3 - AVISO\nModelo de Anúncio: Concurso público\nData de Envio do Anúncio: 22-09-2025\n\n5 - PROCESSO\nTipo de Procedimento: Concurso público\nPreço base do procedimento: Sim\nValor do preço base do procedimento: 93.000,00 EUR\nProcedimento com lotes? Não\n\n6 - OBJETO DO CONTRATO\nNúmero de referência interna: CP/919/2025\nDesignação do contrato: CP/919/2025 - Prestação de Serviços de Relato por Telerradiologia para exames de RMN\nDescrição: CP/919/2025 -Prestação de Serviços de Relato por Telerradiologia para exames de RMN\nTipo de Contrato Principal: Aquisição de Serviços\nTipo de Contrato: Aquisição de Serviços\nClassificação CPV (Vocabulário Comum para os Contratos Públicos)\nObjeto principal\nVocabulário Principal: 85100000\nPreço base s/IVA: 93.000,00 EUR\n\n7 - INDICAÇÕES ADICIONAIS\nO contrato envolve aquisição conjunta (satisfação de várias entidades)? Não\nO contrato é adjudicado por uma central de compras? Não\n\n8 - TÉCNICAS\nO concurso destina-se à celebração de um acordo-quadro? Inexistência de acordo-quadro\nÉ utilizado um leilão eletrónico? Não\nÉ adotada uma fase de negociação? Não\nSistema de Aquisição Dinâmico: Inexistência de sistema de aquisição dinâmico\n\n9 - LOCAL DA EXECUÇÃO DO CONTRATO\nLOCAL DA EXECUÇÃO DO CONTRATO (PROCEDIMENTO)\nPaís: Portugal\nNUT III: PT11A\nLocalidade: Área Metropolitana do Porto\nDistrito: Porto\nConcelho: Porto\nFreguesia: Todas\n\n10 - PRAZO DE EXECUÇÃO DO CONTRATO\nPrazo de execução do contrato: 14 MESES\nPrevisão de renovações: Não\n\n11 - FUNDOS EU\nTêm fundos EU? Não\n\n12 - DOCUMENTOS DE HABILITAÇÃO\nHabilitação para o exercício da atividade profissional: Não\n\n13 - CONDIÇÕES DE APRESENTAÇÃO\nPlataforma eletrónica utilizada pela entidade adjudicante: VORTAL\nURL para Apresentação: https://community.vortal.biz/public/\nAdmissibilidade da apresentação de propostas variantes: Não autorizado\nPrazo para apresentação das propostas: 08-10-2025 23:59\nPrazo durante o qual os concorrentes são obrigados a manter as respetivas propostas: 120 dias a contar do termo do prazo para a apresentação das propostas\nIndicação de Subcontratação na Proposta: Inexistência de indicação de subcontratação\n\n14 - PRESTAÇÃO DE CAUÇÃO\nPrestação de caução: Não\n\n15 - FORNECIMENTO DAS PEÇAS DO CONCURSO, APRESENTAÇÃO DE PEDIDOS DE PARTICIPAÇÃO E APRESENTAÇÃO DAS PROPOSTAS\nLink para acesso às peças do concurso (URL): https://community.vortal.biz/Public/public-tender-documents/S09TT0NLRGVqMEF2YVRnRExrOHAwbE9NTzRmbmpaOVlyN1B4bWd4NnN5elpQRGFtM0RLRXNJSFljamNIWGRqZnl3MFRrZVkyZzJHVFlpYTZUY2NUWnc9PTJeV3NF\n\n20 - OUTROS REQUISITOS\nInformação sobre contratos reservados. Aplica-se a contratos reservados (54º-A)? Não\n\n21 - CRITÉRIO DE ADJUDICAÇÃO\nMultifator: Não\nMonofator:\nNome: Preço\n\n24 - CONDIÇÕES DO CONTRATO\nFaturação Eletrónica: Permitido\nObrigação de Subcontratação:\nCódigo da Obrigação de Subcontratação: Não é aplicável nenhuma obrigação de subcontratação.\n\n25 - COMPRA PÚBLICA ESTRATÉGICA\nCompra Pública Estratégica: Inexistência de contratação pública estratégica\n\n26 - INFORMAÇÕES ADICIONAIS\nContrato adequado para PME: Sim\nCobertura ACP (Acordo dos Contratos Públicos da Organização Mundial do Comércio): Não\n\n27 - IDENTIFICAÇÃO E CONTACTOS DO ÓRGÃO DE RECURSOS ADMINISTRATIVOS\nDesignação: Conselho de Administração\nEndereço: Largo Professor Abel Salazar\nCódigo postal: 4099-001\nLocalidade: Porto\nTelefone: +351 222077500\nFax: +351 223320318\nEndereço eletrónico: secretariado.aprov@chporto.min-saude.pt\n\n28 - IDENTIFICAÇÃO DO(S) AUTOR(ES) DE ANÚNCIO\nNome: Sandra Eusébio\nCargo: Técnico Superior\n419555697",
    "nipc": "517392259",
    "distrito": "Porto",
    "concelho": "Porto",
    "freguesia": "Todas",
    "site": "www.hgsa.pt",
    "email": "helpdesk.b-on@hgsa.min-saude.pt",
    "designacao_contrato": "CP/919/2025 - Prestação de Serviços de Relato por Telerradiologia para exames de RMN",
    "descricao": "CP/919/2025 -Prestação de Serviços de Relato por Telerradiologia para exames de RMN",
    "preco_base": "93.000,00 EUR",
    "prazo_execucao": "14 MESES",
    "prazo_apresentacao_propostas": "08-10-2025 23:59",
    "fundos_eu": "Não",
    "plataforma_eletronica": "VORTAL",
    "url_procedimento": "https://community.vortal.biz/public/",
    "autor_nome": "Sandra Eusébio",
    "autor_cargo": "Técnico Superior"
  },
  {
    "numero_procedimento": "N/A",
    "entidade": "Unidade Local de Saúde da Lezíria, E. P. E.",
    "link": "https://diariodarepublica.pt/dr/detalhe/contrato-publico/25004-936194632",
    "detalhes_completos": "1 - IDENTIFICAÇÃO E CONTACTOS DA ENTIDADE ADJUDICANTE\nDesignação da entidade adjudicante: Unidade Local de Saúde da Lezíria, E. P. E.\nNIPC: 506361462\nEndereço: Av. Bernardo Santareno S/N\nCódigo postal: 2005-177\nLocalidade: Santarém\nPaís: Portugal\nNUT III: PT185\nDistrito: Santarém\nConcelho: Santarém\nFreguesia: União de Freguesias da Cidade de Santarém\nTelefone: 243300200\nFax: 243370220\nEndereço da Entidade (URL): www.hds.min-saude.pt\nEndereço Eletrónico: hdsca@hds.min-saude.pt\neDelivery Gateway (URL): https://community.vortal.biz/public/\nFunção da Organização: Adquirente\nNorma jurídica da Entidade Adjudicante: Organismo de direito público\nÁrea de atividade da Autoridade Adjudicante: Saúde\n\n2 - JORNAL OFICIAL DA UNIÃO EUROPEIA\nO procedimento a que este anúncio diz respeito também é publicitado no Jornal Oficial da União Europeia? Não\n\n3 - AVISO\nModelo de Anúncio: Concurso público\nData de Envio do Anúncio: 22-09-2025\n\n5 - PROCESSO\nTipo de Procedimento: Concurso público\nPreço base do procedimento: Sim\nValor do preço base do procedimento: 201.861,54 EUR\nProcedimento com lotes? Não\n\n6 - OBJETO DO CONTRATO\nNúmero de referência interna: 170014/2025\nDesignação do contrato: Empreitada para a construção da nova base da VMER da ULS Lezíria, E.P.E\nDescrição: Empreitada para a construção da nova base da VMER da ULS Lezíria, E.P.E\nTipo de Contrato Principal: Empreitada de Obras Públicas\nTipo de Contrato: Empreitada de Obras Públicas\nClassificação CPV (Vocabulário Comum para os Contratos Públicos)\nObjeto principal\nVocabulário Principal: 45215100\nPreço base s/IVA: 201.861,54 EUR\n\n7 - INDICAÇÕES ADICIONAIS\nO contrato envolve aquisição conjunta (satisfação de várias entidades)? Não\nO contrato é adjudicado por uma central de compras? Não\n\n8 - TÉCNICAS\nO concurso destina-se à celebração de um acordo-quadro? Inexistência de acordo-quadro\nÉ utilizado um leilão eletrónico? Não\nÉ adotada uma fase de negociação? Não\nSistema de Aquisição Dinâmico: Inexistência de sistema de aquisição dinâmico\n\n9 - LOCAL DA EXECUÇÃO DO CONTRATO\nLOCAL DA EXECUÇÃO DO CONTRATO (PROCEDIMENTO)\nPaís: Portugal\nNUT III: PT185\nLocalidade: Santarém\nDistrito: Santarém\nConcelho: Santarém\nFreguesia: União de Freguesias da Cidade de Santarém\n\n10 - PRAZO DE EXECUÇÃO DO CONTRATO\nPrazo de execução do contrato: 150 DIAS\nPrevisão de renovações: Não\n\n11 - FUNDOS EU\nTêm fundos EU? Não\n\n12 - DOCUMENTOS DE HABILITAÇÃO\nHabilitação para o exercício da atividade profissional: Não\n\n13 - CONDIÇÕES DE APRESENTAÇÃO\nPlataforma eletrónica utilizada pela entidade adjudicante: VORTAL\nURL para Apresentação: https://community.vortal.biz/public/\nAdmissibilidade da apresentação de propostas variantes: Não autorizado\nPrazo para apresentação das propostas: 08-10-2025 23:59\nPrazo durante o qual os concorrentes são obrigados a manter as respetivas propostas: 90 dias a contar do termo do prazo para a apresentação das propostas\nIndicação de Subcontratação na Proposta: Inexistência de indicação de subcontratação\n\n14 - PRESTAÇÃO DE CAUÇÃO\nPrestação de caução: Não\n\n15 - FORNECIMENTO DAS PEÇAS DO CONCURSO, APRESENTAÇÃO DE PEDIDOS DE PARTICIPAÇÃO E APRESENTAÇÃO DAS PROPOSTAS\nLink para acesso às peças do concurso (URL): https://community.vortal.biz/Public/public-tender-documents/UFpMVGdPYmd0dU1BdFNhVk15Vkd4QzdCVHlOKzYxdWZBdGF2bTllU1lMNjhNOHNiczloeUxBWlJ1VkVYV205RFplQ3ZQN2xHMlpYSzU5MVFIZUNpbWc9PU1SRTBu\n\n20 - OUTROS REQUISITOS\nInformação sobre contratos reservados. Aplica-se a contratos reservados (54º-A)? Não\n\n21 - CRITÉRIO DE ADJUDICAÇÃO\nMultifator: Sim\nFator: \nNome: Preço\nPonderação: 60%\nSubfatores: Não\nFator: \nNome: Outros\nOutro Nome: Prazo de execução \nPonderação: 40%\nSubfatores: Não\n\n24 - CONDIÇÕES DO CONTRATO\nFaturação Eletrónica: Permitido\nObrigação de Subcontratação:\nCódigo da Obrigação de Subcontratação: Não é aplicável nenhuma obrigação de subcontratação.\n\n25 - COMPRA PÚBLICA ESTRATÉGICA\nCompra Pública Estratégica: Inexistência de contratação pública estratégica\n\n26 - INFORMAÇÕES ADICIONAIS\nContrato adequado para PME: Sim\nCobertura ACP (Acordo dos Contratos Públicos da Organização Mundial do Comércio): Não\n\n27 - IDENTIFICAÇÃO E CONTACTOS DO ÓRGÃO DE RECURSOS ADMINISTRATIVOS\nDesignação: Conselho de Administração\nEndereço: Avenida Bernardo santareno S/N\nCódigo postal: 2005-177\nLocalidade: Santarém\nTelefone: +351 243300200\nFax: +351 243370220\nEndereço eletrónico: ca@ulsleziria.min-saude.pt\n\n28 - IDENTIFICAÇÃO DO(S) AUTOR(ES) DE ANÚNCIO\nNome: Dr. Pedro Manuel Dias de Figueiredo Pereira Marques \nCargo: Presidente do Conselho de Administração \n419562654",
    "nipc": "506361462",
    "distrito": "Santarém",
    "concelho": "Santarém",
    "freguesia": "União de Freguesias da Cidade de Santarém",
    "site": "www.hds.min-saude.pt",
    "email": "hdsca@hds.min-saude.pt",
    "designacao_contrato": "Empreitada para a construção da nova base da VMER da ULS Lezíria, E.P.E",
    "descricao": "Empreitada para a construção da nova base da VMER da ULS Lezíria, E.P.E",
    "preco_base": "201.861,54 EUR",
    "prazo_execucao": "150 DIAS",
    "prazo_apresentacao_propostas": "08-10-2025 23:59",
    "fundos_eu": "Não",
    "plataforma_eletronica": "VORTAL",
    "url_procedimento": "https://community.vortal.biz/public/",
    "autor_nome": "Dr. Pedro Manuel Dias de Figueiredo Pereira Marques",
    "autor_cargo": "Presidente do Conselho de Administração"
  },
  {
    "numero_procedimento": "N/A",
    "entidade": "Unidade Local de Saúde de Trás-os-Montes e Alto Douro, E. P. E.",
    "link": "https://diariodarepublica.pt/dr/detalhe/contrato-publico/25006-936194633",
    "detalhes_completos": "1 - IDENTIFICAÇÃO E CONTACTOS DA ENTIDADE ADJUDICANTE\nDesignação da entidade adjudicante: Unidade Local de Saúde de Trás-os-Montes e Alto Douro, E. P. E.\nNIPC: 508100496\nEndereço: Av. Da Noruega - Lordelo S/N\nCódigo postal: 5000-508\nLocalidade: Vila Real\nPaís: Portugal\nNUT III: PT11D\nDistrito: Vila Real\nConcelho: Vila Real\nFreguesia: Todas\nTelefone: 259300500\nFax: 259300503\nEndereço da Entidade (URL): www.chtmad.min-saude.pt\nEndereço Eletrónico: admin@chtmad.min-saude.pt\neDelivery Gateway (URL): https://community.vortal.biz/public/\nFunção da Organização: Adquirente\nNorma jurídica da Entidade Adjudicante: Organismo de direito público\nÁrea de atividade da Autoridade Adjudicante: Saúde\n\n2 - JORNAL OFICIAL DA UNIÃO EUROPEIA\nO procedimento a que este anúncio diz respeito também é publicitado no Jornal Oficial da União Europeia? Não\n\n3 - AVISO\nModelo de Anúncio: Concurso público\nData de Envio do Anúncio: 22-09-2025\n\n5 - PROCESSO\nTipo de Procedimento: Concurso público\nPreço base do procedimento: Sim\nValor do preço base do procedimento: 5.977,00 EUR\nProcedimento com lotes? Não\n\n6 - OBJETO DO CONTRATO\nNúmero de referência interna: CP 3472-2025\nDesignação do contrato: CP 3472-2025 Aquisição de sistema de chamada de enfermagem para internamento de Medicina em Chaves da ULSTMAD, EPE.\nDescrição: CP 3472-2025 Aquisição de sistema de chamada de enfermagem para internamento de Medicina em Chaves da ULSTMAD, EPE.\nTipo de Contrato Principal: Aquisição de Bens Móveis\nTipo de Contrato: Aquisição de Bens Móveis\nClassificação CPV (Vocabulário Comum para os Contratos Públicos)\nObjeto principal\nVocabulário Principal: 32500000\nPreço base s/IVA: 5.977,00 EUR\n\n7 - INDICAÇÕES ADICIONAIS\nO contrato envolve aquisição conjunta (satisfação de várias entidades)? Não\nO contrato é adjudicado por uma central de compras? Não\n\n8 - TÉCNICAS\nO concurso destina-se à celebração de um acordo-quadro? Inexistência de acordo-quadro\nÉ utilizado um leilão eletrónico? Não\nÉ adotada uma fase de negociação? Não\nSistema de Aquisição Dinâmico: Inexistência de sistema de aquisição dinâmico\n\n9 - LOCAL DA EXECUÇÃO DO CONTRATO\nLOCAL DA EXECUÇÃO DO CONTRATO (PROCEDIMENTO)\nPaís: Portugal\nNUT III: PT11D\nLocalidade: Vila Real\nDistrito: Vila Real\nConcelho: Vila Real\nFreguesia: Freguesia de Lordelo - Vila Real\n\n10 - PRAZO DE EXECUÇÃO DO CONTRATO\nPrazo de execução do contrato: 60 DIAS\nPrevisão de renovações: Não\n\n11 - FUNDOS EU\nTêm fundos EU? Não\n\n12 - DOCUMENTOS DE HABILITAÇÃO\nHabilitação para o exercício da atividade profissional: Não\n\n13 - CONDIÇÕES DE APRESENTAÇÃO\nPlataforma eletrónica utilizada pela entidade adjudicante: VORTAL\nURL para Apresentação: https://community.vortal.biz/public/\nAdmissibilidade da apresentação de propostas variantes: Não autorizado\nPrazo para apresentação das propostas: 29-09-2025 17:00\nPrazo durante o qual os concorrentes são obrigados a manter as respetivas propostas: 180 dias a contar do termo do prazo para a apresentação das propostas\nIndicação de Subcontratação na Proposta: Inexistência de indicação de subcontratação\n\n14 - PRESTAÇÃO DE CAUÇÃO\nPrestação de caução: Não\n\n15 - FORNECIMENTO DAS PEÇAS DO CONCURSO, APRESENTAÇÃO DE PEDIDOS DE PARTICIPAÇÃO E APRESENTAÇÃO DAS PROPOSTAS\nLink para acesso às peças do concurso (URL): https://community.vortal.biz/Public/public-tender-documents/L0h4bDBqY0QrNHZWWEFjbTgvZmpXNEZBYlMyK0Q2UzA0QmYrd2VKQXRNVUFQazJxZDlIcFk0RHNobjcyVGRZY1NidDM5K3lOYTR5dzZtUUNnU3UrTVE9PUp1aF5y\n\n20 - OUTROS REQUISITOS\nInformação sobre contratos reservados. Aplica-se a contratos reservados (54º-A)? Não\n\n21 - CRITÉRIO DE ADJUDICAÇÃO\nMultifator: Não\nMonofator:\nNome: Preço\n\n24 - CONDIÇÕES DO CONTRATO\nFaturação Eletrónica: Permitido\nObrigação de Subcontratação:\nCódigo da Obrigação de Subcontratação: Não é aplicável nenhuma obrigação de subcontratação.\n\n25 - COMPRA PÚBLICA ESTRATÉGICA\nCompra Pública Estratégica: Inexistência de contratação pública estratégica\n\n26 - INFORMAÇÕES ADICIONAIS\nContrato adequado para PME: Sim\nCobertura ACP (Acordo dos Contratos Públicos da Organização Mundial do Comércio): Não\n\n27 - IDENTIFICAÇÃO E CONTACTOS DO ÓRGÃO DE RECURSOS ADMINISTRATIVOS\nDesignação: Conselho de administração da ULSTMAD\nEndereço: Avenida da Noruega S/N - Lordelo\nCódigo postal: 5000-508\nLocalidade: Vila Real\nTelefone: +351 259300500\nFax: +351 259300558\nEndereço eletrónico: admin@chtmad.min-saude.pt\n\n28 - IDENTIFICAÇÃO DO(S) AUTOR(ES) DE ANÚNCIO\nNome: Raquel Marques\nCargo: Assistente técnico\n419563959",
    "nipc": "508100496",
    "distrito": "Vila Real",
    "concelho": "Vila Real",
    "freguesia": "Todas",
    "site": "www.chtmad.min-saude.pt",
    "email": "admin@chtmad.min-saude.pt",
    "designacao_contrato": "CP 3472-2025 Aquisição de sistema de chamada de enfermagem para internamento de Medicina em Chaves da ULSTMAD, EPE.",
    "descricao": "CP 3472-2025 Aquisição de sistema de chamada de enfermagem para internamento de Medicina em Chaves da ULSTMAD, EPE.",
    "preco_base": "5.977,00 EUR",
    "prazo_execucao": "60 DIAS",
    "prazo_apresentacao_propostas": "29-09-2025 17:00",
    "fundos_eu": "Não",
    "plataforma_eletronica": "VORTAL",
    "url_procedimento": "https://community.vortal.biz/public/",
    "autor_nome": "Raquel Marques",
    "autor_cargo": "Assistente técnico"
  },
  {
    "numero_procedimento": "N/A",
    "entidade": "CMPH Empresa de Habitação e Manutenção do Município do Porto, E.M.",
    "link": "https://diariodarepublica.pt/dr/detalhe/contrato-publico/25010-936194634",
    "detalhes_completos": "1 - IDENTIFICAÇÃO E CONTACTOS DA ENTIDADE ADJUDICANTE\nDesignação da entidade adjudicante: CMPH Empresa de Habitação e Manutenção do Município do Porto, E.M.\nNIPC: 505037700\nServiço/Órgão/Pessoa de contacto: CMPH Empresa de Habitação e Manutenção do Município do Porto, E.M.\nEndereço: Rua do Monte dos Burgos, 12\nCódigo postal: 4250-309\nLocalidade: Porto\nPaís: Portugal\nNUT III: PT11A\nDistrito: Porto\nConcelho: Porto\nFreguesia: Freguesia de Paranhos - Porto\nTelefone: 228330000\nFax: 228330000\nEndereço da Entidade (URL): www.domussocial.pt\nEndereço Eletrónico: geral@domussocial.pt\neDelivery Gateway (URL): https://www.acingov.pt\nFunção da Organização: Adquirente\nNorma jurídica da Entidade Adjudicante: Empresa pública, controlada por uma autoridade local\nÁrea de atividade da Autoridade Adjudicante: Serviços públicos das administrações públicas\n\n2 - JORNAL OFICIAL DA UNIÃO EUROPEIA\nO procedimento a que este anúncio diz respeito também é publicitado no Jornal Oficial da União Europeia? Não\n\n3 - AVISO\nModelo de Anúncio: Concurso público\nData de Envio do Anúncio: 22-09-2025\n\n5 - PROCESSO\nTipo de Procedimento: Concurso público\nPreço base do procedimento: Sim\nValor do preço base do procedimento: 201.040,00 EUR\nProcedimento com lotes? Não\n\n6 - OBJETO DO CONTRATO\nNúmero de referência interna: SE00120250000063\nDesignação do contrato: Aquisição de serviços de arqueologia, fiscalização e controlo da empreitada de reabilitação de edifícios na Rua Cimo de Vila n.º 109-113 (SE.001.2025.063)\nDescrição: Aquisição de serviços de arqueologia, fiscalização e controlo da empreitada de reabilitação de edifícios na Rua Cimo de Vila n.º 109-113 (SE.001.2025.063)\nTipo de Contrato Principal: Aquisição de Serviços\nTipo de Contrato: Aquisição de Serviços\nClassificação CPV (Vocabulário Comum para os Contratos Públicos)\nObjeto principal\nVocabulário Principal: 71000000\nPreço base s/IVA: 201.040,00 EUR\n\n7 - INDICAÇÕES ADICIONAIS\nO contrato envolve aquisição conjunta (satisfação de várias entidades)? Não\nO contrato é adjudicado por uma central de compras? Não\n\n8 - TÉCNICAS\nO concurso destina-se à celebração de um acordo-quadro? Inexistência de acordo-quadro\nÉ utilizado um leilão eletrónico? Não\nÉ adotada uma fase de negociação? Não\nSistema de Aquisição Dinâmico: Inexistência de sistema de aquisição dinâmico\n\n9 - LOCAL DA EXECUÇÃO DO CONTRATO\nLOCAL DA EXECUÇÃO DO CONTRATO (PROCEDIMENTO)\nPaís: Portugal\nNUT III: PT11A\nLocalidade: Porto\nDistrito: Porto\nConcelho: Porto\nFreguesia: União das Freguesias de Cedofeita, Santo Ildefonso, Sé, Miragaia, São Nicolau e Vitória\n\n10 - PRAZO DE EXECUÇÃO DO CONTRATO\nPrazo de execução do contrato: 585 DIAS\nPrevisão de renovações: Não\n\n11 - FUNDOS EU\nTêm fundos EU? Não\n\n12 - DOCUMENTOS DE HABILITAÇÃO\nHabilitação para o exercício da atividade profissional: Sim\nTipo: Outros\nDescrição - Outros: Os requisitos/documentos de habilitação encontram-se previstos nos artigos 23.º e 24.º do Programa Procedimento, respetivamente \nDescrição: Documentos de Habilitação\n\n13 - CONDIÇÕES DE APRESENTAÇÃO\nPlataforma eletrónica utilizada pela entidade adjudicante: ACIN\nURL para Apresentação: https://www.acingov.pt\nAdmissibilidade da apresentação de propostas variantes: Não autorizado\nPrazo para apresentação das propostas: 13-10-2025 18:00\nPrazo durante o qual os concorrentes são obrigados a manter as respetivas propostas: 90 dias a contar do termo do prazo para a apresentação das propostas\nIndicação de Subcontratação na Proposta: Inexistência de indicação de subcontratação\n\n14 - PRESTAÇÃO DE CAUÇÃO\nPrestação de caução: Sim\nPercentagem: 5%\nDescrição da Garantia Exigida: O valor da caução é de 5.00% do preço contratual.\n\n15 - FORNECIMENTO DAS PEÇAS DO CONCURSO, APRESENTAÇÃO DE PEDIDOS DE PARTICIPAÇÃO E APRESENTAÇÃO DAS PROPOSTAS\nLink para acesso às peças do concurso (URL): https://www.acingov.pt/acingovprod/2/zonaPublica/zona_publica_c/donwloadProcedurePiece/OTc5OTgw\n\n20 - OUTROS REQUISITOS\nInformação sobre contratos reservados. Aplica-se a contratos reservados (54º-A)? Não\n\n21 - CRITÉRIO DE ADJUDICAÇÃO\nMultifator: Não\nMonofator:\nNome: Preço\n\n24 - CONDIÇÕES DO CONTRATO\nFaturação Eletrónica: Permitido\nObrigação de Subcontratação:\nCódigo da Obrigação de Subcontratação: Não é aplicável nenhuma obrigação de subcontratação.\n\n25 - COMPRA PÚBLICA ESTRATÉGICA\nCompra Pública Estratégica: Inexistência de contratação pública estratégica\n\n26 - INFORMAÇÕES ADICIONAIS\nContrato adequado para PME: Sim\nCobertura ACP (Acordo dos Contratos Públicos da Organização Mundial do Comércio): Não\n\n27 - IDENTIFICAÇÃO E CONTACTOS DO ÓRGÃO DE RECURSOS ADMINISTRATIVOS\nDesignação: CMPH Empresa de Habitação e Manutenção do Município do Porto, E.M.\nEndereço: Rua do Monte dos Burgos, 12\nCódigo postal: 4250-309\nLocalidade: Porto\nTelefone: 228330000\nFax: 228330000\nEndereço eletrónico: geral@domussocial.pt\nPrazo de interposição do recurso: 7 dias\n\n28 - IDENTIFICAÇÃO DO(S) AUTOR(ES) DE ANÚNCIO\nNome: Filipa Alexandra Dias Pereira de Sousa Melo Tavares\nCargo: Vice-Presidente do Conselho de Administração\n419560686",
    "nipc": "505037700",
    "distrito": "Porto",
    "concelho": "Porto",
    "freguesia": "Freguesia de Paranhos - Porto",
    "site": "www.domussocial.pt",
    "email": "geral@domussocial.pt",
    "designacao_contrato": "Aquisição de serviços de arqueologia, fiscalização e controlo da empreitada de reabilitação de edifícios na Rua Cimo de Vila n.º 109-113 (SE.001.2025.063)",
    "descricao": "Aquisição de serviços de arqueologia, fiscalização e controlo da empreitada de reabilitação de edifícios na Rua Cimo de Vila n.º 109-113 (SE.001.2025.063)",
    "preco_base": "201.040,00 EUR",
    "prazo_execucao": "585 DIAS",
    "prazo_apresentacao_propostas": "13-10-2025 18:00",
    "fundos_eu": "Não",
    "plataforma_eletronica": "ACIN",
    "url_procedimento": "https://www.acingov.pt",
    "autor_nome": "Filipa Alexandra Dias Pereira de Sousa Melo Tavares",
    "autor_cargo": "Vice-Presidente do Conselho de Administração"
  },
  {
    "numero_procedimento": "N/A",
    "entidade": "Município de Barcelos",
    "link": "https://diariodarepublica.pt/dr/detalhe/contrato-publico/25014-936194638",
    "detalhes_completos": "1 - IDENTIFICAÇÃO E CONTACTOS DA ENTIDADE ADJUDICANTE\nDesignação da entidade adjudicante: Município de Barcelos\nNIPC: 505584760\nServiço/Órgão/Pessoa de contacto: vereador do Pelouro\nEndereço: Largo Município\nCódigo postal: 4750-323\nLocalidade: Braga\nPaís: Portugal\nNUT III: PT112\nDistrito: Braga\nConcelho: Barcelos\nFreguesia: União das Freguesias de Barcelos, Vila Boa e Vila Frescainha (São Martinho e São Pedro)\nTelefone: 253809600\nFax: 253821263\nEndereço da Entidade (URL): www.cm-barcelos.pt\nEndereço Eletrónico: geral@cm-barcelos.pt\neDelivery Gateway (URL): https://community.vortal.biz/public/\nFunção da Organização: Adquirente\nNorma jurídica da Entidade Adjudicante: Organismo de direito público\nÁrea de atividade da Autoridade Adjudicante: Serviços públicos das administrações públicas\n\n2 - JORNAL OFICIAL DA UNIÃO EUROPEIA\nO procedimento a que este anúncio diz respeito também é publicitado no Jornal Oficial da União Europeia? Não\n\n3 - AVISO\nModelo de Anúncio: Concurso público\nData de Envio do Anúncio: 22-09-2025\n\n5 - PROCESSO\nTipo de Procedimento: Concurso público\nPreço base do procedimento: Sim\nValor do preço base do procedimento: 15.000,00 EUR\nProcedimento com lotes? Não\n\n6 - OBJETO DO CONTRATO\nNúmero de referência interna: CP45/2025 \nDesignação do contrato: Aquisição de ZW CAD Profissional\nDescrição: Aquisição de ZW CAD Profissional\nTipo de Contrato Principal: Aquisição de Bens Móveis\nTipo de Contrato: Aquisição de Bens Móveis\nClassificação CPV (Vocabulário Comum para os Contratos Públicos)\nObjeto principal\nVocabulário Principal: 48218000\nPreço base s/IVA: 15.000,00 EUR\n\n7 - INDICAÇÕES ADICIONAIS\nO contrato envolve aquisição conjunta (satisfação de várias entidades)? Não\nO contrato é adjudicado por uma central de compras? Não\n\n8 - TÉCNICAS\nO concurso destina-se à celebração de um acordo-quadro? Inexistência de acordo-quadro\nÉ utilizado um leilão eletrónico? Não\nÉ adotada uma fase de negociação? Não\nSistema de Aquisição Dinâmico: Inexistência de sistema de aquisição dinâmico\n\n9 - LOCAL DA EXECUÇÃO DO CONTRATO\nLOCAL DA EXECUÇÃO DO CONTRATO (PROCEDIMENTO)\nPaís: Portugal\nNUT III: PT112\nLocalidade: Braga\nDistrito: Braga\nConcelho: Barcelos\nFreguesia: União das Freguesias de Barcelos, Vila Boa e Vila Frescainha (São Martinho e São Pedro)\n\n10 - PRAZO DE EXECUÇÃO DO CONTRATO\nPrazo de execução do contrato: 1 DIAS\nPrevisão de renovações: Não\n\n11 - FUNDOS EU\nTêm fundos EU? Não\n\n12 - DOCUMENTOS DE HABILITAÇÃO\nHabilitação para o exercício da atividade profissional: Sim\nTipo: Outros\nDescrição - Outros: Outros\nDescrição: Documentos solicitados no ponto 81º do CCP\n\n13 - CONDIÇÕES DE APRESENTAÇÃO\nPlataforma eletrónica utilizada pela entidade adjudicante: VORTAL\nURL para Apresentação: https://community.vortal.biz/public/\nAdmissibilidade da apresentação de propostas variantes: Não autorizado\nPrazo para apresentação das propostas: 29-09-2025 23:59\nPrazo durante o qual os concorrentes são obrigados a manter as respetivas propostas: 90 dias a contar do termo do prazo para a apresentação das propostas\nIndicação de Subcontratação na Proposta: Inexistência de indicação de subcontratação\n\n14 - PRESTAÇÃO DE CAUÇÃO\nPrestação de caução: Não\n\n15 - FORNECIMENTO DAS PEÇAS DO CONCURSO, APRESENTAÇÃO DE PEDIDOS DE PARTICIPAÇÃO E APRESENTAÇÃO DAS PROPOSTAS\nLink para acesso às peças do concurso (URL): https://community.vortal.biz/Public/public-tender-documents/ZHJITElHSlZ2MHI2Tjc3ZUhyc1EwTU9IYXVEdjlBWUhUN1lyaHZqOHVzZFlCWkZNdzdTZGNGY1RoWllNOGNvc3N6aDQ4UlV2RU1RcHpMY2JRS0xOVUE9PSFBMlgm\n\n20 - OUTROS REQUISITOS\nInformação sobre contratos reservados. Aplica-se a contratos reservados (54º-A)? Não\n\n21 - CRITÉRIO DE ADJUDICAÇÃO\nMultifator: Não\nMonofator:\nNome: Preço\n\n24 - CONDIÇÕES DO CONTRATO\nFaturação Eletrónica: Permitido\nObrigação de Subcontratação:\nCódigo da Obrigação de Subcontratação: Não é aplicável nenhuma obrigação de subcontratação.\n\n25 - COMPRA PÚBLICA ESTRATÉGICA\nCompra Pública Estratégica: Inexistência de contratação pública estratégica\n\n26 - INFORMAÇÕES ADICIONAIS\nContrato adequado para PME: Sim\nCobertura ACP (Acordo dos Contratos Públicos da Organização Mundial do Comércio): Não\n\n27 - IDENTIFICAÇÃO E CONTACTOS DO ÓRGÃO DE RECURSOS ADMINISTRATIVOS\nDesignação: Municipio de Barcelos\nEndereço: Largo do Município.\nCódigo postal: 4750-323\nLocalidade: Barcelos\nTelefone: +351 253809600\nFax: +351 253821263\nEndereço eletrónico: geral@cm-barcelos.pt\n\n28 - IDENTIFICAÇÃO DO(S) AUTOR(ES) DE ANÚNCIO\nNome: Camara Municipal de Barcelos\nCargo: Vereador do Pelouro da Câmara Municipal de Barcelos.\n419561658",
    "nipc": "505584760",
    "distrito": "Braga",
    "concelho": "Barcelos",
    "freguesia": "União das Freguesias de Barcelos, Vila Boa e Vila Frescainha (São Martinho e São Pedro)",
    "site": "www.cm-barcelos.pt",
    "email": "geral@cm-barcelos.pt",
    "designacao_contrato": "Aquisição de ZW CAD Profissional",
    "descricao": "Aquisição de ZW CAD Profissional",
    "preco_base": "15.000,00 EUR",
    "prazo_execucao": "1 DIAS",
    "prazo_apresentacao_propostas": "29-09-2025 23:59",
    "fundos_eu": "Não",
    "plataforma_eletronica": "VORTAL",
    "url_procedimento": "https://community.vortal.biz/public/",
    "autor_nome": "Camara Municipal de Barcelos",
    "autor_cargo": "Vereador do Pelouro da Câmara Municipal de Barcelos."
  },
  {
    "numero_procedimento": "N/A",
    "entidade": "Instituto Português do Mar e da Atmosfera,I.P.",
    "link": "https://diariodarepublica.pt/dr/detalhe/contrato-publico/25015-936194639",
    "detalhes_completos": "1 - IDENTIFICAÇÃO E CONTACTOS DA ENTIDADE ADJUDICANTE\nDesignação da entidade adjudicante: Instituto Português do Mar e da Atmosfera,I.P.\nNIPC: 510265600\nServiço/Órgão/Pessoa de contacto: Conselho Diretivo\nEndereço: Rua C do Aeroporto de Lisboa\nCódigo postal: 1749-077\nLocalidade: Lisboa\nPaís: Portugal\nNUT III: PT170\nDistrito: Lisboa\nConcelho: Lisboa\nFreguesia: Freguesia de Olivais\nTelefone: 218447000\nFax: 218402370\nEndereço da Entidade (URL): https://www.ipma.pt\nEndereço Eletrónico: contratacao@ipma.pt\nFunção da Organização: Adquirente\nNorma jurídica da Entidade Adjudicante: Autoridade da administração central\nÁrea de atividade da Entidade Adjudicante: Atividades aeroportuárias\n\n2 - JORNAL OFICIAL DA UNIÃO EUROPEIA\nO procedimento a que este anúncio diz respeito também é publicitado no Jornal Oficial da União Europeia? Não\n\n3 - AVISO\nModelo de Anúncio: Concurso público\nData de Envio do Anúncio: 22-09-2025\n\n5 - PROCESSO\nTipo de Procedimento: Concurso público\nPreço base do procedimento: Sim\nValor do preço base do procedimento: 78.480,00 EUR\nProcedimento com lotes? Sim\nNº Máx. de Lotes Autorizado: 8\nNúmero máximo de lotes que podem ser adjudicados a um concorrente: 8\n\n6 - OBJETO DO CONTRATO\nNúmero de referência interna: CP 181/2025\nDesignação do contrato: Aquisição de serviços de manutenção preventiva para os equipamentos de AVAC\nDescrição: Aquisição de serviços de manutenção preventiva para os equipamentos de AVAC\nTipo de Contrato Principal: Aquisição de Serviços\nTipo de Contrato: Aquisição de Serviços\nClassificação CPV (Vocabulário Comum para os Contratos Públicos)\nObjeto principal\nVocabulário Principal: 50730000\nPreço base s/IVA: 78.480,00 EUR\nLotes: \nNº: LOT-0001\nDescrição do Lote: Lote 1 - Edifício Sede e Campus Algés\nPreço base s/IVA: 27.520,00 EUR\nClassificação CPV (Vocabulário Comum para os Contratos Públicos)\nObjeto principal\nVocabulário Principal: 50730000\nNº: LOT-0002\nDescrição do Lote: Lote 1 A - Edifício Sede - Data Center\nPreço base s/IVA: 3.000,00 EUR\nClassificação CPV (Vocabulário Comum para os Contratos Públicos)\nObjeto principal\nVocabulário Principal: 50730000\nNº: LOT-0003\nDescrição do Lote: Lote 2 - Centro Regional de Investigação Pesqueira de Olhão (CRIP), Estação Experimental  de Piscicultura (EPPO) de Olhão e Estação Experimental de Moluscicultura Tavira (EEM)\nPreço base s/IVA: 28.600,00 EUR\nClassificação CPV (Vocabulário Comum para os Contratos Públicos)\nObjeto principal\nVocabulário Principal: 50730000\nNº: LOT-0004\nDescrição do Lote: Lote 3 - Delegação Regional dos Açores\nPreço base s/IVA: 5.360,00 EUR\nClassificação CPV (Vocabulário Comum para os Contratos Públicos)\nObjeto principal\nVocabulário Principal: 50730000\nNº: LOT-0005\nDescrição do Lote:  Lote 4 - Delegação Regional da Madeira\nPreço base s/IVA: 3.500,00 EUR\nClassificação CPV (Vocabulário Comum para os Contratos Públicos)\nObjeto principal\nVocabulário Principal: 50730000\nNº: LOT-0006\nDescrição do Lote: Lote 5 - Radar de Arouca, Estação Meteorológica de Viseu, Estação Sísmica de Vila Real e  Estação Meteorológica de Viana do Castelo\nPreço base s/IVA: 5.000,00 EUR\nClassificação CPV (Vocabulário Comum para os Contratos Públicos)\nObjeto principal\nVocabulário Principal: 50730000\nNº: LOT-0007\nDescrição do Lote: Lote 6 -  Estação Meteorológica de Évora\nPreço base s/IVA: 2.600,00 EUR\nClassificação CPV (Vocabulário Comum para os Contratos Públicos)\nObjeto principal\nVocabulário Principal: 50730000\nNº: LOT-0008\nDescrição do Lote: Lote 7 - Estação Meteorológica de Castelo Branco\nPreço base s/IVA: 2.900,00 EUR\nClassificação CPV (Vocabulário Comum para os Contratos Públicos)\nObjeto principal\nVocabulário Principal: 50730000\n\n7 - INDICAÇÕES ADICIONAIS\nO contrato envolve aquisição conjunta (satisfação de várias entidades)? Não\nO contrato é adjudicado por uma central de compras? Não\n\n8 - TÉCNICAS\nO concurso destina-se à celebração de um acordo-quadro? Inexistência de acordo-quadro\nÉ utilizado um leilão eletrónico? Não\nÉ adotada uma fase de negociação? Não\nSistema de Aquisição Dinâmico: Inexistência de sistema de aquisição dinâmico\n\n9 - LOCAL DA EXECUÇÃO DO CONTRATO\nLOCAL DA EXECUÇÃO DO CONTRATO (PROCEDIMENTO)\nLOCAL DA EXECUÇÃO DO CONTRATO (LOTE)\nIdentificador do Lote: LOT-0001\nPaís: Portugal\nNUT III: PT170\nLocalidade: Lisboa \nDistrito: Lisboa\nConcelho: Todos\nFreguesia: Todas\nIdentificador do Lote: LOT-0002\nPaís: Portugal\nNUT III: PT170\nLocalidade: Lisboa \nDistrito: Lisboa\nConcelho: Lisboa\nFreguesia: Freguesia de Olivais\nIdentificador do Lote: LOT-0003\nPaís: Portugal\nNUT III: PT150\nLocalidade: Algarve \nDistrito: Faro\nConcelho: Todos\nFreguesia: Todas\nIdentificador do Lote: LOT-0004\nPaís: Portugal\nNUT III: PT200\nLocalidade: Açores\nDistrito: Região Autónoma dos Açores\nConcelho: Todos\nFreguesia: Todas\nIdentificador do Lote: LOT-0005\nPaís: Portugal\nNUT III: PT300\nLocalidade: Madeira \nDistrito: Região Autónoma da Madeira\nConcelho: Todos\nFreguesia: Todas\nIdentificador do Lote: LOT-0006\nPaís: Portugal\nNUT III: PTZZZ\nLocalidade: Todas \nDistrito: Todos\nConcelho: Todos\nFreguesia: Todas\nIdentificador do Lote: LOT-0007\nPaís: Portugal\nNUT III: PT184\nLocalidade: Évora \nDistrito: Évora\nConcelho: Évora\nFreguesia: Todas\nIdentificador do Lote: LOT-0008\nPaís: Portugal\nNUT III: PT16H\nLocalidade: Castelo Branco \nDistrito: Castelo Branco\nConcelho: Castelo Branco\nFreguesia: Todas\n\n10 - PRAZO DE EXECUÇÃO DO CONTRATO\nIdentificador do Lote: LOT-0001\nPrazo de execução do contrato: 24 MESES\nPrevisão de renovações: Não\nIdentificador do Lote: LOT-0002\nPrazo de execução do contrato: 24 MESES\nPrevisão de renovações: Não\nIdentificador do Lote: LOT-0003\nPrazo de execução do contrato: 24 MESES\nPrevisão de renovações: Não\nIdentificador do Lote: LOT-0004\nPrazo de execução do contrato: 24 MESES\nPrevisão de renovações: Não\nIdentificador do Lote: LOT-0005\nPrazo de execução do contrato: 24 MESES\nPrevisão de renovações: Não\nIdentificador do Lote: LOT-0006\nPrazo de execução do contrato: 24 MESES\nPrevisão de renovações: Não\nIdentificador do Lote: LOT-0007\nPrazo de execução do contrato: 24 MESES\nPrevisão de renovações: Não\nIdentificador do Lote: LOT-0008\nPrazo de execução do contrato: 24 MESES\nPrevisão de renovações: Não\n\n11 - FUNDOS EU\nIdentificador do Lote: LOT-0001; LOT-0002; LOT-0003; LOT-0004; LOT-0005; LOT-0006; LOT-0007; LOT-0008\nTêm fundos EU? Não\n\n12 - DOCUMENTOS DE HABILITAÇÃO\nHabilitação para o exercício da atividade profissional: Não\n\n13 - CONDIÇÕES DE APRESENTAÇÃO\nPlataforma eletrónica utilizada pela entidade adjudicante: ANOGOV\nURL para Apresentação: https://www.anogov.com/op-ipma/faces/\nAdmissibilidade da apresentação de propostas variantes: Não autorizado\nPrazo para apresentação das propostas: 01-10-2025 23:59\nPrazo durante o qual os concorrentes são obrigados a manter as respetivas propostas: 66 dias a contar do termo do prazo para a apresentação das propostas\nApresentação de Catálogo Eletrónico: Permitido\nIndicação de Subcontratação na Proposta: Inexistência de indicação de subcontratação\n\n14 - PRESTAÇÃO DE CAUÇÃO\nPrestação de caução: Não\n\n15 - FORNECIMENTO DAS PEÇAS DO CONCURSO, APRESENTAÇÃO DE PEDIDOS DE PARTICIPAÇÃO E APRESENTAÇÃO DAS PROPOSTAS\nLink para acesso às peças do concurso (URL): https://www.anogov.com/op-ipma/faces/app/acessoDocs.jsp?codigoAcesso=EeS44nozHcjfDzjKRCTf511sl28cdvf8C52MQ5nuNvkfjklFcP\n\n20 - OUTROS REQUISITOS\nIdentificador do Lote: LOT-0001; LOT-0002; LOT-0003; LOT-0004; LOT-0005; LOT-0006; LOT-0007; LOT-0008\nInformação sobre contratos reservados. Aplica-se a contratos reservados (54º-A)? Não\n\n21 - CRITÉRIO DE ADJUDICAÇÃO\nO Critério de adjudicação é diferenciado por lote? Não\nMultifator: Não\nMonofator:\nNome: Preço\n\n24 - CONDIÇÕES DO CONTRATO\nIdentificador do Lote: LOT-0001; LOT-0002; LOT-0003; LOT-0004; LOT-0005; LOT-0006; LOT-0007; LOT-0008\nFaturação Eletrónica: Permitido\nObrigação de Subcontratação:\nCódigo da Obrigação de Subcontratação: Não é aplicável nenhuma obrigação de subcontratação.\n\n25 - COMPRA PÚBLICA ESTRATÉGICA\nCompra Pública Estratégica: Inexistência de contratação pública estratégica\n\n26 - INFORMAÇÕES ADICIONAIS\nIdentificador do Lote: LOT-0001\nContrato adequado para PME: Sim\nCobertura ACP (Acordo dos Contratos Públicos da Organização Mundial do Comércio): Não\nIdentificador do Lote: LOT-0002\nContrato adequado para PME: Sim\nCobertura ACP (Acordo dos Contratos Públicos da Organização Mundial do Comércio): Não\nIdentificador do Lote: LOT-0003\nContrato adequado para PME: Sim\nCobertura ACP (Acordo dos Contratos Públicos da Organização Mundial do Comércio): Não\nIdentificador do Lote: LOT-0004\nContrato adequado para PME: Sim\nCobertura ACP (Acordo dos Contratos Públicos da Organização Mundial do Comércio): Não\nIdentificador do Lote: LOT-0005\nContrato adequado para PME: Sim\nCobertura ACP (Acordo dos Contratos Públicos da Organização Mundial do Comércio): Não\nIdentificador do Lote: LOT-0006\nContrato adequado para PME: Sim\nCobertura ACP (Acordo dos Contratos Públicos da Organização Mundial do Comércio): Não\nIdentificador do Lote: LOT-0007\nContrato adequado para PME: Sim\nCobertura ACP (Acordo dos Contratos Públicos da Organização Mundial do Comércio): Não\nIdentificador do Lote: LOT-0008\nContrato adequado para PME: Sim\nCobertura ACP (Acordo dos Contratos Públicos da Organização Mundial do Comércio): Não\n\n27 - IDENTIFICAÇÃO E CONTACTOS DO ÓRGÃO DE RECURSOS ADMINISTRATIVOS\nDesignação: Instituto Português do Mar e da Atmosfera, I.P.\nEndereço: Rua C do Aeroporto de Lisboa\nCódigo postal: 1749-077\nLocalidade: Lisboa\nEndereço eletrónico: presidencia@ipma.pt\n\n28 - IDENTIFICAÇÃO DO(S) AUTOR(ES) DE ANÚNCIO\nNome: Leonor Silva \nCargo: Técnica superior \n419563683",
    "nipc": "510265600",
    "distrito": "Lisboa",
    "concelho": "Lisboa",
    "freguesia": "Freguesia de Olivais",
    "site": "https://www.ipma.pt",
    "email": "contratacao@ipma.pt",
    "designacao_contrato": "Aquisição de serviços de manutenção preventiva para os equipamentos de AVAC",
    "descricao": "Aquisição de serviços de manutenção preventiva para os equipamentos de AVAC",
    "preco_base": "78.480,00 EUR",
    "prazo_execucao": "24 MESES",
    "prazo_apresentacao_propostas": "01-10-2025 23:59",
    "fundos_eu": "Não",
    "plataforma_eletronica": "ANOGOV",
    "url_procedimento": "https://www.anogov.com/op-ipma/faces/",
    "autor_nome": "Leonor Silva",
    "autor_cargo": "Técnica superior"
  },
  {
    "numero_procedimento": "N/A",
    "entidade": "Instituto Português do Mar e da Atmosfera,I.P.",
    "link": "https://diariodarepublica.pt/dr/detalhe/contrato-publico/25017-936209679",
    "detalhes_completos": "1 - IDENTIFICAÇÃO E CONTACTOS DA ENTIDADE ADJUDICANTE\nDesignação da entidade adjudicante: Instituto Português do Mar e da Atmosfera,I.P.\nNIPC: 510265600\nServiço/Órgão/Pessoa de contacto: Conselho Diretivo\nEndereço: Rua C do Aeroporto de Lisboa\nCódigo postal: 1749-077\nLocalidade: Lisboa\nPaís: Portugal\nNUT III: PT170\nDistrito: Lisboa\nConcelho: Lisboa\nFreguesia: Freguesia de Olivais\nTelefone: 218447000\nFax: 218402370\nEndereço da Entidade (URL): https://www.ipma.pt\nEndereço Eletrónico: contratacao@ipma.pt\nFunção da Organização: Adquirente\nNorma jurídica da Entidade Adjudicante: Autoridade da administração central\nÁrea de atividade da Entidade Adjudicante: Atividades aeroportuárias\n\n2 - JORNAL OFICIAL DA UNIÃO EUROPEIA\nO procedimento a que este anúncio diz respeito também é publicitado no Jornal Oficial da União Europeia? Não\n\n3 - AVISO\nModelo de Anúncio: Concurso público\nData de Envio do Anúncio: 22-09-2025\n\n5 - PROCESSO\nTipo de Procedimento: Concurso público\nPreço base do procedimento: Sim\nValor do preço base do procedimento: 97.914,00 EUR\nProcedimento com lotes? Não\n\n6 - OBJETO DO CONTRATO\nNúmero de referência interna: CP 180/2025\nDesignação do contrato: Aquisição de serviços de manutenção corretiva/preventiva nas instalações do Instituto Português do Mar e da Atmosfera, I.P\nDescrição: Aquisição de serviços de manutenção corretiva/preventiva nas instalações do Instituto Português do Mar e da Atmosfera, I.P\nTipo de Contrato Principal: Aquisição de Serviços\nTipo de Contrato: Aquisição de Serviços\nClassificação CPV (Vocabulário Comum para os Contratos Públicos)\nObjeto principal\nVocabulário Principal: 50324200\nPreço base s/IVA: 97.914,00 EUR\n\n7 - INDICAÇÕES ADICIONAIS\nO contrato envolve aquisição conjunta (satisfação de várias entidades)? Não\nO contrato é adjudicado por uma central de compras? Não\n\n8 - TÉCNICAS\nO concurso destina-se à celebração de um acordo-quadro? Inexistência de acordo-quadro\nÉ utilizado um leilão eletrónico? Não\nÉ adotada uma fase de negociação? Não\nSistema de Aquisição Dinâmico: Inexistência de sistema de aquisição dinâmico\n\n9 - LOCAL DA EXECUÇÃO DO CONTRATO\nLOCAL DA EXECUÇÃO DO CONTRATO (PROCEDIMENTO)\nPaís: Portugal\nNUT III: PT170\nLocalidade: Lisboa \nDistrito: Lisboa\nConcelho: Todos\nFreguesia: Todas\n\n10 - PRAZO DE EXECUÇÃO DO CONTRATO\nPrazo de execução do contrato: 36 MESES\nPrevisão de renovações: Não\n\n11 - FUNDOS EU\nTêm fundos EU? Não\n\n12 - DOCUMENTOS DE HABILITAÇÃO\nHabilitação para o exercício da atividade profissional: Não\n\n13 - CONDIÇÕES DE APRESENTAÇÃO\nPlataforma eletrónica utilizada pela entidade adjudicante: ANOGOV\nURL para Apresentação: https://www.anogov.com/op-ipma/faces/\nAdmissibilidade da apresentação de propostas variantes: Não autorizado\nPrazo para apresentação das propostas: 28-09-2025 23:59\nPrazo durante o qual os concorrentes são obrigados a manter as respetivas propostas: 66 dias a contar do termo do prazo para a apresentação das propostas\nApresentação de Catálogo Eletrónico: Permitido\nIndicação de Subcontratação na Proposta: Inexistência de indicação de subcontratação\n\n14 - PRESTAÇÃO DE CAUÇÃO\nPrestação de caução: Não\n\n15 - FORNECIMENTO DAS PEÇAS DO CONCURSO, APRESENTAÇÃO DE PEDIDOS DE PARTICIPAÇÃO E APRESENTAÇÃO DAS PROPOSTAS\nLink para acesso às peças do concurso (URL): https://www.anogov.com/op-ipma/faces/app/acessoDocs.jsp?codigoAcesso=A1HBw1cxcY8GLhKPRusfqdhQ4yt7DhFYAUsbijHzQgYMf11369\n\n20 - OUTROS REQUISITOS\nInformação sobre contratos reservados. Aplica-se a contratos reservados (54º-A)? Não\n\n21 - CRITÉRIO DE ADJUDICAÇÃO\nMultifator: Não\nMonofator:\nNome: Preço\n\n24 - CONDIÇÕES DO CONTRATO\nFaturação Eletrónica: Permitido\nObrigação de Subcontratação:\nCódigo da Obrigação de Subcontratação: Não é aplicável nenhuma obrigação de subcontratação.\n\n25 - COMPRA PÚBLICA ESTRATÉGICA\nCompra Pública Estratégica: Inexistência de contratação pública estratégica\n\n26 - INFORMAÇÕES ADICIONAIS\nContrato adequado para PME: Sim\nCobertura ACP (Acordo dos Contratos Públicos da Organização Mundial do Comércio): Não\n\n27 - IDENTIFICAÇÃO E CONTACTOS DO ÓRGÃO DE RECURSOS ADMINISTRATIVOS\nDesignação: Instituto Português do Mar e da Atmosfera, I.P.\nEndereço: Rua C do Aeroporto de Lisboa\nCódigo postal: 1749-077\nLocalidade: Lisboa\nEndereço eletrónico: presidencia@ipma.pt\n\n28 - IDENTIFICAÇÃO DO(S) AUTOR(ES) DE ANÚNCIO\nNome: Leonor Silva \nCargo: Técnica superior \n419564874",
    "nipc": "510265600",
    "distrito": "Lisboa",
    "concelho": "Lisboa",
    "freguesia": "Freguesia de Olivais",
    "site": "https://www.ipma.pt",
    "email": "contratacao@ipma.pt",
    "designacao_contrato": "Aquisição de serviços de manutenção corretiva/preventiva nas instalações do Instituto Português do Mar e da Atmosfera, I.P",
    "descricao": "Aquisição de serviços de manutenção corretiva/preventiva nas instalações do Instituto Português do Mar e da Atmosfera, I.P",
    "preco_base": "97.914,00 EUR",
    "prazo_execucao": "36 MESES",
    "prazo_apresentacao_propostas": "28-09-2025 23:59",
    "fundos_eu": "Não",
    "plataforma_eletronica": "ANOGOV",
    "url_procedimento": "https://www.anogov.com/op-ipma/faces/",
    "autor_nome": "Leonor Silva",
    "autor_cargo": "Técnica superior"
  },
  {
    "numero_procedimento": "N/A",
    "entidade": "AGERE – Emp. Águas, Efluentes e Resíduos de Braga",
    "link": "https://diariodarepublica.pt/dr/detalhe/contrato-publico/25018-936209685",
    "detalhes_completos": "1 - IDENTIFICAÇÃO E CONTACTOS DA ENTIDADE ADJUDICANTE\nDesignação da entidade adjudicante: AGERE – Emp. Águas, Efluentes e Resíduos de Braga\nNIPC: 504807692\nEndereço: Praça Conde de Agrolongo, 115\nCódigo postal: 4700-312\nLocalidade: Braga\nPaís: Portugal\nNUT III: PT112\nDistrito: Braga\nConcelho: Braga\nFreguesia: Todas\nTelefone: 253205000\nFax: 253205075\nEndereço da Entidade (URL): www.agere.pt\nEndereço Eletrónico: agere@agere.pt\neDelivery Gateway (URL): https://community.vortal.biz/public/\nFunção da Organização: Adquirente\nNorma jurídica da Entidade Adjudicante: Empresa pública\nÁrea de atividade da Entidade Adjudicante: Atividades relacionadas com a água\n\n2 - JORNAL OFICIAL DA UNIÃO EUROPEIA\nO procedimento a que este anúncio diz respeito também é publicitado no Jornal Oficial da União Europeia? Não\n\n3 - AVISO\nModelo de Anúncio: Concurso público\nData de Envio do Anúncio: 23-09-2025\n\n5 - PROCESSO\nTipo de Procedimento: Concurso público\nPreço base do procedimento: Sim\nValor do preço base do procedimento: 353.454,89 EUR\nProcedimento com lotes? Não\n\n6 - OBJETO DO CONTRATO\nNúmero de referência interna: CP EMP DC 10/2025\nDesignação do contrato: EMPREITADA: “PROLONGAMENTOS DE REDES DE ABASTECIMENTO DE ÁGUA E DE SANEAMENTO DE ÁGUAS RESIDUAIS E INSTALAÇÕES ELEVATÓRIAS”.\nDescrição: EMPREITADA: “PROLONGAMENTOS DE REDES DE ABASTECIMENTO DE ÁGUA E DE SANEAMENTO DE ÁGUAS RESIDUAIS E INSTALAÇÕES ELEVATÓRIAS”.\nTipo de Contrato Principal: Empreitada de Obras Públicas\nTipo de Contrato: Empreitada de Obras Públicas\nClassificação CPV (Vocabulário Comum para os Contratos Públicos)\nObjeto principal\nVocabulário Principal: 45231300\nPreço base s/IVA: 353.454,89 EUR\n\n7 - INDICAÇÕES ADICIONAIS\nO contrato envolve aquisição conjunta (satisfação de várias entidades)? Não\nO contrato é adjudicado por uma central de compras? Não\n\n8 - TÉCNICAS\nO concurso destina-se à celebração de um acordo-quadro? Inexistência de acordo-quadro\nÉ utilizado um leilão eletrónico? Não\nÉ adotada uma fase de negociação? Não\nSistema de Aquisição Dinâmico: Inexistência de sistema de aquisição dinâmico\n\n9 - LOCAL DA EXECUÇÃO DO CONTRATO\nLOCAL DA EXECUÇÃO DO CONTRATO (PROCEDIMENTO)\nPaís: Portugal\nNUT III: PT112\nLocalidade: Braga\nDistrito: Braga\nConcelho: Braga\nFreguesia: União das Freguesias de Braga (São José de São Lázaro e São João do Souto)\n\n10 - PRAZO DE EXECUÇÃO DO CONTRATO\nPrazo de execução do contrato: 150 DIAS\nPrevisão de renovações: Não\n\n11 - FUNDOS EU\nTêm fundos EU? Não\n\n12 - DOCUMENTOS DE HABILITAÇÃO\nHabilitação para o exercício da atividade profissional: Não\n\n13 - CONDIÇÕES DE APRESENTAÇÃO\nPlataforma eletrónica utilizada pela entidade adjudicante: VORTAL\nURL para Apresentação: https://community.vortal.biz/public/\nAdmissibilidade da apresentação de propostas variantes: Não autorizado\nPrazo para apresentação das propostas: 07-10-2025 17:00\nPrazo durante o qual os concorrentes são obrigados a manter as respetivas propostas: 66 dias a contar do termo do prazo para a apresentação das propostas\nIndicação de Subcontratação na Proposta: Inexistência de indicação de subcontratação\n\n14 - PRESTAÇÃO DE CAUÇÃO\nPrestação de caução: Sim\nPercentagem: 5%\nDescrição da Garantia Exigida: definido no programa de procedimento\n\n15 - FORNECIMENTO DAS PEÇAS DO CONCURSO, APRESENTAÇÃO DE PEDIDOS DE PARTICIPAÇÃO E APRESENTAÇÃO DAS PROPOSTAS\nLink para acesso às peças do concurso (URL): https://community.vortal.biz/Public/public-tender-documents/eG5BeUtuMVhKZjNBeUZvNFNxdk5JK2QyRE5nYy9VMXRmUzVST2Jvb09SR216MktuUWtabzIvSTZ6U1puRGRBSHY4NGM5VE91eUJKbyttdEphVkV5TWc9PVFsejAw\n\n20 - OUTROS REQUISITOS\nInformação sobre contratos reservados. Aplica-se a contratos reservados (54º-A)? Não\n\n21 - CRITÉRIO DE ADJUDICAÇÃO\nMultifator: Não\nMonofator:\nNome: Preço\n\n24 - CONDIÇÕES DO CONTRATO\nFaturação Eletrónica: Permitido\nObrigação de Subcontratação:\nCódigo da Obrigação de Subcontratação: Não é aplicável nenhuma obrigação de subcontratação.\n\n25 - COMPRA PÚBLICA ESTRATÉGICA\nCompra Pública Estratégica: Inexistência de contratação pública estratégica\n\n26 - INFORMAÇÕES ADICIONAIS\nContrato adequado para PME: Sim\nCobertura ACP (Acordo dos Contratos Públicos da Organização Mundial do Comércio): Não\n\n27 - IDENTIFICAÇÃO E CONTACTOS DO ÓRGÃO DE RECURSOS ADMINISTRATIVOS\nDesignação: Conselho de Administração da AGERE EM\nEndereço: Praça Conde de Agrolongo, 115\nCódigo postal: 4700-312\nLocalidade: Braga\nTelefone: +351 253205001\nFax: +351 253205075\nEndereço eletrónico: administracao@agere.pt\n\n28 - IDENTIFICAÇÃO DO(S) AUTOR(ES) DE ANÚNCIO\nNome: Engª Paula Campos\nCargo: Administradora Executiva\n419565019",
    "nipc": "504807692",
    "distrito": "Braga",
    "concelho": "Braga",
    "freguesia": "Todas",
    "site": "www.agere.pt",
    "email": "agere@agere.pt",
    "designacao_contrato": "EMPREITADA: “PROLONGAMENTOS DE REDES DE ABASTECIMENTO DE ÁGUA E DE SANEAMENTO DE ÁGUAS RESIDUAIS E INSTALAÇÕES ELEVATÓRIAS”.",
    "descricao": "EMPREITADA: “PROLONGAMENTOS DE REDES DE ABASTECIMENTO DE ÁGUA E DE SANEAMENTO DE ÁGUAS RESIDUAIS E INSTALAÇÕES ELEVATÓRIAS”.",
    "preco_base": "353.454,89 EUR",
    "prazo_execucao": "150 DIAS",
    "prazo_apresentacao_propostas": "07-10-2025 17:00",
    "fundos_eu": "Não",
    "plataforma_eletronica": "VORTAL",
    "url_procedimento": "https://community.vortal.biz/public/",
    "autor_nome": "Engª Paula Campos",
    "autor_cargo": "Administradora Executiva"
  },
  {
    "numero_procedimento": "N/A",
    "entidade": "Câmara Municipal de Viseu",
    "link": "https://diariodarepublica.pt/dr/detalhe/contrato-publico/25019-936209686",
    "detalhes_completos": "1 - IDENTIFICAÇÃO E CONTACTOS DA ENTIDADE ADJUDICANTE\nDesignação da entidade adjudicante: Câmara Municipal de Viseu\nNIPC: 506697320\nServiço/Órgão/Pessoa de contacto: Câmara Municipal de Viseu\nEndereço: Praça da República S/N\nCódigo postal: 3514-501\nLocalidade: Viseu\nPaís: Portugal\nNUT III: PT16G\nDistrito: Viseu\nConcelho: Viseu\nFreguesia: Freguesia de Viseu\nTelefone: 232427427\nFax: 232427742\nEndereço da Entidade (URL): www.cm-viseu.pt\nEndereço Eletrónico: obrasmunicipais@cmviseu.pt\neDelivery Gateway (URL): https://www.acingov.pt\nFunção da Organização: Adquirente\nNorma jurídica da Entidade Adjudicante: Organismo de direito público\nÁrea de atividade da Autoridade Adjudicante: Serviços públicos das administrações públicas\n\n2 - JORNAL OFICIAL DA UNIÃO EUROPEIA\nO procedimento a que este anúncio diz respeito também é publicitado no Jornal Oficial da União Europeia? Não\n\n3 - AVISO\nModelo de Anúncio: Concurso público\nData de Envio do Anúncio: 23-09-2025\n\n5 - PROCESSO\nTipo de Procedimento: Concurso público\nPreço base do procedimento: Sim\nValor do preço base do procedimento: 157.610,25 EUR\nProcedimento com lotes? Não\n\n6 - OBJETO DO CONTRATO\nNúmero de referência interna: 2025 99 EDOC_2025_85284\nDesignação do contrato: ELHV - Reabilitação de moradia na Rua do Povo nº 4 - Outeiro - Farminhão\nDescrição: ELHV - Reabilitação de moradia na Rua do Povo nº 4 - Outeiro - Farminhão\nTipo de Contrato Principal: Empreitada de Obras Públicas\nTipo de Contrato: Empreitada de Obras Públicas\nClassificação CPV (Vocabulário Comum para os Contratos Públicos)\nObjeto principal\nVocabulário Principal: 45210000\nPreço base s/IVA: 157.610,25 EUR\n\n7 - INDICAÇÕES ADICIONAIS\nO contrato envolve aquisição conjunta (satisfação de várias entidades)? Não\nO contrato é adjudicado por uma central de compras? Não\n\n8 - TÉCNICAS\nO concurso destina-se à celebração de um acordo-quadro? Inexistência de acordo-quadro\nÉ utilizado um leilão eletrónico? Não\nÉ adotada uma fase de negociação? Não\nSistema de Aquisição Dinâmico: Inexistência de sistema de aquisição dinâmico\n\n9 - LOCAL DA EXECUÇÃO DO CONTRATO\nLOCAL DA EXECUÇÃO DO CONTRATO (PROCEDIMENTO)\nPaís: Portugal\nNUT III: PT16G\nLocalidade: União das Freguesias de Boa Aldeia, Farminhão e Torredeita\nDistrito: Viseu\nConcelho: Viseu\nFreguesia: União das Freguesias de Boa Aldeia, Farminhão e Torredeita\n\n10 - PRAZO DE EXECUÇÃO DO CONTRATO\nPrazo de execução do contrato: 364 DIAS\nPrevisão de renovações: Não\n\n11 - FUNDOS EU\nTêm fundos EU? Sim\n\n12 - DOCUMENTOS DE HABILITAÇÃO\nHabilitação para o exercício da atividade profissional: Sim\nTipo: Alvará\nDescrição: Alvará ou documento comprovativo da titularidade de alvará ou certificado de empreiteiro de obras públicas emitido pelo IMPIC, necessário para a execução da obra, contendo as seguintes categorias: : 1.ª, 2.ª, 4.ª, 5.ª, 6.ª, 7.ª, 8.ª, 9.ª subcategorias da 1.ª categoria, 1.ª, 2.ª, 3.ª, 7.ª, 8.ª e 10.ª subcategorias da 4.ª categoria e 1.ª, 2.ª e 11.ª subcategorias da 5.ª categoria. A 1.ª subcategoria da 1.ª categoria deve ser de valor que cubra a proposta.\n\n13 - CONDIÇÕES DE APRESENTAÇÃO\nPlataforma eletrónica utilizada pela entidade adjudicante: ACIN\nURL para Apresentação: https://www.acingov.pt\nAdmissibilidade da apresentação de propostas variantes: Não autorizado\nPrazo para apresentação das propostas: 07-10-2025 23:59\nPrazo durante o qual os concorrentes são obrigados a manter as respetivas propostas: 90 dias a contar do termo do prazo para a apresentação das propostas\nIndicação de Subcontratação na Proposta: Inexistência de indicação de subcontratação\n\n14 - PRESTAÇÃO DE CAUÇÃO\nPrestação de caução: Sim\nPercentagem: 5%\nDescrição da Garantia Exigida: O valor da caução é de 5.00% do preço contratual.\n\n15 - FORNECIMENTO DAS PEÇAS DO CONCURSO, APRESENTAÇÃO DE PEDIDOS DE PARTICIPAÇÃO E APRESENTAÇÃO DAS PROPOSTAS\nLink para acesso às peças do concurso (URL): https://www.acingov.pt/acingovprod/2/zonaPublica/zona_publica_c/donwloadProcedurePiece/OTc5NzU3\n\n20 - OUTROS REQUISITOS\nInformação sobre contratos reservados. Aplica-se a contratos reservados (54º-A)? Não\n\n21 - CRITÉRIO DE ADJUDICAÇÃO\nMultifator: Não\nMonofator:\nNome: Preço\n\n24 - CONDIÇÕES DO CONTRATO\nFaturação Eletrónica: Permitido\nObrigação de Subcontratação:\nCódigo da Obrigação de Subcontratação: Não é aplicável nenhuma obrigação de subcontratação.\n\n25 - COMPRA PÚBLICA ESTRATÉGICA\nCompra Pública Estratégica: Realização dos objetivos sociais\nCategorias da estratégia nacional: Outros\nOutra categoria (Descrição): N/A\nContratos Públicos Sociais: Outros\nCritério de Acessibilidade: Os critérios de acessibilidade para as pessoas com deficiência não estão incluídos porque o contrato não se destina a pessoas singulares\n\n26 - INFORMAÇÕES ADICIONAIS\nContrato adequado para PME: Sim\nCobertura ACP (Acordo dos Contratos Públicos da Organização Mundial do Comércio): Não\n\n27 - IDENTIFICAÇÃO E CONTACTOS DO ÓRGÃO DE RECURSOS ADMINISTRATIVOS\nDesignação: Câmara Municipal de Viseu\nEndereço: Praça da República S/N\nCódigo postal: 3514-501\nLocalidade: Viseu\nTelefone: 232427427\nFax: 232427742\nEndereço eletrónico: obrasmunicipais@cmviseu.pt\nPrazo de interposição do recurso: 5 dias\n\n28 - IDENTIFICAÇÃO DO(S) AUTOR(ES) DE ANÚNCIO\nNome: Ângela Isabel Martins Fernandes\nCargo: Assistente Técnico\n419558912",
    "nipc": "506697320",
    "distrito": "Viseu",
    "concelho": "Viseu",
    "freguesia": "Freguesia de Viseu",
    "site": "www.cm-viseu.pt",
    "email": "obrasmunicipais@cmviseu.pt",
    "designacao_contrato": "ELHV - Reabilitação de moradia na Rua do Povo nº 4 - Outeiro - Farminhão",
    "descricao": "ELHV - Reabilitação de moradia na Rua do Povo nº 4 - Outeiro - Farminhão",
    "preco_base": "157.610,25 EUR",
    "prazo_execucao": "364 DIAS",
    "prazo_apresentacao_propostas": "07-10-2025 23:59",
    "fundos_eu": "Sim",
    "plataforma_eletronica": "ACIN",
    "url_procedimento": "https://www.acingov.pt",
    "autor_nome": "Ângela Isabel Martins Fernandes",
    "autor_cargo": "Assistente Técnico"
  }
]