[
  {
    "numero_procedimento": "N/A",
    "entidade": "AnÃºncio de procedimento  n.Âº 27789/2025  -  DiÃ¡rio da RepÃºblica n.Âº 205/2025, SÃ©rie II de 2025-10-23",
    "link": "https://diariodarepublica.pt/dr/detalhe/contrato-publico/27789-941706029"
  },
  {
    "numero_procedimento": "N/A",
    "entidade": "Centro de Formação Profissional das Pescas e do Mar (FOR-MAR)",
    "link": "https://diariodarepublica.pt/dr/detalhe/contrato-publico/27790-941706032",
    "detalhes_completos": "1 - IDENTIFICAÇÃO E CONTACTOS DA ENTIDADE ADJUDICANTE\nDesignação da entidade adjudicante: Centro de Formação Profissional das Pescas e do Mar (FOR-MAR)\nNIPC: 508590582\nEndereço: Av. Brasília, edifício FOR-MAR   Pedrouços\nCódigo postal: 1400-038\nLocalidade: Lisboa\nPaís: Portugal\nNUT III: PT170\nDistrito: Lisboa\nConcelho: Lisboa\nFreguesia: Todas\nTelefone: 213037100\nFax: 213037199\nEndereço da Entidade (URL): https://for-mar.pt/\nEndereço Eletrónico: maria.gita@for-mar.pt\neDelivery Gateway (URL): https://community.vortal.biz/public/\nFunção da Organização: Adquirente\nNorma jurídica da Entidade Adjudicante: Organismo de direito público\nÁrea de atividade da Autoridade Adjudicante: Educação\n\n2 - JORNAL OFICIAL DA UNIÃO EUROPEIA\nO procedimento a que este anúncio diz respeito também é publicitado no Jornal Oficial da União Europeia? Não\n\n3 - AVISO\nModelo de Anúncio: Concurso público\nData de Envio do Anúncio: 22-10-2025\n\n5 - PROCESSO\nTipo de Procedimento: Concurso público\nPreço base do procedimento: Sim\nValor do preço base do procedimento: 67.370,00 EUR\nProcedimento com lotes? Sim\nNº Máx. de Lotes Autorizado: 4\nNúmero máximo de lotes que podem ser adjudicados a um concorrente: 4\n\n6 - OBJETO DO CONTRATO\nNúmero de referência interna: 372025CP | Reenchimento Jangadas e Aq.Garrafas CO2\nDesignação do contrato: Aquisição de Serviços de Reenchimento de Jangadas e Aquisição de garrafas CO2 de 33grs para coletes insufláveis para a formação para o ano 2026\nDescrição: Aquisição de Serviços de Reenchimento de Jangadas e Aquisição de garrafas CO2 de 33grs para coletes insufláveis para a formação para o ano 2026\nTipo de Contrato Principal: Aquisição de Serviços\nTipo de Contrato: Aquisição de Serviços\nClassificação CPV (Vocabulário Comum para os Contratos Públicos)\nObjeto principal\nVocabulário Principal: 50241100\nPreço base s/IVA: 67.370,00 EUR\nLotes: \nNº: LOT-0001\nDescrição do Lote: Lote 1\nPreço base s/IVA: 28.260,00 EUR\nClassificação CPV (Vocabulário Comum para os Contratos Públicos)\nObjeto principal\nVocabulário Principal: 50241100\nNº: LOT-0002\nDescrição do Lote: Lote 2\nPreço base s/IVA: 16.380,00 EUR\nClassificação CPV (Vocabulário Comum para os Contratos Públicos)\nObjeto principal\nVocabulário Principal: 50241100\nNº: LOT-0003\nDescrição do Lote: Lote 3\nPreço base s/IVA: 8.125,00 EUR\nClassificação CPV (Vocabulário Comum para os Contratos Públicos)\nObjeto principal\nVocabulário Principal: 50241100\nNº: LOT-0004\nDescrição do Lote: Lote 4\nPreço base s/IVA: 14.605,00 EUR\nClassificação CPV (Vocabulário Comum para os Contratos Públicos)\nObjeto principal\nVocabulário Principal: 50241100\n\n7 - INDICAÇÕES ADICIONAIS\nO contrato envolve aquisição conjunta (satisfação de várias entidades)? Não\nO contrato é adjudicado por uma central de compras? Não\n\n8 - TÉCNICAS\nO concurso destina-se à celebração de um acordo-quadro? Inexistência de acordo-quadro\nÉ utilizado um leilão eletrónico? Não\nÉ adotada uma fase de negociação? Não\nSistema de Aquisição Dinâmico: Inexistência de sistema de aquisição dinâmico\n\n9 - LOCAL DA EXECUÇÃO DO CONTRATO\nLOCAL DA EXECUÇÃO DO CONTRATO (PROCEDIMENTO)\nPaís: Portugal\nNUT III: PT11A\nLocalidade: Área Metropolitana do Porto\nDistrito: Porto\nConcelho: Porto\nFreguesia: Todas\nLOCAL DA EXECUÇÃO DO CONTRATO (LOTE)\nIdentificador do Lote: LOT-0001; LOT-0002; LOT-0003; LOT-0004\nPaís: Portugal\nNUT III: PT11A\nLocalidade: Área Metropolitana do Porto\nDistrito: Porto\nConcelho: Porto\nFreguesia: Todas\nIdentificador do Lote: LOT-0001; LOT-0002; LOT-0003; LOT-0004\nPaís: Portugal\nNUT III: PT150\nLocalidade: Faro\nDistrito: Faro\nConcelho: Olhão\nFreguesia: Todas\nIdentificador do Lote: LOT-0001; LOT-0002; LOT-0003; LOT-0004\nPaís: Portugal\nNUT III: PT11A\nLocalidade: Área Metropolitana do Porto\nDistrito: Porto\nConcelho: Porto\nFreguesia: Todas\nIdentificador do Lote: LOT-0001; LOT-0002; LOT-0003; LOT-0004\nPaís: Portugal\nNUT III: PT170\nLocalidade: Lisboa\nDistrito: Lisboa\nConcelho: Lisboa\nFreguesia: Todas\nIdentificador do Lote: LOT-0001; LOT-0002; LOT-0003; LOT-0004\nPaís: Portugal\nNUT III: PT16E\nLocalidade: Coimbra\nDistrito: Coimbra\nConcelho: Figueira da Foz\nFreguesia: Todas\n\n10 - PRAZO DE EXECUÇÃO DO CONTRATO\nIdentificador do Lote: LOT-0001; LOT-0002; LOT-0003; LOT-0004\nPrazo de execução do contrato: 12 MESES\nPrevisão de renovações: Não\n\n11 - FUNDOS EU\nIdentificador do Lote: LOT-0001; LOT-0002; LOT-0003; LOT-0004\nTêm fundos EU? Não\n\n12 - DOCUMENTOS DE HABILITAÇÃO\nHabilitação para o exercício da atividade profissional: Não\n\n13 - CONDIÇÕES DE APRESENTAÇÃO\nPlataforma eletrónica utilizada pela entidade adjudicante: VORTAL\nURL para Apresentação: https://community.vortal.biz/public/\nAdmissibilidade da apresentação de propostas variantes: Não autorizado\nPrazo para apresentação das propostas: 31-10-2025 23:59\nPrazo durante o qual os concorrentes são obrigados a manter as respetivas propostas: 66 dias a contar do termo do prazo para a apresentação das propostas\nIndicação de Subcontratação na Proposta: Inexistência de indicação de subcontratação\n\n14 - PRESTAÇÃO DE CAUÇÃO\nPrestação de caução: Não\n\n15 - FORNECIMENTO DAS PEÇAS DO CONCURSO, APRESENTAÇÃO DE PEDIDOS DE PARTICIPAÇÃO E APRESENTAÇÃO DAS PROPOSTAS\nLink para acesso às peças do concurso (URL): https://community.vortal.biz/Public/public-tender-documents/WVgxaHdTaGt1YU9IS3pINE8vcHpRYmsrdUlDMkFwSHFaSzNkYWtTcVJYYjVyODZVQis4MHAxM01zaGhoSWdkMGJ1SzlNWG5FRWhGZWRRWktsNmtONFE9PTdMYjZB\n\n20 - OUTROS REQUISITOS\nIdentificador do Lote: LOT-0001; LOT-0002; LOT-0003; LOT-0004\nInformação sobre contratos reservados. Aplica-se a contratos reservados (54º-A)? Não\n\n21 - CRITÉRIO DE ADJUDICAÇÃO\nO Critério de adjudicação é diferenciado por lote? Não\nMultifator: Não\nMonofator:\nNome: Preço\n\n24 - CONDIÇÕES DO CONTRATO\nIdentificador do Lote: LOT-0001; LOT-0002; LOT-0003; LOT-0004\nFaturação Eletrónica: Permitido\nObrigação de Subcontratação:\nCódigo da Obrigação de Subcontratação: Não é aplicável nenhuma obrigação de subcontratação.\n\n25 - COMPRA PÚBLICA ESTRATÉGICA\nCompra Pública Estratégica: Inexistência de contratação pública estratégica\n\n26 - INFORMAÇÕES ADICIONAIS\nIdentificador do Lote: LOT-0001; LOT-0002; LOT-0003; LOT-0004\nContrato adequado para PME: Sim\nCobertura ACP (Acordo dos Contratos Públicos da Organização Mundial do Comércio): Não\n\n27 - IDENTIFICAÇÃO E CONTACTOS DO ÓRGÃO DE RECURSOS ADMINISTRATIVOS\nDesignação: Conselho de Administração\nEndereço: AVENIDA BRASÍLIA, EDIFÍCIO FOR-MAR\nCódigo postal: 1400-038\nLocalidade: Lisboa\nTelefone: +351 213037100\nFax: +351 213037100\nEndereço eletrónico: for-mar@for-mar.pt\n\n28 - IDENTIFICAÇÃO DO(S) AUTOR(ES) DE ANÚNCIO\nNome: Maria João Morgado\nCargo: Técnica Superior\n419686196",
    "nipc": "508590582",
    "distrito": "Lisboa",
    "concelho": "Lisboa",
    "freguesia": "Todas",
    "site": "https://for-mar.pt/",
    "email": "maria.gita@for-mar.pt",
    "designacao_contrato": "Aquisição de Serviços de Reenchimento de Jangadas e Aquisição de garrafas CO2 de 33grs para coletes insufláveis para a formação para o ano 2026",
    "descricao": "Aquisição de Serviços de Reenchimento de Jangadas e Aquisição de garrafas CO2 de 33grs para coletes insufláveis para a formação para o ano 2026",
    "preco_base": "67.370,00 EUR",
    "prazo_execucao": "12 MESES",
    "prazo_apresentacao_propostas": "31-10-2025 23:59",
    "fundos_eu": "Não",
    "plataforma_eletronica": "VORTAL",
    "url_procedimento": "https://community.vortal.biz/public/",
    "autor_nome": "Maria João Morgado",
    "autor_cargo": "Técnica Superior"
  },
  {
    "numero_procedimento": "N/A",
    "entidade": "ATEC - Associação de Formação para a Indústria",
    "link": "https://diariodarepublica.pt/dr/detalhe/contrato-publico/27793-941706040",
    "detalhes_completos": "1 - IDENTIFICAÇÃO E CONTACTOS DA ENTIDADE ADJUDICANTE\nDesignação da entidade adjudicante: ATEC - Associação de Formação para a Indústria\nNIPC: 506803228\nServiço/Órgão/Pessoa de contacto: Departamento de Compras\nEndereço: Edifício ATEC, Quinta da Marqueza Palmela, Parque Industrial da Volkswagen Autoeuropa.\nCódigo postal: 2950-557\nLocalidade: Quinta do Anjo\nPaís: Portugal\nNUT III: PT170\nDistrito: Setúbal\nConcelho: Palmela\nFreguesia: Freguesia de Quinta do Anjo\nTelefone: 212107300\nFax: 212107300\nEndereço da Entidade (URL): www.atec.pt\nEndereço Eletrónico: compras@atec.pt\neDelivery Gateway (URL): https://www.acingov.pt\nFunção da Organização: Adquirente\nNorma jurídica da Entidade Adjudicante: Empresa pública\nÁrea de atividade da Autoridade Adjudicante: Educação\n\n2 - JORNAL OFICIAL DA UNIÃO EUROPEIA\nO procedimento a que este anúncio diz respeito também é publicitado no Jornal Oficial da União Europeia? Sim\n\n3 - AVISO\nModelo de Anúncio: Concurso público\nData de Envio do Anúncio: 20-10-2025\n\n5 - PROCESSO\nTipo de Procedimento: Concurso público\nPreço base do procedimento: Sim\nValor do preço base do procedimento: 324.200,00 EUR\nProcedimento com lotes? Sim\nNº Máx. de Lotes Autorizado: 8\nNúmero máximo de lotes que podem ser adjudicados a um concorrente: 8\n\n6 - OBJETO DO CONTRATO\nNúmero de referência interna: FP/CPI/1/2025/ATEC\nDesignação do contrato: Procedimento de Concurso Público Internacional para a para Aquisição de material elétrico e de soldadura\nDescrição: Aquisição de material elétrico e de soldadura\nOpções: Não\nTipo de Contrato Principal: Aquisição de Bens Móveis\nTipo de Contrato: Aquisição de Bens Móveis\nClassificação CPV (Vocabulário Comum para os Contratos Públicos)\nObjeto principal\nVocabulário Principal: 31681410\nPreço base s/IVA: 135.395,00 EUR\nObjeto Complementar\nVocabulário Principal: 31711000\nPreço base s/IVA: 107.420,00 EUR\nObjeto Complementar\nVocabulário Principal: 42661100\nPreço base s/IVA: 71.910,00 EUR\nObjeto Complementar\nVocabulário Principal: 42611000\nPreço base s/IVA: 9.475,00 EUR\nLotes: \nNº: LOT-0001\nDescrição do Lote: Material elétrico\nPreço base s/IVA: 135.395,00 EUR\nClassificação CPV (Vocabulário Comum para os Contratos Públicos)\nObjeto principal\nVocabulário Principal: 31681410\nNº: LOT-0002\nDescrição do Lote: Material eletrónico\nPreço base s/IVA: 57.600,00 EUR\nClassificação CPV (Vocabulário Comum para os Contratos Públicos)\nObjeto principal\nVocabulário Principal: 31711000\nNº: LOT-0003\nDescrição do Lote: Material Telecomunicações\nPreço base s/IVA: 360,00 EUR\nClassificação CPV (Vocabulário Comum para os Contratos Públicos)\nObjeto principal\nVocabulário Principal: 31711000\nNº: LOT-0004\nDescrição do Lote: Material Instrumentação/Controlo\nPreço base s/IVA: 2.395,00 EUR\nClassificação CPV (Vocabulário Comum para os Contratos Públicos)\nObjeto principal\nVocabulário Principal: 31711000\nNº: LOT-0005\nDescrição do Lote: Consumíveis Instrumentação/Controlo\nPreço base s/IVA: 25.245,00 EUR\nClassificação CPV (Vocabulário Comum para os Contratos Públicos)\nObjeto principal\nVocabulário Principal: 31711000\nNº: LOT-0006\nDescrição do Lote: Ferramentas e Ferragens\nPreço base s/IVA: 9.475,00 EUR\nClassificação CPV (Vocabulário Comum para os Contratos Públicos)\nObjeto principal\nVocabulário Principal: 42611000\nNº: LOT-0007\nDescrição do Lote: Materiais consumíveis Soldadura\nPreço base s/IVA: 71.910,00 EUR\nClassificação CPV (Vocabulário Comum para os Contratos Públicos)\nObjeto principal\nVocabulário Principal: 42661100\nNº: LOT-0008\nDescrição do Lote: Material Domótica KNX\nPreço base s/IVA: 21.820,00 EUR\nClassificação CPV (Vocabulário Comum para os Contratos Públicos)\nObjeto principal\nVocabulário Principal: 31711000\n\n7 - INDICAÇÕES ADICIONAIS\nO contrato envolve aquisição conjunta (satisfação de várias entidades)? Não\nO contrato é adjudicado por uma central de compras? Não\n\n8 - TÉCNICAS\nO concurso destina-se à celebração de um acordo-quadro? Inexistência de acordo-quadro\nÉ utilizado um leilão eletrónico? Não\nÉ adotada uma fase de negociação? Não\nSistema de Aquisição Dinâmico: Inexistência de sistema de aquisição dinâmico\n\n9 - LOCAL DA EXECUÇÃO DO CONTRATO\nLOCAL DA EXECUÇÃO DO CONTRATO (PROCEDIMENTO)\nPaís: Portugal\nNUT III: PT11A\nLocalidade: União das Freguesias de Perafita, Lavra e Santa Cruz do Bispo\nDistrito: Porto\nConcelho: Matosinhos\nFreguesia: União das Freguesias de Perafita, Lavra e Santa Cruz do Bispo\nPaís: Portugal\nNUT III: PT170\nLocalidade: Freguesia de Quinta do Anjo\nDistrito: Setúbal\nConcelho: Palmela\nFreguesia: Freguesia de Quinta do Anjo\nLOCAL DA EXECUÇÃO DO CONTRATO (LOTE)\nIdentificador do Lote: LOT-0001; LOT-0002; LOT-0003; LOT-0004; LOT-0005; LOT-0006; LOT-0007; LOT-0008\nPaís: Portugal\nNUT III: PT11A\nLocalidade: União das Freguesias de Perafita, Lavra e Santa Cruz do Bispo\nDistrito: Porto\nConcelho: Matosinhos\nFreguesia: União das Freguesias de Perafita, Lavra e Santa Cruz do Bispo\nIdentificador do Lote: LOT-0001; LOT-0002; LOT-0003; LOT-0004; LOT-0005; LOT-0006; LOT-0007; LOT-0008\nPaís: Portugal\nNUT III: PT170\nLocalidade: Freguesia de Quinta do Anjo\nDistrito: Setúbal\nConcelho: Palmela\nFreguesia: Freguesia de Quinta do Anjo\n\n10 - PRAZO DE EXECUÇÃO DO CONTRATO\nIdentificador do Lote: LOT-0001; LOT-0002; LOT-0003; LOT-0004; LOT-0005; LOT-0006; LOT-0007; LOT-0008\nPrazo de execução do contrato: 24 MESES\nPrevisão de renovações: Não\n\n11 - FUNDOS EU\nIdentificador do Lote: LOT-0001; LOT-0002; LOT-0003; LOT-0004; LOT-0005; LOT-0006; LOT-0007; LOT-0008\nTêm fundos EU? Não\n\n12 - DOCUMENTOS DE HABILITAÇÃO\nHabilitação para o exercício da atividade profissional: Não\n\n13 - CONDIÇÕES DE APRESENTAÇÃO\nPlataforma eletrónica utilizada pela entidade adjudicante: ACIN\nURL para Apresentação: https://www.acingov.pt\nAdmissibilidade da apresentação de propostas variantes: Não autorizado\nPrazo para apresentação das propostas: 19-11-2025 23:59\nPrazo durante o qual os concorrentes são obrigados a manter as respetivas propostas: 90 dias a contar do termo do prazo para a apresentação das propostas\nApresentação de Catálogo Eletrónico: Permitido\nIndicação de Subcontratação na Proposta: Inexistência de indicação de subcontratação\n\n14 - PRESTAÇÃO DE CAUÇÃO\nPrestação de caução: Não\n\n15 - FORNECIMENTO DAS PEÇAS DO CONCURSO, APRESENTAÇÃO DE PEDIDOS DE PARTICIPAÇÃO E APRESENTAÇÃO DAS PROPOSTAS\nLink para acesso às peças do concurso (URL): https://www.acingov.pt/acingovprod/2/zonaPublica/zona_publica_c/donwloadProcedurePiece/OTg3MTU0\n\n20 - OUTROS REQUISITOS\nIdentificador do Lote: LOT-0001; LOT-0002; LOT-0003; LOT-0004; LOT-0005; LOT-0006; LOT-0007; LOT-0008\nInformação sobre contratos reservados. Aplica-se a contratos reservados (54º-A)? Não\n\n21 - CRITÉRIO DE ADJUDICAÇÃO\nO Critério de adjudicação é diferenciado por lote? Não\nMultifator: Não\nMonofator:\nNome: Preço\n\n24 - CONDIÇÕES DO CONTRATO\nIdentificador do Lote: LOT-0001; LOT-0002; LOT-0003; LOT-0004; LOT-0005; LOT-0006; LOT-0007; LOT-0008\nFaturação Eletrónica: Necessário\nObrigação de Subcontratação:\nCódigo da Obrigação de Subcontratação: Não é aplicável nenhuma obrigação de subcontratação.\n\n25 - COMPRA PÚBLICA ESTRATÉGICA\nCompra Pública Estratégica: Inexistência de contratação pública estratégica\n\n26 - INFORMAÇÕES ADICIONAIS\nIdentificador do Lote: LOT-0001; LOT-0002; LOT-0003; LOT-0004; LOT-0005; LOT-0006; LOT-0007; LOT-0008\nContrato adequado para PME: Sim\nCobertura ACP (Acordo dos Contratos Públicos da Organização Mundial do Comércio): Não\n\n27 - IDENTIFICAÇÃO E CONTACTOS DO ÓRGÃO DE RECURSOS ADMINISTRATIVOS\nDesignação: Compras\nEndereço: Edifício ATEC, Quinta da Marqueza Palmela, Parque Industrial da Volkswagen Autoeuropa.\nCódigo postal: 2950-557\nLocalidade: Quinta do Anjo\nTelefone: 212107300\nFax: 212107300\nEndereço eletrónico: compras@atec.pt\nPrazo de interposição do recurso: 30 dias\n\n28 - IDENTIFICAÇÃO DO(S) AUTOR(ES) DE ANÚNCIO\nNome: David Parreira\nCargo: Gestão de Compras\n419674937",
    "nipc": "506803228",
    "distrito": "Setúbal",
    "concelho": "Palmela",
    "freguesia": "Freguesia de Quinta do Anjo",
    "site": "www.atec.pt",
    "email": "compras@atec.pt",
    "designacao_contrato": "Procedimento de Concurso Público Internacional para a para Aquisição de material elétrico e de soldadura",
    "descricao": "Aquisição de material elétrico e de soldadura",
    "preco_base": "135.395,00 EUR",
    "prazo_execucao": "24 MESES",
    "prazo_apresentacao_propostas": "19-11-2025 23:59",
    "fundos_eu": "Não",
    "plataforma_eletronica": "ACIN",
    "url_procedimento": "https://www.acingov.pt",
    "autor_nome": "David Parreira",
    "autor_cargo": "Gestão de Compras"
  },
  {
    "numero_procedimento": "N/A",
    "entidade": "Município de Arcos de Valdevez",
    "link": "https://diariodarepublica.pt/dr/detalhe/contrato-publico/27795-941706059",
    "detalhes_completos": "1 - IDENTIFICAÇÃO E CONTACTOS DA ENTIDADE ADJUDICANTE\nDesignação da entidade adjudicante: Município de Arcos de Valdevez\nNIPC: 505211696\nEndereço: Praça  Municipal\nCódigo postal: 4974-003\nLocalidade: Viana do Castelo\nPaís: Portugal\nNUT III: PT111\nDistrito: Viana do Castelo\nConcelho: Arcos de Valdevez\nFreguesia: União das Freguesias de Arcos de Valdevez (São Paio) e Giela\nTelefone: 258520500\nFax: 258520509\nEndereço da Entidade (URL): www.cmav.pt\nEndereço Eletrónico: geral@cmav.pt\neDelivery Gateway (URL): https://community.vortal.biz/public/\nFunção da Organização: Adquirente\nNorma jurídica da Entidade Adjudicante: Autoridade local\nÁrea de atividade da Autoridade Adjudicante: Serviços públicos das administrações públicas\n\n2 - JORNAL OFICIAL DA UNIÃO EUROPEIA\nO procedimento a que este anúncio diz respeito também é publicitado no Jornal Oficial da União Europeia? Não\n\n3 - AVISO\nModelo de Anúncio: Concurso público\nData de Envio do Anúncio: 22-10-2025\n\n5 - PROCESSO\nTipo de Procedimento: Concurso público\nPreço base do procedimento: Sim\nValor do preço base do procedimento: 500.000,00 EUR\nProcedimento com lotes? Não\n\n6 - OBJETO DO CONTRATO\nNúmero de referência interna: PO 597/2025\nDesignação do contrato: PO 597/2025 - Reabilitação das margens do Rio Vez - Pavimentos e passadiços\nDescrição: PO 597/2025 - Reabilitação das margens do Rio Vez - Pavimentos e passadiços\nTipo de Contrato Principal: Empreitada de Obras Públicas\nTipo de Contrato: Empreitada de Obras Públicas\nClassificação CPV (Vocabulário Comum para os Contratos Públicos)\nObjeto principal\nVocabulário Principal: 45262350\nPreço base s/IVA: 500.000,00 EUR\n\n7 - INDICAÇÕES ADICIONAIS\nO contrato envolve aquisição conjunta (satisfação de várias entidades)? Não\nO contrato é adjudicado por uma central de compras? Não\n\n8 - TÉCNICAS\nO concurso destina-se à celebração de um acordo-quadro? Inexistência de acordo-quadro\nÉ utilizado um leilão eletrónico? Não\nÉ adotada uma fase de negociação? Não\nSistema de Aquisição Dinâmico: Inexistência de sistema de aquisição dinâmico\n\n9 - LOCAL DA EXECUÇÃO DO CONTRATO\nLOCAL DA EXECUÇÃO DO CONTRATO (PROCEDIMENTO)\nPaís: Portugal\nNUT III: PT111\nLocalidade: Viana do Castelo\nDistrito: Viana do Castelo\nConcelho: Arcos de Valdevez\nFreguesia: União das Freguesias de Arcos de Valdevez (São Paio) e Giela\n\n10 - PRAZO DE EXECUÇÃO DO CONTRATO\nPrazo de execução do contrato: 180 DIAS\nPrevisão de renovações: Não\n\n11 - FUNDOS EU\nTêm fundos EU? Não\n\n12 - DOCUMENTOS DE HABILITAÇÃO\nHabilitação para o exercício da atividade profissional: Sim\nTipo: Alvará\nDescrição: Conforme descrito no artigo n.º 16.º do Programa de Procedimento\n\n13 - CONDIÇÕES DE APRESENTAÇÃO\nPlataforma eletrónica utilizada pela entidade adjudicante: VORTAL\nURL para Apresentação: https://community.vortal.biz/public/\nAdmissibilidade da apresentação de propostas variantes: Não autorizado\nPrazo para apresentação das propostas: 18-11-2025 18:00\nPrazo durante o qual os concorrentes são obrigados a manter as respetivas propostas: 120 dias a contar do termo do prazo para a apresentação das propostas\nIndicação de Subcontratação na Proposta: Inexistência de indicação de subcontratação\n\n14 - PRESTAÇÃO DE CAUÇÃO\nPrestação de caução: Sim\nPercentagem: 5%\nDescrição da Garantia Exigida: Conforme descrito no artigo 18.º do Programa de Procedimento\n\n15 - FORNECIMENTO DAS PEÇAS DO CONCURSO, APRESENTAÇÃO DE PEDIDOS DE PARTICIPAÇÃO E APRESENTAÇÃO DAS PROPOSTAS\nLink para acesso às peças do concurso (URL): https://community.vortal.biz/Public/public-tender-documents/bFI2WHF1VEhST3lCVDJCVytreDhpVVBQVzdWZTRMRndqdm9CZk1OVVVUQzlFQVU5cjlINmFqMXVmU0JKSDl5OGFhcGI0SGhEekVkYVhzVzc3QnFLeVE9PW54V2oz\n\n20 - OUTROS REQUISITOS\nInformação sobre contratos reservados. Aplica-se a contratos reservados (54º-A)? Não\n\n21 - CRITÉRIO DE ADJUDICAÇÃO\nMultifator: Sim\nFator: \nNome: Preço\nPonderação: 50%\nSubfatores: Não\nFator: \nNome: Qualidade\nPonderação: 50%\nSubfatores: Sim\nSubfatores: \nNome: Plano de Trabalhos (PT)\nPonderação : 50%; \nNome: Plano de Mão-de-obra (PMO)\nPonderação : 25%; \nNome: Plano de Equipamentos (PE)\nPonderação : 25%; \n\n24 - CONDIÇÕES DO CONTRATO\nFaturação Eletrónica: Permitido\nObrigação de Subcontratação:\nCódigo da Obrigação de Subcontratação: Não é aplicável nenhuma obrigação de subcontratação.\n\n25 - COMPRA PÚBLICA ESTRATÉGICA\nCompra Pública Estratégica: Redução dos impactos ambientais\nDescrição do Processo de Adjudicação Estratégico: Conforme as peças do procedimento\nCritérios de contratos Públicos Ecológicos: Critérios de contratação pública ecológica nacional\nCategorias da estratégia nacional: Manutenção de espaços públicos\nContratos Públicos Ecológicos: A proteção e o restauro da biodiversidade e dos ecossistemas\nDiretiva Veículos Não Poluentes: Não\nCritério de Acessibilidade: Os critérios de acessibilidade para as pessoas com deficiência não estão incluídos, com a seguinte justificação\nJustificação relativa à Acessibilidade: Não aplicável face ao objeto do contrato\n\n26 - INFORMAÇÕES ADICIONAIS\nContrato adequado para PME: Sim\nCobertura ACP (Acordo dos Contratos Públicos da Organização Mundial do Comércio): Não\n\n27 - IDENTIFICAÇÃO E CONTACTOS DO ÓRGÃO DE RECURSOS ADMINISTRATIVOS\nDesignação: Município de Arcos de Valdevez\nEndereço: Praça Municipal\nCódigo postal: 4974-003\nLocalidade: Arcos de Valdevez\nTelefone: +351 258520500\nFax: +351 258520509\nEndereço eletrónico: geral@cmav.pt\n\n28 - IDENTIFICAÇÃO DO(S) AUTOR(ES) DE ANÚNCIO\nNome: Olegário Gomes Gonçalves\nCargo: Presidente da Câmara\n419686447",
    "nipc": "505211696",
    "distrito": "Viana do Castelo",
    "concelho": "Arcos de Valdevez",
    "freguesia": "União das Freguesias de Arcos de Valdevez (São Paio) e Giela",
    "site": "www.cmav.pt",
    "email": "geral@cmav.pt",
    "designacao_contrato": "PO 597/2025 - Reabilitação das margens do Rio Vez - Pavimentos e passadiços",
    "descricao": "PO 597/2025 - Reabilitação das margens do Rio Vez - Pavimentos e passadiços",
    "preco_base": "500.000,00 EUR",
    "prazo_execucao": "180 DIAS",
    "prazo_apresentacao_propostas": "18-11-2025 18:00",
    "fundos_eu": "Não",
    "plataforma_eletronica": "VORTAL",
    "url_procedimento": "https://community.vortal.biz/public/",
    "autor_nome": "Olegário Gomes Gonçalves",
    "autor_cargo": "Presidente da Câmara"
  },
  {
    "numero_procedimento": "N/A",
    "entidade": "Secretaria Regional da Juventude, Habitação e Emprego",
    "link": "https://diariodarepublica.pt/dr/detalhe/contrato-publico/27797-941706061",
    "detalhes_completos": "1 - IDENTIFICAÇÃO E CONTACTOS DA ENTIDADE ADJUDICANTE\nDesignação da entidade adjudicante: Secretaria Regional da Juventude, Habitação e Emprego\nNIPC: 600087549\nServiço/Órgão/Pessoa de contacto: Diretor Regional da Habitação\nEndereço: Rua Dr. José Bruno Tavares Carreiro s/n\nCódigo postal: 9500-119\nLocalidade: Ponta Delgada\nPaís: Portugal\nNUT III: PT200\nDistrito: Região Autónoma dos Açores\nConcelho: Angra do Heroismo\nFreguesia: Todas\nTelefone: 296308000\nFax: 296628376\nEndereço da Entidade (URL): https://portal.azores.gov.pt/web/srjhe\nEndereço Eletrónico: drh.contratacaopublica@azores.gov.pt\neDelivery Gateway (URL): https://www.acingov.pt\nFunção da Organização: Adquirente\nNorma jurídica da Entidade Adjudicante: Organismo de direito público\nÁrea de atividade da Autoridade Adjudicante: Serviços públicos das administrações públicas\n\n2 - JORNAL OFICIAL DA UNIÃO EUROPEIA\nO procedimento a que este anúncio diz respeito também é publicitado no Jornal Oficial da União Europeia? Sim\n\n3 - AVISO\nModelo de Anúncio: Concurso público\nData de Envio do Anúncio: 20-10-2025\n\n5 - PROCESSO\nTipo de Procedimento: Concurso público\nPreço base do procedimento: Sim\nValor do preço base do procedimento: 870.100,00 EUR\nProcedimento com lotes? Sim\nNº Máx. de Lotes Autorizado: 3\nNúmero máximo de lotes que podem ser adjudicados a um concorrente: 3\n\n6 - OBJETO DO CONTRATO\nNúmero de referência interna: CCP/2025/25\nDesignação do contrato: Empreitada de Reabilitação de 14 Habitações Dispersas do Parque Habitacional da Região Autónoma dos Açores - Ilha Terceira\nDescrição: Reabilitação de 14 Habitações Dispersas do Parque Habitacional da Região Autónoma dos Açores - Ilha Terceira\nOpções: Não\nTipo de Contrato Principal: Empreitada de Obras Públicas\nTipo de Contrato: Empreitada de Obras Públicas\nClassificação CPV (Vocabulário Comum para os Contratos Públicos)\nObjeto principal\nVocabulário Principal: 45453100\nPreço base s/IVA: 870.100,00 EUR\nLotes: \nNº: LOT-0001\nDescrição do Lote: Constituído pelos seguintes imóveis: 1.1 Às nove, n.º 5, (Grota do Carneirinho) - Santa Bárbara - Angra do Heroísmo; 2.1 Caminho de Cima, n.º 20, (Canada do Terreiro) - Santa Bárbara - Angra do Heroísmo; 3.1 Ao Salto, n.º 78, (Quebradas) - São Bartolomeu - Angra do Heroísmo; 4.1 Canada do Passal, n.º 10 - São Mateus - Angra do Heroísmo.\nPreço base s/IVA: 272.800,00 EUR\nClassificação CPV (Vocabulário Comum para os Contratos Públicos)\nObjeto principal\nVocabulário Principal: 45453100\nNº: LOT-0002\nDescrição do Lote: Constituído pelos seguintes imóveis: 1.2 Chafariz Velho, n.º 25, (Ladeira Branca) - Santa Luzia - Angra do Heroísmo; 2.2 Canada Ponta Gorda, n.º 10, (Cam. da Esperança) - Porto Judeu- Angra do Heroísmo; 3.2 Terreiro do Paço, n.º 29 - Ribeirinha - Angra do Heroísmo; 4.2 São Luís, n.º 373 - São Bento - Angra do Heroísmo.\nPreço base s/IVA: 311.300,00 EUR\nClassificação CPV (Vocabulário Comum para os Contratos Públicos)\nObjeto principal\nVocabulário Principal: 45453100\nNº: LOT-0003\nDescrição do Lote: Constituído pelos seguintes imóveis: 1.3 Canada das Fontinhas, n.º 34  Fontinhas - Praia da Vitória; 2.3 Canada das Fontinhas, n.º 40  Fontinhas - Praia da Vitória; 3.3 Pedreiras, n.º 30, (Canada da Furna) - Lajes - Praia da Vitória; 4.3 Rua do Picão, n.º 22 - Lajes - Praia da Vitória; 5.3 Canada da Vista, n.º 49 - Quatro Ribeiras - Praia da Vitória; 6.3 Canada Grande, ...\nPreço base s/IVA: 286.000,00 EUR\nClassificação CPV (Vocabulário Comum para os Contratos Públicos)\nObjeto principal\nVocabulário Principal: 45453100\n\n7 - INDICAÇÕES ADICIONAIS\nO contrato envolve aquisição conjunta (satisfação de várias entidades)? Não\nO contrato é adjudicado por uma central de compras? Não\n\n8 - TÉCNICAS\nO concurso destina-se à celebração de um acordo-quadro? Inexistência de acordo-quadro\nÉ utilizado um leilão eletrónico? Não\nÉ adotada uma fase de negociação? Não\nSistema de Aquisição Dinâmico: Inexistência de sistema de aquisição dinâmico\n\n9 - LOCAL DA EXECUÇÃO DO CONTRATO\nLOCAL DA EXECUÇÃO DO CONTRATO (PROCEDIMENTO)\nPaís: Portugal\nNUT III: PT200\nLocalidade: Angra do Heroísmo\nDistrito: Região Autónoma dos Açores\nConcelho: Angra do Heroismo\nFreguesia: Todas\nPaís: Portugal\nNUT III: PT200\nLocalidade: Praia da Vitória\nDistrito: Região Autónoma dos Açores\nConcelho: Praia da Vitória\nFreguesia: Todas\nLOCAL DA EXECUÇÃO DO CONTRATO (LOTE)\nIdentificador do Lote: LOT-0001; LOT-0002; LOT-0003\nPaís: Portugal\nNUT III: PT200\nLocalidade: Angra do Heroísmo\nDistrito: Região Autónoma dos Açores\nConcelho: Angra do Heroismo\nFreguesia: Todas\nIdentificador do Lote: LOT-0001; LOT-0002; LOT-0003\nPaís: Portugal\nNUT III: PT200\nLocalidade: Praia da Vitória\nDistrito: Região Autónoma dos Açores\nConcelho: Praia da Vitória\nFreguesia: Todas\n\n10 - PRAZO DE EXECUÇÃO DO CONTRATO\nIdentificador do Lote: LOT-0001; LOT-0002; LOT-0003\nPrazo de execução do contrato: 240 DIAS\nPrevisão de renovações: Não\n\n11 - FUNDOS EU\nIdentificador do Lote: LOT-0001; LOT-0002; LOT-0003\nTêm fundos EU? Sim\n\n12 - DOCUMENTOS DE HABILITAÇÃO\nHabilitação para o exercício da atividade profissional: Sim\nTipo: Alvará\nDescrição: o1ª Categoria (Edifícios e Património Construído)\n▪1ª Subcategoria (Estruturas e elementos de betão)\n▪2ª Subcategoria (Estruturas metálicas)\n▪3ª Subcategoria (Estruturas de madeira)\n▪4ª Subcategoria (Alvenarias, rebocos e assentamento de cantarias)\n▪5ª Subcategoria (Estuques, pinturas e outros revestimentos)\n▪6ª Subcategoria (Carpintarias)\n▪7ª Subcategoria (Trabalhos em perfis não estruturais)\n▪8ª Subcategoria (Canalizações e condutas em edifícios)\no2ª Categoria (Vias de Comunicação, Obras de Urbanização e Outras Infraestruturas)\n▪8ª Subcategoria (Calcetamentos)\n▪9ª Subcategoria (Ajardinamentos)\no4ª Categoria (Instalações Elétricas e Mecânicas)\n▪1ª Subcategoria (Instalações elétricas de utilização de baixa tensão com potência até 50 kVA)\n▪4ª Subcategoria (Redes e instalações elétricas de tensão de serviço até 30 kV)\n▪9ª Subcategoria (Infraestruturas de telecomunicações)\no5ª Categoria (Outros Trabalhos)\n▪1ª Subcategoria (Demolições)\n▪2ª Subcategoria (Movimentação de terras)\n▪4ª Subcategoria (Fundações especiais)\n▪7ª Subcategoria (Drenagens e tratamento de taludes)\n▪8ª Subcategoria (Armaduras para betão armado)\n▪9ª Subcategoria (Reparações e tratamentos superficiais em estruturas metálicas)\n▪10ª Subcategoria (Cofragens)\n▪11ª Subcategoria (Impermeabilizações e isolamentos)\n▪12ª Subcategoria (Andaimes e outras estruturas provisórias)\n\n13 - CONDIÇÕES DE APRESENTAÇÃO\nPlataforma eletrónica utilizada pela entidade adjudicante: ACIN\nURL para Apresentação: https://www.acingov.pt\nAdmissibilidade da apresentação de propostas variantes: Não autorizado\nPrazo para apresentação das propostas: 03-11-2025 23:59\nPrazo durante o qual os concorrentes são obrigados a manter as respetivas propostas: 180 dias a contar do termo do prazo para a apresentação das propostas\nApresentação de Catálogo Eletrónico: Não autorizado\nIndicação de Subcontratação na Proposta: Inexistência de indicação de subcontratação\n\n14 - PRESTAÇÃO DE CAUÇÃO\nPrestação de caução: Sim\nPercentagem: 2%\nDescrição da Garantia Exigida: O valor da caução é de 2.00% do preço contratual.\n\n15 - FORNECIMENTO DAS PEÇAS DO CONCURSO, APRESENTAÇÃO DE PEDIDOS DE PARTICIPAÇÃO E APRESENTAÇÃO DAS PROPOSTAS\nLink para acesso às peças do concurso (URL): https://www.acingov.pt/acingovprod/2/zonaPublica/zona_publica_c/donwloadProcedurePiece/OTg4NDk1\n\n20 - OUTROS REQUISITOS\nIdentificador do Lote: LOT-0001; LOT-0002; LOT-0003\nInformação sobre contratos reservados. Aplica-se a contratos reservados (54º-A)? Não\n\n21 - CRITÉRIO DE ADJUDICAÇÃO\nO Critério de adjudicação é diferenciado por lote? Não\nMultifator: Sim\nFator: \nNome: Preço\nPonderação: 70%\nSubfatores: Não\nFator: \nNome: Qualidade\nPonderação: 30%\nSubfatores: Não\n\n24 - CONDIÇÕES DO CONTRATO\nIdentificador do Lote: LOT-0001; LOT-0002; LOT-0003\nFaturação Eletrónica: Permitido\nObrigação de Subcontratação:\nCódigo da Obrigação de Subcontratação: Não é aplicável nenhuma obrigação de subcontratação.\n\n25 - COMPRA PÚBLICA ESTRATÉGICA\nCompra Pública Estratégica: Inexistência de contratação pública estratégica\n\n26 - INFORMAÇÕES ADICIONAIS\nIdentificador do Lote: LOT-0001; LOT-0002; LOT-0003\nContrato adequado para PME: Sim\nCobertura ACP (Acordo dos Contratos Públicos da Organização Mundial do Comércio): Não\n\n27 - IDENTIFICAÇÃO E CONTACTOS DO ÓRGÃO DE RECURSOS ADMINISTRATIVOS\nDesignação: Secretaria Regional da Juventude, Habitação e Emprego\nEndereço: Rua Dr. José Bruno Tavares Carreiro s/n\nCódigo postal: 9500-119\nLocalidade: Ponta Delgada\nTelefone: 296308000\nFax: \nEndereço eletrónico: drh.contratacaopublica@azores.gov.pt\nPrazo de interposição do recurso: 10 dias\n\n28 - IDENTIFICAÇÃO DO(S) AUTOR(ES) DE ANÚNCIO\nNome: Márcio Patricio Medeiros Almeida\nCargo: Técnico Superior\n419678022",
    "nipc": "600087549",
    "distrito": "Região Autónoma dos Açores",
    "concelho": "Angra do Heroismo",
    "freguesia": "Todas",
    "site": "https://portal.azores.gov.pt/web/srjhe",
    "email": "drh.contratacaopublica@azores.gov.pt",
    "designacao_contrato": "Empreitada de Reabilitação de 14 Habitações Dispersas do Parque Habitacional da Região Autónoma dos Açores - Ilha Terceira",
    "descricao": "Reabilitação de 14 Habitações Dispersas do Parque Habitacional da Região Autónoma dos Açores - Ilha Terceira",
    "preco_base": "870.100,00 EUR",
    "prazo_execucao": "240 DIAS",
    "prazo_apresentacao_propostas": "03-11-2025 23:59",
    "fundos_eu": "Sim",
    "plataforma_eletronica": "ACIN",
    "url_procedimento": "https://www.acingov.pt",
    "autor_nome": "Márcio Patricio Medeiros Almeida",
    "autor_cargo": "Técnico Superior"
  },
  {
    "numero_procedimento": "N/A",
    "entidade": "AnÃºncio de procedimento  n.Âº 27799/2025  -  DiÃ¡rio da RepÃºblica n.Âº 205/2025, SÃ©rie II de 2025-10-23",
    "link": "https://diariodarepublica.pt/dr/detalhe/contrato-publico/27799-941706062"
  },
  {
    "numero_procedimento": "N/A",
    "entidade": "Agência Espacial Portuguesa - Portugal Space",
    "link": "https://diariodarepublica.pt/dr/detalhe/contrato-publico/27800-941706071",
    "detalhes_completos": "Alteração do Anúncio de procedimento n.º 27687/2025, de 2025-10-21, com o ID 419678444\n\n1 - IDENTIFICAÇÃO E CONTACTOS DA ENTIDADE ADJUDICANTE\nDesignação da entidade adjudicante: Agência Espacial Portuguesa - Portugal Space\nNIPC: 515388211\nServiço/Órgão/Pessoa de contacto: Agência Espacial Portuguesa\nEndereço: Bairro da Bela Vista n.º1\nCódigo postal: 9580-406\nLocalidade: Vila do Porto\nPaís: Portugal\nNUT III: PT200\nDistrito: Região Autónoma dos Açores\nConcelho: Vila do Porto\nFreguesia: Freguesia de Vila do Porto\nTelefone: 217231017\nEndereço da Entidade (URL): www.ptspace.pt\nEndereço Eletrónico: secretariado@ptspace.pt\neDelivery Gateway (URL): https://www.acingov.pt\nFunção da Organização: Adquirente\nNorma jurídica da Entidade Adjudicante: Organismo de direito público\nÁrea de atividade da Autoridade Adjudicante: Serviços públicos das administrações públicas\n\n2 - JORNAL OFICIAL DA UNIÃO EUROPEIA\nO procedimento a que este anúncio diz respeito também é publicitado no Jornal Oficial da União Europeia? Não\n\n3 - AVISO\nModelo de Anúncio: Concurso público\nData de Envio do Anúncio: 22-10-2025\n\n5 - PROCESSO\nTipo de Procedimento: Concurso público\nPreço base do procedimento: Sim\nValor do preço base do procedimento: 198.000,00 EUR\nProcedimento com lotes? Não\n\n6 - OBJETO DO CONTRATO\nNúmero de referência interna: CP2025-123\nDesignação do contrato: O presente concurso insere-se no CPV 45454000-4 - Obras de reestruturação, de acordo com o Regulamento (CE) nº 213/2008, da Comissão de 28 de novembro de 2007, publicado no Jornal Oficial da União Europeia nº L 74 de 15 de março de 2008.\nDescrição: O objeto do presente concurso insere-se no CPV 45454000-4 - Obras de reestruturação, de acordo com o Regulamento (CE) nº 213/2008, da Comissão de 28 de novembro de 2007, publicado no Jornal Oficial da União Europeia nº L 74 de 15 de março de 2008.\nTipo de Contrato Principal: Empreitada de Obras Públicas\nTipo de Contrato: Empreitada de Obras Públicas\nClassificação CPV (Vocabulário Comum para os Contratos Públicos)\nObjeto principal\nVocabulário Principal: 45454000\nPreço base s/IVA: 198.000,00 EUR\n\n7 - INDICAÇÕES ADICIONAIS\nO contrato envolve aquisição conjunta (satisfação de várias entidades)? Não\nO contrato é adjudicado por uma central de compras? Não\n\n8 - TÉCNICAS\nO concurso destina-se à celebração de um acordo-quadro? Inexistência de acordo-quadro\nÉ utilizado um leilão eletrónico? Não\nÉ adotada uma fase de negociação? Não\nSistema de Aquisição Dinâmico: Inexistência de sistema de aquisição dinâmico\n\n9 - LOCAL DA EXECUÇÃO DO CONTRATO\nLOCAL DA EXECUÇÃO DO CONTRATO (PROCEDIMENTO)\nPaís: Portugal\nNUT III: PT200\nLocalidade: Freguesia de Vila do Porto\nDistrito: Região Autónoma dos Açores\nConcelho: Vila do Porto\nFreguesia: Freguesia de Vila do Porto\n\n10 - PRAZO DE EXECUÇÃO DO CONTRATO\nPrazo de execução do contrato: 60 DIAS\nPrevisão de renovações: Não\n\n11 - FUNDOS EU\nTêm fundos EU? Não\n\n12 - DOCUMENTOS DE HABILITAÇÃO\nHabilitação para o exercício da atividade profissional: Não\n\n13 - CONDIÇÕES DE APRESENTAÇÃO\nPlataforma eletrónica utilizada pela entidade adjudicante: ACIN\nURL para Apresentação: https://www.acingov.pt\nAdmissibilidade da apresentação de propostas variantes: Não autorizado\nPrazo para apresentação das propostas: 10-11-2025 18:00\nPrazo durante o qual os concorrentes são obrigados a manter as respetivas propostas: 66 dias a contar do termo do prazo para a apresentação das propostas\nIndicação de Subcontratação na Proposta: Inexistência de indicação de subcontratação\n\n14 - PRESTAÇÃO DE CAUÇÃO\nPrestação de caução: Sim\nPercentagem: 2%\nDescrição da Garantia Exigida: O valor da caução é de 2.00% do preço contratual.\n\n15 - FORNECIMENTO DAS PEÇAS DO CONCURSO, APRESENTAÇÃO DE PEDIDOS DE PARTICIPAÇÃO E APRESENTAÇÃO DAS PROPOSTAS\nLink para acesso às peças do concurso (URL): https://www.acingov.pt/acingovprod/2/zonaPublica/zona_publica_c/donwloadProcedurePiece/OTg4MzQ5\n\n20 - OUTROS REQUISITOS\nInformação sobre contratos reservados. Aplica-se a contratos reservados (54º-A)? Não\n\n21 - CRITÉRIO DE ADJUDICAÇÃO\nMultifator: Sim\nFator: \nNome: Outros\nOutro Nome: fator F1 - Preço (P)\nPonderação: 40%\nSubfatores: Não\nFator: \nNome: Outros\nOutro Nome: fator F2 - Prazo para execução da empreitada Menos de 30 dias → 100 31 a 45 dias → 75 46 a 55 dias → 50 56 a 60 dias → 25\nPonderação: 40%\nSubfatores: Não\nFator: \nNome: Outros\nOutro Nome: Fator 3 - Experiência da equipa afeta à execução dos serviços (EX) = Número de contratos de empreitada celebrados com entidades públicas, nos últimos 2 anos, identificando cada contrato com o número constante do Portal Base.  ≥ 7 obras → 100 pts  5 a 6 obras → 75 pts  3 a 4 obras →50 pts  1 a 2 obras → 25 pts\nPonderação: 20%\nSubfatores: Não\n\n24 - CONDIÇÕES DO CONTRATO\nFaturação Eletrónica: Permitido\nObrigação de Subcontratação:\nCódigo da Obrigação de Subcontratação: Não é aplicável nenhuma obrigação de subcontratação.\n\n25 - COMPRA PÚBLICA ESTRATÉGICA\nCompra Pública Estratégica: Inexistência de contratação pública estratégica\n\n26 - INFORMAÇÕES ADICIONAIS\nContrato adequado para PME: Não\nCobertura ACP (Acordo dos Contratos Públicos da Organização Mundial do Comércio): Não\n\n27 - IDENTIFICAÇÃO E CONTACTOS DO ÓRGÃO DE RECURSOS ADMINISTRATIVOS\nDesignação: Agência Espacial Portuguesa\nEndereço: Estrada das Laranjeiras, 205\nCódigo postal: 1649-018\nLocalidade: Lisboa\nTelefone: 217231017\nFax: \nEndereço eletrónico: concursos@ptspace.pt\n\n28 - IDENTIFICAÇÃO DO(S) AUTOR(ES) DE ANÚNCIO\nNome: Mónica Reis\nCargo: Internal Operations officer\n\n29 - ALTERAÇÃO\nMotivo da Alteração: Correção pelo adquirente\nIdentificador da Versão do Anúncio a Alterar: 028d97fd-2c97-40ea-a180-5578791a7864-01\nIdentificador das Secções Alteradas do Anúncio Anterior: Condições de Apresentação\nDescrição das Alterações: Modificação do prazo para a apresentação de propostas\nAlteração dos Documentos do Concurso: Não\n419688512",
    "nipc": "515388211",
    "distrito": "Região Autónoma dos Açores",
    "concelho": "Vila do Porto",
    "freguesia": "Freguesia de Vila do Porto",
    "site": "www.ptspace.pt",
    "email": "secretariado@ptspace.pt",
    "designacao_contrato": "O presente concurso insere-se no CPV 45454000-4 - Obras de reestruturação, de acordo com o Regulamento (CE) nº 213/2008, da Comissão de 28 de novembro de 2007, publicado no Jornal Oficial da União Europeia nº L 74 de 15 de março de 2008.",
    "descricao": "O objeto do presente concurso insere-se no CPV 45454000-4 - Obras de reestruturação, de acordo com o Regulamento (CE) nº 213/2008, da Comissão de 28 de novembro de 2007, publicado no Jornal Oficial da União Europeia nº L 74 de 15 de março de 2008.",
    "preco_base": "198.000,00 EUR",
    "prazo_execucao": "60 DIAS",
    "prazo_apresentacao_propostas": "10-11-2025 18:00",
    "fundos_eu": "Não",
    "plataforma_eletronica": "ACIN",
    "url_procedimento": "https://www.acingov.pt",
    "autor_nome": "Mónica Reis",
    "autor_cargo": "Internal Operations officer"
  },
  {
    "numero_procedimento": "N/A",
    "entidade": "Município de Ovar",
    "link": "https://diariodarepublica.pt/dr/detalhe/contrato-publico/27802-941706072",
    "detalhes_completos": "1 - IDENTIFICAÇÃO E CONTACTOS DA ENTIDADE ADJUDICANTE\nDesignação da entidade adjudicante: Município de Ovar\nNIPC: 501306269\nServiço/Órgão/Pessoa de contacto: Departamento Administrativo, Jurídico e Financeiro - Serviço de Contratação Pública\nEndereço: Praça República\nCódigo postal: 3880-141\nLocalidade: Ovar\nPaís: Portugal\nNUT III: PT16D\nDistrito: Aveiro\nConcelho: Ovar\nFreguesia: Todas\nTelefone: 256581300\nFax: 256586611\nEndereço da Entidade (URL): www.cm-ovar.pt\nEndereço Eletrónico: avisosdepropostas@cm-ovar.pt\neDelivery Gateway (URL): https://community.vortal.biz/public/\nFunção da Organização: Adquirente\nNorma jurídica da Entidade Adjudicante: Autoridade local\nÁrea de atividade da Autoridade Adjudicante: Serviços públicos das administrações públicas\n\n2 - JORNAL OFICIAL DA UNIÃO EUROPEIA\nO procedimento a que este anúncio diz respeito também é publicitado no Jornal Oficial da União Europeia? Não\n\n3 - AVISO\nModelo de Anúncio: Concurso limitado por prévia qualificação\nData de Envio do Anúncio: 22-10-2025\n\n5 - PROCESSO\nTipo de Procedimento: Concurso limitado por prévia qualificação\nPreço base do procedimento: Sim\nValor do preço base do procedimento: 55.000,00 EUR\nProcedimento com lotes? Não\n\n6 - OBJETO DO CONTRATO\nNúmero de referência interna: 2025/300.10.005/1051\nDesignação do contrato: Aquisição de serviços para disponibilização de bancadas para o Carnaval de Ovar de 2026\nDescrição: Aquisição de serviços para disponibilização de bancadas para o Carnaval de Ovar de 2026\nTipo de Contrato Principal: Aquisição de Serviços\nTipo de Contrato: Aquisição de Serviços\nClassificação CPV (Vocabulário Comum para os Contratos Públicos)\nObjeto principal\nVocabulário Principal: 51500000\nPreço base s/IVA: 55.000,00 EUR\n\n7 - INDICAÇÕES ADICIONAIS\nO contrato envolve aquisição conjunta (satisfação de várias entidades)? Não\nO contrato é adjudicado por uma central de compras? Não\n\n8 - TÉCNICAS\nO concurso destina-se à celebração de um acordo-quadro? Inexistência de acordo-quadro\nÉ utilizado um leilão eletrónico? Não\nSistema de Aquisição Dinâmico: Inexistência de sistema de aquisição dinâmico\n\n9 - LOCAL DA EXECUÇÃO DO CONTRATO\nLOCAL DA EXECUÇÃO DO CONTRATO (PROCEDIMENTO)\nPaís: Portugal\nNUT III: PT16D\nLocalidade: Ovar\nDistrito: Aveiro\nConcelho: Ovar\nFreguesia: União das Freguesias de Ovar, São João, Arada e São Vicente de Pereira Jusã\n\n10 - PRAZO DE EXECUÇÃO DO CONTRATO\nPrazo de execução do contrato: 66 DIAS\nPrevisão de renovações: Não\n\n11 - FUNDOS EU\nTêm fundos EU? Não\n\n12 - DOCUMENTOS DE HABILITAÇÃO\nHabilitação para o exercício da atividade profissional: Não\n\n13 - CONDIÇÕES DE APRESENTAÇÃO\nPlataforma eletrónica utilizada pela entidade adjudicante: VORTAL\nURL para Apresentação: https://community.vortal.biz/public/\nAdmissibilidade da apresentação de propostas variantes: Não autorizado\nPrazo para apresentação das candidaturas: 03-11-2025 17:00\nRequisitos mínimos \nRequisitos mínimos de capacidade técnica: Conforme ponto 6 do Programa de Procedimento\nRequisitos mínimos de capacidade financeira: Conforme as peças do procedimento\nPrazo durante o qual os concorrentes são obrigados a manter as respetivas propostas: 44 dias a contar do termo do prazo para a apresentação das propostas\nIndicação de Subcontratação na Proposta: Inexistência de indicação de subcontratação\n\n14 - PRESTAÇÃO DE CAUÇÃO\nPrestação de caução: Não\n\n15 - FORNECIMENTO DAS PEÇAS DO CONCURSO, APRESENTAÇÃO DE PEDIDOS DE PARTICIPAÇÃO E APRESENTAÇÃO DAS PROPOSTAS\nLink para acesso às peças do concurso (URL): https://community.vortal.biz/Public/public-tender-documents/djBCbWs3YS9HeG5ORFVWS2x0RUNFSXNZajRiNE9EdVdXOXFCWkNpNWpFTVprOVJkWGJVRDJaRGZKMlVOdW5pMlc3RHh3b0xEd3oxSUVrNkJTUTZSS0E9PUlXVW1i\n\n20 - OUTROS REQUISITOS\nInformação sobre contratos reservados. Aplica-se a contratos reservados (54º-A)? Não\n\n21 - CRITÉRIO DE ADJUDICAÇÃO\nMultifator: Não\nMonofator:\nNome: Preço\n\n24 - CONDIÇÕES DO CONTRATO\nFaturação Eletrónica: Permitido\nObrigação de Subcontratação:\nCódigo da Obrigação de Subcontratação: Não é aplicável nenhuma obrigação de subcontratação.\n\n25 - COMPRA PÚBLICA ESTRATÉGICA\nCompra Pública Estratégica: Inexistência de contratação pública estratégica\n\n26 - INFORMAÇÕES ADICIONAIS\nContrato adequado para PME: Sim\nCobertura ACP (Acordo dos Contratos Públicos da Organização Mundial do Comércio): Não\n\n27 - IDENTIFICAÇÃO E CONTACTOS DO ÓRGÃO DE RECURSOS ADMINISTRATIVOS\nDesignação: Câmara Municipal de Ovar\nEndereço: Praça da República\nCódigo postal: 3880-141\nLocalidade: Ovar\nTelefone: +351 256581300\nFax: +351 256586611\nEndereço eletrónico: gapresidencia@cm-ovar.pt\n\n28 - IDENTIFICAÇÃO DO(S) AUTOR(ES) DE ANÚNCIO\nNome: Domingos Silva\nCargo: Presidente da Câmara Municipal de Ovar\n419683182",
    "nipc": "501306269",
    "distrito": "Aveiro",
    "concelho": "Ovar",
    "freguesia": "Todas",
    "site": "www.cm-ovar.pt",
    "email": "avisosdepropostas@cm-ovar.pt",
    "designacao_contrato": "Aquisição de serviços para disponibilização de bancadas para o Carnaval de Ovar de 2026",
    "descricao": "Aquisição de serviços para disponibilização de bancadas para o Carnaval de Ovar de 2026",
    "preco_base": "55.000,00 EUR",
    "prazo_execucao": "66 DIAS",
    "prazo_apresentacao_propostas": null,
    "fundos_eu": "Não",
    "plataforma_eletronica": "VORTAL",
    "url_procedimento": "https://community.vortal.biz/public/",
    "autor_nome": "Domingos Silva",
    "autor_cargo": "Presidente da Câmara Municipal de Ovar"
  },
  {
    "numero_procedimento": "N/A",
    "entidade": "Agência Espacial Portuguesa - Portugal Space",
    "link": "https://diariodarepublica.pt/dr/detalhe/contrato-publico/27804-941706073",
    "detalhes_completos": "Alteração do Anúncio de procedimento n.º 27688/2025, de 2025-10-21, com o ID 419678452\n\n1 - IDENTIFICAÇÃO E CONTACTOS DA ENTIDADE ADJUDICANTE\nDesignação da entidade adjudicante: Agência Espacial Portuguesa - Portugal Space\nNIPC: 515388211\nServiço/Órgão/Pessoa de contacto: Agência Espacial Portuguesa\nEndereço: Bairro da Bela Vista n.º1\nCódigo postal: 9580-406\nLocalidade: Vila do Porto\nPaís: Portugal\nNUT III: PT200\nDistrito: Região Autónoma dos Açores\nConcelho: Vila do Porto\nFreguesia: Freguesia de Vila do Porto\nTelefone: 217231017\nEndereço da Entidade (URL): www.ptspace.pt\nEndereço Eletrónico: secretariado@ptspace.pt\neDelivery Gateway (URL): https://www.acingov.pt\nFunção da Organização: Adquirente\nNorma jurídica da Entidade Adjudicante: Organismo de direito público\nÁrea de atividade da Autoridade Adjudicante: Serviços públicos das administrações públicas\n\n2 - JORNAL OFICIAL DA UNIÃO EUROPEIA\nO procedimento a que este anúncio diz respeito também é publicitado no Jornal Oficial da União Europeia? Não\n\n3 - AVISO\nModelo de Anúncio: Concurso público\nData de Envio do Anúncio: 22-10-2025\n\n5 - PROCESSO\nTipo de Procedimento: Concurso público\nPreço base do procedimento: Sim\nValor do preço base do procedimento: 114.900,00 EUR\nProcedimento com lotes? Não\n\n6 - OBJETO DO CONTRATO\nNúmero de referência interna: CP2025-124\nDesignação do contrato: O presente procedimento tem por objeto a aquisição de mobiliário de escritório destinado às instalações da Agência Espacial Portuguesa em Lisboa, sitas no edifício Greenpark, na Avenida dos Combatentes, Quinta da Palma de Cima, n.ºs 43 e 43-A, piso 2, fração C e D, 1600-042, Lisboa, freguesia de São Domingos de Benfica, de acordo com os trabalhos definidos, quanto à sua espécie, quantidade e condições técnicas de execução constantes da Parte II  Especificações Técnicas e seus anexos do presente Caderno de Encargos, nos termos e condições elencados.\nDescrição: O presente procedimento tem por objeto a aquisição de mobiliário de escritório destinado às instalações da Agência Espacial Portuguesa em Lisboa, sitas no edifício Greenpark, na Avenida dos Combatentes, Quinta da Palma de Cima, n.ºs 43 e 43-A, piso 2, fração C e D, 1600-042, Lisboa, freguesia de São Domingos de Benfica, de acordo com os trabalhos definidos, quanto à sua espécie, quantidade e condições técnicas de execução constantes da Parte II  Especificações Técnicas e seus anexos do presente Caderno de Encargos, nos termos e condições elencados.\nTipo de Contrato Principal: Aquisição de Bens Móveis\nTipo de Contrato: Aquisição de Bens Móveis\nClassificação CPV (Vocabulário Comum para os Contratos Públicos)\nObjeto principal\nVocabulário Principal: 39130000\nPreço base s/IVA: 114.900,00 EUR\n\n7 - INDICAÇÕES ADICIONAIS\nO contrato envolve aquisição conjunta (satisfação de várias entidades)? Não\nO contrato é adjudicado por uma central de compras? Não\n\n8 - TÉCNICAS\nO concurso destina-se à celebração de um acordo-quadro? Inexistência de acordo-quadro\nÉ utilizado um leilão eletrónico? Não\nÉ adotada uma fase de negociação? Não\nSistema de Aquisição Dinâmico: Inexistência de sistema de aquisição dinâmico\n\n9 - LOCAL DA EXECUÇÃO DO CONTRATO\nLOCAL DA EXECUÇÃO DO CONTRATO (PROCEDIMENTO)\nPaís: Portugal\nNUT III: PT200\nLocalidade: Freguesia de Vila do Porto\nDistrito: Região Autónoma dos Açores\nConcelho: Vila do Porto\nFreguesia: Freguesia de Vila do Porto\n\n10 - PRAZO DE EXECUÇÃO DO CONTRATO\nPrazo de execução do contrato: 3 MESES\nPrevisão de renovações: Não\n\n11 - FUNDOS EU\nTêm fundos EU? Não\n\n12 - DOCUMENTOS DE HABILITAÇÃO\nHabilitação para o exercício da atividade profissional: Não\n\n13 - CONDIÇÕES DE APRESENTAÇÃO\nPlataforma eletrónica utilizada pela entidade adjudicante: ACIN\nURL para Apresentação: https://www.acingov.pt\nAdmissibilidade da apresentação de propostas variantes: Não autorizado\nPrazo para apresentação das propostas: 10-11-2025 18:00\nPrazo durante o qual os concorrentes são obrigados a manter as respetivas propostas: 66 dias a contar do termo do prazo para a apresentação das propostas\nIndicação de Subcontratação na Proposta: Inexistência de indicação de subcontratação\n\n14 - PRESTAÇÃO DE CAUÇÃO\nPrestação de caução: Sim\nPercentagem: 2%\nDescrição da Garantia Exigida: O valor da caução é de 2.00% do preço contratual.\n\n15 - FORNECIMENTO DAS PEÇAS DO CONCURSO, APRESENTAÇÃO DE PEDIDOS DE PARTICIPAÇÃO E APRESENTAÇÃO DAS PROPOSTAS\nLink para acesso às peças do concurso (URL): https://www.acingov.pt/acingovprod/2/zonaPublica/zona_publica_c/donwloadProcedurePiece/OTg4NDIz\n\n20 - OUTROS REQUISITOS\nInformação sobre contratos reservados. Aplica-se a contratos reservados (54º-A)? Não\n\n21 - CRITÉRIO DE ADJUDICAÇÃO\nMultifator: Sim\nFator: \nNome: Outros\nOutro Nome: F1  Preço (P)\nPonderação: 70%\nSubfatores: Não\nFator: \nNome: Outros\nOutro Nome: F2 - Qualidade da proposta (Q) terá em conta os trabalhos apresentados em cumprimento da alínea c) do n. º1 do artigo 13.º do presente programa, e será obtida através dos seguintes critérios: i. Funcionalidade: Verificar se o design atende ao seu propósito funcional, considerando os públicos-alvo da Agência Espacial Portuguesa e a população em geral; ii. Estética Apropria...\nPonderação: 30%\nSubfatores: Não\n\n24 - CONDIÇÕES DO CONTRATO\nFaturação Eletrónica: Permitido\nObrigação de Subcontratação:\nCódigo da Obrigação de Subcontratação: Não é aplicável nenhuma obrigação de subcontratação.\n\n25 - COMPRA PÚBLICA ESTRATÉGICA\nCompra Pública Estratégica: Inexistência de contratação pública estratégica\n\n26 - INFORMAÇÕES ADICIONAIS\nContrato adequado para PME: Sim\nCobertura ACP (Acordo dos Contratos Públicos da Organização Mundial do Comércio): Não\n\n27 - IDENTIFICAÇÃO E CONTACTOS DO ÓRGÃO DE RECURSOS ADMINISTRATIVOS\nDesignação: Agência Espacial Portuguesa\nEndereço: Estrada das Laranjeiras, 205\nCódigo postal: 1649-018\nLocalidade: Lisboa\nTelefone: 910784397\nFax: \nEndereço eletrónico: concursos@ptspace.pt\nPrazo de interposição do recurso: 5 dias\n\n28 - IDENTIFICAÇÃO DO(S) AUTOR(ES) DE ANÚNCIO\nNome: Mónica Reis\nCargo: Internal Operations Officer\n\n29 - ALTERAÇÃO\nMotivo da Alteração: Correção pelo adquirente\nIdentificador da Versão do Anúncio a Alterar: 25038ed3-0d77-43f3-889c-2bd3c8bfa04c-01\nIdentificador das Secções Alteradas do Anúncio Anterior: Condições de Apresentação\nDescrição das Alterações: Modificação do prazo para a apresentação de propostas\nAlteração dos Documentos do Concurso: Não\n419688667",
    "nipc": "515388211",
    "distrito": "Região Autónoma dos Açores",
    "concelho": "Vila do Porto",
    "freguesia": "Freguesia de Vila do Porto",
    "site": "www.ptspace.pt",
    "email": "secretariado@ptspace.pt",
    "designacao_contrato": "O presente procedimento tem por objeto a aquisição de mobiliário de escritório destinado às instalações da Agência Espacial Portuguesa em Lisboa, sitas no edifício Greenpark, na Avenida dos Combatentes, Quinta da Palma de Cima, n.ºs 43 e 43-A, piso 2, fração C e D, 1600-042, Lisboa, freguesia de São Domingos de Benfica, de acordo com os trabalhos definidos, quanto à sua espécie, quantidade e condições técnicas de execução constantes da Parte II  Especificações Técnicas e seus anexos do presente Caderno de Encargos, nos termos e condições elencados.",
    "descricao": "O presente procedimento tem por objeto a aquisição de mobiliário de escritório destinado às instalações da Agência Espacial Portuguesa em Lisboa, sitas no edifício Greenpark, na Avenida dos Combatentes, Quinta da Palma de Cima, n.ºs 43 e 43-A, piso 2, fração C e D, 1600-042, Lisboa, freguesia de São Domingos de Benfica, de acordo com os trabalhos definidos, quanto à sua espécie, quantidade e condições técnicas de execução constantes da Parte II  Especificações Técnicas e seus anexos do presente Caderno de Encargos, nos termos e condições elencados.",
    "preco_base": "114.900,00 EUR",
    "prazo_execucao": "3 MESES",
    "prazo_apresentacao_propostas": "10-11-2025 18:00",
    "fundos_eu": "Não",
    "plataforma_eletronica": "ACIN",
    "url_procedimento": "https://www.acingov.pt",
    "autor_nome": "Mónica Reis",
    "autor_cargo": "Internal Operations Officer"
  },
  {
    "numero_procedimento": "N/A",
    "entidade": "AnÃºncio de procedimento  n.Âº 27791/2025  -  DiÃ¡rio da RepÃºblica n.Âº 205/2025, SÃ©rie II de 2025-10-23",
    "link": "https://diariodarepublica.pt/dr/detalhe/contrato-publico/27791-941764875"
  },
  {
    "numero_procedimento": "N/A",
    "entidade": "Unidade Local de Saúde de Coimbra, E. P. E.",
    "link": "https://diariodarepublica.pt/dr/detalhe/contrato-publico/27792-941764879",
    "detalhes_completos": "1 - IDENTIFICAÇÃO E CONTACTOS DA ENTIDADE ADJUDICANTE\nDesignação da entidade adjudicante: Unidade Local de Saúde de Coimbra, E. P. E.\nNIPC: 510103448\nEndereço: Praceta Prof. Mota Pinto\nCódigo postal: 3004-561\nLocalidade: Coimbra\nPaís: Portugal\nNUT III: PT16E\nDistrito: Coimbra\nConcelho: Coimbra\nFreguesia: Todas\nTelefone: 239400605\nFax: 239400605\nEndereço da Entidade (URL): https://www.chuc.min-saude.pt\nEndereço Eletrónico: ana.rosete@ulscoimbra.min-saude.pt\neDelivery Gateway (URL): https://community.vortal.biz/public/\nFunção da Organização: Adquirente\nNorma jurídica da Entidade Adjudicante: Organismo de direito público\nÁrea de atividade da Autoridade Adjudicante: Saúde\n\n2 - JORNAL OFICIAL DA UNIÃO EUROPEIA\nO procedimento a que este anúncio diz respeito também é publicitado no Jornal Oficial da União Europeia? Sim\n\n3 - AVISO\nModelo de Anúncio: Concurso público\nData de Envio do Anúncio: 20-10-2025\n\n5 - PROCESSO\nTipo de Procedimento: Concurso público\nPreço base do procedimento: Sim\nValor do preço base do procedimento: 450.000,00 EUR\nProcedimento com lotes? Sim\nNº Máx. de Lotes Autorizado: 2\nNúmero máximo de lotes que podem ser adjudicados a um concorrente: 2\n\n6 - OBJETO DO CONTRATO\nNúmero de referência interna: 010900532025\nDesignação do contrato: Aquisição de 600 (seiscentos) computadores de secretária para a Unidade Local de Saúde de Coimbra, E.P.E \nDescrição: Aquisição de 600 (seiscentos) computadores de secretária para a Unidade Local de Saúde de Coimbra, E.P.E\nOpções: Não\nTipo de Contrato Principal: Aquisição de Bens Móveis\nTipo de Contrato: Aquisição de Bens Móveis\nClassificação CPV (Vocabulário Comum para os Contratos Públicos)\nObjeto principal\nVocabulário Principal: 30200000\nPreço base s/IVA: 450.000,00 EUR\nLotes: \nNº: LOT-0001\nDescrição do Lote: Lote 1\nPreço base s/IVA: 225.000,00 EUR\nClassificação CPV (Vocabulário Comum para os Contratos Públicos)\nObjeto principal\nVocabulário Principal: 30200000\nNº: LOT-0002\nDescrição do Lote: Lote 2\nPreço base s/IVA: 225.000,00 EUR\nClassificação CPV (Vocabulário Comum para os Contratos Públicos)\nObjeto principal\nVocabulário Principal: 30200000\n\n7 - INDICAÇÕES ADICIONAIS\nO contrato envolve aquisição conjunta (satisfação de várias entidades)? Não\nO contrato é adjudicado por uma central de compras? Não\n\n8 - TÉCNICAS\nO concurso destina-se à celebração de um acordo-quadro? Inexistência de acordo-quadro\nÉ utilizado um leilão eletrónico? Não\nÉ adotada uma fase de negociação? Não\nSistema de Aquisição Dinâmico: Inexistência de sistema de aquisição dinâmico\n\n9 - LOCAL DA EXECUÇÃO DO CONTRATO\nLOCAL DA EXECUÇÃO DO CONTRATO (PROCEDIMENTO)\nPaís: Portugal\nNUT III: PT16E\nLocalidade: Coimbra\nDistrito: Coimbra\nConcelho: Coimbra\nFreguesia: Freguesia de Santo António dos Olivais\nLOCAL DA EXECUÇÃO DO CONTRATO (LOTE)\nIdentificador do Lote: LOT-0001; LOT-0002\nPaís: Portugal\nNUT III: PT16E\nLocalidade: Coimbra\nDistrito: Coimbra\nConcelho: Coimbra\nFreguesia: Freguesia de Santo António dos Olivais\n\n10 - PRAZO DE EXECUÇÃO DO CONTRATO\nIdentificador do Lote: LOT-0001; LOT-0002\nPrazo de execução do contrato: 60 DIAS\nPrevisão de renovações: Não\n\n11 - FUNDOS EU\nIdentificador do Lote: LOT-0001; LOT-0002\nTêm fundos EU? Não\n\n12 - DOCUMENTOS DE HABILITAÇÃO\nHabilitação para o exercício da atividade profissional: Não\n\n13 - CONDIÇÕES DE APRESENTAÇÃO\nPlataforma eletrónica utilizada pela entidade adjudicante: VORTAL\nURL para Apresentação: https://community.vortal.biz/public/\nAdmissibilidade da apresentação de propostas variantes: Não autorizado\nPrazo para apresentação das propostas: 25-11-2025 23:59\nPrazo durante o qual os concorrentes são obrigados a manter as respetivas propostas: 90 dias a contar do termo do prazo para a apresentação das propostas\nApresentação de Catálogo Eletrónico: Não autorizado\nIndicação de Subcontratação na Proposta: Inexistência de indicação de subcontratação\n\n14 - PRESTAÇÃO DE CAUÇÃO\nPrestação de caução: Não\n\n15 - FORNECIMENTO DAS PEÇAS DO CONCURSO, APRESENTAÇÃO DE PEDIDOS DE PARTICIPAÇÃO E APRESENTAÇÃO DAS PROPOSTAS\nLink para acesso às peças do concurso (URL): https://community.vortal.biz/Public/public-tender-documents/VzhaMVM4Q0pmeEhJK2dYZDJiUnhubHhjOFRUU3ViKzcrUEFHSmYrWEtkU3hJUU9ITEVvZUdIbXVmS0o4Vms3YkhlUlRXSVlYMWltRG50em1GTVMrbmc9PTU5ZEdF\n\n20 - OUTROS REQUISITOS\nIdentificador do Lote: LOT-0001; LOT-0002\nInformação sobre contratos reservados. Aplica-se a contratos reservados (54º-A)? Não\n\n21 - CRITÉRIO DE ADJUDICAÇÃO\nO Critério de adjudicação é diferenciado por lote? Não\nMultifator: Não\nMonofator:\nNome: Preço\n\n24 - CONDIÇÕES DO CONTRATO\nIdentificador do Lote: LOT-0001; LOT-0002\nFaturação Eletrónica: Permitido\nObrigação de Subcontratação:\nCódigo da Obrigação de Subcontratação: Não é aplicável nenhuma obrigação de subcontratação.\n\n25 - COMPRA PÚBLICA ESTRATÉGICA\nCompra Pública Estratégica: Inexistência de contratação pública estratégica\n\n26 - INFORMAÇÕES ADICIONAIS\nIdentificador do Lote: LOT-0001; LOT-0002\nContrato adequado para PME: Sim\nCobertura ACP (Acordo dos Contratos Públicos da Organização Mundial do Comércio): Não\n\n27 - IDENTIFICAÇÃO E CONTACTOS DO ÓRGÃO DE RECURSOS ADMINISTRATIVOS\nDesignação: Conselho de Administração da ULS Coimbra, E.P.E.\nEndereço: Praceta Prof. Mota Pinto\nCódigo postal: 3004-561\nLocalidade: Coimbra\nTelefone: +351 239400400\nFax: +351 239400400\nEndereço eletrónico: casec@ulscoimbra.min-saude.pt\n\n28 - IDENTIFICAÇÃO DO(S) AUTOR(ES) DE ANÚNCIO\nNome: Teresa Roseiro\nCargo: Assistente Técnica\n419675569",
    "nipc": "510103448",
    "distrito": "Coimbra",
    "concelho": "Coimbra",
    "freguesia": "Todas",
    "site": "https://www.chuc.min-saude.pt",
    "email": "ana.rosete@ulscoimbra.min-saude.pt",
    "designacao_contrato": "Aquisição de 600 (seiscentos) computadores de secretária para a Unidade Local de Saúde de Coimbra, E.P.E",
    "descricao": "Aquisição de 600 (seiscentos) computadores de secretária para a Unidade Local de Saúde de Coimbra, E.P.E",
    "preco_base": "450.000,00 EUR",
    "prazo_execucao": "60 DIAS",
    "prazo_apresentacao_propostas": "25-11-2025 23:59",
    "fundos_eu": "Não",
    "plataforma_eletronica": "VORTAL",
    "url_procedimento": "https://community.vortal.biz/public/",
    "autor_nome": "Teresa Roseiro",
    "autor_cargo": "Assistente Técnica"
  },
  {
    "numero_procedimento": "N/A",
    "entidade": "Ensiguarda Escola Profissional, L.da",
    "link": "https://diariodarepublica.pt/dr/detalhe/contrato-publico/27794-941764897",
    "detalhes_completos": "1 - IDENTIFICAÇÃO E CONTACTOS DA ENTIDADE ADJUDICANTE\nDesignação da entidade adjudicante: Ensiguarda Escola Profissional, L.da\nNIPC: 506044882\nEndereço: Rua Comandante Salvador do Nascimento, nº43\nCódigo postal: 6300-678\nLocalidade: Guarda\nPaís: Portugal\nNUT III: PT16J\nDistrito: Guarda\nConcelho: Guarda\nFreguesia: Freguesia de Guarda\nTelefone: 271237034\nFax: 271220410\nEndereço da Entidade (URL): http://www.ensiguarda.com\nEndereço Eletrónico: geral@ensiguarda.com\neDelivery Gateway (URL): https://www.acingov.pt\nFunção da Organização: Adquirente\nNorma jurídica da Entidade Adjudicante: Organismo de direito público\nÁrea de atividade da Autoridade Adjudicante: Educação\n\n2 - JORNAL OFICIAL DA UNIÃO EUROPEIA\nO procedimento a que este anúncio diz respeito também é publicitado no Jornal Oficial da União Europeia? Não\n\n3 - AVISO\nModelo de Anúncio: Concurso público\nData de Envio do Anúncio: 22-10-2025\n\n5 - PROCESSO\nTipo de Procedimento: Concurso público\nPreço base do procedimento: Sim\nValor do preço base do procedimento: 45.000,00 EUR\nProcedimento com lotes? Não\n\n6 - OBJETO DO CONTRATO\nNúmero de referência interna: 1_FDEE_2025\nDesignação do contrato: FORNECIMENTO DE ENERGIA ELÉCTRICA PARA AS INSTALAÇÕES DA ENSIGUARDA  ESCOLA PROFISSIONAL, LDA.\nDescrição: FORNECIMENTO DE ENERGIA ELÉCTRICA PARA AS INSTALAÇÕES DA ENSIGUARDA  ESCOLA PROFISSIONAL, LDA.\nTipo de Contrato Principal: Aquisição de Bens Móveis\nTipo de Contrato: Aquisição de Bens Móveis\nClassificação CPV (Vocabulário Comum para os Contratos Públicos)\nObjeto principal\nVocabulário Principal: 09310000\nPreço base s/IVA: 45.000,00 EUR\n\n7 - INDICAÇÕES ADICIONAIS\nO contrato envolve aquisição conjunta (satisfação de várias entidades)? Não\nO contrato é adjudicado por uma central de compras? Não\n\n8 - TÉCNICAS\nO concurso destina-se à celebração de um acordo-quadro? Inexistência de acordo-quadro\nÉ utilizado um leilão eletrónico? Não\nÉ adotada uma fase de negociação? Não\nSistema de Aquisição Dinâmico: Inexistência de sistema de aquisição dinâmico\n\n9 - LOCAL DA EXECUÇÃO DO CONTRATO\nLOCAL DA EXECUÇÃO DO CONTRATO (PROCEDIMENTO)\nPaís: Portugal\nNUT III: PT16J\nLocalidade: Freguesia de Guarda\nDistrito: Guarda\nConcelho: Guarda\nFreguesia: Freguesia de Guarda\n\n10 - PRAZO DE EXECUÇÃO DO CONTRATO\nPrazo de execução do contrato: 730 DIAS\nPrevisão de renovações: Não\n\n11 - FUNDOS EU\nTêm fundos EU? Sim\n\n12 - DOCUMENTOS DE HABILITAÇÃO\nHabilitação para o exercício da atividade profissional: Sim\nTipo: Outros\nDescrição - Outros: Licença de comercializador de energia elétrica.\nDescrição: Documentos de Habilitação\n\n13 - CONDIÇÕES DE APRESENTAÇÃO\nPlataforma eletrónica utilizada pela entidade adjudicante: ACIN\nURL para Apresentação: https://www.acingov.pt\nAdmissibilidade da apresentação de propostas variantes: Não autorizado\nPrazo para apresentação das propostas: 29-10-2025 23:59\nPrazo durante o qual os concorrentes são obrigados a manter as respetivas propostas: 66 dias a contar do termo do prazo para a apresentação das propostas\nIndicação de Subcontratação na Proposta: Inexistência de indicação de subcontratação\n\n14 - PRESTAÇÃO DE CAUÇÃO\nPrestação de caução: Não\n\n15 - FORNECIMENTO DAS PEÇAS DO CONCURSO, APRESENTAÇÃO DE PEDIDOS DE PARTICIPAÇÃO E APRESENTAÇÃO DAS PROPOSTAS\nLink para acesso às peças do concurso (URL): https://www.acingov.pt/acingovprod/2/zonaPublica/zona_publica_c/donwloadProcedurePiece/OTg5NTY2\n\n20 - OUTROS REQUISITOS\nInformação sobre contratos reservados. Aplica-se a contratos reservados (54º-A)? Não\n\n21 - CRITÉRIO DE ADJUDICAÇÃO\nMultifator: Não\nMonofator:\nNome: Preço\n\n24 - CONDIÇÕES DO CONTRATO\nFaturação Eletrónica: Permitido\nObrigação de Subcontratação:\nCódigo da Obrigação de Subcontratação: Não é aplicável nenhuma obrigação de subcontratação.\n\n25 - COMPRA PÚBLICA ESTRATÉGICA\nCompra Pública Estratégica: Inexistência de contratação pública estratégica\n\n26 - INFORMAÇÕES ADICIONAIS\nContrato adequado para PME: Não\nCobertura ACP (Acordo dos Contratos Públicos da Organização Mundial do Comércio): Não\n\n27 - IDENTIFICAÇÃO E CONTACTOS DO ÓRGÃO DE RECURSOS ADMINISTRATIVOS\nDesignação: Gerência da Ensiguarda\nEndereço: Rua Comandante Salvador do Nascimento, nº43\nCódigo postal: 6300-678\nLocalidade: Guarda\nTelefone: 271237034\nFax: \nEndereço eletrónico: geral@ensiguarda.com\nPrazo de interposição do recurso: 10 dias\n\n28 - IDENTIFICAÇÃO DO(S) AUTOR(ES) DE ANÚNCIO\nNome: Catarina Moitinha\nCargo: Jurista\n419688359",
    "nipc": "506044882",
    "distrito": "Guarda",
    "concelho": "Guarda",
    "freguesia": "Freguesia de Guarda",
    "site": "http://www.ensiguarda.com",
    "email": "geral@ensiguarda.com",
    "designacao_contrato": "FORNECIMENTO DE ENERGIA ELÉCTRICA PARA AS INSTALAÇÕES DA ENSIGUARDA  ESCOLA PROFISSIONAL, LDA.",
    "descricao": "FORNECIMENTO DE ENERGIA ELÉCTRICA PARA AS INSTALAÇÕES DA ENSIGUARDA  ESCOLA PROFISSIONAL, LDA.",
    "preco_base": "45.000,00 EUR",
    "prazo_execucao": "730 DIAS",
    "prazo_apresentacao_propostas": "29-10-2025 23:59",
    "fundos_eu": "Sim",
    "plataforma_eletronica": "ACIN",
    "url_procedimento": "https://www.acingov.pt",
    "autor_nome": "Catarina Moitinha",
    "autor_cargo": "Jurista"
  },
  {
    "numero_procedimento": "N/A",
    "entidade": "Carristur Inovação em Transportes Urbanos e Regionais, Sociedade Unipessoal, L.da",
    "link": "https://diariodarepublica.pt/dr/detalhe/contrato-publico/27796-941764903",
    "detalhes_completos": "1 - IDENTIFICAÇÃO E CONTACTOS DA ENTIDADE ADJUDICANTE\nDesignação da entidade adjudicante: Carristur Inovação em Transportes Urbanos e Regionais, Sociedade Unipessoal, L.da\nNIPC: 501597395\nEndereço: Complexo da Carris de Cabo Ruivo - Av. Dr. Augusto Castro\nCódigo postal: 1950-082\nLocalidade: Lisboa\nPaís: Portugal\nNUT III: PT170\nDistrito: Lisboa\nConcelho: Lisboa\nFreguesia: Todas\nTelefone: 213613193\nFax: 213613052\nEndereço da Entidade (URL): www.carristur.pt\nEndereço Eletrónico: geral.carristur@carris.pt\neDelivery Gateway (URL): https://community.vortal.biz/public/\nFunção da Organização: Adquirente\nNorma jurídica da Entidade Adjudicante: Empresa pública\nÁrea de atividade da Entidade Adjudicante: Serviços urbanos de caminho de ferro, de elétricos, de tróleis ou de autocarros\n\n2 - JORNAL OFICIAL DA UNIÃO EUROPEIA\nO procedimento a que este anúncio diz respeito também é publicitado no Jornal Oficial da União Europeia? Não\n\n3 - AVISO\nModelo de Anúncio: Concurso público\nData de Envio do Anúncio: 22-10-2025\n\n5 - PROCESSO\nTipo de Procedimento: Concurso público\nPreço base do procedimento: Sim\nValor do preço base do procedimento: 220.800,00 EUR\nProcedimento com lotes? Não\n\n6 - OBJETO DO CONTRATO\nNúmero de referência interna: CP 10/2025\nDesignação do contrato: GUIAS TURÍSTICOS\nDescrição: O presente procedimento tem como objeto a aquisição de Serviços de Guias Turísticos em Circuitos Pedestres e de Autocarro, a realizar nas regiões de Lisboa, Setúbal e do Porto, podendo o serviço ser prestado noutras cidades em Portugal, para a CARRISTUR, nos termos melhores definidos nas cláusulas técnicas do presente Caderno de Encargos.\nTipo de Contrato Principal: Aquisição de Serviços\nTipo de Contrato: Aquisição de Serviços\nClassificação CPV (Vocabulário Comum para os Contratos Públicos)\nObjeto principal\nVocabulário Principal: 63514000\nPreço base s/IVA: 220.800,00 EUR\n\n7 - INDICAÇÕES ADICIONAIS\nO contrato envolve aquisição conjunta (satisfação de várias entidades)? Não\nO contrato é adjudicado por uma central de compras? Não\n\n8 - TÉCNICAS\nO concurso destina-se à celebração de um acordo-quadro? Inexistência de acordo-quadro\nÉ utilizado um leilão eletrónico? Não\nÉ adotada uma fase de negociação? Não\nSistema de Aquisição Dinâmico: Inexistência de sistema de aquisição dinâmico\n\n9 - LOCAL DA EXECUÇÃO DO CONTRATO\nLOCAL DA EXECUÇÃO DO CONTRATO (PROCEDIMENTO)\nPaís: Portugal\nNUT III: PT170\nLocalidade: Lisboa\nDistrito: Lisboa\nConcelho: Lisboa\nFreguesia: Todas\n\n10 - PRAZO DE EXECUÇÃO DO CONTRATO\nPrazo de execução do contrato: 12 MESES\nPrevisão de renovações: Não\n\n11 - FUNDOS EU\nTêm fundos EU? Não\n\n12 - DOCUMENTOS DE HABILITAÇÃO\nHabilitação para o exercício da atividade profissional: Não\n\n13 - CONDIÇÕES DE APRESENTAÇÃO\nPlataforma eletrónica utilizada pela entidade adjudicante: VORTAL\nURL para Apresentação: https://community.vortal.biz/public/\nAdmissibilidade da apresentação de propostas variantes: Não autorizado\nPrazo para apresentação das propostas: 30-10-2025 23:59\nPrazo durante o qual os concorrentes são obrigados a manter as respetivas propostas: 66 dias a contar do termo do prazo para a apresentação das propostas\nIndicação de Subcontratação na Proposta: Inexistência de indicação de subcontratação\n\n14 - PRESTAÇÃO DE CAUÇÃO\nPrestação de caução: Não\n\n15 - FORNECIMENTO DAS PEÇAS DO CONCURSO, APRESENTAÇÃO DE PEDIDOS DE PARTICIPAÇÃO E APRESENTAÇÃO DAS PROPOSTAS\nLink para acesso às peças do concurso (URL): https://community.vortal.biz/Public/public-tender-documents/TEtRdWI5V1k2dk84bTAzektjN2tSWUF1d0IybitObFlCWVcrZ3NhSUNJUC9EY0hrK2U2Y2YzV3B6d3lIVG1rdGRmWjZkQ2NhSmdkMnQ0WGU1YlZsaWc9PUpJISpl\n\n20 - OUTROS REQUISITOS\nInformação sobre contratos reservados. Aplica-se a contratos reservados (54º-A)? Não\n\n21 - CRITÉRIO DE ADJUDICAÇÃO\nMultifator: Não\nMonofator:\nNome: Preço\n\n24 - CONDIÇÕES DO CONTRATO\nFaturação Eletrónica: Permitido\nObrigação de Subcontratação:\nCódigo da Obrigação de Subcontratação: Não é aplicável nenhuma obrigação de subcontratação.\n\n25 - COMPRA PÚBLICA ESTRATÉGICA\nCompra Pública Estratégica: Inexistência de contratação pública estratégica\n\n26 - INFORMAÇÕES ADICIONAIS\nContrato adequado para PME: Sim\nCobertura ACP (Acordo dos Contratos Públicos da Organização Mundial do Comércio): Não\n\n27 - IDENTIFICAÇÃO E CONTACTOS DO ÓRGÃO DE RECURSOS ADMINISTRATIVOS\nDesignação: Carristur, Inovação em Transportes Urbanos e Regionais, Lda.\nEndereço: Complexo da Carris de Cabo Ruivo - Av. Dr. Augusto Castro\nCódigo postal: 1950-082\nLocalidade: Lisboa\nTelefone: +351 213613193\nFax: +351 213613152\nEndereço eletrónico: joao.oliveira@carris.pt\n\n28 - IDENTIFICAÇÃO DO(S) AUTOR(ES) DE ANÚNCIO\nNome: João Oliveira\nCargo: Procurement\n419686836",
    "nipc": "501597395",
    "distrito": "Lisboa",
    "concelho": "Lisboa",
    "freguesia": "Todas",
    "site": "www.carristur.pt",
    "email": "geral.carristur@carris.pt",
    "designacao_contrato": "GUIAS TURÍSTICOS",
    "descricao": "O presente procedimento tem como objeto a aquisição de Serviços de Guias Turísticos em Circuitos Pedestres e de Autocarro, a realizar nas regiões de Lisboa, Setúbal e do Porto, podendo o serviço ser prestado noutras cidades em Portugal, para a CARRISTUR, nos termos melhores definidos nas cláusulas técnicas do presente Caderno de Encargos.",
    "preco_base": "220.800,00 EUR",
    "prazo_execucao": "12 MESES",
    "prazo_apresentacao_propostas": "30-10-2025 23:59",
    "fundos_eu": "Não",
    "plataforma_eletronica": "VORTAL",
    "url_procedimento": "https://community.vortal.biz/public/",
    "autor_nome": "João Oliveira",
    "autor_cargo": "Procurement"
  },
  {
    "numero_procedimento": "N/A",
    "entidade": "Município de Ovar",
    "link": "https://diariodarepublica.pt/dr/detalhe/contrato-publico/27798-941764904",
    "detalhes_completos": "1 - IDENTIFICAÇÃO E CONTACTOS DA ENTIDADE ADJUDICANTE\nDesignação da entidade adjudicante: Município de Ovar\nNIPC: 501306269\nServiço/Órgão/Pessoa de contacto: Departamento Administrativo, Jurídico e Financeiro - Serviço de Contratação Pública\nEndereço: Praça República\nCódigo postal: 3880-141\nLocalidade: Ovar\nPaís: Portugal\nNUT III: PT16D\nDistrito: Aveiro\nConcelho: Ovar\nFreguesia: Todas\nTelefone: 256581300\nFax: 256586611\nEndereço da Entidade (URL): www.cm-ovar.pt\nEndereço Eletrónico: avisosdepropostas@cm-ovar.pt\neDelivery Gateway (URL): https://community.vortal.biz/public/\nFunção da Organização: Adquirente\nNorma jurídica da Entidade Adjudicante: Autoridade local\nÁrea de atividade da Autoridade Adjudicante: Serviços públicos das administrações públicas\n\n2 - JORNAL OFICIAL DA UNIÃO EUROPEIA\nO procedimento a que este anúncio diz respeito também é publicitado no Jornal Oficial da União Europeia? Não\n\n3 - AVISO\nModelo de Anúncio: Concurso limitado por prévia qualificação\nData de Envio do Anúncio: 22-10-2025\n\n5 - PROCESSO\nTipo de Procedimento: Concurso limitado por prévia qualificação\nPreço base do procedimento: Sim\nValor do preço base do procedimento: 65.842,00 EUR\nProcedimento com lotes? Não\n\n6 - OBJETO DO CONTRATO\nNúmero de referência interna: 2025/300.10.005/1052\nDesignação do contrato: Aquisição de serviços de segurança e vigilância do evento \"Carnaval de Ovar de 2026\"\nDescrição: Aquisição de serviços de segurança e vigilância do evento \"Carnaval de Ovar de 2026\"\nTipo de Contrato Principal: Aquisição de Serviços\nTipo de Contrato: Aquisição de Serviços\nClassificação CPV (Vocabulário Comum para os Contratos Públicos)\nObjeto principal\nVocabulário Principal: 79714000\nPreço base s/IVA: 65.842,00 EUR\n\n7 - INDICAÇÕES ADICIONAIS\nO contrato envolve aquisição conjunta (satisfação de várias entidades)? Não\nO contrato é adjudicado por uma central de compras? Não\n\n8 - TÉCNICAS\nO concurso destina-se à celebração de um acordo-quadro? Inexistência de acordo-quadro\nÉ utilizado um leilão eletrónico? Não\nSistema de Aquisição Dinâmico: Inexistência de sistema de aquisição dinâmico\n\n9 - LOCAL DA EXECUÇÃO DO CONTRATO\nLOCAL DA EXECUÇÃO DO CONTRATO (PROCEDIMENTO)\nPaís: Portugal\nNUT III: PT16D\nLocalidade: Ovar\nDistrito: Aveiro\nConcelho: Ovar\nFreguesia: União das Freguesias de Ovar, São João, Arada e São Vicente de Pereira Jusã\n\n10 - PRAZO DE EXECUÇÃO DO CONTRATO\nPrazo de execução do contrato: 34 DIAS\nPrevisão de renovações: Não\n\n11 - FUNDOS EU\nTêm fundos EU? Não\n\n12 - DOCUMENTOS DE HABILITAÇÃO\nHabilitação para o exercício da atividade profissional: Não\n\n13 - CONDIÇÕES DE APRESENTAÇÃO\nPlataforma eletrónica utilizada pela entidade adjudicante: VORTAL\nURL para Apresentação: https://community.vortal.biz/public/\nAdmissibilidade da apresentação de propostas variantes: Não autorizado\nPrazo para apresentação das candidaturas: 04-11-2025 17:00\nRequisitos mínimos \nRequisitos mínimos de capacidade técnica: Conforme as peças do procedimento\nRequisitos mínimos de capacidade financeira: Conforme as peças do procedimento\nPrazo durante o qual os concorrentes são obrigados a manter as respetivas propostas: 44 dias a contar do termo do prazo para a apresentação das propostas\nIndicação de Subcontratação na Proposta: Inexistência de indicação de subcontratação\n\n14 - PRESTAÇÃO DE CAUÇÃO\nPrestação de caução: Não\n\n15 - FORNECIMENTO DAS PEÇAS DO CONCURSO, APRESENTAÇÃO DE PEDIDOS DE PARTICIPAÇÃO E APRESENTAÇÃO DAS PROPOSTAS\nLink para acesso às peças do concurso (URL): https://community.vortal.biz/Public/public-tender-documents/ZTVnaVljYTRpa0xDWC9HSlBNWndES1hXSDFNM051Y3ZrMHR5MEN6Tk90elBra2VTRHdxMzVvd2hBdmdrV3RnRGZNS1RUQ3ZaMG5hSVBPaGFqWWFNSXc9PUBQZSlC\n\n20 - OUTROS REQUISITOS\nInformação sobre contratos reservados. Aplica-se a contratos reservados (54º-A)? Não\n\n21 - CRITÉRIO DE ADJUDICAÇÃO\nMultifator: Não\nMonofator:\nNome: Preço\n\n24 - CONDIÇÕES DO CONTRATO\nFaturação Eletrónica: Permitido\nObrigação de Subcontratação:\nCódigo da Obrigação de Subcontratação: Não é aplicável nenhuma obrigação de subcontratação.\n\n25 - COMPRA PÚBLICA ESTRATÉGICA\nCompra Pública Estratégica: Inexistência de contratação pública estratégica\n\n26 - INFORMAÇÕES ADICIONAIS\nContrato adequado para PME: Sim\nCobertura ACP (Acordo dos Contratos Públicos da Organização Mundial do Comércio): Não\n\n27 - IDENTIFICAÇÃO E CONTACTOS DO ÓRGÃO DE RECURSOS ADMINISTRATIVOS\nDesignação: Câmara Municipal de Ovar\nEndereço: Praça da República\nCódigo postal: 3880-141\nLocalidade: Ovar\nTelefone: +351 256581300\nFax: +351 256586611\nEndereço eletrónico: gapresidencia@cm-ovar.pt\n\n28 - IDENTIFICAÇÃO DO(S) AUTOR(ES) DE ANÚNCIO\nNome: Domingos Silva\nCargo: Presidente da Câmara Municipal de Ovar\n419685734",
    "nipc": "501306269",
    "distrito": "Aveiro",
    "concelho": "Ovar",
    "freguesia": "Todas",
    "site": "www.cm-ovar.pt",
    "email": "avisosdepropostas@cm-ovar.pt",
    "designacao_contrato": "Aquisição de serviços de segurança e vigilância do evento \"Carnaval de Ovar de 2026\"",
    "descricao": "Aquisição de serviços de segurança e vigilância do evento \"Carnaval de Ovar de 2026\"",
    "preco_base": "65.842,00 EUR",
    "prazo_execucao": "34 DIAS",
    "prazo_apresentacao_propostas": null,
    "fundos_eu": "Não",
    "plataforma_eletronica": "VORTAL",
    "url_procedimento": "https://community.vortal.biz/public/",
    "autor_nome": "Domingos Silva",
    "autor_cargo": "Presidente da Câmara Municipal de Ovar"
  },
  {
    "numero_procedimento": "N/A",
    "entidade": "AnÃºncio de procedimento  n.Âº 27801/2025  -  DiÃ¡rio da RepÃºblica n.Âº 205/2025, SÃ©rie II de 2025-10-23",
    "link": "https://diariodarepublica.pt/dr/detalhe/contrato-publico/27801-941764911"
  },
  {
    "numero_procedimento": "N/A",
    "entidade": "Município de Ovar",
    "link": "https://diariodarepublica.pt/dr/detalhe/contrato-publico/27803-941764912",
    "detalhes_completos": "1 - IDENTIFICAÇÃO E CONTACTOS DA ENTIDADE ADJUDICANTE\nDesignação da entidade adjudicante: Município de Ovar\nNIPC: 501306269\nServiço/Órgão/Pessoa de contacto: Departamento Administrativo, Jurídico e Financeiro - Serviço de Contratação Pública\nEndereço: Praça República\nCódigo postal: 3880-141\nLocalidade: Ovar\nPaís: Portugal\nNUT III: PT16D\nDistrito: Aveiro\nConcelho: Ovar\nFreguesia: Todas\nTelefone: 256581300\nFax: 256586611\nEndereço da Entidade (URL): www.cm-ovar.pt\nEndereço Eletrónico: avisosdepropostas@cm-ovar.pt\neDelivery Gateway (URL): https://community.vortal.biz/public/\nFunção da Organização: Adquirente\nNorma jurídica da Entidade Adjudicante: Autoridade local\nÁrea de atividade da Autoridade Adjudicante: Serviços públicos das administrações públicas\n\n2 - JORNAL OFICIAL DA UNIÃO EUROPEIA\nO procedimento a que este anúncio diz respeito também é publicitado no Jornal Oficial da União Europeia? Não\n\n3 - AVISO\nModelo de Anúncio: Concurso público\nData de Envio do Anúncio: 22-10-2025\n\n5 - PROCESSO\nTipo de Procedimento: Concurso público\nPreço base do procedimento: Sim\nValor do preço base do procedimento: 9.075,00 EUR\nProcedimento com lotes? Não\n\n6 - OBJETO DO CONTRATO\nNúmero de referência interna: 2025/300.10.005/1060\nDesignação do contrato: Aquisição de serviços de pré-produção e produção executiva para o Carnaval de Ovar de 2026\nDescrição: Aquisição de serviços de pré-produção e produção executiva para o Carnaval de Ovar de 2026\nTipo de Contrato Principal: Aquisição de Serviços\nTipo de Contrato: Aquisição de Serviços\nClassificação CPV (Vocabulário Comum para os Contratos Públicos)\nObjeto principal\nVocabulário Principal: 79952100\nPreço base s/IVA: 9.075,00 EUR\n\n7 - INDICAÇÕES ADICIONAIS\nO contrato envolve aquisição conjunta (satisfação de várias entidades)? Não\nO contrato é adjudicado por uma central de compras? Não\n\n8 - TÉCNICAS\nO concurso destina-se à celebração de um acordo-quadro? Inexistência de acordo-quadro\nÉ utilizado um leilão eletrónico? Não\nÉ adotada uma fase de negociação? Não\nSistema de Aquisição Dinâmico: Inexistência de sistema de aquisição dinâmico\n\n9 - LOCAL DA EXECUÇÃO DO CONTRATO\nLOCAL DA EXECUÇÃO DO CONTRATO (PROCEDIMENTO)\nPaís: Portugal\nNUT III: PT16D\nLocalidade: Ovar\nDistrito: Aveiro\nConcelho: Ovar\nFreguesia: União das Freguesias de Ovar, São João, Arada e São Vicente de Pereira Jusã\n\n10 - PRAZO DE EXECUÇÃO DO CONTRATO\nPrazo de execução do contrato: 90 DIAS\nPrevisão de renovações: Não\n\n11 - FUNDOS EU\nTêm fundos EU? Não\n\n12 - DOCUMENTOS DE HABILITAÇÃO\nHabilitação para o exercício da atividade profissional: Não\n\n13 - CONDIÇÕES DE APRESENTAÇÃO\nPlataforma eletrónica utilizada pela entidade adjudicante: VORTAL\nURL para Apresentação: https://community.vortal.biz/public/\nAdmissibilidade da apresentação de propostas variantes: Não autorizado\nPrazo para apresentação das propostas: 31-10-2025 17:00\nPrazo durante o qual os concorrentes são obrigados a manter as respetivas propostas: 66 dias a contar do termo do prazo para a apresentação das propostas\nIndicação de Subcontratação na Proposta: Inexistência de indicação de subcontratação\n\n14 - PRESTAÇÃO DE CAUÇÃO\nPrestação de caução: Não\n\n15 - FORNECIMENTO DAS PEÇAS DO CONCURSO, APRESENTAÇÃO DE PEDIDOS DE PARTICIPAÇÃO E APRESENTAÇÃO DAS PROPOSTAS\nLink para acesso às peças do concurso (URL): https://community.vortal.biz/Public/public-tender-documents/MysxeCtOQVB1MVB2YzlGUXQ5NVNGQzRqckUrb2FlVzloWjFWbjhTT1J6SnZIN0NsNzNBWFljUi9Oc3pla0dzMDVCZThEbnhDd25vaDZKZnJEWCtlQXc9PVNPRXhE\n\n20 - OUTROS REQUISITOS\nInformação sobre contratos reservados. Aplica-se a contratos reservados (54º-A)? Não\n\n21 - CRITÉRIO DE ADJUDICAÇÃO\nMultifator: Sim\nFator: \nNome: Preço\nPonderação: 20%\nSubfatores: Não\nFator: \nNome: Qualidade\nPonderação: 80%\nSubfatores: Não\n\n24 - CONDIÇÕES DO CONTRATO\nFaturação Eletrónica: Permitido\nObrigação de Subcontratação:\nCódigo da Obrigação de Subcontratação: Não é aplicável nenhuma obrigação de subcontratação.\n\n25 - COMPRA PÚBLICA ESTRATÉGICA\nCompra Pública Estratégica: Inexistência de contratação pública estratégica\n\n26 - INFORMAÇÕES ADICIONAIS\nContrato adequado para PME: Sim\nCobertura ACP (Acordo dos Contratos Públicos da Organização Mundial do Comércio): Não\n\n27 - IDENTIFICAÇÃO E CONTACTOS DO ÓRGÃO DE RECURSOS ADMINISTRATIVOS\nDesignação: Câmara Municipal de Ovar\nEndereço: Praça da República\nCódigo postal: 3880-141\nLocalidade: Ovar\nTelefone: +351 256581300\nFax: +351 256586611\nEndereço eletrónico: gapresidencia@cm-ovar.pt\n\n28 - IDENTIFICAÇÃO DO(S) AUTOR(ES) DE ANÚNCIO\nNome: Domingos Silva\nCargo: Presidente da Câmara Municipal de Ovar\n419682883",
    "nipc": "501306269",
    "distrito": "Aveiro",
    "concelho": "Ovar",
    "freguesia": "Todas",
    "site": "www.cm-ovar.pt",
    "email": "avisosdepropostas@cm-ovar.pt",
    "designacao_contrato": "Aquisição de serviços de pré-produção e produção executiva para o Carnaval de Ovar de 2026",
    "descricao": "Aquisição de serviços de pré-produção e produção executiva para o Carnaval de Ovar de 2026",
    "preco_base": "9.075,00 EUR",
    "prazo_execucao": "90 DIAS",
    "prazo_apresentacao_propostas": "31-10-2025 17:00",
    "fundos_eu": "Não",
    "plataforma_eletronica": "VORTAL",
    "url_procedimento": "https://community.vortal.biz/public/",
    "autor_nome": "Domingos Silva",
    "autor_cargo": "Presidente da Câmara Municipal de Ovar"
  },
  {
    "numero_procedimento": "N/A",
    "entidade": "AnÃºncio de procedimento  n.Âº 27805/2025  -  DiÃ¡rio da RepÃºblica n.Âº 205/2025, SÃ©rie II de 2025-10-23",
    "link": "https://diariodarepublica.pt/dr/detalhe/contrato-publico/27805-941764935"
  },
  {
    "numero_procedimento": "N/A",
    "entidade": "E. P. F. - Ensino Profissional de Felgueiras, E. M., Unipessoal, L.da",
    "link": "https://diariodarepublica.pt/dr/detalhe/contrato-publico/27806-941764936",
    "detalhes_completos": "1 - IDENTIFICAÇÃO E CONTACTOS DA ENTIDADE ADJUDICANTE\nDesignação da entidade adjudicante: E. P. F. - Ensino Profissional de Felgueiras, E. M., Unipessoal, L.da\nNIPC: 504575848\nServiço/Órgão/Pessoa de contacto: Gerência\nEndereço: Rua dos Bombeiros Voluntários de Felgueiras, 104\nCódigo postal: 4610-165\nLocalidade: Felgueiras\nPaís: Portugal\nNUT III: PT11C\nDistrito: Porto\nConcelho: Felgueiras\nFreguesia: União das Freguesias de Margaride (Santa Eulália), Várzea, Lagares, Varziela e Moure\nTelefone: 255312482\nFax: 255312419\nEndereço da Entidade (URL): www.epfelgueiras.pt\nEndereço Eletrónico: epf@epfelgueiras.pt\neDelivery Gateway (URL): https://www.acingov.pt\nFunção da Organização: Adquirente\nNorma jurídica da Entidade Adjudicante: Organismo de direito público\nÁrea de atividade da Autoridade Adjudicante: Serviços públicos das administrações públicas\n\n2 - JORNAL OFICIAL DA UNIÃO EUROPEIA\nO procedimento a que este anúncio diz respeito também é publicitado no Jornal Oficial da União Europeia? Não\n\n3 - AVISO\nModelo de Anúncio: Concurso público\nData de Envio do Anúncio: 22-10-2025\n\n5 - PROCESSO\nTipo de Procedimento: Concurso público\nPreço base do procedimento: Sim\nValor do preço base do procedimento: 4.000,00 EUR\nProcedimento com lotes? Não\n\n6 - OBJETO DO CONTRATO\nNúmero de referência interna: CoP006/2025\nDesignação do contrato: Aquisição de serviços de transporte para sessões formativas para o ano letivo 2025/2026\nDescrição: Aquisição de serviços de transporte para sessões formativas para o ano letivo 2025/2026\nTipo de Contrato Principal: Aquisição de Serviços\nTipo de Contrato: Aquisição de Serviços\nClassificação CPV (Vocabulário Comum para os Contratos Públicos)\nObjeto principal\nVocabulário Principal: 60130000\nPreço base s/IVA: 4.000,00 EUR\n\n7 - INDICAÇÕES ADICIONAIS\nO contrato envolve aquisição conjunta (satisfação de várias entidades)? Não\nO contrato é adjudicado por uma central de compras? Não\n\n8 - TÉCNICAS\nO concurso destina-se à celebração de um acordo-quadro? Inexistência de acordo-quadro\nÉ utilizado um leilão eletrónico? Não\nÉ adotada uma fase de negociação? Não\nSistema de Aquisição Dinâmico: Inexistência de sistema de aquisição dinâmico\n\n9 - LOCAL DA EXECUÇÃO DO CONTRATO\nLOCAL DA EXECUÇÃO DO CONTRATO (PROCEDIMENTO)\nPaís: Portugal\nNUT III: PT11C\nLocalidade: União das Freguesias de Margaride (Santa Eulália), Várzea, Lagares, Varziela e Moure\nDistrito: Porto\nConcelho: Felgueiras\nFreguesia: União das Freguesias de Margaride (Santa Eulália), Várzea, Lagares, Varziela e Moure\n\n10 - PRAZO DE EXECUÇÃO DO CONTRATO\nPrazo de execução do contrato: 263 DIAS\nPrevisão de renovações: Não\n\n11 - FUNDOS EU\nTêm fundos EU? Sim\n\n12 - DOCUMENTOS DE HABILITAÇÃO\nHabilitação para o exercício da atividade profissional: Não\n\n13 - CONDIÇÕES DE APRESENTAÇÃO\nPlataforma eletrónica utilizada pela entidade adjudicante: ACIN\nURL para Apresentação: https://www.acingov.pt\nAdmissibilidade da apresentação de propostas variantes: Não autorizado\nPrazo para apresentação das propostas: 28-10-2025 23:59\nPrazo durante o qual os concorrentes são obrigados a manter as respetivas propostas: 66 dias a contar do termo do prazo para a apresentação das propostas\nIndicação de Subcontratação na Proposta: Inexistência de indicação de subcontratação\n\n14 - PRESTAÇÃO DE CAUÇÃO\nPrestação de caução: Não\n\n15 - FORNECIMENTO DAS PEÇAS DO CONCURSO, APRESENTAÇÃO DE PEDIDOS DE PARTICIPAÇÃO E APRESENTAÇÃO DAS PROPOSTAS\nLink para acesso às peças do concurso (URL): https://www.acingov.pt/acingovprod/2/zonaPublica/zona_publica_c/donwloadProcedurePiece/OTg5Mzgx\n\n20 - OUTROS REQUISITOS\nInformação sobre contratos reservados. Aplica-se a contratos reservados (54º-A)? Não\n\n21 - CRITÉRIO DE ADJUDICAÇÃO\nMultifator: Não\nMonofator:\nNome: Outros\nOutro nome: Fator Preço\n\n24 - CONDIÇÕES DO CONTRATO\nFaturação Eletrónica: Necessário\nObrigação de Subcontratação:\nCódigo da Obrigação de Subcontratação: Não é aplicável nenhuma obrigação de subcontratação.\n\n25 - COMPRA PÚBLICA ESTRATÉGICA\nCompra Pública Estratégica: Inexistência de contratação pública estratégica\n\n26 - INFORMAÇÕES ADICIONAIS\nContrato adequado para PME: Sim\nCobertura ACP (Acordo dos Contratos Públicos da Organização Mundial do Comércio): Não\n\n27 - IDENTIFICAÇÃO E CONTACTOS DO ÓRGÃO DE RECURSOS ADMINISTRATIVOS\nDesignação: Gerência\nEndereço: Rua dos Bombeiros Voluntários de Felgueiras, 104\nCódigo postal: 4610-165\nLocalidade: Felgueiras\nTelefone: 255312482\nFax: 255312419\nEndereço eletrónico: epf@epfelgueiras.pt\nPrazo de interposição do recurso: 5 dias\n\n28 - IDENTIFICAÇÃO DO(S) AUTOR(ES) DE ANÚNCIO\nNome: Vera Lúcia Ribeiro Sampaio\nCargo: Gerência\n419689103",
    "nipc": "504575848",
    "distrito": "Porto",
    "concelho": "Felgueiras",
    "freguesia": "União das Freguesias de Margaride (Santa Eulália), Várzea, Lagares, Varziela e Moure",
    "site": "www.epfelgueiras.pt",
    "email": "epf@epfelgueiras.pt",
    "designacao_contrato": "Aquisição de serviços de transporte para sessões formativas para o ano letivo 2025/2026",
    "descricao": "Aquisição de serviços de transporte para sessões formativas para o ano letivo 2025/2026",
    "preco_base": "4.000,00 EUR",
    "prazo_execucao": "263 DIAS",
    "prazo_apresentacao_propostas": "28-10-2025 23:59",
    "fundos_eu": "Sim",
    "plataforma_eletronica": "ACIN",
    "url_procedimento": "https://www.acingov.pt",
    "autor_nome": "Vera Lúcia Ribeiro Sampaio",
    "autor_cargo": "Gerência"
  },
  {
    "numero_procedimento": "N/A",
    "entidade": "ISCTE - Instituto Universitário de Lisboa",
    "link": "https://diariodarepublica.pt/dr/detalhe/contrato-publico/27807-941764937",
    "detalhes_completos": "1 - IDENTIFICAÇÃO E CONTACTOS DA ENTIDADE ADJUDICANTE\nDesignação da entidade adjudicante: ISCTE - Instituto Universitário de Lisboa\nNIPC: 501510184\nServiço/Órgão/Pessoa de contacto: Unidade de Compras\nEndereço: Avenida Das Forças Armadas (Iscte)\nCódigo postal: 1600-083\nLocalidade: Lisboa\nPaís: Portugal\nNUT III: PT170\nDistrito: Lisboa\nConcelho: Lisboa\nFreguesia: Freguesia de Alvalade - Lisboa\nTelefone: 217903000\nEndereço da Entidade (URL): https://www.iscte-iul.pt/\nEndereço Eletrónico: upc@iscte-iul.pt\neDelivery Gateway (URL): https://www.acingov.pt\nFunção da Organização: Adquirente\nSubfunção da Organização: Líder do grupo\nNorma jurídica da Entidade Adjudicante: Organismo de direito público\nÁrea de atividade da Autoridade Adjudicante: Serviços públicos das administrações públicas\n\n2 - JORNAL OFICIAL DA UNIÃO EUROPEIA\nO procedimento a que este anúncio diz respeito também é publicitado no Jornal Oficial da União Europeia? Não\n\n3 - AVISO\nModelo de Anúncio: Concurso público\nData de Envio do Anúncio: 22-10-2025\n\n5 - PROCESSO\nTipo de Procedimento: Concurso público\nPreço base do procedimento: Sim\nValor do preço base do procedimento: 181.000,00 EUR\nProcedimento com lotes? Não\n\n6 - OBJETO DO CONTRATO\nNúmero de referência interna: REF.ª 2025/ SPF/UC/1411\nDesignação do contrato: CONCURSO PUBLICO PARA A PRESTAÇÃO DE SERVIÇOS DE PAGAMENTOS ELETRÓNICOS NO ISCTE\nDescrição: CONCURSO PUBLICO PARA A PRESTAÇÃO DE SERVIÇOS DE PAGAMENTOS ELETRÓNICOS NO ISCTE\nTipo de Contrato Principal: Aquisição de Serviços\nTipo de Contrato: Aquisição de Serviços\nClassificação CPV (Vocabulário Comum para os Contratos Públicos)\nObjeto principal\nVocabulário Principal: 66152000\nPreço base s/IVA: 181.000,00 EUR\n\n7 - INDICAÇÕES ADICIONAIS\nO contrato envolve aquisição conjunta (satisfação de várias entidades)? Não\nO contrato é adjudicado por uma central de compras? Não\n\n8 - TÉCNICAS\nO concurso destina-se à celebração de um acordo-quadro? Inexistência de acordo-quadro\nÉ utilizado um leilão eletrónico? Não\nÉ adotada uma fase de negociação? Não\nSistema de Aquisição Dinâmico: Inexistência de sistema de aquisição dinâmico\n\n9 - LOCAL DA EXECUÇÃO DO CONTRATO\nLOCAL DA EXECUÇÃO DO CONTRATO (PROCEDIMENTO)\nPaís: Portugal\nNUT III: PT170\nLocalidade: Freguesia de Alvalade - Lisboa\nDistrito: Lisboa\nConcelho: Lisboa\nFreguesia: Freguesia de Alvalade - Lisboa\n\n10 - PRAZO DE EXECUÇÃO DO CONTRATO\nPrazo de execução do contrato: 24 MESES\nPrevisão de renovações: Não\n\n11 - FUNDOS EU\nTêm fundos EU? Não\n\n12 - DOCUMENTOS DE HABILITAÇÃO\nHabilitação para o exercício da atividade profissional: Não\n\n13 - CONDIÇÕES DE APRESENTAÇÃO\nPlataforma eletrónica utilizada pela entidade adjudicante: ACIN\nURL para Apresentação: https://www.acingov.pt\nAdmissibilidade da apresentação de propostas variantes: Não autorizado\nPrazo para apresentação das propostas: 27-10-2025 17:00\nPrazo durante o qual os concorrentes são obrigados a manter as respetivas propostas: 66 dias a contar do termo do prazo para a apresentação das propostas\nIndicação de Subcontratação na Proposta: Inexistência de indicação de subcontratação\n\n14 - PRESTAÇÃO DE CAUÇÃO\nPrestação de caução: Não\n\n15 - FORNECIMENTO DAS PEÇAS DO CONCURSO, APRESENTAÇÃO DE PEDIDOS DE PARTICIPAÇÃO E APRESENTAÇÃO DAS PROPOSTAS\nLink para acesso às peças do concurso (URL): https://www.acingov.pt/acingovprod/2/zonaPublica/zona_publica_c/donwloadProcedurePiece/OTg4NjE2\n\n20 - OUTROS REQUISITOS\nInformação sobre contratos reservados. Aplica-se a contratos reservados (54º-A)? Não\n\n21 - CRITÉRIO DE ADJUDICAÇÃO\nMultifator: Não\nMonofator:\nNome: Preço\n\n24 - CONDIÇÕES DO CONTRATO\nFaturação Eletrónica: Permitido\nObrigação de Subcontratação:\nCódigo da Obrigação de Subcontratação: Não é aplicável nenhuma obrigação de subcontratação.\n\n25 - COMPRA PÚBLICA ESTRATÉGICA\nCompra Pública Estratégica: Inexistência de contratação pública estratégica\n\n26 - INFORMAÇÕES ADICIONAIS\nContrato adequado para PME: Não\nCobertura ACP (Acordo dos Contratos Públicos da Organização Mundial do Comércio): Não\n\n27 - IDENTIFICAÇÃO E CONTACTOS DO ÓRGÃO DE RECURSOS ADMINISTRATIVOS\nDesignação: Iscte\nEndereço: Av. Forças Armadas, Edifício ISCTE\nCódigo postal: 1649-026\nLocalidade: Lisboa\nTelefone: 963297705\nFax: \nEndereço eletrónico: upc@iscte-iul.pt\nPrazo de interposição do recurso: 30 dias\n\n28 - IDENTIFICAÇÃO DO(S) AUTOR(ES) DE ANÚNCIO\nNome: Maria de Lurdes Rodrigues\nCargo: Reitora\n419681724",
    "nipc": "501510184",
    "distrito": "Lisboa",
    "concelho": "Lisboa",
    "freguesia": "Freguesia de Alvalade - Lisboa",
    "site": "https://www.iscte-iul.pt/",
    "email": "upc@iscte-iul.pt",
    "designacao_contrato": "CONCURSO PUBLICO PARA A PRESTAÇÃO DE SERVIÇOS DE PAGAMENTOS ELETRÓNICOS NO ISCTE",
    "descricao": "CONCURSO PUBLICO PARA A PRESTAÇÃO DE SERVIÇOS DE PAGAMENTOS ELETRÓNICOS NO ISCTE",
    "preco_base": "181.000,00 EUR",
    "prazo_execucao": "24 MESES",
    "prazo_apresentacao_propostas": "27-10-2025 17:00",
    "fundos_eu": "Não",
    "plataforma_eletronica": "ACIN",
    "url_procedimento": "https://www.acingov.pt",
    "autor_nome": "Maria de Lurdes Rodrigues",
    "autor_cargo": "Reitora"
  },
  {
    "numero_procedimento": "N/A",
    "entidade": "SPMS - Serviços Partilhados do Ministério da Saúde, E. P. E.",
    "link": "https://diariodarepublica.pt/dr/detalhe/contrato-publico/27808-941764938",
    "detalhes_completos": "1 - IDENTIFICAÇÃO E CONTACTOS DA ENTIDADE ADJUDICANTE\nDesignação da entidade adjudicante: SPMS - Serviços Partilhados do Ministério da Saúde, E. P. E.\nNIPC: 509540716\nEndereço: Avenida da República 61\nCódigo postal: 1050-189\nLocalidade: Lisboa\nPaís: Portugal\nNUT III: PT170\nDistrito: Lisboa\nConcelho: Lisboa\nFreguesia: Todas\nTelefone: 211545600\nFax: 211545649\nEndereço da Entidade (URL): www.spms.min-saude.pt/\nEndereço Eletrónico: contratacao@spms.min-saude.pt\neDelivery Gateway (URL): https://community.vortal.biz/public/\nFunção da Organização: Adquirente\nNorma jurídica da Entidade Adjudicante: Empresa pública\nÁrea de atividade da Autoridade Adjudicante: Saúde\n\n2 - JORNAL OFICIAL DA UNIÃO EUROPEIA\nO procedimento a que este anúncio diz respeito também é publicitado no Jornal Oficial da União Europeia? Sim\n\n3 - AVISO\nModelo de Anúncio: Concurso público\nData de Envio do Anúncio: 20-10-2025\n\n5 - PROCESSO\nTipo de Procedimento: Concurso público\nPreço base do procedimento: Não\nProcedimento com lotes? Não\n\n6 - OBJETO DO CONTRATO\nNúmero de referência interna: 1746/2025 \nDesignação do contrato: Medicamentos do grupo do sangue\nDescrição: Acordo-quadro de medicamentos do grupo do sangue\nOpções: Não\nTipo de Contrato Principal: Aquisição de Bens Móveis\nTipo de Contrato: Aquisição de Bens Móveis\nClassificação CPV (Vocabulário Comum para os Contratos Públicos)\nObjeto principal\nVocabulário Principal: 33600000\n\n7 - INDICAÇÕES ADICIONAIS\nO contrato envolve aquisição conjunta (satisfação de várias entidades)? Não\nO contrato é adjudicado por uma central de compras? Não\n\n8 - TÉCNICAS\nO concurso destina-se à celebração de um acordo-quadro? Acordo-quadro, com reabertura de concurso\nModalidade: Com várias entidades\nPrazo de vigência: \nValor estimado: Não\nÉ utilizado um leilão eletrónico? Não\nÉ adotada uma fase de negociação? Não\nSistema de Aquisição Dinâmico: Inexistência de sistema de aquisição dinâmico\n\n9 - LOCAL DA EXECUÇÃO DO CONTRATO\nLOCAL DA EXECUÇÃO DO CONTRATO (PROCEDIMENTO)\nPaís: Portugal\nNUT III: PTZZZ\nLocalidade: PORTUGAL\nDistrito: Todos\nConcelho: Todos\nFreguesia: Todas\n\n10 - PRAZO DE EXECUÇÃO DO CONTRATO\nPrazo de execução do contrato: 12 MESES\nPrevisão de renovações: Não\n\n11 - FUNDOS EU\nTêm fundos EU? Não\n\n12 - DOCUMENTOS DE HABILITAÇÃO\nHabilitação para o exercício da atividade profissional: Não\n\n13 - CONDIÇÕES DE APRESENTAÇÃO\nPlataforma eletrónica utilizada pela entidade adjudicante: VORTAL\nURL para Apresentação: https://community.vortal.biz/public/\nAdmissibilidade da apresentação de propostas variantes: Não autorizado\nPrazo para apresentação das propostas: 19-11-2025 18:00\nPrazo durante o qual os concorrentes são obrigados a manter as respetivas propostas: 180 dias a contar do termo do prazo para a apresentação das propostas\nApresentação de Catálogo Eletrónico: Permitido\nIndicação de Subcontratação na Proposta: Inexistência de indicação de subcontratação\n\n14 - PRESTAÇÃO DE CAUÇÃO\nPrestação de caução: Não\n\n15 - FORNECIMENTO DAS PEÇAS DO CONCURSO, APRESENTAÇÃO DE PEDIDOS DE PARTICIPAÇÃO E APRESENTAÇÃO DAS PROPOSTAS\nLink para acesso às peças do concurso (URL): https://community.vortal.biz/Public/public-tender-documents/djdINlR4NmNSbU4xeVFSWXd2akFJaXYvUlRUSHZKQ2p3b3Rvay9mZG1kZ05rUzhDTjdCMUpmTGJvSVFNUHVnVkd3aHZ2eXB3UVN0cHVKQlYwYk9zd0E9PTk5Q2wy\n\n20 - OUTROS REQUISITOS\nInformação sobre contratos reservados. Aplica-se a contratos reservados (54º-A)? Não\n\n21 - CRITÉRIO DE ADJUDICAÇÃO\nMultifator: Não\nMonofator:\nNome: Preço\n\n24 - CONDIÇÕES DO CONTRATO\nFaturação Eletrónica: Permitido\nObrigação de Subcontratação:\nCódigo da Obrigação de Subcontratação: Não é aplicável nenhuma obrigação de subcontratação.\n\n25 - COMPRA PÚBLICA ESTRATÉGICA\nCompra Pública Estratégica: Inexistência de contratação pública estratégica\n\n26 - INFORMAÇÕES ADICIONAIS\nContrato adequado para PME: Sim\nCobertura ACP (Acordo dos Contratos Públicos da Organização Mundial do Comércio): Não\n\n27 - IDENTIFICAÇÃO E CONTACTOS DO ÓRGÃO DE RECURSOS ADMINISTRATIVOS\nDesignação: SPMS, EPE.\nEndereço: Av. República, n.º 61\nCódigo postal: 1050-189\nLocalidade: Lisboa\nTelefone: +351 211545600\nFax: +351 211545649\nEndereço eletrónico: catalogo@spms.min-saude.pt\n\n28 - IDENTIFICAÇÃO DO(S) AUTOR(ES) DE ANÚNCIO\nNome: Sofia Martins\nCargo: Técnica Superior \n419679684",
    "nipc": "509540716",
    "distrito": "Lisboa",
    "concelho": "Lisboa",
    "freguesia": "Todas",
    "site": "www.spms.min-saude.pt/",
    "email": "contratacao@spms.min-saude.pt",
    "designacao_contrato": "Medicamentos do grupo do sangue",
    "descricao": "Acordo-quadro de medicamentos do grupo do sangue",
    "preco_base": null,
    "prazo_execucao": "12 MESES",
    "prazo_apresentacao_propostas": "19-11-2025 18:00",
    "fundos_eu": "Não",
    "plataforma_eletronica": "VORTAL",
    "url_procedimento": "https://community.vortal.biz/public/",
    "autor_nome": "Sofia Martins",
    "autor_cargo": "Técnica Superior"
  },
  {
    "numero_procedimento": "N/A",
    "entidade": "Instituto Português de Oncologia de Lisboa Francisco Gentil, E. P. E.",
    "link": "https://diariodarepublica.pt/dr/detalhe/contrato-publico/27813-941785817",
    "detalhes_completos": "1 - IDENTIFICAÇÃO E CONTACTOS DA ENTIDADE ADJUDICANTE\nDesignação da entidade adjudicante: Instituto Português de Oncologia de Lisboa Francisco Gentil, E. P. E.\nNIPC: 506361616\nEndereço: Rua Profº Lima Basto\nCódigo postal: 1099-023\nLocalidade: Lisboa\nPaís: Portugal\nNUT III: PT170\nDistrito: Lisboa\nConcelho: Lisboa\nFreguesia: Todas\nTelefone: 217229800\nFax: 217229880\nEndereço da Entidade (URL): www.ipolisboa.min-saude.pt/\nEndereço Eletrónico: ipofg@ipolisboa.min-saude.pt\neDelivery Gateway (URL): https://community.vortal.biz/public/\nFunção da Organização: Adquirente\nNorma jurídica da Entidade Adjudicante: Organismo de direito público\nÁrea de atividade da Autoridade Adjudicante: Saúde\n\n2 - JORNAL OFICIAL DA UNIÃO EUROPEIA\nO procedimento a que este anúncio diz respeito também é publicitado no Jornal Oficial da União Europeia? Não\n\n3 - AVISO\nModelo de Anúncio: Concurso público\nData de Envio do Anúncio: 23-10-2025\n\n5 - PROCESSO\nTipo de Procedimento: Concurso público\nPreço base do procedimento: Sim\nValor do preço base do procedimento: 65.500,00 EUR\nProcedimento com lotes? Não\n\n6 - OBJETO DO CONTRATO\nNúmero de referência interna: PN/2882/2025\nDesignação do contrato: Aquisição de Sistema de Ecocardiografia \nDescrição: Aquisição de Sistema de Ecocardiografia \nTipo de Contrato Principal: Aquisição de Bens Móveis\nTipo de Contrato: Aquisição de Bens Móveis\nClassificação CPV (Vocabulário Comum para os Contratos Públicos)\nObjeto principal\nVocabulário Principal: 33100000\nPreço base s/IVA: 65.500,00 EUR\n\n7 - INDICAÇÕES ADICIONAIS\nO contrato envolve aquisição conjunta (satisfação de várias entidades)? Não\nO contrato é adjudicado por uma central de compras? Não\n\n8 - TÉCNICAS\nO concurso destina-se à celebração de um acordo-quadro? Inexistência de acordo-quadro\nÉ utilizado um leilão eletrónico? Não\nÉ adotada uma fase de negociação? Não\nSistema de Aquisição Dinâmico: Inexistência de sistema de aquisição dinâmico\n\n9 - LOCAL DA EXECUÇÃO DO CONTRATO\nLOCAL DA EXECUÇÃO DO CONTRATO (PROCEDIMENTO)\nPaís: Portugal\nNUT III: PT170\nLocalidade: Lisboa\nDistrito: Lisboa\nConcelho: Lisboa\nFreguesia: Freguesia de São Domingos de Benfica\n\n10 - PRAZO DE EXECUÇÃO DO CONTRATO\nPrazo de execução do contrato: 30 DIAS\nPrevisão de renovações: Não\n\n11 - FUNDOS EU\nTêm fundos EU? Sim\n\n12 - DOCUMENTOS DE HABILITAÇÃO\nHabilitação para o exercício da atividade profissional: Não\n\n13 - CONDIÇÕES DE APRESENTAÇÃO\nPlataforma eletrónica utilizada pela entidade adjudicante: VORTAL\nURL para Apresentação: https://community.vortal.biz/public/\nAdmissibilidade da apresentação de propostas variantes: Não autorizado\nPrazo para apresentação das propostas: 31-10-2025 17:59\nPrazo durante o qual os concorrentes são obrigados a manter as respetivas propostas: 90 dias a contar do termo do prazo para a apresentação das propostas\nIndicação de Subcontratação na Proposta: Inexistência de indicação de subcontratação\n\n14 - PRESTAÇÃO DE CAUÇÃO\nPrestação de caução: Não\n\n15 - FORNECIMENTO DAS PEÇAS DO CONCURSO, APRESENTAÇÃO DE PEDIDOS DE PARTICIPAÇÃO E APRESENTAÇÃO DAS PROPOSTAS\nLink para acesso às peças do concurso (URL): https://community.vortal.biz/Public/public-tender-documents/eFNyM1FUVnh3bjBnY1ZTc1hGNDlBUHlDNnVpTFV3V2lnM1lSYWxzMjVEVUo2ZTJ4MFoyekxLZVdDRktBNm50ZGt1dVl3UE5qRzU1aXRzNEZybGF6dWc9PWZkVyFo\n\n20 - OUTROS REQUISITOS\nInformação sobre contratos reservados. Aplica-se a contratos reservados (54º-A)? Não\n\n21 - CRITÉRIO DE ADJUDICAÇÃO\nMultifator: Não\nMonofator:\nNome: Preço\n\n24 - CONDIÇÕES DO CONTRATO\nFaturação Eletrónica: Permitido\nObrigação de Subcontratação:\nCódigo da Obrigação de Subcontratação: Não é aplicável nenhuma obrigação de subcontratação.\n\n25 - COMPRA PÚBLICA ESTRATÉGICA\nCompra Pública Estratégica: Inexistência de contratação pública estratégica\n\n26 - INFORMAÇÕES ADICIONAIS\nContrato adequado para PME: Sim\nCobertura ACP (Acordo dos Contratos Públicos da Organização Mundial do Comércio): Não\n\n27 - IDENTIFICAÇÃO E CONTACTOS DO ÓRGÃO DE RECURSOS ADMINISTRATIVOS\nDesignação: Conselho de Administração\nEndereço: Rua Prof. Lima Basto\nCódigo postal: 1099-023\nLocalidade: Lisboa\nTelefone: +351 217229800\nFax: +351 217229880\nEndereço eletrónico: ipofg@ipolisboa.min-saude.pt\n\n28 - IDENTIFICAÇÃO DO(S) AUTOR(ES) DE ANÚNCIO\nNome: Ricardo Costa\nCargo: Técnico Superior\n419688415",
    "nipc": "506361616",
    "distrito": "Lisboa",
    "concelho": "Lisboa",
    "freguesia": "Todas",
    "site": "www.ipolisboa.min-saude.pt/",
    "email": "ipofg@ipolisboa.min-saude.pt",
    "designacao_contrato": "Aquisição de Sistema de Ecocardiografia",
    "descricao": "Aquisição de Sistema de Ecocardiografia",
    "preco_base": "65.500,00 EUR",
    "prazo_execucao": "30 DIAS",
    "prazo_apresentacao_propostas": "31-10-2025 17:59",
    "fundos_eu": "Sim",
    "plataforma_eletronica": "VORTAL",
    "url_procedimento": "https://community.vortal.biz/public/",
    "autor_nome": "Ricardo Costa",
    "autor_cargo": "Técnico Superior"
  },
  {
    "numero_procedimento": "N/A",
    "entidade": "Instituto Politécnico de Portalegre",
    "link": "https://diariodarepublica.pt/dr/detalhe/contrato-publico/27809-941845779",
    "detalhes_completos": "1 - IDENTIFICAÇÃO E CONTACTOS DA ENTIDADE ADJUDICANTE\nDesignação da entidade adjudicante: Instituto Politécnico de Portalegre\nNIPC: 600028348\nServiço/Órgão/Pessoa de contacto: Serviços de Aquisições e Aprovisionamento do IPP\nEndereço: Praça do Município, n.º 11\nCódigo postal: 7300-110\nLocalidade: Portalegre\nPaís: Portugal\nNUT III: PT186\nDistrito: Portalegre\nConcelho: Portalegre\nFreguesia: União das Freguesias da Sé e São Lourenço\nTelefone: 245301500\nFax: 245330353\nEndereço da Entidade (URL): http://www.ipportalegre.pt/\nEndereço Eletrónico: geral@ipportalegre.pt\neDelivery Gateway (URL): https://www.acingov.pt\nFunção da Organização: Adquirente\nNorma jurídica da Entidade Adjudicante: Organismo de direito público\nÁrea de atividade da Autoridade Adjudicante: Serviços públicos das administrações públicas\n\n2 - JORNAL OFICIAL DA UNIÃO EUROPEIA\nO procedimento a que este anúncio diz respeito também é publicitado no Jornal Oficial da União Europeia? Não\n\n3 - AVISO\nModelo de Anúncio: Concurso público\nData de Envio do Anúncio: 22-10-2025\n\n5 - PROCESSO\nTipo de Procedimento: Concurso público\nPreço base do procedimento: Sim\nValor do preço base do procedimento: 211.850,00 EUR\nProcedimento com lotes? Sim\nNº Máx. de Lotes Autorizado: 2\nNúmero máximo de lotes que podem ser adjudicados a um concorrente: 2\n\n6 - OBJETO DO CONTRATO\nNúmero de referência interna: CPúblico/AEPV_476/IPP/2025\nDesignação do contrato: Aquisição de Equipamentos no âmbito do Projeto VALORIZA, constituído por 2 lotes\nDescrição: Aquisição de Equipamentos no âmbito do Projeto VALORIZA, constituído por 2 lotes\nTipo de Contrato Principal: Aquisição de Bens Móveis\nTipo de Contrato: Aquisição de Bens Móveis\nClassificação CPV (Vocabulário Comum para os Contratos Públicos)\nObjeto principal\nVocabulário Principal: 39300000\nPreço base s/IVA: 126.500,00 EUR\nObjeto Complementar\nVocabulário Principal: 38432000\nPreço base s/IVA: 85.350,00 EUR\nLotes: \nNº: LOT-0001\nDescrição do Lote: Gaseificador Térmico\nPreço base s/IVA: 126.500,00 EUR\nClassificação CPV (Vocabulário Comum para os Contratos Públicos)\nObjeto principal\nVocabulário Principal: 39300000\nNº: LOT-0002\nDescrição do Lote: Microscópio Eletrónico de Varrimento de Bancada (SEM de bancada)\nPreço base s/IVA: 85.350,00 EUR\nClassificação CPV (Vocabulário Comum para os Contratos Públicos)\nObjeto principal\nVocabulário Principal: 38432000\n\n7 - INDICAÇÕES ADICIONAIS\nO contrato envolve aquisição conjunta (satisfação de várias entidades)? Não\nO contrato é adjudicado por uma central de compras? Não\n\n8 - TÉCNICAS\nO concurso destina-se à celebração de um acordo-quadro? Inexistência de acordo-quadro\nÉ utilizado um leilão eletrónico? Não\nÉ adotada uma fase de negociação? Não\nSistema de Aquisição Dinâmico: Inexistência de sistema de aquisição dinâmico\n\n9 - LOCAL DA EXECUÇÃO DO CONTRATO\nLOCAL DA EXECUÇÃO DO CONTRATO (PROCEDIMENTO)\nPaís: Portugal\nNUT III: PT186\nLocalidade: União das Freguesias da Sé e São Lourenço\nDistrito: Portalegre\nConcelho: Portalegre\nFreguesia: União das Freguesias da Sé e São Lourenço\nLOCAL DA EXECUÇÃO DO CONTRATO (LOTE)\nIdentificador do Lote: LOT-0001; LOT-0002\nPaís: Portugal\nNUT III: PT186\nLocalidade: União das Freguesias da Sé e São Lourenço\nDistrito: Portalegre\nConcelho: Portalegre\nFreguesia: União das Freguesias da Sé e São Lourenço\n\n10 - PRAZO DE EXECUÇÃO DO CONTRATO\nIdentificador do Lote: LOT-0001; LOT-0002\nPrazo de execução do contrato: 190 DIAS\nPrevisão de renovações: Não\n\n11 - FUNDOS EU\nIdentificador do Lote: LOT-0001; LOT-0002\nTêm fundos EU? Sim\n\n12 - DOCUMENTOS DE HABILITAÇÃO\nHabilitação para o exercício da atividade profissional: Não\n\n13 - CONDIÇÕES DE APRESENTAÇÃO\nPlataforma eletrónica utilizada pela entidade adjudicante: ACIN\nURL para Apresentação: https://www.acingov.pt\nAdmissibilidade da apresentação de propostas variantes: Não autorizado\nPrazo para apresentação das propostas: 31-10-2025 23:59\nPrazo durante o qual os concorrentes são obrigados a manter as respetivas propostas: 120 dias a contar do termo do prazo para a apresentação das propostas\nIndicação de Subcontratação na Proposta: Inexistência de indicação de subcontratação\n\n14 - PRESTAÇÃO DE CAUÇÃO\nPrestação de caução: Não\n\n15 - FORNECIMENTO DAS PEÇAS DO CONCURSO, APRESENTAÇÃO DE PEDIDOS DE PARTICIPAÇÃO E APRESENTAÇÃO DAS PROPOSTAS\nLink para acesso às peças do concurso (URL): https://www.acingov.pt/acingovprod/2/zonaPublica/zona_publica_c/donwloadProcedurePiece/OTg2OTU0\n\n20 - OUTROS REQUISITOS\nIdentificador do Lote: LOT-0001; LOT-0002\nInformação sobre contratos reservados. Aplica-se a contratos reservados (54º-A)? Não\n\n21 - CRITÉRIO DE ADJUDICAÇÃO\nO Critério de adjudicação é diferenciado por lote? Não\nMultifator: Não\nMonofator:\nNome: Preço\n\n24 - CONDIÇÕES DO CONTRATO\nIdentificador do Lote: LOT-0001; LOT-0002\nFaturação Eletrónica: Permitido\nObrigação de Subcontratação:\nCódigo da Obrigação de Subcontratação: Não é aplicável nenhuma obrigação de subcontratação.\n\n25 - COMPRA PÚBLICA ESTRATÉGICA\nCompra Pública Estratégica: Inexistência de contratação pública estratégica\n\n26 - INFORMAÇÕES ADICIONAIS\nIdentificador do Lote: LOT-0001; LOT-0002\nContrato adequado para PME: Sim\nCobertura ACP (Acordo dos Contratos Públicos da Organização Mundial do Comércio): Não\n\n27 - IDENTIFICAÇÃO E CONTACTOS DO ÓRGÃO DE RECURSOS ADMINISTRATIVOS\nDesignação: Presidente\nEndereço: Praça do Município, n.º 11\nCódigo postal: 7300-110\nLocalidade: Portalegre\nTelefone: 245301500\nFax: 245330353\nEndereço eletrónico: geral@ipportalegre.pt\nPrazo de interposição do recurso: 10 dias\n\n28 - IDENTIFICAÇÃO DO(S) AUTOR(ES) DE ANÚNCIO\nNome: Luis Carlos Loures\nCargo: Presidente\n419689339",
    "nipc": "600028348",
    "distrito": "Portalegre",
    "concelho": "Portalegre",
    "freguesia": "União das Freguesias da Sé e São Lourenço",
    "site": "http://www.ipportalegre.pt/",
    "email": "geral@ipportalegre.pt",
    "designacao_contrato": "Aquisição de Equipamentos no âmbito do Projeto VALORIZA, constituído por 2 lotes",
    "descricao": "Aquisição de Equipamentos no âmbito do Projeto VALORIZA, constituído por 2 lotes",
    "preco_base": "126.500,00 EUR",
    "prazo_execucao": "190 DIAS",
    "prazo_apresentacao_propostas": "31-10-2025 23:59",
    "fundos_eu": "Sim",
    "plataforma_eletronica": "ACIN",
    "url_procedimento": "https://www.acingov.pt",
    "autor_nome": "Luis Carlos Loures",
    "autor_cargo": "Presidente"
  },
  {
    "numero_procedimento": "N/A",
    "entidade": "Águas do Norte, S. A.",
    "link": "https://diariodarepublica.pt/dr/detalhe/contrato-publico/27810-941845780",
    "detalhes_completos": "1 - IDENTIFICAÇÃO E CONTACTOS DA ENTIDADE ADJUDICANTE\nDesignação da entidade adjudicante: Águas do Norte, S. A.\nNIPC: 513606084\nServiço/Órgão/Pessoa de contacto: Compras e Logística\nEndereço: Rua Dom Pedro de Castro, n.º 1A\nCódigo postal: 5000-669\nLocalidade: Vila Real\nPaís: Portugal\nNUT III: PT11D\nDistrito: Vila Real\nConcelho: Vila Real\nFreguesia: Freguesia de Vila Real\nTelefone: 259309370\nFax: 259309371\nEndereço da Entidade (URL): www.adnorte.pt\nEndereço Eletrónico: geral.adnorte@adp.pt\neDelivery Gateway (URL): https://www.acingov.pt\nFunção da Organização: Adquirente\nNorma jurídica da Entidade Adjudicante: Organismo de direito público\nÁrea de atividade da Autoridade Adjudicante: Serviços públicos das administrações públicas\n\n2 - JORNAL OFICIAL DA UNIÃO EUROPEIA\nO procedimento a que este anúncio diz respeito também é publicitado no Jornal Oficial da União Europeia? Sim\n\n3 - AVISO\nModelo de Anúncio: Concurso público\nData de Envio do Anúncio: 21-10-2025\n\n5 - PROCESSO\nTipo de Procedimento: Concurso público\nPreço base do procedimento: Sim\nValor do preço base do procedimento: 4.050.000,00 EUR\nProcedimento com lotes? Não\n\n6 - OBJETO DO CONTRATO\nNúmero de referência interna: PRC_0358/2025_DEX\nDesignação do contrato: PRC_0358/2025_DEX - Fornecimento de Floculantes para as Estações de Tratamento da Águas do Norte, S.A.\nDescrição: PRC_0358/2025_DEX - Fornecimento de Floculantes para as Estações de Tratamento da Águas do Norte, S.A.\nOpções: Não\nTipo de Contrato Principal: Aquisição de Bens Móveis\nTipo de Contrato: Aquisição de Bens Móveis\nClassificação CPV (Vocabulário Comum para os Contratos Públicos)\nObjeto principal\nVocabulário Principal: 24958200\nPreço base s/IVA: 4.050.000,00 EUR\n\n7 - INDICAÇÕES ADICIONAIS\nO contrato envolve aquisição conjunta (satisfação de várias entidades)? Não\nO contrato é adjudicado por uma central de compras? Não\n\n8 - TÉCNICAS\nO concurso destina-se à celebração de um acordo-quadro? Inexistência de acordo-quadro\nÉ utilizado um leilão eletrónico? Não\nÉ adotada uma fase de negociação? Não\nSistema de Aquisição Dinâmico: Inexistência de sistema de aquisição dinâmico\n\n9 - LOCAL DA EXECUÇÃO DO CONTRATO\nLOCAL DA EXECUÇÃO DO CONTRATO (PROCEDIMENTO)\nPaís: Portugal\nNUT III: PT112\nLocalidade: Todas\nDistrito: Braga\nConcelho: Esposende\nFreguesia: Todas\nPaís: Portugal\nNUT III: PT119\nLocalidade: União das Freguesias de Serzedo e Calvos\nDistrito: Braga\nConcelho: Guimarães\nFreguesia: União das Freguesias de Serzedo e Calvos\nPaís: Portugal\nNUT III: PT112\nLocalidade: União das Freguesias de Areias de Vilar e Encourados\nDistrito: Braga\nConcelho: Barcelos\nFreguesia: União das Freguesias de Areias de Vilar e Encourados\nPaís: Portugal\nNUT III: PT119\nLocalidade: Freguesia de Lordelo - Guimarães\nDistrito: Braga\nConcelho: Guimarães\nFreguesia: Freguesia de Lordelo - Guimarães\nPaís: Portugal\nNUT III: PT119\nLocalidade: Freguesia de Serzedelo - Guimarães\nDistrito: Braga\nConcelho: Guimarães\nFreguesia: Freguesia de Serzedelo - Guimarães\nPaís: Portugal\nNUT III: PT119\nLocalidade: Freguesia de Fradelos - Vila Nova de Famalicão\nDistrito: Braga\nConcelho: Vila Nova de Famalicão\nFreguesia: Freguesia de Fradelos - Vila Nova de Famalicão\nPaís: Portugal\nNUT III: PT11E\nLocalidade: Todas\nDistrito: Braganca\nConcelho: Bragança\nFreguesia: Todas\nPaís: Portugal\nNUT III: PT11D\nLocalidade: Todas\nDistrito: Braganca\nConcelho: Torre de Moncorvo\nFreguesia: Todas\nPaís: Portugal\nNUT III: PT11D\nLocalidade: Todas\nDistrito: Guarda\nConcelho: Vila Nova de Foz Coa\nFreguesia: Todas\nPaís: Portugal\nNUT III: PT11A\nLocalidade: Todas\nDistrito: Porto\nConcelho: Santo Tirso\nFreguesia: Todas\nPaís: Portugal\nNUT III: PT11A\nLocalidade: Todas\nDistrito: Porto\nConcelho: Santo Tirso\nFreguesia: Todas\nPaís: Portugal\nNUT III: PT111\nLocalidade: Todas\nDistrito: Viana do Castelo\nConcelho: Viana do Castelo\nFreguesia: Todas\nPaís: Portugal\nNUT III: PT111\nLocalidade: Todas\nDistrito: Viana do Castelo\nConcelho: Caminha\nFreguesia: Todas\nPaís: Portugal\nNUT III: PT11B\nLocalidade: Todas\nDistrito: Vila Real\nConcelho: Chaves\nFreguesia: Todas\nPaís: Portugal\nNUT III: PT11D\nLocalidade: Todas\nDistrito: Vila Real\nConcelho: Vila Real\nFreguesia: Todas\nPaís: Portugal\nNUT III: PT11B\nLocalidade: Todas\nDistrito: Vila Real\nConcelho: Ribeira de Pena\nFreguesia: Todas\nPaís: Portugal\nNUT III: PT11D\nLocalidade: Todas\nDistrito: Viseu\nConcelho: Lamego\nFreguesia: Todas\nPaís: Portugal\nNUT III: PT11C\nLocalidade: Todas\nDistrito: Viseu\nConcelho: Resende\nFreguesia: Todas\n\n10 - PRAZO DE EXECUÇÃO DO CONTRATO\nPrazo de execução do contrato: 3 ANOS\nPrevisão de renovações: Sim\nIndicar número máximo de renovações: 2\nPrazo de renovações diferente do prazo inicial: Não\n\n11 - FUNDOS EU\nTêm fundos EU? Não\n\n12 - DOCUMENTOS DE HABILITAÇÃO\nHabilitação para o exercício da atividade profissional: Não\n\n13 - CONDIÇÕES DE APRESENTAÇÃO\nPlataforma eletrónica utilizada pela entidade adjudicante: ACIN\nURL para Apresentação: https://www.acingov.pt\nAdmissibilidade da apresentação de propostas variantes: Não autorizado\nPrazo para apresentação das propostas: 20-11-2025 17:00\nPrazo durante o qual os concorrentes são obrigados a manter as respetivas propostas: 120 dias a contar do termo do prazo para a apresentação das propostas\nApresentação de Catálogo Eletrónico: Não autorizado\nIndicação de Subcontratação na Proposta: Inexistência de indicação de subcontratação\n\n14 - PRESTAÇÃO DE CAUÇÃO\nPrestação de caução: Sim\nPercentagem: 2%\nDescrição da Garantia Exigida: O valor da caução é de 2.00% do preço contratual.\n\n15 - FORNECIMENTO DAS PEÇAS DO CONCURSO, APRESENTAÇÃO DE PEDIDOS DE PARTICIPAÇÃO E APRESENTAÇÃO DAS PROPOSTAS\nLink para acesso às peças do concurso (URL): https://www.acingov.pt/acingovprod/2/zonaPublica/zona_publica_c/donwloadProcedurePiece/OTg4NjAy\n\n20 - OUTROS REQUISITOS\nInformação sobre contratos reservados. Aplica-se a contratos reservados (54º-A)? Não\n\n21 - CRITÉRIO DE ADJUDICAÇÃO\nMultifator: Não\nMonofator:\nNome: Preço\n\n24 - CONDIÇÕES DO CONTRATO\nFaturação Eletrónica: Permitido\nObrigação de Subcontratação:\nCódigo da Obrigação de Subcontratação: Não é aplicável nenhuma obrigação de subcontratação.\n\n25 - COMPRA PÚBLICA ESTRATÉGICA\nCompra Pública Estratégica: Inexistência de contratação pública estratégica\n\n26 - INFORMAÇÕES ADICIONAIS\nContrato adequado para PME: Sim\nCobertura ACP (Acordo dos Contratos Públicos da Organização Mundial do Comércio): Não\n\n27 - IDENTIFICAÇÃO E CONTACTOS DO ÓRGÃO DE RECURSOS ADMINISTRATIVOS\nDesignação: Conselho de Administração da Águas do Norte, S.A.\nEndereço: Rua Dom Pedro de Castro, n.º 1A\nCódigo postal: 5000-669\nLocalidade: Vila Real\nTelefone: 259309370\nFax: 259309371\nEndereço eletrónico: geral.adnorte@adp.pt\n\n28 - IDENTIFICAÇÃO DO(S) AUTOR(ES) DE ANÚNCIO\nNome: Alice Maria Carvalho Alves\nCargo: Técnica Superior de Compras e Logística\n419675666",
    "nipc": "513606084",
    "distrito": "Vila Real",
    "concelho": "Vila Real",
    "freguesia": "Freguesia de Vila Real",
    "site": "www.adnorte.pt",
    "email": "geral.adnorte@adp.pt",
    "designacao_contrato": "PRC_0358/2025_DEX - Fornecimento de Floculantes para as Estações de Tratamento da Águas do Norte, S.A.",
    "descricao": "PRC_0358/2025_DEX - Fornecimento de Floculantes para as Estações de Tratamento da Águas do Norte, S.A.",
    "preco_base": "4.050.000,00 EUR",
    "prazo_execucao": "3 ANOS",
    "prazo_apresentacao_propostas": "20-11-2025 17:00",
    "fundos_eu": "Não",
    "plataforma_eletronica": "ACIN",
    "url_procedimento": "https://www.acingov.pt",
    "autor_nome": "Alice Maria Carvalho Alves",
    "autor_cargo": "Técnica Superior de Compras e Logística"
  },
  {
    "numero_procedimento": "N/A",
    "entidade": "Águas do Norte, S. A.",
    "link": "https://diariodarepublica.pt/dr/detalhe/contrato-publico/27811-941845781",
    "detalhes_completos": "1 - IDENTIFICAÇÃO E CONTACTOS DA ENTIDADE ADJUDICANTE\nDesignação da entidade adjudicante: Águas do Norte, S. A.\nNIPC: 513606084\nEndereço: Rua Dom Pedro de Castro, N.º 1A\nCódigo postal: 5000-669\nLocalidade: Vila Real\nPaís: Portugal\nNUT III: PT11D\nDistrito: Vila Real\nConcelho: Vila Real\nFreguesia: Freguesia de Vila Real\nTelefone: 259309370\nFax: 259309371\nEndereço da Entidade (URL): www.adnorte.pt\nEndereço Eletrónico: geral.adnorte@adp.pt\neDelivery Gateway (URL): https://www.acingov.pt\nFunção da Organização: Adquirente\nNorma jurídica da Entidade Adjudicante: Organismo de direito público\nÁrea de atividade da Autoridade Adjudicante: Serviços públicos das administrações públicas\n\n2 - JORNAL OFICIAL DA UNIÃO EUROPEIA\nO procedimento a que este anúncio diz respeito também é publicitado no Jornal Oficial da União Europeia? Sim\n\n3 - AVISO\nModelo de Anúncio: Concurso público\nData de Envio do Anúncio: 21-10-2025\n\n5 - PROCESSO\nTipo de Procedimento: Concurso público\nPreço base do procedimento: Sim\nValor do preço base do procedimento: 26.000.000,00 EUR\nProcedimento com lotes? Não\n\n6 - OBJETO DO CONTRATO\nNúmero de referência interna: PRC_0288/2025_GAE-AR1114\nDesignação do contrato: PRC_0288/2025_GAE-AR1114 - Empreitada de Conceção-Construção de Unidade Centralizada de Tratamento de Lamas da ETAR de Serzedelo (Guimarães)\nDescrição: PRC_0288/2025_GAE-AR1114 - Empreitada de Conceção-Construção de Unidade Centralizada de Tratamento de Lamas da ETAR de Serzedelo (Guimarães)\nOpções: Não\nTipo de Contrato Principal: Empreitada de Obras Públicas\nTipo de Contrato: Empreitada de Obras Públicas\nClassificação CPV (Vocabulário Comum para os Contratos Públicos)\nObjeto principal\nVocabulário Principal: 45232422\nPreço base s/IVA: 20.000.000,00 EUR\nObjeto Complementar\nVocabulário Principal: 45251220\nPreço base s/IVA: 6.000.000,00 EUR\n\n7 - INDICAÇÕES ADICIONAIS\nO contrato envolve aquisição conjunta (satisfação de várias entidades)? Não\nO contrato é adjudicado por uma central de compras? Não\n\n8 - TÉCNICAS\nO concurso destina-se à celebração de um acordo-quadro? Inexistência de acordo-quadro\nÉ utilizado um leilão eletrónico? Não\nÉ adotada uma fase de negociação? Não\nSistema de Aquisição Dinâmico: Inexistência de sistema de aquisição dinâmico\n\n9 - LOCAL DA EXECUÇÃO DO CONTRATO\nLOCAL DA EXECUÇÃO DO CONTRATO (PROCEDIMENTO)\nPaís: Portugal\nNUT III: PT119\nLocalidade: Freguesia de Serzedelo - Guimarães\nDistrito: Braga\nConcelho: Guimarães\nFreguesia: Freguesia de Serzedelo - Guimarães\n\n10 - PRAZO DE EXECUÇÃO DO CONTRATO\nPrazo de execução do contrato: 1092 DIAS\nPrevisão de renovações: Não\n\n11 - FUNDOS EU\nTêm fundos EU? Não\n\n12 - DOCUMENTOS DE HABILITAÇÃO\nHabilitação para o exercício da atividade profissional: Sim\nTipo: Alvará\nDescrição: Documentos de Habilitação\n\n13 - CONDIÇÕES DE APRESENTAÇÃO\nPlataforma eletrónica utilizada pela entidade adjudicante: ACIN\nURL para Apresentação: https://www.acingov.pt\nAdmissibilidade da apresentação de propostas variantes: Não autorizado\nPrazo para apresentação das propostas: 13-01-2026 18:00\nPrazo durante o qual os concorrentes são obrigados a manter as respetivas propostas: 90 dias a contar do termo do prazo para a apresentação das propostas\nApresentação de Catálogo Eletrónico: Não autorizado\nIndicação de Subcontratação na Proposta: Inexistência de indicação de subcontratação\n\n14 - PRESTAÇÃO DE CAUÇÃO\nPrestação de caução: Sim\nPercentagem: 5%\nDescrição da Garantia Exigida: O valor da caução é de 5.00% do preço contratual.\n\n15 - FORNECIMENTO DAS PEÇAS DO CONCURSO, APRESENTAÇÃO DE PEDIDOS DE PARTICIPAÇÃO E APRESENTAÇÃO DAS PROPOSTAS\nLink para acesso às peças do concurso (URL): https://www.acingov.pt/acingovprod/2/zonaPublica/zona_publica_c/donwloadProcedurePiece/OTgyNTky\n\n20 - OUTROS REQUISITOS\nInformação sobre contratos reservados. Aplica-se a contratos reservados (54º-A)? Não\n\n21 - CRITÉRIO DE ADJUDICAÇÃO\nMultifator: Sim\nFator: \nNome: Preço\nPonderação: 40%\nSubfatores: Não\nFator: \nNome: Outros\nOutro Nome: Valia Técnica\nPonderação: 60%\nSubfatores: Não\n\n24 - CONDIÇÕES DO CONTRATO\nFaturação Eletrónica: Permitido\nObrigação de Subcontratação:\nCódigo da Obrigação de Subcontratação: Não é aplicável nenhuma obrigação de subcontratação.\n\n25 - COMPRA PÚBLICA ESTRATÉGICA\nCompra Pública Estratégica: Inexistência de contratação pública estratégica\n\n26 - INFORMAÇÕES ADICIONAIS\nContrato adequado para PME: Não\nCobertura ACP (Acordo dos Contratos Públicos da Organização Mundial do Comércio): Não\n\n27 - IDENTIFICAÇÃO E CONTACTOS DO ÓRGÃO DE RECURSOS ADMINISTRATIVOS\nDesignação: Conselho de Administração da Águas do Norte, S.A.\nEndereço: Rua Dom Pedro de Castro, N.º 1A\nCódigo postal: 5000-669\nLocalidade: Vila Real\nTelefone: 259309370\nFax: 259309371\nEndereço eletrónico: geral.adnorte@adp.pt\nPrazo de interposição do recurso: 5 dias\n\n28 - IDENTIFICAÇÃO DO(S) AUTOR(ES) DE ANÚNCIO\nNome: Alexandra Bezelga\nCargo: Técnica Superior de Gestão de Ativos e Engenharia\n419676135",
    "nipc": "513606084",
    "distrito": "Vila Real",
    "concelho": "Vila Real",
    "freguesia": "Freguesia de Vila Real",
    "site": "www.adnorte.pt",
    "email": "geral.adnorte@adp.pt",
    "designacao_contrato": "PRC_0288/2025_GAE-AR1114 - Empreitada de Conceção-Construção de Unidade Centralizada de Tratamento de Lamas da ETAR de Serzedelo (Guimarães)",
    "descricao": "PRC_0288/2025_GAE-AR1114 - Empreitada de Conceção-Construção de Unidade Centralizada de Tratamento de Lamas da ETAR de Serzedelo (Guimarães)",
    "preco_base": "20.000.000,00 EUR",
    "prazo_execucao": "1092 DIAS",
    "prazo_apresentacao_propostas": "13-01-2026 18:00",
    "fundos_eu": "Não",
    "plataforma_eletronica": "ACIN",
    "url_procedimento": "https://www.acingov.pt",
    "autor_nome": "Alexandra Bezelga",
    "autor_cargo": "Técnica Superior de Gestão de Ativos e Engenharia"
  },
  {
    "numero_procedimento": "N/A",
    "entidade": "Município de Oeiras",
    "link": "https://diariodarepublica.pt/dr/detalhe/contrato-publico/27812-941845782",
    "detalhes_completos": "1 - IDENTIFICAÇÃO E CONTACTOS DA ENTIDADE ADJUDICANTE\nDesignação da entidade adjudicante: Município de Oeiras\nNIPC: 500745943\nEndereço: Largo Marquês de Pombal\nCódigo postal: 2784-501\nLocalidade: Lisboa\nPaís: Portugal\nNUT III: PT170\nDistrito: Lisboa\nConcelho: Oeiras\nFreguesia: União das Freguesias de Oeiras e São Julião da Barra, Paço de Arcos e Caxias\nTelefone: 214408300\nFax: 214408712\nEndereço da Entidade (URL): www.cm-oeiras.pt\nEndereço Eletrónico: divisao.contratacaopublica@cm-oeiras.pt\neDelivery Gateway (URL): https://community.vortal.biz/public/\nFunção da Organização: Adquirente\nNorma jurídica da Entidade Adjudicante: Autoridade local\nÁrea de atividade da Autoridade Adjudicante: Serviços públicos das administrações públicas\n\n2 - JORNAL OFICIAL DA UNIÃO EUROPEIA\nO procedimento a que este anúncio diz respeito também é publicitado no Jornal Oficial da União Europeia? Não\n\n3 - AVISO\nModelo de Anúncio: Concurso público\nData de Envio do Anúncio: 23-10-2025\n\n5 - PROCESSO\nTipo de Procedimento: Concurso público\nPreço base do procedimento: Sim\nValor do preço base do procedimento: 200.000,00 EUR\nProcedimento com lotes? Não\n\n6 - OBJETO DO CONTRATO\nNúmero de referência interna: 300.10.005/2025/1525/UPGO\nDesignação do contrato: Reparações e substituições de bancos de jardim, em regime de fornecimento  continuo\nDescrição: Reparações e substituições de bancos de jardim, em regime de fornecimento \ncontinuo\nTipo de Contrato Principal: Aquisição de Serviços\nTipo de Contrato: Aquisição de Serviços\nClassificação CPV (Vocabulário Comum para os Contratos Públicos)\nObjeto principal\nVocabulário Principal: 50800000\nPreço base s/IVA: 200.000,00 EUR\n\n7 - INDICAÇÕES ADICIONAIS\nO contrato envolve aquisição conjunta (satisfação de várias entidades)? Não\nO contrato é adjudicado por uma central de compras? Não\n\n8 - TÉCNICAS\nO concurso destina-se à celebração de um acordo-quadro? Inexistência de acordo-quadro\nÉ utilizado um leilão eletrónico? Não\nÉ adotada uma fase de negociação? Não\nSistema de Aquisição Dinâmico: Inexistência de sistema de aquisição dinâmico\n\n9 - LOCAL DA EXECUÇÃO DO CONTRATO\nLOCAL DA EXECUÇÃO DO CONTRATO (PROCEDIMENTO)\nPaís: Portugal\nNUT III: PT170\nLocalidade: Lisboa\nDistrito: Lisboa\nConcelho: Oeiras\nFreguesia: União das Freguesias de Oeiras e São Julião da Barra, Paço de Arcos e Caxias\n\n10 - PRAZO DE EXECUÇÃO DO CONTRATO\nPrazo de execução do contrato: 365 DIAS\nPrevisão de renovações: Sim\nIndicar número máximo de renovações: 1\nPrazo de renovações diferente do prazo inicial: Não\n\n11 - FUNDOS EU\nTêm fundos EU? Não\n\n12 - DOCUMENTOS DE HABILITAÇÃO\nHabilitação para o exercício da atividade profissional: Não\n\n13 - CONDIÇÕES DE APRESENTAÇÃO\nPlataforma eletrónica utilizada pela entidade adjudicante: VORTAL\nURL para Apresentação: https://community.vortal.biz/public/\nAdmissibilidade da apresentação de propostas variantes: Não autorizado\nPrazo para apresentação das propostas: 24-11-2025 17:00\nPrazo durante o qual os concorrentes são obrigados a manter as respetivas propostas: 66 dias a contar do termo do prazo para a apresentação das propostas\nIndicação de Subcontratação na Proposta: Inexistência de indicação de subcontratação\n\n14 - PRESTAÇÃO DE CAUÇÃO\nPrestação de caução: Sim\nPercentagem: 5%\nDescrição da Garantia Exigida: Ver Programa de Procedimento \n\n15 - FORNECIMENTO DAS PEÇAS DO CONCURSO, APRESENTAÇÃO DE PEDIDOS DE PARTICIPAÇÃO E APRESENTAÇÃO DAS PROPOSTAS\nLink para acesso às peças do concurso (URL): https://community.vortal.biz/Public/public-tender-documents/c1ZPc0VWTE1mUU5UaEJDTGNtYVZoMTFmdDFqNlpsRXNGUXFpKytBNW9uUUgwam9NQXRvQ09mcHN5VS94U3RVRExFcGpac3dCRkdCTkoySXJPbGlON2c9PTIpVkBP\n\n20 - OUTROS REQUISITOS\nInformação sobre contratos reservados. Aplica-se a contratos reservados (54º-A)? Não\n\n21 - CRITÉRIO DE ADJUDICAÇÃO\nMultifator: Não\nMonofator:\nNome: Outros\nOutro nome: Preço\n\n24 - CONDIÇÕES DO CONTRATO\nFaturação Eletrónica: Permitido\nObrigação de Subcontratação:\nCódigo da Obrigação de Subcontratação: Não é aplicável nenhuma obrigação de subcontratação.\n\n25 - COMPRA PÚBLICA ESTRATÉGICA\nCompra Pública Estratégica: Inexistência de contratação pública estratégica\n\n26 - INFORMAÇÕES ADICIONAIS\nContrato adequado para PME: Sim\nCobertura ACP (Acordo dos Contratos Públicos da Organização Mundial do Comércio): Não\n\n27 - IDENTIFICAÇÃO E CONTACTOS DO ÓRGÃO DE RECURSOS ADMINISTRATIVOS\nDesignação: Presidente CMO\nEndereço: LARGO MARQUÊS POMBAL\nCódigo postal: 2784-501\nLocalidade: Oeiras\nTelefone: +351 214483000\nFax: +351 214483000\nEndereço eletrónico: upgo@oeiras.pt\n\n28 - IDENTIFICAÇÃO DO(S) AUTOR(ES) DE ANÚNCIO\nNome: Isaltino Morais\nCargo: Prsidente\n419688942",
    "nipc": "500745943",
    "distrito": "Lisboa",
    "concelho": "Oeiras",
    "freguesia": "União das Freguesias de Oeiras e São Julião da Barra, Paço de Arcos e Caxias",
    "site": "www.cm-oeiras.pt",
    "email": "divisao.contratacaopublica@cm-oeiras.pt",
    "designacao_contrato": "Reparações e substituições de bancos de jardim, em regime de fornecimento continuo",
    "descricao": "Reparações e substituições de bancos de jardim, em regime de fornecimento",
    "preco_base": "200.000,00 EUR",
    "prazo_execucao": "365 DIAS",
    "prazo_apresentacao_propostas": "24-11-2025 17:00",
    "fundos_eu": "Não",
    "plataforma_eletronica": "VORTAL",
    "url_procedimento": "https://community.vortal.biz/public/",
    "autor_nome": "Isaltino Morais",
    "autor_cargo": "Prsidente"
  }
]