[
  {
    "numero_procedimento": "N/A",
    "entidade": "AnÃºncio de procedimento  n.Âº 25092/2025  -  DiÃ¡rio da RepÃºblica n.Âº 184/2025, SÃ©rie II de 2025-09-24",
    "link": "https://diariodarepublica.pt/dr/detalhe/contrato-publico/25092-936209734"
  },
  {
    "numero_procedimento": "N/A",
    "entidade": "AnÃºncio de procedimento  n.Âº 25094/2025  -  DiÃ¡rio da RepÃºblica n.Âº 184/2025, SÃ©rie II de 2025-09-24",
    "link": "https://diariodarepublica.pt/dr/detalhe/contrato-publico/25094-936209735"
  },
  {
    "numero_procedimento": "N/A",
    "entidade": "AnÃºncio de procedimento  n.Âº 25095/2025  -  DiÃ¡rio da RepÃºblica n.Âº 184/2025, SÃ©rie II de 2025-09-24",
    "link": "https://diariodarepublica.pt/dr/detalhe/contrato-publico/25095-936209736"
  },
  {
    "numero_procedimento": "N/A",
    "entidade": "SIMAS Oeiras e Amadora",
    "link": "https://diariodarepublica.pt/dr/detalhe/contrato-publico/25096-936209737",
    "detalhes_completos": "1 - IDENTIFICAÇÃO E CONTACTOS DA ENTIDADE ADJUDICANTE\nDesignação da entidade adjudicante: SIMAS Oeiras e Amadora\nNIPC: 680015019\nEndereço: Avenida Dr. Francisco Sá Carneiro nº 19, Urbanização Moinho das Antas\nCódigo postal: 2784-541\nLocalidade: Lisboa\nPaís: Portugal\nNUT III: PT170\nDistrito: Lisboa\nConcelho: Oeiras\nFreguesia: Todas\nTelefone: 214408300\nFax: 214414342\nEndereço da Entidade (URL): www.simas-oeiras-amadora.pt\nEndereço Eletrónico: geral@simas-oeiras-amadora.pt\neDelivery Gateway (URL): https://community.vortal.biz/public/\nFunção da Organização: Adquirente\nNorma jurídica da Entidade Adjudicante: Autoridade da administração central\nÁrea de atividade da Autoridade Adjudicante: Serviços públicos das administrações públicas\n\n2 - JORNAL OFICIAL DA UNIÃO EUROPEIA\nO procedimento a que este anúncio diz respeito também é publicitado no Jornal Oficial da União Europeia? Não\n\n3 - AVISO\nModelo de Anúncio: Concurso público\nData de Envio do Anúncio: 23-09-2025\n\n5 - PROCESSO\nTipo de Procedimento: Concurso público\nPreço base do procedimento: Sim\nValor do preço base do procedimento: 8.062,50 EUR\nProcedimento com lotes? Não\n\n6 - OBJETO DO CONTRATO\nNúmero de referência interna: CP 94/2025/404\nDesignação do contrato: Concurso Público, destinado à prestação de serviços no âmbito do contrato de manutenção preventiva das portas automáticas dos edifícios dos SIMAS de Oeiras e Amadora.\nDescrição: Concurso Público, destinado à prestação de serviços no âmbito do contrato de manutenção preventiva das portas automáticas dos edifícios dos SIMAS de Oeiras e Amadora.\nTipo de Contrato Principal: Aquisição de Serviços\nTipo de Contrato: Aquisição de Serviços\nClassificação CPV (Vocabulário Comum para os Contratos Públicos)\nObjeto principal\nVocabulário Principal: 50324200\nPreço base s/IVA: 8.062,50 EUR\n\n7 - INDICAÇÕES ADICIONAIS\nO contrato envolve aquisição conjunta (satisfação de várias entidades)? Não\nO contrato é adjudicado por uma central de compras? Não\n\n8 - TÉCNICAS\nO concurso destina-se à celebração de um acordo-quadro? Inexistência de acordo-quadro\nÉ utilizado um leilão eletrónico? Não\nÉ adotada uma fase de negociação? Não\nSistema de Aquisição Dinâmico: Inexistência de sistema de aquisição dinâmico\n\n9 - LOCAL DA EXECUÇÃO DO CONTRATO\nLOCAL DA EXECUÇÃO DO CONTRATO (PROCEDIMENTO)\nPaís: Portugal\nNUT III: PT170\nLocalidade: Lisboa\nDistrito: Lisboa\nConcelho: Oeiras\nFreguesia: União das Freguesias de Oeiras e São Julião da Barra, Paço de Arcos e Caxias\n\n10 - PRAZO DE EXECUÇÃO DO CONTRATO\nPrazo de execução do contrato: 1095 DIAS\nPrevisão de renovações: Não\n\n11 - FUNDOS EU\nTêm fundos EU? Não\n\n12 - DOCUMENTOS DE HABILITAÇÃO\nHabilitação para o exercício da atividade profissional: Não\n\n13 - CONDIÇÕES DE APRESENTAÇÃO\nPlataforma eletrónica utilizada pela entidade adjudicante: VORTAL\nURL para Apresentação: https://community.vortal.biz/public/\nAdmissibilidade da apresentação de propostas variantes: Não autorizado\nPrazo para apresentação das propostas: 29-09-2025 23:59\nPrazo durante o qual os concorrentes são obrigados a manter as respetivas propostas: 180 dias a contar do termo do prazo para a apresentação das propostas\nIndicação de Subcontratação na Proposta: Inexistência de indicação de subcontratação\n\n14 - PRESTAÇÃO DE CAUÇÃO\nPrestação de caução: Não\n\n15 - FORNECIMENTO DAS PEÇAS DO CONCURSO, APRESENTAÇÃO DE PEDIDOS DE PARTICIPAÇÃO E APRESENTAÇÃO DAS PROPOSTAS\nLink para acesso às peças do concurso (URL): https://community.vortal.biz/Public/public-tender-documents/ZXovMXZ2WXg4Qng3SkVocnNnRnN6NTgvSHZQV2dDazlGUmhkSkhBUnhhYXQwV0MzdUhySStCWVFvUmhYY2dNZGkyZ3d4NVZyU040Y2J4ejlWVUdNSEE9PVIwXkoq\n\n20 - OUTROS REQUISITOS\nInformação sobre contratos reservados. Aplica-se a contratos reservados (54º-A)? Não\n\n21 - CRITÉRIO DE ADJUDICAÇÃO\nMultifator: Não\nMonofator:\nNome: Outros\nOutro nome: Preço\n\n24 - CONDIÇÕES DO CONTRATO\nFaturação Eletrónica: Permitido\nObrigação de Subcontratação:\nCódigo da Obrigação de Subcontratação: Não é aplicável nenhuma obrigação de subcontratação.\n\n25 - COMPRA PÚBLICA ESTRATÉGICA\nCompra Pública Estratégica: Inexistência de contratação pública estratégica\n\n26 - INFORMAÇÕES ADICIONAIS\nContrato adequado para PME: Sim\nCobertura ACP (Acordo dos Contratos Públicos da Organização Mundial do Comércio): Não\n\n27 - IDENTIFICAÇÃO E CONTACTOS DO ÓRGÃO DE RECURSOS ADMINISTRATIVOS\nDesignação: Juízo de Contratos Públicos do Tribunal Administrativo de Círculo de Lisboa\nEndereço: Avenida Dom João II, 1.08.01, edifício G, 6.º andar\nCódigo postal: 1900-097\nLocalidade: Lisboa\nTelefone: +351 218367100\nFax: +351 211545188\nEndereço eletrónico: lisboa.tacl@tribunais.org.pt\n\n28 - IDENTIFICAÇÃO DO(S) AUTOR(ES) DE ANÚNCIO\nNome: Joana Baptista\nCargo: Presidente do C.A.\n419568454",
    "nipc": "680015019",
    "distrito": "Lisboa",
    "concelho": "Oeiras",
    "freguesia": "Todas",
    "site": "www.simas-oeiras-amadora.pt",
    "email": "geral@simas-oeiras-amadora.pt",
    "designacao_contrato": "Concurso Público, destinado à prestação de serviços no âmbito do contrato de manutenção preventiva das portas automáticas dos edifícios dos SIMAS de Oeiras e Amadora.",
    "descricao": "Concurso Público, destinado à prestação de serviços no âmbito do contrato de manutenção preventiva das portas automáticas dos edifícios dos SIMAS de Oeiras e Amadora.",
    "preco_base": "8.062,50 EUR",
    "prazo_execucao": "1095 DIAS",
    "prazo_apresentacao_propostas": "29-09-2025 23:59",
    "fundos_eu": "Não",
    "plataforma_eletronica": "VORTAL",
    "url_procedimento": "https://community.vortal.biz/public/",
    "autor_nome": "Joana Baptista",
    "autor_cargo": "Presidente do C.A."
  },
  {
    "numero_procedimento": "N/A",
    "entidade": "AnÃºncio de procedimento  n.Âº 25099/2025  -  DiÃ¡rio da RepÃºblica n.Âº 184/2025, SÃ©rie II de 2025-09-24",
    "link": "https://diariodarepublica.pt/dr/detalhe/contrato-publico/25099-936209738"
  },
  {
    "numero_procedimento": "N/A",
    "entidade": "AnÃºncio de procedimento  n.Âº 25100/2025  -  DiÃ¡rio da RepÃºblica n.Âº 184/2025, SÃ©rie II de 2025-09-24",
    "link": "https://diariodarepublica.pt/dr/detalhe/contrato-publico/25100-936209739"
  },
  {
    "numero_procedimento": "N/A",
    "entidade": "AnÃºncio de procedimento  n.Âº 25101/2025  -  DiÃ¡rio da RepÃºblica n.Âº 184/2025, SÃ©rie II de 2025-09-24",
    "link": "https://diariodarepublica.pt/dr/detalhe/contrato-publico/25101-936209741"
  },
  {
    "numero_procedimento": "N/A",
    "entidade": "AnÃºncio de procedimento  n.Âº 25108/2025  -  DiÃ¡rio da RepÃºblica n.Âº 184/2025, SÃ©rie II de 2025-09-24",
    "link": "https://diariodarepublica.pt/dr/detalhe/contrato-publico/25108-936209742"
  },
  {
    "numero_procedimento": "N/A",
    "entidade": "AnÃºncio de procedimento  n.Âº 25093/2025  -  DiÃ¡rio da RepÃºblica n.Âº 184/2025, SÃ©rie II de 2025-09-24",
    "link": "https://diariodarepublica.pt/dr/detalhe/contrato-publico/25093-936380134"
  },
  {
    "numero_procedimento": "N/A",
    "entidade": "AnÃºncio de procedimento  n.Âº 25097/2025  -  DiÃ¡rio da RepÃºblica n.Âº 184/2025, SÃ©rie II de 2025-09-24",
    "link": "https://diariodarepublica.pt/dr/detalhe/contrato-publico/25097-936380136"
  },
  {
    "numero_procedimento": "N/A",
    "entidade": "AnÃºncio de procedimento  n.Âº 25098/2025  -  DiÃ¡rio da RepÃºblica n.Âº 184/2025, SÃ©rie II de 2025-09-24",
    "link": "https://diariodarepublica.pt/dr/detalhe/contrato-publico/25098-936380137"
  },
  {
    "numero_procedimento": "N/A",
    "entidade": "AnÃºncio de procedimento  n.Âº 25102/2025  -  DiÃ¡rio da RepÃºblica n.Âº 184/2025, SÃ©rie II de 2025-09-24",
    "link": "https://diariodarepublica.pt/dr/detalhe/contrato-publico/25102-936380158"
  },
  {
    "numero_procedimento": "N/A",
    "entidade": "AnÃºncio de procedimento  n.Âº 25103/2025  -  DiÃ¡rio da RepÃºblica n.Âº 184/2025, SÃ©rie II de 2025-09-24",
    "link": "https://diariodarepublica.pt/dr/detalhe/contrato-publico/25103-936380159"
  },
  {
    "numero_procedimento": "N/A",
    "entidade": "AnÃºncio de procedimento  n.Âº 25104/2025  -  DiÃ¡rio da RepÃºblica n.Âº 184/2025, SÃ©rie II de 2025-09-24",
    "link": "https://diariodarepublica.pt/dr/detalhe/contrato-publico/25104-936380160"
  },
  {
    "numero_procedimento": "N/A",
    "entidade": "AnÃºncio de procedimento  n.Âº 25105/2025  -  DiÃ¡rio da RepÃºblica n.Âº 184/2025, SÃ©rie II de 2025-09-24",
    "link": "https://diariodarepublica.pt/dr/detalhe/contrato-publico/25105-936380161"
  },
  {
    "numero_procedimento": "N/A",
    "entidade": "AnÃºncio de procedimento  n.Âº 25106/2025  -  DiÃ¡rio da RepÃºblica n.Âº 184/2025, SÃ©rie II de 2025-09-24",
    "link": "https://diariodarepublica.pt/dr/detalhe/contrato-publico/25106-936380162"
  },
  {
    "numero_procedimento": "N/A",
    "entidade": "AnÃºncio de procedimento  n.Âº 25107/2025  -  DiÃ¡rio da RepÃºblica n.Âº 184/2025, SÃ©rie II de 2025-09-24",
    "link": "https://diariodarepublica.pt/dr/detalhe/contrato-publico/25107-936380163"
  },
  {
    "numero_procedimento": "N/A",
    "entidade": "AnÃºncio de procedimento  n.Âº 25109/2025  -  DiÃ¡rio da RepÃºblica n.Âº 184/2025, SÃ©rie II de 2025-09-24",
    "link": "https://diariodarepublica.pt/dr/detalhe/contrato-publico/25109-936380164"
  },
  {
    "numero_procedimento": "N/A",
    "entidade": "AnÃºncio de procedimento  n.Âº 25110/2025  -  DiÃ¡rio da RepÃºblica n.Âº 184/2025, SÃ©rie II de 2025-09-24",
    "link": "https://diariodarepublica.pt/dr/detalhe/contrato-publico/25110-936380165"
  },
  {
    "numero_procedimento": "N/A",
    "entidade": "AnÃºncio de procedimento  n.Âº 25111/2025  -  DiÃ¡rio da RepÃºblica n.Âº 184/2025, SÃ©rie II de 2025-09-24",
    "link": "https://diariodarepublica.pt/dr/detalhe/contrato-publico/25111-936381454"
  }
]