[
  {
    "numero_procedimento": "N/A",
    "entidade": "Município de Olhão",
    "link": "https://diariodarepublica.pt/dr/detalhe/contrato-publico/22591-933044028",
    "detalhes_completos": "1 - IDENTIFICAÇÃO E CONTACTOS DA ENTIDADE ADJUDICANTE\nDesignação da entidade adjudicante: Município de Olhão\nNIPC: 506321894\nServiço/Órgão/Pessoa de contacto: Departamento de Desporto, Ambiente, Juventude e Empreendedorismo\nEndereço: Largo Sebastião Martins Mestre\nCódigo postal: 8700-349\nLocalidade: Olhão\nPaís: Portugal\nNUT III: PT150\nDistrito: Faro\nConcelho: Olhão\nFreguesia: Freguesia de Quelfes\nTelefone: 289700100\nEndereço da Entidade (URL): WWW.cm-olhao.pt\nEndereço Eletrónico: contratacaopublica@cm-olhao.pt\neDelivery Gateway (URL): https://www.acingov.pt\nFunção da Organização: Adquirente\nNorma jurídica da Entidade Adjudicante: Organismo de direito público\nÁrea de atividade da Autoridade Adjudicante: Serviços públicos das administrações públicas\n\n2 - JORNAL OFICIAL DA UNIÃO EUROPEIA\nO procedimento a que este anúncio diz respeito também é publicitado no Jornal Oficial da União Europeia? Não\n\n3 - AVISO\nModelo de Anúncio: Concurso público\nData de Envio do Anúncio: 22-08-2025\n\n5 - PROCESSO\nTipo de Procedimento: Concurso público\nPreço base do procedimento: Sim\nValor do preço base do procedimento: 490.000,00 EUR\nProcedimento com lotes? Não\n\n6 - OBJETO DO CONTRATO\nNúmero de referência interna: 25/OM/2025\nDesignação do contrato: 25/OM/2025- Obras de Execução de Cobertura do Pavilhão Municipal\nDescrição: 25/OM/2025- Obras de Execução de Cobertura do Pavilhão Municipal\nTipo de Contrato Principal: Empreitada de Obras Públicas\nTipo de Contrato: Empreitada de Obras Públicas\nClassificação CPV (Vocabulário Comum para os Contratos Públicos)\nObjeto principal\nVocabulário Principal: 45260000\nPreço base s/IVA: 490.000,00 EUR\n\n7 - INDICAÇÕES ADICIONAIS\nO contrato envolve aquisição conjunta (satisfação de várias entidades)? Não\nO contrato é adjudicado por uma central de compras? Não\n\n8 - TÉCNICAS\nO concurso destina-se à celebração de um acordo-quadro? Inexistência de acordo-quadro\nÉ utilizado um leilão eletrónico? Não\nÉ adotada uma fase de negociação? Não\nSistema de Aquisição Dinâmico: Inexistência de sistema de aquisição dinâmico\n\n9 - LOCAL DA EXECUÇÃO DO CONTRATO\nLOCAL DA EXECUÇÃO DO CONTRATO (PROCEDIMENTO)\nPaís: Portugal\nNUT III: PT150\nLocalidade: Freguesia de Quelfes\nDistrito: Faro\nConcelho: Olhão\nFreguesia: Freguesia de Quelfes\n\n10 - PRAZO DE EXECUÇÃO DO CONTRATO\nPrazo de execução do contrato: 90 DIAS\nPrevisão de renovações: Não\n\n11 - FUNDOS EU\nTêm fundos EU? Não\n\n12 - DOCUMENTOS DE HABILITAÇÃO\nHabilitação para o exercício da atividade profissional: Sim\nTipo: Alvará\nDescrição: Alvará:  1.ª subcategoria da 2.ª categoria\n        11.ª subcategoria da 2.ª categoria\n        1.ª e 2.ª subcategoria da 5.ª categoria\n\n13 - CONDIÇÕES DE APRESENTAÇÃO\nPlataforma eletrónica utilizada pela entidade adjudicante: ACIN\nURL para Apresentação: https://www.acingov.pt\nAdmissibilidade da apresentação de propostas variantes: Não autorizado\nPrazo para apresentação das propostas: 27-08-2025 23:59\nPrazo durante o qual os concorrentes são obrigados a manter as respetivas propostas: 66 dias a contar do termo do prazo para a apresentação das propostas\nIndicação de Subcontratação na Proposta: Inexistência de indicação de subcontratação\n\n14 - PRESTAÇÃO DE CAUÇÃO\nPrestação de caução: Sim\nPercentagem: 5%\nDescrição da Garantia Exigida: O valor da caução é de 5.00% do preço contratual.\n\n15 - FORNECIMENTO DAS PEÇAS DO CONCURSO, APRESENTAÇÃO DE PEDIDOS DE PARTICIPAÇÃO E APRESENTAÇÃO DAS PROPOSTAS\nLink para acesso às peças do concurso (URL): https://www.acingov.pt/acingovprod/2/zonaPublica/zona_publica_c/donwloadProcedurePiece/OTM1NDY4\n\n20 - OUTROS REQUISITOS\nInformação sobre contratos reservados. Aplica-se a contratos reservados (54º-A)? Não\n\n21 - CRITÉRIO DE ADJUDICAÇÃO\nMultifator: Não\nMonofator:\nNome: Outros\nOutro nome: Fator Preço\n\n24 - CONDIÇÕES DO CONTRATO\nFaturação Eletrónica: Necessário\nObrigação de Subcontratação:\nCódigo da Obrigação de Subcontratação: Não é aplicável nenhuma obrigação de subcontratação.\n\n25 - COMPRA PÚBLICA ESTRATÉGICA\nCompra Pública Estratégica: Inexistência de contratação pública estratégica\n\n26 - INFORMAÇÕES ADICIONAIS\nContrato adequado para PME: Sim\nCobertura ACP (Acordo dos Contratos Públicos da Organização Mundial do Comércio): Não\n\n27 - IDENTIFICAÇÃO E CONTACTOS DO ÓRGÃO DE RECURSOS ADMINISTRATIVOS\nDesignação: Tribunal Administrativo e Fiscal de Loulé\nEndereço: Rua Dr.ª Laura Ayres\nCódigo postal: 8100-851\nLocalidade: Loulé\nTelefone: 289400390\nFax: 213506010\nEndereço eletrónico: loule.taf@tribunais.org.pt\nPrazo de interposição do recurso: 10 dias\n\n28 - IDENTIFICAÇÃO DO(S) AUTOR(ES) DE ANÚNCIO\nNome: Antonio Miguel Ventura Pina\nCargo: Presidente\n419455823",
    "nipc": "506321894",
    "distrito": "Faro",
    "concelho": "Olhão",
    "freguesia": "Freguesia de Quelfes",
    "site": "WWW.cm-olhao.pt",
    "email": "contratacaopublica@cm-olhao.pt",
    "designacao_contrato": "25/OM/2025- Obras de Execução de Cobertura do Pavilhão Municipal",
    "descricao": "25/OM/2025- Obras de Execução de Cobertura do Pavilhão Municipal",
    "preco_base": "490.000,00 EUR",
    "prazo_execucao": "90 DIAS",
    "prazo_apresentacao_propostas": "27-08-2025 23:59",
    "fundos_eu": "Não",
    "plataforma_eletronica": "ACIN",
    "url_procedimento": "https://www.acingov.pt",
    "autor_nome": "Antonio Miguel Ventura Pina",
    "autor_cargo": "Presidente"
  },
  {
    "numero_procedimento": "N/A",
    "entidade": "GEBALIS - Gestão do Arrendamento da Habitação Municipal de Lisboa, E.M., S.A.",
    "link": "https://diariodarepublica.pt/dr/detalhe/contrato-publico/22596-933044029",
    "detalhes_completos": "Alteração do Anúncio de procedimento n.º 21023/2025, de 2025-08-05, com o ID 419396272\n\n1 - IDENTIFICAÇÃO E CONTACTOS DA ENTIDADE ADJUDICANTE\nDesignação da entidade adjudicante: GEBALIS - Gestão do Arrendamento da Habitação Municipal de Lisboa, E.M., S.A.\nNIPC: 503541567\nServiço/Órgão/Pessoa de contacto: Joana Pereira\nEndereço: Rua Laura Alves, n.º 12, 7º Piso\nCódigo postal: 1050-138\nLocalidade: Lisboa\nPaís: Portugal\nNUT III: PT170\nDistrito: Lisboa\nConcelho: Lisboa\nFreguesia: Freguesia de Avenidas Novas\nTelefone: 217511000\nFax: 217511000\nEndereço da Entidade (URL): www.gebalis.pt\nEndereço Eletrónico: contratacao.publica@gebalis.pt\nFunção da Organização: Adquirente\nNorma jurídica da Entidade Adjudicante: Empresa pública, controlada por uma autoridade local\nÁrea de atividade da Autoridade Adjudicante: Habitação e equipamentos coletivos\n\n2 - JORNAL OFICIAL DA UNIÃO EUROPEIA\nO procedimento a que este anúncio diz respeito também é publicitado no Jornal Oficial da União Europeia? Não\n\n3 - AVISO\nModelo de Anúncio: Concurso público\nData de Envio do Anúncio: 22-08-2025\n\n5 - PROCESSO\nTipo de Procedimento: Concurso público\nPreço base do procedimento: Sim\nValor do preço base do procedimento: 4.547.285,81 EUR\nProcedimento com lotes? Não\n\n6 - OBJETO DO CONTRATO\nNúmero de referência interna: Empreitada 55/Gebalis/2025 \nDesignação do contrato: Empreitada 55/GEBALIS/2025 - Bairro do Condado ¿ Obras de reabilitação e conservação de edifícios\nDescrição: Empreitada 55/GEBALIS/2025 - Bairro do Condado ¿ Obras de reabilitação e conservação de edifícios\nTipo de Contrato Principal: Empreitada de Obras Públicas\nTipo de Contrato: Empreitada de Obras Públicas\nClassificação CPV (Vocabulário Comum para os Contratos Públicos)\nObjeto principal\nVocabulário Principal: 45453100\nPreço base s/IVA: 4.547.285,81 EUR\n\n7 - INDICAÇÕES ADICIONAIS\nO contrato envolve aquisição conjunta (satisfação de várias entidades)? Não\nO contrato é adjudicado por uma central de compras? Não\n\n8 - TÉCNICAS\nO concurso destina-se à celebração de um acordo-quadro? Inexistência de acordo-quadro\nÉ utilizado um leilão eletrónico? Não\nÉ adotada uma fase de negociação? Não\nSistema de Aquisição Dinâmico: Inexistência de sistema de aquisição dinâmico\n\n9 - LOCAL DA EXECUÇÃO DO CONTRATO\nLOCAL DA EXECUÇÃO DO CONTRATO (PROCEDIMENTO)\nPaís: Portugal\nNUT III: PT170\nLocalidade: Lisboa\nDistrito: Lisboa\nConcelho: Lisboa\nFreguesia: Freguesia de Marvila - Lisboa\n\n10 - PRAZO DE EXECUÇÃO DO CONTRATO\nPrazo de execução do contrato: 12 MESES\nPrevisão de renovações: Não\n\n11 - FUNDOS EU\nTêm fundos EU? Não\n\n12 - DOCUMENTOS DE HABILITAÇÃO\nHabilitação para o exercício da atividade profissional: Sim\nTipo: Alvará\nDescrição: Conforme Programa de Concurso\n\n13 - CONDIÇÕES DE APRESENTAÇÃO\nPlataforma eletrónica utilizada pela entidade adjudicante: ANOGOV\nURL para Apresentação: https://www.anogov.com/em-gebalis/faces/\nAdmissibilidade da apresentação de propostas variantes: Não autorizado\nPrazo para apresentação das propostas: 08-09-2025 23:59\nPrazo durante o qual os concorrentes são obrigados a manter as respetivas propostas: 180 dias a contar do termo do prazo para a apresentação das propostas\nApresentação de Catálogo Eletrónico: Permitido\nIndicação de Subcontratação na Proposta: Inexistência de indicação de subcontratação\n\n14 - PRESTAÇÃO DE CAUÇÃO\nPrestação de caução: Sim\nPercentagem: 5%\nDescrição da Garantia Exigida: Ponto 21 Programa Concurso\n\n15 - FORNECIMENTO DAS PEÇAS DO CONCURSO, APRESENTAÇÃO DE PEDIDOS DE PARTICIPAÇÃO E APRESENTAÇÃO DAS PROPOSTAS\nLink para acesso às peças do concurso (URL): https://www.anogov.com/em-gebalis/faces/app/acessoDocs.jsp?codigoAcesso=pg6mhT6wbJmXaNUD695A5zVXlrAirDRMbl4t1MnSQxVbFlqjp3\n\n20 - OUTROS REQUISITOS\nInformação sobre contratos reservados. Aplica-se a contratos reservados (54º-A)? Não\n\n21 - CRITÉRIO DE ADJUDICAÇÃO\nMultifator: Sim\nFator: \nNome: Preço\nPonderação: 60%\nSubfatores: Não\nFator: \nNome: Qualidade\nPonderação: 30%\nSubfatores: Não\nFator: \nNome: Outros\nOutro Nome: Prazo\nPonderação: 10%\nSubfatores: Não\n\n24 - CONDIÇÕES DO CONTRATO\nFaturação Eletrónica: Permitido\nObrigação de Subcontratação:\nCódigo da Obrigação de Subcontratação: Não é aplicável nenhuma obrigação de subcontratação.\n\n25 - COMPRA PÚBLICA ESTRATÉGICA\nCompra Pública Estratégica: Inexistência de contratação pública estratégica\n\n26 - INFORMAÇÕES ADICIONAIS\nContrato adequado para PME: Não\nCobertura ACP (Acordo dos Contratos Públicos da Organização Mundial do Comércio): Não\n\n27 - IDENTIFICAÇÃO E CONTACTOS DO ÓRGÃO DE RECURSOS ADMINISTRATIVOS\nDesignação: Conselho de Administração\nEndereço: Rua Laura Alves, 12, 7º\nCódigo postal: 1050-138\nLocalidade: Lisboa\nEndereço eletrónico: contratacao.publica@gebalis.pt\n\n28 - IDENTIFICAÇÃO DO(S) AUTOR(ES) DE ANÚNCIO\nNome: Miguel Silva Pereira\nCargo: Vogal Conselho de Administração\n\n29 - ALTERAÇÃO\nMotivo da Alteração: Informações atualizadas\nIdentificador da Versão do Anúncio a Alterar: 2d7be482-3def-4397-9b62-006610392e4b-01\nIdentificador das Secções Alteradas do Anúncio Anterior: Condições de Apresentação\nDescrição das Alterações: Prorrogação prazo apresentação propostas\nAlteração dos Documentos do Concurso: Não\n419460529",
    "nipc": "503541567",
    "distrito": "Lisboa",
    "concelho": "Lisboa",
    "freguesia": "Freguesia de Avenidas Novas",
    "site": "www.gebalis.pt",
    "email": "contratacao.publica@gebalis.pt",
    "designacao_contrato": "Empreitada 55/GEBALIS/2025 - Bairro do Condado ¿ Obras de reabilitação e conservação de edifícios",
    "descricao": "Empreitada 55/GEBALIS/2025 - Bairro do Condado ¿ Obras de reabilitação e conservação de edifícios",
    "preco_base": "4.547.285,81 EUR",
    "prazo_execucao": "12 MESES",
    "prazo_apresentacao_propostas": "08-09-2025 23:59",
    "fundos_eu": "Não",
    "plataforma_eletronica": "ANOGOV",
    "url_procedimento": "https://www.anogov.com/em-gebalis/faces/",
    "autor_nome": "Miguel Silva Pereira",
    "autor_cargo": "Vogal Conselho de Administração"
  },
  {
    "numero_procedimento": "N/A",
    "entidade": "AgdA - Águas Públicas do Alentejo, S. A.",
    "link": "https://diariodarepublica.pt/dr/detalhe/contrato-publico/22597-933044030",
    "detalhes_completos": "Alteração do Anúncio de procedimento n.º 22376/2025, de 2025-08-21, com o ID 419452672\n\n1 - IDENTIFICAÇÃO E CONTACTOS DA ENTIDADE ADJUDICANTE\nDesignação da entidade adjudicante: AgdA - Águas Públicas do Alentejo, S. A.\nNIPC: 509133843\nServiço/Órgão/Pessoa de contacto: Serviço de Compras e Logística\nEndereço: Rua Dr. Aresta Branco, nº.51\nCódigo postal: 7800-310\nLocalidade: Beja\nPaís: Portugal\nNUT III: PT184\nDistrito: Beja\nConcelho: Beja\nFreguesia: União das Freguesias de Beja (Salvador e Santa Maria da Feira)\nTelefone: 284101100\nFax: 284101199\nEndereço da Entidade (URL): https://www.agda.pt\nEndereço Eletrónico: geral.agda@adp.pt\neDelivery Gateway (URL): https://www.acingov.pt\nFunção da Organização: Adquirente\nNorma jurídica da Entidade Adjudicante: Organismo de direito público\nÁrea de atividade da Autoridade Adjudicante: Serviços públicos das administrações públicas\n\n2 - JORNAL OFICIAL DA UNIÃO EUROPEIA\nO procedimento a que este anúncio diz respeito também é publicitado no Jornal Oficial da União Europeia? Não\n\n3 - AVISO\nModelo de Anúncio: Concurso público\nData de Envio do Anúncio: 22-08-2025\n\n5 - PROCESSO\nTipo de Procedimento: Concurso público\nPreço base do procedimento: Sim\nValor do preço base do procedimento: 974.000,00 EUR\nProcedimento com lotes? Não\n\n6 - OBJETO DO CONTRATO\nNúmero de referência interna: 85_040_25_CP_EO\nDesignação do contrato: Empreitada de Execução da Reabilitação dos Reservatórios de Almograve e São Francisco da Serra\nDescrição: Reabilitação dos Reservatórios de Almograve e São Francisco da Serra\nTipo de Contrato Principal: Empreitada de Obras Públicas\nTipo de Contrato: Empreitada de Obras Públicas\nClassificação CPV (Vocabulário Comum para os Contratos Públicos)\nObjeto principal\nVocabulário Principal: 45453100\nPreço base s/IVA: 974.000,00 EUR\n\n7 - INDICAÇÕES ADICIONAIS\nO contrato envolve aquisição conjunta (satisfação de várias entidades)? Não\nO contrato é adjudicado por uma central de compras? Não\n\n8 - TÉCNICAS\nO concurso destina-se à celebração de um acordo-quadro? Inexistência de acordo-quadro\nÉ utilizado um leilão eletrónico? Não\nÉ adotada uma fase de negociação? Não\nSistema de Aquisição Dinâmico: Inexistência de sistema de aquisição dinâmico\n\n9 - LOCAL DA EXECUÇÃO DO CONTRATO\nLOCAL DA EXECUÇÃO DO CONTRATO (PROCEDIMENTO)\nPaís: Portugal\nNUT III: PT184\nLocalidade: Almograve\nDistrito: Beja\nConcelho: Odemira\nFreguesia: Freguesia de Longueira/Almograve\nPaís: Portugal\nNUT III: PT181\nLocalidade: São Francisco da Serra\nDistrito: Setúbal\nConcelho: Santiago do Cacém\nFreguesia: Freguesia de São Francisco da Serra\n\n10 - PRAZO DE EXECUÇÃO DO CONTRATO\nPrazo de execução do contrato: 210 DIAS\nPrevisão de renovações: Não\n\n11 - FUNDOS EU\nTêm fundos EU? Não\n\n12 - DOCUMENTOS DE HABILITAÇÃO\nHabilitação para o exercício da atividade profissional: Sim\nTipo: Alvará\nDescrição: 6ª subcategoria da 2ª categoria e da classe correspondente ao valor global da proposta;\n1ª, 2ª, 4ª, 5ª, e 7ªsubcategorias da 1ª categoria, da classe correspondente ao valor dos trabalhos especializados que lhe respeite, consoante a parte que a esses trabalhos cabe na proposta;\n1ª subcategoria da 4ª categoria, da classe correspondente ao valor dos trabalhos especializados que lhe respeite, consoante a parte que a esses trabalhos cabe na proposta.\n2ª, 5ª, 8ª, 9ª, 10ª, 11ª, e 12 ª subcategoria da 5ª categoria, da classe correspondente ao valor dos trabalhos especializados que lhe respeite, consoante a parte que a esses trabalhos cabe na proposta\n\n13 - CONDIÇÕES DE APRESENTAÇÃO\nPlataforma eletrónica utilizada pela entidade adjudicante: ACIN\nURL para Apresentação: https://www.acingov.pt\nAdmissibilidade da apresentação de propostas variantes: Não autorizado\nPrazo para apresentação das propostas: 19-09-2025 18:00\nPrazo durante o qual os concorrentes são obrigados a manter as respetivas propostas: 90 dias a contar do termo do prazo para a apresentação das propostas\nIndicação de Subcontratação na Proposta: Inexistência de indicação de subcontratação\n\n14 - PRESTAÇÃO DE CAUÇÃO\nPrestação de caução: Sim\nPercentagem: 5%\nDescrição da Garantia Exigida: O valor da caução é de 5.00% do preço contratual.\n\n15 - FORNECIMENTO DAS PEÇAS DO CONCURSO, APRESENTAÇÃO DE PEDIDOS DE PARTICIPAÇÃO E APRESENTAÇÃO DAS PROPOSTAS\nLink para acesso às peças do concurso (URL): https://www.acingov.pt/acingovprod/2/zonaPublica/zona_publica_c/donwloadProcedurePiece/OTMwMzcx\n\n20 - OUTROS REQUISITOS\nInformação sobre contratos reservados. Aplica-se a contratos reservados (54º-A)? Não\n\n21 - CRITÉRIO DE ADJUDICAÇÃO\nMultifator: Sim\nFator: \nNome: Outros\nOutro Nome: Preço, cfr. Artigo 15º do Programa do Procedimento\nPonderação: 50%\nSubfatores: Não\nFator: \nNome: Outros\nOutro Nome: Valia Técnica, cfr. Artigo 15º do Programa do Procedimento\nPonderação: 50%\nSubfatores: Sim\nSubfatores: \nNome: Metodologia de execução da obra\nPonderação : 50%; \nNome: Detalhe e consistência do Plano de Trabalhos - Plano de trabalhos\nPonderação : 20%; \nNome: Detalhe e consistência do Plano de Trabalhos - Plano de Meios\nPonderação : 10%; \nNome: Caracterização dos equipamentos e materiais\nPonderação : 20%; \n\n24 - CONDIÇÕES DO CONTRATO\nFaturação Eletrónica: Permitido\nObrigação de Subcontratação:\nCódigo da Obrigação de Subcontratação: Não é aplicável nenhuma obrigação de subcontratação.\n\n25 - COMPRA PÚBLICA ESTRATÉGICA\nCompra Pública Estratégica: Inexistência de contratação pública estratégica\n\n26 - INFORMAÇÕES ADICIONAIS\nContrato adequado para PME: Não\nCobertura ACP (Acordo dos Contratos Públicos da Organização Mundial do Comércio): Não\n\n27 - IDENTIFICAÇÃO E CONTACTOS DO ÓRGÃO DE RECURSOS ADMINISTRATIVOS\nDesignação: AgdA-Águas Públicas do Alentejo, S.A.\nEndereço: Rua Dr. Aresta Branco, nº.51\nCódigo postal: 7800-310\nLocalidade: Beja\nTelefone: 284101100\nFax: \nEndereço eletrónico: geral.agda@adp.pt\nPrazo de interposição do recurso: 10 dias\n\n28 - IDENTIFICAÇÃO DO(S) AUTOR(ES) DE ANÚNCIO\nNome: Maria de Fátima Costa\nCargo: Gestora do Procedimento\n\n29 - ALTERAÇÃO\nMotivo da Alteração: Informações atualizadas\nIdentificador da Versão do Anúncio a Alterar: 8d1817b6-a50e-48aa-9e53-d90b0e0af079-01\nIdentificador das Secções Alteradas do Anúncio Anterior: Documentos de habilitação; Critério de adjudicação\nDescrição das Alterações: Campo \"Critério de adjudicação\" e Campo 12. \" Documentos de habilitação\"\nAlteração dos Documentos do Concurso: Não\n419460772",
    "nipc": "509133843",
    "distrito": "Beja",
    "concelho": "Beja",
    "freguesia": "União das Freguesias de Beja (Salvador e Santa Maria da Feira)",
    "site": "https://www.agda.pt",
    "email": "geral.agda@adp.pt",
    "designacao_contrato": "Empreitada de Execução da Reabilitação dos Reservatórios de Almograve e São Francisco da Serra",
    "descricao": "Reabilitação dos Reservatórios de Almograve e São Francisco da Serra",
    "preco_base": "974.000,00 EUR",
    "prazo_execucao": "210 DIAS",
    "prazo_apresentacao_propostas": "19-09-2025 18:00",
    "fundos_eu": "Não",
    "plataforma_eletronica": "ACIN",
    "url_procedimento": "https://www.acingov.pt",
    "autor_nome": "Maria de Fátima Costa",
    "autor_cargo": "Gestora do Procedimento"
  },
  {
    "numero_procedimento": "N/A",
    "entidade": "Escola Secundária Antero de Quental",
    "link": "https://diariodarepublica.pt/dr/detalhe/contrato-publico/22598-933044031",
    "detalhes_completos": "1 - IDENTIFICAÇÃO E CONTACTOS DA ENTIDADE ADJUDICANTE\nDesignação da entidade adjudicante: Escola Secundária Antero de Quental\nNIPC: 672000962\nServiço/Órgão/Pessoa de contacto: Carlos Miguel de Carvalho Amaral\nEndereço: Largo Mártires da Pátria\nCódigo postal: 9504-520\nLocalidade: Ponta Delgada\nPaís: Portugal\nNUT III: PT200\nDistrito: Região Autónoma dos Açores\nConcelho: Ponta Delgada\nFreguesia: Freguesia de Ponta Delgada (São Sebastião)\nTelefone: 296205540\nFax: 296205544\nEndereço da Entidade (URL): www.esaq.pt\nEndereço Eletrónico: es.anteroquental@edu.azores.gov.pt\neDelivery Gateway (URL): https://www.acingov.pt\nFunção da Organização: Adquirente\nNorma jurídica da Entidade Adjudicante: Organismo de direito público\nÁrea de atividade da Autoridade Adjudicante: Educação\n\n2 - JORNAL OFICIAL DA UNIÃO EUROPEIA\nO procedimento a que este anúncio diz respeito também é publicitado no Jornal Oficial da União Europeia? Sim\n\n3 - AVISO\nModelo de Anúncio: Concurso público\nData de Envio do Anúncio: 20-08-2025\n\n5 - PROCESSO\nTipo de Procedimento: Concurso público\nPreço base do procedimento: Sim\nValor do preço base do procedimento: 566.361,08 EUR\nProcedimento com lotes? Sim\nNº Máx. de Lotes Autorizado: 6\nNúmero máximo de lotes que podem ser adjudicados a um concorrente: 6\n\n6 - OBJETO DO CONTRATO\nNúmero de referência interna: CPI/1/2025/AQ\nDesignação do contrato: CPI/1/2025/AQ - Aquisição de manuais escolares digitais para o ano letivo 2025/2026, para os 7º, 8º, 9º, 10º, 11º e 12º anos de escolaridade.\nDescrição: CPI/1/2025/AQ - Aquisição de manuais escolares digitais para o ano letivo 2025/2026, para os 7º, 8º, 9º, 10º, 11º e 12º anos de escolaridade.\nOpções: Não\nTipo de Contrato Principal: Aquisição de Bens Móveis\nTipo de Contrato: Aquisição de Bens Móveis; Aquisição de Serviços\nClassificação CPV (Vocabulário Comum para os Contratos Públicos)\nObjeto principal\nVocabulário Principal: 22112000\nPreço base s/IVA: 566.361,08 EUR\nLotes: \nNº: LOT-0001\nDescrição do Lote: Aquisição de manuais escolares digitais para os alunos do 7.º ano de escolaridade: 30 Packs e 111 Licenças\nPreço base s/IVA: 69.713,73 EUR\nClassificação CPV (Vocabulário Comum para os Contratos Públicos)\nObjeto principal\nVocabulário Principal: 22112000\nNº: LOT-0002\nDescrição do Lote: Aquisição de nmanuais escolares digitais para o 8º ano de escolaridade\nPreço base s/IVA: 79.190,65 EUR\nClassificação CPV (Vocabulário Comum para os Contratos Públicos)\nObjeto principal\nVocabulário Principal: 22112000\nNº: LOT-0003\nDescrição do Lote: Aquisição de manuais Escolares digitais para o 9º ano de escolaridade\nPreço base s/IVA: 54.617,92 EUR\nClassificação CPV (Vocabulário Comum para os Contratos Públicos)\nObjeto principal\nVocabulário Principal: 22112000\nNº: LOT-0004\nDescrição do Lote: Aquisição de manuais escolares digitais para o 10º ano de escolaridade\nPreço base s/IVA: 82.288,36 EUR\nClassificação CPV (Vocabulário Comum para os Contratos Públicos)\nObjeto principal\nVocabulário Principal: 22112000\nNº: LOT-0005\nDescrição do Lote: Aquisição de mauais escolares digitais para o 11º ano\nPreço base s/IVA: 142.696,70 EUR\nClassificação CPV (Vocabulário Comum para os Contratos Públicos)\nObjeto principal\nVocabulário Principal: 22112000\nNº: LOT-0006\nDescrição do Lote: Aquisição de manuais escolares digitais para o 12º ano\nPreço base s/IVA: 137.853,72 EUR\nClassificação CPV (Vocabulário Comum para os Contratos Públicos)\nObjeto principal\nVocabulário Principal: 22112000\n\n7 - INDICAÇÕES ADICIONAIS\nO contrato envolve aquisição conjunta (satisfação de várias entidades)? Não\nO contrato é adjudicado por uma central de compras? Não\n\n8 - TÉCNICAS\nO concurso destina-se à celebração de um acordo-quadro? Inexistência de acordo-quadro\nÉ utilizado um leilão eletrónico? Não\nÉ adotada uma fase de negociação? Não\nSistema de Aquisição Dinâmico: Inexistência de sistema de aquisição dinâmico\n\n9 - LOCAL DA EXECUÇÃO DO CONTRATO\nLOCAL DA EXECUÇÃO DO CONTRATO (PROCEDIMENTO)\nPaís: Portugal\nNUT III: PT200\nLocalidade: Freguesia de Ponta Delgada (São Sebastião)\nDistrito: Região Autónoma dos Açores\nConcelho: Ponta Delgada\nFreguesia: Freguesia de Ponta Delgada (São Sebastião)\nLOCAL DA EXECUÇÃO DO CONTRATO (LOTE)\nIdentificador do Lote: LOT-0001; LOT-0002; LOT-0003; LOT-0004; LOT-0005; LOT-0006\nPaís: Portugal\nNUT III: PT200\nLocalidade: Freguesia de Ponta Delgada (São Sebastião)\nDistrito: Região Autónoma dos Açores\nConcelho: Ponta Delgada\nFreguesia: Freguesia de Ponta Delgada (São Sebastião)\n\n10 - PRAZO DE EXECUÇÃO DO CONTRATO\nIdentificador do Lote: LOT-0001; LOT-0002; LOT-0003; LOT-0004; LOT-0005; LOT-0006\nPrazo de execução do contrato: 201 DIAS\nPrevisão de renovações: Não\n\n11 - FUNDOS EU\nIdentificador do Lote: LOT-0001; LOT-0002; LOT-0003; LOT-0004; LOT-0005; LOT-0006\nTêm fundos EU? Não\n\n12 - DOCUMENTOS DE HABILITAÇÃO\nHabilitação para o exercício da atividade profissional: Não\n\n13 - CONDIÇÕES DE APRESENTAÇÃO\nPlataforma eletrónica utilizada pela entidade adjudicante: ACIN\nURL para Apresentação: https://www.acingov.pt\nAdmissibilidade da apresentação de propostas variantes: Não autorizado\nPrazo para apresentação das propostas: 19-09-2025 23:59\nPrazo durante o qual os concorrentes são obrigados a manter as respetivas propostas: 120 dias a contar do termo do prazo para a apresentação das propostas\nApresentação de Catálogo Eletrónico: Permitido\nIndicação de Subcontratação na Proposta: Inexistência de indicação de subcontratação\n\n14 - PRESTAÇÃO DE CAUÇÃO\nPrestação de caução: Sim\nPercentagem: 2%\nDescrição da Garantia Exigida: O valor da caução é de 2.00% do preço contratual.\n\n15 - FORNECIMENTO DAS PEÇAS DO CONCURSO, APRESENTAÇÃO DE PEDIDOS DE PARTICIPAÇÃO E APRESENTAÇÃO DAS PROPOSTAS\nLink para acesso às peças do concurso (URL): https://www.acingov.pt/acingovprod/2/zonaPublica/zona_publica_c/donwloadProcedurePiece/OTMzODQz\n\n20 - OUTROS REQUISITOS\nIdentificador do Lote: LOT-0001; LOT-0002; LOT-0003; LOT-0004; LOT-0005; LOT-0006\nInformação sobre contratos reservados. Aplica-se a contratos reservados (54º-A)? Não\n\n21 - CRITÉRIO DE ADJUDICAÇÃO\nO Critério de adjudicação é diferenciado por lote? Não\nMultifator: Não\nMonofator:\nNome: Preço\n\n24 - CONDIÇÕES DO CONTRATO\nIdentificador do Lote: LOT-0001; LOT-0002; LOT-0003; LOT-0004; LOT-0005; LOT-0006\nFaturação Eletrónica: Permitido\nObrigação de Subcontratação:\nCódigo da Obrigação de Subcontratação: Não é aplicável nenhuma obrigação de subcontratação.\n\n25 - COMPRA PÚBLICA ESTRATÉGICA\nCompra Pública Estratégica: Inexistência de contratação pública estratégica\n\n26 - INFORMAÇÕES ADICIONAIS\nIdentificador do Lote: LOT-0001; LOT-0002; LOT-0003; LOT-0004; LOT-0005; LOT-0006\nContrato adequado para PME: Não\nCobertura ACP (Acordo dos Contratos Públicos da Organização Mundial do Comércio): Não\n\n27 - IDENTIFICAÇÃO E CONTACTOS DO ÓRGÃO DE RECURSOS ADMINISTRATIVOS\nDesignação: Secretaria de Educação, Cultura e Desporto\nEndereço: Paços da Junta Geral - Carreira dos Cavalos\nCódigo postal: 9700-167\nLocalidade: Angra do Heoismo\nTelefone: 295401100\nFax: \nEndereço eletrónico: drae.info@azores.gov.pt\nPrazo de interposição do recurso: 5 dias\n\n28 - IDENTIFICAÇÃO DO(S) AUTOR(ES) DE ANÚNCIO\nNome: Anésia Fátima da Costa Medeiros Benevides\nCargo: Coordenadora Técnica\n419453863",
    "nipc": "672000962",
    "distrito": "Região Autónoma dos Açores",
    "concelho": "Ponta Delgada",
    "freguesia": "Freguesia de Ponta Delgada (São Sebastião)",
    "site": "www.esaq.pt",
    "email": "es.anteroquental@edu.azores.gov.pt",
    "designacao_contrato": "CPI/1/2025/AQ - Aquisição de manuais escolares digitais para o ano letivo 2025/2026, para os 7º, 8º, 9º, 10º, 11º e 12º anos de escolaridade.",
    "descricao": "CPI/1/2025/AQ - Aquisição de manuais escolares digitais para o ano letivo 2025/2026, para os 7º, 8º, 9º, 10º, 11º e 12º anos de escolaridade.",
    "preco_base": "566.361,08 EUR",
    "prazo_execucao": "201 DIAS",
    "prazo_apresentacao_propostas": "19-09-2025 23:59",
    "fundos_eu": "Não",
    "plataforma_eletronica": "ACIN",
    "url_procedimento": "https://www.acingov.pt",
    "autor_nome": "Anésia Fátima da Costa Medeiros Benevides",
    "autor_cargo": "Coordenadora Técnica"
  },
  {
    "numero_procedimento": "N/A",
    "entidade": "PSP - Polícia de Segurança Pública",
    "link": "https://diariodarepublica.pt/dr/detalhe/contrato-publico/22599-933044032",
    "detalhes_completos": "1 - IDENTIFICAÇÃO E CONTACTOS DA ENTIDADE ADJUDICANTE\nDesignação da entidade adjudicante: PSP - Polícia de Segurança Pública\nNIPC: 600006662\nEndereço: Av. António Augusto de Aguiar, 20 8º\nCódigo postal: 1050-016\nLocalidade: Lisboa\nPaís: Portugal\nNUT III: PT170\nDistrito: Lisboa\nConcelho: Lisboa\nFreguesia: Freguesia de Avenidas Novas\nTelefone: 213588383\nEndereço da Entidade (URL): https://www.psp.pt/\nEndereço Eletrónico: dl@psp.pt\neDelivery Gateway (URL): https://community.vortal.biz/public/\nFunção da Organização: Adquirente\nNorma jurídica da Entidade Adjudicante: Organismo de direito público\nÁrea de atividade da Autoridade Adjudicante: Segurança e ordem pública\n\n2 - JORNAL OFICIAL DA UNIÃO EUROPEIA\nO procedimento a que este anúncio diz respeito também é publicitado no Jornal Oficial da União Europeia? Sim\n\n3 - AVISO\nModelo de Anúncio: Concurso público\nData de Envio do Anúncio: 20-08-2025\n\n5 - PROCESSO\nTipo de Procedimento: Concurso público\nPreço base do procedimento: Sim\nValor do preço base do procedimento: 1.485.604,75 EUR\nProcedimento com lotes? Sim\nNº Máx. de Lotes Autorizado: 3\nNúmero máximo de lotes que podem ser adjudicados a um concorrente: 3\n\n6 - OBJETO DO CONTRATO\nNúmero de referência interna: Concurso Público nº 35/DAC/2025\nDesignação do contrato: Aquisição de refeições confecionadas para as unidades aeroportuárias \nDescrição: Aquisição de refeições confecionadas para as unidades aeroportuárias \nOpções: Não\nTipo de Contrato Principal: Aquisição de Bens Móveis\nTipo de Contrato: Aquisição de Bens Móveis\nClassificação CPV (Vocabulário Comum para os Contratos Públicos)\nObjeto principal\nVocabulário Principal: 15100000\nPreço base s/IVA: 1.485.604,75 EUR\nLotes: \nNº: LOT-0001\nDescrição do Lote: Lote 1\nPreço base s/IVA: 573.477,05 EUR\nClassificação CPV (Vocabulário Comum para os Contratos Públicos)\nObjeto principal\nVocabulário Principal: 15100000\nNº: LOT-0002\nDescrição do Lote: Lote 2\nPreço base s/IVA: 711.366,75 EUR\nClassificação CPV (Vocabulário Comum para os Contratos Públicos)\nObjeto principal\nVocabulário Principal: 15100000\nNº: LOT-0003\nDescrição do Lote: Lote 3\nPreço base s/IVA: 200.760,95 EUR\nClassificação CPV (Vocabulário Comum para os Contratos Públicos)\nObjeto principal\nVocabulário Principal: 15100000\n\n7 - INDICAÇÕES ADICIONAIS\nO contrato envolve aquisição conjunta (satisfação de várias entidades)? Não\nO contrato é adjudicado por uma central de compras? Não\n\n8 - TÉCNICAS\nO concurso destina-se à celebração de um acordo-quadro? Inexistência de acordo-quadro\nÉ utilizado um leilão eletrónico? Não\nÉ adotada uma fase de negociação? Não\nSistema de Aquisição Dinâmico: Inexistência de sistema de aquisição dinâmico\n\n9 - LOCAL DA EXECUÇÃO DO CONTRATO\nLOCAL DA EXECUÇÃO DO CONTRATO (PROCEDIMENTO)\nPaís: Portugal\nNUT III: PT170\nLocalidade: Lisboa\nDistrito: Lisboa\nConcelho: Lisboa\nFreguesia: Freguesia de Avenidas Novas\nLOCAL DA EXECUÇÃO DO CONTRATO (LOTE)\nIdentificador do Lote: LOT-0001; LOT-0002; LOT-0003\nPaís: Portugal\nNUT III: PT170\nLocalidade: Lisboa\nDistrito: Lisboa\nConcelho: Lisboa\nFreguesia: Freguesia de Avenidas Novas\n\n10 - PRAZO DE EXECUÇÃO DO CONTRATO\nIdentificador do Lote: LOT-0001; LOT-0002; LOT-0003\nPrazo de execução do contrato: 365 DIAS\nPrevisão de renovações: Não\n\n11 - FUNDOS EU\nIdentificador do Lote: LOT-0001; LOT-0002; LOT-0003\nTêm fundos EU? Não\n\n12 - DOCUMENTOS DE HABILITAÇÃO\nHabilitação para o exercício da atividade profissional: Não\n\n13 - CONDIÇÕES DE APRESENTAÇÃO\nPlataforma eletrónica utilizada pela entidade adjudicante: VORTAL\nURL para Apresentação: https://community.vortal.biz/public/\nAdmissibilidade da apresentação de propostas variantes: Não autorizado\nPrazo para apresentação das propostas: 25-09-2025 18:00\nPrazo durante o qual os concorrentes são obrigados a manter as respetivas propostas: 180 dias a contar do termo do prazo para a apresentação das propostas\nApresentação de Catálogo Eletrónico: Permitido\nIndicação de Subcontratação na Proposta: Inexistência de indicação de subcontratação\n\n14 - PRESTAÇÃO DE CAUÇÃO\nPrestação de caução: Não\n\n15 - FORNECIMENTO DAS PEÇAS DO CONCURSO, APRESENTAÇÃO DE PEDIDOS DE PARTICIPAÇÃO E APRESENTAÇÃO DAS PROPOSTAS\nLink para acesso às peças do concurso (URL): https://community.vortal.biz/Public/public-tender-documents/dTNlOWgxRHVlTGpObk4yRnJ0a3piTzVsZERVd1ZISW1kanZaVXZmQUJwS0xQTVY1MThoZTdRNVVXcjhIZlZnOXlDSG1GUEFPTUVCRGJpTlZFZmJOb1E9PU1NJGtL\n\n20 - OUTROS REQUISITOS\nIdentificador do Lote: LOT-0001; LOT-0002; LOT-0003\nInformação sobre contratos reservados. Aplica-se a contratos reservados (54º-A)? Não\n\n21 - CRITÉRIO DE ADJUDICAÇÃO\nO Critério de adjudicação é diferenciado por lote? Não\nMultifator: Não\nMonofator:\nNome: Preço\n\n24 - CONDIÇÕES DO CONTRATO\nIdentificador do Lote: LOT-0001; LOT-0002; LOT-0003\nFaturação Eletrónica: Permitido\nObrigação de Subcontratação:\nCódigo da Obrigação de Subcontratação: Não é aplicável nenhuma obrigação de subcontratação.\n\n25 - COMPRA PÚBLICA ESTRATÉGICA\nCompra Pública Estratégica: Redução dos impactos ambientais\nDescrição do Processo de Adjudicação Estratégico: Conforme as peças do procedimento\nCritérios de contratos Públicos Ecológicos: Critérios de contratação pública ecológica nacional\nCategorias da estratégia nacional: Outros\nOutra categoria (Descrição): Critérios ecológicos de embalamento e destruição de resíduos\nDiretiva Veículos Não Poluentes: Não\nCritério de Acessibilidade: Os critérios de acessibilidade para as pessoas com deficiência não estão incluídos porque o contrato não se destina a pessoas singulares\n\n26 - INFORMAÇÕES ADICIONAIS\nIdentificador do Lote: LOT-0001; LOT-0002; LOT-0003\nContrato adequado para PME: Sim\nCobertura ACP (Acordo dos Contratos Públicos da Organização Mundial do Comércio): Não\n\n27 - IDENTIFICAÇÃO E CONTACTOS DO ÓRGÃO DE RECURSOS ADMINISTRATIVOS\nDesignação: Ministério da Administração Interna\nEndereço: Av. António Augusto de Aguiar, 20 8º\nCódigo postal: 1050-016\nLocalidade: Lisboa\nTelefone: +351 213409000\nFax: +351 213409000\nEndereço eletrónico: gab.sec.geral@sg.mai.gov.pt\n\n28 - IDENTIFICAÇÃO DO(S) AUTOR(ES) DE ANÚNCIO\nNome: Licinio Cardoso Vaz\nCargo: Chefe de Divisão\n419452518",
    "nipc": "600006662",
    "distrito": "Lisboa",
    "concelho": "Lisboa",
    "freguesia": "Freguesia de Avenidas Novas",
    "site": "https://www.psp.pt/",
    "email": "dl@psp.pt",
    "designacao_contrato": "Aquisição de refeições confecionadas para as unidades aeroportuárias",
    "descricao": "Aquisição de refeições confecionadas para as unidades aeroportuárias",
    "preco_base": "1.485.604,75 EUR",
    "prazo_execucao": "365 DIAS",
    "prazo_apresentacao_propostas": "25-09-2025 18:00",
    "fundos_eu": "Não",
    "plataforma_eletronica": "VORTAL",
    "url_procedimento": "https://community.vortal.biz/public/",
    "autor_nome": "Licinio Cardoso Vaz",
    "autor_cargo": "Chefe de Divisão"
  },
  {
    "numero_procedimento": "N/A",
    "entidade": "ESTADO-MAIOR-GENERAL DAS FORÇAS ARMADAS",
    "link": "https://diariodarepublica.pt/dr/detalhe/contrato-publico/22603-933044033",
    "detalhes_completos": "Alteração do Anúncio de procedimento n.º 22348/2025, de 2025-08-21, com o ID 419444686\n\n1 - IDENTIFICAÇÃO E CONTACTOS DA ENTIDADE ADJUDICANTE\nDesignação da entidade adjudicante: ESTADO-MAIOR-GENERAL DAS FORÇAS ARMADAS\nNIPC: 600010180\nServiço/Órgão/Pessoa de contacto: DIREÇÃO DE FINANÇAS/ SECÇÃO DE AQUISIÇÕES E CONTRATOS\nEndereço: AVENIDA ILHA DA MADEIRA\nCódigo postal: 1449-004\nLocalidade: Lisboa\nPaís: Portugal\nNUT III: PT170\nDistrito: Lisboa\nConcelho: Lisboa\nFreguesia: Freguesia de Lumiar\nTelefone: 2130100001\nEndereço da Entidade (URL): www.emgfa.pt\nEndereço Eletrónico: DIRFIN_Contratos@emgfa.pt\neDelivery Gateway (URL): https://www.acingov.pt\nFunção da Organização: Adquirente\nNorma jurídica da Entidade Adjudicante: Organismo de direito público\nÁrea de atividade da Autoridade Adjudicante: Serviços públicos das administrações públicas\n\n2 - JORNAL OFICIAL DA UNIÃO EUROPEIA\nO procedimento a que este anúncio diz respeito também é publicitado no Jornal Oficial da União Europeia? Sim\n\n3 - AVISO\nModelo de Anúncio: Concurso público\nData de Envio do Anúncio: 21-08-2025\n\n5 - PROCESSO\nTipo de Procedimento: Concurso público\nPreço base do procedimento: Sim\nValor do preço base do procedimento: 154.000,00 EUR\nProcedimento com lotes? Não\n\n6 - OBJETO DO CONTRATO\nNúmero de referência interna: 2025005854\nDesignação do contrato: Licenciamento e Equipamentos CheckPoint\nDescrição: Licenciamento e Equipamentos CheckPoint\nOpções: Não\nTipo de Contrato Principal: Aquisição de Serviços\nTipo de Contrato: Aquisição de Bens Móveis; Aquisição de Serviços\nClassificação CPV (Vocabulário Comum para os Contratos Públicos)\nObjeto principal\nVocabulário Principal: 72100000\nPreço base s/IVA: 106.547,63 EUR\nObjeto Complementar\nVocabulário Principal: 30230000\nPreço base s/IVA: 47.452,37 EUR\n\n7 - INDICAÇÕES ADICIONAIS\nO contrato envolve aquisição conjunta (satisfação de várias entidades)? Não\nO contrato é adjudicado por uma central de compras? Não\n\n8 - TÉCNICAS\nO concurso destina-se à celebração de um acordo-quadro? Inexistência de acordo-quadro\nÉ utilizado um leilão eletrónico? Não\nÉ adotada uma fase de negociação? Não\nSistema de Aquisição Dinâmico: Inexistência de sistema de aquisição dinâmico\n\n9 - LOCAL DA EXECUÇÃO DO CONTRATO\nLOCAL DA EXECUÇÃO DO CONTRATO (PROCEDIMENTO)\nPaís: Portugal\nNUT III: PT170\nLocalidade: Freguesia de Belém\nDistrito: Lisboa\nConcelho: Lisboa\nFreguesia: Freguesia de Belém\n\n10 - PRAZO DE EXECUÇÃO DO CONTRATO\nPrazo de execução do contrato: 30 DIAS\nPrevisão de renovações: Não\n\n11 - FUNDOS EU\nTêm fundos EU? Não\n\n12 - DOCUMENTOS DE HABILITAÇÃO\nHabilitação para o exercício da atividade profissional: Não\n\n13 - CONDIÇÕES DE APRESENTAÇÃO\nPlataforma eletrónica utilizada pela entidade adjudicante: ACIN\nURL para Apresentação: https://www.acingov.pt\nAdmissibilidade da apresentação de propostas variantes: Não autorizado\nPrazo para apresentação das propostas: 20-09-2025 23:59\nPrazo durante o qual os concorrentes são obrigados a manter as respetivas propostas: 88 dias a contar do termo do prazo para a apresentação das propostas\nApresentação de Catálogo Eletrónico: Permitido\nIndicação de Subcontratação na Proposta: Inexistência de indicação de subcontratação\n\n14 - PRESTAÇÃO DE CAUÇÃO\nPrestação de caução: Não\n\n15 - FORNECIMENTO DAS PEÇAS DO CONCURSO, APRESENTAÇÃO DE PEDIDOS DE PARTICIPAÇÃO E APRESENTAÇÃO DAS PROPOSTAS\nLink para acesso às peças do concurso (URL): https://www.acingov.pt/acingovprod/2/zonaPublica/zona_publica_c/donwloadProcedurePiece/OTM0MjE3\n\n20 - OUTROS REQUISITOS\nInformação sobre contratos reservados. Aplica-se a contratos reservados (54º-A)? Não\n\n21 - CRITÉRIO DE ADJUDICAÇÃO\nMultifator: Não\nMonofator:\nNome: Preço\n\n24 - CONDIÇÕES DO CONTRATO\nFaturação Eletrónica: Permitido\nObrigação de Subcontratação:\nCódigo da Obrigação de Subcontratação: Não é aplicável nenhuma obrigação de subcontratação.\n\n25 - COMPRA PÚBLICA ESTRATÉGICA\nCompra Pública Estratégica: Inexistência de contratação pública estratégica\n\n26 - INFORMAÇÕES ADICIONAIS\nContrato adequado para PME: Sim\nCobertura ACP (Acordo dos Contratos Públicos da Organização Mundial do Comércio): Não\n\n27 - IDENTIFICAÇÃO E CONTACTOS DO ÓRGÃO DE RECURSOS ADMINISTRATIVOS\nDesignação: Direção de Finanças\nEndereço: AVENIDA ILHA DA MADEIRA\nCódigo postal: 1449-004\nLocalidade: Lisboa\nTelefone: 213043000\nFax: \nEndereço eletrónico: DIRFIN_Contratos@emgfa.pt\n\n28 - IDENTIFICAÇÃO DO(S) AUTOR(ES) DE ANÚNCIO\nNome: Brigadeiro General Rui Manuel da Silva Pina\nCargo: Diretor de Finanças\n\n29 - ALTERAÇÃO\nMotivo da Alteração: Correção pelo editor\nIdentificador da Versão do Anúncio a Alterar: aa748310-a2a1-4193-b3df-cd0066b9329d-01\nIdentificador das Secções Alteradas do Anúncio Anterior: Condições de Apresentação\nAlteração dos Documentos do Concurso: Não\n419455053",
    "nipc": "600010180",
    "distrito": "Lisboa",
    "concelho": "Lisboa",
    "freguesia": "Freguesia de Lumiar",
    "site": "www.emgfa.pt",
    "email": "DIRFIN_Contratos@emgfa.pt",
    "designacao_contrato": "Licenciamento e Equipamentos CheckPoint",
    "descricao": "Licenciamento e Equipamentos CheckPoint",
    "preco_base": "106.547,63 EUR",
    "prazo_execucao": "30 DIAS",
    "prazo_apresentacao_propostas": "20-09-2025 23:59",
    "fundos_eu": "Não",
    "plataforma_eletronica": "ACIN",
    "url_procedimento": "https://www.acingov.pt",
    "autor_nome": "Brigadeiro General Rui Manuel da Silva Pina",
    "autor_cargo": "Diretor de Finanças"
  },
  {
    "numero_procedimento": "N/A",
    "entidade": "Escola Secundária Domingos Rebelo",
    "link": "https://diariodarepublica.pt/dr/detalhe/contrato-publico/22605-933044034",
    "detalhes_completos": "Alteração do Anúncio de procedimento n.º 22306/2025, de 2025-08-20, com o ID 419443251\n\n1 - IDENTIFICAÇÃO E CONTACTOS DA ENTIDADE ADJUDICANTE\nDesignação da entidade adjudicante: Escola Secundária Domingos Rebelo\nNIPC: 672001004\nServiço/Órgão/Pessoa de contacto: Lúcia Maria de Sousa Dias e Nunes Medeiros\nEndereço: Avenida Antero de Quental, s/n\nCódigo postal: 9504-501\nLocalidade: Ponta Delgada\nPaís: Portugal\nNUT III: PT200\nDistrito: Região Autónoma dos Açores\nConcelho: Ponta Delgada\nFreguesia: Freguesia de Ponta Delgada (São José)\nTelefone: 296301430\nFax: 296288384\nEndereço da Entidade (URL): https://www.esdomingosrebelo.net/esdr\nEndereço Eletrónico: cees.domingosrebelo@edu.azores.gov.pt\neDelivery Gateway (URL): https://www.acingov.pt\nFunção da Organização: Adquirente\nNorma jurídica da Entidade Adjudicante: Organismo de direito público\nÁrea de atividade da Autoridade Adjudicante: Educação\n\n2 - JORNAL OFICIAL DA UNIÃO EUROPEIA\nO procedimento a que este anúncio diz respeito também é publicitado no Jornal Oficial da União Europeia? Sim\n\n3 - AVISO\nModelo de Anúncio: Concurso público\nData de Envio do Anúncio: 21-08-2025\n\n5 - PROCESSO\nTipo de Procedimento: Concurso público\nPreço base do procedimento: Sim\nValor do preço base do procedimento: 1.049.677,64 EUR\nProcedimento com lotes? Sim\nNº Máx. de Lotes Autorizado: 6\nNúmero máximo de lotes que podem ser adjudicados a um concorrente: 6\n\n6 - OBJETO DO CONTRATO\nNúmero de referência interna: CPI/1/2025\nDesignação do contrato: Manuais Digitais para o ano letivo 2025/2026\nDescrição: Aquisição de Manuais Digitais - Equipamentos e Licenças - para o ano letivo 2025/2026\nOpções: Não\nTipo de Contrato Principal: Aquisição de Bens Móveis\nTipo de Contrato: Aquisição de Bens Móveis\nClassificação CPV (Vocabulário Comum para os Contratos Públicos)\nObjeto principal\nVocabulário Principal: 30213100\nPreço base s/IVA: 1.049.677,64 EUR\nLotes: \nNº: LOT-0001\nDescrição do Lote: Licenças para o 7.º ano\nPreço base s/IVA: 132.075,90 EUR\nClassificação CPV (Vocabulário Comum para os Contratos Públicos)\nObjeto principal\nVocabulário Principal: 30213100\nNº: LOT-0002\nDescrição do Lote: Equipamentos e Licenças para o 8.º ano\nPreço base s/IVA: 284.124,40 EUR\nClassificação CPV (Vocabulário Comum para os Contratos Públicos)\nObjeto principal\nVocabulário Principal: 30213100\nNº: LOT-0003\nDescrição do Lote: Licenças para o 9.º ano\nPreço base s/IVA: 143.925,60 EUR\nClassificação CPV (Vocabulário Comum para os Contratos Públicos)\nObjeto principal\nVocabulário Principal: 30213100\nNº: LOT-0004\nDescrição do Lote: Licenças para o 10.º ano\nPreço base s/IVA: 104.454,50 EUR\nClassificação CPV (Vocabulário Comum para os Contratos Públicos)\nObjeto principal\nVocabulário Principal: 30213100\nNº: LOT-0005\nDescrição do Lote: Equipamentos e Licenças para o 11.º ano\nPreço base s/IVA: 205.954,00 EUR\nClassificação CPV (Vocabulário Comum para os Contratos Públicos)\nObjeto principal\nVocabulário Principal: 30213100\nNº: LOT-0006\nDescrição do Lote: Equipamentos e Licenças para o 12.º ano\nPreço base s/IVA: 179.143,24 EUR\nClassificação CPV (Vocabulário Comum para os Contratos Públicos)\nObjeto principal\nVocabulário Principal: 30213100\n\n7 - INDICAÇÕES ADICIONAIS\nO contrato envolve aquisição conjunta (satisfação de várias entidades)? Não\nO contrato é adjudicado por uma central de compras? Não\n\n8 - TÉCNICAS\nO concurso destina-se à celebração de um acordo-quadro? Inexistência de acordo-quadro\nÉ utilizado um leilão eletrónico? Não\nÉ adotada uma fase de negociação? Não\nSistema de Aquisição Dinâmico: Inexistência de sistema de aquisição dinâmico\n\n9 - LOCAL DA EXECUÇÃO DO CONTRATO\nLOCAL DA EXECUÇÃO DO CONTRATO (PROCEDIMENTO)\nPaís: Portugal\nNUT III: PT200\nLocalidade: PONTA DELGADA\nDistrito: Região Autónoma dos Açores\nConcelho: Ponta Delgada\nFreguesia: Freguesia de Ponta Delgada (São José)\nLOCAL DA EXECUÇÃO DO CONTRATO (LOTE)\nIdentificador do Lote: LOT-0001; LOT-0002; LOT-0003; LOT-0004; LOT-0005; LOT-0006\nPaís: Portugal\nNUT III: PT200\nLocalidade: Ponta Delgada\nDistrito: Região Autónoma dos Açores\nConcelho: Ponta Delgada\nFreguesia: Freguesia de Ponta Delgada (São José)\n\n10 - PRAZO DE EXECUÇÃO DO CONTRATO\nIdentificador do Lote: LOT-0001; LOT-0002; LOT-0003; LOT-0004; LOT-0005; LOT-0006\nData de Início: 11-09-2025\nData de Fim: 12-06-2026\nPrevisão de renovações: Não\n\n11 - FUNDOS EU\nIdentificador do Lote: LOT-0001; LOT-0002; LOT-0003; LOT-0004; LOT-0005; LOT-0006\nTêm fundos EU? Sim\n\n12 - DOCUMENTOS DE HABILITAÇÃO\nHabilitação para o exercício da atividade profissional: Não\n\n13 - CONDIÇÕES DE APRESENTAÇÃO\nPlataforma eletrónica utilizada pela entidade adjudicante: ACIN\nURL para Apresentação: https://www.acingov.pt\nAdmissibilidade da apresentação de propostas variantes: Não autorizado\nPrazo para apresentação das propostas: 13-09-2025 23:59\nPrazo durante o qual os concorrentes são obrigados a manter as respetivas propostas: 120 dias a contar do termo do prazo para a apresentação das propostas\nApresentação de Catálogo Eletrónico: Permitido\nIndicação de Subcontratação na Proposta: Inexistência de indicação de subcontratação\n\n14 - PRESTAÇÃO DE CAUÇÃO\nPrestação de caução: Sim\nPercentagem: 2%\nDescrição da Garantia Exigida: O valor da caução é de 2.00% do preço contratual.\n\n15 - FORNECIMENTO DAS PEÇAS DO CONCURSO, APRESENTAÇÃO DE PEDIDOS DE PARTICIPAÇÃO E APRESENTAÇÃO DAS PROPOSTAS\nLink para acesso às peças do concurso (URL): https://www.acingov.pt/acingovprod/2/zonaPublica/zona_publica_c/donwloadProcedurePiece/OTM0MzUw\n\n20 - OUTROS REQUISITOS\nIdentificador do Lote: LOT-0001; LOT-0002; LOT-0003; LOT-0004; LOT-0005; LOT-0006\nInformação sobre contratos reservados. Aplica-se a contratos reservados (54º-A)? Não\n\n21 - CRITÉRIO DE ADJUDICAÇÃO\nO Critério de adjudicação é diferenciado por lote? Não\nMultifator: Não\nMonofator:\nNome: Preço\n\n24 - CONDIÇÕES DO CONTRATO\nIdentificador do Lote: LOT-0001; LOT-0002; LOT-0003; LOT-0004; LOT-0005; LOT-0006\nFaturação Eletrónica: Permitido\nObrigação de Subcontratação:\nCódigo da Obrigação de Subcontratação: Não é aplicável nenhuma obrigação de subcontratação.\n\n25 - COMPRA PÚBLICA ESTRATÉGICA\nCompra Pública Estratégica: Inexistência de contratação pública estratégica\n\n26 - INFORMAÇÕES ADICIONAIS\nIdentificador do Lote: LOT-0001; LOT-0002; LOT-0003; LOT-0004; LOT-0005; LOT-0006\nContrato adequado para PME: Não\nCobertura ACP (Acordo dos Contratos Públicos da Organização Mundial do Comércio): Não\n\n27 - IDENTIFICAÇÃO E CONTACTOS DO ÓRGÃO DE RECURSOS ADMINISTRATIVOS\nDesignação: Secretaria Regional da Educação, Cultura e Desporto\nEndereço: Paços da Junta Geral - Carreira dos Cavalos Apartado 46\nCódigo postal: 9700-167\nLocalidade: Angra do Heroísmo\nTelefone: 295401100\nFax: 295240886\nEndereço eletrónico: drae.info@azores.gov.pt\n\n28 - IDENTIFICAÇÃO DO(S) AUTOR(ES) DE ANÚNCIO\nNome: Lúcia Maria de Sousa Dias e Nunes Medeiros\nCargo: Presidente do Conselho Administrativo\n\n29 - ALTERAÇÃO\nMotivo da Alteração: Correção pelo adquirente\nIdentificador da Versão do Anúncio a Alterar: fcc175df-0de2-47f4-95d2-24a24df1d0ee-02\nIdentificador das Secções Alteradas do Anúncio Anterior: Prazo de execução do contrato\nDescrição das Alterações: 31 - Alteração/anulação Identificador das secções alteradas do anúncio anterior: (*) 10? Prazo de execução do contrato? Identificador do Lote: LOT -001; OT -002; LOT -003; LOT -004; LOT -005; LOT -006 Identificador da versão do anúncio a alterar: (*) JORAA II Série n.º 156, Anúncio n.º 453/2025 de 18 de agosto de 2025, retificado com o n.º 85/2025, de 19 de agosto de 2025 Descrição das alterações: Data de início: data do visto do Tribunal de Contas\nAlteração dos Documentos do Concurso: Não\n419455159",
    "nipc": "672001004",
    "distrito": "Região Autónoma dos Açores",
    "concelho": "Ponta Delgada",
    "freguesia": "Freguesia de Ponta Delgada (São José)",
    "site": "https://www.esdomingosrebelo.net/esdr",
    "email": "cees.domingosrebelo@edu.azores.gov.pt",
    "designacao_contrato": "Manuais Digitais para o ano letivo 2025/2026",
    "descricao": "Aquisição de Manuais Digitais - Equipamentos e Licenças - para o ano letivo 2025/2026",
    "preco_base": "1.049.677,64 EUR",
    "prazo_execucao": null,
    "prazo_apresentacao_propostas": "13-09-2025 23:59",
    "fundos_eu": "Sim",
    "plataforma_eletronica": "ACIN",
    "url_procedimento": "https://www.acingov.pt",
    "autor_nome": "Lúcia Maria de Sousa Dias e Nunes Medeiros",
    "autor_cargo": "Presidente do Conselho Administrativo"
  },
  {
    "numero_procedimento": "N/A",
    "entidade": "COMISSÃO DO MERCADO DE VALORES MOBILIARIOS",
    "link": "https://diariodarepublica.pt/dr/detalhe/contrato-publico/22607-933044035",
    "detalhes_completos": "1 - IDENTIFICAÇÃO E CONTACTOS DA ENTIDADE ADJUDICANTE\nDesignação da entidade adjudicante: COMISSÃO DO MERCADO DE VALORES MOBILIARIOS\nNIPC: 502549254\nEndereço: Rua Laura Alves, Nº 4\nCódigo postal: 1050-138\nLocalidade: Lisboa\nPaís: Portugal\nNUT III: PT170\nDistrito: Lisboa\nConcelho: Lisboa\nFreguesia: Freguesia de Avenidas Novas\nTelefone: 213177000\nFax: 213537077\nEndereço da Entidade (URL): https://www.cmvm.pt/\nEndereço Eletrónico: cmvm@cmvm.pt\neDelivery Gateway (URL): https://community.vortal.biz/public/\nFunção da Organização: Adquirente\nNorma jurídica da Entidade Adjudicante: Instituição, órgão ou agência da UE\nÁrea de atividade da Autoridade Adjudicante: Assuntos económicos\n\n2 - JORNAL OFICIAL DA UNIÃO EUROPEIA\nO procedimento a que este anúncio diz respeito também é publicitado no Jornal Oficial da União Europeia? Sim\n\n3 - AVISO\nModelo de Anúncio: Concurso público\nData de Envio do Anúncio: 21-08-2025\n\n5 - PROCESSO\nTipo de Procedimento: Concurso público\nPreço base do procedimento: Sim\nValor do preço base do procedimento: 370.000,00 EUR\nProcedimento com lotes? Não\n\n6 - OBJETO DO CONTRATO\nNúmero de referência interna: CP 17/2025_Axway\nDesignação do contrato: Renovação da plataforma Axway Secure Transport\nDescrição: Renovação da subscrição do software/licenciamento dos componentes que compõem a arquitetura da plataforma Axway Secure Transport e Serviços de assistência técnica\nOpções: Não\nTipo de Contrato Principal: Aquisição de Serviços\nTipo de Contrato: Aquisição de Serviços\nClassificação CPV (Vocabulário Comum para os Contratos Públicos)\nObjeto principal\nVocabulário Principal: 72260000\nPreço base s/IVA: 370.000,00 EUR\n\n7 - INDICAÇÕES ADICIONAIS\nO contrato envolve aquisição conjunta (satisfação de várias entidades)? Não\nO contrato é adjudicado por uma central de compras? Não\n\n8 - TÉCNICAS\nO concurso destina-se à celebração de um acordo-quadro? Inexistência de acordo-quadro\nÉ utilizado um leilão eletrónico? Não\nÉ adotada uma fase de negociação? Não\nSistema de Aquisição Dinâmico: Inexistência de sistema de aquisição dinâmico\n\n9 - LOCAL DA EXECUÇÃO DO CONTRATO\nLOCAL DA EXECUÇÃO DO CONTRATO (PROCEDIMENTO)\nPaís: Portugal\nNUT III: PT170\nLocalidade: Lisboa\nDistrito: Lisboa\nConcelho: Lisboa\nFreguesia: Freguesia de Avenidas Novas\n\n10 - PRAZO DE EXECUÇÃO DO CONTRATO\nPrazo de execução do contrato: 3 ANOS\nPrevisão de renovações: Não\n\n11 - FUNDOS EU\nTêm fundos EU? Não\n\n12 - DOCUMENTOS DE HABILITAÇÃO\nHabilitação para o exercício da atividade profissional: Não\n\n13 - CONDIÇÕES DE APRESENTAÇÃO\nPlataforma eletrónica utilizada pela entidade adjudicante: VORTAL\nURL para Apresentação: https://community.vortal.biz/public/\nAdmissibilidade da apresentação de propostas variantes: Não autorizado\nPrazo para apresentação das propostas: 23-09-2025 17:00\nPrazo durante o qual os concorrentes são obrigados a manter as respetivas propostas: 66 dias a contar do termo do prazo para a apresentação das propostas\nApresentação de Catálogo Eletrónico: Não autorizado\nIndicação de Subcontratação na Proposta: Inexistência de indicação de subcontratação\n\n14 - PRESTAÇÃO DE CAUÇÃO\nPrestação de caução: Não\n\n15 - FORNECIMENTO DAS PEÇAS DO CONCURSO, APRESENTAÇÃO DE PEDIDOS DE PARTICIPAÇÃO E APRESENTAÇÃO DAS PROPOSTAS\nLink para acesso às peças do concurso (URL): https://community.vortal.biz/Public/public-tender-documents/d3lXd0g3ckp1WjYxUGF5VTEzMjgxemhFUlpUZ2pmQVhpUVlvNlZEbTRucEhscnRaZG9RWnhaL3dqSXh3YU9EN0JQaEg2VFRiTU1ZM2NOSU85VzhVTWc9PXdhU0FB\n\n20 - OUTROS REQUISITOS\nInformação sobre contratos reservados. Aplica-se a contratos reservados (54º-A)? Não\n\n21 - CRITÉRIO DE ADJUDICAÇÃO\nMultifator: Não\nMonofator:\nNome: Preço\n\n24 - CONDIÇÕES DO CONTRATO\nFaturação Eletrónica: Permitido\nObrigação de Subcontratação:\nCódigo da Obrigação de Subcontratação: Não é aplicável nenhuma obrigação de subcontratação.\n\n25 - COMPRA PÚBLICA ESTRATÉGICA\nCompra Pública Estratégica: Inexistência de contratação pública estratégica\n\n26 - INFORMAÇÕES ADICIONAIS\nContrato adequado para PME: Sim\nCobertura ACP (Acordo dos Contratos Públicos da Organização Mundial do Comércio): Não\n\n27 - IDENTIFICAÇÃO E CONTACTOS DO ÓRGÃO DE RECURSOS ADMINISTRATIVOS\nDesignação: CMVM\nEndereço: Rua Laura Alves n.º 4\nCódigo postal: 1050-138\nLocalidade: Lisboa\nTelefone: +351 213177000\nFax: +351 213537077\nEndereço eletrónico: cmvm@cmvm.pt\n\n28 - IDENTIFICAÇÃO DO(S) AUTOR(ES) DE ANÚNCIO\nNome: Compras \nCargo: DFPA\n419456025",
    "nipc": "502549254",
    "distrito": "Lisboa",
    "concelho": "Lisboa",
    "freguesia": "Freguesia de Avenidas Novas",
    "site": "https://www.cmvm.pt/",
    "email": "cmvm@cmvm.pt",
    "designacao_contrato": "Renovação da plataforma Axway Secure Transport",
    "descricao": "Renovação da subscrição do software/licenciamento dos componentes que compõem a arquitetura da plataforma Axway Secure Transport e Serviços de assistência técnica",
    "preco_base": "370.000,00 EUR",
    "prazo_execucao": "3 ANOS",
    "prazo_apresentacao_propostas": "23-09-2025 17:00",
    "fundos_eu": "Não",
    "plataforma_eletronica": "VORTAL",
    "url_procedimento": "https://community.vortal.biz/public/",
    "autor_nome": "Compras",
    "autor_cargo": "DFPA"
  },
  {
    "numero_procedimento": "N/A",
    "entidade": "BANCO DE PORTUGAL",
    "link": "https://diariodarepublica.pt/dr/detalhe/contrato-publico/22608-933044036",
    "detalhes_completos": "1 - IDENTIFICAÇÃO E CONTACTOS DA ENTIDADE ADJUDICANTE\nDesignação da entidade adjudicante: BANCO DE PORTUGAL\nNIPC: 500792771\nEndereço: Rua Francisco Ribeiro, 2\nCódigo postal: 1150-165\nLocalidade: Lisboa\nPaís: Portugal\nNUT III: PT170\nDistrito: Lisboa\nConcelho: Lisboa\nFreguesia: Todas\nTelefone: 213130000\nFax: 213128124\nEndereço da Entidade (URL): www.bportugal.pt\nEndereço Eletrónico: bdp.compras@bportugal.pt\neDelivery Gateway (URL): https://community.vortal.biz/public/\nFunção da Organização: Adquirente\nNorma jurídica da Entidade Adjudicante: Organismo de direito público\nÁrea de atividade da Autoridade Adjudicante: Assuntos económicos\n\n2 - JORNAL OFICIAL DA UNIÃO EUROPEIA\nO procedimento a que este anúncio diz respeito também é publicitado no Jornal Oficial da União Europeia? Sim\n\n3 - AVISO\nModelo de Anúncio: Concurso público\nData de Envio do Anúncio: 21-08-2025\n\n5 - PROCESSO\nTipo de Procedimento: Concurso público\nPreço base do procedimento: Sim\nValor do preço base do procedimento: 1.396.700,00 EUR\nProcedimento com lotes? Sim\nNº Máx. de Lotes Autorizado: 2\nNúmero máximo de lotes que podem ser adjudicados a um concorrente: 2\n\n6 - OBJETO DO CONTRATO\nNúmero de referência interna: OA021925\nDesignação do contrato: Aquisição de serviços de manutenção geral\nDescrição: Aquisição de serviços de manutenção geral (Filial, Rede Regional Norte e Delegação Regional dos Açores)\nOpções: Não\nTipo de Contrato Principal: Aquisição de Serviços\nTipo de Contrato: Aquisição de Serviços\nClassificação CPV (Vocabulário Comum para os Contratos Públicos)\nObjeto principal\nVocabulário Principal: 50700000\nPreço base s/IVA: 1.396.700,00 EUR\nLotes: \nNº: LOT-0001\nDescrição do Lote: Lote 1\nPreço base s/IVA: 1.266.800,00 EUR\nClassificação CPV (Vocabulário Comum para os Contratos Públicos)\nObjeto principal\nVocabulário Principal: 50700000\nNº: LOT-0002\nDescrição do Lote: Lote 2\nPreço base s/IVA: 129.900,00 EUR\nClassificação CPV (Vocabulário Comum para os Contratos Públicos)\nObjeto principal\nVocabulário Principal: 50700000\n\n7 - INDICAÇÕES ADICIONAIS\nO contrato envolve aquisição conjunta (satisfação de várias entidades)? Não\nO contrato é adjudicado por uma central de compras? Não\n\n8 - TÉCNICAS\nO concurso destina-se à celebração de um acordo-quadro? Inexistência de acordo-quadro\nÉ utilizado um leilão eletrónico? Não\nÉ adotada uma fase de negociação? Não\nSistema de Aquisição Dinâmico: Inexistência de sistema de aquisição dinâmico\n\n9 - LOCAL DA EXECUÇÃO DO CONTRATO\nLOCAL DA EXECUÇÃO DO CONTRATO (PROCEDIMENTO)\nPaís: Portugal\nNUT III: PT170\nLocalidade: Lisboa\nDistrito: Lisboa\nConcelho: Lisboa\nFreguesia: Todas\nLOCAL DA EXECUÇÃO DO CONTRATO (LOTE)\nIdentificador do Lote: LOT-0001; LOT-0002\nPaís: Portugal\nNUT III: PT170\nLocalidade: Lisboa\nDistrito: Lisboa\nConcelho: Lisboa\nFreguesia: Todas\n\n10 - PRAZO DE EXECUÇÃO DO CONTRATO\nIdentificador do Lote: LOT-0001; LOT-0002\nPrazo de execução do contrato: 5 ANOS\nPrevisão de renovações: Não\n\n11 - FUNDOS EU\nIdentificador do Lote: LOT-0001; LOT-0002\nTêm fundos EU? Não\n\n12 - DOCUMENTOS DE HABILITAÇÃO\nHabilitação para o exercício da atividade profissional: Não\n\n13 - CONDIÇÕES DE APRESENTAÇÃO\nPlataforma eletrónica utilizada pela entidade adjudicante: VORTAL\nURL para Apresentação: https://community.vortal.biz/public/\nAdmissibilidade da apresentação de propostas variantes: Não autorizado\nPrazo para apresentação das propostas: 22-09-2025 17:00\nPrazo durante o qual os concorrentes são obrigados a manter as respetivas propostas: 120 dias a contar do termo do prazo para a apresentação das propostas\nApresentação de Catálogo Eletrónico: Não autorizado\nIndicação de Subcontratação na Proposta: Inexistência de indicação de subcontratação\n\n14 - PRESTAÇÃO DE CAUÇÃO\nPrestação de caução: Sim\nPercentagem: 5%\nDescrição da Garantia Exigida: Garantia bancária, seguro-caução ou depósito em dinheiro ou títulos\n\n15 - FORNECIMENTO DAS PEÇAS DO CONCURSO, APRESENTAÇÃO DE PEDIDOS DE PARTICIPAÇÃO E APRESENTAÇÃO DAS PROPOSTAS\nLink para acesso às peças do concurso (URL): https://community.vortal.biz/Public/public-tender-documents/bkE4bkxrL2FNTSszTmk3YWs0QmJNN2lKVEFjVVl3ZHpzTjkzcHB1LzhzVDJMWFZMM2NsTkEzSjhSL1JUbGEzVFZWbXYvMm9OcXgzYjRadzc2cGx1a1E9PWczMW4z\n\n20 - OUTROS REQUISITOS\nIdentificador do Lote: LOT-0001; LOT-0002\nInformação sobre contratos reservados. Aplica-se a contratos reservados (54º-A)? Não\n\n21 - CRITÉRIO DE ADJUDICAÇÃO\nO Critério de adjudicação é diferenciado por lote? Não\nMultifator: Não\nMonofator:\nNome: Preço\n\n24 - CONDIÇÕES DO CONTRATO\nIdentificador do Lote: LOT-0001; LOT-0002\nFaturação Eletrónica: Permitido\nObrigação de Subcontratação:\nCódigo da Obrigação de Subcontratação: Não é aplicável nenhuma obrigação de subcontratação.\n\n25 - COMPRA PÚBLICA ESTRATÉGICA\nCompra Pública Estratégica: Inexistência de contratação pública estratégica\n\n26 - INFORMAÇÕES ADICIONAIS\nIdentificador do Lote: LOT-0001; LOT-0002\nContrato adequado para PME: Sim\nCobertura ACP (Acordo dos Contratos Públicos da Organização Mundial do Comércio): Não\n\n27 - IDENTIFICAÇÃO E CONTACTOS DO ÓRGÃO DE RECURSOS ADMINISTRATIVOS\nDesignação: Conselho de Administração do Banco de Portugal\nEndereço: Rua Francisco Ribeiro, n.º 2\nCódigo postal: 1150-165\nLocalidade: Lisboa\nTelefone: +351 213130000\nFax: +351 213128124\nEndereço eletrónico: bdp.compras@bportugal.pt\n\n28 - IDENTIFICAÇÃO DO(S) AUTOR(ES) DE ANÚNCIO\nNome: DLIAC-UFC\nCargo: DLIAC-UFC\n419453182",
    "nipc": "500792771",
    "distrito": "Lisboa",
    "concelho": "Lisboa",
    "freguesia": "Todas",
    "site": "www.bportugal.pt",
    "email": "bdp.compras@bportugal.pt",
    "designacao_contrato": "Aquisição de serviços de manutenção geral",
    "descricao": "Aquisição de serviços de manutenção geral (Filial, Rede Regional Norte e Delegação Regional dos Açores)",
    "preco_base": "1.396.700,00 EUR",
    "prazo_execucao": "5 ANOS",
    "prazo_apresentacao_propostas": "22-09-2025 17:00",
    "fundos_eu": "Não",
    "plataforma_eletronica": "VORTAL",
    "url_procedimento": "https://community.vortal.biz/public/",
    "autor_nome": "DLIAC-UFC",
    "autor_cargo": "DLIAC-UFC"
  },
  {
    "numero_procedimento": "N/A",
    "entidade": "BANCO DE PORTUGAL",
    "link": "https://diariodarepublica.pt/dr/detalhe/contrato-publico/22609-933044037",
    "detalhes_completos": "Alteração do Anúncio de procedimento n.º 20826/2025, de 2025-08-04, com o ID 419376524\n\n1 - IDENTIFICAÇÃO E CONTACTOS DA ENTIDADE ADJUDICANTE\nDesignação da entidade adjudicante: BANCO DE PORTUGAL\nNIPC: 500792771\nEndereço: Rua Francisco Ribeiro, 2\nCódigo postal: 1150-165\nLocalidade: Lisboa\nPaís: Portugal\nNUT III: PT170\nDistrito: Lisboa\nConcelho: Lisboa\nFreguesia: Todas\nTelefone: 213130000\nFax: 213128124\nEndereço da Entidade (URL): www.bportugal.pt\nEndereço Eletrónico: bdp.compras@bportugal.pt\neDelivery Gateway (URL): https://community.vortal.biz/public/\nFunção da Organização: Adquirente\nNorma jurídica da Entidade Adjudicante: Organismo de direito público\nÁrea de atividade da Autoridade Adjudicante: Assuntos económicos\n\n2 - JORNAL OFICIAL DA UNIÃO EUROPEIA\nO procedimento a que este anúncio diz respeito também é publicitado no Jornal Oficial da União Europeia? Sim\n\n3 - AVISO\nModelo de Anúncio: Concurso público\nData de Envio do Anúncio: 21-08-2025\n\n5 - PROCESSO\nTipo de Procedimento: Concurso público\nPreço base do procedimento: Sim\nValor do preço base do procedimento: 1.109.525,28 EUR\nProcedimento com lotes? Não\n\n6 - OBJETO DO CONTRATO\nNúmero de referência interna: OA020725\nDesignação do contrato: Aquisição de serviços de apoio logístico e documental\nDescrição: Aquisição de serviços de apoio logístico e documental\nOpções: Não\nTipo de Contrato Principal: Aquisição de Serviços\nTipo de Contrato: Aquisição de Serviços\nClassificação CPV (Vocabulário Comum para os Contratos Públicos)\nObjeto principal\nVocabulário Principal: 79500000\nPreço base s/IVA: 1.109.525,28 EUR\n\n7 - INDICAÇÕES ADICIONAIS\nO contrato envolve aquisição conjunta (satisfação de várias entidades)? Não\nO contrato é adjudicado por uma central de compras? Não\n\n8 - TÉCNICAS\nO concurso destina-se à celebração de um acordo-quadro? Inexistência de acordo-quadro\nÉ utilizado um leilão eletrónico? Não\nÉ adotada uma fase de negociação? Não\nSistema de Aquisição Dinâmico: Inexistência de sistema de aquisição dinâmico\n\n9 - LOCAL DA EXECUÇÃO DO CONTRATO\nLOCAL DA EXECUÇÃO DO CONTRATO (PROCEDIMENTO)\nPaís: Portugal\nNUT III: PT170\nLocalidade: Lisboa\nDistrito: Lisboa\nConcelho: Lisboa\nFreguesia: Todas\n\n10 - PRAZO DE EXECUÇÃO DO CONTRATO\nPrazo de execução do contrato: 3 ANOS\nPrevisão de renovações: Não\n\n11 - FUNDOS EU\nTêm fundos EU? Não\n\n12 - DOCUMENTOS DE HABILITAÇÃO\nHabilitação para o exercício da atividade profissional: Não\n\n13 - CONDIÇÕES DE APRESENTAÇÃO\nPlataforma eletrónica utilizada pela entidade adjudicante: VORTAL\nURL para Apresentação: https://community.vortal.biz/public/\nAdmissibilidade da apresentação de propostas variantes: Não autorizado\nPrazo para apresentação das propostas: 18-09-2025 17:00\nPrazo durante o qual os concorrentes são obrigados a manter as respetivas propostas: 120 dias a contar do termo do prazo para a apresentação das propostas\nApresentação de Catálogo Eletrónico: Não autorizado\nIndicação de Subcontratação na Proposta: Inexistência de indicação de subcontratação\n\n14 - PRESTAÇÃO DE CAUÇÃO\nPrestação de caução: Sim\nPercentagem: 5%\nDescrição da Garantia Exigida: Garantia bancária, seguro-caução ou depósito em dinheiro ou títulos\n\n15 - FORNECIMENTO DAS PEÇAS DO CONCURSO, APRESENTAÇÃO DE PEDIDOS DE PARTICIPAÇÃO E APRESENTAÇÃO DAS PROPOSTAS\nLink para acesso às peças do concurso (URL): https://community.vortal.biz/Public/public-tender-documents/QlQrdXlQNUsrYmt4K044OFdIbExHamJkb2g4ZWp6VzJYdXNRYVJYOHJTK1pHeHlCNGM3T1d1Rm1CTGYxQzg0SUZ4bk9mUTh0cVd1S3JSZEpYN0pBSVE9PSRyeGkk\n\n20 - OUTROS REQUISITOS\nInformação sobre contratos reservados. Aplica-se a contratos reservados (54º-A)? Não\n\n21 - CRITÉRIO DE ADJUDICAÇÃO\nMultifator: Não\nMonofator:\nNome: Outros\nOutro nome: Preço/Hora por recurso\n\n24 - CONDIÇÕES DO CONTRATO\nFaturação Eletrónica: Permitido\nObrigação de Subcontratação:\nCódigo da Obrigação de Subcontratação: Não é aplicável nenhuma obrigação de subcontratação.\n\n25 - COMPRA PÚBLICA ESTRATÉGICA\nCompra Pública Estratégica: Inexistência de contratação pública estratégica\n\n26 - INFORMAÇÕES ADICIONAIS\nContrato adequado para PME: Sim\nCobertura ACP (Acordo dos Contratos Públicos da Organização Mundial do Comércio): Não\n\n27 - IDENTIFICAÇÃO E CONTACTOS DO ÓRGÃO DE RECURSOS ADMINISTRATIVOS\nDesignação: Conselho de Administração do Banco de Portugal\nEndereço: Rua Francisco Ribeiro, n.º 2\nCódigo postal: 1150-165\nLocalidade: Lisboa\nTelefone: +351 213130000\nFax: +351 213128124\nEndereço eletrónico: bdp.compras@bportugal.pt\n\n28 - IDENTIFICAÇÃO DO(S) AUTOR(ES) DE ANÚNCIO\nNome: DLIAC-UFC\nCargo: DLIAC-UFC\n\n29 - ALTERAÇÃO\nMotivo da Alteração: Informações atualizadas\nIdentificador da Versão do Anúncio a Alterar: 85871763-26d1-40f9-a8cb-e2f45783e8d9-01\nIdentificador das Secções Alteradas do Anúncio Anterior: Alteração\nAlteração dos Documentos do Concurso: Sim\nData de alteração dos documentos do concurso: 21-08-2025\n419454981",
    "nipc": "500792771",
    "distrito": "Lisboa",
    "concelho": "Lisboa",
    "freguesia": "Todas",
    "site": "www.bportugal.pt",
    "email": "bdp.compras@bportugal.pt",
    "designacao_contrato": "Aquisição de serviços de apoio logístico e documental",
    "descricao": "Aquisição de serviços de apoio logístico e documental",
    "preco_base": "1.109.525,28 EUR",
    "prazo_execucao": "3 ANOS",
    "prazo_apresentacao_propostas": "18-09-2025 17:00",
    "fundos_eu": "Não",
    "plataforma_eletronica": "VORTAL",
    "url_procedimento": "https://community.vortal.biz/public/",
    "autor_nome": "DLIAC-UFC",
    "autor_cargo": "DLIAC-UFC"
  },
  {
    "numero_procedimento": "N/A",
    "entidade": "AnÃºncio de procedimento  n.Âº 22610/2025  -  DiÃ¡rio da RepÃºblica n.Âº 162/2025, SÃ©rie II de 2025-08-25",
    "link": "https://diariodarepublica.pt/dr/detalhe/contrato-publico/22610-933044038"
  },
  {
    "numero_procedimento": "N/A",
    "entidade": "SIMAS Oeiras e Amadora",
    "link": "https://diariodarepublica.pt/dr/detalhe/contrato-publico/22612-933044039",
    "detalhes_completos": "1 - IDENTIFICAÇÃO E CONTACTOS DA ENTIDADE ADJUDICANTE\nDesignação da entidade adjudicante: SIMAS Oeiras e Amadora\nNIPC: 680015019\nEndereço: Avenida Dr. Francisco Sá Carneiro nº 19, Urbanização Moinho das Antas\nCódigo postal: 2784-541\nLocalidade: Lisboa\nPaís: Portugal\nNUT III: PT170\nDistrito: Lisboa\nConcelho: Oeiras\nFreguesia: Todas\nTelefone: 214408300\nFax: 214414342\nEndereço da Entidade (URL): www.simas-oeiras-amadora.pt\nEndereço Eletrónico: geral@simas-oeiras-amadora.pt\neDelivery Gateway (URL): https://community.vortal.biz/public/\nFunção da Organização: Adquirente\nNorma jurídica da Entidade Adjudicante: Autoridade da administração central\nÁrea de atividade da Autoridade Adjudicante: Serviços públicos das administrações públicas\n\n2 - JORNAL OFICIAL DA UNIÃO EUROPEIA\nO procedimento a que este anúncio diz respeito também é publicitado no Jornal Oficial da União Europeia? Sim\n\n3 - AVISO\nModelo de Anúncio: Concurso público\nData de Envio do Anúncio: 21-08-2025\n\n5 - PROCESSO\nTipo de Procedimento: Concurso público\nPreço base do procedimento: Sim\nValor do preço base do procedimento: 658.405,00 EUR\nProcedimento com lotes? Não\n\n6 - OBJETO DO CONTRATO\nNúmero de referência interna: CPI 78/2025/342\nDesignação do contrato: Concurso Público internacional, para a aquisição de serviços destinado à renovação do Licenciamento Microsoft Enterprise Agreement.\nDescrição: Concurso Público internacional, para a aquisição de serviços destinado à renovação do Licenciamento Microsoft Enterprise Agreement.\nOpções: Não\nTipo de Contrato Principal: Aquisição de Serviços\nTipo de Contrato: Aquisição de Serviços\nClassificação CPV (Vocabulário Comum para os Contratos Públicos)\nObjeto principal\nVocabulário Principal: 72267100\nPreço base s/IVA: 658.405,00 EUR\n\n7 - INDICAÇÕES ADICIONAIS\nO contrato envolve aquisição conjunta (satisfação de várias entidades)? Não\nO contrato é adjudicado por uma central de compras? Não\n\n8 - TÉCNICAS\nO concurso destina-se à celebração de um acordo-quadro? Inexistência de acordo-quadro\nÉ utilizado um leilão eletrónico? Não\nÉ adotada uma fase de negociação? Não\nSistema de Aquisição Dinâmico: Inexistência de sistema de aquisição dinâmico\n\n9 - LOCAL DA EXECUÇÃO DO CONTRATO\nLOCAL DA EXECUÇÃO DO CONTRATO (PROCEDIMENTO)\nPaís: Portugal\nNUT III: PT170\nLocalidade: Lisboa\nDistrito: Lisboa\nConcelho: Oeiras\nFreguesia: União das Freguesias de Oeiras e São Julião da Barra, Paço de Arcos e Caxias\n\n10 - PRAZO DE EXECUÇÃO DO CONTRATO\nPrazo de execução do contrato: 1080 DIAS\nPrevisão de renovações: Não\n\n11 - FUNDOS EU\nTêm fundos EU? Não\n\n12 - DOCUMENTOS DE HABILITAÇÃO\nHabilitação para o exercício da atividade profissional: Não\n\n13 - CONDIÇÕES DE APRESENTAÇÃO\nPlataforma eletrónica utilizada pela entidade adjudicante: VORTAL\nURL para Apresentação: https://community.vortal.biz/public/\nAdmissibilidade da apresentação de propostas variantes: Não autorizado\nPrazo para apresentação das propostas: 20-09-2025 23:59\nPrazo durante o qual os concorrentes são obrigados a manter as respetivas propostas: 180 dias a contar do termo do prazo para a apresentação das propostas\nApresentação de Catálogo Eletrónico: Permitido\nIndicação de Subcontratação na Proposta: Inexistência de indicação de subcontratação\n\n14 - PRESTAÇÃO DE CAUÇÃO\nPrestação de caução: Sim\nPercentagem: 5%\nDescrição da Garantia Exigida: GUIA DE DEPÓSITO BANCÁRIO, SEGURO-CAUÇÃO, GARANTIA BANCÁRIA.\n\n15 - FORNECIMENTO DAS PEÇAS DO CONCURSO, APRESENTAÇÃO DE PEDIDOS DE PARTICIPAÇÃO E APRESENTAÇÃO DAS PROPOSTAS\nLink para acesso às peças do concurso (URL): https://community.vortal.biz/Public/public-tender-documents/VVRoMDBrWW5SV2xzQWpDSmxDS3M1dGVJc1NlcDl1ZDBhNzM4U3RuK1hrdGRqRGwwVjdRaXdKeStBS2dqNXFXZCtaeW92bFlJMHVvbUxyTHlUZ3NEOGc9PTFUQ0RG\n\n20 - OUTROS REQUISITOS\nInformação sobre contratos reservados. Aplica-se a contratos reservados (54º-A)? Não\n\n21 - CRITÉRIO DE ADJUDICAÇÃO\nMultifator: Não\nMonofator:\nNome: Outros\nOutro nome: Preço\n\n24 - CONDIÇÕES DO CONTRATO\nFaturação Eletrónica: Permitido\nObrigação de Subcontratação:\nCódigo da Obrigação de Subcontratação: Não é aplicável nenhuma obrigação de subcontratação.\n\n25 - COMPRA PÚBLICA ESTRATÉGICA\nCompra Pública Estratégica: Inexistência de contratação pública estratégica\n\n26 - INFORMAÇÕES ADICIONAIS\nContrato adequado para PME: Sim\nCobertura ACP (Acordo dos Contratos Públicos da Organização Mundial do Comércio): Não\n\n27 - IDENTIFICAÇÃO E CONTACTOS DO ÓRGÃO DE RECURSOS ADMINISTRATIVOS\nDesignação: Juízo de Contratos Públicos do Tribunal Administrativo de Círculo de Lisboa\nEndereço: Avenida Dom João II, 1.08.01, edifício G, 6.º andar\nCódigo postal: 1900-097\nLocalidade: Lisboa\nTelefone: +351 218367100\nFax: +351 211545188\nEndereço eletrónico: lisboa.tacl@tribunais.org.pt\n\n28 - IDENTIFICAÇÃO DO(S) AUTOR(ES) DE ANÚNCIO\nNome: Joana Baptista\nCargo: Presidente do C.A.\n419456041",
    "nipc": "680015019",
    "distrito": "Lisboa",
    "concelho": "Oeiras",
    "freguesia": "Todas",
    "site": "www.simas-oeiras-amadora.pt",
    "email": "geral@simas-oeiras-amadora.pt",
    "designacao_contrato": "Concurso Público internacional, para a aquisição de serviços destinado à renovação do Licenciamento Microsoft Enterprise Agreement.",
    "descricao": "Concurso Público internacional, para a aquisição de serviços destinado à renovação do Licenciamento Microsoft Enterprise Agreement.",
    "preco_base": "658.405,00 EUR",
    "prazo_execucao": "1080 DIAS",
    "prazo_apresentacao_propostas": "20-09-2025 23:59",
    "fundos_eu": "Não",
    "plataforma_eletronica": "VORTAL",
    "url_procedimento": "https://community.vortal.biz/public/",
    "autor_nome": "Joana Baptista",
    "autor_cargo": "Presidente do C.A."
  },
  {
    "numero_procedimento": "N/A",
    "entidade": "Escola Secundária Vitorino Nemésio",
    "link": "https://diariodarepublica.pt/dr/detalhe/contrato-publico/22613-933044040",
    "detalhes_completos": "1 - IDENTIFICAÇÃO E CONTACTOS DA ENTIDADE ADJUDICANTE\nDesignação da entidade adjudicante: Escola Secundária Vitorino Nemésio\nNIPC: 672001764\nServiço/Órgão/Pessoa de contacto: Rosa Maria Ribeiro Pinto\nEndereço: Rua Comendador Francisco José Barcelos\nCódigo postal: 9760-587\nLocalidade: Praia da Vitória\nPaís: Portugal\nNUT III: PT200\nDistrito: Região Autónoma dos Açores\nConcelho: Praia da Vitória\nFreguesia: Freguesia de Praia da Vitória (Santa Cruz)\nTelefone: 295542470\nFax: 295542451\nEndereço da Entidade (URL): http://www.esvnemesio.pt/\nEndereço Eletrónico: cees.vinemesio@azores.gov.pt\neDelivery Gateway (URL): https://www.acingov.pt\nFunção da Organização: Adquirente\nNorma jurídica da Entidade Adjudicante: Organismo de direito público\nÁrea de atividade da Autoridade Adjudicante: Serviços públicos das administrações públicas\n\n2 - JORNAL OFICIAL DA UNIÃO EUROPEIA\nO procedimento a que este anúncio diz respeito também é publicitado no Jornal Oficial da União Europeia? Sim\n\n3 - AVISO\nModelo de Anúncio: Concurso público\nData de Envio do Anúncio: 21-08-2025\n\n5 - PROCESSO\nTipo de Procedimento: Concurso público\nPreço base do procedimento: Sim\nValor do preço base do procedimento: 343.088,94 EUR\nProcedimento com lotes? Sim\nNº Máx. de Lotes Autorizado: 6\nNúmero máximo de lotes que podem ser adjudicados a um concorrente: 6\n\n6 - OBJETO DO CONTRATO\nNúmero de referência interna: CPI/1/2025/A538-ESVN\nDesignação do contrato: AQUISIÇÃO DE MANUAIS ESCOLARES DIGITAIS PARA O ANO LETIVO DE 2025/2026\nDescrição: AQUISIÇÃO DE MANUAIS ESCOLARES DIGITAIS PARA O ANO LETIVO DE 2025/2026\n\nOpções: Não\nTipo de Contrato Principal: Aquisição de Bens Móveis\nTipo de Contrato: Aquisição de Bens Móveis\nClassificação CPV (Vocabulário Comum para os Contratos Públicos)\nObjeto principal\nVocabulário Principal: 22112000\nPreço base s/IVA: 343.088,94 EUR\nLotes: \nNº: LOT-0001\nDescrição do Lote: Licenças\nPreço base s/IVA: 50.428,98 EUR\nClassificação CPV (Vocabulário Comum para os Contratos Públicos)\nObjeto principal\nVocabulário Principal: 22112000\nNº: LOT-0002\nDescrição do Lote: Equipamento (Pack)\nPreço base s/IVA: 76.880,72 EUR\nClassificação CPV (Vocabulário Comum para os Contratos Públicos)\nObjeto principal\nVocabulário Principal: 22112000\nNº: LOT-0003\nDescrição do Lote: Licenças para alunos do 9.º ano de escolaridade\nPreço base s/IVA: 36.904,00 EUR\nClassificação CPV (Vocabulário Comum para os Contratos Públicos)\nObjeto principal\nVocabulário Principal: 22112000\nNº: LOT-0004\nDescrição do Lote: Licenças para alunos do 10.º ano de escolaridade\nPreço base s/IVA: 43.803,50 EUR\nClassificação CPV (Vocabulário Comum para os Contratos Públicos)\nObjeto principal\nVocabulário Principal: 22112000\nNº: LOT-0005\nDescrição do Lote: Equipamento (Pack) para alunos do 11.º ano de escolaridade\nPreço base s/IVA: 69.141,70 EUR\nClassificação CPV (Vocabulário Comum para os Contratos Públicos)\nObjeto principal\nVocabulário Principal: 22112000\nNº: LOT-0006\nDescrição do Lote: Equipamento (Pack) para alunos do 12.º ano de escolaridade\nPreço base s/IVA: 65.930,04 EUR\nClassificação CPV (Vocabulário Comum para os Contratos Públicos)\nObjeto principal\nVocabulário Principal: 22112000\n\n7 - INDICAÇÕES ADICIONAIS\nO contrato envolve aquisição conjunta (satisfação de várias entidades)? Não\nO contrato é adjudicado por uma central de compras? Não\n\n8 - TÉCNICAS\nO concurso destina-se à celebração de um acordo-quadro? Inexistência de acordo-quadro\nÉ utilizado um leilão eletrónico? Não\nÉ adotada uma fase de negociação? Não\nSistema de Aquisição Dinâmico: Inexistência de sistema de aquisição dinâmico\n\n9 - LOCAL DA EXECUÇÃO DO CONTRATO\nLOCAL DA EXECUÇÃO DO CONTRATO (PROCEDIMENTO)\nPaís: Portugal\nNUT III: PT200\nLocalidade: Praia da Vitória (Santa Cruz)\nDistrito: Região Autónoma dos Açores\nConcelho: Praia da Vitória\nFreguesia: Freguesia de Praia da Vitória (Santa Cruz)\nLOCAL DA EXECUÇÃO DO CONTRATO (LOTE)\nIdentificador do Lote: LOT-0001; LOT-0002; LOT-0003; LOT-0004; LOT-0005; LOT-0006\nPaís: Portugal\nNUT III: PT200\nLocalidade: Praia da Vitória (Santa Cruz)\nDistrito: Região Autónoma dos Açores\nConcelho: Praia da Vitória\nFreguesia: Freguesia de Praia da Vitória (Santa Cruz)\n\n10 - PRAZO DE EXECUÇÃO DO CONTRATO\nIdentificador do Lote: LOT-0001; LOT-0002; LOT-0003; LOT-0004; LOT-0005; LOT-0006\nPrazo de execução do contrato: 12 MESES\nPrevisão de renovações: Não\n\n11 - FUNDOS EU\nIdentificador do Lote: LOT-0001; LOT-0002; LOT-0003; LOT-0004; LOT-0005; LOT-0006\nTêm fundos EU? Não\n\n12 - DOCUMENTOS DE HABILITAÇÃO\nHabilitação para o exercício da atividade profissional: Não\n\n13 - CONDIÇÕES DE APRESENTAÇÃO\nPlataforma eletrónica utilizada pela entidade adjudicante: ACIN\nURL para Apresentação: https://www.acingov.pt\nAdmissibilidade da apresentação de propostas variantes: Não autorizado\nPrazo para apresentação das propostas: 19-09-2025 23:59\nPrazo durante o qual os concorrentes são obrigados a manter as respetivas propostas: 120 dias a contar do termo do prazo para a apresentação das propostas\nApresentação de Catálogo Eletrónico: Permitido\nIndicação de Subcontratação na Proposta: Inexistência de indicação de subcontratação\n\n14 - PRESTAÇÃO DE CAUÇÃO\nPrestação de caução: Sim\nPercentagem: 2%\nDescrição da Garantia Exigida: O valor da caução é de 2.00% do preço contratual.\n\n15 - FORNECIMENTO DAS PEÇAS DO CONCURSO, APRESENTAÇÃO DE PEDIDOS DE PARTICIPAÇÃO E APRESENTAÇÃO DAS PROPOSTAS\nLink para acesso às peças do concurso (URL): https://www.acingov.pt/acingovprod/2/zonaPublica/zona_publica_c/donwloadProcedurePiece/OTMyOTUz\n\n20 - OUTROS REQUISITOS\nIdentificador do Lote: LOT-0001; LOT-0002; LOT-0003; LOT-0004; LOT-0005; LOT-0006\nInformação sobre contratos reservados. Aplica-se a contratos reservados (54º-A)? Não\n\n21 - CRITÉRIO DE ADJUDICAÇÃO\nO Critério de adjudicação é diferenciado por lote? Não\nMultifator: Não\nMonofator:\nNome: Preço\n\n24 - CONDIÇÕES DO CONTRATO\nIdentificador do Lote: LOT-0001; LOT-0002; LOT-0003; LOT-0004; LOT-0005; LOT-0006\nFaturação Eletrónica: Permitido\nObrigação de Subcontratação:\nCódigo da Obrigação de Subcontratação: Não é aplicável nenhuma obrigação de subcontratação.\n\n25 - COMPRA PÚBLICA ESTRATÉGICA\nCompra Pública Estratégica: Inexistência de contratação pública estratégica\n\n26 - INFORMAÇÕES ADICIONAIS\nIdentificador do Lote: LOT-0001; LOT-0002; LOT-0003; LOT-0004; LOT-0005; LOT-0006\nContrato adequado para PME: Não\nCobertura ACP (Acordo dos Contratos Públicos da Organização Mundial do Comércio): Não\n\n27 - IDENTIFICAÇÃO E CONTACTOS DO ÓRGÃO DE RECURSOS ADMINISTRATIVOS\nDesignação: Secretaria Regional da Educação, Cultura e Desporto\nEndereço: Rua Carreira dos Cavalos\nCódigo postal: 9760-587\nLocalidade: Angra do Heroísmo\nTelefone: 295401100\nFax: 295542451\nEndereço eletrónico: srec.gabinete@azores.gov.pt\n\n28 - IDENTIFICAÇÃO DO(S) AUTOR(ES) DE ANÚNCIO\nNome: Ricardo Manuel Oliveira Prudêncio\nCargo: Assistente Técnico\n419450558",
    "nipc": "672001764",
    "distrito": "Região Autónoma dos Açores",
    "concelho": "Praia da Vitória",
    "freguesia": "Freguesia de Praia da Vitória (Santa Cruz)",
    "site": "http://www.esvnemesio.pt/",
    "email": "cees.vinemesio@azores.gov.pt",
    "designacao_contrato": "AQUISIÇÃO DE MANUAIS ESCOLARES DIGITAIS PARA O ANO LETIVO DE 2025/2026",
    "descricao": "AQUISIÇÃO DE MANUAIS ESCOLARES DIGITAIS PARA O ANO LETIVO DE 2025/2026",
    "preco_base": "343.088,94 EUR",
    "prazo_execucao": "12 MESES",
    "prazo_apresentacao_propostas": "19-09-2025 23:59",
    "fundos_eu": "Não",
    "plataforma_eletronica": "ACIN",
    "url_procedimento": "https://www.acingov.pt",
    "autor_nome": "Ricardo Manuel Oliveira Prudêncio",
    "autor_cargo": "Assistente Técnico"
  },
  {
    "numero_procedimento": "N/A",
    "entidade": "Agrupamento de Escolas n.º 2 de Beja",
    "link": "https://diariodarepublica.pt/dr/detalhe/contrato-publico/22615-933044041",
    "detalhes_completos": "1 - IDENTIFICAÇÃO E CONTACTOS DA ENTIDADE ADJUDICANTE\nDesignação da entidade adjudicante: Agrupamento de Escolas n.º 2 de Beja\nNIPC: 600071707\nEndereço: R. de S. João de Deus\nCódigo postal: 7800-478\nLocalidade: Beja\nPaís: Portugal\nNUT III: PT184\nDistrito: Beja\nConcelho: Beja\nFreguesia: Todas\nTelefone: 284313140\nFax: 284313141\nEndereço da Entidade (URL): https://www.ae2beja.pt\nEndereço Eletrónico: secretaria@ae2beja.pt\neDelivery Gateway (URL): https://community.vortal.biz/public/\nFunção da Organização: Adquirente\nNorma jurídica da Entidade Adjudicante: Organismo de direito público\nÁrea de atividade da Autoridade Adjudicante: Educação\n\n2 - JORNAL OFICIAL DA UNIÃO EUROPEIA\nO procedimento a que este anúncio diz respeito também é publicitado no Jornal Oficial da União Europeia? Sim\n\n3 - AVISO\nModelo de Anúncio: Concurso público\nData de Envio do Anúncio: 21-08-2025\n\n5 - PROCESSO\nTipo de Procedimento: Concurso público\nPreço base do procedimento: Sim\nValor do preço base do procedimento: 853.327,00 EUR\nProcedimento com lotes? Sim\nNº Máx. de Lotes Autorizado: 9\nNúmero máximo de lotes que podem ser adjudicados a um concorrente: 9\n\n6 - OBJETO DO CONTRATO\nNúmero de referência interna: CPI 01/2025\nDesignação do contrato: CTE Informática\nDescrição: Apetrechamento Salas de Informática\nOpções: Não\nTipo de Contrato Principal: Aquisição de Bens Móveis\nTipo de Contrato: Aquisição de Bens Móveis\nClassificação CPV (Vocabulário Comum para os Contratos Públicos)\nObjeto principal\nVocabulário Principal: 30200000\nPreço base s/IVA: 853.327,00 EUR\nLotes: \nNº: LOT-0001\nDescrição do Lote: Lote 1 - Auditório\nPreço base s/IVA: 134.761,38 EUR\nClassificação CPV (Vocabulário Comum para os Contratos Públicos)\nObjeto principal\nVocabulário Principal: 30200000\nNº: LOT-0002\nDescrição do Lote: Lote 2 - Software\nPreço base s/IVA: 32.110,05 EUR\nClassificação CPV (Vocabulário Comum para os Contratos Públicos)\nObjeto principal\nVocabulário Principal: 30200000\nNº: LOT-0003\nDescrição do Lote: Lote 3 - MotherBoard; Processador; Memórias; Discos; Placas; Caixa; Placas; Fontes; Outros; Kit Programação e Robótica e Aver DL 10 e Aver M5\nPreço base s/IVA: 134.011,36 EUR\nClassificação CPV (Vocabulário Comum para os Contratos Públicos)\nObjeto principal\nVocabulário Principal: 30200000\nNº: LOT-0004\nDescrição do Lote: Lote 4 - Surface; Kit -Eval-Kit 5G; Aver A30\nPreço base s/IVA: 124.601,42 EUR\nClassificação CPV (Vocabulário Comum para os Contratos Públicos)\nObjeto principal\nVocabulário Principal: 30200000\nNº: LOT-0005\nDescrição do Lote: Lote 5 - Computadores\nPreço base s/IVA: 120.068,76 EUR\nClassificação CPV (Vocabulário Comum para os Contratos Públicos)\nObjeto principal\nVocabulário Principal: 30200000\nNº: LOT-0006\nDescrição do Lote: Lote 6 - Monitores\nPreço base s/IVA: 29.461,32 EUR\nClassificação CPV (Vocabulário Comum para os Contratos Públicos)\nObjeto principal\nVocabulário Principal: 30200000\nNº: LOT-0007\nDescrição do Lote: Lote 7 - Servidor; Wacom; Plataforma; Impressora; Samsung Galaxy; Becam; Ipad; Storage; Discos Câmara; SandisK Extreme.\nPreço base s/IVA: 124.559,16 EUR\nClassificação CPV (Vocabulário Comum para os Contratos Públicos)\nObjeto principal\nVocabulário Principal: 30200000\nNº: LOT-0008\nDescrição do Lote: Lote 8 - Vários Equipamentos\nPreço base s/IVA: 129.985,07 EUR\nClassificação CPV (Vocabulário Comum para os Contratos Públicos)\nObjeto principal\nVocabulário Principal: 30200000\nNº: LOT-0009\nDescrição do Lote: Lote 9 - Ferramentas\nPreço base s/IVA: 23.768,48 EUR\nClassificação CPV (Vocabulário Comum para os Contratos Públicos)\nObjeto principal\nVocabulário Principal: 30200000\n\n7 - INDICAÇÕES ADICIONAIS\nO contrato envolve aquisição conjunta (satisfação de várias entidades)? Não\nO contrato é adjudicado por uma central de compras? Não\n\n8 - TÉCNICAS\nO concurso destina-se à celebração de um acordo-quadro? Inexistência de acordo-quadro\nÉ utilizado um leilão eletrónico? Não\nÉ adotada uma fase de negociação? Não\nSistema de Aquisição Dinâmico: Inexistência de sistema de aquisição dinâmico\n\n9 - LOCAL DA EXECUÇÃO DO CONTRATO\nLOCAL DA EXECUÇÃO DO CONTRATO (PROCEDIMENTO)\nPaís: Portugal\nNUT III: PT184\nLocalidade: Beja\nDistrito: Beja\nConcelho: Beja\nFreguesia: Todas\nLOCAL DA EXECUÇÃO DO CONTRATO (LOTE)\nIdentificador do Lote: LOT-0001; LOT-0002; LOT-0003; LOT-0004; LOT-0005; LOT-0006; LOT-0007; LOT-0008; LOT-0009\nPaís: Portugal\nNUT III: PT184\nLocalidade: Beja\nDistrito: Beja\nConcelho: Beja\nFreguesia: Todas\n\n10 - PRAZO DE EXECUÇÃO DO CONTRATO\nIdentificador do Lote: LOT-0001; LOT-0002; LOT-0003; LOT-0004; LOT-0005; LOT-0006; LOT-0007; LOT-0008; LOT-0009\nPrazo de execução do contrato: 60 DIAS\nPrevisão de renovações: Não\n\n11 - FUNDOS EU\nIdentificador do Lote: LOT-0001; LOT-0002; LOT-0003; LOT-0004; LOT-0005; LOT-0006; LOT-0007; LOT-0008; LOT-0009\nTêm fundos EU? Não\n\n12 - DOCUMENTOS DE HABILITAÇÃO\nHabilitação para o exercício da atividade profissional: Sim\nTipo: Outros\nDescrição - Outros: Comprovativos \nDescrição: Consultar art. 13º do Programa do Concurso\n\n13 - CONDIÇÕES DE APRESENTAÇÃO\nPlataforma eletrónica utilizada pela entidade adjudicante: VORTAL\nURL para Apresentação: https://community.vortal.biz/public/\nAdmissibilidade da apresentação de propostas variantes: Não autorizado\nPrazo para apresentação das propostas: 17-09-2025 23:59\nPrazo durante o qual os concorrentes são obrigados a manter as respetivas propostas: 66 dias a contar do termo do prazo para a apresentação das propostas\nApresentação de Catálogo Eletrónico: Não autorizado\nIndicação de Subcontratação na Proposta: Inexistência de indicação de subcontratação\n\n14 - PRESTAÇÃO DE CAUÇÃO\nPrestação de caução: Não\n\n15 - FORNECIMENTO DAS PEÇAS DO CONCURSO, APRESENTAÇÃO DE PEDIDOS DE PARTICIPAÇÃO E APRESENTAÇÃO DAS PROPOSTAS\nLink para acesso às peças do concurso (URL): https://community.vortal.biz/Public/public-tender-documents/d3FrRkhGM1l2TERuQkxQM2daSm5UcTM5REUxRlVmU1VyT012K2FHQ1dwU1crZXVjZXpicWpBcjhOUjYrL3ZpRzE4NmNyWVF6R2hHU29yRWtKZFpFblE9PUtNWlNC\n\n20 - OUTROS REQUISITOS\nIdentificador do Lote: LOT-0001; LOT-0002; LOT-0003; LOT-0004; LOT-0005; LOT-0006; LOT-0007; LOT-0008; LOT-0009\nInformação sobre contratos reservados. Aplica-se a contratos reservados (54º-A)? Não\n\n21 - CRITÉRIO DE ADJUDICAÇÃO\nO Critério de adjudicação é diferenciado por lote? Não\nMultifator: Não\nMonofator:\nNome: Preço\n\n24 - CONDIÇÕES DO CONTRATO\nIdentificador do Lote: LOT-0001; LOT-0002; LOT-0003; LOT-0004; LOT-0005; LOT-0006; LOT-0007; LOT-0008; LOT-0009\nFaturação Eletrónica: Permitido\nObrigação de Subcontratação:\nCódigo da Obrigação de Subcontratação: Não é aplicável nenhuma obrigação de subcontratação.\n\n25 - COMPRA PÚBLICA ESTRATÉGICA\nCompra Pública Estratégica: Inexistência de contratação pública estratégica\n\n26 - INFORMAÇÕES ADICIONAIS\nIdentificador do Lote: LOT-0001; LOT-0002; LOT-0003; LOT-0004; LOT-0005; LOT-0006; LOT-0007; LOT-0008; LOT-0009\nContrato adequado para PME: Sim\nCobertura ACP (Acordo dos Contratos Públicos da Organização Mundial do Comércio): Não\n\n27 - IDENTIFICAÇÃO E CONTACTOS DO ÓRGÃO DE RECURSOS ADMINISTRATIVOS\nDesignação: Conselho Administrativo\nEndereço: Rua São João de Deus\nCódigo postal: 7800-478\nLocalidade: Beja\nTelefone: +351 284313140\nFax: +351 284313140\nEndereço eletrónico: concursocompraspublicas@gmail.com\n\n28 - IDENTIFICAÇÃO DO(S) AUTOR(ES) DE ANÚNCIO\nNome: Maria de Jesus Vidinha Vieira Silva Dionisio\nCargo: Coordenadora\n419443527",
    "nipc": "600071707",
    "distrito": "Beja",
    "concelho": "Beja",
    "freguesia": "Todas",
    "site": "https://www.ae2beja.pt",
    "email": "secretaria@ae2beja.pt",
    "designacao_contrato": "CTE Informática",
    "descricao": "Apetrechamento Salas de Informática",
    "preco_base": "853.327,00 EUR",
    "prazo_execucao": "60 DIAS",
    "prazo_apresentacao_propostas": "17-09-2025 23:59",
    "fundos_eu": "Não",
    "plataforma_eletronica": "VORTAL",
    "url_procedimento": "https://community.vortal.biz/public/",
    "autor_nome": "Maria de Jesus Vidinha Vieira Silva Dionisio",
    "autor_cargo": "Coordenadora"
  },
  {
    "numero_procedimento": "N/A",
    "entidade": "EMAC - Empresa Municipal de Ambiente de Cascais, EM, SA",
    "link": "https://diariodarepublica.pt/dr/detalhe/contrato-publico/22616-933044042",
    "detalhes_completos": "1 - IDENTIFICAÇÃO E CONTACTOS DA ENTIDADE ADJUDICANTE\nDesignação da entidade adjudicante: EMAC - Empresa Municipal de Ambiente de Cascais, EM, SA\nNIPC: 507396081\nServiço/Órgão/Pessoa de contacto: Departamento Financeiro\nEndereço: Complexo Multiserviços, Estrada de Manique, nº 1830, Alcoitão\nCódigo postal: 2645-138\nLocalidade: Alcabideche\nPaís: Portugal\nNUT III: PT170\nDistrito: Lisboa\nConcelho: Cascais\nFreguesia: Freguesia de Alcabideche\nTelefone: +351214604249\nFax: +351214604249\nEndereço da Entidade (URL): http://www.cascaisambiente.pt/\nEndereço Eletrónico: geral@cascaisambiente.pt\neDelivery Gateway (URL): https://www.acingov.pt\nFunção da Organização: Adquirente\nNorma jurídica da Entidade Adjudicante: Empresa pública, controlada por uma autoridade local\nÁrea de atividade da Autoridade Adjudicante: Serviços públicos das administrações públicas\n\n2 - JORNAL OFICIAL DA UNIÃO EUROPEIA\nO procedimento a que este anúncio diz respeito também é publicitado no Jornal Oficial da União Europeia? Sim\n\n3 - AVISO\nModelo de Anúncio: Concurso público\nData de Envio do Anúncio: 21-08-2025\n\n5 - PROCESSO\nTipo de Procedimento: Concurso público\nPreço base do procedimento: Sim\nValor do preço base do procedimento: 821.000,00 EUR\nProcedimento com lotes? Sim\nNº Máx. de Lotes Autorizado: 3\nNúmero máximo de lotes que podem ser adjudicados a um concorrente: 3\n\n6 - OBJETO DO CONTRATO\nNúmero de referência interna: CPUB008DTEDGA2025\nDesignação do contrato: CPUB008DTEDGA2025 - Aquisição de viaturas de limpeza urbana.\nDescrição: CPUB008DTEDGA2025 - Aquisição de viaturas de limpeza urbana. \nOpções: Não\nTipo de Contrato Principal: Aquisição de Bens Móveis\nTipo de Contrato: Aquisição de Bens Móveis\nClassificação CPV (Vocabulário Comum para os Contratos Públicos)\nObjeto principal\nVocabulário Principal: 34144900\nPreço base s/IVA: 619.000,00 EUR\nObjeto Complementar\nVocabulário Principal: 34100000\nPreço base s/IVA: 202.000,00 EUR\nLotes: \nNº: LOT-0001\nDescrição do Lote: Aquisição de viaturas de limpeza urbana - Varredora 100% Elétrica 5m3\nPreço base s/IVA: 430.000,00 EUR\nClassificação CPV (Vocabulário Comum para os Contratos Públicos)\nObjeto principal\nVocabulário Principal: 34144900\nNº: LOT-0002\nDescrição do Lote: Aquisição de viaturas de limpeza urbana - Varredora a gasóleo 4m3\nPreço base s/IVA: 202.000,00 EUR\nClassificação CPV (Vocabulário Comum para os Contratos Públicos)\nObjeto principal\nVocabulário Principal: 34100000\nNº: LOT-0003\nDescrição do Lote: Aquisição de viaturas de limpeza urbana - Lavadora 100% Elétrica com capacidade de 2000 litros\nPreço base s/IVA: 189.000,00 EUR\nClassificação CPV (Vocabulário Comum para os Contratos Públicos)\nObjeto principal\nVocabulário Principal: 34144900\n\n7 - INDICAÇÕES ADICIONAIS\nO contrato envolve aquisição conjunta (satisfação de várias entidades)? Não\nO contrato é adjudicado por uma central de compras? Não\n\n8 - TÉCNICAS\nO concurso destina-se à celebração de um acordo-quadro? Inexistência de acordo-quadro\nÉ utilizado um leilão eletrónico? Não\nÉ adotada uma fase de negociação? Não\nSistema de Aquisição Dinâmico: Inexistência de sistema de aquisição dinâmico\n\n9 - LOCAL DA EXECUÇÃO DO CONTRATO\nLOCAL DA EXECUÇÃO DO CONTRATO (PROCEDIMENTO)\nPaís: Portugal\nNUT III: PT170\nLocalidade: Freguesia de Alcabideche\nDistrito: Lisboa\nConcelho: Cascais\nFreguesia: Freguesia de Alcabideche\nLOCAL DA EXECUÇÃO DO CONTRATO (LOTE)\nIdentificador do Lote: LOT-0001; LOT-0002; LOT-0003\nPaís: Portugal\nNUT III: PT170\nLocalidade: Freguesia de Alcabideche\nDistrito: Lisboa\nConcelho: Cascais\nFreguesia: Freguesia de Alcabideche\n\n10 - PRAZO DE EXECUÇÃO DO CONTRATO\nIdentificador do Lote: LOT-0001; LOT-0002\nPrazo de execução do contrato: 30 DIAS\nPrevisão de renovações: Não\nIdentificador do Lote: LOT-0003\nPrazo de execução do contrato: 60 DIAS\nPrevisão de renovações: Não\n\n11 - FUNDOS EU\nIdentificador do Lote: LOT-0001; LOT-0002; LOT-0003\nTêm fundos EU? Não\n\n12 - DOCUMENTOS DE HABILITAÇÃO\nHabilitação para o exercício da atividade profissional: Não\n\n13 - CONDIÇÕES DE APRESENTAÇÃO\nPlataforma eletrónica utilizada pela entidade adjudicante: ACIN\nURL para Apresentação: https://www.acingov.pt\nAdmissibilidade da apresentação de propostas variantes: Não autorizado\nPrazo para apresentação das propostas: 20-09-2025 23:59\nPrazo durante o qual os concorrentes são obrigados a manter as respetivas propostas: 120 dias a contar do termo do prazo para a apresentação das propostas\nApresentação de Catálogo Eletrónico: Não autorizado\nIndicação de Subcontratação na Proposta: Inexistência de indicação de subcontratação\n\n14 - PRESTAÇÃO DE CAUÇÃO\nPrestação de caução: Não\n\n15 - FORNECIMENTO DAS PEÇAS DO CONCURSO, APRESENTAÇÃO DE PEDIDOS DE PARTICIPAÇÃO E APRESENTAÇÃO DAS PROPOSTAS\nLink para acesso às peças do concurso (URL): https://www.acingov.pt/acingovprod/2/zonaPublica/zona_publica_c/donwloadProcedurePiece/OTcwNzQz\n\n20 - OUTROS REQUISITOS\nIdentificador do Lote: LOT-0001; LOT-0002; LOT-0003\nInformação sobre contratos reservados. Aplica-se a contratos reservados (54º-A)? Não\n\n21 - CRITÉRIO DE ADJUDICAÇÃO\nO Critério de adjudicação é diferenciado por lote? Não\nMultifator: Não\nMonofator:\nNome: Preço\n\n24 - CONDIÇÕES DO CONTRATO\nIdentificador do Lote: LOT-0001; LOT-0002; LOT-0003\nFaturação Eletrónica: Necessário\nObrigação de Subcontratação:\nCódigo da Obrigação de Subcontratação: Não é aplicável nenhuma obrigação de subcontratação.\n\n25 - COMPRA PÚBLICA ESTRATÉGICA\nCompra Pública Estratégica: Inexistência de contratação pública estratégica\n\n26 - INFORMAÇÕES ADICIONAIS\nIdentificador do Lote: LOT-0002; LOT-0003\nContrato adequado para PME: Sim\nCobertura ACP (Acordo dos Contratos Públicos da Organização Mundial do Comércio): Não\nIdentificador do Lote: LOT-0001\nContrato adequado para PME: Sim\nCobertura ACP (Acordo dos Contratos Públicos da Organização Mundial do Comércio): Sim\n\n27 - IDENTIFICAÇÃO E CONTACTOS DO ÓRGÃO DE RECURSOS ADMINISTRATIVOS\nDesignação: EMAC - Empresa Municipal de Ambiente de Cascais, EM, SA\nEndereço: Complexo Multiserviços, Estrada de Manique, nº 1830, Alcoitão,\nCódigo postal: 2645-138\nLocalidade: Alcabideche\nTelefone: 214604249\nFax: 351214604249\nEndereço eletrónico: geral@cascaisambiente.pt\nPrazo de interposição do recurso: 30 dias\n\n28 - IDENTIFICAÇÃO DO(S) AUTOR(ES) DE ANÚNCIO\nNome: Ana Maria de Bessa e Meneses Machado\nCargo: Unidade de Compras e Contratação\n419457013",
    "nipc": "507396081",
    "distrito": "Lisboa",
    "concelho": "Cascais",
    "freguesia": "Freguesia de Alcabideche",
    "site": "http://www.cascaisambiente.pt/",
    "email": "geral@cascaisambiente.pt",
    "designacao_contrato": "CPUB008DTEDGA2025 - Aquisição de viaturas de limpeza urbana.",
    "descricao": "CPUB008DTEDGA2025 - Aquisição de viaturas de limpeza urbana.",
    "preco_base": "619.000,00 EUR",
    "prazo_execucao": "30 DIAS",
    "prazo_apresentacao_propostas": "20-09-2025 23:59",
    "fundos_eu": "Não",
    "plataforma_eletronica": "ACIN",
    "url_procedimento": "https://www.acingov.pt",
    "autor_nome": "Ana Maria de Bessa e Meneses Machado",
    "autor_cargo": "Unidade de Compras e Contratação"
  },
  {
    "numero_procedimento": "N/A",
    "entidade": "SPMS- Serviços Partilhados do M. da Saúde, E.P.E.",
    "link": "https://diariodarepublica.pt/dr/detalhe/contrato-publico/22618-933044043",
    "detalhes_completos": "1 - IDENTIFICAÇÃO E CONTACTOS DA ENTIDADE ADJUDICANTE\nDesignação da entidade adjudicante: SPMS- Serviços Partilhados do M. da Saúde, E.P.E.\nNIPC: 509540716\nEndereço: Avenida da República 61\nCódigo postal: 1050-189\nLocalidade: Lisboa\nPaís: Portugal\nNUT III: PT170\nDistrito: Lisboa\nConcelho: Lisboa\nFreguesia: Todas\nTelefone: 211545600\nFax: 211545649\nEndereço da Entidade (URL): www.spms.min-saude.pt/\nEndereço Eletrónico: contratacao@spms.min-saude.pt\neDelivery Gateway (URL): https://community.vortal.biz/public/\nFunção da Organização: Adquirente\nNorma jurídica da Entidade Adjudicante: Empresa pública\nÁrea de atividade da Autoridade Adjudicante: Saúde\n\n2 - JORNAL OFICIAL DA UNIÃO EUROPEIA\nO procedimento a que este anúncio diz respeito também é publicitado no Jornal Oficial da União Europeia? Sim\n\n3 - AVISO\nModelo de Anúncio: Concurso público\nData de Envio do Anúncio: 21-08-2025\n\n5 - PROCESSO\nTipo de Procedimento: Concurso público\nPreço base do procedimento: Sim\nValor do preço base do procedimento: 502.000,00 EUR\nProcedimento com lotes? Sim\nNº Máx. de Lotes Autorizado: 4\nNúmero máximo de lotes que podem ser adjudicados a um concorrente: 4\n\n6 - OBJETO DO CONTRATO\nNúmero de referência interna: 1540 /2025\nDesignação do contrato: 1540/2025 - Concurso público com publicação no jornal oficial da união europeia para aquisição de Instrumental Cirúrgico para Bloco Operatório para o Hospital de Proximidade de Sintra\nDescrição: 1540/2025 - Concurso público com publicação no jornal oficial da união europeia para aquisição de Instrumental Cirúrgico para Bloco Operatório para o Hospital de Proximidade de Sintra\nOpções: Não\nTipo de Contrato Principal: Aquisição de Bens Móveis\nTipo de Contrato: Aquisição de Bens Móveis\nClassificação CPV (Vocabulário Comum para os Contratos Públicos)\nObjeto principal\nVocabulário Principal: 33100000\nPreço base s/IVA: 502.000,00 EUR\nLotes: \nNº: LOT-0001\nDescrição do Lote: CAIXAS INSTRUMENTAL CIRÚRGICO ORL\nPreço base s/IVA: 137.000,00 EUR\nClassificação CPV (Vocabulário Comum para os Contratos Públicos)\nObjeto principal\nVocabulário Principal: 33100000\nNº: LOT-0002\nDescrição do Lote: CAIXAS INSTRUMENTAL CIRÚRGICO ORTOPEDIA\nPreço base s/IVA: 67.000,00 EUR\nClassificação CPV (Vocabulário Comum para os Contratos Públicos)\nObjeto principal\nVocabulário Principal: 33100000\nNº: LOT-0003\nDescrição do Lote: CAIXAS INSTRUMENTAL CIRÚRGICO VÁRIAS ESPECIALIDADES\nPreço base s/IVA: 275.000,00 EUR\nClassificação CPV (Vocabulário Comum para os Contratos Públicos)\nObjeto principal\nVocabulário Principal: 33100000\nNº: LOT-0004\nDescrição do Lote: CAIXAS CPR\nPreço base s/IVA: 23.000,00 EUR\nClassificação CPV (Vocabulário Comum para os Contratos Públicos)\nObjeto principal\nVocabulário Principal: 33100000\n\n7 - INDICAÇÕES ADICIONAIS\nO contrato envolve aquisição conjunta (satisfação de várias entidades)? Sim\nA entidade adjudicante atua como compradora no procedimento? Não\nNIPC: 503035416\nDesignação da entidade adjudicante: Unidade Local de Saude Amadora/Sintra, E.P.E.\nUnidades Orgânicas: Serviço de compras\nValor: 502000\nO contrato é adjudicado por uma central de compras? Sim\n\n8 - TÉCNICAS\nO concurso destina-se à celebração de um acordo-quadro? Inexistência de acordo-quadro\nÉ utilizado um leilão eletrónico? Não\nÉ adotada uma fase de negociação? Não\nSistema de Aquisição Dinâmico: Inexistência de sistema de aquisição dinâmico\n\n9 - LOCAL DA EXECUÇÃO DO CONTRATO\nLOCAL DA EXECUÇÃO DO CONTRATO (PROCEDIMENTO)\nPaís: Portugal\nNUT III: PT170\nLocalidade: Lisboa\nDistrito: Lisboa\nConcelho: Sintra\nFreguesia: Todas\nLOCAL DA EXECUÇÃO DO CONTRATO (LOTE)\nIdentificador do Lote: LOT-0001; LOT-0002; LOT-0003; LOT-0004\nPaís: Portugal\nNUT III: PT170\nLocalidade: Lisboa\nDistrito: Lisboa\nConcelho: Sintra\nFreguesia: Todas\n\n10 - PRAZO DE EXECUÇÃO DO CONTRATO\nIdentificador do Lote: LOT-0001; LOT-0002; LOT-0003; LOT-0004\nPrazo de execução do contrato: 4 MESES\nPrevisão de renovações: Não\n\n11 - FUNDOS EU\nIdentificador do Lote: LOT-0001; LOT-0002; LOT-0003; LOT-0004\nTêm fundos EU? Não\n\n12 - DOCUMENTOS DE HABILITAÇÃO\nHabilitação para o exercício da atividade profissional: Não\n\n13 - CONDIÇÕES DE APRESENTAÇÃO\nPlataforma eletrónica utilizada pela entidade adjudicante: VORTAL\nURL para Apresentação: https://community.vortal.biz/public/\nAdmissibilidade da apresentação de propostas variantes: Não autorizado\nPrazo para apresentação das propostas: 22-09-2025 18:00\nPrazo durante o qual os concorrentes são obrigados a manter as respetivas propostas: 180 dias a contar do termo do prazo para a apresentação das propostas\nApresentação de Catálogo Eletrónico: Permitido\nIndicação de Subcontratação na Proposta: Inexistência de indicação de subcontratação\n\n14 - PRESTAÇÃO DE CAUÇÃO\nPrestação de caução: Não\n\n15 - FORNECIMENTO DAS PEÇAS DO CONCURSO, APRESENTAÇÃO DE PEDIDOS DE PARTICIPAÇÃO E APRESENTAÇÃO DAS PROPOSTAS\nLink para acesso às peças do concurso (URL): https://community.vortal.biz/Public/public-tender-documents/Z0VqU2dZa29taTZmem1rQUJMTlROYVBLQnNsaUg4OWY1YzFvQ1lmM2xrTEUxTmFlZnI2YndCaFZVb1lVVVY3OVNJMGJGdlhOUEZPeWcwVUNTdVV4amc9PTREdnJl\n\n20 - OUTROS REQUISITOS\nIdentificador do Lote: LOT-0001; LOT-0002; LOT-0003; LOT-0004\nInformação sobre contratos reservados. Aplica-se a contratos reservados (54º-A)? Não\n\n21 - CRITÉRIO DE ADJUDICAÇÃO\nO Critério de adjudicação é diferenciado por lote? Não\nMultifator: Sim\nFator: \nNome: Preço\nPonderação: 90%\nSubfatores: Não\nFator: \nNome: Qualidade\nPonderação: 10%\nSubfatores: Não\n\n24 - CONDIÇÕES DO CONTRATO\nIdentificador do Lote: LOT-0001; LOT-0002; LOT-0003; LOT-0004\nFaturação Eletrónica: Permitido\nObrigação de Subcontratação:\nCódigo da Obrigação de Subcontratação: Não é aplicável nenhuma obrigação de subcontratação.\n\n25 - COMPRA PÚBLICA ESTRATÉGICA\nCompra Pública Estratégica: Inexistência de contratação pública estratégica\n\n26 - INFORMAÇÕES ADICIONAIS\nIdentificador do Lote: LOT-0001; LOT-0002; LOT-0003; LOT-0004\nContrato adequado para PME: Sim\nCobertura ACP (Acordo dos Contratos Públicos da Organização Mundial do Comércio): Não\n\n27 - IDENTIFICAÇÃO E CONTACTOS DO ÓRGÃO DE RECURSOS ADMINISTRATIVOS\nDesignação: Serviços Partilhados do Ministério da Saúde\nEndereço: Avenida da República n.º 61\nCódigo postal: 1050-189\nLocalidade: Lisboa\nTelefone: +351 211545600\nFax: +351 211545649\nEndereço eletrónico: catalogo@spms.min-saude.pt\n\n28 - IDENTIFICAÇÃO DO(S) AUTOR(ES) DE ANÚNCIO\nNome: Joana Lopes\nCargo: Técnica Superior\n419457913",
    "nipc": "509540716",
    "distrito": "Lisboa",
    "concelho": "Lisboa",
    "freguesia": "Todas",
    "site": "www.spms.min-saude.pt/",
    "email": "contratacao@spms.min-saude.pt",
    "designacao_contrato": "1540/2025 - Concurso público com publicação no jornal oficial da união europeia para aquisição de Instrumental Cirúrgico para Bloco Operatório para o Hospital de Proximidade de Sintra",
    "descricao": "1540/2025 - Concurso público com publicação no jornal oficial da união europeia para aquisição de Instrumental Cirúrgico para Bloco Operatório para o Hospital de Proximidade de Sintra",
    "preco_base": "502.000,00 EUR",
    "prazo_execucao": "4 MESES",
    "prazo_apresentacao_propostas": "22-09-2025 18:00",
    "fundos_eu": "Não",
    "plataforma_eletronica": "VORTAL",
    "url_procedimento": "https://community.vortal.biz/public/",
    "autor_nome": "Joana Lopes",
    "autor_cargo": "Técnica Superior"
  },
  {
    "numero_procedimento": "N/A",
    "entidade": "Unidade Local de Saúde de Viseu Dão-Lafões, E.P.E.",
    "link": "https://diariodarepublica.pt/dr/detalhe/contrato-publico/22621-933044044",
    "detalhes_completos": "Alteração do Anúncio de procedimento n.º 21984/2025, de 2025-08-14, com o ID 419426169\n\n1 - IDENTIFICAÇÃO E CONTACTOS DA ENTIDADE ADJUDICANTE\nDesignação da entidade adjudicante: Unidade Local de Saúde de Viseu Dão-Lafões, E.P.E.\nNIPC: 509822940\nEndereço: Av. Rei D. Duarte\nCódigo postal: 3504-509\nLocalidade: Viseu\nPaís: Portugal\nNUT III: PT16G\nDistrito: Viseu\nConcelho: Viseu\nFreguesia: Todas\nTelefone: 232420589\nFax: 232421217\nEndereço da Entidade (URL): http://www.hstviseu.min-saude.pt/\nEndereço Eletrónico: aprovisionamento.diretor@hstviseu.min-saude.pt\neDelivery Gateway (URL): https://community.vortal.biz/public/\nFunção da Organização: Adquirente\nNorma jurídica da Entidade Adjudicante: Empresa pública\nÁrea de atividade da Autoridade Adjudicante: Saúde\n\n2 - JORNAL OFICIAL DA UNIÃO EUROPEIA\nO procedimento a que este anúncio diz respeito também é publicitado no Jornal Oficial da União Europeia? Sim\n\n3 - AVISO\nModelo de Anúncio: Concurso público\nData de Envio do Anúncio: 22-08-2025\n\n5 - PROCESSO\nTipo de Procedimento: Concurso público\nPreço base do procedimento: Sim\nValor do preço base do procedimento: 6.200.000,00 EUR\nProcedimento com lotes? Não\n\n6 - OBJETO DO CONTRATO\nNúmero de referência interna: 30/07072/2025\nDesignação do contrato: PRR – EMPREITADA DE CONSTRUÇÃO DE EDIFÍCIO CENTRAIS TÉCNICAS FASE 1 NO HOSPITAL SÃO TEOTÓNIO-VISEU\nDescrição: PRR – EMPREITADA DE CONSTRUÇÃO DE EDIFÍCIO CENTRAIS TÉCNICAS FASE 1 NO HOSPITAL SÃO TEOTÓNIO-VISEU\nOpções: Não\nTipo de Contrato Principal: Empreitada de Obras Públicas\nTipo de Contrato: Empreitada de Obras Públicas\nClassificação CPV (Vocabulário Comum para os Contratos Públicos)\nObjeto principal\nVocabulário Principal: 45215100\nPreço base s/IVA: 6.200.000,00 EUR\n\n7 - INDICAÇÕES ADICIONAIS\nO contrato envolve aquisição conjunta (satisfação de várias entidades)? Não\nO contrato é adjudicado por uma central de compras? Não\n\n8 - TÉCNICAS\nO concurso destina-se à celebração de um acordo-quadro? Inexistência de acordo-quadro\nÉ utilizado um leilão eletrónico? Não\nÉ adotada uma fase de negociação? Não\nSistema de Aquisição Dinâmico: Inexistência de sistema de aquisição dinâmico\n\n9 - LOCAL DA EXECUÇÃO DO CONTRATO\nLOCAL DA EXECUÇÃO DO CONTRATO (PROCEDIMENTO)\nPaís: Portugal\nNUT III: PT16G\nLocalidade: Viseu\nDistrito: Viseu\nConcelho: Viseu\nFreguesia: Freguesia de Viseu\n\n10 - PRAZO DE EXECUÇÃO DO CONTRATO\nPrazo de execução do contrato: 270 DIAS\nPrevisão de renovações: Não\n\n11 - FUNDOS EU\nTêm fundos EU? Sim\n\n12 - DOCUMENTOS DE HABILITAÇÃO\nHabilitação para o exercício da atividade profissional: Não\n\n13 - CONDIÇÕES DE APRESENTAÇÃO\nPlataforma eletrónica utilizada pela entidade adjudicante: VORTAL\nURL para Apresentação: https://community.vortal.biz/public/\nAdmissibilidade da apresentação de propostas variantes: Não autorizado\nPrazo para apresentação das propostas: 01-09-2025 17:30\nPrazo durante o qual os concorrentes são obrigados a manter as respetivas propostas: 120 dias a contar do termo do prazo para a apresentação das propostas\nApresentação de Catálogo Eletrónico: Permitido\nIndicação de Subcontratação na Proposta: Inexistência de indicação de subcontratação\n\n14 - PRESTAÇÃO DE CAUÇÃO\nPrestação de caução: Sim\nPercentagem: 5%\nDescrição da Garantia Exigida: Conforme indicado no artigo 41.º do Programa do Concurso.\n\n15 - FORNECIMENTO DAS PEÇAS DO CONCURSO, APRESENTAÇÃO DE PEDIDOS DE PARTICIPAÇÃO E APRESENTAÇÃO DAS PROPOSTAS\nLink para acesso às peças do concurso (URL): https://community.vortal.biz/Public/public-tender-documents/QkMyMnM1L0x3dEtVR0R6ZW1LMU1NSGFzZ2x4WXJ3NHBVdEIwdHNKQ0I1TXowUFZRbEZLNk9qRkp5Nzc5dThsMjRST1ZQM2crVjAwWVJ3VFZPWmQ5OEE9PWEqa0RH\n\n20 - OUTROS REQUISITOS\nInformação sobre contratos reservados. Aplica-se a contratos reservados (54º-A)? Não\n\n21 - CRITÉRIO DE ADJUDICAÇÃO\nMultifator: Sim\nFator: \nNome: Preço\nPonderação: 75%\nSubfatores: Não\nFator: \nNome: Outros\nOutro Nome: Prazo de Execução Proposto\nPonderação: 25%\nSubfatores: Não\n\n24 - CONDIÇÕES DO CONTRATO\nFaturação Eletrónica: Permitido\nObrigação de Subcontratação:\nCódigo da Obrigação de Subcontratação: Não é aplicável nenhuma obrigação de subcontratação.\n\n25 - COMPRA PÚBLICA ESTRATÉGICA\nCompra Pública Estratégica: Inexistência de contratação pública estratégica\n\n26 - INFORMAÇÕES ADICIONAIS\nContrato adequado para PME: Sim\nCobertura ACP (Acordo dos Contratos Públicos da Organização Mundial do Comércio): Não\n\n27 - IDENTIFICAÇÃO E CONTACTOS DO ÓRGÃO DE RECURSOS ADMINISTRATIVOS\nDesignação: CONSELHO DE ADMINISTRAÇÃO\nEndereço: VISEU\nCódigo postal: 3504-509\nLocalidade: Viseu\nTelefone: +351 232420589\nFax: +351 232421217\nEndereço eletrónico: sec.presidente@ulsvdl.min-saude.pt\n\n28 - IDENTIFICAÇÃO DO(S) AUTOR(ES) DE ANÚNCIO\nNome: Fátima Cruz\nCargo: Coordenadora\n\n29 - ALTERAÇÃO\nMotivo da Alteração: Correção pelo editor\nIdentificador da Versão do Anúncio a Alterar: 417a71de-b9a3-4540-a022-eb3baea2f44c-01\nIdentificador das Secções Alteradas do Anúncio Anterior: Acesso às peças do concurso, pedidos de participação e apresentação das propostas\nDescrição das Alterações: Prorrogação do prazo de apresentação de propostas\nAlteração dos Documentos do Concurso: Não\n419457192",
    "nipc": "509822940",
    "distrito": "Viseu",
    "concelho": "Viseu",
    "freguesia": "Todas",
    "site": "http://www.hstviseu.min-saude.pt/",
    "email": "aprovisionamento.diretor@hstviseu.min-saude.pt",
    "designacao_contrato": "PRR – EMPREITADA DE CONSTRUÇÃO DE EDIFÍCIO CENTRAIS TÉCNICAS FASE 1 NO HOSPITAL SÃO TEOTÓNIO-VISEU",
    "descricao": "PRR – EMPREITADA DE CONSTRUÇÃO DE EDIFÍCIO CENTRAIS TÉCNICAS FASE 1 NO HOSPITAL SÃO TEOTÓNIO-VISEU",
    "preco_base": "6.200.000,00 EUR",
    "prazo_execucao": "270 DIAS",
    "prazo_apresentacao_propostas": "01-09-2025 17:30",
    "fundos_eu": "Sim",
    "plataforma_eletronica": "VORTAL",
    "url_procedimento": "https://community.vortal.biz/public/",
    "autor_nome": "Fátima Cruz",
    "autor_cargo": "Coordenadora"
  },
  {
    "numero_procedimento": "N/A",
    "entidade": "Instituto Português de Oncologia de Coimbra - Francisco Gentil E.P.E.",
    "link": "https://diariodarepublica.pt/dr/detalhe/contrato-publico/22626-933044045",
    "detalhes_completos": "1 - IDENTIFICAÇÃO E CONTACTOS DA ENTIDADE ADJUDICANTE\nDesignação da entidade adjudicante: Instituto Português de Oncologia de Coimbra - Francisco Gentil E.P.E.\nNIPC: 506361438\nEndereço: Av Bissaya Barreto, 98\nCódigo postal: 3000-075\nLocalidade: Coimbra\nPaís: Portugal\nNUT III: PT16E\nDistrito: Coimbra\nConcelho: Coimbra\nFreguesia: Freguesia de Santo António dos Olivais\nTelefone: 239400200\nFax: 239484317\nEndereço da Entidade (URL): www.ipocoimbra.min-saude.pt\nEndereço Eletrónico: aprovc@ipocoimbra.min-saude.pt\nFunção da Organização: Adquirente\nNorma jurídica da Entidade Adjudicante: Organismo de direito público\nÁrea de atividade da Autoridade Adjudicante: Saúde\n\n2 - JORNAL OFICIAL DA UNIÃO EUROPEIA\nO procedimento a que este anúncio diz respeito também é publicitado no Jornal Oficial da União Europeia? Sim\n\n3 - AVISO\nModelo de Anúncio: Concurso público\nData de Envio do Anúncio: 22-08-2025\n\n5 - PROCESSO\nTipo de Procedimento: Concurso público\nPreço base do procedimento: Sim\nValor do preço base do procedimento: 3.612.268,16 EUR\nProcedimento com lotes? Sim\nNº Máx. de Lotes Autorizado: 2\nNúmero máximo de lotes que podem ser adjudicados a um concorrente: 2\n\n6 - OBJETO DO CONTRATO\nNúmero de referência interna: .995AS25\nDesignação do contrato: EQUIPAMENTO MÉDICO PESADO IMAGIOLOGIA ¿ RM E TC II(PRR)\nDescrição: EQUIPAMENTO MÉDICO PESADO IMAGIOLOGIA ¿ RM E TC II(PRR)\nOpções: Não\nTipo de Contrato Principal: Aquisição de Bens Móveis\nTipo de Contrato: Aquisição de Bens Móveis\nClassificação CPV (Vocabulário Comum para os Contratos Públicos)\nObjeto principal\nVocabulário Principal: 33110000\nPreço base s/IVA: 3.612.268,16 EUR\nLotes: \nNº: LOT-0001\nDescrição do Lote: Um equipamento de Tomografia Computorizada (TC) Volumétrico Espectral, Multicorte dedicado à Radiologia de Diagnóstico e Intervenção com os respetivos acessórios e elementos complementares\nPreço base s/IVA: 1.212.268,16 EUR\nClassificação CPV (Vocabulário Comum para os Contratos Públicos)\nObjeto principal\nVocabulário Principal: 33110000\nNº: LOT-0002\nDescrição do Lote: Um equipamento de Ressonância Magnética 3T (RM), de corpo inteiro com os respetivos acessórios e elementos complementares\nPreço base s/IVA: 2.400.000,00 EUR\nClassificação CPV (Vocabulário Comum para os Contratos Públicos)\nObjeto principal\nVocabulário Principal: 33110000\n\n7 - INDICAÇÕES ADICIONAIS\nO contrato envolve aquisição conjunta (satisfação de várias entidades)? Não\nO contrato é adjudicado por uma central de compras? Não\n\n8 - TÉCNICAS\nO concurso destina-se à celebração de um acordo-quadro? Inexistência de acordo-quadro\nÉ utilizado um leilão eletrónico? Não\nÉ adotada uma fase de negociação? Não\nSistema de Aquisição Dinâmico: Inexistência de sistema de aquisição dinâmico\n\n9 - LOCAL DA EXECUÇÃO DO CONTRATO\nLOCAL DA EXECUÇÃO DO CONTRATO (PROCEDIMENTO)\nLOCAL DA EXECUÇÃO DO CONTRATO (LOTE)\nIdentificador do Lote: LOT-0001\nPaís: Portugal\nNUT III: PT16E\nLocalidade: Coimbra\nDistrito: Coimbra\nConcelho: Coimbra\nFreguesia: Freguesia de Santo António dos Olivais\nIdentificador do Lote: LOT-0002\nPaís: Portugal\nNUT III: PT16E\nLocalidade: Coimbra\nDistrito: Coimbra\nConcelho: Coimbra\nFreguesia: Freguesia de Santo António dos Olivais\n\n10 - PRAZO DE EXECUÇÃO DO CONTRATO\nIdentificador do Lote: LOT-0001\nPrazo de execução do contrato: 2 ANOS\nPrevisão de renovações: Não\nIdentificador do Lote: LOT-0002\nPrazo de execução do contrato: 2 ANOS\nPrevisão de renovações: Não\n\n11 - FUNDOS EU\nIdentificador do Lote: LOT-0001; LOT-0002\nTêm fundos EU? Sim\n\n12 - DOCUMENTOS DE HABILITAÇÃO\nHabilitação para o exercício da atividade profissional: Não\n\n13 - CONDIÇÕES DE APRESENTAÇÃO\nPlataforma eletrónica utilizada pela entidade adjudicante: ANOGOV\nURL para Apresentação: https://www.anogov.com/ss-ipocoimbra/faces/\nAdmissibilidade da apresentação de propostas variantes: Não autorizado\nPrazo para apresentação das propostas: 24-09-2025 23:59\nPrazo durante o qual os concorrentes são obrigados a manter as respetivas propostas: 120 dias a contar do termo do prazo para a apresentação das propostas\nApresentação de Catálogo Eletrónico: Necessário\nIndicação de Subcontratação na Proposta: Inexistência de indicação de subcontratação\n\n14 - PRESTAÇÃO DE CAUÇÃO\nPrestação de caução: Sim\nPercentagem: 5%\nDescrição da Garantia Exigida: de acordo peças concursais\n\n15 - FORNECIMENTO DAS PEÇAS DO CONCURSO, APRESENTAÇÃO DE PEDIDOS DE PARTICIPAÇÃO E APRESENTAÇÃO DAS PROPOSTAS\nLink para acesso às peças do concurso (URL): https://www.anogov.com/ss-ipocoimbra/faces/app/acessoDocs.jsp?codigoAcesso=g8wWEUwKwHNNb2kk3gLw80XrjQXcVcHXaF4RNQ45MSKdy6t4rd\n\n20 - OUTROS REQUISITOS\nIdentificador do Lote: LOT-0001; LOT-0002\nInformação sobre contratos reservados. Aplica-se a contratos reservados (54º-A)? Não\n\n21 - CRITÉRIO DE ADJUDICAÇÃO\nO Critério de adjudicação é diferenciado por lote? Sim\nIdentificador do lote: LOT-0001\nMultifator: Sim\nFator: \nNome: Outros\nOutro Nome: Mérito Tecnico\nPonderação: 40%\nSubfatores: Não\nFator: \nNome: Outros\nOutro Nome: Avaliação Funcional\nPonderação: 25%\nSubfatores: Não\nFator: \nNome: Outros\nOutro Nome: Duração garantia\nPonderação: 10%\nSubfatores: Não\nFator: \nNome: Outros\nOutro Nome: Manutenção e Assistência Técnica\nPonderação: 5%\nSubfatores: Não\nFator: \nNome: Preço\nPonderação: 20%\nSubfatores: Não\nO Critério de adjudicação é diferenciado por lote? Sim\nIdentificador do lote: LOT-0002\nMultifator: Sim\nFator: \nNome: Outros\nOutro Nome: Avaliação Funcional\nPonderação: 30%\nSubfatores: Não\nFator: \nNome: Preço\nPonderação: 10%\nSubfatores: Não\nFator: \nNome: Outros\nOutro Nome: Duração garantia\nPonderação: 10%\nSubfatores: Não\nFator: \nNome: Outros\nOutro Nome: Mérito Tecnico\nPonderação: 45%\nSubfatores: Não\nFator: \nNome: Outros\nOutro Nome: Manutenção e Assistência Técnica\nPonderação: 5%\nSubfatores: Não\n\n24 - CONDIÇÕES DO CONTRATO\nIdentificador do Lote: LOT-0001; LOT-0002\nFaturação Eletrónica: Necessário\nObrigação de Subcontratação:\nCódigo da Obrigação de Subcontratação: Não é aplicável nenhuma obrigação de subcontratação.\n\n25 - COMPRA PÚBLICA ESTRATÉGICA\nCompra Pública Estratégica: Inexistência de contratação pública estratégica\n\n26 - INFORMAÇÕES ADICIONAIS\nIdentificador do Lote: LOT-0001\nContrato adequado para PME: Sim\nCobertura ACP (Acordo dos Contratos Públicos da Organização Mundial do Comércio): Não\nIdentificador do Lote: LOT-0002\nContrato adequado para PME: Sim\nCobertura ACP (Acordo dos Contratos Públicos da Organização Mundial do Comércio): Não\n\n27 - IDENTIFICAÇÃO E CONTACTOS DO ÓRGÃO DE RECURSOS ADMINISTRATIVOS\nDesignação: Conselho de Administração do IPO Coimbra F.G., EPE\nEndereço: Av. Bissaya Barreto nº 98\nCódigo postal: 3000-075\nLocalidade: Coimbra\nEndereço eletrónico: secad@ipocoimbra.min-saude.pt\n\n28 - IDENTIFICAÇÃO DO(S) AUTOR(ES) DE ANÚNCIO\nNome: Teresa Goulão\nCargo: Diretora do Serviço Aprovisionamento\n419459477",
    "nipc": "506361438",
    "distrito": "Coimbra",
    "concelho": "Coimbra",
    "freguesia": "Freguesia de Santo António dos Olivais",
    "site": "www.ipocoimbra.min-saude.pt",
    "email": "aprovc@ipocoimbra.min-saude.pt",
    "designacao_contrato": "EQUIPAMENTO MÉDICO PESADO IMAGIOLOGIA ¿ RM E TC II(PRR)",
    "descricao": "EQUIPAMENTO MÉDICO PESADO IMAGIOLOGIA ¿ RM E TC II(PRR)",
    "preco_base": "3.612.268,16 EUR",
    "prazo_execucao": "2 ANOS",
    "prazo_apresentacao_propostas": "24-09-2025 23:59",
    "fundos_eu": "Sim",
    "plataforma_eletronica": "ANOGOV",
    "url_procedimento": "https://www.anogov.com/ss-ipocoimbra/faces/",
    "autor_nome": "Teresa Goulão",
    "autor_cargo": "Diretora do Serviço Aprovisionamento"
  },
  {
    "numero_procedimento": "N/A",
    "entidade": "Unidade Local de Saúde do Baixo Mondego, EPE",
    "link": "https://diariodarepublica.pt/dr/detalhe/contrato-publico/22627-933044046",
    "detalhes_completos": "1 - IDENTIFICAÇÃO E CONTACTOS DA ENTIDADE ADJUDICANTE\nDesignação da entidade adjudicante: Unidade Local de Saúde do Baixo Mondego, EPE\nNIPC: 506361527\nServiço/Órgão/Pessoa de contacto: Serviço de Aprovisionamento\nEndereço: Rua do Hospital\nCódigo postal: 3094-001\nLocalidade: Gala, Figueira da Foz\nPaís: Portugal\nNUT III: PT16E\nDistrito: Coimbra\nConcelho: Figueira da Foz\nFreguesia: Freguesia de São Pedro - Figueira da Foz\nTelefone: 233402000\nFax: 233431268\nEndereço da Entidade (URL): https://www.hdfigueira.min-saude.pt/\nEndereço Eletrónico: secretariado.ca@ulsbm.min-saude.pt\neDelivery Gateway (URL): https://www.acingov.pt\nFunção da Organização: Adquirente\nSubfunção da Organização: Organização cujo orçamento é utilizado para pagar o contrato; Organização que executa o pagamento; Organização que fornece informações adicionais sobre o processo de adjudicação; Organização que fornece mais informações sobre os prazos dos procedimentos de recurso; Organização que fornece acesso fora de linha aos documentos do concurso; Organização responsável pelo tratamento das propostas; Organização que recebe as propostas; Organização que trata os pedidos de participação; Organização que recebe pedidos de participação; Organização que fornece mais informações sobre os procedimentos de recurso; Organização que assina o contrato\nNorma jurídica da Entidade Adjudicante: Organismo de direito público\nÁrea de atividade da Autoridade Adjudicante: Serviços públicos das administrações públicas\n\n2 - JORNAL OFICIAL DA UNIÃO EUROPEIA\nO procedimento a que este anúncio diz respeito também é publicitado no Jornal Oficial da União Europeia? Sim\n\n3 - AVISO\nModelo de Anúncio: Concurso público\nData de Envio do Anúncio: 22-08-2025\n\n5 - PROCESSO\nTipo de Procedimento: Concurso público\nPreço base do procedimento: Sim\nValor do preço base do procedimento: 498.040,01 EUR\nProcedimento com lotes? Não\n\n6 - OBJETO DO CONTRATO\nNúmero de referência interna: 2201/2025\nDesignação do contrato: Lentes e consumíveis para oftalmologia com colocação de equipamento\nDescrição: Lentes e consumíveis para oftalmologia com colocação de equipamento\nOpções: Não\nTipo de Contrato Principal: Aquisição de Bens Móveis\nTipo de Contrato: Aquisição de Bens Móveis\nClassificação CPV (Vocabulário Comum para os Contratos Públicos)\nObjeto principal\nVocabulário Principal: 33731110\nPreço base s/IVA: 498.040,01 EUR\n\n7 - INDICAÇÕES ADICIONAIS\nO contrato envolve aquisição conjunta (satisfação de várias entidades)? Não\nO contrato é adjudicado por uma central de compras? Não\n\n8 - TÉCNICAS\nO concurso destina-se à celebração de um acordo-quadro? Inexistência de acordo-quadro\nÉ utilizado um leilão eletrónico? Não\nÉ adotada uma fase de negociação? Não\nSistema de Aquisição Dinâmico: Inexistência de sistema de aquisição dinâmico\n\n9 - LOCAL DA EXECUÇÃO DO CONTRATO\nLOCAL DA EXECUÇÃO DO CONTRATO (PROCEDIMENTO)\nPaís: Portugal\nNUT III: PT16E\nLocalidade: Freguesia de São Pedro - Figueira da Foz\nDistrito: Coimbra\nConcelho: Figueira da Foz\nFreguesia: Freguesia de São Pedro - Figueira da Foz\n\n10 - PRAZO DE EXECUÇÃO DO CONTRATO\nPrazo de execução do contrato: 1 ANOS\nPrevisão de renovações: Não\n\n11 - FUNDOS EU\nTêm fundos EU? Não\n\n12 - DOCUMENTOS DE HABILITAÇÃO\nHabilitação para o exercício da atividade profissional: Não\n\n13 - CONDIÇÕES DE APRESENTAÇÃO\nPlataforma eletrónica utilizada pela entidade adjudicante: ACIN\nURL para Apresentação: https://www.acingov.pt\nAdmissibilidade da apresentação de propostas variantes: Não autorizado\nPrazo para apresentação das propostas: 21-09-2025 23:59\nPrazo durante o qual os concorrentes são obrigados a manter as respetivas propostas: 90 dias a contar do termo do prazo para a apresentação das propostas\nApresentação de Catálogo Eletrónico: Permitido\nIndicação de Subcontratação na Proposta: Inexistência de indicação de subcontratação\n\n14 - PRESTAÇÃO DE CAUÇÃO\nPrestação de caução: Sim\nPercentagem: 5%\nDescrição da Garantia Exigida: O valor da caução é de 5.00% do preço contratual.\n\n15 - FORNECIMENTO DAS PEÇAS DO CONCURSO, APRESENTAÇÃO DE PEDIDOS DE PARTICIPAÇÃO E APRESENTAÇÃO DAS PROPOSTAS\nLink para acesso às peças do concurso (URL): https://www.acingov.pt/acingovprod/2/zonaPublica/zona_publica_c/donwloadProcedurePiece/OTcwODcx\n\n20 - OUTROS REQUISITOS\nInformação sobre contratos reservados. Aplica-se a contratos reservados (54º-A)? Não\n\n21 - CRITÉRIO DE ADJUDICAÇÃO\nMultifator: Não\nMonofator:\nNome: Preço\n\n24 - CONDIÇÕES DO CONTRATO\nFaturação Eletrónica: Necessário\nObrigação de Subcontratação:\nCódigo da Obrigação de Subcontratação: Não é aplicável nenhuma obrigação de subcontratação.\n\n25 - COMPRA PÚBLICA ESTRATÉGICA\nCompra Pública Estratégica: Inexistência de contratação pública estratégica\n\n26 - INFORMAÇÕES ADICIONAIS\nContrato adequado para PME: Não\nCobertura ACP (Acordo dos Contratos Públicos da Organização Mundial do Comércio): Não\n\n27 - IDENTIFICAÇÃO E CONTACTOS DO ÓRGÃO DE RECURSOS ADMINISTRATIVOS\nDesignação: Conselho de Administração\nEndereço: Rua do Hospital\nCódigo postal: 3094-001\nLocalidade: Gala, Figueira da Foz\nTelefone: 233402000\nFax: 233431268\nEndereço eletrónico: secretariado.ca@ulsbm.min-saude.pt\nPrazo de interposição do recurso: 5 dias\n\n28 - IDENTIFICAÇÃO DO(S) AUTOR(ES) DE ANÚNCIO\nNome: Ana Raquel Farias Correia dos Santos Andrade\nCargo: Presidente do Conselho de Administração da ULSBM, EPE\n419459233",
    "nipc": "506361527",
    "distrito": "Coimbra",
    "concelho": "Figueira da Foz",
    "freguesia": "Freguesia de São Pedro - Figueira da Foz",
    "site": "https://www.hdfigueira.min-saude.pt/",
    "email": "secretariado.ca@ulsbm.min-saude.pt",
    "designacao_contrato": "Lentes e consumíveis para oftalmologia com colocação de equipamento",
    "descricao": "Lentes e consumíveis para oftalmologia com colocação de equipamento",
    "preco_base": "498.040,01 EUR",
    "prazo_execucao": "1 ANOS",
    "prazo_apresentacao_propostas": "21-09-2025 23:59",
    "fundos_eu": "Não",
    "plataforma_eletronica": "ACIN",
    "url_procedimento": "https://www.acingov.pt",
    "autor_nome": "Ana Raquel Farias Correia dos Santos Andrade",
    "autor_cargo": "Presidente do Conselho de Administração da ULSBM, EPE"
  },
  {
    "numero_procedimento": "N/A",
    "entidade": "SPMS- Serviços Partilhados do M. da Saúde, E.P.E.",
    "link": "https://diariodarepublica.pt/dr/detalhe/contrato-publico/22628-933044047",
    "detalhes_completos": "1 - IDENTIFICAÇÃO E CONTACTOS DA ENTIDADE ADJUDICANTE\nDesignação da entidade adjudicante: SPMS- Serviços Partilhados do M. da Saúde, E.P.E.\nNIPC: 509540716\nEndereço: Avenida da República 61\nCódigo postal: 1050-189\nLocalidade: Lisboa\nPaís: Portugal\nNUT III: PT170\nDistrito: Lisboa\nConcelho: Lisboa\nFreguesia: Todas\nTelefone: 211545600\nFax: 211545649\nEndereço da Entidade (URL): www.spms.min-saude.pt/\nEndereço Eletrónico: contratacao@spms.min-saude.pt\neDelivery Gateway (URL): https://community.vortal.biz/public/\nFunção da Organização: Adquirente\nNorma jurídica da Entidade Adjudicante: Empresa pública\nÁrea de atividade da Autoridade Adjudicante: Saúde\n\n2 - JORNAL OFICIAL DA UNIÃO EUROPEIA\nO procedimento a que este anúncio diz respeito também é publicitado no Jornal Oficial da União Europeia? Sim\n\n3 - AVISO\nModelo de Anúncio: Concurso público\nData de Envio do Anúncio: 22-08-2025\n\n5 - PROCESSO\nTipo de Procedimento: Concurso público\nPreço base do procedimento: Sim\nValor do preço base do procedimento: 750.000,00 EUR\nProcedimento com lotes? Não\n\n6 - OBJETO DO CONTRATO\nNúmero de referência interna: 1710_2025\nDesignação do contrato: 1710_2025 - Concurso público com publicação no jornal oficial da união europeia para aquisição de Equipamentos para Unidade de Esterilização para o Hospital de Proximidade de Sintra \nDescrição: 1710_2025 - Concurso público com publicação no jornal oficial da união europeia para aquisição de Equipamentos para Unidade de Esterilização para o Hospital de Proximidade de Sintra \nOpções: Não\nTipo de Contrato Principal: Aquisição de Bens Móveis\nTipo de Contrato: Aquisição de Bens Móveis\nClassificação CPV (Vocabulário Comum para os Contratos Públicos)\nObjeto principal\nVocabulário Principal: 33100000\nPreço base s/IVA: 750.000,00 EUR\n\n7 - INDICAÇÕES ADICIONAIS\nO contrato envolve aquisição conjunta (satisfação de várias entidades)? Sim\nA entidade adjudicante atua como compradora no procedimento? Não\nNIPC: 503035416\nDesignação da entidade adjudicante: Unidade Local de Saude Amadora/Sintra, E.P.E.\nUnidades Orgânicas: Serviço de compras\nValor: 750000\nO contrato é adjudicado por uma central de compras? Sim\n\n8 - TÉCNICAS\nO concurso destina-se à celebração de um acordo-quadro? Inexistência de acordo-quadro\nÉ utilizado um leilão eletrónico? Não\nÉ adotada uma fase de negociação? Não\nSistema de Aquisição Dinâmico: Inexistência de sistema de aquisição dinâmico\n\n9 - LOCAL DA EXECUÇÃO DO CONTRATO\nLOCAL DA EXECUÇÃO DO CONTRATO (PROCEDIMENTO)\nPaís: Portugal\nNUT III: PT170\nLocalidade: Lisboa\nDistrito: Lisboa\nConcelho: Sintra\nFreguesia: Todas\n\n10 - PRAZO DE EXECUÇÃO DO CONTRATO\nPrazo de execução do contrato: 4 MESES\nPrevisão de renovações: Não\n\n11 - FUNDOS EU\nTêm fundos EU? Sim\n\n12 - DOCUMENTOS DE HABILITAÇÃO\nHabilitação para o exercício da atividade profissional: Não\n\n13 - CONDIÇÕES DE APRESENTAÇÃO\nPlataforma eletrónica utilizada pela entidade adjudicante: VORTAL\nURL para Apresentação: https://community.vortal.biz/public/\nAdmissibilidade da apresentação de propostas variantes: Não autorizado\nPrazo para apresentação das propostas: 22-09-2025 18:00\nPrazo durante o qual os concorrentes são obrigados a manter as respetivas propostas: 180 dias a contar do termo do prazo para a apresentação das propostas\nApresentação de Catálogo Eletrónico: Permitido\nIndicação de Subcontratação na Proposta: Inexistência de indicação de subcontratação\n\n14 - PRESTAÇÃO DE CAUÇÃO\nPrestação de caução: Não\n\n15 - FORNECIMENTO DAS PEÇAS DO CONCURSO, APRESENTAÇÃO DE PEDIDOS DE PARTICIPAÇÃO E APRESENTAÇÃO DAS PROPOSTAS\nLink para acesso às peças do concurso (URL): https://community.vortal.biz/Public/public-tender-documents/dE1zMTFabHpaYlNKWUYraUFDNDdyVHplM0g2bU1FOFZZOHpOTXlGS1htaE96czhoZUIrVUdiemtmQXBOVVhVNkNISFhBalB1QUhHb1VQc09yT3locWc9PU5PZFp3\n\n20 - OUTROS REQUISITOS\nInformação sobre contratos reservados. Aplica-se a contratos reservados (54º-A)? Não\n\n21 - CRITÉRIO DE ADJUDICAÇÃO\nMultifator: Sim\nFator: \nNome: Preço\nPonderação: 80%\nSubfatores: Não\nFator: \nNome: Qualidade\nPonderação: 20%\nSubfatores: Não\n\n24 - CONDIÇÕES DO CONTRATO\nFaturação Eletrónica: Permitido\nObrigação de Subcontratação:\nCódigo da Obrigação de Subcontratação: Não é aplicável nenhuma obrigação de subcontratação.\n\n25 - COMPRA PÚBLICA ESTRATÉGICA\nCompra Pública Estratégica: Inexistência de contratação pública estratégica\n\n26 - INFORMAÇÕES ADICIONAIS\nContrato adequado para PME: Sim\nCobertura ACP (Acordo dos Contratos Públicos da Organização Mundial do Comércio): Não\n\n27 - IDENTIFICAÇÃO E CONTACTOS DO ÓRGÃO DE RECURSOS ADMINISTRATIVOS\nDesignação: Serviços Partilhados do Ministério da Saúde\nEndereço: Avenida da Républica, n61\nCódigo postal: 1050-189\nLocalidade: Lisboa\nTelefone: +351 211545600\nFax: +351 211545649\nEndereço eletrónico: catalogo@spms.min-saude.pt\n\n28 - IDENTIFICAÇÃO DO(S) AUTOR(ES) DE ANÚNCIO\nNome: Joana lopes\nCargo: Técnica superior\n419459177",
    "nipc": "509540716",
    "distrito": "Lisboa",
    "concelho": "Lisboa",
    "freguesia": "Todas",
    "site": "www.spms.min-saude.pt/",
    "email": "contratacao@spms.min-saude.pt",
    "designacao_contrato": "1710_2025 - Concurso público com publicação no jornal oficial da união europeia para aquisição de Equipamentos para Unidade de Esterilização para o Hospital de Proximidade de Sintra",
    "descricao": "1710_2025 - Concurso público com publicação no jornal oficial da união europeia para aquisição de Equipamentos para Unidade de Esterilização para o Hospital de Proximidade de Sintra",
    "preco_base": "750.000,00 EUR",
    "prazo_execucao": "4 MESES",
    "prazo_apresentacao_propostas": "22-09-2025 18:00",
    "fundos_eu": "Sim",
    "plataforma_eletronica": "VORTAL",
    "url_procedimento": "https://community.vortal.biz/public/",
    "autor_nome": "Joana lopes",
    "autor_cargo": "Técnica superior"
  },
  {
    "numero_procedimento": "N/A",
    "entidade": "União de Freguesias de Trancoso e Souto Maior",
    "link": "https://diariodarepublica.pt/dr/detalhe/contrato-publico/22630-933044048",
    "detalhes_completos": "1 - IDENTIFICAÇÃO E CONTACTOS DA ENTIDADE ADJUDICANTE\nDesignação da entidade adjudicante: União de Freguesias de Trancoso e Souto Maior\nNIPC: 510840647\nServiço/Órgão/Pessoa de contacto: Presidente da Junta da União de Freguesias\nEndereço: Av. Calouste Gulbenkian, nº 27\nCódigo postal: 6420-033\nLocalidade: Trancoso\nPaís: Portugal\nNUT III: PT16J\nDistrito: Guarda\nConcelho: Trancoso\nFreguesia: União das Freguesias de Trancoso (São Pedro e Santa Maria) e Souto Maior\nTelefone: 271812620\nFax: 271812620\nEndereço da Entidade (URL): https://www.facebook.com/freguesiatrancoso/?locale=pt_PT\nEndereço Eletrónico: uftrancoso@sapo.pt\neDelivery Gateway (URL): https://www.acingov.pt\nFunção da Organização: Adquirente\nSubfunção da Organização: Organização que recebe as propostas\nNorma jurídica da Entidade Adjudicante: Organismo de direito público\nÁrea de atividade da Autoridade Adjudicante: Serviços públicos das administrações públicas\n\n2 - JORNAL OFICIAL DA UNIÃO EUROPEIA\nO procedimento a que este anúncio diz respeito também é publicitado no Jornal Oficial da União Europeia? Sim\n\n3 - AVISO\nModelo de Anúncio: Concurso público\nData de Envio do Anúncio: 22-08-2025\n\n5 - PROCESSO\nTipo de Procedimento: Concurso público\nPreço base do procedimento: Sim\nValor do preço base do procedimento: 140.104,41 EUR\nProcedimento com lotes? Não\n\n6 - OBJETO DO CONTRATO\nNúmero de referência interna: CPI/1/2025\nDesignação do contrato: Aquisição de Serviços referente à execução da Candidatura n.º 51, da Medida programática Condomínio de Aldeia  Programa Integrado de Apoio às Aldeias Localizadas em Territórios de Floresta, no âmbito do investimento RE-C08-i01: Transformação da Paisagem dos Territórios de Floresta Vulneráveis da Componente C08  Floresta do Plano de Recuperação e Resiliência, AVISO N.º 05/C08-I01/2023, para implementação dos Condomínios de Aldeia nas localidades de Trancoso, Castaíde, Miguel Choco, São Martinho, Venda do Cepo, Aldeia de Santo Inácio, Souto Maior, Sintrão e Montes, pertencentes ao Município de Trancoso\nDescrição: Aquisição de Serviços referente à execução da Candidatura n.º 51, da Medida programática Condomínio de Aldeia  Programa Integrado de Apoio às Aldeias Localizadas em Territórios de Floresta, no âmbito do investimento RE-C08-i01: Transformação da Paisagem dos Territórios de Floresta Vulneráveis da Componente C08  Floresta do Plano de Recuperação e Resiliência, AVISO N.º 05/C08-I01/2023, para implementação dos Condomínios de Aldeia nas localidades de Trancoso, Castaíde, Miguel Choco, São Martinho, Venda do Cepo, Aldeia de Santo Inácio, Souto Maior, Sintrão e Montes, pertencentes ao Município de Trancoso\nOpções: Não\nTipo de Contrato Principal: Aquisição de Serviços\nTipo de Contrato: Aquisição de Serviços\nClassificação CPV (Vocabulário Comum para os Contratos Públicos)\nObjeto principal\nVocabulário Principal: 77314000\nPreço base s/IVA: 140.104,41 EUR\n\n7 - INDICAÇÕES ADICIONAIS\nO contrato envolve aquisição conjunta (satisfação de várias entidades)? Não\nO contrato é adjudicado por uma central de compras? Não\n\n8 - TÉCNICAS\nO concurso destina-se à celebração de um acordo-quadro? Inexistência de acordo-quadro\nÉ utilizado um leilão eletrónico? Não\nÉ adotada uma fase de negociação? Não\nSistema de Aquisição Dinâmico: Inexistência de sistema de aquisição dinâmico\n\n9 - LOCAL DA EXECUÇÃO DO CONTRATO\nLOCAL DA EXECUÇÃO DO CONTRATO (PROCEDIMENTO)\nPaís: Portugal\nNUT III: PT16J\nLocalidade: União das Freguesias de Trancoso (São Pedro e Santa Maria) e Souto Maior\nDistrito: Guarda\nConcelho: Trancoso\nFreguesia: União das Freguesias de Trancoso (São Pedro e Santa Maria) e Souto Maior\n\n10 - PRAZO DE EXECUÇÃO DO CONTRATO\nData de Início: 01-10-2025\nData de Fim: 31-03-2026\nPrevisão de renovações: Não\n\n11 - FUNDOS EU\nTêm fundos EU? Sim\n\n12 - DOCUMENTOS DE HABILITAÇÃO\nHabilitação para o exercício da atividade profissional: Não\n\n13 - CONDIÇÕES DE APRESENTAÇÃO\nPlataforma eletrónica utilizada pela entidade adjudicante: ACIN\nURL para Apresentação: https://www.acingov.pt\nAdmissibilidade da apresentação de propostas variantes: Não autorizado\nPrazo para apresentação das propostas: 21-09-2025 17:59\nPrazo durante o qual os concorrentes são obrigados a manter as respetivas propostas: 66 dias a contar do termo do prazo para a apresentação das propostas\nApresentação de Catálogo Eletrónico: Permitido\nIndicação de Subcontratação na Proposta: Inexistência de indicação de subcontratação\n\n14 - PRESTAÇÃO DE CAUÇÃO\nPrestação de caução: Não\n\n15 - FORNECIMENTO DAS PEÇAS DO CONCURSO, APRESENTAÇÃO DE PEDIDOS DE PARTICIPAÇÃO E APRESENTAÇÃO DAS PROPOSTAS\nLink para acesso às peças do concurso (URL): https://www.acingov.pt/acingovprod/2/zonaPublica/zona_publica_c/donwloadProcedurePiece/OTMyMjA1\n\n20 - OUTROS REQUISITOS\nInformação sobre contratos reservados. Aplica-se a contratos reservados (54º-A)? Não\n\n21 - CRITÉRIO DE ADJUDICAÇÃO\nMultifator: Sim\nFator: \nNome: Outros\nOutro Nome: Valia Técnica da Proposta\nPonderação: 75%\nSubfatores: Sim\nSubfatores: \nNome: Memória descritiva\nPonderação : 50%; \nNome: Programação de trabalhos\nPonderação : 30%; \nNome: Experiência acumulada na execução desta tipologia de trabalhos Condomínios de Aldeia\nPonderação : 20%; \nFator: \nNome: Preço\nPonderação: 25%\nSubfatores: Não\n\n24 - CONDIÇÕES DO CONTRATO\nFaturação Eletrónica: Permitido\nObrigação de Subcontratação:\nCódigo da Obrigação de Subcontratação: Não é aplicável nenhuma obrigação de subcontratação.\n\n25 - COMPRA PÚBLICA ESTRATÉGICA\nCompra Pública Estratégica: Inexistência de contratação pública estratégica\n\n26 - INFORMAÇÕES ADICIONAIS\nContrato adequado para PME: Não\nCobertura ACP (Acordo dos Contratos Públicos da Organização Mundial do Comércio): Não\n\n27 - IDENTIFICAÇÃO E CONTACTOS DO ÓRGÃO DE RECURSOS ADMINISTRATIVOS\nDesignação: Junta da União de Freguesias\nEndereço: Av. Calouste Gulbenkian, nº 27\nCódigo postal: 6420-033\nLocalidade: Trancoso\nTelefone: 271812620\nFax: 271812620\nEndereço eletrónico: uftrancoso@sapo.pt\nPrazo de interposição do recurso: 30 dias\n\n28 - IDENTIFICAÇÃO DO(S) AUTOR(ES) DE ANÚNCIO\nNome: Andre Miguel Pinheiro Lourenço Pinto\nCargo: Presidente\n419460067",
    "nipc": "510840647",
    "distrito": "Guarda",
    "concelho": "Trancoso",
    "freguesia": "União das Freguesias de Trancoso (São Pedro e Santa Maria) e Souto Maior",
    "site": "https://www.facebook.com/freguesiatrancoso/?locale=pt_PT",
    "email": "uftrancoso@sapo.pt",
    "designacao_contrato": "Aquisição de Serviços referente à execução da Candidatura n.º 51, da Medida programática Condomínio de Aldeia  Programa Integrado de Apoio às Aldeias Localizadas em Territórios de Floresta, no âmbito do investimento RE-C08-i01: Transformação da Paisagem dos Territórios de Floresta Vulneráveis da Componente C08  Floresta do Plano de Recuperação e Resiliência, AVISO N.º 05/C08-I01/2023, para implementação dos Condomínios de Aldeia nas localidades de Trancoso, Castaíde, Miguel Choco, São Martinho, Venda do Cepo, Aldeia de Santo Inácio, Souto Maior, Sintrão e Montes, pertencentes ao Município de Trancoso",
    "descricao": "Aquisição de Serviços referente à execução da Candidatura n.º 51, da Medida programática Condomínio de Aldeia  Programa Integrado de Apoio às Aldeias Localizadas em Territórios de Floresta, no âmbito do investimento RE-C08-i01: Transformação da Paisagem dos Territórios de Floresta Vulneráveis da Componente C08  Floresta do Plano de Recuperação e Resiliência, AVISO N.º 05/C08-I01/2023, para implementação dos Condomínios de Aldeia nas localidades de Trancoso, Castaíde, Miguel Choco, São Martinho, Venda do Cepo, Aldeia de Santo Inácio, Souto Maior, Sintrão e Montes, pertencentes ao Município de Trancoso",
    "preco_base": "140.104,41 EUR",
    "prazo_execucao": null,
    "prazo_apresentacao_propostas": "21-09-2025 17:59",
    "fundos_eu": "Sim",
    "plataforma_eletronica": "ACIN",
    "url_procedimento": "https://www.acingov.pt",
    "autor_nome": "Andre Miguel Pinheiro Lourenço Pinto",
    "autor_cargo": "Presidente"
  },
  {
    "numero_procedimento": "N/A",
    "entidade": "Etapas Remotas - Transportes Rodoviários, Lda",
    "link": "https://diariodarepublica.pt/dr/detalhe/contrato-publico/22634-933044049",
    "detalhes_completos": "1 - IDENTIFICAÇÃO E CONTACTOS DA ENTIDADE ADJUDICANTE\nDesignação da entidade adjudicante: Etapas Remotas - Transportes Rodoviários, Lda\nNIPC: 516524135\nEndereço: Rua Antiga de Brito, n 117\nCódigo postal: 4590-754\nLocalidade: Porto\nPaís: Portugal\nNUT III: PT11C\nDistrito: Porto\nConcelho: Paços de Ferreira\nFreguesia: Freguesia de Ferreira - Paços de Ferreira\nTelefone: 255860220\nEndereço da Entidade (URL): https://www.cimtamegaesousa.pt/areas-de-intervencao-mobilidade-e-transportes\nEndereço Eletrónico: etapasremotas@gmail.com\neDelivery Gateway (URL): https://community.vortal.biz/public/\nFunção da Organização: Adquirente\nNorma jurídica da Entidade Adjudicante: Organização que adjudica um contrato subvencionado por uma autoridade da administração central\nÁrea de atividade da Autoridade Adjudicante: Assuntos económicos\n\n2 - JORNAL OFICIAL DA UNIÃO EUROPEIA\nO procedimento a que este anúncio diz respeito também é publicitado no Jornal Oficial da União Europeia? Sim\n\n3 - AVISO\nModelo de Anúncio: Concurso público\nData de Envio do Anúncio: 22-08-2025\n\n5 - PROCESSO\nTipo de Procedimento: Concurso público\nPreço base do procedimento: Sim\nValor do preço base do procedimento: 2.750.000,00 EUR\nProcedimento com lotes? Não\n\n6 - OBJETO DO CONTRATO\nNúmero de referência interna: CPI_04_25_ER\nDesignação do contrato: AQUISIÇÃO DE CINCO AUTOCARROS STANDARD 100% ELÉCTRICOS\nDescrição: Procedimento pré-contratual de Concurso Público com publicação de anúncio no Jornal oficial da União Europeia, que tem por objeto principal a “aquisição 5 autocarros standard 100% elétricos”\nOpções: Não\nTipo de Contrato Principal: Aquisição de Bens Móveis\nTipo de Contrato: Aquisição de Bens Móveis\nClassificação CPV (Vocabulário Comum para os Contratos Públicos)\nObjeto principal\nVocabulário Principal: 34144910\nPreço base s/IVA: 2.750.000,00 EUR\n\n7 - INDICAÇÕES ADICIONAIS\nO contrato envolve aquisição conjunta (satisfação de várias entidades)? Não\nO contrato é adjudicado por uma central de compras? Não\n\n8 - TÉCNICAS\nO concurso destina-se à celebração de um acordo-quadro? Inexistência de acordo-quadro\nÉ utilizado um leilão eletrónico? Não\nÉ adotada uma fase de negociação? Não\nSistema de Aquisição Dinâmico: Inexistência de sistema de aquisição dinâmico\n\n9 - LOCAL DA EXECUÇÃO DO CONTRATO\nLOCAL DA EXECUÇÃO DO CONTRATO (PROCEDIMENTO)\nPaís: Portugal\nNUT III: PT11C\nLocalidade: Porto\nDistrito: Porto\nConcelho: Paços de Ferreira\nFreguesia: Freguesia de Ferreira - Paços de Ferreira\n\n10 - PRAZO DE EXECUÇÃO DO CONTRATO\nPrazo de execução do contrato: 5 MESES\nPrevisão de renovações: Não\n\n11 - FUNDOS EU\nTêm fundos EU? Sim\n\n12 - DOCUMENTOS DE HABILITAÇÃO\nHabilitação para o exercício da atividade profissional: Não\n\n13 - CONDIÇÕES DE APRESENTAÇÃO\nPlataforma eletrónica utilizada pela entidade adjudicante: VORTAL\nURL para Apresentação: https://community.vortal.biz/public/\nAdmissibilidade da apresentação de propostas variantes: Não autorizado\nPrazo para apresentação das propostas: 21-09-2025 17:00\nPrazo durante o qual os concorrentes são obrigados a manter as respetivas propostas: 90 dias a contar do termo do prazo para a apresentação das propostas\nApresentação de Catálogo Eletrónico: Permitido\nIndicação de Subcontratação na Proposta: Inexistência de indicação de subcontratação\n\n14 - PRESTAÇÃO DE CAUÇÃO\nPrestação de caução: Sim\nPercentagem: 5%\nDescrição da Garantia Exigida: Deposito em dinheiro ou mediante garantia bancária\n\n15 - FORNECIMENTO DAS PEÇAS DO CONCURSO, APRESENTAÇÃO DE PEDIDOS DE PARTICIPAÇÃO E APRESENTAÇÃO DAS PROPOSTAS\nLink para acesso às peças do concurso (URL): https://community.vortal.biz/Public/public-tender-documents/ZDRHaFBpam9Qa25mUWdoZTN4SnBLTnphV0ZzTDA3Rmw0YkE4NnZjU2JSZE14RGIxRzNXc0p0cCtpaVlJdnIwZXVMQnZtSExJTWc3V1RvZ2dPeUNpVlE9PXEhT0hy\n\n20 - OUTROS REQUISITOS\nInformação sobre contratos reservados. Aplica-se a contratos reservados (54º-A)? Não\n\n21 - CRITÉRIO DE ADJUDICAÇÃO\nMultifator: Não\nMonofator:\nNome: Preço\n\n24 - CONDIÇÕES DO CONTRATO\nFaturação Eletrónica: Permitido\nObrigação de Subcontratação:\nCódigo da Obrigação de Subcontratação: Não é aplicável nenhuma obrigação de subcontratação.\n\n25 - COMPRA PÚBLICA ESTRATÉGICA\nCompra Pública Estratégica: Inexistência de contratação pública estratégica\n\n26 - INFORMAÇÕES ADICIONAIS\nContrato adequado para PME: Sim\nCobertura ACP (Acordo dos Contratos Públicos da Organização Mundial do Comércio): Não\n\n27 - IDENTIFICAÇÃO E CONTACTOS DO ÓRGÃO DE RECURSOS ADMINISTRATIVOS\nDesignação: Etapas Remotas - Transportes Rodoviários, Lda\nEndereço: Rua Antiga de Brito, n 117\nCódigo postal: 4590-754\nLocalidade: Paços de Ferreira\nTelefone: +351 255860220\nFax: +351 255860220\nEndereço eletrónico: etapasremotas@gmail.com\n\n28 - IDENTIFICAÇÃO DO(S) AUTOR(ES) DE ANÚNCIO\nNome: Miguel Maia\nCargo: Gerente\n419460804",
    "nipc": "516524135",
    "distrito": "Porto",
    "concelho": "Paços de Ferreira",
    "freguesia": "Freguesia de Ferreira - Paços de Ferreira",
    "site": "https://www.cimtamegaesousa.pt/areas-de-intervencao-mobilidade-e-transportes",
    "email": "etapasremotas@gmail.com",
    "designacao_contrato": "AQUISIÇÃO DE CINCO AUTOCARROS STANDARD 100% ELÉCTRICOS",
    "descricao": "Procedimento pré-contratual de Concurso Público com publicação de anúncio no Jornal oficial da União Europeia, que tem por objeto principal a “aquisição 5 autocarros standard 100% elétricos”",
    "preco_base": "2.750.000,00 EUR",
    "prazo_execucao": "5 MESES",
    "prazo_apresentacao_propostas": "21-09-2025 17:00",
    "fundos_eu": "Sim",
    "plataforma_eletronica": "VORTAL",
    "url_procedimento": "https://community.vortal.biz/public/",
    "autor_nome": "Miguel Maia",
    "autor_cargo": "Gerente"
  },
  {
    "numero_procedimento": "N/A",
    "entidade": "Águas e Energia do Porto E.M",
    "link": "https://diariodarepublica.pt/dr/detalhe/contrato-publico/22637-933044050",
    "detalhes_completos": "1 - IDENTIFICAÇÃO E CONTACTOS DA ENTIDADE ADJUDICANTE\nDesignação da entidade adjudicante: Águas e Energia do Porto E.M\nNIPC: 507718666\nServiço/Órgão/Pessoa de contacto: Administrador\nEndereço: Rua Barão de Nova Sintra, Nº 285\nCódigo postal: 4300-367\nLocalidade: Porto\nPaís: Portugal\nNUT III: PTZZZ\nDistrito: Todos\nConcelho: Todos\nFreguesia: Todas\nTelefone: 225190854\nFax: 225190807\nEndereço da Entidade (URL): www.aguasdoporto.pt\nEndereço Eletrónico: contratos@aguasdoporto.pt\neDelivery Gateway (URL): https://www.acingov.pt\nFunção da Organização: Adquirente\nNorma jurídica da Entidade Adjudicante: Organismo de direito público\nÁrea de atividade da Autoridade Adjudicante: Serviços públicos das administrações públicas\n\n2 - JORNAL OFICIAL DA UNIÃO EUROPEIA\nO procedimento a que este anúncio diz respeito também é publicitado no Jornal Oficial da União Europeia? Sim\n\n3 - AVISO\nModelo de Anúncio: Concurso público\nData de Envio do Anúncio: 22-08-2025\n\n5 - PROCESSO\nTipo de Procedimento: Concurso público\nPreço base do procedimento: Sim\nValor do preço base do procedimento: 4.050.000,00 EUR\nProcedimento com lotes? Sim\nNº Máx. de Lotes Autorizado: 2\nNúmero máximo de lotes que podem ser adjudicados a um concorrente: 2\n\n6 - OBJETO DO CONTRATO\nNúmero de referência interna: 1861CPI25\nDesignação do contrato: 1861CPI25 - Aquisição de Serviços de Recolha, Transporte, Tratamento e Destino Final de Lamas das ETAR do Freixo e Sobreiras\nDescrição: 1861CPI25 - Aquisição de Serviços de Recolha, Transporte, Tratamento e Destino Final de Lamas das ETAR do Freixo e Sobreiras\nOpções: Não\nTipo de Contrato Principal: Aquisição de Serviços\nTipo de Contrato: Aquisição de Serviços\nClassificação CPV (Vocabulário Comum para os Contratos Públicos)\nObjeto principal\nVocabulário Principal: 90513700\nPreço base s/IVA: 4.050.000,00 EUR\nLotes: \nNº: LOT-0001\nDescrição do Lote: Lote 1  Recolha, transporte, tratamento e destino final de lamas das ETAR de Sobreiras\nPreço base s/IVA: 3.375.000,00 EUR\nClassificação CPV (Vocabulário Comum para os Contratos Públicos)\nObjeto principal\nVocabulário Principal: 90513700\nNº: LOT-0002\nDescrição do Lote: Lote 2  Recolha, transporte, tratamento e destino final de lamas da ETAR do Freixo\nPreço base s/IVA: 675.000,00 EUR\nClassificação CPV (Vocabulário Comum para os Contratos Públicos)\nObjeto principal\nVocabulário Principal: 90513700\n\n7 - INDICAÇÕES ADICIONAIS\nO contrato envolve aquisição conjunta (satisfação de várias entidades)? Não\nO contrato é adjudicado por uma central de compras? Não\n\n8 - TÉCNICAS\nO concurso destina-se à celebração de um acordo-quadro? Inexistência de acordo-quadro\nÉ utilizado um leilão eletrónico? Não\nÉ adotada uma fase de negociação? Não\nSistema de Aquisição Dinâmico: Inexistência de sistema de aquisição dinâmico\n\n9 - LOCAL DA EXECUÇÃO DO CONTRATO\nLOCAL DA EXECUÇÃO DO CONTRATO (PROCEDIMENTO)\nPaís: Portugal\nNUT III: PT11A\nLocalidade: Porto\nDistrito: Porto\nConcelho: Porto\nFreguesia: Todas\nLOCAL DA EXECUÇÃO DO CONTRATO (LOTE)\nIdentificador do Lote: LOT-0001; LOT-0002\nPaís: Portugal\nNUT III: PT11A\nLocalidade: Porto\nDistrito: Porto\nConcelho: Porto\nFreguesia: Todas\n\n10 - PRAZO DE EXECUÇÃO DO CONTRATO\nIdentificador do Lote: LOT-0001; LOT-0002\nPrazo de execução do contrato: 365 DIAS\nPrevisão de renovações: Não\n\n11 - FUNDOS EU\nIdentificador do Lote: LOT-0001; LOT-0002\nTêm fundos EU? Não\n\n12 - DOCUMENTOS DE HABILITAÇÃO\nHabilitação para o exercício da atividade profissional: Sim\nTipo: Outros\nDescrição - Outros: i) Alvará da licença para o transporte, tratamento e deposição final das lamas;\nii) Alvará da Licença para o armazenamento temporário;\niii) Alvará de Licença para o Destino Final adequado;\niv) Plano de Gestão de Lamas (PGL). \n\nDescrição: i) Alvará da licença para o transporte, tratamento e deposição final das lamas;\nii) Alvará da Licença para o armazenamento temporário;\niii) Alvará de Licença para o Destino Final adequado;\niv) Plano de Gestão de Lamas (PGL). \n\n13 - CONDIÇÕES DE APRESENTAÇÃO\nPlataforma eletrónica utilizada pela entidade adjudicante: ACIN\nURL para Apresentação: https://www.acingov.pt\nAdmissibilidade da apresentação de propostas variantes: Não autorizado\nPrazo para apresentação das propostas: 24-09-2025 17:00\nPrazo durante o qual os concorrentes são obrigados a manter as respetivas propostas: 66 dias a contar do termo do prazo para a apresentação das propostas\nApresentação de Catálogo Eletrónico: Permitido\nIndicação de Subcontratação na Proposta: Inexistência de indicação de subcontratação\n\n14 - PRESTAÇÃO DE CAUÇÃO\nPrestação de caução: Sim\nPercentagem: 5%\nDescrição da Garantia Exigida: O valor da caução é de 5.00% do preço contratual.\n\n15 - FORNECIMENTO DAS PEÇAS DO CONCURSO, APRESENTAÇÃO DE PEDIDOS DE PARTICIPAÇÃO E APRESENTAÇÃO DAS PROPOSTAS\nLink para acesso às peças do concurso (URL): https://www.acingov.pt/acingovprod/2/zonaPublica/zona_publica_c/donwloadProcedurePiece/OTcwODkw\n\n20 - OUTROS REQUISITOS\nIdentificador do Lote: LOT-0001; LOT-0002\nInformação sobre contratos reservados. Aplica-se a contratos reservados (54º-A)? Não\n\n21 - CRITÉRIO DE ADJUDICAÇÃO\nO Critério de adjudicação é diferenciado por lote? Não\nMultifator: Não\nMonofator:\nNome: Preço\n\n24 - CONDIÇÕES DO CONTRATO\nIdentificador do Lote: LOT-0001; LOT-0002\nFaturação Eletrónica: Permitido\nObrigação de Subcontratação:\nCódigo da Obrigação de Subcontratação: Não é aplicável nenhuma obrigação de subcontratação.\n\n25 - COMPRA PÚBLICA ESTRATÉGICA\nCompra Pública Estratégica: Inexistência de contratação pública estratégica\n\n26 - INFORMAÇÕES ADICIONAIS\nIdentificador do Lote: LOT-0001; LOT-0002\nContrato adequado para PME: Não\nCobertura ACP (Acordo dos Contratos Públicos da Organização Mundial do Comércio): Não\n\n27 - IDENTIFICAÇÃO E CONTACTOS DO ÓRGÃO DE RECURSOS ADMINISTRATIVOS\nDesignação: Conselho de Administração da CMPEAE - Empresa de Águas e Energia do Município do Porto, E. M.\nEndereço: R. do Barão de Nova Sintra 285\nCódigo postal: 4300-367\nLocalidade: Porto\nTelefone: 220100220\nFax: \nEndereço eletrónico: contratos@aguasdoporto.pt\n\n28 - IDENTIFICAÇÃO DO(S) AUTOR(ES) DE ANÚNCIO\nNome: Eng. Ruben Fernandes\nCargo: Administrador Executivo\n419456739",
    "nipc": "507718666",
    "distrito": "Todos",
    "concelho": "Todos",
    "freguesia": "Todas",
    "site": "www.aguasdoporto.pt",
    "email": "contratos@aguasdoporto.pt",
    "designacao_contrato": "1861CPI25 - Aquisição de Serviços de Recolha, Transporte, Tratamento e Destino Final de Lamas das ETAR do Freixo e Sobreiras",
    "descricao": "1861CPI25 - Aquisição de Serviços de Recolha, Transporte, Tratamento e Destino Final de Lamas das ETAR do Freixo e Sobreiras",
    "preco_base": "4.050.000,00 EUR",
    "prazo_execucao": "365 DIAS",
    "prazo_apresentacao_propostas": "24-09-2025 17:00",
    "fundos_eu": "Não",
    "plataforma_eletronica": "ACIN",
    "url_procedimento": "https://www.acingov.pt",
    "autor_nome": "Eng. Ruben Fernandes",
    "autor_cargo": "Administrador Executivo"
  },
  {
    "numero_procedimento": "N/A",
    "entidade": "Município do Funchal",
    "link": "https://diariodarepublica.pt/dr/detalhe/contrato-publico/22638-933044051",
    "detalhes_completos": "1 - IDENTIFICAÇÃO E CONTACTOS DA ENTIDADE ADJUDICANTE\nDesignação da entidade adjudicante: Município do Funchal\nNIPC: 511217315\nServiço/Órgão/Pessoa de contacto: Divisão de Contratação Pública\nEndereço: Praça do Município\nCódigo postal: 9004-512\nLocalidade: Funchal\nPaís: Portugal\nNUT III: PT300\nDistrito: Região Autónoma da Madeira\nConcelho: Funchal\nFreguesia: Freguesia de Sé (Funchal)\nTelefone: 291211000\nFax: 00351291211000\nEndereço da Entidade (URL): www.funchal.pt\nEndereço Eletrónico: dcpa@funchal.pt\neDelivery Gateway (URL): https://www.acingov.pt\nFunção da Organização: Adquirente\nSubfunção da Organização: Organização cujo orçamento é utilizado para pagar o contrato; Organização que executa o pagamento; Organização que fornece informações adicionais sobre o processo de adjudicação; Organização responsável pelo tratamento das propostas; Organização que recebe as propostas; Organização que trata os pedidos de participação; Organização que recebe pedidos de participação; Organização que assina o contrato\nNorma jurídica da Entidade Adjudicante: Organismo de direito público\nÁrea de atividade da Autoridade Adjudicante: Serviços públicos das administrações públicas\n\n2 - JORNAL OFICIAL DA UNIÃO EUROPEIA\nO procedimento a que este anúncio diz respeito também é publicitado no Jornal Oficial da União Europeia? Sim\n\n3 - AVISO\nModelo de Anúncio: Concurso público\nData de Envio do Anúncio: 22-08-2025\n\n5 - PROCESSO\nTipo de Procedimento: Concurso público\nPreço base do procedimento: Sim\nValor do preço base do procedimento: 302.151,66 EUR\nProcedimento com lotes? Sim\nNº Máx. de Lotes Autorizado: 3\nNúmero máximo de lotes que podem ser adjudicados a um concorrente: 3\n\n6 - OBJETO DO CONTRATO\nNúmero de referência interna: 105/DSINT/DSI/2025\nDesignação do contrato: Aquisição de Equipamentos de Rede\nDescrição: Aquisição de Equipamentos de Rede\nOpções: Não\nTipo de Contrato Principal: Aquisição de Bens Móveis\nTipo de Contrato: Aquisição de Bens Móveis\nClassificação CPV (Vocabulário Comum para os Contratos Públicos)\nObjeto principal\nVocabulário Principal: 32420000\nPreço base s/IVA: 302.151,66 EUR\nLotes: \nNº: LOT-0001\nDescrição do Lote: Equipamentos de Rede\nPreço base s/IVA: 233.805,67 EUR\nClassificação CPV (Vocabulário Comum para os Contratos Públicos)\nObjeto principal\nVocabulário Principal: 32420000\nNº: LOT-0002\nDescrição do Lote: Conectores\nPreço base s/IVA: 61.707,41 EUR\nClassificação CPV (Vocabulário Comum para os Contratos Públicos)\nObjeto principal\nVocabulário Principal: 30236000\nNº: LOT-0003\nDescrição do Lote: Licenciamento Cisco\nPreço base s/IVA: 6.638,58 EUR\nClassificação CPV (Vocabulário Comum para os Contratos Públicos)\nObjeto principal\nVocabulário Principal: 48730000\n\n7 - INDICAÇÕES ADICIONAIS\nO contrato envolve aquisição conjunta (satisfação de várias entidades)? Não\nO contrato é adjudicado por uma central de compras? Não\n\n8 - TÉCNICAS\nO concurso destina-se à celebração de um acordo-quadro? Inexistência de acordo-quadro\nÉ utilizado um leilão eletrónico? Não\nÉ adotada uma fase de negociação? Não\nSistema de Aquisição Dinâmico: Inexistência de sistema de aquisição dinâmico\n\n9 - LOCAL DA EXECUÇÃO DO CONTRATO\nLOCAL DA EXECUÇÃO DO CONTRATO (PROCEDIMENTO)\nPaís: Portugal\nNUT III: PT300\nLocalidade: Freguesia de Sé (Funchal)\nDistrito: Região Autónoma da Madeira\nConcelho: Funchal\nFreguesia: Freguesia de Sé (Funchal)\nLOCAL DA EXECUÇÃO DO CONTRATO (LOTE)\nIdentificador do Lote: LOT-0001; LOT-0002; LOT-0003\nPaís: Portugal\nNUT III: PT300\nLocalidade: Freguesia de Sé (Funchal)\nDistrito: Região Autónoma da Madeira\nConcelho: Funchal\nFreguesia: Freguesia de Sé (Funchal)\n\n10 - PRAZO DE EXECUÇÃO DO CONTRATO\nIdentificador do Lote: LOT-0001; LOT-0002\nPrazo de execução do contrato: 120 DIAS\nPrevisão de renovações: Não\nIdentificador do Lote: LOT-0003\nPrazo de execução do contrato: 36 MESES\nPrevisão de renovações: Não\n\n11 - FUNDOS EU\nIdentificador do Lote: LOT-0001; LOT-0002; LOT-0003\nTêm fundos EU? Sim\n\n12 - DOCUMENTOS DE HABILITAÇÃO\nHabilitação para o exercício da atividade profissional: Não\n\n13 - CONDIÇÕES DE APRESENTAÇÃO\nPlataforma eletrónica utilizada pela entidade adjudicante: ACIN\nURL para Apresentação: https://www.acingov.pt\nAdmissibilidade da apresentação de propostas variantes: Não autorizado\nPrazo para apresentação das propostas: 21-09-2025 23:59\nPrazo durante o qual os concorrentes são obrigados a manter as respetivas propostas: 180 dias a contar do termo do prazo para a apresentação das propostas\nApresentação de Catálogo Eletrónico: Permitido\nIndicação de Subcontratação na Proposta: Inexistência de indicação de subcontratação\n\n14 - PRESTAÇÃO DE CAUÇÃO\nPrestação de caução: Não\n\n15 - FORNECIMENTO DAS PEÇAS DO CONCURSO, APRESENTAÇÃO DE PEDIDOS DE PARTICIPAÇÃO E APRESENTAÇÃO DAS PROPOSTAS\nLink para acesso às peças do concurso (URL): https://www.acingov.pt/acingovprod/2/zonaPublica/zona_publica_c/donwloadProcedurePiece/OTM1MTQ1\n\n20 - OUTROS REQUISITOS\nIdentificador do Lote: LOT-0001; LOT-0002; LOT-0003\nInformação sobre contratos reservados. Aplica-se a contratos reservados (54º-A)? Não\n\n21 - CRITÉRIO DE ADJUDICAÇÃO\nO Critério de adjudicação é diferenciado por lote? Não\nMultifator: Não\nMonofator:\nNome: Preço\n\n24 - CONDIÇÕES DO CONTRATO\nIdentificador do Lote: LOT-0001; LOT-0002; LOT-0003\nFaturação Eletrónica: Permitido\nObrigação de Subcontratação:\nCódigo da Obrigação de Subcontratação: Não é aplicável nenhuma obrigação de subcontratação.\n\n25 - COMPRA PÚBLICA ESTRATÉGICA\nCompra Pública Estratégica: Inexistência de contratação pública estratégica\n\n26 - INFORMAÇÕES ADICIONAIS\nIdentificador do Lote: LOT-0001; LOT-0002; LOT-0003\nContrato adequado para PME: Sim\nCobertura ACP (Acordo dos Contratos Públicos da Organização Mundial do Comércio): Não\n\n27 - IDENTIFICAÇÃO E CONTACTOS DO ÓRGÃO DE RECURSOS ADMINISTRATIVOS\nDesignação: Júri\nEndereço: Praça do Município\nCódigo postal: 9004-512\nLocalidade: Funchal\nTelefone: 291211000\nFax: \nEndereço eletrónico: dcpa@funchal.pt\nPrazo de interposição do recurso: 10 dias\n\n28 - IDENTIFICAÇÃO DO(S) AUTOR(ES) DE ANÚNCIO\nNome: Ana Bracamonte\nCargo: Vereadora da Câmara Municipal do Funchal\n419459744",
    "nipc": "511217315",
    "distrito": "Região Autónoma da Madeira",
    "concelho": "Funchal",
    "freguesia": "Freguesia de Sé (Funchal)",
    "site": "www.funchal.pt",
    "email": "dcpa@funchal.pt",
    "designacao_contrato": "Aquisição de Equipamentos de Rede",
    "descricao": "Aquisição de Equipamentos de Rede",
    "preco_base": "302.151,66 EUR",
    "prazo_execucao": "120 DIAS",
    "prazo_apresentacao_propostas": "21-09-2025 23:59",
    "fundos_eu": "Sim",
    "plataforma_eletronica": "ACIN",
    "url_procedimento": "https://www.acingov.pt",
    "autor_nome": "Ana Bracamonte",
    "autor_cargo": "Vereadora da Câmara Municipal do Funchal"
  },
  {
    "numero_procedimento": "N/A",
    "entidade": "Autoridade Tributária e Aduaneira",
    "link": "https://diariodarepublica.pt/dr/detalhe/contrato-publico/22643-933044052",
    "detalhes_completos": "1 - IDENTIFICAÇÃO E CONTACTOS DA ENTIDADE ADJUDICANTE\nDesignação da entidade adjudicante: Autoridade Tributária e Aduaneira\nNIPC: 600084779\nEndereço: RUA DA PRATA Nº 1O\nCódigo postal: 1149-027\nLocalidade: Lisboa\nPaís: Portugal\nNUT III: PT170\nDistrito: Lisboa\nConcelho: Lisboa\nFreguesia: Freguesia de Santa Maria Maior - Lisboa\nTelefone: 218812600\nFax: 218812935\nEndereço da Entidade (URL): https://www.portaldasfinancas.gov.pt/\nEndereço Eletrónico: at@at.gov.pt\neDelivery Gateway (URL): https://community.vortal.biz/public/\nFunção da Organização: Adquirente\nNorma jurídica da Entidade Adjudicante: Autoridade da administração central\nÁrea de atividade da Autoridade Adjudicante: Assuntos económicos\n\n2 - JORNAL OFICIAL DA UNIÃO EUROPEIA\nO procedimento a que este anúncio diz respeito também é publicitado no Jornal Oficial da União Europeia? Sim\n\n3 - AVISO\nModelo de Anúncio: Concurso limitado por prévia qualificação\nData de Envio do Anúncio: 22-08-2025\n\n5 - PROCESSO\nTipo de Procedimento: Concurso limitado por prévia qualificação\nPreço base do procedimento: Sim\nValor do preço base do procedimento: 1.499.937,90 EUR\nProcedimento com lotes? Não\n\n6 - OBJETO DO CONTRATO\nNúmero de referência interna: 39/CLPQ/AT/2025\nDesignação do contrato: Aquisição de serviços técnicos de informática para administração da plataforma Unix/Linux\nDescrição: Aquisição de serviços técnicos de informática para administração da plataforma Unix/Linux\nOpções: Não\nTipo de Contrato Principal: Aquisição de Serviços\nTipo de Contrato: Aquisição de Serviços\nClassificação CPV (Vocabulário Comum para os Contratos Públicos)\nObjeto principal\nVocabulário Principal: 72253200\nPreço base s/IVA: 1.499.937,90 EUR\n\n7 - INDICAÇÕES ADICIONAIS\nO contrato envolve aquisição conjunta (satisfação de várias entidades)? Não\nO contrato é adjudicado por uma central de compras? Não\n\n8 - TÉCNICAS\nO concurso destina-se à celebração de um acordo-quadro? Inexistência de acordo-quadro\nÉ utilizado um leilão eletrónico? Não\nSistema de Aquisição Dinâmico: Inexistência de sistema de aquisição dinâmico\n\n9 - LOCAL DA EXECUÇÃO DO CONTRATO\nLOCAL DA EXECUÇÃO DO CONTRATO (PROCEDIMENTO)\nPaís: Portugal\nNUT III: PT170\nLocalidade: Lisboa\nDistrito: Lisboa\nConcelho: Lisboa\nFreguesia: Todas\n\n10 - PRAZO DE EXECUÇÃO DO CONTRATO\nPrazo de execução do contrato: 36 MESES\nPrevisão de renovações: Sim\nIndicar número máximo de renovações: 2\nPrazo de renovações diferente do prazo inicial: Não\n\n11 - FUNDOS EU\nTêm fundos EU? Não\n\n12 - DOCUMENTOS DE HABILITAÇÃO\nHabilitação para o exercício da atividade profissional: Não\n\n13 - CONDIÇÕES DE APRESENTAÇÃO\nPlataforma eletrónica utilizada pela entidade adjudicante: VORTAL\nURL para Apresentação: https://community.vortal.biz/public/\nAdmissibilidade da apresentação de propostas variantes: Não autorizado\nPrazo para apresentação das candidaturas: 24-09-2025 17:00\nRequisitos mínimos \nRequisitos mínimos de capacidade técnica: Conforme consta das Peças do Procedimento\nRequisitos mínimos de capacidade financeira: Conforme consta das Peças do Procedimento\nPrazo durante o qual os concorrentes são obrigados a manter as respetivas propostas: 90 dias a contar do termo do prazo para a apresentação das propostas\nApresentação de Catálogo Eletrónico: Permitido\nIndicação de Subcontratação na Proposta: Inexistência de indicação de subcontratação\n\n14 - PRESTAÇÃO DE CAUÇÃO\nPrestação de caução: Sim\nPercentagem: 5%\nDescrição da Garantia Exigida: Conforme consta do Programa de Procedimento\n\n15 - FORNECIMENTO DAS PEÇAS DO CONCURSO, APRESENTAÇÃO DE PEDIDOS DE PARTICIPAÇÃO E APRESENTAÇÃO DAS PROPOSTAS\nLink para acesso às peças do concurso (URL): https://community.vortal.biz/Public/public-tender-documents/Wnl3TFJZdnJOS0xJTjE3MUNqK0lsaTdhRFkvYXloaC9hVDBRNVlWVWdTUHJYUG9TYnlCbzZqd1dyL3hpOTBYcUhVY0h5Sm0zdXBQNmR3aVdZemp6aEE9PWV3dWZm\n\n20 - OUTROS REQUISITOS\nInformação sobre contratos reservados. Aplica-se a contratos reservados (54º-A)? Não\n\n21 - CRITÉRIO DE ADJUDICAÇÃO\nMultifator: Sim\nFator: \nNome: Preço\nPonderação: 60%\nSubfatores: Não\nFator: \nNome: Qualidade\nPonderação: 40%\nSubfatores: Sim\nSubfatores: \nNome: SE SENIOR\nPonderação : 60%; \nNome: SE JUNIOR\nPonderação : 40%; \n\n24 - CONDIÇÕES DO CONTRATO\nFaturação Eletrónica: Permitido\nObrigação de Subcontratação:\nCódigo da Obrigação de Subcontratação: Não é aplicável nenhuma obrigação de subcontratação.\n\n25 - COMPRA PÚBLICA ESTRATÉGICA\nCompra Pública Estratégica: Inexistência de contratação pública estratégica\n\n26 - INFORMAÇÕES ADICIONAIS\nContrato adequado para PME: Sim\nCobertura ACP (Acordo dos Contratos Públicos da Organização Mundial do Comércio): Não\n\n27 - IDENTIFICAÇÃO E CONTACTOS DO ÓRGÃO DE RECURSOS ADMINISTRATIVOS\nDesignação: Secretária de Estado dos Assuntos Fiscais\nEndereço: Avenida do Infante D Henrique 1\nCódigo postal: 1149-009\nLocalidade: Lisboa\nTelefone: +351 218816800\nFax: +351 218816800\nEndereço eletrónico: seaf@mf.gov.pt\n\n28 - IDENTIFICAÇÃO DO(S) AUTOR(ES) DE ANÚNCIO\nNome: Helena Borges Alves\nCargo: Diretora Geral da AT\n419458845",
    "nipc": "600084779",
    "distrito": "Lisboa",
    "concelho": "Lisboa",
    "freguesia": "Freguesia de Santa Maria Maior - Lisboa",
    "site": "https://www.portaldasfinancas.gov.pt/",
    "email": "at@at.gov.pt",
    "designacao_contrato": "Aquisição de serviços técnicos de informática para administração da plataforma Unix/Linux",
    "descricao": "Aquisição de serviços técnicos de informática para administração da plataforma Unix/Linux",
    "preco_base": "1.499.937,90 EUR",
    "prazo_execucao": "36 MESES",
    "prazo_apresentacao_propostas": null,
    "fundos_eu": "Não",
    "plataforma_eletronica": "VORTAL",
    "url_procedimento": "https://community.vortal.biz/public/",
    "autor_nome": "Helena Borges Alves",
    "autor_cargo": "Diretora Geral da AT"
  },
  {
    "numero_procedimento": "N/A",
    "entidade": "SERVIÇO DE SAÚDE DA REGIÃO AUTONÓMA DA MADEIRA, EPERAM",
    "link": "https://diariodarepublica.pt/dr/detalhe/contrato-publico/22644-933044053",
    "detalhes_completos": "Alteração do Anúncio de procedimento n.º 20108/2025, de 2025-07-28, com o ID 419351835\n\n1 - IDENTIFICAÇÃO E CONTACTOS DA ENTIDADE ADJUDICANTE\nDesignação da entidade adjudicante: SERVIÇO DE SAÚDE DA REGIÃO AUTONÓMA DA MADEIRA, EPERAM\nNIPC: 511228848\nServiço/Órgão/Pessoa de contacto: NÚCLEO DE APROVISIONAMENTO\nEndereço: AVENIDA LUÍS DE CAMÕES, 57\nCódigo postal: 9004-514\nLocalidade: FUNCHAL\nPaís: Portugal\nNUT III: PT300\nDistrito: Região Autónoma da Madeira\nConcelho: Todos\nFreguesia: Todas\nTelefone: 291709600\nFax: 291709601\nEndereço da Entidade (URL): www.sesaram.pt\nEndereço Eletrónico: aprovisionamento@sesaram.pt\neDelivery Gateway (URL): https://www.acingov.pt\nFunção da Organização: Adquirente\nNorma jurídica da Entidade Adjudicante: Organismo de direito público\nÁrea de atividade da Autoridade Adjudicante: Serviços públicos das administrações públicas\n\n2 - JORNAL OFICIAL DA UNIÃO EUROPEIA\nO procedimento a que este anúncio diz respeito também é publicitado no Jornal Oficial da União Europeia? Sim\n\n3 - AVISO\nModelo de Anúncio: Concurso público\nData de Envio do Anúncio: 22-08-2025\n\n5 - PROCESSO\nTipo de Procedimento: Concurso público\nPreço base do procedimento: Sim\nValor do preço base do procedimento: 2.318.338,56 EUR\nProcedimento com lotes? Sim\nNº Máx. de Lotes Autorizado: 8\nNúmero máximo de lotes que podem ser adjudicados a um concorrente: 8\n\n6 - OBJETO DO CONTRATO\nNúmero de referência interna: I CP20250095\nDesignação do contrato: PRESTAÇÃO DE SERVIÇOS DE ALUGUER OPERACIONAL DE AUTOMÓVEIS LIGEIROS DE PASSAGEIROS PARA O SESARAM, EPERAM\nDescrição: PRESTAÇÃO DE SERVIÇOS DE ALUGUER OPERACIONAL DE AUTOMÓVEIS LIGEIROS DE PASSAGEIROS PARA O SESARAM, EPERAM\nOpções: Não\nTipo de Contrato Principal: Locação de Bens Móveis\nTipo de Contrato: Locação de Bens Móveis\nClassificação CPV (Vocabulário Comum para os Contratos Públicos)\nObjeto principal\nVocabulário Principal: 34110000\nPreço base s/IVA: 2.318.338,56 EUR\nLotes: \nNº: LOT-0001\nDescrição do Lote: lote 1 - INFERIOR SEGMENTO B\nPreço base s/IVA: 1.207.305,12 EUR\nClassificação CPV (Vocabulário Comum para os Contratos Públicos)\nObjeto principal\nVocabulário Principal: 34110000\nNº: LOT-0002\nDescrição do Lote: Lote 2 - MÉDIO INFERIOR SEGMENTO C\nPreço base s/IVA: 329.424,48 EUR\nClassificação CPV (Vocabulário Comum para os Contratos Públicos)\nObjeto principal\nVocabulário Principal: 34110000\nNº: LOT-0003\nDescrição do Lote: Lote 3 - ELÉTRICO INFERIOR SEGMENTO B\nPreço base s/IVA: 397.180,80 EUR\nClassificação CPV (Vocabulário Comum para os Contratos Públicos)\nObjeto principal\nVocabulário Principal: 34110000\nNº: LOT-0004\nDescrição do Lote: Lote 4 - SUV 4X4\nPreço base s/IVA: 33.699,36 EUR\nClassificação CPV (Vocabulário Comum para os Contratos Públicos)\nObjeto principal\nVocabulário Principal: 34110000\nNº: LOT-0005\nDescrição do Lote: Lote 5 - PICK-UP 4X4\nPreço base s/IVA: 61.656,00 EUR\nClassificação CPV (Vocabulário Comum para os Contratos Públicos)\nObjeto principal\nVocabulário Principal: 34110000\nNº: LOT-0006\nDescrição do Lote: Lote 6 - LIGEIRO DE MERCADORIAS\nPreço base s/IVA: 72.704,16 EUR\nClassificação CPV (Vocabulário Comum para os Contratos Públicos)\nObjeto principal\nVocabulário Principal: 34110000\nNº: LOT-0007\nDescrição do Lote: Lote 7 - LIGEIRO DE PASSAGEIROS (FURGÃO)\nPreço base s/IVA: 86.563,20 EUR\nClassificação CPV (Vocabulário Comum para os Contratos Públicos)\nObjeto principal\nVocabulário Principal: 34110000\nNº: LOT-0008\nDescrição do Lote: Lote 8 - LIGEIRO COMERCIAL\nPreço base s/IVA: 129.805,44 EUR\nClassificação CPV (Vocabulário Comum para os Contratos Públicos)\nObjeto principal\nVocabulário Principal: 34110000\n\n7 - INDICAÇÕES ADICIONAIS\nO contrato envolve aquisição conjunta (satisfação de várias entidades)? Não\nO contrato é adjudicado por uma central de compras? Não\n\n8 - TÉCNICAS\nO concurso destina-se à celebração de um acordo-quadro? Inexistência de acordo-quadro\nÉ utilizado um leilão eletrónico? Não\nÉ adotada uma fase de negociação? Não\nSistema de Aquisição Dinâmico: Inexistência de sistema de aquisição dinâmico\n\n9 - LOCAL DA EXECUÇÃO DO CONTRATO\nLOCAL DA EXECUÇÃO DO CONTRATO (PROCEDIMENTO)\nPaís: Portugal\nNUT III: PT300\nLocalidade: Funchal\nDistrito: Região Autónoma da Madeira\nConcelho: Todos\nFreguesia: Todas\nLOCAL DA EXECUÇÃO DO CONTRATO (LOTE)\nIdentificador do Lote: LOT-0001; LOT-0002; LOT-0003; LOT-0004; LOT-0005; LOT-0006; LOT-0007; LOT-0008\nPaís: Portugal\nNUT III: PT300\nLocalidade: Funchal\nDistrito: Região Autónoma da Madeira\nConcelho: Todos\nFreguesia: Todas\n\n10 - PRAZO DE EXECUÇÃO DO CONTRATO\nIdentificador do Lote: LOT-0001; LOT-0002; LOT-0003; LOT-0004; LOT-0005; LOT-0006; LOT-0007; LOT-0008\nPrazo de execução do contrato: 48 MESES\nPrevisão de renovações: Não\n\n11 - FUNDOS EU\nIdentificador do Lote: LOT-0001; LOT-0002; LOT-0003; LOT-0004; LOT-0005; LOT-0006; LOT-0007; LOT-0008\nTêm fundos EU? Não\n\n12 - DOCUMENTOS DE HABILITAÇÃO\nHabilitação para o exercício da atividade profissional: Não\n\n13 - CONDIÇÕES DE APRESENTAÇÃO\nPlataforma eletrónica utilizada pela entidade adjudicante: ACIN\nURL para Apresentação: https://www.acingov.pt\nAdmissibilidade da apresentação de propostas variantes: Não autorizado\nPrazo para apresentação das propostas: 24-09-2025 17:00\nPrazo durante o qual os concorrentes são obrigados a manter as respetivas propostas: 66 dias a contar do termo do prazo para a apresentação das propostas\nApresentação de Catálogo Eletrónico: Necessário\nIndicação de Subcontratação na Proposta: Inexistência de indicação de subcontratação\n\n14 - PRESTAÇÃO DE CAUÇÃO\nPrestação de caução: Sim\nPercentagem: 2%\nDescrição da Garantia Exigida: O valor da caução é de 2.00% do preço contratual.\n\n15 - FORNECIMENTO DAS PEÇAS DO CONCURSO, APRESENTAÇÃO DE PEDIDOS DE PARTICIPAÇÃO E APRESENTAÇÃO DAS PROPOSTAS\nLink para acesso às peças do concurso (URL): https://www.acingov.pt/acingovprod/2/zonaPublica/zona_publica_c/donwloadProcedurePiece/OTE4Njky\n\n20 - OUTROS REQUISITOS\nIdentificador do Lote: LOT-0001; LOT-0002; LOT-0003; LOT-0004; LOT-0005; LOT-0006; LOT-0007; LOT-0008\nInformação sobre contratos reservados. Aplica-se a contratos reservados (54º-A)? Não\n\n21 - CRITÉRIO DE ADJUDICAÇÃO\nO Critério de adjudicação é diferenciado por lote? Não\nMultifator: Não\nMonofator:\nNome: Preço\n\n24 - CONDIÇÕES DO CONTRATO\nIdentificador do Lote: LOT-0001; LOT-0002; LOT-0003; LOT-0004; LOT-0005; LOT-0006; LOT-0007; LOT-0008\nFaturação Eletrónica: Permitido\nObrigação de Subcontratação:\nCódigo da Obrigação de Subcontratação: Não é aplicável nenhuma obrigação de subcontratação.\n\n25 - COMPRA PÚBLICA ESTRATÉGICA\nCompra Pública Estratégica: Inexistência de contratação pública estratégica\n\n26 - INFORMAÇÕES ADICIONAIS\nIdentificador do Lote: LOT-0001; LOT-0002; LOT-0003; LOT-0004; LOT-0005; LOT-0006; LOT-0007; LOT-0008\nContrato adequado para PME: Não\nCobertura ACP (Acordo dos Contratos Públicos da Organização Mundial do Comércio): Não\n\n27 - IDENTIFICAÇÃO E CONTACTOS DO ÓRGÃO DE RECURSOS ADMINISTRATIVOS\nDesignação: Conselho de Administração\nEndereço: Avenida Luís de Camões, nº 57\nCódigo postal: 9004-514\nLocalidade: Funchal\nTelefone: 291709600\nFax: 291709601\nEndereço eletrónico: aprovisionamento@sesaram.pt\n\n28 - IDENTIFICAÇÃO DO(S) AUTOR(ES) DE ANÚNCIO\nNome: Célia Maria Sousa Gonçalves\nCargo: Assistente Técnica\n\n29 - ALTERAÇÃO\nMotivo da Alteração: Informações atualizadas\nIdentificador da Versão do Anúncio a Alterar: 15ae5619-5f56-4fab-926d-59c3605d92b1-01\nIdentificador das Secções Alteradas do Anúncio Anterior: Condições de Apresentação\nDescrição das Alterações: Conforme o indicado na Ata do Júri (Resposta a pedido de esclarecimentos) a disponibilizar na plataforma ACINGOV \nAlteração dos Documentos do Concurso: Não\n419459136",
    "nipc": "511228848",
    "distrito": "Região Autónoma da Madeira",
    "concelho": "Todos",
    "freguesia": "Todas",
    "site": "www.sesaram.pt",
    "email": "aprovisionamento@sesaram.pt",
    "designacao_contrato": "PRESTAÇÃO DE SERVIÇOS DE ALUGUER OPERACIONAL DE AUTOMÓVEIS LIGEIROS DE PASSAGEIROS PARA O SESARAM, EPERAM",
    "descricao": "PRESTAÇÃO DE SERVIÇOS DE ALUGUER OPERACIONAL DE AUTOMÓVEIS LIGEIROS DE PASSAGEIROS PARA O SESARAM, EPERAM",
    "preco_base": "2.318.338,56 EUR",
    "prazo_execucao": "48 MESES",
    "prazo_apresentacao_propostas": "24-09-2025 17:00",
    "fundos_eu": "Não",
    "plataforma_eletronica": "ACIN",
    "url_procedimento": "https://www.acingov.pt",
    "autor_nome": "Célia Maria Sousa Gonçalves",
    "autor_cargo": "Assistente Técnica"
  },
  {
    "numero_procedimento": "N/A",
    "entidade": "SPMS- Serviços Partilhados do M. da Saúde, E.P.E.",
    "link": "https://diariodarepublica.pt/dr/detalhe/contrato-publico/22645-933044054",
    "detalhes_completos": "1 - IDENTIFICAÇÃO E CONTACTOS DA ENTIDADE ADJUDICANTE\nDesignação da entidade adjudicante: SPMS- Serviços Partilhados do M. da Saúde, E.P.E.\nNIPC: 509540716\nEndereço: Avenida da República 61\nCódigo postal: 1050-189\nLocalidade: Lisboa\nPaís: Portugal\nNUT III: PT170\nDistrito: Lisboa\nConcelho: Lisboa\nFreguesia: Todas\nTelefone: 211545600\nFax: 211545649\nEndereço da Entidade (URL): www.spms.min-saude.pt/\nEndereço Eletrónico: contratacao@spms.min-saude.pt\neDelivery Gateway (URL): https://community.vortal.biz/public/\nFunção da Organização: Adquirente\nNorma jurídica da Entidade Adjudicante: Empresa pública\nÁrea de atividade da Autoridade Adjudicante: Saúde\n\n2 - JORNAL OFICIAL DA UNIÃO EUROPEIA\nO procedimento a que este anúncio diz respeito também é publicitado no Jornal Oficial da União Europeia? Sim\n\n3 - AVISO\nModelo de Anúncio: Concurso público\nData de Envio do Anúncio: 22-08-2025\n\n5 - PROCESSO\nTipo de Procedimento: Concurso público\nPreço base do procedimento: Sim\nValor do preço base do procedimento: 723.987,84 EUR\nProcedimento com lotes? Não\n\n6 - OBJETO DO CONTRATO\nNúmero de referência interna: 20250378\nDesignação do contrato: (DAG) Aquisição de Serviços de Gestão de Projeto, Arquitetura, Desenho, Análise, Desenvolvimento, Testes, Implementação, Formação e Ativação do SI para Gestão de Referenciação (PRR) (20250378)\nDescrição: (DAG) Aquisição de Serviços de Gestão de Projeto, Arquitetura, Desenho, Análise, Desenvolvimento, Testes, Implementação, Formação e Ativação do SI para Gestão de Referenciação para a Rede Nacional de Cuidados Continuados Integradas e a Rede Nacional de Cuidados Paliativos - Reforma dos SI disponibilizados ao Profissional - Pilar 3 - PRR (20250378)\nOpções: Não\nTipo de Contrato Principal: Aquisição de Serviços\nTipo de Contrato: Aquisição de Serviços\nClassificação CPV (Vocabulário Comum para os Contratos Públicos)\nObjeto principal\nVocabulário Principal: 72500000\nPreço base s/IVA: 723.987,84 EUR\n\n7 - INDICAÇÕES ADICIONAIS\nO contrato envolve aquisição conjunta (satisfação de várias entidades)? Não\nO contrato é adjudicado por uma central de compras? Não\n\n8 - TÉCNICAS\nO concurso destina-se à celebração de um acordo-quadro? Inexistência de acordo-quadro\nÉ utilizado um leilão eletrónico? Não\nÉ adotada uma fase de negociação? Não\nSistema de Aquisição Dinâmico: Inexistência de sistema de aquisição dinâmico\n\n9 - LOCAL DA EXECUÇÃO DO CONTRATO\nLOCAL DA EXECUÇÃO DO CONTRATO (PROCEDIMENTO)\nPaís: Portugal\nNUT III: PT170\nLocalidade: Lisboa\nDistrito: Lisboa\nConcelho: Lisboa\nFreguesia: Todas\n\n10 - PRAZO DE EXECUÇÃO DO CONTRATO\nPrazo de execução do contrato: 10 MESES\nPrevisão de renovações: Não\n\n11 - FUNDOS EU\nTêm fundos EU? Sim\n\n12 - DOCUMENTOS DE HABILITAÇÃO\nHabilitação para o exercício da atividade profissional: Não\n\n13 - CONDIÇÕES DE APRESENTAÇÃO\nPlataforma eletrónica utilizada pela entidade adjudicante: VORTAL\nURL para Apresentação: https://community.vortal.biz/public/\nAdmissibilidade da apresentação de propostas variantes: Não autorizado\nPrazo para apresentação das propostas: 22-09-2025 18:00\nPrazo durante o qual os concorrentes são obrigados a manter as respetivas propostas: 180 dias a contar do termo do prazo para a apresentação das propostas\nApresentação de Catálogo Eletrónico: Permitido\nIndicação de Subcontratação na Proposta: Inexistência de indicação de subcontratação\n\n14 - PRESTAÇÃO DE CAUÇÃO\nPrestação de caução: Sim\nPercentagem: 5%\nDescrição da Garantia Exigida: Ver Peças do Procedimento - v. artigo 30.º do Programa de Concurso\n\n15 - FORNECIMENTO DAS PEÇAS DO CONCURSO, APRESENTAÇÃO DE PEDIDOS DE PARTICIPAÇÃO E APRESENTAÇÃO DAS PROPOSTAS\nLink para acesso às peças do concurso (URL): https://community.vortal.biz/Public/public-tender-documents/YnJLK1ByVU1zZURMSlBsSGRkRVdJZmhSZXdBemhOejV1UEpGK1pyY3JjYk1vNU10Vk9hWHQ2Mkx0dUZhWm9PSG1rTjFVYTk2OXAzZ1ZBalhrSXdSOFE9PUZLb15m\n\n20 - OUTROS REQUISITOS\nInformação sobre contratos reservados. Aplica-se a contratos reservados (54º-A)? Não\n\n21 - CRITÉRIO DE ADJUDICAÇÃO\nMultifator: Sim\nFator: \nNome: Preço\nPonderação: 40%\nSubfatores: Não\nFator: \nNome: Qualidade\nPonderação: 60%\nSubfatores: Sim\nSubfatores: \nNome: Gestor de Projeto\nPonderação : 16%; \nNome: 1.º Perfil de Consultor Funcional (Análise)\nPonderação : 7%; \nNome: 2.º Perfil de Consultor Funcional (Análise)\nPonderação : 7%; \nNome: 3.º Perfil de Consultor Funcional (Análise)\nPonderação : 7%; \nNome: 1.º Perfil de Consultor de Testes\nPonderação : 7%; \nNome: 2.º Perfil de Consultor de Testes\nPonderação : 7%; \nNome: 1.º Perfil de Consultor Tecnológico Sénior - Des. Software I (Oracle APEX)\nPonderação : 7%; \nNome: 2.º Perfil de Consultor Tecnológico Sénior - Des. Software I (Oracle APEX)\nPonderação : 7%; \nNome: 1.º Perfil de Consultor Tecnológico Sénior - Des. Software II (Oracle APEX)\nPonderação : 7%; \nNome: 2.º Perfil de Consultor Tecnológico Sénior - Des. Software II (Oracle APEX)\nPonderação : 7%; \nNome: 3.º Perfil de Consultor Tecnológico Sénior - Des. Software II (Oracle APEX)\nPonderação : 7%; \nNome: 4.º Perfil de Consultor Tecnológico Sénior - Des. Software II (Oracle APEX)\nPonderação : 7%; \nNome: Consultor Tecnológico Sénior - Des. Software (Interoperabilidade)\nPonderação : 7%; \n\n24 - CONDIÇÕES DO CONTRATO\nFaturação Eletrónica: Permitido\nObrigação de Subcontratação:\nCódigo da Obrigação de Subcontratação: O contratante tem de indicar qualquer mudança de subcontratantes durante a execução do contrato.\n\n25 - COMPRA PÚBLICA ESTRATÉGICA\nCompra Pública Estratégica: Inexistência de contratação pública estratégica\n\n26 - INFORMAÇÕES ADICIONAIS\nContrato adequado para PME: Sim\nCobertura ACP (Acordo dos Contratos Públicos da Organização Mundial do Comércio): Não\n\n27 - IDENTIFICAÇÃO E CONTACTOS DO ÓRGÃO DE RECURSOS ADMINISTRATIVOS\nDesignação: Conselho de Administração da SPMS, EPE\nEndereço: Avenida da República, 61\nCódigo postal: 1050-189\nLocalidade: Lisboa\nTelefone: +351 211545600\nFax: +351 211545649\nEndereço eletrónico: contratacao@spms.min-saude.pt\n\n28 - IDENTIFICAÇÃO DO(S) AUTOR(ES) DE ANÚNCIO\nNome: Laura Raposo\nCargo: Diretora da Direção de Administração Geral\n419460942",
    "nipc": "509540716",
    "distrito": "Lisboa",
    "concelho": "Lisboa",
    "freguesia": "Todas",
    "site": "www.spms.min-saude.pt/",
    "email": "contratacao@spms.min-saude.pt",
    "designacao_contrato": "(DAG) Aquisição de Serviços de Gestão de Projeto, Arquitetura, Desenho, Análise, Desenvolvimento, Testes, Implementação, Formação e Ativação do SI para Gestão de Referenciação (PRR) (20250378)",
    "descricao": "(DAG) Aquisição de Serviços de Gestão de Projeto, Arquitetura, Desenho, Análise, Desenvolvimento, Testes, Implementação, Formação e Ativação do SI para Gestão de Referenciação para a Rede Nacional de Cuidados Continuados Integradas e a Rede Nacional de Cuidados Paliativos - Reforma dos SI disponibilizados ao Profissional - Pilar 3 - PRR (20250378)",
    "preco_base": "723.987,84 EUR",
    "prazo_execucao": "10 MESES",
    "prazo_apresentacao_propostas": "22-09-2025 18:00",
    "fundos_eu": "Sim",
    "plataforma_eletronica": "VORTAL",
    "url_procedimento": "https://community.vortal.biz/public/",
    "autor_nome": "Laura Raposo",
    "autor_cargo": "Diretora da Direção de Administração Geral"
  },
  {
    "numero_procedimento": "N/A",
    "entidade": "Município de Ponta Delgada",
    "link": "https://diariodarepublica.pt/dr/detalhe/contrato-publico/22646-933044055",
    "detalhes_completos": "1 - IDENTIFICAÇÃO E CONTACTOS DA ENTIDADE ADJUDICANTE\nDesignação da entidade adjudicante: Município de Ponta Delgada\nNIPC: 512012814\nEndereço: Praça do Município\nCódigo postal: 9504-523\nLocalidade: Região Autónoma dos Açores\nPaís: Portugal\nNUT III: PT200\nDistrito: Região Autónoma dos Açores\nConcelho: Ponta Delgada\nFreguesia: Freguesia de Ponta Delgada (São Sebastião)\nTelefone: 296304400\nFax: 296304401\nEndereço da Entidade (URL): https://www.cm-pontadelgada.pt/\nEndereço Eletrónico: aaa@aaa.pt\neDelivery Gateway (URL): https://community.vortal.biz/public/\nFunção da Organização: Adquirente\nNorma jurídica da Entidade Adjudicante: Organismo de direito público\nÁrea de atividade da Autoridade Adjudicante: Serviços públicos das administrações públicas\n\n2 - JORNAL OFICIAL DA UNIÃO EUROPEIA\nO procedimento a que este anúncio diz respeito também é publicitado no Jornal Oficial da União Europeia? Sim\n\n3 - AVISO\nModelo de Anúncio: Concurso público\nData de Envio do Anúncio: 22-08-2025\n\n5 - PROCESSO\nTipo de Procedimento: Concurso público\nPreço base do procedimento: Sim\nValor do preço base do procedimento: 228.195,00 EUR\nProcedimento com lotes? Sim\nNº Máx. de Lotes Autorizado: 2\nNúmero máximo de lotes que podem ser adjudicados a um concorrente: 2\n\n6 - OBJETO DO CONTRATO\nNúmero de referência interna: 46/CP/L/25/V-DGFP-NIPG25101/25\nDesignação do contrato: Locação com montagem, desmontagem e manutenção de material de iluminação e sonorização 2025/2026\nDescrição: Locação com montagem, desmontagem e manutenção de material de iluminação e sonorização 2025/2026\nOpções: Não\nTipo de Contrato Principal: Locação de Bens Móveis\nTipo de Contrato: Locação de Bens Móveis\nClassificação CPV (Vocabulário Comum para os Contratos Públicos)\nObjeto principal\nVocabulário Principal: 31500000\nPreço base s/IVA: 228.195,00 EUR\nLotes: \nNº: LOT-0001\nDescrição do Lote: Lote 1\nPreço base s/IVA: 212.508,00 EUR\nClassificação CPV (Vocabulário Comum para os Contratos Públicos)\nObjeto principal\nVocabulário Principal: 31500000\nNº: LOT-0002\nDescrição do Lote: Lote 2\nPreço base s/IVA: 15.687,00 EUR\nClassificação CPV (Vocabulário Comum para os Contratos Públicos)\nObjeto principal\nVocabulário Principal: 31500000\n\n7 - INDICAÇÕES ADICIONAIS\nO contrato envolve aquisição conjunta (satisfação de várias entidades)? Não\nO contrato é adjudicado por uma central de compras? Não\n\n8 - TÉCNICAS\nO concurso destina-se à celebração de um acordo-quadro? Inexistência de acordo-quadro\nÉ utilizado um leilão eletrónico? Não\nÉ adotada uma fase de negociação? Não\nSistema de Aquisição Dinâmico: Inexistência de sistema de aquisição dinâmico\n\n9 - LOCAL DA EXECUÇÃO DO CONTRATO\nLOCAL DA EXECUÇÃO DO CONTRATO (PROCEDIMENTO)\nPaís: Portugal\nNUT III: PT200\nLocalidade: Região Autónoma dos Açores\nDistrito: Região Autónoma dos Açores\nConcelho: Ponta Delgada\nFreguesia: Freguesia de Ponta Delgada (São Sebastião)\nLOCAL DA EXECUÇÃO DO CONTRATO (LOTE)\nIdentificador do Lote: LOT-0001; LOT-0002\nPaís: Portugal\nNUT III: PT200\nLocalidade: Região Autónoma dos Açores\nDistrito: Região Autónoma dos Açores\nConcelho: Ponta Delgada\nFreguesia: Freguesia de Ponta Delgada (São Sebastião)\n\n10 - PRAZO DE EXECUÇÃO DO CONTRATO\nIdentificador do Lote: LOT-0001; LOT-0002\nPrazo de execução do contrato: 139 DIAS\nPrevisão de renovações: Não\n\n11 - FUNDOS EU\nIdentificador do Lote: LOT-0001; LOT-0002\nTêm fundos EU? Não\n\n12 - DOCUMENTOS DE HABILITAÇÃO\nHabilitação para o exercício da atividade profissional: Não\n\n13 - CONDIÇÕES DE APRESENTAÇÃO\nPlataforma eletrónica utilizada pela entidade adjudicante: VORTAL\nURL para Apresentação: https://community.vortal.biz/public/\nAdmissibilidade da apresentação de propostas variantes: Não autorizado\nPrazo para apresentação das propostas: 19-09-2025 17:30\nPrazo durante o qual os concorrentes são obrigados a manter as respetivas propostas: 90 dias a contar do termo do prazo para a apresentação das propostas\nApresentação de Catálogo Eletrónico: Não autorizado\nIndicação de Subcontratação na Proposta: Inexistência de indicação de subcontratação\n\n14 - PRESTAÇÃO DE CAUÇÃO\nPrestação de caução: Sim\nPercentagem: 2%\nDescrição da Garantia Exigida: Conforme artigo n37.º do Programa de Procedimento\n\n15 - FORNECIMENTO DAS PEÇAS DO CONCURSO, APRESENTAÇÃO DE PEDIDOS DE PARTICIPAÇÃO E APRESENTAÇÃO DAS PROPOSTAS\nLink para acesso às peças do concurso (URL): https://community.vortal.biz/Public/public-tender-documents/QW9mVE02MlNtMm4xemZBVisxRGE1ZVRFM3NmOXk0SkhVRS94MHh3am41dWVFWHk5QTlDS1cySWsyVWdoSUJ3ZlkrMnVWeVI3U1FOMFBuMzRpa2d4aWc9PW1yYjN1\n\n20 - OUTROS REQUISITOS\nIdentificador do Lote: LOT-0001; LOT-0002\nInformação sobre contratos reservados. Aplica-se a contratos reservados (54º-A)? Não\n\n21 - CRITÉRIO DE ADJUDICAÇÃO\nO Critério de adjudicação é diferenciado por lote? Sim\nIdentificador do lote: LOT-0001\nMultifator: Sim\nFator: \nNome: Preço\nPonderação: 40%\nSubfatores: Não\nFator: \nNome: Qualidade\nPonderação: 40%\nSubfatores: Não\nFator: \nNome: Outros\nOutro Nome: Estética\nPonderação: 20%\nSubfatores: Não\nO Critério de adjudicação é diferenciado por lote? Sim\nIdentificador do lote: LOT-0002\nMultifator: Sim\nFator: \nNome: Preço\nPonderação: 40%\nSubfatores: Não\nFator: \nNome: Outros\nOutro Nome: Número de postes\nPonderação: 60%\nSubfatores: Não\n\n24 - CONDIÇÕES DO CONTRATO\nIdentificador do Lote: LOT-0001; LOT-0002\nFaturação Eletrónica: Permitido\nObrigação de Subcontratação:\nCódigo da Obrigação de Subcontratação: Não é aplicável nenhuma obrigação de subcontratação.\n\n25 - COMPRA PÚBLICA ESTRATÉGICA\nCompra Pública Estratégica: Redução dos impactos ambientais\nDescrição do Processo de Adjudicação Estratégico: Conforme as peças do procedimento\nCritérios de contratos Públicos Ecológicos: Critérios de contratação pública ecológica nacional\nCategorias da estratégia nacional: Outros\nOutra categoria (Descrição): não aplicável\nDiretiva Veículos Não Poluentes: Não\nCritério de Acessibilidade: Os critérios de acessibilidade para as pessoas com deficiência estão incluídos\n\n26 - INFORMAÇÕES ADICIONAIS\nIdentificador do Lote: LOT-0001; LOT-0002\nContrato adequado para PME: Sim\nCobertura ACP (Acordo dos Contratos Públicos da Organização Mundial do Comércio): Não\n\n27 - IDENTIFICAÇÃO E CONTACTOS DO ÓRGÃO DE RECURSOS ADMINISTRATIVOS\nDesignação: Municipio de Ponta Delgada\nEndereço: Praça do Município\nCódigo postal: 9504-523\nLocalidade: Ponta Delgada\nTelefone: +351 296304400\nFax: +351 296304401\nEndereço eletrónico: geral@mpdelgada.pt\n\n28 - IDENTIFICAÇÃO DO(S) AUTOR(ES) DE ANÚNCIO\nNome: Pedro do Nascimento Cabral\nCargo: Presidente da Câmara Municipal\n419454146",
    "nipc": "512012814",
    "distrito": "Região Autónoma dos Açores",
    "concelho": "Ponta Delgada",
    "freguesia": "Freguesia de Ponta Delgada (São Sebastião)",
    "site": "https://www.cm-pontadelgada.pt/",
    "email": "aaa@aaa.pt",
    "designacao_contrato": "Locação com montagem, desmontagem e manutenção de material de iluminação e sonorização 2025/2026",
    "descricao": "Locação com montagem, desmontagem e manutenção de material de iluminação e sonorização 2025/2026",
    "preco_base": "228.195,00 EUR",
    "prazo_execucao": "139 DIAS",
    "prazo_apresentacao_propostas": "19-09-2025 17:30",
    "fundos_eu": "Não",
    "plataforma_eletronica": "VORTAL",
    "url_procedimento": "https://community.vortal.biz/public/",
    "autor_nome": "Pedro do Nascimento Cabral",
    "autor_cargo": "Presidente da Câmara Municipal"
  },
  {
    "numero_procedimento": "N/A",
    "entidade": "Município da Guarda",
    "link": "https://diariodarepublica.pt/dr/detalhe/contrato-publico/22648-933044056",
    "detalhes_completos": "1 - IDENTIFICAÇÃO E CONTACTOS DA ENTIDADE ADJUDICANTE\nDesignação da entidade adjudicante: Município da Guarda\nNIPC: 501131140\nEndereço: Praça do Município, nº 1\nCódigo postal: 6301-854\nLocalidade: Guarda\nPaís: Portugal\nNUT III: PT16J\nDistrito: Guarda\nConcelho: Guarda\nFreguesia: Freguesia de Guarda\nTelefone: 271220200\nFax: 271220280\nEndereço da Entidade (URL): www.mun-guarda.pt\nEndereço Eletrónico: geral@mun-guarda.pt\neDelivery Gateway (URL): https://community.vortal.biz/public/\nFunção da Organização: Adquirente\nNorma jurídica da Entidade Adjudicante: Autoridade da administração central\nÁrea de atividade da Autoridade Adjudicante: Serviços públicos das administrações públicas\n\n2 - JORNAL OFICIAL DA UNIÃO EUROPEIA\nO procedimento a que este anúncio diz respeito também é publicitado no Jornal Oficial da União Europeia? Sim\n\n3 - AVISO\nModelo de Anúncio: Concurso público\nData de Envio do Anúncio: 22-08-2025\n\n5 - PROCESSO\nTipo de Procedimento: Concurso público\nPreço base do procedimento: Sim\nValor do preço base do procedimento: 590.000,00 EUR\nProcedimento com lotes? Não\n\n6 - OBJETO DO CONTRATO\nNúmero de referência interna: Concessão Nº 2/2025\nDesignação do contrato: Concessão de Uso Privativo do Dominio Público no Municipio da Guarda para Instalação e Exploração Publicitária de Mobiliário Urbano\nDescrição: Concessão de Uso Privativo do Dominio Público no Municipio da Guarda para Instalação e Exploração Publicitária de Mobiliário Urbano\nOpções: Não\nTipo de Contrato Principal: Concessão de Serviços Públicos\nTipo de Contrato: Concessão de Serviços Públicos\nClassificação CPV (Vocabulário Comum para os Contratos Públicos)\nObjeto principal\nVocabulário Principal: 79341200\nPreço base s/IVA: 590.000,00 EUR\n\n7 - INDICAÇÕES ADICIONAIS\nO contrato envolve aquisição conjunta (satisfação de várias entidades)? Não\nO contrato é adjudicado por uma central de compras? Não\n\n8 - TÉCNICAS\nO concurso destina-se à celebração de um acordo-quadro? Inexistência de acordo-quadro\nÉ utilizado um leilão eletrónico? Não\nÉ adotada uma fase de negociação? Não\nSistema de Aquisição Dinâmico: Inexistência de sistema de aquisição dinâmico\n\n9 - LOCAL DA EXECUÇÃO DO CONTRATO\nLOCAL DA EXECUÇÃO DO CONTRATO (PROCEDIMENTO)\nPaís: Portugal\nNUT III: PT16J\nLocalidade: Guarda\nDistrito: Guarda\nConcelho: Guarda\nFreguesia: Freguesia de Guarda\n\n10 - PRAZO DE EXECUÇÃO DO CONTRATO\nPrazo de execução do contrato: 15 ANOS\nPrevisão de renovações: Não\n\n11 - FUNDOS EU\nTêm fundos EU? Não\n\n12 - DOCUMENTOS DE HABILITAÇÃO\nHabilitação para o exercício da atividade profissional: Não\n\n13 - CONDIÇÕES DE APRESENTAÇÃO\nPlataforma eletrónica utilizada pela entidade adjudicante: VORTAL\nURL para Apresentação: https://community.vortal.biz/public/\nAdmissibilidade da apresentação de propostas variantes: Não autorizado\nPrazo para apresentação das propostas: 09-10-2025 17:00\nPrazo durante o qual os concorrentes são obrigados a manter as respetivas propostas: 180 dias a contar do termo do prazo para a apresentação das propostas\nApresentação de Catálogo Eletrónico: Permitido\nIndicação de Subcontratação na Proposta: Inexistência de indicação de subcontratação\n\n14 - PRESTAÇÃO DE CAUÇÃO\nPrestação de caução: Sim\nPercentagem: 3%\nDescrição da Garantia Exigida: Conforme anexos ao programa de procedimento\n\n15 - FORNECIMENTO DAS PEÇAS DO CONCURSO, APRESENTAÇÃO DE PEDIDOS DE PARTICIPAÇÃO E APRESENTAÇÃO DAS PROPOSTAS\nLink para acesso às peças do concurso (URL): https://community.vortal.biz/Public/public-tender-documents/c2dqMUJlQjAveVdpK0JNQ29zQmZMUkxucytCT2ZSRkZ5OHNST3BBTkJOWE1nVDJVdnVPWitKY2F3OE1TdDNGRUsxK1loTVdJdUNleUlyNTNNbzBoakE9PVlKNF5U\n\n20 - OUTROS REQUISITOS\nInformação sobre contratos reservados. Aplica-se a contratos reservados (54º-A)? Não\n\n21 - CRITÉRIO DE ADJUDICAÇÃO\nMultifator: Sim\nFator: \nNome: Preço\nPonderação: 60%\nSubfatores: Não\nFator: \nNome: Qualidade\nPonderação: 20%\nSubfatores: Não\nFator: \nNome: Qualidade\nPonderação: 20%\nSubfatores: Não\n\n24 - CONDIÇÕES DO CONTRATO\nFaturação Eletrónica: Permitido\nObrigação de Subcontratação:\nCódigo da Obrigação de Subcontratação: Não é aplicável nenhuma obrigação de subcontratação.\n\n25 - COMPRA PÚBLICA ESTRATÉGICA\nCompra Pública Estratégica: Inexistência de contratação pública estratégica\n\n26 - INFORMAÇÕES ADICIONAIS\nContrato adequado para PME: Sim\nCobertura ACP (Acordo dos Contratos Públicos da Organização Mundial do Comércio): Não\n\n27 - IDENTIFICAÇÃO E CONTACTOS DO ÓRGÃO DE RECURSOS ADMINISTRATIVOS\nDesignação: Presidente da Câmara Municipal da Guarda\nEndereço: Praça do Municipio\nCódigo postal: 6301-854\nLocalidade: Guarda\nTelefone: +351 271220200\nFax: +351 271220280\nEndereço eletrónico: contratacaopublica@mun-guarda.pt\n\n28 - IDENTIFICAÇÃO DO(S) AUTOR(ES) DE ANÚNCIO\nNome: Sérgio Fernando da Silva Costa\nCargo: O Presidente da Cãmara Municipal da Guarda\n419459882",
    "nipc": "501131140",
    "distrito": "Guarda",
    "concelho": "Guarda",
    "freguesia": "Freguesia de Guarda",
    "site": "www.mun-guarda.pt",
    "email": "geral@mun-guarda.pt",
    "designacao_contrato": "Concessão de Uso Privativo do Dominio Público no Municipio da Guarda para Instalação e Exploração Publicitária de Mobiliário Urbano",
    "descricao": "Concessão de Uso Privativo do Dominio Público no Municipio da Guarda para Instalação e Exploração Publicitária de Mobiliário Urbano",
    "preco_base": "590.000,00 EUR",
    "prazo_execucao": "15 ANOS",
    "prazo_apresentacao_propostas": "09-10-2025 17:00",
    "fundos_eu": "Não",
    "plataforma_eletronica": "VORTAL",
    "url_procedimento": "https://community.vortal.biz/public/",
    "autor_nome": "Sérgio Fernando da Silva Costa",
    "autor_cargo": "O Presidente da Cãmara Municipal da Guarda"
  },
  {
    "numero_procedimento": "N/A",
    "entidade": "CÂMARA MUNICIPAL DE ALMADA",
    "link": "https://diariodarepublica.pt/dr/detalhe/contrato-publico/22649-933044057",
    "detalhes_completos": "Alteração do Anúncio de procedimento n.º 21184/2025, de 2025-08-06, com o ID 419393429\n\n1 - IDENTIFICAÇÃO E CONTACTOS DA ENTIDADE ADJUDICANTE\nDesignação da entidade adjudicante: CÂMARA MUNICIPAL DE ALMADA\nNIPC: 500051054\nEndereço: Largo Luís de Camões\nCódigo postal: 2800-158\nLocalidade: Setúbal\nPaís: Portugal\nNUT III: PT170\nDistrito: Setúbal\nConcelho: Almada\nFreguesia: União das Freguesias de Almada, Cova da Piedade, Pragal e Cacilhas\nTelefone: 212724000\nFax: 212724599\nEndereço da Entidade (URL): www.m-almada.pt\nEndereço Eletrónico: almadainforma@cma.m-almada.pt\neDelivery Gateway (URL): https://community.vortal.biz/public/\nFunção da Organização: Adquirente\nNorma jurídica da Entidade Adjudicante: Autoridade local\nÁrea de atividade da Autoridade Adjudicante: Serviços públicos das administrações públicas\n\n2 - JORNAL OFICIAL DA UNIÃO EUROPEIA\nO procedimento a que este anúncio diz respeito também é publicitado no Jornal Oficial da União Europeia? Sim\n\n3 - AVISO\nModelo de Anúncio: Concurso público\nData de Envio do Anúncio: 22-08-2025\n\n5 - PROCESSO\nTipo de Procedimento: Concurso público\nPreço base do procedimento: Sim\nValor do preço base do procedimento: 365.853,66 EUR\nProcedimento com lotes? Não\n\n6 - OBJETO DO CONTRATO\nNúmero de referência interna: CPN00573S2025\nDesignação do contrato: Aquisição de serviços de SOC - Security Operation Center pelo prazo de 2 anos\nDescrição: Aquisição de serviços de SOC - Security Operation Center pelo prazo de 2 anos\nOpções: Não\nTipo de Contrato Principal: Aquisição de Serviços\nTipo de Contrato: Aquisição de Serviços\nClassificação CPV (Vocabulário Comum para os Contratos Públicos)\nObjeto principal\nVocabulário Principal: 72910000\nPreço base s/IVA: 365.853,66 EUR\n\n7 - INDICAÇÕES ADICIONAIS\nO contrato envolve aquisição conjunta (satisfação de várias entidades)? Não\nO contrato é adjudicado por uma central de compras? Não\n\n8 - TÉCNICAS\nO concurso destina-se à celebração de um acordo-quadro? Inexistência de acordo-quadro\nÉ utilizado um leilão eletrónico? Não\nÉ adotada uma fase de negociação? Não\nSistema de Aquisição Dinâmico: Inexistência de sistema de aquisição dinâmico\n\n9 - LOCAL DA EXECUÇÃO DO CONTRATO\nLOCAL DA EXECUÇÃO DO CONTRATO (PROCEDIMENTO)\nPaís: Portugal\nNUT III: PT170\nLocalidade: Setúbal\nDistrito: Setúbal\nConcelho: Almada\nFreguesia: Todas\n\n10 - PRAZO DE EXECUÇÃO DO CONTRATO\nPrazo de execução do contrato: 2 ANOS\nPrevisão de renovações: Não\n\n11 - FUNDOS EU\nTêm fundos EU? Não\n\n12 - DOCUMENTOS DE HABILITAÇÃO\nHabilitação para o exercício da atividade profissional: Sim\nTipo: Outros\nDescrição - Outros: Não aplicável\nDescrição: Não aplicável\n\n13 - CONDIÇÕES DE APRESENTAÇÃO\nPlataforma eletrónica utilizada pela entidade adjudicante: VORTAL\nURL para Apresentação: https://community.vortal.biz/public/\nAdmissibilidade da apresentação de propostas variantes: Não autorizado\nPrazo para apresentação das propostas: 22-09-2025 23:59\nPrazo durante o qual os concorrentes são obrigados a manter as respetivas propostas: 120 dias a contar do termo do prazo para a apresentação das propostas\nApresentação de Catálogo Eletrónico: Não autorizado\nIndicação de Subcontratação na Proposta: Inexistência de indicação de subcontratação\n\n14 - PRESTAÇÃO DE CAUÇÃO\nPrestação de caução: Não\n\n15 - FORNECIMENTO DAS PEÇAS DO CONCURSO, APRESENTAÇÃO DE PEDIDOS DE PARTICIPAÇÃO E APRESENTAÇÃO DAS PROPOSTAS\nLink para acesso às peças do concurso (URL): https://community.vortal.biz/Public/public-tender-documents/ZTlLQTRzTzN3TXI4bFVIZFNoZmxqMlFlQWcyZVNlbSthV25EOWE1aHQ0a0xoUE5wVkw3RDJjelBta3FYTWN0Q29mNW1icmlQZjFuemphYWM3aDFkbWc9PWVNRWZA\n\n20 - OUTROS REQUISITOS\nInformação sobre contratos reservados. Aplica-se a contratos reservados (54º-A)? Não\n\n21 - CRITÉRIO DE ADJUDICAÇÃO\nMultifator: Sim\nFator: \nNome: Outros\nOutro Nome: Preço da proposta\nPonderação: 50%\nSubfatores: Não\nFator: \nNome: Qualidade\nPonderação: 45%\nSubfatores: Não\nFator: \nNome: Qualidade\nPonderação: 5%\nSubfatores: Não\n\n24 - CONDIÇÕES DO CONTRATO\nFaturação Eletrónica: Permitido\nObrigação de Subcontratação:\nCódigo da Obrigação de Subcontratação: Não é aplicável nenhuma obrigação de subcontratação.\n\n25 - COMPRA PÚBLICA ESTRATÉGICA\nCompra Pública Estratégica: Inexistência de contratação pública estratégica\n\n26 - INFORMAÇÕES ADICIONAIS\nContrato adequado para PME: Sim\nCobertura ACP (Acordo dos Contratos Públicos da Organização Mundial do Comércio): Não\n\n27 - IDENTIFICAÇÃO E CONTACTOS DO ÓRGÃO DE RECURSOS ADMINISTRATIVOS\nDesignação: Município de Almada\nEndereço: Largo Luís Camões\nCódigo postal: 2800-158\nLocalidade: Almada\nTelefone: +351 212724000\nFax: +351 212724000\nEndereço eletrónico: gab.presidenciia@cma.m-almada.pt\n\n28 - IDENTIFICAÇÃO DO(S) AUTOR(ES) DE ANÚNCIO\nNome: Inês de Medeiros\nCargo: Presidente da Câmara Municipal de Almada\n\n29 - ALTERAÇÃO\nMotivo da Alteração: Correção pelo adquirente\nIdentificador da Versão do Anúncio a Alterar: e858f63e-456b-4f09-ac92-7979180ec735-01\nIdentificador das Secções Alteradas do Anúncio Anterior: Condições de Apresentação\nDescrição das Alterações: Prorrogação do prazo para apresentação de propostas\nAlteração dos Documentos do Concurso: Não\n419461541",
    "nipc": "500051054",
    "distrito": "Setúbal",
    "concelho": "Almada",
    "freguesia": "União das Freguesias de Almada, Cova da Piedade, Pragal e Cacilhas",
    "site": "www.m-almada.pt",
    "email": "almadainforma@cma.m-almada.pt",
    "designacao_contrato": "Aquisição de serviços de SOC - Security Operation Center pelo prazo de 2 anos",
    "descricao": "Aquisição de serviços de SOC - Security Operation Center pelo prazo de 2 anos",
    "preco_base": "365.853,66 EUR",
    "prazo_execucao": "2 ANOS",
    "prazo_apresentacao_propostas": "22-09-2025 23:59",
    "fundos_eu": "Não",
    "plataforma_eletronica": "VORTAL",
    "url_procedimento": "https://community.vortal.biz/public/",
    "autor_nome": "Inês de Medeiros",
    "autor_cargo": "Presidente da Câmara Municipal de Almada"
  },
  {
    "numero_procedimento": "N/A",
    "entidade": "AdP - Águas de Portugal, S.A.",
    "link": "https://diariodarepublica.pt/dr/detalhe/contrato-publico/22651-933044058",
    "detalhes_completos": "1 - IDENTIFICAÇÃO E CONTACTOS DA ENTIDADE ADJUDICANTE\nDesignação da entidade adjudicante: AdP - Águas de Portugal, S.A.\nNIPC: 503093742\nServiço/Órgão/Pessoa de contacto: Direção de Compras\nEndereço: Rua Visconde de Seabra, 3, 4.º piso\nCódigo postal: 1700-421\nLocalidade: Lisboa\nPaís: Portugal\nNUT III: PT170\nDistrito: Lisboa\nConcelho: Lisboa\nFreguesia: Freguesia de Alvalade - Lisboa\nTelefone: +351 212 469 400\nFax: 212469401\nEndereço da Entidade (URL): www.adp.pt\nEndereço Eletrónico: compras@adp.pt\neDelivery Gateway (URL): https://www.acingov.pt\nFunção da Organização: Adquirente\nSubfunção da Organização: Organização cujo orçamento é utilizado para pagar o contrato; Organização que executa o pagamento; Líder do grupo; Organização que fornece informações adicionais sobre o processo de adjudicação; Organização que fornece mais informações sobre os prazos dos procedimentos de recurso; Organização que fornece acesso fora de linha aos documentos do concurso; Organização responsável pelo tratamento das propostas; Organização que recebe as propostas; Organização que trata os pedidos de participação; Organização que recebe pedidos de participação; Organização que fornece mais informações sobre os procedimentos de recurso; Organização que assina o contrato\nNorma jurídica da Entidade Adjudicante: Organismo de direito público\nÁrea de atividade da Autoridade Adjudicante: Proteção ambiental\n\n2 - JORNAL OFICIAL DA UNIÃO EUROPEIA\nO procedimento a que este anúncio diz respeito também é publicitado no Jornal Oficial da União Europeia? Sim\n\n3 - AVISO\nModelo de Anúncio: Concurso público\nData de Envio do Anúncio: 22-08-2025\n\n5 - PROCESSO\nTipo de Procedimento: Concurso público\nPreço base do procedimento: Sim\nValor do preço base do procedimento: 4.680.469,00 EUR\nProcedimento com lotes? Sim\nNº Máx. de Lotes Autorizado: 2\nNúmero máximo de lotes que podem ser adjudicados a um concorrente: 2\n\n6 - OBJETO DO CONTRATO\nNúmero de referência interna: 2025_017CP\nDesignação do contrato: 2025_017CP - Aquisição de Cloreto Férrico pelas Empresas do Grupo Águas de Portugal\nDescrição: 2025_017CP - Aquisição de Cloreto Férrico pelas Empresas do Grupo Águas de Portugal\nOpções: Não\nTipo de Contrato Principal: Aquisição de Bens Móveis\nTipo de Contrato: Aquisição de Bens Móveis\nClassificação CPV (Vocabulário Comum para os Contratos Públicos)\nObjeto principal\nVocabulário Principal: 24312122\nPreço base s/IVA: 4.680.469,00 EUR\nLotes: \nNº: LOT-0001\nDescrição do Lote: Aquisição de Cloreto Férrico pelas Empresas do Grupo Águas de Portugal\nPreço base s/IVA: 2.360.360,00 EUR\nClassificação CPV (Vocabulário Comum para os Contratos Públicos)\nObjeto principal\nVocabulário Principal: 24312122\nNº: LOT-0002\nDescrição do Lote: Aquisição de Cloreto Férrico pelas Empresas do Grupo Águas de Portugal\nPreço base s/IVA: 2.320.109,00 EUR\nClassificação CPV (Vocabulário Comum para os Contratos Públicos)\nObjeto principal\nVocabulário Principal: 24312122\n\n7 - INDICAÇÕES ADICIONAIS\nO contrato envolve aquisição conjunta (satisfação de várias entidades)? Sim\nA entidade adjudicante atua como compradora no procedimento? Não\nNIPC: 513606130\nDesignação da entidade adjudicante: Águas do Vale do Tejo, S.A.\nUnidades Orgânicas: Direcção de Compras e Logística\nValor: 1160559\nNIPC: 514310103\nDesignação da entidade adjudicante: SIMDOURO - Saneamento do Grande Porto S.A.\nUnidades Orgânicas: Direcção de Compras e Logística\nValor: 50700\nNIPC: 514310774\nDesignação da entidade adjudicante: Águas do Douro e Paiva, S.A.\nUnidades Orgânicas: Direcção de Compras e Logística\nValor: 90000\nNIPC: 514385901\nDesignação da entidade adjudicante: SIMARSUL - Saneamento da Península de Setúbal, S.A.\nUnidades Orgânicas: Direcção de Compras e Logística\nValor: 514550\nNIPC: 514387130\nDesignação da entidade adjudicante: Águas do Tejo Atlântico, SA\nUnidades Orgânicas: Direcção de Compras e Logística\nValor: 2065200\nNIPC: 513606084\nDesignação da entidade adjudicante: Águas do Norte, SA\nUnidades Orgânicas: Direcção de Compras e Logística\nValor: 165960\nNIPC: 513606181\nDesignação da entidade adjudicante: Águas do Centro Litoral, SA\nUnidades Orgânicas: Direcção de Compras e Logística\nValor: 633500\nO contrato é adjudicado por uma central de compras? Não\n\n8 - TÉCNICAS\nO concurso destina-se à celebração de um acordo-quadro? Inexistência de acordo-quadro\nÉ utilizado um leilão eletrónico? Não\nÉ adotada uma fase de negociação? Não\nSistema de Aquisição Dinâmico: Inexistência de sistema de aquisição dinâmico\n\n9 - LOCAL DA EXECUÇÃO DO CONTRATO\nLOCAL DA EXECUÇÃO DO CONTRATO (PROCEDIMENTO)\nPaís: Portugal\nNUT III: PT111\nLocalidade: Freguesia de Alvalade - Lisboa\nDistrito: Lisboa\nConcelho: Lisboa\nFreguesia: Freguesia de Alvalade - Lisboa\nLOCAL DA EXECUÇÃO DO CONTRATO (LOTE)\nIdentificador do Lote: LOT-0001; LOT-0002\nPaís: Portugal\nNUT III: PT111\nLocalidade: Freguesia de Alvalade - Lisboa\nDistrito: Lisboa\nConcelho: Lisboa\nFreguesia: Freguesia de Alvalade - Lisboa\n\n10 - PRAZO DE EXECUÇÃO DO CONTRATO\nIdentificador do Lote: LOT-0001\nData de Início: 30-10-2025\nData de Fim: 14-12-2026\nPrevisão de renovações: Sim\nIndicar número máximo de renovações: 1\nPrazo de renovações diferente do prazo inicial: Não\nIdentificador do Lote: LOT-0002\nData de Início: 14-12-2025\nData de Fim: 14-12-2026\nPrevisão de renovações: Sim\nIndicar número máximo de renovações: 1\nPrazo de renovações diferente do prazo inicial: Não\n\n11 - FUNDOS EU\nIdentificador do Lote: LOT-0001; LOT-0002\nTêm fundos EU? Não\n\n12 - DOCUMENTOS DE HABILITAÇÃO\nHabilitação para o exercício da atividade profissional: Não\n\n13 - CONDIÇÕES DE APRESENTAÇÃO\nPlataforma eletrónica utilizada pela entidade adjudicante: ACIN\nURL para Apresentação: https://www.acingov.pt\nAdmissibilidade da apresentação de propostas variantes: Não autorizado\nPrazo para apresentação das propostas: 22-09-2025 18:00\nPrazo durante o qual os concorrentes são obrigados a manter as respetivas propostas: 66 dias a contar do termo do prazo para a apresentação das propostas\nApresentação de Catálogo Eletrónico: Permitido\nIndicação de Subcontratação na Proposta: Inexistência de indicação de subcontratação\n\n14 - PRESTAÇÃO DE CAUÇÃO\nPrestação de caução: Sim\nPercentagem: 1.5%\nDescrição da Garantia Exigida: O valor da caução é de 1.50% do preço contratual.\n\n15 - FORNECIMENTO DAS PEÇAS DO CONCURSO, APRESENTAÇÃO DE PEDIDOS DE PARTICIPAÇÃO E APRESENTAÇÃO DAS PROPOSTAS\nLink para acesso às peças do concurso (URL): https://www.acingov.pt/acingovprod/2/zonaPublica/zona_publica_c/donwloadProcedurePiece/OTAyODE1\n\n20 - OUTROS REQUISITOS\nIdentificador do Lote: LOT-0001; LOT-0002\nInformação sobre contratos reservados. Aplica-se a contratos reservados (54º-A)? Não\n\n21 - CRITÉRIO DE ADJUDICAÇÃO\nO Critério de adjudicação é diferenciado por lote? Não\nMultifator: Não\nMonofator:\nNome: Preço\n\n24 - CONDIÇÕES DO CONTRATO\nIdentificador do Lote: LOT-0001; LOT-0002\nFaturação Eletrónica: Necessário\nObrigação de Subcontratação:\nCódigo da Obrigação de Subcontratação: Não é aplicável nenhuma obrigação de subcontratação.\n\n25 - COMPRA PÚBLICA ESTRATÉGICA\nCompra Pública Estratégica: Inexistência de contratação pública estratégica\n\n26 - INFORMAÇÕES ADICIONAIS\nIdentificador do Lote: LOT-0001; LOT-0002\nContrato adequado para PME: Não\nCobertura ACP (Acordo dos Contratos Públicos da Organização Mundial do Comércio): Não\n\n27 - IDENTIFICAÇÃO E CONTACTOS DO ÓRGÃO DE RECURSOS ADMINISTRATIVOS\nDesignação: Comissão Executiva da AdP - Águas de Portugal, SGPS, S.A\nEndereço: Rua Visconde de Seabra, 3, 4.º piso\nCódigo postal: 1700-421\nLocalidade: Lisboa\nTelefone: 351212469400\nFax: \nEndereço eletrónico: compras@adp.pt\nPrazo de interposição do recurso: 5 dias\n\n28 - IDENTIFICAÇÃO DO(S) AUTOR(ES) DE ANÚNCIO\nNome: David Baranqueiro\nCargo: Diretor de Compras\n419462287",
    "nipc": "503093742",
    "distrito": "Lisboa",
    "concelho": "Lisboa",
    "freguesia": "Freguesia de Alvalade - Lisboa",
    "site": "www.adp.pt",
    "email": "compras@adp.pt",
    "designacao_contrato": "2025_017CP - Aquisição de Cloreto Férrico pelas Empresas do Grupo Águas de Portugal",
    "descricao": "2025_017CP - Aquisição de Cloreto Férrico pelas Empresas do Grupo Águas de Portugal",
    "preco_base": "4.680.469,00 EUR",
    "prazo_execucao": null,
    "prazo_apresentacao_propostas": "22-09-2025 18:00",
    "fundos_eu": "Não",
    "plataforma_eletronica": "ACIN",
    "url_procedimento": "https://www.acingov.pt",
    "autor_nome": "David Baranqueiro",
    "autor_cargo": "Diretor de Compras"
  },
  {
    "numero_procedimento": "N/A",
    "entidade": "AnÃºncio de procedimento  n.Âº 22652/2025  -  DiÃ¡rio da RepÃºblica n.Âº 162/2025, SÃ©rie II de 2025-08-25",
    "link": "https://diariodarepublica.pt/dr/detalhe/contrato-publico/22652-933044059"
  },
  {
    "numero_procedimento": "N/A",
    "entidade": "Artemave - Associação de Promoção das Artes e Música do Vale do Ave",
    "link": "https://diariodarepublica.pt/dr/detalhe/contrato-publico/22653-933044065",
    "detalhes_completos": "1 - IDENTIFICAÇÃO E CONTACTOS DA ENTIDADE ADJUDICANTE\nDesignação da entidade adjudicante: Artemave - Associação de Promoção das Artes e Música do Vale do Ave\nNIPC: 507519736\nEndereço: Complexo Educativo do Colégio das Caldinhas - Caldas da Saúde\nCódigo postal: 4784-907\nLocalidade: Areias STS\nPaís: Portugal\nNUT III: PT11D\nDistrito: Porto\nConcelho: Santo Tirso\nFreguesia: União das Freguesias de Areias, Sequeiró, Lama e Palmeira\nTelefone: 252808830\nEndereço Eletrónico: geral@artave.pt\nFunção da Organização: Adquirente\nNorma jurídica da Entidade Adjudicante: Organização que adjudica um contrato subvencionado por uma autoridade da administração central\nÁrea de atividade da Autoridade Adjudicante: Educação\n\n2 - JORNAL OFICIAL DA UNIÃO EUROPEIA\nO procedimento a que este anúncio diz respeito também é publicitado no Jornal Oficial da União Europeia? Não\n\n3 - AVISO\nModelo de Anúncio: Concurso público\nData de Envio do Anúncio: 24-08-2025\n\n5 - PROCESSO\nTipo de Procedimento: Concurso público\nPreço base do procedimento: Sim\nValor do preço base do procedimento: 183.450,00 EUR\nProcedimento com lotes? Sim\nNº Máx. de Lotes Autorizado: 3\nNúmero máximo de lotes que podem ser adjudicados a um concorrente: 1\n\n6 - OBJETO DO CONTRATO\nNúmero de referência interna: CP01/25\nDesignação do contrato: Serviço de transporte escolar\nDescrição: Serviço de transporte escolar\nTipo de Contrato Principal: Aquisição de Serviços\nTipo de Contrato: Aquisição de Serviços\nClassificação CPV (Vocabulário Comum para os Contratos Públicos)\nObjeto principal\nVocabulário Principal: 60130000\nPreço base s/IVA: 183.450,00 EUR\nLotes: \nNº: LOT-0001\nDescrição do Lote: Percursos 1\nPreço base s/IVA: 63.400,00 EUR\nClassificação CPV (Vocabulário Comum para os Contratos Públicos)\nObjeto principal\nVocabulário Principal: 60130000\nNº: LOT-0002\nDescrição do Lote: Percursos 2\nPreço base s/IVA: 71.900,00 EUR\nClassificação CPV (Vocabulário Comum para os Contratos Públicos)\nObjeto principal\nVocabulário Principal: 60130000\nNº: LOT-0003\nDescrição do Lote: Percursos 3\nPreço base s/IVA: 48.150,00 EUR\nClassificação CPV (Vocabulário Comum para os Contratos Públicos)\nObjeto principal\nVocabulário Principal: 60130000\n\n7 - INDICAÇÕES ADICIONAIS\nO contrato envolve aquisição conjunta (satisfação de várias entidades)? Não\nO contrato é adjudicado por uma central de compras? Não\n\n8 - TÉCNICAS\nO concurso destina-se à celebração de um acordo-quadro? Inexistência de acordo-quadro\nÉ utilizado um leilão eletrónico? Não\nÉ adotada uma fase de negociação? Não\nSistema de Aquisição Dinâmico: Inexistência de sistema de aquisição dinâmico\n\n9 - LOCAL DA EXECUÇÃO DO CONTRATO\nLOCAL DA EXECUÇÃO DO CONTRATO (PROCEDIMENTO)\nPaís: Portugal\nNUT III: PT11D\nLocalidade: Santo Tirso\nDistrito: Porto\nConcelho: Santo Tirso\nFreguesia: União das Freguesias de Areias, Sequeiró, Lama e Palmeira\nLOCAL DA EXECUÇÃO DO CONTRATO (LOTE)\nIdentificador do Lote: LOT-0001; LOT-0002; LOT-0003\nPaís: Portugal\nNUT III: PT11D\nLocalidade: Santo Tirso\nDistrito: Porto\nConcelho: Santo Tirso\nFreguesia: União das Freguesias de Areias, Sequeiró, Lama e Palmeira\n\n10 - PRAZO DE EXECUÇÃO DO CONTRATO\nIdentificador do Lote: LOT-0001; LOT-0002; LOT-0003\nPrazo de execução do contrato: 210 DIAS\nPrevisão de renovações: Não\n\n11 - FUNDOS EU\nIdentificador do Lote: LOT-0001; LOT-0002; LOT-0003\nTêm fundos EU? Não\n\n12 - DOCUMENTOS DE HABILITAÇÃO\nHabilitação para o exercício da atividade profissional: Não\n\n13 - CONDIÇÕES DE APRESENTAÇÃO\nPlataforma eletrónica utilizada pela entidade adjudicante: ANOGOV\nURL para Apresentação: https://www.anogov.com/op-apamva/faces/app/dashboard.jsp\nAdmissibilidade da apresentação de propostas variantes: Não autorizado\nPrazo para apresentação das propostas: 03-09-2025 23:59\nPrazo durante o qual os concorrentes são obrigados a manter as respetivas propostas: 90 dias a contar do termo do prazo para a apresentação das propostas\nIndicação de Subcontratação na Proposta: Inexistência de indicação de subcontratação\n\n14 - PRESTAÇÃO DE CAUÇÃO\nPrestação de caução: Não\n\n15 - FORNECIMENTO DAS PEÇAS DO CONCURSO, APRESENTAÇÃO DE PEDIDOS DE PARTICIPAÇÃO E APRESENTAÇÃO DAS PROPOSTAS\nLink para acesso às peças do concurso (URL): https://www.anogov.com/op-apamva/faces/app/dashboard.jsp\n\n20 - OUTROS REQUISITOS\nIdentificador do Lote: LOT-0001; LOT-0002; LOT-0003\nInformação sobre contratos reservados. Aplica-se a contratos reservados (54º-A)? Não\n\n21 - CRITÉRIO DE ADJUDICAÇÃO\nO Critério de adjudicação é diferenciado por lote? Não\nMultifator: Não\nMonofator:\nNome: Preço\n\n24 - CONDIÇÕES DO CONTRATO\nIdentificador do Lote: LOT-0001; LOT-0002; LOT-0003\nFaturação Eletrónica: Permitido\n\n25 - COMPRA PÚBLICA ESTRATÉGICA\nCompra Pública Estratégica: Inexistência de contratação pública estratégica\n\n26 - INFORMAÇÕES ADICIONAIS\nIdentificador do Lote: LOT-0001; LOT-0002; LOT-0003\nContrato adequado para PME: Não\nCobertura ACP (Acordo dos Contratos Públicos da Organização Mundial do Comércio): Não\n\n27 - IDENTIFICAÇÃO E CONTACTOS DO ÓRGÃO DE RECURSOS ADMINISTRATIVOS\nDesignação: Associação de Promoção das Artes e Música do Vale do Ave (ARTEMAVE)\nEndereço: Complexo Educativo do Colégio das Caldinhas - Caldas da Saúde\nCódigo postal: 4784-907\nLocalidade: Areias STS\nEndereço eletrónico: geral@artave.pt\nPrazo de interposição do recurso: 30 dias\n\n28 - IDENTIFICAÇÃO DO(S) AUTOR(ES) DE ANÚNCIO\nNome: Liliana Marisa Alves Leal, Dr.ª\nCargo: Diretora da ARTAVE\n419462992",
    "nipc": "507519736",
    "distrito": "Porto",
    "concelho": "Santo Tirso",
    "freguesia": "União das Freguesias de Areias, Sequeiró, Lama e Palmeira",
    "site": null,
    "email": "geral@artave.pt",
    "designacao_contrato": "Serviço de transporte escolar",
    "descricao": "Serviço de transporte escolar",
    "preco_base": "183.450,00 EUR",
    "prazo_execucao": "210 DIAS",
    "prazo_apresentacao_propostas": "03-09-2025 23:59",
    "fundos_eu": "Não",
    "plataforma_eletronica": "ANOGOV",
    "url_procedimento": "https://www.anogov.com/op-apamva/faces/app/dashboard.jsp",
    "autor_nome": "Liliana Marisa Alves Leal, Dr.ª",
    "autor_cargo": "Diretora da ARTAVE"
  },
  {
    "numero_procedimento": "N/A",
    "entidade": "Instituto Português de Oncologia de Lisboa FG, E.P.E.",
    "link": "https://diariodarepublica.pt/dr/detalhe/contrato-publico/22654-933044066",
    "detalhes_completos": "1 - IDENTIFICAÇÃO E CONTACTOS DA ENTIDADE ADJUDICANTE\nDesignação da entidade adjudicante: Instituto Português de Oncologia de Lisboa FG, E.P.E.\nNIPC: 506361616\nEndereço: Rua Profº Lima Basto\nCódigo postal: 1099-023\nLocalidade: Lisboa\nPaís: Portugal\nNUT III: PT170\nDistrito: Lisboa\nConcelho: Lisboa\nFreguesia: Todas\nTelefone: 217229800\nFax: 217229880\nEndereço da Entidade (URL): www.ipolisboa.min-saude.pt/\nEndereço Eletrónico: ipofg@ipolisboa.min-saude.pt\neDelivery Gateway (URL): https://community.vortal.biz/public/\nFunção da Organização: Adquirente\nNorma jurídica da Entidade Adjudicante: Organismo de direito público\nÁrea de atividade da Autoridade Adjudicante: Saúde\n\n2 - JORNAL OFICIAL DA UNIÃO EUROPEIA\nO procedimento a que este anúncio diz respeito também é publicitado no Jornal Oficial da União Europeia? Não\n\n3 - AVISO\nModelo de Anúncio: Concurso público urgente\nData de Envio do Anúncio: 25-08-2025 08:47:00\n\n5 - PROCESSO\nTipo de Procedimento: Concurso público\nPreço base do procedimento: Sim\nValor do preço base do procedimento: 179.103,27 EUR\nProcedimento com lotes? Não\n\n6 - OBJETO DO CONTRATO\nNúmero de referência interna: PU/2481/2025\nDesignação do contrato: PU/2481/2025 - PRESTAÇÃO DE SERVIÇOS DE HIGIENE E LIMPEZA E FORNECIMENTO DE CONSUMÍVEIS DE CASA DE BANHO\nDescrição: PU/2481/2025 - PRESTAÇÃO DE SERVIÇOS DE HIGIENE E LIMPEZA E FORNECIMENTO DE CONSUMÍVEIS DE CASA DE BANHO\nTipo de Contrato Principal: Aquisição de Serviços\nTipo de Contrato: Aquisição de Serviços\nClassificação CPV (Vocabulário Comum para os Contratos Públicos)\nObjeto principal\nVocabulário Principal: 90910000\nPreço base s/IVA: 179.103,27 EUR\n\n7 - INDICAÇÕES ADICIONAIS\nO contrato envolve aquisição conjunta (satisfação de várias entidades)? Não\nO contrato é adjudicado por uma central de compras? Não\n\n8 - TÉCNICAS\nO concurso destina-se à celebração de um acordo-quadro? Inexistência de acordo-quadro\nÉ utilizado um leilão eletrónico? Não\nÉ adotada uma fase de negociação? Não\nSistema de Aquisição Dinâmico: Inexistência de sistema de aquisição dinâmico\n\n9 - LOCAL DA EXECUÇÃO DO CONTRATO\nLOCAL DA EXECUÇÃO DO CONTRATO (PROCEDIMENTO)\nPaís: Portugal\nNUT III: PT170\nLocalidade: Lisboa\nDistrito: Lisboa\nConcelho: Lisboa\nFreguesia: Freguesia de São Domingos de Benfica\n\n10 - PRAZO DE EXECUÇÃO DO CONTRATO\nPrazo de execução do contrato: 1 MESES\nPrevisão de renovações: Não\n\n11 - FUNDOS EU\nTêm fundos EU? Não\n\n12 - DOCUMENTOS DE HABILITAÇÃO\nHabilitação para o exercício da atividade profissional: Não\n\n13 - CONDIÇÕES DE APRESENTAÇÃO\nPlataforma eletrónica utilizada pela entidade adjudicante: VORTAL\nURL para Apresentação: https://community.vortal.biz/public/\nAdmissibilidade da apresentação de propostas variantes: Não autorizado\nPrazo para apresentação das propostas: 27-08-2025 10:00\nPrazo durante o qual os concorrentes são obrigados a manter as respetivas propostas: 10 dias a contar do termo do prazo para a apresentação das propostas\nIndicação de Subcontratação na Proposta: Inexistência de indicação de subcontratação\n\n14 - PRESTAÇÃO DE CAUÇÃO\nPrestação de caução: Não\n\n15 - FORNECIMENTO DAS PEÇAS DO CONCURSO, APRESENTAÇÃO DE PEDIDOS DE PARTICIPAÇÃO E APRESENTAÇÃO DAS PROPOSTAS\nLink para acesso às peças do concurso (URL): https://community.vortal.biz/Public/public-tender-documents/NmI3endlUXlMcUpXUUZmK1hERTloNGRQbmRWYksyZTdENDlWUXdzQW50dFZhbUZNcU4wdXRXR3c2aFREUkZ2MTFnUTNPb3N4bXN2dDRuNWJGb1A2ZkE9PUBOdHN6\n\n20 - OUTROS REQUISITOS\nInformação sobre contratos reservados. Aplica-se a contratos reservados (54º-A)? Não\n\n21 - CRITÉRIO DE ADJUDICAÇÃO\nMultifator: Não\nMonofator:\nNome: Preço\n\n24 - CONDIÇÕES DO CONTRATO\nFaturação Eletrónica: Permitido\nObrigação de Subcontratação:\nCódigo da Obrigação de Subcontratação: Não é aplicável nenhuma obrigação de subcontratação.\n\n25 - COMPRA PÚBLICA ESTRATÉGICA\nCompra Pública Estratégica: Inexistência de contratação pública estratégica\n\n26 - INFORMAÇÕES ADICIONAIS\nContrato adequado para PME: Sim\nCobertura ACP (Acordo dos Contratos Públicos da Organização Mundial do Comércio): Não\n\n27 - IDENTIFICAÇÃO E CONTACTOS DO ÓRGÃO DE RECURSOS ADMINISTRATIVOS\nDesignação: Conselho de Administração\nEndereço: Rua Professor Lima Basto\nCódigo postal: 1099-023\nLocalidade: Lisboa\nTelefone: +351 217229800\nFax: +351 217229833\nEndereço eletrónico: ipofg@ipolisboa.min-saude.pt\n\n28 - IDENTIFICAÇÃO DO(S) AUTOR(ES) DE ANÚNCIO\nNome: Ana Sofia da Silva Vaz\nCargo: Assistente Técnico\n419462546",
    "nipc": "506361616",
    "distrito": "Lisboa",
    "concelho": "Lisboa",
    "freguesia": "Todas",
    "site": "www.ipolisboa.min-saude.pt/",
    "email": "ipofg@ipolisboa.min-saude.pt",
    "designacao_contrato": "PU/2481/2025 - PRESTAÇÃO DE SERVIÇOS DE HIGIENE E LIMPEZA E FORNECIMENTO DE CONSUMÍVEIS DE CASA DE BANHO",
    "descricao": "PU/2481/2025 - PRESTAÇÃO DE SERVIÇOS DE HIGIENE E LIMPEZA E FORNECIMENTO DE CONSUMÍVEIS DE CASA DE BANHO",
    "preco_base": "179.103,27 EUR",
    "prazo_execucao": "1 MESES",
    "prazo_apresentacao_propostas": "27-08-2025 10:00",
    "fundos_eu": "Não",
    "plataforma_eletronica": "VORTAL",
    "url_procedimento": "https://community.vortal.biz/public/",
    "autor_nome": "Ana Sofia da Silva Vaz",
    "autor_cargo": "Assistente Técnico"
  },
  {
    "numero_procedimento": "N/A",
    "entidade": "EDA - ELECTRICIDADE DOS AÇORES, S.A.",
    "link": "https://diariodarepublica.pt/dr/detalhe/contrato-publico/22592-933115820",
    "detalhes_completos": "1 - IDENTIFICAÇÃO E CONTACTOS DA ENTIDADE ADJUDICANTE\nDesignação da entidade adjudicante: EDA - ELECTRICIDADE DOS AÇORES, S.A.\nNIPC: 512012032\nEndereço: Rua Francisco Pereira Ataíde, nº1\nCódigo postal: 9504-535\nLocalidade: Região Autónoma dos Açores\nPaís: Portugal\nNUT III: PT200\nDistrito: Região Autónoma dos Açores\nConcelho: Ponta Delgada\nFreguesia: Freguesia de Ponta Delgada (São Sebastião)\nTelefone: 296202000\nFax: 296202399\nEndereço da Entidade (URL): www.eda.pt\nEndereço Eletrónico: eda@eda.pt\neDelivery Gateway (URL): https://community.vortal.biz/public/\nFunção da Organização: Adquirente\nNorma jurídica da Entidade Adjudicante: Empresa pública, controlada por uma autoridade regional\nÁrea de atividade da Entidade Adjudicante: Atividades relacionadas com a eletricidade\n\n2 - JORNAL OFICIAL DA UNIÃO EUROPEIA\nO procedimento a que este anúncio diz respeito também é publicitado no Jornal Oficial da União Europeia? Sim\n\n3 - AVISO\nModelo de Anúncio: Concurso público\nData de Envio do Anúncio: 20-08-2025\n\n5 - PROCESSO\nTipo de Procedimento: Concurso público\nPreço base do procedimento: Sim\nValor do preço base do procedimento: 3.000.000,00 EUR\nProcedimento com lotes? Não\n\n6 - OBJETO DO CONTRATO\nNúmero de referência interna: CP 07/CINFE/2025 -AQUISIÇÃO CENTRAIS EMERGÊNCIA\nDesignação do contrato: AQUISIÇÃO DE CENTRAIS DE EMERGÊNCIA\nDescrição: Fornecimento, formação, ensaios, transporte e colocação em serviço de 5 (cinco) grupos de emergência e 8 (oito) subestações contentorizadas, bem como assistência técnica e manutenção em período de garantia de todos os equipamentos elétricos e mecânicos e sistemas necessários à correta operação dos equipamentos fornecidos.\nOpções: Não\nTipo de Contrato Principal: Aquisição de Bens Móveis\nTipo de Contrato: Aquisição de Bens Móveis\nClassificação CPV (Vocabulário Comum para os Contratos Públicos)\nObjeto principal\nVocabulário Principal: 31682500\nPreço base s/IVA: 3.000.000,00 EUR\n\n7 - INDICAÇÕES ADICIONAIS\nO contrato envolve aquisição conjunta (satisfação de várias entidades)? Não\nO contrato é adjudicado por uma central de compras? Não\n\n8 - TÉCNICAS\nO concurso destina-se à celebração de um acordo-quadro? Inexistência de acordo-quadro\nÉ utilizado um leilão eletrónico? Não\nÉ adotada uma fase de negociação? Não\nSistema de Aquisição Dinâmico: Inexistência de sistema de aquisição dinâmico\n\n9 - LOCAL DA EXECUÇÃO DO CONTRATO\nLOCAL DA EXECUÇÃO DO CONTRATO (PROCEDIMENTO)\nPaís: Portugal\nNUT III: PT200\nLocalidade: Região Autónoma dos Açores\nDistrito: Região Autónoma dos Açores\nConcelho: Ponta Delgada\nFreguesia: Freguesia de Ponta Delgada (São Sebastião)\n\n10 - PRAZO DE EXECUÇÃO DO CONTRATO\nPrazo de execução do contrato: 18 MESES\nPrevisão de renovações: Não\n\n11 - FUNDOS EU\nTêm fundos EU? Não\n\n12 - DOCUMENTOS DE HABILITAÇÃO\nHabilitação para o exercício da atividade profissional: Não\n\n13 - CONDIÇÕES DE APRESENTAÇÃO\nPlataforma eletrónica utilizada pela entidade adjudicante: VORTAL\nURL para Apresentação: https://community.vortal.biz/public/\nAdmissibilidade da apresentação de propostas variantes: Não autorizado\nPrazo para apresentação das propostas: 22-09-2025 23:59\nPrazo durante o qual os concorrentes são obrigados a manter as respetivas propostas: 180 dias a contar do termo do prazo para a apresentação das propostas\nApresentação de Catálogo Eletrónico: Não autorizado\nIndicação de Subcontratação na Proposta: Inexistência de indicação de subcontratação\n\n14 - PRESTAÇÃO DE CAUÇÃO\nPrestação de caução: Sim\nPercentagem: 5%\nDescrição da Garantia Exigida: Nos termos do Artigo 24.º ponto 2 do Programa de Concurso\n\n15 - FORNECIMENTO DAS PEÇAS DO CONCURSO, APRESENTAÇÃO DE PEDIDOS DE PARTICIPAÇÃO E APRESENTAÇÃO DAS PROPOSTAS\nLink para acesso às peças do concurso (URL): https://community.vortal.biz/Public/public-tender-documents/bEh2TXFMZkM2dGFPSUVFa2N3WnVVZW0vM1YrcGY5MHFwbmhTRFkrSkhOT0YycVdXVVVBMExUSmQzTXlLU2tjd2g0VXJoaGhUVEtrTnB6QXBzSC9wTnc9PSFHWkZL\n\n20 - OUTROS REQUISITOS\nInformação sobre contratos reservados. Aplica-se a contratos reservados (54º-A)? Não\n\n21 - CRITÉRIO DE ADJUDICAÇÃO\nMultifator: Não\nMonofator:\nNome: Outros\nOutro nome: O mais baixo preço proposto\n\n24 - CONDIÇÕES DO CONTRATO\nFaturação Eletrónica: Permitido\nObrigação de Subcontratação:\nCódigo da Obrigação de Subcontratação: Não é aplicável nenhuma obrigação de subcontratação.\n\n25 - COMPRA PÚBLICA ESTRATÉGICA\nCompra Pública Estratégica: Redução dos impactos ambientais\nDescrição do Processo de Adjudicação Estratégico: Conforme as peças do procedimento\nCritérios de contratos Públicos Ecológicos: Critérios de contratação pública ecológica nacional\nCategorias da estratégia nacional: Eletricidade\nDiretiva Veículos Não Poluentes: Não\nCritério de Acessibilidade: Os critérios de acessibilidade para as pessoas com deficiência não estão incluídos porque o contrato não se destina a pessoas singulares\n\n26 - INFORMAÇÕES ADICIONAIS\nContrato adequado para PME: Sim\nCobertura ACP (Acordo dos Contratos Públicos da Organização Mundial do Comércio): Não\n\n27 - IDENTIFICAÇÃO E CONTACTOS DO ÓRGÃO DE RECURSOS ADMINISTRATIVOS\nDesignação: Conselho de Administração\nEndereço: Rua Francisco Pereira Ataíde, nº1\nCódigo postal: 9504-535\nLocalidade: Ponta Delgada\nTelefone: +351 296202000\nFax: +351 296202399\nEndereço eletrónico: eda@eda.pt\n\n28 - IDENTIFICAÇÃO DO(S) AUTOR(ES) DE ANÚNCIO\nNome: Carlos Jorge Morais Loures \nCargo: Quadro Superior- Departamento de Contratação Pública e Apoio Jurídico \n419453109",
    "nipc": "512012032",
    "distrito": "Região Autónoma dos Açores",
    "concelho": "Ponta Delgada",
    "freguesia": "Freguesia de Ponta Delgada (São Sebastião)",
    "site": "www.eda.pt",
    "email": "eda@eda.pt",
    "designacao_contrato": "AQUISIÇÃO DE CENTRAIS DE EMERGÊNCIA",
    "descricao": "Fornecimento, formação, ensaios, transporte e colocação em serviço de 5 (cinco) grupos de emergência e 8 (oito) subestações contentorizadas, bem como assistência técnica e manutenção em período de garantia de todos os equipamentos elétricos e mecânicos e sistemas necessários à correta operação dos equipamentos fornecidos.",
    "preco_base": "3.000.000,00 EUR",
    "prazo_execucao": "18 MESES",
    "prazo_apresentacao_propostas": "22-09-2025 23:59",
    "fundos_eu": "Não",
    "plataforma_eletronica": "VORTAL",
    "url_procedimento": "https://community.vortal.biz/public/",
    "autor_nome": "Carlos Jorge Morais Loures",
    "autor_cargo": "Quadro Superior- Departamento de Contratação Pública e Apoio Jurídico"
  },
  {
    "numero_procedimento": "N/A",
    "entidade": "EMAC - Empresa Municipal de Ambiente de Cascais, EM, SA",
    "link": "https://diariodarepublica.pt/dr/detalhe/contrato-publico/22593-933115821",
    "detalhes_completos": "1 - IDENTIFICAÇÃO E CONTACTOS DA ENTIDADE ADJUDICANTE\nDesignação da entidade adjudicante: EMAC - Empresa Municipal de Ambiente de Cascais, EM, SA\nNIPC: 507396081\nServiço/Órgão/Pessoa de contacto: Departamento Financeiro\nEndereço: Complexo Multiserviços da CMC, Estrada de Manique, nº 1830\nCódigo postal: 2645-138\nLocalidade: Alcabideche\nPaís: Portugal\nNUT III: PT170\nDistrito: Lisboa\nConcelho: Cascais\nFreguesia: Freguesia de Alcabideche\nTelefone: +351214604249\nFax: +351214604249\nEndereço da Entidade (URL): https://ambiente.cascais.pt\nEndereço Eletrónico: compras@cascaisambiente.pt\neDelivery Gateway (URL): https://www.acingov.pt\nFunção da Organização: Adquirente\nNorma jurídica da Entidade Adjudicante: Empresa pública, controlada por uma autoridade local\nÁrea de atividade da Autoridade Adjudicante: Serviços públicos das administrações públicas\n\n2 - JORNAL OFICIAL DA UNIÃO EUROPEIA\nO procedimento a que este anúncio diz respeito também é publicitado no Jornal Oficial da União Europeia? Sim\n\n3 - AVISO\nModelo de Anúncio: Concurso público\nData de Envio do Anúncio: 20-08-2025\n\n5 - PROCESSO\nTipo de Procedimento: Concurso público\nPreço base do procedimento: Sim\nValor do preço base do procedimento: 352.750,00 EUR\nProcedimento com lotes? Sim\nNº Máx. de Lotes Autorizado: 12\nNúmero máximo de lotes que podem ser adjudicados a um concorrente: 12\n\n6 - OBJETO DO CONTRATO\nNúmero de referência interna: CPUB007DFJ2025\nDesignação do contrato: CPUB007DFJ2025  Locação Financeira para Aquisição de Viaturas\nDescrição: CPUB007DFJ2025  Locação Financeira para Aquisição de Viaturas\nOpções: Não\nTipo de Contrato Principal: Aquisição de Serviços\nTipo de Contrato: Aquisição de Serviços\nClassificação CPV (Vocabulário Comum para os Contratos Públicos)\nObjeto principal\nVocabulário Principal: 66114000\nPreço base s/IVA: 352.750,00 EUR\nLotes: \nNº: LOT-0001\nDescrição do Lote: Locação Financeira para aquisição de viatura - Renault Kangoo L1 equilibre Blue dCi 95\nPreço base s/IVA: 26.500,00 EUR\nClassificação CPV (Vocabulário Comum para os Contratos Públicos)\nObjeto principal\nVocabulário Principal: 66114000\nNº: LOT-0002\nDescrição do Lote: Locação Financeira para aquisição de viatura - Renault Kangoo L1 equilibre Blue dCi 95\nPreço base s/IVA: 26.500,00 EUR\nClassificação CPV (Vocabulário Comum para os Contratos Públicos)\nObjeto principal\nVocabulário Principal: 66114000\nNº: LOT-0003\nDescrição do Lote: Locação Financeira para aquisição de viatura - Renault Kangoo L1 equilibre Blue dCi 95\nPreço base s/IVA: 26.500,00 EUR\nClassificação CPV (Vocabulário Comum para os Contratos Públicos)\nObjeto principal\nVocabulário Principal: 66114000\nNº: LOT-0004\nDescrição do Lote: Locação Financeira para aquisição de viatura - Renault Kangoo L1 equilibre Blue dCi 95\nPreço base s/IVA: 26.500,00 EUR\nClassificação CPV (Vocabulário Comum para os Contratos Públicos)\nObjeto principal\nVocabulário Principal: 66114000\nNº: LOT-0005\nDescrição do Lote: Locação Financeira para aquisição de viatura - Renault Kangoo L1 equilibre Blue dCi 95\nPreço base s/IVA: 26.500,00 EUR\nClassificação CPV (Vocabulário Comum para os Contratos Públicos)\nObjeto principal\nVocabulário Principal: 66114000\nNº: LOT-0006\nDescrição do Lote: Locação financeira para aquisição de viatura - Renault Kangoo E-Tech Eletrico L1 equilibre autonomia confort 22 CA/80 CC\nPreço base s/IVA: 27.250,00 EUR\nClassificação CPV (Vocabulário Comum para os Contratos Públicos)\nObjeto principal\nVocabulário Principal: 66114000\nNº: LOT-0007\nDescrição do Lote: Locação financeira para aquisição de viatura - Renault Kangoo E-Tech Eletrico L1 equilibre autonomia confort 22 CA/80 CC\nPreço base s/IVA: 27.250,00 EUR\nClassificação CPV (Vocabulário Comum para os Contratos Públicos)\nObjeto principal\nVocabulário Principal: 66114000\nNº: LOT-0008\nDescrição do Lote: Locação financeira para aquisição de viatura - Renault Kangoo E-Tech Eletrico L1 equilibre autonomia confort 22 CA/80 CC\nPreço base s/IVA: 27.250,00 EUR\nClassificação CPV (Vocabulário Comum para os Contratos Públicos)\nObjeto principal\nVocabulário Principal: 66114000\nNº: LOT-0009\nDescrição do Lote: Locação financeira para aquisição de viatura - Renault Kangoo E-Tech Eletrico L1 equilibre autonomia confort 22 CA/80 CC\nPreço base s/IVA: 27.250,00 EUR\nClassificação CPV (Vocabulário Comum para os Contratos Públicos)\nObjeto principal\nVocabulário Principal: 66114000\nNº: LOT-0010\nDescrição do Lote: Locação financeira para aquisição de viatura - Renault Kangoo E-Tech Eletrico L1 equilibre autonomia confort 22 CA/80 CC\nPreço base s/IVA: 27.250,00 EUR\nClassificação CPV (Vocabulário Comum para os Contratos Públicos)\nObjeto principal\nVocabulário Principal: 66114000\nNº: LOT-0011\nDescrição do Lote: Locação financeira para aquisição de viatura - Toyota Hilux 2.4 Cabine dupla, Caixa Madeira\nPreço base s/IVA: 42.000,00 EUR\nClassificação CPV (Vocabulário Comum para os Contratos Públicos)\nObjeto principal\nVocabulário Principal: 66114000\nNº: LOT-0012\nDescrição do Lote: Locação financeira para aquisição de viatura - Toyota Hilux 2.4 Cabine dupla, Caixa Madeira\nPreço base s/IVA: 42.000,00 EUR\nClassificação CPV (Vocabulário Comum para os Contratos Públicos)\nObjeto principal\nVocabulário Principal: 66114000\n\n7 - INDICAÇÕES ADICIONAIS\nO contrato envolve aquisição conjunta (satisfação de várias entidades)? Não\nO contrato é adjudicado por uma central de compras? Não\n\n8 - TÉCNICAS\nO concurso destina-se à celebração de um acordo-quadro? Inexistência de acordo-quadro\nÉ utilizado um leilão eletrónico? Não\nÉ adotada uma fase de negociação? Não\nSistema de Aquisição Dinâmico: Inexistência de sistema de aquisição dinâmico\n\n9 - LOCAL DA EXECUÇÃO DO CONTRATO\nLOCAL DA EXECUÇÃO DO CONTRATO (PROCEDIMENTO)\nPaís: Portugal\nNUT III: PT170\nLocalidade: Freguesia de Alcabideche\nDistrito: Lisboa\nConcelho: Cascais\nFreguesia: Freguesia de Alcabideche\nLOCAL DA EXECUÇÃO DO CONTRATO (LOTE)\nIdentificador do Lote: LOT-0001; LOT-0002; LOT-0003; LOT-0004; LOT-0005; LOT-0006; LOT-0007; LOT-0008; LOT-0009; LOT-0010; LOT-0011; LOT-0012\nPaís: Portugal\nNUT III: PT170\nLocalidade: Freguesia de Alcabideche\nDistrito: Lisboa\nConcelho: Cascais\nFreguesia: Freguesia de Alcabideche\n\n10 - PRAZO DE EXECUÇÃO DO CONTRATO\nIdentificador do Lote: LOT-0001; LOT-0002; LOT-0003; LOT-0004; LOT-0005; LOT-0006; LOT-0007; LOT-0008; LOT-0009; LOT-0010; LOT-0011; LOT-0012\nPrazo de execução do contrato: 48 MESES\nPrevisão de renovações: Não\n\n11 - FUNDOS EU\nIdentificador do Lote: LOT-0001; LOT-0002; LOT-0003; LOT-0004; LOT-0005; LOT-0006; LOT-0007; LOT-0008; LOT-0009; LOT-0010; LOT-0011; LOT-0012\nTêm fundos EU? Não\n\n12 - DOCUMENTOS DE HABILITAÇÃO\nHabilitação para o exercício da atividade profissional: Não\n\n13 - CONDIÇÕES DE APRESENTAÇÃO\nPlataforma eletrónica utilizada pela entidade adjudicante: ACIN\nURL para Apresentação: https://www.acingov.pt\nAdmissibilidade da apresentação de propostas variantes: Não autorizado\nPrazo para apresentação das propostas: 19-09-2025 23:59\nPrazo durante o qual os concorrentes são obrigados a manter as respetivas propostas: 120 dias a contar do termo do prazo para a apresentação das propostas\nApresentação de Catálogo Eletrónico: Não autorizado\nIndicação de Subcontratação na Proposta: Inexistência de indicação de subcontratação\n\n14 - PRESTAÇÃO DE CAUÇÃO\nPrestação de caução: Não\n\n15 - FORNECIMENTO DAS PEÇAS DO CONCURSO, APRESENTAÇÃO DE PEDIDOS DE PARTICIPAÇÃO E APRESENTAÇÃO DAS PROPOSTAS\nLink para acesso às peças do concurso (URL): https://www.acingov.pt/acingovprod/2/zonaPublica/zona_publica_c/donwloadProcedurePiece/OTMzMjU4\n\n20 - OUTROS REQUISITOS\nIdentificador do Lote: LOT-0001; LOT-0002; LOT-0003; LOT-0004; LOT-0005; LOT-0006; LOT-0007; LOT-0008; LOT-0009; LOT-0010; LOT-0011; LOT-0012\nInformação sobre contratos reservados. Aplica-se a contratos reservados (54º-A)? Não\n\n21 - CRITÉRIO DE ADJUDICAÇÃO\nO Critério de adjudicação é diferenciado por lote? Não\nMultifator: Não\nMonofator:\nNome: Preço\n\n24 - CONDIÇÕES DO CONTRATO\nIdentificador do Lote: LOT-0001; LOT-0002; LOT-0003; LOT-0004; LOT-0005; LOT-0006; LOT-0007; LOT-0008; LOT-0009; LOT-0010; LOT-0011; LOT-0012\nFaturação Eletrónica: Necessário\nObrigação de Subcontratação:\nCódigo da Obrigação de Subcontratação: Não é aplicável nenhuma obrigação de subcontratação.\n\n25 - COMPRA PÚBLICA ESTRATÉGICA\nCompra Pública Estratégica: Inexistência de contratação pública estratégica\n\n26 - INFORMAÇÕES ADICIONAIS\nIdentificador do Lote: LOT-0001; LOT-0002; LOT-0003; LOT-0004; LOT-0005; LOT-0006; LOT-0007; LOT-0008; LOT-0009; LOT-0010; LOT-0011; LOT-0012\nContrato adequado para PME: Sim\nCobertura ACP (Acordo dos Contratos Públicos da Organização Mundial do Comércio): Sim\n\n27 - IDENTIFICAÇÃO E CONTACTOS DO ÓRGÃO DE RECURSOS ADMINISTRATIVOS\nDesignação: EMAC - Empresa Municipal de Ambiente de Cascais, EM, SA\nEndereço: Complexo Multiserviços da CMC, Estrada de Manique, nº 1830, Alcoitão,\nCódigo postal: 2645-138\nLocalidade: Alcabideche\nTelefone: 351214604249\nFax: 351214604249\nEndereço eletrónico: geral@cascaisambiente.pt\nPrazo de interposição do recurso: 30 dias\n\n28 - IDENTIFICAÇÃO DO(S) AUTOR(ES) DE ANÚNCIO\nNome: Ana Maria de Bessa e Meneses Machado\nCargo: Unidade de Compras e Contratação\n419452331",
    "nipc": "507396081",
    "distrito": "Lisboa",
    "concelho": "Cascais",
    "freguesia": "Freguesia de Alcabideche",
    "site": "https://ambiente.cascais.pt",
    "email": "compras@cascaisambiente.pt",
    "designacao_contrato": "CPUB007DFJ2025  Locação Financeira para Aquisição de Viaturas",
    "descricao": "CPUB007DFJ2025  Locação Financeira para Aquisição de Viaturas",
    "preco_base": "352.750,00 EUR",
    "prazo_execucao": "48 MESES",
    "prazo_apresentacao_propostas": "19-09-2025 23:59",
    "fundos_eu": "Não",
    "plataforma_eletronica": "ACIN",
    "url_procedimento": "https://www.acingov.pt",
    "autor_nome": "Ana Maria de Bessa e Meneses Machado",
    "autor_cargo": "Unidade de Compras e Contratação"
  },
  {
    "numero_procedimento": "N/A",
    "entidade": "CMPH Empresa de Habitação e Manutenção do Município do Porto, E.M.",
    "link": "https://diariodarepublica.pt/dr/detalhe/contrato-publico/22594-933115822",
    "detalhes_completos": "1 - IDENTIFICAÇÃO E CONTACTOS DA ENTIDADE ADJUDICANTE\nDesignação da entidade adjudicante: CMPH Empresa de Habitação e Manutenção do Município do Porto, E.M.\nNIPC: 505037700\nServiço/Órgão/Pessoa de contacto: CMPH Empresa de Habitação e Manutenção do Município do Porto, E.M.\nEndereço: Rua do Monte dos Burgos, 12\nCódigo postal: 4250-309\nLocalidade: Porto\nPaís: Portugal\nNUT III: PT11A\nDistrito: Porto\nConcelho: Porto\nFreguesia: Freguesia de Paranhos - Porto\nTelefone: 228330000\nFax: 228330000\nEndereço da Entidade (URL): www.domussocial.pt\nEndereço Eletrónico: geral@domussocial.pt\neDelivery Gateway (URL): https://www.acingov.pt\nFunção da Organização: Adquirente\nNorma jurídica da Entidade Adjudicante: Empresa pública, controlada por uma autoridade local\nÁrea de atividade da Autoridade Adjudicante: Serviços públicos das administrações públicas\n\n2 - JORNAL OFICIAL DA UNIÃO EUROPEIA\nO procedimento a que este anúncio diz respeito também é publicitado no Jornal Oficial da União Europeia? Sim\n\n3 - AVISO\nModelo de Anúncio: Concurso público\nData de Envio do Anúncio: 20-08-2025\n\n5 - PROCESSO\nTipo de Procedimento: Concurso público\nPreço base do procedimento: Não\nProcedimento com lotes? Sim\nNº Máx. de Lotes Autorizado: 2\nNúmero máximo de lotes que podem ser adjudicados a um concorrente: 1\n\n6 - OBJETO DO CONTRATO\nNúmero de referência interna: COM-2025-0250\nDesignação do contrato: Celebração de dois acordos-quadro singulares para a prestação de serviços de fiscalização e controlo das empreitadas de reabilitação de habitações devolutas que integram o parque habitacional do Município do Porto\nDescrição: Celebração de dois acordos-quadro singulares para a prestação de serviços de fiscalização e controlo das empreitadas de reabilitação de habitações devolutas que integram o parque habitacional do Município do Porto \nOpções: Sim\nDescrição das opções: O direito de opção e o número de opções encontram-se previstos nas cláusulas 7.ª e 8.ª do Caderno Encargos, respetivamente\nTipo de Contrato Principal: Aquisição de Serviços\nTipo de Contrato: Aquisição de Serviços\nClassificação CPV (Vocabulário Comum para os Contratos Públicos)\nObjeto principal\nVocabulário Principal: 71520000\nLotes: \nNº: LOT-0001\nDescrição do Lote: Zona Ocidental\nValor Estimado do Lote: 1.350.000,00 EUR\nClassificação CPV (Vocabulário Comum para os Contratos Públicos)\nObjeto principal\nVocabulário Principal: 71520000\nNº: LOT-0002\nDescrição do Lote: Zona Oriental\nValor Estimado do Lote: 1.350.000,00 EUR\nClassificação CPV (Vocabulário Comum para os Contratos Públicos)\nObjeto principal\nVocabulário Principal: 71520000\n\n7 - INDICAÇÕES ADICIONAIS\nO contrato envolve aquisição conjunta (satisfação de várias entidades)? Não\nO contrato é adjudicado por uma central de compras? Não\n\n8 - TÉCNICAS\nO concurso destina-se à celebração de um acordo-quadro? Acordo-quadro, sem reabertura de concurso\nModalidade: Com uma entidade\nPrazo de vigência: \nValor estimado: Não\nPara Acordo-Quadro — valor total máximo estimado para toda a duração do Acordo-Quadro: 2.700.000,00 EUR\nÉ utilizado um leilão eletrónico? Não\nÉ adotada uma fase de negociação? Não\nSistema de Aquisição Dinâmico: Inexistência de sistema de aquisição dinâmico\n\n9 - LOCAL DA EXECUÇÃO DO CONTRATO\nLOCAL DA EXECUÇÃO DO CONTRATO (PROCEDIMENTO)\nPaís: Portugal\nNUT III: PT11A\nLocalidade: Porto\nDistrito: Porto\nConcelho: Porto\nFreguesia: Todas\nLOCAL DA EXECUÇÃO DO CONTRATO (LOTE)\nIdentificador do Lote: LOT-0001; LOT-0002\nPaís: Portugal\nNUT III: PT11A\nLocalidade: Porto\nDistrito: Porto\nConcelho: Porto\nFreguesia: Todas\n\n10 - PRAZO DE EXECUÇÃO DO CONTRATO\nIdentificador do Lote: LOT-0001; LOT-0002\nPrazo de execução do contrato: 4 ANOS\nPrevisão de renovações: Não\n\n11 - FUNDOS EU\nIdentificador do Lote: LOT-0001; LOT-0002\nTêm fundos EU? Não\n\n12 - DOCUMENTOS DE HABILITAÇÃO\nHabilitação para o exercício da atividade profissional: Sim\nTipo: Outros\nDescrição - Outros: Os requisitos/documentos de habilitação encontram-se previstos nos artigos 23.º e 24.º do Programa Procedimento, respetivamente\nDescrição: Documentos de Habilitação\n\n13 - CONDIÇÕES DE APRESENTAÇÃO\nPlataforma eletrónica utilizada pela entidade adjudicante: ACIN\nURL para Apresentação: https://www.acingov.pt\nAdmissibilidade da apresentação de propostas variantes: Não autorizado\nPrazo para apresentação das propostas: 25-09-2025 18:00\nPrazo durante o qual os concorrentes são obrigados a manter as respetivas propostas: 90 dias a contar do termo do prazo para a apresentação das propostas\nApresentação de Catálogo Eletrónico: Não autorizado\nIndicação de Subcontratação na Proposta: Inexistência de indicação de subcontratação\n\n14 - PRESTAÇÃO DE CAUÇÃO\nPrestação de caução: Sim\nPercentagem: 5%\nDescrição da Garantia Exigida: Nos termos do n.º 1 da cláusula 23.ª do Caderno Encargos, cada adjudicatário garantirá por caução, nos termos do disposto no artigo 254.º do CCP, em valor correspondente a 5.000,00  (cinco mil euros), as obrigações emergentes de cada acordo-quadro que outorgar\n\n15 - FORNECIMENTO DAS PEÇAS DO CONCURSO, APRESENTAÇÃO DE PEDIDOS DE PARTICIPAÇÃO E APRESENTAÇÃO DAS PROPOSTAS\nLink para acesso às peças do concurso (URL): https://www.acingov.pt/acingovprod/2/zonaPublica/zona_publica_c/donwloadProcedurePiece/OTM1NTQ5\n\n20 - OUTROS REQUISITOS\nIdentificador do Lote: LOT-0001; LOT-0002\nInformação sobre contratos reservados. Aplica-se a contratos reservados (54º-A)? Não\n\n21 - CRITÉRIO DE ADJUDICAÇÃO\nO Critério de adjudicação é diferenciado por lote? Não\nMultifator: Não\nMonofator:\nNome: Preço\n\n24 - CONDIÇÕES DO CONTRATO\nIdentificador do Lote: LOT-0001; LOT-0002\nFaturação Eletrónica: Permitido\nObrigação de Subcontratação:\nCódigo da Obrigação de Subcontratação: Não é aplicável nenhuma obrigação de subcontratação.\n\n25 - COMPRA PÚBLICA ESTRATÉGICA\nCompra Pública Estratégica: Inexistência de contratação pública estratégica\n\n26 - INFORMAÇÕES ADICIONAIS\nIdentificador do Lote: LOT-0001; LOT-0002\nContrato adequado para PME: Sim\nCobertura ACP (Acordo dos Contratos Públicos da Organização Mundial do Comércio): Não\n\n27 - IDENTIFICAÇÃO E CONTACTOS DO ÓRGÃO DE RECURSOS ADMINISTRATIVOS\nDesignação: CMPH Empresa de Habitação e Manutenção do Município do Porto, E.M.\nEndereço: Rua do Monte dos Burgos, 12\nCódigo postal: 4250-309\nLocalidade: Porto\nTelefone: 228330000\nFax: 228330000\nEndereço eletrónico: geral@domussocial.pt\nPrazo de interposição do recurso: 12 dias\n\n28 - IDENTIFICAÇÃO DO(S) AUTOR(ES) DE ANÚNCIO\nNome: Filipa Alexandra Dias Pereira de Sousa Melo Tavares\nCargo: Vice-Presidente do Conselho de Administração\n419450671",
    "nipc": "505037700",
    "distrito": "Porto",
    "concelho": "Porto",
    "freguesia": "Freguesia de Paranhos - Porto",
    "site": "www.domussocial.pt",
    "email": "geral@domussocial.pt",
    "designacao_contrato": "Celebração de dois acordos-quadro singulares para a prestação de serviços de fiscalização e controlo das empreitadas de reabilitação de habitações devolutas que integram o parque habitacional do Município do Porto",
    "descricao": "Celebração de dois acordos-quadro singulares para a prestação de serviços de fiscalização e controlo das empreitadas de reabilitação de habitações devolutas que integram o parque habitacional do Município do Porto",
    "preco_base": null,
    "prazo_execucao": "4 ANOS",
    "prazo_apresentacao_propostas": "25-09-2025 18:00",
    "fundos_eu": "Não",
    "plataforma_eletronica": "ACIN",
    "url_procedimento": "https://www.acingov.pt",
    "autor_nome": "Filipa Alexandra Dias Pereira de Sousa Melo Tavares",
    "autor_cargo": "Vice-Presidente do Conselho de Administração"
  },
  {
    "numero_procedimento": "N/A",
    "entidade": "COMISSÃO DO MERCADO DE VALORES MOBILIARIOS",
    "link": "https://diariodarepublica.pt/dr/detalhe/contrato-publico/22595-933115823",
    "detalhes_completos": "1 - IDENTIFICAÇÃO E CONTACTOS DA ENTIDADE ADJUDICANTE\nDesignação da entidade adjudicante: COMISSÃO DO MERCADO DE VALORES MOBILIARIOS\nNIPC: 502549254\nEndereço: Rua Laura Alves, Nº 4\nCódigo postal: 1050-138\nLocalidade: Lisboa\nPaís: Portugal\nNUT III: PT170\nDistrito: Lisboa\nConcelho: Lisboa\nFreguesia: Freguesia de Avenidas Novas\nTelefone: 213177000\nFax: 213537077\nEndereço da Entidade (URL): https://www.cmvm.pt/\nEndereço Eletrónico: cmvm@cmvm.pt\neDelivery Gateway (URL): https://community.vortal.biz/public/\nFunção da Organização: Adquirente\nNorma jurídica da Entidade Adjudicante: Instituição, órgão ou agência da UE\nÁrea de atividade da Autoridade Adjudicante: Assuntos económicos\n\n2 - JORNAL OFICIAL DA UNIÃO EUROPEIA\nO procedimento a que este anúncio diz respeito também é publicitado no Jornal Oficial da União Europeia? Não\n\n3 - AVISO\nModelo de Anúncio: Concurso público\nData de Envio do Anúncio: 22-08-2025\n\n5 - PROCESSO\nTipo de Procedimento: Concurso público\nPreço base do procedimento: Sim\nValor do preço base do procedimento: 219.000,00 EUR\nProcedimento com lotes? Não\n\n6 - OBJETO DO CONTRATO\nNúmero de referência interna: CP 16/2025_Módulo de Conformidade de Documentos \nDesignação do contrato: Módulo de Conformidade de Documentos \nDescrição: Implementação de um Módulo de Conformidade de Documentos e serviços de assistência técnica\nTipo de Contrato Principal: Aquisição de Serviços\nTipo de Contrato: Aquisição de Serviços\nClassificação CPV (Vocabulário Comum para os Contratos Públicos)\nObjeto principal\nVocabulário Principal: 72212000\nPreço base s/IVA: 170.000,00 EUR\nObjeto Complementar\nVocabulário Principal: 50324100\nPreço base s/IVA: 49.000,00 EUR\n\n7 - INDICAÇÕES ADICIONAIS\nO contrato envolve aquisição conjunta (satisfação de várias entidades)? Não\nO contrato é adjudicado por uma central de compras? Não\n\n8 - TÉCNICAS\nO concurso destina-se à celebração de um acordo-quadro? Inexistência de acordo-quadro\nÉ utilizado um leilão eletrónico? Não\nÉ adotada uma fase de negociação? Não\nSistema de Aquisição Dinâmico: Inexistência de sistema de aquisição dinâmico\n\n9 - LOCAL DA EXECUÇÃO DO CONTRATO\nLOCAL DA EXECUÇÃO DO CONTRATO (PROCEDIMENTO)\nPaís: Portugal\nNUT III: PT170\nLocalidade: Lisboa\nDistrito: Lisboa\nConcelho: Lisboa\nFreguesia: Freguesia de Avenidas Novas\n\n10 - PRAZO DE EXECUÇÃO DO CONTRATO\nPrazo de execução do contrato: 16 MESES\nPrevisão de renovações: Não\n\n11 - FUNDOS EU\nTêm fundos EU? Não\n\n12 - DOCUMENTOS DE HABILITAÇÃO\nHabilitação para o exercício da atividade profissional: Não\n\n13 - CONDIÇÕES DE APRESENTAÇÃO\nPlataforma eletrónica utilizada pela entidade adjudicante: VORTAL\nURL para Apresentação: https://community.vortal.biz/public/\nAdmissibilidade da apresentação de propostas variantes: Não autorizado\nPrazo para apresentação das propostas: 06-09-2025 17:00\nPrazo durante o qual os concorrentes são obrigados a manter as respetivas propostas: 66 dias a contar do termo do prazo para a apresentação das propostas\nIndicação de Subcontratação na Proposta: Inexistência de indicação de subcontratação\n\n14 - PRESTAÇÃO DE CAUÇÃO\nPrestação de caução: Não\n\n15 - FORNECIMENTO DAS PEÇAS DO CONCURSO, APRESENTAÇÃO DE PEDIDOS DE PARTICIPAÇÃO E APRESENTAÇÃO DAS PROPOSTAS\nLink para acesso às peças do concurso (URL): https://community.vortal.biz/Public/public-tender-documents/MmNkbUgxdHNHSUtrd2pLVUpkQ0JLaEVOMTBJZ3YzT05nQ243MFVEblljei94YUpVQTRxdVJHVmFMUjJPUEZPdUpLQkI4bTRDMGxMVmdQNFVSVzdhUXc9PWYxNXNV\n\n20 - OUTROS REQUISITOS\nInformação sobre contratos reservados. Aplica-se a contratos reservados (54º-A)? Não\n\n21 - CRITÉRIO DE ADJUDICAÇÃO\nMultifator: Não\nMonofator:\nNome: Preço\n\n24 - CONDIÇÕES DO CONTRATO\nFaturação Eletrónica: Permitido\nObrigação de Subcontratação:\nCódigo da Obrigação de Subcontratação: Não é aplicável nenhuma obrigação de subcontratação.\n\n25 - COMPRA PÚBLICA ESTRATÉGICA\nCompra Pública Estratégica: Inexistência de contratação pública estratégica\n\n26 - INFORMAÇÕES ADICIONAIS\nContrato adequado para PME: Sim\nCobertura ACP (Acordo dos Contratos Públicos da Organização Mundial do Comércio): Não\n\n27 - IDENTIFICAÇÃO E CONTACTOS DO ÓRGÃO DE RECURSOS ADMINISTRATIVOS\nDesignação: CMVM\nEndereço: Rua Laura Alves n.º 4\nCódigo postal: 1050-138\nLocalidade: Lisboa\nTelefone: +351 213177000\nFax: +351 213537077\nEndereço eletrónico: cmvm@cmvm.pt\n\n28 - IDENTIFICAÇÃO DO(S) AUTOR(ES) DE ANÚNCIO\nNome: Compras\nCargo: DFPA\n419461906",
    "nipc": "502549254",
    "distrito": "Lisboa",
    "concelho": "Lisboa",
    "freguesia": "Freguesia de Avenidas Novas",
    "site": "https://www.cmvm.pt/",
    "email": "cmvm@cmvm.pt",
    "designacao_contrato": "Módulo de Conformidade de Documentos",
    "descricao": "Implementação de um Módulo de Conformidade de Documentos e serviços de assistência técnica",
    "preco_base": "170.000,00 EUR",
    "prazo_execucao": "16 MESES",
    "prazo_apresentacao_propostas": "06-09-2025 17:00",
    "fundos_eu": "Não",
    "plataforma_eletronica": "VORTAL",
    "url_procedimento": "https://community.vortal.biz/public/",
    "autor_nome": "Compras",
    "autor_cargo": "DFPA"
  },
  {
    "numero_procedimento": "N/A",
    "entidade": "Santa Casa da Misericórdia de Vieira do Minho",
    "link": "https://diariodarepublica.pt/dr/detalhe/contrato-publico/22600-933115828",
    "detalhes_completos": "Alteração do Anúncio de procedimento n.º 21732/2025, de 2025-08-12, com o ID 419429069\n\n1 - IDENTIFICAÇÃO E CONTACTOS DA ENTIDADE ADJUDICANTE\nDesignação da entidade adjudicante: Santa Casa da Misericórdia de Vieira do Minho\nNIPC: 500956383\nEndereço: Praça Guilherme de Abreu\nCódigo postal: 4850-527\nLocalidade: Braga\nPaís: Portugal\nNUT III: PT119\nDistrito: Braga\nConcelho: Vieira do Minho\nFreguesia: Freguesia de Vieira do Minho\nTelefone: 253649330\nFax: 253649331\nEndereço Eletrónico: geral@scmvm.pt\neDelivery Gateway (URL): https://community.vortal.biz/public/\nFunção da Organização: Adquirente\nNorma jurídica da Entidade Adjudicante: Autoridade da administração central\nÁrea de atividade da Autoridade Adjudicante: Proteção social\n\n2 - JORNAL OFICIAL DA UNIÃO EUROPEIA\nO procedimento a que este anúncio diz respeito também é publicitado no Jornal Oficial da União Europeia? Não\n\n3 - AVISO\nModelo de Anúncio: Concurso público\nData de Envio do Anúncio: 22-08-2025\n\n5 - PROCESSO\nTipo de Procedimento: Concurso público\nPreço base do procedimento: Sim\nValor do preço base do procedimento: 189.831,38 EUR\nProcedimento com lotes? Não\n\n6 - OBJETO DO CONTRATO\nNúmero de referência interna: CP 01/2025\nDesignação do contrato: Remodelação e Ampliação do SAD da Santa Casa da Misericórdia de Vieira do Minho\nDescrição: Remodelação e Ampliação do SAD da Santa Casa da Misericórdia de Vieira do Minho\nTipo de Contrato Principal: Empreitada de Obras Públicas\nTipo de Contrato: Empreitada de Obras Públicas\nClassificação CPV (Vocabulário Comum para os Contratos Públicos)\nObjeto principal\nVocabulário Principal: 45215200\nPreço base s/IVA: 189.831,38 EUR\n\n7 - INDICAÇÕES ADICIONAIS\nO contrato envolve aquisição conjunta (satisfação de várias entidades)? Não\nO contrato é adjudicado por uma central de compras? Não\n\n8 - TÉCNICAS\nO concurso destina-se à celebração de um acordo-quadro? Inexistência de acordo-quadro\nÉ utilizado um leilão eletrónico? Não\nÉ adotada uma fase de negociação? Não\nSistema de Aquisição Dinâmico: Inexistência de sistema de aquisição dinâmico\n\n9 - LOCAL DA EXECUÇÃO DO CONTRATO\nLOCAL DA EXECUÇÃO DO CONTRATO (PROCEDIMENTO)\nPaís: Portugal\nNUT III: PT119\nLocalidade: Braga\nDistrito: Braga\nConcelho: Vieira do Minho\nFreguesia: Freguesia de Vieira do Minho\n\n10 - PRAZO DE EXECUÇÃO DO CONTRATO\nPrazo de execução do contrato: 4 MESES\nPrevisão de renovações: Não\n\n11 - FUNDOS EU\nTêm fundos EU? Sim\n\n12 - DOCUMENTOS DE HABILITAÇÃO\nHabilitação para o exercício da atividade profissional: Não\n\n13 - CONDIÇÕES DE APRESENTAÇÃO\nPlataforma eletrónica utilizada pela entidade adjudicante: VORTAL\nURL para Apresentação: https://community.vortal.biz/public/\nAdmissibilidade da apresentação de propostas variantes: Não autorizado\nPrazo para apresentação das propostas: 06-09-2025 17:00\nPrazo durante o qual os concorrentes são obrigados a manter as respetivas propostas: 90 dias a contar do termo do prazo para a apresentação das propostas\nApresentação de Catálogo Eletrónico: Permitido\nIndicação de Subcontratação na Proposta: Inexistência de indicação de subcontratação\n\n14 - PRESTAÇÃO DE CAUÇÃO\nPrestação de caução: Não\n\n15 - FORNECIMENTO DAS PEÇAS DO CONCURSO, APRESENTAÇÃO DE PEDIDOS DE PARTICIPAÇÃO E APRESENTAÇÃO DAS PROPOSTAS\nLink para acesso às peças do concurso (URL): https://community.vortal.biz/Public/public-tender-documents/WTRvcXhwWURKV3g4ZXBULysweUI0d0FpRHBpRCtmYTAxUHBTbHl2MStWVnNUOXQzdUhMendpMW50RytCdE15N1daRGp6M3laS3NSMi95SDUyV255VEE9PWQ3VmRr\n\n20 - OUTROS REQUISITOS\nInformação sobre contratos reservados. Aplica-se a contratos reservados (54º-A)? Não\n\n21 - CRITÉRIO DE ADJUDICAÇÃO\nMultifator: Sim\nFator: \nNome: Outros\nOutro Nome: Preço\nPonderação: 50%\nSubfatores: Não\nFator: \nNome: Qualidade\nPonderação: 50%\nSubfatores: Sim\nSubfatores: \nNome: MDJ - Memória descritiva e justificativa\nPonderação : 40%; \nNome: PT - Programa de trabalhos\nPonderação : 25%; \nNome: PMO - Plano de mão-de-obra\nPonderação : 10%; \nNome: PE - Plano de Equipamentos\nPonderação : 10%; \nNome: PG - Plano de Pagamentos\nPonderação : 15%; \n\n24 - CONDIÇÕES DO CONTRATO\nFaturação Eletrónica: Permitido\nObrigação de Subcontratação:\nCódigo da Obrigação de Subcontratação: Não é aplicável nenhuma obrigação de subcontratação.\n\n25 - COMPRA PÚBLICA ESTRATÉGICA\nCompra Pública Estratégica: Inexistência de contratação pública estratégica\n\n26 - INFORMAÇÕES ADICIONAIS\nContrato adequado para PME: Sim\nCobertura ACP (Acordo dos Contratos Públicos da Organização Mundial do Comércio): Não\n\n27 - IDENTIFICAÇÃO E CONTACTOS DO ÓRGÃO DE RECURSOS ADMINISTRATIVOS\nDesignação: Direção da Santa Casa da Misericórdia de Vieira do Minho\nEndereço: Rua Dr. Alfredo Ramalho, n.º 35\nCódigo postal: 4850-527\nLocalidade: Vieira do Minho\nTelefone: +351 253649330\nFax: +351 253649330\nEndereço eletrónico: geral@scmvm.pt\n\n28 - IDENTIFICAÇÃO DO(S) AUTOR(ES) DE ANÚNCIO\nNome:  Luís Eugénio da Silva Carneiro\nCargo: Provedor da Santa Casa da Misericórdia de Vieira do Minho\n\n29 - ALTERAÇÃO\nMotivo da Alteração: Correção pelo adquirente\nIdentificador da Versão do Anúncio a Alterar: 684e340e-ce83-432e-bade-f84b83e1e5b8-01\nIdentificador das Secções Alteradas do Anúncio Anterior: Processo\nAlteração dos Documentos do Concurso: Sim\nData de alteração dos documentos do concurso: 22-08-2025\n419462692",
    "nipc": "500956383",
    "distrito": "Braga",
    "concelho": "Vieira do Minho",
    "freguesia": "Freguesia de Vieira do Minho",
    "site": null,
    "email": "geral@scmvm.pt",
    "designacao_contrato": "Remodelação e Ampliação do SAD da Santa Casa da Misericórdia de Vieira do Minho",
    "descricao": "Remodelação e Ampliação do SAD da Santa Casa da Misericórdia de Vieira do Minho",
    "preco_base": "189.831,38 EUR",
    "prazo_execucao": "4 MESES",
    "prazo_apresentacao_propostas": "06-09-2025 17:00",
    "fundos_eu": "Sim",
    "plataforma_eletronica": "VORTAL",
    "url_procedimento": "https://community.vortal.biz/public/",
    "autor_nome": "Luís Eugénio da Silva Carneiro",
    "autor_cargo": "Provedor da Santa Casa da Misericórdia de Vieira do Minho"
  },
  {
    "numero_procedimento": "N/A",
    "entidade": "Agência Portuguesa do Ambiente, IP",
    "link": "https://diariodarepublica.pt/dr/detalhe/contrato-publico/22601-933115829",
    "detalhes_completos": "1 - IDENTIFICAÇÃO E CONTACTOS DA ENTIDADE ADJUDICANTE\nDesignação da entidade adjudicante: Agência Portuguesa do Ambiente, IP\nNIPC: 510306624\nServiço/Órgão/Pessoa de contacto: DRHL/ARH Algarve/Maria de Fátima Correia Martins\nEndereço: Rua da Murgueira, 9/9A- Zambujal -Ap. 7585\nCódigo postal: 2610-124\nLocalidade: Amadora\nPaís: Portugal\nNUT III: PT170\nDistrito: Lisboa\nConcelho: Todos\nFreguesia: Todas\nTelefone: 214728200\nFax: 214719074\nEndereço da Entidade (URL): www.apambiente.pt\nEndereço Eletrónico: geral@apambiente.pt\neDelivery Gateway (URL): https://www.acingov.pt\nFunção da Organização: Adquirente\nNorma jurídica da Entidade Adjudicante: Organismo de direito público\nÁrea de atividade da Autoridade Adjudicante: Proteção ambiental\n\n2 - JORNAL OFICIAL DA UNIÃO EUROPEIA\nO procedimento a que este anúncio diz respeito também é publicitado no Jornal Oficial da União Europeia? Sim\n\n3 - AVISO\nModelo de Anúncio: Concurso público\nData de Envio do Anúncio: 21-08-2025\n\n5 - PROCESSO\nTipo de Procedimento: Concurso público\nPreço base do procedimento: Sim\nValor do preço base do procedimento: 100.000,00 EUR\nProcedimento com lotes? Não\n\n6 - OBJETO DO CONTRATO\nNúmero de referência interna: CPI/9/2025\nDesignação do contrato: Aquisição de serviços de Fiscalização, Gestão da Qualidade, Ambiente e Coordenação de Segurança e Saúde em Obra da Empreitada de Migração Sedimentar para a praia do Vau - Portimão\nDescrição: Aquisição de serviços de Fiscalização, Gestão da Qualidade, Ambiente e Coordenação de Segurança e Saúde em Obra da Empreitada de Migração Sedimentar para a praia do Vau - Portimão\nOpções: Não\nTipo de Contrato Principal: Aquisição de Serviços\nTipo de Contrato: Aquisição de Serviços\nClassificação CPV (Vocabulário Comum para os Contratos Públicos)\nObjeto principal\nVocabulário Principal: 71330000\nPreço base s/IVA: 100.000,00 EUR\n\n7 - INDICAÇÕES ADICIONAIS\nO contrato envolve aquisição conjunta (satisfação de várias entidades)? Não\nO contrato é adjudicado por uma central de compras? Não\n\n8 - TÉCNICAS\nO concurso destina-se à celebração de um acordo-quadro? Inexistência de acordo-quadro\nÉ utilizado um leilão eletrónico? Não\nÉ adotada uma fase de negociação? Não\nSistema de Aquisição Dinâmico: Inexistência de sistema de aquisição dinâmico\n\n9 - LOCAL DA EXECUÇÃO DO CONTRATO\nLOCAL DA EXECUÇÃO DO CONTRATO (PROCEDIMENTO)\nPaís: Portugal\nNUT III: PT150\nLocalidade: Freguesia de Portimão\nDistrito: Faro\nConcelho: Portimão\nFreguesia: Freguesia de Portimão\n\n10 - PRAZO DE EXECUÇÃO DO CONTRATO\nPrazo de execução do contrato: 240 DIAS\nPrevisão de renovações: Não\n\n11 - FUNDOS EU\nTêm fundos EU? Sim\n\n12 - DOCUMENTOS DE HABILITAÇÃO\nHabilitação para o exercício da atividade profissional: Não\n\n13 - CONDIÇÕES DE APRESENTAÇÃO\nPlataforma eletrónica utilizada pela entidade adjudicante: ACIN\nURL para Apresentação: https://www.acingov.pt\nAdmissibilidade da apresentação de propostas variantes: Não autorizado\nPrazo para apresentação das propostas: 18-09-2025 23:59\nPrazo durante o qual os concorrentes são obrigados a manter as respetivas propostas: 66 dias a contar do termo do prazo para a apresentação das propostas\nApresentação de Catálogo Eletrónico: Não autorizado\nIndicação de Subcontratação na Proposta: Inexistência de indicação de subcontratação\n\n14 - PRESTAÇÃO DE CAUÇÃO\nPrestação de caução: Não\n\n15 - FORNECIMENTO DAS PEÇAS DO CONCURSO, APRESENTAÇÃO DE PEDIDOS DE PARTICIPAÇÃO E APRESENTAÇÃO DAS PROPOSTAS\nLink para acesso às peças do concurso (URL): https://www.acingov.pt/acingovprod/2/zonaPublica/zona_publica_c/donwloadProcedurePiece/OTM1MTA4\n\n20 - OUTROS REQUISITOS\nInformação sobre contratos reservados. Aplica-se a contratos reservados (54º-A)? Não\n\n21 - CRITÉRIO DE ADJUDICAÇÃO\nMultifator: Não\nMonofator:\nNome: Preço\n\n24 - CONDIÇÕES DO CONTRATO\nFaturação Eletrónica: Permitido\nObrigação de Subcontratação:\nCódigo da Obrigação de Subcontratação: Não é aplicável nenhuma obrigação de subcontratação.\n\n25 - COMPRA PÚBLICA ESTRATÉGICA\nCompra Pública Estratégica: Inexistência de contratação pública estratégica\n\n26 - INFORMAÇÕES ADICIONAIS\nContrato adequado para PME: Sim\nCobertura ACP (Acordo dos Contratos Públicos da Organização Mundial do Comércio): Não\n\n27 - IDENTIFICAÇÃO E CONTACTOS DO ÓRGÃO DE RECURSOS ADMINISTRATIVOS\nDesignação: Agência Portuguesa do Ambiente, I.P.\nEndereço: Rua da Murgueira, 9/9A- Zambujal -Ap. 7585\nCódigo postal: 2610-124\nLocalidade: Amadora\nTelefone: 214728200\nFax: 214719074\nEndereço eletrónico: geral@apambiente.pt\nPrazo de interposição do recurso: 30 dias\n\n28 - IDENTIFICAÇÃO DO(S) AUTOR(ES) DE ANÚNCIO\nNome: Luís Miguel Guerra\nCargo: Chefe de Divisão\n419449676",
    "nipc": "510306624",
    "distrito": "Lisboa",
    "concelho": "Todos",
    "freguesia": "Todas",
    "site": "www.apambiente.pt",
    "email": "geral@apambiente.pt",
    "designacao_contrato": "Aquisição de serviços de Fiscalização, Gestão da Qualidade, Ambiente e Coordenação de Segurança e Saúde em Obra da Empreitada de Migração Sedimentar para a praia do Vau - Portimão",
    "descricao": "Aquisição de serviços de Fiscalização, Gestão da Qualidade, Ambiente e Coordenação de Segurança e Saúde em Obra da Empreitada de Migração Sedimentar para a praia do Vau - Portimão",
    "preco_base": "100.000,00 EUR",
    "prazo_execucao": "240 DIAS",
    "prazo_apresentacao_propostas": "18-09-2025 23:59",
    "fundos_eu": "Sim",
    "plataforma_eletronica": "ACIN",
    "url_procedimento": "https://www.acingov.pt",
    "autor_nome": "Luís Miguel Guerra",
    "autor_cargo": "Chefe de Divisão"
  },
  {
    "numero_procedimento": "N/A",
    "entidade": "Município da Guarda",
    "link": "https://diariodarepublica.pt/dr/detalhe/contrato-publico/22602-933115830",
    "detalhes_completos": "Alteração do Anúncio de procedimento n.º 22065/2025, de 2025-08-18, com o ID 419437622\n\n1 - IDENTIFICAÇÃO E CONTACTOS DA ENTIDADE ADJUDICANTE\nDesignação da entidade adjudicante: Município da Guarda\nNIPC: 501131140\nEndereço: Praça do Município, nº 1\nCódigo postal: 6301-854\nLocalidade: Guarda\nPaís: Portugal\nNUT III: PT16J\nDistrito: Guarda\nConcelho: Guarda\nFreguesia: Freguesia de Guarda\nTelefone: 271220200\nFax: 271220280\nEndereço da Entidade (URL): www.mun-guarda.pt\nEndereço Eletrónico: geral@mun-guarda.pt\neDelivery Gateway (URL): https://community.vortal.biz/public/\nFunção da Organização: Adquirente\nNorma jurídica da Entidade Adjudicante: Autoridade local\nÁrea de atividade da Autoridade Adjudicante: Serviços públicos das administrações públicas\n\n2 - JORNAL OFICIAL DA UNIÃO EUROPEIA\nO procedimento a que este anúncio diz respeito também é publicitado no Jornal Oficial da União Europeia? Sim\n\n3 - AVISO\nModelo de Anúncio: Concurso público\nData de Envio do Anúncio: 21-08-2025\n\n5 - PROCESSO\nTipo de Procedimento: Concurso público\nPreço base do procedimento: Sim\nValor do preço base do procedimento: 9.420.000,00 EUR\nProcedimento com lotes? Não\n\n6 - OBJETO DO CONTRATO\nNúmero de referência interna: 126/2025\nDesignação do contrato: Prestação de Serviços de Recolha e Transporte a Destino Final de Resíduos Urbanos e Limpeza no Concelho da Guarda\nDescrição: Prestação de Serviços de Recolha e Transporte a Destino Final de Resíduos Urbanos e Limpeza no Concelho da Guarda\nOpções: Não\nTipo de Contrato Principal: Aquisição de Serviços\nTipo de Contrato: Aquisição de Serviços\nClassificação CPV (Vocabulário Comum para os Contratos Públicos)\nObjeto principal\nVocabulário Principal: 90511000\nPreço base s/IVA: 9.420.000,00 EUR\n\n7 - INDICAÇÕES ADICIONAIS\nO contrato envolve aquisição conjunta (satisfação de várias entidades)? Não\nO contrato é adjudicado por uma central de compras? Não\n\n8 - TÉCNICAS\nO concurso destina-se à celebração de um acordo-quadro? Inexistência de acordo-quadro\nÉ utilizado um leilão eletrónico? Não\nÉ adotada uma fase de negociação? Não\nSistema de Aquisição Dinâmico: Inexistência de sistema de aquisição dinâmico\n\n9 - LOCAL DA EXECUÇÃO DO CONTRATO\nLOCAL DA EXECUÇÃO DO CONTRATO (PROCEDIMENTO)\nPaís: Portugal\nNUT III: PT16J\nLocalidade: Guarda\nDistrito: Guarda\nConcelho: Guarda\nFreguesia: Freguesia de Guarda\n\n10 - PRAZO DE EXECUÇÃO DO CONTRATO\nPrazo de execução do contrato: 5 ANOS\nPrevisão de renovações: Não\n\n11 - FUNDOS EU\nTêm fundos EU? Não\n\n12 - DOCUMENTOS DE HABILITAÇÃO\nHabilitação para o exercício da atividade profissional: Sim\nTipo: Outros\nDescrição - Outros: Constantes nas peças procedimentais\nDescrição: Constantes das peças procedimentais\n\n13 - CONDIÇÕES DE APRESENTAÇÃO\nPlataforma eletrónica utilizada pela entidade adjudicante: VORTAL\nURL para Apresentação: https://community.vortal.biz/public/\nAdmissibilidade da apresentação de propostas variantes: Não autorizado\nPrazo para apresentação das propostas: 26-08-2025 16:00\nPrazo durante o qual os concorrentes são obrigados a manter as respetivas propostas: 66 dias a contar do termo do prazo para a apresentação das propostas\nApresentação de Catálogo Eletrónico: Permitido\nIndicação de Subcontratação na Proposta: Inexistência de indicação de subcontratação\n\n14 - PRESTAÇÃO DE CAUÇÃO\nPrestação de caução: Sim\nPercentagem: 5%\nDescrição da Garantia Exigida: Em conformidade com a cláusula 19ª do programa de procedimento\n\n15 - FORNECIMENTO DAS PEÇAS DO CONCURSO, APRESENTAÇÃO DE PEDIDOS DE PARTICIPAÇÃO E APRESENTAÇÃO DAS PROPOSTAS\nLink para acesso às peças do concurso (URL): https://community.vortal.biz/Public/public-tender-documents/QmlORTNWYlN6U3YwUjBGSDdGQitJYithdDRYcWM4WGVreXc2Si9VVURzOFhtbHM3MnpxT2kxS1Z6Ui90YkJ2Uk9VS3hWUmxGRjAwWElYVXMzbmI5eGc9PUFCVGth\n\n20 - OUTROS REQUISITOS\nInformação sobre contratos reservados. Aplica-se a contratos reservados (54º-A)? Não\n\n21 - CRITÉRIO DE ADJUDICAÇÃO\nMultifator: Sim\nFator: \nNome: Preço\nPonderação: 50%\nSubfatores: Não\nFator: \nNome: Qualidade\nPonderação: 50%\nSubfatores: Sim\nSubfatores: \nNome: Memória descritiva e justificativa\nPonderação : 55%; \nNome: Programa de Trabalhos\nPonderação : 45%; \n\n24 - CONDIÇÕES DO CONTRATO\nFaturação Eletrónica: Permitido\nObrigação de Subcontratação:\nCódigo da Obrigação de Subcontratação: Não é aplicável nenhuma obrigação de subcontratação.\n\n25 - COMPRA PÚBLICA ESTRATÉGICA\nCompra Pública Estratégica: Inexistência de contratação pública estratégica\n\n26 - INFORMAÇÕES ADICIONAIS\nContrato adequado para PME: Sim\nCobertura ACP (Acordo dos Contratos Públicos da Organização Mundial do Comércio): Não\n\n27 - IDENTIFICAÇÃO E CONTACTOS DO ÓRGÃO DE RECURSOS ADMINISTRATIVOS\nDesignação: Presidente da Câmara Municipal\nEndereço: Praça do Municipio.\nCódigo postal: 6301-854\nLocalidade: Guarda\nTelefone: +351 271220200\nFax: +351 271220280\nEndereço eletrónico: contratacaopublica@mun-guarda.pt\n\n28 - IDENTIFICAÇÃO DO(S) AUTOR(ES) DE ANÚNCIO\nNome: Sérgio Fernando da Silva Costa\nCargo: Presidente da Câmara Municipal\n\n29 - ALTERAÇÃO\nMotivo da Alteração: Correção pelo editor\nIdentificador da Versão do Anúncio a Alterar: 78382e6a-6a96-4805-8d3b-14bc0b784073-02\nIdentificador das Secções Alteradas do Anúncio Anterior: Condições de Apresentação\nDescrição das Alterações: Por lapso foi colocado mal o prazo para apresentação das propostas, deverão ter em conta o dia 26/08/2025.\nAlteração dos Documentos do Concurso: Não\n419452307",
    "nipc": "501131140",
    "distrito": "Guarda",
    "concelho": "Guarda",
    "freguesia": "Freguesia de Guarda",
    "site": "www.mun-guarda.pt",
    "email": "geral@mun-guarda.pt",
    "designacao_contrato": "Prestação de Serviços de Recolha e Transporte a Destino Final de Resíduos Urbanos e Limpeza no Concelho da Guarda",
    "descricao": "Prestação de Serviços de Recolha e Transporte a Destino Final de Resíduos Urbanos e Limpeza no Concelho da Guarda",
    "preco_base": "9.420.000,00 EUR",
    "prazo_execucao": "5 ANOS",
    "prazo_apresentacao_propostas": "26-08-2025 16:00",
    "fundos_eu": "Não",
    "plataforma_eletronica": "VORTAL",
    "url_procedimento": "https://community.vortal.biz/public/",
    "autor_nome": "Sérgio Fernando da Silva Costa",
    "autor_cargo": "Presidente da Câmara Municipal"
  },
  {
    "numero_procedimento": "N/A",
    "entidade": "AnÃºncio de procedimento  n.Âº 22604/2025  -  DiÃ¡rio da RepÃºblica n.Âº 162/2025, SÃ©rie II de 2025-08-25",
    "link": "https://diariodarepublica.pt/dr/detalhe/contrato-publico/22604-933115831"
  },
  {
    "numero_procedimento": "N/A",
    "entidade": "Unidade Local de Saúde de São José, E. P. E.",
    "link": "https://diariodarepublica.pt/dr/detalhe/contrato-publico/22606-933115832",
    "detalhes_completos": "1 - IDENTIFICAÇÃO E CONTACTOS DA ENTIDADE ADJUDICANTE\nDesignação da entidade adjudicante: Unidade Local de Saúde de São José, E. P. E.\nNIPC: 508080142\nEndereço: Rua José António Serrano\nCódigo postal: 1150-199\nLocalidade: Lisboa\nPaís: Portugal\nNUT III: PT170\nDistrito: Lisboa\nConcelho: Lisboa\nFreguesia: Freguesia de Arroios - Lisboa\nTelefone: 218841403\nFax: 218841025\nEndereço da Entidade (URL): www.chlc.min-saude.pt\nEndereço Eletrónico: geral@chlc.min-saude.pt\neDelivery Gateway (URL): https://community.vortal.biz/public/\nFunção da Organização: Adquirente\nNorma jurídica da Entidade Adjudicante: Organismo de direito público\nÁrea de atividade da Autoridade Adjudicante: Saúde\n\n2 - JORNAL OFICIAL DA UNIÃO EUROPEIA\nO procedimento a que este anúncio diz respeito também é publicitado no Jornal Oficial da União Europeia? Sim\n\n3 - AVISO\nModelo de Anúncio: Concurso público\nData de Envio do Anúncio: 21-08-2025\n\n5 - PROCESSO\nTipo de Procedimento: Concurso público\nPreço base do procedimento: Sim\nValor do preço base do procedimento: 221.554,40 EUR\nProcedimento com lotes? Sim\nNº Máx. de Lotes Autorizado: 29\nNúmero máximo de lotes que podem ser adjudicados a um concorrente: 29\n\n6 - OBJETO DO CONTRATO\nNúmero de referência interna: 12024125\nDesignação do contrato: CONCURSO PÚBLICO TENDENTE AO FORNECIMENTO DE MATERIAL DE DIAGNÓSTICO E EMBOLIZAÇÃO PARA VASCULAR, DESTINADO UNIDADE LOCAL DE SAÚDE DE S. JOSÉ, E.P.E., PARA O ANO DE 2025.\nDescrição: MATERIAL DE DIAGNÓSTICO E EMBOLIZAÇÃO PARA VASCULAR\nOpções: Não\nTipo de Contrato Principal: Aquisição de Bens Móveis\nTipo de Contrato: Aquisição de Bens Móveis\nClassificação CPV (Vocabulário Comum para os Contratos Públicos)\nObjeto principal\nVocabulário Principal: 33140000\nPreço base s/IVA: 221.554,40 EUR\nLotes: \nNº: LOT-0001\nDescrição do Lote: LOTE 1 - COILS DE PLATINA PARA EMBOLIZACAO\nPreço base s/IVA: 6.000,00 EUR\nClassificação CPV (Vocabulário Comum para os Contratos Públicos)\nObjeto principal\nVocabulário Principal: 33140000\nNº: LOT-0002\nDescrição do Lote: LOTE 2 - ESPIRAL DE EMBOLIZACAO 0.35\"\nPreço base s/IVA: 2.125,00 EUR\nClassificação CPV (Vocabulário Comum para os Contratos Públicos)\nObjeto principal\nVocabulário Principal: 33140000\nNº: LOT-0003\nDescrição do Lote: LOTE 3 - MICRO COILS FORMA CONICA 4MM\nPreço base s/IVA: 12.000,00 EUR\nClassificação CPV (Vocabulário Comum para os Contratos Públicos)\nObjeto principal\nVocabulário Principal: 33140000\nNº: LOT-0004\nDescrição do Lote: LOTE 4 - MICROCATETER EMBOLIZACAO 2.5FR-150CM\nPreço base s/IVA: 2.280,00 EUR\nClassificação CPV (Vocabulário Comum para os Contratos Públicos)\nObjeto principal\nVocabulário Principal: 33140000\nNº: LOT-0005\nDescrição do Lote: LOTE 5 - EMPURRADOR DE MICROCOIL 0.18''/180CM\nPreço base s/IVA: 900,00 EUR\nClassificação CPV (Vocabulário Comum para os Contratos Públicos)\nObjeto principal\nVocabulário Principal: 33140000\nNº: LOT-0006\nDescrição do Lote: LOTE 6 - HIDROCOIL DE EMBOLIZACAO\nPreço base s/IVA: 10.600,00 EUR\nClassificação CPV (Vocabulário Comum para os Contratos Públicos)\nObjeto principal\nVocabulário Principal: 33140000\nNº: LOT-0007\nDescrição do Lote: LOTE 7 - HIDROCOIL DE EMBOLIZACAO + ESPIRAL DE EMBOLIZAÇÃO\nPreço base s/IVA: 46.800,00 EUR\nClassificação CPV (Vocabulário Comum para os Contratos Públicos)\nObjeto principal\nVocabulário Principal: 33140000\nNº: LOT-0008\nDescrição do Lote: LOTE 8 - MICROCATETER CO-AXIAL 2.7FR 130CM\nPreço base s/IVA: 14.700,00 EUR\nClassificação CPV (Vocabulário Comum para os Contratos Públicos)\nObjeto principal\nVocabulário Principal: 33140000\nNº: LOT-0009\nDescrição do Lote: LOTE 9 - LIQUIDO EMBOLICO\nPreço base s/IVA: 4.887,00 EUR\nClassificação CPV (Vocabulário Comum para os Contratos Públicos)\nObjeto principal\nVocabulário Principal: 33140000\nNº: LOT-0010\nDescrição do Lote: LOTE 10 - MICROCATETER C/LUMEN P/EMBOLIZACAO\nPreço base s/IVA: 3.500,00 EUR\nClassificação CPV (Vocabulário Comum para os Contratos Públicos)\nObjeto principal\nVocabulário Principal: 33140000\nNº: LOT-0011\nDescrição do Lote: LOTE 11 - MICROCATETER DE LIBERTACAO DE COLAS\nPreço base s/IVA: 3.150,00 EUR\nClassificação CPV (Vocabulário Comum para os Contratos Públicos)\nObjeto principal\nVocabulário Principal: 33140000\nNº: LOT-0012\nDescrição do Lote: LOTE 12 - MICROGUIA TEFLONADA / HIDROFILICA 0,008\"\nPreço base s/IVA: 1.850,00 EUR\nClassificação CPV (Vocabulário Comum para os Contratos Públicos)\nObjeto principal\nVocabulário Principal: 33140000\nNº: LOT-0013\nDescrição do Lote: LOTE 13 - CATETER DE DIAGNOSTICO VERTEBRAL 5F\nPreço base s/IVA: 260,00 EUR\nClassificação CPV (Vocabulário Comum para os Contratos Públicos)\nObjeto principal\nVocabulário Principal: 33140000\nNº: LOT-0014\nDescrição do Lote: LOTE 14 - CATETER DIAGNOSTICO RENAL 5F\nPreço base s/IVA: 130,00 EUR\nClassificação CPV (Vocabulário Comum para os Contratos Públicos)\nObjeto principal\nVocabulário Principal: 33140000\nNº: LOT-0015\nDescrição do Lote: LOTE 15 - CATETER HEADHUNTER 5 F HIGH FLOW 100CM\nPreço base s/IVA: 270,00 EUR\nClassificação CPV (Vocabulário Comum para os Contratos Públicos)\nObjeto principal\nVocabulário Principal: 33140000\nNº: LOT-0016\nDescrição do Lote: LOTE 16 - CATETER DE INFUSAO 130MM 15CM PERFURADO\nPreço base s/IVA: 4.500,00 EUR\nClassificação CPV (Vocabulário Comum para os Contratos Públicos)\nObjeto principal\nVocabulário Principal: 33140000\nNº: LOT-0017\nDescrição do Lote: LOTE 17 - CATETER SIMMONS 1 5F HIGH FLOW 100CM\nPreço base s/IVA: 392,40 EUR\nClassificação CPV (Vocabulário Comum para os Contratos Públicos)\nObjeto principal\nVocabulário Principal: 33140000\nNº: LOT-0018\nDescrição do Lote: LOTE 18 - CATETERES PIGTAIL 5F HIGH FLOW 100CM\nPreço base s/IVA: 1.050,00 EUR\nClassificação CPV (Vocabulário Comum para os Contratos Públicos)\nObjeto principal\nVocabulário Principal: 33140000\nNº: LOT-0019\nDescrição do Lote: LOTE 19 - CATETER MULTIPROPOSE 5F A1 HIGH FLOW 100CM\nPreço base s/IVA: 210,00 EUR\nClassificação CPV (Vocabulário Comum para os Contratos Públicos)\nObjeto principal\nVocabulário Principal: 33140000\nNº: LOT-0020\nDescrição do Lote: LOTE 20 - CATETERES BERENSTEIN  4 F HIDROFILICO 100CM\nPreço base s/IVA: 17.500,00 EUR\nClassificação CPV (Vocabulário Comum para os Contratos Públicos)\nObjeto principal\nVocabulário Principal: 33140000\nNº: LOT-0021\nDescrição do Lote: LOTE 21 - CONJUNTOS VALVULADOS PARA FEMORAL\nPreço base s/IVA: 19.600,00 EUR\nClassificação CPV (Vocabulário Comum para os Contratos Públicos)\nObjeto principal\nVocabulário Principal: 33140000\nNº: LOT-0022\nDescrição do Lote: LOTE 22 - CONJUNTOS VALVULADOS PARA FEMORAL 12F C/ GUIA 0,35 / 0,38\"\nPreço base s/IVA: 2.000,00 EUR\nClassificação CPV (Vocabulário Comum para os Contratos Públicos)\nObjeto principal\nVocabulário Principal: 33140000\nNº: LOT-0023\nDescrição do Lote: LOTE 23 - MICROGUIA TEFLONADA / HIDROFILICA 0.018\"\nPreço base s/IVA: 11.200,00 EUR\nClassificação CPV (Vocabulário Comum para os Contratos Públicos)\nObjeto principal\nVocabulário Principal: 33140000\nNº: LOT-0024\nDescrição do Lote: LOTE 24 - MICROGUIA 0,014\" P/PERIFERICA\nPreço base s/IVA: 4.590,00 EUR\nClassificação CPV (Vocabulário Comum para os Contratos Públicos)\nObjeto principal\nVocabulário Principal: 33140000\nNº: LOT-0025\nDescrição do Lote: LOTE 25 - CATETERES PIGTAIL 5F HIGH FLOW CALIBRADO 100CM\nPreço base s/IVA: 7.050,00 EUR\nClassificação CPV (Vocabulário Comum para os Contratos Públicos)\nObjeto principal\nVocabulário Principal: 33140000\nNº: LOT-0026\nDescrição do Lote: LOTE 26 - SHUNTS PARA CAROTIDA 10 F\nPreço base s/IVA: 5.300,00 EUR\nClassificação CPV (Vocabulário Comum para os Contratos Públicos)\nObjeto principal\nVocabulário Principal: 33140000\nNº: LOT-0027\nDescrição do Lote: LOTE 27 - CATETER DE REENTRADA 120CM\nPreço base s/IVA: 3.700,00 EUR\nClassificação CPV (Vocabulário Comum para os Contratos Públicos)\nObjeto principal\nVocabulário Principal: 33140000\nNº: LOT-0028\nDescrição do Lote: LOTE 28 - CATETER DE SUPORTE E REENTRADA\nPreço base s/IVA: 10.500,00 EUR\nClassificação CPV (Vocabulário Comum para os Contratos Públicos)\nObjeto principal\nVocabulário Principal: 33140000\nNº: LOT-0029\nDescrição do Lote: LOTE 29 - MICROCOIL + PUNHO DE DESTACAMENTO + MICROCATETER\nPreço base s/IVA: 24.510,00 EUR\nClassificação CPV (Vocabulário Comum para os Contratos Públicos)\nObjeto principal\nVocabulário Principal: 33140000\n\n7 - INDICAÇÕES ADICIONAIS\nO contrato envolve aquisição conjunta (satisfação de várias entidades)? Não\nO contrato é adjudicado por uma central de compras? Não\n\n8 - TÉCNICAS\nO concurso destina-se à celebração de um acordo-quadro? Inexistência de acordo-quadro\nÉ utilizado um leilão eletrónico? Não\nÉ adotada uma fase de negociação? Não\nSistema de Aquisição Dinâmico: Inexistência de sistema de aquisição dinâmico\n\n9 - LOCAL DA EXECUÇÃO DO CONTRATO\nLOCAL DA EXECUÇÃO DO CONTRATO (PROCEDIMENTO)\nPaís: Portugal\nNUT III: PT170\nLocalidade: Lisboa\nDistrito: Lisboa\nConcelho: Lisboa\nFreguesia: Freguesia de Arroios - Lisboa\nLOCAL DA EXECUÇÃO DO CONTRATO (LOTE)\nIdentificador do Lote: LOT-0001; LOT-0002; LOT-0003; LOT-0004; LOT-0005; LOT-0006; LOT-0007; LOT-0008; LOT-0009; LOT-0010; LOT-0011; LOT-0012; LOT-0013; LOT-0014; LOT-0015; LOT-0016; LOT-0017; LOT-0018; LOT-0019; LOT-0020; LOT-0021; LOT-0022; LOT-0023; LOT-0024; LOT-0025; LOT-0026; LOT-0027; LOT-0028; LOT-0029\nPaís: Portugal\nNUT III: PT170\nLocalidade: Lisboa\nDistrito: Lisboa\nConcelho: Lisboa\nFreguesia: Freguesia de Arroios - Lisboa\n\n10 - PRAZO DE EXECUÇÃO DO CONTRATO\nIdentificador do Lote: LOT-0001; LOT-0002; LOT-0003; LOT-0004; LOT-0005; LOT-0006; LOT-0007; LOT-0008; LOT-0009; LOT-0010; LOT-0011; LOT-0012; LOT-0013; LOT-0014; LOT-0015; LOT-0016; LOT-0017; LOT-0018; LOT-0019; LOT-0020; LOT-0021; LOT-0022; LOT-0023; LOT-0024; LOT-0025; LOT-0026; LOT-0027; LOT-0028; LOT-0029\nPrazo de execução do contrato: 5 MESES\nPrevisão de renovações: Não\n\n11 - FUNDOS EU\nIdentificador do Lote: LOT-0001; LOT-0002; LOT-0003; LOT-0004; LOT-0005; LOT-0006; LOT-0007; LOT-0008; LOT-0009; LOT-0010; LOT-0011; LOT-0012; LOT-0013; LOT-0014; LOT-0015; LOT-0016; LOT-0017; LOT-0018; LOT-0019; LOT-0020; LOT-0021; LOT-0022; LOT-0023; LOT-0024; LOT-0025; LOT-0026; LOT-0027; LOT-0028; LOT-0029\nTêm fundos EU? Não\n\n12 - DOCUMENTOS DE HABILITAÇÃO\nHabilitação para o exercício da atividade profissional: Não\n\n13 - CONDIÇÕES DE APRESENTAÇÃO\nPlataforma eletrónica utilizada pela entidade adjudicante: VORTAL\nURL para Apresentação: https://community.vortal.biz/public/\nAdmissibilidade da apresentação de propostas variantes: Não autorizado\nPrazo para apresentação das propostas: 23-09-2025 23:59\nPrazo durante o qual os concorrentes são obrigados a manter as respetivas propostas: 120 dias a contar do termo do prazo para a apresentação das propostas\nApresentação de Catálogo Eletrónico: Não autorizado\nIndicação de Subcontratação na Proposta: Inexistência de indicação de subcontratação\n\n14 - PRESTAÇÃO DE CAUÇÃO\nPrestação de caução: Não\n\n15 - FORNECIMENTO DAS PEÇAS DO CONCURSO, APRESENTAÇÃO DE PEDIDOS DE PARTICIPAÇÃO E APRESENTAÇÃO DAS PROPOSTAS\nLink para acesso às peças do concurso (URL): https://community.vortal.biz/Public/public-tender-documents/akx0bk84V2VhYWJ3QW5NNmdtN2VadXE4djA3OFVWazhnbCsyM3dzazFJS2NxV0h0ZnJUR1I2NnV3MlhiQ08wUFh3Y1J5eUpoTFVkZmJnOGVHOWpvRkE9PU1SSk8p\n\n20 - OUTROS REQUISITOS\nIdentificador do Lote: LOT-0001; LOT-0002; LOT-0003; LOT-0004; LOT-0005; LOT-0006; LOT-0007; LOT-0008; LOT-0009; LOT-0010; LOT-0011; LOT-0012; LOT-0013; LOT-0014; LOT-0015; LOT-0016; LOT-0017; LOT-0018; LOT-0019; LOT-0020; LOT-0021; LOT-0022; LOT-0023; LOT-0024; LOT-0025; LOT-0026; LOT-0027; LOT-0028; LOT-0029\nInformação sobre contratos reservados. Aplica-se a contratos reservados (54º-A)? Não\n\n21 - CRITÉRIO DE ADJUDICAÇÃO\nO Critério de adjudicação é diferenciado por lote? Não\nMultifator: Não\nMonofator:\nNome: Preço\n\n24 - CONDIÇÕES DO CONTRATO\nIdentificador do Lote: LOT-0001; LOT-0002; LOT-0003; LOT-0004; LOT-0005; LOT-0006; LOT-0007; LOT-0008; LOT-0009; LOT-0010; LOT-0011; LOT-0012; LOT-0013; LOT-0014; LOT-0015; LOT-0016; LOT-0017; LOT-0018; LOT-0019; LOT-0020; LOT-0021; LOT-0022; LOT-0023; LOT-0024; LOT-0025; LOT-0026; LOT-0027; LOT-0028; LOT-0029\nFaturação Eletrónica: Permitido\nObrigação de Subcontratação:\nCódigo da Obrigação de Subcontratação: Não é aplicável nenhuma obrigação de subcontratação.\n\n25 - COMPRA PÚBLICA ESTRATÉGICA\nCompra Pública Estratégica: Inexistência de contratação pública estratégica\n\n26 - INFORMAÇÕES ADICIONAIS\nIdentificador do Lote: LOT-0001; LOT-0002; LOT-0003; LOT-0004; LOT-0005; LOT-0006; LOT-0007; LOT-0008; LOT-0009; LOT-0010; LOT-0011; LOT-0012; LOT-0013; LOT-0014; LOT-0015; LOT-0016; LOT-0017; LOT-0018; LOT-0019; LOT-0020; LOT-0021; LOT-0022; LOT-0023; LOT-0024; LOT-0025; LOT-0026; LOT-0027; LOT-0028; LOT-0029\nContrato adequado para PME: Sim\nCobertura ACP (Acordo dos Contratos Públicos da Organização Mundial do Comércio): Não\n\n27 - IDENTIFICAÇÃO E CONTACTOS DO ÓRGÃO DE RECURSOS ADMINISTRATIVOS\nDesignação: Conselho de Administração da Unidade Local de Saúde São José E.P.E.\nEndereço: Rua José António Serrano s/n\nCódigo postal: 1150-199\nLocalidade: Lisboa\nTelefone: +351 218841403\nFax: +351 218841025\nEndereço eletrónico: sec.vca@ulssjose.min-saude.pt\n\n28 - IDENTIFICAÇÃO DO(S) AUTOR(ES) DE ANÚNCIO\nNome: Conselho de Administração\nCargo: Conselho de Administração\n419451798",
    "nipc": "508080142",
    "distrito": "Lisboa",
    "concelho": "Lisboa",
    "freguesia": "Freguesia de Arroios - Lisboa",
    "site": "www.chlc.min-saude.pt",
    "email": "geral@chlc.min-saude.pt",
    "designacao_contrato": "CONCURSO PÚBLICO TENDENTE AO FORNECIMENTO DE MATERIAL DE DIAGNÓSTICO E EMBOLIZAÇÃO PARA VASCULAR, DESTINADO UNIDADE LOCAL DE SAÚDE DE S. JOSÉ, E.P.E., PARA O ANO DE 2025.",
    "descricao": "MATERIAL DE DIAGNÓSTICO E EMBOLIZAÇÃO PARA VASCULAR",
    "preco_base": "221.554,40 EUR",
    "prazo_execucao": "5 MESES",
    "prazo_apresentacao_propostas": "23-09-2025 23:59",
    "fundos_eu": "Não",
    "plataforma_eletronica": "VORTAL",
    "url_procedimento": "https://community.vortal.biz/public/",
    "autor_nome": "Conselho de Administração",
    "autor_cargo": "Conselho de Administração"
  },
  {
    "numero_procedimento": "N/A",
    "entidade": "Fundação INATEL",
    "link": "https://diariodarepublica.pt/dr/detalhe/contrato-publico/22611-933115833",
    "detalhes_completos": "1 - IDENTIFICAÇÃO E CONTACTOS DA ENTIDADE ADJUDICANTE\nDesignação da entidade adjudicante: Fundação INATEL\nNIPC: 500122237\nServiço/Órgão/Pessoa de contacto: Fundação INATEL - Núcleo de Contratação Pública\nEndereço: Calçada de Santana, nº 180\nCódigo postal: 1169-062\nLocalidade: Lisboa\nPaís: Portugal\nNUT III: PT170\nDistrito: Lisboa\nConcelho: Lisboa\nFreguesia: Freguesia de Arroios - Lisboa\nTelefone: 210027000\nFax: 210027000\nEndereço da Entidade (URL): https://www.inatel.pt\nEndereço Eletrónico: fundacao.inatel@inatel.pt\neDelivery Gateway (URL): https://www.acingov.pt\nFunção da Organização: Adquirente\nSubfunção da Organização: Organização cujo orçamento é utilizado para pagar o contrato; Organização que executa o pagamento; Organização que fornece informações adicionais sobre o processo de adjudicação; Organização que fornece mais informações sobre os prazos dos procedimentos de recurso; Organização que fornece acesso fora de linha aos documentos do concurso; Organização responsável pelo tratamento das propostas; Organização que recebe as propostas; Organização que trata os pedidos de participação; Organização que recebe pedidos de participação; Organização que fornece mais informações sobre os procedimentos de recurso; Organização que assina o contrato\nNorma jurídica da Entidade Adjudicante: Organismo de direito público\nÁrea de atividade da Autoridade Adjudicante: Atividades recreativas, culturais e religiosas\n\n2 - JORNAL OFICIAL DA UNIÃO EUROPEIA\nO procedimento a que este anúncio diz respeito também é publicitado no Jornal Oficial da União Europeia? Sim\n\n3 - AVISO\nModelo de Anúncio: Concurso limitado por prévia qualificação\nData de Envio do Anúncio: 21-08-2025\n\n5 - PROCESSO\nTipo de Procedimento: Concurso limitado por prévia qualificação\nPreço base do procedimento: Sim\nValor do preço base do procedimento: 479.000,00 EUR\nProcedimento com lotes? Não\n\n6 - OBJETO DO CONTRATO\nNúmero de referência interna: P.25.197/NCP\nDesignação do contrato: Aquisição de serviços de alojamento de servidores centrais e de comunicação de dados em Datacenter e respetivos serviços de monitorização e administração de sistemas\nDescrição: Aquisição de serviços de alojamento de servidores centrais e de comunicação de dados em Datacenter e respetivos serviços de monitorização e administração de sistemas\nOpções: Não\nTipo de Contrato Principal: Aquisição de Serviços\nTipo de Contrato: Aquisição de Serviços\nClassificação CPV (Vocabulário Comum para os Contratos Públicos)\nObjeto principal\nVocabulário Principal: 72514300\nPreço base s/IVA: 479.000,00 EUR\n\n7 - INDICAÇÕES ADICIONAIS\nO contrato envolve aquisição conjunta (satisfação de várias entidades)? Não\nO contrato é adjudicado por uma central de compras? Não\n\n8 - TÉCNICAS\nO concurso destina-se à celebração de um acordo-quadro? Inexistência de acordo-quadro\nÉ utilizado um leilão eletrónico? Não\nSistema de Aquisição Dinâmico: Inexistência de sistema de aquisição dinâmico\n\n9 - LOCAL DA EXECUÇÃO DO CONTRATO\nLOCAL DA EXECUÇÃO DO CONTRATO (PROCEDIMENTO)\nPaís: Portugal\nNUT III: PT170\nLocalidade: Freguesia de Arroios - Lisboa\nDistrito: Lisboa\nConcelho: Lisboa\nFreguesia: Freguesia de Arroios - Lisboa\n\n10 - PRAZO DE EXECUÇÃO DO CONTRATO\nData de Início: 01-12-2025\nData de Fim: 30-11-2027\nPrevisão de renovações: Não\n\n11 - FUNDOS EU\nTêm fundos EU? Não\n\n12 - DOCUMENTOS DE HABILITAÇÃO\nHabilitação para o exercício da atividade profissional: Não\n\n13 - CONDIÇÕES DE APRESENTAÇÃO\nPlataforma eletrónica utilizada pela entidade adjudicante: ACIN\nURL para Apresentação: https://www.acingov.pt\nAdmissibilidade da apresentação de propostas variantes: Não autorizado\nPrazo para apresentação das candidaturas: 22-09-2025 23:59\nPrazo para a decisão de qualificação: 44 dias a contar do termo do prazo para a apresentação das candidaturas\nRequisitos mínimos \nRequisitos mínimos de capacidade técnica: Requisitos Mínimos (Artigo 165º do CCP)\nRequisitos mínimos de capacidade financeira: Requisitos Mínimos (Artigo 165º do CCP)\nPrazo durante o qual os concorrentes são obrigados a manter as respetivas propostas: 90 dias a contar do termo do prazo para a apresentação das propostas\nApresentação de Catálogo Eletrónico: Permitido\nIndicação de Subcontratação na Proposta: Inexistência de indicação de subcontratação\n\n14 - PRESTAÇÃO DE CAUÇÃO\nPrestação de caução: Não\n\n15 - FORNECIMENTO DAS PEÇAS DO CONCURSO, APRESENTAÇÃO DE PEDIDOS DE PARTICIPAÇÃO E APRESENTAÇÃO DAS PROPOSTAS\nLink para acesso às peças do concurso (URL): https://www.acingov.pt/acingovprod/2/zonaPublica/zona_publica_c/donwloadProcedurePiece/OTM1NTMw\n\n20 - OUTROS REQUISITOS\nInformação sobre contratos reservados. Aplica-se a contratos reservados (54º-A)? Não\n\n21 - CRITÉRIO DE ADJUDICAÇÃO\nMultifator: Não\nMonofator:\nNome: Outros\nOutro nome: Fator Preço\n\n24 - CONDIÇÕES DO CONTRATO\nFaturação Eletrónica: Permitido\nObrigação de Subcontratação:\nCódigo da Obrigação de Subcontratação: Não é aplicável nenhuma obrigação de subcontratação.\n\n25 - COMPRA PÚBLICA ESTRATÉGICA\nCompra Pública Estratégica: Inexistência de contratação pública estratégica\n\n26 - INFORMAÇÕES ADICIONAIS\nContrato adequado para PME: Não\nCobertura ACP (Acordo dos Contratos Públicos da Organização Mundial do Comércio): Não\n\n27 - IDENTIFICAÇÃO E CONTACTOS DO ÓRGÃO DE RECURSOS ADMINISTRATIVOS\nDesignação: Conselho de Administração\nEndereço: Calçada de Sant'Ana, 180\nCódigo postal: 1169-062\nLocalidade: Lisboa\nTelefone: 210027000\nFax: 210027027\nEndereço eletrónico: ncp-procedimentos@inatel.pt\nPrazo de interposição do recurso: 5 dias\n\n28 - IDENTIFICAÇÃO DO(S) AUTOR(ES) DE ANÚNCIO\nNome: Tiago Tenreiro Alves\nCargo: Técnico\n419456877",
    "nipc": "500122237",
    "distrito": "Lisboa",
    "concelho": "Lisboa",
    "freguesia": "Freguesia de Arroios - Lisboa",
    "site": "https://www.inatel.pt",
    "email": "fundacao.inatel@inatel.pt",
    "designacao_contrato": "Aquisição de serviços de alojamento de servidores centrais e de comunicação de dados em Datacenter e respetivos serviços de monitorização e administração de sistemas",
    "descricao": "Aquisição de serviços de alojamento de servidores centrais e de comunicação de dados em Datacenter e respetivos serviços de monitorização e administração de sistemas",
    "preco_base": "479.000,00 EUR",
    "prazo_execucao": null,
    "prazo_apresentacao_propostas": null,
    "fundos_eu": "Não",
    "plataforma_eletronica": "ACIN",
    "url_procedimento": "https://www.acingov.pt",
    "autor_nome": "Tiago Tenreiro Alves",
    "autor_cargo": "Técnico"
  },
  {
    "numero_procedimento": "N/A",
    "entidade": "Município de Estarreja",
    "link": "https://diariodarepublica.pt/dr/detalhe/contrato-publico/22614-933115834",
    "detalhes_completos": "Alteração do Anúncio de procedimento n.º 20043/2025, de 2025-07-25, com o ID 419345209\n\n1 - IDENTIFICAÇÃO E CONTACTOS DA ENTIDADE ADJUDICANTE\nDesignação da entidade adjudicante: Município de Estarreja\nNIPC: 501190082\nServiço/Órgão/Pessoa de contacto: Divisão Económica e Financeira - Aprovisionamento e Contratação Pública\nEndereço: Praça Francisco Barbosa\nCódigo postal: 3860-001\nLocalidade: Estarreja\nPaís: Portugal\nNUT III: PT16D\nDistrito: Aveiro\nConcelho: Estarreja\nFreguesia: União das Freguesias de Beduído e Veiros\nTelefone: 234840600\nFax: 234840607\nEndereço da Entidade (URL): https://www.cm-estarreja.pt/\nEndereço Eletrónico: geral@cm-estarreja.pt\neDelivery Gateway (URL): https://www.acingov.pt\nFunção da Organização: Adquirente\nNorma jurídica da Entidade Adjudicante: Organismo de direito público\nÁrea de atividade da Autoridade Adjudicante: Serviços públicos das administrações públicas\n\n2 - JORNAL OFICIAL DA UNIÃO EUROPEIA\nO procedimento a que este anúncio diz respeito também é publicitado no Jornal Oficial da União Europeia? Sim\n\n3 - AVISO\nModelo de Anúncio: Concurso público\nData de Envio do Anúncio: 21-08-2025\n\n5 - PROCESSO\nTipo de Procedimento: Concurso público\nPreço base do procedimento: Sim\nValor do preço base do procedimento: 484.380,00 EUR\nProcedimento com lotes? Não\n\n6 - OBJETO DO CONTRATO\nNúmero de referência interna: CPub_S_005/2025\nDesignação do contrato: Recolha seletiva porta a porta de Biorresíduos (orgânicos e verdes) no Município de Estarreja\nDescrição: Recolha seletiva porta a porta de Biorresíduos (orgânicos e verdes) no Município de Estarreja\nOpções: Não\nTipo de Contrato Principal: Aquisição de Serviços\nTipo de Contrato: Aquisição de Serviços\nClassificação CPV (Vocabulário Comum para os Contratos Públicos)\nObjeto principal\nVocabulário Principal: 90511100\nPreço base s/IVA: 484.380,00 EUR\n\n7 - INDICAÇÕES ADICIONAIS\nO contrato envolve aquisição conjunta (satisfação de várias entidades)? Não\nO contrato é adjudicado por uma central de compras? Não\n\n8 - TÉCNICAS\nO concurso destina-se à celebração de um acordo-quadro? Inexistência de acordo-quadro\nÉ utilizado um leilão eletrónico? Não\nÉ adotada uma fase de negociação? Não\nSistema de Aquisição Dinâmico: Inexistência de sistema de aquisição dinâmico\n\n9 - LOCAL DA EXECUÇÃO DO CONTRATO\nLOCAL DA EXECUÇÃO DO CONTRATO (PROCEDIMENTO)\nPaís: Portugal\nNUT III: PT16D\nLocalidade: Estarreja\nDistrito: Aveiro\nConcelho: Estarreja\nFreguesia: Todas\n\n10 - PRAZO DE EXECUÇÃO DO CONTRATO\nPrazo de execução do contrato: 36 MESES\nPrevisão de renovações: Não\n\n11 - FUNDOS EU\nTêm fundos EU? Não\n\n12 - DOCUMENTOS DE HABILITAÇÃO\nHabilitação para o exercício da atividade profissional: Não\n\n13 - CONDIÇÕES DE APRESENTAÇÃO\nPlataforma eletrónica utilizada pela entidade adjudicante: ACIN\nURL para Apresentação: https://www.acingov.pt\nAdmissibilidade da apresentação de propostas variantes: Não autorizado\nPrazo para apresentação das propostas: 12-09-2025 23:59\nPrazo durante o qual os concorrentes são obrigados a manter as respetivas propostas: 120 dias a contar do termo do prazo para a apresentação das propostas\nApresentação de Catálogo Eletrónico: Permitido\nIndicação de Subcontratação na Proposta: Inexistência de indicação de subcontratação\n\n14 - PRESTAÇÃO DE CAUÇÃO\nPrestação de caução: Não\n\n15 - FORNECIMENTO DAS PEÇAS DO CONCURSO, APRESENTAÇÃO DE PEDIDOS DE PARTICIPAÇÃO E APRESENTAÇÃO DAS PROPOSTAS\nLink para acesso às peças do concurso (URL): https://www.acingov.pt/acingovprod/2/zonaPublica/zona_publica_c/donwloadProcedurePiece/OTI2OTYy\n\n20 - OUTROS REQUISITOS\nInformação sobre contratos reservados. Aplica-se a contratos reservados (54º-A)? Não\n\n21 - CRITÉRIO DE ADJUDICAÇÃO\nMultifator: Não\nMonofator:\nNome: Preço\n\n24 - CONDIÇÕES DO CONTRATO\nFaturação Eletrónica: Permitido\nObrigação de Subcontratação:\nCódigo da Obrigação de Subcontratação: Não é aplicável nenhuma obrigação de subcontratação.\n\n25 - COMPRA PÚBLICA ESTRATÉGICA\nCompra Pública Estratégica: Inexistência de contratação pública estratégica\n\n26 - INFORMAÇÕES ADICIONAIS\nContrato adequado para PME: Sim\nCobertura ACP (Acordo dos Contratos Públicos da Organização Mundial do Comércio): Não\n\n27 - IDENTIFICAÇÃO E CONTACTOS DO ÓRGÃO DE RECURSOS ADMINISTRATIVOS\nDesignação: Presidente da Câmara Municipal\nEndereço: Praça Francisco Barbosa\nCódigo postal: 3860-001\nLocalidade: Estarreja\nTelefone: 234840600\nFax: \nEndereço eletrónico: geral@cm-estarreja.pt\nPrazo de interposição do recurso: 5 dias\n\n28 - IDENTIFICAÇÃO DO(S) AUTOR(ES) DE ANÚNCIO\nNome: Diamantino Manuel Sabina\nCargo: Presidente da Câmara\n\n29 - ALTERAÇÃO\nMotivo da Alteração: Correção pelo adquirente\nIdentificador da Versão do Anúncio a Alterar: 27d24d49-8cb7-4455-9499-cb283d99c058-01\nIdentificador das Secções Alteradas do Anúncio Anterior: Condições de Apresentação\nDescrição das Alterações: Prorrogação do prazo para apresentação de propostas\nAlteração dos Documentos do Concurso: Não\n419457557",
    "nipc": "501190082",
    "distrito": "Aveiro",
    "concelho": "Estarreja",
    "freguesia": "União das Freguesias de Beduído e Veiros",
    "site": "https://www.cm-estarreja.pt/",
    "email": "geral@cm-estarreja.pt",
    "designacao_contrato": "Recolha seletiva porta a porta de Biorresíduos (orgânicos e verdes) no Município de Estarreja",
    "descricao": "Recolha seletiva porta a porta de Biorresíduos (orgânicos e verdes) no Município de Estarreja",
    "preco_base": "484.380,00 EUR",
    "prazo_execucao": "36 MESES",
    "prazo_apresentacao_propostas": "12-09-2025 23:59",
    "fundos_eu": "Não",
    "plataforma_eletronica": "ACIN",
    "url_procedimento": "https://www.acingov.pt",
    "autor_nome": "Diamantino Manuel Sabina",
    "autor_cargo": "Presidente da Câmara"
  },
  {
    "numero_procedimento": "N/A",
    "entidade": "TUB - Transportes Urbanos de Braga, E.M.",
    "link": "https://diariodarepublica.pt/dr/detalhe/contrato-publico/22617-933115835",
    "detalhes_completos": "Alteração do Anúncio de procedimento n.º 21248/2025, de 2025-08-07, com o ID 419397196\n\n1 - IDENTIFICAÇÃO E CONTACTOS DA ENTIDADE ADJUDICANTE\nDesignação da entidade adjudicante: TUB - Transportes Urbanos de Braga, E.M.\nNIPC: 504807684\nServiço/Órgão/Pessoa de contacto: Secretaria Geral\nEndereço: Rua Quinta de Santa Maria, Apartado 2383\nCódigo postal: 4700-244\nLocalidade: Braga\nPaís: Portugal\nNUT III: PT112\nDistrito: Braga\nConcelho: Braga\nFreguesia: Todas\nTelefone: 253606890\nFax: 253606899\nEndereço da Entidade (URL): https://tub.pt\nEndereço Eletrónico: geral@tub.pt\neDelivery Gateway (URL): https://www.acingov.pt\nFunção da Organização: Adquirente\nNorma jurídica da Entidade Adjudicante: Organismo de direito público\nÁrea de atividade da Autoridade Adjudicante: Serviços públicos das administrações públicas\n\n2 - JORNAL OFICIAL DA UNIÃO EUROPEIA\nO procedimento a que este anúncio diz respeito também é publicitado no Jornal Oficial da União Europeia? Sim\n\n3 - AVISO\nModelo de Anúncio: Concurso público\nData de Envio do Anúncio: 21-08-2025\n\n5 - PROCESSO\nTipo de Procedimento: Concurso público\nPreço base do procedimento: Sim\nValor do preço base do procedimento: 17.346.000,00 EUR\nProcedimento com lotes? Não\n\n6 - OBJETO DO CONTRATO\nNúmero de referência interna: 42/2025\nDesignação do contrato: Fornecimento de Autocarros Elétricos para Transporte Urbano de Passageiros, Equipamentos de Carregamento e Respetivas Infraestruturas Elétricas e Serviços de Manutenção\nDescrição: Fornecimento de Autocarros Elétricos para Transporte Urbano de Passageiros, Equipamentos de Carregamento e Respetivas Infraestruturas Elétricas e Serviços de Manutenção\nOpções: Não\nTipo de Contrato Principal: Aquisição de Bens Móveis\nTipo de Contrato: Aquisição de Bens Móveis; Aquisição de Serviços\nClassificação CPV (Vocabulário Comum para os Contratos Públicos)\nObjeto principal\nVocabulário Principal: 34144910\nPreço base s/IVA: 10.800.000,00 EUR\nObjeto Complementar\nVocabulário Principal: 31158000\nPreço base s/IVA: 1.200.000,00 EUR\nObjeto Complementar\nVocabulário Principal: 50113200\nPreço base s/IVA: 5.346.000,00 EUR\n\n7 - INDICAÇÕES ADICIONAIS\nO contrato envolve aquisição conjunta (satisfação de várias entidades)? Não\nO contrato é adjudicado por uma central de compras? Não\n\n8 - TÉCNICAS\nO concurso destina-se à celebração de um acordo-quadro? Inexistência de acordo-quadro\nÉ utilizado um leilão eletrónico? Não\nÉ adotada uma fase de negociação? Não\nSistema de Aquisição Dinâmico: Inexistência de sistema de aquisição dinâmico\n\n9 - LOCAL DA EXECUÇÃO DO CONTRATO\nLOCAL DA EXECUÇÃO DO CONTRATO (PROCEDIMENTO)\nPaís: Portugal\nNUT III: PT112\nLocalidade: Braga\nDistrito: Braga\nConcelho: Braga\nFreguesia: Todas\n\n10 - PRAZO DE EXECUÇÃO DO CONTRATO\nPrazo de execução do contrato: 16 ANOS\nPrevisão de renovações: Não\n\n11 - FUNDOS EU\nTêm fundos EU? Sim\n\n12 - DOCUMENTOS DE HABILITAÇÃO\nHabilitação para o exercício da atividade profissional: Não\n\n13 - CONDIÇÕES DE APRESENTAÇÃO\nPlataforma eletrónica utilizada pela entidade adjudicante: ACIN\nURL para Apresentação: https://www.acingov.pt\nAdmissibilidade da apresentação de propostas variantes: Não autorizado\nPrazo para apresentação das propostas: 22-09-2025 23:59\nPrazo durante o qual os concorrentes são obrigados a manter as respetivas propostas: 66 dias a contar do termo do prazo para a apresentação das propostas\nApresentação de Catálogo Eletrónico: Permitido\nIndicação de Subcontratação na Proposta: Inexistência de indicação de subcontratação\n\n14 - PRESTAÇÃO DE CAUÇÃO\nPrestação de caução: Sim\nPercentagem: 5%\nDescrição da Garantia Exigida: O valor da caução é de 5.00% do preço contratual.\n\n15 - FORNECIMENTO DAS PEÇAS DO CONCURSO, APRESENTAÇÃO DE PEDIDOS DE PARTICIPAÇÃO E APRESENTAÇÃO DAS PROPOSTAS\nLink para acesso às peças do concurso (URL): https://www.acingov.pt/acingovprod/2/zonaPublica/zona_publica_c/donwloadProcedurePiece/OTMwNDA5\n\n20 - OUTROS REQUISITOS\nInformação sobre contratos reservados. Aplica-se a contratos reservados (54º-A)? Não\n\n21 - CRITÉRIO DE ADJUDICAÇÃO\nMultifator: Sim\nFator: \nNome: Preço\nPonderação: 60%\nSubfatores: Sim\nSubfatores: \nNome: Preço do Fornecimento das Viaturas\nPonderação : 90%; \nNome: Preço do Fornecimento dos Carregadores e Infraestruturas Elétricas\nPonderação : 10%; \nFator: \nNome: Outros\nOutro Nome: Consumo Específico de Energia\nPonderação: 20%\nSubfatores: Não\nFator: \nNome: Outros\nOutro Nome: Custo por km de Manutenção\nPonderação: 18%\nSubfatores: Não\nFator: \nNome: Outros\nOutro Nome: Existência de Certificação ISO 14001:2015\nPonderação: 2%\nSubfatores: Não\n\n24 - CONDIÇÕES DO CONTRATO\nFaturação Eletrónica: Permitido\nObrigação de Subcontratação:\nCódigo da Obrigação de Subcontratação: Não é aplicável nenhuma obrigação de subcontratação.\n\n25 - COMPRA PÚBLICA ESTRATÉGICA\nCompra Pública Estratégica: Inexistência de contratação pública estratégica\n\n26 - INFORMAÇÕES ADICIONAIS\nContrato adequado para PME: Não\nCobertura ACP (Acordo dos Contratos Públicos da Organização Mundial do Comércio): Não\n\n27 - IDENTIFICAÇÃO E CONTACTOS DO ÓRGÃO DE RECURSOS ADMINISTRATIVOS\nDesignação: Conselho de Administração\nEndereço: Rua Quinta de Santa Maria, Apartado 2383\nCódigo postal: 4700-244\nLocalidade: Braga\nTelefone: 253606890\nFax: 253606899\nEndereço eletrónico: geral@tub.pt\n\n28 - IDENTIFICAÇÃO DO(S) AUTOR(ES) DE ANÚNCIO\nNome: Bruno Filipe Sequeira de Oliveira\nCargo: Jurista\n\n29 - ALTERAÇÃO\nMotivo da Alteração: Informações atualizadas\nIdentificador da Versão do Anúncio a Alterar: 658d3c31-2f2b-4d0d-abee-f13266fdef0b-01\nIdentificador das Secções Alteradas do Anúncio Anterior: Condições de Apresentação\nDescrição das Alterações: Modificação do prazo para a apresentação de propostas\nAlteração dos Documentos do Concurso: Sim\nData de alteração dos documentos do concurso: 20-08-2025\n419458626",
    "nipc": "504807684",
    "distrito": "Braga",
    "concelho": "Braga",
    "freguesia": "Todas",
    "site": "https://tub.pt",
    "email": "geral@tub.pt",
    "designacao_contrato": "Fornecimento de Autocarros Elétricos para Transporte Urbano de Passageiros, Equipamentos de Carregamento e Respetivas Infraestruturas Elétricas e Serviços de Manutenção",
    "descricao": "Fornecimento de Autocarros Elétricos para Transporte Urbano de Passageiros, Equipamentos de Carregamento e Respetivas Infraestruturas Elétricas e Serviços de Manutenção",
    "preco_base": "10.800.000,00 EUR",
    "prazo_execucao": "16 ANOS",
    "prazo_apresentacao_propostas": "22-09-2025 23:59",
    "fundos_eu": "Sim",
    "plataforma_eletronica": "ACIN",
    "url_procedimento": "https://www.acingov.pt",
    "autor_nome": "Bruno Filipe Sequeira de Oliveira",
    "autor_cargo": "Jurista"
  },
  {
    "numero_procedimento": "N/A",
    "entidade": "Câmara Municipal de Matosinhos",
    "link": "https://diariodarepublica.pt/dr/detalhe/contrato-publico/22619-933115836",
    "detalhes_completos": "1 - IDENTIFICAÇÃO E CONTACTOS DA ENTIDADE ADJUDICANTE\nDesignação da entidade adjudicante: Câmara Municipal de Matosinhos\nNIPC: 501305912\nEndereço: Av. D. Afonso Henriques\nCódigo postal: 4454-510\nLocalidade: Matosinhos\nPaís: Portugal\nNUT III: PT11A\nDistrito: Porto\nConcelho: Matosinhos\nFreguesia: Todas\nTelefone: 229390900\nFax: 229351645\nEndereço da Entidade (URL): http://www.cm-matosinhos.pt\nEndereço Eletrónico: contratacaopublica@cm-matosinhos.pt\neDelivery Gateway (URL): https://www.acingov.pt\nFunção da Organização: Adquirente\nSubfunção da Organização: Organização que recebe as propostas\nNorma jurídica da Entidade Adjudicante: Organismo de direito público\nÁrea de atividade da Autoridade Adjudicante: Serviços públicos das administrações públicas\n\n2 - JORNAL OFICIAL DA UNIÃO EUROPEIA\nO procedimento a que este anúncio diz respeito também é publicitado no Jornal Oficial da União Europeia? Sim\n\n3 - AVISO\nModelo de Anúncio: Concurso público\nData de Envio do Anúncio: 21-08-2025\n\n5 - PROCESSO\nTipo de Procedimento: Concurso público\nPreço base do procedimento: Sim\nValor do preço base do procedimento: 243.902,45 EUR\nProcedimento com lotes? Não\n\n6 - OBJETO DO CONTRATO\nNúmero de referência interna: CPI/2025/26204\nDesignação do contrato: Abertura de Procedimento para aquisição de Serviços de Pequenas Reparações ao Domicilio - Matosinhos-REPARA\nDescrição: Abertura de Procedimento para aquisição de Serviços de Pequenas Reparações ao Domicilio - Matosinhos-REPARA\nOpções: Não\nTipo de Contrato Principal: Aquisição de Serviços\nTipo de Contrato: Aquisição de Serviços\nClassificação CPV (Vocabulário Comum para os Contratos Públicos)\nObjeto principal\nVocabulário Principal: 50700000\nPreço base s/IVA: 243.902,45 EUR\n\n7 - INDICAÇÕES ADICIONAIS\nO contrato envolve aquisição conjunta (satisfação de várias entidades)? Não\nO contrato é adjudicado por uma central de compras? Não\n\n8 - TÉCNICAS\nO concurso destina-se à celebração de um acordo-quadro? Inexistência de acordo-quadro\nÉ utilizado um leilão eletrónico? Não\nÉ adotada uma fase de negociação? Não\nSistema de Aquisição Dinâmico: Inexistência de sistema de aquisição dinâmico\n\n9 - LOCAL DA EXECUÇÃO DO CONTRATO\nLOCAL DA EXECUÇÃO DO CONTRATO (PROCEDIMENTO)\nPaís: Portugal\nNUT III: PT11A\nLocalidade: Matosinhos\nDistrito: Porto\nConcelho: Matosinhos\nFreguesia: Todas\n\n10 - PRAZO DE EXECUÇÃO DO CONTRATO\nPrazo de execução do contrato: 36 MESES\nPrevisão de renovações: Não\n\n11 - FUNDOS EU\nTêm fundos EU? Não\n\n12 - DOCUMENTOS DE HABILITAÇÃO\nHabilitação para o exercício da atividade profissional: Não\n\n13 - CONDIÇÕES DE APRESENTAÇÃO\nPlataforma eletrónica utilizada pela entidade adjudicante: ACIN\nURL para Apresentação: https://www.acingov.pt\nAdmissibilidade da apresentação de propostas variantes: Não autorizado\nPrazo para apresentação das propostas: 08-09-2025 23:59\nPrazo durante o qual os concorrentes são obrigados a manter as respetivas propostas: 66 dias a contar do termo do prazo para a apresentação das propostas\nApresentação de Catálogo Eletrónico: Permitido\nIndicação de Subcontratação na Proposta: Inexistência de indicação de subcontratação\n\n14 - PRESTAÇÃO DE CAUÇÃO\nPrestação de caução: Não\n\n15 - FORNECIMENTO DAS PEÇAS DO CONCURSO, APRESENTAÇÃO DE PEDIDOS DE PARTICIPAÇÃO E APRESENTAÇÃO DAS PROPOSTAS\nLink para acesso às peças do concurso (URL): https://www.acingov.pt/acingovprod/2/zonaPublica/zona_publica_c/donwloadProcedurePiece/OTM0NjEx\n\n20 - OUTROS REQUISITOS\nInformação sobre contratos reservados. Aplica-se a contratos reservados (54º-A)? Não\n\n21 - CRITÉRIO DE ADJUDICAÇÃO\nMultifator: Não\nMonofator:\nNome: Preço\n\n24 - CONDIÇÕES DO CONTRATO\nFaturação Eletrónica: Permitido\nObrigação de Subcontratação:\nCódigo da Obrigação de Subcontratação: Não é aplicável nenhuma obrigação de subcontratação.\n\n25 - COMPRA PÚBLICA ESTRATÉGICA\nCompra Pública Estratégica: Inexistência de contratação pública estratégica\n\n26 - INFORMAÇÕES ADICIONAIS\nContrato adequado para PME: Não\nCobertura ACP (Acordo dos Contratos Públicos da Organização Mundial do Comércio): Não\n\n27 - IDENTIFICAÇÃO E CONTACTOS DO ÓRGÃO DE RECURSOS ADMINISTRATIVOS\nDesignação: Município de Matosinhos\nEndereço: Av. D. Afonso Henriques\nCódigo postal: 4454-510\nLocalidade: Matosinhos\nTelefone: 229390900\nFax: \nEndereço eletrónico: contratacaopublica@m-matosinhos.pt\n\n28 - IDENTIFICAÇÃO DO(S) AUTOR(ES) DE ANÚNCIO\nNome: Dr.ª Luísa Salgueiro\nCargo: Presidente da Câmara\n419454357",
    "nipc": "501305912",
    "distrito": "Porto",
    "concelho": "Matosinhos",
    "freguesia": "Todas",
    "site": "http://www.cm-matosinhos.pt",
    "email": "contratacaopublica@cm-matosinhos.pt",
    "designacao_contrato": "Abertura de Procedimento para aquisição de Serviços de Pequenas Reparações ao Domicilio - Matosinhos-REPARA",
    "descricao": "Abertura de Procedimento para aquisição de Serviços de Pequenas Reparações ao Domicilio - Matosinhos-REPARA",
    "preco_base": "243.902,45 EUR",
    "prazo_execucao": "36 MESES",
    "prazo_apresentacao_propostas": "08-09-2025 23:59",
    "fundos_eu": "Não",
    "plataforma_eletronica": "ACIN",
    "url_procedimento": "https://www.acingov.pt",
    "autor_nome": "Dr.ª Luísa Salgueiro",
    "autor_cargo": "Presidente da Câmara"
  },
  {
    "numero_procedimento": "N/A",
    "entidade": "Águas do Norte, S.A.",
    "link": "https://diariodarepublica.pt/dr/detalhe/contrato-publico/22620-933115837",
    "detalhes_completos": "Alteração do Anúncio de procedimento n.º 21542/2025, de 2025-08-11, com o ID 419412236\n\n1 - IDENTIFICAÇÃO E CONTACTOS DA ENTIDADE ADJUDICANTE\nDesignação da entidade adjudicante: Águas do Norte, S.A.\nNIPC: 513606084\nServiço/Órgão/Pessoa de contacto: Compras e Logística\nEndereço: Rua Dom Pedro de Castro, n.º 1A\nCódigo postal: 5000-669\nLocalidade: Vila Real\nPaís: Portugal\nNUT III: PT11D\nDistrito: Vila Real\nConcelho: Vila Real\nFreguesia: Freguesia de Vila Real\nTelefone: 259309370\nFax: 259309371\nEndereço da Entidade (URL): www.adnorte.pt\nEndereço Eletrónico: geral.adnorte@adp.pt\neDelivery Gateway (URL): https://www.acingov.pt\nFunção da Organização: Adquirente\nNorma jurídica da Entidade Adjudicante: Organismo de direito público\nÁrea de atividade da Autoridade Adjudicante: Serviços públicos das administrações públicas\n\n2 - JORNAL OFICIAL DA UNIÃO EUROPEIA\nO procedimento a que este anúncio diz respeito também é publicitado no Jornal Oficial da União Europeia? Sim\n\n3 - AVISO\nModelo de Anúncio: Concurso público\nData de Envio do Anúncio: 22-08-2025\n\n5 - PROCESSO\nTipo de Procedimento: Concurso público\nPreço base do procedimento: Sim\nValor do preço base do procedimento: 274.000,00 EUR\nProcedimento com lotes? Não\n\n6 - OBJETO DO CONTRATO\nNúmero de referência interna: PRC_0233/2025_DEX\nDesignação do contrato: PRC_0233/2025_DEX - Fornecimento de Oxigénio (O2) para a ETAR de Penices\nDescrição: PRC_0233/2025_DEX - Fornecimento de Oxigénio (O2) para a ETAR de Penices\nOpções: Não\nTipo de Contrato Principal: Aquisição de Bens Móveis\nTipo de Contrato: Aquisição de Bens Móveis\nClassificação CPV (Vocabulário Comum para os Contratos Públicos)\nObjeto principal\nVocabulário Principal: 24111900\nPreço base s/IVA: 274.000,00 EUR\n\n7 - INDICAÇÕES ADICIONAIS\nO contrato envolve aquisição conjunta (satisfação de várias entidades)? Não\nO contrato é adjudicado por uma central de compras? Não\n\n8 - TÉCNICAS\nO concurso destina-se à celebração de um acordo-quadro? Inexistência de acordo-quadro\nÉ utilizado um leilão eletrónico? Não\nÉ adotada uma fase de negociação? Não\nSistema de Aquisição Dinâmico: Inexistência de sistema de aquisição dinâmico\n\n9 - LOCAL DA EXECUÇÃO DO CONTRATO\nLOCAL DA EXECUÇÃO DO CONTRATO (PROCEDIMENTO)\nPaís: Portugal\nNUT III: PT119\nLocalidade: União das Freguesias de Gondifelos, Cavalões e Outiz\nDistrito: Braga\nConcelho: Vila Nova de Famalicão\nFreguesia: União das Freguesias de Gondifelos, Cavalões e Outiz\n\n10 - PRAZO DE EXECUÇÃO DO CONTRATO\nPrazo de execução do contrato: 2 ANOS\nPrevisão de renovações: Sim\nIndicar número máximo de renovações: 1\nPrazo de renovações diferente do prazo inicial: Não\n\n11 - FUNDOS EU\nTêm fundos EU? Não\n\n12 - DOCUMENTOS DE HABILITAÇÃO\nHabilitação para o exercício da atividade profissional: Não\n\n13 - CONDIÇÕES DE APRESENTAÇÃO\nPlataforma eletrónica utilizada pela entidade adjudicante: ACIN\nURL para Apresentação: https://www.acingov.pt\nAdmissibilidade da apresentação de propostas variantes: Não autorizado\nPrazo para apresentação das propostas: 03-09-2025 17:00\nPrazo durante o qual os concorrentes são obrigados a manter as respetivas propostas: 90 dias a contar do termo do prazo para a apresentação das propostas\nApresentação de Catálogo Eletrónico: Não autorizado\nIndicação de Subcontratação na Proposta: Inexistência de indicação de subcontratação\n\n14 - PRESTAÇÃO DE CAUÇÃO\nPrestação de caução: Sim\nPercentagem: 2%\nDescrição da Garantia Exigida: O valor da caução é de 2.00% do preço contratual.\n\n15 - FORNECIMENTO DAS PEÇAS DO CONCURSO, APRESENTAÇÃO DE PEDIDOS DE PARTICIPAÇÃO E APRESENTAÇÃO DAS PROPOSTAS\nLink para acesso às peças do concurso (URL): https://www.acingov.pt/acingovprod/2/zonaPublica/zona_publica_c/donwloadProcedurePiece/OTMyNTA2\n\n20 - OUTROS REQUISITOS\nInformação sobre contratos reservados. Aplica-se a contratos reservados (54º-A)? Não\n\n21 - CRITÉRIO DE ADJUDICAÇÃO\nMultifator: Não\nMonofator:\nNome: Preço\n\n24 - CONDIÇÕES DO CONTRATO\nFaturação Eletrónica: Permitido\nObrigação de Subcontratação:\nCódigo da Obrigação de Subcontratação: Não é aplicável nenhuma obrigação de subcontratação.\n\n25 - COMPRA PÚBLICA ESTRATÉGICA\nCompra Pública Estratégica: Inexistência de contratação pública estratégica\n\n26 - INFORMAÇÕES ADICIONAIS\nContrato adequado para PME: Sim\nCobertura ACP (Acordo dos Contratos Públicos da Organização Mundial do Comércio): Não\n\n27 - IDENTIFICAÇÃO E CONTACTOS DO ÓRGÃO DE RECURSOS ADMINISTRATIVOS\nDesignação: Conselho de Administração da Águas do Norte, S.A.\nEndereço: Rua Dom Pedro de Castro, N.º 1A\nCódigo postal: 5000-669\nLocalidade: Vila Real\nTelefone: 259309370\nFax: 259309371\nEndereço eletrónico: geral.adnorte@adp.pt\n\n28 - IDENTIFICAÇÃO DO(S) AUTOR(ES) DE ANÚNCIO\nNome: Alice Maria Carvalho Alves\nCargo: Técnica Superior de Compras e Logística\n\n29 - ALTERAÇÃO\nMotivo da Alteração: Correção pelo adquirente\nIdentificador da Versão do Anúncio a Alterar: 50ad01e3-ac4a-4050-9440-22e20be8a2c6-01\nIdentificador das Secções Alteradas do Anúncio Anterior: Condições de Apresentação\nDescrição das Alterações: Modificação do prazo para a apresentação de propostas\nAlteração dos Documentos do Concurso: Não\n419456471",
    "nipc": "513606084",
    "distrito": "Vila Real",
    "concelho": "Vila Real",
    "freguesia": "Freguesia de Vila Real",
    "site": "www.adnorte.pt",
    "email": "geral.adnorte@adp.pt",
    "designacao_contrato": "PRC_0233/2025_DEX - Fornecimento de Oxigénio (O2) para a ETAR de Penices",
    "descricao": "PRC_0233/2025_DEX - Fornecimento de Oxigénio (O2) para a ETAR de Penices",
    "preco_base": "274.000,00 EUR",
    "prazo_execucao": "2 ANOS",
    "prazo_apresentacao_propostas": "03-09-2025 17:00",
    "fundos_eu": "Não",
    "plataforma_eletronica": "ACIN",
    "url_procedimento": "https://www.acingov.pt",
    "autor_nome": "Alice Maria Carvalho Alves",
    "autor_cargo": "Técnica Superior de Compras e Logística"
  },
  {
    "numero_procedimento": "N/A",
    "entidade": "Serviços Sociais da Câmara Municipal de Lisboa",
    "link": "https://diariodarepublica.pt/dr/detalhe/contrato-publico/22622-933115838",
    "detalhes_completos": "Alteração do Anúncio de procedimento n.º 19375/2025, de 2025-07-21, com o ID 419324124\n\n1 - IDENTIFICAÇÃO E CONTACTOS DA ENTIDADE ADJUDICANTE\nDesignação da entidade adjudicante: Serviços Sociais da Câmara Municipal de Lisboa\nNIPC: 506812782\nServiço/Órgão/Pessoa de contacto: Serviço de Compras\nEndereço: Avenida Afonso Costa, 41\nCódigo postal: 1900-032\nLocalidade: Lisboa\nPaís: Portugal\nNUT III: PT170\nDistrito: Lisboa\nConcelho: Lisboa\nFreguesia: Todas\nTelefone: 218447700\nFax: 218447000\nEndereço da Entidade (URL): https://www.sscml.pt/wp/\nEndereço Eletrónico: geral@sscml.pt\neDelivery Gateway (URL): https://community.vortal.biz/public/\nFunção da Organização: Adquirente\nNorma jurídica da Entidade Adjudicante: Organização que adjudica um contrato subvencionado por uma autoridade local\nÁrea de atividade da Autoridade Adjudicante: Proteção social\n\n2 - JORNAL OFICIAL DA UNIÃO EUROPEIA\nO procedimento a que este anúncio diz respeito também é publicitado no Jornal Oficial da União Europeia? Sim\n\n3 - AVISO\nModelo de Anúncio: Concurso público\nData de Envio do Anúncio: 22-08-2025\n\n5 - PROCESSO\nTipo de Procedimento: Concurso público\nPreço base do procedimento: Sim\nValor do preço base do procedimento: 335.000,00 EUR\nProcedimento com lotes? Não\n\n6 - OBJETO DO CONTRATO\nNúmero de referência interna: 01_CPI_2025\nDesignação do contrato: AQUISIÇÃO DE SERVIÇOS DE CORRETAGEM DE SEGUROS\nDescrição: AQUISIÇÃO DE SERVIÇOS DE CORRETAGEM DE SEGUROS\nOpções: Não\nTipo de Contrato Principal: Aquisição de Serviços\nTipo de Contrato: Aquisição de Serviços\nClassificação CPV (Vocabulário Comum para os Contratos Públicos)\nObjeto principal\nVocabulário Principal: 66518000\nPreço base s/IVA: 335.000,00 EUR\n\n7 - INDICAÇÕES ADICIONAIS\nO contrato envolve aquisição conjunta (satisfação de várias entidades)? Não\nO contrato é adjudicado por uma central de compras? Não\n\n8 - TÉCNICAS\nO concurso destina-se à celebração de um acordo-quadro? Inexistência de acordo-quadro\nÉ utilizado um leilão eletrónico? Não\nÉ adotada uma fase de negociação? Não\nSistema de Aquisição Dinâmico: Inexistência de sistema de aquisição dinâmico\n\n9 - LOCAL DA EXECUÇÃO DO CONTRATO\nLOCAL DA EXECUÇÃO DO CONTRATO (PROCEDIMENTO)\nPaís: Portugal\nNUT III: PT170\nLocalidade: Lisboa\nDistrito: Lisboa\nConcelho: Lisboa\nFreguesia: Todas\n\n10 - PRAZO DE EXECUÇÃO DO CONTRATO\nPrazo de execução do contrato: 36 MESES\nPrevisão de renovações: Não\n\n11 - FUNDOS EU\nTêm fundos EU? Não\n\n12 - DOCUMENTOS DE HABILITAÇÃO\nHabilitação para o exercício da atividade profissional: Sim\nTipo: Certificado\nDescrição: Empresas prestadoras de serviços de corretagem de seguros, desde que legalmente constituídas e autorizadas a explorar os ramos de seguro objeto do presente concurso, nos termos da Lei n.º 7/2019, de 16 de Janeiro, na sua redação atualmente em vigor\n\n13 - CONDIÇÕES DE APRESENTAÇÃO\nPlataforma eletrónica utilizada pela entidade adjudicante: VORTAL\nURL para Apresentação: https://community.vortal.biz/public/\nAdmissibilidade da apresentação de propostas variantes: Não autorizado\nPrazo para apresentação das propostas: 07-09-2025 23:59\nPrazo durante o qual os concorrentes são obrigados a manter as respetivas propostas: 120 dias a contar do termo do prazo para a apresentação das propostas\nApresentação de Catálogo Eletrónico: Não autorizado\nIndicação de Subcontratação na Proposta: Inexistência de indicação de subcontratação\n\n14 - PRESTAÇÃO DE CAUÇÃO\nPrestação de caução: Não\n\n15 - FORNECIMENTO DAS PEÇAS DO CONCURSO, APRESENTAÇÃO DE PEDIDOS DE PARTICIPAÇÃO E APRESENTAÇÃO DAS PROPOSTAS\nLink para acesso às peças do concurso (URL): https://community.vortal.biz/Public/public-tender-documents/SE8rWXcraVVlVWZCVHNTYUFsUk9lTk9Pa1FjVXpic0pmRmxvQ3Z5QzhubEVuaUZ2aWtjUnNFSUFnZEo3T2JuNW5LdU9CWFVWcDA3ZUNETXlHR0JZK2c9PWFBMDck\n\n20 - OUTROS REQUISITOS\nInformação sobre contratos reservados. Aplica-se a contratos reservados (54º-A)? Não\n\n21 - CRITÉRIO DE ADJUDICAÇÃO\nMultifator: Não\nMonofator:\nNome: Outros\nOutro nome: Preço\n\n24 - CONDIÇÕES DO CONTRATO\nFaturação Eletrónica: Permitido\nObrigação de Subcontratação:\nCódigo da Obrigação de Subcontratação: Não é aplicável nenhuma obrigação de subcontratação.\n\n25 - COMPRA PÚBLICA ESTRATÉGICA\nCompra Pública Estratégica: Inexistência de contratação pública estratégica\n\n26 - INFORMAÇÕES ADICIONAIS\nContrato adequado para PME: Sim\nCobertura ACP (Acordo dos Contratos Públicos da Organização Mundial do Comércio): Não\n\n27 - IDENTIFICAÇÃO E CONTACTOS DO ÓRGÃO DE RECURSOS ADMINISTRATIVOS\nDesignação: Tribunal Administrativo de Círculo de Lisboa\nEndereço: Av. Afonso Costa, n.º 41\nCódigo postal: 1900-032\nLocalidade: Lisboa\nTelefone: +351 218367100\nFax: +351 211545188\nEndereço eletrónico: lisboa.tacl@tribunais.org.pt\n\n28 - IDENTIFICAÇÃO DO(S) AUTOR(ES) DE ANÚNCIO\nNome: Maria Martins\nCargo: Técnica do Serviço de Compras\n\n29 - ALTERAÇÃO\nMotivo da Alteração: Correção pelo adquirente\nIdentificador da Versão do Anúncio a Alterar: 4c3f5c68-9f85-4a54-a148-2e407c89c879-01\nIdentificador das Secções Alteradas do Anúncio Anterior: Alteração\nAlteração dos Documentos do Concurso: Sim\nData de alteração dos documentos do concurso: 21-08-2025\n419456609",
    "nipc": "506812782",
    "distrito": "Lisboa",
    "concelho": "Lisboa",
    "freguesia": "Todas",
    "site": "https://www.sscml.pt/wp/",
    "email": "geral@sscml.pt",
    "designacao_contrato": "AQUISIÇÃO DE SERVIÇOS DE CORRETAGEM DE SEGUROS",
    "descricao": "AQUISIÇÃO DE SERVIÇOS DE CORRETAGEM DE SEGUROS",
    "preco_base": "335.000,00 EUR",
    "prazo_execucao": "36 MESES",
    "prazo_apresentacao_propostas": "07-09-2025 23:59",
    "fundos_eu": "Não",
    "plataforma_eletronica": "VORTAL",
    "url_procedimento": "https://community.vortal.biz/public/",
    "autor_nome": "Maria Martins",
    "autor_cargo": "Técnica do Serviço de Compras"
  },
  {
    "numero_procedimento": "N/A",
    "entidade": "Faculdade de Engenharia da Universidade do Porto",
    "link": "https://diariodarepublica.pt/dr/detalhe/contrato-publico/22623-933115839",
    "detalhes_completos": "1 - IDENTIFICAÇÃO E CONTACTOS DA ENTIDADE ADJUDICANTE\nDesignação da entidade adjudicante: Faculdade de Engenharia da Universidade do Porto\nNIPC: 501413197\nServiço/Órgão/Pessoa de contacto: Unidade de Compras e Património\nEndereço: Rua Roberto Frias, s/n\nCódigo postal: 4200-465\nLocalidade: Porto\nPaís: Portugal\nNUT III: PT11A\nDistrito: Porto\nConcelho: Porto\nFreguesia: Freguesia de Paranhos - Porto\nTelefone: 220414515\nFax: 225 081 440\nEndereço da Entidade (URL): http://www.fe.up.pt/\nEndereço Eletrónico: compras@fe.up.pt\nFunção da Organização: Adquirente\nNorma jurídica da Entidade Adjudicante: Organismo de direito público\nÁrea de atividade da Autoridade Adjudicante: Educação\n\n2 - JORNAL OFICIAL DA UNIÃO EUROPEIA\nO procedimento a que este anúncio diz respeito também é publicitado no Jornal Oficial da União Europeia? Sim\n\n3 - AVISO\nModelo de Anúncio: Concurso público\nData de Envio do Anúncio: 22-08-2025\n\n5 - PROCESSO\nTipo de Procedimento: Concurso público\nPreço base do procedimento: Sim\nValor do preço base do procedimento: 530.000,00 EUR\nProcedimento com lotes? Não\n\n6 - OBJETO DO CONTRATO\nNúmero de referência interna: FEUP | CPI N.º 02/2025\nDesignação do contrato: Aquisição de um ASV - Autononous Surface Vehicle\nDescrição: FEUP | CPI N.º 02/2025 - Aquisição de um ASV - Autononous Surface Vehicle\nOpções: Não\nTipo de Contrato Principal: Aquisição de Bens Móveis\nTipo de Contrato: Aquisição de Bens Móveis\nClassificação CPV (Vocabulário Comum para os Contratos Públicos)\nObjeto principal\nVocabulário Principal: 38110000\nPreço base s/IVA: 530.000,00 EUR\n\n7 - INDICAÇÕES ADICIONAIS\nO contrato envolve aquisição conjunta (satisfação de várias entidades)? Não\nO contrato é adjudicado por uma central de compras? Não\n\n8 - TÉCNICAS\nO concurso destina-se à celebração de um acordo-quadro? Inexistência de acordo-quadro\nÉ utilizado um leilão eletrónico? Não\nÉ adotada uma fase de negociação? Não\nSistema de Aquisição Dinâmico: Inexistência de sistema de aquisição dinâmico\n\n9 - LOCAL DA EXECUÇÃO DO CONTRATO\nLOCAL DA EXECUÇÃO DO CONTRATO (PROCEDIMENTO)\nPaís: Portugal\nNUT III: PT11A\nLocalidade: Porto\nDistrito: Porto\nConcelho: Porto\nFreguesia: Freguesia de Paranhos - Porto\n\n10 - PRAZO DE EXECUÇÃO DO CONTRATO\nPrazo de execução do contrato: 6 MESES\nPrevisão de renovações: Não\n\n11 - FUNDOS EU\nTêm fundos EU? Sim\n\n12 - DOCUMENTOS DE HABILITAÇÃO\nHabilitação para o exercício da atividade profissional: Não\n\n13 - CONDIÇÕES DE APRESENTAÇÃO\nPlataforma eletrónica utilizada pela entidade adjudicante: ANOGOV\nURL para Apresentação: https://www.anogov.com/up-feup/faces/\nAdmissibilidade da apresentação de propostas variantes: Não autorizado\nPrazo para apresentação das propostas: 24-09-2025 23:59\nPrazo durante o qual os concorrentes são obrigados a manter as respetivas propostas: 66 dias a contar do termo do prazo para a apresentação das propostas\nApresentação de Catálogo Eletrónico: Permitido\nIndicação de Subcontratação na Proposta: Inexistência de indicação de subcontratação\n\n14 - PRESTAÇÃO DE CAUÇÃO\nPrestação de caução: Sim\nPercentagem: 0.5%\nDescrição da Garantia Exigida: Depósito em dinheiro, garantia bancária ou seguro-caução\n\n15 - FORNECIMENTO DAS PEÇAS DO CONCURSO, APRESENTAÇÃO DE PEDIDOS DE PARTICIPAÇÃO E APRESENTAÇÃO DAS PROPOSTAS\nLink para acesso às peças do concurso (URL): https://www.anogov.com/up-feup/faces/app/acessoDocs.jsp?codigoAcesso=hxqrcWcvpu6iwbVgCumhF2Hv2JzvO06Gyzbobkhgn9NVu0ISf5\n\n20 - OUTROS REQUISITOS\nInformação sobre contratos reservados. Aplica-se a contratos reservados (54º-A)? Não\n\n21 - CRITÉRIO DE ADJUDICAÇÃO\nMultifator: Não\nMonofator:\nNome: Preço\n\n24 - CONDIÇÕES DO CONTRATO\nFaturação Eletrónica: Permitido\nObrigação de Subcontratação:\nCódigo da Obrigação de Subcontratação: Não é aplicável nenhuma obrigação de subcontratação.\n\n25 - COMPRA PÚBLICA ESTRATÉGICA\nCompra Pública Estratégica: Inexistência de contratação pública estratégica\n\n26 - INFORMAÇÕES ADICIONAIS\nContrato adequado para PME: Sim\nCobertura ACP (Acordo dos Contratos Públicos da Organização Mundial do Comércio): Não\n\n27 - IDENTIFICAÇÃO E CONTACTOS DO ÓRGÃO DE RECURSOS ADMINISTRATIVOS\nDesignação: O Diretor da Faculdade de Engenharia da Universidade do Porto\nEndereço: Rua Dr. Roberto Frias, s/n\nCódigo postal: 4200-465\nLocalidade: Porto\nEndereço eletrónico: feup@fe.up.pt\n\n28 - IDENTIFICAÇÃO DO(S) AUTOR(ES) DE ANÚNCIO\nNome: Daniela Machado\nCargo: Técnico Superior\n419458553",
    "nipc": "501413197",
    "distrito": "Porto",
    "concelho": "Porto",
    "freguesia": "Freguesia de Paranhos - Porto",
    "site": "http://www.fe.up.pt/",
    "email": "compras@fe.up.pt",
    "designacao_contrato": "Aquisição de um ASV - Autononous Surface Vehicle",
    "descricao": "FEUP | CPI N.º 02/2025 - Aquisição de um ASV - Autononous Surface Vehicle",
    "preco_base": "530.000,00 EUR",
    "prazo_execucao": "6 MESES",
    "prazo_apresentacao_propostas": "24-09-2025 23:59",
    "fundos_eu": "Sim",
    "plataforma_eletronica": "ANOGOV",
    "url_procedimento": "https://www.anogov.com/up-feup/faces/",
    "autor_nome": "Daniela Machado",
    "autor_cargo": "Técnico Superior"
  },
  {
    "numero_procedimento": "N/A",
    "entidade": "Águas do Tejo Atlântico, SA",
    "link": "https://diariodarepublica.pt/dr/detalhe/contrato-publico/22624-933115840",
    "detalhes_completos": "Alteração do Anúncio de procedimento n.º 18611/2025, de 2025-07-14, com o ID 419293612\n\n1 - IDENTIFICAÇÃO E CONTACTOS DA ENTIDADE ADJUDICANTE\nDesignação da entidade adjudicante: Águas do Tejo Atlântico, SA\nNIPC: 514387130\nServiço/Órgão/Pessoa de contacto: Direção de Gestão de Ativos\nEndereço: ETAR de Alcântara, Av. De Ceuta\nCódigo postal: 1300-254\nLocalidade: LISBOA\nPaís: Portugal\nNUT III: PT170\nDistrito: Lisboa\nConcelho: Lisboa\nFreguesia: Freguesia de Campo de Ourique\nTelefone: 351213107900\nFax: 351213107901\nEndereço da Entidade (URL): https://www.aguasdotejoatlantico.adp.pt/\nEndereço Eletrónico: geral.adta@adp.pt\neDelivery Gateway (URL): https://www.acingov.pt\nFunção da Organização: Adquirente\nSubfunção da Organização: Organização cujo orçamento é utilizado para pagar o contrato; Organização que executa o pagamento; Organização que fornece informações adicionais sobre o processo de adjudicação; Organização que fornece mais informações sobre os prazos dos procedimentos de recurso; Organização que fornece acesso fora de linha aos documentos do concurso; Organização responsável pelo tratamento das propostas; Organização que recebe as propostas; Organização que trata os pedidos de participação; Organização que recebe pedidos de participação; Organização que fornece mais informações sobre os procedimentos de recurso; Organização que assina o contrato\nNorma jurídica da Entidade Adjudicante: Organismo de direito público\nÁrea de atividade da Autoridade Adjudicante: Serviços públicos das administrações públicas\n\n2 - JORNAL OFICIAL DA UNIÃO EUROPEIA\nO procedimento a que este anúncio diz respeito também é publicitado no Jornal Oficial da União Europeia? Sim\n\n3 - AVISO\nModelo de Anúncio: Concurso limitado por prévia qualificação\nData de Envio do Anúncio: 22-08-2025\n\n5 - PROCESSO\nTipo de Procedimento: Concurso limitado por prévia qualificação\nPreço base do procedimento: Sim\nValor do preço base do procedimento: 600.000,00 EUR\nProcedimento com lotes? Não\n\n6 - OBJETO DO CONTRATO\nNúmero de referência interna: TA_25_109_PQ_S_001_DGA\nDesignação do contrato: Aquisição de Serviços para a Elaboração de Estudo e Plano de Ação para a implementação da DARU 2024/3019 nas FA de Alcântara, Guia, Frielas, Beirolas e Chelas\nDescrição: Aquisição de Serviços para a Elaboração de Estudo e Plano de Ação para a implementação da DARU 2024/3019 nas FA de Alcântara, Guia, Frielas, Beirolas e Chelas\nOpções: Não\nTipo de Contrato Principal: Aquisição de Serviços\nTipo de Contrato: Aquisição de Serviços\nClassificação CPV (Vocabulário Comum para os Contratos Públicos)\nObjeto principal\nVocabulário Principal: 71300000\nPreço base s/IVA: 600.000,00 EUR\n\n7 - INDICAÇÕES ADICIONAIS\nO contrato envolve aquisição conjunta (satisfação de várias entidades)? Não\nO contrato é adjudicado por uma central de compras? Não\n\n8 - TÉCNICAS\nO concurso destina-se à celebração de um acordo-quadro? Inexistência de acordo-quadro\nÉ utilizado um leilão eletrónico? Não\nSistema de Aquisição Dinâmico: Inexistência de sistema de aquisição dinâmico\n\n9 - LOCAL DA EXECUÇÃO DO CONTRATO\nLOCAL DA EXECUÇÃO DO CONTRATO (PROCEDIMENTO)\nPaís: Portugal\nNUT III: PT170\nLocalidade: Freguesia de Campo de Ourique\nDistrito: Lisboa\nConcelho: Lisboa\nFreguesia: Freguesia de Campo de Ourique\nPaís: Portugal\nNUT III: PT170\nLocalidade: União das Freguesias de Cascais e Estoril\nDistrito: Lisboa\nConcelho: Cascais\nFreguesia: União das Freguesias de Cascais e Estoril\nPaís: Portugal\nNUT III: PT170\nLocalidade: Freguesia de Alcabideche\nDistrito: Lisboa\nConcelho: Cascais\nFreguesia: Freguesia de Alcabideche\nPaís: Portugal\nNUT III: PT170\nLocalidade: União das Freguesias de Santo António dos Cavaleiros e Frielas\nDistrito: Lisboa\nConcelho: Loures\nFreguesia: União das Freguesias de Santo António dos Cavaleiros e Frielas\nPaís: Portugal\nNUT III: PT170\nLocalidade: Freguesia de Parque das Nações\nDistrito: Lisboa\nConcelho: Lisboa\nFreguesia: Freguesia de Parque das Nações\nPaís: Portugal\nNUT III: PT170\nLocalidade: Freguesia de Marvila - Lisboa\nDistrito: Lisboa\nConcelho: Lisboa\nFreguesia: Freguesia de Marvila - Lisboa\n\n10 - PRAZO DE EXECUÇÃO DO CONTRATO\nPrazo de execução do contrato: 450 DIAS\nPrevisão de renovações: Não\n\n11 - FUNDOS EU\nTêm fundos EU? Não\n\n12 - DOCUMENTOS DE HABILITAÇÃO\nHabilitação para o exercício da atividade profissional: Não\n\n13 - CONDIÇÕES DE APRESENTAÇÃO\nPlataforma eletrónica utilizada pela entidade adjudicante: ACIN\nURL para Apresentação: https://www.acingov.pt\nAdmissibilidade da apresentação de propostas variantes: Não autorizado\nPrazo para apresentação das candidaturas: 06-10-2025 23:59\nPrazo para a decisão de qualificação: 44 dias a contar do termo do prazo para a apresentação das candidaturas\nRequisitos mínimos \nRequisitos mínimos de capacidade técnica: Os definidos nas peças do concurso\nRequisitos mínimos de capacidade financeira: Os definidos nas peças do concurso\nPrazo durante o qual os concorrentes são obrigados a manter as respetivas propostas: 66 dias a contar do termo do prazo para a apresentação das propostas\nApresentação de Catálogo Eletrónico: Não autorizado\nIndicação de Subcontratação na Proposta: Inexistência de indicação de subcontratação\n\n14 - PRESTAÇÃO DE CAUÇÃO\nPrestação de caução: Sim\nPercentagem: 5%\nDescrição da Garantia Exigida: O valor da caução é de 5.00% do preço contratual.\n\n15 - FORNECIMENTO DAS PEÇAS DO CONCURSO, APRESENTAÇÃO DE PEDIDOS DE PARTICIPAÇÃO E APRESENTAÇÃO DAS PROPOSTAS\nLink para acesso às peças do concurso (URL): https://www.acingov.pt/acingovprod/2/zonaPublica/zona_publica_c/donwloadProcedurePiece/NzYyOTYz\n\n20 - OUTROS REQUISITOS\nInformação sobre contratos reservados. Aplica-se a contratos reservados (54º-A)? Não\n\n21 - CRITÉRIO DE ADJUDICAÇÃO\nMultifator: Sim\nFator: \nNome: Preço\nPonderação: 40%\nSubfatores: Não\nFator: \nNome: Outros\nOutro Nome: Qualidade técnica da proposta\nPonderação: 60%\nSubfatores: Sim\nSubfatores: \nNome: Memória descritiva e justificativa\nPonderação : 33.3%; \nNome: Programa de Trabalhos\nPonderação : 8.3%; \nNome: Equipa Técnica\nPonderação : 58.4%; \n\n24 - CONDIÇÕES DO CONTRATO\nFaturação Eletrónica: Necessário\nObrigação de Subcontratação:\nCódigo da Obrigação de Subcontratação: Não é aplicável nenhuma obrigação de subcontratação.\n\n25 - COMPRA PÚBLICA ESTRATÉGICA\nCompra Pública Estratégica: Inexistência de contratação pública estratégica\n\n26 - INFORMAÇÕES ADICIONAIS\nContrato adequado para PME: Sim\nCobertura ACP (Acordo dos Contratos Públicos da Organização Mundial do Comércio): Não\n\n27 - IDENTIFICAÇÃO E CONTACTOS DO ÓRGÃO DE RECURSOS ADMINISTRATIVOS\nDesignação: Águas do Tejo Atlântico\nEndereço: Avenida de Ceuta\nCódigo postal: 1300-254\nLocalidade: Lisboa\nTelefone: 213107900\nFax: \nEndereço eletrónico: compras_contratacao.adta@adp.pt\n\n28 - IDENTIFICAÇÃO DO(S) AUTOR(ES) DE ANÚNCIO\nNome: Nuno Brôco\nCargo: Águas do Tejo Atlântico, S.A\n\n29 - ALTERAÇÃO\nMotivo da Alteração: Informações atualizadas\nIdentificador da Versão do Anúncio a Alterar: d60a2ad2-b7fa-41d9-bed4-97ce3a685b40-01\nIdentificador das Secções Alteradas do Anúncio Anterior: Condições de Apresentação\nDescrição das Alterações: Modificação do prazo para a apresentação de candidaturas\nAlteração dos Documentos do Concurso: Sim\nData de alteração dos documentos do concurso: 21-08-2025\n419459874",
    "nipc": "514387130",
    "distrito": "Lisboa",
    "concelho": "Lisboa",
    "freguesia": "Freguesia de Campo de Ourique",
    "site": "https://www.aguasdotejoatlantico.adp.pt/",
    "email": "geral.adta@adp.pt",
    "designacao_contrato": "Aquisição de Serviços para a Elaboração de Estudo e Plano de Ação para a implementação da DARU 2024/3019 nas FA de Alcântara, Guia, Frielas, Beirolas e Chelas",
    "descricao": "Aquisição de Serviços para a Elaboração de Estudo e Plano de Ação para a implementação da DARU 2024/3019 nas FA de Alcântara, Guia, Frielas, Beirolas e Chelas",
    "preco_base": "600.000,00 EUR",
    "prazo_execucao": "450 DIAS",
    "prazo_apresentacao_propostas": null,
    "fundos_eu": "Não",
    "plataforma_eletronica": "ACIN",
    "url_procedimento": "https://www.acingov.pt",
    "autor_nome": "Nuno Brôco",
    "autor_cargo": "Águas do Tejo Atlântico, S.A"
  },
  {
    "numero_procedimento": "N/A",
    "entidade": "Estrutura de Missão para a Gestão do Plano Estratégico da Política Agrícola Comum no Continente",
    "link": "https://diariodarepublica.pt/dr/detalhe/contrato-publico/22625-933115841",
    "detalhes_completos": "Alteração do Anúncio de procedimento n.º 22418/2025, de 2025-08-21, com o ID 419445293\n\n1 - IDENTIFICAÇÃO E CONTACTOS DA ENTIDADE ADJUDICANTE\nDesignação da entidade adjudicante: Estrutura de Missão para a Gestão do Plano Estratégico da Política Agrícola Comum no Continente\nNIPC: 600087891\nServiço/Órgão/Pessoa de contacto: Claudia Ribeiro\nEndereço: Rua S. Julião, nº 63\nCódigo postal: 1149-030\nLocalidade: Lisboa\nPaís: Portugal\nNUT III: PT170\nDistrito: Lisboa\nConcelho: Lisboa\nFreguesia: Freguesia de Santa Maria Maior - Lisboa\nTelefone: 213819383\nFax: 213819383\nEndereço da Entidade (URL): https://pepacc.pt/\nEndereço Eletrónico: sec.ag@pepacc.pt\nFunção da Organização: Adquirente\nNorma jurídica da Entidade Adjudicante: Autoridade da administração central\nÁrea de atividade da Autoridade Adjudicante: Assuntos económicos\n\n2 - JORNAL OFICIAL DA UNIÃO EUROPEIA\nO procedimento a que este anúncio diz respeito também é publicitado no Jornal Oficial da União Europeia? Sim\n\n3 - AVISO\nModelo de Anúncio: Concurso público\nData de Envio do Anúncio: 22-08-2025\n\n5 - PROCESSO\nTipo de Procedimento: Concurso público\nPreço base do procedimento: Sim\nValor do preço base do procedimento: 3.660.000,00 EUR\nProcedimento com lotes? Não\n\n6 - OBJETO DO CONTRATO\nNúmero de referência interna: 05/CPI/2025\nDesignação do contrato: Aquisição de serviços de desenvolvimento e manutenção de sistemas de informação\nDescrição: Aquisição de serviços de desenvolvimento e manutenção de sistemas de informação\nOpções: Não\nTipo de Contrato Principal: Aquisição de Serviços\nTipo de Contrato: Aquisição de Serviços\nClassificação CPV (Vocabulário Comum para os Contratos Públicos)\nObjeto principal\nVocabulário Principal: 79000000\nPreço base s/IVA: 3.660.000,00 EUR\n\n7 - INDICAÇÕES ADICIONAIS\nO contrato envolve aquisição conjunta (satisfação de várias entidades)? Não\nO contrato é adjudicado por uma central de compras? Não\n\n8 - TÉCNICAS\nO concurso destina-se à celebração de um acordo-quadro? Inexistência de acordo-quadro\nÉ utilizado um leilão eletrónico? Não\nÉ adotada uma fase de negociação? Não\nSistema de Aquisição Dinâmico: Inexistência de sistema de aquisição dinâmico\n\n9 - LOCAL DA EXECUÇÃO DO CONTRATO\nLOCAL DA EXECUÇÃO DO CONTRATO (PROCEDIMENTO)\nPaís: Portugal\nNUT III: PT170\nLocalidade: Lisboa\nDistrito: Lisboa\nConcelho: Lisboa\nFreguesia: Freguesia de Santa Maria Maior - Lisboa\n\n10 - PRAZO DE EXECUÇÃO DO CONTRATO\nPrazo de execução do contrato: 30 MESES\nPrevisão de renovações: Não\n\n11 - FUNDOS EU\nTêm fundos EU? Sim\n\n12 - DOCUMENTOS DE HABILITAÇÃO\nHabilitação para o exercício da atividade profissional: Não\n\n13 - CONDIÇÕES DE APRESENTAÇÃO\nPlataforma eletrónica utilizada pela entidade adjudicante: ANOGOV\nURL para Apresentação: https://www.anogov.com/op-agpdr2020/faces/\nAdmissibilidade da apresentação de propostas variantes: Não autorizado\nPrazo para apresentação das propostas: 20-09-2025 23:59\nPrazo durante o qual os concorrentes são obrigados a manter as respetivas propostas: 120 dias a contar do termo do prazo para a apresentação das propostas\nApresentação de Catálogo Eletrónico: Necessário\nIndicação de Subcontratação na Proposta: Inexistência de indicação de subcontratação\n\n14 - PRESTAÇÃO DE CAUÇÃO\nPrestação de caução: Sim\nPercentagem: 5%\nDescrição da Garantia Exigida: Depósito em dinheiro ou títulos, garantia bancária, seguro caução\n\n15 - FORNECIMENTO DAS PEÇAS DO CONCURSO, APRESENTAÇÃO DE PEDIDOS DE PARTICIPAÇÃO E APRESENTAÇÃO DAS PROPOSTAS\nLink para acesso às peças do concurso (URL): https://www.anogov.com/op-agpdr2020/faces/app/acessoDocs.jsp?codigoAcesso=ju7ZtVC2LCOEWIOm5uMQmiMIKkx5wI7PvE6Ql3KxT7aV9x9UUh\n\n20 - OUTROS REQUISITOS\nInformação sobre contratos reservados. Aplica-se a contratos reservados (54º-A)? Não\n\n21 - CRITÉRIO DE ADJUDICAÇÃO\nMultifator: Sim\nFator: \nNome: Preço\nPonderação: 50%\nSubfatores: Não\nFator: \nNome: Qualidade\nPonderação: 50%\nSubfatores: Não\n\n24 - CONDIÇÕES DO CONTRATO\nFaturação Eletrónica: Permitido\nObrigação de Subcontratação:\nCódigo da Obrigação de Subcontratação: Não é aplicável nenhuma obrigação de subcontratação.\n\n25 - COMPRA PÚBLICA ESTRATÉGICA\nCompra Pública Estratégica: Inexistência de contratação pública estratégica\n\n26 - INFORMAÇÕES ADICIONAIS\nContrato adequado para PME: Sim\nCobertura ACP (Acordo dos Contratos Públicos da Organização Mundial do Comércio): Não\n\n27 - IDENTIFICAÇÃO E CONTACTOS DO ÓRGÃO DE RECURSOS ADMINISTRATIVOS\nDesignação: Estrutura de Missão para a Gestão do Plano Estratégico da Politica Agrícola Comum no Continente\nEndereço: Rua São Julião, 63\nCódigo postal: 1149-030\nLocalidade: Lisboa\nEndereço eletrónico: sec.ag@pepacc.pt\n\n28 - IDENTIFICAÇÃO DO(S) AUTOR(ES) DE ANÚNCIO\nNome: Anabela Reis\nCargo: Vogal da Comissão Diretiva\n\n29 - ALTERAÇÃO\nMotivo da Alteração: Informações atualizadas\nIdentificador da Versão do Anúncio a Alterar: b3c1e05a-4675-4ec9-b757-07431f693977-01\nIdentificador das Secções Alteradas do Anúncio Anterior: Condições de Apresentação\nDescrição das Alterações: Os anuncios, em DR e JOUE, forma publicados com uma incorreção quanto à data limite para apresentação das propostas. A data limite para o efeito, conforme consta da plataforma de contratação, é dia 20/09/2025.\nAlteração dos Documentos do Concurso: Não\n419458131",
    "nipc": "600087891",
    "distrito": "Lisboa",
    "concelho": "Lisboa",
    "freguesia": "Freguesia de Santa Maria Maior - Lisboa",
    "site": "https://pepacc.pt/",
    "email": "sec.ag@pepacc.pt",
    "designacao_contrato": "Aquisição de serviços de desenvolvimento e manutenção de sistemas de informação",
    "descricao": "Aquisição de serviços de desenvolvimento e manutenção de sistemas de informação",
    "preco_base": "3.660.000,00 EUR",
    "prazo_execucao": "30 MESES",
    "prazo_apresentacao_propostas": "20-09-2025 23:59",
    "fundos_eu": "Sim",
    "plataforma_eletronica": "ANOGOV",
    "url_procedimento": "https://www.anogov.com/op-agpdr2020/faces/",
    "autor_nome": "Anabela Reis",
    "autor_cargo": "Vogal da Comissão Diretiva"
  },
  {
    "numero_procedimento": "N/A",
    "entidade": "SPMS- Serviços Partilhados do M. da Saúde, E.P.E.",
    "link": "https://diariodarepublica.pt/dr/detalhe/contrato-publico/22629-933115842",
    "detalhes_completos": "1 - IDENTIFICAÇÃO E CONTACTOS DA ENTIDADE ADJUDICANTE\nDesignação da entidade adjudicante: SPMS- Serviços Partilhados do M. da Saúde, E.P.E.\nNIPC: 509540716\nEndereço: Avenida da República 61\nCódigo postal: 1050-189\nLocalidade: Lisboa\nPaís: Portugal\nNUT III: PT170\nDistrito: Lisboa\nConcelho: Lisboa\nFreguesia: Todas\nTelefone: 211545600\nFax: 211545649\nEndereço da Entidade (URL): www.spms.min-saude.pt/\nEndereço Eletrónico: contratacao@spms.min-saude.pt\neDelivery Gateway (URL): https://community.vortal.biz/public/\nFunção da Organização: Adquirente\nNorma jurídica da Entidade Adjudicante: Empresa pública\nÁrea de atividade da Autoridade Adjudicante: Saúde\n\n2 - JORNAL OFICIAL DA UNIÃO EUROPEIA\nO procedimento a que este anúncio diz respeito também é publicitado no Jornal Oficial da União Europeia? Sim\n\n3 - AVISO\nModelo de Anúncio: Concurso público\nData de Envio do Anúncio: 22-08-2025\n\n5 - PROCESSO\nTipo de Procedimento: Concurso público\nPreço base do procedimento: Sim\nValor do preço base do procedimento: 32.262.000,00 EUR\nProcedimento com lotes? Sim\nNº Máx. de Lotes Autorizado: 3\nNúmero máximo de lotes que podem ser adjudicados a um concorrente: 3\n\n6 - OBJETO DO CONTRATO\nNúmero de referência interna: 1681/2025.\nDesignação do contrato: 1681/2025 - Concurso público internacional para aquisição de equipamentos médicos diversos \nDescrição: 1681/2025 - Concurso público internacional para aquisição de equipamentos médicos diversos \nOpções: Não\nTipo de Contrato Principal: Aquisição de Bens Móveis\nTipo de Contrato: Aquisição de Bens Móveis\nClassificação CPV (Vocabulário Comum para os Contratos Públicos)\nObjeto principal\nVocabulário Principal: 33600000\nPreço base s/IVA: 32.262.000,00 EUR\nLotes: \nNº: LOT-0001\nDescrição do Lote: Lote 1\nPreço base s/IVA: 12.000,00 EUR\nClassificação CPV (Vocabulário Comum para os Contratos Públicos)\nObjeto principal\nVocabulário Principal: 33600000\nNº: LOT-0002\nDescrição do Lote: Lote 2\nPreço base s/IVA: 14.250.000,00 EUR\nClassificação CPV (Vocabulário Comum para os Contratos Públicos)\nObjeto principal\nVocabulário Principal: 33600000\nNº: LOT-0003\nDescrição do Lote: Lote 3\nPreço base s/IVA: 18.000.000,00 EUR\nClassificação CPV (Vocabulário Comum para os Contratos Públicos)\nObjeto principal\nVocabulário Principal: 33600000\n\n7 - INDICAÇÕES ADICIONAIS\nO contrato envolve aquisição conjunta (satisfação de várias entidades)? Sim\nA entidade adjudicante atua como compradora no procedimento? Não\nNIPC: 501356126\nDesignação da entidade adjudicante: INEM -Instituto Nacional de Emergência Médica\nUnidades Orgânicas: Gestão de Compras\nValor: 32262000\nO contrato é adjudicado por uma central de compras? Sim\n\n8 - TÉCNICAS\nO concurso destina-se à celebração de um acordo-quadro? Inexistência de acordo-quadro\nÉ utilizado um leilão eletrónico? Não\nÉ adotada uma fase de negociação? Não\nSistema de Aquisição Dinâmico: Inexistência de sistema de aquisição dinâmico\n\n9 - LOCAL DA EXECUÇÃO DO CONTRATO\nLOCAL DA EXECUÇÃO DO CONTRATO (PROCEDIMENTO)\nPaís: Portugal\nNUT III: PT170\nLocalidade: Lisboa\nDistrito: Lisboa\nConcelho: Lisboa\nFreguesia: Freguesia de Avenidas Novas\nLOCAL DA EXECUÇÃO DO CONTRATO (LOTE)\nIdentificador do Lote: LOT-0001; LOT-0002; LOT-0003\nPaís: Portugal\nNUT III: PT170\nLocalidade: Lisboa\nDistrito: Lisboa\nConcelho: Lisboa\nFreguesia: Freguesia de Avenidas Novas\n\n10 - PRAZO DE EXECUÇÃO DO CONTRATO\nIdentificador do Lote: LOT-0001; LOT-0002; LOT-0003\nPrazo de execução do contrato: 16 MESES\nPrevisão de renovações: Não\n\n11 - FUNDOS EU\nIdentificador do Lote: LOT-0001; LOT-0002; LOT-0003\nTêm fundos EU? Não\n\n12 - DOCUMENTOS DE HABILITAÇÃO\nHabilitação para o exercício da atividade profissional: Não\n\n13 - CONDIÇÕES DE APRESENTAÇÃO\nPlataforma eletrónica utilizada pela entidade adjudicante: VORTAL\nURL para Apresentação: https://community.vortal.biz/public/\nAdmissibilidade da apresentação de propostas variantes: Não autorizado\nPrazo para apresentação das propostas: 25-09-2025 18:00\nPrazo durante o qual os concorrentes são obrigados a manter as respetivas propostas: 180 dias a contar do termo do prazo para a apresentação das propostas\nApresentação de Catálogo Eletrónico: Permitido\nIndicação de Subcontratação na Proposta: Inexistência de indicação de subcontratação\n\n14 - PRESTAÇÃO DE CAUÇÃO\nPrestação de caução: Sim\nPercentagem: 5%\nDescrição da Garantia Exigida: depósito em dinheiro ou em títulos emitidos ou garantidos pelo Estado, ou mediante garantia bancária ou seguro-caução\n\n15 - FORNECIMENTO DAS PEÇAS DO CONCURSO, APRESENTAÇÃO DE PEDIDOS DE PARTICIPAÇÃO E APRESENTAÇÃO DAS PROPOSTAS\nLink para acesso às peças do concurso (URL): https://community.vortal.biz/Public/public-tender-documents/SFZKRUtldXd4WlkxcXBITHB4cFY0RUVOWTlrVlIrSjViZlUzMHZsUUZtaGZqMzZZSzRDS2RlcEQzdWVpK2JnNkRDQ2Z3bHZDZXc3SE9nWjBoZDAxTFE9PVApZ2g4\n\n20 - OUTROS REQUISITOS\nIdentificador do Lote: LOT-0001; LOT-0002; LOT-0003\nInformação sobre contratos reservados. Aplica-se a contratos reservados (54º-A)? Não\n\n21 - CRITÉRIO DE ADJUDICAÇÃO\nO Critério de adjudicação é diferenciado por lote? Não\nMultifator: Não\nMonofator:\nNome: Preço\n\n24 - CONDIÇÕES DO CONTRATO\nIdentificador do Lote: LOT-0001; LOT-0002; LOT-0003\nFaturação Eletrónica: Permitido\nObrigação de Subcontratação:\nCódigo da Obrigação de Subcontratação: Não é aplicável nenhuma obrigação de subcontratação.\n\n25 - COMPRA PÚBLICA ESTRATÉGICA\nCompra Pública Estratégica: Inexistência de contratação pública estratégica\n\n26 - INFORMAÇÕES ADICIONAIS\nIdentificador do Lote: LOT-0001; LOT-0002; LOT-0003\nContrato adequado para PME: Sim\nCobertura ACP (Acordo dos Contratos Públicos da Organização Mundial do Comércio): Não\n\n27 - IDENTIFICAÇÃO E CONTACTOS DO ÓRGÃO DE RECURSOS ADMINISTRATIVOS\nDesignação: SPMS- Serviços Partilhados do M. da Saúde, E.P.E.\nEndereço: Avenida da República, 61\nCódigo postal: 1050-189\nLocalidade: Lisboa\nTelefone: +351 211545600\nFax: +351 211545649\nEndereço eletrónico: catalogo@spms.min-saude.pt\n\n28 - IDENTIFICAÇÃO DO(S) AUTOR(ES) DE ANÚNCIO\nNome: Andreia Jerónimo\nCargo: Técnica Superior\n419460156",
    "nipc": "509540716",
    "distrito": "Lisboa",
    "concelho": "Lisboa",
    "freguesia": "Todas",
    "site": "www.spms.min-saude.pt/",
    "email": "contratacao@spms.min-saude.pt",
    "designacao_contrato": "1681/2025 - Concurso público internacional para aquisição de equipamentos médicos diversos",
    "descricao": "1681/2025 - Concurso público internacional para aquisição de equipamentos médicos diversos",
    "preco_base": "32.262.000,00 EUR",
    "prazo_execucao": "16 MESES",
    "prazo_apresentacao_propostas": "25-09-2025 18:00",
    "fundos_eu": "Não",
    "plataforma_eletronica": "VORTAL",
    "url_procedimento": "https://community.vortal.biz/public/",
    "autor_nome": "Andreia Jerónimo",
    "autor_cargo": "Técnica Superior"
  },
  {
    "numero_procedimento": "N/A",
    "entidade": "Comissão de Coordenação e Desenvolvimento Regional do Centro, I.P.",
    "link": "https://diariodarepublica.pt/dr/detalhe/contrato-publico/22631-933115843",
    "detalhes_completos": "Alteração do Anúncio de procedimento n.º 20069/2025, de 2025-07-25, com o ID 419347729\n\n1 - IDENTIFICAÇÃO E CONTACTOS DA ENTIDADE ADJUDICANTE\nDesignação da entidade adjudicante: Comissão de Coordenação e Desenvolvimento Regional do Centro, I.P.\nNIPC: 517638754\nEndereço: Rua Bernardim Ribeiro, 80\nCódigo postal: 3000-069\nLocalidade: Coimbra\nPaís: Portugal\nNUT III: PT16E\nDistrito: Coimbra\nConcelho: Coimbra\nFreguesia: Todas\nTelefone: 239400100\nEndereço da Entidade (URL): https://www.ccdrc.pt/pt/\nEndereço Eletrónico: geral@ccdrc.pt\neDelivery Gateway (URL): https://community.vortal.biz/public/\nFunção da Organização: Adquirente\nNorma jurídica da Entidade Adjudicante: Organismo de direito público\nÁrea de atividade da Autoridade Adjudicante: Serviços públicos das administrações públicas\n\n2 - JORNAL OFICIAL DA UNIÃO EUROPEIA\nO procedimento a que este anúncio diz respeito também é publicitado no Jornal Oficial da União Europeia? Sim\n\n3 - AVISO\nModelo de Anúncio: Concurso público\nData de Envio do Anúncio: 22-08-2025\n\n5 - PROCESSO\nTipo de Procedimento: Concurso público\nPreço base do procedimento: Sim\nValor do preço base do procedimento: 436.128,00 EUR\nProcedimento com lotes? Não\n\n6 - OBJETO DO CONTRATO\nNúmero de referência interna: PRO_2025_179721\nDesignação do contrato: Aquisição de serviços e equipamentos para a comunicação unificada de voz e dados, fixos e móveis\nDescrição: Serviços e equipamentos para a comunicação unificada de voz e dados, fixos e móveis\nOpções: Não\nTipo de Contrato Principal: Aquisição de Serviços\nTipo de Contrato: Aquisição de Serviços\nClassificação CPV (Vocabulário Comum para os Contratos Públicos)\nObjeto principal\nVocabulário Principal: 64227000\nPreço base s/IVA: 436.128,00 EUR\n\n7 - INDICAÇÕES ADICIONAIS\nO contrato envolve aquisição conjunta (satisfação de várias entidades)? Não\nO contrato é adjudicado por uma central de compras? Não\n\n8 - TÉCNICAS\nO concurso destina-se à celebração de um acordo-quadro? Inexistência de acordo-quadro\nÉ utilizado um leilão eletrónico? Não\nÉ adotada uma fase de negociação? Não\nSistema de Aquisição Dinâmico: Inexistência de sistema de aquisição dinâmico\n\n9 - LOCAL DA EXECUÇÃO DO CONTRATO\nLOCAL DA EXECUÇÃO DO CONTRATO (PROCEDIMENTO)\nPaís: Portugal\nNUT III: PT16E\nLocalidade: Coimbra\nDistrito: Coimbra\nConcelho: Coimbra\nFreguesia: Todas\n\n10 - PRAZO DE EXECUÇÃO DO CONTRATO\nPrazo de execução do contrato: 48 MESES\nPrevisão de renovações: Não\n\n11 - FUNDOS EU\nTêm fundos EU? Sim\n\n12 - DOCUMENTOS DE HABILITAÇÃO\nHabilitação para o exercício da atividade profissional: Não\n\n13 - CONDIÇÕES DE APRESENTAÇÃO\nPlataforma eletrónica utilizada pela entidade adjudicante: VORTAL\nURL para Apresentação: https://community.vortal.biz/public/\nAdmissibilidade da apresentação de propostas variantes: Não autorizado\nPrazo para apresentação das propostas: 04-09-2025 17:00\nPrazo durante o qual os concorrentes são obrigados a manter as respetivas propostas: 90 dias a contar do termo do prazo para a apresentação das propostas\nApresentação de Catálogo Eletrónico: Permitido\nIndicação de Subcontratação na Proposta: Inexistência de indicação de subcontratação\n\n14 - PRESTAÇÃO DE CAUÇÃO\nPrestação de caução: Não\n\n15 - FORNECIMENTO DAS PEÇAS DO CONCURSO, APRESENTAÇÃO DE PEDIDOS DE PARTICIPAÇÃO E APRESENTAÇÃO DAS PROPOSTAS\nLink para acesso às peças do concurso (URL): https://community.vortal.biz/Public/public-tender-documents/WUpWTnc2TnEyVi9NUjhWSStBYlErQUtJbjZDaktFWU1IaTRHM2xWWGpIakU0bnJUODB3L2IrUVllTlEra01rYjE4Q0tITnp5UnZuRTMwaGgzU0lveWc9PSNNQVNo\n\n20 - OUTROS REQUISITOS\nInformação sobre contratos reservados. Aplica-se a contratos reservados (54º-A)? Não\n\n21 - CRITÉRIO DE ADJUDICAÇÃO\nMultifator: Não\nMonofator:\nNome: Preço\n\n24 - CONDIÇÕES DO CONTRATO\nFaturação Eletrónica: Permitido\nObrigação de Subcontratação:\nCódigo da Obrigação de Subcontratação: Não é aplicável nenhuma obrigação de subcontratação.\n\n25 - COMPRA PÚBLICA ESTRATÉGICA\nCompra Pública Estratégica: Inexistência de contratação pública estratégica\n\n26 - INFORMAÇÕES ADICIONAIS\nContrato adequado para PME: Sim\nCobertura ACP (Acordo dos Contratos Públicos da Organização Mundial do Comércio): Não\n\n27 - IDENTIFICAÇÃO E CONTACTOS DO ÓRGÃO DE RECURSOS ADMINISTRATIVOS\nDesignação: Tribunal Administrativo e Fiscal de Coimbra\nEndereço: Av. Fernão de Magalhães, 223\nCódigo postal: 3000-176\nLocalidade: Coimbra\nTelefone: +351 239853480\nFax: +351 213506005\nEndereço eletrónico: coimbra.taf@tribunais.org.pt\n\n28 - IDENTIFICAÇÃO DO(S) AUTOR(ES) DE ANÚNCIO\nNome: Nuno José de Campos Nogueira Cortez\nCargo: Chefe de Divisão\n\n29 - ALTERAÇÃO\nMotivo da Alteração: Informações atualizadas\nIdentificador da Versão do Anúncio a Alterar: 6e49e5a7-a2c6-42de-bf2c-c4aa31a80776-01\nIdentificador das Secções Alteradas do Anúncio Anterior: Alteração\nAlteração dos Documentos do Concurso: Não\n419460626",
    "nipc": "517638754",
    "distrito": "Coimbra",
    "concelho": "Coimbra",
    "freguesia": "Todas",
    "site": "https://www.ccdrc.pt/pt/",
    "email": "geral@ccdrc.pt",
    "designacao_contrato": "Aquisição de serviços e equipamentos para a comunicação unificada de voz e dados, fixos e móveis",
    "descricao": "Serviços e equipamentos para a comunicação unificada de voz e dados, fixos e móveis",
    "preco_base": "436.128,00 EUR",
    "prazo_execucao": "48 MESES",
    "prazo_apresentacao_propostas": "04-09-2025 17:00",
    "fundos_eu": "Sim",
    "plataforma_eletronica": "VORTAL",
    "url_procedimento": "https://community.vortal.biz/public/",
    "autor_nome": "Nuno José de Campos Nogueira Cortez",
    "autor_cargo": "Chefe de Divisão"
  },
  {
    "numero_procedimento": "N/A",
    "entidade": "SPMS- Serviços Partilhados do M. da Saúde, E.P.E.",
    "link": "https://diariodarepublica.pt/dr/detalhe/contrato-publico/22632-933115844",
    "detalhes_completos": "1 - IDENTIFICAÇÃO E CONTACTOS DA ENTIDADE ADJUDICANTE\nDesignação da entidade adjudicante: SPMS- Serviços Partilhados do M. da Saúde, E.P.E.\nNIPC: 509540716\nEndereço: Avenida da República 61\nCódigo postal: 1050-189\nLocalidade: Lisboa\nPaís: Portugal\nNUT III: PT170\nDistrito: Lisboa\nConcelho: Lisboa\nFreguesia: Todas\nTelefone: 211545600\nFax: 211545649\nEndereço da Entidade (URL): www.spms.min-saude.pt/\nEndereço Eletrónico: contratacao@spms.min-saude.pt\neDelivery Gateway (URL): https://community.vortal.biz/public/\nFunção da Organização: Adquirente\nNorma jurídica da Entidade Adjudicante: Empresa pública\nÁrea de atividade da Autoridade Adjudicante: Saúde\n\n2 - JORNAL OFICIAL DA UNIÃO EUROPEIA\nO procedimento a que este anúncio diz respeito também é publicitado no Jornal Oficial da União Europeia? Sim\n\n3 - AVISO\nModelo de Anúncio: Concurso público\nData de Envio do Anúncio: 22-08-2025\n\n5 - PROCESSO\nTipo de Procedimento: Concurso público\nPreço base do procedimento: Sim\nValor do preço base do procedimento: 729.354,56 EUR\nProcedimento com lotes? Não\n\n6 - OBJETO DO CONTRATO\nNúmero de referência interna: 20250118\nDesignação do contrato: (DAG) Aquisição de solução para uma plataforma de resumo de informação clínica do utente para o Pilar 3 – Reforma dos SI disponibilizados aos profissionais de saúde (PRR) (20250118) \nDescrição: (DAG) Aquisição de solução para uma plataforma de resumo de informação clínica do utente para o Pilar 3 – Reforma dos SI disponibilizados aos profissionais de saúde (PRR) (20250118) \nOpções: Não\nTipo de Contrato Principal: Aquisição de Serviços\nTipo de Contrato: Aquisição de Serviços\nClassificação CPV (Vocabulário Comum para os Contratos Públicos)\nObjeto principal\nVocabulário Principal: 72500000\nPreço base s/IVA: 729.354,56 EUR\n\n7 - INDICAÇÕES ADICIONAIS\nO contrato envolve aquisição conjunta (satisfação de várias entidades)? Não\nO contrato é adjudicado por uma central de compras? Não\n\n8 - TÉCNICAS\nO concurso destina-se à celebração de um acordo-quadro? Inexistência de acordo-quadro\nÉ utilizado um leilão eletrónico? Não\nÉ adotada uma fase de negociação? Não\nSistema de Aquisição Dinâmico: Inexistência de sistema de aquisição dinâmico\n\n9 - LOCAL DA EXECUÇÃO DO CONTRATO\nLOCAL DA EXECUÇÃO DO CONTRATO (PROCEDIMENTO)\nPaís: Portugal\nNUT III: PT170\nLocalidade: Lisboa\nDistrito: Lisboa\nConcelho: Lisboa\nFreguesia: Todas\n\n10 - PRAZO DE EXECUÇÃO DO CONTRATO\nPrazo de execução do contrato: 10 MESES\nPrevisão de renovações: Não\n\n11 - FUNDOS EU\nTêm fundos EU? Sim\n\n12 - DOCUMENTOS DE HABILITAÇÃO\nHabilitação para o exercício da atividade profissional: Não\n\n13 - CONDIÇÕES DE APRESENTAÇÃO\nPlataforma eletrónica utilizada pela entidade adjudicante: VORTAL\nURL para Apresentação: https://community.vortal.biz/public/\nAdmissibilidade da apresentação de propostas variantes: Não autorizado\nPrazo para apresentação das propostas: 22-09-2025 18:00\nPrazo durante o qual os concorrentes são obrigados a manter as respetivas propostas: 180 dias a contar do termo do prazo para a apresentação das propostas\nApresentação de Catálogo Eletrónico: Permitido\nIndicação de Subcontratação na Proposta: Inexistência de indicação de subcontratação\n\n14 - PRESTAÇÃO DE CAUÇÃO\nPrestação de caução: Sim\nPercentagem: 5%\nDescrição da Garantia Exigida: Conforme artigo 29.º do Programa de Procedimento\n\n15 - FORNECIMENTO DAS PEÇAS DO CONCURSO, APRESENTAÇÃO DE PEDIDOS DE PARTICIPAÇÃO E APRESENTAÇÃO DAS PROPOSTAS\nLink para acesso às peças do concurso (URL): https://community.vortal.biz/Public/public-tender-documents/ZGFtVTNhbExMYlRMSmtrVGRUK0VDUUtGcWVRUHBnV0NGYTFKOGdWNEZ5WktLbU9uazdoRlR6VnpUQVhFZ0o3U3R6cUpQUExKSnRvbnh6cUlSYzZtTWc9PVpuRkUy\n\n20 - OUTROS REQUISITOS\nInformação sobre contratos reservados. Aplica-se a contratos reservados (54º-A)? Não\n\n21 - CRITÉRIO DE ADJUDICAÇÃO\nMultifator: Não\nMonofator:\nNome: Preço\n\n24 - CONDIÇÕES DO CONTRATO\nFaturação Eletrónica: Permitido\nObrigação de Subcontratação:\nCódigo da Obrigação de Subcontratação: O contratante tem de indicar qualquer mudança de subcontratantes durante a execução do contrato.\n\n25 - COMPRA PÚBLICA ESTRATÉGICA\nCompra Pública Estratégica: Inexistência de contratação pública estratégica\n\n26 - INFORMAÇÕES ADICIONAIS\nContrato adequado para PME: Sim\nCobertura ACP (Acordo dos Contratos Públicos da Organização Mundial do Comércio): Não\n\n27 - IDENTIFICAÇÃO E CONTACTOS DO ÓRGÃO DE RECURSOS ADMINISTRATIVOS\nDesignação: Conselho de Administração da SPMS, EPE\nEndereço: Avenida da República 61\nCódigo postal: 1050-099\nLocalidade: Lisboa\nTelefone: +351 211545600\nFax: +351 211545649\nEndereço eletrónico: contratacao@spms.min-saude.pt\n\n28 - IDENTIFICAÇÃO DO(S) AUTOR(ES) DE ANÚNCIO\nNome: Laura Raposo\nCargo: Diretora da Direção de Administração Geral\n419459403",
    "nipc": "509540716",
    "distrito": "Lisboa",
    "concelho": "Lisboa",
    "freguesia": "Todas",
    "site": "www.spms.min-saude.pt/",
    "email": "contratacao@spms.min-saude.pt",
    "designacao_contrato": "(DAG) Aquisição de solução para uma plataforma de resumo de informação clínica do utente para o Pilar 3 – Reforma dos SI disponibilizados aos profissionais de saúde (PRR) (20250118)",
    "descricao": "(DAG) Aquisição de solução para uma plataforma de resumo de informação clínica do utente para o Pilar 3 – Reforma dos SI disponibilizados aos profissionais de saúde (PRR) (20250118)",
    "preco_base": "729.354,56 EUR",
    "prazo_execucao": "10 MESES",
    "prazo_apresentacao_propostas": "22-09-2025 18:00",
    "fundos_eu": "Sim",
    "plataforma_eletronica": "VORTAL",
    "url_procedimento": "https://community.vortal.biz/public/",
    "autor_nome": "Laura Raposo",
    "autor_cargo": "Diretora da Direção de Administração Geral"
  },
  {
    "numero_procedimento": "N/A",
    "entidade": "Auto Viação Pacense, Lda",
    "link": "https://diariodarepublica.pt/dr/detalhe/contrato-publico/22633-933115845",
    "detalhes_completos": "1 - IDENTIFICAÇÃO E CONTACTOS DA ENTIDADE ADJUDICANTE\nDesignação da entidade adjudicante: Auto Viação Pacense, Lda\nNIPC: 500038589\nEndereço: Rua Antiga de Brito, n 117\nCódigo postal: 4590-754\nLocalidade: Porto\nPaís: Portugal\nNUT III: PT11C\nDistrito: Porto\nConcelho: Paços de Ferreira\nFreguesia: Freguesia de Ferreira - Paços de Ferreira\nTelefone: 255860220\nFax: 255860229\nEndereço da Entidade (URL): http://www.avpacense.pt/\nEndereço Eletrónico: avpacense@avpacense.pt\neDelivery Gateway (URL): https://community.vortal.biz/public/\nFunção da Organização: Adquirente\nNorma jurídica da Entidade Adjudicante: Organização que adjudica um contrato subvencionado por uma autoridade da administração central\nÁrea de atividade da Autoridade Adjudicante: Assuntos económicos\n\n2 - JORNAL OFICIAL DA UNIÃO EUROPEIA\nO procedimento a que este anúncio diz respeito também é publicitado no Jornal Oficial da União Europeia? Sim\n\n3 - AVISO\nModelo de Anúncio: Concurso público\nData de Envio do Anúncio: 22-08-2025\n\n5 - PROCESSO\nTipo de Procedimento: Concurso público\nPreço base do procedimento: Sim\nValor do preço base do procedimento: 2.750.000,00 EUR\nProcedimento com lotes? Não\n\n6 - OBJETO DO CONTRATO\nNúmero de referência interna: CPI_07_25_AVP\nDesignação do contrato: AQUISIÇÃO DE CINCO AUTOCARROS STANDARD 100%  ELÉTRICOS\nDescrição: Procedimento pré-contratual de Concurso Público com publicação de anúncio no Jornal oficial da \nUnião Europeia, que tem por objeto principal a “Aquisição de cinco autocarros standard 100% \nelétricos”\nOpções: Não\nTipo de Contrato Principal: Aquisição de Bens Móveis\nTipo de Contrato: Aquisição de Bens Móveis\nClassificação CPV (Vocabulário Comum para os Contratos Públicos)\nObjeto principal\nVocabulário Principal: 34144910\nPreço base s/IVA: 2.750.000,00 EUR\n\n7 - INDICAÇÕES ADICIONAIS\nO contrato envolve aquisição conjunta (satisfação de várias entidades)? Não\nO contrato é adjudicado por uma central de compras? Não\n\n8 - TÉCNICAS\nO concurso destina-se à celebração de um acordo-quadro? Inexistência de acordo-quadro\nÉ utilizado um leilão eletrónico? Não\nÉ adotada uma fase de negociação? Não\nSistema de Aquisição Dinâmico: Inexistência de sistema de aquisição dinâmico\n\n9 - LOCAL DA EXECUÇÃO DO CONTRATO\nLOCAL DA EXECUÇÃO DO CONTRATO (PROCEDIMENTO)\nPaís: Portugal\nNUT III: PT11C\nLocalidade: Porto\nDistrito: Porto\nConcelho: Paços de Ferreira\nFreguesia: Freguesia de Ferreira - Paços de Ferreira\n\n10 - PRAZO DE EXECUÇÃO DO CONTRATO\nPrazo de execução do contrato: 5 MESES\nPrevisão de renovações: Não\n\n11 - FUNDOS EU\nTêm fundos EU? Sim\n\n12 - DOCUMENTOS DE HABILITAÇÃO\nHabilitação para o exercício da atividade profissional: Não\n\n13 - CONDIÇÕES DE APRESENTAÇÃO\nPlataforma eletrónica utilizada pela entidade adjudicante: VORTAL\nURL para Apresentação: https://community.vortal.biz/public/\nAdmissibilidade da apresentação de propostas variantes: Não autorizado\nPrazo para apresentação das propostas: 21-09-2025 17:00\nPrazo durante o qual os concorrentes são obrigados a manter as respetivas propostas: 90 dias a contar do termo do prazo para a apresentação das propostas\nApresentação de Catálogo Eletrónico: Permitido\nIndicação de Subcontratação na Proposta: Inexistência de indicação de subcontratação\n\n14 - PRESTAÇÃO DE CAUÇÃO\nPrestação de caução: Sim\nPercentagem: 5%\nDescrição da Garantia Exigida: Depósito em dinheiro ou mediante garantia bancária\n\n15 - FORNECIMENTO DAS PEÇAS DO CONCURSO, APRESENTAÇÃO DE PEDIDOS DE PARTICIPAÇÃO E APRESENTAÇÃO DAS PROPOSTAS\nLink para acesso às peças do concurso (URL): https://community.vortal.biz/Public/public-tender-documents/dmlQSE5SZ0NINURtVlpWUkMwcmk0Zmg1WlVmUHpKUGxBNmZWMk55RVRZSW9qeVdOSWJoMHQ0THBBb3hmU0NmVEpsd2dyYVF4WmdURnFvMHVNRTZTNnc9PU1zOFhY\n\n20 - OUTROS REQUISITOS\nInformação sobre contratos reservados. Aplica-se a contratos reservados (54º-A)? Não\n\n21 - CRITÉRIO DE ADJUDICAÇÃO\nMultifator: Não\nMonofator:\nNome: Preço\n\n24 - CONDIÇÕES DO CONTRATO\nFaturação Eletrónica: Permitido\nObrigação de Subcontratação:\nCódigo da Obrigação de Subcontratação: Não é aplicável nenhuma obrigação de subcontratação.\n\n25 - COMPRA PÚBLICA ESTRATÉGICA\nCompra Pública Estratégica: Inexistência de contratação pública estratégica\n\n26 - INFORMAÇÕES ADICIONAIS\nContrato adequado para PME: Sim\nCobertura ACP (Acordo dos Contratos Públicos da Organização Mundial do Comércio): Não\n\n27 - IDENTIFICAÇÃO E CONTACTOS DO ÓRGÃO DE RECURSOS ADMINISTRATIVOS\nDesignação: Auto Viação Pacense, Lda.\nEndereço: Rua Antiga de Brito, n 117\nCódigo postal: 4590-754\nLocalidade: Paços de Ferreira\nTelefone: +351 255860220\nFax: +351 255860220\nEndereço eletrónico: miguelmaia@avpacense.pt\n\n28 - IDENTIFICAÇÃO DO(S) AUTOR(ES) DE ANÚNCIO\nNome: Miguel Maia\nCargo: Gerente\n419460715",
    "nipc": "500038589",
    "distrito": "Porto",
    "concelho": "Paços de Ferreira",
    "freguesia": "Freguesia de Ferreira - Paços de Ferreira",
    "site": "http://www.avpacense.pt/",
    "email": "avpacense@avpacense.pt",
    "designacao_contrato": "AQUISIÇÃO DE CINCO AUTOCARROS STANDARD 100% ELÉTRICOS",
    "descricao": "Procedimento pré-contratual de Concurso Público com publicação de anúncio no Jornal oficial da",
    "preco_base": "2.750.000,00 EUR",
    "prazo_execucao": "5 MESES",
    "prazo_apresentacao_propostas": "21-09-2025 17:00",
    "fundos_eu": "Sim",
    "plataforma_eletronica": "VORTAL",
    "url_procedimento": "https://community.vortal.biz/public/",
    "autor_nome": "Miguel Maia",
    "autor_cargo": "Gerente"
  },
  {
    "numero_procedimento": "N/A",
    "entidade": "Águas do Tejo Atlântico, SA",
    "link": "https://diariodarepublica.pt/dr/detalhe/contrato-publico/22635-933115846",
    "detalhes_completos": "Alteração do Anúncio de procedimento n.º 16527/2025, de 2025-06-23, com o ID 419202219\n\n1 - IDENTIFICAÇÃO E CONTACTOS DA ENTIDADE ADJUDICANTE\nDesignação da entidade adjudicante: Águas do Tejo Atlântico, SA\nNIPC: 514387130\nServiço/Órgão/Pessoa de contacto: DGA/Paulo Inocêncio\nEndereço: ETAR de Alcântara, Av. De Ceuta\nCódigo postal: 1300-254\nLocalidade: LISBOA\nPaís: Portugal\nNUT III: PT170\nDistrito: Lisboa\nConcelho: Lisboa\nFreguesia: Freguesia de Campo de Ourique\nTelefone: 351213107900\nFax: 351213107901\nEndereço da Entidade (URL): https://www.aguasdotejoatlantico.adp.pt/\nEndereço Eletrónico: geral.adta@adp.pt\neDelivery Gateway (URL): https://www.acingov.pt\nFunção da Organização: Adquirente\nSubfunção da Organização: Organização cujo orçamento é utilizado para pagar o contrato; Organização que executa o pagamento; Organização que fornece informações adicionais sobre o processo de adjudicação; Organização que fornece mais informações sobre os prazos dos procedimentos de recurso; Organização que fornece acesso fora de linha aos documentos do concurso; Organização responsável pelo tratamento das propostas; Organização que recebe as propostas; Organização que trata os pedidos de participação; Organização que recebe pedidos de participação; Organização que fornece mais informações sobre os procedimentos de recurso; Organização que assina o contrato\nNorma jurídica da Entidade Adjudicante: Organismo de direito público\nÁrea de atividade da Autoridade Adjudicante: Serviços públicos das administrações públicas\n\n2 - JORNAL OFICIAL DA UNIÃO EUROPEIA\nO procedimento a que este anúncio diz respeito também é publicitado no Jornal Oficial da União Europeia? Sim\n\n3 - AVISO\nModelo de Anúncio: Concurso público\nData de Envio do Anúncio: 22-08-2025\n\n5 - PROCESSO\nTipo de Procedimento: Concurso público\nPreço base do procedimento: Sim\nValor do preço base do procedimento: 24.000.000,00 EUR\nProcedimento com lotes? Não\n\n6 - OBJETO DO CONTRATO\nNúmero de referência interna: TA_25_114_CI_O_003_DGA\nDesignação do contrato: Empreitada de Conceção-Construção da Instalação de Hidrólise Térmica da Fábrica de Água de Frielas\nDescrição: Empreitada de Conceção-Construção da Instalação de Hidrólise Térmica da Fábrica de Água de Frielas\nOpções: Não\nTipo de Contrato Principal: Empreitada de Obras Públicas\nTipo de Contrato: Empreitada de Obras Públicas\nClassificação CPV (Vocabulário Comum para os Contratos Públicos)\nObjeto principal\nVocabulário Principal: 45252127\nPreço base s/IVA: 24.000.000,00 EUR\n\n7 - INDICAÇÕES ADICIONAIS\nO contrato envolve aquisição conjunta (satisfação de várias entidades)? Não\nO contrato é adjudicado por uma central de compras? Não\n\n8 - TÉCNICAS\nO concurso destina-se à celebração de um acordo-quadro? Inexistência de acordo-quadro\nÉ utilizado um leilão eletrónico? Não\nÉ adotada uma fase de negociação? Não\nSistema de Aquisição Dinâmico: Inexistência de sistema de aquisição dinâmico\n\n9 - LOCAL DA EXECUÇÃO DO CONTRATO\nLOCAL DA EXECUÇÃO DO CONTRATO (PROCEDIMENTO)\nPaís: Portugal\nNUT III: PT170\nLocalidade: União das Freguesias de Santo António dos Cavaleiros e Frielas\nDistrito: Lisboa\nConcelho: Loures\nFreguesia: União das Freguesias de Santo António dos Cavaleiros e Frielas\n\n10 - PRAZO DE EXECUÇÃO DO CONTRATO\nPrazo de execução do contrato: 1055 DIAS\nPrevisão de renovações: Não\n\n11 - FUNDOS EU\nTêm fundos EU? Não\n\n12 - DOCUMENTOS DE HABILITAÇÃO\nHabilitação para o exercício da atividade profissional: Sim\nTipo: Alvará\nDescrição: 13ª subcategoria da 4ª categoria e da classe correspondente ao valor global da proposta;\n\n1ª e 2ª subcategorias da 1ª categoria, da classe correspondente ao valor dos trabalhos especializados que lhes respeite, consoante a parte que a esses trabalhos cabe na proposta;\n\n6ª subcategoria da 2ª categoria, da classe correspondente ao valor dos trabalhos especializados que lhes respeite, consoante a parte que a esses trabalhos cabe na proposta;\n\n1ª, 3ª, 4ª, 6ª, 10ª, 11ª,12ª, 14ª e 19ª subcategorias da 4ª categoria, de classes correspondentes ao valor dos trabalhos especializados que lhes respeitem, consoante a parte que a esses trabalhos cabe na proposta;\n\n4ª subcategoria da 5ª categoria, da classe correspondente ao valor dos trabalhos especializados que lhes respeite, consoante a parte que a esses trabalhos cabe na proposta.\n\n13 - CONDIÇÕES DE APRESENTAÇÃO\nPlataforma eletrónica utilizada pela entidade adjudicante: ACIN\nURL para Apresentação: https://www.acingov.pt\nAdmissibilidade da apresentação de propostas variantes: Não autorizado\nPrazo para apresentação das propostas: 20-11-2025 23:59\nPrazo durante o qual os concorrentes são obrigados a manter as respetivas propostas: 90 dias a contar do termo do prazo para a apresentação das propostas\nApresentação de Catálogo Eletrónico: Não autorizado\nIndicação de Subcontratação na Proposta: A parte do contrato que o proponente tenciona subcontratar\n\n14 - PRESTAÇÃO DE CAUÇÃO\nPrestação de caução: Sim\nPercentagem: 5%\nDescrição da Garantia Exigida: O valor da caução é de 5.00% do preço contratual.\n\n15 - FORNECIMENTO DAS PEÇAS DO CONCURSO, APRESENTAÇÃO DE PEDIDOS DE PARTICIPAÇÃO E APRESENTAÇÃO DAS PROPOSTAS\nLink para acesso às peças do concurso (URL): https://www.acingov.pt/acingovprod/2/zonaPublica/zona_publica_c/donwloadProcedurePiece/OTEwODYx\n\n20 - OUTROS REQUISITOS\nInformação sobre contratos reservados. Aplica-se a contratos reservados (54º-A)? Não\n\n21 - CRITÉRIO DE ADJUDICAÇÃO\nMultifator: Sim\nFator: \nNome: Preço\nPonderação: 35%\nSubfatores: Não\nFator: \nNome: Outros\nOutro Nome: Custos de Exploração Normalizados a Longo Prazo\nPonderação: 10%\nSubfatores: Não\nFator: \nNome: Outros\nOutro Nome: Valia Técnica\nPonderação: 55%\nSubfatores: Sim\nSubfatores: \nNome: Conceção e Fundamentação da Solução Proposta\nPonderação : 81.82%; \nNome: Metodologia de Execução da Obra\nPonderação : 9.09%; \nNome: Detalhe e Consistência do Plano de Trabalhos\nPonderação : 9.09%; \n\n24 - CONDIÇÕES DO CONTRATO\nFaturação Eletrónica: Necessário\nObrigação de Subcontratação:\nCódigo da Obrigação de Subcontratação: Não é aplicável nenhuma obrigação de subcontratação.\n\n25 - COMPRA PÚBLICA ESTRATÉGICA\nCompra Pública Estratégica: Redução dos impactos ambientais\nDescrição do Processo de Adjudicação Estratégico: Utilização de materiais reutilizados ou reciclados\nCritérios de contratos Públicos Ecológicos: Critérios de contratação pública ecológica da UE; Critérios de contratação pública ecológica nacional\nCategorias da estratégia nacional: Infraestruturas de tratamento de águas residuais\nContratos Públicos Ecológicos: A transição para uma economia circular\nDiretiva Veículos Não Poluentes: Não\nCritério de Acessibilidade: Os critérios de acessibilidade para as pessoas com deficiência não estão incluídos porque o contrato não se destina a pessoas singulares\n\n26 - INFORMAÇÕES ADICIONAIS\nContrato adequado para PME: Sim\nCobertura ACP (Acordo dos Contratos Públicos da Organização Mundial do Comércio): Não\n\n27 - IDENTIFICAÇÃO E CONTACTOS DO ÓRGÃO DE RECURSOS ADMINISTRATIVOS\nDesignação: Conselho de Administração.\nEndereço: ETAR de Alcântara, Av. De Ceuta\nCódigo postal: 1300-254\nLocalidade: LISBOA\nTelefone: 213107900\nFax: \nEndereço eletrónico: compras_contratacao.adta@adp.pt\n\n28 - IDENTIFICAÇÃO DO(S) AUTOR(ES) DE ANÚNCIO\nNome: Nuno Brôco\nCargo: Presidente do Conselho de Administração\n\n29 - ALTERAÇÃO\nMotivo da Alteração: Informações agora disponíveis\nIdentificador da Versão do Anúncio a Alterar: 808f9f25-d043-46f5-9358-30b3393ca2e6-01\nIdentificador das Secções Alteradas do Anúncio Anterior: Condições de Apresentação\nDescrição das Alterações: Modificação do prazo para a apresentação de propostas\nAlteração dos Documentos do Concurso: Sim\nData de alteração dos documentos do concurso: 21-08-2025\n419460415",
    "nipc": "514387130",
    "distrito": "Lisboa",
    "concelho": "Lisboa",
    "freguesia": "Freguesia de Campo de Ourique",
    "site": "https://www.aguasdotejoatlantico.adp.pt/",
    "email": "geral.adta@adp.pt",
    "designacao_contrato": "Empreitada de Conceção-Construção da Instalação de Hidrólise Térmica da Fábrica de Água de Frielas",
    "descricao": "Empreitada de Conceção-Construção da Instalação de Hidrólise Térmica da Fábrica de Água de Frielas",
    "preco_base": "24.000.000,00 EUR",
    "prazo_execucao": "1055 DIAS",
    "prazo_apresentacao_propostas": "20-11-2025 23:59",
    "fundos_eu": "Não",
    "plataforma_eletronica": "ACIN",
    "url_procedimento": "https://www.acingov.pt",
    "autor_nome": "Nuno Brôco",
    "autor_cargo": "Presidente do Conselho de Administração"
  },
  {
    "numero_procedimento": "N/A",
    "entidade": "Águas e Energia do Porto E.M",
    "link": "https://diariodarepublica.pt/dr/detalhe/contrato-publico/22636-933115847",
    "detalhes_completos": "1 - IDENTIFICAÇÃO E CONTACTOS DA ENTIDADE ADJUDICANTE\nDesignação da entidade adjudicante: Águas e Energia do Porto E.M\nNIPC: 507718666\nServiço/Órgão/Pessoa de contacto: Administrador\nEndereço: Rua Barão de Nova Sintra, Nº 285\nCódigo postal: 4300-367\nLocalidade: Porto\nPaís: Portugal\nNUT III: PTZZZ\nDistrito: Todos\nConcelho: Todos\nFreguesia: Todas\nTelefone: 225190854\nFax: 225190807\nEndereço da Entidade (URL): www.aguasdoporto.pt\nEndereço Eletrónico: contratos@aguasdoporto.pt\neDelivery Gateway (URL): https://www.acingov.pt\nFunção da Organização: Adquirente\nNorma jurídica da Entidade Adjudicante: Organismo de direito público\nÁrea de atividade da Autoridade Adjudicante: Serviços públicos das administrações públicas\n\n2 - JORNAL OFICIAL DA UNIÃO EUROPEIA\nO procedimento a que este anúncio diz respeito também é publicitado no Jornal Oficial da União Europeia? Sim\n\n3 - AVISO\nModelo de Anúncio: Concurso público\nData de Envio do Anúncio: 22-08-2025\n\n5 - PROCESSO\nTipo de Procedimento: Concurso público\nPreço base do procedimento: Sim\nValor do preço base do procedimento: 582.532,00 EUR\nProcedimento com lotes? Não\n\n6 - OBJETO DO CONTRATO\nNúmero de referência interna: 483CPI25\nDesignação do contrato: 483CPI25 Aquisição de Serviços de Limpeza e Higienização das Instalações da AEdP\nDescrição: 483CPI25 Aquisição de Serviços de Limpeza e Higienização das Instalações da AEdP\nOpções: Não\nTipo de Contrato Principal: Aquisição de Serviços\nTipo de Contrato: Aquisição de Serviços\nClassificação CPV (Vocabulário Comum para os Contratos Públicos)\nObjeto principal\nVocabulário Principal: 90910000\nPreço base s/IVA: 582.532,00 EUR\n\n7 - INDICAÇÕES ADICIONAIS\nO contrato envolve aquisição conjunta (satisfação de várias entidades)? Não\nO contrato é adjudicado por uma central de compras? Não\n\n8 - TÉCNICAS\nO concurso destina-se à celebração de um acordo-quadro? Inexistência de acordo-quadro\nÉ utilizado um leilão eletrónico? Não\nÉ adotada uma fase de negociação? Não\nSistema de Aquisição Dinâmico: Inexistência de sistema de aquisição dinâmico\n\n9 - LOCAL DA EXECUÇÃO DO CONTRATO\nLOCAL DA EXECUÇÃO DO CONTRATO (PROCEDIMENTO)\nPaís: Portugal\nNUT III: PT11A\nLocalidade: Porto\nDistrito: Porto\nConcelho: Porto\nFreguesia: Todas\n\n10 - PRAZO DE EXECUÇÃO DO CONTRATO\nPrazo de execução do contrato: 365 DIAS\nPrevisão de renovações: Sim\nIndicar número máximo de renovações: 2\nPrazo de renovações diferente do prazo inicial: Não\n\n11 - FUNDOS EU\nTêm fundos EU? Não\n\n12 - DOCUMENTOS DE HABILITAÇÃO\nHabilitação para o exercício da atividade profissional: Não\n\n13 - CONDIÇÕES DE APRESENTAÇÃO\nPlataforma eletrónica utilizada pela entidade adjudicante: ACIN\nURL para Apresentação: https://www.acingov.pt\nAdmissibilidade da apresentação de propostas variantes: Não autorizado\nPrazo para apresentação das propostas: 24-09-2025 17:00\nPrazo durante o qual os concorrentes são obrigados a manter as respetivas propostas: 66 dias a contar do termo do prazo para a apresentação das propostas\nApresentação de Catálogo Eletrónico: Permitido\nIndicação de Subcontratação na Proposta: Inexistência de indicação de subcontratação\n\n14 - PRESTAÇÃO DE CAUÇÃO\nPrestação de caução: Sim\nPercentagem: 5%\nDescrição da Garantia Exigida: O valor da caução é de 5.00% do preço contratual.\n\n15 - FORNECIMENTO DAS PEÇAS DO CONCURSO, APRESENTAÇÃO DE PEDIDOS DE PARTICIPAÇÃO E APRESENTAÇÃO DAS PROPOSTAS\nLink para acesso às peças do concurso (URL): https://www.acingov.pt/acingovprod/2/zonaPublica/zona_publica_c/donwloadProcedurePiece/OTMyNzgz\n\n20 - OUTROS REQUISITOS\nInformação sobre contratos reservados. Aplica-se a contratos reservados (54º-A)? Não\n\n21 - CRITÉRIO DE ADJUDICAÇÃO\nMultifator: Sim\nFator: \nNome: Preço\nPonderação: 70%\nSubfatores: Não\nFator: \nNome: Outros\nOutro Nome: Qualidade da solução de acompanhamento e execução do Contrato (QL)\nPonderação: 21%\nSubfatores: Não\nFator: \nNome: Outros\nOutro Nome: Tempo de resposta do trabalho extraordinário (TRNP)\nPonderação: 4.5%\nSubfatores: Não\nFator: \nNome: Outros\nOutro Nome: Frequência das ações de supervisão, por instalação (FS)\nPonderação: 4.5%\nSubfatores: Não\n\n24 - CONDIÇÕES DO CONTRATO\nFaturação Eletrónica: Permitido\nObrigação de Subcontratação:\nCódigo da Obrigação de Subcontratação: Não é aplicável nenhuma obrigação de subcontratação.\n\n25 - COMPRA PÚBLICA ESTRATÉGICA\nCompra Pública Estratégica: Inexistência de contratação pública estratégica\n\n26 - INFORMAÇÕES ADICIONAIS\nContrato adequado para PME: Não\nCobertura ACP (Acordo dos Contratos Públicos da Organização Mundial do Comércio): Não\n\n27 - IDENTIFICAÇÃO E CONTACTOS DO ÓRGÃO DE RECURSOS ADMINISTRATIVOS\nDesignação: Conselho de Administração da CMPEAE - Empresa de Águas e Energia do Município do Porto, E. M.\nEndereço: R. do Barão de Nova Sintra 285\nCódigo postal: 4300-367\nLocalidade: Porto\nTelefone: 220100220\nFax: \nEndereço eletrónico: contratos@aguasdoporto.pt\n\n28 - IDENTIFICAÇÃO DO(S) AUTOR(ES) DE ANÚNCIO\nNome: Eng. Ruben Fernandes\nCargo: Administrador Executivo\n419457598",
    "nipc": "507718666",
    "distrito": "Todos",
    "concelho": "Todos",
    "freguesia": "Todas",
    "site": "www.aguasdoporto.pt",
    "email": "contratos@aguasdoporto.pt",
    "designacao_contrato": "483CPI25 Aquisição de Serviços de Limpeza e Higienização das Instalações da AEdP",
    "descricao": "483CPI25 Aquisição de Serviços de Limpeza e Higienização das Instalações da AEdP",
    "preco_base": "582.532,00 EUR",
    "prazo_execucao": "365 DIAS",
    "prazo_apresentacao_propostas": "24-09-2025 17:00",
    "fundos_eu": "Não",
    "plataforma_eletronica": "ACIN",
    "url_procedimento": "https://www.acingov.pt",
    "autor_nome": "Eng. Ruben Fernandes",
    "autor_cargo": "Administrador Executivo"
  },
  {
    "numero_procedimento": "N/A",
    "entidade": "Instituto de Administração da Saúde, IP-RAM",
    "link": "https://diariodarepublica.pt/dr/detalhe/contrato-publico/22639-933115848",
    "detalhes_completos": "Alteração do Anúncio de procedimento n.º 20719/2025, de 2025-08-01, com o ID 419374491\n\n1 - IDENTIFICAÇÃO E CONTACTOS DA ENTIDADE ADJUDICANTE\nDesignação da entidade adjudicante: Instituto de Administração da Saúde, IP-RAM\nNIPC: 511284349\nServiço/Órgão/Pessoa de contacto: Conselho Diretivo\nEndereço: Rua das Pretas, 1\nCódigo postal: 9004-515\nLocalidade: Funchal\nPaís: Portugal\nNUT III: PT300\nDistrito: Região Autónoma da Madeira\nConcelho: Funchal\nFreguesia: Todas\nTelefone: 291 212 300\nFax: 291 212 302\nEndereço da Entidade (URL): https://www.iasaude.pt/\nEndereço Eletrónico: aquisicoes@iasaude.madeira.gov.pt\neDelivery Gateway (URL): https://www.acingov.pt\nFunção da Organização: Adquirente\nNorma jurídica da Entidade Adjudicante: Organismo de direito público\nÁrea de atividade da Autoridade Adjudicante: Serviços públicos das administrações públicas\n\n2 - JORNAL OFICIAL DA UNIÃO EUROPEIA\nO procedimento a que este anúncio diz respeito também é publicitado no Jornal Oficial da União Europeia? Sim\n\n3 - AVISO\nModelo de Anúncio: Concurso público\nData de Envio do Anúncio: 22-08-2025\n\n5 - PROCESSO\nTipo de Procedimento: Concurso público\nPreço base do procedimento: Sim\nValor do preço base do procedimento: 1.850.000,00 EUR\nProcedimento com lotes? Não\n\n6 - OBJETO DO CONTRATO\nNúmero de referência interna: CPI/1/2025-PPC\nDesignação do contrato: Aquisição de serviços de desenvolvimento, conceção, implementação e suporte de uma plataforma de partilha de dados de saúde e respetivas APP, designada por Registo de Saúde do Utente (RSU) para o Instituto de Administração da Saúde, IP  RAM\nDescrição:  Aquisição de serviços de desenvolvimento, conceção, implementação e suporte de uma plataforma de partilha de dados de saúde e respetivas APP, designada por Registo de Saúde do Utente (RSU) para o Instituto de Administração da Saúde, IP  RAM \nOpções: Não\nTipo de Contrato Principal: Aquisição de Serviços\nTipo de Contrato: Aquisição de Serviços\nClassificação CPV (Vocabulário Comum para os Contratos Públicos)\nObjeto principal\nVocabulário Principal: 72230000\nPreço base s/IVA: 1.850.000,00 EUR\n\n7 - INDICAÇÕES ADICIONAIS\nO contrato envolve aquisição conjunta (satisfação de várias entidades)? Não\nO contrato é adjudicado por uma central de compras? Não\n\n8 - TÉCNICAS\nO concurso destina-se à celebração de um acordo-quadro? Inexistência de acordo-quadro\nÉ utilizado um leilão eletrónico? Não\nÉ adotada uma fase de negociação? Não\nSistema de Aquisição Dinâmico: Inexistência de sistema de aquisição dinâmico\n\n9 - LOCAL DA EXECUÇÃO DO CONTRATO\nLOCAL DA EXECUÇÃO DO CONTRATO (PROCEDIMENTO)\nPaís: Portugal\nNUT III: PT300\nLocalidade: Funchal\nDistrito: Região Autónoma da Madeira\nConcelho: Funchal\nFreguesia: Todas\n\n10 - PRAZO DE EXECUÇÃO DO CONTRATO\nPrazo de execução do contrato: 8 MESES\nPrevisão de renovações: Não\n\n11 - FUNDOS EU\nTêm fundos EU? Sim\n\n12 - DOCUMENTOS DE HABILITAÇÃO\nHabilitação para o exercício da atividade profissional: Não\n\n13 - CONDIÇÕES DE APRESENTAÇÃO\nPlataforma eletrónica utilizada pela entidade adjudicante: ACIN\nURL para Apresentação: https://www.acingov.pt\nAdmissibilidade da apresentação de propostas variantes: Não autorizado\nPrazo para apresentação das propostas: 04-09-2025 23:59\nPrazo durante o qual os concorrentes são obrigados a manter as respetivas propostas: 66 dias a contar do termo do prazo para a apresentação das propostas\nApresentação de Catálogo Eletrónico: Permitido\nIndicação de Subcontratação na Proposta: Inexistência de indicação de subcontratação\n\n14 - PRESTAÇÃO DE CAUÇÃO\nPrestação de caução: Sim\nPercentagem: 2%\nDescrição da Garantia Exigida: O valor da caução é de 2.00% do preço contratual.\n\n15 - FORNECIMENTO DAS PEÇAS DO CONCURSO, APRESENTAÇÃO DE PEDIDOS DE PARTICIPAÇÃO E APRESENTAÇÃO DAS PROPOSTAS\nLink para acesso às peças do concurso (URL): https://www.acingov.pt/acingovprod/2/zonaPublica/zona_publica_c/donwloadProcedurePiece/OTI5MTQ1\n\n20 - OUTROS REQUISITOS\nInformação sobre contratos reservados. Aplica-se a contratos reservados (54º-A)? Não\n\n21 - CRITÉRIO DE ADJUDICAÇÃO\nMultifator: Sim\nFator: \nNome: Preço\nPonderação: 20%\nSubfatores: Não\nFator: \nNome: Outros\nOutro Nome: Valia Técnica\nPonderação: 40%\nSubfatores: Não\nFator: \nNome: Outros\nOutro Nome: Qualificações e experiência do pessoal encarregado da execução do contrato\nPonderação: 40%\nSubfatores: Não\n\n24 - CONDIÇÕES DO CONTRATO\nFaturação Eletrónica: Permitido\nObrigação de Subcontratação:\nCódigo da Obrigação de Subcontratação: Não é aplicável nenhuma obrigação de subcontratação.\n\n25 - COMPRA PÚBLICA ESTRATÉGICA\nCompra Pública Estratégica: Inexistência de contratação pública estratégica\n\n26 - INFORMAÇÕES ADICIONAIS\nContrato adequado para PME: Sim\nCobertura ACP (Acordo dos Contratos Públicos da Organização Mundial do Comércio): Não\n\n27 - IDENTIFICAÇÃO E CONTACTOS DO ÓRGÃO DE RECURSOS ADMINISTRATIVOS\nDesignação: Secretaria Regional de Saúde e Proteção Civil\nEndereço: Rua da Carreira, n.º 107\nCódigo postal: 9000-042\nLocalidade: Funchal\nTelefone: 291001520\nFax: \nEndereço eletrónico: gabinete.srs@madeira.gov.pt\nPrazo de interposição do recurso: 10 dias\n\n28 - IDENTIFICAÇÃO DO(S) AUTOR(ES) DE ANÚNCIO\nNome: Rubina Silva\nCargo: Presidente do Conselho Diretivo do IASAÚDE, IP-RAM\n\n29 - ALTERAÇÃO\nMotivo da Alteração: Correção pelo adquirente\nIdentificador da Versão do Anúncio a Alterar: e509e175-7129-41cb-965c-7a670c228e3a-01\nIdentificador das Secções Alteradas do Anúncio Anterior: O procedimento a que este anúncio diz respeito também é publicitado no Jornal Oficial da União Europeia?; Condições de Apresentação\nDescrição das Alterações: Modificação do prazo para a apresentação de propostas\nAlteração dos Documentos do Concurso: Sim\nData de alteração dos documentos do concurso: 19-08-2025\n419460861",
    "nipc": "511284349",
    "distrito": "Região Autónoma da Madeira",
    "concelho": "Funchal",
    "freguesia": "Todas",
    "site": "https://www.iasaude.pt/",
    "email": "aquisicoes@iasaude.madeira.gov.pt",
    "designacao_contrato": "Aquisição de serviços de desenvolvimento, conceção, implementação e suporte de uma plataforma de partilha de dados de saúde e respetivas APP, designada por Registo de Saúde do Utente (RSU) para o Instituto de Administração da Saúde, IP  RAM",
    "descricao": "Aquisição de serviços de desenvolvimento, conceção, implementação e suporte de uma plataforma de partilha de dados de saúde e respetivas APP, designada por Registo de Saúde do Utente (RSU) para o Instituto de Administração da Saúde, IP  RAM",
    "preco_base": "1.850.000,00 EUR",
    "prazo_execucao": "8 MESES",
    "prazo_apresentacao_propostas": "04-09-2025 23:59",
    "fundos_eu": "Sim",
    "plataforma_eletronica": "ACIN",
    "url_procedimento": "https://www.acingov.pt",
    "autor_nome": "Rubina Silva",
    "autor_cargo": "Presidente do Conselho Diretivo do IASAÚDE, IP-RAM"
  },
  {
    "numero_procedimento": "N/A",
    "entidade": "SCML",
    "link": "https://diariodarepublica.pt/dr/detalhe/contrato-publico/22640-933115849",
    "detalhes_completos": "Alteração do Anúncio de procedimento n.º 20634/2025, de 2025-07-31, com o ID 419369461\n\n1 - IDENTIFICAÇÃO E CONTACTOS DA ENTIDADE ADJUDICANTE\nDesignação da entidade adjudicante: SCML\nNIPC: 500745471\nServiço/Órgão/Pessoa de contacto: Exma. Mesa\nEndereço: Largo Trindade Coelho\nCódigo postal: 1200-470\nLocalidade: Lisboa\nPaís: Portugal\nNUT III: PT170\nDistrito: Lisboa\nConcelho: Lisboa\nFreguesia: Freguesia de Misericórdia\nTelefone: 213235000\nFax: 213235013\nEndereço da Entidade (URL): http://www.scml.pt/\nEndereço Eletrónico: dicom.nabse@scml.pt\neDelivery Gateway (URL): https://www.acingov.pt\nFunção da Organização: Adquirente\nSubfunção da Organização: Organização cujo orçamento é utilizado para pagar o contrato; Organização que executa o pagamento; Organização que fornece informações adicionais sobre o processo de adjudicação; Organização que fornece mais informações sobre os prazos dos procedimentos de recurso; Organização que fornece acesso fora de linha aos documentos do concurso; Organização responsável pelo tratamento das propostas; Organização que recebe as propostas; Organização que trata os pedidos de participação; Organização que recebe pedidos de participação; Organização que fornece mais informações sobre os procedimentos de recurso; Organização que assina o contrato\nNorma jurídica da Entidade Adjudicante: Organismo de direito público, controlado por uma autoridade da administração central\nÁrea de atividade da Autoridade Adjudicante: Proteção social\n\n2 - JORNAL OFICIAL DA UNIÃO EUROPEIA\nO procedimento a que este anúncio diz respeito também é publicitado no Jornal Oficial da União Europeia? Sim\n\n3 - AVISO\nModelo de Anúncio: Concurso público\nData de Envio do Anúncio: 22-08-2025\n\n5 - PROCESSO\nTipo de Procedimento: Concurso público\nPreço base do procedimento: Sim\nValor do preço base do procedimento: 712.466,00 EUR\nProcedimento com lotes? Não\n\n6 - OBJETO DO CONTRATO\nNúmero de referência interna: 25DC37CPI004\nDesignação do contrato: Aquisição de serviços de Auxiliares de Ação Médica\nDescrição: Aquisição de serviços de Auxiliares de Ação Médica\nOpções: Não\nTipo de Contrato Principal: Aquisição de Serviços\nTipo de Contrato: Aquisição de Serviços\nClassificação CPV (Vocabulário Comum para os Contratos Públicos)\nObjeto principal\nVocabulário Principal: 85140000\nPreço base s/IVA: 712.466,00 EUR\n\n7 - INDICAÇÕES ADICIONAIS\nO contrato envolve aquisição conjunta (satisfação de várias entidades)? Não\nO contrato é adjudicado por uma central de compras? Não\n\n8 - TÉCNICAS\nO concurso destina-se à celebração de um acordo-quadro? Inexistência de acordo-quadro\nÉ utilizado um leilão eletrónico? Não\nÉ adotada uma fase de negociação? Não\nSistema de Aquisição Dinâmico: Inexistência de sistema de aquisição dinâmico\n\n9 - LOCAL DA EXECUÇÃO DO CONTRATO\nLOCAL DA EXECUÇÃO DO CONTRATO (PROCEDIMENTO)\nPaís: Portugal\nNUT III: PT111\nLocalidade: União das Freguesias de Carcavelos e Parede\nDistrito: Lisboa\nConcelho: Cascais\nFreguesia: União das Freguesias de Carcavelos e Parede\n\n10 - PRAZO DE EXECUÇÃO DO CONTRATO\nPrazo de execução do contrato: 24 MESES\nPrevisão de renovações: Sim\nIndicar número máximo de renovações: 1\nPrazo de renovações diferente do prazo inicial: Não\n\n11 - FUNDOS EU\nTêm fundos EU? Não\n\n12 - DOCUMENTOS DE HABILITAÇÃO\nHabilitação para o exercício da atividade profissional: Não\n\n13 - CONDIÇÕES DE APRESENTAÇÃO\nPlataforma eletrónica utilizada pela entidade adjudicante: ACIN\nURL para Apresentação: https://www.acingov.pt\nAdmissibilidade da apresentação de propostas variantes: Não autorizado\nPrazo para apresentação das propostas: 18-09-2025 17:00\nPrazo durante o qual os concorrentes são obrigados a manter as respetivas propostas: 120 dias a contar do termo do prazo para a apresentação das propostas\nApresentação de Catálogo Eletrónico: Permitido\nIndicação de Subcontratação na Proposta: Inexistência de indicação de subcontratação\n\n14 - PRESTAÇÃO DE CAUÇÃO\nPrestação de caução: Sim\nPercentagem: 5%\nDescrição da Garantia Exigida: 5 % do preço do seu período de vigência inicial\n\n15 - FORNECIMENTO DAS PEÇAS DO CONCURSO, APRESENTAÇÃO DE PEDIDOS DE PARTICIPAÇÃO E APRESENTAÇÃO DAS PROPOSTAS\nLink para acesso às peças do concurso (URL): https://www.acingov.pt/acingovprod/2/zonaPublica/zona_publica_c/donwloadProcedurePiece/OTI5MTk3\n\n20 - OUTROS REQUISITOS\nInformação sobre contratos reservados. Aplica-se a contratos reservados (54º-A)? Não\n\n21 - CRITÉRIO DE ADJUDICAÇÃO\nMultifator: Não\nMonofator:\nNome: Preço\n\n24 - CONDIÇÕES DO CONTRATO\nFaturação Eletrónica: Necessário\nObrigação de Subcontratação:\nCódigo da Obrigação de Subcontratação: Não é aplicável nenhuma obrigação de subcontratação.\n\n25 - COMPRA PÚBLICA ESTRATÉGICA\nCompra Pública Estratégica: Inexistência de contratação pública estratégica\n\n26 - INFORMAÇÕES ADICIONAIS\nContrato adequado para PME: Não\nCobertura ACP (Acordo dos Contratos Públicos da Organização Mundial do Comércio): Não\n\n27 - IDENTIFICAÇÃO E CONTACTOS DO ÓRGÃO DE RECURSOS ADMINISTRATIVOS\nDesignação: Exma. Mesa\nEndereço: Largo Trindade Coelho\nCódigo postal: 1200-470\nLocalidade: Lisboa\nTelefone: 213235000\nFax: 213235013\nEndereço eletrónico: dicom.nabse@scml.pt\nPrazo de interposição do recurso: 10 dias\n\n28 - IDENTIFICAÇÃO DO(S) AUTOR(ES) DE ANÚNCIO\nNome: Vanda Simão\nCargo: Diretora da Direção de Compras\n\n29 - ALTERAÇÃO\nMotivo da Alteração: Correção pelo adquirente\nIdentificador da Versão do Anúncio a Alterar: e51c2404-88cf-4ec0-9755-9e78d9e4c36b-01\nIdentificador das Secções Alteradas do Anúncio Anterior: Condições de Apresentação\nDescrição das Alterações: Modificação do prazo para a apresentação de propostas\nAlteração dos Documentos do Concurso: Não\n419460537",
    "nipc": "500745471",
    "distrito": "Lisboa",
    "concelho": "Lisboa",
    "freguesia": "Freguesia de Misericórdia",
    "site": "http://www.scml.pt/",
    "email": "dicom.nabse@scml.pt",
    "designacao_contrato": "Aquisição de serviços de Auxiliares de Ação Médica",
    "descricao": "Aquisição de serviços de Auxiliares de Ação Médica",
    "preco_base": "712.466,00 EUR",
    "prazo_execucao": "24 MESES",
    "prazo_apresentacao_propostas": "18-09-2025 17:00",
    "fundos_eu": "Não",
    "plataforma_eletronica": "ACIN",
    "url_procedimento": "https://www.acingov.pt",
    "autor_nome": "Vanda Simão",
    "autor_cargo": "Diretora da Direção de Compras"
  },
  {
    "numero_procedimento": "N/A",
    "entidade": "Itecons - Instituto de Investigação e Desenvolvimento Tecnológico para a Construção, Energia, Ambiente e Sustentabilidade",
    "link": "https://diariodarepublica.pt/dr/detalhe/contrato-publico/22641-933115850",
    "detalhes_completos": "1 - IDENTIFICAÇÃO E CONTACTOS DA ENTIDADE ADJUDICANTE\nDesignação da entidade adjudicante: Itecons - Instituto de Investigação e Desenvolvimento Tecnológico para a Construção, Energia, Ambiente e Sustentabilidade\nNIPC: 507487648\nServiço/Órgão/Pessoa de contacto: Beatriz Porto\nEndereço: Rua Pedro Hispano, s/n\nCódigo postal: 3030-289\nLocalidade: Coimbra\nPaís: Portugal\nNUT III: PT16E\nDistrito: Coimbra\nConcelho: Coimbra\nFreguesia: Freguesia de Santo António dos Olivais\nTelefone: 239798949\nFax: 239798949\nEndereço da Entidade (URL): www.itecons.uc.pt\nEndereço Eletrónico: itecons@itecons.uc.pt\neDelivery Gateway (URL): https://www.acingov.pt\nFunção da Organização: Adquirente\nNorma jurídica da Entidade Adjudicante: Organismo de direito público\nÁrea de atividade da Autoridade Adjudicante: Serviços públicos das administrações públicas\n\n2 - JORNAL OFICIAL DA UNIÃO EUROPEIA\nO procedimento a que este anúncio diz respeito também é publicitado no Jornal Oficial da União Europeia? Sim\n\n3 - AVISO\nModelo de Anúncio: Concurso público\nData de Envio do Anúncio: 22-08-2025\n\n5 - PROCESSO\nTipo de Procedimento: Concurso público\nPreço base do procedimento: Sim\nValor do preço base do procedimento: 460.000,00 EUR\nProcedimento com lotes? Não\n\n6 - OBJETO DO CONTRATO\nNúmero de referência interna: CPI/4/2025\nDesignação do contrato: Fornecimento e instalação de Sistema composto por dois atuadores dinâmicos de 100kN\nDescrição: Fornecimento e instalação de Sistema composto por dois atuadores dinâmicos de 100kN\nOpções: Não\nTipo de Contrato Principal: Aquisição de Bens Móveis\nTipo de Contrato: Aquisição de Bens Móveis\nClassificação CPV (Vocabulário Comum para os Contratos Públicos)\nObjeto principal\nVocabulário Principal: 38000000\nPreço base s/IVA: 460.000,00 EUR\n\n7 - INDICAÇÕES ADICIONAIS\nO contrato envolve aquisição conjunta (satisfação de várias entidades)? Não\nO contrato é adjudicado por uma central de compras? Não\n\n8 - TÉCNICAS\nO concurso destina-se à celebração de um acordo-quadro? Inexistência de acordo-quadro\nÉ utilizado um leilão eletrónico? Não\nÉ adotada uma fase de negociação? Não\nSistema de Aquisição Dinâmico: Inexistência de sistema de aquisição dinâmico\n\n9 - LOCAL DA EXECUÇÃO DO CONTRATO\nLOCAL DA EXECUÇÃO DO CONTRATO (PROCEDIMENTO)\nPaís: Portugal\nNUT III: PT16E\nLocalidade: Freguesia de Santo António dos Olivais\nDistrito: Coimbra\nConcelho: Coimbra\nFreguesia: Freguesia de Santo António dos Olivais\n\n10 - PRAZO DE EXECUÇÃO DO CONTRATO\nPrazo de execução do contrato: 3 MESES\nPrevisão de renovações: Não\n\n11 - FUNDOS EU\nTêm fundos EU? Não\n\n12 - DOCUMENTOS DE HABILITAÇÃO\nHabilitação para o exercício da atividade profissional: Não\n\n13 - CONDIÇÕES DE APRESENTAÇÃO\nPlataforma eletrónica utilizada pela entidade adjudicante: ACIN\nURL para Apresentação: https://www.acingov.pt\nAdmissibilidade da apresentação de propostas variantes: Não autorizado\nPrazo para apresentação das propostas: 21-09-2025 23:59\nPrazo durante o qual os concorrentes são obrigados a manter as respetivas propostas: 66 dias a contar do termo do prazo para a apresentação das propostas\nApresentação de Catálogo Eletrónico: Permitido\nIndicação de Subcontratação na Proposta: Inexistência de indicação de subcontratação\n\n14 - PRESTAÇÃO DE CAUÇÃO\nPrestação de caução: Sim\nPercentagem: 5%\nDescrição da Garantia Exigida: O valor da caução é de 5.00% do preço contratual.\n\n15 - FORNECIMENTO DAS PEÇAS DO CONCURSO, APRESENTAÇÃO DE PEDIDOS DE PARTICIPAÇÃO E APRESENTAÇÃO DAS PROPOSTAS\nLink para acesso às peças do concurso (URL): https://www.acingov.pt/acingovprod/2/zonaPublica/zona_publica_c/donwloadProcedurePiece/OTcwODc5\n\n20 - OUTROS REQUISITOS\nInformação sobre contratos reservados. Aplica-se a contratos reservados (54º-A)? Não\n\n21 - CRITÉRIO DE ADJUDICAÇÃO\nMultifator: Não\nMonofator:\nNome: Preço\n\n24 - CONDIÇÕES DO CONTRATO\nFaturação Eletrónica: Permitido\nObrigação de Subcontratação:\nCódigo da Obrigação de Subcontratação: Não é aplicável nenhuma obrigação de subcontratação.\n\n25 - COMPRA PÚBLICA ESTRATÉGICA\nCompra Pública Estratégica: Inexistência de contratação pública estratégica\n\n26 - INFORMAÇÕES ADICIONAIS\nContrato adequado para PME: Não\nCobertura ACP (Acordo dos Contratos Públicos da Organização Mundial do Comércio): Não\n\n27 - IDENTIFICAÇÃO E CONTACTOS DO ÓRGÃO DE RECURSOS ADMINISTRATIVOS\nDesignação: Presidente da Direção\nEndereço: Rua Pedro Hispano, s/n\nCódigo postal: 3030-289\nLocalidade: Coimbra\nTelefone: 239798949\nFax: \nEndereço eletrónico: procedimentos@itecons.uc.pt\nPrazo de interposição do recurso: 5 dias\n\n28 - IDENTIFICAÇÃO DO(S) AUTOR(ES) DE ANÚNCIO\nNome: António Tadeu\nCargo: Presidente da Direção\n419461193",
    "nipc": "507487648",
    "distrito": "Coimbra",
    "concelho": "Coimbra",
    "freguesia": "Freguesia de Santo António dos Olivais",
    "site": "www.itecons.uc.pt",
    "email": "itecons@itecons.uc.pt",
    "designacao_contrato": "Fornecimento e instalação de Sistema composto por dois atuadores dinâmicos de 100kN",
    "descricao": "Fornecimento e instalação de Sistema composto por dois atuadores dinâmicos de 100kN",
    "preco_base": "460.000,00 EUR",
    "prazo_execucao": "3 MESES",
    "prazo_apresentacao_propostas": "21-09-2025 23:59",
    "fundos_eu": "Não",
    "plataforma_eletronica": "ACIN",
    "url_procedimento": "https://www.acingov.pt",
    "autor_nome": "António Tadeu",
    "autor_cargo": "Presidente da Direção"
  },
  {
    "numero_procedimento": "N/A",
    "entidade": "Autoridade Tributária e Aduaneira",
    "link": "https://diariodarepublica.pt/dr/detalhe/contrato-publico/22642-933115851",
    "detalhes_completos": "1 - IDENTIFICAÇÃO E CONTACTOS DA ENTIDADE ADJUDICANTE\nDesignação da entidade adjudicante: Autoridade Tributária e Aduaneira\nNIPC: 600084779\nEndereço: RUA DA PRATA Nº 1O\nCódigo postal: 1149-027\nLocalidade: Lisboa\nPaís: Portugal\nNUT III: PT170\nDistrito: Lisboa\nConcelho: Lisboa\nFreguesia: Freguesia de Santa Maria Maior - Lisboa\nTelefone: 218812600\nFax: 218812935\nEndereço da Entidade (URL): https://www.portaldasfinancas.gov.pt/\nEndereço Eletrónico: at@at.gov.pt\neDelivery Gateway (URL): https://community.vortal.biz/public/\nFunção da Organização: Adquirente\nNorma jurídica da Entidade Adjudicante: Autoridade da administração central\nÁrea de atividade da Autoridade Adjudicante: Assuntos económicos\n\n2 - JORNAL OFICIAL DA UNIÃO EUROPEIA\nO procedimento a que este anúncio diz respeito também é publicitado no Jornal Oficial da União Europeia? Sim\n\n3 - AVISO\nModelo de Anúncio: Concurso limitado por prévia qualificação\nData de Envio do Anúncio: 22-08-2025\n\n5 - PROCESSO\nTipo de Procedimento: Concurso limitado por prévia qualificação\nPreço base do procedimento: Sim\nValor do preço base do procedimento: 1.195.474,80 EUR\nProcedimento com lotes? Não\n\n6 - OBJETO DO CONTRATO\nNúmero de referência interna: 38/CLPQ/AT/2025\nDesignação do contrato: Aquisição de serviços técnicos de informática para administração da plataforma Weblogic\nDescrição: Aquisição de serviços técnicos de informática para administração da plataforma Weblogic\nOpções: Não\nTipo de Contrato Principal: Aquisição de Serviços\nTipo de Contrato: Aquisição de Serviços\nClassificação CPV (Vocabulário Comum para os Contratos Públicos)\nObjeto principal\nVocabulário Principal: 72253200\nPreço base s/IVA: 1.195.474,80 EUR\n\n7 - INDICAÇÕES ADICIONAIS\nO contrato envolve aquisição conjunta (satisfação de várias entidades)? Não\nO contrato é adjudicado por uma central de compras? Não\n\n8 - TÉCNICAS\nO concurso destina-se à celebração de um acordo-quadro? Inexistência de acordo-quadro\nÉ utilizado um leilão eletrónico? Não\nSistema de Aquisição Dinâmico: Inexistência de sistema de aquisição dinâmico\n\n9 - LOCAL DA EXECUÇÃO DO CONTRATO\nLOCAL DA EXECUÇÃO DO CONTRATO (PROCEDIMENTO)\nPaís: Portugal\nNUT III: PT170\nLocalidade: Lisboa\nDistrito: Lisboa\nConcelho: Lisboa\nFreguesia: Todas\n\n10 - PRAZO DE EXECUÇÃO DO CONTRATO\nPrazo de execução do contrato: 36 MESES\nPrevisão de renovações: Sim\nIndicar número máximo de renovações: 2\nPrazo de renovações diferente do prazo inicial: Não\n\n11 - FUNDOS EU\nTêm fundos EU? Não\n\n12 - DOCUMENTOS DE HABILITAÇÃO\nHabilitação para o exercício da atividade profissional: Não\n\n13 - CONDIÇÕES DE APRESENTAÇÃO\nPlataforma eletrónica utilizada pela entidade adjudicante: VORTAL\nURL para Apresentação: https://community.vortal.biz/public/\nAdmissibilidade da apresentação de propostas variantes: Não autorizado\nPrazo para apresentação das candidaturas: 24-09-2025 17:00\nRequisitos mínimos \nRequisitos mínimos de capacidade técnica: Conforme consta das Peças do Procedimento\nRequisitos mínimos de capacidade financeira: Conforme consta das Peças do Procedimento\nPrazo durante o qual os concorrentes são obrigados a manter as respetivas propostas: 90 dias a contar do termo do prazo para a apresentação das propostas\nApresentação de Catálogo Eletrónico: Permitido\nIndicação de Subcontratação na Proposta: Inexistência de indicação de subcontratação\n\n14 - PRESTAÇÃO DE CAUÇÃO\nPrestação de caução: Sim\nPercentagem: 5%\nDescrição da Garantia Exigida: Conforme consta do Programa de Procedimento\n\n15 - FORNECIMENTO DAS PEÇAS DO CONCURSO, APRESENTAÇÃO DE PEDIDOS DE PARTICIPAÇÃO E APRESENTAÇÃO DAS PROPOSTAS\nLink para acesso às peças do concurso (URL): https://community.vortal.biz/Public/public-tender-documents/YkgwRFdpYTVBQVZQSkptK0FjS2lGRnNhWjhITExOQ3BUVGU4amFlUW5VNmhhckM3QTUrNUNqamJsRndsR1RsV1A0UzJ5aTczeWQ0dDNqUFZYQ2JjekE9PVVkOFBP\n\n20 - OUTROS REQUISITOS\nInformação sobre contratos reservados. Aplica-se a contratos reservados (54º-A)? Não\n\n21 - CRITÉRIO DE ADJUDICAÇÃO\nMultifator: Sim\nFator: \nNome: Preço\nPonderação: 60%\nSubfatores: Não\nFator: \nNome: Qualidade\nPonderação: 40%\nSubfatores: Sim\nSubfatores: \nNome: SE SENIOR\nPonderação : 60%; \nNome: SE JUNIOR\nPonderação : 40%; \n\n24 - CONDIÇÕES DO CONTRATO\nFaturação Eletrónica: Permitido\nObrigação de Subcontratação:\nCódigo da Obrigação de Subcontratação: Não é aplicável nenhuma obrigação de subcontratação.\n\n25 - COMPRA PÚBLICA ESTRATÉGICA\nCompra Pública Estratégica: Inexistência de contratação pública estratégica\n\n26 - INFORMAÇÕES ADICIONAIS\nContrato adequado para PME: Sim\nCobertura ACP (Acordo dos Contratos Públicos da Organização Mundial do Comércio): Não\n\n27 - IDENTIFICAÇÃO E CONTACTOS DO ÓRGÃO DE RECURSOS ADMINISTRATIVOS\nDesignação: Secretária de Estado dos Assuntos Fiscais\nEndereço: Avenida do Infante D Henrique 1\nCódigo postal: 1149-009\nLocalidade: Lisboa\nTelefone: +351 218816800\nFax: +351 218816800\nEndereço eletrónico: seaf@mf.gov.pt\n\n28 - IDENTIFICAÇÃO DO(S) AUTOR(ES) DE ANÚNCIO\nNome: Helena Borges Alves\nCargo: Diretora Geral da AT\n419458829",
    "nipc": "600084779",
    "distrito": "Lisboa",
    "concelho": "Lisboa",
    "freguesia": "Freguesia de Santa Maria Maior - Lisboa",
    "site": "https://www.portaldasfinancas.gov.pt/",
    "email": "at@at.gov.pt",
    "designacao_contrato": "Aquisição de serviços técnicos de informática para administração da plataforma Weblogic",
    "descricao": "Aquisição de serviços técnicos de informática para administração da plataforma Weblogic",
    "preco_base": "1.195.474,80 EUR",
    "prazo_execucao": "36 MESES",
    "prazo_apresentacao_propostas": null,
    "fundos_eu": "Não",
    "plataforma_eletronica": "VORTAL",
    "url_procedimento": "https://community.vortal.biz/public/",
    "autor_nome": "Helena Borges Alves",
    "autor_cargo": "Diretora Geral da AT"
  },
  {
    "numero_procedimento": "N/A",
    "entidade": "Águas do Tejo Atlântico, S.A.",
    "link": "https://diariodarepublica.pt/dr/detalhe/contrato-publico/22647-933115852",
    "detalhes_completos": "1 - IDENTIFICAÇÃO E CONTACTOS DA ENTIDADE ADJUDICANTE\nDesignação da entidade adjudicante: Águas do Tejo Atlântico, S.A.\nNIPC: 514387130\nServiço/Órgão/Pessoa de contacto: Área de Compras e Logística da Tejo Atlântico\nEndereço: Fábrica de Água de Água de Alcântara, Avenida de Ceuta, Lisboa\nCódigo postal: 1300-254\nLocalidade: Lisboa\nPaís: Portugal\nNUT III: PT170\nDistrito: Lisboa\nConcelho: Lisboa\nFreguesia: Freguesia de Campo de Ourique\nTelefone: 351 213107900\nFax: 351 213107901\nEndereço da Entidade (URL): https://www.aguasdotejoatlantico.adp.pt/\nEndereço Eletrónico: compras_contratacao.adta@adp.pt\neDelivery Gateway (URL): https://www.acingov.pt\nFunção da Organização: Adquirente\nSubfunção da Organização: Organização cujo orçamento é utilizado para pagar o contrato; Organização que executa o pagamento; Organização que fornece informações adicionais sobre o processo de adjudicação; Organização que fornece mais informações sobre os prazos dos procedimentos de recurso; Organização que fornece acesso fora de linha aos documentos do concurso; Organização responsável pelo tratamento das propostas; Organização que recebe as propostas; Organização que trata os pedidos de participação; Organização que recebe pedidos de participação; Organização que fornece mais informações sobre os procedimentos de recurso; Organização que assina o contrato\nNorma jurídica da Entidade Adjudicante: Organismo de direito público\nÁrea de atividade da Autoridade Adjudicante: Serviços públicos das administrações públicas\n\n2 - JORNAL OFICIAL DA UNIÃO EUROPEIA\nO procedimento a que este anúncio diz respeito também é publicitado no Jornal Oficial da União Europeia? Sim\n\n3 - AVISO\nModelo de Anúncio: Concurso público\nData de Envio do Anúncio: 22-08-2025\n\n5 - PROCESSO\nTipo de Procedimento: Concurso público\nPreço base do procedimento: Sim\nValor do preço base do procedimento: 600.000,00 EUR\nProcedimento com lotes? Não\n\n6 - OBJETO DO CONTRATO\nNúmero de referência interna: TA_25_125_CI_B_007_DMA\nDesignação do contrato: Fornecimento de peças para bombas SEEPEX\nDescrição: Fornecimento de peças para bombas SEEPEX\nOpções: Não\nTipo de Contrato Principal: Aquisição de Bens Móveis\nTipo de Contrato: Aquisição de Bens Móveis\nClassificação CPV (Vocabulário Comum para os Contratos Públicos)\nObjeto principal\nVocabulário Principal: 42124000\nPreço base s/IVA: 600.000,00 EUR\n\n7 - INDICAÇÕES ADICIONAIS\nO contrato envolve aquisição conjunta (satisfação de várias entidades)? Não\nO contrato é adjudicado por uma central de compras? Não\n\n8 - TÉCNICAS\nO concurso destina-se à celebração de um acordo-quadro? Inexistência de acordo-quadro\nÉ utilizado um leilão eletrónico? Não\nÉ adotada uma fase de negociação? Não\nSistema de Aquisição Dinâmico: Inexistência de sistema de aquisição dinâmico\n\n9 - LOCAL DA EXECUÇÃO DO CONTRATO\nLOCAL DA EXECUÇÃO DO CONTRATO (PROCEDIMENTO)\nPaís: Portugal\nNUT III: PT16B\nLocalidade: Todas na área de concessão da Tejo Atlântico\nDistrito: Leiria\nConcelho: Todos\nFreguesia: Todas\nPaís: Portugal\nNUT III: PT170\nLocalidade: Todas na área de concessão da Tejo Atlântico\nDistrito: Lisboa\nConcelho: Todos\nFreguesia: Todas\n\n10 - PRAZO DE EXECUÇÃO DO CONTRATO\nPrazo de execução do contrato: 2 ANOS\nPrevisão de renovações: Não\n\n11 - FUNDOS EU\nTêm fundos EU? Não\n\n12 - DOCUMENTOS DE HABILITAÇÃO\nHabilitação para o exercício da atividade profissional: Não\n\n13 - CONDIÇÕES DE APRESENTAÇÃO\nPlataforma eletrónica utilizada pela entidade adjudicante: ACIN\nURL para Apresentação: https://www.acingov.pt\nAdmissibilidade da apresentação de propostas variantes: Não autorizado\nPrazo para apresentação das propostas: 23-09-2025 23:59\nPrazo durante o qual os concorrentes são obrigados a manter as respetivas propostas: 180 dias a contar do termo do prazo para a apresentação das propostas\nApresentação de Catálogo Eletrónico: Não autorizado\nIndicação de Subcontratação na Proposta: Inexistência de indicação de subcontratação\n\n14 - PRESTAÇÃO DE CAUÇÃO\nPrestação de caução: Sim\nPercentagem: 5%\nDescrição da Garantia Exigida: O valor da caução é de 5.00% do preço contratual.\n\n15 - FORNECIMENTO DAS PEÇAS DO CONCURSO, APRESENTAÇÃO DE PEDIDOS DE PARTICIPAÇÃO E APRESENTAÇÃO DAS PROPOSTAS\nLink para acesso às peças do concurso (URL): https://www.acingov.pt/acingovprod/2/zonaPublica/zona_publica_c/donwloadProcedurePiece/OTcxMjIz\n\n20 - OUTROS REQUISITOS\nInformação sobre contratos reservados. Aplica-se a contratos reservados (54º-A)? Não\n\n21 - CRITÉRIO DE ADJUDICAÇÃO\nMultifator: Não\nMonofator:\nNome: Preço\n\n24 - CONDIÇÕES DO CONTRATO\nFaturação Eletrónica: Necessário\nObrigação de Subcontratação:\nCódigo da Obrigação de Subcontratação: Não é aplicável nenhuma obrigação de subcontratação.\n\n25 - COMPRA PÚBLICA ESTRATÉGICA\nCompra Pública Estratégica: Inexistência de contratação pública estratégica\n\n26 - INFORMAÇÕES ADICIONAIS\nContrato adequado para PME: Sim\nCobertura ACP (Acordo dos Contratos Públicos da Organização Mundial do Comércio): Não\n\n27 - IDENTIFICAÇÃO E CONTACTOS DO ÓRGÃO DE RECURSOS ADMINISTRATIVOS\nDesignação: Águas do Tejo Atlântico, S.A.\nEndereço: Fábrica de Água de Água de Alcântara, Avenida de Ceuta, Lisboa\nCódigo postal: 1300-254\nLocalidade: Lisboa\nTelefone: 351213107900\nFax: 351213107901\nEndereço eletrónico: compras_contratacao.adta@adp.pt\n\n28 - IDENTIFICAÇÃO DO(S) AUTOR(ES) DE ANÚNCIO\nNome: Nuno Brôco\nCargo: Presidente do Conselho de Administração\n419461671",
    "nipc": "514387130",
    "distrito": "Lisboa",
    "concelho": "Lisboa",
    "freguesia": "Freguesia de Campo de Ourique",
    "site": "https://www.aguasdotejoatlantico.adp.pt/",
    "email": "compras_contratacao.adta@adp.pt",
    "designacao_contrato": "Fornecimento de peças para bombas SEEPEX",
    "descricao": "Fornecimento de peças para bombas SEEPEX",
    "preco_base": "600.000,00 EUR",
    "prazo_execucao": "2 ANOS",
    "prazo_apresentacao_propostas": "23-09-2025 23:59",
    "fundos_eu": "Não",
    "plataforma_eletronica": "ACIN",
    "url_procedimento": "https://www.acingov.pt",
    "autor_nome": "Nuno Brôco",
    "autor_cargo": "Presidente do Conselho de Administração"
  },
  {
    "numero_procedimento": "N/A",
    "entidade": "Infraestruturas de Portugal",
    "link": "https://diariodarepublica.pt/dr/detalhe/contrato-publico/22650-933115853",
    "detalhes_completos": "1 - IDENTIFICAÇÃO E CONTACTOS DA ENTIDADE ADJUDICANTE\nDesignação da entidade adjudicante: Infraestruturas de Portugal\nNIPC: 503933813\nServiço/Órgão/Pessoa de contacto: Direção de Compras e Logística - Departamento de Compras - Edifício 2\nEndereço: Praça da Portagem\nCódigo postal: 2809-013\nLocalidade: Almada\nPaís: Portugal\nNUT III: PT170\nDistrito: Setúbal\nConcelho: Almada\nFreguesia: União das Freguesias de Almada, Cova da Piedade, Pragal e Cacilhas\nTelefone:  212 879 300 \nFax: 21 287 90 00\nEndereço da Entidade (URL): www.infraestruturasdeportugal.pt\nEndereço Eletrónico: dcl@infraestruturasdeportugal.pt\nFunção da Organização: Adquirente\nNorma jurídica da Entidade Adjudicante: Organismo de direito público\nÁrea de atividade da Entidade Adjudicante: Serviços ferroviários\nÁrea de atividade da Autoridade Adjudicante: Serviços públicos das administrações públicas\n\n2 - JORNAL OFICIAL DA UNIÃO EUROPEIA\nO procedimento a que este anúncio diz respeito também é publicitado no Jornal Oficial da União Europeia? Sim\n\n3 - AVISO\nModelo de Anúncio: Concurso público\nData de Envio do Anúncio: 22-08-2025\n\n5 - PROCESSO\nTipo de Procedimento: Concurso público\nPreço base do procedimento: Sim\nValor do preço base do procedimento: 944.300,00 EUR\nProcedimento com lotes? Não\n\n6 - OBJETO DO CONTRATO\nNúmero de referência interna: 10021050\nDesignação do contrato: Aquisição de meias grades de agulha de 3ª a 5ª geração\nDescrição: Aquisição de meias grades de agulha de 3ª a 5ª geração\nOpções: Não\nTipo de Contrato Principal: Aquisição de Bens Móveis\nTipo de Contrato: Aquisição de Bens Móveis\nClassificação CPV (Vocabulário Comum para os Contratos Públicos)\nObjeto principal\nVocabulário Principal: 34946120\nPreço base s/IVA: 944.300,00 EUR\n\n7 - INDICAÇÕES ADICIONAIS\nO contrato envolve aquisição conjunta (satisfação de várias entidades)? Não\nO contrato é adjudicado por uma central de compras? Não\n\n8 - TÉCNICAS\nO concurso destina-se à celebração de um acordo-quadro? Inexistência de acordo-quadro\nÉ utilizado um leilão eletrónico? Não\nÉ adotada uma fase de negociação? Não\nSistema de Aquisição Dinâmico: Inexistência de sistema de aquisição dinâmico\n\n9 - LOCAL DA EXECUÇÃO DO CONTRATO\nLOCAL DA EXECUÇÃO DO CONTRATO (PROCEDIMENTO)\nPaís: Portugal\nNUT III: PT16I\nLocalidade: Entroncamento\nDistrito: Santarém\nConcelho: Entroncamento\nFreguesia: Freguesia de Nossa Senhora de Fátima - Entroncamento\n\n10 - PRAZO DE EXECUÇÃO DO CONTRATO\nPrazo de execução do contrato: 610 DIAS\nPrevisão de renovações: Não\n\n11 - FUNDOS EU\nTêm fundos EU? Não\n\n12 - DOCUMENTOS DE HABILITAÇÃO\nHabilitação para o exercício da atividade profissional: Não\n\n13 - CONDIÇÕES DE APRESENTAÇÃO\nPlataforma eletrónica utilizada pela entidade adjudicante: ANOGOV\nURL para Apresentação: https://www.anogov.com/infraestruturasdeportugal-ip/faces/\nAdmissibilidade da apresentação de propostas variantes: Não autorizado\nPrazo para apresentação das propostas: 02-10-2025 17:00\nPrazo durante o qual os concorrentes são obrigados a manter as respetivas propostas: 120 dias a contar do termo do prazo para a apresentação das propostas\nApresentação de Catálogo Eletrónico: Não autorizado\nIndicação de Subcontratação na Proposta: Inexistência de indicação de subcontratação\n\n14 - PRESTAÇÃO DE CAUÇÃO\nPrestação de caução: Sim\nPercentagem: 5%\nDescrição da Garantia Exigida: 5% do preço contratual\n\n15 - FORNECIMENTO DAS PEÇAS DO CONCURSO, APRESENTAÇÃO DE PEDIDOS DE PARTICIPAÇÃO E APRESENTAÇÃO DAS PROPOSTAS\nLink para acesso às peças do concurso (URL): https://www.anogov.com/infraestruturasdeportugal-ip/faces/app/acessoDocs.jsp?codigoAcesso=ZTn9q0wrmBxcGrO5eaki7r0BrZf8kGuAUV5FwKrGIEAOWZ67dr\n\n20 - OUTROS REQUISITOS\nInformação sobre contratos reservados. Aplica-se a contratos reservados (54º-A)? Não\n\n21 - CRITÉRIO DE ADJUDICAÇÃO\nMultifator: Não\nMonofator:\nNome: Preço\n\n24 - CONDIÇÕES DO CONTRATO\nFaturação Eletrónica: Permitido\nObrigação de Subcontratação:\nCódigo da Obrigação de Subcontratação: Não é aplicável nenhuma obrigação de subcontratação.\n\n25 - COMPRA PÚBLICA ESTRATÉGICA\nCompra Pública Estratégica: Inexistência de contratação pública estratégica\n\n26 - INFORMAÇÕES ADICIONAIS\nContrato adequado para PME: Sim\nCobertura ACP (Acordo dos Contratos Públicos da Organização Mundial do Comércio): Não\n\n27 - IDENTIFICAÇÃO E CONTACTOS DO ÓRGÃO DE RECURSOS ADMINISTRATIVOS\nDesignação: Conselho de Administração Executivo da Infraestruturas de Portugal, S.A.\nEndereço: Praça da Portagem\nCódigo postal: 2809-013\nLocalidade: Almada\nTelefone: 212879000\nFax: \nEndereço eletrónico: compras@infraestruturasdeportugal.pt\n\n28 - IDENTIFICAÇÃO DO(S) AUTOR(ES) DE ANÚNCIO\nNome: Clara Manuela de Carvalho Lourenço\nCargo: Diretora da Direção de Compras e Logística\n419460991",
    "nipc": "503933813",
    "distrito": "Setúbal",
    "concelho": "Almada",
    "freguesia": "União das Freguesias de Almada, Cova da Piedade, Pragal e Cacilhas",
    "site": "www.infraestruturasdeportugal.pt",
    "email": "dcl@infraestruturasdeportugal.pt",
    "designacao_contrato": "Aquisição de meias grades de agulha de 3ª a 5ª geração",
    "descricao": "Aquisição de meias grades de agulha de 3ª a 5ª geração",
    "preco_base": "944.300,00 EUR",
    "prazo_execucao": "610 DIAS",
    "prazo_apresentacao_propostas": "02-10-2025 17:00",
    "fundos_eu": "Não",
    "plataforma_eletronica": "ANOGOV",
    "url_procedimento": "https://www.anogov.com/infraestruturasdeportugal-ip/faces/",
    "autor_nome": "Clara Manuela de Carvalho Lourenço",
    "autor_cargo": "Diretora da Direção de Compras e Logística"
  }
]