[
  {
    "numero_procedimento": "N/A",
    "entidade": "Unidade Local de Saúde Tâmega e Sousa, E.P.E.",
    "link": "https://diariodarepublica.pt/dr/detalhe/contrato-publico/25337-936743753",
    "detalhes_completos": "1 - IDENTIFICAÇÃO E CONTACTOS DA ENTIDADE ADJUDICANTE\nDesignação da entidade adjudicante: Unidade Local de Saúde Tâmega e Sousa, E.P.E.\nNIPC: 508318262\nServiço/Órgão/Pessoa de contacto: Serviço de Compras\nEndereço: Avenida Padre Américo, Nº210\nCódigo postal: 4560-136\nLocalidade: Porto\nPaís: Portugal\nNUT III: PT11C\nDistrito: Porto\nConcelho: Penafiel\nFreguesia: Todas\nTelefone: 255714000\nEndereço da Entidade (URL): www.chtamegasousa.pt\nEndereço Eletrónico: concursos@chts.min-saude.pt\neDelivery Gateway (URL): https://community.vortal.biz/public/\nFunção da Organização: Adquirente\nNorma jurídica da Entidade Adjudicante: Empresa pública\nÁrea de atividade da Autoridade Adjudicante: Saúde\n\n2 - JORNAL OFICIAL DA UNIÃO EUROPEIA\nO procedimento a que este anúncio diz respeito também é publicitado no Jornal Oficial da União Europeia? Não\n\n3 - AVISO\nModelo de Anúncio: Concurso público\nData de Envio do Anúncio: 25-09-2025\n\n5 - PROCESSO\nTipo de Procedimento: Concurso público\nPreço base do procedimento: Sim\nValor do preço base do procedimento: 21.000,00 EUR\nProcedimento com lotes? Não\n\n6 - OBJETO DO CONTRATO\nNúmero de referência interna: 07/CP.25.1859\nDesignação do contrato: Aquisição de Equipamentos Rede de Frio para os CSP\nDescrição: Aquisição de Equipamentos Rede de Frio para os CSP\nTipo de Contrato Principal: Aquisição de Bens Móveis\nTipo de Contrato: Aquisição de Bens Móveis\nClassificação CPV (Vocabulário Comum para os Contratos Públicos)\nObjeto principal\nVocabulário Principal: 39711100\nPreço base s/IVA: 21.000,00 EUR\n\n7 - INDICAÇÕES ADICIONAIS\nO contrato envolve aquisição conjunta (satisfação de várias entidades)? Não\nO contrato é adjudicado por uma central de compras? Não\n\n8 - TÉCNICAS\nO concurso destina-se à celebração de um acordo-quadro? Inexistência de acordo-quadro\nÉ utilizado um leilão eletrónico? Não\nÉ adotada uma fase de negociação? Não\nSistema de Aquisição Dinâmico: Inexistência de sistema de aquisição dinâmico\n\n9 - LOCAL DA EXECUÇÃO DO CONTRATO\nLOCAL DA EXECUÇÃO DO CONTRATO (PROCEDIMENTO)\nPaís: Portugal\nNUT III: PT11C\nLocalidade: Porto\nDistrito: Porto\nConcelho: Penafiel\nFreguesia: Freguesia de Guilhufe e Urrô\n\n10 - PRAZO DE EXECUÇÃO DO CONTRATO\nPrazo de execução do contrato: 30 DIAS\nPrevisão de renovações: Não\n\n11 - FUNDOS EU\nTêm fundos EU? Não\n\n12 - DOCUMENTOS DE HABILITAÇÃO\nHabilitação para o exercício da atividade profissional: Não\n\n13 - CONDIÇÕES DE APRESENTAÇÃO\nPlataforma eletrónica utilizada pela entidade adjudicante: VORTAL\nURL para Apresentação: https://community.vortal.biz/public/\nAdmissibilidade da apresentação de propostas variantes: Não autorizado\nPrazo para apresentação das propostas: 08-10-2025 17:00\nPrazo durante o qual os concorrentes são obrigados a manter as respetivas propostas: 180 dias a contar do termo do prazo para a apresentação das propostas\nIndicação de Subcontratação na Proposta: Inexistência de indicação de subcontratação\n\n14 - PRESTAÇÃO DE CAUÇÃO\nPrestação de caução: Não\n\n15 - FORNECIMENTO DAS PEÇAS DO CONCURSO, APRESENTAÇÃO DE PEDIDOS DE PARTICIPAÇÃO E APRESENTAÇÃO DAS PROPOSTAS\nLink para acesso às peças do concurso (URL): https://community.vortal.biz/Public/public-tender-documents/aUtkR0YwL3NHY0dPdlhRc2t6allFMTh5QjJlcVFJWmZlZnJzSkZmOXdzblRqUkNMTHFBQmM2cGhMSFZQMVVsQW9Eb3NtRkFHaitEbzZ1czFmVGYvK1E9PUBKMEx5\n\n20 - OUTROS REQUISITOS\nInformação sobre contratos reservados. Aplica-se a contratos reservados (54º-A)? Não\n\n21 - CRITÉRIO DE ADJUDICAÇÃO\nMultifator: Sim\nFator: \nNome: Preço\nPonderação: 70%\nSubfatores: Não\nFator: \nNome: Qualidade\nPonderação: 30%\nSubfatores: Não\n\n24 - CONDIÇÕES DO CONTRATO\nFaturação Eletrónica: Permitido\nObrigação de Subcontratação:\nCódigo da Obrigação de Subcontratação: Não é aplicável nenhuma obrigação de subcontratação.\n\n25 - COMPRA PÚBLICA ESTRATÉGICA\nCompra Pública Estratégica: Inexistência de contratação pública estratégica\n\n26 - INFORMAÇÕES ADICIONAIS\nContrato adequado para PME: Sim\nCobertura ACP (Acordo dos Contratos Públicos da Organização Mundial do Comércio): Não\n\n27 - IDENTIFICAÇÃO E CONTACTOS DO ÓRGÃO DE RECURSOS ADMINISTRATIVOS\nDesignação: Unidade Local de Saúde do Tâmega e Sousa, E.P.E.\nEndereço: Avenida do Hospital Padre Américo, 210\nCódigo postal: 4560-136\nLocalidade: Penafiel\nTelefone: +351 255714000\nFax: +351 255714000\nEndereço eletrónico: administracao@ulsts.min-saude.pt\n\n28 - IDENTIFICAÇÃO DO(S) AUTOR(ES) DE ANÚNCIO\nNome: Unidade Local de Saúde do Tâmega e Sousa, E.P.E\nCargo: Serviço de Compras\n419575185",
    "nipc": "508318262",
    "distrito": "Porto",
    "concelho": "Penafiel",
    "freguesia": "Todas",
    "site": "www.chtamegasousa.pt",
    "email": "concursos@chts.min-saude.pt",
    "designacao_contrato": "Aquisição de Equipamentos Rede de Frio para os CSP",
    "descricao": "Aquisição de Equipamentos Rede de Frio para os CSP",
    "preco_base": "21.000,00 EUR",
    "prazo_execucao": "30 DIAS",
    "prazo_apresentacao_propostas": "08-10-2025 17:00",
    "fundos_eu": "Não",
    "plataforma_eletronica": "VORTAL",
    "url_procedimento": "https://community.vortal.biz/public/",
    "autor_nome": "Unidade Local de Saúde do Tâmega e Sousa, E.P.E",
    "autor_cargo": "Serviço de Compras"
  },
  {
    "numero_procedimento": "N/A",
    "entidade": "Instituto de Informática, I.P.",
    "link": "https://diariodarepublica.pt/dr/detalhe/contrato-publico/25341-936743754",
    "detalhes_completos": "1 - IDENTIFICAÇÃO E CONTACTOS DA ENTIDADE ADJUDICANTE\nDesignação da entidade adjudicante: Instituto de Informática, I.P.\nNIPC: 504322915\nServiço/Órgão/Pessoa de contacto: Área de Contratação Pública\nEndereço: Avenida Professor Dr. Cavaco Silva, n.º 17, Edifício Ciência I\nCódigo postal: 2740-120\nLocalidade: Porto Salvo\nPaís: Portugal\nNUT III: PT170\nDistrito: Lisboa\nConcelho: Oeiras\nFreguesia: Freguesia de Porto Salvo\nTelefone: 214230000\nEndereço da Entidade (URL): http://www.seg-social.pt\nEndereço Eletrónico: ii-contratacao@seg-social.pt\neDelivery Gateway (URL): https://www.acingov.pt\nFunção da Organização: Adquirente\nNorma jurídica da Entidade Adjudicante: Organismo de direito público\nÁrea de atividade da Autoridade Adjudicante: Proteção social\n\n2 - JORNAL OFICIAL DA UNIÃO EUROPEIA\nO procedimento a que este anúncio diz respeito também é publicitado no Jornal Oficial da União Europeia? Sim\n\n3 - AVISO\nModelo de Anúncio: Concurso público\nData de Envio do Anúncio: 23-09-2025\n\n5 - PROCESSO\nTipo de Procedimento: Concurso público\nPreço base do procedimento: Sim\nValor do preço base do procedimento: 607.608,00 EUR\nProcedimento com lotes? Não\n\n6 - OBJETO DO CONTRATO\nNúmero de referência interna: 2325000215\nDesignação do contrato: 2325000215 - Aquisição de serviços de bolsa de horas para gestão de projetos\nDescrição: Aquisição de serviços de bolsa de horas para gestão de projetos\nOpções: Não\nTipo de Contrato Principal: Aquisição de Serviços\nTipo de Contrato: Aquisição de Serviços\nClassificação CPV (Vocabulário Comum para os Contratos Públicos)\nObjeto principal\nVocabulário Principal: 72224000\nPreço base s/IVA: 607.608,00 EUR\n\n7 - INDICAÇÕES ADICIONAIS\nO contrato envolve aquisição conjunta (satisfação de várias entidades)? Não\nO contrato é adjudicado por uma central de compras? Não\n\n8 - TÉCNICAS\nO concurso destina-se à celebração de um acordo-quadro? Inexistência de acordo-quadro\nÉ utilizado um leilão eletrónico? Não\nÉ adotada uma fase de negociação? Não\nSistema de Aquisição Dinâmico: Inexistência de sistema de aquisição dinâmico\n\n9 - LOCAL DA EXECUÇÃO DO CONTRATO\nLOCAL DA EXECUÇÃO DO CONTRATO (PROCEDIMENTO)\nPaís: Portugal\nNUT III: PT170\nLocalidade: Freguesia de Porto Salvo\nDistrito: Lisboa\nConcelho: Oeiras\nFreguesia: Freguesia de Porto Salvo\n\n10 - PRAZO DE EXECUÇÃO DO CONTRATO\nPrazo de execução do contrato: 36 MESES\nPrevisão de renovações: Não\n\n11 - FUNDOS EU\nTêm fundos EU? Não\n\n12 - DOCUMENTOS DE HABILITAÇÃO\nHabilitação para o exercício da atividade profissional: Não\n\n13 - CONDIÇÕES DE APRESENTAÇÃO\nPlataforma eletrónica utilizada pela entidade adjudicante: ACIN\nURL para Apresentação: https://www.acingov.pt\nAdmissibilidade da apresentação de propostas variantes: Não autorizado\nPrazo para apresentação das propostas: 23-10-2025 23:59\nPrazo durante o qual os concorrentes são obrigados a manter as respetivas propostas: 66 dias a contar do termo do prazo para a apresentação das propostas\nApresentação de Catálogo Eletrónico: Não autorizado\nIndicação de Subcontratação na Proposta: Inexistência de indicação de subcontratação\n\n14 - PRESTAÇÃO DE CAUÇÃO\nPrestação de caução: Sim\nPercentagem: 5%\nDescrição da Garantia Exigida: O valor da caução é de 5.00% do preço contratual.\n\n15 - FORNECIMENTO DAS PEÇAS DO CONCURSO, APRESENTAÇÃO DE PEDIDOS DE PARTICIPAÇÃO E APRESENTAÇÃO DAS PROPOSTAS\nLink para acesso às peças do concurso (URL): https://www.acingov.pt/acingovprod/2/zonaPublica/zona_publica_c/donwloadProcedurePiece/OTgwNjI0\n\n20 - OUTROS REQUISITOS\nInformação sobre contratos reservados. Aplica-se a contratos reservados (54º-A)? Não\n\n21 - CRITÉRIO DE ADJUDICAÇÃO\nMultifator: Sim\nFator: \nNome: Preço\nPonderação: 20%\nSubfatores: Não\nFator: \nNome: Outros\nOutro Nome: Mérito técnico da proposta\nPonderação: 40%\nSubfatores: Não\nFator: \nNome: Outros\nOutro Nome: Competência e Experiência Profissional\nPonderação: 40%\nSubfatores: Não\n\n24 - CONDIÇÕES DO CONTRATO\nFaturação Eletrónica: Permitido\nObrigação de Subcontratação:\nCódigo da Obrigação de Subcontratação: Não é aplicável nenhuma obrigação de subcontratação.\n\n25 - COMPRA PÚBLICA ESTRATÉGICA\nCompra Pública Estratégica: Inexistência de contratação pública estratégica\n\n26 - INFORMAÇÕES ADICIONAIS\nContrato adequado para PME: Sim\nCobertura ACP (Acordo dos Contratos Públicos da Organização Mundial do Comércio): Não\n\n27 - IDENTIFICAÇÃO E CONTACTOS DO ÓRGÃO DE RECURSOS ADMINISTRATIVOS\nDesignação: Conselho Diretivo\nEndereço: Avenida Professor Dr. Cavaco Silva, n.º 17, Edifício Ciência I\nCódigo postal: 2740-120\nLocalidade: Porto Salvo\nTelefone: 214230000\nFax: 214230000\nEndereço eletrónico: ii-contratacao@seg-social.pt\nPrazo de interposição do recurso: 5 dias\n\n28 - IDENTIFICAÇÃO DO(S) AUTOR(ES) DE ANÚNCIO\nNome: Helga Patricia Fino da Silva Beirão Paulo\nCargo: Diretora do Departamento de Organização e Gestão de Pessoas\n419568551",
    "nipc": "504322915",
    "distrito": "Lisboa",
    "concelho": "Oeiras",
    "freguesia": "Freguesia de Porto Salvo",
    "site": "http://www.seg-social.pt",
    "email": "ii-contratacao@seg-social.pt",
    "designacao_contrato": "2325000215 - Aquisição de serviços de bolsa de horas para gestão de projetos",
    "descricao": "Aquisição de serviços de bolsa de horas para gestão de projetos",
    "preco_base": "607.608,00 EUR",
    "prazo_execucao": "36 MESES",
    "prazo_apresentacao_propostas": "23-10-2025 23:59",
    "fundos_eu": "Não",
    "plataforma_eletronica": "ACIN",
    "url_procedimento": "https://www.acingov.pt",
    "autor_nome": "Helga Patricia Fino da Silva Beirão Paulo",
    "autor_cargo": "Diretora do Departamento de Organização e Gestão de Pessoas"
  },
  {
    "numero_procedimento": "N/A",
    "entidade": "Instituto de Informática, I.P.",
    "link": "https://diariodarepublica.pt/dr/detalhe/contrato-publico/25342-936743755",
    "detalhes_completos": "1 - IDENTIFICAÇÃO E CONTACTOS DA ENTIDADE ADJUDICANTE\nDesignação da entidade adjudicante: Instituto de Informática, I.P.\nNIPC: 504322915\nServiço/Órgão/Pessoa de contacto: Área de Contratação Pública\nEndereço: Avenida Professor Dr. Cavaco Silva, n.º 17, Edifício Ciência I\nCódigo postal: 2740-120\nLocalidade: Porto Salvo\nPaís: Portugal\nNUT III: PT170\nDistrito: Lisboa\nConcelho: Oeiras\nFreguesia: Freguesia de Porto Salvo\nTelefone: 214230000\nEndereço da Entidade (URL): http://www.seg-social.pt\nEndereço Eletrónico: ii-contratacao@seg-social.pt\neDelivery Gateway (URL): https://www.acingov.pt\nFunção da Organização: Adquirente\nNorma jurídica da Entidade Adjudicante: Organismo de direito público\nÁrea de atividade da Autoridade Adjudicante: Proteção social\n\n2 - JORNAL OFICIAL DA UNIÃO EUROPEIA\nO procedimento a que este anúncio diz respeito também é publicitado no Jornal Oficial da União Europeia? Sim\n\n3 - AVISO\nModelo de Anúncio: Concurso público\nData de Envio do Anúncio: 23-09-2025\n\n5 - PROCESSO\nTipo de Procedimento: Concurso público\nPreço base do procedimento: Sim\nValor do preço base do procedimento: 333.696,00 EUR\nProcedimento com lotes? Não\n\n6 - OBJETO DO CONTRATO\nNúmero de referência interna: 2325000209\nDesignação do contrato: 2325000209 - Aquisição Serviços de Gestão e Administração SAP\nDescrição: 2325000209 - Aquisição Serviços de Gestão e Administração SAP\nOpções: Não\nTipo de Contrato Principal: Aquisição de Serviços\nTipo de Contrato: Aquisição de Serviços\nClassificação CPV (Vocabulário Comum para os Contratos Públicos)\nObjeto principal\nVocabulário Principal: 72590000\nPreço base s/IVA: 333.696,00 EUR\n\n7 - INDICAÇÕES ADICIONAIS\nO contrato envolve aquisição conjunta (satisfação de várias entidades)? Não\nO contrato é adjudicado por uma central de compras? Não\n\n8 - TÉCNICAS\nO concurso destina-se à celebração de um acordo-quadro? Inexistência de acordo-quadro\nÉ utilizado um leilão eletrónico? Não\nÉ adotada uma fase de negociação? Não\nSistema de Aquisição Dinâmico: Inexistência de sistema de aquisição dinâmico\n\n9 - LOCAL DA EXECUÇÃO DO CONTRATO\nLOCAL DA EXECUÇÃO DO CONTRATO (PROCEDIMENTO)\nPaís: Portugal\nNUT III: PT170\nLocalidade: Freguesia de Porto Salvo\nDistrito: Lisboa\nConcelho: Oeiras\nFreguesia: Freguesia de Porto Salvo\n\n10 - PRAZO DE EXECUÇÃO DO CONTRATO\nPrazo de execução do contrato: 36 MESES\nPrevisão de renovações: Não\n\n11 - FUNDOS EU\nTêm fundos EU? Não\n\n12 - DOCUMENTOS DE HABILITAÇÃO\nHabilitação para o exercício da atividade profissional: Não\n\n13 - CONDIÇÕES DE APRESENTAÇÃO\nPlataforma eletrónica utilizada pela entidade adjudicante: ACIN\nURL para Apresentação: https://www.acingov.pt\nAdmissibilidade da apresentação de propostas variantes: Não autorizado\nPrazo para apresentação das propostas: 23-10-2025 23:59\nPrazo durante o qual os concorrentes são obrigados a manter as respetivas propostas: 66 dias a contar do termo do prazo para a apresentação das propostas\nApresentação de Catálogo Eletrónico: Não autorizado\nIndicação de Subcontratação na Proposta: Inexistência de indicação de subcontratação\n\n14 - PRESTAÇÃO DE CAUÇÃO\nPrestação de caução: Sim\nPercentagem: 5%\nDescrição da Garantia Exigida: O valor da caução é de 5.00% do preço contratual.\n\n15 - FORNECIMENTO DAS PEÇAS DO CONCURSO, APRESENTAÇÃO DE PEDIDOS DE PARTICIPAÇÃO E APRESENTAÇÃO DAS PROPOSTAS\nLink para acesso às peças do concurso (URL): https://www.acingov.pt/acingovprod/2/zonaPublica/zona_publica_c/donwloadProcedurePiece/OTgwNTg0\n\n20 - OUTROS REQUISITOS\nInformação sobre contratos reservados. Aplica-se a contratos reservados (54º-A)? Não\n\n21 - CRITÉRIO DE ADJUDICAÇÃO\nMultifator: Sim\nFator: \nNome: Preço\nPonderação: 20%\nSubfatores: Não\nFator: \nNome: Outros\nOutro Nome: Mérito Técnico da proposta\nPonderação: 40%\nSubfatores: Não\nFator: \nNome: Outros\nOutro Nome: Competência e Experiência Profissional\nPonderação: 40%\nSubfatores: Não\n\n24 - CONDIÇÕES DO CONTRATO\nFaturação Eletrónica: Necessário\nObrigação de Subcontratação:\nCódigo da Obrigação de Subcontratação: Não é aplicável nenhuma obrigação de subcontratação.\n\n25 - COMPRA PÚBLICA ESTRATÉGICA\nCompra Pública Estratégica: Inexistência de contratação pública estratégica\n\n26 - INFORMAÇÕES ADICIONAIS\nContrato adequado para PME: Não\nCobertura ACP (Acordo dos Contratos Públicos da Organização Mundial do Comércio): Não\n\n27 - IDENTIFICAÇÃO E CONTACTOS DO ÓRGÃO DE RECURSOS ADMINISTRATIVOS\nDesignação: Conselho Diretivo\nEndereço: Avenida Professor Dr. Cavaco Silva, n.º 17, Edifício Ciência I\nCódigo postal: 2740-120\nLocalidade: Porto Salvo\nTelefone: 214230000\nFax: 214230000\nEndereço eletrónico: ii-contratacao@seg-social.pt\nPrazo de interposição do recurso: 5 dias\n\n28 - IDENTIFICAÇÃO DO(S) AUTOR(ES) DE ANÚNCIO\nNome: Helga Patricia Fino da Silva Beirão Paulo\nCargo: Diretora do Departamento de Organização e Gestão de Pessoas\n419568462",
    "nipc": "504322915",
    "distrito": "Lisboa",
    "concelho": "Oeiras",
    "freguesia": "Freguesia de Porto Salvo",
    "site": "http://www.seg-social.pt",
    "email": "ii-contratacao@seg-social.pt",
    "designacao_contrato": "2325000209 - Aquisição Serviços de Gestão e Administração SAP",
    "descricao": "2325000209 - Aquisição Serviços de Gestão e Administração SAP",
    "preco_base": "333.696,00 EUR",
    "prazo_execucao": "36 MESES",
    "prazo_apresentacao_propostas": "23-10-2025 23:59",
    "fundos_eu": "Não",
    "plataforma_eletronica": "ACIN",
    "url_procedimento": "https://www.acingov.pt",
    "autor_nome": "Helga Patricia Fino da Silva Beirão Paulo",
    "autor_cargo": "Diretora do Departamento de Organização e Gestão de Pessoas"
  },
  {
    "numero_procedimento": "N/A",
    "entidade": "Agrupamento de Escolas de Moimenta da Beira",
    "link": "https://diariodarepublica.pt/dr/detalhe/contrato-publico/25343-936743756",
    "detalhes_completos": "1 - IDENTIFICAÇÃO E CONTACTOS DA ENTIDADE ADJUDICANTE\nDesignação da entidade adjudicante: Agrupamento de Escolas de Moimenta da Beira\nNIPC: 600075648\nEndereço: RUA DOUTOR JOÃO LIMA GOMES, 3\nCódigo postal: 3620-368\nLocalidade: Viseu\nPaís: Portugal\nNUT III: PT11D\nDistrito: Viseu\nConcelho: Moimenta da Beira\nFreguesia: Freguesia de Moimenta da Beira\nTelefone: 254520110\nEndereço da Entidade (URL): https://escolasmoimenta.pt/\nEndereço Eletrónico: hugo.sousa@escolasmoimenta.pt\neDelivery Gateway (URL): https://community.vortal.biz/public/\nFunção da Organização: Adquirente\nNorma jurídica da Entidade Adjudicante: Instituição, órgão ou agência da UE\nÁrea de atividade da Autoridade Adjudicante: Educação\n\n2 - JORNAL OFICIAL DA UNIÃO EUROPEIA\nO procedimento a que este anúncio diz respeito também é publicitado no Jornal Oficial da União Europeia? Não\n\n3 - AVISO\nModelo de Anúncio: Concurso público\nData de Envio do Anúncio: 25-09-2025\n\n5 - PROCESSO\nTipo de Procedimento: Concurso público\nPreço base do procedimento: Sim\nValor do preço base do procedimento: 81.174,48 EUR\nProcedimento com lotes? Não\n\n6 - OBJETO DO CONTRATO\nNúmero de referência interna: 4-CTE-2025(Industrial-Software)\nDesignação do contrato: Aquisição de Software para o Agrupamento de Escolas de Moimenta da Beira, no âmbito dos centros tecnológicos especializados (CTE) na área Industrial\nDescrição: Aquisição de Software para o Agrupamento de Escolas de Moimenta da Beira, no âmbito dos centros tecnológicos especializados (CTE) na área Industrial, apoiada no âmbito do Plano de Recuperação e Resiliência, nos termos do Aviso de Abertura de Concurso (AAC) n.º01/C06-i01.01/2022.\nTipo de Contrato Principal: Aquisição de Bens Móveis\nTipo de Contrato: Aquisição de Bens Móveis\nClassificação CPV (Vocabulário Comum para os Contratos Públicos)\nObjeto principal\nVocabulário Principal: 48190000\nPreço base s/IVA: 81.174,48 EUR\n\n7 - INDICAÇÕES ADICIONAIS\nO contrato envolve aquisição conjunta (satisfação de várias entidades)? Não\nO contrato é adjudicado por uma central de compras? Não\n\n8 - TÉCNICAS\nO concurso destina-se à celebração de um acordo-quadro? Inexistência de acordo-quadro\nÉ utilizado um leilão eletrónico? Não\nÉ adotada uma fase de negociação? Não\nSistema de Aquisição Dinâmico: Inexistência de sistema de aquisição dinâmico\n\n9 - LOCAL DA EXECUÇÃO DO CONTRATO\nLOCAL DA EXECUÇÃO DO CONTRATO (PROCEDIMENTO)\nPaís: Portugal\nNUT III: PT11D\nLocalidade: Viseu\nDistrito: Viseu\nConcelho: Moimenta da Beira\nFreguesia: Todas\n\n10 - PRAZO DE EXECUÇÃO DO CONTRATO\nPrazo de execução do contrato: 45 DIAS\nPrevisão de renovações: Não\n\n11 - FUNDOS EU\nTêm fundos EU? Não\n\n12 - DOCUMENTOS DE HABILITAÇÃO\nHabilitação para o exercício da atividade profissional: Não\n\n13 - CONDIÇÕES DE APRESENTAÇÃO\nPlataforma eletrónica utilizada pela entidade adjudicante: VORTAL\nURL para Apresentação: https://community.vortal.biz/public/\nAdmissibilidade da apresentação de propostas variantes: Não autorizado\nPrazo para apresentação das propostas: 08-10-2025 00:59\nPrazo durante o qual os concorrentes são obrigados a manter as respetivas propostas: 66 dias a contar do termo do prazo para a apresentação das propostas\nIndicação de Subcontratação na Proposta: Inexistência de indicação de subcontratação\n\n14 - PRESTAÇÃO DE CAUÇÃO\nPrestação de caução: Não\n\n15 - FORNECIMENTO DAS PEÇAS DO CONCURSO, APRESENTAÇÃO DE PEDIDOS DE PARTICIPAÇÃO E APRESENTAÇÃO DAS PROPOSTAS\nLink para acesso às peças do concurso (URL): https://community.vortal.biz/Public/public-tender-documents/Q09KU2J2VUpweXc3cWc0eThCbmpjVitKR0VBVEdQVThyWWxvb3FDSWdodGF4NXcwWUM3dUNkUjhNKzFvN2krSVpXZWdkN2lUeXVXUE1pSFByQnBXeFE9PVcmJmJ2\n\n20 - OUTROS REQUISITOS\nInformação sobre contratos reservados. Aplica-se a contratos reservados (54º-A)? Não\n\n21 - CRITÉRIO DE ADJUDICAÇÃO\nMultifator: Sim\nFator: \nNome: Preço\nPonderação: 80%\nSubfatores: Não\nFator: \nNome: Qualidade\nPonderação: 20%\nSubfatores: Sim\nSubfatores: \nNome: Prazo de entrega dos bens\nPonderação : 50%; \nNome: Certificação da empresa\nPonderação : 50%; \n\n24 - CONDIÇÕES DO CONTRATO\nFaturação Eletrónica: Permitido\nObrigação de Subcontratação:\nCódigo da Obrigação de Subcontratação: Não é aplicável nenhuma obrigação de subcontratação.\n\n25 - COMPRA PÚBLICA ESTRATÉGICA\nCompra Pública Estratégica: Inexistência de contratação pública estratégica\n\n26 - INFORMAÇÕES ADICIONAIS\nContrato adequado para PME: Sim\nCobertura ACP (Acordo dos Contratos Públicos da Organização Mundial do Comércio): Não\n\n27 - IDENTIFICAÇÃO E CONTACTOS DO ÓRGÃO DE RECURSOS ADMINISTRATIVOS\nDesignação: Paula Alexandra Casimiro Alves Requeijo\nEndereço: Av. Dr. João Lima Gomes\nCódigo postal: 3620-368\nLocalidade: Moimenta da Beira\nTelefone: +351 254520110\nFax: +351 254520110\nEndereço eletrónico: servicos@escolasmoimenta.pt\n\n28 - IDENTIFICAÇÃO DO(S) AUTOR(ES) DE ANÚNCIO\nNome: Paula da Ascensão Santos Monteiro Fernandes\nCargo: Diretora\n419576676",
    "nipc": "600075648",
    "distrito": "Viseu",
    "concelho": "Moimenta da Beira",
    "freguesia": "Freguesia de Moimenta da Beira",
    "site": "https://escolasmoimenta.pt/",
    "email": "hugo.sousa@escolasmoimenta.pt",
    "designacao_contrato": "Aquisição de Software para o Agrupamento de Escolas de Moimenta da Beira, no âmbito dos centros tecnológicos especializados (CTE) na área Industrial",
    "descricao": "Aquisição de Software para o Agrupamento de Escolas de Moimenta da Beira, no âmbito dos centros tecnológicos especializados (CTE) na área Industrial, apoiada no âmbito do Plano de Recuperação e Resiliência, nos termos do Aviso de Abertura de Concurso (AAC) n.º01/C06-i01.01/2022.",
    "preco_base": "81.174,48 EUR",
    "prazo_execucao": "45 DIAS",
    "prazo_apresentacao_propostas": "08-10-2025 00:59",
    "fundos_eu": "Não",
    "plataforma_eletronica": "VORTAL",
    "url_procedimento": "https://community.vortal.biz/public/",
    "autor_nome": "Paula da Ascensão Santos Monteiro Fernandes",
    "autor_cargo": "Diretora"
  },
  {
    "numero_procedimento": "N/A",
    "entidade": "FUNDAÇÃO D. ANNA DE SOMMER CHAMPALIMAUD E DR CARLOS MONTEZ CHAMPALIMAUD",
    "link": "https://diariodarepublica.pt/dr/detalhe/contrato-publico/25346-936743765",
    "detalhes_completos": "1 - IDENTIFICAÇÃO E CONTACTOS DA ENTIDADE ADJUDICANTE\nDesignação da entidade adjudicante: FUNDAÇÃO D. ANNA DE SOMMER CHAMPALIMAUD E DR CARLOS MONTEZ CHAMPALIMAUD\nNIPC: 507131827\nServiço/Órgão/Pessoa de contacto: José Mário Leite\nEndereço: Avenida de Brasilia\nCódigo postal: 1400-038\nLocalidade: Lisboa\nPaís: Portugal\nNUT III: PT170\nDistrito: Lisboa\nConcelho: Lisboa\nFreguesia: Freguesia de Belém\nTelefone: 210480200\nFax: 210480299\nEndereço da Entidade (URL): https://www.fchampalimaud.org/pt-pt\nEndereço Eletrónico: jose.leite@fundacaochampalimaud.pt\nFunção da Organização: Adquirente\nSubfunção da Organização: Organização que assina o contrato\nNorma jurídica da Entidade Adjudicante: Organização que adjudica um contrato subvencionado por uma autoridade regional\nÁrea de atividade da Autoridade Adjudicante: Saúde\n\n3 - AVISO\nModelo de Anúncio: Concurso público simplificado\nData de Envio do Anúncio: 25-09-2025\n\n5 - PROCESSO\nTipo de Procedimento: Concurso público simplificado\nPreço base do procedimento: Não\nProcedimento com lotes? Não\n\n6 - OBJETO DO CONTRATO\nNúmero de referência interna: FC006/25\nDesignação do contrato: Recuperação da Casa de Pomarchão\nDescrição: Encontros Improváveis do Barroco a Norte - Recuperação da Casa de Pomarchão\nTipo de Contrato Principal: Empreitada de Obras Públicas\nTipo de Contrato: Empreitada de Obras Públicas\nClassificação CPV (Vocabulário Comum para os Contratos Públicos)\nObjeto principal\nVocabulário Principal: 45000000\n\n7 - INDICAÇÕES ADICIONAIS\nO contrato envolve aquisição conjunta (satisfação de várias entidades)? Não\n\n8 - TÉCNICAS\nSistema de Aquisição Dinâmico: Inexistência de sistema de aquisição dinâmico\n\n9 - LOCAL DA EXECUÇÃO DO CONTRATO\nLOCAL DA EXECUÇÃO DO CONTRATO (PROCEDIMENTO)\nPaís: Portugal\nNUT III: PT111\nLocalidade: Arcozelo\nDistrito: Viana do Castelo\nConcelho: Ponte de Lima\nFreguesia: Freguesia de Arcozelo - Ponte de Lima\n\n10 - PRAZO DE EXECUÇÃO DO CONTRATO\nPrazo de execução do contrato: 2 ANOS\nPrevisão de renovações: Não\n\n11 - FUNDOS EU\nTêm fundos EU? Não\n\n12 - DOCUMENTOS DE HABILITAÇÃO\nHabilitação para o exercício da atividade profissional: Não\n\n13 - CONDIÇÕES DE APRESENTAÇÃO\nPlataforma eletrónica utilizada pela entidade adjudicante: ANOGOV\nURL para Apresentação: https://www.anogov.com/op-fchampalimaud/faces/\nAdmissibilidade da apresentação de propostas variantes: Não autorizado\nPrazo para apresentação das propostas: 10-10-2025 23:59\nPrazo durante o qual os concorrentes são obrigados a manter as respetivas propostas: 66 dias a contar do termo do prazo para a apresentação das propostas\nApresentação de Catálogo Eletrónico: Permitido\nIndicação de Subcontratação na Proposta: O(s) subcontratante(s) proposto(s) necessário(s) para cumprir a obrigação de subcontratar uma percentagem mínima do contrato\n\n14 - PRESTAÇÃO DE CAUÇÃO\nPrestação de caução: Não\n\n15 - FORNECIMENTO DAS PEÇAS DO CONCURSO, APRESENTAÇÃO DE PEDIDOS DE PARTICIPAÇÃO E APRESENTAÇÃO DAS PROPOSTAS\nLink para acesso às peças do concurso (URL): https://www.anogov.com/op-fchampalimaud/faces/app/acessoDocs.jsp?codigoAcesso=kvRWepVwNC7FQVpWT0fLLidJLUddS3YHtLjYfTjzqC79yjiCP5\n\n20 - OUTROS REQUISITOS\nInformação sobre contratos reservados. Aplica-se a contratos reservados (54º-A)? Não\n\n21 - CRITÉRIO DE ADJUDICAÇÃO\nMultifator: Sim\nFator: \nNome: Qualidade\nPonderação: 40%\nSubfatores: Não\nFator: \nNome: Preço\nPonderação: 50%\nSubfatores: Não\nFator: \nNome: Outros\nOutro Nome: Tempo de execução\nPonderação: 10%\nSubfatores: Não\n\n24 - CONDIÇÕES DO CONTRATO\nFaturação Eletrónica: Permitido\nObrigação de Subcontratação:\nCódigo da Obrigação de Subcontratação: Não é aplicável nenhuma obrigação de subcontratação.\n\n25 - COMPRA PÚBLICA ESTRATÉGICA\nCompra Pública Estratégica: Inexistência de contratação pública estratégica\n\n26 - INFORMAÇÕES ADICIONAIS\nContrato adequado para PME: Não\nCobertura ACP (Acordo dos Contratos Públicos da Organização Mundial do Comércio): Não\n\n27 - IDENTIFICAÇÃO E CONTACTOS DO ÓRGÃO DE RECURSOS ADMINISTRATIVOS\nDesignação: Conselho de Administração da Fundação Champalimaud\nEndereço: Avenida de Brasilia\nCódigo postal: 1400-038\nLocalidade: Lisboa\nTelefone: 210480200\nFax: \nEndereço eletrónico: jose.leite@fundacaochampalimaud.pt\nPrazo de interposição do recurso: 5 dias\n\n28 - IDENTIFICAÇÃO DO(S) AUTOR(ES) DE ANÚNCIO\nNome: José Mário Leite\nCargo: Secretário Geral\n419580596",
    "nipc": "507131827",
    "distrito": "Lisboa",
    "concelho": "Lisboa",
    "freguesia": "Freguesia de Belém",
    "site": "https://www.fchampalimaud.org/pt-pt",
    "email": "jose.leite@fundacaochampalimaud.pt",
    "designacao_contrato": "Recuperação da Casa de Pomarchão",
    "descricao": "Encontros Improváveis do Barroco a Norte - Recuperação da Casa de Pomarchão",
    "preco_base": null,
    "prazo_execucao": "2 ANOS",
    "prazo_apresentacao_propostas": "10-10-2025 23:59",
    "fundos_eu": "Não",
    "plataforma_eletronica": "ANOGOV",
    "url_procedimento": "https://www.anogov.com/op-fchampalimaud/faces/",
    "autor_nome": "José Mário Leite",
    "autor_cargo": "Secretário Geral"
  },
  {
    "numero_procedimento": "N/A",
    "entidade": "LNEC - Laboratório Nacional de Engenharia Civil,IP",
    "link": "https://diariodarepublica.pt/dr/detalhe/contrato-publico/25347-936743766",
    "detalhes_completos": "1 - IDENTIFICAÇÃO E CONTACTOS DA ENTIDADE ADJUDICANTE\nDesignação da entidade adjudicante: LNEC - Laboratório Nacional de Engenharia Civil,IP\nNIPC: 501389660\nEndereço: Av.  do Brasil, 101\nCódigo postal: 1700-066\nLocalidade: Lisboa\nPaís: Portugal\nNUT III: PT170\nDistrito: Lisboa\nConcelho: Lisboa\nFreguesia: Freguesia de Alvalade - Lisboa\nTelefone: 218443000\nFax: 218443021\nEndereço da Entidade (URL): www.lnec.pt\nEndereço Eletrónico: aprovisionamento@lnec.pt\neDelivery Gateway (URL): https://community.vortal.biz/public/\nFunção da Organização: Adquirente\nNorma jurídica da Entidade Adjudicante: Organismo de direito público\nÁrea de atividade da Autoridade Adjudicante: Serviços públicos das administrações públicas\n\n2 - JORNAL OFICIAL DA UNIÃO EUROPEIA\nO procedimento a que este anúncio diz respeito também é publicitado no Jornal Oficial da União Europeia? Não\n\n3 - AVISO\nModelo de Anúncio: Concurso público\nData de Envio do Anúncio: 25-09-2025\n\n5 - PROCESSO\nTipo de Procedimento: Concurso público\nPreço base do procedimento: Sim\nValor do preço base do procedimento: 74.945,28 EUR\nProcedimento com lotes? Não\n\n6 - OBJETO DO CONTRATO\nNúmero de referência interna: 2305/A07/312\nDesignação do contrato: Fornecimento de consumíveis de higiene para os anos de 2026/2028\nDescrição: Fornecimento de consumíveis de higiene 2026/2028\nTipo de Contrato Principal: Aquisição de Bens Móveis\nTipo de Contrato: Aquisição de Bens Móveis\nClassificação CPV (Vocabulário Comum para os Contratos Públicos)\nObjeto principal\nVocabulário Principal: 33771000\nPreço base s/IVA: 74.945,28 EUR\n\n7 - INDICAÇÕES ADICIONAIS\nO contrato envolve aquisição conjunta (satisfação de várias entidades)? Não\nO contrato é adjudicado por uma central de compras? Não\n\n8 - TÉCNICAS\nO concurso destina-se à celebração de um acordo-quadro? Inexistência de acordo-quadro\nÉ utilizado um leilão eletrónico? Não\nÉ adotada uma fase de negociação? Não\nSistema de Aquisição Dinâmico: Inexistência de sistema de aquisição dinâmico\n\n9 - LOCAL DA EXECUÇÃO DO CONTRATO\nLOCAL DA EXECUÇÃO DO CONTRATO (PROCEDIMENTO)\nPaís: Portugal\nNUT III: PT170\nLocalidade: Lisboa\nDistrito: Lisboa\nConcelho: Lisboa\nFreguesia: Todas\n\n10 - PRAZO DE EXECUÇÃO DO CONTRATO\nPrazo de execução do contrato: 36 MESES\nPrevisão de renovações: Não\n\n11 - FUNDOS EU\nTêm fundos EU? Não\n\n12 - DOCUMENTOS DE HABILITAÇÃO\nHabilitação para o exercício da atividade profissional: Não\n\n13 - CONDIÇÕES DE APRESENTAÇÃO\nPlataforma eletrónica utilizada pela entidade adjudicante: VORTAL\nURL para Apresentação: https://community.vortal.biz/public/\nAdmissibilidade da apresentação de propostas variantes: Não autorizado\nPrazo para apresentação das propostas: 30-09-2025 23:59\nPrazo durante o qual os concorrentes são obrigados a manter as respetivas propostas: 66 dias a contar do termo do prazo para a apresentação das propostas\nIndicação de Subcontratação na Proposta: Inexistência de indicação de subcontratação\n\n14 - PRESTAÇÃO DE CAUÇÃO\nPrestação de caução: Não\n\n15 - FORNECIMENTO DAS PEÇAS DO CONCURSO, APRESENTAÇÃO DE PEDIDOS DE PARTICIPAÇÃO E APRESENTAÇÃO DAS PROPOSTAS\nLink para acesso às peças do concurso (URL): https://community.vortal.biz/Public/public-tender-documents/UmhreHdvQW9Ec3BEY05rOE1uaXJRQ05Qcm9PYWxwTGpERG5aUDBqalpiRWpkamZLZDlIYjIvNnpiU1VnT0dNc3V2ck9PQWtBUllkLzhKeEREakRmUUE9PUEqKCVj\n\n20 - OUTROS REQUISITOS\nInformação sobre contratos reservados. Aplica-se a contratos reservados (54º-A)? Não\n\n21 - CRITÉRIO DE ADJUDICAÇÃO\nMultifator: Não\nMonofator:\nNome: Preço\n\n24 - CONDIÇÕES DO CONTRATO\nFaturação Eletrónica: Permitido\nObrigação de Subcontratação:\nCódigo da Obrigação de Subcontratação: Não é aplicável nenhuma obrigação de subcontratação.\n\n25 - COMPRA PÚBLICA ESTRATÉGICA\nCompra Pública Estratégica: Inexistência de contratação pública estratégica\n\n26 - INFORMAÇÕES ADICIONAIS\nContrato adequado para PME: Sim\nCobertura ACP (Acordo dos Contratos Públicos da Organização Mundial do Comércio): Não\n\n27 - IDENTIFICAÇÃO E CONTACTOS DO ÓRGÃO DE RECURSOS ADMINISTRATIVOS\nDesignação: Conselho Diretivo\nEndereço: Avenida do Brasil, 101\nCódigo postal: 1700-066\nLocalidade: Lisboa\nTelefone: +351 218443214\nFax: +351 218443214\nEndereço eletrónico: aprovisionamento@lnec.pt\n\n28 - IDENTIFICAÇÃO DO(S) AUTOR(ES) DE ANÚNCIO\nNome: Laura Maria Mello Saraiva Caldeira\nCargo: Presidente do Conselho Diretivo\n419575347",
    "nipc": "501389660",
    "distrito": "Lisboa",
    "concelho": "Lisboa",
    "freguesia": "Freguesia de Alvalade - Lisboa",
    "site": "www.lnec.pt",
    "email": "aprovisionamento@lnec.pt",
    "designacao_contrato": "Fornecimento de consumíveis de higiene para os anos de 2026/2028",
    "descricao": "Fornecimento de consumíveis de higiene 2026/2028",
    "preco_base": "74.945,28 EUR",
    "prazo_execucao": "36 MESES",
    "prazo_apresentacao_propostas": "30-09-2025 23:59",
    "fundos_eu": "Não",
    "plataforma_eletronica": "VORTAL",
    "url_procedimento": "https://community.vortal.biz/public/",
    "autor_nome": "Laura Maria Mello Saraiva Caldeira",
    "autor_cargo": "Presidente do Conselho Diretivo"
  },
  {
    "numero_procedimento": "N/A",
    "entidade": "ESTADO-MAIOR-GENERAL DAS FORÇAS ARMADAS",
    "link": "https://diariodarepublica.pt/dr/detalhe/contrato-publico/25351-936743767",
    "detalhes_completos": "1 - IDENTIFICAÇÃO E CONTACTOS DA ENTIDADE ADJUDICANTE\nDesignação da entidade adjudicante: ESTADO-MAIOR-GENERAL DAS FORÇAS ARMADAS\nNIPC: 600010180\nServiço/Órgão/Pessoa de contacto: Direção de Finanças\nEndereço: AVENIDA ILHA DA MADEIRA\nCódigo postal: 1449-004\nLocalidade: Lisboa\nPaís: Portugal\nNUT III: PT170\nDistrito: Lisboa\nConcelho: Lisboa\nFreguesia: Freguesia de Lumiar\nTelefone: 2130100001\nEndereço da Entidade (URL): www.emgfa.pt\nEndereço Eletrónico: DIRFIN_Contratos@emgfa.pt\neDelivery Gateway (URL): https://www.acingov.pt\nFunção da Organização: Adquirente\nNorma jurídica da Entidade Adjudicante: Organismo de direito público\nÁrea de atividade da Autoridade Adjudicante: Serviços públicos das administrações públicas\n\n2 - JORNAL OFICIAL DA UNIÃO EUROPEIA\nO procedimento a que este anúncio diz respeito também é publicitado no Jornal Oficial da União Europeia? Não\n\n3 - AVISO\nModelo de Anúncio: Concurso público\nData de Envio do Anúncio: 25-09-2025\n\n5 - PROCESSO\nTipo de Procedimento: Concurso público\nPreço base do procedimento: Sim\nValor do preço base do procedimento: 47.500,00 EUR\nProcedimento com lotes? Sim\nNº Máx. de Lotes Autorizado: 7\nNúmero máximo de lotes que podem ser adjudicados a um concorrente: 7\n\n6 - OBJETO DO CONTRATO\nNúmero de referência interna: 2025007436\nDesignação do contrato: CP TB20/2025 - TRANSPORTE DE BENS PESSOAIS\nDescrição: CP TB20/2025 - TRANSPORTE DE BENS PESSOAIS\nTipo de Contrato Principal: Aquisição de Serviços\nTipo de Contrato: Aquisição de Serviços\nClassificação CPV (Vocabulário Comum para os Contratos Públicos)\nObjeto principal\nVocabulário Principal: 63521000\nPreço base s/IVA: 47.500,00 EUR\nLotes: \nNº: LOT-0001\nDescrição do Lote: TRANSPORTE DE BENS BELGICA/PORTUGAL\nPreço base s/IVA: 6.000,00 EUR\nClassificação CPV (Vocabulário Comum para os Contratos Públicos)\nObjeto principal\nVocabulário Principal: 63521000\nNº: LOT-0002\nDescrição do Lote: TRANSPORTE DE BENS PORTUGAL/ITALIA\nPreço base s/IVA: 6.000,00 EUR\nClassificação CPV (Vocabulário Comum para os Contratos Públicos)\nObjeto principal\nVocabulário Principal: 63521000\nNº: LOT-0003\nDescrição do Lote: TRANSPORTE DE BENS PORTUGAL/BELGICA\nPreço base s/IVA: 3.000,00 EUR\nClassificação CPV (Vocabulário Comum para os Contratos Públicos)\nObjeto principal\nVocabulário Principal: 63521000\nNº: LOT-0004\nDescrição do Lote: TRANSPORTE DE BENS PORTUGAL/ESTADOS-UNIDOS DA AMERICA\nPreço base s/IVA: 10.000,00 EUR\nClassificação CPV (Vocabulário Comum para os Contratos Públicos)\nObjeto principal\nVocabulário Principal: 63521000\nNº: LOT-0005\nDescrição do Lote: TRANSPORTE DE BENS ESTADOS-UNIDOS DA AMERICA/PORTUGAL\nPreço base s/IVA: 15.000,00 EUR\nClassificação CPV (Vocabulário Comum para os Contratos Públicos)\nObjeto principal\nVocabulário Principal: 63521000\nNº: LOT-0006\nDescrição do Lote: TRANSPORTE DE BENS PORTUGAL/ITALIA\nPreço base s/IVA: 3.500,00 EUR\nClassificação CPV (Vocabulário Comum para os Contratos Públicos)\nObjeto principal\nVocabulário Principal: 63521000\nNº: LOT-0007\nDescrição do Lote: TRANSPORTE DE BENS ITALIA/PORTUGAL\nPreço base s/IVA: 4.000,00 EUR\nClassificação CPV (Vocabulário Comum para os Contratos Públicos)\nObjeto principal\nVocabulário Principal: 63521000\n\n7 - INDICAÇÕES ADICIONAIS\nO contrato envolve aquisição conjunta (satisfação de várias entidades)? Não\nO contrato é adjudicado por uma central de compras? Não\n\n8 - TÉCNICAS\nO concurso destina-se à celebração de um acordo-quadro? Inexistência de acordo-quadro\nÉ utilizado um leilão eletrónico? Não\nÉ adotada uma fase de negociação? Não\nSistema de Aquisição Dinâmico: Inexistência de sistema de aquisição dinâmico\n\n9 - LOCAL DA EXECUÇÃO DO CONTRATO\nLOCAL DA EXECUÇÃO DO CONTRATO (PROCEDIMENTO)\nPaís: Portugal\nNUT III: PT170\nLocalidade: Freguesia de Belém\nDistrito: Lisboa\nConcelho: Lisboa\nFreguesia: Freguesia de Belém\nLOCAL DA EXECUÇÃO DO CONTRATO (LOTE)\nIdentificador do Lote: LOT-0001; LOT-0002; LOT-0003; LOT-0004; LOT-0005; LOT-0006; LOT-0007\nPaís: Portugal\nNUT III: PT170\nLocalidade: Freguesia de Belém\nDistrito: Lisboa\nConcelho: Lisboa\nFreguesia: Freguesia de Belém\n\n10 - PRAZO DE EXECUÇÃO DO CONTRATO\nIdentificador do Lote: LOT-0001; LOT-0002; LOT-0003; LOT-0004; LOT-0005; LOT-0006; LOT-0007\nPrazo de execução do contrato: 60 DIAS\nPrevisão de renovações: Não\n\n11 - FUNDOS EU\nIdentificador do Lote: LOT-0001; LOT-0002; LOT-0003; LOT-0004; LOT-0005; LOT-0006; LOT-0007\nTêm fundos EU? Não\n\n12 - DOCUMENTOS DE HABILITAÇÃO\nHabilitação para o exercício da atividade profissional: Não\n\n13 - CONDIÇÕES DE APRESENTAÇÃO\nPlataforma eletrónica utilizada pela entidade adjudicante: ACIN\nURL para Apresentação: https://www.acingov.pt\nAdmissibilidade da apresentação de propostas variantes: Não autorizado\nPrazo para apresentação das propostas: 07-10-2025 23:59\nPrazo durante o qual os concorrentes são obrigados a manter as respetivas propostas: 88 dias a contar do termo do prazo para a apresentação das propostas\nIndicação de Subcontratação na Proposta: Inexistência de indicação de subcontratação\n\n14 - PRESTAÇÃO DE CAUÇÃO\nPrestação de caução: Não\n\n15 - FORNECIMENTO DAS PEÇAS DO CONCURSO, APRESENTAÇÃO DE PEDIDOS DE PARTICIPAÇÃO E APRESENTAÇÃO DAS PROPOSTAS\nLink para acesso às peças do concurso (URL): https://www.acingov.pt/acingovprod/2/zonaPublica/zona_publica_c/donwloadProcedurePiece/OTgxMjcx\n\n20 - OUTROS REQUISITOS\nIdentificador do Lote: LOT-0001; LOT-0002; LOT-0003; LOT-0004; LOT-0005; LOT-0006; LOT-0007\nInformação sobre contratos reservados. Aplica-se a contratos reservados (54º-A)? Não\n\n21 - CRITÉRIO DE ADJUDICAÇÃO\nO Critério de adjudicação é diferenciado por lote? Não\nMultifator: Não\nMonofator:\nNome: Preço\n\n24 - CONDIÇÕES DO CONTRATO\nIdentificador do Lote: LOT-0001; LOT-0002; LOT-0003; LOT-0004; LOT-0005; LOT-0006; LOT-0007\nFaturação Eletrónica: Permitido\nObrigação de Subcontratação:\nCódigo da Obrigação de Subcontratação: Não é aplicável nenhuma obrigação de subcontratação.\n\n25 - COMPRA PÚBLICA ESTRATÉGICA\nCompra Pública Estratégica: Inexistência de contratação pública estratégica\n\n26 - INFORMAÇÕES ADICIONAIS\nIdentificador do Lote: LOT-0001; LOT-0002; LOT-0003; LOT-0004; LOT-0005; LOT-0006; LOT-0007\nContrato adequado para PME: Sim\nCobertura ACP (Acordo dos Contratos Públicos da Organização Mundial do Comércio): Não\n\n27 - IDENTIFICAÇÃO E CONTACTOS DO ÓRGÃO DE RECURSOS ADMINISTRATIVOS\nDesignação: General Chefe Estado-Maior-General das Forças Armadas\nEndereço: AVENIDA ILHA DA MADEIRA\nCódigo postal: 1449-004\nLocalidade: Lisboa\nTelefone: 213043000\nFax: \nEndereço eletrónico: DIRFIN_Contratos@emgfa.pt\nPrazo de interposição do recurso: 10 dias\n\n28 - IDENTIFICAÇÃO DO(S) AUTOR(ES) DE ANÚNCIO\nNome: Rui Manuel da Silva Pina\nCargo: Diretor de Finanças\n419580369",
    "nipc": "600010180",
    "distrito": "Lisboa",
    "concelho": "Lisboa",
    "freguesia": "Freguesia de Lumiar",
    "site": "www.emgfa.pt",
    "email": "DIRFIN_Contratos@emgfa.pt",
    "designacao_contrato": "CP TB20/2025 - TRANSPORTE DE BENS PESSOAIS",
    "descricao": "CP TB20/2025 - TRANSPORTE DE BENS PESSOAIS",
    "preco_base": "47.500,00 EUR",
    "prazo_execucao": "60 DIAS",
    "prazo_apresentacao_propostas": "07-10-2025 23:59",
    "fundos_eu": "Não",
    "plataforma_eletronica": "ACIN",
    "url_procedimento": "https://www.acingov.pt",
    "autor_nome": "Rui Manuel da Silva Pina",
    "autor_cargo": "Diretor de Finanças"
  },
  {
    "numero_procedimento": "N/A",
    "entidade": "MUNICÍPIO DE ALBUFEIRA",
    "link": "https://diariodarepublica.pt/dr/detalhe/contrato-publico/25335-936770281",
    "detalhes_completos": "1 - IDENTIFICAÇÃO E CONTACTOS DA ENTIDADE ADJUDICANTE\nDesignação da entidade adjudicante: MUNICÍPIO DE ALBUFEIRA\nNIPC: 503539473\nEndereço: R. Município\nCódigo postal: 8201-863\nLocalidade: Faro\nPaís: Portugal\nNUT III: PT150\nDistrito: Faro\nConcelho: Albufeira\nFreguesia: Freguesia de Albufeira e Olhos de Água\nTelefone: 289 599 500\nEndereço da Entidade (URL): www.cm-albufeira.pt\nEndereço Eletrónico: geral@cm-albufeira.pt\neDelivery Gateway (URL): https://community.vortal.biz/public/\nFunção da Organização: Adquirente\nNorma jurídica da Entidade Adjudicante: Organismo de direito público\nÁrea de atividade da Autoridade Adjudicante: Serviços públicos das administrações públicas\n\n2 - JORNAL OFICIAL DA UNIÃO EUROPEIA\nO procedimento a que este anúncio diz respeito também é publicitado no Jornal Oficial da União Europeia? Não\n\n3 - AVISO\nModelo de Anúncio: Concurso público\nData de Envio do Anúncio: 25-09-2025\n\n5 - PROCESSO\nTipo de Procedimento: Concurso público\nPreço base do procedimento: Sim\nValor do preço base do procedimento: 88.958,64 EUR\nProcedimento com lotes? Não\n\n6 - OBJETO DO CONTRATO\nNúmero de referência interna: DPEM-DEEM/2025/83\nDesignação do contrato: Empreitada de alteração de pavimento e melhoria nas instalações sanitárias- Jardim Infância Ferreiras \nDescrição: Empreitada de alteração de pavimento e melhoria nas instalações sanitárias- Jardim Infância Ferreiras \nTipo de Contrato Principal: Empreitada de Obras Públicas\nTipo de Contrato: Empreitada de Obras Públicas\nClassificação CPV (Vocabulário Comum para os Contratos Públicos)\nObjeto principal\nVocabulário Principal: 45262690\nPreço base s/IVA: 88.958,64 EUR\n\n7 - INDICAÇÕES ADICIONAIS\nO contrato envolve aquisição conjunta (satisfação de várias entidades)? Não\nO contrato é adjudicado por uma central de compras? Não\n\n8 - TÉCNICAS\nO concurso destina-se à celebração de um acordo-quadro? Inexistência de acordo-quadro\nÉ utilizado um leilão eletrónico? Não\nÉ adotada uma fase de negociação? Não\nSistema de Aquisição Dinâmico: Inexistência de sistema de aquisição dinâmico\n\n9 - LOCAL DA EXECUÇÃO DO CONTRATO\nLOCAL DA EXECUÇÃO DO CONTRATO (PROCEDIMENTO)\nPaís: Portugal\nNUT III: PT150\nLocalidade: Faro\nDistrito: Faro\nConcelho: Albufeira\nFreguesia: Freguesia de Albufeira e Olhos de Água\n\n10 - PRAZO DE EXECUÇÃO DO CONTRATO\nPrazo de execução do contrato: 60 DIAS\nPrevisão de renovações: Não\n\n11 - FUNDOS EU\nTêm fundos EU? Não\n\n12 - DOCUMENTOS DE HABILITAÇÃO\nHabilitação para o exercício da atividade profissional: Sim\nTipo: Alvará\nDescrição: Alvará emitido pelo Instituto dos Mercados Públicos do Imobiliário e da Construção (IMPIC, I.P.), deve conter as subcategorias e categorias a seguir indicadas:\n- 5.ª Subcategoria (Estuques, pinturas e outros revestimentos) da 1.ª Categoria (Edifícios e património construído), em classe correspondente ao valor global da proposta;\n- 6.ª subcategoria (Carpintarias) da 1ª Categoria, correspondente aos respectivos valores de trabalho, constantes das suas propostas\n\n13 - CONDIÇÕES DE APRESENTAÇÃO\nPlataforma eletrónica utilizada pela entidade adjudicante: VORTAL\nURL para Apresentação: https://community.vortal.biz/public/\nAdmissibilidade da apresentação de propostas variantes: Não autorizado\nPrazo para apresentação das propostas: 01-10-2025 23:59\nPrazo durante o qual os concorrentes são obrigados a manter as respetivas propostas: 66 dias a contar do termo do prazo para a apresentação das propostas\nIndicação de Subcontratação na Proposta: Inexistência de indicação de subcontratação\n\n14 - PRESTAÇÃO DE CAUÇÃO\nPrestação de caução: Não\n\n15 - FORNECIMENTO DAS PEÇAS DO CONCURSO, APRESENTAÇÃO DE PEDIDOS DE PARTICIPAÇÃO E APRESENTAÇÃO DAS PROPOSTAS\nLink para acesso às peças do concurso (URL): https://community.vortal.biz/Public/public-tender-documents/bXplR3JjVXQyeUIrcEFFbENpdlhFRU54ZjBvazFvaEVaYVhJZTFmUnQ0WUdlN3V6VVRQQUxDZTNuRDRaSFlldlZaQmU1OUVNT21ieHNpODlybTFjQ2c9PTMwYk9X\n\n20 - OUTROS REQUISITOS\nInformação sobre contratos reservados. Aplica-se a contratos reservados (54º-A)? Não\n\n21 - CRITÉRIO DE ADJUDICAÇÃO\nMultifator: Não\nMonofator:\nNome: Outros\nOutro nome: Preço\n\n24 - CONDIÇÕES DO CONTRATO\nFaturação Eletrónica: Permitido\nObrigação de Subcontratação:\nCódigo da Obrigação de Subcontratação: Não é aplicável nenhuma obrigação de subcontratação.\n\n25 - COMPRA PÚBLICA ESTRATÉGICA\nCompra Pública Estratégica: Inexistência de contratação pública estratégica\n\n26 - INFORMAÇÕES ADICIONAIS\nContrato adequado para PME: Sim\nCobertura ACP (Acordo dos Contratos Públicos da Organização Mundial do Comércio): Não\n\n27 - IDENTIFICAÇÃO E CONTACTOS DO ÓRGÃO DE RECURSOS ADMINISTRATIVOS\nDesignação: Município de Albufeira\nEndereço: R. do Município\nCódigo postal: 8200-863\nLocalidade: Albufeira\nTelefone: +351 289599500\nFax: +351 289589558\nEndereço eletrónico: geral@cm-albufeira.pt\n\n28 - IDENTIFICAÇÃO DO(S) AUTOR(ES) DE ANÚNCIO\nNome: João Carlos Martins Rolo\nCargo: Presidente da Câmara Municipal\n419574172",
    "nipc": "503539473",
    "distrito": "Faro",
    "concelho": "Albufeira",
    "freguesia": "Freguesia de Albufeira e Olhos de Água",
    "site": "www.cm-albufeira.pt",
    "email": "geral@cm-albufeira.pt",
    "designacao_contrato": "Empreitada de alteração de pavimento e melhoria nas instalações sanitárias- Jardim Infância Ferreiras",
    "descricao": "Empreitada de alteração de pavimento e melhoria nas instalações sanitárias- Jardim Infância Ferreiras",
    "preco_base": "88.958,64 EUR",
    "prazo_execucao": "60 DIAS",
    "prazo_apresentacao_propostas": "01-10-2025 23:59",
    "fundos_eu": "Não",
    "plataforma_eletronica": "VORTAL",
    "url_procedimento": "https://community.vortal.biz/public/",
    "autor_nome": "João Carlos Martins Rolo",
    "autor_cargo": "Presidente da Câmara Municipal"
  },
  {
    "numero_procedimento": "N/A",
    "entidade": "Maiambiente, EM",
    "link": "https://diariodarepublica.pt/dr/detalhe/contrato-publico/25336-936770282",
    "detalhes_completos": "Alteração do Anúncio de procedimento n.º 24571/2025, de 2025-09-17, com o ID 419538881\n\n1 - IDENTIFICAÇÃO E CONTACTOS DA ENTIDADE ADJUDICANTE\nDesignação da entidade adjudicante: Maiambiente, EM\nNIPC: 505060868\nServiço/Órgão/Pessoa de contacto: Unidade de Compras e Aprovisionamento\nEndereço: Rua 5 de Outubro, 359\nCódigo postal: 4475-302\nLocalidade: Maia\nPaís: Portugal\nNUT III: PT11A\nDistrito: Porto\nConcelho: Maia\nFreguesia: Freguesia de Milheirós\nTelefone: 229478130\nFax: 229478139\nEndereço da Entidade (URL): www.maiambiente.pt\nEndereço Eletrónico: daf@maiambiente.pt\neDelivery Gateway (URL): https://www.acingov.pt\nFunção da Organização: Adquirente\nSubfunção da Organização: Organização que recebe as propostas\nNorma jurídica da Entidade Adjudicante: Organismo de direito público\nÁrea de atividade da Autoridade Adjudicante: Serviços públicos das administrações públicas\n\n2 - JORNAL OFICIAL DA UNIÃO EUROPEIA\nO procedimento a que este anúncio diz respeito também é publicitado no Jornal Oficial da União Europeia? Não\n\n3 - AVISO\nModelo de Anúncio: Concurso público\nData de Envio do Anúncio: 25-09-2025\n\n5 - PROCESSO\nTipo de Procedimento: Concurso público\nPreço base do procedimento: Sim\nValor do preço base do procedimento: 47.500,00 EUR\nProcedimento com lotes? Sim\nNº Máx. de Lotes Autorizado: 2\nNúmero máximo de lotes que podem ser adjudicados a um concorrente: 2\n\n6 - OBJETO DO CONTRATO\nNúmero de referência interna: 25/2025\nDesignação do contrato: Aquisição de 2 compactadores\nDescrição: Aquisição de 2 compactadores\nTipo de Contrato Principal: Aquisição de Bens Móveis\nTipo de Contrato: Aquisição de Bens Móveis\nClassificação CPV (Vocabulário Comum para os Contratos Públicos)\nObjeto principal\nVocabulário Principal: 39713300\nPreço base s/IVA: 47.500,00 EUR\nLotes: \nNº: LOT-0001\nDescrição do Lote: Compactador para resíduos volumosos\nPreço base s/IVA: 29.000,00 EUR\nClassificação CPV (Vocabulário Comum para os Contratos Públicos)\nObjeto principal\nVocabulário Principal: 39713300\nNº: LOT-0002\nDescrição do Lote: Compactador monobloco para resíduos reciclávies\nPreço base s/IVA: 18.500,00 EUR\nClassificação CPV (Vocabulário Comum para os Contratos Públicos)\nObjeto principal\nVocabulário Principal: 39713300\n\n7 - INDICAÇÕES ADICIONAIS\nO contrato envolve aquisição conjunta (satisfação de várias entidades)? Não\nO contrato é adjudicado por uma central de compras? Não\n\n8 - TÉCNICAS\nO concurso destina-se à celebração de um acordo-quadro? Inexistência de acordo-quadro\nÉ utilizado um leilão eletrónico? Não\nÉ adotada uma fase de negociação? Não\nSistema de Aquisição Dinâmico: Inexistência de sistema de aquisição dinâmico\n\n9 - LOCAL DA EXECUÇÃO DO CONTRATO\nLOCAL DA EXECUÇÃO DO CONTRATO (PROCEDIMENTO)\nPaís: Portugal\nNUT III: PT11A\nLocalidade: Freguesia de Milheirós\nDistrito: Porto\nConcelho: Maia\nFreguesia: Freguesia de Milheirós\nLOCAL DA EXECUÇÃO DO CONTRATO (LOTE)\nIdentificador do Lote: LOT-0001; LOT-0002\nPaís: Portugal\nNUT III: PT11A\nLocalidade: Freguesia de Milheirós\nDistrito: Porto\nConcelho: Maia\nFreguesia: Freguesia de Milheirós\n\n10 - PRAZO DE EXECUÇÃO DO CONTRATO\nIdentificador do Lote: LOT-0001; LOT-0002\nPrazo de execução do contrato: 90 DIAS\nPrevisão de renovações: Não\n\n11 - FUNDOS EU\nIdentificador do Lote: LOT-0001; LOT-0002\nTêm fundos EU? Não\n\n12 - DOCUMENTOS DE HABILITAÇÃO\nHabilitação para o exercício da atividade profissional: Não\n\n13 - CONDIÇÕES DE APRESENTAÇÃO\nPlataforma eletrónica utilizada pela entidade adjudicante: ACIN\nURL para Apresentação: https://www.acingov.pt\nAdmissibilidade da apresentação de propostas variantes: Não autorizado\nPrazo para apresentação das propostas: 01-10-2025 18:00\nPrazo durante o qual os concorrentes são obrigados a manter as respetivas propostas: 66 dias a contar do termo do prazo para a apresentação das propostas\nIndicação de Subcontratação na Proposta: Inexistência de indicação de subcontratação\n\n14 - PRESTAÇÃO DE CAUÇÃO\nPrestação de caução: Não\n\n15 - FORNECIMENTO DAS PEÇAS DO CONCURSO, APRESENTAÇÃO DE PEDIDOS DE PARTICIPAÇÃO E APRESENTAÇÃO DAS PROPOSTAS\nLink para acesso às peças do concurso (URL): https://www.acingov.pt/acingovprod/2/zonaPublica/zona_publica_c/donwloadProcedurePiece/OTc4MTQx\n\n20 - OUTROS REQUISITOS\nIdentificador do Lote: LOT-0001; LOT-0002\nInformação sobre contratos reservados. Aplica-se a contratos reservados (54º-A)? Não\n\n21 - CRITÉRIO DE ADJUDICAÇÃO\nO Critério de adjudicação é diferenciado por lote? Não\nMultifator: Sim\nFator: \nNome: Outros\nOutro Nome: Fator 1: Fator Preço da Proposta\nPonderação: 60%\nSubfatores: Não\nFator: \nNome: Outros\nOutro Nome: Fator 2: Fator Prazo de Entrega dos Equipamentos\nPonderação: 30%\nSubfatores: Não\nFator: \nNome: Outros\nOutro Nome: Fator 3: Fator Prazo de Garantia dos Equipamentos\nPonderação: 10%\nSubfatores: Não\n\n24 - CONDIÇÕES DO CONTRATO\nIdentificador do Lote: LOT-0001; LOT-0002\nFaturação Eletrónica: Permitido\nObrigação de Subcontratação:\nCódigo da Obrigação de Subcontratação: Não é aplicável nenhuma obrigação de subcontratação.\n\n25 - COMPRA PÚBLICA ESTRATÉGICA\nCompra Pública Estratégica: Inexistência de contratação pública estratégica\n\n26 - INFORMAÇÕES ADICIONAIS\nIdentificador do Lote: LOT-0001; LOT-0002\nContrato adequado para PME: Sim\nCobertura ACP (Acordo dos Contratos Públicos da Organização Mundial do Comércio): Não\n\n27 - IDENTIFICAÇÃO E CONTACTOS DO ÓRGÃO DE RECURSOS ADMINISTRATIVOS\nDesignação: Presidente do Conselho de Administração\nEndereço: Rua 5 de Outubro, 359\nCódigo postal: 4475-302\nLocalidade: Maia\nTelefone: 229478130\nFax: 229478139\nEndereço eletrónico: daf@maiambiente.pt\n\n28 - IDENTIFICAÇÃO DO(S) AUTOR(ES) DE ANÚNCIO\nNome: Marta Moreira de Sá Peneda\nCargo: Presidente do Conselho de Administração\n\n29 - ALTERAÇÃO\nMotivo da Alteração: Correção pelo adquirente\nIdentificador da Versão do Anúncio a Alterar: 6edba994-bbce-409e-a36f-5456ba4b9ef3-01\nIdentificador das Secções Alteradas do Anúncio Anterior: Condições de Apresentação\nDescrição das Alterações: Modificação do prazo para a apresentação de propostas\nAlteração dos Documentos do Concurso: Não\n419579746",
    "nipc": "505060868",
    "distrito": "Porto",
    "concelho": "Maia",
    "freguesia": "Freguesia de Milheirós",
    "site": "www.maiambiente.pt",
    "email": "daf@maiambiente.pt",
    "designacao_contrato": "Aquisição de 2 compactadores",
    "descricao": "Aquisição de 2 compactadores",
    "preco_base": "47.500,00 EUR",
    "prazo_execucao": "90 DIAS",
    "prazo_apresentacao_propostas": "01-10-2025 18:00",
    "fundos_eu": "Não",
    "plataforma_eletronica": "ACIN",
    "url_procedimento": "https://www.acingov.pt",
    "autor_nome": "Marta Moreira de Sá Peneda",
    "autor_cargo": "Presidente do Conselho de Administração"
  },
  {
    "numero_procedimento": "N/A",
    "entidade": "Município de Montalegre",
    "link": "https://diariodarepublica.pt/dr/detalhe/contrato-publico/25338-936770284",
    "detalhes_completos": "1 - IDENTIFICAÇÃO E CONTACTOS DA ENTIDADE ADJUDICANTE\nDesignação da entidade adjudicante: Município de Montalegre\nNIPC: 506149811\nEndereço: Praça do Município de Montalegre\nCódigo postal: 5470-214\nLocalidade: Montalegre \nPaís: Portugal\nNUT III: PT11E\nDistrito: Vila Real\nConcelho: Montalegre\nFreguesia: União das Freguesias de Montalegre e Padroso\nTelefone: 276510200\nFax: 276510201\nEndereço da Entidade (URL): www.cm-montalegre.pt\nEndereço Eletrónico: municipio@cm-montalegre.pt\nFunção da Organização: Adquirente\nNorma jurídica da Entidade Adjudicante: Autoridade local\nÁrea de atividade da Autoridade Adjudicante: Serviços públicos das administrações públicas\n\n2 - JORNAL OFICIAL DA UNIÃO EUROPEIA\nO procedimento a que este anúncio diz respeito também é publicitado no Jornal Oficial da União Europeia? Não\n\n3 - AVISO\nModelo de Anúncio: Concurso público\nData de Envio do Anúncio: 25-09-2025\n\n5 - PROCESSO\nTipo de Procedimento: Concurso público\nPreço base do procedimento: Sim\nValor do preço base do procedimento: 70.065,62 EUR\nProcedimento com lotes? Não\n\n6 - OBJETO DO CONTRATO\nNúmero de referência interna: DOM N.º 82/2025\nDesignação do contrato: Instalação de um miradouro em Parada e a consequente beneficiação do seu caminho de acesso\nDescrição: Instalação de um miradouro em Parada e a consequente beneficiação do seu caminho de acesso\nTipo de Contrato Principal: Empreitada de Obras Públicas\nTipo de Contrato: Empreitada de Obras Públicas\nClassificação CPV (Vocabulário Comum para os Contratos Públicos)\nObjeto principal\nVocabulário Principal: 45233160\nPreço base s/IVA: 70.065,62 EUR\n\n7 - INDICAÇÕES ADICIONAIS\nO contrato envolve aquisição conjunta (satisfação de várias entidades)? Não\nO contrato é adjudicado por uma central de compras? Não\n\n8 - TÉCNICAS\nO concurso destina-se à celebração de um acordo-quadro? Inexistência de acordo-quadro\nÉ utilizado um leilão eletrónico? Não\nÉ adotada uma fase de negociação? Não\nSistema de Aquisição Dinâmico: Inexistência de sistema de aquisição dinâmico\n\n9 - LOCAL DA EXECUÇÃO DO CONTRATO\nLOCAL DA EXECUÇÃO DO CONTRATO (PROCEDIMENTO)\nPaís: Portugal\nNUT III: PT11E\nLocalidade: Parada\nDistrito: Vila Real\nConcelho: Montalegre\nFreguesia: Freguesia de Outeiro - Montalegre\n\n10 - PRAZO DE EXECUÇÃO DO CONTRATO\nPrazo de execução do contrato: 60 DIAS\nPrevisão de renovações: Não\n\n11 - FUNDOS EU\nTêm fundos EU? Não\n\n12 - DOCUMENTOS DE HABILITAÇÃO\nHabilitação para o exercício da atividade profissional: Sim\nTipo: Alvará\nDescrição: 8.ª subcategoria (Calcetamentos) da 2.ª categoria (Vias de comunicação, obras de urbanização e outras infraestruturas)\n\n13 - CONDIÇÕES DE APRESENTAÇÃO\nPlataforma eletrónica utilizada pela entidade adjudicante: COMPRASPT\nURL para Apresentação: https://www.compraspt.com/cpt-cmma/faces/\nAdmissibilidade da apresentação de propostas variantes: Não autorizado\nPrazo para apresentação das propostas: 10-10-2025 23:59\nPrazo durante o qual os concorrentes são obrigados a manter as respetivas propostas: 66 dias a contar do termo do prazo para a apresentação das propostas\nApresentação de Catálogo Eletrónico: Necessário\nIndicação de Subcontratação na Proposta: A parte do contrato que o proponente tenciona subcontratar\n\n14 - PRESTAÇÃO DE CAUÇÃO\nPrestação de caução: Não\n\n15 - FORNECIMENTO DAS PEÇAS DO CONCURSO, APRESENTAÇÃO DE PEDIDOS DE PARTICIPAÇÃO E APRESENTAÇÃO DAS PROPOSTAS\nLink para acesso às peças do concurso (URL): https://www.compraspt.com/cpt-cmma/faces/app/acessoDocs.jsp?codigoAcesso=rYI4WUbsPX670JEHyA1iIqWKmjZXem99I7FNldk4fkSJuxeZ6w\n\n20 - OUTROS REQUISITOS\nInformação sobre contratos reservados. Aplica-se a contratos reservados (54º-A)? Não\n\n21 - CRITÉRIO DE ADJUDICAÇÃO\nMultifator: Não\nMonofator:\nNome: Preço\n\n24 - CONDIÇÕES DO CONTRATO\nFaturação Eletrónica: Permitido\nObrigação de Subcontratação:\nCódigo da Obrigação de Subcontratação: Não é aplicável nenhuma obrigação de subcontratação.\n\n25 - COMPRA PÚBLICA ESTRATÉGICA\nCompra Pública Estratégica: Inexistência de contratação pública estratégica\n\n26 - INFORMAÇÕES ADICIONAIS\nContrato adequado para PME: Sim\nCobertura ACP (Acordo dos Contratos Públicos da Organização Mundial do Comércio): Não\n\n27 - IDENTIFICAÇÃO E CONTACTOS DO ÓRGÃO DE RECURSOS ADMINISTRATIVOS\nDesignação: TAF Mirandela\nEndereço: Rua da República\nCódigo postal: 5370-347\nLocalidade: Mirandela\nEndereço eletrónico: mirandela.taf@tribunais.org.pt\n\n28 - IDENTIFICAÇÃO DO(S) AUTOR(ES) DE ANÚNCIO\nNome: Maria de Fátima Pereira Fernandes Alves\nCargo: Presidente da Câmara\n419579202",
    "nipc": "506149811",
    "distrito": "Vila Real",
    "concelho": "Montalegre",
    "freguesia": "União das Freguesias de Montalegre e Padroso",
    "site": "www.cm-montalegre.pt",
    "email": "municipio@cm-montalegre.pt",
    "designacao_contrato": "Instalação de um miradouro em Parada e a consequente beneficiação do seu caminho de acesso",
    "descricao": "Instalação de um miradouro em Parada e a consequente beneficiação do seu caminho de acesso",
    "preco_base": "70.065,62 EUR",
    "prazo_execucao": "60 DIAS",
    "prazo_apresentacao_propostas": "10-10-2025 23:59",
    "fundos_eu": "Não",
    "plataforma_eletronica": "COMPRASPT",
    "url_procedimento": "https://www.compraspt.com/cpt-cmma/faces/",
    "autor_nome": "Maria de Fátima Pereira Fernandes Alves",
    "autor_cargo": "Presidente da Câmara"
  },
  {
    "numero_procedimento": "N/A",
    "entidade": "Lisboa SRU",
    "link": "https://diariodarepublica.pt/dr/detalhe/contrato-publico/25339-936770285",
    "detalhes_completos": "1 - IDENTIFICAÇÃO E CONTACTOS DA ENTIDADE ADJUDICANTE\nDesignação da entidade adjudicante: Lisboa SRU\nNIPC: 507023129\nEndereço: Praça do Município, 31 ¿ 2.º/4.º Piso\nCódigo postal: 1100-365\nLocalidade: Lisboa\nPaís: Portugal\nNUT III: PT170\nDistrito: Lisboa\nConcelho: Lisboa\nFreguesia: Freguesia de Santa Maria Maior - Lisboa\nTelefone: 218847030\nFax: 2188470030\nEndereço da Entidade (URL): https://www.lisboaocidentalsru.pt\nEndereço Eletrónico: compras.publicas@lisboaocidentalsru.pt\nFunção da Organização: Adquirente\nNorma jurídica da Entidade Adjudicante: Organismo de direito público, controlado por uma autoridade da administração central\nÁrea de atividade da Autoridade Adjudicante: Serviços públicos das administrações públicas\n\n2 - JORNAL OFICIAL DA UNIÃO EUROPEIA\nO procedimento a que este anúncio diz respeito também é publicitado no Jornal Oficial da União Europeia? Sim\n\n3 - AVISO\nModelo de Anúncio: Concurso público\nData de Envio do Anúncio: 23-09-2025\n\n5 - PROCESSO\nTipo de Procedimento: Concurso público\nPreço base do procedimento: Sim\nValor do preço base do procedimento: 7.050.000,00 EUR\nProcedimento com lotes? Não\n\n6 - OBJETO DO CONTRATO\nNúmero de referência interna: SRU20250000486\nDesignação do contrato: Empreitada de Reabilitação do Palacete dos Marqueses de Pombal para Adaptação às Instalações do Espaço Atlântida Centro de Estudos da História da Leitura\nDescrição: Empreitada de Reabilitação do Palacete dos Marqueses de Pombal para Adaptação às Instalações do Espaço Atlântida Centro de Estudos da História da Leitura\nOpções: Não\nTipo de Contrato Principal: Empreitada de Obras Públicas\nTipo de Contrato: Empreitada de Obras Públicas\nClassificação CPV (Vocabulário Comum para os Contratos Públicos)\nObjeto principal\nVocabulário Principal: 45222000\nPreço base s/IVA: 7.050.000,00 EUR\n\n7 - INDICAÇÕES ADICIONAIS\nO contrato envolve aquisição conjunta (satisfação de várias entidades)? Não\nO contrato é adjudicado por uma central de compras? Não\n\n8 - TÉCNICAS\nO concurso destina-se à celebração de um acordo-quadro? Inexistência de acordo-quadro\nÉ utilizado um leilão eletrónico? Não\nÉ adotada uma fase de negociação? Não\nSistema de Aquisição Dinâmico: Inexistência de sistema de aquisição dinâmico\n\n9 - LOCAL DA EXECUÇÃO DO CONTRATO\nLOCAL DA EXECUÇÃO DO CONTRATO (PROCEDIMENTO)\nPaís: Portugal\nNUT III: PT170\nLocalidade: Lisboa\nDistrito: Lisboa\nConcelho: Lisboa\nFreguesia: Freguesia da Estrela\n\n10 - PRAZO DE EXECUÇÃO DO CONTRATO\nPrazo de execução do contrato: 1080 DIAS\nPrevisão de renovações: Não\n\n11 - FUNDOS EU\nTêm fundos EU? Não\n\n12 - DOCUMENTOS DE HABILITAÇÃO\nHabilitação para o exercício da atividade profissional: Sim\nTipo: Alvará\nDescrição: De acordo com as peças do procedimento\n\n13 - CONDIÇÕES DE APRESENTAÇÃO\nPlataforma eletrónica utilizada pela entidade adjudicante: ANOGOV\nURL para Apresentação: https://www.anogov.com/lisboaocidental-sru/faces/\nAdmissibilidade da apresentação de propostas variantes: Não autorizado\nPrazo para apresentação das propostas: 23-10-2025 17:00\nPrazo durante o qual os concorrentes são obrigados a manter as respetivas propostas: 120 dias a contar do termo do prazo para a apresentação das propostas\nApresentação de Catálogo Eletrónico: Não autorizado\nIndicação de Subcontratação na Proposta: O(s) subcontratante(s) proposto(s) necessário(s) para cumprir a obrigação de subcontratar uma percentagem mínima do contrato\n\n14 - PRESTAÇÃO DE CAUÇÃO\nPrestação de caução: Sim\nPercentagem: 5%\nDescrição da Garantia Exigida: De acordo com as peças do procedimento\n\n15 - FORNECIMENTO DAS PEÇAS DO CONCURSO, APRESENTAÇÃO DE PEDIDOS DE PARTICIPAÇÃO E APRESENTAÇÃO DAS PROPOSTAS\nLink para acesso às peças do concurso (URL): https://www.anogov.com/lisboaocidental-sru/faces/app/acessoDocs.jsp?codigoAcesso=gIOI118vR6Md0BYFFGXQqlEM2xY0ZQjHIbMTyLk2gnoC2XWvaV\n\n20 - OUTROS REQUISITOS\nInformação sobre contratos reservados. Aplica-se a contratos reservados (54º-A)? Não\n\n21 - CRITÉRIO DE ADJUDICAÇÃO\nMultifator: Sim\nFator: \nNome: Preço\nPonderação: 90%\nSubfatores: Não\nFator: \nNome: Qualidade\nPonderação: 10%\nSubfatores: Não\n\n24 - CONDIÇÕES DO CONTRATO\nFaturação Eletrónica: Permitido\nObrigação de Subcontratação:\nCódigo da Obrigação de Subcontratação: Não é aplicável nenhuma obrigação de subcontratação.\n\n25 - COMPRA PÚBLICA ESTRATÉGICA\nCompra Pública Estratégica: Inexistência de contratação pública estratégica\n\n26 - INFORMAÇÕES ADICIONAIS\nContrato adequado para PME: Sim\nCobertura ACP (Acordo dos Contratos Públicos da Organização Mundial do Comércio): Não\n\n27 - IDENTIFICAÇÃO E CONTACTOS DO ÓRGÃO DE RECURSOS ADMINISTRATIVOS\nDesignação: Lisboa Ocidental SRU EM S.A\nEndereço: Praça do Município 31 2º\nCódigo postal: 1100-365\nLocalidade: Lisboa\nEndereço eletrónico: geral@lisboasru.pt\n\n28 - IDENTIFICAÇÃO DO(S) AUTOR(ES) DE ANÚNCIO\nNome: Luis Santos\nCargo: Assistente Técnico\n419566997",
    "nipc": "507023129",
    "distrito": "Lisboa",
    "concelho": "Lisboa",
    "freguesia": "Freguesia de Santa Maria Maior - Lisboa",
    "site": "https://www.lisboaocidentalsru.pt",
    "email": "compras.publicas@lisboaocidentalsru.pt",
    "designacao_contrato": "Empreitada de Reabilitação do Palacete dos Marqueses de Pombal para Adaptação às Instalações do Espaço Atlântida Centro de Estudos da História da Leitura",
    "descricao": "Empreitada de Reabilitação do Palacete dos Marqueses de Pombal para Adaptação às Instalações do Espaço Atlântida Centro de Estudos da História da Leitura",
    "preco_base": "7.050.000,00 EUR",
    "prazo_execucao": "1080 DIAS",
    "prazo_apresentacao_propostas": "23-10-2025 17:00",
    "fundos_eu": "Não",
    "plataforma_eletronica": "ANOGOV",
    "url_procedimento": "https://www.anogov.com/lisboaocidental-sru/faces/",
    "autor_nome": "Luis Santos",
    "autor_cargo": "Assistente Técnico"
  },
  {
    "numero_procedimento": "N/A",
    "entidade": "Secretaria-Geral do Min. dos Negócios Estrangeiros",
    "link": "https://diariodarepublica.pt/dr/detalhe/contrato-publico/25340-936770286",
    "detalhes_completos": "1 - IDENTIFICAÇÃO E CONTACTOS DA ENTIDADE ADJUDICANTE\nDesignação da entidade adjudicante: Secretaria-Geral do Min. dos Negócios Estrangeiros\nNIPC: 600014576\nEndereço: Palácio das Necessidades, Largo do Rilvas\nCódigo postal: 1399-030\nLocalidade: Lisboa\nPaís: Portugal\nNUT III: PT170\nDistrito: Lisboa\nConcelho: Lisboa\nFreguesia: Freguesia da Estrela\nTelefone: 213946000\nFax: 213946070\nEndereço da Entidade (URL): www.mne.gov.pt\nEndereço Eletrónico: umc@mne.pt\neDelivery Gateway (URL): https://community.vortal.biz/public/\nFunção da Organização: Adquirente\nNorma jurídica da Entidade Adjudicante: Autoridade da administração central\nÁrea de atividade da Autoridade Adjudicante: Serviços públicos das administrações públicas\n\n2 - JORNAL OFICIAL DA UNIÃO EUROPEIA\nO procedimento a que este anúncio diz respeito também é publicitado no Jornal Oficial da União Europeia? Sim\n\n3 - AVISO\nModelo de Anúncio: Concurso público\nData de Envio do Anúncio: 23-09-2025\n\n5 - PROCESSO\nTipo de Procedimento: Concurso público\nPreço base do procedimento: Sim\nValor do preço base do procedimento: 145.152,00 EUR\nProcedimento com lotes? Não\n\n6 - OBJETO DO CONTRATO\nNúmero de referência interna: 216/UMC/2025\nDesignação do contrato: Aquisição de Serviços de Apoio ao Núcleo de Estágios do Instituto Diplomático (IDI)\nDescrição: Aquisição de Serviços de Apoio ao Núcleo de Estágios do Instituto Diplomático (IDI)\nOpções: Não\nTipo de Contrato Principal: Aquisição de Serviços\nTipo de Contrato: Aquisição de Serviços\nClassificação CPV (Vocabulário Comum para os Contratos Públicos)\nObjeto principal\nVocabulário Principal: 71356300\nPreço base s/IVA: 145.152,00 EUR\n\n7 - INDICAÇÕES ADICIONAIS\nO contrato envolve aquisição conjunta (satisfação de várias entidades)? Não\nO contrato é adjudicado por uma central de compras? Não\n\n8 - TÉCNICAS\nO concurso destina-se à celebração de um acordo-quadro? Inexistência de acordo-quadro\nÉ utilizado um leilão eletrónico? Não\nÉ adotada uma fase de negociação? Não\nSistema de Aquisição Dinâmico: Inexistência de sistema de aquisição dinâmico\n\n9 - LOCAL DA EXECUÇÃO DO CONTRATO\nLOCAL DA EXECUÇÃO DO CONTRATO (PROCEDIMENTO)\nPaís: Portugal\nNUT III: PT170\nLocalidade: Lisboa\nDistrito: Lisboa\nConcelho: Lisboa\nFreguesia: Todas\n\n10 - PRAZO DE EXECUÇÃO DO CONTRATO\nPrazo de execução do contrato: 12 MESES\nPrevisão de renovações: Não\n\n11 - FUNDOS EU\nTêm fundos EU? Não\n\n12 - DOCUMENTOS DE HABILITAÇÃO\nHabilitação para o exercício da atividade profissional: Não\n\n13 - CONDIÇÕES DE APRESENTAÇÃO\nPlataforma eletrónica utilizada pela entidade adjudicante: VORTAL\nURL para Apresentação: https://community.vortal.biz/public/\nAdmissibilidade da apresentação de propostas variantes: Não autorizado\nPrazo para apresentação das propostas: 24-10-2025 16:59\nPrazo durante o qual os concorrentes são obrigados a manter as respetivas propostas: 120 dias a contar do termo do prazo para a apresentação das propostas\nApresentação de Catálogo Eletrónico: Não autorizado\nIndicação de Subcontratação na Proposta: Inexistência de indicação de subcontratação\n\n14 - PRESTAÇÃO DE CAUÇÃO\nPrestação de caução: Não\n\n15 - FORNECIMENTO DAS PEÇAS DO CONCURSO, APRESENTAÇÃO DE PEDIDOS DE PARTICIPAÇÃO E APRESENTAÇÃO DAS PROPOSTAS\nLink para acesso às peças do concurso (URL): https://community.vortal.biz/Public/public-tender-documents/bEpZK2lBSWFERTJ6SkxSdVJ0ZmpIQzByWThWVlBWZE10MWU0cENNNVF1eFBkSWdCbjhpdWFUdXlpQ2xhTkJVRjhwR0Z0c1JXemtFenJHTEV0V3ZsY2c9PWlZU1k1\n\n20 - OUTROS REQUISITOS\nInformação sobre contratos reservados. Aplica-se a contratos reservados (54º-A)? Não\n\n21 - CRITÉRIO DE ADJUDICAÇÃO\nMultifator: Sim\nFator: \nNome: Preço\nPonderação: 30%\nSubfatores: Não\nFator: \nNome: Qualidade\nPonderação: 30%\nSubfatores: Não\nFator: \nNome: Qualidade\nPonderação: 40%\nSubfatores: Não\n\n24 - CONDIÇÕES DO CONTRATO\nFaturação Eletrónica: Permitido\nObrigação de Subcontratação:\nCódigo da Obrigação de Subcontratação: Não é aplicável nenhuma obrigação de subcontratação.\n\n25 - COMPRA PÚBLICA ESTRATÉGICA\nCompra Pública Estratégica: Inexistência de contratação pública estratégica\n\n26 - INFORMAÇÕES ADICIONAIS\nContrato adequado para PME: Sim\nCobertura ACP (Acordo dos Contratos Públicos da Organização Mundial do Comércio): Não\n\n27 - IDENTIFICAÇÃO E CONTACTOS DO ÓRGÃO DE RECURSOS ADMINISTRATIVOS\nDesignação: MNE\nEndereço: Palácio das Necessidades Largo do Rilvas\nCódigo postal: 1399-030\nLocalidade: Lisboa\nTelefone: +351 213946000\nFax: +351 213946000\nEndereço eletrónico: umc@mne.pt\n\n28 - IDENTIFICAÇÃO DO(S) AUTOR(ES) DE ANÚNCIO\nNome: MNE\nCargo: DGA\n419569637",
    "nipc": "600014576",
    "distrito": "Lisboa",
    "concelho": "Lisboa",
    "freguesia": "Freguesia da Estrela",
    "site": "www.mne.gov.pt",
    "email": "umc@mne.pt",
    "designacao_contrato": "Aquisição de Serviços de Apoio ao Núcleo de Estágios do Instituto Diplomático (IDI)",
    "descricao": "Aquisição de Serviços de Apoio ao Núcleo de Estágios do Instituto Diplomático (IDI)",
    "preco_base": "145.152,00 EUR",
    "prazo_execucao": "12 MESES",
    "prazo_apresentacao_propostas": "24-10-2025 16:59",
    "fundos_eu": "Não",
    "plataforma_eletronica": "VORTAL",
    "url_procedimento": "https://community.vortal.biz/public/",
    "autor_nome": "MNE",
    "autor_cargo": "DGA"
  },
  {
    "numero_procedimento": "N/A",
    "entidade": "Agrupamento de Escolas de Santo António, Barreiro",
    "link": "https://diariodarepublica.pt/dr/detalhe/contrato-publico/25344-936770307",
    "detalhes_completos": "1 - IDENTIFICAÇÃO E CONTACTOS DA ENTIDADE ADJUDICANTE\nDesignação da entidade adjudicante: Agrupamento de Escolas de Santo António, Barreiro\nNIPC: 600082997\nEndereço: Rua António Aleixo Cidade Sol\nCódigo postal: 2835-511\nLocalidade: Setúbal\nPaís: Portugal\nNUT III: PT170\nDistrito: Setúbal\nConcelho: Barreiro\nFreguesia: União das Freguesias de Barreiro e Lavradio\nTelefone: 212150072\nFax: 212150072\nEndereço da Entidade (URL): https://www.escolasdestantonio.edu.pt/\nEndereço Eletrónico: info@escolasdestantonio.edu.pt\neDelivery Gateway (URL): https://community.vortal.biz/public/\nFunção da Organização: Adquirente\nNorma jurídica da Entidade Adjudicante: Organismo de direito público\nÁrea de atividade da Autoridade Adjudicante: Educação\n\n2 - JORNAL OFICIAL DA UNIÃO EUROPEIA\nO procedimento a que este anúncio diz respeito também é publicitado no Jornal Oficial da União Europeia? Sim\n\n3 - AVISO\nModelo de Anúncio: Concurso público\nData de Envio do Anúncio: 23-09-2025\n\n5 - PROCESSO\nTipo de Procedimento: Concurso público\nPreço base do procedimento: Sim\nValor do preço base do procedimento: 1.068.803,56 EUR\nProcedimento com lotes? Sim\nNº Máx. de Lotes Autorizado: 2\nNúmero máximo de lotes que podem ser adjudicados a um concorrente: 2\n\n6 - OBJETO DO CONTRATO\nNúmero de referência interna: PROCEDIMENTO nº 3/2025\nDesignação do contrato: Aquisição de equipamentos, mobiliário, hardware e software no âmbito do Centro Tecnológico Especializado Informática\nDescrição: Aquisição de equipamentos, mobiliário, hardware e software no âmbito do Centro Tecnológico Especializado Informática do Agrupamento de Escolas de Santo António \nOpções: Não\nTipo de Contrato Principal: Aquisição de Bens Móveis\nTipo de Contrato: Aquisição de Bens Móveis\nClassificação CPV (Vocabulário Comum para os Contratos Públicos)\nObjeto principal\nVocabulário Principal: 30200000\nPreço base s/IVA: 913.050,44 EUR\nObjeto Complementar\nVocabulário Principal: 39160000\nPreço base s/IVA: 155.753,12 EUR\nLotes: \nNº: LOT-0001\nDescrição do Lote: Lote 1 - Equipamento Informático, Software e Hardware\nPreço base s/IVA: 913.050,44 EUR\nClassificação CPV (Vocabulário Comum para os Contratos Públicos)\nObjeto principal\nVocabulário Principal: 30200000\nObjeto Complementar\nVocabulário Principal: 39160000\nNº: LOT-0002\nDescrição do Lote: Lote 2 - Mobiliário Educativo\nPreço base s/IVA: 155.753,12 EUR\nClassificação CPV (Vocabulário Comum para os Contratos Públicos)\nObjeto principal\nVocabulário Principal: 30200000\nObjeto Complementar\nVocabulário Principal: 39160000\n\n7 - INDICAÇÕES ADICIONAIS\nO contrato envolve aquisição conjunta (satisfação de várias entidades)? Não\nO contrato é adjudicado por uma central de compras? Não\n\n8 - TÉCNICAS\nO concurso destina-se à celebração de um acordo-quadro? Inexistência de acordo-quadro\nÉ utilizado um leilão eletrónico? Não\nÉ adotada uma fase de negociação? Não\nSistema de Aquisição Dinâmico: Inexistência de sistema de aquisição dinâmico\n\n9 - LOCAL DA EXECUÇÃO DO CONTRATO\nLOCAL DA EXECUÇÃO DO CONTRATO (PROCEDIMENTO)\nPaís: Portugal\nNUT III: PT170\nLocalidade: Setúbal\nDistrito: Setúbal\nConcelho: Barreiro\nFreguesia: Todas\nLOCAL DA EXECUÇÃO DO CONTRATO (LOTE)\nIdentificador do Lote: LOT-0001; LOT-0002\nPaís: Portugal\nNUT III: PT170\nLocalidade: Setúbal\nDistrito: Setúbal\nConcelho: Barreiro\nFreguesia: Todas\n\n10 - PRAZO DE EXECUÇÃO DO CONTRATO\nIdentificador do Lote: LOT-0001; LOT-0002\nPrazo de execução do contrato: 60 DIAS\nPrevisão de renovações: Não\n\n11 - FUNDOS EU\nIdentificador do Lote: LOT-0001; LOT-0002\nTêm fundos EU? Não\n\n12 - DOCUMENTOS DE HABILITAÇÃO\nHabilitação para o exercício da atividade profissional: Não\n\n13 - CONDIÇÕES DE APRESENTAÇÃO\nPlataforma eletrónica utilizada pela entidade adjudicante: VORTAL\nURL para Apresentação: https://community.vortal.biz/public/\nAdmissibilidade da apresentação de propostas variantes: Não autorizado\nPrazo para apresentação das propostas: 23-10-2025 23:59\nPrazo durante o qual os concorrentes são obrigados a manter as respetivas propostas: 90 dias a contar do termo do prazo para a apresentação das propostas\nApresentação de Catálogo Eletrónico: Permitido\nIndicação de Subcontratação na Proposta: Inexistência de indicação de subcontratação\n\n14 - PRESTAÇÃO DE CAUÇÃO\nPrestação de caução: Sim\nPercentagem: 5%\nDescrição da Garantia Exigida: Conforme peças do procedimento\n\n15 - FORNECIMENTO DAS PEÇAS DO CONCURSO, APRESENTAÇÃO DE PEDIDOS DE PARTICIPAÇÃO E APRESENTAÇÃO DAS PROPOSTAS\nLink para acesso às peças do concurso (URL): https://community.vortal.biz/Public/public-tender-documents/dzRnQlpVZjRaeUllTC9MYnVrcEY4eWlnS3pjcm00YVc2T1VpSFVraGpuRmh4a3NPd2x5R2J1b3Jxb2ZUaHkwdjJ6cUdxMVY0VGl1eTErUTU3Sm5CZVE9PVB0UTVB\n\n20 - OUTROS REQUISITOS\nIdentificador do Lote: LOT-0001; LOT-0002\nInformação sobre contratos reservados. Aplica-se a contratos reservados (54º-A)? Não\n\n21 - CRITÉRIO DE ADJUDICAÇÃO\nO Critério de adjudicação é diferenciado por lote? Não\nMultifator: Sim\nFator: \nNome: Preço\nPonderação: 60%\nSubfatores: Não\nFator: \nNome: Qualidade\nPonderação: 15%\nSubfatores: Não\nFator: \nNome: Qualidade\nPonderação: 10%\nSubfatores: Não\nFator: \nNome: Qualidade\nPonderação: 10%\nSubfatores: Não\nFator: \nNome: Qualidade\nPonderação: 5%\nSubfatores: Não\n\n24 - CONDIÇÕES DO CONTRATO\nIdentificador do Lote: LOT-0001; LOT-0002\nFaturação Eletrónica: Permitido\nObrigação de Subcontratação:\nCódigo da Obrigação de Subcontratação: Não é aplicável nenhuma obrigação de subcontratação.\n\n25 - COMPRA PÚBLICA ESTRATÉGICA\nCompra Pública Estratégica: Redução dos impactos ambientais\nDescrição do Processo de Adjudicação Estratégico: Conforme as peças do procedimento\nCritérios de contratos Públicos Ecológicos: Critérios de contratação pública ecológica nacional\nCategorias da estratégia nacional: Computadores, monitores, tabletes e telemóveis inteligentes\nDiretiva Veículos Não Poluentes: Não\nCritério de Acessibilidade: Os critérios de acessibilidade para as pessoas com deficiência estão incluídos\n\n26 - INFORMAÇÕES ADICIONAIS\nIdentificador do Lote: LOT-0001; LOT-0002\nContrato adequado para PME: Sim\nCobertura ACP (Acordo dos Contratos Públicos da Organização Mundial do Comércio): Não\n\n27 - IDENTIFICAÇÃO E CONTACTOS DO ÓRGÃO DE RECURSOS ADMINISTRATIVOS\nDesignação: Paula Cristina Borges Domingues\nEndereço: Rua António Aleixo\nCódigo postal: 2835-511\nLocalidade: Barreiro\nTelefone: +351 212150072\nFax: +351 212150167\nEndereço eletrónico: info@escolasdestantonio.edu.pt\n\n28 - IDENTIFICAÇÃO DO(S) AUTOR(ES) DE ANÚNCIO\nNome: Paula Cristina Borges Domingues\nCargo: Diretora do AE\n419569718",
    "nipc": "600082997",
    "distrito": "Setúbal",
    "concelho": "Barreiro",
    "freguesia": "União das Freguesias de Barreiro e Lavradio",
    "site": "https://www.escolasdestantonio.edu.pt/",
    "email": "info@escolasdestantonio.edu.pt",
    "designacao_contrato": "Aquisição de equipamentos, mobiliário, hardware e software no âmbito do Centro Tecnológico Especializado Informática",
    "descricao": "Aquisição de equipamentos, mobiliário, hardware e software no âmbito do Centro Tecnológico Especializado Informática do Agrupamento de Escolas de Santo António",
    "preco_base": "913.050,44 EUR",
    "prazo_execucao": "60 DIAS",
    "prazo_apresentacao_propostas": "23-10-2025 23:59",
    "fundos_eu": "Não",
    "plataforma_eletronica": "VORTAL",
    "url_procedimento": "https://community.vortal.biz/public/",
    "autor_nome": "Paula Cristina Borges Domingues",
    "autor_cargo": "Diretora do AE"
  },
  {
    "numero_procedimento": "N/A",
    "entidade": "UNIVERSIDADE DE TRAS-OS-MONTES E ALTO DOURO",
    "link": "https://diariodarepublica.pt/dr/detalhe/contrato-publico/25345-936770308",
    "detalhes_completos": "1 - IDENTIFICAÇÃO E CONTACTOS DA ENTIDADE ADJUDICANTE\nDesignação da entidade adjudicante: UNIVERSIDADE DE TRAS-OS-MONTES E ALTO DOURO\nNIPC: 501345361\nServiço/Órgão/Pessoa de contacto: Universidade de Trás-os-Montes e Alto Douro\nEndereço: Quinta de Prados\nCódigo postal: 5000-801\nLocalidade: Vila Real\nPaís: Portugal\nNUT III: PT11D\nDistrito: Vila Real\nConcelho: Vila Real\nFreguesia: Freguesia de Folhadela\nTelefone: 259350000\nFax: 259350000\nEndereço da Entidade (URL): www.utad.pt\nEndereço Eletrónico: centcompras@utad.pt\nFunção da Organização: Adquirente\nNorma jurídica da Entidade Adjudicante: Organismo de direito público\nÁrea de atividade da Autoridade Adjudicante: Educação\n\n2 - JORNAL OFICIAL DA UNIÃO EUROPEIA\nO procedimento a que este anúncio diz respeito também é publicitado no Jornal Oficial da União Europeia? Sim\n\n3 - AVISO\nModelo de Anúncio: Concurso público\nData de Envio do Anúncio: 23-09-2025\n\n5 - PROCESSO\nTipo de Procedimento: Concurso público\nPreço base do procedimento: Sim\nValor do preço base do procedimento: 257.867,13 EUR\nProcedimento com lotes? Sim\nNº Máx. de Lotes Autorizado: 12\nNúmero máximo de lotes que podem ser adjudicados a um concorrente: 12\n\n6 - OBJETO DO CONTRATO\nNúmero de referência interna: CP_PC 502/2025\nDesignação do contrato: Aquisição de Serviços de Inspeção e Manutenção Preventiva e Corretiva de Equipamento do Hospital Veterinário da UTAD\nDescrição: Aquisição de Serviços de Inspeção e Manutenção Preventiva e Corretiva de Equipamento do Hospital Veterinário da UTAD\nOpções: Não\nTipo de Contrato Principal: Aquisição de Serviços\nTipo de Contrato: Aquisição de Serviços\nClassificação CPV (Vocabulário Comum para os Contratos Públicos)\nObjeto principal\nVocabulário Principal: 50800000\nPreço base s/IVA: 257.867,13 EUR\nLotes: \nNº: LOT-0001\nDescrição do Lote: Equipamento Infusão/Perfusão \nPreço base s/IVA: 11.054,93 EUR\nClassificação CPV (Vocabulário Comum para os Contratos Públicos)\nObjeto principal\nVocabulário Principal: 50800000\nNº: LOT-0002\nDescrição do Lote: Outros Equipamentos Infusão/Perfusão\nPreço base s/IVA: 19.166,77 EUR\nClassificação CPV (Vocabulário Comum para os Contratos Públicos)\nObjeto principal\nVocabulário Principal: 50800000\nNº: LOT-0003\nDescrição do Lote: Equipamento Imagiologia\nPreço base s/IVA: 21.286,34 EUR\nClassificação CPV (Vocabulário Comum para os Contratos Públicos)\nObjeto principal\nVocabulário Principal: 50800000\nNº: LOT-0004\nDescrição do Lote: Equipamento Anestésico e Monitorização Multiparametrica \nPreço base s/IVA: 51.701,07 EUR\nClassificação CPV (Vocabulário Comum para os Contratos Públicos)\nObjeto principal\nVocabulário Principal: 50800000\nNº: LOT-0005\nDescrição do Lote: Equipamento de Esterilização\nPreço base s/IVA: 15.377,84 EUR\nClassificação CPV (Vocabulário Comum para os Contratos Públicos)\nObjeto principal\nVocabulário Principal: 50800000\nNº: LOT-0006\nDescrição do Lote: Sistema de Iluminação do Bloco Operatório\nPreço base s/IVA: 23.843,32 EUR\nClassificação CPV (Vocabulário Comum para os Contratos Públicos)\nObjeto principal\nVocabulário Principal: 50800000\nNº: LOT-0007\nDescrição do Lote: Seringa Perfusora \nPreço base s/IVA: 2.338,72 EUR\nClassificação CPV (Vocabulário Comum para os Contratos Públicos)\nObjeto principal\nVocabulário Principal: 50800000\nNº: LOT-0008\nDescrição do Lote: Outro Equipamento Anestésico e Monitorização Multiparametrica\nPreço base s/IVA: 9.630,21 EUR\nClassificação CPV (Vocabulário Comum para os Contratos Públicos)\nObjeto principal\nVocabulário Principal: 50800000\nNº: LOT-0009\nDescrição do Lote: Outros Equipamentos Imagiologia\nPreço base s/IVA: 5.419,02 EUR\nClassificação CPV (Vocabulário Comum para os Contratos Públicos)\nObjeto principal\nVocabulário Principal: 50800000\nNº: LOT-0010\nDescrição do Lote: Outro Equipamento Cirúrgico \nPreço base s/IVA: 4.203,00 EUR\nClassificação CPV (Vocabulário Comum para os Contratos Públicos)\nObjeto principal\nVocabulário Principal: 50800000\nNº: LOT-0011\nDescrição do Lote: Estufas\nPreço base s/IVA: 5.407,41 EUR\nClassificação CPV (Vocabulário Comum para os Contratos Públicos)\nObjeto principal\nVocabulário Principal: 50800000\nNº: LOT-0012\nDescrição do Lote: Equipamento de Laboratório\nPreço base s/IVA: 88.438,50 EUR\nClassificação CPV (Vocabulário Comum para os Contratos Públicos)\nObjeto principal\nVocabulário Principal: 50800000\n\n7 - INDICAÇÕES ADICIONAIS\nO contrato envolve aquisição conjunta (satisfação de várias entidades)? Não\nO contrato é adjudicado por uma central de compras? Não\n\n8 - TÉCNICAS\nO concurso destina-se à celebração de um acordo-quadro? Inexistência de acordo-quadro\nÉ utilizado um leilão eletrónico? Não\nÉ adotada uma fase de negociação? Não\nSistema de Aquisição Dinâmico: Inexistência de sistema de aquisição dinâmico\n\n9 - LOCAL DA EXECUÇÃO DO CONTRATO\nLOCAL DA EXECUÇÃO DO CONTRATO (PROCEDIMENTO)\nLOCAL DA EXECUÇÃO DO CONTRATO (LOTE)\nIdentificador do Lote: LOT-0001\nPaís: Portugal\nNUT III: PT11D\nLocalidade: Vila Real\nDistrito: Vila Real\nConcelho: Vila Real\nFreguesia: Freguesia de Folhadela\nIdentificador do Lote: LOT-0002\nPaís: Portugal\nNUT III: PT11D\nLocalidade: Vila Real\nDistrito: Vila Real\nConcelho: Vila Real\nFreguesia: Freguesia de Folhadela\nIdentificador do Lote: LOT-0003\nPaís: Portugal\nNUT III: PT11D\nLocalidade: Vila Real\nDistrito: Vila Real\nConcelho: Vila Real\nFreguesia: Freguesia de Folhadela\nIdentificador do Lote: LOT-0004\nPaís: Portugal\nNUT III: PT11D\nLocalidade: Vila Real\nDistrito: Vila Real\nConcelho: Vila Real\nFreguesia: Freguesia de Folhadela\nIdentificador do Lote: LOT-0005\nPaís: Portugal\nNUT III: PT11D\nLocalidade: Vila Real\nDistrito: Vila Real\nConcelho: Vila Real\nFreguesia: Freguesia de Folhadela\nIdentificador do Lote: LOT-0006\nPaís: Portugal\nNUT III: PT11D\nLocalidade: Vila Real\nDistrito: Vila Real\nConcelho: Vila Real\nFreguesia: Freguesia de Folhadela\nIdentificador do Lote: LOT-0007\nPaís: Portugal\nNUT III: PT11D\nLocalidade: Vila Real\nDistrito: Vila Real\nConcelho: Vila Real\nFreguesia: Freguesia de Folhadela\nIdentificador do Lote: LOT-0008\nPaís: Portugal\nNUT III: PT11D\nLocalidade: Vila Real\nDistrito: Vila Real\nConcelho: Vila Real\nFreguesia: Freguesia de Folhadela\nIdentificador do Lote: LOT-0009\nPaís: Portugal\nNUT III: PT11D\nLocalidade: Vila Real\nDistrito: Vila Real\nConcelho: Vila Real\nFreguesia: Freguesia de Folhadela\nIdentificador do Lote: LOT-0010\nPaís: Portugal\nNUT III: PT11D\nLocalidade: Vila Real\nDistrito: Vila Real\nConcelho: Vila Real\nFreguesia: Freguesia de Folhadela\nIdentificador do Lote: LOT-0011\nPaís: Portugal\nNUT III: PT11D\nLocalidade: Vila Real\nDistrito: Vila Real\nConcelho: Vila Real\nFreguesia: Freguesia de Folhadela\nIdentificador do Lote: LOT-0012\nPaís: Portugal\nNUT III: PT11D\nLocalidade: Vila Real\nDistrito: Vila Real\nConcelho: Vila Real\nFreguesia: Freguesia de Folhadela\n\n10 - PRAZO DE EXECUÇÃO DO CONTRATO\nIdentificador do Lote: LOT-0001\nPrazo de execução do contrato: 3 ANOS\nPrevisão de renovações: Não\nIdentificador do Lote: LOT-0002\nPrazo de execução do contrato: 3 ANOS\nPrevisão de renovações: Não\nIdentificador do Lote: LOT-0003\nPrazo de execução do contrato: 3 ANOS\nPrevisão de renovações: Não\nIdentificador do Lote: LOT-0004\nPrazo de execução do contrato: 3 ANOS\nPrevisão de renovações: Não\nIdentificador do Lote: LOT-0005\nPrazo de execução do contrato: 3 ANOS\nPrevisão de renovações: Não\nIdentificador do Lote: LOT-0006\nPrazo de execução do contrato: 3 ANOS\nPrevisão de renovações: Não\nIdentificador do Lote: LOT-0007\nPrazo de execução do contrato: 3 ANOS\nPrevisão de renovações: Não\nIdentificador do Lote: LOT-0008\nPrazo de execução do contrato: 3 ANOS\nPrevisão de renovações: Não\nIdentificador do Lote: LOT-0009\nPrazo de execução do contrato: 3 ANOS\nPrevisão de renovações: Não\nIdentificador do Lote: LOT-0010\nPrazo de execução do contrato: 3 ANOS\nPrevisão de renovações: Não\nIdentificador do Lote: LOT-0011\nPrazo de execução do contrato: 3 ANOS\nPrevisão de renovações: Não\nIdentificador do Lote: LOT-0012\nPrazo de execução do contrato: 3 ANOS\nPrevisão de renovações: Não\n\n11 - FUNDOS EU\nIdentificador do Lote: LOT-0001; LOT-0002; LOT-0003; LOT-0004; LOT-0005; LOT-0006; LOT-0007; LOT-0008; LOT-0009; LOT-0010; LOT-0011; LOT-0012\nTêm fundos EU? Não\n\n12 - DOCUMENTOS DE HABILITAÇÃO\nHabilitação para o exercício da atividade profissional: Não\n\n13 - CONDIÇÕES DE APRESENTAÇÃO\nPlataforma eletrónica utilizada pela entidade adjudicante: ANOGOV\nURL para Apresentação: https://www.anogov.com/me-utad/faces/\nAdmissibilidade da apresentação de propostas variantes: Não autorizado\nPrazo para apresentação das propostas: 23-10-2025 23:59\nPrazo durante o qual os concorrentes são obrigados a manter as respetivas propostas: 66 dias a contar do termo do prazo para a apresentação das propostas\nApresentação de Catálogo Eletrónico: Não autorizado\nIndicação de Subcontratação na Proposta: Inexistência de indicação de subcontratação\n\n14 - PRESTAÇÃO DE CAUÇÃO\nPrestação de caução: Não\n\n15 - FORNECIMENTO DAS PEÇAS DO CONCURSO, APRESENTAÇÃO DE PEDIDOS DE PARTICIPAÇÃO E APRESENTAÇÃO DAS PROPOSTAS\nLink para acesso às peças do concurso (URL): https://www.anogov.com/me-utad/faces/app/acessoDocs.jsp?codigoAcesso=37K5tlLgfknDEt6VsRRjhxwX8YQAjOVaYjLz63n8QoLFzXH1eF\n\n20 - OUTROS REQUISITOS\nIdentificador do Lote: LOT-0001; LOT-0002; LOT-0003; LOT-0004; LOT-0005; LOT-0006; LOT-0007; LOT-0008; LOT-0009; LOT-0010; LOT-0011; LOT-0012\nInformação sobre contratos reservados. Aplica-se a contratos reservados (54º-A)? Não\n\n21 - CRITÉRIO DE ADJUDICAÇÃO\nO Critério de adjudicação é diferenciado por lote? Não\nMultifator: Não\nMonofator:\nNome: Preço\n\n24 - CONDIÇÕES DO CONTRATO\nIdentificador do Lote: LOT-0001; LOT-0002; LOT-0003; LOT-0004; LOT-0005; LOT-0006; LOT-0007; LOT-0008; LOT-0009; LOT-0010; LOT-0011; LOT-0012\nFaturação Eletrónica: Permitido\nObrigação de Subcontratação:\nCódigo da Obrigação de Subcontratação: Não é aplicável nenhuma obrigação de subcontratação.\n\n25 - COMPRA PÚBLICA ESTRATÉGICA\nCompra Pública Estratégica: Inexistência de contratação pública estratégica\n\n26 - INFORMAÇÕES ADICIONAIS\nIdentificador do Lote: LOT-0001\nContrato adequado para PME: Sim\nCobertura ACP (Acordo dos Contratos Públicos da Organização Mundial do Comércio): Não\nIdentificador do Lote: LOT-0002\nContrato adequado para PME: Sim\nCobertura ACP (Acordo dos Contratos Públicos da Organização Mundial do Comércio): Não\nIdentificador do Lote: LOT-0003\nContrato adequado para PME: Sim\nCobertura ACP (Acordo dos Contratos Públicos da Organização Mundial do Comércio): Não\nIdentificador do Lote: LOT-0004\nContrato adequado para PME: Sim\nCobertura ACP (Acordo dos Contratos Públicos da Organização Mundial do Comércio): Não\nIdentificador do Lote: LOT-0005\nContrato adequado para PME: Sim\nCobertura ACP (Acordo dos Contratos Públicos da Organização Mundial do Comércio): Não\nIdentificador do Lote: LOT-0006\nContrato adequado para PME: Sim\nCobertura ACP (Acordo dos Contratos Públicos da Organização Mundial do Comércio): Não\nIdentificador do Lote: LOT-0007\nContrato adequado para PME: Sim\nCobertura ACP (Acordo dos Contratos Públicos da Organização Mundial do Comércio): Não\nIdentificador do Lote: LOT-0008\nContrato adequado para PME: Sim\nCobertura ACP (Acordo dos Contratos Públicos da Organização Mundial do Comércio): Não\nIdentificador do Lote: LOT-0009\nContrato adequado para PME: Sim\nCobertura ACP (Acordo dos Contratos Públicos da Organização Mundial do Comércio): Não\nIdentificador do Lote: LOT-0010\nContrato adequado para PME: Sim\nCobertura ACP (Acordo dos Contratos Públicos da Organização Mundial do Comércio): Não\nIdentificador do Lote: LOT-0011\nContrato adequado para PME: Sim\nCobertura ACP (Acordo dos Contratos Públicos da Organização Mundial do Comércio): Não\nIdentificador do Lote: LOT-0012\nContrato adequado para PME: Sim\nCobertura ACP (Acordo dos Contratos Públicos da Organização Mundial do Comércio): Não\n\n27 - IDENTIFICAÇÃO E CONTACTOS DO ÓRGÃO DE RECURSOS ADMINISTRATIVOS\nDesignação: Universidade de Trás-os-Montes e Alto Douro\nEndereço: Quinta de Prados - Folhadela\nCódigo postal: 5000-801\nLocalidade: Vila Real\nEndereço eletrónico: reitor@utad.pt\n\n28 - IDENTIFICAÇÃO DO(S) AUTOR(ES) DE ANÚNCIO\nNome: Bruno Jorge Dos Santos Oliveira\nCargo: Técnico Superior\n419565238",
    "nipc": "501345361",
    "distrito": "Vila Real",
    "concelho": "Vila Real",
    "freguesia": "Freguesia de Folhadela",
    "site": "www.utad.pt",
    "email": "centcompras@utad.pt",
    "designacao_contrato": "Aquisição de Serviços de Inspeção e Manutenção Preventiva e Corretiva de Equipamento do Hospital Veterinário da UTAD",
    "descricao": "Aquisição de Serviços de Inspeção e Manutenção Preventiva e Corretiva de Equipamento do Hospital Veterinário da UTAD",
    "preco_base": "257.867,13 EUR",
    "prazo_execucao": "3 ANOS",
    "prazo_apresentacao_propostas": "23-10-2025 23:59",
    "fundos_eu": "Não",
    "plataforma_eletronica": "ANOGOV",
    "url_procedimento": "https://www.anogov.com/me-utad/faces/",
    "autor_nome": "Bruno Jorge Dos Santos Oliveira",
    "autor_cargo": "Técnico Superior"
  },
  {
    "numero_procedimento": "N/A",
    "entidade": "Santa Casa da Misericordia do Fundão",
    "link": "https://diariodarepublica.pt/dr/detalhe/contrato-publico/25348-936770309",
    "detalhes_completos": "Alteração do Anúncio de procedimento n.º 24076/2025, de 2025-09-11, com o ID 419524535\n\n1 - IDENTIFICAÇÃO E CONTACTOS DA ENTIDADE ADJUDICANTE\nDesignação da entidade adjudicante: Santa Casa da Misericordia do Fundão\nNIPC: 500867640\nServiço/Órgão/Pessoa de contacto: Maria Alice Matos Rosa\nEndereço: Rua João Franco, 59\nCódigo postal: 6230-296\nLocalidade: Castelo Branco\nPaís: Portugal\nNUT III: PT16J\nDistrito: Castelo Branco\nConcelho: Fundão\nFreguesia: União das Freguesias de Fundão, Valverde, Donas, Aldeia de Joanes e Aldeia Nova do Cabo\nTelefone: 275772365\nFax: 275773265\nEndereço Eletrónico: geral@misericordiafundao.pt\neDelivery Gateway (URL): https://community.vortal.biz/public/\nFunção da Organização: Adquirente\nNorma jurídica da Entidade Adjudicante: Autoridade da administração central\nÁrea de atividade da Autoridade Adjudicante: Proteção social\n\n2 - JORNAL OFICIAL DA UNIÃO EUROPEIA\nO procedimento a que este anúncio diz respeito também é publicitado no Jornal Oficial da União Europeia? Não\n\n3 - AVISO\nModelo de Anúncio: Concurso público\nData de Envio do Anúncio: 25-09-2025\n\n5 - PROCESSO\nTipo de Procedimento: Concurso público\nPreço base do procedimento: Sim\nValor do preço base do procedimento: 5.450.000,00 EUR\nProcedimento com lotes? Não\n\n6 - OBJETO DO CONTRATO\nNúmero de referência interna: 02/2025\nDesignação do contrato: Empreitada de Conceção-Construção da Unidade de Continuados Integrados e Cuidados Paliativos da Santa Casa da Misericórdia do Fundão\nDescrição: Empreitada de Conceção-Construção da Unidade de Continuados\nIntegrados e Cuidados Paliativos da Santa Casa da Misericórdia do Fundão\nTipo de Contrato Principal: Empreitada de Obras Públicas\nTipo de Contrato: Empreitada de Obras Públicas\nClassificação CPV (Vocabulário Comum para os Contratos Públicos)\nObjeto principal\nVocabulário Principal: 45215140\nPreço base s/IVA: 5.450.000,00 EUR\n\n7 - INDICAÇÕES ADICIONAIS\nO contrato envolve aquisição conjunta (satisfação de várias entidades)? Não\nO contrato é adjudicado por uma central de compras? Não\n\n8 - TÉCNICAS\nO concurso destina-se à celebração de um acordo-quadro? Inexistência de acordo-quadro\nÉ utilizado um leilão eletrónico? Não\nÉ adotada uma fase de negociação? Não\nSistema de Aquisição Dinâmico: Inexistência de sistema de aquisição dinâmico\n\n9 - LOCAL DA EXECUÇÃO DO CONTRATO\nLOCAL DA EXECUÇÃO DO CONTRATO (PROCEDIMENTO)\nPaís: Portugal\nNUT III: PT16J\nLocalidade: Castelo Branco\nDistrito: Castelo Branco\nConcelho: Fundão\nFreguesia: União das Freguesias de Fundão, Valverde, Donas, Aldeia de Joanes e Aldeia Nova do Cabo\n\n10 - PRAZO DE EXECUÇÃO DO CONTRATO\nPrazo de execução do contrato: 210 DIAS\nPrevisão de renovações: Não\n\n11 - FUNDOS EU\nTêm fundos EU? Sim\n\n12 - DOCUMENTOS DE HABILITAÇÃO\nHabilitação para o exercício da atividade profissional: Não\n\n13 - CONDIÇÕES DE APRESENTAÇÃO\nPlataforma eletrónica utilizada pela entidade adjudicante: VORTAL\nURL para Apresentação: https://community.vortal.biz/public/\nAdmissibilidade da apresentação de propostas variantes: Não autorizado\nPrazo para apresentação das propostas: 26-09-2025 17:00\nPrazo durante o qual os concorrentes são obrigados a manter as respetivas propostas: 66 dias a contar do termo do prazo para a apresentação das propostas\nIndicação de Subcontratação na Proposta: Inexistência de indicação de subcontratação\n\n14 - PRESTAÇÃO DE CAUÇÃO\nPrestação de caução: Sim\nPercentagem: 5%\nDescrição da Garantia Exigida: Em conformidade com o Artigo 18.º do Programa do Procedimento\n\n15 - FORNECIMENTO DAS PEÇAS DO CONCURSO, APRESENTAÇÃO DE PEDIDOS DE PARTICIPAÇÃO E APRESENTAÇÃO DAS PROPOSTAS\nLink para acesso às peças do concurso (URL): https://community.vortal.biz/Public/public-tender-documents/YlNZTzJlZk04Tkl0cXdZMWJqTGhKTWwvaExKdUhLb3pjTW55bE5IWUwxbFhmRTl2SXFveUFLUUdKWjVKcHJyMGR1T0VQQVVoZjRuclg2OUZHd01ublE9PUFLbio3\n\n20 - OUTROS REQUISITOS\nInformação sobre contratos reservados. Aplica-se a contratos reservados (54º-A)? Não\n\n21 - CRITÉRIO DE ADJUDICAÇÃO\nMultifator: Sim\nFator: \nNome: Qualidade\nPonderação: 67%\nSubfatores: Não\nFator: \nNome: Preço\nPonderação: 27%\nSubfatores: Não\nFator: \nNome: Qualidade\nPonderação: 6%\nSubfatores: Não\n\n24 - CONDIÇÕES DO CONTRATO\nFaturação Eletrónica: Permitido\nObrigação de Subcontratação:\nCódigo da Obrigação de Subcontratação: Não é aplicável nenhuma obrigação de subcontratação.\n\n25 - COMPRA PÚBLICA ESTRATÉGICA\nCompra Pública Estratégica: Inexistência de contratação pública estratégica\n\n26 - INFORMAÇÕES ADICIONAIS\nContrato adequado para PME: Sim\nCobertura ACP (Acordo dos Contratos Públicos da Organização Mundial do Comércio): Não\n\n27 - IDENTIFICAÇÃO E CONTACTOS DO ÓRGÃO DE RECURSOS ADMINISTRATIVOS\nDesignação: Mesa Administrativa da Santa Casa da Misericórdia do Fundão\nEndereço: Rua dos Descobridores\nCódigo postal: 6230-215\nLocalidade: Fundão\nTelefone: +351 275772365\nFax: +351 275772365\nEndereço eletrónico: geral@misericordiafundao.pt\n\n28 - IDENTIFICAÇÃO DO(S) AUTOR(ES) DE ANÚNCIO\nNome: Santa Casa da Misericórdia do Fundão\nCargo: Entidade Adjudicante\n\n29 - ALTERAÇÃO\nMotivo da Alteração: Informações atualizadas\nIdentificador da Versão do Anúncio a Alterar: 7cf6d0b1-9aba-4c98-868d-93d59a7cd4d7-01\nIdentificador das Secções Alteradas do Anúncio Anterior: Alteração\nDescrição das Alterações: Alteração no campo 13 - Data de apresentação de propostas\nAlteração dos Documentos do Concurso: Não\n419580636",
    "nipc": "500867640",
    "distrito": "Castelo Branco",
    "concelho": "Fundão",
    "freguesia": "União das Freguesias de Fundão, Valverde, Donas, Aldeia de Joanes e Aldeia Nova do Cabo",
    "site": null,
    "email": "geral@misericordiafundao.pt",
    "designacao_contrato": "Empreitada de Conceção-Construção da Unidade de Continuados Integrados e Cuidados Paliativos da Santa Casa da Misericórdia do Fundão",
    "descricao": "Empreitada de Conceção-Construção da Unidade de Continuados",
    "preco_base": "5.450.000,00 EUR",
    "prazo_execucao": "210 DIAS",
    "prazo_apresentacao_propostas": "26-09-2025 17:00",
    "fundos_eu": "Sim",
    "plataforma_eletronica": "VORTAL",
    "url_procedimento": "https://community.vortal.biz/public/",
    "autor_nome": "Santa Casa da Misericórdia do Fundão",
    "autor_cargo": "Entidade Adjudicante"
  },
  {
    "numero_procedimento": "N/A",
    "entidade": "UNIDADE LOCAL DE SAÚDE DA GUARDA, E.P.E",
    "link": "https://diariodarepublica.pt/dr/detalhe/contrato-publico/25349-936770311",
    "detalhes_completos": "1 - IDENTIFICAÇÃO E CONTACTOS DA ENTIDADE ADJUDICANTE\nDesignação da entidade adjudicante: UNIDADE LOCAL DE SAÚDE DA GUARDA, E.P.E\nNIPC: 508752000\nEndereço: AVENIDA RAINHA DONA AMÉLIA\nCódigo postal: 6301-858\nLocalidade: Guarda\nPaís: Portugal\nNUT III: PT16J\nDistrito: Guarda\nConcelho: Guarda\nFreguesia: Freguesia de Guarda\nTelefone: 271 200 200\nFax: 271200305\nEndereço da Entidade (URL): http://www.ulsguarda.min-saude.pt/\nEndereço Eletrónico: nmatias@ulsguarda.min-saude.pt\neDelivery Gateway (URL): https://community.vortal.biz/public/\nFunção da Organização: Adquirente\nNorma jurídica da Entidade Adjudicante: Organismo de direito público\nÁrea de atividade da Autoridade Adjudicante: Saúde\n\n2 - JORNAL OFICIAL DA UNIÃO EUROPEIA\nO procedimento a que este anúncio diz respeito também é publicitado no Jornal Oficial da União Europeia? Não\n\n3 - AVISO\nModelo de Anúncio: Concurso público\nData de Envio do Anúncio: 25-09-2025\n\n5 - PROCESSO\nTipo de Procedimento: Concurso público\nPreço base do procedimento: Sim\nValor do preço base do procedimento: 33.255,00 EUR\nProcedimento com lotes? Sim\nNº Máx. de Lotes Autorizado: 2\nNúmero máximo de lotes que podem ser adjudicados a um concorrente: 2\n\n6 - OBJETO DO CONTRATO\nNúmero de referência interna: 19/33/2025\nDesignação do contrato: Aquisição de 45 computadores e monitores para a ULS da Guarda, E.P.E.\nDescrição: Aquisição de 45 computadores e monitores para a ULS da Guarda, E.P.E.\nTipo de Contrato Principal: Aquisição de Bens Móveis\nTipo de Contrato: Aquisição de Bens Móveis\nClassificação CPV (Vocabulário Comum para os Contratos Públicos)\nObjeto principal\nVocabulário Principal: 30213300\nPreço base s/IVA: 33.255,00 EUR\nLotes: \nNº: LOT-0001\nDescrição do Lote: Lote 1\nPreço base s/IVA: 26.730,00 EUR\nClassificação CPV (Vocabulário Comum para os Contratos Públicos)\nObjeto principal\nVocabulário Principal: 30213300\nNº: LOT-0002\nDescrição do Lote: Lote 2\nPreço base s/IVA: 6.525,00 EUR\nClassificação CPV (Vocabulário Comum para os Contratos Públicos)\nObjeto principal\nVocabulário Principal: 30213300\n\n7 - INDICAÇÕES ADICIONAIS\nO contrato envolve aquisição conjunta (satisfação de várias entidades)? Não\nO contrato é adjudicado por uma central de compras? Não\n\n8 - TÉCNICAS\nO concurso destina-se à celebração de um acordo-quadro? Inexistência de acordo-quadro\nÉ utilizado um leilão eletrónico? Não\nÉ adotada uma fase de negociação? Não\nSistema de Aquisição Dinâmico: Inexistência de sistema de aquisição dinâmico\n\n9 - LOCAL DA EXECUÇÃO DO CONTRATO\nLOCAL DA EXECUÇÃO DO CONTRATO (PROCEDIMENTO)\nPaís: Portugal\nNUT III: PT16J\nLocalidade: Guarda\nDistrito: Guarda\nConcelho: Guarda\nFreguesia: Todas\nLOCAL DA EXECUÇÃO DO CONTRATO (LOTE)\nIdentificador do Lote: LOT-0001; LOT-0002\nPaís: Portugal\nNUT III: PT16J\nLocalidade: Guarda\nDistrito: Guarda\nConcelho: Guarda\nFreguesia: Todas\n\n10 - PRAZO DE EXECUÇÃO DO CONTRATO\nIdentificador do Lote: LOT-0001; LOT-0002\nPrazo de execução do contrato: 30 DIAS\nPrevisão de renovações: Não\n\n11 - FUNDOS EU\nIdentificador do Lote: LOT-0001; LOT-0002\nTêm fundos EU? Não\n\n12 - DOCUMENTOS DE HABILITAÇÃO\nHabilitação para o exercício da atividade profissional: Não\n\n13 - CONDIÇÕES DE APRESENTAÇÃO\nPlataforma eletrónica utilizada pela entidade adjudicante: VORTAL\nURL para Apresentação: https://community.vortal.biz/public/\nAdmissibilidade da apresentação de propostas variantes: Não autorizado\nPrazo para apresentação das propostas: 05-10-2025 18:00\nPrazo durante o qual os concorrentes são obrigados a manter as respetivas propostas: 66 dias a contar do termo do prazo para a apresentação das propostas\nIndicação de Subcontratação na Proposta: Inexistência de indicação de subcontratação\n\n14 - PRESTAÇÃO DE CAUÇÃO\nPrestação de caução: Não\n\n15 - FORNECIMENTO DAS PEÇAS DO CONCURSO, APRESENTAÇÃO DE PEDIDOS DE PARTICIPAÇÃO E APRESENTAÇÃO DAS PROPOSTAS\nLink para acesso às peças do concurso (URL): https://community.vortal.biz/Public/public-tender-documents/bnJwZnNxam5TNTB0YWxOYlArMzg1NCs2K1hGSlRjblRReEduR1hqLzlvajE1aWFjUlZjOS9uN25yYlpCU1JxTS9IMEtaY3l1cmlDclNxTkI1RVpBaWc9PSZDWFRJ\n\n20 - OUTROS REQUISITOS\nIdentificador do Lote: LOT-0001; LOT-0002\nInformação sobre contratos reservados. Aplica-se a contratos reservados (54º-A)? Não\n\n21 - CRITÉRIO DE ADJUDICAÇÃO\nO Critério de adjudicação é diferenciado por lote? Não\nMultifator: Não\nMonofator:\nNome: Preço\n\n24 - CONDIÇÕES DO CONTRATO\nIdentificador do Lote: LOT-0001; LOT-0002\nFaturação Eletrónica: Permitido\nObrigação de Subcontratação:\nCódigo da Obrigação de Subcontratação: Não é aplicável nenhuma obrigação de subcontratação.\n\n25 - COMPRA PÚBLICA ESTRATÉGICA\nCompra Pública Estratégica: Inexistência de contratação pública estratégica\n\n26 - INFORMAÇÕES ADICIONAIS\nIdentificador do Lote: LOT-0001; LOT-0002\nContrato adequado para PME: Sim\nCobertura ACP (Acordo dos Contratos Públicos da Organização Mundial do Comércio): Não\n\n27 - IDENTIFICAÇÃO E CONTACTOS DO ÓRGÃO DE RECURSOS ADMINISTRATIVOS\nDesignação: Conselho de Administração da ULS da Guarda\nEndereço: Av. Rainha D. Amélia, s/n\nCódigo postal: 6301-857\nLocalidade: Guarda\nTelefone: +351 271200200\nFax: +351 271200200\nEndereço eletrónico: secretaiado.ca@ulsguarda.min-saude.pt\n\n28 - IDENTIFICAÇÃO DO(S) AUTOR(ES) DE ANÚNCIO\nNome: Nuno Matias\nCargo: Diretor do SCLP\n419580474",
    "nipc": "508752000",
    "distrito": "Guarda",
    "concelho": "Guarda",
    "freguesia": "Freguesia de Guarda",
    "site": "http://www.ulsguarda.min-saude.pt/",
    "email": "nmatias@ulsguarda.min-saude.pt",
    "designacao_contrato": "Aquisição de 45 computadores e monitores para a ULS da Guarda, E.P.E.",
    "descricao": "Aquisição de 45 computadores e monitores para a ULS da Guarda, E.P.E.",
    "preco_base": "33.255,00 EUR",
    "prazo_execucao": "30 DIAS",
    "prazo_apresentacao_propostas": "05-10-2025 18:00",
    "fundos_eu": "Não",
    "plataforma_eletronica": "VORTAL",
    "url_procedimento": "https://community.vortal.biz/public/",
    "autor_nome": "Nuno Matias",
    "autor_cargo": "Diretor do SCLP"
  },
  {
    "numero_procedimento": "N/A",
    "entidade": "AnÃºncio de procedimento  n.Âº 25350/2025  -  DiÃ¡rio da RepÃºblica n.Âº 186/2025, SÃ©rie II de 2025-09-26",
    "link": "https://diariodarepublica.pt/dr/detalhe/contrato-publico/25350-936770312"
  },
  {
    "numero_procedimento": "N/A",
    "entidade": "AnÃºncio de procedimento  n.Âº 25352/2025  -  DiÃ¡rio da RepÃºblica n.Âº 186/2025, SÃ©rie II de 2025-09-26",
    "link": "https://diariodarepublica.pt/dr/detalhe/contrato-publico/25352-936770313"
  },
  {
    "numero_procedimento": "N/A",
    "entidade": "AnÃºncio de procedimento  n.Âº 25353/2025  -  DiÃ¡rio da RepÃºblica n.Âº 186/2025, SÃ©rie II de 2025-09-26",
    "link": "https://diariodarepublica.pt/dr/detalhe/contrato-publico/25353-936770314"
  },
  {
    "numero_procedimento": "N/A",
    "entidade": "Serviços Municipalizados de Água e Saneamento de Viseu",
    "link": "https://diariodarepublica.pt/dr/detalhe/contrato-publico/25354-936770318",
    "detalhes_completos": "1 - IDENTIFICAÇÃO E CONTACTOS DA ENTIDADE ADJUDICANTE\nDesignação da entidade adjudicante: Serviços Municipalizados de Água e Saneamento de Viseu\nNIPC: 680020063\nEndereço: Rua Conselheiro Afonso de Melo\nCódigo postal: 3510-024\nLocalidade: Viseu\nPaís: Portugal\nNUT III: PT16G\nDistrito: Viseu\nConcelho: Viseu\nFreguesia: Freguesia de Viseu\nTelefone: 232470670\nFax: 232424080\nEndereço da Entidade (URL): www.smasviseu.pt\nEndereço Eletrónico: geral@smasviseu.pt\neDelivery Gateway (URL): https://www.acingov.pt\nFunção da Organização: Adquirente\nNorma jurídica da Entidade Adjudicante: Autoridade local\nÁrea de atividade da Autoridade Adjudicante: Serviços públicos das administrações públicas\n\n2 - JORNAL OFICIAL DA UNIÃO EUROPEIA\nO procedimento a que este anúncio diz respeito também é publicitado no Jornal Oficial da União Europeia? Não\n\n3 - AVISO\nModelo de Anúncio: Concurso público\nData de Envio do Anúncio: 26-09-2025\n\n5 - PROCESSO\nTipo de Procedimento: Concurso público\nPreço base do procedimento: Sim\nValor do preço base do procedimento: 368.044,69 EUR\nProcedimento com lotes? Não\n\n6 - OBJETO DO CONTRATO\nNúmero de referência interna: E1206\nDesignação do contrato: Prolongamento das redes de água e saneamento na zona Sul do Concelho - 2025\nDescrição: Prolongamento das redes de água e saneamento na zona Sul do Concelho - 2025\nTipo de Contrato Principal: Empreitada de Obras Públicas\nTipo de Contrato: Empreitada de Obras Públicas\nClassificação CPV (Vocabulário Comum para os Contratos Públicos)\nObjeto principal\nVocabulário Principal: 45232460\nPreço base s/IVA: 368.044,69 EUR\n\n7 - INDICAÇÕES ADICIONAIS\nO contrato envolve aquisição conjunta (satisfação de várias entidades)? Não\nO contrato é adjudicado por uma central de compras? Não\n\n8 - TÉCNICAS\nO concurso destina-se à celebração de um acordo-quadro? Inexistência de acordo-quadro\nÉ utilizado um leilão eletrónico? Não\nÉ adotada uma fase de negociação? Não\nSistema de Aquisição Dinâmico: Inexistência de sistema de aquisição dinâmico\n\n9 - LOCAL DA EXECUÇÃO DO CONTRATO\nLOCAL DA EXECUÇÃO DO CONTRATO (PROCEDIMENTO)\nPaís: Portugal\nNUT III: PT16G\nLocalidade: Viseu\nDistrito: Viseu\nConcelho: Viseu\nFreguesia: Todas\n\n10 - PRAZO DE EXECUÇÃO DO CONTRATO\nPrazo de execução do contrato: 365 DIAS\nPrevisão de renovações: Não\n\n11 - FUNDOS EU\nTêm fundos EU? Não\n\n12 - DOCUMENTOS DE HABILITAÇÃO\nHabilitação para o exercício da atividade profissional: Sim\nTipo: Alvará\nDescrição: O certificado do alvará de construção previsto deve conter:\nA 6ª subcategoria da 2ª categoria, sendo que a classe da 6ª subcategoria da 2ª categoria tem de ser de classe que cubra o valor global da proposta e integrar-se na categoria em que o tipo da obra se enquadra.\n\n13 - CONDIÇÕES DE APRESENTAÇÃO\nPlataforma eletrónica utilizada pela entidade adjudicante: ACIN\nURL para Apresentação: https://www.acingov.pt\nAdmissibilidade da apresentação de propostas variantes: Não autorizado\nPrazo para apresentação das propostas: 17-10-2025 23:59\nPrazo durante o qual os concorrentes são obrigados a manter as respetivas propostas: 120 dias a contar do termo do prazo para a apresentação das propostas\nIndicação de Subcontratação na Proposta: Inexistência de indicação de subcontratação\n\n14 - PRESTAÇÃO DE CAUÇÃO\nPrestação de caução: Não\n\n15 - FORNECIMENTO DAS PEÇAS DO CONCURSO, APRESENTAÇÃO DE PEDIDOS DE PARTICIPAÇÃO E APRESENTAÇÃO DAS PROPOSTAS\nLink para acesso às peças do concurso (URL): https://www.acingov.pt/acingovprod/2/zonaPublica/zona_publica_c/donwloadProcedurePiece/OTc5OTc1\n\n20 - OUTROS REQUISITOS\nInformação sobre contratos reservados. Aplica-se a contratos reservados (54º-A)? Não\n\n21 - CRITÉRIO DE ADJUDICAÇÃO\nMultifator: Não\nMonofator:\nNome: Preço\n\n24 - CONDIÇÕES DO CONTRATO\nFaturação Eletrónica: Permitido\nObrigação de Subcontratação:\nCódigo da Obrigação de Subcontratação: Não é aplicável nenhuma obrigação de subcontratação.\n\n25 - COMPRA PÚBLICA ESTRATÉGICA\nCompra Pública Estratégica: Inexistência de contratação pública estratégica\n\n26 - INFORMAÇÕES ADICIONAIS\nContrato adequado para PME: Sim\nCobertura ACP (Acordo dos Contratos Públicos da Organização Mundial do Comércio): Não\n\n27 - IDENTIFICAÇÃO E CONTACTOS DO ÓRGÃO DE RECURSOS ADMINISTRATIVOS\nDesignação: Município de Viseu\nEndereço: Praça da República S/N\nCódigo postal: 3514-501\nLocalidade: Viseu\nTelefone: 00351232427427\nFax: 00351232423112\nEndereço eletrónico: geral@cmviseu.pt\nPrazo de interposição do recurso: 5 dias\n\n28 - IDENTIFICAÇÃO DO(S) AUTOR(ES) DE ANÚNCIO\nNome: João Paulo Lopes Gouveia\nCargo: Vogal do Conselho de Administração\n419562857",
    "nipc": "680020063",
    "distrito": "Viseu",
    "concelho": "Viseu",
    "freguesia": "Freguesia de Viseu",
    "site": "www.smasviseu.pt",
    "email": "geral@smasviseu.pt",
    "designacao_contrato": "Prolongamento das redes de água e saneamento na zona Sul do Concelho - 2025",
    "descricao": "Prolongamento das redes de água e saneamento na zona Sul do Concelho - 2025",
    "preco_base": "368.044,69 EUR",
    "prazo_execucao": "365 DIAS",
    "prazo_apresentacao_propostas": "17-10-2025 23:59",
    "fundos_eu": "Não",
    "plataforma_eletronica": "ACIN",
    "url_procedimento": "https://www.acingov.pt",
    "autor_nome": "João Paulo Lopes Gouveia",
    "autor_cargo": "Vogal do Conselho de Administração"
  }
]