[
  {
    "numero_procedimento": "N/A",
    "entidade": "Município de Terras de Bouro",
    "link": "https://diariodarepublica.pt/dr/detalhe/contrato-publico/25638-937193346",
    "detalhes_completos": "1 - IDENTIFICAÇÃO E CONTACTOS DA ENTIDADE ADJUDICANTE\nDesignação da entidade adjudicante: Município de Terras de Bouro\nNIPC: 506907619\nServiço/Órgão/Pessoa de contacto: Divisão Administrativa e Financeira\nEndereço: Largo Padre Martins Capela\nCódigo postal: 4840-100\nLocalidade: Braga\nPaís: Portugal\nNUT III: PT112\nDistrito: Braga\nConcelho: Terras de Bouro\nFreguesia: Todas\nTelefone: 253350010\nFax: 253351894\nEndereço da Entidade (URL): www.cm-terrasdebouro.pt\nEndereço Eletrónico: teresa.braga@cm-terrasdebouro.pt\neDelivery Gateway (URL): https://community.vortal.biz/public/\nFunção da Organização: Adquirente\nNorma jurídica da Entidade Adjudicante: Autoridade local\nÁrea de atividade da Autoridade Adjudicante: Serviços públicos das administrações públicas\n\n2 - JORNAL OFICIAL DA UNIÃO EUROPEIA\nO procedimento a que este anúncio diz respeito também é publicitado no Jornal Oficial da União Europeia? Não\n\n3 - AVISO\nModelo de Anúncio: Concurso público\nData de Envio do Anúncio: 29-09-2025\n\n5 - PROCESSO\nTipo de Procedimento: Concurso público\nPreço base do procedimento: Sim\nValor do preço base do procedimento: 1.022.061,95 EUR\nProcedimento com lotes? Não\n\n6 - OBJETO DO CONTRATO\nNúmero de referência interna: 117/2025\nDesignação do contrato: BENEFICIAÇÃO DO CAMINHO FLORESTAL GUARDA/ ALBERGARIA | ORDENAMENTO DA VISITAÇÃO\nDescrição: BENEFICIAÇÃO DO CAMINHO FLORESTAL GUARDA/ ALBERGARIA | ORDENAMENTO DA VISITAÇÃO\nTipo de Contrato Principal: Empreitada de Obras Públicas\nTipo de Contrato: Empreitada de Obras Públicas\nClassificação CPV (Vocabulário Comum para os Contratos Públicos)\nObjeto principal\nVocabulário Principal: 45112730\nPreço base s/IVA: 1.022.061,95 EUR\n\n7 - INDICAÇÕES ADICIONAIS\nO contrato envolve aquisição conjunta (satisfação de várias entidades)? Não\nO contrato é adjudicado por uma central de compras? Não\n\n8 - TÉCNICAS\nO concurso destina-se à celebração de um acordo-quadro? Inexistência de acordo-quadro\nÉ utilizado um leilão eletrónico? Não\nÉ adotada uma fase de negociação? Não\nSistema de Aquisição Dinâmico: Inexistência de sistema de aquisição dinâmico\n\n9 - LOCAL DA EXECUÇÃO DO CONTRATO\nLOCAL DA EXECUÇÃO DO CONTRATO (PROCEDIMENTO)\nPaís: Portugal\nNUT III: PTZZZ\nLocalidade: PORTUGAL\nDistrito: Braga\nConcelho: Terras de Bouro\nFreguesia: Freguesia de Campo do Gerês\n\n10 - PRAZO DE EXECUÇÃO DO CONTRATO\nPrazo de execução do contrato: 270 DIAS\nPrevisão de renovações: Não\n\n11 - FUNDOS EU\nTêm fundos EU? Não\n\n12 - DOCUMENTOS DE HABILITAÇÃO\nHabilitação para o exercício da atividade profissional: Não\n\n13 - CONDIÇÕES DE APRESENTAÇÃO\nPlataforma eletrónica utilizada pela entidade adjudicante: VORTAL\nURL para Apresentação: https://community.vortal.biz/public/\nAdmissibilidade da apresentação de propostas variantes: Não autorizado\nPrazo para apresentação das propostas: 14-10-2025 17:00\nPrazo durante o qual os concorrentes são obrigados a manter as respetivas propostas: 66 dias a contar do termo do prazo para a apresentação das propostas\nIndicação de Subcontratação na Proposta: Inexistência de indicação de subcontratação\n\n14 - PRESTAÇÃO DE CAUÇÃO\nPrestação de caução: Sim\nPercentagem: 5%\nDescrição da Garantia Exigida: ver artigo 35.º do programa do procedimento\n\n15 - FORNECIMENTO DAS PEÇAS DO CONCURSO, APRESENTAÇÃO DE PEDIDOS DE PARTICIPAÇÃO E APRESENTAÇÃO DAS PROPOSTAS\nLink para acesso às peças do concurso (URL): https://community.vortal.biz/Public/public-tender-documents/dTFtUXQ0TzY2RWpuRnlKWHZzaENPQlNYNFYzQmtZT0tHaGs0OWQvODl5UXorMDVxQ1dmY3M4bXh6akhhOXMvUTJhSFFHaTJxczB1NTZ3cU5EbUk0eXc9PUdkMkNY\n\n20 - OUTROS REQUISITOS\nInformação sobre contratos reservados. Aplica-se a contratos reservados (54º-A)? Não\n\n21 - CRITÉRIO DE ADJUDICAÇÃO\nMultifator: Não\nMonofator:\nNome: Preço\n\n24 - CONDIÇÕES DO CONTRATO\nFaturação Eletrónica: Permitido\nObrigação de Subcontratação:\nCódigo da Obrigação de Subcontratação: Não é aplicável nenhuma obrigação de subcontratação.\n\n25 - COMPRA PÚBLICA ESTRATÉGICA\nCompra Pública Estratégica: Inexistência de contratação pública estratégica\n\n26 - INFORMAÇÕES ADICIONAIS\nContrato adequado para PME: Sim\nCobertura ACP (Acordo dos Contratos Públicos da Organização Mundial do Comércio): Não\n\n27 - IDENTIFICAÇÃO E CONTACTOS DO ÓRGÃO DE RECURSOS ADMINISTRATIVOS\nDesignação: Divisão Administrativa e Financeira\nEndereço: Praça do Município\nCódigo postal: 4840-100\nLocalidade: Terras de Bouro\nTelefone: +351 253350010\nFax: +351 253351894\nEndereço eletrónico: da@cm-terrasdebouro.pt\n\n28 - IDENTIFICAÇÃO DO(S) AUTOR(ES) DE ANÚNCIO\nNome: Manuel João Sampaio Tibo\nCargo: Presidente da Câmara Municipal\n419584979",
    "nipc": "506907619",
    "distrito": "Braga",
    "concelho": "Terras de Bouro",
    "freguesia": "Todas",
    "site": "www.cm-terrasdebouro.pt",
    "email": "teresa.braga@cm-terrasdebouro.pt",
    "designacao_contrato": "BENEFICIAÇÃO DO CAMINHO FLORESTAL GUARDA/ ALBERGARIA | ORDENAMENTO DA VISITAÇÃO",
    "descricao": "BENEFICIAÇÃO DO CAMINHO FLORESTAL GUARDA/ ALBERGARIA | ORDENAMENTO DA VISITAÇÃO",
    "preco_base": "1.022.061,95 EUR",
    "prazo_execucao": "270 DIAS",
    "prazo_apresentacao_propostas": "14-10-2025 17:00",
    "fundos_eu": "Não",
    "plataforma_eletronica": "VORTAL",
    "url_procedimento": "https://community.vortal.biz/public/",
    "autor_nome": "Manuel João Sampaio Tibo",
    "autor_cargo": "Presidente da Câmara Municipal"
  },
  {
    "numero_procedimento": "N/A",
    "entidade": "Camara Municipal",
    "link": "https://diariodarepublica.pt/dr/detalhe/contrato-publico/25640-937193347",
    "detalhes_completos": "1 - IDENTIFICAÇÃO E CONTACTOS DA ENTIDADE ADJUDICANTE\nDesignação da entidade adjudicante: Camara Municipal\nNIPC: 506892646\nServiço/Órgão/Pessoa de contacto: DPOAU\nEndereço: Avenida Marquês de Soveral, n.º 67\nCódigo postal: 5130-321\nLocalidade: S. João da Pesqueira\nPaís: Portugal\nNUT III: PT11D\nDistrito: Viseu\nConcelho: São João da Pesqueira\nFreguesia: União das Freguesias de São João da Pesqueira e Várzea de Trevões\nTelefone: 254489999\nFax: 254489999\nEndereço da Entidade (URL): https://www.acingov.pt/acingovprod/2/\nEndereço Eletrónico: cmsjp@sjpesqueira.pt\neDelivery Gateway (URL): https://www.acingov.pt\nFunção da Organização: Adquirente\nNorma jurídica da Entidade Adjudicante: Organismo de direito público\nÁrea de atividade da Autoridade Adjudicante: Serviços públicos das administrações públicas\n\n2 - JORNAL OFICIAL DA UNIÃO EUROPEIA\nO procedimento a que este anúncio diz respeito também é publicitado no Jornal Oficial da União Europeia? Não\n\n3 - AVISO\nModelo de Anúncio: Concurso público\nData de Envio do Anúncio: 29-09-2025\n\n5 - PROCESSO\nTipo de Procedimento: Concurso público\nPreço base do procedimento: Sim\nValor do preço base do procedimento: 943.603,67 EUR\nProcedimento com lotes? Não\n\n6 - OBJETO DO CONTRATO\nNúmero de referência interna: CP/15/2025\nDesignação do contrato: Remoção de pavimentos, rede de abastecimento de água, rede de drenagem de esgotos domésticos, rede de drenagem de águas pluviais, demolições, execução de pavimentos em cubo de granito, imobiliário urbano e plantações, infraestruturas elétricas, rede de telecomunicações, outros trabalhos e movimento de terras\nDescrição: Regeneração Urbana - Rua Dr. Paradela de Oliveira, Rua General Humberto Delgado, Rua da Cruz e Praça de Santa Maria, na Vila de São João da Pesqueira\n\nTipo de Contrato Principal: Empreitada de Obras Públicas\nTipo de Contrato: Empreitada de Obras Públicas\nClassificação CPV (Vocabulário Comum para os Contratos Públicos)\nObjeto principal\nVocabulário Principal: 45233252\nPreço base s/IVA: 943.603,67 EUR\n\n7 - INDICAÇÕES ADICIONAIS\nO contrato envolve aquisição conjunta (satisfação de várias entidades)? Não\nO contrato é adjudicado por uma central de compras? Não\n\n8 - TÉCNICAS\nO concurso destina-se à celebração de um acordo-quadro? Inexistência de acordo-quadro\nÉ utilizado um leilão eletrónico? Não\nÉ adotada uma fase de negociação? Não\nSistema de Aquisição Dinâmico: Inexistência de sistema de aquisição dinâmico\n\n9 - LOCAL DA EXECUÇÃO DO CONTRATO\nLOCAL DA EXECUÇÃO DO CONTRATO (PROCEDIMENTO)\nPaís: Portugal\nNUT III: PT11D\nLocalidade: União das Freguesias de São João da Pesqueira e Várzea de Trevões\nDistrito: Viseu\nConcelho: São João da Pesqueira\nFreguesia: União das Freguesias de São João da Pesqueira e Várzea de Trevões\n\n10 - PRAZO DE EXECUÇÃO DO CONTRATO\nPrazo de execução do contrato: 360 DIAS\nPrevisão de renovações: Não\n\n11 - FUNDOS EU\nTêm fundos EU? Sim\n\n12 - DOCUMENTOS DE HABILITAÇÃO\nHabilitação para o exercício da atividade profissional: Sim\nTipo: Alvará\nDescrição: IMPIC, I.P, na 2ª categoria (Vias de Comunicação, Obras de Urbanização e outras Infraestruturas), da qual deve ser da classe corresponde ao valor dos trabalhos a que respeita, a proposta; e a 6.ª subcategoria da 2.ª categoria (Saneamento básico), da qual deve ser da classe que cubra o valor global dos trabalhos; e a 8. ª subcategoria da 2.ª categoria (Calcetamentos), da qual deve ser da classe que cubra o valor global dos trabalhos; e a 9.ª subcategoria da 2.ª categoria (Ajardinamentos), da qual deve ser da classe que cubra o valor global dos trabalhos; e a 10.ª subcategoria da 2.ª categoria (Infraestruturas de desporto e de lazer), da qual deve ser da classe que cubra o valor global dos trabalhos; e a 4.ª categoria (Instalações Elétricas e Mecânica), da qual deve ser da classe que cubra o valor global dos trabalhos; e a 1.ª subcategoria da 4.ª categoria (Instalações elétricas de utilização de baixa tensão), da qual deve ser da classe que cubra o valor global dos trabalhos; e a 7.ª subcategoria da 4.ª categoria (Infraestruturas de telecomunicações), da qual deve ser da classe que cubra o valor global dos trabalhos, e a 5.ª categoria (Outros Trabalhos), da qual deve ser da classe que cubra o valor global dos trabalhos; e a 2.ª subcategoria da 5.ª categoria (Movimento de terras), da qual deve ser da classe que cubra o valor global dos trabalhos \n\n13 - CONDIÇÕES DE APRESENTAÇÃO\nPlataforma eletrónica utilizada pela entidade adjudicante: ACIN\nURL para Apresentação: https://www.acingov.pt\nAdmissibilidade da apresentação de propostas variantes: Não autorizado\nPrazo para apresentação das propostas: 19-10-2025 23:59\nPrazo durante o qual os concorrentes são obrigados a manter as respetivas propostas: 120 dias a contar do termo do prazo para a apresentação das propostas\nIndicação de Subcontratação na Proposta: Inexistência de indicação de subcontratação\n\n14 - PRESTAÇÃO DE CAUÇÃO\nPrestação de caução: Sim\nPercentagem: 5%\nDescrição da Garantia Exigida: O valor da caução é de 5.00% do preço contratual.\n\n15 - FORNECIMENTO DAS PEÇAS DO CONCURSO, APRESENTAÇÃO DE PEDIDOS DE PARTICIPAÇÃO E APRESENTAÇÃO DAS PROPOSTAS\nLink para acesso às peças do concurso (URL): https://www.acingov.pt/acingovprod/2/zonaPublica/zona_publica_c/donwloadProcedurePiece/OTgyMjQ2\n\n20 - OUTROS REQUISITOS\nInformação sobre contratos reservados. Aplica-se a contratos reservados (54º-A)? Não\n\n21 - CRITÉRIO DE ADJUDICAÇÃO\nMultifator: Não\nMonofator:\nNome: Preço\n\n24 - CONDIÇÕES DO CONTRATO\nFaturação Eletrónica: Permitido\nObrigação de Subcontratação:\nCódigo da Obrigação de Subcontratação: Não é aplicável nenhuma obrigação de subcontratação.\n\n25 - COMPRA PÚBLICA ESTRATÉGICA\nCompra Pública Estratégica: Inexistência de contratação pública estratégica\n\n26 - INFORMAÇÕES ADICIONAIS\nContrato adequado para PME: Sim\nCobertura ACP (Acordo dos Contratos Públicos da Organização Mundial do Comércio): Não\n\n27 - IDENTIFICAÇÃO E CONTACTOS DO ÓRGÃO DE RECURSOS ADMINISTRATIVOS\nDesignação: Câmara Municipal\nEndereço: Avenida Marquês de Soveral, n.º 67\nCódigo postal: 5130-321\nLocalidade: S. João da Pesqueira\nTelefone: 254489999\nFax: 254489999\nEndereço eletrónico: cmsjp@sjpesqueira.pt\nPrazo de interposição do recurso: 5 dias\n\n28 - IDENTIFICAÇÃO DO(S) AUTOR(ES) DE ANÚNCIO\nNome: Manuel António Natário Cordeiro\nCargo: Presidente\n419590072",
    "nipc": "506892646",
    "distrito": "Viseu",
    "concelho": "São João da Pesqueira",
    "freguesia": "União das Freguesias de São João da Pesqueira e Várzea de Trevões",
    "site": "https://www.acingov.pt/acingovprod/2/",
    "email": "cmsjp@sjpesqueira.pt",
    "designacao_contrato": "Remoção de pavimentos, rede de abastecimento de água, rede de drenagem de esgotos domésticos, rede de drenagem de águas pluviais, demolições, execução de pavimentos em cubo de granito, imobiliário urbano e plantações, infraestruturas elétricas, rede de telecomunicações, outros trabalhos e movimento de terras",
    "descricao": "Regeneração Urbana - Rua Dr. Paradela de Oliveira, Rua General Humberto Delgado, Rua da Cruz e Praça de Santa Maria, na Vila de São João da Pesqueira",
    "preco_base": "943.603,67 EUR",
    "prazo_execucao": "360 DIAS",
    "prazo_apresentacao_propostas": "19-10-2025 23:59",
    "fundos_eu": "Sim",
    "plataforma_eletronica": "ACIN",
    "url_procedimento": "https://www.acingov.pt",
    "autor_nome": "Manuel António Natário Cordeiro",
    "autor_cargo": "Presidente"
  },
  {
    "numero_procedimento": "N/A",
    "entidade": "Serviços Municipalizados de Sintra (SMAS)",
    "link": "https://diariodarepublica.pt/dr/detalhe/contrato-publico/25642-937193348",
    "detalhes_completos": "1 - IDENTIFICAÇÃO E CONTACTOS DA ENTIDADE ADJUDICANTE\nDesignação da entidade adjudicante: Serviços Municipalizados de Sintra (SMAS)\nNIPC: 680000054\nEndereço: Avenida Movimento Da Forças Armadas, 16\nCódigo postal: 2714-503\nLocalidade: Sintra\nPaís: Portugal\nNUT III: PT170\nDistrito: Lisboa\nConcelho: Sintra\nFreguesia: Todas\nTelefone: 219119016\nFax: 219232650\nEndereço da Entidade (URL): www.smas-sintra.pt\nEndereço Eletrónico: aprov.stocks@smas-sintra.pt\neDelivery Gateway (URL): https://community.vortal.biz/public/\nFunção da Organização: Adquirente\nNorma jurídica da Entidade Adjudicante: Autoridade local\nÁrea de atividade da Autoridade Adjudicante: Serviços públicos das administrações públicas\n\n2 - JORNAL OFICIAL DA UNIÃO EUROPEIA\nO procedimento a que este anúncio diz respeito também é publicitado no Jornal Oficial da União Europeia? Não\n\n3 - AVISO\nModelo de Anúncio: Concurso público\nData de Envio do Anúncio: 29-09-2025\n\n5 - PROCESSO\nTipo de Procedimento: Concurso público\nPreço base do procedimento: Sim\nValor do preço base do procedimento: 48.478,50 EUR\nProcedimento com lotes? Não\n\n6 - OBJETO DO CONTRATO\nNúmero de referência interna: Concurso Público nº 37PF/2025\nDesignação do contrato: Concurso Público nº 37PF/2025 – Aquisição de Ergelit Superfix 35 ou Equivalente\nDescrição: Aquisição de Ergelit Superfix 35 ou Equivalente\nTipo de Contrato Principal: Aquisição de Bens Móveis\nTipo de Contrato: Aquisição de Bens Móveis\nClassificação CPV (Vocabulário Comum para os Contratos Públicos)\nObjeto principal\nVocabulário Principal: 44111800\nPreço base s/IVA: 48.478,50 EUR\n\n7 - INDICAÇÕES ADICIONAIS\nO contrato envolve aquisição conjunta (satisfação de várias entidades)? Não\nO contrato é adjudicado por uma central de compras? Não\n\n8 - TÉCNICAS\nO concurso destina-se à celebração de um acordo-quadro? Inexistência de acordo-quadro\nÉ utilizado um leilão eletrónico? Não\nÉ adotada uma fase de negociação? Não\nSistema de Aquisição Dinâmico: Inexistência de sistema de aquisição dinâmico\n\n9 - LOCAL DA EXECUÇÃO DO CONTRATO\nLOCAL DA EXECUÇÃO DO CONTRATO (PROCEDIMENTO)\nPaís: Portugal\nNUT III: PT170\nLocalidade: Lisboa\nDistrito: Lisboa\nConcelho: Sintra\nFreguesia: União das Freguesias de Sintra (Santa Maria e São Miguel, São Martinho e São Pedro de Penaferrim)\n\n10 - PRAZO DE EXECUÇÃO DO CONTRATO\nPrazo de execução do contrato: 1 ANOS\nPrevisão de renovações: Não\n\n11 - FUNDOS EU\nTêm fundos EU? Não\n\n12 - DOCUMENTOS DE HABILITAÇÃO\nHabilitação para o exercício da atividade profissional: Sim\nTipo: Outros\nDescrição - Outros: De acordo com as Peças do Procedimento\nDescrição: Conforme indicado nas peças do procedimento\n\n13 - CONDIÇÕES DE APRESENTAÇÃO\nPlataforma eletrónica utilizada pela entidade adjudicante: VORTAL\nURL para Apresentação: https://community.vortal.biz/public/\nAdmissibilidade da apresentação de propostas variantes: Não autorizado\nPrazo para apresentação das propostas: 13-10-2025 17:00\nPrazo durante o qual os concorrentes são obrigados a manter as respetivas propostas: 90 dias a contar do termo do prazo para a apresentação das propostas\nIndicação de Subcontratação na Proposta: Inexistência de indicação de subcontratação\n\n14 - PRESTAÇÃO DE CAUÇÃO\nPrestação de caução: Não\n\n15 - FORNECIMENTO DAS PEÇAS DO CONCURSO, APRESENTAÇÃO DE PEDIDOS DE PARTICIPAÇÃO E APRESENTAÇÃO DAS PROPOSTAS\nLink para acesso às peças do concurso (URL): https://community.vortal.biz/Public/public-tender-documents/MXcvR0krdmw4NSt0THJubjl0QXhKU0dBTGhUcERhZ2VOTkg4YnBjNDZJbHhVUTMyREZIOGF2OWV0Q2hBMm1NLzN5S0lUYmM2WEFZckYrZFAwNzJjTUE9PUpJdkVj\n\n20 - OUTROS REQUISITOS\nInformação sobre contratos reservados. Aplica-se a contratos reservados (54º-A)? Não\n\n21 - CRITÉRIO DE ADJUDICAÇÃO\nMultifator: Não\nMonofator:\nNome: Preço\n\n24 - CONDIÇÕES DO CONTRATO\nFaturação Eletrónica: Permitido\nObrigação de Subcontratação:\nCódigo da Obrigação de Subcontratação: Não é aplicável nenhuma obrigação de subcontratação.\n\n25 - COMPRA PÚBLICA ESTRATÉGICA\nCompra Pública Estratégica: Inexistência de contratação pública estratégica\n\n26 - INFORMAÇÕES ADICIONAIS\nContrato adequado para PME: Sim\nCobertura ACP (Acordo dos Contratos Públicos da Organização Mundial do Comércio): Não\n\n27 - IDENTIFICAÇÃO E CONTACTOS DO ÓRGÃO DE RECURSOS ADMINISTRATIVOS\nDesignação: Câmara Municipal de Sintra\nEndereço: Largo Dr. Virgílio Horta\nCódigo postal: 2714-501\nLocalidade: Sintra\nTelefone: +351 219238500\nFax: +351 219238657\nEndereço eletrónico: geral@cm-sintra.pt\n\n28 - IDENTIFICAÇÃO DO(S) AUTOR(ES) DE ANÚNCIO\nNome: Basílio Adolfo Mendonça Horta da Franca\nCargo: Presidente do Conselho de Administração dos SMAS-Sintra\n419583617",
    "nipc": "680000054",
    "distrito": "Lisboa",
    "concelho": "Sintra",
    "freguesia": "Todas",
    "site": "www.smas-sintra.pt",
    "email": "aprov.stocks@smas-sintra.pt",
    "designacao_contrato": "Concurso Público nº 37PF/2025 – Aquisição de Ergelit Superfix 35 ou Equivalente",
    "descricao": "Aquisição de Ergelit Superfix 35 ou Equivalente",
    "preco_base": "48.478,50 EUR",
    "prazo_execucao": "1 ANOS",
    "prazo_apresentacao_propostas": "13-10-2025 17:00",
    "fundos_eu": "Não",
    "plataforma_eletronica": "VORTAL",
    "url_procedimento": "https://community.vortal.biz/public/",
    "autor_nome": "Basílio Adolfo Mendonça Horta da Franca",
    "autor_cargo": "Presidente do Conselho de Administração dos SMAS-Sintra"
  },
  {
    "numero_procedimento": "N/A",
    "entidade": "Município do Porto",
    "link": "https://diariodarepublica.pt/dr/detalhe/contrato-publico/25644-937193352",
    "detalhes_completos": "1 - IDENTIFICAÇÃO E CONTACTOS DA ENTIDADE ADJUDICANTE\nDesignação da entidade adjudicante: Município do Porto\nNIPC: 501306099\nServiço/Órgão/Pessoa de contacto: Divisão Municipal de Compras Gerais\nEndereço: Rua do Bolhão, 162, 6.º piso\nCódigo postal: 4000-111\nLocalidade: Porto\nPaís: Portugal\nNUT III: PT11A\nDistrito: Porto\nConcelho: Porto\nFreguesia: União das Freguesias de Cedofeita, Santo Ildefonso, Sé, Miragaia, São Nicolau e Vitória\nTelefone: 222097216\nFax: 222097296\nEndereço da Entidade (URL): http://www.cm-porto.pt\nEndereço Eletrónico: suportepce@cm-porto.pt\neDelivery Gateway (URL): https://www.acingov.pt\nFunção da Organização: Adquirente\nNorma jurídica da Entidade Adjudicante: Autoridade local\nÁrea de atividade da Autoridade Adjudicante: Serviços públicos das administrações públicas\n\n2 - JORNAL OFICIAL DA UNIÃO EUROPEIA\nO procedimento a que este anúncio diz respeito também é publicitado no Jornal Oficial da União Europeia? Não\n\n3 - AVISO\nModelo de Anúncio: Concurso público\nData de Envio do Anúncio: 29-09-2025\n\n5 - PROCESSO\nTipo de Procedimento: Concurso público\nPreço base do procedimento: Sim\nValor do preço base do procedimento: 77.900,00 EUR\nProcedimento com lotes? Não\n\n6 - OBJETO DO CONTRATO\nNúmero de referência interna: CP/52/2025/DMCG\nDesignação do contrato: Locação de casas de madeira.\nDescrição: Locação de casas de madeira\n\nTipo de Contrato Principal: Locação de Bens Móveis\nTipo de Contrato: Locação de Bens Móveis; Aquisição de Serviços\nClassificação CPV (Vocabulário Comum para os Contratos Públicos)\nObjeto principal\nVocabulário Principal: 44211100\nPreço base s/IVA: 58.800,00 EUR\nObjeto Complementar\nVocabulário Principal: 63111000\nPreço base s/IVA: 6.600,00 EUR\nObjeto Complementar\nVocabulário Principal: 71356200\nPreço base s/IVA: 1.500,00 EUR\nObjeto Complementar\nVocabulário Principal: 71314100\nPreço base s/IVA: 11.000,00 EUR\n\n7 - INDICAÇÕES ADICIONAIS\nO contrato envolve aquisição conjunta (satisfação de várias entidades)? Não\nO contrato é adjudicado por uma central de compras? Não\n\n8 - TÉCNICAS\nO concurso destina-se à celebração de um acordo-quadro? Inexistência de acordo-quadro\nÉ utilizado um leilão eletrónico? Não\nÉ adotada uma fase de negociação? Não\nSistema de Aquisição Dinâmico: Inexistência de sistema de aquisição dinâmico\n\n9 - LOCAL DA EXECUÇÃO DO CONTRATO\nLOCAL DA EXECUÇÃO DO CONTRATO (PROCEDIMENTO)\nPaís: Portugal\nNUT III: PT11A\nLocalidade: Porto\nDistrito: Porto\nConcelho: Todos\nFreguesia: Todas\n\n10 - PRAZO DE EXECUÇÃO DO CONTRATO\nPrazo de execução do contrato: 6 MESES\nPrevisão de renovações: Não\n\n11 - FUNDOS EU\nTêm fundos EU? Não\n\n12 - DOCUMENTOS DE HABILITAÇÃO\nHabilitação para o exercício da atividade profissional: Não\n\n13 - CONDIÇÕES DE APRESENTAÇÃO\nPlataforma eletrónica utilizada pela entidade adjudicante: ACIN\nURL para Apresentação: https://www.acingov.pt\nAdmissibilidade da apresentação de propostas variantes: Não autorizado\nPrazo para apresentação das propostas: 08-10-2025 17:00\nPrazo durante o qual os concorrentes são obrigados a manter as respetivas propostas: 66 dias a contar do termo do prazo para a apresentação das propostas\nIndicação de Subcontratação na Proposta: Inexistência de indicação de subcontratação\n\n14 - PRESTAÇÃO DE CAUÇÃO\nPrestação de caução: Não\n\n15 - FORNECIMENTO DAS PEÇAS DO CONCURSO, APRESENTAÇÃO DE PEDIDOS DE PARTICIPAÇÃO E APRESENTAÇÃO DAS PROPOSTAS\nLink para acesso às peças do concurso (URL): https://www.acingov.pt/acingovprod/2/zonaPublica/zona_publica_c/donwloadProcedurePiece/OTc3MjA4\n\n20 - OUTROS REQUISITOS\nInformação sobre contratos reservados. Aplica-se a contratos reservados (54º-A)? Não\n\n21 - CRITÉRIO DE ADJUDICAÇÃO\nMultifator: Não\nMonofator:\nNome: Preço\n\n24 - CONDIÇÕES DO CONTRATO\nFaturação Eletrónica: Necessário\nObrigação de Subcontratação:\nCódigo da Obrigação de Subcontratação: Não é aplicável nenhuma obrigação de subcontratação.\n\n25 - COMPRA PÚBLICA ESTRATÉGICA\nCompra Pública Estratégica: Inexistência de contratação pública estratégica\n\n26 - INFORMAÇÕES ADICIONAIS\nContrato adequado para PME: Sim\nCobertura ACP (Acordo dos Contratos Públicos da Organização Mundial do Comércio): Não\n\n27 - IDENTIFICAÇÃO E CONTACTOS DO ÓRGÃO DE RECURSOS ADMINISTRATIVOS\nDesignação: Divisão Municipal de Compras Gerais.\nEndereço: Rua do Bolhão,162.º-6º\nCódigo postal: 4000-111\nLocalidade: Porto\nTelefone: 222097216\nFax: 222097296\nEndereço eletrónico: dmcompras@cm-porto.pt\n\n28 - IDENTIFICAÇÃO DO(S) AUTOR(ES) DE ANÚNCIO\nNome: Vera Lúcia Nogueira Sampaio\nCargo: Chefe de Divisão Municipal de Compras Gerais\n419586711",
    "nipc": "501306099",
    "distrito": "Porto",
    "concelho": "Porto",
    "freguesia": "União das Freguesias de Cedofeita, Santo Ildefonso, Sé, Miragaia, São Nicolau e Vitória",
    "site": "http://www.cm-porto.pt",
    "email": "suportepce@cm-porto.pt",
    "designacao_contrato": "Locação de casas de madeira.",
    "descricao": "Locação de casas de madeira",
    "preco_base": "58.800,00 EUR",
    "prazo_execucao": "6 MESES",
    "prazo_apresentacao_propostas": "08-10-2025 17:00",
    "fundos_eu": "Não",
    "plataforma_eletronica": "ACIN",
    "url_procedimento": "https://www.acingov.pt",
    "autor_nome": "Vera Lúcia Nogueira Sampaio",
    "autor_cargo": "Chefe de Divisão Municipal de Compras Gerais"
  },
  {
    "numero_procedimento": "N/A",
    "entidade": "APRAM – Adm. dos Portos da Reg. Aut.da Madeira",
    "link": "https://diariodarepublica.pt/dr/detalhe/contrato-publico/25647-937193355",
    "detalhes_completos": "Alteração do Anúncio de procedimento n.º 24512/2025, de 2025-09-17, com o ID 419544242\n\n1 - IDENTIFICAÇÃO E CONTACTOS DA ENTIDADE ADJUDICANTE\nDesignação da entidade adjudicante: APRAM – Adm. dos Portos da Reg. Aut.da Madeira\nNIPC: 511137753\nEndereço: Gare Marítima da Madeira, Molhe da Pontinha, Porto do Funchal\nCódigo postal: 9004-518\nLocalidade: Região Autónoma da Madeira\nPaís: Portugal\nNUT III: PT300\nDistrito: Região Autónoma da Madeira\nConcelho: Funchal\nFreguesia: Freguesia de Sé (Funchal)\nTelefone: 291208600\nFax: 291220196\nEndereço da Entidade (URL): https://www.apram.pt\nEndereço Eletrónico: portosdamadeira@apram.pt\neDelivery Gateway (URL): https://community.vortal.biz/public/\nFunção da Organização: Adquirente\nNorma jurídica da Entidade Adjudicante: Empresa pública, controlada por uma autoridade regional\nÁrea de atividade da Entidade Adjudicante: Atividades portuárias\n\n2 - JORNAL OFICIAL DA UNIÃO EUROPEIA\nO procedimento a que este anúncio diz respeito também é publicitado no Jornal Oficial da União Europeia? Não\n\n3 - AVISO\nModelo de Anúncio: Concurso público\nData de Envio do Anúncio: 29-09-2025\n\n5 - PROCESSO\nTipo de Procedimento: Concurso público\nPreço base do procedimento: Sim\nValor do preço base do procedimento: 123.954,36 EUR\nProcedimento com lotes? Não\n\n6 - OBJETO DO CONTRATO\nNúmero de referência interna: 10.01.0048/10\nDesignação do contrato: Concurso Público para locação de licença para plataforma digital de Inventário de emissões provenientes de navios nos portos da APRAM, S.A.\nDescrição: Locação de licença para plataforma digital de Inventário de Emissões Provenientes de Navios nos Portos da APRAM, S.A.\nTipo de Contrato Principal: Aquisição de Serviços\nTipo de Contrato: Aquisição de Serviços\nClassificação CPV (Vocabulário Comum para os Contratos Públicos)\nObjeto principal\nVocabulário Principal: 72268000\nPreço base s/IVA: 123.954,36 EUR\n\n7 - INDICAÇÕES ADICIONAIS\nO contrato envolve aquisição conjunta (satisfação de várias entidades)? Não\nO contrato é adjudicado por uma central de compras? Não\n\n8 - TÉCNICAS\nO concurso destina-se à celebração de um acordo-quadro? Inexistência de acordo-quadro\nÉ utilizado um leilão eletrónico? Não\nÉ adotada uma fase de negociação? Não\nSistema de Aquisição Dinâmico: Inexistência de sistema de aquisição dinâmico\n\n9 - LOCAL DA EXECUÇÃO DO CONTRATO\nLOCAL DA EXECUÇÃO DO CONTRATO (PROCEDIMENTO)\nPaís: Portugal\nNUT III: PTZZZ\nLocalidade: PORTUGAL\nDistrito: Todos\nConcelho: Todos\nFreguesia: Todas\n\n10 - PRAZO DE EXECUÇÃO DO CONTRATO\nPrazo de execução do contrato: 3 ANOS\nPrevisão de renovações: Não\n\n11 - FUNDOS EU\nTêm fundos EU? Sim\n\n12 - DOCUMENTOS DE HABILITAÇÃO\nHabilitação para o exercício da atividade profissional: Sim\nTipo: Outros\nDescrição - Outros: Os constantes do programa do procedimento.\nDescrição: Os constantes do programa do procedimento.\n\n13 - CONDIÇÕES DE APRESENTAÇÃO\nPlataforma eletrónica utilizada pela entidade adjudicante: VORTAL\nURL para Apresentação: https://community.vortal.biz/public/\nAdmissibilidade da apresentação de propostas variantes: Não autorizado\nPrazo para apresentação das propostas: 02-10-2025 18:00\nPrazo durante o qual os concorrentes são obrigados a manter as respetivas propostas: 120 dias a contar do termo do prazo para a apresentação das propostas\nIndicação de Subcontratação na Proposta: Inexistência de indicação de subcontratação\n\n14 - PRESTAÇÃO DE CAUÇÃO\nPrestação de caução: Não\n\n15 - FORNECIMENTO DAS PEÇAS DO CONCURSO, APRESENTAÇÃO DE PEDIDOS DE PARTICIPAÇÃO E APRESENTAÇÃO DAS PROPOSTAS\nLink para acesso às peças do concurso (URL): https://community.vortal.biz/Public/public-tender-documents/c21QMUtBcXR0c0UvK25Ma0xqVmY2MWNXcTh1UHYyeWFOajhkV3NVMDVPT28xZkRwcnJwUDkyY1hHV0JFcVJjKzg4ZDAxVFBpTCt1QTBHVUMrT3BQU0E9PWdaU0sm\n\n20 - OUTROS REQUISITOS\nInformação sobre contratos reservados. Aplica-se a contratos reservados (54º-A)? Não\n\n21 - CRITÉRIO DE ADJUDICAÇÃO\nMultifator: Não\nMonofator:\nNome: Outros\nOutro nome: Preço mais baixo proposto\n\n24 - CONDIÇÕES DO CONTRATO\nFaturação Eletrónica: Permitido\nObrigação de Subcontratação:\nCódigo da Obrigação de Subcontratação: Não é aplicável nenhuma obrigação de subcontratação.\n\n25 - COMPRA PÚBLICA ESTRATÉGICA\nCompra Pública Estratégica: Inexistência de contratação pública estratégica\n\n26 - INFORMAÇÕES ADICIONAIS\nContrato adequado para PME: Sim\nCobertura ACP (Acordo dos Contratos Públicos da Organização Mundial do Comércio): Não\n\n27 - IDENTIFICAÇÃO E CONTACTOS DO ÓRGÃO DE RECURSOS ADMINISTRATIVOS\nDesignação: Conselho de Administração da APRAM, S.A.\nEndereço: Gare Marítima da Madeira\nCódigo postal: 9004-518\nLocalidade: Funchal\nTelefone: +351 291208600\nFax: +351 291220196\nEndereço eletrónico: portosdamadeira@apram.pt\n\n28 - IDENTIFICAÇÃO DO(S) AUTOR(ES) DE ANÚNCIO\nNome: Paula Cristina de Araújo Dias Cabaço da Silva\nCargo: Presidente do Conselho de Administração da \n\n29 - ALTERAÇÃO\nMotivo da Alteração: Informações atualizadas\nIdentificador da Versão do Anúncio a Alterar: f5c0dab9-3dbe-4198-946e-d6252cd033d4-01\nIdentificador das Secções Alteradas do Anúncio Anterior: Condições de Apresentação\nDescrição das Alterações: Alteração do prazo de entrega de propostas.\nAlteração dos Documentos do Concurso: Não\n419591522",
    "nipc": "511137753",
    "distrito": "Região Autónoma da Madeira",
    "concelho": "Funchal",
    "freguesia": "Freguesia de Sé (Funchal)",
    "site": "https://www.apram.pt",
    "email": "portosdamadeira@apram.pt",
    "designacao_contrato": "Concurso Público para locação de licença para plataforma digital de Inventário de emissões provenientes de navios nos portos da APRAM, S.A.",
    "descricao": "Locação de licença para plataforma digital de Inventário de Emissões Provenientes de Navios nos Portos da APRAM, S.A.",
    "preco_base": "123.954,36 EUR",
    "prazo_execucao": "3 ANOS",
    "prazo_apresentacao_propostas": "02-10-2025 18:00",
    "fundos_eu": "Sim",
    "plataforma_eletronica": "VORTAL",
    "url_procedimento": "https://community.vortal.biz/public/",
    "autor_nome": "Paula Cristina de Araújo Dias Cabaço da Silva",
    "autor_cargo": "Presidente do Conselho de Administração da"
  },
  {
    "numero_procedimento": "N/A",
    "entidade": "Escola Secundária José Saramago, Mafra",
    "link": "https://diariodarepublica.pt/dr/detalhe/contrato-publico/25648-937193356",
    "detalhes_completos": "1 - IDENTIFICAÇÃO E CONTACTOS DA ENTIDADE ADJUDICANTE\nDesignação da entidade adjudicante: Escola Secundária José Saramago, Mafra\nNIPC: 600020290\nEndereço: Av. Cidade de Leimen\nCódigo postal: 2640-470\nLocalidade: Lisboa\nPaís: Portugal\nNUT III: PT170\nDistrito: Lisboa\nConcelho: Mafra\nFreguesia: Freguesia de Mafra\nTelefone: 261811194\nEndereço da Entidade (URL): https://escola.esjs-mafra.net/\nEndereço Eletrónico: direcao@esjs-mafra.net\neDelivery Gateway (URL): https://community.vortal.biz/public/\nFunção da Organização: Adquirente\nNorma jurídica da Entidade Adjudicante: Organismo de direito público\nÁrea de atividade da Autoridade Adjudicante: Educação\n\n2 - JORNAL OFICIAL DA UNIÃO EUROPEIA\nO procedimento a que este anúncio diz respeito também é publicitado no Jornal Oficial da União Europeia? Não\n\n3 - AVISO\nModelo de Anúncio: Concurso público\nData de Envio do Anúncio: 29-09-2025\n\n5 - PROCESSO\nTipo de Procedimento: Concurso público\nPreço base do procedimento: Sim\nValor do preço base do procedimento: 518.480,59 EUR\nProcedimento com lotes? Não\n\n6 - OBJETO DO CONTRATO\nNúmero de referência interna: CP05/ESJS/2025_IND\nDesignação do contrato: CP05/ESJS/2025_IND\nDescrição: Empreitada de obras públicas no âmbito do Centro Tecnológico Especializado\nTipo de Contrato Principal: Empreitada de Obras Públicas\nTipo de Contrato: Empreitada de Obras Públicas\nClassificação CPV (Vocabulário Comum para os Contratos Públicos)\nObjeto principal\nVocabulário Principal: 45113000\nPreço base s/IVA: 518.480,59 EUR\n\n7 - INDICAÇÕES ADICIONAIS\nO contrato envolve aquisição conjunta (satisfação de várias entidades)? Não\nO contrato é adjudicado por uma central de compras? Não\n\n8 - TÉCNICAS\nO concurso destina-se à celebração de um acordo-quadro? Inexistência de acordo-quadro\nÉ utilizado um leilão eletrónico? Não\nÉ adotada uma fase de negociação? Não\nSistema de Aquisição Dinâmico: Inexistência de sistema de aquisição dinâmico\n\n9 - LOCAL DA EXECUÇÃO DO CONTRATO\nLOCAL DA EXECUÇÃO DO CONTRATO (PROCEDIMENTO)\nPaís: Portugal\nNUT III: PT170\nLocalidade: Lisboa\nDistrito: Lisboa\nConcelho: Mafra\nFreguesia: Todas\n\n10 - PRAZO DE EXECUÇÃO DO CONTRATO\nPrazo de execução do contrato: 5 MESES\nPrevisão de renovações: Não\n\n11 - FUNDOS EU\nTêm fundos EU? Sim\n\n12 - DOCUMENTOS DE HABILITAÇÃO\nHabilitação para o exercício da atividade profissional: Não\n\n13 - CONDIÇÕES DE APRESENTAÇÃO\nPlataforma eletrónica utilizada pela entidade adjudicante: VORTAL\nURL para Apresentação: https://community.vortal.biz/public/\nAdmissibilidade da apresentação de propostas variantes: Não autorizado\nPrazo para apresentação das propostas: 16-10-2025 23:59\nPrazo durante o qual os concorrentes são obrigados a manter as respetivas propostas: 90 dias a contar do termo do prazo para a apresentação das propostas\nIndicação de Subcontratação na Proposta: Inexistência de indicação de subcontratação\n\n14 - PRESTAÇÃO DE CAUÇÃO\nPrestação de caução: Sim\nPercentagem: 5%\nDescrição da Garantia Exigida: Garantia Bancária (preferencial) \n\n15 - FORNECIMENTO DAS PEÇAS DO CONCURSO, APRESENTAÇÃO DE PEDIDOS DE PARTICIPAÇÃO E APRESENTAÇÃO DAS PROPOSTAS\nLink para acesso às peças do concurso (URL): https://community.vortal.biz/Public/public-tender-documents/RnZEajJ5Rjlwc3RqRWVGcFZJOG03ZWgyREE5Mm1RRndJait2UFNnOUlSa0M0KzVEYzJsNW8yL0dscnZpcGlFSWoyZGN6V1NrbWhkTEV3dVRuaU9UVlE9PVVUREFh\n\n20 - OUTROS REQUISITOS\nInformação sobre contratos reservados. Aplica-se a contratos reservados (54º-A)? Não\n\n21 - CRITÉRIO DE ADJUDICAÇÃO\nMultifator: Sim\nFator: \nNome: Preço\nPonderação: 40%\nSubfatores: Não\nFator: \nNome: Qualidade\nPonderação: 60%\nSubfatores: Não\n\n24 - CONDIÇÕES DO CONTRATO\nFaturação Eletrónica: Permitido\nObrigação de Subcontratação:\nCódigo da Obrigação de Subcontratação: Não é aplicável nenhuma obrigação de subcontratação.\n\n25 - COMPRA PÚBLICA ESTRATÉGICA\nCompra Pública Estratégica: Inexistência de contratação pública estratégica\n\n26 - INFORMAÇÕES ADICIONAIS\nContrato adequado para PME: Sim\nCobertura ACP (Acordo dos Contratos Públicos da Organização Mundial do Comércio): Não\n\n27 - IDENTIFICAÇÃO E CONTACTOS DO ÓRGÃO DE RECURSOS ADMINISTRATIVOS\nDesignação: Conselho Administrativo\nEndereço: Avenida Cidade de Leimen\nCódigo postal: 2640-470\nLocalidade: Mafra\nTelefone: +351 261811194\nFax: +351 261811194\nEndereço eletrónico: direcao@esjs-mafra.net\n\n28 - IDENTIFICAÇÃO DO(S) AUTOR(ES) DE ANÚNCIO\nNome: Pedro Liberto Ferreira \nCargo: Diretor\n419591571",
    "nipc": "600020290",
    "distrito": "Lisboa",
    "concelho": "Mafra",
    "freguesia": "Freguesia de Mafra",
    "site": "https://escola.esjs-mafra.net/",
    "email": "direcao@esjs-mafra.net",
    "designacao_contrato": "CP05/ESJS/2025_IND",
    "descricao": "Empreitada de obras públicas no âmbito do Centro Tecnológico Especializado",
    "preco_base": "518.480,59 EUR",
    "prazo_execucao": "5 MESES",
    "prazo_apresentacao_propostas": "16-10-2025 23:59",
    "fundos_eu": "Sim",
    "plataforma_eletronica": "VORTAL",
    "url_procedimento": "https://community.vortal.biz/public/",
    "autor_nome": "Pedro Liberto Ferreira",
    "autor_cargo": "Diretor"
  },
  {
    "numero_procedimento": "N/A",
    "entidade": "Município de Santo Tirso",
    "link": "https://diariodarepublica.pt/dr/detalhe/contrato-publico/25649-937193357",
    "detalhes_completos": "1 - IDENTIFICAÇÃO E CONTACTOS DA ENTIDADE ADJUDICANTE\nDesignação da entidade adjudicante: Município de Santo Tirso\nNIPC: 501306870\nEndereço: Praça 25 de Abril\nCódigo postal: 4780-373\nLocalidade: Área Metropolitana do Porto\nPaís: Portugal\nNUT III: PT11A\nDistrito: Porto\nConcelho: Santo Tirso\nFreguesia: União das Freguesias de Santo Tirso, Couto (Santa Cristina e São Miguel) e Burgães\nTelefone: 252830400\nFax: 252856534\nEndereço da Entidade (URL): www.cm-stirso.pt\nEndereço Eletrónico: santotirso@cm-stirso.pt\neDelivery Gateway (URL): https://community.vortal.biz/public/\nFunção da Organização: Adquirente\nNorma jurídica da Entidade Adjudicante: Autoridade local\nÁrea de atividade da Autoridade Adjudicante: Serviços públicos das administrações públicas\n\n2 - JORNAL OFICIAL DA UNIÃO EUROPEIA\nO procedimento a que este anúncio diz respeito também é publicitado no Jornal Oficial da União Europeia? Não\n\n3 - AVISO\nModelo de Anúncio: Concurso público\nData de Envio do Anúncio: 29-09-2025\n\n5 - PROCESSO\nTipo de Procedimento: Concurso público\nPreço base do procedimento: Sim\nValor do preço base do procedimento: 42.768,00 EUR\nProcedimento com lotes? Não\n\n6 - OBJETO DO CONTRATO\nNúmero de referência interna: NIPG25253/25\nDesignação do contrato: Contrato de prestação de serviços na modalidade de tarefa para aulas de karaté adaptado e defesa pessoal - Santo Tirso Ativo\nDescrição: Contrato de prestação de serviços na modalidade de tarefa para aulas de karaté adaptado e defesa pessoal - Santo Tirso Ativo\nTipo de Contrato Principal: Aquisição de Serviços\nTipo de Contrato: Aquisição de Serviços\nClassificação CPV (Vocabulário Comum para os Contratos Públicos)\nObjeto principal\nVocabulário Principal: 98330000\nPreço base s/IVA: 42.768,00 EUR\n\n7 - INDICAÇÕES ADICIONAIS\nO contrato envolve aquisição conjunta (satisfação de várias entidades)? Não\nO contrato é adjudicado por uma central de compras? Não\n\n8 - TÉCNICAS\nO concurso destina-se à celebração de um acordo-quadro? Inexistência de acordo-quadro\nÉ utilizado um leilão eletrónico? Não\nÉ adotada uma fase de negociação? Não\nSistema de Aquisição Dinâmico: Inexistência de sistema de aquisição dinâmico\n\n9 - LOCAL DA EXECUÇÃO DO CONTRATO\nLOCAL DA EXECUÇÃO DO CONTRATO (PROCEDIMENTO)\nPaís: Portugal\nNUT III: PT11A\nLocalidade: Área Metropolitana do Porto\nDistrito: Porto\nConcelho: Santo Tirso\nFreguesia: União das Freguesias de Santo Tirso, Couto (Santa Cristina e São Miguel) e Burgães\n\n10 - PRAZO DE EXECUÇÃO DO CONTRATO\nPrazo de execução do contrato: 32 MESES\nPrevisão de renovações: Não\n\n11 - FUNDOS EU\nTêm fundos EU? Não\n\n12 - DOCUMENTOS DE HABILITAÇÃO\nHabilitação para o exercício da atividade profissional: Não\n\n13 - CONDIÇÕES DE APRESENTAÇÃO\nPlataforma eletrónica utilizada pela entidade adjudicante: VORTAL\nURL para Apresentação: https://community.vortal.biz/public/\nAdmissibilidade da apresentação de propostas variantes: Não autorizado\nPrazo para apresentação das propostas: 09-10-2025 17:30\nPrazo durante o qual os concorrentes são obrigados a manter as respetivas propostas: 66 dias a contar do termo do prazo para a apresentação das propostas\nIndicação de Subcontratação na Proposta: Inexistência de indicação de subcontratação\n\n14 - PRESTAÇÃO DE CAUÇÃO\nPrestação de caução: Não\n\n15 - FORNECIMENTO DAS PEÇAS DO CONCURSO, APRESENTAÇÃO DE PEDIDOS DE PARTICIPAÇÃO E APRESENTAÇÃO DAS PROPOSTAS\nLink para acesso às peças do concurso (URL): https://community.vortal.biz/Public/public-tender-documents/RkJnMTZJNyttK2dpYnhmeGJ5b1NlanljQjNPSW5qdDI0V0RYVytZT1daT283QlVCMUI1ekdmSmxucEc0R3Yxd0dVVUZUNXozNllwamhiSzRWZWJ1Y1E9PXUyQGlj\n\n20 - OUTROS REQUISITOS\nInformação sobre contratos reservados. Aplica-se a contratos reservados (54º-A)? Não\n\n21 - CRITÉRIO DE ADJUDICAÇÃO\nMultifator: Não\nMonofator:\nNome: Outros\nOutro nome: Preço\n\n24 - CONDIÇÕES DO CONTRATO\nFaturação Eletrónica: Permitido\nObrigação de Subcontratação:\nCódigo da Obrigação de Subcontratação: Não é aplicável nenhuma obrigação de subcontratação.\n\n25 - COMPRA PÚBLICA ESTRATÉGICA\nCompra Pública Estratégica: Inexistência de contratação pública estratégica\n\n26 - INFORMAÇÕES ADICIONAIS\nContrato adequado para PME: Sim\nCobertura ACP (Acordo dos Contratos Públicos da Organização Mundial do Comércio): Não\n\n27 - IDENTIFICAÇÃO E CONTACTOS DO ÓRGÃO DE RECURSOS ADMINISTRATIVOS\nDesignação: Câmara Municipal de Santo Tirso\nEndereço: Praça 25 de abril\nCódigo postal: 4780-373\nLocalidade: Santo Tirso\nTelefone: +351 252830400\nFax: +351 252856534\nEndereço eletrónico: santotirso@cm-stirso.pt\n\n28 - IDENTIFICAÇÃO DO(S) AUTOR(ES) DE ANÚNCIO\nNome: Alberto Manuel Martins da Costa\nCargo: Presidente da Câmara\n419591028",
    "nipc": "501306870",
    "distrito": "Porto",
    "concelho": "Santo Tirso",
    "freguesia": "União das Freguesias de Santo Tirso, Couto (Santa Cristina e São Miguel) e Burgães",
    "site": "www.cm-stirso.pt",
    "email": "santotirso@cm-stirso.pt",
    "designacao_contrato": "Contrato de prestação de serviços na modalidade de tarefa para aulas de karaté adaptado e defesa pessoal - Santo Tirso Ativo",
    "descricao": "Contrato de prestação de serviços na modalidade de tarefa para aulas de karaté adaptado e defesa pessoal - Santo Tirso Ativo",
    "preco_base": "42.768,00 EUR",
    "prazo_execucao": "32 MESES",
    "prazo_apresentacao_propostas": "09-10-2025 17:30",
    "fundos_eu": "Não",
    "plataforma_eletronica": "VORTAL",
    "url_procedimento": "https://community.vortal.biz/public/",
    "autor_nome": "Alberto Manuel Martins da Costa",
    "autor_cargo": "Presidente da Câmara"
  },
  {
    "numero_procedimento": "N/A",
    "entidade": "Município de Ponte da Barca",
    "link": "https://diariodarepublica.pt/dr/detalhe/contrato-publico/25650-937193358",
    "detalhes_completos": "1 - IDENTIFICAÇÃO E CONTACTOS DA ENTIDADE ADJUDICANTE\nDesignação da entidade adjudicante: Município de Ponte da Barca\nNIPC: 505676770\nEndereço: Praça Dr. António Lacerda\nCódigo postal: 4980-626\nLocalidade: Ponte da Barca\nPaís: Portugal\nNUT III: PT111\nDistrito: Viana do Castelo\nConcelho: Ponte da Barca\nFreguesia: Todas\nTelefone: 258480180\nFax: 258480189\nEndereço da Entidade (URL): www.cmpb.pt\nEndereço Eletrónico: informatica@cmpb.pt\neDelivery Gateway (URL): https://community.vortal.biz/public/\nFunção da Organização: Adquirente\nNorma jurídica da Entidade Adjudicante: Autoridade local\nÁrea de atividade da Autoridade Adjudicante: Serviços públicos das administrações públicas\n\n2 - JORNAL OFICIAL DA UNIÃO EUROPEIA\nO procedimento a que este anúncio diz respeito também é publicitado no Jornal Oficial da União Europeia? Não\n\n3 - AVISO\nModelo de Anúncio: Concurso público\nData de Envio do Anúncio: 29-09-2025\n\n5 - PROCESSO\nTipo de Procedimento: Concurso público\nPreço base do procedimento: Sim\nValor do preço base do procedimento: 334.582,16 EUR\nProcedimento com lotes? Não\n\n6 - OBJETO DO CONTRATO\nNúmero de referência interna: E_29/2025\nDesignação do contrato: Execução e Expansão de Rede de Saneamento em Vila Nova de Muía em Ponte da Barca\nDescrição: Execução e Expansão de Rede de Saneamento em Vila Nova de Muía em Ponte da Barca - Rua de Muía, Travessa de Muía, Travessa do Couto, Rua de Souto Movos, Travessa de Quintela de Cima, Rua de Quintela de Cima e Rua da Venda\nTipo de Contrato Principal: Empreitada de Obras Públicas\nTipo de Contrato: Empreitada de Obras Públicas\nClassificação CPV (Vocabulário Comum para os Contratos Públicos)\nObjeto principal\nVocabulário Principal: 45232460\nPreço base s/IVA: 334.582,16 EUR\n\n7 - INDICAÇÕES ADICIONAIS\nO contrato envolve aquisição conjunta (satisfação de várias entidades)? Não\nO contrato é adjudicado por uma central de compras? Não\n\n8 - TÉCNICAS\nO concurso destina-se à celebração de um acordo-quadro? Inexistência de acordo-quadro\nÉ utilizado um leilão eletrónico? Não\nÉ adotada uma fase de negociação? Não\nSistema de Aquisição Dinâmico: Inexistência de sistema de aquisição dinâmico\n\n9 - LOCAL DA EXECUÇÃO DO CONTRATO\nLOCAL DA EXECUÇÃO DO CONTRATO (PROCEDIMENTO)\nPaís: Portugal\nNUT III: PTZZZ\nLocalidade: PORTUGAL\nDistrito: Todos\nConcelho: Todos\nFreguesia: Todas\n\n10 - PRAZO DE EXECUÇÃO DO CONTRATO\nPrazo de execução do contrato: 180 DIAS\nPrevisão de renovações: Não\n\n11 - FUNDOS EU\nTêm fundos EU? Não\n\n12 - DOCUMENTOS DE HABILITAÇÃO\nHabilitação para o exercício da atividade profissional: Sim\nTipo: Alvará\nDescrição: Alvará - 6.ª subcategoria da 2.ª categoria - Saneamento Básico\n\n13 - CONDIÇÕES DE APRESENTAÇÃO\nPlataforma eletrónica utilizada pela entidade adjudicante: VORTAL\nURL para Apresentação: https://community.vortal.biz/public/\nAdmissibilidade da apresentação de propostas variantes: Não autorizado\nPrazo para apresentação das propostas: 20-10-2025 23:59\nPrazo durante o qual os concorrentes são obrigados a manter as respetivas propostas: 66 dias a contar do termo do prazo para a apresentação das propostas\nIndicação de Subcontratação na Proposta: Inexistência de indicação de subcontratação\n\n14 - PRESTAÇÃO DE CAUÇÃO\nPrestação de caução: Sim\nPercentagem: 10%\nDescrição da Garantia Exigida: Por depósito em dinheiro ou em títulos emitidos ou garantidos pelo Estado Português à ordem da entidade que for indicada pelo Município de Ponte da Barca ou mediante garantia bancária ou seguro-caução.\n\n15 - FORNECIMENTO DAS PEÇAS DO CONCURSO, APRESENTAÇÃO DE PEDIDOS DE PARTICIPAÇÃO E APRESENTAÇÃO DAS PROPOSTAS\nLink para acesso às peças do concurso (URL): https://community.vortal.biz/Public/public-tender-documents/bXdHclZjWVpwc3V1NmJGK0dKRTYyUFlaLzA1WXBmTjBZQTllVDBkTW5tbzNwOEJJMHBMZ0IrUVZ6b1ptWDF5YTl3K3JmbnBxWS9yeEFuMGVVaU5Hcnc9PUBlU3Ik\n\n20 - OUTROS REQUISITOS\nInformação sobre contratos reservados. Aplica-se a contratos reservados (54º-A)? Não\n\n21 - CRITÉRIO DE ADJUDICAÇÃO\nMultifator: Sim\nFator: \nNome: Preço\nPonderação: 80%\nSubfatores: Não\nFator: \nNome: Qualidade\nPonderação: 20%\nSubfatores: Sim\nSubfatores: \nNome: Número de anos acima do prazo legal, previsto na alínea a) do nº 2 do artigo 397º do CCP\nPonderação : 20%; \nNome: Número de anos acima do prazo legal, previsto na alínea b) do nº 2 do artigo 397º do CCP\nPonderação : 40%; \nNome: Número de anos acima do prazo legal, previsto na alínea c) do nº 2 do artigo 397º do CCP\nPonderação : 40%; \n\n24 - CONDIÇÕES DO CONTRATO\nFaturação Eletrónica: Permitido\nObrigação de Subcontratação:\nCódigo da Obrigação de Subcontratação: Não é aplicável nenhuma obrigação de subcontratação.\n\n25 - COMPRA PÚBLICA ESTRATÉGICA\nCompra Pública Estratégica: Inexistência de contratação pública estratégica\n\n26 - INFORMAÇÕES ADICIONAIS\nContrato adequado para PME: Sim\nCobertura ACP (Acordo dos Contratos Públicos da Organização Mundial do Comércio): Não\n\n27 - IDENTIFICAÇÃO E CONTACTOS DO ÓRGÃO DE RECURSOS ADMINISTRATIVOS\nDesignação: Presidente da Câmara Municipal de Ponte da Barca\nEndereço: Praça Dr. António Lacerda\nCódigo postal: 4980-626\nLocalidade: Ponte da Barca\nTelefone: +351 258480180\nFax: +351 258480180\nEndereço eletrónico: geral@cmpb.pt\n\n28 - IDENTIFICAÇÃO DO(S) AUTOR(ES) DE ANÚNCIO\nNome: Augusto Manuel dos Reis Marinho\nCargo: Presidente da Cãmara Municipal\n419590631",
    "nipc": "505676770",
    "distrito": "Viana do Castelo",
    "concelho": "Ponte da Barca",
    "freguesia": "Todas",
    "site": "www.cmpb.pt",
    "email": "informatica@cmpb.pt",
    "designacao_contrato": "Execução e Expansão de Rede de Saneamento em Vila Nova de Muía em Ponte da Barca",
    "descricao": "Execução e Expansão de Rede de Saneamento em Vila Nova de Muía em Ponte da Barca - Rua de Muía, Travessa de Muía, Travessa do Couto, Rua de Souto Movos, Travessa de Quintela de Cima, Rua de Quintela de Cima e Rua da Venda",
    "preco_base": "334.582,16 EUR",
    "prazo_execucao": "180 DIAS",
    "prazo_apresentacao_propostas": "20-10-2025 23:59",
    "fundos_eu": "Não",
    "plataforma_eletronica": "VORTAL",
    "url_procedimento": "https://community.vortal.biz/public/",
    "autor_nome": "Augusto Manuel dos Reis Marinho",
    "autor_cargo": "Presidente da Cãmara Municipal"
  },
  {
    "numero_procedimento": "N/A",
    "entidade": "Município de Ponte da Barca",
    "link": "https://diariodarepublica.pt/dr/detalhe/contrato-publico/25651-937193359",
    "detalhes_completos": "1 - IDENTIFICAÇÃO E CONTACTOS DA ENTIDADE ADJUDICANTE\nDesignação da entidade adjudicante: Município de Ponte da Barca\nNIPC: 505676770\nEndereço: Praça Dr. António Lacerda\nCódigo postal: 4980-626\nLocalidade: Ponte da Barca\nPaís: Portugal\nNUT III: PT111\nDistrito: Viana do Castelo\nConcelho: Ponte da Barca\nFreguesia: Todas\nTelefone: 258480180\nFax: 258480189\nEndereço da Entidade (URL): www.cmpb.pt\nEndereço Eletrónico: informatica@cmpb.pt\neDelivery Gateway (URL): https://community.vortal.biz/public/\nFunção da Organização: Adquirente\nNorma jurídica da Entidade Adjudicante: Autoridade local\nÁrea de atividade da Autoridade Adjudicante: Serviços públicos das administrações públicas\n\n2 - JORNAL OFICIAL DA UNIÃO EUROPEIA\nO procedimento a que este anúncio diz respeito também é publicitado no Jornal Oficial da União Europeia? Não\n\n3 - AVISO\nModelo de Anúncio: Concurso público\nData de Envio do Anúncio: 29-09-2025\n\n5 - PROCESSO\nTipo de Procedimento: Concurso público\nPreço base do procedimento: Sim\nValor do preço base do procedimento: 324.588,60 EUR\nProcedimento com lotes? Não\n\n6 - OBJETO DO CONTRATO\nNúmero de referência interna: E_28/2025\nDesignação do contrato: Execução e Expansão de Rede de Saneamento na Rua de Santa Catarina - Nogueira Ponte da Barca\nDescrição: Execução e Expansão de Rede de Saneamento na Rua de Santa Catarina - Nogueira Ponte da Barca\nTipo de Contrato Principal: Empreitada de Obras Públicas\nTipo de Contrato: Empreitada de Obras Públicas\nClassificação CPV (Vocabulário Comum para os Contratos Públicos)\nObjeto principal\nVocabulário Principal: 45232460\nPreço base s/IVA: 324.588,60 EUR\n\n7 - INDICAÇÕES ADICIONAIS\nO contrato envolve aquisição conjunta (satisfação de várias entidades)? Não\nO contrato é adjudicado por uma central de compras? Não\n\n8 - TÉCNICAS\nO concurso destina-se à celebração de um acordo-quadro? Inexistência de acordo-quadro\nÉ utilizado um leilão eletrónico? Não\nÉ adotada uma fase de negociação? Não\nSistema de Aquisição Dinâmico: Inexistência de sistema de aquisição dinâmico\n\n9 - LOCAL DA EXECUÇÃO DO CONTRATO\nLOCAL DA EXECUÇÃO DO CONTRATO (PROCEDIMENTO)\nPaís: Portugal\nNUT III: PTZZZ\nLocalidade: PORTUGAL\nDistrito: Todos\nConcelho: Todos\nFreguesia: Todas\n\n10 - PRAZO DE EXECUÇÃO DO CONTRATO\nPrazo de execução do contrato: 150 DIAS\nPrevisão de renovações: Não\n\n11 - FUNDOS EU\nTêm fundos EU? Não\n\n12 - DOCUMENTOS DE HABILITAÇÃO\nHabilitação para o exercício da atividade profissional: Sim\nTipo: Alvará\nDescrição: Alvará - 6.ª subcategoria da 2.ª categoria - Saneamento Básico\n\n13 - CONDIÇÕES DE APRESENTAÇÃO\nPlataforma eletrónica utilizada pela entidade adjudicante: VORTAL\nURL para Apresentação: https://community.vortal.biz/public/\nAdmissibilidade da apresentação de propostas variantes: Não autorizado\nPrazo para apresentação das propostas: 20-10-2025 23:59\nPrazo durante o qual os concorrentes são obrigados a manter as respetivas propostas: 66 dias a contar do termo do prazo para a apresentação das propostas\nIndicação de Subcontratação na Proposta: Inexistência de indicação de subcontratação\n\n14 - PRESTAÇÃO DE CAUÇÃO\nPrestação de caução: Sim\nPercentagem: 10%\nDescrição da Garantia Exigida: Por depósito em dinheiro ou em títulos emitidos ou garantidos pelo Estado Português à ordem da entidade que for indicada pelo Município de Ponte da Barca ou mediante garantia bancária ou seguro-caução.\n\n15 - FORNECIMENTO DAS PEÇAS DO CONCURSO, APRESENTAÇÃO DE PEDIDOS DE PARTICIPAÇÃO E APRESENTAÇÃO DAS PROPOSTAS\nLink para acesso às peças do concurso (URL): https://community.vortal.biz/Public/public-tender-documents/MFJhNnZYVHNZQm5xUzZMSUF2VkRYZVBMVlVmdUtLNFZtZXF4eE5wc2xadHlQd1pRMHpwNWZ2NWtScHd1aHJwQm1meWppQ3BUOHh2Ymw1aFAxR2NFRWc9PSNnb1Qx\n\n20 - OUTROS REQUISITOS\nInformação sobre contratos reservados. Aplica-se a contratos reservados (54º-A)? Não\n\n21 - CRITÉRIO DE ADJUDICAÇÃO\nMultifator: Sim\nFator: \nNome: Preço\nPonderação: 80%\nSubfatores: Não\nFator: \nNome: Qualidade\nPonderação: 20%\nSubfatores: Sim\nSubfatores: \nNome: Número de anos acima do prazo legal, previsto na alínea a) do nº 2 do artigo 397º do CCP\nPonderação : 20%; \nNome: Número de anos acima do prazo legal, previsto na alínea b) do nº 2 do artigo 397º do CCP\nPonderação : 40%; \nNome: Número de anos acima do prazo legal, previsto na alínea c) do nº 2 do artigo 397º do CCP\nPonderação : 40%; \n\n24 - CONDIÇÕES DO CONTRATO\nFaturação Eletrónica: Permitido\nObrigação de Subcontratação:\nCódigo da Obrigação de Subcontratação: Não é aplicável nenhuma obrigação de subcontratação.\n\n25 - COMPRA PÚBLICA ESTRATÉGICA\nCompra Pública Estratégica: Inexistência de contratação pública estratégica\n\n26 - INFORMAÇÕES ADICIONAIS\nContrato adequado para PME: Sim\nCobertura ACP (Acordo dos Contratos Públicos da Organização Mundial do Comércio): Não\n\n27 - IDENTIFICAÇÃO E CONTACTOS DO ÓRGÃO DE RECURSOS ADMINISTRATIVOS\nDesignação: Presidente da Câmara Municipal de Ponte da Barca\nEndereço: Praça Dr. António Lacerda\nCódigo postal: 4980-626\nLocalidade: Ponte da Barca\nTelefone: +351 258480180\nFax: +351 258480180\nEndereço eletrónico: geral@cmpb.pt\n\n28 - IDENTIFICAÇÃO DO(S) AUTOR(ES) DE ANÚNCIO\nNome: Augusto Manuel dos Reis Marinho\nCargo: Presidente da Câmara Municipal\n419590007",
    "nipc": "505676770",
    "distrito": "Viana do Castelo",
    "concelho": "Ponte da Barca",
    "freguesia": "Todas",
    "site": "www.cmpb.pt",
    "email": "informatica@cmpb.pt",
    "designacao_contrato": "Execução e Expansão de Rede de Saneamento na Rua de Santa Catarina - Nogueira Ponte da Barca",
    "descricao": "Execução e Expansão de Rede de Saneamento na Rua de Santa Catarina - Nogueira Ponte da Barca",
    "preco_base": "324.588,60 EUR",
    "prazo_execucao": "150 DIAS",
    "prazo_apresentacao_propostas": "20-10-2025 23:59",
    "fundos_eu": "Não",
    "plataforma_eletronica": "VORTAL",
    "url_procedimento": "https://community.vortal.biz/public/",
    "autor_nome": "Augusto Manuel dos Reis Marinho",
    "autor_cargo": "Presidente da Câmara Municipal"
  },
  {
    "numero_procedimento": "N/A",
    "entidade": "Parques de Sintra-Monte da Lua, SA",
    "link": "https://diariodarepublica.pt/dr/detalhe/contrato-publico/25653-937193360",
    "detalhes_completos": "1 - IDENTIFICAÇÃO E CONTACTOS DA ENTIDADE ADJUDICANTE\nDesignação da entidade adjudicante: Parques de Sintra-Monte da Lua, SA\nNIPC: 505174839\nEndereço: ESTRADA MONSERRATE, PARQUE DE MONSERRATE\nCódigo postal: 2710-405\nLocalidade: Sintra\nPaís: Portugal\nNUT III: PT170\nDistrito: Lisboa\nConcelho: Sintra\nFreguesia: Todas\nTelefone: 219237300\nFax: 219237350\nEndereço da Entidade (URL): www.parquesdesintra.pt/pt/\nEndereço Eletrónico: viviane.crouzier@parquesdesintra.pt\neDelivery Gateway (URL): https://community.vortal.biz/public/\nFunção da Organização: Adquirente\nNorma jurídica da Entidade Adjudicante: Autoridade da administração central\nÁrea de atividade da Autoridade Adjudicante: Serviços públicos das administrações públicas\n\n2 - JORNAL OFICIAL DA UNIÃO EUROPEIA\nO procedimento a que este anúncio diz respeito também é publicitado no Jornal Oficial da União Europeia? Não\n\n3 - AVISO\nModelo de Anúncio: Concurso público\nData de Envio do Anúncio: 29-09-2025\n\n5 - PROCESSO\nTipo de Procedimento: Concurso público\nPreço base do procedimento: Sim\nValor do preço base do procedimento: 2.800.000,00 EUR\nProcedimento com lotes? Não\n\n6 - OBJETO DO CONTRATO\nNúmero de referência interna: 01440.2025\nDesignação do contrato: Conservação e Restauro da Capela Real do Palácio Nacional de Sintra\nDescrição: Conservação e Restauro da Capela Real do Palácio\nNacional de Sintra\nTipo de Contrato Principal: Empreitada de Obras Públicas\nTipo de Contrato: Empreitada de Obras Públicas\nClassificação CPV (Vocabulário Comum para os Contratos Públicos)\nObjeto principal\nVocabulário Principal: 45453000\nPreço base s/IVA: 2.800.000,00 EUR\n\n7 - INDICAÇÕES ADICIONAIS\nO contrato envolve aquisição conjunta (satisfação de várias entidades)? Não\nO contrato é adjudicado por uma central de compras? Não\n\n8 - TÉCNICAS\nO concurso destina-se à celebração de um acordo-quadro? Inexistência de acordo-quadro\nÉ utilizado um leilão eletrónico? Não\nÉ adotada uma fase de negociação? Não\nSistema de Aquisição Dinâmico: Inexistência de sistema de aquisição dinâmico\n\n9 - LOCAL DA EXECUÇÃO DO CONTRATO\nLOCAL DA EXECUÇÃO DO CONTRATO (PROCEDIMENTO)\nPaís: Portugal\nNUT III: PT170\nLocalidade: Lisboa\nDistrito: Lisboa\nConcelho: Sintra\nFreguesia: Todas\n\n10 - PRAZO DE EXECUÇÃO DO CONTRATO\nPrazo de execução do contrato: 22 MESES\nPrevisão de renovações: Não\n\n11 - FUNDOS EU\nTêm fundos EU? Não\n\n12 - DOCUMENTOS DE HABILITAÇÃO\nHabilitação para o exercício da atividade profissional: Não\n\n13 - CONDIÇÕES DE APRESENTAÇÃO\nPlataforma eletrónica utilizada pela entidade adjudicante: VORTAL\nURL para Apresentação: https://community.vortal.biz/public/\nAdmissibilidade da apresentação de propostas variantes: Não autorizado\nPrazo para apresentação das propostas: 09-11-2025 23:59\nPrazo durante o qual os concorrentes são obrigados a manter as respetivas propostas: 66 dias a contar do termo do prazo para a apresentação das propostas\nIndicação de Subcontratação na Proposta: Inexistência de indicação de subcontratação\n\n14 - PRESTAÇÃO DE CAUÇÃO\nPrestação de caução: Sim\nPercentagem: 5%\nDescrição da Garantia Exigida: Garantia bancária ou Seguro-caução\n\n15 - FORNECIMENTO DAS PEÇAS DO CONCURSO, APRESENTAÇÃO DE PEDIDOS DE PARTICIPAÇÃO E APRESENTAÇÃO DAS PROPOSTAS\nLink para acesso às peças do concurso (URL): https://community.vortal.biz/Public/public-tender-documents/WmFKVEJwNnBEVTNUb3pNMzJ3c1hudGZ0S1l1ZkhoNVVndE1vMHJWYjlDSzJJL2tnN1VOaXp4UkpNamZWdWp0MWl0cUF0Qjh1SXJEVExaYjNFWjB5WVE9PUx1Mmkj\n\n20 - OUTROS REQUISITOS\nInformação sobre contratos reservados. Aplica-se a contratos reservados (54º-A)? Não\n\n21 - CRITÉRIO DE ADJUDICAÇÃO\nMultifator: Sim\nFator: \nNome: Preço\nPonderação: 40%\nSubfatores: Não\nFator: \nNome: Qualidade\nPonderação: 60%\nSubfatores: Não\n\n24 - CONDIÇÕES DO CONTRATO\nFaturação Eletrónica: Permitido\nObrigação de Subcontratação:\nCódigo da Obrigação de Subcontratação: Não é aplicável nenhuma obrigação de subcontratação.\n\n25 - COMPRA PÚBLICA ESTRATÉGICA\nCompra Pública Estratégica: Inexistência de contratação pública estratégica\n\n26 - INFORMAÇÕES ADICIONAIS\nContrato adequado para PME: Sim\nCobertura ACP (Acordo dos Contratos Públicos da Organização Mundial do Comércio): Não\n\n27 - IDENTIFICAÇÃO E CONTACTOS DO ÓRGÃO DE RECURSOS ADMINISTRATIVOS\nDesignação: Conselho de Administração\nEndereço: Estrada de Monserrate, Parque de Monserrate\nCódigo postal: 2710-405\nLocalidade: Sintra\nTelefone: +351 219237300\nFax: +351 219237300\nEndereço eletrónico: info@parquesdesintra.pt\n\n28 - IDENTIFICAÇÃO DO(S) AUTOR(ES) DE ANÚNCIO\nNome: Mariana Peralta Aguiar\nCargo: Jurista | Departamento Jurídico\n419589166",
    "nipc": "505174839",
    "distrito": "Lisboa",
    "concelho": "Sintra",
    "freguesia": "Todas",
    "site": "www.parquesdesintra.pt/pt/",
    "email": "viviane.crouzier@parquesdesintra.pt",
    "designacao_contrato": "Conservação e Restauro da Capela Real do Palácio Nacional de Sintra",
    "descricao": "Conservação e Restauro da Capela Real do Palácio",
    "preco_base": "2.800.000,00 EUR",
    "prazo_execucao": "22 MESES",
    "prazo_apresentacao_propostas": "09-11-2025 23:59",
    "fundos_eu": "Não",
    "plataforma_eletronica": "VORTAL",
    "url_procedimento": "https://community.vortal.biz/public/",
    "autor_nome": "Mariana Peralta Aguiar",
    "autor_cargo": "Jurista | Departamento Jurídico"
  },
  {
    "numero_procedimento": "N/A",
    "entidade": "Instituto da Conservação da Natureza e das Florestas, I.P.",
    "link": "https://diariodarepublica.pt/dr/detalhe/contrato-publico/25654-937193361",
    "detalhes_completos": "Alteração do Anúncio de procedimento n.º 23782/2025, de 2025-09-08, com o ID 419511542\n\n1 - IDENTIFICAÇÃO E CONTACTOS DA ENTIDADE ADJUDICANTE\nDesignação da entidade adjudicante: Instituto da Conservação da Natureza e das Florestas, I.P.\nNIPC: 510342647\nEndereço: Av. Dr. Alfredo Magalhães Ramalho, nº 1\nCódigo postal: 1495-165\nLocalidade: Lisboa\nPaís: Portugal\nNUT III: PT170\nDistrito: Lisboa\nConcelho: Oeiras\nFreguesia: União das Freguesias de Algés, Linda-a-Velha e Cruz Quebrada-Dafundo\nTelefone: 213124800\nFax: 213124800\nEndereço da Entidade (URL): https://www.icnf.pt/\nEndereço Eletrónico: geral@icnf.pt\neDelivery Gateway (URL): https://community.vortal.biz/public/\nFunção da Organização: Adquirente\nNorma jurídica da Entidade Adjudicante: Instituição, órgão ou agência da UE\nÁrea de atividade da Autoridade Adjudicante: Proteção ambiental\n\n2 - JORNAL OFICIAL DA UNIÃO EUROPEIA\nO procedimento a que este anúncio diz respeito também é publicitado no Jornal Oficial da União Europeia? Não\n\n3 - AVISO\nModelo de Anúncio: Concurso público\nData de Envio do Anúncio: 29-09-2025\n\n5 - PROCESSO\nTipo de Procedimento: Concurso público\nPreço base do procedimento: Sim\nValor do preço base do procedimento: 754.038,00 EUR\nProcedimento com lotes? Não\n\n6 - OBJETO DO CONTRATO\nNúmero de referência interna: CP/28/2025/ICNF/SEDE \nDesignação do contrato: Empreitada obras públicas no Viveiro Florestal de Valverde\nDescrição: Empreitada obras públicas no Viveiro Florestal de Valverde,no âmbito do protocolo de Colaboração Técnica e Financeira entre o Fundo Ambiental e o ICNF, I.P. \nTipo de Contrato Principal: Empreitada de Obras Públicas\nTipo de Contrato: Empreitada de Obras Públicas\nClassificação CPV (Vocabulário Comum para os Contratos Públicos)\nObjeto principal\nVocabulário Principal: 45453100\nPreço base s/IVA: 754.038,00 EUR\n\n7 - INDICAÇÕES ADICIONAIS\nO contrato envolve aquisição conjunta (satisfação de várias entidades)? Não\nO contrato é adjudicado por uma central de compras? Não\n\n8 - TÉCNICAS\nO concurso destina-se à celebração de um acordo-quadro? Inexistência de acordo-quadro\nÉ utilizado um leilão eletrónico? Não\nÉ adotada uma fase de negociação? Não\nSistema de Aquisição Dinâmico: Inexistência de sistema de aquisição dinâmico\n\n9 - LOCAL DA EXECUÇÃO DO CONTRATO\nLOCAL DA EXECUÇÃO DO CONTRATO (PROCEDIMENTO)\nPaís: Portugal\nNUT III: PT170\nLocalidade: Algés\nDistrito: Lisboa\nConcelho: Oeiras\nFreguesia: União das Freguesias de Algés, Linda-a-Velha e Cruz Quebrada-Dafundo\n\n10 - PRAZO DE EXECUÇÃO DO CONTRATO\nPrazo de execução do contrato: 180 DIAS\nPrevisão de renovações: Não\n\n11 - FUNDOS EU\nTêm fundos EU? Não\n\n12 - DOCUMENTOS DE HABILITAÇÃO\nHabilitação para o exercício da atividade profissional: Não\n\n13 - CONDIÇÕES DE APRESENTAÇÃO\nPlataforma eletrónica utilizada pela entidade adjudicante: VORTAL\nURL para Apresentação: https://community.vortal.biz/public/\nAdmissibilidade da apresentação de propostas variantes: Não autorizado\nPrazo para apresentação das propostas: 06-10-2025 23:59\nPrazo durante o qual os concorrentes são obrigados a manter as respetivas propostas: 90 dias a contar do termo do prazo para a apresentação das propostas\nIndicação de Subcontratação na Proposta: Inexistência de indicação de subcontratação\n\n14 - PRESTAÇÃO DE CAUÇÃO\nPrestação de caução: Sim\nPercentagem: 5%\nDescrição da Garantia Exigida: Artigo 12.º Programa Procedimento\n\n15 - FORNECIMENTO DAS PEÇAS DO CONCURSO, APRESENTAÇÃO DE PEDIDOS DE PARTICIPAÇÃO E APRESENTAÇÃO DAS PROPOSTAS\nLink para acesso às peças do concurso (URL): https://community.vortal.biz/Public/public-tender-documents/MkZTdDZueG1mMHhYZmJoK0luaFh1akNLendKT0VPQVA0ZDl6S1I3MkNqTCtESEh1M1pFZTZPc2wvZHBsQUFGbzQvc05Zb1FEWkkrWExuRjlQRmNoa0E9PVU3JlM4\n\n20 - OUTROS REQUISITOS\nInformação sobre contratos reservados. Aplica-se a contratos reservados (54º-A)? Não\n\n21 - CRITÉRIO DE ADJUDICAÇÃO\nMultifator: Sim\nFator: \nNome: Preço\nPonderação: 90%\nSubfatores: Não\nFator: \nNome: Qualidade\nPonderação: 10%\nSubfatores: Não\n\n24 - CONDIÇÕES DO CONTRATO\nFaturação Eletrónica: Permitido\nObrigação de Subcontratação:\nCódigo da Obrigação de Subcontratação: Não é aplicável nenhuma obrigação de subcontratação.\n\n25 - COMPRA PÚBLICA ESTRATÉGICA\nCompra Pública Estratégica: Redução dos impactos ambientais\nDescrição do Processo de Adjudicação Estratégico: Ver peças procedimento\nCritérios de contratos Públicos Ecológicos: Critérios de contratação pública ecológica nacional\nCategorias da estratégia nacional: Outros\nOutra categoria (Descrição): RCM n.º 132/2023\nDiretiva Veículos Não Poluentes: Não\nCritério de Acessibilidade: Os critérios de acessibilidade para as pessoas com deficiência não estão incluídos porque o contrato não se destina a pessoas singulares\n\n26 - INFORMAÇÕES ADICIONAIS\nContrato adequado para PME: Sim\nCobertura ACP (Acordo dos Contratos Públicos da Organização Mundial do Comércio): Não\n\n27 - IDENTIFICAÇÃO E CONTACTOS DO ÓRGÃO DE RECURSOS ADMINISTRATIVOS\nDesignação: Conselho Diretivo do ICNF, I.P.\nEndereço: Av. Dr. Alfredo Magalhães Ramalho 1\nCódigo postal: 1495-165\nLocalidade: Oeiras\nTelefone: +351 213507900\nFax: +351 213507900\nEndereço eletrónico: geral@icnf.pt\n\n28 - IDENTIFICAÇÃO DO(S) AUTOR(ES) DE ANÚNCIO\nNome: Helena Silva\nCargo: Técnica Superior da Divisão de Contratação e Logística\n\n29 - ALTERAÇÃO\nMotivo da Alteração: Correção pelo adquirente\nIdentificador da Versão do Anúncio a Alterar: 2f99c513-f00e-41a0-b9f9-74740c84afc6-01\nIdentificador das Secções Alteradas do Anúncio Anterior: Condições de Apresentação\nDescrição das Alterações: Prorrogação do prazo para apresentação de propostas, fixando-se o seu termo em 06.10.2025\nAlteração dos Documentos do Concurso: Não\n419591588",
    "nipc": "510342647",
    "distrito": "Lisboa",
    "concelho": "Oeiras",
    "freguesia": "União das Freguesias de Algés, Linda-a-Velha e Cruz Quebrada-Dafundo",
    "site": "https://www.icnf.pt/",
    "email": "geral@icnf.pt",
    "designacao_contrato": "Empreitada obras públicas no Viveiro Florestal de Valverde",
    "descricao": "Empreitada obras públicas no Viveiro Florestal de Valverde,no âmbito do protocolo de Colaboração Técnica e Financeira entre o Fundo Ambiental e o ICNF, I.P.",
    "preco_base": "754.038,00 EUR",
    "prazo_execucao": "180 DIAS",
    "prazo_apresentacao_propostas": "06-10-2025 23:59",
    "fundos_eu": "Não",
    "plataforma_eletronica": "VORTAL",
    "url_procedimento": "https://community.vortal.biz/public/",
    "autor_nome": "Helena Silva",
    "autor_cargo": "Técnica Superior da Divisão de Contratação e Logística"
  },
  {
    "numero_procedimento": "N/A",
    "entidade": "Estado - Ministério da Defesa Nacional  Comando da Logística da Força Aérea  Direção de Infraestruturas",
    "link": "https://diariodarepublica.pt/dr/detalhe/contrato-publico/25655-937193362",
    "detalhes_completos": "Alteração do Anúncio de procedimento n.º 25028/2025, de 2025-09-23, com o ID 419565651\n\n1 - IDENTIFICAÇÃO E CONTACTOS DA ENTIDADE ADJUDICANTE\nDesignação da entidade adjudicante: Estado - Ministério da Defesa Nacional  Comando da Logística da Força Aérea  Direção de Infraestruturas\nNIPC: 600010686\nServiço/Órgão/Pessoa de contacto: Força Aérea - Comando da Logística  Direção de Infraestruturas\nEndereço: Avenida da Força Aérea Portuguesa, Nº1, Edif. A, Piso 6\nCódigo postal: 2614-506\nLocalidade: Amadora\nPaís: Portugal\nNUT III: PT170\nDistrito: Lisboa\nConcelho: Amadora\nFreguesia: Freguesia de Alfragide\nTelefone: 214723696\nEndereço da Entidade (URL): www.emfa.pt\nEndereço Eletrónico: di.rprojetos.chf@emfa.gov.pt\neDelivery Gateway (URL): https://www.acingov.pt\nFunção da Organização: Adquirente\nNorma jurídica da Entidade Adjudicante: Organismo de direito público\nÁrea de atividade da Autoridade Adjudicante: Defesa\n\n2 - JORNAL OFICIAL DA UNIÃO EUROPEIA\nO procedimento a que este anúncio diz respeito também é publicitado no Jornal Oficial da União Europeia? Não\n\n3 - AVISO\nModelo de Anúncio: Concurso público\nData de Envio do Anúncio: 29-09-2025\n\n5 - PROCESSO\nTipo de Procedimento: Concurso público\nPreço base do procedimento: Sim\nValor do preço base do procedimento: 50.000,00 EUR\nProcedimento com lotes? Não\n\n6 - OBJETO DO CONTRATO\nNúmero de referência interna: CP 32/DI/2025\nDesignação do contrato: BENEFICIAÇÃO DE INFRAESTRUTURAS ELÉTRICAS DE VALINHOS\nDescrição: BENEFICIAÇÃO DE INFRAESTRUTURAS ELÉTRICAS DE VALINHOS\nTipo de Contrato Principal: Empreitada de Obras Públicas\nTipo de Contrato: Empreitada de Obras Públicas\nClassificação CPV (Vocabulário Comum para os Contratos Públicos)\nObjeto principal\nVocabulário Principal: 45315300\nPreço base s/IVA: 50.000,00 EUR\n\n7 - INDICAÇÕES ADICIONAIS\nO contrato envolve aquisição conjunta (satisfação de várias entidades)? Não\nO contrato é adjudicado por uma central de compras? Não\n\n8 - TÉCNICAS\nO concurso destina-se à celebração de um acordo-quadro? Inexistência de acordo-quadro\nÉ utilizado um leilão eletrónico? Não\nÉ adotada uma fase de negociação? Não\nSistema de Aquisição Dinâmico: Inexistência de sistema de aquisição dinâmico\n\n9 - LOCAL DA EXECUÇÃO DO CONTRATO\nLOCAL DA EXECUÇÃO DO CONTRATO (PROCEDIMENTO)\nPaís: Portugal\nNUT III: PT150\nLocalidade: Freguesia de Monchique\nDistrito: Faro\nConcelho: Monchique\nFreguesia: Freguesia de Monchique\n\n10 - PRAZO DE EXECUÇÃO DO CONTRATO\nPrazo de execução do contrato: 60 DIAS\nPrevisão de renovações: Não\n\n11 - FUNDOS EU\nTêm fundos EU? Não\n\n12 - DOCUMENTOS DE HABILITAÇÃO\nHabilitação para o exercício da atividade profissional: Sim\nTipo: Alvará\nDescrição: A 1.ª subcategoria da 4.ª categoria, a qual tem que ser de classe que cubra o valor global da proposta e integrar-se na categoria em que o tipo de obra se enquadra;\nA 4.ª subcategoria da 1.ª categoria e a 2.ª subcategoria da 5.ª categoria, na classe correspondente à parte dos trabalhos a que respeitem.\n\n13 - CONDIÇÕES DE APRESENTAÇÃO\nPlataforma eletrónica utilizada pela entidade adjudicante: ACIN\nURL para Apresentação: https://www.acingov.pt\nAdmissibilidade da apresentação de propostas variantes: Não autorizado\nPrazo para apresentação das propostas: 03-10-2025 23:00\nPrazo durante o qual os concorrentes são obrigados a manter as respetivas propostas: 66 dias a contar do termo do prazo para a apresentação das propostas\nIndicação de Subcontratação na Proposta: Inexistência de indicação de subcontratação\n\n14 - PRESTAÇÃO DE CAUÇÃO\nPrestação de caução: Sim\nPercentagem: 5%\nDescrição da Garantia Exigida: O valor da caução é de 5.00% do preço contratual.\n\n15 - FORNECIMENTO DAS PEÇAS DO CONCURSO, APRESENTAÇÃO DE PEDIDOS DE PARTICIPAÇÃO E APRESENTAÇÃO DAS PROPOSTAS\nLink para acesso às peças do concurso (URL): https://www.acingov.pt/acingovprod/2/zonaPublica/zona_publica_c/donwloadProcedurePiece/OTgwMjIy\n\n20 - OUTROS REQUISITOS\nInformação sobre contratos reservados. Aplica-se a contratos reservados (54º-A)? Não\n\n21 - CRITÉRIO DE ADJUDICAÇÃO\nMultifator: Não\nMonofator:\nNome: Preço\n\n24 - CONDIÇÕES DO CONTRATO\nFaturação Eletrónica: Permitido\nObrigação de Subcontratação:\nCódigo da Obrigação de Subcontratação: Não é aplicável nenhuma obrigação de subcontratação.\n\n25 - COMPRA PÚBLICA ESTRATÉGICA\nCompra Pública Estratégica: Inexistência de contratação pública estratégica\n\n26 - INFORMAÇÕES ADICIONAIS\nContrato adequado para PME: Não\nCobertura ACP (Acordo dos Contratos Públicos da Organização Mundial do Comércio): Não\n\n27 - IDENTIFICAÇÃO E CONTACTOS DO ÓRGÃO DE RECURSOS ADMINISTRATIVOS\nDesignação: Chefe do Estado-Maior da Força Aérea\nEndereço: Avenida da Força Aérea Portuguesa, Nº1\nCódigo postal: 2614-506\nLocalidade: Amadora\nEndereço eletrónico: clafa.secpub@emfa.gov.pt\n\n28 - IDENTIFICAÇÃO DO(S) AUTOR(ES) DE ANÚNCIO\nNome: COR FILIPE RODRIGUES\nCargo: CHEFE DO GAP\n\n29 - ALTERAÇÃO\nMotivo da Alteração: Informações atualizadas\nIdentificador da Versão do Anúncio a Alterar: 46a49632-bd33-49c7-8f8f-b2f014cca20f-01\nIdentificador das Secções Alteradas do Anúncio Anterior: Condições de Apresentação\nDescrição das Alterações: Modificação do prazo para a apresentação de propostas\nAlteração dos Documentos do Concurso: Não\n419591806",
    "nipc": "600010686",
    "distrito": "Lisboa",
    "concelho": "Amadora",
    "freguesia": "Freguesia de Alfragide",
    "site": "www.emfa.pt",
    "email": "di.rprojetos.chf@emfa.gov.pt",
    "designacao_contrato": "BENEFICIAÇÃO DE INFRAESTRUTURAS ELÉTRICAS DE VALINHOS",
    "descricao": "BENEFICIAÇÃO DE INFRAESTRUTURAS ELÉTRICAS DE VALINHOS",
    "preco_base": "50.000,00 EUR",
    "prazo_execucao": "60 DIAS",
    "prazo_apresentacao_propostas": "03-10-2025 23:00",
    "fundos_eu": "Não",
    "plataforma_eletronica": "ACIN",
    "url_procedimento": "https://www.acingov.pt",
    "autor_nome": "COR FILIPE RODRIGUES",
    "autor_cargo": "CHEFE DO GAP"
  },
  {
    "numero_procedimento": "N/A",
    "entidade": "Ordem Dos Engenheiros",
    "link": "https://diariodarepublica.pt/dr/detalhe/contrato-publico/25657-937193363",
    "detalhes_completos": "Alteração do Anúncio de procedimento n.º 25474/2025, de 2025-09-29, com o ID 419584102\n\n1 - IDENTIFICAÇÃO E CONTACTOS DA ENTIDADE ADJUDICANTE\nDesignação da entidade adjudicante: Ordem Dos Engenheiros\nNIPC: 500839166\nEndereço: Avenida António Augusto de Aguiar,3D\nCódigo postal: 1069-030\nLocalidade: Lisboa\nPaís: Portugal\nNUT III: PT170\nDistrito: Lisboa\nConcelho: Lisboa\nFreguesia: Todas\nTelefone: 213132611\nFax: 213524632\nEndereço da Entidade (URL): www.ordemengenheiros.pt\nEndereço Eletrónico: secretariageral@oep.pt\neDelivery Gateway (URL): https://community.vortal.biz/public/\nFunção da Organização: Adquirente\nNorma jurídica da Entidade Adjudicante: Organismo de direito público\nÁrea de atividade da Autoridade Adjudicante: Serviços públicos das administrações públicas\n\n2 - JORNAL OFICIAL DA UNIÃO EUROPEIA\nO procedimento a que este anúncio diz respeito também é publicitado no Jornal Oficial da União Europeia? Não\n\n3 - AVISO\nModelo de Anúncio: Concurso público\nData de Envio do Anúncio: 29-09-2025\n\n5 - PROCESSO\nTipo de Procedimento: Concurso público\nPreço base do procedimento: Sim\nValor do preço base do procedimento: 100.000,00 EUR\nProcedimento com lotes? Não\n\n6 - OBJETO DO CONTRATO\nNúmero de referência interna: CDN 31/2025\nDesignação do contrato: Aquisição de Serviços de Produção Gráfica (Impressão, Acabamento, Endereçamento e Embalamento) da Revista \"INGENIUM\"\nDescrição: Aquisição de Serviços de Produção Gráfica (Impressão, Acabamento, Endereçamento e Embalamento) da Revista \"INGENIUM\"\nTipo de Contrato Principal: Aquisição de Serviços\nTipo de Contrato: Aquisição de Serviços\nClassificação CPV (Vocabulário Comum para os Contratos Públicos)\nObjeto principal\nVocabulário Principal: 79800000\nPreço base s/IVA: 100.000,00 EUR\n\n7 - INDICAÇÕES ADICIONAIS\nO contrato envolve aquisição conjunta (satisfação de várias entidades)? Não\nO contrato é adjudicado por uma central de compras? Não\n\n8 - TÉCNICAS\nO concurso destina-se à celebração de um acordo-quadro? Inexistência de acordo-quadro\nÉ utilizado um leilão eletrónico? Não\nÉ adotada uma fase de negociação? Não\nSistema de Aquisição Dinâmico: Inexistência de sistema de aquisição dinâmico\n\n9 - LOCAL DA EXECUÇÃO DO CONTRATO\nLOCAL DA EXECUÇÃO DO CONTRATO (PROCEDIMENTO)\nPaís: Portugal\nNUT III: PT170\nLocalidade: Lisboa\nDistrito: Lisboa\nConcelho: Lisboa\nFreguesia: Todas\n\n10 - PRAZO DE EXECUÇÃO DO CONTRATO\nPrazo de execução do contrato: 1 ANOS\nPrevisão de renovações: Não\n\n11 - FUNDOS EU\nTêm fundos EU? Não\n\n12 - DOCUMENTOS DE HABILITAÇÃO\nHabilitação para o exercício da atividade profissional: Não\n\n13 - CONDIÇÕES DE APRESENTAÇÃO\nPlataforma eletrónica utilizada pela entidade adjudicante: VORTAL\nURL para Apresentação: https://community.vortal.biz/public/\nAdmissibilidade da apresentação de propostas variantes: Não autorizado\nPrazo para apresentação das propostas: 06-10-2025 23:59\nPrazo durante o qual os concorrentes são obrigados a manter as respetivas propostas: 180 dias a contar do termo do prazo para a apresentação das propostas\nApresentação de Catálogo Eletrónico: Permitido\nIndicação de Subcontratação na Proposta: Inexistência de indicação de subcontratação\n\n14 - PRESTAÇÃO DE CAUÇÃO\nPrestação de caução: Não\n\n15 - FORNECIMENTO DAS PEÇAS DO CONCURSO, APRESENTAÇÃO DE PEDIDOS DE PARTICIPAÇÃO E APRESENTAÇÃO DAS PROPOSTAS\nLink para acesso às peças do concurso (URL): https://community.vortal.biz/Public/public-tender-documents/clMzbFB0a1IvOUNDcWhmWjM1aHpwckMvSkNGbUxSMGRtL0pYOFkrbmsrOXJUNW9tOTROMTBuSGk4WUUwMVhHTGhzK3YyVjVNanZDeUsvV1N0UitKcUE9PWJOODFZ\n\n20 - OUTROS REQUISITOS\nInformação sobre contratos reservados. Aplica-se a contratos reservados (54º-A)? Não\n\n21 - CRITÉRIO DE ADJUDICAÇÃO\nMultifator: Sim\nFator: \nNome: Preço\nPonderação: 45%\nSubfatores: Não\nFator: \nNome: Qualidade\nPonderação: 35%\nSubfatores: Não\nFator: \nNome: Qualidade\nPonderação: 20%\nSubfatores: Não\n\n24 - CONDIÇÕES DO CONTRATO\nFaturação Eletrónica: Permitido\nObrigação de Subcontratação:\nCódigo da Obrigação de Subcontratação: Não é aplicável nenhuma obrigação de subcontratação.\n\n25 - COMPRA PÚBLICA ESTRATÉGICA\nCompra Pública Estratégica: Inexistência de contratação pública estratégica\n\n26 - INFORMAÇÕES ADICIONAIS\nContrato adequado para PME: Sim\nCobertura ACP (Acordo dos Contratos Públicos da Organização Mundial do Comércio): Não\n\n27 - IDENTIFICAÇÃO E CONTACTOS DO ÓRGÃO DE RECURSOS ADMINISTRATIVOS\nDesignação: CDN\nEndereço: Avenida António Augusto de Aguiar, 3D\nCódigo postal: 1069-030\nLocalidade: Lisboa\nTelefone: +351 213132611\nFax: +351 213132601\nEndereço eletrónico: liliana.carvalho@oep.pt\n\n28 - IDENTIFICAÇÃO DO(S) AUTOR(ES) DE ANÚNCIO\nNome: Nelson Jerónimo\nCargo: Secretário-geral\n\n29 - ALTERAÇÃO\nMotivo da Alteração: Correção pelo adquirente\nIdentificador da Versão do Anúncio a Alterar: ca901880-ad8d-4c2e-9c6a-bc22d1c69041-01\nIdentificador das Secções Alteradas do Anúncio Anterior: Condições de Apresentação\nAlteração dos Documentos do Concurso: Não\n419587927",
    "nipc": "500839166",
    "distrito": "Lisboa",
    "concelho": "Lisboa",
    "freguesia": "Todas",
    "site": "www.ordemengenheiros.pt",
    "email": "secretariageral@oep.pt",
    "designacao_contrato": "Aquisição de Serviços de Produção Gráfica (Impressão, Acabamento, Endereçamento e Embalamento) da Revista \"INGENIUM\"",
    "descricao": "Aquisição de Serviços de Produção Gráfica (Impressão, Acabamento, Endereçamento e Embalamento) da Revista \"INGENIUM\"",
    "preco_base": "100.000,00 EUR",
    "prazo_execucao": "1 ANOS",
    "prazo_apresentacao_propostas": "06-10-2025 23:59",
    "fundos_eu": "Não",
    "plataforma_eletronica": "VORTAL",
    "url_procedimento": "https://community.vortal.biz/public/",
    "autor_nome": "Nelson Jerónimo",
    "autor_cargo": "Secretário-geral"
  },
  {
    "numero_procedimento": "N/A",
    "entidade": "Comunidade Intermunicipal da Região de Coimbra",
    "link": "https://diariodarepublica.pt/dr/detalhe/contrato-publico/25659-937193367",
    "detalhes_completos": "1 - IDENTIFICAÇÃO E CONTACTOS DA ENTIDADE ADJUDICANTE\nDesignação da entidade adjudicante: Comunidade Intermunicipal da Região de Coimbra\nNIPC: 508354617\nEndereço: Rua do Brasil, 131\nCódigo postal: 3030-175\nLocalidade: Coimbra\nPaís: Portugal\nNUT III: PTZZZ\nDistrito: Todos\nConcelho: Todos\nFreguesia: Todas\nTelefone: 239795200\nEndereço da Entidade (URL): https://cim-regiaodecoimbra.pt\nEndereço Eletrónico: geral@cim-regiaodecoimbra.pt\neDelivery Gateway (URL): https://www.acingov.pt\nFunção da Organização: Adquirente\nNorma jurídica da Entidade Adjudicante: Organismo de direito público\nÁrea de atividade da Autoridade Adjudicante: Serviços públicos das administrações públicas\n\n2 - JORNAL OFICIAL DA UNIÃO EUROPEIA\nO procedimento a que este anúncio diz respeito também é publicitado no Jornal Oficial da União Europeia? Não\n\n3 - AVISO\nModelo de Anúncio: Concurso público\nData de Envio do Anúncio: 30-09-2025\n\n5 - PROCESSO\nTipo de Procedimento: Concurso público\nPreço base do procedimento: Sim\nValor do preço base do procedimento: 219.120,00 EUR\nProcedimento com lotes? Não\n\n6 - OBJETO DO CONTRATO\nNúmero de referência interna: CP18/2025\nDesignação do contrato: CP18/2025 - Coimbra Sustainable Tourism LLM SHIFT Coimbra - Execução da Estratégia de Comunicação 2025-2028\nDescrição: CP18/2025 - Coimbra Sustainable Tourism LLM SHIFT Coimbra - Execução da Estratégia de Comunicação 2025-2028\nTipo de Contrato Principal: Aquisição de Serviços\nTipo de Contrato: Aquisição de Serviços\nClassificação CPV (Vocabulário Comum para os Contratos Públicos)\nObjeto principal\nVocabulário Principal: 79342000\nPreço base s/IVA: 219.120,00 EUR\n\n7 - INDICAÇÕES ADICIONAIS\nO contrato envolve aquisição conjunta (satisfação de várias entidades)? Não\nO contrato é adjudicado por uma central de compras? Não\n\n8 - TÉCNICAS\nO concurso destina-se à celebração de um acordo-quadro? Inexistência de acordo-quadro\nÉ utilizado um leilão eletrónico? Não\nÉ adotada uma fase de negociação? Não\nSistema de Aquisição Dinâmico: Inexistência de sistema de aquisição dinâmico\n\n9 - LOCAL DA EXECUÇÃO DO CONTRATO\nLOCAL DA EXECUÇÃO DO CONTRATO (PROCEDIMENTO)\nPaís: Portugal\nNUT III: PT16E\nLocalidade: Freguesia de Santo António dos Olivais\nDistrito: Coimbra\nConcelho: Coimbra\nFreguesia: Freguesia de Santo António dos Olivais\n\n10 - PRAZO DE EXECUÇÃO DO CONTRATO\nPrazo de execução do contrato: 944 DIAS\nPrevisão de renovações: Não\n\n11 - FUNDOS EU\nTêm fundos EU? Não\n\n12 - DOCUMENTOS DE HABILITAÇÃO\nHabilitação para o exercício da atividade profissional: Não\n\n13 - CONDIÇÕES DE APRESENTAÇÃO\nPlataforma eletrónica utilizada pela entidade adjudicante: ACIN\nURL para Apresentação: https://www.acingov.pt\nAdmissibilidade da apresentação de propostas variantes: Não autorizado\nPrazo para apresentação das propostas: 05-10-2025 23:59\nPrazo durante o qual os concorrentes são obrigados a manter as respetivas propostas: 120 dias a contar do termo do prazo para a apresentação das propostas\nIndicação de Subcontratação na Proposta: Inexistência de indicação de subcontratação\n\n14 - PRESTAÇÃO DE CAUÇÃO\nPrestação de caução: Não\n\n15 - FORNECIMENTO DAS PEÇAS DO CONCURSO, APRESENTAÇÃO DE PEDIDOS DE PARTICIPAÇÃO E APRESENTAÇÃO DAS PROPOSTAS\nLink para acesso às peças do concurso (URL): https://www.acingov.pt/acingovprod/2/zonaPublica/zona_publica_c/donwloadProcedurePiece/OTgyMTY0\n\n20 - OUTROS REQUISITOS\nInformação sobre contratos reservados. Aplica-se a contratos reservados (54º-A)? Não\n\n21 - CRITÉRIO DE ADJUDICAÇÃO\nMultifator: Sim\nFator: \nNome: Preço\nPonderação: 35%\nSubfatores: Não\nFator: \nNome: Outros\nOutro Nome: Experiência da Equipa\nPonderação: 65%\nSubfatores: Não\n\n24 - CONDIÇÕES DO CONTRATO\nFaturação Eletrónica: Permitido\nObrigação de Subcontratação:\nCódigo da Obrigação de Subcontratação: Não é aplicável nenhuma obrigação de subcontratação.\n\n25 - COMPRA PÚBLICA ESTRATÉGICA\nCompra Pública Estratégica: Inexistência de contratação pública estratégica\n\n26 - INFORMAÇÕES ADICIONAIS\nContrato adequado para PME: Sim\nCobertura ACP (Acordo dos Contratos Públicos da Organização Mundial do Comércio): Não\n\n27 - IDENTIFICAÇÃO E CONTACTOS DO ÓRGÃO DE RECURSOS ADMINISTRATIVOS\nDesignação: Conselho Intermunicipal da Comunidade Intermunicipal da Região de Coimbra\nEndereço: Rua do Brasil, 131\nCódigo postal: 3030-175\nLocalidade: Coimbra\nTelefone: 239795200\nFax: 000000000\nEndereço eletrónico: geral@cim-regiaodecoimbra.pt\nPrazo de interposição do recurso: 5 dias\n\n28 - IDENTIFICAÇÃO DO(S) AUTOR(ES) DE ANÚNCIO\nNome: Jorge Brito\nCargo: Secretário Executivo Intermunicipal\n419589028",
    "nipc": "508354617",
    "distrito": "Todos",
    "concelho": "Todos",
    "freguesia": "Todas",
    "site": "https://cim-regiaodecoimbra.pt",
    "email": "geral@cim-regiaodecoimbra.pt",
    "designacao_contrato": "CP18/2025 - Coimbra Sustainable Tourism LLM SHIFT Coimbra - Execução da Estratégia de Comunicação 2025-2028",
    "descricao": "CP18/2025 - Coimbra Sustainable Tourism LLM SHIFT Coimbra - Execução da Estratégia de Comunicação 2025-2028",
    "preco_base": "219.120,00 EUR",
    "prazo_execucao": "944 DIAS",
    "prazo_apresentacao_propostas": "05-10-2025 23:59",
    "fundos_eu": "Não",
    "plataforma_eletronica": "ACIN",
    "url_procedimento": "https://www.acingov.pt",
    "autor_nome": "Jorge Brito",
    "autor_cargo": "Secretário Executivo Intermunicipal"
  },
  {
    "numero_procedimento": "N/A",
    "entidade": "Município de Silves",
    "link": "https://diariodarepublica.pt/dr/detalhe/contrato-publico/25661-937193368",
    "detalhes_completos": "1 - IDENTIFICAÇÃO E CONTACTOS DA ENTIDADE ADJUDICANTE\nDesignação da entidade adjudicante: Município de Silves\nNIPC: 506818837\nServiço/Órgão/Pessoa de contacto: Município de Silves\nEndereço: Largo do Município\nCódigo postal: 8300-117\nLocalidade: Silves\nPaís: Portugal\nNUT III: PT150\nDistrito: Faro\nConcelho: Silves\nFreguesia: Todas\nTelefone: 282440800\nFax: 282440850\nEndereço da Entidade (URL): www.cm-silves.pt\nEndereço Eletrónico: gabinete.presidente@cm-silves.pt\neDelivery Gateway (URL): https://www.acingov.pt\nFunção da Organização: Adquirente\nNorma jurídica da Entidade Adjudicante: Organismo de direito público\nÁrea de atividade da Autoridade Adjudicante: Serviços públicos das administrações públicas\n\n2 - JORNAL OFICIAL DA UNIÃO EUROPEIA\nO procedimento a que este anúncio diz respeito também é publicitado no Jornal Oficial da União Europeia? Não\n\n3 - AVISO\nModelo de Anúncio: Concurso público\nData de Envio do Anúncio: 30-09-2025\n\n5 - PROCESSO\nTipo de Procedimento: Concurso público\nPreço base do procedimento: Sim\nValor do preço base do procedimento: 169.200,00 EUR\nProcedimento com lotes? Não\n\n6 - OBJETO DO CONTRATO\nNúmero de referência interna: 196/CP/2025/SAPR\nDesignação do contrato: PRESTAÇÃO DE SERVIÇOS DE SEGURANÇA INTEGRADA EM EDIFÍCIOS E ESPAÇOS GERIDOS PELO MUNICÍPIO DE SILVES\nDescrição: PRESTAÇÃO DE SERVIÇOS DE SEGURANÇA INTEGRADA EM EDIFÍCIOS E ESPAÇOS GERIDOS PELO MUNICÍPIO DE SILVES\nTipo de Contrato Principal: Aquisição de Serviços\nTipo de Contrato: Aquisição de Serviços\nClassificação CPV (Vocabulário Comum para os Contratos Públicos)\nObjeto principal\nVocabulário Principal: 79711000\nPreço base s/IVA: 169.200,00 EUR\n\n7 - INDICAÇÕES ADICIONAIS\nO contrato envolve aquisição conjunta (satisfação de várias entidades)? Não\nO contrato é adjudicado por uma central de compras? Não\n\n8 - TÉCNICAS\nO concurso destina-se à celebração de um acordo-quadro? Inexistência de acordo-quadro\nÉ utilizado um leilão eletrónico? Não\nÉ adotada uma fase de negociação? Não\nSistema de Aquisição Dinâmico: Inexistência de sistema de aquisição dinâmico\n\n9 - LOCAL DA EXECUÇÃO DO CONTRATO\nLOCAL DA EXECUÇÃO DO CONTRATO (PROCEDIMENTO)\nPaís: Portugal\nNUT III: PT150\nLocalidade: Silves\nDistrito: Faro\nConcelho: Silves\nFreguesia: Todas\n\n10 - PRAZO DE EXECUÇÃO DO CONTRATO\nPrazo de execução do contrato: 3 ANOS\nPrevisão de renovações: Não\n\n11 - FUNDOS EU\nTêm fundos EU? Não\n\n12 - DOCUMENTOS DE HABILITAÇÃO\nHabilitação para o exercício da atividade profissional: Não\n\n13 - CONDIÇÕES DE APRESENTAÇÃO\nPlataforma eletrónica utilizada pela entidade adjudicante: ACIN\nURL para Apresentação: https://www.acingov.pt\nAdmissibilidade da apresentação de propostas variantes: Não autorizado\nPrazo para apresentação das propostas: 09-10-2025 17:00\nPrazo durante o qual os concorrentes são obrigados a manter as respetivas propostas: 66 dias a contar do termo do prazo para a apresentação das propostas\nIndicação de Subcontratação na Proposta: Inexistência de indicação de subcontratação\n\n14 - PRESTAÇÃO DE CAUÇÃO\nPrestação de caução: Não\n\n15 - FORNECIMENTO DAS PEÇAS DO CONCURSO, APRESENTAÇÃO DE PEDIDOS DE PARTICIPAÇÃO E APRESENTAÇÃO DAS PROPOSTAS\nLink para acesso às peças do concurso (URL): https://www.acingov.pt/acingovprod/2/zonaPublica/zona_publica_c/donwloadProcedurePiece/OTgxNDE4\n\n20 - OUTROS REQUISITOS\nInformação sobre contratos reservados. Aplica-se a contratos reservados (54º-A)? Não\n\n21 - CRITÉRIO DE ADJUDICAÇÃO\nMultifator: Não\nMonofator:\nNome: Outros\nOutro nome: A adjudicação é efetuada de acordo com o critério da proposta economicamente mais vantajosa determinada pela modalidade Monofator, designadamente o preço, de acordo com o disposto na alínea b) do n.º 1 do artigo 74.º do Código dos Contratos Públicos.\n\n24 - CONDIÇÕES DO CONTRATO\nFaturação Eletrónica: Permitido\nObrigação de Subcontratação:\nCódigo da Obrigação de Subcontratação: Não é aplicável nenhuma obrigação de subcontratação.\n\n25 - COMPRA PÚBLICA ESTRATÉGICA\nCompra Pública Estratégica: Inexistência de contratação pública estratégica\n\n26 - INFORMAÇÕES ADICIONAIS\nContrato adequado para PME: Sim\nCobertura ACP (Acordo dos Contratos Públicos da Organização Mundial do Comércio): Não\n\n27 - IDENTIFICAÇÃO E CONTACTOS DO ÓRGÃO DE RECURSOS ADMINISTRATIVOS\nDesignação: Municipio de Silves\nEndereço: Lg Municipio\nCódigo postal: 8300-117\nLocalidade: Silves\nTelefone: 282440800\nFax: \nEndereço eletrónico: aprovisionamento@cm-silves.pt\nPrazo de interposição do recurso: 5 dias\n\n28 - IDENTIFICAÇÃO DO(S) AUTOR(ES) DE ANÚNCIO\nNome: Rosa Cristina Gonçalves da Palma\nCargo: Presidente\n419586096",
    "nipc": "506818837",
    "distrito": "Faro",
    "concelho": "Silves",
    "freguesia": "Todas",
    "site": "www.cm-silves.pt",
    "email": "gabinete.presidente@cm-silves.pt",
    "designacao_contrato": "PRESTAÇÃO DE SERVIÇOS DE SEGURANÇA INTEGRADA EM EDIFÍCIOS E ESPAÇOS GERIDOS PELO MUNICÍPIO DE SILVES",
    "descricao": "PRESTAÇÃO DE SERVIÇOS DE SEGURANÇA INTEGRADA EM EDIFÍCIOS E ESPAÇOS GERIDOS PELO MUNICÍPIO DE SILVES",
    "preco_base": "169.200,00 EUR",
    "prazo_execucao": "3 ANOS",
    "prazo_apresentacao_propostas": "09-10-2025 17:00",
    "fundos_eu": "Não",
    "plataforma_eletronica": "ACIN",
    "url_procedimento": "https://www.acingov.pt",
    "autor_nome": "Rosa Cristina Gonçalves da Palma",
    "autor_cargo": "Presidente"
  },
  {
    "numero_procedimento": "N/A",
    "entidade": "Unidade Local de Saúde do Alentejo Central, E.P.E",
    "link": "https://diariodarepublica.pt/dr/detalhe/contrato-publico/25639-937197397",
    "detalhes_completos": "1 - IDENTIFICAÇÃO E CONTACTOS DA ENTIDADE ADJUDICANTE\nDesignação da entidade adjudicante: Unidade Local de Saúde do Alentejo Central, E.P.E\nNIPC: 508085888\nEndereço: Largo Sr. da Pobreza\nCódigo postal: 7000-811\nLocalidade: Évora\nPaís: Portugal\nNUT III: PT187\nDistrito: Évora\nConcelho: Évora\nFreguesia: Todas\nTelefone: 266740111\nFax: 266744212\nEndereço da Entidade (URL): www.hevora.min-saude.pt\nEndereço Eletrónico: concursos.aprov@ulsac.min-saude.pt\neDelivery Gateway (URL): https://community.vortal.biz/public/\nFunção da Organização: Adquirente\nNorma jurídica da Entidade Adjudicante: Organismo de direito público\nÁrea de atividade da Autoridade Adjudicante: Saúde\n\n2 - JORNAL OFICIAL DA UNIÃO EUROPEIA\nO procedimento a que este anúncio diz respeito também é publicitado no Jornal Oficial da União Europeia? Não\n\n3 - AVISO\nModelo de Anúncio: Concurso público\nData de Envio do Anúncio: 29-09-2025\n\n5 - PROCESSO\nTipo de Procedimento: Concurso público\nPreço base do procedimento: Sim\nValor do preço base do procedimento: 124.000,00 EUR\nProcedimento com lotes? Sim\nNº Máx. de Lotes Autorizado: 2\nNúmero máximo de lotes que podem ser adjudicados a um concorrente: 2\n\n6 - OBJETO DO CONTRATO\nNúmero de referência interna: 180116/25\nDesignação do contrato: Equipamentos para o Serviço de Neonatologia\nDescrição: Aquisição de Equipamentos para o Serviço de Neonatologia\nTipo de Contrato Principal: Aquisição de Bens Móveis\nTipo de Contrato: Aquisição de Bens Móveis\nClassificação CPV (Vocabulário Comum para os Contratos Públicos)\nObjeto principal\nVocabulário Principal: 33100000\nPreço base s/IVA: 124.000,00 EUR\nLotes: \nNº: LOT-0001\nDescrição do Lote: Lote 1\nPreço base s/IVA: 64.000,00 EUR\nClassificação CPV (Vocabulário Comum para os Contratos Públicos)\nObjeto principal\nVocabulário Principal: 33100000\nNº: LOT-0002\nDescrição do Lote: Lote 2\nPreço base s/IVA: 60.000,00 EUR\nClassificação CPV (Vocabulário Comum para os Contratos Públicos)\nObjeto principal\nVocabulário Principal: 33100000\n\n7 - INDICAÇÕES ADICIONAIS\nO contrato envolve aquisição conjunta (satisfação de várias entidades)? Não\nO contrato é adjudicado por uma central de compras? Não\n\n8 - TÉCNICAS\nO concurso destina-se à celebração de um acordo-quadro? Inexistência de acordo-quadro\nÉ utilizado um leilão eletrónico? Não\nÉ adotada uma fase de negociação? Não\nSistema de Aquisição Dinâmico: Inexistência de sistema de aquisição dinâmico\n\n9 - LOCAL DA EXECUÇÃO DO CONTRATO\nLOCAL DA EXECUÇÃO DO CONTRATO (PROCEDIMENTO)\nPaís: Portugal\nNUT III: PT187\nLocalidade: Évora\nDistrito: Évora\nConcelho: Évora\nFreguesia: União das Freguesias de Évora (São Mamede, Sé, São Pedro e Santo Antão)\nLOCAL DA EXECUÇÃO DO CONTRATO (LOTE)\nIdentificador do Lote: LOT-0001; LOT-0002\nPaís: Portugal\nNUT III: PT187\nLocalidade: Évora\nDistrito: Évora\nConcelho: Évora\nFreguesia: União das Freguesias de Évora (São Mamede, Sé, São Pedro e Santo Antão)\n\n10 - PRAZO DE EXECUÇÃO DO CONTRATO\nIdentificador do Lote: LOT-0001; LOT-0002\nPrazo de execução do contrato: 20 DIAS\nPrevisão de renovações: Não\n\n11 - FUNDOS EU\nIdentificador do Lote: LOT-0001; LOT-0002\nTêm fundos EU? Não\n\n12 - DOCUMENTOS DE HABILITAÇÃO\nHabilitação para o exercício da atividade profissional: Não\n\n13 - CONDIÇÕES DE APRESENTAÇÃO\nPlataforma eletrónica utilizada pela entidade adjudicante: VORTAL\nURL para Apresentação: https://community.vortal.biz/public/\nAdmissibilidade da apresentação de propostas variantes: Não autorizado\nPrazo para apresentação das propostas: 14-10-2025 18:00\nPrazo durante o qual os concorrentes são obrigados a manter as respetivas propostas: 120 dias a contar do termo do prazo para a apresentação das propostas\nIndicação de Subcontratação na Proposta: Inexistência de indicação de subcontratação\n\n14 - PRESTAÇÃO DE CAUÇÃO\nPrestação de caução: Não\n\n15 - FORNECIMENTO DAS PEÇAS DO CONCURSO, APRESENTAÇÃO DE PEDIDOS DE PARTICIPAÇÃO E APRESENTAÇÃO DAS PROPOSTAS\nLink para acesso às peças do concurso (URL): https://community.vortal.biz/Public/public-tender-documents/dlAzZ1dZTXBYaGtRYUN0b3hZbjRhb2Z4T0VRL1dvMzNTeUZEbTZxaDE5czVoSHZXNlpISlp3K01WOW16NmVWL1hEdHF0QmVOWkdmc3hGb2lxTkdsSXc9PSQhdDJz\n\n20 - OUTROS REQUISITOS\nIdentificador do Lote: LOT-0001; LOT-0002\nInformação sobre contratos reservados. Aplica-se a contratos reservados (54º-A)? Não\n\n21 - CRITÉRIO DE ADJUDICAÇÃO\nO Critério de adjudicação é diferenciado por lote? Não\nMultifator: Sim\nFator: \nNome: Preço\nPonderação: 60%\nSubfatores: Não\nFator: \nNome: Qualidade\nPonderação: 10%\nSubfatores: Não\nFator: \nNome: Qualidade\nPonderação: 20%\nSubfatores: Não\nFator: \nNome: Qualidade\nPonderação: 10%\nSubfatores: Não\n\n24 - CONDIÇÕES DO CONTRATO\nIdentificador do Lote: LOT-0001; LOT-0002\nFaturação Eletrónica: Permitido\nObrigação de Subcontratação:\nCódigo da Obrigação de Subcontratação: Não é aplicável nenhuma obrigação de subcontratação.\n\n25 - COMPRA PÚBLICA ESTRATÉGICA\nCompra Pública Estratégica: Inexistência de contratação pública estratégica\n\n26 - INFORMAÇÕES ADICIONAIS\nIdentificador do Lote: LOT-0001; LOT-0002\nContrato adequado para PME: Sim\nCobertura ACP (Acordo dos Contratos Públicos da Organização Mundial do Comércio): Não\n\n27 - IDENTIFICAÇÃO E CONTACTOS DO ÓRGÃO DE RECURSOS ADMINISTRATIVOS\nDesignação: Conselho de Administração\nEndereço: Largo Sr. de Pobreza\nCódigo postal: 7000-811\nLocalidade: Évora\nTelefone: +351 266740111\nFax: +351 266744212\nEndereço eletrónico: concursos.aprov@ulsac.min-saude.pt\n\n28 - IDENTIFICAÇÃO DO(S) AUTOR(ES) DE ANÚNCIO\nNome: Vitor Rui Gomes Fialho\nCargo: Presidente Conselho de Administração\n419587198",
    "nipc": "508085888",
    "distrito": "Évora",
    "concelho": "Évora",
    "freguesia": "Todas",
    "site": "www.hevora.min-saude.pt",
    "email": "concursos.aprov@ulsac.min-saude.pt",
    "designacao_contrato": "Equipamentos para o Serviço de Neonatologia",
    "descricao": "Aquisição de Equipamentos para o Serviço de Neonatologia",
    "preco_base": "124.000,00 EUR",
    "prazo_execucao": "20 DIAS",
    "prazo_apresentacao_propostas": "14-10-2025 18:00",
    "fundos_eu": "Não",
    "plataforma_eletronica": "VORTAL",
    "url_procedimento": "https://community.vortal.biz/public/",
    "autor_nome": "Vitor Rui Gomes Fialho",
    "autor_cargo": "Presidente Conselho de Administração"
  },
  {
    "numero_procedimento": "N/A",
    "entidade": "Força Aérea Portuguesa",
    "link": "https://diariodarepublica.pt/dr/detalhe/contrato-publico/25641-937197399",
    "detalhes_completos": "1 - IDENTIFICAÇÃO E CONTACTOS DA ENTIDADE ADJUDICANTE\nDesignação da entidade adjudicante: Força Aérea Portuguesa\nNIPC: 600010686\nServiço/Órgão/Pessoa de contacto: Ministério da Defesa Nacional  Comando da Logística da Força Aérea  Direção de Comunicações e Sistemas de Informação\nEndereço: Avenida da Força Aérea Portuguesa, Nº1\nCódigo postal: 2614-506\nLocalidade: Amadora\nPaís: Portugal\nNUT III: PT170\nDistrito: Lisboa\nConcelho: Amadora\nFreguesia: Freguesia de Alfragide\nTelefone: 214723726\nFax: 214723850\nEndereço da Entidade (URL): http://www.emfa.pt/www/contactos\nEndereço Eletrónico: CLAFA.AQUIS@EMFA.GOV.PT\neDelivery Gateway (URL): https://www.acingov.pt\nFunção da Organização: Adquirente\nNorma jurídica da Entidade Adjudicante: Organismo de direito público\nÁrea de atividade da Autoridade Adjudicante: Defesa\n\n2 - JORNAL OFICIAL DA UNIÃO EUROPEIA\nO procedimento a que este anúncio diz respeito também é publicitado no Jornal Oficial da União Europeia? Não\n\n3 - AVISO\nModelo de Anúncio: Concurso público\nData de Envio do Anúncio: 29-09-2025\n\n5 - PROCESSO\nTipo de Procedimento: Concurso público\nPreço base do procedimento: Sim\nValor do preço base do procedimento: 137.896,00 EUR\nProcedimento com lotes? Não\n\n6 - OBJETO DO CONTRATO\nNúmero de referência interna: DCSI 5025012640\nDesignação do contrato: AQUISIÇÃO DE SERVIÇOS DE COMUNICAÇÕES SATÉLITE PARA 24MESES\nDescrição: AQUISIÇÃO DE SERVIÇOS DE COMUNICAÇÕES SATÉLITE PARA 24MESES\nTipo de Contrato Principal: Aquisição de Serviços\nTipo de Contrato: Aquisição de Serviços\nClassificação CPV (Vocabulário Comum para os Contratos Públicos)\nObjeto principal\nVocabulário Principal: 64200000\nPreço base s/IVA: 137.896,00 EUR\n\n7 - INDICAÇÕES ADICIONAIS\nO contrato envolve aquisição conjunta (satisfação de várias entidades)? Não\nO contrato é adjudicado por uma central de compras? Não\n\n8 - TÉCNICAS\nO concurso destina-se à celebração de um acordo-quadro? Inexistência de acordo-quadro\nÉ utilizado um leilão eletrónico? Não\nÉ adotada uma fase de negociação? Não\nSistema de Aquisição Dinâmico: Inexistência de sistema de aquisição dinâmico\n\n9 - LOCAL DA EXECUÇÃO DO CONTRATO\nLOCAL DA EXECUÇÃO DO CONTRATO (PROCEDIMENTO)\nPaís: Portugal\nNUT III: PTZZZ\nLocalidade: De acordo com o CE.\nDistrito: Todos\nConcelho: Todos\nFreguesia: Todas\n\n10 - PRAZO DE EXECUÇÃO DO CONTRATO\nPrazo de execução do contrato: 5 DIAS\nPrevisão de renovações: Não\n\n11 - FUNDOS EU\nTêm fundos EU? Não\n\n12 - DOCUMENTOS DE HABILITAÇÃO\nHabilitação para o exercício da atividade profissional: Não\n\n13 - CONDIÇÕES DE APRESENTAÇÃO\nPlataforma eletrónica utilizada pela entidade adjudicante: ACIN\nURL para Apresentação: https://www.acingov.pt\nAdmissibilidade da apresentação de propostas variantes: Não autorizado\nPrazo para apresentação das propostas: 13-10-2025 23:00\nPrazo durante o qual os concorrentes são obrigados a manter as respetivas propostas: 66 dias a contar do termo do prazo para a apresentação das propostas\nIndicação de Subcontratação na Proposta: Inexistência de indicação de subcontratação\n\n14 - PRESTAÇÃO DE CAUÇÃO\nPrestação de caução: Não\n\n15 - FORNECIMENTO DAS PEÇAS DO CONCURSO, APRESENTAÇÃO DE PEDIDOS DE PARTICIPAÇÃO E APRESENTAÇÃO DAS PROPOSTAS\nLink para acesso às peças do concurso (URL): https://www.acingov.pt/acingovprod/2/zonaPublica/zona_publica_c/donwloadProcedurePiece/OTgyMjY2\n\n20 - OUTROS REQUISITOS\nInformação sobre contratos reservados. Aplica-se a contratos reservados (54º-A)? Não\n\n21 - CRITÉRIO DE ADJUDICAÇÃO\nMultifator: Não\nMonofator:\nNome: Preço\n\n24 - CONDIÇÕES DO CONTRATO\nFaturação Eletrónica: Permitido\nObrigação de Subcontratação:\nCódigo da Obrigação de Subcontratação: Não é aplicável nenhuma obrigação de subcontratação.\n\n25 - COMPRA PÚBLICA ESTRATÉGICA\nCompra Pública Estratégica: Inexistência de contratação pública estratégica\n\n26 - INFORMAÇÕES ADICIONAIS\nContrato adequado para PME: Sim\nCobertura ACP (Acordo dos Contratos Públicos da Organização Mundial do Comércio): Não\n\n27 - IDENTIFICAÇÃO E CONTACTOS DO ÓRGÃO DE RECURSOS ADMINISTRATIVOS\nDesignação: CHEFE DO ESTADO-MAIOR DA FORÇA AÉREA\nEndereço: Avenida da Força Aérea Portuguesa, N.º 1\nCódigo postal: 2614-506\nLocalidade: Amadora\nTelefone: 214723861\nFax: \nEndereço eletrónico: CLAFA.AQUIS@EMFA.GOV.PT\n\n28 - IDENTIFICAÇÃO DO(S) AUTOR(ES) DE ANÚNCIO\nNome: COR/ADMAER FILIPE RODRIGUES\nCargo: CHEFE DO GAP\n419590818",
    "nipc": "600010686",
    "distrito": "Lisboa",
    "concelho": "Amadora",
    "freguesia": "Freguesia de Alfragide",
    "site": "http://www.emfa.pt/www/contactos",
    "email": "CLAFA.AQUIS@EMFA.GOV.PT",
    "designacao_contrato": "AQUISIÇÃO DE SERVIÇOS DE COMUNICAÇÕES SATÉLITE PARA 24MESES",
    "descricao": "AQUISIÇÃO DE SERVIÇOS DE COMUNICAÇÕES SATÉLITE PARA 24MESES",
    "preco_base": "137.896,00 EUR",
    "prazo_execucao": "5 DIAS",
    "prazo_apresentacao_propostas": "13-10-2025 23:00",
    "fundos_eu": "Não",
    "plataforma_eletronica": "ACIN",
    "url_procedimento": "https://www.acingov.pt",
    "autor_nome": "COR/ADMAER FILIPE RODRIGUES",
    "autor_cargo": "CHEFE DO GAP"
  },
  {
    "numero_procedimento": "N/A",
    "entidade": "Unidade Local de Saúde de Coimbra, E. P. E.",
    "link": "https://diariodarepublica.pt/dr/detalhe/contrato-publico/25643-937197403",
    "detalhes_completos": "1 - IDENTIFICAÇÃO E CONTACTOS DA ENTIDADE ADJUDICANTE\nDesignação da entidade adjudicante: Unidade Local de Saúde de Coimbra, E. P. E.\nNIPC: 510103448\nEndereço: Praceta Prof. Mota Pinto\nCódigo postal: 3004-561\nLocalidade: Coimbra\nPaís: Portugal\nNUT III: PT16E\nDistrito: Coimbra\nConcelho: Coimbra\nFreguesia: Todas\nTelefone: 239400605\nFax: 239400605\nEndereço da Entidade (URL): https://www.chuc.min-saude.pt\nEndereço Eletrónico: ana.rosete@ulscoimbra.min-saude.pt\neDelivery Gateway (URL): https://community.vortal.biz/public/\nFunção da Organização: Adquirente\nNorma jurídica da Entidade Adjudicante: Organismo de direito público\nÁrea de atividade da Autoridade Adjudicante: Saúde\n\n2 - JORNAL OFICIAL DA UNIÃO EUROPEIA\nO procedimento a que este anúncio diz respeito também é publicitado no Jornal Oficial da União Europeia? Não\n\n3 - AVISO\nModelo de Anúncio: Concurso público\nData de Envio do Anúncio: 29-09-2025\n\n5 - PROCESSO\nTipo de Procedimento: Concurso público\nPreço base do procedimento: Sim\nValor do preço base do procedimento: 69.000,00 EUR\nProcedimento com lotes? Não\n\n6 - OBJETO DO CONTRATO\nNúmero de referência interna: 010900592025\nDesignação do contrato: Aquisição de equipamento de eletroconvulsoterapia para o Serviço de Psiquiatria da Unidade Local de Saúde de Coimbra, E.P.E.\nDescrição: Aquisição de um equipamento de eletroconvulsoterapia para o Serviço de Psiquiatria\nTipo de Contrato Principal: Aquisição de Bens Móveis\nTipo de Contrato: Aquisição de Bens Móveis\nClassificação CPV (Vocabulário Comum para os Contratos Públicos)\nObjeto principal\nVocabulário Principal: 33158200\nPreço base s/IVA: 69.000,00 EUR\n\n7 - INDICAÇÕES ADICIONAIS\nO contrato envolve aquisição conjunta (satisfação de várias entidades)? Não\nO contrato é adjudicado por uma central de compras? Não\n\n8 - TÉCNICAS\nO concurso destina-se à celebração de um acordo-quadro? Inexistência de acordo-quadro\nÉ utilizado um leilão eletrónico? Não\nÉ adotada uma fase de negociação? Não\nSistema de Aquisição Dinâmico: Inexistência de sistema de aquisição dinâmico\n\n9 - LOCAL DA EXECUÇÃO DO CONTRATO\nLOCAL DA EXECUÇÃO DO CONTRATO (PROCEDIMENTO)\nPaís: Portugal\nNUT III: PT16E\nLocalidade: Coimbra\nDistrito: Coimbra\nConcelho: Coimbra\nFreguesia: Freguesia de Santo António dos Olivais\n\n10 - PRAZO DE EXECUÇÃO DO CONTRATO\nPrazo de execução do contrato: 30 DIAS\nPrevisão de renovações: Não\n\n11 - FUNDOS EU\nTêm fundos EU? Não\n\n12 - DOCUMENTOS DE HABILITAÇÃO\nHabilitação para o exercício da atividade profissional: Não\n\n13 - CONDIÇÕES DE APRESENTAÇÃO\nPlataforma eletrónica utilizada pela entidade adjudicante: VORTAL\nURL para Apresentação: https://community.vortal.biz/public/\nAdmissibilidade da apresentação de propostas variantes: Não autorizado\nPrazo para apresentação das propostas: 20-10-2025 23:59\nPrazo durante o qual os concorrentes são obrigados a manter as respetivas propostas: 90 dias a contar do termo do prazo para a apresentação das propostas\nIndicação de Subcontratação na Proposta: Inexistência de indicação de subcontratação\n\n14 - PRESTAÇÃO DE CAUÇÃO\nPrestação de caução: Não\n\n15 - FORNECIMENTO DAS PEÇAS DO CONCURSO, APRESENTAÇÃO DE PEDIDOS DE PARTICIPAÇÃO E APRESENTAÇÃO DAS PROPOSTAS\nLink para acesso às peças do concurso (URL): https://community.vortal.biz/Public/public-tender-documents/aHdKMnhkQlU4TGxSakR2Y1gzT1BQaFM5SXVURmoxWXBiN2tHZmFPaXFRa3o3N0R2VEliVlZpNkNYTnJOVmhReU5ZZWZDb3ROQVlxV0xOTytiQkhQQkE9PWlZRjAo\n\n20 - OUTROS REQUISITOS\nInformação sobre contratos reservados. Aplica-se a contratos reservados (54º-A)? Não\n\n21 - CRITÉRIO DE ADJUDICAÇÃO\nMultifator: Sim\nFator: \nNome: Preço\nPonderação: 70%\nSubfatores: Não\nFator: \nNome: Qualidade\nPonderação: 30%\nSubfatores: Não\n\n24 - CONDIÇÕES DO CONTRATO\nFaturação Eletrónica: Permitido\nObrigação de Subcontratação:\nCódigo da Obrigação de Subcontratação: Não é aplicável nenhuma obrigação de subcontratação.\n\n25 - COMPRA PÚBLICA ESTRATÉGICA\nCompra Pública Estratégica: Inexistência de contratação pública estratégica\n\n26 - INFORMAÇÕES ADICIONAIS\nContrato adequado para PME: Sim\nCobertura ACP (Acordo dos Contratos Públicos da Organização Mundial do Comércio): Não\n\n27 - IDENTIFICAÇÃO E CONTACTOS DO ÓRGÃO DE RECURSOS ADMINISTRATIVOS\nDesignação: Conselho de Administração da Unidade Local de Saúde de Coimbra, E.P.E.\nEndereço: Praceta Prof. Mota Pinto\nCódigo postal: 3004-561\nLocalidade: Coimbra\nTelefone: +351 239400400\nFax: +351 239400400\nEndereço eletrónico: casec@ulscoimbra.min-saude.pt\n\n28 - IDENTIFICAÇÃO DO(S) AUTOR(ES) DE ANÚNCIO\nNome: Esperança Mariano\nCargo: Assistente Técnica\n419586071",
    "nipc": "510103448",
    "distrito": "Coimbra",
    "concelho": "Coimbra",
    "freguesia": "Todas",
    "site": "https://www.chuc.min-saude.pt",
    "email": "ana.rosete@ulscoimbra.min-saude.pt",
    "designacao_contrato": "Aquisição de equipamento de eletroconvulsoterapia para o Serviço de Psiquiatria da Unidade Local de Saúde de Coimbra, E.P.E.",
    "descricao": "Aquisição de um equipamento de eletroconvulsoterapia para o Serviço de Psiquiatria",
    "preco_base": "69.000,00 EUR",
    "prazo_execucao": "30 DIAS",
    "prazo_apresentacao_propostas": "20-10-2025 23:59",
    "fundos_eu": "Não",
    "plataforma_eletronica": "VORTAL",
    "url_procedimento": "https://community.vortal.biz/public/",
    "autor_nome": "Esperança Mariano",
    "autor_cargo": "Assistente Técnica"
  },
  {
    "numero_procedimento": "N/A",
    "entidade": "Município do Montijo",
    "link": "https://diariodarepublica.pt/dr/detalhe/contrato-publico/25645-937197408",
    "detalhes_completos": "1 - IDENTIFICAÇÃO E CONTACTOS DA ENTIDADE ADJUDICANTE\nDesignação da entidade adjudicante: Município do Montijo\nNIPC: 502834846\nEndereço: Rua Manuel Neves Nunes de Almeida\nCódigo postal: 2870-352\nLocalidade: Setúbal\nPaís: Portugal\nNUT III: PT170\nDistrito: Setúbal\nConcelho: Montijo\nFreguesia: Todas\nTelefone: 212327600\nFax: 212327600\nEndereço da Entidade (URL): www.mun-montijo.pt\nEndereço Eletrónico: geral@mun-montijo.pt\neDelivery Gateway (URL): https://community.vortal.biz/public/\nFunção da Organização: Adquirente\nNorma jurídica da Entidade Adjudicante: Autoridade local\nÁrea de atividade da Autoridade Adjudicante: Serviços públicos das administrações públicas\n\n2 - JORNAL OFICIAL DA UNIÃO EUROPEIA\nO procedimento a que este anúncio diz respeito também é publicitado no Jornal Oficial da União Europeia? Não\n\n3 - AVISO\nModelo de Anúncio: Concurso público\nData de Envio do Anúncio: 29-09-2025\n\n5 - PROCESSO\nTipo de Procedimento: Concurso público\nPreço base do procedimento: Sim\nValor do preço base do procedimento: 70.898,40 EUR\nProcedimento com lotes? Não\n\n6 - OBJETO DO CONTRATO\nNúmero de referência interna: 157/2025\nDesignação do contrato: Aquisição de serviços de sensibilização e promoção da adesão (Fase II) ao sistema de recolha de biorresíduos na União de Freguesia de Montijo e Afonsoeiro\nDescrição: Aquisição de serviços de sensibilização e de promoção da adesão (Fase II) ao sistema de recolha de biorresíduos na União de Freguesia de Montijo e Afonsoeiro\nTipo de Contrato Principal: Aquisição de Serviços\nTipo de Contrato: Aquisição de Serviços\nClassificação CPV (Vocabulário Comum para os Contratos Públicos)\nObjeto principal\nVocabulário Principal: 79340000\nPreço base s/IVA: 70.898,40 EUR\n\n7 - INDICAÇÕES ADICIONAIS\nO contrato envolve aquisição conjunta (satisfação de várias entidades)? Não\nO contrato é adjudicado por uma central de compras? Não\n\n8 - TÉCNICAS\nO concurso destina-se à celebração de um acordo-quadro? Inexistência de acordo-quadro\nÉ utilizado um leilão eletrónico? Não\nÉ adotada uma fase de negociação? Não\nSistema de Aquisição Dinâmico: Inexistência de sistema de aquisição dinâmico\n\n9 - LOCAL DA EXECUÇÃO DO CONTRATO\nLOCAL DA EXECUÇÃO DO CONTRATO (PROCEDIMENTO)\nPaís: Portugal\nNUT III: PT170\nLocalidade: Setúbal\nDistrito: Setúbal\nConcelho: Montijo\nFreguesia: União das Freguesias de Montijo e Afonsoeiro\n\n10 - PRAZO DE EXECUÇÃO DO CONTRATO\nPrazo de execução do contrato: 60 DIAS\nPrevisão de renovações: Não\n\n11 - FUNDOS EU\nTêm fundos EU? Não\n\n12 - DOCUMENTOS DE HABILITAÇÃO\nHabilitação para o exercício da atividade profissional: Não\n\n13 - CONDIÇÕES DE APRESENTAÇÃO\nPlataforma eletrónica utilizada pela entidade adjudicante: VORTAL\nURL para Apresentação: https://community.vortal.biz/public/\nAdmissibilidade da apresentação de propostas variantes: Não autorizado\nPrazo para apresentação das propostas: 06-10-2025 18:00\nPrazo durante o qual os concorrentes são obrigados a manter as respetivas propostas: 90 dias a contar do termo do prazo para a apresentação das propostas\nIndicação de Subcontratação na Proposta: Inexistência de indicação de subcontratação\n\n14 - PRESTAÇÃO DE CAUÇÃO\nPrestação de caução: Não\n\n15 - FORNECIMENTO DAS PEÇAS DO CONCURSO, APRESENTAÇÃO DE PEDIDOS DE PARTICIPAÇÃO E APRESENTAÇÃO DAS PROPOSTAS\nLink para acesso às peças do concurso (URL): https://community.vortal.biz/Public/public-tender-documents/cENIcEs3ajJsYlBacVkxT1N6bjZGdDFkd2dZNTRvRUsrRllGeWV2ZzR1VmY1VTBlRVdkdkNva1FEUndwcWoxV0NWaUFEMm94YjJTUzZMa1YwUHRWL0E9PUNDYzdw\n\n20 - OUTROS REQUISITOS\nInformação sobre contratos reservados. Aplica-se a contratos reservados (54º-A)? Não\n\n21 - CRITÉRIO DE ADJUDICAÇÃO\nMultifator: Não\nMonofator:\nNome: Preço\n\n24 - CONDIÇÕES DO CONTRATO\nFaturação Eletrónica: Permitido\nObrigação de Subcontratação:\nCódigo da Obrigação de Subcontratação: Não é aplicável nenhuma obrigação de subcontratação.\n\n25 - COMPRA PÚBLICA ESTRATÉGICA\nCompra Pública Estratégica: Inexistência de contratação pública estratégica\n\n26 - INFORMAÇÕES ADICIONAIS\nContrato adequado para PME: Sim\nCobertura ACP (Acordo dos Contratos Públicos da Organização Mundial do Comércio): Não\n\n27 - IDENTIFICAÇÃO E CONTACTOS DO ÓRGÃO DE RECURSOS ADMINISTRATIVOS\nDesignação: Município de Montijo\nEndereço: Rua Dr. Manuel Neves Nunes de Almeida\nCódigo postal: 2870-352\nLocalidade: Montijo\nTelefone: +351 212327600\nFax: +351 000000000\nEndereço eletrónico: dgfp.contratacaopublica@mun-montijo.pt\n\n28 - IDENTIFICAÇÃO DO(S) AUTOR(ES) DE ANÚNCIO\nNome: Maria Clara de Oliveria da Silva\nCargo: Presidente da Câmara Municipal de Montijo\n419584808",
    "nipc": "502834846",
    "distrito": "Setúbal",
    "concelho": "Montijo",
    "freguesia": "Todas",
    "site": "www.mun-montijo.pt",
    "email": "geral@mun-montijo.pt",
    "designacao_contrato": "Aquisição de serviços de sensibilização e promoção da adesão (Fase II) ao sistema de recolha de biorresíduos na União de Freguesia de Montijo e Afonsoeiro",
    "descricao": "Aquisição de serviços de sensibilização e de promoção da adesão (Fase II) ao sistema de recolha de biorresíduos na União de Freguesia de Montijo e Afonsoeiro",
    "preco_base": "70.898,40 EUR",
    "prazo_execucao": "60 DIAS",
    "prazo_apresentacao_propostas": "06-10-2025 18:00",
    "fundos_eu": "Não",
    "plataforma_eletronica": "VORTAL",
    "url_procedimento": "https://community.vortal.biz/public/",
    "autor_nome": "Maria Clara de Oliveria da Silva",
    "autor_cargo": "Presidente da Câmara Municipal de Montijo"
  },
  {
    "numero_procedimento": "N/A",
    "entidade": "Fundação INATEL",
    "link": "https://diariodarepublica.pt/dr/detalhe/contrato-publico/25646-937197411",
    "detalhes_completos": "1 - IDENTIFICAÇÃO E CONTACTOS DA ENTIDADE ADJUDICANTE\nDesignação da entidade adjudicante: Fundação INATEL\nNIPC: 500122237\nServiço/Órgão/Pessoa de contacto: NCP\nEndereço: Calçada de Santana, nº 180\nCódigo postal: 1169-062\nLocalidade: Lisboa\nPaís: Portugal\nNUT III: PT170\nDistrito: Lisboa\nConcelho: Lisboa\nFreguesia: Freguesia de Arroios - Lisboa\nTelefone: 210027000\nFax: 210027000\nEndereço da Entidade (URL): https://www.inatel.pt\nEndereço Eletrónico: fundacao.inatel@inatel.pt\neDelivery Gateway (URL): https://www.acingov.pt\nFunção da Organização: Adquirente\nSubfunção da Organização: Organização cujo orçamento é utilizado para pagar o contrato; Organização que executa o pagamento; Organização que fornece informações adicionais sobre o processo de adjudicação; Organização que fornece mais informações sobre os prazos dos procedimentos de recurso; Organização que fornece acesso fora de linha aos documentos do concurso; Organização responsável pelo tratamento das propostas; Organização que recebe as propostas; Organização que trata os pedidos de participação; Organização que recebe pedidos de participação; Organização que fornece mais informações sobre os procedimentos de recurso; Organização que assina o contrato\nNorma jurídica da Entidade Adjudicante: Organismo de direito público\nÁrea de atividade da Autoridade Adjudicante: Atividades recreativas, culturais e religiosas\n\n2 - JORNAL OFICIAL DA UNIÃO EUROPEIA\nO procedimento a que este anúncio diz respeito também é publicitado no Jornal Oficial da União Europeia? Não\n\n3 - AVISO\nModelo de Anúncio: Concurso público\nData de Envio do Anúncio: 29-09-2025\n\n5 - PROCESSO\nTipo de Procedimento: Concurso público\nPreço base do procedimento: Sim\nValor do preço base do procedimento: 3.000,00 EUR\nProcedimento com lotes? Não\n\n6 - OBJETO DO CONTRATO\nNúmero de referência interna: P.25.216/NCP\nDesignação do contrato: SERVIÇOS DE LAVANDARIA EM REGIME DE OUTSOURCING PARA A UNIDADE HOTELEIRA DA FUNDAÇÃO INATEL - ALBUFEIRA\nDescrição: SERVIÇOS DE LAVANDARIA EM REGIME DE OUTSOURCING PARA A UNIDADE HOTELEIRA DA FUNDAÇÃO INATEL - ALBUFEIRA\nTipo de Contrato Principal: Aquisição de Serviços\nTipo de Contrato: Aquisição de Serviços\nClassificação CPV (Vocabulário Comum para os Contratos Públicos)\nObjeto principal\nVocabulário Principal: 98311000\nPreço base s/IVA: 3.000,00 EUR\n\n7 - INDICAÇÕES ADICIONAIS\nO contrato envolve aquisição conjunta (satisfação de várias entidades)? Não\nO contrato é adjudicado por uma central de compras? Não\n\n8 - TÉCNICAS\nO concurso destina-se à celebração de um acordo-quadro? Inexistência de acordo-quadro\nÉ utilizado um leilão eletrónico? Não\nÉ adotada uma fase de negociação? Não\nSistema de Aquisição Dinâmico: Inexistência de sistema de aquisição dinâmico\n\n9 - LOCAL DA EXECUÇÃO DO CONTRATO\nLOCAL DA EXECUÇÃO DO CONTRATO (PROCEDIMENTO)\nPaís: Portugal\nNUT III: PT150\nLocalidade: todos\nDistrito: Faro\nConcelho: Albufeira\nFreguesia: Todas\n\n10 - PRAZO DE EXECUÇÃO DO CONTRATO\nPrazo de execução do contrato: 3 MESES\nPrevisão de renovações: Não\n\n11 - FUNDOS EU\nTêm fundos EU? Não\n\n12 - DOCUMENTOS DE HABILITAÇÃO\nHabilitação para o exercício da atividade profissional: Não\n\n13 - CONDIÇÕES DE APRESENTAÇÃO\nPlataforma eletrónica utilizada pela entidade adjudicante: ACIN\nURL para Apresentação: https://www.acingov.pt\nAdmissibilidade da apresentação de propostas variantes: Não autorizado\nPrazo para apresentação das propostas: 03-10-2025 23:59\nPrazo durante o qual os concorrentes são obrigados a manter as respetivas propostas: 66 dias a contar do termo do prazo para a apresentação das propostas\nIndicação de Subcontratação na Proposta: Inexistência de indicação de subcontratação\n\n14 - PRESTAÇÃO DE CAUÇÃO\nPrestação de caução: Não\n\n15 - FORNECIMENTO DAS PEÇAS DO CONCURSO, APRESENTAÇÃO DE PEDIDOS DE PARTICIPAÇÃO E APRESENTAÇÃO DAS PROPOSTAS\nLink para acesso às peças do concurso (URL): https://www.acingov.pt/acingovprod/2/zonaPublica/zona_publica_c/donwloadProcedurePiece/OTgxMDQx\n\n20 - OUTROS REQUISITOS\nInformação sobre contratos reservados. Aplica-se a contratos reservados (54º-A)? Não\n\n21 - CRITÉRIO DE ADJUDICAÇÃO\nMultifator: Não\nMonofator:\nNome: Outros\nOutro nome: Fator Preço\n\n24 - CONDIÇÕES DO CONTRATO\nFaturação Eletrónica: Permitido\nObrigação de Subcontratação:\nCódigo da Obrigação de Subcontratação: Não é aplicável nenhuma obrigação de subcontratação.\n\n25 - COMPRA PÚBLICA ESTRATÉGICA\nCompra Pública Estratégica: Inexistência de contratação pública estratégica\n\n26 - INFORMAÇÕES ADICIONAIS\nContrato adequado para PME: Sim\nCobertura ACP (Acordo dos Contratos Públicos da Organização Mundial do Comércio): Não\n\n27 - IDENTIFICAÇÃO E CONTACTOS DO ÓRGÃO DE RECURSOS ADMINISTRATIVOS\nDesignação: CA\nEndereço: Calçada de Santana 180\nCódigo postal: 1169-062\nLocalidade: Lisboa\nTelefone: 210027000\nFax: 210027027\nEndereço eletrónico: ncp-procedimentos@inatel.pt\nPrazo de interposição do recurso: 5 dias\n\n28 - IDENTIFICAÇÃO DO(S) AUTOR(ES) DE ANÚNCIO\nNome: Tiago Tenreiro Alves\nCargo: Técnico\n419581202",
    "nipc": "500122237",
    "distrito": "Lisboa",
    "concelho": "Lisboa",
    "freguesia": "Freguesia de Arroios - Lisboa",
    "site": "https://www.inatel.pt",
    "email": "fundacao.inatel@inatel.pt",
    "designacao_contrato": "SERVIÇOS DE LAVANDARIA EM REGIME DE OUTSOURCING PARA A UNIDADE HOTELEIRA DA FUNDAÇÃO INATEL - ALBUFEIRA",
    "descricao": "SERVIÇOS DE LAVANDARIA EM REGIME DE OUTSOURCING PARA A UNIDADE HOTELEIRA DA FUNDAÇÃO INATEL - ALBUFEIRA",
    "preco_base": "3.000,00 EUR",
    "prazo_execucao": "3 MESES",
    "prazo_apresentacao_propostas": "03-10-2025 23:59",
    "fundos_eu": "Não",
    "plataforma_eletronica": "ACIN",
    "url_procedimento": "https://www.acingov.pt",
    "autor_nome": "Tiago Tenreiro Alves",
    "autor_cargo": "Técnico"
  },
  {
    "numero_procedimento": "N/A",
    "entidade": "Município de Ponte da Barca",
    "link": "https://diariodarepublica.pt/dr/detalhe/contrato-publico/25652-937197420",
    "detalhes_completos": "1 - IDENTIFICAÇÃO E CONTACTOS DA ENTIDADE ADJUDICANTE\nDesignação da entidade adjudicante: Município de Ponte da Barca\nNIPC: 505676770\nEndereço: Praça Dr. António Lacerda\nCódigo postal: 4980-626\nLocalidade: Ponte da Barca\nPaís: Portugal\nNUT III: PT111\nDistrito: Viana do Castelo\nConcelho: Ponte da Barca\nFreguesia: Todas\nTelefone: 258480180\nFax: 258480189\nEndereço da Entidade (URL): www.cmpb.pt\nEndereço Eletrónico: informatica@cmpb.pt\neDelivery Gateway (URL): https://community.vortal.biz/public/\nFunção da Organização: Adquirente\nNorma jurídica da Entidade Adjudicante: Autoridade local\nÁrea de atividade da Autoridade Adjudicante: Serviços públicos das administrações públicas\n\n2 - JORNAL OFICIAL DA UNIÃO EUROPEIA\nO procedimento a que este anúncio diz respeito também é publicitado no Jornal Oficial da União Europeia? Não\n\n3 - AVISO\nModelo de Anúncio: Concurso público\nData de Envio do Anúncio: 29-09-2025\n\n5 - PROCESSO\nTipo de Procedimento: Concurso público\nPreço base do procedimento: Sim\nValor do preço base do procedimento: 164.362,60 EUR\nProcedimento com lotes? Não\n\n6 - OBJETO DO CONTRATO\nNúmero de referência interna: E_34/2025\nDesignação do contrato: Repavimentação e Saneamento da Rua dos Enxutos e Rua Ribeiro Da Granja - Oleiros\nDescrição: Repavimentação e Saneamento da Rua dos Enxutos e Rua Ribeiro Da Granja - Oleiros\nTipo de Contrato Principal: Empreitada de Obras Públicas\nTipo de Contrato: Empreitada de Obras Públicas\nClassificação CPV (Vocabulário Comum para os Contratos Públicos)\nObjeto principal\nVocabulário Principal: 45232460\nPreço base s/IVA: 164.362,60 EUR\n\n7 - INDICAÇÕES ADICIONAIS\nO contrato envolve aquisição conjunta (satisfação de várias entidades)? Não\nO contrato é adjudicado por uma central de compras? Não\n\n8 - TÉCNICAS\nO concurso destina-se à celebração de um acordo-quadro? Inexistência de acordo-quadro\nÉ utilizado um leilão eletrónico? Não\nÉ adotada uma fase de negociação? Não\nSistema de Aquisição Dinâmico: Inexistência de sistema de aquisição dinâmico\n\n9 - LOCAL DA EXECUÇÃO DO CONTRATO\nLOCAL DA EXECUÇÃO DO CONTRATO (PROCEDIMENTO)\nPaís: Portugal\nNUT III: PTZZZ\nLocalidade: PORTUGAL\nDistrito: Todos\nConcelho: Todos\nFreguesia: Todas\n\n10 - PRAZO DE EXECUÇÃO DO CONTRATO\nPrazo de execução do contrato: 30 DIAS\nPrevisão de renovações: Não\n\n11 - FUNDOS EU\nTêm fundos EU? Não\n\n12 - DOCUMENTOS DE HABILITAÇÃO\nHabilitação para o exercício da atividade profissional: Sim\nTipo: Alvará\nDescrição: Alvará - 6.ª subcategoria da 2.ª categoria - Saneamento Básico\n\n13 - CONDIÇÕES DE APRESENTAÇÃO\nPlataforma eletrónica utilizada pela entidade adjudicante: VORTAL\nURL para Apresentação: https://community.vortal.biz/public/\nAdmissibilidade da apresentação de propostas variantes: Não autorizado\nPrazo para apresentação das propostas: 20-10-2025 23:59\nPrazo durante o qual os concorrentes são obrigados a manter as respetivas propostas: 66 dias a contar do termo do prazo para a apresentação das propostas\nIndicação de Subcontratação na Proposta: Inexistência de indicação de subcontratação\n\n14 - PRESTAÇÃO DE CAUÇÃO\nPrestação de caução: Sim\nPercentagem: 10%\nDescrição da Garantia Exigida: Por depósito em dinheiro ou em títulos emitidos ou garantidos pelo Estado Português à ordem da entidade que for indicada pelo Município de Ponte da Barca ou mediante garantia bancária ou seguro-caução.\n\n15 - FORNECIMENTO DAS PEÇAS DO CONCURSO, APRESENTAÇÃO DE PEDIDOS DE PARTICIPAÇÃO E APRESENTAÇÃO DAS PROPOSTAS\nLink para acesso às peças do concurso (URL): https://community.vortal.biz/Public/public-tender-documents/UXM5L0htRS84a04rMnNScVBiQjBaOEZhdHV5aDB6d2Y0V1FwRStKL2ZCN2VFT1NBZ3B1MGI5WkR4ZkZUZXFKVzRBTUsrQ3g5VGdaNEJVb2lJMmNoTUE9PVllcUNR\n\n20 - OUTROS REQUISITOS\nInformação sobre contratos reservados. Aplica-se a contratos reservados (54º-A)? Não\n\n21 - CRITÉRIO DE ADJUDICAÇÃO\nMultifator: Sim\nFator: \nNome: Preço\nPonderação: 80%\nSubfatores: Não\nFator: \nNome: Qualidade\nPonderação: 20%\nSubfatores: Sim\nSubfatores: \nNome: Número de anos acima do prazo legal, previsto na alínea a) do nº 2 do artigo 397º do CCP\nPonderação : 20%; \nNome: Número de anos acima do prazo legal, previsto na alínea b) do nº 2 do artigo 397º do CCP\nPonderação : 40%; \nNome: Número de anos acima do prazo legal, previsto na alínea c) do nº 2 do artigo 397º do CCP\nPonderação : 40%; \n\n24 - CONDIÇÕES DO CONTRATO\nFaturação Eletrónica: Permitido\nObrigação de Subcontratação:\nCódigo da Obrigação de Subcontratação: Não é aplicável nenhuma obrigação de subcontratação.\n\n25 - COMPRA PÚBLICA ESTRATÉGICA\nCompra Pública Estratégica: Inexistência de contratação pública estratégica\n\n26 - INFORMAÇÕES ADICIONAIS\nContrato adequado para PME: Sim\nCobertura ACP (Acordo dos Contratos Públicos da Organização Mundial do Comércio): Não\n\n27 - IDENTIFICAÇÃO E CONTACTOS DO ÓRGÃO DE RECURSOS ADMINISTRATIVOS\nDesignação: Presidente da Câmara Municipal de Ponte da Barca\nEndereço: Praça Dr. António Lacerda\nCódigo postal: 4980-626\nLocalidade: Ponte da Barca\nTelefone: +351 258480180\nFax: +351 258480180\nEndereço eletrónico: geral@cmpb.pt\n\n28 - IDENTIFICAÇÃO DO(S) AUTOR(ES) DE ANÚNCIO\nNome: Augusto Manuel dos Reis Marinho\nCargo: Presidente da Câmara Municipal de Ponte da Barca\n419589944",
    "nipc": "505676770",
    "distrito": "Viana do Castelo",
    "concelho": "Ponte da Barca",
    "freguesia": "Todas",
    "site": "www.cmpb.pt",
    "email": "informatica@cmpb.pt",
    "designacao_contrato": "Repavimentação e Saneamento da Rua dos Enxutos e Rua Ribeiro Da Granja - Oleiros",
    "descricao": "Repavimentação e Saneamento da Rua dos Enxutos e Rua Ribeiro Da Granja - Oleiros",
    "preco_base": "164.362,60 EUR",
    "prazo_execucao": "30 DIAS",
    "prazo_apresentacao_propostas": "20-10-2025 23:59",
    "fundos_eu": "Não",
    "plataforma_eletronica": "VORTAL",
    "url_procedimento": "https://community.vortal.biz/public/",
    "autor_nome": "Augusto Manuel dos Reis Marinho",
    "autor_cargo": "Presidente da Câmara Municipal de Ponte da Barca"
  },
  {
    "numero_procedimento": "N/A",
    "entidade": "Ágora - Cultura e Desporto do Porto, E.M., S.A.",
    "link": "https://diariodarepublica.pt/dr/detalhe/contrato-publico/25656-937197425",
    "detalhes_completos": "1 - IDENTIFICAÇÃO E CONTACTOS DA ENTIDADE ADJUDICANTE\nDesignação da entidade adjudicante: Ágora - Cultura e Desporto do Porto, E.M., S.A.\nNIPC: 507718640\nServiço/Órgão/Pessoa de contacto: Administradores Executivos\nEndereço: Rua Bartolomeu Velho, 648\nCódigo postal: 4150-124\nLocalidade: Porto\nPaís: Portugal\nNUT III: PT11A\nDistrito: Porto\nConcelho: Porto\nFreguesia: União das Freguesias de Aldoar, Foz do Douro e Nevogilde\nTelefone: 226199860\nFax: 226199869\nEndereço da Entidade (URL): www.agoraporto.pt\nEndereço Eletrónico: geral@agoraporto.pt\neDelivery Gateway (URL): https://www.acingov.pt\nFunção da Organização: Adquirente\nNorma jurídica da Entidade Adjudicante: Organismo de direito público\nÁrea de atividade da Autoridade Adjudicante: Serviços públicos das administrações públicas\n\n2 - JORNAL OFICIAL DA UNIÃO EUROPEIA\nO procedimento a que este anúncio diz respeito também é publicitado no Jornal Oficial da União Europeia? Não\n\n3 - AVISO\nModelo de Anúncio: Concurso público\nData de Envio do Anúncio: 29-09-2025\n\n5 - PROCESSO\nTipo de Procedimento: Concurso público\nPreço base do procedimento: Sim\nValor do preço base do procedimento: 14.000,00 EUR\nProcedimento com lotes? Não\n\n6 - OBJETO DO CONTRATO\nNúmero de referência interna: CP/53/2025\nDesignação do contrato: Contratação de serviços de montagem e desmontagem de estruturas para cumprimento do desenho expositivo da exposição CALÓ&QUEIMADELA;\nDescrição: Contratação de serviços de montagem e desmontagem de estruturas para cumprimento do desenho expositivo da exposição CALÓ&QUEIMADELA;.\nTipo de Contrato Principal: Aquisição de Serviços\nTipo de Contrato: Aquisição de Serviços\nClassificação CPV (Vocabulário Comum para os Contratos Públicos)\nObjeto principal\nVocabulário Principal: 71320000\nPreço base s/IVA: 14.000,00 EUR\n\n7 - INDICAÇÕES ADICIONAIS\nO contrato envolve aquisição conjunta (satisfação de várias entidades)? Não\nO contrato é adjudicado por uma central de compras? Sim\n\n8 - TÉCNICAS\nO concurso destina-se à celebração de um acordo-quadro? Inexistência de acordo-quadro\nÉ utilizado um leilão eletrónico? Não\nÉ adotada uma fase de negociação? Não\nSistema de Aquisição Dinâmico: Inexistência de sistema de aquisição dinâmico\n\n9 - LOCAL DA EXECUÇÃO DO CONTRATO\nLOCAL DA EXECUÇÃO DO CONTRATO (PROCEDIMENTO)\nPaís: Portugal\nNUT III: PT11A\nLocalidade: Porto\nDistrito: Porto\nConcelho: Porto\nFreguesia: Todas\n\n10 - PRAZO DE EXECUÇÃO DO CONTRATO\nPrazo de execução do contrato: 5 MESES\nPrevisão de renovações: Não\n\n11 - FUNDOS EU\nTêm fundos EU? Não\n\n12 - DOCUMENTOS DE HABILITAÇÃO\nHabilitação para o exercício da atividade profissional: Não\n\n13 - CONDIÇÕES DE APRESENTAÇÃO\nPlataforma eletrónica utilizada pela entidade adjudicante: ACIN\nURL para Apresentação: https://www.acingov.pt\nAdmissibilidade da apresentação de propostas variantes: Não autorizado\nPrazo para apresentação das propostas: 08-10-2025 17:00\nPrazo durante o qual os concorrentes são obrigados a manter as respetivas propostas: 66 dias a contar do termo do prazo para a apresentação das propostas\nIndicação de Subcontratação na Proposta: Inexistência de indicação de subcontratação\n\n14 - PRESTAÇÃO DE CAUÇÃO\nPrestação de caução: Não\n\n15 - FORNECIMENTO DAS PEÇAS DO CONCURSO, APRESENTAÇÃO DE PEDIDOS DE PARTICIPAÇÃO E APRESENTAÇÃO DAS PROPOSTAS\nLink para acesso às peças do concurso (URL): https://www.acingov.pt/acingovprod/2/zonaPublica/zona_publica_c/donwloadProcedurePiece/OTgwOTI3\n\n20 - OUTROS REQUISITOS\nInformação sobre contratos reservados. Aplica-se a contratos reservados (54º-A)? Não\n\n21 - CRITÉRIO DE ADJUDICAÇÃO\nMultifator: Não\nMonofator:\nNome: Preço\n\n24 - CONDIÇÕES DO CONTRATO\nFaturação Eletrónica: Permitido\nObrigação de Subcontratação:\nCódigo da Obrigação de Subcontratação: Não é aplicável nenhuma obrigação de subcontratação.\n\n25 - COMPRA PÚBLICA ESTRATÉGICA\nCompra Pública Estratégica: Inexistência de contratação pública estratégica\n\n26 - INFORMAÇÕES ADICIONAIS\nContrato adequado para PME: Não\nCobertura ACP (Acordo dos Contratos Públicos da Organização Mundial do Comércio): Não\n\n27 - IDENTIFICAÇÃO E CONTACTOS DO ÓRGÃO DE RECURSOS ADMINISTRATIVOS\nDesignação: Conselho de Administração\nEndereço: Rua da Constituição, n.º 2555\nCódigo postal: 4250-173\nLocalidade: Porto\nTelefone: 226199860\nFax: \nEndereço eletrónico: geral@agoraporto.pt\n\n28 - IDENTIFICAÇÃO DO(S) AUTOR(ES) DE ANÚNCIO\nNome: Beatriz Penedo de Freitas Radiche Leite\nCargo: Técnica superior\n419588989",
    "nipc": "507718640",
    "distrito": "Porto",
    "concelho": "Porto",
    "freguesia": "União das Freguesias de Aldoar, Foz do Douro e Nevogilde",
    "site": "www.agoraporto.pt",
    "email": "geral@agoraporto.pt",
    "designacao_contrato": "Contratação de serviços de montagem e desmontagem de estruturas para cumprimento do desenho expositivo da exposição CALÓ&QUEIMADELA;",
    "descricao": "Contratação de serviços de montagem e desmontagem de estruturas para cumprimento do desenho expositivo da exposição CALÓ&QUEIMADELA;.",
    "preco_base": "14.000,00 EUR",
    "prazo_execucao": "5 MESES",
    "prazo_apresentacao_propostas": "08-10-2025 17:00",
    "fundos_eu": "Não",
    "plataforma_eletronica": "ACIN",
    "url_procedimento": "https://www.acingov.pt",
    "autor_nome": "Beatriz Penedo de Freitas Radiche Leite",
    "autor_cargo": "Técnica superior"
  },
  {
    "numero_procedimento": "N/A",
    "entidade": "ESTADO-MAIOR-GENERAL DAS FORÇAS ARMADAS",
    "link": "https://diariodarepublica.pt/dr/detalhe/contrato-publico/25658-937197429",
    "detalhes_completos": "1 - IDENTIFICAÇÃO E CONTACTOS DA ENTIDADE ADJUDICANTE\nDesignação da entidade adjudicante: ESTADO-MAIOR-GENERAL DAS FORÇAS ARMADAS\nNIPC: 600010180\nServiço/Órgão/Pessoa de contacto: DepComp/DF/HFAR\nEndereço: AVENIDA ILHA DA MADEIRA\nCódigo postal: 1449-004\nLocalidade: Lisboa\nPaís: Portugal\nNUT III: PT170\nDistrito: Lisboa\nConcelho: Lisboa\nFreguesia: Freguesia de Lumiar\nTelefone: 2130100001\nEndereço da Entidade (URL): www.emgfa.pt\nEndereço Eletrónico: DIRFIN_Contratos@emgfa.pt\neDelivery Gateway (URL): https://www.acingov.pt\nFunção da Organização: Adquirente\nNorma jurídica da Entidade Adjudicante: Organismo de direito público\nÁrea de atividade da Autoridade Adjudicante: Serviços públicos das administrações públicas\n\n2 - JORNAL OFICIAL DA UNIÃO EUROPEIA\nO procedimento a que este anúncio diz respeito também é publicitado no Jornal Oficial da União Europeia? Não\n\n3 - AVISO\nModelo de Anúncio: Concurso público\nData de Envio do Anúncio: 30-09-2025\n\n5 - PROCESSO\nTipo de Procedimento: Concurso público\nPreço base do procedimento: Sim\nValor do preço base do procedimento: 94.470,00 EUR\nProcedimento com lotes? Sim\nNº Máx. de Lotes Autorizado: 3\nNúmero máximo de lotes que podem ser adjudicados a um concorrente: 3\n\n6 - OBJETO DO CONTRATO\nNúmero de referência interna: HFAR-PL 2025007043\nDesignação do contrato: 2025007043/HFAR-SCSI - EQUIPAMENTOS INFORMATICOS\nDescrição: 2025007043/HFAR-SCSI - EQUIPAMENTOS INFORMATICOS\nTipo de Contrato Principal: Aquisição de Bens Móveis\nTipo de Contrato: Aquisição de Bens Móveis\nClassificação CPV (Vocabulário Comum para os Contratos Públicos)\nObjeto principal\nVocabulário Principal: 30213300\nPreço base s/IVA: 94.470,00 EUR\nLotes: \nNº: LOT-0001\nDescrição do Lote: COMPUTADORES DESKTOP\nPreço base s/IVA: 58.500,00 EUR\nClassificação CPV (Vocabulário Comum para os Contratos Públicos)\nObjeto principal\nVocabulário Principal: 30213300\nNº: LOT-0002\nDescrição do Lote: MONITORES\nPreço base s/IVA: 32.970,00 EUR\nClassificação CPV (Vocabulário Comum para os Contratos Públicos)\nObjeto principal\nVocabulário Principal: 33195100\nNº: LOT-0003\nDescrição do Lote: TECLADOS E RATO\nPreço base s/IVA: 3.000,00 EUR\nClassificação CPV (Vocabulário Comum para os Contratos Públicos)\nObjeto principal\nVocabulário Principal: 30237460\n\n7 - INDICAÇÕES ADICIONAIS\nO contrato envolve aquisição conjunta (satisfação de várias entidades)? Não\nO contrato é adjudicado por uma central de compras? Não\n\n8 - TÉCNICAS\nO concurso destina-se à celebração de um acordo-quadro? Inexistência de acordo-quadro\nÉ utilizado um leilão eletrónico? Não\nÉ adotada uma fase de negociação? Não\nSistema de Aquisição Dinâmico: Inexistência de sistema de aquisição dinâmico\n\n9 - LOCAL DA EXECUÇÃO DO CONTRATO\nLOCAL DA EXECUÇÃO DO CONTRATO (PROCEDIMENTO)\nPaís: Portugal\nNUT III: PT170\nLocalidade: Freguesia de Lumiar\nDistrito: Lisboa\nConcelho: Lisboa\nFreguesia: Freguesia de Lumiar\nLOCAL DA EXECUÇÃO DO CONTRATO (LOTE)\nIdentificador do Lote: LOT-0001; LOT-0002; LOT-0003\nPaís: Portugal\nNUT III: PT170\nLocalidade: Lumiar\nDistrito: Lisboa\nConcelho: Lisboa\nFreguesia: Todas\n\n10 - PRAZO DE EXECUÇÃO DO CONTRATO\nIdentificador do Lote: LOT-0001; LOT-0002; LOT-0003\nPrazo de execução do contrato: 45 DIAS\nPrevisão de renovações: Não\n\n11 - FUNDOS EU\nIdentificador do Lote: LOT-0001; LOT-0002; LOT-0003\nTêm fundos EU? Não\n\n12 - DOCUMENTOS DE HABILITAÇÃO\nHabilitação para o exercício da atividade profissional: Não\n\n13 - CONDIÇÕES DE APRESENTAÇÃO\nPlataforma eletrónica utilizada pela entidade adjudicante: ACIN\nURL para Apresentação: https://www.acingov.pt\nAdmissibilidade da apresentação de propostas variantes: Não autorizado\nPrazo para apresentação das propostas: 08-10-2025 23:59\nPrazo durante o qual os concorrentes são obrigados a manter as respetivas propostas: 66 dias a contar do termo do prazo para a apresentação das propostas\nIndicação de Subcontratação na Proposta: Inexistência de indicação de subcontratação\n\n14 - PRESTAÇÃO DE CAUÇÃO\nPrestação de caução: Não\n\n15 - FORNECIMENTO DAS PEÇAS DO CONCURSO, APRESENTAÇÃO DE PEDIDOS DE PARTICIPAÇÃO E APRESENTAÇÃO DAS PROPOSTAS\nLink para acesso às peças do concurso (URL): https://www.acingov.pt/acingovprod/2/zonaPublica/zona_publica_c/donwloadProcedurePiece/OTgyMzYy\n\n20 - OUTROS REQUISITOS\nIdentificador do Lote: LOT-0001; LOT-0002; LOT-0003\nInformação sobre contratos reservados. Aplica-se a contratos reservados (54º-A)? Não\n\n21 - CRITÉRIO DE ADJUDICAÇÃO\nO Critério de adjudicação é diferenciado por lote? Não\nMultifator: Não\nMonofator:\nNome: Preço\n\n24 - CONDIÇÕES DO CONTRATO\nIdentificador do Lote: LOT-0001; LOT-0002; LOT-0003\nFaturação Eletrónica: Permitido\nObrigação de Subcontratação:\nCódigo da Obrigação de Subcontratação: Não é aplicável nenhuma obrigação de subcontratação.\n\n25 - COMPRA PÚBLICA ESTRATÉGICA\nCompra Pública Estratégica: Inexistência de contratação pública estratégica\n\n26 - INFORMAÇÕES ADICIONAIS\nIdentificador do Lote: LOT-0001; LOT-0002; LOT-0003\nContrato adequado para PME: Sim\nCobertura ACP (Acordo dos Contratos Públicos da Organização Mundial do Comércio): Não\n\n27 - IDENTIFICAÇÃO E CONTACTOS DO ÓRGÃO DE RECURSOS ADMINISTRATIVOS\nDesignação: EMGMFA\nEndereço: Av. Ilha da Madeira N.º 1\nCódigo postal: 1449-004\nLocalidade: LISBOA\nEndereço eletrónico: emgfa@emgfa.pt\n\n28 - IDENTIFICAÇÃO DO(S) AUTOR(ES) DE ANÚNCIO\nNome: BGEN JOSÉ CARLOS CANDEIAS PINHEIRO MONGE\nCargo: DIRETOR DO HFAR\n419591636",
    "nipc": "600010180",
    "distrito": "Lisboa",
    "concelho": "Lisboa",
    "freguesia": "Freguesia de Lumiar",
    "site": "www.emgfa.pt",
    "email": "DIRFIN_Contratos@emgfa.pt",
    "designacao_contrato": "2025007043/HFAR-SCSI - EQUIPAMENTOS INFORMATICOS",
    "descricao": "2025007043/HFAR-SCSI - EQUIPAMENTOS INFORMATICOS",
    "preco_base": "94.470,00 EUR",
    "prazo_execucao": "45 DIAS",
    "prazo_apresentacao_propostas": "08-10-2025 23:59",
    "fundos_eu": "Não",
    "plataforma_eletronica": "ACIN",
    "url_procedimento": "https://www.acingov.pt",
    "autor_nome": "BGEN JOSÉ CARLOS CANDEIAS PINHEIRO MONGE",
    "autor_cargo": "DIRETOR DO HFAR"
  },
  {
    "numero_procedimento": "N/A",
    "entidade": "Município de Póvoa de Varzim",
    "link": "https://diariodarepublica.pt/dr/detalhe/contrato-publico/25660-937197430",
    "detalhes_completos": "1 - IDENTIFICAÇÃO E CONTACTOS DA ENTIDADE ADJUDICANTE\nDesignação da entidade adjudicante: Município de Póvoa de Varzim\nNIPC: 506741400\nEndereço: Praça do Almada, 18\nCódigo postal: 4490-438\nLocalidade: Póvoa de Varzim\nPaís: Portugal\nNUT III: PT11A\nDistrito: Porto\nConcelho: Póvoa de Varzim\nFreguesia: Todas\nTelefone: 252090000\nFax: 252090010\nEndereço da Entidade (URL): www.cm-pvarzim.pt\nEndereço Eletrónico: geral@cm-pvarzim.pt\neDelivery Gateway (URL): https://community.vortal.biz/public/\nFunção da Organização: Adquirente\nNorma jurídica da Entidade Adjudicante: Organismo de direito público\nÁrea de atividade da Autoridade Adjudicante: Serviços públicos das administrações públicas\n\n2 - JORNAL OFICIAL DA UNIÃO EUROPEIA\nO procedimento a que este anúncio diz respeito também é publicitado no Jornal Oficial da União Europeia? Não\n\n3 - AVISO\nModelo de Anúncio: Concurso público\nData de Envio do Anúncio: 30-09-2025\n\n5 - PROCESSO\nTipo de Procedimento: Concurso público\nPreço base do procedimento: Sim\nValor do preço base do procedimento: 250.000,00 EUR\nProcedimento com lotes? Não\n\n6 - OBJETO DO CONTRATO\nNúmero de referência interna: CP055/25\nDesignação do contrato: Reabilitação do Bairro Social de Amorim: Interiores (Aviso n.º 01/C02-i01/2021 Programa apoio ao acesso à habitação - PRR  59923)\nDescrição: Reabilitação do Bairro Social de Amorim: Interiores (Aviso n.º 01/C02-i01/2021 Programa apoio ao acesso à habitação - PRR  59923)\nTipo de Contrato Principal: Empreitada de Obras Públicas\nTipo de Contrato: Empreitada de Obras Públicas\nClassificação CPV (Vocabulário Comum para os Contratos Públicos)\nObjeto principal\nVocabulário Principal: 45453100\nPreço base s/IVA: 250.000,00 EUR\n\n7 - INDICAÇÕES ADICIONAIS\nO contrato envolve aquisição conjunta (satisfação de várias entidades)? Não\nO contrato é adjudicado por uma central de compras? Não\n\n8 - TÉCNICAS\nO concurso destina-se à celebração de um acordo-quadro? Inexistência de acordo-quadro\nÉ utilizado um leilão eletrónico? Não\nÉ adotada uma fase de negociação? Não\nSistema de Aquisição Dinâmico: Inexistência de sistema de aquisição dinâmico\n\n9 - LOCAL DA EXECUÇÃO DO CONTRATO\nLOCAL DA EXECUÇÃO DO CONTRATO (PROCEDIMENTO)\nPaís: Portugal\nNUT III: PT11A\nLocalidade: Área Metropolitana do Porto\nDistrito: Porto\nConcelho: Póvoa de Varzim\nFreguesia: Todas\n\n10 - PRAZO DE EXECUÇÃO DO CONTRATO\nPrazo de execução do contrato: 90 DIAS\nPrevisão de renovações: Não\n\n11 - FUNDOS EU\nTêm fundos EU? Sim\n\n12 - DOCUMENTOS DE HABILITAÇÃO\nHabilitação para o exercício da atividade profissional: Sim\nTipo: Alvará\nDescrição: Alvarás nos termos da peças do procedimento\n\n13 - CONDIÇÕES DE APRESENTAÇÃO\nPlataforma eletrónica utilizada pela entidade adjudicante: VORTAL\nURL para Apresentação: https://community.vortal.biz/public/\nAdmissibilidade da apresentação de propostas variantes: Não autorizado\nPrazo para apresentação das propostas: 15-10-2025 17:00\nPrazo durante o qual os concorrentes são obrigados a manter as respetivas propostas: 66 dias a contar do termo do prazo para a apresentação das propostas\nIndicação de Subcontratação na Proposta: Inexistência de indicação de subcontratação\n\n14 - PRESTAÇÃO DE CAUÇÃO\nPrestação de caução: Não\n\n15 - FORNECIMENTO DAS PEÇAS DO CONCURSO, APRESENTAÇÃO DE PEDIDOS DE PARTICIPAÇÃO E APRESENTAÇÃO DAS PROPOSTAS\nLink para acesso às peças do concurso (URL): https://community.vortal.biz/Public/public-tender-documents/bjVkbG5KYXk4K3V2TDRuTWcrN2Zaak1VZXZMb0hhSUl6RjhhUGRLRDNibVRMS1JTdTk4Q2JzZU9XM0NGZTlnR2t6ckVXVU5zM1lKaHFpZHdFT1R4cUE9PVVOWjgp\n\n20 - OUTROS REQUISITOS\nInformação sobre contratos reservados. Aplica-se a contratos reservados (54º-A)? Não\n\n21 - CRITÉRIO DE ADJUDICAÇÃO\nMultifator: Não\nMonofator:\nNome: Preço\n\n24 - CONDIÇÕES DO CONTRATO\nFaturação Eletrónica: Permitido\nObrigação de Subcontratação:\nCódigo da Obrigação de Subcontratação: Não é aplicável nenhuma obrigação de subcontratação.\n\n25 - COMPRA PÚBLICA ESTRATÉGICA\nCompra Pública Estratégica: Inexistência de contratação pública estratégica\n\n26 - INFORMAÇÕES ADICIONAIS\nContrato adequado para PME: Sim\nCobertura ACP (Acordo dos Contratos Públicos da Organização Mundial do Comércio): Não\n\n27 - IDENTIFICAÇÃO E CONTACTOS DO ÓRGÃO DE RECURSOS ADMINISTRATIVOS\nDesignação: Presidente da Câmara Municipal da Póvoa de Varzim\nEndereço: Praça do Almada\nCódigo postal: 4490-438\nLocalidade: Póvoa de Varzim\nTelefone: +351 252090000\nFax: +351 252090010\nEndereço eletrónico: geral@cm-pvarzim.pt\n\n28 - IDENTIFICAÇÃO DO(S) AUTOR(ES) DE ANÚNCIO\nNome: Município da Póvoa de Varzim\nCargo: Presidente da Câmara Municipal da Póvoa de Varzim\n419590729",
    "nipc": "506741400",
    "distrito": "Porto",
    "concelho": "Póvoa de Varzim",
    "freguesia": "Todas",
    "site": "www.cm-pvarzim.pt",
    "email": "geral@cm-pvarzim.pt",
    "designacao_contrato": "Reabilitação do Bairro Social de Amorim: Interiores (Aviso n.º 01/C02-i01/2021 Programa apoio ao acesso à habitação - PRR 59923)",
    "descricao": "Reabilitação do Bairro Social de Amorim: Interiores (Aviso n.º 01/C02-i01/2021 Programa apoio ao acesso à habitação - PRR 59923)",
    "preco_base": "250.000,00 EUR",
    "prazo_execucao": "90 DIAS",
    "prazo_apresentacao_propostas": "15-10-2025 17:00",
    "fundos_eu": "Sim",
    "plataforma_eletronica": "VORTAL",
    "url_procedimento": "https://community.vortal.biz/public/",
    "autor_nome": "Município da Póvoa de Varzim",
    "autor_cargo": "Presidente da Câmara Municipal da Póvoa de Varzim"
  }
]